{
  "type": "Feature",
  "properties": {
    "iso:country":"US",
    "sg:address":"411 W Chickasha Ave",
    "sg:city":"Chickasha",
    "sg:classifiers":[
        {
            "category":"Professional",
            "subcategory":"Lawyer & Legal Services",
            "type":"Services"
        }
    ],
    "sg:phone":"+1 405 224 1091",
    "sg:postcode":"73018",
    "sg:province":"OK",
    "sg:tags":[
        "attorney"
    ],
    "wof:name":"Keith W Heck",
    "wof:placetype":"venue"
},
  "geometry": {"coordinates":[-97.938219,35.051076],"type":"Point"}
}