{
  "type": "Feature",
  "properties": {
    "iso:country":"US",
    "sg:address":"1635 S Memorial Dr",
    "sg:city":"Tulsa",
    "sg:classifiers":[
        {
            "category":"Shopping",
            "subcategory":"Used Merchandise",
            "type":"Retail Goods"
        }
    ],
    "sg:phone":"+1 918 665 1289",
    "sg:postcode":"74112",
    "sg:province":"OK",
    "sg:tags":[
        "pawnbroker"
    ],
    "wof:name":"Big State Pawn Of Tulsa",
    "wof:placetype":"venue"
},
  "geometry": {"coordinates":[-95.886601,36.137714],"type":"Point"}
}