{
  "type": "Feature",
  "properties": {
    "iso:country":"US",
    "sg:address":"252 N Millard St",
    "sg:city":"Fairfax",
    "sg:classifiers":[
        {
            "category":"Retail",
            "subcategory":"Repair Shop",
            "type":"Services"
        }
    ],
    "sg:phone":"+1 918 642 5240",
    "sg:postcode":"74637",
    "sg:province":"OK",
    "sg:tags":[
        "welding"
    ],
    "wof:name":"Mc Farland Welding",
    "wof:placetype":"venue"
},
  "geometry": {"coordinates":[-96.713647,36.572689],"type":"Point"}
}