{
  "type": "Feature",
  "properties": {
    "iso:country":"US",
    "sg:address":"1409 E Kenosha St",
    "sg:city":"Broken Arrow",
    "sg:classifiers":[
        {
            "category":"Utilities",
            "subcategory":"Mobile Phone",
            "type":"Services"
        }
    ],
    "sg:phone":"+1 918 251 1139",
    "sg:postcode":"74012",
    "sg:province":"OK",
    "sg:tags":[
        "telephone",
        "cellular"
    ],
    "wof:name":"Catalyst Marketing Inc",
    "wof:placetype":"venue"
},
  "geometry": {"coordinates":[-95.773315,36.061065],"type":"Point"}
}