{
  "type": "Feature",
  "properties": {
    "iso:country":"US",
    "sg:address":"601 Evanhale Rd",
    "sg:city":"Oklahoma City",
    "sg:classifiers":[
        {
            "category":"Retail",
            "subcategory":"Auto Repair",
            "type":"Services"
        }
    ],
    "sg:phone":"+1 405 942 1231",
    "sg:postcode":"73127",
    "sg:province":"OK",
    "sg:tags":[
        "repairing",
        "automobile"
    ],
    "wof:name":"Pete's Automotive Svc",
    "wof:placetype":"venue"
},
  "geometry": {"coordinates":[-97.605538,35.474672],"type":"Point"}
}