{
  "type": "Feature",
  "properties": {
    "addr:full":"981 N Santa Fe Ave Edmond OK 73003",
    "addr:housenumber":"981",
    "addr:postcode":"73003",
    "addr:street":"N Santa Fe Ave",
    "iso:country":"US",
    "sg:address":"981 N Santa Fe Ave",
    "sg:city":"Edmond",
    "sg:classifiers":[
        {
            "category":"Shopping",
            "type":"Retail Goods"
        }
    ],
    "sg:phone":"+1 405 348 9150",
    "sg:postcode":"73003",
    "sg:province":"OK",
    "sg:tags":[
        "pet",
        "food",
        "supply"
    ],
    "wof:name":"Puppy Love",
    "wof:placetype":"venue"
},
  "geometry": {"coordinates":[-97.514083,35.663326],"type":"Point"}
}