{
  "type": "Feature",
  "properties": {
    "addr:full":"1437 S Boulder Ave Bsmt Tulsa OK 74119",
    "addr:housenumber":"1437",
    "addr:postcode":"74119",
    "addr:street":"S Boulder Ave",
    "iso:country":"US",
    "sg:address":"1437 S Boulder Ave Bsmt",
    "sg:city":"Tulsa",
    "sg:classifiers":[
        {
            "category":"Wholesale",
            "subcategory":"Petroleum",
            "type":"Manufacturing & Wholesale Goods"
        },
        {
            "category":"Utilities",
            "subcategory":"Fuel Oil & Lpg",
            "type":"Services"
        }
    ],
    "sg:phone":"+1 918 582 4242",
    "sg:postcode":"74119",
    "sg:province":"OK",
    "sg:tags":[
        "well",
        "drilling"
    ],
    "wof:name":"Masterson West Llp",
    "wof:placetype":"venue"
},
  "geometry": {"coordinates":[-95.98848,36.141737],"type":"Point"}
}