{
  "type": "Feature",
  "properties": {
    "iso:country":"US",
    "sg:address":"6938 E Tower Rd",
    "sg:city":"Ponca City",
    "sg:classifiers":[
        {
            "category":"Farming",
            "subcategory":"Farm",
            "type":"Manufacturing & Wholesale Goods"
        }
    ],
    "sg:phone":"+1 580 762 7811",
    "sg:postcode":"74604",
    "sg:province":"OK",
    "sg:tags":[
        "crop",
        "general"
    ],
    "wof:name":"Lawrence Horinek",
    "wof:placetype":"venue"
},
  "geometry": {"coordinates":[-96.978792,36.781793],"type":"Point"}
}