{
  "type": "Feature",
  "properties": {
    "addr:full":"435 E 2nd Ave Owasso OK 74055",
    "addr:housenumber":"435",
    "addr:postcode":"74055",
    "addr:street":"E 2Nd Ave",
    "iso:country":"US",
    "sg:address":"435 E 2nd Ave",
    "sg:city":"Owasso",
    "sg:classifiers":[
        {
            "category":"Health Services",
            "subcategory":"Chiropractor",
            "type":"Services"
        }
    ],
    "sg:phone":"+1 918 272 8054",
    "sg:postcode":"74055",
    "sg:province":"OK",
    "sg:tags":[
        "chiropractic"
    ],
    "wof:name":"Complete Care Chiropractic Inc",
    "wof:placetype":"venue"
},
  "geometry": {"coordinates":[-95.850774,36.264124],"type":"Point"}
}