{
  "type": "Feature",
  "properties": {
    "iso:country":"US",
    "sg:address":"202 W Stuart Roosa Dr",
    "sg:city":"Claremore",
    "sg:classifiers":[
        {
            "category":"Real Estate",
            "subcategory":"Real Estate Operator",
            "type":"Services"
        }
    ],
    "sg:phone":"+1 918 342 2494",
    "sg:postcode":"74017",
    "sg:province":"OK",
    "sg:tags":[
        "apartment"
    ],
    "wof:name":"Will Rogers Senior Apartments",
    "wof:placetype":"venue"
},
  "geometry": {"coordinates":[-95.604495,36.329165],"type":"Point"}
}