{
  "type": "Feature",
  "properties": {
    "iso:country":"US",
    "sg:address":"5101 N Classen Cir",
    "sg:city":"Oklahoma City",
    "sg:classifiers":[
        {
            "category":"Travel",
            "subcategory":"Travel Agent",
            "type":"Entertainment"
        }
    ],
    "sg:phone":"+1 405 841 3333",
    "sg:postcode":"73118",
    "sg:province":"OK",
    "sg:tags":[
        "agency",
        "bureau"
    ],
    "wof:name":"Grace Travel",
    "wof:placetype":"venue"
},
  "geometry": {"coordinates":[-97.532296,35.5233],"type":"Point"}
}