{
  "type": "Feature",
  "properties": {
    "iso:country":"US",
    "sg:address":"2801 Parklawn Dr",
    "sg:city":"Oklahoma City",
    "sg:classifiers":[
        {
            "category":"Health Services",
            "subcategory":"Health Practitioner",
            "type":"Services"
        }
    ],
    "sg:phone":"+1 405 732 9100",
    "sg:postcode":"73110",
    "sg:province":"OK",
    "sg:tags":[
        "correction",
        "laser",
        "vision"
    ],
    "wof:name":"BVA",
    "wof:placetype":"venue"
},
  "geometry": {"coordinates":[-97.393267,35.465067],"type":"Point"}
}