{
  "type": "Feature",
  "properties": {
    "iso:country":"US",
    "sg:address":"8224 SW 3rd St",
    "sg:city":"Oklahoma City",
    "sg:classifiers":[
        {
            "category":"Retail",
            "subcategory":"Repair Shop",
            "type":"Services"
        }
    ],
    "sg:phone":"+1 405 440 2821",
    "sg:postcode":"73128",
    "sg:province":"OK",
    "sg:tags":[
        "natural",
        "gas",
        "compression"
    ],
    "wof:name":"Worldwide Enrgy Solutions LLC",
    "wof:placetype":"venue"
},
  "geometry": {"coordinates":[-97.656768,35.46241],"type":"Point"}
}