{
  "type": "Feature",
  "properties": {
    "addr:full":"1375 E 27th St Tulsa OK 74114",
    "addr:housenumber":"1375",
    "addr:postcode":"74114",
    "addr:street":"E 27Th St",
    "iso:country":"US",
    "sg:address":"1375 E 27th St",
    "sg:city":"Tulsa",
    "sg:classifiers":[
        {
            "category":"Professional",
            "subcategory":"Management & Consulting",
            "type":"Services"
        }
    ],
    "sg:phone":"+1 918 743 3676",
    "sg:postcode":"74114",
    "sg:province":"OK",
    "sg:tags":[
        "consultant",
        "business"
    ],
    "wof:name":"Formation Consultants Inc",
    "wof:placetype":"venue"
},
  "geometry": {"coordinates":[-95.972612,36.125692],"type":"Point"}
}