{
  "type": "Feature",
  "properties": {
    "addr:full":"6117 S Mingo Rd Tulsa OK 74133",
    "addr:housenumber":"6117",
    "addr:postcode":"74133",
    "addr:street":"S Mingo Rd",
    "iso:country":"US",
    "sg:address":"6117 S Mingo Rd",
    "sg:city":"Tulsa",
    "sg:classifiers":[
        {
            "category":"Shopping",
            "subcategory":"Shoes",
            "type":"Retail Goods"
        }
    ],
    "sg:phone":"+1 918 294 0500",
    "sg:postcode":"74133",
    "sg:province":"OK",
    "sg:website":"www.goodfeet.com",
    "wof:name":"Good Feet Store",
    "wof:placetype":"venue"
},
  "geometry": {"coordinates":[-95.868476,36.073923],"type":"Point"}
}