{
  "type": "Feature",
  "properties": {
    "addr:full":"11809 Hollyrock Dr Yukon OK 73099",
    "addr:housenumber":"11809",
    "addr:postcode":"73099",
    "addr:street":"Hollyrock Dr",
    "iso:country":"US",
    "sg:address":"11809 Hollyrock Dr",
    "sg:city":"Yukon",
    "sg:classifiers":[
        {
            "category":"Professional",
            "subcategory":"Business Services",
            "type":"Services"
        }
    ],
    "sg:phone":"+1 405 265 0403",
    "sg:postcode":"73099",
    "sg:province":"OK",
    "wof:name":"Data Center Solutions Inc",
    "wof:placetype":"venue"
},
  "geometry": {"coordinates":[-97.7337,35.469029],"type":"Point"}
}