{
  "type": "Feature",
  "properties": {
    "iso:country":"US",
    "sg:address":"23075 E 87th St",
    "sg:city":"Broken Arrow",
    "sg:classifiers":[
        {
            "category":"Real Estate",
            "subcategory":"Developer",
            "type":"Services"
        }
    ],
    "sg:phone":"+1 918 251 9815",
    "sg:postcode":"74014",
    "sg:province":"OK",
    "wof:name":"Willis Development Co",
    "wof:placetype":"venue"
},
  "geometry": {"coordinates":[-95.719012,36.036425],"type":"Point"}
}