{
  "type": "Feature",
  "properties": {
    "addr:full":"23075 E 87th St Broken Arrow OK 74014",
    "addr:housenumber":"23075",
    "addr:postcode":"74014",
    "addr:street":"E 87Th St",
    "iso:country":"US",
    "sg:address":"23075 E 87th St",
    "sg:city":"Broken Arrow",
    "sg:classifiers":[
        {
            "category":"Real Estate",
            "subcategory":"Developer",
            "type":"Services"
        }
    ],
    "sg:phone":"+1 918 251 9815",
    "sg:postcode":"74014",
    "sg:province":"OK",
    "wof:name":"Willis Development Co",
    "wof:placetype":"venue"
},
  "geometry": {"coordinates":[-95.71901200000001,36.036425],"type":"Point"}
}