{
  "type": "Feature",
  "properties": {
    "addr:full":"603 E Jackson St Hugo OK 74743",
    "addr:housenumber":"603",
    "addr:postcode":"74743",
    "addr:street":"E Jackson St",
    "iso:country":"US",
    "sg:address":"603 E Jackson St",
    "sg:city":"Hugo",
    "sg:classifiers":[
        {
            "category":"Restaurant",
            "type":"Food & Drink"
        },
        {
            "category":"Ice Cream",
            "type":"Food & Drink"
        }
    ],
    "sg:menulink":"http://www.allmenus.com/ok/hugo/218844-braums-ice-cream--dairy-stores/menu/",
    "sg:phone":"+1 580 326 9435",
    "sg:postcode":"74743",
    "sg:province":"OK",
    "sg:tags":[
        "american",
        "ice",
        "cream"
    ],
    "wof:name":"Braum's Ice Cream & Dairy Stores",
    "wof:placetype":"venue"
},
  "geometry": {"coordinates":[-95.50623899999999,34.010673],"type":"Point"}
}