{
  "type": "Feature",
  "properties": {
    "addr:full":"2827 N Garrison Ave Tulsa OK 74106",
    "addr:housenumber":"2827",
    "addr:postcode":"74106",
    "addr:street":"N Garrison Ave",
    "iso:country":"US",
    "sg:address":"2827 N Garrison Ave",
    "sg:city":"Tulsa",
    "sg:classifiers":[
        {
            "category":"Personal",
            "subcategory":"Beauty Salon",
            "type":"Services"
        }
    ],
    "sg:phone":"+1 918 430 9980",
    "sg:postcode":"74106",
    "sg:province":"OK",
    "wof:name":"Good Looks",
    "wof:placetype":"venue"
},
  "geometry": {"coordinates":[-95.986694,36.196698],"type":"Point"}
}