{
  "type": "Feature",
  "properties": {
    "iso:country":"US",
    "sg:address":"1 W Central Ave",
    "sg:city":"Miami",
    "sg:classifiers":[
        {
            "category":"Health Services",
            "subcategory":"Doctor",
            "type":"Services"
        }
    ],
    "sg:phone":"+1 918 542 1867",
    "sg:postcode":"74354",
    "sg:province":"OK",
    "wof:name":"R A Kirkpatrick DDS Inc",
    "wof:placetype":"venue"
},
  "geometry": {"coordinates":[-94.87866,36.87468],"type":"Point"}
}