{
  "type": "Feature",
  "properties": {
    "iso:country":"US",
    "sg:address":"1704 Dartmouth Ct",
    "sg:city":"Norman",
    "sg:classifiers":[
        {
            "category":"Professional",
            "type":"Services"
        }
    ],
    "sg:phone":"+1 405 573 9283",
    "sg:postcode":"73071",
    "sg:province":"OK",
    "sg:tags":[
        "establishment"
    ],
    "wof:name":"Harvey Watt & Co",
    "wof:placetype":"venue"
},
  "geometry": {"coordinates":[-97.41206,35.239036],"type":"Point"}
}