{
  "type": "Feature",
  "properties": {
    "iso:country":"US",
    "sg:address":"7100 S I- 35 Svc Rd",
    "sg:city":"Oklahoma City",
    "sg:classifiers":[
        {
            "category":"Health Services",
            "subcategory":"Doctor",
            "type":"Services"
        }
    ],
    "sg:phone":"+1 405 632 1002",
    "sg:postcode":"73149",
    "sg:province":"OK",
    "sg:tags":[
        "clinic"
    ],
    "sg:website":"www.concentra.com",
    "wof:name":"Concentra Medical Ctr",
    "wof:placetype":"venue"
},
  "geometry": {"coordinates":[-97.494676,35.395942],"type":"Point"}
}