{
  "type": "Feature",
  "properties": {
    "iso:country":"US",
    "sg:address":"412 N Draper Ave",
    "sg:city":"Shawnee",
    "sg:classifiers":[
        {
            "category":"Education",
            "subcategory":"School",
            "type":"Public Place"
        }
    ],
    "sg:phone":"+1 405 273 1806",
    "sg:postcode":"74801",
    "sg:province":"OK",
    "sg:tags":[
        "elementary"
    ],
    "sg:website":"www.shawnee.k12.ok.us",
    "wof:name":"Horace Mann Elementary School",
    "wof:placetype":"venue"
},
  "geometry": {"coordinates":[-96.905557,35.331413],"type":"Point"}
}