{
  "type": "Feature",
  "properties": {
    "iso:country":"US",
    "sg:address":"5460 S 103rd East Ave",
    "sg:city":"Tulsa",
    "sg:classifiers":[
        {
            "category":"Wholesale",
            "subcategory":"Drugs",
            "type":"Manufacturing & Wholesale Goods"
        }
    ],
    "sg:phone":"+1 918 622 8070",
    "sg:postcode":"74146",
    "sg:province":"OK",
    "wof:name":"Sequoia Health Services Inc",
    "wof:placetype":"venue"
},
  "geometry": {"coordinates":[-95.861607,36.085407],"type":"Point"}
}