{
  "type": "Feature",
  "properties": {
    "addr:full":"700 Evanhale Rd Oklahoma City OK 73127",
    "addr:housenumber":"700",
    "addr:postcode":"73127",
    "addr:street":"Evanhale Rd",
    "iso:country":"US",
    "sg:address":"700 Evanhale Rd",
    "sg:city":"Oklahoma City",
    "sg:classifiers":[
        {
            "category":"Recreation",
            "subcategory":"Marina",
            "type":"Entertainment"
        }
    ],
    "sg:phone":"+1 405 947 7878",
    "sg:postcode":"73127",
    "sg:province":"OK",
    "sg:tags":[
        "equipment",
        "operation",
        "industrial"
    ],
    "sg:website":"www.allpurposestorage.com",
    "wof:name":"All PURPOSE Storage Inc",
    "wof:placetype":"venue"
},
  "geometry": {"coordinates":[-97.60546600000001,35.473637],"type":"Point"}
}