{
  "type": "Feature",
  "properties": {
    "addr:full":"828 Texas St Muskogee OK 74403",
    "addr:housenumber":"828",
    "addr:postcode":"74403",
    "addr:street":"Texas St",
    "iso:country":"US",
    "sg:address":"828 Texas St",
    "sg:city":"Muskogee",
    "sg:classifiers":[
        {
            "category":"Building & Trades",
            "subcategory":"Construction",
            "type":"Services"
        }
    ],
    "sg:phone":"+1 918 681 4370",
    "sg:postcode":"74403",
    "sg:province":"OK",
    "sg:tags":[
        "hanging",
        "contractor"
    ],
    "wof:name":"Gray Mare Paint & Paper",
    "wof:placetype":"venue"
},
  "geometry": {"coordinates":[-95.354044,35.735828],"type":"Point"}
}