{
  "type": "Feature",
  "properties": {
    "addr:full":"521 5th St Alva OK 73717",
    "addr:housenumber":"521",
    "addr:postcode":"73717",
    "addr:street":"5Th St",
    "iso:country":"US",
    "sg:address":"521 5th St",
    "sg:city":"Alva",
    "sg:classifiers":[
        {
            "category":"Banks & Credit Unions",
            "subcategory":"Bank",
            "type":"Services"
        }
    ],
    "sg:phone":"+1 580 327 0870",
    "sg:postcode":"73717",
    "sg:province":"OK",
    "sg:tags":[
        "federal",
        "agency"
    ],
    "wof:name":"Farm Crdit Bank Western Okla",
    "wof:placetype":"venue"
},
  "geometry": {"coordinates":[-98.665246,36.803521],"type":"Point"}
}