{
  "type": "Feature",
  "properties": {
    "iso:country":"US",
    "sg:address":"7308 N Western Ave",
    "sg:city":"Oklahoma City",
    "sg:classifiers":[
        {
            "category":"Shopping",
            "subcategory":"Gifts & Souvenirs",
            "type":"Retail Goods"
        }
    ],
    "sg:phone":"+1 405 840 2122",
    "sg:postcode":"73116",
    "sg:province":"OK",
    "sg:tags":[
        "leather",
        "luggage"
    ],
    "wof:name":"Kambers",
    "wof:placetype":"venue"
},
  "geometry": {"coordinates":[-97.52968300000001,35.546336],"type":"Point"}
}