{
  "type": "Feature",
  "properties": {
    "iso:country":"US",
    "sg:address":"2010 N Little Ave",
    "sg:city":"Cushing",
    "sg:classifiers":[
        {
            "category":"Organizations",
            "subcategory":"Religious Organization",
            "type":"Services"
        }
    ],
    "sg:phone":"+1 918 225 1110",
    "sg:postcode":"74023",
    "sg:province":"OK",
    "sg:tags":[
        "church"
    ],
    "wof:name":"Full Gospel Assembly Of God",
    "wof:placetype":"venue"
},
  "geometry": {"coordinates":[-96.767539,36.000125],"type":"Point"}
}