{
  "type": "Feature",
  "properties": {
    "iso:country":"US",
    "sg:address":"1700 E 141st St",
    "sg:city":"Glenpool",
    "sg:classifiers":[
        {
            "category":"Social Services",
            "subcategory":"Job Training",
            "type":"Services"
        }
    ],
    "sg:phone":"+1 918 291 2055",
    "sg:postcode":"74033",
    "sg:province":"OK",
    "sg:tags":[
        "rehabilitation"
    ],
    "wof:name":"Stein Ancillary Svc",
    "wof:placetype":"venue"
},
  "geometry": {"coordinates":[-95.983935,35.959129],"type":"Point"}
}