{
  "type": "Feature",
  "properties": {
    "addr:full":"8321 NW 10th St Oklahoma City OK 73127",
    "addr:housenumber":"8321",
    "addr:postcode":"73127",
    "addr:street":"Nw 10Th St",
    "iso:country":"US",
    "sg:address":"8321 NW 10th St",
    "sg:city":"Oklahoma City",
    "sg:classifiers":[
        {
            "category":"Wholesale",
            "subcategory":"Groceries",
            "type":"Manufacturing & Wholesale Goods"
        }
    ],
    "sg:phone":"+1 405 787 1938",
    "sg:postcode":"73127",
    "sg:province":"OK",
    "wof:name":"L & H Bean Sprout Operations",
    "wof:placetype":"venue"
},
  "geometry": {"coordinates":[-97.662423,35.478835],"type":"Point"}
}