{
  "type": "Feature",
  "properties": {
    "addr:full":"4303 E Pine St Tulsa OK 74115",
    "addr:housenumber":"4303",
    "addr:postcode":"74115",
    "addr:street":"E Pine St",
    "iso:country":"US",
    "sg:address":"4303 E Pine St",
    "sg:city":"Tulsa",
    "sg:classifiers":[
        {
            "category":"Retail",
            "subcategory":"Auto Repair",
            "type":"Services"
        }
    ],
    "sg:phone":"+1 918 835 4651",
    "sg:postcode":"74115",
    "sg:province":"OK",
    "sg:tags":[
        "repairing",
        "automobile"
    ],
    "wof:name":"Humble Performance",
    "wof:placetype":"venue"
},
  "geometry": {"coordinates":[-95.92866100000001,36.177191],"type":"Point"}
}