{
  "type": "Feature",
  "properties": {
    "iso:country":"US",
    "sg:address":"200 S 12th St",
    "sg:city":"Frederick",
    "sg:classifiers":[
        {
            "category":"Education",
            "subcategory":"School",
            "type":"Public Place"
        }
    ],
    "sg:phone":"+1 580 335 3001",
    "sg:postcode":"73542",
    "sg:province":"OK",
    "wof:name":"Whittier Annex School",
    "wof:placetype":"venue"
},
  "geometry": {"coordinates":[-99.014482,34.388436],"type":"Point"}
}