{
  "type": "Feature",
  "properties": {
    "iso:country":"US",
    "sg:address":"1059 E Pecan St",
    "sg:city":"Altus",
    "sg:classifiers":[
        {
            "category":"Health Services",
            "subcategory":"Nursing And Care Facility",
            "type":"Services"
        }
    ],
    "sg:phone":"+1 580 482 8342",
    "sg:postcode":"73521",
    "sg:province":"OK",
    "sg:tags":[
        "home",
        "convalescent"
    ],
    "wof:name":"Grace Living Ctr",
    "wof:placetype":"venue"
},
  "geometry": {"coordinates":[-99.321382,34.634587],"type":"Point"}
}