{
  "type": "Feature",
  "properties": {
    "iso:country":"US",
    "sg:address":"5101 N Classen Cir",
    "sg:city":"Oklahoma City",
    "sg:classifiers":[
        {
            "category":"Professional",
            "subcategory":"Computer Services",
            "type":"Services"
        }
    ],
    "sg:phone":"+1 405 848 0258",
    "sg:postcode":"73118",
    "sg:province":"OK",
    "sg:tags":[
        "processing",
        "datum"
    ],
    "wof:name":"Oklahoma Data Svc",
    "wof:placetype":"venue"
},
  "geometry": {"coordinates":[-97.532296,35.5233],"type":"Point"}
}