{
  "type": "Feature",
  "properties": {
    "addr:full":"5601 NW 72nd St Oklahoma City OK 73132",
    "addr:housenumber":"5601",
    "addr:postcode":"73132",
    "addr:street":"Nw 72Nd St",
    "iso:country":"US",
    "sg:address":"5601 NW 72nd St",
    "sg:city":"Oklahoma City",
    "sg:classifiers":[
        {
            "category":"Insurance",
            "subcategory":"Insurance Agent",
            "type":"Services"
        }
    ],
    "sg:phone":"+1 405 720 1405",
    "sg:postcode":"73132",
    "sg:province":"OK",
    "sg:tags":[
        "processing"
    ],
    "wof:name":"Alternative Svc Concepts LLC",
    "wof:placetype":"venue"
},
  "geometry": {"coordinates":[-97.61313,35.545321],"type":"Point"}
}