{
  "type": "Feature",
  "properties": {
    "iso:country":"US",
    "sg:address":"3817 Spitz Dr",
    "sg:city":"Oklahoma City",
    "sg:classifiers":[
        {
            "category":"Organizations",
            "subcategory":"Religious Organization",
            "type":"Services"
        }
    ],
    "sg:phone":"+1 405 672 6974",
    "sg:postcode":"73135",
    "sg:province":"OK",
    "wof:name":"Jesus Film Outreach Ministry",
    "wof:placetype":"venue"
},
  "geometry": {"coordinates":[-97.447725,35.411577],"type":"Point"}
}