{
  "type": "Feature",
  "properties": {
    "addr:full":"3301 NE 50th St Oklahoma City OK 73121",
    "addr:housenumber":"3301",
    "addr:postcode":"73121",
    "addr:street":"Ne 50Th St",
    "iso:country":"US",
    "sg:address":"3301 NE 50th St",
    "sg:city":"Oklahoma City",
    "sg:classifiers":[
        {
            "category":"Building & Trades",
            "subcategory":"Construction",
            "type":"Services"
        }
    ],
    "sg:phone":"+1 405 424 6000",
    "sg:postcode":"73121",
    "sg:province":"OK",
    "sg:tags":[
        "excavation"
    ],
    "wof:name":"RD2 Inc",
    "wof:placetype":"venue"
},
  "geometry": {"coordinates":[-97.45572199999999,35.522326],"type":"Point"}
}