{
  "type": "Feature",
  "properties": {
    "addr:full":"12534 SE 134th St Oklahoma City OK 73165",
    "addr:postcode":"12534;73165",
    "addr:street":"Se 134Th St",
    "iso:country":"US",
    "sg:address":"12534 SE 134th St",
    "sg:city":"Oklahoma City",
    "sg:classifiers":[
        {
            "category":"Professional",
            "subcategory":"Accounting & Tax Preparation",
            "type":"Services"
        }
    ],
    "sg:phone":"+1 405 794 4050",
    "sg:postcode":"73165",
    "sg:province":"OK",
    "sg:tags":[
        "accountant"
    ],
    "wof:name":"Walter B Reif CPA",
    "wof:placetype":"venue"
},
  "geometry": {"coordinates":[-97.30642400000001,35.334033],"type":"Point"}
}