{
  "type": "Feature",
  "properties": {
    "iso:country":"US",
    "sg:address":"222 W Main St",
    "sg:city":"Pawhuska",
    "sg:classifiers":[
        {
            "category":"Organizations",
            "subcategory":"Professional Association",
            "type":"Services"
        }
    ],
    "sg:phone":"+1 918 287 2799",
    "sg:postcode":"74056",
    "sg:province":"OK",
    "wof:name":"Osage County Arts Assn",
    "wof:placetype":"venue"
},
  "geometry": {"coordinates":[-96.342218,36.663563],"type":"Point"}
}