{
  "type": "Feature",
  "properties": {
    "iso:country":"US",
    "sg:address":"6486 River Rd",
    "sg:city":"Colbert",
    "sg:phone":"+1 580 296 2562",
    "sg:postcode":"74733",
    "sg:province":"OK",
    "sg:tags":[
        "farm",
        "field",
        "crop"
    ],
    "wof:name":"Jerry Winnett",
    "wof:placetype":"venue"
},
  "geometry": {"coordinates":[-96.464544,33.794739],"type":"Point"}
}