{
  "type": "Feature",
  "properties": {
    "iso:country":"US",
    "sg:address":"363 N Interstate Dr",
    "sg:city":"Norman",
    "sg:classifiers":[
        {
            "category":"Autos & Motor Vehicles",
            "subcategory":"Fuel & Gas Station",
            "type":"Retail Goods"
        }
    ],
    "sg:phone":"+1 405 447 2078",
    "sg:postcode":"73069",
    "sg:province":"OK",
    "sg:tags":[
        "oil"
    ],
    "wof:name":"Murphy Oil USA Inc",
    "wof:placetype":"venue"
},
  "geometry": {"coordinates":[-97.485027,35.221322],"type":"Point"}
}