{
  "type": "Feature",
  "properties": {
    "iso:country":"US",
    "sg:address":"516 N Main St",
    "sg:city":"Broken Arrow",
    "sg:classifiers":[
        {
            "category":"Shopping",
            "subcategory":"Gifts & Souvenirs",
            "type":"Retail Goods"
        }
    ],
    "sg:phone":"+1 918 251 2702",
    "sg:postcode":"74012",
    "sg:province":"OK",
    "sg:tags":[
        "shop"
    ],
    "wof:name":"Southern Hospitality",
    "wof:placetype":"venue"
},
  "geometry": {"coordinates":[-95.790847,36.056532],"type":"Point"}
}