{
  "type": "Feature",
  "properties": {
    "addr:full":"9759 E 31st St Tulsa OK 74146",
    "addr:housenumber":"9759",
    "addr:postcode":"74146",
    "addr:street":"E 31St St",
    "iso:country":"US",
    "sg:address":"9759 E 31st St",
    "sg:city":"Tulsa",
    "sg:classifiers":[
        {
            "category":"Health Services",
            "subcategory":"Doctor",
            "type":"Services"
        }
    ],
    "sg:phone":"+1 918 622 6067",
    "sg:postcode":"74146",
    "sg:province":"OK",
    "wof:name":"D M Schoemann DDS",
    "wof:placetype":"venue"
},
  "geometry": {"coordinates":[-95.867119,36.119019],"type":"Point"}
}