{
  "type": "Feature",
  "properties": {
    "addr:full":"1404 E 3rd St Okmulgee OK 74447",
    "addr:housenumber":"1404",
    "addr:postcode":"74447",
    "addr:street":"E 3Rd St",
    "iso:country":"US",
    "sg:address":"1404 E 3rd St",
    "sg:city":"Okmulgee",
    "sg:classifiers":[
        {
            "category":"Social Services",
            "subcategory":"Child Care",
            "type":"Services"
        }
    ],
    "sg:phone":"+1 918 756 7041",
    "sg:postcode":"74447",
    "sg:province":"OK",
    "sg:tags":[
        "day"
    ],
    "wof:name":"McGee Day Care Learning Ctr",
    "wof:placetype":"venue"
},
  "geometry": {"coordinates":[-95.950407,35.625272],"type":"Point"}
}