{
  "type": "Feature",
  "properties": {
    "iso:country":"US",
    "sg:address":"3017 Azalea Park Dr",
    "sg:city":"Muskogee",
    "sg:classifiers":[
        {
            "category":"Shopping",
            "type":"Retail Goods"
        }
    ],
    "sg:phone":"+1 918 682 6932",
    "sg:postcode":"74401",
    "sg:province":"OK",
    "sg:tags":[
        "merchandise"
    ],
    "sg:website":"www.afeatheredaffair.com",
    "wof:name":"A Feathered Affair",
    "wof:placetype":"venue"
},
  "geometry": {"coordinates":[-95.400205,35.768772],"type":"Point"}
}