{
  "type": "Feature",
  "properties": {
    "iso:country":"US",
    "sg:address":"1014 W Main St",
    "sg:city":"Jenks",
    "sg:classifiers":[
        {
            "category":"Insurance",
            "subcategory":"Insurance Agent",
            "type":"Services"
        }
    ],
    "sg:phone":"+1 918 299 0945",
    "sg:postcode":"74037",
    "sg:province":"OK",
    "wof:name":"Farmers Insurance Group",
    "wof:placetype":"venue"
},
  "geometry": {"coordinates":[-95.98570100000001,36.024661],"type":"Point"}
}