{
  "type": "Feature",
  "properties": {
    "iso:country":"US",
    "sg:address":"5251 S Peoria Ave",
    "sg:city":"Tulsa",
    "sg:classifiers":[
        {
            "category":"Retail",
            "subcategory":"Auto Repair",
            "type":"Services"
        }
    ],
    "sg:phone":"+1 918 743 6351",
    "sg:postcode":"74105",
    "sg:province":"OK",
    "sg:tags":[
        "shop",
        "lube",
        "oil"
    ],
    "wof:name":"Jiffy Lube Tulsa Auto Lube",
    "wof:placetype":"venue"
},
  "geometry": {"coordinates":[-95.975731,36.086768],"type":"Point"}
}