{
  "type": "Feature",
  "properties": {
    "iso:country":"US",
    "sg:address":"407 S Broadway St",
    "sg:city":"Coalgate",
    "sg:classifiers":[
        {
            "category":"Organizations",
            "subcategory":"Professional Association",
            "type":"Services"
        }
    ],
    "sg:phone":"+1 580 927 1076",
    "sg:postcode":"74538",
    "sg:province":"OK",
    "sg:tags":[
        "business"
    ],
    "wof:name":"Choctaw Nation Council Member",
    "wof:placetype":"venue"
},
  "geometry": {"coordinates":[-96.21741900000001,34.533156],"type":"Point"}
}