{
  "type": "Feature",
  "properties": {
    "iso:country":"US",
    "sg:address":"1037 15th Ave NW",
    "sg:city":"Ardmore",
    "sg:classifiers":[
        {
            "category":"Social Services",
            "subcategory":"Job Training",
            "type":"Services"
        }
    ],
    "sg:phone":"+1 580 226 3979",
    "sg:postcode":"73401",
    "sg:province":"OK",
    "sg:tags":[
        "rehabilitation"
    ],
    "wof:name":"Red River Rehabilitation",
    "wof:placetype":"venue"
},
  "geometry": {"coordinates":[-97.140974,34.189865],"type":"Point"}
}