{
  "type": "Feature",
  "properties": {
    "iso:country":"US",
    "sg:address":"801 W 9th St",
    "sg:city":"Hobart",
    "sg:classifiers":[
        {
            "category":"Retail",
            "subcategory":"Laundry & Dry Cleaning",
            "type":"Services"
        }
    ],
    "sg:phone":"+1 580 726 5842",
    "sg:postcode":"73651",
    "sg:province":"OK",
    "sg:tags":[
        "launderer",
        "industrial"
    ],
    "wof:name":"Western Unf & Towel Svc Okla",
    "wof:placetype":"venue"
},
  "geometry": {"coordinates":[-99.100117,35.017952],"type":"Point"}
}