{
  "type": "Feature",
  "properties": {
    "iso:country":"US",
    "sg:address":"400261 W 3400 Rd",
    "sg:city":"Ramona",
    "sg:classifiers":[
        {
            "category":"Building & Trades",
            "subcategory":"Construction",
            "type":"Services"
        }
    ],
    "sg:phone":"+1 918 536 4325",
    "sg:postcode":"74061",
    "sg:province":"OK",
    "sg:tags":[
        "contractor"
    ],
    "wof:name":"AG Quip Inc",
    "wof:placetype":"venue"
},
  "geometry": {"coordinates":[-95.882459,36.525163],"type":"Point"}
}