{
  "type": "Feature",
  "properties": {
    "addr:full":"211 Moorman Dr Chandler OK 74834",
    "addr:housenumber":"211",
    "addr:postcode":"74834",
    "addr:street":"Moorman Dr",
    "iso:country":"US",
    "sg:address":"211 Moorman Dr",
    "sg:city":"Chandler",
    "sg:classifiers":[
        {
            "category":"Social Services",
            "type":"Services"
        }
    ],
    "sg:phone":"+1 405 258 3096",
    "sg:postcode":"74834",
    "sg:province":"OK",
    "wof:name":"Associate In Counceling",
    "wof:placetype":"venue"
},
  "geometry": {"coordinates":[-96.870662,35.707949],"type":"Point"}
}