{
  "type": "Feature",
  "properties": {
    "iso:country":"US",
    "sg:address":"10137 E 71st St",
    "sg:city":"Tulsa",
    "sg:classifiers":[
        {
            "category":"Home & Garden",
            "subcategory":"Home Furnishings",
            "type":"Retail Goods"
        },
        {
            "category":"Home & Garden",
            "subcategory":"Carpets & Floor Coverings",
            "type":"Retail Goods"
        },
        {
            "category":"Manufacturing",
            "subcategory":"Furniture",
            "type":"Manufacturing & Wholesale Goods"
        },
        {
            "category":"Home & Garden",
            "subcategory":"Furniture",
            "type":"Retail Goods"
        }
    ],
    "sg:phone":"+1 918 254 6618",
    "sg:postcode":"74133",
    "sg:province":"OK",
    "sg:tags":[
        "decor",
        "designer",
        "supply",
        "builder",
        "mattress",
        "decorator",
        "interior",
        "custom",
        "store"
    ],
    "sg:website":"http://www.bassettfurniture.com",
    "wof:name":"Bassett Home Furnishings",
    "wof:placetype":"venue"
},
  "geometry": {"coordinates":[-95.8629,36.060982],"type":"Point"}
}