{
  "type": "Feature",
  "properties": {
    "addr:full":"215 S Cleveland St Enid OK 73703",
    "addr:housenumber":"215",
    "addr:postcode":"73703",
    "addr:street":"S Cleveland St",
    "iso:country":"US",
    "sg:address":"215 S Cleveland St",
    "sg:city":"Enid",
    "sg:classifiers":[
        {
            "category":"Organizations",
            "subcategory":"Religious Organization",
            "type":"Services"
        }
    ],
    "sg:phone":"+1 580 234 6622",
    "sg:postcode":"73703",
    "sg:province":"OK",
    "sg:website":"www.redeemer-enid.com",
    "wof:name":"Redeemer Lutheran Church",
    "wof:placetype":"venue"
},
  "geometry": {"coordinates":[-97.907813,36.395477],"type":"Point"}
}