{
  "type": "Feature",
  "properties": {
    "iso:country":"US",
    "sg:address":"7006 NW 63rd St",
    "sg:city":"Bethany",
    "sg:classifiers":[
        {
            "category":"Manufacturing",
            "subcategory":"Printing",
            "type":"Manufacturing & Wholesale Goods"
        }
    ],
    "sg:phone":"+1 405 722 0945",
    "sg:postcode":"73008",
    "sg:province":"OK",
    "sg:tags":[
        "newspaper"
    ],
    "wof:name":"Country Registar",
    "wof:placetype":"venue"
},
  "geometry": {"coordinates":[-97.641114,35.536947],"type":"Point"}
}