{
  "type": "Feature",
  "properties": {
    "addr:full":"2448 SE Washington Blvd Bartlesville OK 74006",
    "addr:housenumber":"2448",
    "addr:postcode":"74006",
    "addr:street":"Se Washington Blvd",
    "iso:country":"US",
    "sg:address":"2448 SE Washington Blvd",
    "sg:city":"Bartlesville",
    "sg:classifiers":[
        {
            "category":"Health Services",
            "subcategory":"Nursing And Care Facility",
            "type":"Services"
        },
        {
            "category":"Wholesale",
            "subcategory":"Medical Equipment & Supplies",
            "type":"Manufacturing & Wholesale Goods"
        }
    ],
    "sg:phone":"+1 918 333 1400",
    "sg:postcode":"74006",
    "sg:province":"OK",
    "sg:tags":[
        "hospice"
    ],
    "wof:name":"Carter Healthcare Inc",
    "wof:placetype":"venue"
},
  "geometry": {"coordinates":[-95.935046,36.714457],"type":"Point"}
}