{
  "type": "Feature",
  "properties": {
    "iso:country":"US",
    "sg:address":"9001 SE 29th St",
    "sg:city":"Oklahoma City",
    "sg:classifiers":[
        {
            "category":"Autos & Motor Vehicles",
            "subcategory":"Fuel & Gas Station",
            "type":"Retail Goods"
        }
    ],
    "sg:phone":"+1 405 733 4160",
    "sg:postcode":"73130",
    "sg:province":"OK",
    "sg:tags":[
        "grocery",
        "station",
        "gasoline"
    ],
    "wof:name":"Boulevard 66",
    "wof:placetype":"venue"
},
  "geometry": {"coordinates":[-97.369439,35.435207],"type":"Point"}
}