{
  "type": "Feature",
  "properties": {
    "iso:country":"US",
    "sg:address":"10111 E 45th Pl",
    "sg:city":"Tulsa",
    "sg:classifiers":[
        {
            "category":"Professional",
            "subcategory":"Advertising",
            "type":"Services"
        }
    ],
    "sg:phone":"+1 918 664 4724",
    "sg:postcode":"74146",
    "sg:province":"OK",
    "sg:tags":[
        "outdoor",
        "spec",
        "mfg"
    ],
    "wof:name":"Stokely Outdoor Advertising",
    "wof:placetype":"venue"
},
  "geometry": {"coordinates":[-95.862751,36.098029],"type":"Point"}
}