{
  "type": "Feature",
  "properties": {
    "iso:country":"US",
    "sg:address":"203 Broadway St",
    "sg:city":"Hooker",
    "sg:classifiers":[
        {
            "category":"Shopping",
            "subcategory":"Discount & Variety Stores",
            "type":"Retail Goods"
        }
    ],
    "sg:phone":"+1 580 652 3343",
    "sg:postcode":"73945",
    "sg:province":"OK",
    "wof:name":"Duckwall",
    "wof:placetype":"venue"
},
  "geometry": {"coordinates":[-101.214625,36.861486],"type":"Point"}
}