{
  "type": "Feature",
  "properties": {
    "iso:country":"US",
    "sg:address":"7875 E 51st St",
    "sg:city":"Tulsa",
    "sg:classifiers":[
        {
            "category":"Health Services",
            "subcategory":"Hospital",
            "type":"Services"
        },
        {
            "category":"Health Services",
            "subcategory":"Nursing And Care Facility",
            "type":"Services"
        },
        {
            "category":"Health Services",
            "subcategory":"Health Practitioner",
            "type":"Services"
        },
        {
            "category":"Health Services",
            "subcategory":"Clinic",
            "type":"Services"
        }
    ],
    "sg:phone":"+1 918 743 9810",
    "sg:postcode":"74145",
    "sg:province":"OK",
    "sg:tags":[
        "physician",
        "assistant",
        "medical",
        "registry",
        "home",
        "nurse",
        "eldercare-home"
    ],
    "sg:website":"http://www.vnatulsa.org",
    "wof:name":"Visiting Nurse Association",
    "wof:placetype":"venue"
},
  "geometry": {"coordinates":[-95.889323,36.089912],"type":"Point"}
}