{
  "type": "Feature",
  "properties": {
    "iso:country":"US",
    "sg:address":"5846 S Pittsburg Ave",
    "sg:city":"Tulsa",
    "sg:classifiers":[
        {
            "category":"Manufacturing",
            "subcategory":"Apparel",
            "type":"Manufacturing & Wholesale Goods"
        }
    ],
    "sg:phone":"+1 918 747 7343",
    "sg:postcode":"74135",
    "sg:province":"OK",
    "wof:name":"Stylish Embroidery",
    "wof:placetype":"venue"
},
  "geometry": {"coordinates":[-95.930699,36.078953],"type":"Point"}
}