{
  "type": "Feature",
  "properties": {
    "iso:country":"US",
    "sg:address":"2713 E 49th St",
    "sg:city":"Tulsa",
    "sg:classifiers":[
        {
            "category":"Social Services",
            "type":"Services"
        }
    ],
    "sg:phone":"+1 918 747 6827",
    "sg:postcode":"74105",
    "sg:province":"OK",
    "wof:name":"A Friend For A Friend",
    "wof:placetype":"venue"
},
  "geometry": {"coordinates":[-95.950631,36.092561],"type":"Point"}
}