{
  "type": "Feature",
  "properties": {
    "addr:full":"5900 Baylor Dr Bartlesville OK 74006",
    "addr:housenumber":"5900",
    "addr:postcode":"74006",
    "addr:street":"Baylor Dr",
    "iso:country":"US",
    "sg:address":"5900 Baylor Dr",
    "sg:city":"Bartlesville",
    "sg:classifiers":[
        {
            "category":"Education",
            "subcategory":"School",
            "type":"Public Place"
        }
    ],
    "sg:phone":"+1 918 333 4444",
    "sg:postcode":"74006",
    "sg:province":"OK",
    "wof:name":"Mid High School",
    "wof:placetype":"venue"
},
  "geometry": {"coordinates":[-95.911535,36.747637],"type":"Point"}
}