{
  "type": "Feature",
  "properties": {
    "addr:full":"2508 E 71st St S Tulsa OK 74136",
    "addr:housenumber":"2508",
    "addr:postcode":"74136",
    "addr:street":"E 71St St",
    "iso:country":"US",
    "sg:address":"2508 E 71st St S",
    "sg:city":"Tulsa",
    "sg:classifiers":[
        {
            "category":"Professional",
            "subcategory":"Management & Consulting",
            "type":"Services"
        }
    ],
    "sg:phone":"+1 918 488 1500",
    "sg:postcode":"74136",
    "sg:province":"OK",
    "sg:tags":[
        "business"
    ],
    "wof:name":"Orion Systems",
    "wof:placetype":"venue"
},
  "geometry": {"coordinates":[-95.955163,36.060755],"type":"Point"}
}