{
  "type": "Feature",
  "properties": {
    "iso:country":"US",
    "sg:address":"1222 Kenilworth Rd",
    "sg:city":"Oklahoma City",
    "sg:classifiers":[
        {
            "category":"Building & Trades",
            "subcategory":"Construction",
            "type":"Services"
        }
    ],
    "sg:phone":"+1 405 848 5939",
    "sg:postcode":"73114",
    "sg:province":"OK",
    "sg:tags":[
        "roofing",
        "contractor"
    ],
    "wof:name":"Troy Benear",
    "wof:placetype":"venue"
},
  "geometry": {"coordinates":[-97.537728,35.558561],"type":"Point"}
}