{
  "type": "Feature",
  "properties": {
    "iso:country":"US",
    "sg:address":"2700 N 5th St",
    "sg:city":"Mcalester",
    "sg:classifiers":[
        {
            "category":"Organizations",
            "subcategory":"Religious Organization",
            "type":"Services"
        }
    ],
    "sg:phone":"+1 918 423 4385",
    "sg:postcode":"74501",
    "sg:province":"OK",
    "sg:tags":[
        "church"
    ],
    "wof:name":"Second Baptist Church",
    "wof:placetype":"venue"
},
  "geometry": {"coordinates":[-95.75769099999999,34.955214],"type":"Point"}
}