{
  "type": "Feature",
  "properties": {
    "iso:country":"US",
    "sg:address":"1812 N Midwest Blvd",
    "sg:city":"Oklahoma City",
    "sg:classifiers":[
        {
            "category":"Professional",
            "subcategory":"Computer Services",
            "type":"Services"
        }
    ],
    "sg:phone":"+1 405 741 3580",
    "sg:postcode":"73141",
    "sg:province":"OK",
    "sg:tags":[
        "datum"
    ],
    "wof:name":"Digital 6 Productions LLC",
    "wof:placetype":"venue"
},
  "geometry": {"coordinates":[-97.388524,35.487606],"type":"Point"}
}