{
  "type": "Feature",
  "properties": {
    "addr:full":"318 N Howard Ave Elk City OK 73644",
    "addr:housenumber":"318",
    "addr:postcode":"73644",
    "addr:street":"N Howard Ave",
    "iso:country":"US",
    "sg:address":"318 N Howard Ave",
    "sg:city":"Elk City",
    "sg:classifiers":[
        {
            "category":"Retail",
            "subcategory":"Auto Rental",
            "type":"Services"
        }
    ],
    "sg:phone":"+1 580 225 7609",
    "sg:postcode":"73644",
    "sg:province":"OK",
    "sg:tags":[
        "passenger",
        "car"
    ],
    "wof:name":"Haines Wreck Service LLC",
    "wof:placetype":"venue"
},
  "geometry": {"coordinates":[-99.416145,35.413076],"type":"Point"}
}