{
  "type": "Feature",
  "properties": {
    "iso:country":"US",
    "sg:address":"2709 W I- 44 Svc Rd",
    "sg:city":"Oklahoma City",
    "sg:classifiers":[
        {
            "category":"Professional",
            "subcategory":"Management & Consulting",
            "type":"Services"
        }
    ],
    "sg:phone":"+1 405 601 1930",
    "sg:postcode":"73112",
    "sg:province":"OK",
    "sg:tags":[
        "consultant",
        "business"
    ],
    "wof:name":"Terry Neece Ctr",
    "wof:placetype":"venue"
},
  "geometry": {"coordinates":[-97.563284,35.511382],"type":"Point"}
}