{
  "type": "Feature",
  "properties": {
    "iso:country":"US",
    "sg:address":"4005 NW 42nd St",
    "sg:city":"Oklahoma City",
    "sg:classifiers":[
        {
            "category":"Health Services",
            "subcategory":"Health Practitioner",
            "type":"Services"
        }
    ],
    "sg:phone":"+1 405 601 9150",
    "sg:postcode":"73112",
    "sg:province":"OK",
    "sg:tags":[
        "pathologist",
        "speech"
    ],
    "sg:website":"www.speechreadinglaboratory.com",
    "wof:name":"Speechreading Laboratory Inc",
    "wof:placetype":"venue"
},
  "geometry": {"coordinates":[-97.592212,35.51512],"type":"Point"}
}