{
  "type": "Feature",
  "properties": {
    "iso:country":"US",
    "sg:address":"1032 SW 29th St",
    "sg:city":"Oklahoma City",
    "sg:classifiers":[
        {
            "category":"Home & Garden",
            "subcategory":"Furniture",
            "type":"Retail Goods"
        }
    ],
    "sg:phone":"+1 405 632 7858",
    "sg:postcode":"73109",
    "sg:province":"OK",
    "wof:name":"Owens Furniture Inc",
    "wof:placetype":"venue"
},
  "geometry": {"coordinates":[-97.533453,35.435169],"type":"Point"}
}