{
  "type": "Feature",
  "properties": {
    "iso:country":"US",
    "sg:address":"1306 N 14th St",
    "sg:city":"Enid",
    "sg:classifiers":[
        {
            "category":"Building & Trades",
            "subcategory":"Plumbing",
            "type":"Services"
        }
    ],
    "sg:phone":"+1 580 234 0555",
    "sg:postcode":"73701",
    "sg:province":"OK",
    "sg:tags":[
        "sheet",
        "work",
        "metal",
        "contractor"
    ],
    "wof:name":"Larry's Sheet Metal Co",
    "wof:placetype":"venue"
},
  "geometry": {"coordinates":[-97.857078,36.409161],"type":"Point"}
}