{
  "type": "Feature",
  "properties": {
    "iso:country":"US",
    "sg:address":"212 W Oklahoma Ave",
    "sg:city":"Guthrie",
    "sg:classifiers":[
        {
            "category":"Professional",
            "subcategory":"Management & Consulting",
            "type":"Services"
        }
    ],
    "sg:phone":"+1 405 282 0060",
    "sg:postcode":"73044",
    "sg:province":"OK",
    "sg:tags":[
        "development",
        "economic",
        "agency"
    ],
    "wof:name":"Logan County Economic Dev",
    "wof:placetype":"venue"
},
  "geometry": {"coordinates":[-97.427463,35.87811],"type":"Point"}
}