{
  "type": "Feature",
  "properties": {
    "addr:full":"114 W Monroe St Crescent OK 73028",
    "addr:housenumber":"114",
    "addr:postcode":"73028",
    "addr:street":"W Monroe St Crescent",
    "iso:country":"US",
    "sg:address":"114 W Monroe St",
    "sg:city":"Crescent",
    "sg:classifiers":[
        {
            "category":"Local Transit",
            "type":"Transportation"
        }
    ],
    "sg:phone":"+1 405 969 2000",
    "sg:postcode":"73028",
    "sg:province":"OK",
    "sg:tags":[
        "ambulance"
    ],
    "wof:name":"Crescent Ambulance Dist",
    "wof:placetype":"venue"
},
  "geometry": {"coordinates":[-97.59565600000001,35.952682],"type":"Point"}
}