{
  "type": "Feature",
  "properties": {
    "addr:full":"110 W Charles Ave Pauls Valley OK 73075",
    "addr:housenumber":"110",
    "addr:postcode":"73075",
    "addr:street":"W Charles Ave",
    "iso:country":"US",
    "sg:address":"110 W Charles Ave",
    "sg:city":"Pauls Valley",
    "sg:classifiers":[
        {
            "category":"Personal",
            "subcategory":"Beauty Salon",
            "type":"Services"
        }
    ],
    "sg:phone":"+1 405 238 4488",
    "sg:postcode":"73075",
    "sg:province":"OK",
    "sg:tags":[
        "manicuring"
    ],
    "wof:name":"New Nails",
    "wof:placetype":"venue"
},
  "geometry": {"coordinates":[-97.218514,34.739434],"type":"Point"}
}