{
  "type": "Feature",
  "properties": {
    "iso:country":"US",
    "sg:address":"600 N 5th St",
    "sg:city":"Tecumseh",
    "sg:classifiers":[
        {
            "category":"Real Estate",
            "subcategory":"Real Estate Operator",
            "type":"Services"
        }
    ],
    "sg:phone":"+1 405 598 6872",
    "sg:postcode":"74873",
    "sg:province":"OK",
    "sg:tags":[
        "apartment"
    ],
    "wof:name":"O K Village Apartments",
    "wof:placetype":"venue"
},
  "geometry": {"coordinates":[-96.93811599999999,35.263791],"type":"Point"}
}