{
  "type": "Feature",
  "properties": {
    "iso:country":"US",
    "sg:address":"3214 N Lake Ave",
    "sg:city":"Oklahoma City",
    "sg:classifiers":[
        {
            "category":"Organizations",
            "subcategory":"Religious Organization",
            "type":"Services"
        }
    ],
    "sg:phone":"+1 405 525 2349",
    "sg:postcode":"73118",
    "sg:province":"OK",
    "wof:name":"Our Ladys Cathedral",
    "wof:placetype":"venue"
},
  "geometry": {"coordinates":[-97.531002,35.502776],"type":"Point"}
}