{
  "type": "Feature",
  "properties": {
    "addr:full":"109 S Harper St Poteau OK 74953",
    "addr:housenumber":"109",
    "addr:postcode":"74953",
    "addr:street":"S Harper St",
    "iso:country":"US",
    "sg:address":"109 S Harper St",
    "sg:city":"Poteau",
    "sg:classifiers":[
        {
            "category":"Organizations",
            "subcategory":"Religious Organization",
            "type":"Services"
        }
    ],
    "sg:phone":"+1 918 647 2217",
    "sg:postcode":"74953",
    "sg:province":"OK",
    "wof:name":"First United Methodist Church",
    "wof:placetype":"venue"
},
  "geometry": {"coordinates":[-94.620836,35.051418],"type":"Point"}
}