{
  "type": "Feature",
  "properties": {
    "iso:country":"US",
    "sg:address":"5101 N May Ave",
    "sg:city":"Oklahoma City",
    "sg:classifiers":[
        {
            "category":"Organizations",
            "subcategory":"Religious Organization",
            "type":"Services"
        }
    ],
    "sg:phone":"+1 405 942 5591",
    "sg:postcode":"73112",
    "sg:province":"OK",
    "wof:name":"Central Presbyterian Church",
    "wof:placetype":"venue"
},
  "geometry": {"coordinates":[-97.56567699999999,35.524065],"type":"Point"}
}