{
  "type": "Feature",
  "properties": {
    "iso:country":"US",
    "sg:address":"4560 N Lewis Ave",
    "sg:city":"Tulsa",
    "sg:classifiers":[
        {
            "category":"Restaurant",
            "type":"Food & Drink"
        }
    ],
    "sg:phone":"+1 918 430 0018",
    "sg:postcode":"74110",
    "sg:province":"OK",
    "sg:tags":[
        "barbecue"
    ],
    "wof:name":"Big Daddys All American Bbq",
    "wof:placetype":"venue"
},
  "geometry": {"coordinates":[-95.958331,36.220093],"type":"Point"}
}