{
  "type": "Feature",
  "properties": {
    "iso:country":"US",
    "sg:address":"3825 E Main St",
    "sg:city":"Weatherford",
    "sg:classifiers":[
        {
            "category":"Travel",
            "subcategory":"Hotels & Motels",
            "type":"Entertainment"
        }
    ],
    "sg:phone":"+1 580 774 0400",
    "sg:postcode":"73096",
    "sg:province":"OK",
    "wof:name":"Holiday Inn Express Weatherfrd",
    "wof:placetype":"venue"
},
  "geometry": {"coordinates":[-98.676876,35.536594],"type":"Point"}
}