{
  "type": "Feature",
  "properties": {
    "iso:country":"US",
    "sg:address":"8255 State Hwy 16",
    "sg:city":"Beggs",
    "sg:classifiers":[
        {
            "category":"Manufacturing",
            "subcategory":"Tools & Machinery",
            "type":"Manufacturing & Wholesale Goods"
        }
    ],
    "sg:phone":"+1 918 267 5942",
    "sg:postcode":"74421",
    "sg:province":"OK",
    "sg:tags":[
        "industrial",
        "truck"
    ],
    "wof:name":"American Equipment",
    "wof:placetype":"venue"
},
  "geometry": {"coordinates":[-96.043058,35.74089],"type":"Point"}
}