{
  "type": "Feature",
  "properties": {
    "iso:country":"US",
    "sg:address":"331 W Graham Ave",
    "sg:city":"Pryor",
    "sg:classifiers":[
        {
            "category":"Shopping",
            "subcategory":"Clothing, Apparel, & Fashions",
            "type":"Retail Goods"
        }
    ],
    "sg:phone":"+1 918 824 7675",
    "sg:postcode":"74361",
    "sg:province":"OK",
    "wof:name":"His & Her Store",
    "wof:placetype":"venue"
},
  "geometry": {"coordinates":[-95.325128,36.309692],"type":"Point"}
}