{
  "type": "Feature",
  "properties": {
    "addr:full":"617 NW 88th St Oklahoma City OK 73114",
    "addr:housenumber":"617",
    "addr:postcode":"73114",
    "addr:street":"Nw 88Th St",
    "iso:country":"US",
    "sg:address":"617 NW 88th St",
    "sg:city":"Oklahoma City",
    "sg:classifiers":[
        {
            "category":"Social Services",
            "subcategory":"Child Care",
            "type":"Services"
        }
    ],
    "sg:phone":"+1 405 767 3384",
    "sg:postcode":"73114",
    "sg:province":"OK",
    "wof:name":"Ouap Daycare",
    "wof:placetype":"venue"
},
  "geometry": {"coordinates":[-97.523803,35.560507],"type":"Point"}
}