{
  "type": "Feature",
  "properties": {
    "iso:country":"US",
    "sg:address":"1200 S Reno Ave",
    "sg:city":"El Reno",
    "sg:phone":"+1 405 262 1678",
    "sg:postcode":"73036",
    "sg:province":"OK",
    "sg:tags":[
        "farm",
        "wheat",
        "beef",
        "feedlot",
        "cattle"
    ],
    "wof:name":"Donald Elmenhorst",
    "wof:placetype":"venue"
},
  "geometry": {"coordinates":[-97.96269599999999,35.519424],"type":"Point"}
}