{
  "type": "Feature",
  "properties": {
    "iso:country":"US",
    "sg:address":"315 S Main St",
    "sg:city":"Lindsay",
    "sg:classifiers":[
        {
            "category":"Shopping",
            "subcategory":"Computers & Home Electronics",
            "type":"Retail Goods"
        }
    ],
    "sg:phone":"+1 405 756 8877",
    "sg:postcode":"73052",
    "sg:province":"OK",
    "sg:tags":[
        "equipment",
        "dealer"
    ],
    "wof:name":"Ideal Solutions",
    "wof:placetype":"venue"
},
  "geometry": {"coordinates":[-97.602643,34.834481],"type":"Point"}
}