{
  "type": "Feature",
  "properties": {
    "iso:country":"US",
    "sg:address":"8529 Daman Pl",
    "sg:city":"Oklahoma City",
    "sg:classifiers":[
        {
            "category":"Professional",
            "subcategory":"Detective & Security Services",
            "type":"Services"
        }
    ],
    "sg:phone":"+1 405 685 1010",
    "sg:postcode":"73159",
    "sg:province":"OK",
    "sg:tags":[
        "guard"
    ],
    "wof:name":"Kenneth L Rinehart",
    "wof:placetype":"venue"
},
  "geometry": {"coordinates":[-97.542686,35.380895],"type":"Point"}
}