{
  "type": "Feature",
  "properties": {
    "iso:country":"US",
    "sg:address":"36 W Memorial Rd",
    "sg:city":"Oklahoma City",
    "sg:classifiers":[
        {
            "category":"Professional",
            "subcategory":"Research",
            "type":"Services"
        }
    ],
    "sg:phone":"+1 405 748 4190",
    "sg:postcode":"73114",
    "sg:province":"OK",
    "sg:tags":[
        "development",
        "laboratory"
    ],
    "wof:name":"Clinical Reference Lab",
    "wof:placetype":"venue"
},
  "geometry": {"coordinates":[-97.517296,35.609081],"type":"Point"}
}