{
  "type": "Feature",
  "properties": {
    "addr:full":"8801 S Victoria Dr Oklahoma City OK 73159",
    "addr:housenumber":"8801",
    "addr:postcode":"73159",
    "addr:street":"S Victoria Dr",
    "iso:country":"US",
    "sg:address":"8801 S Victoria Dr",
    "sg:city":"Oklahoma City",
    "sg:classifiers":[
        {
            "category":"Shopping",
            "subcategory":"Hobbies, Toys, & Games",
            "type":"Retail Goods"
        }
    ],
    "sg:phone":"+1 405 686 1934",
    "sg:postcode":"73159",
    "sg:province":"OK",
    "wof:name":"Kohers Kountry Kraft Inc",
    "wof:placetype":"venue"
},
  "geometry": {"coordinates":[-97.550792,35.378464],"type":"Point"}
}