{
  "type": "Feature",
  "properties": {
    "iso:country":"US",
    "sg:address":"501 Cherry Creek Dr",
    "sg:city":"Norman",
    "sg:classifiers":[
        {
            "category":"Shopping",
            "subcategory":"Bicycles & Sporting Goods",
            "type":"Retail Goods"
        }
    ],
    "sg:phone":"+1 405 364 2783",
    "sg:postcode":"73072",
    "sg:province":"OK",
    "wof:name":"Robert C",
    "wof:placetype":"venue"
},
  "geometry": {"coordinates":[-97.500793,35.213384],"type":"Point"}
}