{
  "type": "Feature",
  "properties": {
    "addr:full":"7925 E 71st St Tulsa OK 74133",
    "addr:housenumber":"7925",
    "addr:postcode":"74133",
    "addr:street":"E 71St St",
    "iso:country":"US",
    "sg:address":"7925 E 71st St",
    "sg:city":"Tulsa",
    "sg:classifiers":[
        {
            "category":"Restaurant",
            "type":"Food & Drink"
        }
    ],
    "sg:menulink":"http://www.allmenus.com/ok/tulsa/175346-arbys/menu/",
    "sg:phone":"+1 918 250 9254",
    "sg:postcode":"74133",
    "sg:province":"OK",
    "sg:tags":[
        "burger",
        "american"
    ],
    "wof:name":"Arby's",
    "wof:placetype":"venue"
},
  "geometry": {"coordinates":[-95.887659,36.061237],"type":"Point"}
}