{
  "type": "Feature",
  "properties": {
    "iso:country":"US",
    "sg:address":"326 S Santa Fe Ave",
    "sg:city":"Edmond",
    "sg:classifiers":[
        {
            "category":"Shopping",
            "subcategory":"Computers & Home Electronics",
            "type":"Retail Goods"
        }
    ],
    "sg:phone":"+1 405 216 0066",
    "sg:postcode":"73003",
    "sg:province":"OK",
    "sg:tags":[
        "equipment",
        "dealer"
    ],
    "wof:name":"My PC Intl Inc",
    "wof:placetype":"venue"
},
  "geometry": {"coordinates":[-97.513823,35.649898],"type":"Point"}
}