{
  "type": "Feature",
  "properties": {
    "iso:country":"US",
    "sg:address":"804 E Taft Ave",
    "sg:city":"Sapulpa",
    "sg:classifiers":[
        {
            "category":"Shopping",
            "subcategory":"Optical Goods",
            "type":"Retail Goods"
        }
    ],
    "sg:phone":"+1 918 227 2020",
    "sg:postcode":"74066",
    "sg:province":"OK",
    "wof:name":"Garys Family Eyewear",
    "wof:placetype":"venue"
},
  "geometry": {"coordinates":[-96.102275,35.988293],"type":"Point"}
}