{
  "type": "Feature",
  "properties": {
    "iso:country":"US",
    "sg:address":"1301 N 1st Ave",
    "sg:city":"Durant",
    "sg:classifiers":[
        {
            "category":"Restaurant",
            "type":"Food & Drink"
        }
    ],
    "sg:phone":"+1 580 924 4198",
    "sg:postcode":"74701",
    "sg:province":"OK",
    "sg:tags":[
        "drive"
    ],
    "wof:name":"Georges Drive Inn",
    "wof:placetype":"venue"
},
  "geometry": {"coordinates":[-96.37301600000001,34.002616],"type":"Point"}
}