{
  "type": "Feature",
  "properties": {
    "iso:country":"US",
    "sg:address":"3516 Banner Ct",
    "sg:city":"Edmond",
    "sg:classifiers":[
        {
            "category":"Real Estate",
            "subcategory":"Architect",
            "type":"Services"
        }
    ],
    "sg:phone":"+1 405 844 6970",
    "sg:postcode":"73013",
    "sg:province":"OK",
    "sg:tags":[
        "architectural"
    ],
    "wof:name":"Pointe Design Architects PC",
    "wof:placetype":"venue"
},
  "geometry": {"coordinates":[-97.47222499999999,35.620734],"type":"Point"}
}