{
  "type": "Feature",
  "properties": {
    "iso:country":"US",
    "sg:address":"5515 S Mingo Rd",
    "sg:city":"Tulsa",
    "sg:classifiers":[
        {
            "category":"Retail",
            "subcategory":"Repair Shop",
            "type":"Services"
        }
    ],
    "sg:phone":"+1 918 665 8160",
    "sg:postcode":"74146",
    "sg:province":"OK",
    "sg:tags":[
        "lock",
        "locksmith"
    ],
    "wof:name":"Dennis Spyres Sooner Lock Key",
    "wof:placetype":"venue"
},
  "geometry": {"coordinates":[-95.86853000000001,36.082764],"type":"Point"}
}