{
  "type": "Feature",
  "properties": {
    "iso:country":"US",
    "sg:address":"6004 N Rockwell Ave",
    "sg:city":"Bethany",
    "sg:classifiers":[
        {
            "category":"Autos & Motor Vehicles",
            "subcategory":"Auto Supplies",
            "type":"Retail Goods"
        }
    ],
    "sg:phone":"+1 405 728 2570",
    "sg:postcode":"73008",
    "sg:province":"OK",
    "sg:tags":[
        "repair",
        "general"
    ],
    "wof:name":"After 5 Automotive",
    "wof:placetype":"venue"
},
  "geometry": {"coordinates":[-97.636694,35.531043],"type":"Point"}
}