{
  "type": "Feature",
  "properties": {
    "iso:country":"US",
    "sg:address":"21908 N Douglas Ave",
    "sg:city":"Edmond",
    "sg:classifiers":[
        {
            "category":"Freight",
            "type":"Transportation"
        }
    ],
    "sg:phone":"+1 405 330 6302",
    "sg:postcode":"73003",
    "sg:province":"OK",
    "sg:tags":[
        "trucking"
    ],
    "wof:name":"Rojo's Trucking Inc",
    "wof:placetype":"venue"
},
  "geometry": {"coordinates":[-97.536167,35.694581],"type":"Point"}
}