{
  "type": "Feature",
  "properties": {
    "iso:country":"US",
    "sg:address":"806 W Blackwell Ave",
    "sg:city":"Blackwell",
    "sg:classifiers":[
        {
            "category":"Real Estate",
            "subcategory":"Real Estate Operator",
            "type":"Services"
        }
    ],
    "sg:phone":"+1 580 363 4738",
    "sg:postcode":"74631",
    "sg:province":"OK",
    "sg:tags":[
        "building",
        "apartment"
    ],
    "wof:name":"Kittie Houston Apartments Inc",
    "wof:placetype":"venue"
},
  "geometry": {"coordinates":[-97.29443000000001,36.804315],"type":"Point"}
}