{
  "type": "Feature",
  "properties": {
    "iso:country":"US",
    "sg:address":"6333 E Tecumseh St",
    "sg:city":"Tulsa",
    "sg:classifiers":[
        {
            "category":"Wholesale",
            "subcategory":"Machinery & Supplies",
            "type":"Manufacturing & Wholesale Goods"
        }
    ],
    "sg:phone":"+1 918 254 4789",
    "sg:postcode":"74115",
    "sg:province":"OK",
    "sg:tags":[
        "hardware",
        "industrial"
    ],
    "wof:name":"Lyda General Supply Inc",
    "wof:placetype":"venue"
},
  "geometry": {"coordinates":[-95.905475,36.182134],"type":"Point"}
}