{
  "type": "Feature",
  "properties": {
    "iso:country":"US",
    "sg:address":"2525 NW 10th St",
    "sg:city":"Oklahoma City",
    "sg:classifiers":[
        {
            "category":"Bars & Pubs",
            "type":"Food & Drink"
        }
    ],
    "sg:phone":"+1 405 521 1290",
    "sg:postcode":"73107",
    "sg:province":"OK",
    "sg:tags":[
        "club",
        "drinking",
        "night"
    ],
    "wof:name":"Danny's Blues Saloon",
    "wof:placetype":"venue"
},
  "geometry": {"coordinates":[-97.558412,35.478733],"type":"Point"}
}