{
  "type": "Feature",
  "properties": {
    "iso:country":"US",
    "sg:address":"17767 W 820 Rd",
    "sg:city":"Tahlequah",
    "sg:classifiers":[
        {
            "category":"Social Services",
            "subcategory":"Job Training",
            "type":"Services"
        }
    ],
    "sg:phone":"+1 918 456 1732",
    "sg:postcode":"74464",
    "sg:province":"OK",
    "sg:tags":[
        "counseling",
        "vocational"
    ],
    "wof:name":"AGM Consulting",
    "wof:placetype":"venue"
},
  "geometry": {"coordinates":[-94.987075,35.827164],"type":"Point"}
}