{
  "type": "Feature",
  "properties": {
    "iso:country":"US",
    "sg:address":"4521 Brentco Dr",
    "sg:city":"Oklahoma City",
    "sg:classifiers":[
        {
            "category":"Retail",
            "subcategory":"Auto Repair",
            "type":"Services"
        }
    ],
    "sg:phone":"+1 405 677 7255",
    "sg:postcode":"73115",
    "sg:province":"OK",
    "sg:tags":[
        "body"
    ],
    "wof:name":"Ken Holmes Enterprises",
    "wof:placetype":"venue"
},
  "geometry": {"coordinates":[-97.43514,35.433943],"type":"Point"}
}