{
  "type": "Feature",
  "properties": {
    "addr:full":"1515 E Main St Yukon OK 73099",
    "addr:housenumber":"1515",
    "addr:postcode":"73099",
    "addr:street":"E Main St",
    "iso:country":"US",
    "sg:address":"1515 E Main St",
    "sg:city":"Yukon",
    "sg:classifiers":[
        {
            "category":"Retail",
            "subcategory":"Auto Repair",
            "type":"Services"
        }
    ],
    "sg:phone":"+1 405 350 0285",
    "sg:postcode":"73099",
    "sg:province":"OK",
    "sg:tags":[
        "general"
    ],
    "wof:name":"Beatty Body Works",
    "wof:placetype":"venue"
},
  "geometry": {"coordinates":[-97.718255,35.510486],"type":"Point"}
}