{
  "type": "Feature",
  "properties": {
    "iso:country":"US",
    "sg:address":"4130 S Harvard Ave",
    "sg:city":"Tulsa",
    "sg:classifiers":[
        {
            "category":"Health Services",
            "subcategory":"Chiropractor",
            "type":"Services"
        }
    ],
    "sg:phone":"+1 918 743 0659",
    "sg:postcode":"74135",
    "sg:province":"OK",
    "wof:name":"Bill Mead Chiropractic",
    "wof:placetype":"venue"
},
  "geometry": {"coordinates":[-95.940278,36.101838],"type":"Point"}
}