{
  "type": "Feature",
  "properties": {
    "iso:country":"US",
    "sg:address":"2021 S Division St",
    "sg:city":"Guthrie",
    "sg:classifiers":[
        {
            "category":"Real Estate",
            "subcategory":"Real Estate Agent",
            "type":"Services"
        }
    ],
    "sg:phone":"+1 405 260 1800",
    "sg:postcode":"73044",
    "sg:province":"OK",
    "wof:name":"United Country Central Ok Land",
    "wof:placetype":"venue"
},
  "geometry": {"coordinates":[-97.425484,35.858962],"type":"Point"}
}