{
  "type": "Feature",
  "properties": {
    "iso:country":"US",
    "sg:address":"1833 S Irvington Ave",
    "sg:city":"Tulsa",
    "sg:classifiers":[
        {
            "category":"Building & Trades",
            "subcategory":"Landscaping Services",
            "type":"Services"
        }
    ],
    "sg:phone":"+1 918 835 0060",
    "sg:postcode":"74112",
    "sg:province":"OK",
    "sg:tags":[
        "tree"
    ],
    "wof:name":"Dave's Quality Tree Care",
    "wof:placetype":"venue"
},
  "geometry": {"coordinates":[-95.91194400000001,36.13471],"type":"Point"}
}