{
  "type": "Feature",
  "properties": {
    "addr:full":"2016 Main Ave Woodward OK 73801",
    "addr:housenumber":"2016",
    "addr:postcode":"73801",
    "addr:street":"Main Ave",
    "iso:country":"US",
    "sg:address":"2016 Main Ave",
    "sg:city":"Woodward",
    "sg:classifiers":[
        {
            "category":"Personal",
            "subcategory":"Beauty Salon",
            "type":"Services"
        }
    ],
    "sg:phone":"+1 580 256 5353",
    "sg:postcode":"73801",
    "sg:province":"OK",
    "wof:name":"A Hair Divided",
    "wof:placetype":"venue"
},
  "geometry": {"coordinates":[-99.40595,36.436051],"type":"Point"}
}