{
  "type": "Feature",
  "properties": {
    "iso:country":"US",
    "sg:address":"1403 W Walnut St",
    "sg:city":"Tecumseh",
    "sg:classifiers":[
        {
            "category":"Autos & Motor Vehicles",
            "subcategory":"Fuel & Gas Station",
            "type":"Retail Goods"
        }
    ],
    "sg:phone":"+1 405 598 6495",
    "sg:postcode":"74873",
    "sg:province":"OK",
    "sg:tags":[
        "station",
        "gasoline",
        "oil"
    ],
    "wof:name":"Mike's Service Station",
    "wof:placetype":"venue"
},
  "geometry": {"coordinates":[-96.952569,35.260886],"type":"Point"}
}