{
  "type": "Feature",
  "properties": {
    "addr:full":"3000 N Portland Ave Oklahoma City OK 73107",
    "addr:housenumber":"3000",
    "addr:postcode":"73107",
    "addr:street":"N Portland Ave",
    "iso:country":"US",
    "sg:address":"3000 N Portland Ave",
    "sg:city":"Oklahoma City",
    "sg:classifiers":[
        {
            "category":"Restaurant",
            "type":"Food & Drink"
        }
    ],
    "sg:phone":"+1 405 943 3637",
    "sg:postcode":"73107",
    "sg:province":"OK",
    "sg:tags":[
        "eating"
    ],
    "wof:name":"Mc Salty's Pizza",
    "wof:placetype":"venue"
},
  "geometry": {"coordinates":[-97.583384,35.499296],"type":"Point"}
}