{
  "type": "Feature",
  "properties": {
    "addr:full":"130 N Gray St Sapulpa OK 74066",
    "addr:housenumber":"130",
    "addr:postcode":"74066",
    "addr:street":"N Gray St",
    "iso:country":"US",
    "sg:address":"130 N Gray St",
    "sg:city":"Sapulpa",
    "sg:classifiers":[
        {
            "category":"Organizations",
            "subcategory":"Religious Organization",
            "type":"Services"
        }
    ],
    "sg:phone":"+1 918 227 4115",
    "sg:postcode":"74066",
    "sg:province":"OK",
    "sg:tags":[
        "church"
    ],
    "wof:name":"Mount Olive Baptist Church",
    "wof:placetype":"venue"
},
  "geometry": {"coordinates":[-96.12339900000001,35.999909],"type":"Point"}
}