{
  "type": "Feature",
  "properties": {
    "iso:country":"US",
    "sg:address":"1005 N Wentz St",
    "sg:city":"Guthrie",
    "sg:classifiers":[
        {
            "category":"Retail",
            "subcategory":"Animal Services",
            "type":"Services"
        }
    ],
    "sg:phone":"+1 405 282 6192",
    "sg:postcode":"73044",
    "sg:province":"OK",
    "sg:tags":[
        "pet",
        "grooming",
        "washing"
    ],
    "wof:name":"Pet Palace",
    "wof:placetype":"venue"
},
  "geometry": {"coordinates":[-97.424112,35.889617],"type":"Point"}
}