{
  "type": "Feature",
  "properties": {
    "addr:full":"2830 NW 32nd St Newcastle OK 73065",
    "addr:housenumber":"2830",
    "addr:postcode":"73065",
    "addr:street":"Nw 32Nd St",
    "iso:country":"US",
    "sg:address":"2830 NW 32nd St",
    "sg:city":"Newcastle",
    "sg:classifiers":[
        {
            "category":"Real Estate",
            "subcategory":"Real Estate Operator",
            "type":"Services"
        }
    ],
    "sg:phone":"+1 405 387 5223",
    "sg:postcode":"73065",
    "sg:province":"OK",
    "sg:tags":[
        "building",
        "parks"
    ],
    "wof:name":"Tri City West Office",
    "wof:placetype":"venue"
},
  "geometry": {"coordinates":[-97.644918,35.290912],"type":"Point"}
}