{
  "type": "Feature",
  "properties": {
    "iso:country":"US",
    "sg:address":"9501 SE 164th St",
    "sg:city":"Norman",
    "sg:classifiers":[
        {
            "category":"Freight",
            "type":"Transportation"
        }
    ],
    "sg:phone":"+1 405 237 1817",
    "sg:postcode":"73026",
    "sg:province":"OK",
    "sg:tags":[
        "carriage"
    ],
    "wof:name":"Pleasant Hill Carriage",
    "wof:placetype":"venue"
},
  "geometry": {"coordinates":[-97.359325,35.305158],"type":"Point"}
}