{
  "type": "Feature",
  "properties": {
    "addr:full":"601 Delaware St Perry OK 73077",
    "addr:housenumber":"601",
    "addr:postcode":"73077",
    "addr:street":"Delaware St",
    "iso:country":"US",
    "sg:address":"601 Delaware St",
    "sg:city":"Perry",
    "sg:classifiers":[
        {
            "category":"Banks & Credit Unions",
            "subcategory":"Investment Brokerage",
            "type":"Services"
        }
    ],
    "sg:phone":"+1 580 336 2244",
    "sg:postcode":"73077",
    "sg:province":"OK",
    "wof:name":"Morris Financial Svc",
    "wof:placetype":"venue"
},
  "geometry": {"coordinates":[-97.28577199999999,36.28726],"type":"Point"}
}