{
  "type": "Feature",
  "properties": {
    "iso:country":"US",
    "sg:address":"2508 S Sheridan Rd",
    "sg:city":"Tulsa",
    "sg:classifiers":[
        {
            "category":"Retail",
            "subcategory":"Auto Repair",
            "type":"Services"
        }
    ],
    "sg:phone":"+1 918 831 1550",
    "sg:postcode":"74129",
    "sg:province":"OK",
    "sg:tags":[
        "repairing",
        "automobile"
    ],
    "wof:name":"B & S Muffler & Brake",
    "wof:placetype":"venue"
},
  "geometry": {"coordinates":[-95.90461500000001,36.125783],"type":"Point"}
}