{
  "type": "Feature",
  "properties": {
    "addr:full":"2429 N Key Blvd Oklahoma City OK 73110",
    "addr:housenumber":"2429",
    "addr:postcode":"73110",
    "addr:street":"N Key Blvd",
    "iso:country":"US",
    "sg:address":"2429 N Key Blvd",
    "sg:city":"Oklahoma City",
    "sg:classifiers":[
        {
            "category":"Building & Trades",
            "subcategory":"Cleaning & Sanitation",
            "type":"Services"
        }
    ],
    "sg:phone":"+1 405 314 5749",
    "sg:postcode":"73110",
    "sg:province":"OK",
    "sg:tags":[
        "maintenance"
    ],
    "wof:name":"BMW Janitorial Services",
    "wof:placetype":"venue"
},
  "geometry": {"coordinates":[-97.397925,35.462123],"type":"Point"}
}