{
  "type": "Feature",
  "properties": {
    "iso:country":"US",
    "sg:address":"1642 E 2nd St",
    "sg:city":"Tulsa",
    "sg:classifiers":[
        {
            "category":"Retail",
            "subcategory":"Auto Repair",
            "type":"Services"
        }
    ],
    "sg:phone":"+1 918 582 4773",
    "sg:postcode":"74120",
    "sg:province":"OK",
    "sg:tags":[
        "machine",
        "automobile",
        "shop"
    ],
    "wof:name":"Rothhammer Cylinder Head Shop",
    "wof:placetype":"venue"
},
  "geometry": {"coordinates":[-95.967885,36.157579],"type":"Point"}
}