{
  "type": "Feature",
  "properties": {
    "addr:full":"6618 S Cedar Ave Broken Arrow OK 74011",
    "addr:housenumber":"6618",
    "addr:postcode":"74011",
    "addr:street":"S Cedar Ave",
    "iso:country":"US",
    "sg:address":"6618 S Cedar Ave",
    "sg:city":"Broken Arrow",
    "sg:classifiers":[
        {
            "category":"Manufacturing",
            "subcategory":"Rubber & Plastics",
            "type":"Manufacturing & Wholesale Goods"
        }
    ],
    "sg:phone":"+1 918 451 6774",
    "sg:postcode":"74011",
    "sg:province":"OK",
    "sg:tags":[
        "product",
        "mfg"
    ],
    "wof:name":"Norseman Plastics Inc",
    "wof:placetype":"venue"
},
  "geometry": {"coordinates":[-95.79210999999999,35.987571],"type":"Point"}
}