{
  "type": "Feature",
  "properties": {
    "iso:country":"US",
    "sg:address":"904 S Agnew Ave",
    "sg:city":"Oklahoma City",
    "sg:classifiers":[
        {
            "category":"Retail",
            "subcategory":"Auto Repair",
            "type":"Services"
        }
    ],
    "sg:phone":"+1 405 524 2768",
    "sg:postcode":"73108",
    "sg:province":"OK",
    "sg:tags":[
        "trailer"
    ],
    "wof:name":"Marcy Service Ctr",
    "wof:placetype":"venue"
},
  "geometry": {"coordinates":[-97.554692,35.458035],"type":"Point"}
}