{
  "type": "Feature",
  "properties": {
    "iso:country":"US",
    "sg:address":"2223 S Agnew Ave",
    "sg:city":"Oklahoma City",
    "sg:classifiers":[
        {
            "category":"Autos & Motor Vehicles",
            "subcategory":"Automobile Sales",
            "type":"Retail Goods"
        }
    ],
    "sg:phone":"+1 405 634 7722",
    "sg:postcode":"73108",
    "sg:province":"OK",
    "sg:tags":[
        "car",
        "dealer"
    ],
    "wof:name":"Paul's Auto Sales",
    "wof:placetype":"venue"
},
  "geometry": {"coordinates":[-97.554697,35.442654],"type":"Point"}
}