{
  "type": "Feature",
  "properties": {
    "addr:full":"1606 N Commerce St Ardmore OK 73401",
    "addr:housenumber":"1606",
    "addr:postcode":"73401",
    "addr:street":"N Commerce St",
    "iso:country":"US",
    "sg:address":"1606 N Commerce St",
    "sg:city":"Ardmore",
    "sg:classifiers":[
        {
            "category":"Restaurant",
            "type":"Food & Drink"
        }
    ],
    "sg:menulink":"http://www.allmenus.com/ok/ardmore/74625-pizza-hut/menu/",
    "sg:phone":"+1 580 226 2502",
    "sg:postcode":"73401",
    "sg:province":"OK",
    "sg:tags":[
        "american",
        "pizza"
    ],
    "wof:name":"Pizza Hut",
    "wof:placetype":"venue"
},
  "geometry": {"coordinates":[-97.143169,34.190844],"type":"Point"}
}