{
  "type": "Feature",
  "properties": {
    "addr:full":"1847 N 105th East Ave Tulsa OK 74116",
    "addr:housenumber":"1847",
    "addr:postcode":"74116",
    "addr:street":"N 105Th;Ave",
    "iso:country":"US",
    "sg:address":"1847 N 105th East Ave",
    "sg:city":"Tulsa",
    "sg:classifiers":[
        {
            "category":"Wholesale",
            "subcategory":"Electrical",
            "type":"Manufacturing & Wholesale Goods"
        }
    ],
    "sg:phone":"+1 918 838 7777",
    "sg:postcode":"74116",
    "sg:province":"OK",
    "sg:tags":[
        "industrial",
        "lighting",
        "janitorial",
        "supply"
    ],
    "wof:name":"Lektron Industrial Ltg Sup",
    "wof:placetype":"venue"
},
  "geometry": {"coordinates":[-95.859847,36.180914],"type":"Point"}
}