{
  "type": "Feature",
  "properties": {
    "addr:full":"7101 NW 23rd St Bethany OK 73008",
    "addr:housenumber":"7101",
    "addr:postcode":"73008",
    "addr:street":"Nw 23Rd St",
    "iso:country":"US",
    "sg:address":"7101 NW 23rd St",
    "sg:city":"Bethany",
    "sg:classifiers":[
        {
            "category":"Restaurant",
            "type":"Food & Drink"
        }
    ],
    "sg:menulink":"http://www.allmenus.com/ok/oklahoma-city/106934-soup-man/menu/",
    "sg:phone":"+1 405 789 2834",
    "sg:postcode":"73008",
    "sg:province":"OK",
    "sg:tags":[
        "soup",
        "american",
        "salad"
    ],
    "wof:name":"Soup Man",
    "wof:placetype":"venue"
},
  "geometry": {"coordinates":[-97.636645,35.493395],"type":"Point"}
}