{
  "type": "Feature",
  "properties": {
    "addr:full":"401 S 7th St Henryetta OK 74437",
    "addr:housenumber":"401",
    "addr:postcode":"74437",
    "addr:street":"S 7Th St",
    "iso:country":"US",
    "sg:address":"401 S 7th St",
    "sg:city":"Henryetta",
    "sg:classifiers":[
        {
            "category":"Organizations",
            "subcategory":"Religious Organization",
            "type":"Services"
        }
    ],
    "sg:phone":"+1 918 652 2752",
    "sg:postcode":"74437",
    "sg:province":"OK",
    "sg:tags":[
        "church"
    ],
    "wof:name":"Victory Christian Church",
    "wof:placetype":"venue"
},
  "geometry": {"coordinates":[-95.98957799999999,35.43658],"type":"Point"}
}