{
  "type": "Feature",
  "properties": {
    "iso:country":"US",
    "sg:address":"102 N Ellison St",
    "sg:city":"Guymon",
    "sg:classifiers":[
        {
            "category":"Autos & Motor Vehicles",
            "subcategory":"Motorcycle Sales",
            "type":"Retail Goods"
        }
    ],
    "sg:phone":"+1 580 338 4647",
    "sg:postcode":"73942",
    "sg:province":"OK",
    "sg:tags":[
        "scooter"
    ],
    "wof:name":"House Of Thunder",
    "wof:placetype":"venue"
},
  "geometry": {"coordinates":[-101.48026400000001,36.679905],"type":"Point"}
}