{
  "type": "Feature",
  "properties": {
    "iso:country":"US",
    "sg:address":"2309 W Nashville Ct",
    "sg:city":"Broken Arrow",
    "sg:classifiers":[
        {
            "category":"Wholesale",
            "subcategory":"Machinery & Supplies",
            "type":"Manufacturing & Wholesale Goods"
        }
    ],
    "sg:phone":"+1 918 258 8444",
    "sg:postcode":"74012",
    "sg:province":"OK",
    "sg:tags":[
        "equipment",
        "irrigation",
        "system"
    ],
    "wof:name":"Irrigation Engineering Inc",
    "wof:placetype":"venue"
},
  "geometry": {"coordinates":[-95.81712,36.040414],"type":"Point"}
}