{
  "type": "Feature",
  "properties": {
    "iso:country":"US",
    "sg:address":"500 SE Frank Phillips Blvd",
    "sg:city":"Bartlesville",
    "sg:classifiers":[
        {
            "category":"Health Services",
            "subcategory":"Doctor",
            "type":"Services"
        }
    ],
    "sg:phone":"+1 918 337 5222",
    "sg:postcode":"74003",
    "sg:province":"OK",
    "sg:tags":[
        "clinic"
    ],
    "wof:name":"Green Country Free Clinic",
    "wof:placetype":"venue"
},
  "geometry": {"coordinates":[-95.971897,36.750662],"type":"Point"}
}