{
  "type": "Feature",
  "properties": {
    "addr:full":"5320 N Portland Ave Oklahoma City OK 73112",
    "addr:housenumber":"5320",
    "addr:postcode":"73112",
    "addr:street":"N Portland Ave",
    "iso:country":"US",
    "sg:address":"5320 N Portland Ave",
    "sg:city":"Oklahoma City",
    "sg:classifiers":[
        {
            "category":"Health Services",
            "subcategory":"Doctor",
            "type":"Services"
        }
    ],
    "sg:phone":"+1 405 947 3330",
    "sg:postcode":"73112",
    "sg:province":"OK",
    "sg:tags":[
        "physician"
    ],
    "wof:name":"Blackwell Carol MD",
    "wof:placetype":"venue"
},
  "geometry": {"coordinates":[-97.58336300000001,35.524411],"type":"Point"}
}