{
  "type": "Feature",
  "properties": {
    "iso:country":"US",
    "sg:address":"529 S Harrison St",
    "sg:city":"Shawnee",
    "sg:classifiers":[
        {
            "category":"Wholesale",
            "subcategory":"Auto Parts",
            "type":"Manufacturing & Wholesale Goods"
        }
    ],
    "sg:phone":"+1 405 214 5463",
    "sg:postcode":"74801",
    "sg:province":"OK",
    "sg:tags":[
        "truck",
        "accessory"
    ],
    "wof:name":"Line-X Of Shawnee",
    "wof:placetype":"venue"
},
  "geometry": {"coordinates":[-96.912084,35.32074],"type":"Point"}
}