{
  "type": "Feature",
  "properties": {
    "addr:full":"3509 NW 58th St Oklahoma City OK 73112",
    "addr:housenumber":"3509",
    "addr:postcode":"73112",
    "addr:street":"Nw 58Th St",
    "iso:country":"US",
    "sg:address":"3509 NW 58th St",
    "sg:city":"Oklahoma City",
    "sg:classifiers":[
        {
            "category":"Restaurant",
            "type":"Food & Drink"
        }
    ],
    "sg:phone":"+1 405 946 5771",
    "sg:postcode":"73112",
    "sg:province":"OK",
    "wof:name":"Henry Hudson's Pub",
    "wof:placetype":"venue"
},
  "geometry": {"coordinates":[-97.579526,35.529676],"type":"Point"}
}