{
  "type": "Feature",
  "properties": {
    "iso:country":"US",
    "sg:address":"734 Arlington St",
    "sg:city":"Ada",
    "sg:classifiers":[
        {
            "category":"Health Services",
            "subcategory":"Chiropractor",
            "type":"Services"
        }
    ],
    "sg:phone":"+1 580 310 9755",
    "sg:postcode":"74820",
    "sg:province":"OK",
    "wof:name":"Hale Chiropractic",
    "wof:placetype":"venue"
},
  "geometry": {"coordinates":[-96.669193,34.781783],"type":"Point"}
}