{
  "type": "Feature",
  "properties": {
    "addr:full":"1209 S Utah St Muskogee OK 74403",
    "addr:housenumber":"1209",
    "addr:postcode":"74403",
    "addr:street":"S Utah St",
    "iso:country":"US",
    "sg:address":"1209 S Utah St",
    "sg:city":"Muskogee",
    "sg:classifiers":[
        {
            "category":"Building & Trades",
            "subcategory":"Plumbing",
            "type":"Services"
        }
    ],
    "sg:phone":"+1 918 687 6605",
    "sg:postcode":"74403",
    "sg:province":"OK",
    "sg:tags":[
        "conditioning",
        "air",
        "system",
        "contractor"
    ],
    "wof:name":"Martin Service Co",
    "wof:placetype":"venue"
},
  "geometry": {"coordinates":[-95.344229,35.730417],"type":"Point"}
}