{
  "type": "Feature",
  "properties": {
    "iso:country":"US",
    "sg:address":"3423 S Gary Pl",
    "sg:city":"Tulsa",
    "sg:classifiers":[
        {
            "category":"Restaurant",
            "type":"Food & Drink"
        }
    ],
    "sg:phone":"+1 918 747 4753",
    "sg:postcode":"74105",
    "sg:province":"OK",
    "sg:tags":[
        "eating"
    ],
    "wof:name":"Chinatown Restaurant",
    "wof:placetype":"venue"
},
  "geometry": {"coordinates":[-95.940898,36.11191],"type":"Point"}
}