{
  "type": "Feature",
  "properties": {
    "addr:full":"1001 E Will Rogers Blvd Claremore OK 74017",
    "addr:housenumber":"1001",
    "addr:postcode":"74017",
    "addr:street":"E Will Rogers Blvd",
    "iso:country":"US",
    "sg:address":"1001 E Will Rogers Blvd",
    "sg:city":"Claremore",
    "sg:classifiers":[
        {
            "category":"Freight",
            "type":"Transportation"
        }
    ],
    "sg:phone":"+1 918 342 1535",
    "sg:postcode":"74017",
    "sg:province":"OK",
    "sg:tags":[
        "commercial",
        "storage"
    ],
    "wof:name":"More Storage",
    "wof:placetype":"venue"
},
  "geometry": {"coordinates":[-95.59805,36.307379],"type":"Point"}
}