{
  "type": "Feature",
  "properties": {
    "iso:country":"US",
    "sg:address":"1424 W Easton Pl",
    "sg:city":"Tulsa",
    "sg:classifiers":[
        {
            "category":"Professional",
            "subcategory":"Testing Lab",
            "type":"Services"
        }
    ],
    "sg:phone":"+1 918 587 3764",
    "sg:postcode":"74127",
    "sg:province":"OK",
    "sg:tags":[
        "calibration"
    ],
    "wof:name":"MRS Calibrations",
    "wof:placetype":"venue"
},
  "geometry": {"coordinates":[-96.009287,36.160072],"type":"Point"}
}