{
  "type": "Feature",
  "properties": {
    "iso:country":"US",
    "sg:address":"4615 S 49th West Ave",
    "sg:city":"Tulsa",
    "sg:classifiers":[
        {
            "category":"Manufacturing",
            "subcategory":"Wood Products",
            "type":"Manufacturing & Wholesale Goods"
        },
        {
            "category":"Home & Garden",
            "subcategory":"Furniture",
            "type":"Retail Goods"
        }
    ],
    "sg:phone":"+1 918 749 7062",
    "sg:postcode":"74107",
    "sg:province":"OK",
    "sg:tags":[
        "cabinet",
        "equipment-household",
        "millwork-wholesale",
        "manufacturer",
        "millwork",
        "kitchen"
    ],
    "sg:website":"http://www.woodsystems.net",
    "wof:name":"Wood Systems, Inc.",
    "wof:placetype":"venue"
},
  "geometry": {"coordinates":[-96.047434,36.095786],"type":"Point"}
}