{
  "type": "Feature",
  "properties": {
    "addr:full":"605 Heatherstone Rd Edmond OK 73034",
    "addr:housenumber":"605",
    "addr:postcode":"73034",
    "addr:street":"Heatherstone Rd",
    "iso:country":"US",
    "sg:address":"605 Heatherstone Rd",
    "sg:city":"Edmond",
    "sg:classifiers":[
        {
            "category":"Freight",
            "type":"Transportation"
        }
    ],
    "sg:phone":"+1 405 330 4745",
    "sg:postcode":"73034",
    "sg:province":"OK",
    "wof:name":"Werner Enterprises Inc",
    "wof:placetype":"venue"
},
  "geometry": {"coordinates":[-97.471609,35.676507],"type":"Point"}
}