{
  "type": "Feature",
  "properties": {
    "iso:country":"US",
    "sg:address":"1000 N Santa Fe Ave",
    "sg:city":"Oklahoma City",
    "sg:classifiers":[
        {
            "category":"Retail",
            "subcategory":"Auto Rental",
            "type":"Services"
        }
    ],
    "sg:phone":"+1 405 844 4892",
    "sg:postcode":"73160",
    "sg:province":"OK",
    "sg:tags":[
        "truck"
    ],
    "wof:name":"Ryder",
    "wof:placetype":"venue"
},
  "geometry": {"coordinates":[-97.51215500000001,35.346422],"type":"Point"}
}