{
  "type": "Feature",
  "properties": {
    "iso:country":"US",
    "sg:address":"842 W Danforth Rd",
    "sg:city":"Edmond",
    "sg:classifiers":[
        {
            "category":"Education",
            "subcategory":"Dance Studio",
            "type":"Public Place"
        }
    ],
    "sg:phone":"+1 405 348 7827",
    "sg:postcode":"73003",
    "sg:province":"OK",
    "wof:name":"Star Steps Inc",
    "wof:placetype":"venue"
},
  "geometry": {"coordinates":[-97.492564,35.667368],"type":"Point"}
}