{
  "type": "Feature",
  "properties": {
    "iso:country":"US",
    "sg:address":"112 S Central Ave",
    "sg:city":"Idabel",
    "sg:classifiers":[
        {
            "category":"Banks & Credit Unions",
            "subcategory":"Bank",
            "type":"Services"
        }
    ],
    "sg:phone":"+1 580 286 4441",
    "sg:postcode":"74745",
    "sg:province":"OK",
    "sg:tags":[
        "loan",
        "real estate"
    ],
    "wof:name":"United Mortgage",
    "wof:placetype":"venue"
},
  "geometry": {"coordinates":[-94.8267,33.893183],"type":"Point"}
}