{
  "type": "Feature",
  "properties": {
    "iso:country":"US",
    "sg:address":"600 S Washington St",
    "sg:city":"Ardmore",
    "sg:classifiers":[
        {
            "category":"Building & Trades",
            "subcategory":"Construction",
            "type":"Services"
        }
    ],
    "sg:phone":"+1 580 223 1304",
    "sg:postcode":"73401",
    "sg:province":"OK",
    "sg:tags":[
        "house"
    ],
    "wof:name":"Redrock Design & Construction",
    "wof:placetype":"venue"
},
  "geometry": {"coordinates":[-97.131296,34.165644],"type":"Point"}
}