{
  "type": "Feature",
  "properties": {
    "addr:full":"804 W Curtis Dr Oklahoma City OK 73110",
    "addr:housenumber":"804",
    "addr:postcode":"73110",
    "addr:street":"W Curtis Dr",
    "iso:country":"US",
    "sg:address":"804 W Curtis Dr",
    "sg:city":"Oklahoma City",
    "sg:classifiers":[
        {
            "category":"Real Estate",
            "subcategory":"Real Estate Agent",
            "type":"Services"
        }
    ],
    "sg:phone":"+1 405 736 1054",
    "sg:postcode":"73110",
    "sg:province":"OK",
    "wof:name":"Yukon Properties Management",
    "wof:placetype":"venue"
},
  "geometry": {"coordinates":[-97.411188,35.437501],"type":"Point"}
}