{
  "type": "Feature",
  "properties": {
    "addr:full":"1560 SE Washington Blvd Bartlesville OK 74006",
    "addr:housenumber":"1560",
    "addr:postcode":"74006",
    "addr:street":"Se Washington Blvd",
    "iso:country":"US",
    "sg:address":"1560 SE Washington Blvd",
    "sg:city":"Bartlesville",
    "sg:classifiers":[
        {
            "category":"Personal",
            "type":"Services"
        }
    ],
    "sg:phone":"+1 918 331 0304",
    "sg:postcode":"74006",
    "sg:province":"OK",
    "sg:tags":[
        "therapist",
        "massage"
    ],
    "wof:name":"Generating Wellness By Massage",
    "wof:placetype":"venue"
},
  "geometry": {"coordinates":[-95.935089,36.730667],"type":"Point"}
}