{
  "type": "Feature",
  "properties": {
    "iso:country":"US",
    "sg:address":"4201 W Memorial Rd",
    "sg:city":"Oklahoma City",
    "sg:classifiers":[
        {
            "category":"Professional",
            "subcategory":"Management & Consulting",
            "type":"Services"
        }
    ],
    "sg:phone":"+1 405 951 8762",
    "sg:postcode":"73134",
    "sg:province":"OK",
    "wof:name":"Organizational Design Sol",
    "wof:placetype":"venue"
},
  "geometry": {"coordinates":[-97.59805799999999,35.610265],"type":"Point"}
}