{
  "type": "Feature",
  "properties": {
    "iso:country":"US",
    "sg:address":"4425 E 31st St S",
    "sg:city":"Tulsa",
    "sg:classifiers":[
        {
            "category":"Professional",
            "subcategory":"Lawyer & Legal Services",
            "type":"Services"
        }
    ],
    "sg:phone":"+1 918 749 1262",
    "sg:postcode":"74135",
    "sg:province":"OK",
    "wof:name":"Caldwell Catherine M Attny At",
    "wof:placetype":"venue"
},
  "geometry": {"coordinates":[-95.92741599999999,36.118928],"type":"Point"}
}