{
  "type": "Feature",
  "properties": {
    "addr:full":"6510 E 24th St Tulsa OK 74129",
    "addr:housenumber":"6510",
    "addr:postcode":"74129",
    "addr:street":"E 24Th St",
    "iso:country":"US",
    "sg:address":"6510 E 24th St",
    "sg:city":"Tulsa",
    "sg:classifiers":[
        {
            "category":"Real Estate",
            "subcategory":"Real Estate Agent",
            "type":"Services"
        }
    ],
    "sg:phone":"+1 918 744 7653",
    "sg:postcode":"74129",
    "sg:province":"OK",
    "wof:name":"Team One Realtors",
    "wof:placetype":"venue"
},
  "geometry": {"coordinates":[-95.900244,36.128748],"type":"Point"}
}