{
  "type": "Feature",
  "properties": {
    "addr:full":"601 N Lester St Elk City OK 73644",
    "addr:housenumber":"601",
    "addr:postcode":"73644",
    "addr:street":"N Lester St",
    "iso:country":"US",
    "sg:address":"601 N Lester St",
    "sg:city":"Elk City",
    "sg:classifiers":[
        {
            "category":"Restaurant",
            "type":"Food & Drink"
        }
    ],
    "sg:phone":"+1 580 225 4186",
    "sg:postcode":"73644",
    "sg:province":"OK",
    "sg:tags":[
        "eating"
    ],
    "wof:name":"Lupes Cantina",
    "wof:placetype":"venue"
},
  "geometry": {"coordinates":[-99.389967,35.415493],"type":"Point"}
}