{
  "type": "Feature",
  "properties": {
    "addr:full":"6110 Flaming Oaks Cir Norman OK 73026",
    "addr:housenumber":"6110",
    "addr:postcode":"73026",
    "addr:street":"Flaming Oaks Cir",
    "iso:country":"US",
    "sg:address":"6110 Flaming Oaks Cir",
    "sg:city":"Norman",
    "sg:classifiers":[
        {
            "category":"Professional",
            "subcategory":"Lawyer & Legal Services",
            "type":"Services"
        }
    ],
    "sg:phone":"+1 405 360 7152",
    "sg:postcode":"73026",
    "sg:province":"OK",
    "wof:name":"Donald K Russell",
    "wof:placetype":"venue"
},
  "geometry": {"coordinates":[-97.351124,35.20655],"type":"Point"}
}