{
  "type": "Feature",
  "properties": {
    "iso:country":"US",
    "sg:address":"1223 W Boston Ct",
    "sg:city":"Broken Arrow",
    "sg:classifiers":[
        {
            "category":"Building & Trades",
            "subcategory":"Pest Control",
            "type":"Services"
        }
    ],
    "sg:phone":"+1 918 455 5271",
    "sg:postcode":"74012",
    "sg:province":"OK",
    "wof:name":"A Plus Exterminators",
    "wof:placetype":"venue"
},
  "geometry": {"coordinates":[-95.803548,36.026717],"type":"Point"}
}