{
  "type": "Feature",
  "properties": {
    "addr:full":"824 US Hwy 177 Carney OK 74832",
    "addr:housenumber":"824",
    "addr:postcode":"74832",
    "addr:street":"Us Hwy 177",
    "iso:country":"US",
    "sg:address":"824 US Hwy 177",
    "sg:city":"Carney",
    "sg:classifiers":[
        {
            "category":"Restaurant",
            "type":"Food & Drink"
        }
    ],
    "sg:phone":"+1 405 865 3142",
    "sg:postcode":"74832",
    "sg:province":"OK",
    "wof:name":"Power Line",
    "wof:placetype":"venue"
},
  "geometry": {"coordinates":[-97.017912,35.797153],"type":"Point"}
}