{
  "type": "Feature",
  "properties": {
    "iso:country":"US",
    "sg:address":"1604 NW 5th St",
    "sg:city":"Oklahoma City",
    "sg:classifiers":[
        {
            "category":"Manufacturing",
            "subcategory":"Furniture",
            "type":"Manufacturing & Wholesale Goods"
        }
    ],
    "sg:phone":"+1 405 239 7363",
    "sg:postcode":"73106",
    "sg:province":"OK",
    "sg:website":"www.arwoodfurniture.com",
    "wof:name":"Arwood Industries",
    "wof:placetype":"venue"
},
  "geometry": {"coordinates":[-97.543321,35.473174],"type":"Point"}
}