{
  "type": "Feature",
  "properties": {
    "iso:country":"US",
    "sg:address":"11500 N Garnett Rd",
    "sg:city":"Owasso",
    "sg:classifiers":[
        {
            "category":"Banks & Credit Unions",
            "subcategory":"Bank",
            "type":"Services"
        }
    ],
    "sg:phone":"+1 918 371 4504",
    "sg:postcode":"74055",
    "sg:province":"OK",
    "wof:name":"First Bank Of Owasso",
    "wof:placetype":"venue"
},
  "geometry": {"coordinates":[-95.848232,36.320449],"type":"Point"}
}