{
  "type": "Feature",
  "properties": {
    "addr:full":"7750 S 655 Rd Quapaw OK 74363",
    "addr:housenumber":"7750",
    "addr:postcode":"74363",
    "addr:street":"S 655 Rd",
    "iso:country":"US",
    "sg:address":"7750 S 655 Rd",
    "sg:city":"Quapaw",
    "sg:classifiers":[
        {
            "category":"Travel",
            "subcategory":"Campground",
            "type":"Entertainment"
        }
    ],
    "sg:phone":"+1 918 542 1547",
    "sg:postcode":"74363",
    "sg:province":"OK",
    "sg:tags":[
        "camp"
    ],
    "wof:name":"Sky Ranch At Cave Spring",
    "wof:placetype":"venue"
},
  "geometry": {"coordinates":[-94.70704600000001,36.904179],"type":"Point"}
}