{
  "type": "Feature",
  "properties": {
    "addr:full":"9904 Sahara Dr Oklahoma City OK 73162",
    "addr:housenumber":"9904",
    "addr:postcode":"73162",
    "addr:street":"Sahara Dr",
    "iso:country":"US",
    "sg:address":"9904 Sahara Dr",
    "sg:city":"Oklahoma City",
    "sg:classifiers":[
        {
            "category":"Building & Trades",
            "subcategory":"Landscaping Services",
            "type":"Services"
        }
    ],
    "sg:phone":"+1 405 720 2215",
    "sg:postcode":"73162",
    "sg:province":"OK",
    "sg:tags":[
        "lawn",
        "maintenance",
        "grounds"
    ],
    "wof:name":"Lawn Care Svc",
    "wof:placetype":"venue"
},
  "geometry": {"coordinates":[-97.62126000000001,35.571642],"type":"Point"}
}