{
  "type": "Feature",
  "properties": {
    "iso:country":"US",
    "sg:address":"1316 S 79th West Ave",
    "sg:city":"Tulsa",
    "sg:classifiers":[
        {
            "category":"Education",
            "subcategory":"School",
            "type":"Public Place"
        }
    ],
    "sg:phone":"+1 918 246 1564",
    "sg:postcode":"74127",
    "sg:province":"OK",
    "wof:name":"Lake School",
    "wof:placetype":"venue"
},
  "geometry": {"coordinates":[-96.081758,36.14231],"type":"Point"}
}