{
  "type": "Feature",
  "properties": {
    "iso:country":"US",
    "sg:address":"8512 Main St",
    "sg:city":"Spencer",
    "sg:classifiers":[
        {
            "category":"Organizations",
            "subcategory":"Religious Organization",
            "type":"Services"
        }
    ],
    "sg:phone":"+1 405 771 3377",
    "sg:postcode":"73084",
    "sg:province":"OK",
    "sg:tags":[
        "church"
    ],
    "wof:name":"First Deliverance Church",
    "wof:placetype":"venue"
},
  "geometry": {"coordinates":[-97.377923,35.522646],"type":"Point"}
}