{
  "type": "Feature",
  "properties": {
    "iso:country":"US",
    "sg:address":"1410 E 56th St",
    "sg:city":"Tulsa",
    "sg:classifiers":[
        {
            "category":"Social Services",
            "type":"Services"
        }
    ],
    "sg:phone":"+1 918 747 4320",
    "sg:postcode":"74105",
    "sg:province":"OK",
    "sg:tags":[
        "arts",
        "providing",
        "music",
        "education",
        "humanities"
    ],
    "wof:name":"Intouch Foundation Inc",
    "wof:placetype":"venue"
},
  "geometry": {"coordinates":[-95.972571,36.082403],"type":"Point"}
}