{
  "type": "Feature",
  "properties": {
    "addr:full":"5020 NW 63rd St Oklahoma City OK 73132",
    "addr:housenumber":"5020",
    "addr:postcode":"73132",
    "addr:street":"Nw 63Rd St",
    "iso:country":"US",
    "sg:address":"5020 NW 63rd St",
    "sg:city":"Oklahoma City",
    "sg:classifiers":[
        {
            "category":"Organizations",
            "subcategory":"Religious Organization",
            "type":"Services"
        }
    ],
    "sg:phone":"+1 405 721 5888",
    "sg:postcode":"73132",
    "sg:province":"OK",
    "sg:tags":[
        "church"
    ],
    "wof:name":"Church Of Jesus Christ Of Lds",
    "wof:placetype":"venue"
},
  "geometry": {"coordinates":[-97.609105,35.536745],"type":"Point"}
}