{
  "type": "Feature",
  "properties": {
    "iso:country":"US",
    "sg:address":"1615 S Denver Ave",
    "sg:city":"Tulsa",
    "sg:classifiers":[
        {
            "category":"Professional",
            "subcategory":"Management & Consulting",
            "type":"Services"
        }
    ],
    "sg:phone":"+1 918 585 2211",
    "sg:postcode":"74119",
    "sg:province":"OK",
    "sg:tags":[
        "consultant"
    ],
    "wof:name":"Lift Consulting",
    "wof:placetype":"venue"
},
  "geometry": {"coordinates":[-95.9923,36.139348],"type":"Point"}
}