{
  "type": "Feature",
  "properties": {
    "iso:country":"US",
    "sg:address":"329 N Magnolia Ave",
    "sg:city":"Newkirk",
    "sg:classifiers":[
        {
            "category":"Social Services",
            "subcategory":"Child Care",
            "type":"Services"
        }
    ],
    "sg:phone":"+1 580 362 2325",
    "sg:postcode":"74647",
    "sg:province":"OK",
    "sg:tags":[
        "day"
    ],
    "wof:name":"Harris Gerri Day Care",
    "wof:placetype":"venue"
},
  "geometry": {"coordinates":[-97.058018,36.88601],"type":"Point"}
}