{
  "type": "Feature",
  "properties": {
    "addr:full":"919 E Wyandotte Ave Bache OK 74501",
    "addr:housenumber":"919",
    "addr:postcode":"74501",
    "addr:street":"E Wyandotte Ave",
    "iso:country":"US",
    "sg:address":"919 E Wyandotte Ave",
    "sg:city":"Bache",
    "sg:classifiers":[
        {
            "category":"Wholesale",
            "subcategory":"Machinery & Supplies",
            "type":"Manufacturing & Wholesale Goods"
        }
    ],
    "sg:phone":"+1 918 423 8979",
    "sg:postcode":"74501",
    "sg:province":"OK",
    "sg:tags":[
        "equipment",
        "establishment"
    ],
    "wof:name":"Headhunters By Elex",
    "wof:placetype":"venue"
},
  "geometry": {"coordinates":[-95.758782,34.926258],"type":"Point"}
}