{
  "type": "Feature",
  "properties": {
    "iso:country":"US",
    "sg:address":"2001 Exchange Ave",
    "sg:city":"Oklahoma City",
    "sg:classifiers":[
        {
            "category":"Professional",
            "subcategory":"Detective & Security Services",
            "type":"Services"
        }
    ],
    "sg:phone":"+1 405 235 0800",
    "sg:postcode":"73108",
    "sg:province":"OK",
    "sg:tags":[
        "car",
        "insurance"
    ],
    "wof:name":"Trace Detective Agency",
    "wof:placetype":"venue"
},
  "geometry": {"coordinates":[-97.551611,35.452821],"type":"Point"}
}