{
  "type": "Feature",
  "properties": {
    "iso:country":"US",
    "sg:address":"211 S Chisholm Ave",
    "sg:city":"Tishomingo",
    "sg:classifiers":[
        {
            "category":"Education",
            "subcategory":"School",
            "type":"Public Place"
        }
    ],
    "sg:phone":"+1 580 371 2567",
    "sg:postcode":"73460",
    "sg:province":"OK",
    "wof:name":"Tishomingo Vocational Agri",
    "wof:placetype":"venue"
},
  "geometry": {"coordinates":[-96.662384,34.228671],"type":"Point"}
}