{
  "type": "Feature",
  "properties": {
    "addr:full":"3801 91st Ave NE Norman OK 73026",
    "addr:housenumber":"3801",
    "addr:postcode":"73026",
    "addr:street":"91St Ave Ne",
    "iso:country":"US",
    "sg:address":"3801 91st Ave NE",
    "sg:city":"Norman",
    "sg:classifiers":[
        {
            "category":"Building & Trades",
            "subcategory":"Construction",
            "type":"Services"
        }
    ],
    "sg:phone":"+1 405 321 4924",
    "sg:postcode":"73026",
    "sg:province":"OK",
    "sg:tags":[
        "paint",
        "commercial",
        "contractor"
    ],
    "wof:name":"Wet Paint",
    "wof:placetype":"venue"
},
  "geometry": {"coordinates":[-97.30714,35.261926],"type":"Point"}
}