{
  "type": "Feature",
  "properties": {
    "addr:full":"2132 S 91st East Ave Tulsa OK 74129",
    "addr:housenumber":"2132",
    "addr:postcode":"74129",
    "addr:street":"S 91St;Ave",
    "iso:country":"US",
    "sg:address":"2132 S 91st East Ave",
    "sg:city":"Tulsa",
    "sg:classifiers":[
        {
            "category":"Restaurant",
            "type":"Food & Drink"
        }
    ],
    "sg:phone":"+1 918 627 4941",
    "sg:postcode":"74129",
    "sg:province":"OK",
    "sg:tags":[
        "delicatessen"
    ],
    "wof:name":"Cathy's Snack Bar",
    "wof:placetype":"venue"
},
  "geometry": {"coordinates":[-95.875553,36.130439],"type":"Point"}
}