{
  "type": "Feature",
  "properties": {
    "addr:full":"14101 Parkway Commons Dr Oklahoma City OK 73134",
    "addr:housenumber":"14101",
    "addr:postcode":"73134",
    "addr:street":"Parkway Commons Dr",
    "iso:country":"US",
    "sg:address":"14101 Parkway Commons Dr",
    "sg:city":"Oklahoma City",
    "sg:classifiers":[
        {
            "category":"Health Services",
            "subcategory":"Medical Lab",
            "type":"Services"
        }
    ],
    "sg:phone":"+1 405 749 6277",
    "sg:postcode":"73134",
    "sg:province":"OK",
    "sg:tags":[
        "laboratory"
    ],
    "wof:name":"Spinal Diagnostic SDG",
    "wof:placetype":"venue"
},
  "geometry": {"coordinates":[-97.58247299999999,35.613594],"type":"Point"}
}