{
  "type": "Feature",
  "properties": {
    "iso:country":"US",
    "sg:address":"3700 N Walker Ave",
    "sg:city":"Oklahoma City",
    "sg:classifiers":[
        {
            "category":"Social Services",
            "subcategory":"Child Care",
            "type":"Services"
        }
    ],
    "sg:phone":"+1 405 525 0878",
    "sg:postcode":"73118",
    "sg:province":"OK",
    "wof:name":"Preschool Children's Day Out",
    "wof:placetype":"venue"
},
  "geometry": {"coordinates":[-97.520979,35.508638],"type":"Point"}
}