{
  "type": "Feature",
  "properties": {
    "iso:country":"US",
    "sg:address":"6301 NW 10th St",
    "sg:city":"Oklahoma City",
    "sg:classifiers":[
        {
            "category":"Autos & Motor Vehicles",
            "subcategory":"Boat Sales",
            "type":"Retail Goods"
        }
    ],
    "sg:phone":"+1 405 789 2628",
    "sg:postcode":"73127",
    "sg:province":"OK",
    "wof:name":"Davids Sports Center Inc",
    "wof:placetype":"venue"
},
  "geometry": {"coordinates":[-97.623402,35.478877],"type":"Point"}
}