{
  "type": "Feature",
  "properties": {
    "iso:country":"US",
    "sg:address":"618 NW 19th St",
    "sg:city":"Lawton",
    "sg:classifiers":[
        {
            "category":"Personal",
            "type":"Services"
        }
    ],
    "sg:phone":"+1 580 355 5709",
    "sg:postcode":"73507",
    "sg:province":"OK",
    "sg:tags":[
        "therapist",
        "massage"
    ],
    "wof:name":"Professional Massage Therapy",
    "wof:placetype":"venue"
},
  "geometry": {"coordinates":[-98.41672800000001,34.615335],"type":"Point"}
}