{
  "type": "Feature",
  "properties": {
    "addr:full":"2500 S Broadway St Edmond OK 73013",
    "addr:housenumber":"2500",
    "addr:postcode":"73013",
    "addr:street":"S Broadway St",
    "iso:country":"US",
    "sg:address":"2500 S Broadway St",
    "sg:city":"Edmond",
    "sg:classifiers":[
        {
            "category":"Mining & Drilling",
            "type":"Manufacturing & Wholesale Goods"
        }
    ],
    "sg:phone":"+1 405 330 2016",
    "sg:postcode":"73013",
    "sg:province":"OK",
    "sg:tags":[
        "development",
        "gas",
        "oil",
        "exploration"
    ],
    "wof:name":"M A Miceli",
    "wof:placetype":"venue"
},
  "geometry": {"coordinates":[-97.484453,35.628666],"type":"Point"}
}