{
  "type": "Feature",
  "properties": {
    "iso:country":"US",
    "sg:address":"3512 N Macarthur Blvd",
    "sg:city":"Warr Acres",
    "sg:classifiers":[
        {
            "category":"Insurance",
            "subcategory":"Insurance Agent",
            "type":"Services"
        }
    ],
    "sg:phone":"+1 405 948 0683",
    "sg:postcode":"73122",
    "sg:province":"OK",
    "wof:name":"Cable & Assoc Insurance",
    "wof:placetype":"venue"
},
  "geometry": {"coordinates":[-97.618865,35.506682],"type":"Point"}
}