{
  "type": "Feature",
  "properties": {
    "iso:country":"US",
    "sg:address":"215 SW Main St",
    "sg:city":"Weatherford",
    "sg:classifiers":[
        {
            "category":"Restaurant",
            "type":"Food & Drink"
        }
    ],
    "sg:phone":"+1 580 772 7418",
    "sg:postcode":"73096",
    "sg:province":"OK",
    "sg:tags":[
        "caterer"
    ],
    "wof:name":"Willie's Grill & Diner",
    "wof:placetype":"venue"
},
  "geometry": {"coordinates":[-98.712644,35.524637],"type":"Point"}
}