{
  "type": "Feature",
  "properties": {
    "addr:full":"364 E Willow Rd Enid OK 73701",
    "addr:housenumber":"364",
    "addr:postcode":"73701",
    "addr:street":"E Willow Rd",
    "iso:country":"US",
    "sg:address":"364 E Willow Rd",
    "sg:city":"Enid",
    "sg:classifiers":[
        {
            "category":"Restaurant",
            "type":"Food & Drink"
        }
    ],
    "sg:phone":"+1 580 242 3105",
    "sg:postcode":"73701",
    "sg:province":"OK",
    "wof:name":"Willow Inn Cafe",
    "wof:placetype":"venue"
},
  "geometry": {"coordinates":[-97.872822,36.420041],"type":"Point"}
}