{
  "type": "Feature",
  "properties": {
    "addr:full":"100 Washington Ave Pawhuska OK 74056",
    "addr:housenumber":"100",
    "addr:postcode":"74056",
    "addr:street":"Washington Ave",
    "iso:country":"US",
    "sg:address":"100 Washington Ave",
    "sg:city":"Pawhuska",
    "sg:classifiers":[
        {
            "category":"Retail",
            "subcategory":"Auto Repair",
            "type":"Services"
        }
    ],
    "sg:phone":"+1 918 287 2983",
    "sg:postcode":"74056",
    "sg:province":"OK",
    "sg:tags":[
        "repairing",
        "automobile"
    ],
    "wof:name":"Brownie's Garage",
    "wof:placetype":"venue"
},
  "geometry": {"coordinates":[-96.32381599999999,36.657788],"type":"Point"}
}