{
  "type": "Feature",
  "properties": {
    "iso:country":"US",
    "sg:address":"6505 N Wheatley Ln",
    "sg:city":"Stillwater",
    "sg:classifiers":[
        {
            "category":"Building & Trades",
            "subcategory":"Construction",
            "type":"Services"
        }
    ],
    "sg:phone":"+1 405 372 7809",
    "sg:postcode":"74075",
    "sg:province":"OK",
    "sg:tags":[
        "general",
        "contractor"
    ],
    "wof:name":"Tom Wheatley Dozer Service",
    "wof:placetype":"venue"
},
  "geometry": {"coordinates":[-97.059197,36.190952],"type":"Point"}
}