{
  "type": "Feature",
  "properties": {
    "iso:country":"US",
    "sg:address":"500 Colcord Dr",
    "sg:city":"Oklahoma City",
    "sg:classifiers":[
        {
            "category":"Professional",
            "subcategory":"Lawyer & Legal Services",
            "type":"Services"
        }
    ],
    "sg:phone":"+1 405 236 3571",
    "sg:postcode":"73102",
    "sg:province":"OK",
    "wof:name":"Shirk Work & Robinson PC",
    "wof:placetype":"venue"
},
  "geometry": {"coordinates":[-97.522621,35.468588],"type":"Point"}
}