{
  "type": "Feature",
  "properties": {
    "iso:country":"US",
    "sg:address":"9115 S 43rd W Ave",
    "sg:city":"Tulsa",
    "sg:classifiers":[
        {
            "category":"Professional",
            "subcategory":"Accounting & Tax Preparation",
            "type":"Services"
        }
    ],
    "sg:phone":"+1 918 224 1928",
    "sg:postcode":"74132",
    "sg:province":"OK",
    "sg:tags":[
        "accountant"
    ],
    "wof:name":"Angela Sowell CPA",
    "wof:placetype":"venue"
},
  "geometry": {"coordinates":[-96.039558,36.031817],"type":"Point"}
}