{
  "type": "Feature",
  "properties": {
    "addr:full":"808 S Harmony Rd Cushing OK 74023",
    "addr:housenumber":"808",
    "addr:postcode":"74023",
    "addr:street":"S Harmony Rd",
    "iso:country":"US",
    "sg:address":"808 S Harmony Rd",
    "sg:city":"Cushing",
    "sg:classifiers":[
        {
            "category":"Building & Trades",
            "subcategory":"Construction",
            "type":"Services"
        }
    ],
    "sg:phone":"+1 918 225 6912",
    "sg:postcode":"74023",
    "sg:province":"OK",
    "sg:tags":[
        "repairing",
        "remodeling",
        "contractor"
    ],
    "wof:name":"Bathtub Liners By Alternative",
    "wof:placetype":"venue"
},
  "geometry": {"coordinates":[-96.732011,35.971876],"type":"Point"}
}