{
  "type": "Feature",
  "properties": {
    "iso:country":"US",
    "sg:address":"701 S Eastern Ave",
    "sg:city":"Hominy",
    "sg:classifiers":[
        {
            "category":"Retail",
            "subcategory":"Repair Shop",
            "type":"Services"
        }
    ],
    "sg:phone":"+1 918 885 6194",
    "sg:postcode":"74035",
    "sg:province":"OK",
    "sg:tags":[
        "machine",
        "contractor",
        "industrial",
        "trade",
        "mfg"
    ],
    "wof:name":"Bevard Enterprises",
    "wof:placetype":"venue"
},
  "geometry": {"coordinates":[-96.38952399999999,36.409285],"type":"Point"}
}