{
  "type": "Feature",
  "properties": {
    "iso:country":"US",
    "sg:address":"616 S 3rd St",
    "sg:city":"Yukon",
    "sg:classifiers":[
        {
            "category":"Organizations",
            "subcategory":"Religious Organization",
            "type":"Services"
        }
    ],
    "sg:phone":"+1 405 350 1522",
    "sg:postcode":"73099",
    "sg:province":"OK",
    "sg:tags":[
        "church"
    ],
    "wof:name":"Yukon Seventh-Day Adventist",
    "wof:placetype":"venue"
},
  "geometry": {"coordinates":[-97.746994,35.500716],"type":"Point"}
}