{
  "type": "Feature",
  "properties": {
    "iso:country":"US",
    "sg:address":"7500 E 151st St S",
    "sg:city":"Bixby",
    "sg:classifiers":[
        {
            "category":"Home & Garden",
            "subcategory":"Carpets & Floor Coverings",
            "type":"Retail Goods"
        }
    ],
    "sg:phone":"+1 918 491 6111",
    "sg:postcode":"74008",
    "sg:province":"OK",
    "sg:tags":[
        "material"
    ],
    "wof:name":"C & C Wood Floor Co",
    "wof:placetype":"venue"
},
  "geometry": {"coordinates":[-95.901124,35.944773],"type":"Point"}
}