{
  "type": "Feature",
  "properties": {
    "addr:full":"2402 Wildwood Dr Enid OK 73703",
    "addr:housenumber":"2402",
    "addr:postcode":"73703",
    "addr:street":"Wildwood Dr",
    "iso:country":"US",
    "sg:address":"2402 Wildwood Dr",
    "sg:city":"Enid",
    "sg:classifiers":[
        {
            "category":"Professional",
            "subcategory":"Accounting & Tax Preparation",
            "type":"Services"
        }
    ],
    "sg:phone":"+1 580 233 7267",
    "sg:postcode":"73703",
    "sg:province":"OK",
    "wof:name":"Robbie Butler",
    "wof:placetype":"venue"
},
  "geometry": {"coordinates":[-97.910239,36.420818],"type":"Point"}
}