{
  "type": "Feature",
  "properties": {
    "iso:country":"US",
    "sg:address":"5909 E 25th St",
    "sg:city":"Tulsa",
    "sg:classifiers":[
        {
            "category":"Building & Trades",
            "subcategory":"Construction",
            "type":"Services"
        }
    ],
    "sg:phone":"+1 918 437 1923",
    "sg:postcode":"74114",
    "sg:province":"OK",
    "sg:tags":[
        "resurfacing",
        "laying",
        "refinishing",
        "floor"
    ],
    "wof:name":"Thousand Woods",
    "wof:placetype":"venue"
},
  "geometry": {"coordinates":[-95.90585,36.127564],"type":"Point"}
}