{
  "type": "Feature",
  "properties": {
    "iso:country":"US",
    "sg:address":"5 SW 5th St",
    "sg:city":"Lawton",
    "sg:classifiers":[
        {
            "category":"Social Services",
            "type":"Services"
        }
    ],
    "sg:phone":"+1 580 355 9622",
    "sg:postcode":"73501",
    "sg:province":"OK",
    "sg:tags":[
        "organization",
        "welfare"
    ],
    "wof:name":"YMCA",
    "wof:placetype":"venue"
},
  "geometry": {"coordinates":[-98.395284,34.608013],"type":"Point"}
}