{
  "type": "Feature",
  "properties": {
    "iso:country":"US",
    "sg:address":"403 W Commercial St",
    "sg:city":"Inola",
    "sg:classifiers":[
        {
            "category":"Building & Trades",
            "subcategory":"Plumbing",
            "type":"Services"
        }
    ],
    "sg:phone":"+1 918 543 4076",
    "sg:postcode":"74036",
    "sg:province":"OK",
    "sg:tags":[
        "plumbing",
        "contractor"
    ],
    "wof:name":"All State Plumbing",
    "wof:placetype":"venue"
},
  "geometry": {"coordinates":[-95.513969,36.149095],"type":"Point"}
}