{
  "type": "Feature",
  "properties": {
    "iso:country":"US",
    "sg:address":"927 W Choctaw Ave",
    "sg:city":"Chickasha",
    "sg:classifiers":[
        {
            "category":"Autos & Motor Vehicles",
            "subcategory":"Automobile Sales",
            "type":"Retail Goods"
        }
    ],
    "sg:phone":"+1 405 224 5685",
    "sg:postcode":"73018",
    "sg:province":"OK",
    "sg:tags":[
        "car",
        "used",
        "dealer"
    ],
    "wof:name":"Null's Used Cars",
    "wof:placetype":"venue"
},
  "geometry": {"coordinates":[-97.945207,35.052311],"type":"Point"}
}