{
  "type": "Feature",
  "properties": {
    "iso:country":"US",
    "sg:address":"200 Sam Noble Pkwy",
    "sg:city":"Ardmore",
    "sg:classifiers":[
        {
            "category":"Autos & Motor Vehicles",
            "subcategory":"Automobile Sales",
            "type":"Retail Goods"
        }
    ],
    "sg:phone":"+1 580 226 3718",
    "sg:postcode":"73401",
    "sg:province":"OK",
    "sg:tags":[
        "car",
        "used",
        "dealer"
    ],
    "wof:name":"Kips Klunkers",
    "wof:placetype":"venue"
},
  "geometry": {"coordinates":[-97.12050000000001,34.186019],"type":"Point"}
}