{
  "type": "Feature",
  "properties": {
    "iso:country":"US",
    "sg:address":"916 SW D Ave",
    "sg:city":"Lawton",
    "sg:classifiers":[
        {
            "category":"Home & Garden",
            "subcategory":"Household Appliances",
            "type":"Retail Goods"
        }
    ],
    "sg:phone":"+1 580 353 8800",
    "sg:postcode":"73501",
    "sg:province":"OK",
    "sg:tags":[
        "machine",
        "sewing"
    ],
    "wof:name":"Herzig Sew Vac & Alterations",
    "wof:placetype":"venue"
},
  "geometry": {"coordinates":[-98.402977,34.603976],"type":"Point"}
}