{
  "type": "Feature",
  "properties": {
    "iso:country":"US",
    "sg:address":"206 Cedar Ave",
    "sg:city":"Wellston",
    "sg:classifiers":[
        {
            "category":"Social Services",
            "subcategory":"Adult Care",
            "type":"Services"
        }
    ],
    "sg:phone":"+1 405 356 0012",
    "sg:postcode":"74881",
    "sg:province":"OK",
    "sg:tags":[
        "organization",
        "senior",
        "citizen"
    ],
    "wof:name":"Wellston Elderly Nutrition",
    "wof:placetype":"venue"
},
  "geometry": {"coordinates":[-97.064914,35.695491],"type":"Point"}
}