{
  "type": "Feature",
  "properties": {
    "addr:full":"1201 E 3rd St Tulsa OK 74120",
    "addr:housenumber":"1201",
    "addr:postcode":"74120",
    "addr:street":"E 3Rd St",
    "iso:country":"US",
    "sg:address":"1201 E 3rd St",
    "sg:city":"Tulsa",
    "sg:classifiers":[
        {
            "category":"Home & Garden",
            "subcategory":"Garden Supply",
            "type":"Retail Goods"
        }
    ],
    "sg:phone":"+1 918 592 3382",
    "sg:postcode":"74120",
    "sg:province":"OK",
    "sg:tags":[
        "center"
    ],
    "sg:website":"www.gardendeva.com",
    "wof:name":"Garden Deva Sculpture Co",
    "wof:placetype":"venue"
},
  "geometry": {"coordinates":[-95.97638999999999,36.156701],"type":"Point"}
}