{
  "type": "Feature",
  "properties": {
    "iso:country":"US",
    "sg:address":"4823 N Xanthus Ave",
    "sg:city":"Tulsa",
    "sg:classifiers":[
        {
            "category":"Building & Trades",
            "subcategory":"Plumbing",
            "type":"Services"
        }
    ],
    "sg:phone":"+1 918 425 2498",
    "sg:postcode":"74130",
    "sg:province":"OK",
    "sg:tags":[
        "contractor"
    ],
    "wof:name":"Brewer Brothers",
    "wof:placetype":"venue"
},
  "geometry": {"coordinates":[-95.963931,36.225161],"type":"Point"}
}