{
  "type": "Feature",
  "properties": {
    "addr:full":"4921 N May Ave Oklahoma City OK 73112",
    "addr:housenumber":"4921",
    "addr:postcode":"73112",
    "addr:street":"N May Ave",
    "iso:country":"US",
    "sg:address":"4921 N May Ave",
    "sg:city":"Oklahoma City",
    "sg:classifiers":[
        {
            "category":"Professional",
            "subcategory":"Advertising",
            "type":"Services"
        }
    ],
    "sg:phone":"+1 405 602 6677",
    "sg:postcode":"73112",
    "sg:province":"OK",
    "sg:tags":[
        "counselor"
    ],
    "wof:name":"Bledsoe Agency",
    "wof:placetype":"venue"
},
  "geometry": {"coordinates":[-97.565753,35.521106],"type":"Point"}
}