{
  "type": "Feature",
  "properties": {
    "iso:country":"US",
    "sg:address":"6437 Avondale Dr",
    "sg:city":"Oklahoma City",
    "sg:classifiers":[
        {
            "category":"Restaurant",
            "type":"Food & Drink"
        }
    ],
    "sg:menulink":"http://www.allmenus.com/ok/oklahoma-city/4658-the-coach-house/menu/",
    "sg:phone":"+1 405 842 1000",
    "sg:postcode":"73116",
    "sg:province":"OK",
    "sg:tags":[
        "american"
    ],
    "wof:name":"The Coach House",
    "wof:placetype":"venue"
},
  "geometry": {"coordinates":[-97.53142,35.53847],"type":"Point"}
}