{
  "type": "Feature",
  "properties": {
    "iso:country":"US",
    "sg:address":"2122 S Harvard Ave",
    "sg:city":"Tulsa",
    "sg:classifiers":[
        {
            "category":"Restaurant",
            "type":"Food & Drink"
        }
    ],
    "sg:phone":"+1 918 749 7721",
    "sg:postcode":"74114",
    "sg:province":"OK",
    "wof:name":"El Toro Mexican Restaurant Inc",
    "wof:placetype":"venue"
},
  "geometry": {"coordinates":[-95.940386,36.132389],"type":"Point"}
}