{
  "type": "Feature",
  "properties": {
    "addr:full":"10660 E 31st St Tulsa OK 74146",
    "addr:housenumber":"10660",
    "addr:postcode":"74146",
    "addr:street":"E 31St St",
    "iso:country":"US",
    "sg:address":"10660 E 31st St",
    "sg:city":"Tulsa",
    "sg:classifiers":[
        {
            "category":"Manufacturing",
            "subcategory":"Tools & Machinery",
            "type":"Manufacturing & Wholesale Goods"
        }
    ],
    "sg:phone":"+1 918 270 4207",
    "sg:postcode":"74146",
    "sg:province":"OK",
    "sg:tags":[
        "machine"
    ],
    "wof:name":"Hilti North American",
    "wof:placetype":"venue"
},
  "geometry": {"coordinates":[-95.856961,36.118912],"type":"Point"}
}