{
  "type": "Feature",
  "properties": {
    "iso:country":"US",
    "sg:address":"3040 del View Dr",
    "sg:city":"Oklahoma City",
    "sg:classifiers":[
        {
            "category":"Social Services",
            "subcategory":"Child Care",
            "type":"Services"
        }
    ],
    "sg:phone":"+1 405 677 2103",
    "sg:postcode":"73115",
    "sg:province":"OK",
    "wof:name":"Del City Lighthouse Academy",
    "wof:placetype":"venue"
},
  "geometry": {"coordinates":[-97.428898,35.433511],"type":"Point"}
}