{
  "type": "Feature",
  "properties": {
    "iso:country":"US",
    "sg:address":"15625 E Pine St",
    "sg:city":"Tulsa",
    "sg:classifiers":[
        {
            "category":"Sports & Exercise",
            "subcategory":"Race Track",
            "type":"Entertainment"
        }
    ],
    "sg:phone":"+1 918 438 7856",
    "sg:postcode":"74116",
    "sg:province":"OK",
    "sg:tags":[
        "operation",
        "racing",
        "or"
    ],
    "wof:name":"Port City Raceway",
    "wof:placetype":"venue"
},
  "geometry": {"coordinates":[-95.802759,36.177135],"type":"Point"}
}