{
  "type": "Feature",
  "properties": {
    "addr:full":"1508 Overland Dr Duncan OK 73533",
    "addr:housenumber":"1508",
    "addr:postcode":"73533",
    "addr:street":"Overland Dr",
    "iso:country":"US",
    "sg:address":"1508 Overland Dr",
    "sg:city":"Duncan",
    "sg:classifiers":[
        {
            "category":"Real Estate",
            "subcategory":"Real Estate Operator",
            "type":"Services"
        }
    ],
    "sg:phone":"+1 580 252 3500",
    "sg:postcode":"73533",
    "sg:province":"OK",
    "sg:tags":[
        "apartment"
    ],
    "wof:name":"Willow's Apartments",
    "wof:placetype":"venue"
},
  "geometry": {"coordinates":[-97.972917,34.521929],"type":"Point"}
}