{
  "type": "Feature",
  "properties": {
    "iso:country":"US",
    "sg:address":"1010 Manvel Ave",
    "sg:city":"Chandler",
    "sg:classifiers":[
        {
            "category":"Professional",
            "subcategory":"Business Services",
            "type":"Services"
        },
        {
            "category":"Professional",
            "subcategory":"Accounting & Tax Preparation",
            "type":"Services"
        }
    ],
    "sg:phone":"+1 405 258 1362",
    "sg:postcode":"74834",
    "sg:province":"OK",
    "sg:tags":[
        "billing"
    ],
    "wof:name":"Corvel Med Check Inc",
    "wof:placetype":"venue"
},
  "geometry": {"coordinates":[-96.880618,35.700409],"type":"Point"}
}