{
  "type": "Feature",
  "properties": {
    "iso:country":"US",
    "sg:address":"1603 N Santa Fe Ave",
    "sg:city":"Edmond",
    "sg:classifiers":[
        {
            "category":"Social Services",
            "subcategory":"Child Care",
            "type":"Services"
        }
    ],
    "sg:phone":"+1 405 844 1033",
    "sg:postcode":"73003",
    "sg:province":"OK",
    "sg:tags":[
        "day"
    ],
    "sg:website":"www.santafedayschool.org",
    "wof:name":"Santa Fe Dayschool",
    "wof:placetype":"venue"
},
  "geometry": {"coordinates":[-97.514114,35.670651],"type":"Point"}
}