{
  "type": "Feature",
  "properties": {
    "iso:country":"US",
    "sg:address":"124 E Dewey Ave",
    "sg:city":"Sapulpa",
    "sg:classifiers":[
        {
            "category":"Shopping",
            "subcategory":"Used Merchandise",
            "type":"Retail Goods"
        }
    ],
    "sg:phone":"+1 918 224 4478",
    "sg:postcode":"74066",
    "sg:province":"OK",
    "sg:tags":[
        "shop",
        "thrift"
    ],
    "wof:name":"Salvation Army",
    "wof:placetype":"venue"
},
  "geometry": {"coordinates":[-96.112517,35.99854],"type":"Point"}
}