{
  "type": "Feature",
  "properties": {
    "iso:country":"US",
    "sg:address":"710 Ridgecrest Ct",
    "sg:city":"Norman",
    "sg:classifiers":[
        {
            "category":"Building & Trades",
            "subcategory":"Construction",
            "type":"Services"
        }
    ],
    "sg:phone":"+1 405 573 9659",
    "sg:postcode":"73072",
    "sg:province":"OK",
    "sg:tags":[
        "project"
    ],
    "wof:name":"Mayhall Construction Inc",
    "wof:placetype":"venue"
},
  "geometry": {"coordinates":[-97.452594,35.185413],"type":"Point"}
}