{
  "type": "Feature",
  "properties": {
    "iso:country":"US",
    "sg:address":"109 W Main St",
    "sg:city":"Davis",
    "sg:classifiers":[
        {
            "category":"Health Services",
            "subcategory":"Clinic",
            "type":"Services"
        }
    ],
    "sg:phone":"+1 580 369 5531",
    "sg:postcode":"73030",
    "sg:province":"OK",
    "sg:tags":[
        "home"
    ],
    "sg:website":"www.healthback.com",
    "wof:name":"Healthback Of Davis",
    "wof:placetype":"venue"
},
  "geometry": {"coordinates":[-97.121189,34.503463],"type":"Point"}
}