{
  "type": "Feature",
  "properties": {
    "iso:country":"US",
    "sg:address":"417 W Rogers Blvd",
    "sg:city":"Skiatook",
    "sg:classifiers":[
        {
            "category":"Real Estate",
            "subcategory":"Real Estate Agent",
            "type":"Services"
        }
    ],
    "sg:phone":"+1 918 396 9899",
    "sg:postcode":"74070",
    "sg:province":"OK",
    "wof:name":"House To Home Real Estate",
    "wof:placetype":"venue"
},
  "geometry": {"coordinates":[-96.005656,36.368607],"type":"Point"}
}