{
  "type": "Feature",
  "properties": {
    "iso:country":"US",
    "sg:address":"5901 N Western Ave",
    "sg:city":"Oklahoma City",
    "sg:classifiers":[
        {
            "category":"Professional",
            "subcategory":"Accounting & Tax Preparation",
            "type":"Services"
        }
    ],
    "sg:phone":"+1 405 842 3662",
    "sg:postcode":"73118",
    "sg:province":"OK",
    "sg:tags":[
        "accountant"
    ],
    "wof:name":"Wedel Rahill & Assoc",
    "wof:placetype":"venue"
},
  "geometry": {"coordinates":[-97.529879,35.532647],"type":"Point"}
}