{
  "type": "Feature",
  "properties": {
    "iso:country":"US",
    "sg:address":"101 W Sequoyah Ln",
    "sg:city":"Altus",
    "sg:classifiers":[
        {
            "category":"Professional",
            "subcategory":"Advertising",
            "type":"Services"
        }
    ],
    "sg:phone":"+1 580 477 4500",
    "sg:postcode":"73521",
    "sg:province":"OK",
    "sg:tags":[
        "announcement",
        "temp"
    ],
    "wof:name":"Time & Temperature",
    "wof:placetype":"venue"
},
  "geometry": {"coordinates":[-99.334689,34.663689],"type":"Point"}
}