{
  "type": "Feature",
  "properties": {
    "iso:country":"US",
    "sg:address":"3825 Cypress Dr",
    "sg:city":"Woodward",
    "sg:classifiers":[
        {
            "category":"Government",
            "subcategory":"Office",
            "type":"Public Place"
        }
    ],
    "sg:phone":"+1 580 256 4951",
    "sg:postcode":"73801",
    "sg:province":"OK",
    "sg:tags":[
        "management",
        "agency",
        "labor"
    ],
    "wof:name":"Civilian Personnel Mgt Svc",
    "wof:placetype":"venue"
},
  "geometry": {"coordinates":[-99.43072,36.424945],"type":"Point"}
}