{
  "type": "Feature",
  "properties": {
    "addr:full":"110 N Ohio Ave Atoka OK 74525",
    "addr:housenumber":"110",
    "addr:postcode":"74525",
    "addr:street":"N Ohio Ave",
    "iso:country":"US",
    "sg:address":"110 N Ohio Ave",
    "sg:city":"Atoka",
    "sg:classifiers":[
        {
            "category":"Home & Garden",
            "subcategory":"Furniture",
            "type":"Retail Goods"
        }
    ],
    "sg:phone":"+1 580 889 3143",
    "sg:postcode":"74525",
    "sg:province":"OK",
    "wof:name":"Star Furniture & Appliance",
    "wof:placetype":"venue"
},
  "geometry": {"coordinates":[-96.12431100000001,34.385472],"type":"Point"}
}