{
  "type": "Feature",
  "properties": {
    "iso:country":"US",
    "sg:address":"301 N 16th Ave",
    "sg:city":"Durant",
    "sg:classifiers":[
        {
            "category":"Organizations",
            "subcategory":"Community Association",
            "type":"Services"
        }
    ],
    "sg:phone":"+1 580 924 3659",
    "sg:postcode":"74701",
    "sg:province":"OK",
    "sg:tags":[
        "civic",
        "social"
    ],
    "wof:name":"Rsvp Inc",
    "wof:placetype":"venue"
},
  "geometry": {"coordinates":[-96.392268,33.997637],"type":"Point"}
}