{
  "type": "Feature",
  "properties": {
    "iso:country":"US",
    "sg:address":"6231 E 15th St",
    "sg:city":"Tulsa",
    "sg:classifiers":[
        {
            "category":"Retail",
            "subcategory":"Animal Services",
            "type":"Services"
        }
    ],
    "sg:phone":"+1 918 836 7369",
    "sg:postcode":"74112",
    "sg:province":"OK",
    "wof:name":"Animal Showcase",
    "wof:placetype":"venue"
},
  "geometry": {"coordinates":[-95.907504,36.140733],"type":"Point"}
}