{
  "type": "Feature",
  "properties": {
    "addr:full":"2905 Sandstone Dr Norman OK 73071",
    "addr:housenumber":"2905",
    "addr:postcode":"73071",
    "addr:street":"Sandstone Dr",
    "iso:country":"US",
    "sg:address":"2905 Sandstone Dr",
    "sg:city":"Norman",
    "sg:classifiers":[
        {
            "category":"Wholesale",
            "subcategory":"Vending Machines",
            "type":"Manufacturing & Wholesale Goods"
        }
    ],
    "sg:phone":"+1 405 447 6164",
    "sg:postcode":"73071",
    "sg:province":"OK",
    "sg:tags":[
        "operator",
        "insurance"
    ],
    "wof:name":"State Farm Insurance",
    "wof:placetype":"venue"
},
  "geometry": {"coordinates":[-97.397633,35.219617],"type":"Point"}
}