{
  "type": "Feature",
  "properties": {
    "iso:country":"US",
    "sg:address":"1515 N Harvard Ave",
    "sg:city":"Tulsa",
    "sg:classifiers":[
        {
            "category":"Professional",
            "type":"Services"
        }
    ],
    "sg:phone":"+1 918 712 4100",
    "sg:postcode":"74115",
    "sg:province":"OK",
    "sg:tags":[
        "establishment"
    ],
    "wof:name":"PSSI Business Office",
    "wof:placetype":"venue"
},
  "geometry": {"coordinates":[-95.940245,36.178874],"type":"Point"}
}