{
  "type": "Feature",
  "properties": {
    "addr:full":"419 W Will Rogers Blvd Claremore OK 74017",
    "addr:housenumber":"419",
    "addr:postcode":"74017",
    "addr:street":"W Will Rogers Blvd",
    "iso:country":"US",
    "sg:address":"419 W Will Rogers Blvd",
    "sg:city":"Claremore",
    "sg:classifiers":[
        {
            "category":"Organizations",
            "subcategory":"Professional Association",
            "type":"Services"
        }
    ],
    "sg:phone":"+1 918 341 2818",
    "sg:postcode":"74017",
    "sg:province":"OK",
    "sg:tags":[
        "chambers",
        "commerce"
    ],
    "wof:name":"Chamber Of Commerce",
    "wof:placetype":"venue"
},
  "geometry": {"coordinates":[-95.614766,36.311936],"type":"Point"}
}