{
  "type": "Feature",
  "properties": {
    "iso:country":"US",
    "sg:address":"610 W Bowman Ave",
    "sg:city":"Kingfisher",
    "sg:classifiers":[
        {
            "category":"Organizations",
            "subcategory":"Non-profit Organization",
            "type":"Services"
        }
    ],
    "sg:phone":"+1 405 375 3327",
    "sg:postcode":"73750",
    "sg:province":"OK",
    "sg:tags":[
        "social"
    ],
    "wof:name":"Headstart",
    "wof:placetype":"venue"
},
  "geometry": {"coordinates":[-97.93949000000001,35.856919],"type":"Point"}
}