{
  "type": "Feature",
  "properties": {
    "addr:full":"1226 N 143rd East Ave Tulsa OK 74116",
    "addr:housenumber":"1226",
    "addr:postcode":"74116",
    "addr:street":"N 143Rd;Ave",
    "iso:country":"US",
    "sg:address":"1226 N 143rd East Ave",
    "sg:city":"Tulsa",
    "sg:classifiers":[
        {
            "category":"Professional",
            "subcategory":"Detective & Security Services",
            "type":"Services"
        }
    ],
    "sg:phone":"+1 918 234 9777",
    "sg:postcode":"74116",
    "sg:province":"OK",
    "sg:tags":[
        "equipment",
        "system"
    ],
    "wof:name":"Patriot Vaults",
    "wof:placetype":"venue"
},
  "geometry": {"coordinates":[-95.81812499999999,36.174641],"type":"Point"}
}