{
  "type": "Feature",
  "properties": {
    "iso:country":"US",
    "sg:address":"1226 N 143rd East Ave",
    "sg:city":"Tulsa",
    "sg:classifiers":[
        {
            "category":"Professional",
            "subcategory":"Detective & Security Services",
            "type":"Services"
        }
    ],
    "sg:phone":"+1 918 234 9777",
    "sg:postcode":"74116",
    "sg:province":"OK",
    "sg:tags":[
        "equipment",
        "system"
    ],
    "wof:name":"Patriot Vaults",
    "wof:placetype":"venue"
},
  "geometry": {"coordinates":[-95.818125,36.174641],"type":"Point"}
}