{
  "type": "Feature",
  "properties": {
    "addr:full":"9130 N Macarthur Blvd Oklahoma City OK 73132",
    "addr:housenumber":"9130",
    "addr:postcode":"73132",
    "addr:street":"N Macarthur Blvd",
    "iso:country":"US",
    "sg:address":"9130 N Macarthur Blvd",
    "sg:city":"Oklahoma City",
    "sg:classifiers":[
        {
            "category":"Organizations",
            "subcategory":"Religious Organization",
            "type":"Services"
        }
    ],
    "sg:phone":"+1 405 720 4977",
    "sg:postcode":"73132",
    "sg:province":"OK",
    "sg:tags":[
        "church"
    ],
    "sg:website":"www.knoxchurchopc.org",
    "wof:name":"KNOX Presbyterian Church",
    "wof:placetype":"venue"
},
  "geometry": {"coordinates":[-97.620625,35.562799],"type":"Point"}
}