{
  "type": "Feature",
  "properties": {
    "iso:country":"US",
    "sg:address":"11231 N Rockwell Ave",
    "sg:city":"Oklahoma City",
    "sg:classifiers":[
        {
            "category":"Food & Beverages",
            "subcategory":"Groceries & Convenience Stores",
            "type":"Retail Goods"
        }
    ],
    "sg:phone":"+1 405 773 8541",
    "sg:postcode":"73132",
    "sg:province":"OK",
    "wof:name":"7-Eleven",
    "wof:placetype":"venue"
},
  "geometry": {"coordinates":[-97.638525,35.580709],"type":"Point"}
}