{
  "type": "Feature",
  "properties": {
    "iso:country":"US",
    "sg:address":"1311 Huron St",
    "sg:city":"Norman",
    "sg:classifiers":[
        {
            "category":"Building & Trades",
            "subcategory":"Construction",
            "type":"Services"
        }
    ],
    "sg:phone":"+1 405 321 4743",
    "sg:postcode":"73071",
    "sg:province":"OK",
    "sg:tags":[
        "contractor"
    ],
    "wof:name":"Millus Masonry",
    "wof:placetype":"venue"
},
  "geometry": {"coordinates":[-97.418391,35.233912],"type":"Point"}
}