{
  "type": "Feature",
  "properties": {
    "iso:country":"US",
    "sg:address":"3615 S I- 35 Svc Rd",
    "sg:city":"Oklahoma City",
    "sg:classifiers":[
        {
            "category":"Organizations",
            "subcategory":"Professional Association",
            "type":"Services"
        }
    ],
    "sg:phone":"+1 405 912 9400",
    "sg:postcode":"73129",
    "sg:province":"OK",
    "wof:name":"Ok State Assn",
    "wof:placetype":"venue"
},
  "geometry": {"coordinates":[-97.486727,35.429095],"type":"Point"}
}