{
  "type": "Feature",
  "properties": {
    "iso:country":"US",
    "sg:address":"7455 S Knoxville Ave",
    "sg:city":"Tulsa",
    "sg:classifiers":[
        {
            "category":"Professional",
            "subcategory":"Art Services",
            "type":"Services"
        }
    ],
    "sg:phone":"+1 918 492 1999",
    "sg:postcode":"74136",
    "sg:province":"OK",
    "sg:tags":[
        "commercial",
        "design"
    ],
    "wof:name":"Ronda Roush Studios",
    "wof:placetype":"venue"
},
  "geometry": {"coordinates":[-95.93595500000001,36.054374],"type":"Point"}
}