{
  "type": "Feature",
  "properties": {
    "addr:full":"6102 N Macarthur Blvd Oklahoma City OK 73122",
    "addr:housenumber":"6102",
    "addr:postcode":"73122",
    "addr:street":"N Macarthur Blvd",
    "iso:country":"US",
    "sg:address":"6102 N Macarthur Blvd",
    "sg:city":"Oklahoma City",
    "sg:classifiers":[
        {
            "category":"Social Services",
            "type":"Services"
        }
    ],
    "sg:phone":"+1 405 621 5875",
    "sg:postcode":"73122",
    "sg:province":"OK",
    "sg:tags":[
        "program",
        "outreach"
    ],
    "wof:name":"Lost and Found Community",
    "wof:placetype":"venue"
},
  "geometry": {"coordinates":[-97.618916,35.532876],"type":"Point"}
}