{
  "type": "Feature",
  "properties": {
    "addr:full":"215 E Choctaw Ave Mcalester OK 74501",
    "addr:housenumber":"215",
    "addr:postcode":"74501",
    "addr:street":"E Choctaw Ave",
    "iso:country":"US",
    "sg:address":"215 E Choctaw Ave",
    "sg:city":"Mcalester",
    "sg:classifiers":[
        {
            "category":"Health Services",
            "subcategory":"Doctor",
            "type":"Services"
        }
    ],
    "sg:phone":"+1 918 423 2605",
    "sg:postcode":"74501",
    "sg:province":"OK",
    "sg:tags":[
        "dentist"
    ],
    "wof:name":"Bailey W Harrison DDS",
    "wof:placetype":"venue"
},
  "geometry": {"coordinates":[-95.767218,34.931667],"type":"Point"}
}