{
  "type": "Feature",
  "properties": {
    "addr:full":"3136 Venice Blvd Oklahoma City OK 73112",
    "addr:housenumber":"3136",
    "addr:postcode":"73112",
    "addr:street":"Venice Blvd",
    "iso:country":"US",
    "sg:address":"3136 Venice Blvd",
    "sg:city":"Oklahoma City",
    "sg:classifiers":[
        {
            "category":"Professional",
            "subcategory":"Advertising",
            "type":"Services"
        }
    ],
    "sg:phone":"+1 405 946 4334",
    "sg:postcode":"73112",
    "sg:province":"OK",
    "sg:tags":[
        "agency"
    ],
    "wof:name":"Incite Advertising Inc",
    "wof:placetype":"venue"
},
  "geometry": {"coordinates":[-97.561702,35.502111],"type":"Point"}
}