{
  "type": "Feature",
  "properties": {
    "iso:country":"US",
    "sg:address":"2719 113th St",
    "sg:city":"Sperry",
    "sg:classifiers":[
        {
            "category":"Building & Trades",
            "subcategory":"Electrical",
            "type":"Services"
        }
    ],
    "sg:phone":"+1 918 288 6533",
    "sg:postcode":"74073",
    "sg:province":"OK",
    "sg:tags":[
        "electric",
        "contractor"
    ],
    "wof:name":"Qualls Electric Co",
    "wof:placetype":"venue"
},
  "geometry": {"coordinates":[-96.022661,36.318019],"type":"Point"}
}