{
  "type": "Feature",
  "properties": {
    "addr:full":"182 Fruit St Lone Grove OK 73443",
    "addr:housenumber":"182",
    "addr:postcode":"73443",
    "addr:street":"Fruit St",
    "iso:country":"US",
    "sg:address":"182 Fruit St",
    "sg:city":"Lone Grove",
    "sg:classifiers":[
        {
            "category":"Home & Garden",
            "subcategory":"Furniture",
            "type":"Retail Goods"
        }
    ],
    "sg:phone":"+1 580 657 4682",
    "sg:postcode":"73443",
    "sg:province":"OK",
    "wof:name":"Morgans Cabinet Shop",
    "wof:placetype":"venue"
},
  "geometry": {"coordinates":[-97.257537,34.175422],"type":"Point"}
}