{
  "type": "Feature",
  "properties": {
    "addr:full":"203 Sandpiper Cir Durant OK 74701",
    "addr:housenumber":"203",
    "addr:postcode":"74701",
    "addr:street":"Sandpiper Cir",
    "iso:country":"US",
    "sg:address":"203 Sandpiper Cir",
    "sg:city":"Durant",
    "sg:classifiers":[
        {
            "category":"Shopping",
            "subcategory":"Catalog Store",
            "type":"Retail Goods"
        }
    ],
    "sg:phone":"+1 580 924 6558",
    "sg:postcode":"74701",
    "sg:province":"OK",
    "sg:tags":[
        "house",
        "mail",
        "sales",
        "direct"
    ],
    "wof:name":"Mary Kay Cosmetics",
    "wof:placetype":"venue"
},
  "geometry": {"coordinates":[-96.41405899999999,33.995336],"type":"Point"}
}