{
  "type": "Feature",
  "properties": {
    "addr:full":"804 Tottingham Rd Anadarko OK 73005",
    "addr:housenumber":"804",
    "addr:postcode":"73005",
    "addr:street":"Tottingham Rd",
    "iso:country":"US",
    "sg:address":"804 Tottingham Rd",
    "sg:city":"Anadarko",
    "sg:classifiers":[
        {
            "category":"Professional",
            "subcategory":"Accounting & Tax Preparation",
            "type":"Services"
        }
    ],
    "sg:phone":"+1 405 247 5021",
    "sg:postcode":"73005",
    "sg:province":"OK",
    "wof:name":"Leuch H Dean",
    "wof:placetype":"venue"
},
  "geometry": {"coordinates":[-98.254999,35.060401],"type":"Point"}
}