{
  "type": "Feature",
  "properties": {
    "addr:full":"8801 N Western Ave Oklahoma City OK 73114",
    "addr:housenumber":"8801",
    "addr:postcode":"73114",
    "addr:street":"N Western Ave",
    "iso:country":"US",
    "sg:address":"8801 N Western Ave",
    "sg:city":"Oklahoma City",
    "sg:classifiers":[
        {
            "category":"Organizations",
            "subcategory":"Religious Organization",
            "type":"Services"
        }
    ],
    "sg:phone":"+1 405 767 2025",
    "sg:postcode":"73114",
    "sg:province":"OK",
    "wof:name":"Northwest Community Church",
    "wof:placetype":"venue"
},
  "geometry": {"coordinates":[-97.531278,35.559698],"type":"Point"}
}