{
  "type": "Feature",
  "properties": {
    "addr:full":"12205 Dalton Dr Oklahoma City OK 73162",
    "addr:housenumber":"12205",
    "addr:postcode":"73162",
    "addr:street":"Dalton Dr",
    "iso:country":"US",
    "sg:address":"12205 Dalton Dr",
    "sg:city":"Oklahoma City",
    "sg:classifiers":[
        {
            "category":"Autos & Motor Vehicles",
            "subcategory":"Automobile Sales",
            "type":"Retail Goods"
        }
    ],
    "sg:phone":"+1 405 650 7811",
    "sg:postcode":"73162",
    "sg:province":"OK",
    "sg:tags":[
        "car",
        "dealer"
    ],
    "wof:name":"Triple M Auto Sales",
    "wof:placetype":"venue"
},
  "geometry": {"coordinates":[-97.648004,35.592344],"type":"Point"}
}