{
  "type": "Feature",
  "properties": {
    "iso:country":"US",
    "sg:address":"332 Candice Dr NW",
    "sg:city":"Piedmont",
    "sg:classifiers":[
        {
            "category":"Building & Trades",
            "subcategory":"Construction",
            "type":"Services"
        }
    ],
    "sg:phone":"+1 405 373 4399",
    "sg:postcode":"73078",
    "sg:province":"OK",
    "sg:tags":[
        "contractor"
    ],
    "wof:name":"Schwemley Stone Masonry",
    "wof:placetype":"venue"
},
  "geometry": {"coordinates":[-97.76052300000001,35.642449],"type":"Point"}
}