{
  "type": "Feature",
  "properties": {
    "iso:country":"US",
    "sg:address":"324 Paxton Ct",
    "sg:city":"Norman",
    "sg:classifiers":[
        {
            "category":"Shopping",
            "subcategory":"Gifts & Souvenirs",
            "type":"Retail Goods"
        }
    ],
    "sg:phone":"+1 405 427 2073",
    "sg:postcode":"73069",
    "sg:province":"OK",
    "wof:name":"J L Enterprises",
    "wof:placetype":"venue"
},
  "geometry": {"coordinates":[-97.445281,35.247863],"type":"Point"}
}