{
  "type": "Feature",
  "properties": {
    "iso:country":"US",
    "sg:address":"6125 S Sheridan Rd",
    "sg:city":"Tulsa",
    "sg:classifiers":[
        {
            "category":"Restaurant",
            "type":"Food & Drink"
        }
    ],
    "sg:phone":"+1 918 499 1555",
    "sg:postcode":"74133",
    "sg:province":"OK",
    "wof:name":"Congas Restaurant",
    "wof:placetype":"venue"
},
  "geometry": {"coordinates":[-95.904229,36.074505],"type":"Point"}
}