{
  "type": "Feature",
  "properties": {
    "iso:country":"US",
    "sg:address":"7016 E 77th Pl",
    "sg:city":"Tulsa",
    "sg:classifiers":[
        {
            "category":"Building & Trades",
            "subcategory":"Landscaping Services",
            "type":"Services"
        }
    ],
    "sg:phone":"+1 918 492 8855",
    "sg:postcode":"74133",
    "sg:province":"OK",
    "wof:name":"All-Service",
    "wof:placetype":"venue"
},
  "geometry": {"coordinates":[-95.898243,36.052405],"type":"Point"}
}