{
  "type": "Feature",
  "properties": {
    "iso:country":"US",
    "sg:address":"720 E Main St",
    "sg:city":"Tishomingo",
    "sg:classifiers":[
        {
            "category":"Retail",
            "subcategory":"Auto Repair",
            "type":"Services"
        }
    ],
    "sg:phone":"+1 580 371 3669",
    "sg:postcode":"73460",
    "sg:province":"OK",
    "sg:tags":[
        "body",
        "automobile",
        "painting",
        "parking"
    ],
    "wof:name":"Tish Car Color Inc",
    "wof:placetype":"venue"
},
  "geometry": {"coordinates":[-96.670878,34.230926],"type":"Point"}
}