{
  "type": "Feature",
  "properties": {
    "addr:full":"8650 N Indian Meridian Jones OK 73049",
    "addr:housenumber":"8650",
    "addr:postcode":"73049",
    "addr:street":"N Indian",
    "iso:country":"US",
    "sg:address":"8650 N Indian Meridian",
    "sg:city":"Jones",
    "sg:classifiers":[
        {
            "category":"Farming",
            "subcategory":"Farm",
            "type":"Manufacturing & Wholesale Goods"
        }
    ],
    "sg:phone":"+1 405 399 2453",
    "sg:postcode":"73049",
    "sg:province":"OK",
    "sg:tags":[
        "crop",
        "general"
    ],
    "wof:name":"Manwell Farms",
    "wof:placetype":"venue"
},
  "geometry": {"coordinates":[-97.247196,35.5619],"type":"Point"}
}