{
  "type": "Feature",
  "properties": {
    "addr:full":"9 S 9th St Duncan OK 73533",
    "addr:housenumber":"9",
    "addr:postcode":"73533",
    "addr:street":"S 9Th St",
    "iso:country":"US",
    "sg:address":"9 S 9th St",
    "sg:city":"Duncan",
    "sg:classifiers":[
        {
            "category":"Shopping",
            "type":"Retail Goods"
        }
    ],
    "sg:phone":"+1 580 255 3400",
    "sg:postcode":"73533",
    "sg:province":"OK",
    "sg:tags":[
        "coin",
        "dealer",
        "supply"
    ],
    "wof:name":"Stan's Coins",
    "wof:placetype":"venue"
},
  "geometry": {"coordinates":[-97.958342,34.501848],"type":"Point"}
}