{
  "type": "Feature",
  "properties": {
    "iso:country":"US",
    "sg:address":"931 N Elm Pl",
    "sg:city":"Broken Arrow",
    "sg:classifiers":[
        {
            "category":"Professional",
            "subcategory":"Accounting & Tax Preparation",
            "type":"Services"
        }
    ],
    "sg:phone":"+1 918 251 3776",
    "sg:postcode":"74012",
    "sg:province":"OK",
    "sg:tags":[
        "return",
        "filing"
    ],
    "sg:website":"www.libertytax.com",
    "wof:name":"Liberty Tax Svc",
    "wof:placetype":"venue"
},
  "geometry": {"coordinates":[-95.79735599999999,36.060813],"type":"Point"}
}