{
  "type": "Feature",
  "properties": {
    "addr:full":"10309 E 61st St Tulsa OK 74133",
    "addr:housenumber":"10309",
    "addr:postcode":"74133",
    "addr:street":"E 61St St",
    "iso:country":"US",
    "sg:address":"10309 E 61st St",
    "sg:city":"Tulsa",
    "sg:classifiers":[
        {
            "category":"Restaurant",
            "type":"Food & Drink"
        }
    ],
    "sg:phone":"+1 918 459 0096",
    "sg:postcode":"74133",
    "sg:province":"OK",
    "sg:tags":[
        "pizza"
    ],
    "sg:website":"www.joemommas.com",
    "wof:name":"Joe Momma's Pizza",
    "wof:placetype":"venue"
},
  "geometry": {"coordinates":[-95.899181,36.01437],"type":"Point"}
}