{
  "type": "Feature",
  "properties": {
    "iso:country":"US",
    "sg:address":"313 S Rambo St",
    "sg:city":"Dill City",
    "sg:classifiers":[
        {
            "category":"Government",
            "subcategory":"Police Station",
            "type":"Public Place"
        }
    ],
    "sg:phone":"+1 580 674 3959",
    "sg:postcode":"73641",
    "sg:province":"OK",
    "sg:tags":[
        "department"
    ],
    "wof:name":"Dill City Police Dept",
    "wof:placetype":"venue"
},
  "geometry": {"coordinates":[-99.135029,35.281142],"type":"Point"}
}