{
  "type": "Feature",
  "properties": {
    "iso:country":"US",
    "sg:address":"1501 E Kenosha St",
    "sg:city":"Broken Arrow",
    "sg:classifiers":[
        {
            "category":"Recreation",
            "subcategory":"Marina",
            "type":"Entertainment"
        }
    ],
    "sg:phone":"+1 918 251 2656",
    "sg:postcode":"74012",
    "sg:province":"OK",
    "wof:name":"Jimmy Houston Marine",
    "wof:placetype":"venue"
},
  "geometry": {"coordinates":[-95.77428500000001,36.061073],"type":"Point"}
}