{
  "type": "Feature",
  "properties": {
    "iso:country":"US",
    "sg:address":"400 E Gladstone Ave",
    "sg:city":"Frederick",
    "sg:classifiers":[
        {
            "category":"Communications",
            "subcategory":"Radio Station",
            "type":"Services"
        }
    ],
    "sg:phone":"+1 580 335 5500",
    "sg:postcode":"73542",
    "sg:province":"OK",
    "sg:tags":[
        "company",
        "broadcasting"
    ],
    "wof:name":"KSYE",
    "wof:placetype":"venue"
},
  "geometry": {"coordinates":[-99.01327,34.392026],"type":"Point"}
}