{
  "type": "Feature",
  "properties": {
    "iso:country":"US",
    "sg:address":"124 S Main St",
    "sg:city":"Wagoner",
    "sg:classifiers":[
        {
            "category":"Professional",
            "subcategory":"Accounting & Tax Preparation",
            "type":"Services"
        }
    ],
    "sg:phone":"+1 918 485 6905",
    "sg:postcode":"74467",
    "sg:province":"OK",
    "sg:tags":[
        "accountant"
    ],
    "wof:name":"Rodney Nelson CPA",
    "wof:placetype":"venue"
},
  "geometry": {"coordinates":[-95.377031,35.95947],"type":"Point"}
}