{
  "type": "Feature",
  "properties": {
    "addr:full":"204 SE 3rd St Wagoner OK 74467",
    "addr:housenumber":"204",
    "addr:postcode":"74467",
    "addr:street":"Se 3Rd St",
    "iso:country":"US",
    "sg:address":"204 SE 3rd St",
    "sg:city":"Wagoner",
    "sg:classifiers":[
        {
            "category":"Building & Trades",
            "subcategory":"Construction",
            "type":"Services"
        }
    ],
    "sg:phone":"+1 918 485 2684",
    "sg:postcode":"74467",
    "sg:province":"OK",
    "sg:tags":[
        "contractor"
    ],
    "wof:name":"Wilson Roofing & Construction",
    "wof:placetype":"venue"
},
  "geometry": {"coordinates":[-95.374797,35.956529],"type":"Point"}
}