{
  "type": "Feature",
  "properties": {
    "iso:country":"US",
    "sg:address":"505 Leisure Ct",
    "sg:city":"Oklahoma City",
    "sg:classifiers":[
        {
            "category":"Banks & Credit Unions",
            "subcategory":"Financial Services",
            "type":"Services"
        }
    ],
    "sg:phone":"+1 405 732 4613",
    "sg:postcode":"73110",
    "sg:province":"OK",
    "sg:tags":[
        "investor"
    ],
    "wof:name":"N & B Investments",
    "wof:placetype":"venue"
},
  "geometry": {"coordinates":[-97.389442,35.471881],"type":"Point"}
}