{
  "type": "Feature",
  "properties": {
    "addr:full":"514 SE 83rd St Oklahoma City OK 73149",
    "addr:housenumber":"514",
    "addr:postcode":"73149",
    "addr:street":"Se 83Rd St",
    "iso:country":"US",
    "sg:address":"514 SE 83rd St",
    "sg:city":"Oklahoma City",
    "sg:classifiers":[
        {
            "category":"Bus Charters",
            "type":"Transportation"
        }
    ],
    "sg:phone":"+1 405 634 3311",
    "sg:postcode":"73149",
    "sg:province":"OK",
    "sg:tags":[
        "local"
    ],
    "wof:name":"Kincaid Travel",
    "wof:placetype":"venue"
},
  "geometry": {"coordinates":[-97.49695699999999,35.383034],"type":"Point"}
}