{
  "type": "Feature",
  "properties": {
    "iso:country":"US",
    "sg:address":"2701 Coltrane Pl",
    "sg:city":"Edmond",
    "sg:classifiers":[
        {
            "category":"Communications",
            "subcategory":"Film & Video Production",
            "type":"Services"
        }
    ],
    "sg:phone":"+1 405 705 2602",
    "sg:postcode":"73034",
    "sg:province":"OK",
    "sg:tags":[
        "taping"
    ],
    "wof:name":"Redrock Video Svc",
    "wof:placetype":"venue"
},
  "geometry": {"coordinates":[-97.4429,35.649556],"type":"Point"}
}