{
  "type": "Feature",
  "properties": {
    "iso:country":"US",
    "sg:address":"330 H St SE",
    "sg:city":"Miami",
    "sg:classifiers":[
        {
            "category":"Home & Garden",
            "subcategory":"Building Materials",
            "type":"Retail Goods"
        },
        {
            "category":"Home & Garden",
            "subcategory":"Home Furnishings",
            "type":"Retail Goods"
        }
    ],
    "sg:phone":"+1 918 542 4594",
    "sg:postcode":"74354",
    "sg:province":"OK",
    "sg:tags":[
        "installs",
        "glass",
        "mirror"
    ],
    "wof:name":"Miami Glass & Mirror Inc",
    "wof:placetype":"venue"
},
  "geometry": {"coordinates":[-94.868959,36.870728],"type":"Point"}
}