{
  "type": "Feature",
  "properties": {
    "iso:country":"US",
    "sg:address":"8022 S Memorial Dr",
    "sg:city":"Tulsa",
    "sg:classifiers":[
        {
            "category":"Real Estate",
            "subcategory":"Real Estate Agent",
            "type":"Services"
        }
    ],
    "sg:phone":"+1 918 459 8227",
    "sg:postcode":"74133",
    "sg:province":"OK",
    "wof:name":"Oaktree Center",
    "wof:placetype":"venue"
},
  "geometry": {"coordinates":[-95.886273,36.046838],"type":"Point"}
}