{
  "type": "Feature",
  "properties": {
    "iso:country":"US",
    "sg:address":"1300 P St NE",
    "sg:city":"Ardmore",
    "sg:classifiers":[
        {
            "category":"Autos & Motor Vehicles",
            "subcategory":"Fuel & Gas Station",
            "type":"Retail Goods"
        }
    ],
    "sg:phone":"+1 580 226 4547",
    "sg:postcode":"73401",
    "sg:province":"OK",
    "sg:tags":[
        "station",
        "gasoline"
    ],
    "wof:name":"Rutledge Auto Service",
    "wof:placetype":"venue"
},
  "geometry": {"coordinates":[-97.108188,34.185371],"type":"Point"}
}