{
  "type": "Feature",
  "properties": {
    "addr:full":"2614 Sunset Dr El Reno OK 73036",
    "addr:housenumber":"2614",
    "addr:postcode":"73036",
    "addr:street":"Sunset Dr",
    "iso:country":"US",
    "sg:address":"2614 Sunset Dr",
    "sg:city":"El Reno",
    "sg:classifiers":[
        {
            "category":"Home & Garden",
            "subcategory":"Building Materials",
            "type":"Retail Goods"
        }
    ],
    "sg:phone":"+1 405 262 6242",
    "sg:postcode":"73036",
    "sg:province":"OK",
    "sg:tags":[
        "glass",
        "window",
        "plate"
    ],
    "wof:name":"Robert's Glass",
    "wof:placetype":"venue"
},
  "geometry": {"coordinates":[-97.983811,35.536982],"type":"Point"}
}