{
  "type": "Feature",
  "properties": {
    "iso:country":"US",
    "sg:address":"3905 NE 23rd St",
    "sg:city":"Oklahoma City",
    "sg:classifiers":[
        {
            "category":"Social Services",
            "subcategory":"Child Care",
            "type":"Services"
        }
    ],
    "sg:phone":"+1 405 424 5253",
    "sg:postcode":"73121",
    "sg:province":"OK",
    "sg:tags":[
        "day"
    ],
    "wof:name":"E C S Learning Center",
    "wof:placetype":"venue"
},
  "geometry": {"coordinates":[-97.44335,35.493288],"type":"Point"}
}