{
  "type": "Feature",
  "properties": {
    "iso:country":"US",
    "sg:address":"501 S Lynn Riggs Blvd",
    "sg:city":"Claremore",
    "sg:classifiers":[
        {
            "category":"Travel",
            "subcategory":"Travel Agent",
            "type":"Entertainment"
        }
    ],
    "sg:phone":"+1 918 342 2301",
    "sg:postcode":"74017",
    "sg:province":"OK",
    "sg:tags":[
        "agency",
        "bureau"
    ],
    "wof:name":"Claremore Travel Svc Inc",
    "wof:placetype":"venue"
},
  "geometry": {"coordinates":[-95.61862000000001,36.3084],"type":"Point"}
}