{
  "type": "Feature",
  "properties": {
    "addr:full":"4502 E 41st St Tulsa OK 74135",
    "addr:housenumber":"4502",
    "addr:postcode":"74135",
    "addr:street":"E 41St St",
    "iso:country":"US",
    "sg:address":"4502 E 41st St",
    "sg:city":"Tulsa",
    "sg:classifiers":[
        {
            "category":"Mining & Drilling",
            "type":"Manufacturing & Wholesale Goods"
        }
    ],
    "sg:phone":"+1 918 660 3824",
    "sg:postcode":"74135",
    "sg:province":"OK",
    "sg:tags":[
        "field",
        "oil",
        "well",
        "log",
        "library"
    ],
    "wof:name":"Schlumberger Technology Corp",
    "wof:placetype":"venue"
},
  "geometry": {"coordinates":[-95.927279,36.104351],"type":"Point"}
}