{
  "type": "Feature",
  "properties": {
    "iso:country":"US",
    "sg:address":"10309 E Tower Ests",
    "sg:city":"Glencoe",
    "sg:classifiers":[
        {
            "category":"Manufacturing",
            "subcategory":"Chemicals & Compounds",
            "type":"Manufacturing & Wholesale Goods"
        }
    ],
    "sg:phone":"+1 580 669 2520",
    "sg:postcode":"74032",
    "sg:province":"OK",
    "sg:tags":[
        "plastic"
    ],
    "wof:name":"Oklahoma Hand Pours",
    "wof:placetype":"venue"
},
  "geometry": {"coordinates":[-96.913411,36.197752],"type":"Point"}
}