{
  "type": "Feature",
  "properties": {
    "iso:country":"US",
    "sg:address":"902 S Sheridan Rd",
    "sg:city":"Tulsa",
    "sg:classifiers":[
        {
            "category":"Restaurant",
            "type":"Food & Drink"
        }
    ],
    "sg:menulink":"http://www.allmenus.com/ok/tulsa/232986-lees-famous-recipe-chicken/menu/",
    "sg:phone":"+1 918 835 7988",
    "sg:postcode":"74112",
    "sg:province":"OK",
    "sg:tags":[
        "american"
    ],
    "wof:name":"Lee's Famous Recipe Chicken",
    "wof:placetype":"venue"
},
  "geometry": {"coordinates":[-95.904938,36.149446],"type":"Point"}
}