{
  "type": "Feature",
  "properties": {
    "iso:country":"US",
    "sg:address":"212 E Main St",
    "sg:city":"Antlers",
    "sg:classifiers":[
        {
            "category":"Professional",
            "subcategory":"Accounting & Tax Preparation",
            "type":"Services"
        }
    ],
    "sg:phone":"+1 580 298 6655",
    "sg:postcode":"74523",
    "sg:province":"OK",
    "sg:tags":[
        "accountant"
    ],
    "wof:name":"Cecilia K Julian CPA",
    "wof:placetype":"venue"
},
  "geometry": {"coordinates":[-95.618177,34.231416],"type":"Point"}
}