{
  "type": "Feature",
  "properties": {
    "addr:full":"222 E Graham Ave Pryor OK 74361",
    "addr:housenumber":"222",
    "addr:postcode":"74361",
    "addr:street":"E Graham Ave",
    "iso:country":"US",
    "sg:address":"222 E Graham Ave",
    "sg:city":"Pryor",
    "sg:classifiers":[
        {
            "category":"Shopping",
            "subcategory":"Computers & Home Electronics",
            "type":"Retail Goods"
        }
    ],
    "sg:phone":"+1 918 825 8200",
    "sg:postcode":"74361",
    "sg:province":"OK",
    "sg:website":"www.ages.com",
    "wof:name":"Ages Computers",
    "wof:placetype":"venue"
},
  "geometry": {"coordinates":[-95.31677000000001,36.307615],"type":"Point"}
}