{
  "type": "Feature",
  "properties": {
    "iso:country":"US",
    "sg:address":"601 N Main St",
    "sg:city":"Bristow",
    "sg:classifiers":[
        {
            "category":"Banks & Credit Unions",
            "subcategory":"Bank",
            "type":"Services"
        }
    ],
    "sg:phone":"+1 918 367 3311",
    "sg:postcode":"74010",
    "sg:province":"OK",
    "sg:tags":[
        "state",
        "chartered"
    ],
    "wof:name":"Spiritbank",
    "wof:placetype":"venue"
},
  "geometry": {"coordinates":[-96.39103799999999,35.838742],"type":"Point"}
}