{
  "type": "Feature",
  "properties": {
    "iso:country":"US",
    "sg:address":"1005 S 10th St",
    "sg:city":"Clinton",
    "sg:classifiers":[
        {
            "category":"Shopping",
            "subcategory":"Department Store",
            "type":"Retail Goods"
        }
    ],
    "sg:phone":"+1 580 323 1461",
    "sg:postcode":"73601",
    "sg:province":"OK",
    "wof:name":"Wall's Special Edition",
    "wof:placetype":"venue"
},
  "geometry": {"coordinates":[-98.971969,35.50437],"type":"Point"}
}