{
  "type": "Feature",
  "properties": {
    "addr:full":"12020 N Mustang Rd Yukon OK 73078",
    "addr:housenumber":"12020",
    "addr:postcode":"73078",
    "addr:street":"N Mustang Rd",
    "iso:country":"US",
    "sg:address":"12020 N Mustang Rd",
    "sg:city":"Yukon",
    "sg:classifiers":[
        {
            "category":"Organizations",
            "subcategory":"Religious Organization",
            "type":"Services"
        }
    ],
    "sg:phone":"+1 405 373 2526",
    "sg:postcode":"73078",
    "sg:province":"OK",
    "sg:tags":[
        "church"
    ],
    "wof:name":"Oklahoma City Temple",
    "wof:placetype":"venue"
},
  "geometry": {"coordinates":[-97.72715700000001,35.592044],"type":"Point"}
}