{
  "type": "Feature",
  "properties": {
    "iso:country":"US",
    "sg:address":"108 SE Washington St",
    "sg:city":"Idabel",
    "sg:classifiers":[
        {
            "category":"Building & Trades",
            "subcategory":"Pest Control",
            "type":"Services"
        }
    ],
    "sg:phone":"+1 580 286 6484",
    "sg:postcode":"74745",
    "sg:province":"OK",
    "wof:name":"4 Way Pro Pest Control",
    "wof:placetype":"venue"
},
  "geometry": {"coordinates":[-94.824868,33.895002],"type":"Point"}
}