{
  "type": "Feature",
  "properties": {
    "addr:full":"900 W Maple Ave Enid OK 73701",
    "addr:housenumber":"900",
    "addr:postcode":"73701",
    "addr:street":"W Maple Ave",
    "iso:country":"US",
    "sg:address":"900 W Maple Ave",
    "sg:city":"Enid",
    "sg:classifiers":[
        {
            "category":"Real Estate",
            "subcategory":"Real Estate Agent",
            "type":"Services"
        }
    ],
    "sg:phone":"+1 580 234 7000",
    "sg:postcode":"73701",
    "sg:province":"OK",
    "sg:website":"www.nicholasre.com",
    "wof:name":"Nicholas Real Estate",
    "wof:placetype":"venue"
},
  "geometry": {"coordinates":[-97.889805,36.39907],"type":"Point"}
}