{
  "type": "Feature",
  "properties": {
    "iso:country":"US",
    "sg:address":"1400 NE 2nd St",
    "sg:city":"Oklahoma City",
    "sg:classifiers":[
        {
            "category":"Building & Trades",
            "subcategory":"Construction",
            "type":"Services"
        }
    ],
    "sg:phone":"+1 405 236 2701",
    "sg:postcode":"73117",
    "sg:province":"OK",
    "sg:tags":[
        "paving",
        "contractor"
    ],
    "wof:name":"Haskell Lemon Construction Co",
    "wof:placetype":"venue"
},
  "geometry": {"coordinates":[-97.488281,35.469982],"type":"Point"}
}