{
  "type": "Feature",
  "properties": {
    "iso:country":"US",
    "sg:address":"11027 N Cincinnati Ave",
    "sg:city":"Skiatook",
    "sg:classifiers":[
        {
            "category":"Manufacturing",
            "subcategory":"Tools & Machinery",
            "type":"Manufacturing & Wholesale Goods"
        }
    ],
    "sg:phone":"+1 918 288 7241",
    "sg:postcode":"74070",
    "sg:province":"OK",
    "sg:tags":[
        "machine",
        "mfg"
    ],
    "wof:name":"Kennys Machine Shop",
    "wof:placetype":"venue"
},
  "geometry": {"coordinates":[-95.99142999999999,36.307592],"type":"Point"}
}