{
  "type": "Feature",
  "properties": {
    "iso:country":"US",
    "sg:address":"904 NE 5th St",
    "sg:city":"Oklahoma City",
    "sg:classifiers":[
        {
            "category":"Professional",
            "subcategory":"Detective & Security Services",
            "type":"Services"
        }
    ],
    "sg:phone":"+1 405 895 6366",
    "sg:postcode":"73160",
    "sg:province":"OK",
    "sg:tags":[
        "keeper",
        "gate"
    ],
    "wof:name":"Roy Hoffman",
    "wof:placetype":"venue"
},
  "geometry": {"coordinates":[-97.472402,35.343369],"type":"Point"}
}