{
  "type": "Feature",
  "properties": {
    "addr:full":"102 Wellston Park Rd Sand Springs OK 74063",
    "addr:housenumber":"102",
    "addr:postcode":"74063",
    "addr:street":"Wellston Park Rd",
    "iso:country":"US",
    "sg:address":"102 Wellston Park Rd",
    "sg:city":"Sand Springs",
    "sg:classifiers":[
        {
            "category":"Manufacturing",
            "subcategory":"Tools & Machinery",
            "type":"Manufacturing & Wholesale Goods"
        }
    ],
    "sg:phone":"+1 918 246 9695",
    "sg:postcode":"74063",
    "sg:province":"OK",
    "sg:tags":[
        "machine",
        "shop"
    ],
    "wof:name":"Accent Machine Inc",
    "wof:placetype":"venue"
},
  "geometry": {"coordinates":[-96.13154,36.137319],"type":"Point"}
}