{
  "type": "Feature",
  "properties": {
    "iso:country":"US",
    "sg:address":"6801 S Anderson Rd",
    "sg:city":"Oklahoma City",
    "sg:classifiers":[
        {
            "category":"Shopping",
            "subcategory":"Books",
            "type":"Retail Goods"
        }
    ],
    "sg:phone":"+1 405 737 1397",
    "sg:postcode":"73150",
    "sg:province":"OK",
    "sg:tags":[
        "dealer"
    ],
    "wof:name":"Words Of Life Christian Bkstr",
    "wof:placetype":"venue"
},
  "geometry": {"coordinates":[-97.31787,35.398821],"type":"Point"}
}