{
  "type": "Feature",
  "properties": {
    "iso:country":"US",
    "sg:address":"2600 E St SW",
    "sg:city":"Miami",
    "sg:classifiers":[
        {
            "category":"Manufacturing",
            "subcategory":"Metals",
            "type":"Manufacturing & Wholesale Goods"
        }
    ],
    "sg:phone":"+1 918 542 5832",
    "sg:postcode":"74354",
    "sg:province":"OK",
    "wof:name":"Armstrong Metal Products",
    "wof:placetype":"venue"
},
  "geometry": {"coordinates":[-94.882548,36.835552],"type":"Point"}
}