{
  "type": "Feature",
  "properties": {
    "addr:full":"20520 W Wekiwa Rd Sand Springs OK 74063",
    "addr:housenumber":"20520",
    "addr:postcode":"74063",
    "addr:street":"W Wekiwa Rd",
    "iso:country":"US",
    "sg:address":"20520 W Wekiwa Rd",
    "sg:city":"Sand Springs",
    "sg:classifiers":[
        {
            "category":"Wholesale",
            "subcategory":"Durable Goods & Equipment",
            "type":"Manufacturing & Wholesale Goods"
        }
    ],
    "sg:phone":"+1 918 241 8800",
    "sg:postcode":"74063",
    "sg:province":"OK",
    "sg:tags":[
        "laboratory",
        "supply"
    ],
    "wof:name":"TDH",
    "wof:placetype":"venue"
},
  "geometry": {"coordinates":[-96.21790900000001,36.148302],"type":"Point"}
}