{
  "type": "Feature",
  "properties": {
    "addr:full":"2128 Denver Harner Dr Miami OK 74354",
    "addr:housenumber":"2128",
    "addr:postcode":"74354",
    "addr:street":"Denver Harner Dr",
    "iso:country":"US",
    "sg:address":"2128 Denver Harner Dr",
    "sg:city":"Miami",
    "sg:classifiers":[
        {
            "category":"Health Services",
            "subcategory":"Nursing And Care Facility",
            "type":"Services"
        }
    ],
    "sg:phone":"+1 918 542 4040",
    "sg:postcode":"74354",
    "sg:province":"OK",
    "sg:tags":[
        "skilled"
    ],
    "wof:name":"Heartland Plaza",
    "wof:placetype":"venue"
},
  "geometry": {"coordinates":[-94.85773500000001,36.899071],"type":"Point"}
}