{
  "type": "Feature",
  "properties": {
    "iso:country":"US",
    "sg:address":"206 W Sycamore St",
    "sg:city":"Coweta",
    "sg:classifiers":[
        {
            "category":"Government",
            "subcategory":"Post Office",
            "type":"Public Place"
        }
    ],
    "sg:phone":"+1 918 486 5634",
    "sg:postcode":"74429",
    "sg:province":"OK",
    "wof:name":"US Post Office",
    "wof:placetype":"venue"
},
  "geometry": {"coordinates":[-95.65186300000001,35.950855],"type":"Point"}
}