{
  "type": "Feature",
  "properties": {
    "iso:country":"US",
    "sg:address":"730 S 4th St",
    "sg:city":"Clinton",
    "sg:classifiers":[
        {
            "category":"Autos & Motor Vehicles",
            "subcategory":"Automobile Sales",
            "type":"Retail Goods"
        }
    ],
    "sg:phone":"+1 580 323 1400",
    "sg:postcode":"73601",
    "sg:province":"OK",
    "sg:tags":[
        "used"
    ],
    "wof:name":"Brads Quality Auto Sales",
    "wof:placetype":"venue"
},
  "geometry": {"coordinates":[-98.96484599999999,35.508217],"type":"Point"}
}