{
  "type": "Feature",
  "properties": {
    "addr:full":"1824 Kansas Ave Woodward OK 73801",
    "addr:housenumber":"1824",
    "addr:postcode":"73801",
    "addr:street":"Kansas Ave",
    "iso:country":"US",
    "sg:address":"1824 Kansas Ave",
    "sg:city":"Woodward",
    "sg:classifiers":[
        {
            "category":"Health Services",
            "subcategory":"Doctor",
            "type":"Services"
        }
    ],
    "sg:phone":"+1 580 256 3196",
    "sg:postcode":"73801",
    "sg:province":"OK",
    "sg:tags":[
        "medical"
    ],
    "wof:name":"Healthlink-Kansas Avenue",
    "wof:placetype":"venue"
},
  "geometry": {"coordinates":[-99.403216,36.437237],"type":"Point"}
}