{
  "type": "Feature",
  "properties": {
    "iso:country":"US",
    "sg:address":"4603 SE 29th St",
    "sg:city":"Oklahoma City",
    "sg:classifiers":[
        {
            "category":"Shopping",
            "subcategory":"Gifts & Souvenirs",
            "type":"Retail Goods"
        }
    ],
    "sg:phone":"+1 405 672 6404",
    "sg:postcode":"73115",
    "sg:province":"OK",
    "wof:name":"and Bear Makes 3 Inc",
    "wof:placetype":"venue"
},
  "geometry": {"coordinates":[-97.43274599999999,35.434911],"type":"Point"}
}