{
  "type": "Feature",
  "properties": {
    "iso:country":"US",
    "sg:address":"114 S Main St",
    "sg:city":"Okeene",
    "sg:classifiers":[
        {
            "category":"Building & Trades",
            "subcategory":"Plumbing",
            "type":"Services"
        }
    ],
    "sg:phone":"+1 580 822 4819",
    "sg:postcode":"73763",
    "sg:province":"OK",
    "sg:tags":[
        "conditioning",
        "air",
        "system",
        "contractor"
    ],
    "wof:name":"Greb Appliance Inc",
    "wof:placetype":"venue"
},
  "geometry": {"coordinates":[-98.317155,36.115822],"type":"Point"}
}