{
  "type": "Feature",
  "properties": {
    "iso:country":"US",
    "sg:address":"606 N 15th St",
    "sg:city":"Perry",
    "sg:classifiers":[
        {
            "category":"Retail",
            "subcategory":"Laundry & Dry Cleaning",
            "type":"Services"
        }
    ],
    "sg:phone":"+1 580 336 3444",
    "sg:postcode":"73077",
    "sg:province":"OK",
    "sg:tags":[
        "drycleaning",
        "plant",
        "cleaners"
    ],
    "wof:name":"Hahn's Cleaners",
    "wof:placetype":"venue"
},
  "geometry": {"coordinates":[-97.300911,36.292523],"type":"Point"}
}