{
  "type": "Feature",
  "properties": {
    "iso:country":"US",
    "sg:address":"517 N Porter Ave",
    "sg:city":"Norman",
    "sg:classifiers":[
        {
            "category":"Restaurant",
            "type":"Food & Drink"
        }
    ],
    "sg:phone":"+1 405 364 4171",
    "sg:postcode":"73071",
    "sg:province":"OK",
    "sg:tags":[
        "eating"
    ],
    "wof:name":"J Pats Restaurant Inc",
    "wof:placetype":"venue"
},
  "geometry": {"coordinates":[-97.441004,35.226008],"type":"Point"}
}