{
  "type": "Feature",
  "properties": {
    "iso:country":"US",
    "sg:address":"231 E 10th St",
    "sg:city":"Ada",
    "sg:classifiers":[
        {
            "category":"Home & Garden",
            "subcategory":"Building Materials",
            "type":"Retail Goods"
        }
    ],
    "sg:phone":"+1 580 436 3638",
    "sg:postcode":"74820",
    "sg:province":"OK",
    "sg:tags":[
        "floor",
        "covering"
    ],
    "wof:name":"Carpet Depot",
    "wof:placetype":"venue"
},
  "geometry": {"coordinates":[-96.676537,34.775508],"type":"Point"}
}