{
  "type": "Feature",
  "properties": {
    "iso:country":"US",
    "sg:address":"1111 W Willow Ave",
    "sg:city":"Duncan",
    "sg:classifiers":[
        {
            "category":"Professional",
            "subcategory":"Secretarial Services",
            "type":"Services"
        }
    ],
    "sg:phone":"+1 580 475 0226",
    "sg:postcode":"73533",
    "sg:province":"OK",
    "sg:tags":[
        "reporting",
        "court"
    ],
    "wof:name":"Secretary For A Day",
    "wof:placetype":"venue"
},
  "geometry": {"coordinates":[-97.962654,34.501291],"type":"Point"}
}