{
  "type": "Feature",
  "properties": {
    "addr:full":"7901 NW 26th St Bethany OK 73008",
    "addr:housenumber":"7901",
    "addr:postcode":"73008",
    "addr:street":"Nw 26Th St",
    "iso:country":"US",
    "sg:address":"7901 NW 26th St",
    "sg:city":"Bethany",
    "sg:classifiers":[
        {
            "category":"Real Estate",
            "subcategory":"Real Estate Agent",
            "type":"Services"
        }
    ],
    "sg:phone":"+1 405 787 1441",
    "sg:postcode":"73008",
    "sg:province":"OK",
    "wof:name":"AAA Realtors",
    "wof:placetype":"venue"
},
  "geometry": {"coordinates":[-97.65428199999999,35.496012],"type":"Point"}
}