{
  "type": "Feature",
  "properties": {
    "addr:full":"200 E Frisco Ave Blackwell OK 74631",
    "addr:housenumber":"200",
    "addr:postcode":"74631",
    "addr:street":"E Frisco Ave",
    "iso:country":"US",
    "sg:address":"200 E Frisco Ave",
    "sg:city":"Blackwell",
    "sg:classifiers":[
        {
            "category":"Building & Trades",
            "subcategory":"Electrical",
            "type":"Services"
        }
    ],
    "sg:phone":"+1 580 363 5697",
    "sg:postcode":"74631",
    "sg:province":"OK",
    "sg:tags":[
        "electric",
        "contractor"
    ],
    "wof:name":"Holmes Electrical Contractor",
    "wof:placetype":"venue"
},
  "geometry": {"coordinates":[-97.28169,36.80828],"type":"Point"}
}