{
  "type": "Feature",
  "properties": {
    "iso:country":"US",
    "sg:address":"119 N Main St",
    "sg:city":"Broken Bow",
    "sg:classifiers":[
        {
            "category":"Social Services",
            "type":"Services"
        }
    ],
    "sg:phone":"+1 580 584 6403",
    "sg:postcode":"74728",
    "sg:province":"OK",
    "sg:tags":[
        "organization",
        "welfare"
    ],
    "wof:name":"SOS For Families",
    "wof:placetype":"venue"
},
  "geometry": {"coordinates":[-94.737148,34.028201],"type":"Point"}
}