{
  "type": "Feature",
  "properties": {
    "iso:country":"US",
    "sg:address":"900 84th Ave SE",
    "sg:city":"Norman",
    "sg:classifiers":[
        {
            "category":"Building & Trades",
            "subcategory":"Construction",
            "type":"Services"
        }
    ],
    "sg:phone":"+1 405 447 4307",
    "sg:postcode":"73026",
    "sg:province":"OK",
    "sg:tags":[
        "residential"
    ],
    "wof:name":"Shamrock Tile",
    "wof:placetype":"venue"
},
  "geometry": {"coordinates":[-97.318069,35.208437],"type":"Point"}
}