{
  "type": "Feature",
  "properties": {
    "iso:country":"US",
    "sg:address":"4912 N Classen Blvd",
    "sg:city":"Oklahoma City",
    "sg:classifiers":[
        {
            "category":"Retail",
            "subcategory":"Auto Repair",
            "type":"Services"
        }
    ],
    "sg:phone":"+1 405 840 0023",
    "sg:postcode":"73118",
    "sg:province":"OK",
    "sg:tags":[
        "automotive"
    ],
    "wof:name":"Roadstar Import Car Repair",
    "wof:placetype":"venue"
},
  "geometry": {"coordinates":[-97.534297,35.521356],"type":"Point"}
}