{
  "type": "Feature",
  "properties": {
    "iso:country":"US",
    "sg:address":"14001 N Piedmont Rd",
    "sg:city":"Piedmont",
    "sg:classifiers":[
        {
            "category":"Farming",
            "subcategory":"Farm",
            "type":"Manufacturing & Wholesale Goods"
        }
    ],
    "sg:phone":"+1 405 373 2268",
    "sg:postcode":"73078",
    "sg:province":"OK",
    "sg:tags":[
        "crop",
        "general"
    ],
    "wof:name":"Joan Yowell",
    "wof:placetype":"venue"
},
  "geometry": {"coordinates":[-97.74541600000001,35.618658],"type":"Point"}
}