{
  "type": "Feature",
  "properties": {
    "iso:country":"US",
    "sg:address":"25825 S Hwy 66",
    "sg:city":"Claremore",
    "sg:classifiers":[
        {
            "category":"Restaurant",
            "type":"Food & Drink"
        }
    ],
    "sg:phone":"+1 918 543 6269",
    "sg:postcode":"74019",
    "sg:province":"OK",
    "sg:tags":[
        "delicatessen"
    ],
    "wof:name":"Cedar Bluff Deli",
    "wof:placetype":"venue"
},
  "geometry": {"coordinates":[-95.67949,36.240239],"type":"Point"}
}