{
  "type": "Feature",
  "properties": {
    "iso:country":"US",
    "sg:address":"8600 NE 23rd St",
    "sg:city":"Oklahoma City",
    "sg:classifiers":[
        {
            "category":"Autos & Motor Vehicles",
            "subcategory":"Automobile Sales",
            "type":"Retail Goods"
        }
    ],
    "sg:phone":"+1 405 259 9001",
    "sg:postcode":"73141",
    "sg:province":"OK",
    "sg:tags":[
        "car",
        "used",
        "dealer"
    ],
    "sg:website":"www.uptownmotorsokc.com",
    "wof:name":"Uptown Motors LLC",
    "wof:placetype":"venue"
},
  "geometry": {"coordinates":[-97.378001,35.492968],"type":"Point"}
}