{
  "type": "Feature",
  "properties": {
    "iso:country":"US",
    "sg:address":"9624 NE 4th St",
    "sg:city":"Oklahoma City",
    "sg:classifiers":[
        {
            "category":"Education",
            "subcategory":"Special Training",
            "type":"Public Place"
        }
    ],
    "sg:phone":"+1 405 733 0864",
    "sg:postcode":"73130",
    "sg:province":"OK",
    "sg:tags":[
        "educational"
    ],
    "wof:name":"Science Teaching Professionals",
    "wof:placetype":"venue"
},
  "geometry": {"coordinates":[-97.35791999999999,35.471202],"type":"Point"}
}