{
  "type": "Feature",
  "properties": {
    "addr:full":"425 N Cimarron Dr Enid OK 73703",
    "addr:housenumber":"425",
    "addr:postcode":"73703",
    "addr:street":"N Cimarron Dr",
    "iso:country":"US",
    "sg:address":"425 N Cimarron Dr",
    "sg:city":"Enid",
    "sg:classifiers":[
        {
            "category":"Social Services",
            "subcategory":"Child Care",
            "type":"Services"
        }
    ],
    "sg:phone":"+1 580 234 5209",
    "sg:postcode":"73703",
    "sg:province":"OK",
    "sg:tags":[
        "day"
    ],
    "wof:name":"Rubys Child Care Center 1",
    "wof:placetype":"venue"
},
  "geometry": {"coordinates":[-97.929738,36.401044],"type":"Point"}
}