{
  "type": "Feature",
  "properties": {
    "addr:full":"3600 NE 50th St Oklahoma City OK 73121",
    "addr:housenumber":"3600",
    "addr:postcode":"73121",
    "addr:street":"Ne 50Th St",
    "iso:country":"US",
    "sg:address":"3600 NE 50th St",
    "sg:city":"Oklahoma City",
    "sg:classifiers":[
        {
            "category":"Social Services",
            "type":"Services"
        }
    ],
    "sg:phone":"+1 405 842 8331",
    "sg:postcode":"73121",
    "sg:province":"OK",
    "sg:tags":[
        "counselor"
    ],
    "wof:name":"Linda Clark",
    "wof:placetype":"venue"
},
  "geometry": {"coordinates":[-97.449941,35.5222],"type":"Point"}
}