{
  "type": "Feature",
  "properties": {
    "addr:full":"415 N Philadelphia Ave Shawnee OK 74801",
    "addr:housenumber":"415",
    "addr:postcode":"74801",
    "addr:street":"N Philadelphia Ave",
    "iso:country":"US",
    "sg:address":"415 N Philadelphia Ave",
    "sg:city":"Shawnee",
    "sg:classifiers":[
        {
            "category":"Shopping",
            "subcategory":"Discount & Variety Stores",
            "type":"Retail Goods"
        }
    ],
    "sg:phone":"+1 405 273 8140",
    "sg:postcode":"74801",
    "sg:province":"OK",
    "wof:name":"Blackwell Doug 00",
    "wof:placetype":"venue"
},
  "geometry": {"coordinates":[-96.919562,35.332532],"type":"Point"}
}