{
  "type": "Feature",
  "properties": {
    "iso:country":"US",
    "sg:address":"812 N Bryant Ave",
    "sg:city":"Oklahoma City",
    "sg:classifiers":[
        {
            "category":"Manufacturing",
            "subcategory":"Petroleum Products",
            "type":"Manufacturing & Wholesale Goods"
        }
    ],
    "sg:phone":"+1 405 552 4110",
    "sg:postcode":"73117",
    "sg:province":"OK",
    "sg:tags":[
        "asphalt",
        "mfg"
    ],
    "wof:name":"Johns Manville Corp",
    "wof:placetype":"venue"
},
  "geometry": {"coordinates":[-97.459114,35.477211],"type":"Point"}
}