{
  "type": "Feature",
  "properties": {
    "addr:full":"129 G St NE Miami OK 74354",
    "addr:housenumber":"129",
    "addr:postcode":"74354",
    "addr:street":"G St Ne",
    "iso:country":"US",
    "sg:address":"129 G St NE",
    "sg:city":"Miami",
    "sg:classifiers":[
        {
            "category":"Education",
            "subcategory":"School",
            "type":"Public Place"
        }
    ],
    "sg:phone":"+1 918 542 5576",
    "sg:postcode":"74354",
    "sg:province":"OK",
    "wof:name":"Roosevelt Elementary School",
    "wof:placetype":"venue"
},
  "geometry": {"coordinates":[-94.870195,36.877295],"type":"Point"}
}