{
  "type": "Feature",
  "properties": {
    "iso:country":"US",
    "sg:address":"1530 SW 89th St",
    "sg:city":"Oklahoma City",
    "sg:classifiers":[
        {
            "category":"Health Services",
            "subcategory":"Doctor",
            "type":"Services"
        }
    ],
    "sg:phone":"+1 405 692 8447",
    "sg:postcode":"73159",
    "sg:province":"OK",
    "sg:tags":[
        "physician",
        "surgeon"
    ],
    "wof:name":"William P Becker MD",
    "wof:placetype":"venue"
},
  "geometry": {"coordinates":[-97.544465,35.377209],"type":"Point"}
}