{
  "type": "Feature",
  "properties": {
    "addr:full":"4624 N Macarthur Blvd Oklahoma City OK 73122",
    "addr:housenumber":"4624",
    "addr:postcode":"73122",
    "addr:street":"N Macarthur Blvd",
    "iso:country":"US",
    "sg:address":"4624 N Macarthur Blvd",
    "sg:city":"Oklahoma City",
    "sg:classifiers":[
        {
            "category":"Personal",
            "subcategory":"Beauty Salon",
            "type":"Services"
        }
    ],
    "sg:phone":"+1 405 789 1346",
    "sg:postcode":"73122",
    "sg:province":"OK",
    "sg:tags":[
        "shop"
    ],
    "wof:name":"Curly Q Carlas",
    "wof:placetype":"venue"
},
  "geometry": {"coordinates":[-97.61888500000001,35.518682],"type":"Point"}
}