{
  "type": "Feature",
  "properties": {
    "iso:country":"US",
    "sg:address":"1090 E 380 Rd",
    "sg:city":"Talala",
    "sg:classifiers":[
        {
            "category":"Shopping",
            "subcategory":"Pets & Pet Supplies",
            "type":"Retail Goods"
        },
        {
            "category":"Retail",
            "subcategory":"Veterinary Services",
            "type":"Services"
        }
    ],
    "sg:phone":"+1 918 371 4998",
    "sg:postcode":"74080",
    "sg:province":"OK",
    "sg:tags":[
        "specialty"
    ],
    "wof:name":"Ram Acres",
    "wof:placetype":"venue"
},
  "geometry": {"coordinates":[-95.810192,36.467062],"type":"Point"}
}