{
  "type": "Feature",
  "properties": {
    "iso:country":"US",
    "sg:address":"1601 Heather Ct",
    "sg:city":"Pryor",
    "sg:classifiers":[
        {
            "category":"Wholesale",
            "subcategory":"Non-durable Goods",
            "type":"Manufacturing & Wholesale Goods"
        }
    ],
    "sg:phone":"+1 918 825 2833",
    "sg:postcode":"74361",
    "sg:province":"OK",
    "wof:name":"Country Scents",
    "wof:placetype":"venue"
},
  "geometry": {"coordinates":[-95.306267,36.286399],"type":"Point"}
}