{
  "type": "Feature",
  "properties": {
    "addr:full":"701 S 9th Ave Durant OK 74701",
    "addr:housenumber":"701",
    "addr:postcode":"74701",
    "addr:street":"S 9Th Ave",
    "iso:country":"US",
    "sg:address":"701 S 9th Ave",
    "sg:city":"Durant",
    "sg:classifiers":[
        {
            "category":"Retail",
            "subcategory":"Repair Shop",
            "type":"Services"
        }
    ],
    "sg:phone":"+1 580 920 0167",
    "sg:postcode":"74701",
    "sg:province":"OK",
    "sg:tags":[
        "electrical"
    ],
    "wof:name":"Electromica Jupper",
    "wof:placetype":"venue"
},
  "geometry": {"coordinates":[-96.387484,33.986032],"type":"Point"}
}