{
  "type": "Feature",
  "properties": {
    "iso:country":"US",
    "sg:address":"207 Albright St",
    "sg:city":"Hooker",
    "sg:classifiers":[
        {
            "category":"Professional",
            "subcategory":"Business Services",
            "type":"Services"
        }
    ],
    "sg:phone":"+1 580 652 2638",
    "sg:postcode":"73945",
    "sg:province":"OK",
    "wof:name":"Lil Miz",
    "wof:placetype":"venue"
},
  "geometry": {"coordinates":[-101.212784,36.862969],"type":"Point"}
}