{
  "type": "Feature",
  "properties": {
    "addr:full":"2911 S Air Depot Blvd Oklahoma City OK 73110",
    "addr:housenumber":"2911",
    "addr:postcode":"73110",
    "addr:street":"S Air Depot Blvd",
    "iso:country":"US",
    "sg:address":"2911 S Air Depot Blvd",
    "sg:city":"Oklahoma City",
    "sg:classifiers":[
        {
            "category":"Banks & Credit Unions",
            "subcategory":"Investment Brokerage",
            "type":"Services"
        }
    ],
    "sg:phone":"+1 405 737 0977",
    "sg:postcode":"73110",
    "sg:province":"OK",
    "sg:tags":[
        "security"
    ],
    "sg:website":"www.investmentcenters.com",
    "wof:name":"Investment Centers Of America",
    "wof:placetype":"venue"
},
  "geometry": {"coordinates":[-97.40605499999999,35.435421],"type":"Point"}
}