{
  "type": "Feature",
  "properties": {
    "iso:country":"US",
    "sg:address":"2223 E Skelly Dr",
    "sg:city":"Tulsa",
    "sg:classifiers":[
        {
            "category":"Professional",
            "subcategory":"Accounting & Tax Preparation",
            "type":"Services"
        }
    ],
    "sg:phone":"+1 918 749 2152",
    "sg:postcode":"74105",
    "sg:province":"OK",
    "sg:tags":[
        "accountant"
    ],
    "wof:name":"J R Hays CPA",
    "wof:placetype":"venue"
},
  "geometry": {"coordinates":[-95.958123,36.091084],"type":"Point"}
}