{
  "type": "Feature",
  "properties": {
    "addr:full":"1060 S Mingo Rd Tulsa OK 74128",
    "addr:housenumber":"1060",
    "addr:postcode":"74128",
    "addr:street":"S Mingo Rd",
    "iso:country":"US",
    "sg:address":"1060 S Mingo Rd",
    "sg:city":"Tulsa",
    "sg:classifiers":[
        {
            "category":"Restaurant",
            "type":"Food & Drink"
        }
    ],
    "sg:phone":"+1 918 835 8569",
    "sg:postcode":"74128",
    "sg:province":"OK",
    "wof:name":"El Gallo Loco",
    "wof:placetype":"venue"
},
  "geometry": {"coordinates":[-95.868707,36.14907],"type":"Point"}
}