{
  "type": "Feature",
  "properties": {
    "iso:country":"US",
    "sg:address":"23841 State Hwy 100",
    "sg:city":"Welling",
    "sg:classifiers":[
        {
            "category":"Freight",
            "type":"Transportation"
        }
    ],
    "sg:phone":"+1 918 457 6060",
    "sg:postcode":"74471",
    "sg:province":"OK",
    "sg:tags":[
        "broker",
        "trucking"
    ],
    "wof:name":"Millennium Transportation Inc",
    "wof:placetype":"venue"
},
  "geometry": {"coordinates":[-94.878902,35.764584],"type":"Point"}
}