{
  "type": "Feature",
  "properties": {
    "addr:full":"215 S Washington St Stillwater OK 74074",
    "addr:housenumber":"215",
    "addr:postcode":"74074",
    "addr:street":"S Washington St",
    "iso:country":"US",
    "sg:address":"215 S Washington St",
    "sg:city":"Stillwater",
    "sg:classifiers":[
        {
            "category":"Restaurant",
            "type":"Food & Drink"
        }
    ],
    "sg:menulink":"http://www.allmenus.com/ok/stillwater/102809-the-pita-pit/menu/",
    "sg:phone":"+1 405 372 7482",
    "sg:postcode":"74074",
    "sg:province":"OK",
    "sg:tags":[
        "salad",
        "soup",
        "eastern",
        "mediterranean",
        "middle",
        "american",
        "greek"
    ],
    "wof:name":"The Pita Pit",
    "wof:placetype":"venue"
},
  "geometry": {"coordinates":[-97.069362,36.11954],"type":"Point"}
}