{
  "type": "Feature",
  "properties": {
    "addr:full":"304 Sooner Rd Holdenville OK 74848",
    "addr:housenumber":"304",
    "addr:postcode":"74848",
    "addr:street":"Sooner Rd",
    "iso:country":"US",
    "sg:address":"304 Sooner Rd",
    "sg:city":"Holdenville",
    "sg:classifiers":[
        {
            "category":"Food & Beverages",
            "subcategory":"Groceries & Convenience Stores",
            "type":"Retail Goods"
        }
    ],
    "sg:phone":"+1 405 379 7476",
    "sg:postcode":"74848",
    "sg:province":"OK",
    "wof:name":"H & H Foods",
    "wof:placetype":"venue"
},
  "geometry": {"coordinates":[-96.376076,35.084365],"type":"Point"}
}