{
  "type": "Feature",
  "properties": {
    "iso:country":"US",
    "sg:address":"7628 NW 101st St",
    "sg:city":"Oklahoma City",
    "sg:classifiers":[
        {
            "category":"Professional",
            "subcategory":"Lawyer & Legal Services",
            "type":"Services"
        }
    ],
    "sg:phone":"+1 405 722 3663",
    "sg:postcode":"73162",
    "sg:province":"OK",
    "sg:tags":[
        "attorney"
    ],
    "wof:name":"Brian Powley",
    "wof:placetype":"venue"
},
  "geometry": {"coordinates":[-97.64939200000001,35.574062],"type":"Point"}
}