{
  "type": "Feature",
  "properties": {
    "addr:full":"2500 S Broadway Edmond OK 73013",
    "addr:housenumber":"2500",
    "addr:postcode":"73013",
    "addr:street":"S Broadway",
    "iso:country":"US",
    "sg:address":"2500 S Broadway",
    "sg:city":"Edmond",
    "sg:classifiers":[
        {
            "category":"Health Services",
            "subcategory":"Health Practitioner",
            "type":"Services"
        }
    ],
    "sg:phone":"+1 405 330 9988",
    "sg:postcode":"73013",
    "sg:province":"OK",
    "sg:tags":[
        "psychotherapist"
    ],
    "wof:name":"Donna K O'Keefe",
    "wof:placetype":"venue"
},
  "geometry": {"coordinates":[-97.484453,35.628666],"type":"Point"}
}