{
  "type": "Feature",
  "properties": {
    "iso:country":"US",
    "sg:address":"819 48th St",
    "sg:city":"Woodward",
    "sg:classifiers":[
        {
            "category":"Professional",
            "type":"Services"
        }
    ],
    "sg:phone":"+1 580 256 1666",
    "sg:postcode":"73801",
    "sg:province":"OK",
    "sg:tags":[
        "establishment"
    ],
    "wof:name":"Bobby Joe Cudd Co",
    "wof:placetype":"venue"
},
  "geometry": {"coordinates":[-99.44356000000001,36.438951],"type":"Point"}
}