{
  "type": "Feature",
  "properties": {
    "iso:country":"US",
    "sg:address":"4205 Holiday Pl",
    "sg:city":"Oklahoma City",
    "sg:classifiers":[
        {
            "category":"Retail",
            "subcategory":"Laundry & Dry Cleaning",
            "type":"Services"
        }
    ],
    "sg:phone":"+1 405 943 0600",
    "sg:postcode":"73112",
    "sg:province":"OK",
    "wof:name":"TLC Carpet Care",
    "wof:placetype":"venue"
},
  "geometry": {"coordinates":[-97.595606,35.536355],"type":"Point"}
}