{
  "type": "Feature",
  "properties": {
    "iso:country":"US",
    "sg:address":"2200 Faircloud Ln",
    "sg:city":"Edmond",
    "sg:classifiers":[
        {
            "category":"Education",
            "subcategory":"Special Training",
            "type":"Public Place"
        }
    ],
    "sg:phone":"+1 405 330 0935",
    "sg:postcode":"73034",
    "sg:province":"OK",
    "wof:name":"Gregory Holeman",
    "wof:placetype":"venue"
},
  "geometry": {"coordinates":[-97.449449,35.671565],"type":"Point"}
}