{
  "type": "Feature",
  "properties": {
    "iso:country":"US",
    "sg:address":"1709 N Allen Ln",
    "sg:city":"Oklahoma City",
    "sg:classifiers":[
        {
            "category":"Manufacturing",
            "subcategory":"Building Materials",
            "type":"Manufacturing & Wholesale Goods"
        }
    ],
    "sg:phone":"+1 405 495 1136",
    "sg:postcode":"73127",
    "sg:province":"OK",
    "sg:tags":[
        "stairs"
    ],
    "wof:name":"Specialty Sales Assoc",
    "wof:placetype":"venue"
},
  "geometry": {"coordinates":[-97.623519,35.489561],"type":"Point"}
}