{
  "type": "Feature",
  "properties": {
    "iso:country":"US",
    "sg:address":"6317 S Sandusky Ave",
    "sg:city":"Tulsa",
    "sg:classifiers":[
        {
            "category":"Shopping",
            "subcategory":"Beauty & Cosmetics",
            "type":"Retail Goods"
        }
    ],
    "sg:phone":"+1 918 488 8100",
    "sg:postcode":"74136",
    "sg:province":"OK",
    "sg:tags":[
        "merchandise"
    ],
    "wof:name":"Mary Kay Cosmetics",
    "wof:placetype":"venue"
},
  "geometry": {"coordinates":[-95.92671,36.071847],"type":"Point"}
}