{
  "type": "Feature",
  "properties": {
    "iso:country":"US",
    "sg:address":"4529 S May Ave",
    "sg:city":"Oklahoma City",
    "sg:classifiers":[
        {
            "category":"Shopping",
            "subcategory":"Discount & Variety Stores",
            "type":"Retail Goods"
        },
        {
            "category":"Shopping",
            "subcategory":"Department Store",
            "type":"Retail Goods"
        }
    ],
    "sg:phone":"+1 405 681 2231",
    "sg:postcode":"73119",
    "sg:province":"OK",
    "sg:tags":[
        "shop"
    ],
    "wof:name":"Dollar General",
    "wof:placetype":"venue"
},
  "geometry": {"coordinates":[-97.565622,35.419069],"type":"Point"}
}