{
  "type": "Feature",
  "properties": {
    "iso:country":"US",
    "sg:address":"120 N Robinson Ave",
    "sg:city":"Oklahoma City",
    "sg:classifiers":[
        {
            "category":"Mining & Drilling",
            "type":"Manufacturing & Wholesale Goods"
        }
    ],
    "sg:phone":"+1 405 272 0204",
    "sg:postcode":"73102",
    "sg:province":"OK",
    "sg:tags":[
        "exploration"
    ],
    "wof:name":"Mid Continent Minerals Inc",
    "wof:placetype":"venue"
},
  "geometry": {"coordinates":[-97.516346,35.468589],"type":"Point"}
}