{
  "type": "Feature",
  "properties": {
    "iso:country":"US",
    "sg:address":"1612 Saratoga Way",
    "sg:city":"Edmond",
    "sg:classifiers":[
        {
            "category":"Restaurant",
            "type":"Food & Drink"
        }
    ],
    "sg:phone":"+1 405 844 8055",
    "sg:postcode":"73003",
    "sg:province":"OK",
    "sg:tags":[
        "eating"
    ],
    "wof:name":"Sonic Drive-In",
    "wof:placetype":"venue"
},
  "geometry": {"coordinates":[-97.50544600000001,35.696074],"type":"Point"}
}