{
  "type": "Feature",
  "properties": {
    "iso:country":"US",
    "sg:address":"1429 S Memorial Dr",
    "sg:city":"Tulsa",
    "sg:classifiers":[
        {
            "category":"Autos & Motor Vehicles",
            "subcategory":"Automobile Sales",
            "type":"Retail Goods"
        }
    ],
    "sg:phone":"+1 918 834 2886",
    "sg:postcode":"74112",
    "sg:province":"OK",
    "sg:tags":[
        "car",
        "dealer"
    ],
    "wof:name":"Discount Auto Sales",
    "wof:placetype":"venue"
},
  "geometry": {"coordinates":[-95.886549,36.141211],"type":"Point"}
}