{
  "type": "Feature",
  "properties": {
    "addr:full":"801 E Wyandotte Ave Mcalester OK 74501",
    "addr:housenumber":"801",
    "addr:postcode":"74501",
    "addr:street":"E Wyandotte Ave",
    "iso:country":"US",
    "sg:address":"801 E Wyandotte Ave",
    "sg:city":"Mcalester",
    "sg:classifiers":[
        {
            "category":"Health Services",
            "subcategory":"Nursing And Care Facility",
            "type":"Services"
        }
    ],
    "sg:phone":"+1 918 423 3911",
    "sg:postcode":"74501",
    "sg:province":"OK",
    "sg:tags":[
        "hospice"
    ],
    "wof:name":"Hospice Of Mc Alester",
    "wof:placetype":"venue"
},
  "geometry": {"coordinates":[-95.760373,34.926617],"type":"Point"}
}