{
  "type": "Feature",
  "properties": {
    "iso:country":"US",
    "sg:address":"2001 S Division St",
    "sg:city":"Guthrie",
    "sg:classifiers":[
        {
            "category":"Health Services",
            "subcategory":"Doctor",
            "type":"Services"
        }
    ],
    "sg:phone":"+1 405 282 6440",
    "sg:postcode":"73044",
    "sg:province":"OK",
    "sg:tags":[
        "dentist"
    ],
    "sg:website":"www.e-communitydental.com",
    "wof:name":"Comfort Dental Group",
    "wof:placetype":"venue"
},
  "geometry": {"coordinates":[-97.425486,35.859147],"type":"Point"}
}