{
  "type": "Feature",
  "properties": {
    "addr:full":"1429 SW 29th St Oklahoma City OK 73119",
    "addr:housenumber":"1429",
    "addr:postcode":"73119",
    "addr:street":"Sw 29Th St",
    "iso:country":"US",
    "sg:address":"1429 SW 29th St",
    "sg:city":"Oklahoma City",
    "sg:classifiers":[
        {
            "category":"Shopping",
            "subcategory":"Discount & Variety Stores",
            "type":"Retail Goods"
        },
        {
            "category":"Shopping",
            "subcategory":"Department Store",
            "type":"Retail Goods"
        }
    ],
    "sg:phone":"+1 405 632 5186",
    "sg:postcode":"73119",
    "sg:province":"OK",
    "sg:tags":[
        "shop"
    ],
    "sg:website":"www.familydollar.com",
    "wof:name":"Family Dollar Stores",
    "wof:placetype":"venue"
},
  "geometry": {"coordinates":[-97.54293199999999,35.435293],"type":"Point"}
}