{
  "type": "Feature",
  "properties": {
    "iso:country":"US",
    "sg:address":"2215 S Van Buren St",
    "sg:city":"Enid",
    "sg:classifiers":[
        {
            "category":"Manufacturing",
            "subcategory":"Tools & Machinery",
            "type":"Manufacturing & Wholesale Goods"
        }
    ],
    "sg:phone":"+1 580 548 2723",
    "sg:postcode":"73703",
    "sg:province":"OK",
    "sg:tags":[
        "equipment",
        "pump",
        "pumping"
    ],
    "sg:website":"www.pumpstar.com",
    "wof:name":"Pumpstar",
    "wof:placetype":"venue"
},
  "geometry": {"coordinates":[-97.889964,36.374247],"type":"Point"}
}