{
  "type": "Feature",
  "properties": {
    "iso:country":"US",
    "sg:address":"4407 S Gary Ave",
    "sg:city":"Tulsa",
    "sg:classifiers":[
        {
            "category":"Shopping",
            "type":"Retail Goods"
        }
    ],
    "sg:phone":"+1 918 747 1697",
    "sg:postcode":"74105",
    "sg:province":"OK",
    "sg:tags":[
        "merchandise"
    ],
    "wof:name":"A & A Awning & Roofing Co",
    "wof:placetype":"venue"
},
  "geometry": {"coordinates":[-95.941587,36.099101],"type":"Point"}
}