{
  "type": "Feature",
  "properties": {
    "iso:country":"US",
    "sg:address":"2805 SW 31st St",
    "sg:city":"Oklahoma City",
    "sg:classifiers":[
        {
            "category":"Building & Trades",
            "subcategory":"Construction",
            "type":"Services"
        }
    ],
    "sg:phone":"+1 405 632 1184",
    "sg:postcode":"73119",
    "sg:province":"OK",
    "sg:tags":[
        "masonry",
        "contractor"
    ],
    "wof:name":"Loftis Stone Masonry Inc",
    "wof:placetype":"venue"
},
  "geometry": {"coordinates":[-97.56552,35.433211],"type":"Point"}
}