{
  "type": "Feature",
  "properties": {
    "iso:country":"US",
    "sg:address":"10760 N 157th East Ave",
    "sg:city":"Owasso",
    "sg:classifiers":[
        {
            "category":"Shopping",
            "subcategory":"Hobbies, Toys, & Games",
            "type":"Retail Goods"
        }
    ],
    "sg:phone":"+1 918 274 9439",
    "sg:postcode":"74055",
    "sg:province":"OK",
    "sg:tags":[
        "supply"
    ],
    "wof:name":"Scrapbook Dreams LLC",
    "wof:placetype":"venue"
},
  "geometry": {"coordinates":[-95.799945,36.311056],"type":"Point"}
}