{
  "type": "Feature",
  "properties": {
    "iso:country":"US",
    "sg:address":"13020 State Hwy 10",
    "sg:city":"Tahlequah",
    "sg:classifiers":[
        {
            "category":"Travel",
            "subcategory":"Hotels & Motels",
            "type":"Entertainment"
        }
    ],
    "sg:phone":"+1 918 456 6272",
    "sg:postcode":"74464",
    "sg:province":"OK",
    "sg:tags":[
        "resort"
    ],
    "wof:name":"War Eagle Resort",
    "wof:placetype":"venue"
},
  "geometry": {"coordinates":[-94.92437099999999,35.981872],"type":"Point"}
}