{
  "type": "Feature",
  "properties": {
    "addr:full":"620 Ed Noble Pkwy Norman OK 73072",
    "addr:housenumber":"620",
    "addr:postcode":"73072",
    "addr:street":"Ed Noble Pkwy",
    "iso:country":"US",
    "sg:address":"620 Ed Noble Pkwy",
    "sg:city":"Norman",
    "sg:classifiers":[
        {
            "category":"Shopping",
            "subcategory":"Stationery & Office Supplies",
            "type":"Retail Goods"
        }
    ],
    "sg:phone":"+1 405 573 2049",
    "sg:postcode":"73072",
    "sg:province":"OK",
    "wof:name":"Office Max",
    "wof:placetype":"venue"
},
  "geometry": {"coordinates":[-97.484433,35.211611],"type":"Point"}
}