{
  "type": "Feature",
  "properties": {
    "iso:country":"US",
    "sg:address":"7317 N Macarthur Blvd",
    "sg:city":"Oklahoma City",
    "sg:classifiers":[
        {
            "category":"Health Services",
            "subcategory":"Doctor",
            "type":"Services"
        }
    ],
    "sg:phone":"+1 405 720 9491",
    "sg:postcode":"73132",
    "sg:province":"OK",
    "sg:tags":[
        "physician",
        "surgeon"
    ],
    "wof:name":"CORRECTIVE Skin & Vein Ctr",
    "wof:placetype":"venue"
},
  "geometry": {"coordinates":[-97.619084,35.547179],"type":"Point"}
}