{
  "type": "Feature",
  "properties": {
    "iso:country":"US",
    "sg:address":"118 N Broadway St",
    "sg:city":"Cleveland",
    "sg:classifiers":[
        {
            "category":"Shopping",
            "subcategory":"Computers & Home Electronics",
            "type":"Retail Goods"
        }
    ],
    "sg:phone":"+1 918 358 1111",
    "sg:postcode":"74020",
    "sg:province":"OK",
    "sg:tags":[
        "software"
    ],
    "wof:name":"RCR Computing",
    "wof:placetype":"venue"
},
  "geometry": {"coordinates":[-96.464117,36.309846],"type":"Point"}
}