{
  "type": "Feature",
  "properties": {
    "iso:country":"US",
    "sg:address":"916 Chestnut St",
    "sg:city":"Muskogee",
    "sg:classifiers":[
        {
            "category":"Education",
            "subcategory":"Special Training",
            "type":"Public Place"
        }
    ],
    "sg:phone":"+1 918 682 2164",
    "sg:postcode":"74403",
    "sg:province":"OK",
    "wof:name":"Grace Escoe Music Studio",
    "wof:placetype":"venue"
},
  "geometry": {"coordinates":[-95.34670199999999,35.752278],"type":"Point"}
}