{
  "type": "Feature",
  "properties": {
    "iso:country":"US",
    "sg:address":"9204 Kimberly Rd",
    "sg:city":"Oklahoma City",
    "sg:classifiers":[
        {
            "category":"Building & Trades",
            "subcategory":"Construction",
            "type":"Services"
        }
    ],
    "sg:phone":"+1 405 722 3010",
    "sg:postcode":"73132",
    "sg:province":"OK",
    "sg:tags":[
        "contractor"
    ],
    "wof:name":"Martin Construction",
    "wof:placetype":"venue"
},
  "geometry": {"coordinates":[-97.670466,35.56462],"type":"Point"}
}