{
  "type": "Feature",
  "properties": {
    "iso:country":"US",
    "sg:address":"800 S Mekusukey Ave",
    "sg:city":"Wewoka",
    "sg:classifiers":[
        {
            "category":"Restaurant",
            "type":"Food & Drink"
        }
    ],
    "sg:phone":"+1 405 257 3185",
    "sg:postcode":"74884",
    "sg:province":"OK",
    "wof:name":"Johnson's Restaurant",
    "wof:placetype":"venue"
},
  "geometry": {"coordinates":[-96.49341,35.151008],"type":"Point"}
}