{
  "type": "Feature",
  "properties": {
    "iso:country":"US",
    "sg:address":"1209 W Lindsey St",
    "sg:city":"Norman",
    "sg:classifiers":[
        {
            "category":"Autos & Motor Vehicles",
            "subcategory":"Fuel & Gas Station",
            "type":"Retail Goods"
        }
    ],
    "sg:phone":"+1 405 329 4311",
    "sg:postcode":"73069",
    "sg:province":"OK",
    "sg:tags":[
        "station",
        "gasoline"
    ],
    "wof:name":"Andrews 66",
    "wof:placetype":"venue"
},
  "geometry": {"coordinates":[-97.459285,35.203981],"type":"Point"}
}