{
  "type": "Feature",
  "properties": {
    "iso:country":"US",
    "sg:address":"748 N Louisville Ave",
    "sg:city":"Tulsa",
    "sg:classifiers":[
        {
            "category":"Organizations",
            "subcategory":"Religious Organization",
            "type":"Services"
        }
    ],
    "sg:phone":"+1 918 834 2434",
    "sg:postcode":"74115",
    "sg:province":"OK",
    "sg:tags":[
        "church"
    ],
    "wof:name":"Rose Hill United Methodist Chr",
    "wof:placetype":"venue"
},
  "geometry": {"coordinates":[-95.93541399999999,36.16534],"type":"Point"}
}