{
  "type": "Feature",
  "properties": {
    "iso:country":"US",
    "sg:address":"201 NW 74th St",
    "sg:city":"Lawton",
    "sg:classifiers":[
        {
            "category":"Building & Trades",
            "subcategory":"Landscaping Services",
            "type":"Services"
        }
    ],
    "sg:phone":"+1 580 536 8932",
    "sg:postcode":"73505",
    "sg:province":"OK",
    "wof:name":"Lawnscape",
    "wof:placetype":"venue"
},
  "geometry": {"coordinates":[-98.481893,34.611067],"type":"Point"}
}