{
  "type": "Feature",
  "properties": {
    "addr:full":"1101 Lynn Ave Pawhuska OK 74056",
    "addr:housenumber":"1101",
    "addr:postcode":"74056",
    "addr:street":"Lynn Ave",
    "iso:country":"US",
    "sg:address":"1101 Lynn Ave",
    "sg:city":"Pawhuska",
    "sg:classifiers":[
        {
            "category":"Retail",
            "subcategory":"Auto Repair",
            "type":"Services"
        }
    ],
    "sg:phone":"+1 918 287 4030",
    "sg:postcode":"74056",
    "sg:province":"OK",
    "sg:tags":[
        "body",
        "automobile",
        "painting"
    ],
    "wof:name":"Parkers Paint & Body",
    "wof:placetype":"venue"
},
  "geometry": {"coordinates":[-96.33171299999999,36.669042],"type":"Point"}
}