{
  "type": "Feature",
  "properties": {
    "iso:country":"US",
    "sg:address":"3807 N Asbury Ave",
    "sg:city":"Bethany",
    "sg:classifiers":[
        {
            "category":"Professional",
            "subcategory":"Lawyer & Legal Services",
            "type":"Services"
        }
    ],
    "sg:phone":"+1 405 789 4611",
    "sg:postcode":"73008",
    "sg:province":"OK",
    "sg:tags":[
        "attorney"
    ],
    "wof:name":"James N Posey",
    "wof:placetype":"venue"
},
  "geometry": {"coordinates":[-97.63096,35.509408],"type":"Point"}
}