{
  "type": "Feature",
  "properties": {
    "iso:country":"US",
    "sg:address":"1125 SW 29th St",
    "sg:city":"Oklahoma City",
    "sg:classifiers":[
        {
            "category":"Food & Beverages",
            "subcategory":"Meat & Fish",
            "type":"Retail Goods"
        }
    ],
    "sg:phone":"+1 405 635 1130",
    "sg:postcode":"73109",
    "sg:province":"OK",
    "wof:name":"LA Michoacana",
    "wof:placetype":"venue"
},
  "geometry": {"coordinates":[-97.534728,35.435316],"type":"Point"}
}