{
  "type": "Feature",
  "properties": {
    "iso:country":"US",
    "sg:address":"2628 NE 18th St",
    "sg:city":"Oklahoma City",
    "sg:classifiers":[
        {
            "category":"Organizations",
            "subcategory":"Non-profit Organization",
            "type":"Services"
        }
    ],
    "sg:phone":"+1 405 424 3368",
    "sg:postcode":"73111",
    "sg:province":"OK",
    "sg:tags":[
        "career",
        "health",
        "focused"
    ],
    "wof:name":"Mtr Consulting Inc",
    "wof:placetype":"venue"
},
  "geometry": {"coordinates":[-97.462456,35.487629],"type":"Point"}
}