{
  "type": "Feature",
  "properties": {
    "iso:country":"US",
    "sg:address":"5333 S Mingo Rd",
    "sg:city":"Tulsa",
    "sg:classifiers":[
        {
            "category":"Utilities",
            "subcategory":"Telephone",
            "type":"Services"
        }
    ],
    "sg:phone":"+1 918 622 5623",
    "sg:postcode":"74146",
    "sg:province":"OK",
    "sg:tags":[
        "communications"
    ],
    "wof:name":"Russian Liaisons",
    "wof:placetype":"venue"
},
  "geometry": {"coordinates":[-95.868539,36.085223],"type":"Point"}
}