{
  "type": "Feature",
  "properties": {
    "addr:full":"2701 Liberty Pkwy Midwest City OK 73110",
    "addr:housenumber":"2701",
    "addr:postcode":"73110",
    "addr:street":"Liberty Pkwy",
    "iso:country":"US",
    "sg:address":"2701 Liberty Pkwy",
    "sg:city":"Midwest City",
    "sg:classifiers":[
        {
            "category":"Banks & Credit Unions",
            "subcategory":"Financial Services",
            "type":"Services"
        }
    ],
    "sg:phone":"+1 405 737 2676",
    "sg:postcode":"73110",
    "sg:province":"OK",
    "sg:tags":[
        "company",
        "venture",
        "capital"
    ],
    "wof:name":"Acorn Growth Co",
    "wof:placetype":"venue"
},
  "geometry": {"coordinates":[-97.421572,35.435228],"type":"Point"}
}