{
  "type": "Feature",
  "properties": {
    "addr:full":"119 N Oak St Sallisaw OK 74955",
    "addr:housenumber":"119",
    "addr:postcode":"74955",
    "addr:street":"N Oak St",
    "iso:country":"US",
    "sg:address":"119 N Oak St",
    "sg:city":"Sallisaw",
    "sg:classifiers":[
        {
            "category":"Insurance",
            "subcategory":"Insurance Agent",
            "type":"Services"
        }
    ],
    "sg:phone":"+1 918 775 4344",
    "sg:postcode":"74955",
    "sg:province":"OK",
    "wof:name":"Ken Stavely Insurance",
    "wof:placetype":"venue"
},
  "geometry": {"coordinates":[-94.78876700000001,35.459404],"type":"Point"}
}