{
  "type": "Feature",
  "properties": {
    "iso:country":"US",
    "sg:address":"2950 NW 63rd St",
    "sg:city":"Oklahoma City",
    "sg:classifiers":[
        {
            "category":"Sports & Exercise",
            "subcategory":"Gym",
            "type":"Entertainment"
        }
    ],
    "sg:phone":"+1 405 848 1199",
    "sg:postcode":"73116",
    "sg:province":"OK",
    "sg:tags":[
        "club",
        "health",
        "studio",
        "gymnasium"
    ],
    "wof:name":"Mademoisell Figure & Fitness",
    "wof:placetype":"venue"
},
  "geometry": {"coordinates":[-97.567216,35.536474],"type":"Point"}
}