{
  "type": "Feature",
  "properties": {
    "iso:country":"US",
    "sg:address":"114 4th St",
    "sg:city":"Verden",
    "sg:classifiers":[
        {
            "category":"Organizations",
            "subcategory":"Religious Organization",
            "type":"Services"
        }
    ],
    "sg:phone":"+1 405 453 7728",
    "sg:postcode":"73092",
    "sg:province":"OK",
    "sg:tags":[
        "church"
    ],
    "wof:name":"Verden Pentecostal Chr-God",
    "wof:placetype":"venue"
},
  "geometry": {"coordinates":[-98.08940699999999,35.083217],"type":"Point"}
}