{
  "type": "Feature",
  "properties": {
    "iso:country":"US",
    "sg:address":"4005 N Pennsylvania Ave",
    "sg:city":"Oklahoma City",
    "sg:classifiers":[
        {
            "category":"Shopping",
            "subcategory":"Tobacco",
            "type":"Retail Goods"
        }
    ],
    "sg:phone":"+1 405 521 9997",
    "sg:postcode":"73112",
    "sg:province":"OK",
    "sg:tags":[
        "shop",
        "smoke",
        "supply"
    ],
    "wof:name":"Ziggyz Smoke Novelty",
    "wof:placetype":"venue"
},
  "geometry": {"coordinates":[-97.546969,35.512166],"type":"Point"}
}