{
  "type": "Feature",
  "properties": {
    "iso:country":"US",
    "sg:address":"1 S Main St",
    "sg:city":"Owasso",
    "sg:classifiers":[
        {
            "category":"Freight",
            "type":"Transportation"
        }
    ],
    "sg:phone":"+1 918 272 5200",
    "sg:postcode":"74055",
    "sg:province":"OK",
    "sg:tags":[
        "commercial",
        "storage"
    ],
    "wof:name":"Owasso Safety Storage",
    "wof:placetype":"venue"
},
  "geometry": {"coordinates":[-95.854992,36.265066],"type":"Point"}
}