{
  "type": "Feature",
  "properties": {
    "iso:country":"US",
    "sg:address":"4900 N Portland Ave",
    "sg:city":"Oklahoma City",
    "sg:classifiers":[
        {
            "category":"Health Services",
            "subcategory":"Doctor",
            "type":"Services"
        }
    ],
    "sg:phone":"+1 405 841 4636",
    "sg:postcode":"73112",
    "sg:province":"OK",
    "sg:tags":[
        "medical"
    ],
    "wof:name":"G Dasharathy",
    "wof:placetype":"venue"
},
  "geometry": {"coordinates":[-97.58343499999999,35.522278],"type":"Point"}
}