{
  "type": "Feature",
  "properties": {
    "addr:full":"1028 7th Pl Ada OK 74820",
    "addr:housenumber":"1028",
    "addr:postcode":"74820",
    "addr:street":"7Th Pl",
    "iso:country":"US",
    "sg:address":"1028 7th Pl",
    "sg:city":"Ada",
    "sg:classifiers":[
        {
            "category":"Professional",
            "subcategory":"Computer Services",
            "type":"Services"
        }
    ],
    "sg:phone":"+1 580 310 1099",
    "sg:postcode":"74820",
    "sg:province":"OK",
    "sg:tags":[
        "datum"
    ],
    "wof:name":"BCI Designs",
    "wof:placetype":"venue"
},
  "geometry": {"coordinates":[-96.66181,34.779325],"type":"Point"}
}