{
  "type": "Feature",
  "properties": {
    "iso:country":"US",
    "sg:address":"848 S Elm Pl",
    "sg:city":"Broken Arrow",
    "sg:classifiers":[
        {
            "category":"Farming",
            "subcategory":"Nursery",
            "type":"Manufacturing & Wholesale Goods"
        }
    ],
    "sg:phone":"+1 918 259 5864",
    "sg:postcode":"74012",
    "sg:province":"OK",
    "sg:tags":[
        "ornamental"
    ],
    "wof:name":"Myers Nursery",
    "wof:placetype":"venue"
},
  "geometry": {"coordinates":[-95.79752,36.044987],"type":"Point"}
}