{
  "type": "Feature",
  "properties": {
    "iso:country":"US",
    "sg:address":"1925 NW 39th St",
    "sg:city":"Oklahoma City",
    "sg:classifiers":[
        {
            "category":"Personal",
            "subcategory":"Beauty Salon",
            "type":"Services"
        }
    ],
    "sg:phone":"+1 405 525 9407",
    "sg:postcode":"73118",
    "sg:province":"OK",
    "sg:tags":[
        "shop"
    ],
    "wof:name":"Don's Cut & Style",
    "wof:placetype":"venue"
},
  "geometry": {"coordinates":[-97.544968,35.51144],"type":"Point"}
}