{
  "type": "Feature",
  "properties": {
    "iso:country":"US",
    "sg:address":"160 Felgar St",
    "sg:city":"Norman",
    "sg:classifiers":[
        {
            "category":"Education",
            "subcategory":"College",
            "type":"Public Place"
        }
    ],
    "sg:phone":"+1 405 325 6212",
    "sg:postcode":"73069",
    "sg:province":"OK",
    "sg:tags":[
        "university"
    ],
    "wof:name":"Physical Plant",
    "wof:placetype":"venue"
},
  "geometry": {"coordinates":[-97.443086,35.209743],"type":"Point"}
}