{
  "type": "Feature",
  "properties": {
    "iso:country":"US",
    "sg:address":"218 York St",
    "sg:city":"Tahlequah",
    "sg:classifiers":[
        {
            "category":"Social Services",
            "type":"Services"
        }
    ],
    "sg:phone":"+1 918 458 1028",
    "sg:postcode":"74464",
    "sg:province":"OK",
    "sg:tags":[
        "crisis",
        "intervention"
    ],
    "wof:name":"Help In Crisis Inc",
    "wof:placetype":"venue"
},
  "geometry": {"coordinates":[-94.97236,35.923284],"type":"Point"}
}