{
  "type": "Feature",
  "properties": {
    "iso:country":"US",
    "sg:address":"1207 W Choctaw St",
    "sg:city":"Broken Bow",
    "sg:classifiers":[
        {
            "category":"Organizations",
            "subcategory":"Religious Organization",
            "type":"Services"
        }
    ],
    "sg:phone":"+1 580 584 6113",
    "sg:postcode":"74728",
    "sg:province":"OK",
    "sg:tags":[
        "church"
    ],
    "wof:name":"Lighthouse Christian Ctr",
    "wof:placetype":"venue"
},
  "geometry": {"coordinates":[-94.746759,34.022524],"type":"Point"}
}