{
  "type": "Feature",
  "properties": {
    "addr:full":"1603 W Memorial Rd Oklahoma City OK 73134",
    "addr:housenumber":"1603",
    "addr:postcode":"73134",
    "addr:street":"W Memorial Rd",
    "iso:country":"US",
    "sg:address":"1603 W Memorial Rd",
    "sg:city":"Oklahoma City",
    "sg:classifiers":[
        {
            "category":"Professional",
            "subcategory":"Lawyer & Legal Services",
            "type":"Services"
        }
    ],
    "sg:phone":"+1 405 753 9914",
    "sg:postcode":"73134",
    "sg:province":"OK",
    "sg:tags":[
        "attorney"
    ],
    "wof:name":"Robert F Groshen Jr",
    "wof:placetype":"venue"
},
  "geometry": {"coordinates":[-97.53887400000001,35.609493],"type":"Point"}
}