{
  "type": "Feature",
  "properties": {
    "iso:country":"US",
    "sg:address":"2312 N 53rd W Ave",
    "sg:city":"Tulsa",
    "sg:classifiers":[
        {
            "category":"Building & Trades",
            "subcategory":"Construction",
            "type":"Services"
        }
    ],
    "sg:phone":"+1 918 592 3197",
    "sg:postcode":"74127",
    "sg:province":"OK",
    "sg:tags":[
        "excavating",
        "contractor"
    ],
    "wof:name":"Ballard's Backhoe Svc",
    "wof:placetype":"venue"
},
  "geometry": {"coordinates":[-96.05085,36.188501],"type":"Point"}
}