{
  "type": "Feature",
  "properties": {
    "iso:country":"US",
    "sg:address":"6415 S Mingo Rd",
    "sg:city":"Tulsa",
    "sg:classifiers":[
        {
            "category":"Recreation",
            "type":"Entertainment"
        }
    ],
    "sg:phone":"+1 918 254 1988",
    "sg:postcode":"74133",
    "sg:province":"OK",
    "sg:tags":[
        "instruction",
        "swimming"
    ],
    "sg:website":"www.millerswim.com",
    "wof:name":"Aquatic Center Of Tulsa",
    "wof:placetype":"venue"
},
  "geometry": {"coordinates":[-95.868464,36.0709],"type":"Point"}
}