{
  "type": "Feature",
  "properties": {
    "iso:country":"US",
    "sg:address":"2117 NW 118th Ter",
    "sg:city":"Oklahoma City",
    "sg:classifiers":[
        {
            "category":"Professional",
            "subcategory":"Computer Services",
            "type":"Services"
        }
    ],
    "sg:phone":"+1 405 302 0609",
    "sg:postcode":"73120",
    "sg:province":"OK",
    "sg:tags":[
        "datum"
    ],
    "wof:name":"Beyond Words Inc",
    "wof:placetype":"venue"
},
  "geometry": {"coordinates":[-97.550989,35.590062],"type":"Point"}
}