{
  "type": "Feature",
  "properties": {
    "iso:country":"US",
    "sg:address":"120 S Grand Ave",
    "sg:city":"Cherokee",
    "sg:classifiers":[
        {
            "category":"Professional",
            "subcategory":"Lawyer & Legal Services",
            "type":"Services"
        }
    ],
    "sg:phone":"+1 580 596 3591",
    "sg:postcode":"73728",
    "sg:province":"OK",
    "sg:tags":[
        "attorney"
    ],
    "wof:name":"Hadwiger Jungman & Kline",
    "wof:placetype":"venue"
},
  "geometry": {"coordinates":[-98.357012,36.757558],"type":"Point"}
}