{
  "type": "Feature",
  "properties": {
    "addr:full":"3502 W Purdue Ave Enid OK 73703",
    "addr:housenumber":"3502",
    "addr:postcode":"73703",
    "addr:street":"W Purdue Ave",
    "iso:country":"US",
    "sg:address":"3502 W Purdue Ave",
    "sg:city":"Enid",
    "sg:classifiers":[
        {
            "category":"Building & Trades",
            "subcategory":"Electrical",
            "type":"Services"
        }
    ],
    "sg:phone":"+1 580 233 7923",
    "sg:postcode":"73703",
    "sg:province":"OK",
    "sg:tags":[
        "electrical",
        "contractor"
    ],
    "wof:name":"A D T Security",
    "wof:placetype":"venue"
},
  "geometry": {"coordinates":[-97.920388,36.434398],"type":"Point"}
}