{
  "type": "Feature",
  "properties": {
    "iso:country":"US",
    "sg:address":"1428 Oakdale Dr",
    "sg:city":"Bartlesville",
    "sg:classifiers":[
        {
            "category":"Restaurant",
            "type":"Food & Drink"
        }
    ],
    "sg:phone":"+1 918 335 3585",
    "sg:postcode":"74006",
    "sg:province":"OK",
    "wof:name":"Alfredo's Restaurante Mexicano",
    "wof:placetype":"venue"
},
  "geometry": {"coordinates":[-95.94371599999999,36.733469],"type":"Point"}
}