{
  "type": "Feature",
  "properties": {
    "addr:full":"3705 Georgia Ave Muskogee OK 74403",
    "addr:housenumber":"3705",
    "addr:postcode":"74403",
    "addr:street":"Georgia Ave",
    "iso:country":"US",
    "sg:address":"3705 Georgia Ave",
    "sg:city":"Muskogee",
    "sg:classifiers":[
        {
            "category":"Building & Trades",
            "subcategory":"Plumbing",
            "type":"Services"
        }
    ],
    "sg:phone":"+1 918 682 0536",
    "sg:postcode":"74403",
    "sg:province":"OK",
    "sg:tags":[
        "plumbing",
        "contractor"
    ],
    "wof:name":"American Estates Builders",
    "wof:placetype":"venue"
},
  "geometry": {"coordinates":[-95.319979,35.730082],"type":"Point"}
}