{
  "type": "Feature",
  "properties": {
    "addr:full":"13148 E 11th St Tulsa OK 74108",
    "addr:housenumber":"13148",
    "addr:postcode":"74108",
    "addr:street":"E 11Th St",
    "iso:country":"US",
    "sg:address":"13148 E 11th St",
    "sg:city":"Tulsa",
    "sg:classifiers":[
        {
            "category":"Manufacturing",
            "subcategory":"Printing",
            "type":"Manufacturing & Wholesale Goods"
        }
    ],
    "sg:phone":"+1 918 437 7253",
    "sg:postcode":"74108",
    "sg:province":"OK",
    "sg:tags":[
        "commercial"
    ],
    "wof:name":"Christees Cars LLC",
    "wof:placetype":"venue"
},
  "geometry": {"coordinates":[-95.828892,36.147905],"type":"Point"}
}