{
  "type": "Feature",
  "properties": {
    "iso:country":"US",
    "sg:address":"2707 60th Ave NW",
    "sg:city":"Norman",
    "sg:classifiers":[
        {
            "category":"Retail",
            "subcategory":"Veterinary Services",
            "type":"Services"
        }
    ],
    "sg:phone":"+1 405 366 0120",
    "sg:postcode":"73072",
    "sg:province":"OK",
    "wof:name":"David Marx Dvm",
    "wof:placetype":"venue"
},
  "geometry": {"coordinates":[-97.529664,35.251617],"type":"Point"}
}