{
  "type": "Feature",
  "properties": {
    "iso:country":"US",
    "sg:address":"3800 S Douglas Ave",
    "sg:city":"Oklahoma City",
    "sg:classifiers":[
        {
            "category":"Professional",
            "type":"Services"
        }
    ],
    "sg:phone":"+1 405 376 0299",
    "sg:postcode":"73109",
    "sg:province":"OK",
    "sg:tags":[
        "establishment"
    ],
    "wof:name":"SMSI",
    "wof:placetype":"venue"
},
  "geometry": {"coordinates":[-97.534572,35.427188],"type":"Point"}
}