{
  "type": "Feature",
  "properties": {
    "iso:country":"US",
    "sg:address":"2728 N Main St",
    "sg:city":"Altus",
    "sg:classifiers":[
        {
            "category":"Restaurant",
            "type":"Food & Drink"
        }
    ],
    "sg:menulink":"http://www.allmenus.com/ok/altus/156954-whataburger/menu/",
    "sg:phone":"+1 580 482 3370",
    "sg:postcode":"73521",
    "sg:province":"OK",
    "sg:tags":[
        "burger",
        "american"
    ],
    "wof:name":"Whataburger",
    "wof:placetype":"venue"
},
  "geometry": {"coordinates":[-99.33408,34.666436],"type":"Point"}
}