{
  "type": "Feature",
  "properties": {
    "iso:country":"US",
    "sg:address":"607 Court St",
    "sg:city":"Muskogee",
    "sg:classifiers":[
        {
            "category":"Retail",
            "subcategory":"Auto Repair",
            "type":"Services"
        }
    ],
    "sg:phone":"+1 918 682 8114",
    "sg:postcode":"74401",
    "sg:province":"OK",
    "sg:tags":[
        "automotive"
    ],
    "wof:name":"Mikes Automotive",
    "wof:placetype":"venue"
},
  "geometry": {"coordinates":[-95.37569000000001,35.752616],"type":"Point"}
}