{
  "type": "Feature",
  "properties": {
    "iso:country":"US",
    "sg:address":"305 N Main St",
    "sg:city":"Bristow",
    "sg:classifiers":[
        {
            "category":"Home & Garden",
            "subcategory":"Furniture",
            "type":"Retail Goods"
        }
    ],
    "sg:phone":"+1 918 367 3324",
    "sg:postcode":"74010",
    "sg:province":"OK",
    "wof:name":"Root's Hometown Furn & Appl",
    "wof:placetype":"venue"
},
  "geometry": {"coordinates":[-96.390918,35.835779],"type":"Point"}
}