{
  "type": "Feature",
  "properties": {
    "iso:country":"US",
    "sg:address":"204 Jefferson St",
    "sg:city":"Sand Springs",
    "sg:classifiers":[
        {
            "category":"Home & Garden",
            "subcategory":"Building Materials",
            "type":"Retail Goods"
        }
    ],
    "sg:phone":"+1 918 241 3402",
    "sg:postcode":"74063",
    "sg:province":"OK",
    "sg:tags":[
        "paint"
    ],
    "wof:name":"Sherwin-Williams Paints",
    "wof:placetype":"venue"
},
  "geometry": {"coordinates":[-96.10475,36.13853],"type":"Point"}
}