{
  "type": "Feature",
  "properties": {
    "iso:country":"US",
    "sg:address":"1212 Holly St",
    "sg:city":"Ardmore",
    "sg:classifiers":[
        {
            "category":"Autos & Motor Vehicles",
            "subcategory":"Automobile Sales",
            "type":"Retail Goods"
        }
    ],
    "sg:phone":"+1 580 226 3277",
    "sg:postcode":"73401",
    "sg:province":"OK",
    "sg:tags":[
        "used"
    ],
    "wof:name":"Red Line Auto Sports Inc",
    "wof:placetype":"venue"
},
  "geometry": {"coordinates":[-97.148096,34.157732],"type":"Point"}
}