{
  "type": "Feature",
  "properties": {
    "iso:country":"US",
    "sg:address":"3115 S Robinson Ave",
    "sg:city":"Oklahoma City",
    "sg:classifiers":[
        {
            "category":"Retail",
            "subcategory":"Auto Repair",
            "type":"Services"
        }
    ],
    "sg:phone":"+1 405 616 5911",
    "sg:postcode":"73109",
    "sg:province":"OK",
    "sg:tags":[
        "repairing",
        "automobile",
        "general"
    ],
    "wof:name":"Conrad's Transmissions",
    "wof:placetype":"venue"
},
  "geometry": {"coordinates":[-97.516243,35.43338],"type":"Point"}
}