{
  "type": "Feature",
  "properties": {
    "iso:country":"US",
    "sg:address":"225 S Brady St",
    "sg:city":"Claremore",
    "sg:classifiers":[
        {
            "category":"Wholesale",
            "subcategory":"Non-durable Goods",
            "type":"Manufacturing & Wholesale Goods"
        }
    ],
    "sg:phone":"+1 918 341 6861",
    "sg:postcode":"74017",
    "sg:province":"OK",
    "sg:tags":[
        "advertising",
        "specialty"
    ],
    "wof:name":"Teamco International",
    "wof:placetype":"venue"
},
  "geometry": {"coordinates":[-95.631079,36.317393],"type":"Point"}
}