{
  "type": "Feature",
  "properties": {
    "addr:full":"2617 S Elm Pl Broken Arrow OK 74012",
    "addr:housenumber":"2617",
    "addr:postcode":"74012",
    "addr:street":"S Elm Pl",
    "iso:country":"US",
    "sg:address":"2617 S Elm Pl",
    "sg:city":"Broken Arrow",
    "sg:classifiers":[
        {
            "category":"Health Services",
            "subcategory":"Doctor",
            "type":"Services"
        }
    ],
    "sg:phone":"+1 918 455 9474",
    "sg:postcode":"74012",
    "sg:province":"OK",
    "sg:tags":[
        "physician",
        "surgeon"
    ],
    "wof:name":"Craig Cook MD",
    "wof:placetype":"venue"
},
  "geometry": {"coordinates":[-95.7974,36.028229],"type":"Point"}
}