{
  "type": "Feature",
  "properties": {
    "addr:full":"14190 SE 29th St Choctaw OK 73020",
    "addr:postcode":"14190;73020",
    "addr:street":"Se 29Th St",
    "iso:country":"US",
    "sg:address":"14190 SE 29th St",
    "sg:city":"Choctaw",
    "sg:classifiers":[
        {
            "category":"Building & Trades",
            "subcategory":"Construction",
            "type":"Services"
        }
    ],
    "sg:phone":"+1 405 733 2840",
    "sg:postcode":"73020",
    "sg:province":"OK",
    "sg:tags":[
        "window",
        "replacement"
    ],
    "wof:name":"Americraft Windows",
    "wof:placetype":"venue"
},
  "geometry": {"coordinates":[-97.27982799999999,35.43525],"type":"Point"}
}