{
  "type": "Feature",
  "properties": {
    "iso:country":"US",
    "sg:address":"3301 W 5th St",
    "sg:city":"Tulsa",
    "sg:classifiers":[
        {
            "category":"Professional",
            "type":"Services"
        },
        {
            "category":"Restaurant",
            "type":"Food & Drink"
        },
        {
            "category":"Fast Food",
            "type":"Food & Drink"
        }
    ],
    "sg:phone":"+1 918 584 0171",
    "sg:postcode":"74127",
    "sg:province":"OK",
    "sg:tags":[
        "style",
        "family",
        "house",
        "take",
        "caterer",
        "barbecue",
        "steak"
    ],
    "sg:website":"http://www.knottypinetulsa.com",
    "wof:name":"Knotty Pine Barbeque",
    "wof:placetype":"venue"
},
  "geometry": {"coordinates":[-96.029282,36.1507],"type":"Point"}
}