{
  "type": "Feature",
  "properties": {
    "addr:full":"840 Research Pkwy Oklahoma City OK 73104",
    "addr:housenumber":"840",
    "addr:postcode":"73104",
    "addr:street":"Research Pkwy",
    "iso:country":"US",
    "sg:address":"840 Research Pkwy",
    "sg:city":"Oklahoma City",
    "sg:classifiers":[
        {
            "category":"Health Services",
            "subcategory":"Medical Lab",
            "type":"Services"
        }
    ],
    "sg:phone":"+1 405 278 2672",
    "sg:postcode":"73104",
    "sg:province":"OK",
    "sg:tags":[
        "laboratory"
    ],
    "wof:name":"Medical Arts Laboratory",
    "wof:placetype":"venue"
},
  "geometry": {"coordinates":[-97.49917600000001,35.476961],"type":"Point"}
}