{
  "type": "Feature",
  "properties": {
    "iso:country":"US",
    "sg:address":"3100 N Kelley Ave",
    "sg:city":"Oklahoma City",
    "sg:classifiers":[
        {
            "category":"Education",
            "subcategory":"School",
            "type":"Public Place"
        }
    ],
    "sg:phone":"+1 405 424 1491",
    "sg:postcode":"73111",
    "sg:province":"OK",
    "wof:name":"Northeast High School",
    "wof:placetype":"venue"
},
  "geometry": {"coordinates":[-97.494435,35.501464],"type":"Point"}
}