{
  "type": "Feature",
  "properties": {
    "iso:country":"US",
    "sg:address":"3200 NW 39th St",
    "sg:city":"Oklahoma City",
    "sg:classifiers":[
        {
            "category":"Government",
            "subcategory":"Jail",
            "type":"Public Place"
        }
    ],
    "sg:phone":"+1 405 917 2150",
    "sg:postcode":"73112",
    "sg:province":"OK",
    "sg:tags":[
        "govt",
        "state",
        "institution"
    ],
    "wof:name":"Kate Barnard Corrections Ctr",
    "wof:placetype":"venue"
},
  "geometry": {"coordinates":[-97.573723,35.511137],"type":"Point"}
}