{
  "type": "Feature",
  "properties": {
    "iso:country":"US",
    "sg:address":"3700 W Robinson St",
    "sg:city":"Norman",
    "sg:classifiers":[
        {
            "category":"Professional",
            "subcategory":"Accounting & Tax Preparation",
            "type":"Services"
        }
    ],
    "sg:phone":"+1 405 366 0101",
    "sg:postcode":"73072",
    "sg:province":"OK",
    "wof:name":"Tax Express",
    "wof:placetype":"venue"
},
  "geometry": {"coordinates":[-97.494913,35.232762],"type":"Point"}
}