{
  "type": "Feature",
  "properties": {
    "iso:country":"US",
    "sg:address":"20 SW 10th St",
    "sg:city":"Oklahoma City",
    "sg:classifiers":[
        {
            "category":"Professional",
            "subcategory":"Advertising",
            "type":"Services"
        }
    ],
    "sg:phone":"+1 405 272 5181",
    "sg:postcode":"73109",
    "sg:province":"OK",
    "sg:tags":[
        "mailing",
        "shipping"
    ],
    "wof:name":"Beaver Express Mail Dist Ctr",
    "wof:placetype":"venue"
},
  "geometry": {"coordinates":[-97.516115,35.454891],"type":"Point"}
}