{
  "type": "Feature",
  "properties": {
    "addr:full":"910 SE 2nd St Lawton OK 73501",
    "addr:housenumber":"910",
    "addr:postcode":"73501",
    "addr:street":"Se 2Nd St",
    "iso:country":"US",
    "sg:address":"910 SE 2nd St",
    "sg:city":"Lawton",
    "sg:classifiers":[
        {
            "category":"Manufacturing",
            "subcategory":"Tools & Machinery",
            "type":"Manufacturing & Wholesale Goods"
        },
        {
            "category":"Retail",
            "subcategory":"Auto Repair",
            "type":"Services"
        }
    ],
    "sg:phone":"+1 580 248 5670",
    "sg:postcode":"73501",
    "sg:province":"OK",
    "sg:tags":[
        "compressor",
        "used",
        "parts",
        "automotive"
    ],
    "wof:name":"Ketchum John Supply Co",
    "wof:placetype":"venue"
},
  "geometry": {"coordinates":[-98.382941,34.596189],"type":"Point"}
}