{
  "type": "Feature",
  "properties": {
    "iso:country":"US",
    "sg:address":"1380 E 52nd St N",
    "sg:city":"Tulsa",
    "sg:classifiers":[
        {
            "category":"Social Services",
            "subcategory":"Child Care",
            "type":"Services"
        }
    ],
    "sg:phone":"+1 918 428 3479",
    "sg:postcode":"74126",
    "sg:province":"OK",
    "wof:name":"Juanita's Home Away From Home",
    "wof:placetype":"venue"
},
  "geometry": {"coordinates":[-95.972339,36.229721],"type":"Point"}
}