{
  "type": "Feature",
  "properties": {
    "iso:country":"US",
    "sg:address":"4491 NW 50th St",
    "sg:city":"Oklahoma City",
    "sg:classifiers":[
        {
            "category":"Shopping",
            "type":"Retail Goods"
        }
    ],
    "sg:phone":"+1 405 949 0140",
    "sg:postcode":"73112",
    "sg:province":"OK",
    "sg:tags":[
        "mexican"
    ],
    "wof:name":"El Sombrero Mexican Restaurant",
    "wof:placetype":"venue"
},
  "geometry": {"coordinates":[-97.597067,35.522392],"type":"Point"}
}