{
  "type": "Feature",
  "properties": {
    "iso:country":"US",
    "sg:address":"105 S Bryant Ave",
    "sg:city":"Edmond",
    "sg:classifiers":[
        {
            "category":"Professional",
            "subcategory":"Research",
            "type":"Services"
        }
    ],
    "sg:phone":"+1 405 341 4913",
    "sg:postcode":"73034",
    "sg:province":"OK",
    "wof:name":"Bariatric Institute Oklahoma",
    "wof:placetype":"venue"
},
  "geometry": {"coordinates":[-97.46051,35.653572],"type":"Point"}
}