{
  "type": "Feature",
  "properties": {
    "iso:country":"US",
    "sg:address":"100 SW 4th St",
    "sg:city":"Oklahoma City",
    "sg:classifiers":[
        {
            "category":"Government",
            "subcategory":"Fire Station",
            "type":"Public Place"
        }
    ],
    "sg:phone":"+1 405 239 7613",
    "sg:postcode":"73109",
    "sg:province":"OK",
    "sg:tags":[
        "protection",
        "provides"
    ],
    "wof:name":"Fire Station 4",
    "wof:placetype":"venue"
},
  "geometry": {"coordinates":[-97.516234,35.461102],"type":"Point"}
}