{
  "type": "Feature",
  "properties": {
    "iso:country":"US",
    "sg:address":"424 Henley St",
    "sg:city":"Miami",
    "sg:classifiers":[
        {
            "category":"Manufacturing",
            "subcategory":"Printing",
            "type":"Manufacturing & Wholesale Goods"
        }
    ],
    "sg:phone":"+1 918 542 1070",
    "sg:postcode":"74354",
    "sg:province":"OK",
    "sg:tags":[
        "a",
        "commercial",
        "design",
        "mfg"
    ],
    "wof:name":"Misaco",
    "wof:placetype":"venue"
},
  "geometry": {"coordinates":[-94.85401899999999,36.870835],"type":"Point"}
}