{
  "type": "Feature",
  "properties": {
    "addr:full":"400 S Grand Ave Cherokee OK 73728",
    "addr:housenumber":"400",
    "addr:postcode":"73728",
    "addr:street":"S Grand Ave",
    "iso:country":"US",
    "sg:address":"400 S Grand Ave",
    "sg:city":"Cherokee",
    "sg:classifiers":[
        {
            "category":"Organizations",
            "subcategory":"Religious Organization",
            "type":"Services"
        }
    ],
    "sg:phone":"+1 580 596 2400",
    "sg:postcode":"73728",
    "sg:province":"OK",
    "wof:name":"First United Methodist Church",
    "wof:placetype":"venue"
},
  "geometry": {"coordinates":[-98.35702499999999,36.754678],"type":"Point"}
}