{
  "type": "Feature",
  "properties": {
    "iso:country":"US",
    "sg:address":"120 W California Ave",
    "sg:city":"Walters",
    "sg:classifiers":[
        {
            "category":"Personal",
            "subcategory":"Beauty Salon",
            "type":"Services"
        }
    ],
    "sg:phone":"+1 580 875 3445",
    "sg:postcode":"73572",
    "sg:province":"OK",
    "sg:tags":[
        "shop",
        "merchandise"
    ],
    "wof:name":"Lila's Headlines",
    "wof:placetype":"venue"
},
  "geometry": {"coordinates":[-98.309407,34.356816],"type":"Point"}
}