{
  "type": "Feature",
  "properties": {
    "iso:country":"US",
    "sg:address":"4722 Plainview Rd",
    "sg:city":"Ardmore",
    "sg:classifiers":[
        {
            "category":"Farming",
            "subcategory":"Livestock Farm",
            "type":"Manufacturing & Wholesale Goods"
        }
    ],
    "sg:phone":"+1 580 226 3831",
    "sg:postcode":"73401",
    "sg:province":"OK",
    "sg:tags":[
        "beef",
        "feedlot",
        "cattle"
    ],
    "wof:name":"William Hoben",
    "wof:placetype":"venue"
},
  "geometry": {"coordinates":[-97.177946,34.128965],"type":"Point"}
}