{
  "type": "Feature",
  "properties": {
    "iso:country":"US",
    "sg:address":"1501 N Hwy 88",
    "sg:city":"Claremore",
    "sg:classifiers":[
        {
            "category":"Restaurant",
            "type":"Food & Drink"
        }
    ],
    "sg:phone":"+1 918 342 8988",
    "sg:postcode":"74017",
    "sg:province":"OK",
    "wof:name":"Okie's Steak House",
    "wof:placetype":"venue"
},
  "geometry": {"coordinates":[-95.63261,36.32619],"type":"Point"}
}