{
  "type": "Feature",
  "properties": {
    "iso:country":"US",
    "sg:address":"3441 E Archer St",
    "sg:city":"Tulsa",
    "sg:classifiers":[
        {
            "category":"Education",
            "subcategory":"School",
            "type":"Public Place"
        }
    ],
    "sg:phone":"+1 918 641 1800",
    "sg:postcode":"74115",
    "sg:province":"OK",
    "sg:tags":[
        "elementary"
    ],
    "sg:website":"www.tulsaschools.org",
    "wof:name":"Sequoyah Elementary School",
    "wof:placetype":"venue"
},
  "geometry": {"coordinates":[-95.93844,36.162675],"type":"Point"}
}