{
  "type": "Feature",
  "properties": {
    "iso:country":"US",
    "sg:address":"1708 E 2nd St",
    "sg:city":"Edmond",
    "sg:classifiers":[
        {
            "category":"Restaurant",
            "type":"Food & Drink"
        }
    ],
    "sg:phone":"+1 405 341 3579",
    "sg:postcode":"73034",
    "sg:province":"OK",
    "sg:tags":[
        "eating"
    ],
    "wof:name":"Marbo Chinese Restaurant",
    "wof:placetype":"venue"
},
  "geometry": {"coordinates":[-97.45874499999999,35.652662],"type":"Point"}
}