{
  "type": "Feature",
  "properties": {
    "addr:full":"8268 NW Expy Oklahoma City OK 73162",
    "addr:housenumber":"8268",
    "addr:postcode":"73162",
    "addr:street":"Nw Expy",
    "iso:country":"US",
    "sg:address":"8268 NW Expy",
    "sg:city":"Oklahoma City",
    "sg:classifiers":[
        {
            "category":"Restaurant",
            "type":"Food & Drink"
        }
    ],
    "sg:phone":"+1 405 728 2144",
    "sg:postcode":"73162",
    "sg:province":"OK",
    "wof:name":"Santa Fe Cattle Co",
    "wof:placetype":"venue"
},
  "geometry": {"coordinates":[-97.66140799999999,35.567868],"type":"Point"}
}