{
  "type": "Feature",
  "properties": {
    "iso:country":"US",
    "sg:address":"3126 NE 122nd St",
    "sg:city":"Edmond",
    "sg:classifiers":[
        {
            "category":"Insurance",
            "subcategory":"Insurance Agent",
            "type":"Services"
        }
    ],
    "sg:phone":"+1 405 340 0393",
    "sg:postcode":"73013",
    "sg:province":"OK",
    "wof:name":"Freeman Financial Group",
    "wof:placetype":"venue"
},
  "geometry": {"coordinates":[-97.456808,35.594503],"type":"Point"}
}