{
  "type": "Feature",
  "properties": {
    "addr:full":"8 SW 3rd St Tuttle OK 73089",
    "addr:housenumber":"8",
    "addr:postcode":"73089",
    "addr:street":"Sw 3Rd St",
    "iso:country":"US",
    "sg:address":"8 SW 3rd St",
    "sg:city":"Tuttle",
    "sg:classifiers":[
        {
            "category":"Manufacturing",
            "subcategory":"Printing",
            "type":"Manufacturing & Wholesale Goods"
        }
    ],
    "sg:phone":"+1 405 381 3173",
    "sg:postcode":"73089",
    "sg:province":"OK",
    "sg:tags":[
        "newspaper"
    ],
    "wof:name":"Tuttle Times",
    "wof:placetype":"venue"
},
  "geometry": {"coordinates":[-97.81591,35.290748],"type":"Point"}
}