{
  "type": "Feature",
  "properties": {
    "iso:country":"US",
    "sg:address":"145 W Main St",
    "sg:city":"Durant",
    "sg:classifiers":[
        {
            "category":"Personal",
            "subcategory":"Beauty Salon",
            "type":"Services"
        }
    ],
    "sg:phone":"+1 580 924 6200",
    "sg:postcode":"74701",
    "sg:province":"OK",
    "sg:tags":[
        "shop"
    ],
    "wof:name":"Salon WORX",
    "wof:placetype":"venue"
},
  "geometry": {"coordinates":[-96.377147,33.990825],"type":"Point"}
}