{
  "type": "Feature",
  "properties": {
    "iso:country":"US",
    "sg:address":"1906 W Broadway Ave",
    "sg:city":"Sulphur",
    "sg:classifiers":[
        {
            "category":"Restaurant",
            "type":"Food & Drink"
        }
    ],
    "sg:phone":"+1 580 622 6235",
    "sg:postcode":"73086",
    "sg:province":"OK",
    "wof:name":"KFC",
    "wof:placetype":"venue"
},
  "geometry": {"coordinates":[-96.993694,34.506385],"type":"Point"}
}