{
  "type": "Feature",
  "properties": {
    "addr:full":"19123 E Admiral Pl Catoosa OK 74015",
    "addr:housenumber":"19123 e",
    "addr:postcode":"74015",
    "addr:street":"Admiral Pl",
    "iso:country":"US",
    "sg:address":"19123 E Admiral Pl",
    "sg:city":"Catoosa",
    "sg:classifiers":[
        {
            "category":"Retail",
            "subcategory":"Auto Rental",
            "type":"Services"
        },
        {
            "category":"Retail",
            "subcategory":"Storage",
            "type":"Services"
        }
    ],
    "sg:phone":"+1 918 272 0190",
    "sg:postcode":"74015",
    "sg:province":"OK",
    "sg:tags":[
        "renting",
        "leasing",
        "car",
        "household",
        "commercial",
        "truck",
        "trailer"
    ],
    "wof:name":"U-Haul Co",
    "wof:placetype":"venue"
},
  "geometry": {"coordinates":[-95.760896,36.160586],"type":"Point"}
}