{
  "type": "Feature",
  "properties": {
    "iso:country":"US",
    "sg:address":"19105 S Hwy 66",
    "sg:city":"Claremore",
    "sg:classifiers":[
        {
            "category":"Autos & Motor Vehicles",
            "subcategory":"Automobile Sales",
            "type":"Retail Goods"
        }
    ],
    "sg:phone":"+1 918 342 5591",
    "sg:postcode":"74017",
    "sg:province":"OK",
    "sg:tags":[
        "truck"
    ],
    "wof:name":"Grant Trucks & Equipment Sales",
    "wof:placetype":"venue"
},
  "geometry": {"coordinates":[-95.596868,36.341058],"type":"Point"}
}