{
  "type": "Feature",
  "properties": {
    "iso:country":"US",
    "sg:address":"2424 W 45th Ct",
    "sg:city":"Tulsa",
    "sg:classifiers":[
        {
            "category":"Professional",
            "subcategory":"Detective & Security Services",
            "type":"Services"
        }
    ],
    "sg:phone":"+1 918 446 3900",
    "sg:postcode":"74107",
    "sg:province":"OK",
    "sg:tags":[
        "guard",
        "patrol"
    ],
    "wof:name":"Harper's Protective Svc",
    "wof:placetype":"venue"
},
  "geometry": {"coordinates":[-96.020205,36.098248],"type":"Point"}
}