{
  "type": "Feature",
  "properties": {
    "iso:country":"US",
    "sg:address":"1511 Exchange Ave",
    "sg:city":"Oklahoma City",
    "sg:classifiers":[
        {
            "category":"Building & Trades",
            "subcategory":"Electrical",
            "type":"Services"
        }
    ],
    "sg:phone":"+1 405 228 3296",
    "sg:postcode":"73108",
    "sg:province":"OK",
    "sg:tags":[
        "electric",
        "contractor"
    ],
    "wof:name":"Capital Electric Contractors",
    "wof:placetype":"venue"
},
  "geometry": {"coordinates":[-97.54201999999999,35.455654],"type":"Point"}
}