{
  "type": "Feature",
  "properties": {
    "iso:country":"US",
    "sg:address":"3301 S 54th St W",
    "sg:city":"Muskogee",
    "sg:classifiers":[
        {
            "category":"Building & Trades",
            "subcategory":"Construction",
            "type":"Services"
        }
    ],
    "sg:phone":"+1 918 683 1784",
    "sg:postcode":"74401",
    "sg:province":"OK",
    "sg:tags":[
        "nonresidential"
    ],
    "wof:name":"Perkins Family Restaurant",
    "wof:placetype":"venue"
},
  "geometry": {"coordinates":[-95.42948800000001,35.716766],"type":"Point"}
}