{
  "type": "Feature",
  "properties": {
    "iso:country":"US",
    "sg:address":"9200 S Grace Dr",
    "sg:city":"Oklahoma City",
    "sg:classifiers":[
        {
            "category":"Building & Trades",
            "subcategory":"Landscaping Services",
            "type":"Services"
        }
    ],
    "sg:phone":"+1 405 691 6263",
    "sg:postcode":"73159",
    "sg:province":"OK",
    "sg:tags":[
        "tree"
    ],
    "wof:name":"Countryside Pest Control",
    "wof:placetype":"venue"
},
  "geometry": {"coordinates":[-97.540007,35.376398],"type":"Point"}
}