{
  "type": "Feature",
  "properties": {
    "addr:full":"800 Share Dr Alva OK 73717",
    "addr:housenumber":"800",
    "addr:postcode":"73717",
    "addr:street":"Share Dr",
    "iso:country":"US",
    "sg:address":"800 Share Dr",
    "sg:city":"Alva",
    "sg:classifiers":[
        {
            "category":"Health Services",
            "subcategory":"Hospital",
            "type":"Services"
        }
    ],
    "sg:phone":"+1 580 327 2800",
    "sg:postcode":"73717",
    "sg:province":"OK",
    "wof:name":"Share Medical Ctr",
    "wof:placetype":"venue"
},
  "geometry": {"coordinates":[-98.67219299999999,36.786977],"type":"Point"}
}