{
  "type": "Feature",
  "properties": {
    "addr:full":"177 W 15th St Edmond OK 73013",
    "addr:housenumber":"177",
    "addr:postcode":"73013",
    "addr:street":"W 15Th St",
    "iso:country":"US",
    "sg:address":"177 W 15th St",
    "sg:city":"Edmond",
    "sg:classifiers":[
        {
            "category":"Shopping",
            "subcategory":"Clothing, Apparel, & Fashions",
            "type":"Retail Goods"
        }
    ],
    "sg:phone":"+1 405 340 4546",
    "sg:postcode":"73013",
    "sg:province":"OK",
    "wof:name":"Eves",
    "wof:placetype":"venue"
},
  "geometry": {"coordinates":[-97.488364,35.638352],"type":"Point"}
}