{
  "type": "Feature",
  "properties": {
    "addr:full":"8004 S Darlington Ave Tulsa OK 74136",
    "addr:housenumber":"8004",
    "addr:postcode":"74136",
    "addr:street":"S Darlington Ave",
    "iso:country":"US",
    "sg:address":"8004 S Darlington Ave",
    "sg:city":"Tulsa",
    "sg:classifiers":[
        {
            "category":"Health Services",
            "subcategory":"Medical Lab",
            "type":"Services"
        }
    ],
    "sg:phone":"+1 918 524 0000",
    "sg:postcode":"74136",
    "sg:province":"OK",
    "sg:tags":[
        "laboratory"
    ],
    "wof:name":"John D Fisher PC",
    "wof:placetype":"venue"
},
  "geometry": {"coordinates":[-95.917371,36.047253],"type":"Point"}
}