{
  "type": "Feature",
  "properties": {
    "addr:full":"910 S Madison Blvd Bartlesville OK 74006",
    "addr:housenumber":"910",
    "addr:postcode":"74006",
    "addr:street":"S Madison Blvd",
    "iso:country":"US",
    "sg:address":"910 S Madison Blvd",
    "sg:city":"Bartlesville",
    "sg:classifiers":[
        {
            "category":"Retail",
            "subcategory":"Laundry & Dry Cleaning",
            "type":"Services"
        }
    ],
    "sg:phone":"+1 918 333 6097",
    "sg:postcode":"74006",
    "sg:province":"OK",
    "sg:tags":[
        "drycleaning",
        "plant",
        "cleaners"
    ],
    "wof:name":"Archers Cleaners",
    "wof:placetype":"venue"
},
  "geometry": {"coordinates":[-95.91717199999999,36.742267],"type":"Point"}
}