{
  "type": "Feature",
  "properties": {
    "addr:full":"3501 NW 63rd St Oklahoma City OK 73116",
    "addr:housenumber":"3501",
    "addr:postcode":"73116",
    "addr:street":"Nw 63Rd St",
    "iso:country":"US",
    "sg:address":"3501 NW 63rd St",
    "sg:city":"Oklahoma City",
    "sg:classifiers":[
        {
            "category":"Manufacturing",
            "subcategory":"Metals",
            "type":"Manufacturing & Wholesale Goods"
        },
        {
            "category":"Building & Trades",
            "subcategory":"Construction",
            "type":"Services"
        }
    ],
    "sg:phone":"+1 405 607 4668",
    "sg:postcode":"73116",
    "sg:province":"OK",
    "sg:tags":[
        "contractor"
    ],
    "wof:name":"Metal Roof Contractors Inc",
    "wof:placetype":"venue"
},
  "geometry": {"coordinates":[-97.57969799999999,35.536832],"type":"Point"}
}