{
  "type": "Feature",
  "properties": {
    "iso:country":"US",
    "sg:address":"2601 Lindsey Ct",
    "sg:city":"Stillwater",
    "sg:classifiers":[
        {
            "category":"Professional",
            "type":"Services"
        }
    ],
    "sg:phone":"+1 405 377 3772",
    "sg:postcode":"74074",
    "sg:province":"OK",
    "wof:name":"Economics Evalation Service",
    "wof:placetype":"venue"
},
  "geometry": {"coordinates":[-97.13637199999999,36.093332],"type":"Point"}
}