{
  "type": "Feature",
  "properties": {
    "addr:full":"300 N Denver Ave Tulsa OK 74103",
    "addr:housenumber":"300",
    "addr:postcode":"74103",
    "addr:street":"N Denver Ave",
    "iso:country":"US",
    "sg:address":"300 N Denver Ave",
    "sg:city":"Tulsa",
    "sg:classifiers":[
        {
            "category":"Government",
            "subcategory":"Police Station",
            "type":"Public Place"
        }
    ],
    "sg:phone":"+1 918 585 9041",
    "sg:postcode":"74103",
    "sg:province":"OK",
    "sg:tags":[
        "department"
    ],
    "wof:name":"Tulsa County Sheriff Office",
    "wof:placetype":"venue"
},
  "geometry": {"coordinates":[-95.997674,36.157914],"type":"Point"}
}