{
  "type": "Feature",
  "properties": {
    "addr:full":"1007 Broadway Marlow OK 73055",
    "addr:housenumber":"1007",
    "addr:postcode":"73055",
    "addr:street":"Broadway",
    "iso:country":"US",
    "sg:address":"1007 Broadway",
    "sg:city":"Marlow",
    "sg:classifiers":[
        {
            "category":"Travel",
            "subcategory":"Hotels & Motels",
            "type":"Entertainment"
        }
    ],
    "sg:phone":"+1 580 658 5441",
    "sg:postcode":"73055",
    "sg:province":"OK",
    "wof:name":"Town N Country Motel",
    "wof:placetype":"venue"
},
  "geometry": {"coordinates":[-97.95844099999999,34.636542],"type":"Point"}
}