{
  "type": "Feature",
  "properties": {
    "iso:country":"US",
    "sg:address":"3513 N Geraldine Ave",
    "sg:city":"Oklahoma City",
    "sg:classifiers":[
        {
            "category":"Organizations",
            "subcategory":"Religious Organization",
            "type":"Services"
        }
    ],
    "sg:phone":"+1 405 946 6626",
    "sg:postcode":"73112",
    "sg:province":"OK",
    "sg:tags":[
        "church"
    ],
    "wof:name":"New Hope Worship Ctr",
    "wof:placetype":"venue"
},
  "geometry": {"coordinates":[-97.597037,35.507696],"type":"Point"}
}