{
  "type": "Feature",
  "properties": {
    "iso:country":"US",
    "sg:address":"2300 NW 23rd St",
    "sg:city":"Oklahoma City",
    "sg:classifiers":[
        {
            "category":"Personal",
            "subcategory":"Barber",
            "type":"Services"
        }
    ],
    "sg:phone":"+1 405 946 3424",
    "sg:postcode":"73107",
    "sg:province":"OK",
    "wof:name":"Shepherd Mall Style Shop",
    "wof:placetype":"venue"
},
  "geometry": {"coordinates":[-97.553823,35.493234],"type":"Point"}
}