{
  "type": "Feature",
  "properties": {
    "iso:country":"US",
    "sg:address":"3433 S 133rd East Ave",
    "sg:city":"Tulsa",
    "sg:classifiers":[
        {
            "category":"Education",
            "subcategory":"School",
            "type":"Public Place"
        }
    ],
    "sg:phone":"+1 918 663 3646",
    "sg:postcode":"74134",
    "sg:province":"OK",
    "wof:name":"Schools",
    "wof:placetype":"venue"
},
  "geometry": {"coordinates":[-95.8284,36.1133],"type":"Point"}
}