{
  "type": "Feature",
  "properties": {
    "iso:country":"US",
    "sg:address":"10123 E 46th Pl",
    "sg:city":"Tulsa",
    "sg:classifiers":[
        {
            "category":"Building & Trades",
            "subcategory":"Plumbing",
            "type":"Services"
        }
    ],
    "sg:phone":"+1 918 627 3415",
    "sg:postcode":"74146",
    "sg:province":"OK",
    "sg:tags":[
        "lawn",
        "contractor",
        "installation",
        "system",
        "sprinkler"
    ],
    "wof:name":"Aqua Weather-Matic Sprinkler",
    "wof:placetype":"venue"
},
  "geometry": {"coordinates":[-95.862863,36.096809],"type":"Point"}
}