{
  "type": "Feature",
  "properties": {
    "iso:country":"US",
    "sg:address":"1000 S Pine St",
    "sg:city":"Ponca City",
    "sg:classifiers":[
        {
            "category":"Banks & Credit Unions",
            "subcategory":"Investment Brokerage",
            "type":"Services"
        }
    ],
    "sg:phone":"+1 580 762 0003",
    "sg:postcode":"74601",
    "sg:province":"OK",
    "sg:tags":[
        "stock",
        "bond"
    ],
    "wof:name":"Smith Barney",
    "wof:placetype":"venue"
},
  "geometry": {"coordinates":[-97.08699900000001,36.694124],"type":"Point"}
}