{
  "type": "Feature",
  "properties": {
    "addr:full":"3620 E 49th Pl Tulsa OK 74135",
    "addr:housenumber":"3620",
    "addr:postcode":"74135",
    "addr:street":"E 49Th Pl",
    "iso:country":"US",
    "sg:address":"3620 E 49th Pl",
    "sg:city":"Tulsa",
    "sg:classifiers":[
        {
            "category":"Building & Trades",
            "subcategory":"Construction",
            "type":"Services"
        }
    ],
    "sg:phone":"+1 918 749 6575",
    "sg:postcode":"74135",
    "sg:province":"OK",
    "sg:tags":[
        "contractor"
    ],
    "wof:name":"John H Hinds",
    "wof:placetype":"venue"
},
  "geometry": {"coordinates":[-95.932672,36.09167],"type":"Point"}
}