{
  "type": "Feature",
  "properties": {
    "iso:country":"US",
    "sg:address":"1641 E 56th St N",
    "sg:city":"Tulsa",
    "sg:classifiers":[
        {
            "category":"Building & Trades",
            "subcategory":"Construction",
            "type":"Services"
        }
    ],
    "sg:phone":"+1 918 425 6863",
    "sg:postcode":"74126",
    "sg:province":"OK",
    "sg:tags":[
        "excavation",
        "contractor"
    ],
    "wof:name":"Morrow Nat Excvtg & Con Work",
    "wof:placetype":"venue"
},
  "geometry": {"coordinates":[-95.968457,36.235152],"type":"Point"}
}