{
  "type": "Feature",
  "properties": {
    "iso:country":"US",
    "sg:address":"118 W Olive St",
    "sg:city":"Stilwell",
    "sg:classifiers":[
        {
            "category":"Insurance",
            "subcategory":"Hazard Insurance",
            "type":"Services"
        },
        {
            "category":"Insurance",
            "subcategory":"Insurance Agent",
            "type":"Services"
        },
        {
            "category":"Insurance",
            "subcategory":"Life Insurance",
            "type":"Services"
        },
        {
            "category":"Insurance",
            "subcategory":"Title Insurance",
            "type":"Services"
        }
    ],
    "sg:phone":"+1 918 696 3371",
    "sg:postcode":"74960",
    "sg:province":"OK",
    "sg:tags":[
        "auto",
        "commercial",
        "business",
        "homeowner"
    ],
    "sg:website":"http://www.farmersagent.com/ngarrettfarrier/",
    "wof:name":"Nancy Garrett - Farmers Insurance",
    "wof:placetype":"venue"
},
  "geometry": {"coordinates":[-94.627231,35.815412],"type":"Point"}
}