{
  "type": "Feature",
  "properties": {
    "iso:country":"US",
    "sg:address":"7500 E 21st St",
    "sg:city":"Tulsa",
    "sg:classifiers":[
        {
            "category":"Organizations",
            "subcategory":"Religious Organization",
            "type":"Services"
        }
    ],
    "sg:phone":"+1 918 627 5100",
    "sg:postcode":"74129",
    "sg:province":"OK",
    "sg:tags":[
        "church"
    ],
    "sg:website":"www.tulsafaith.com",
    "wof:name":"Faith Assembly Of God",
    "wof:placetype":"venue"
},
  "geometry": {"coordinates":[-95.892755,36.133461],"type":"Point"}
}