{
  "type": "Feature",
  "properties": {
    "iso:country":"US",
    "sg:address":"123 N Walnut St",
    "sg:city":"Holdenville",
    "sg:classifiers":[
        {
            "category":"Social Services",
            "subcategory":"Child Care",
            "type":"Services"
        }
    ],
    "sg:phone":"+1 405 379 7674",
    "sg:postcode":"74848",
    "sg:province":"OK",
    "wof:name":"Next Generation Daycare",
    "wof:placetype":"venue"
},
  "geometry": {"coordinates":[-96.405226,35.088168],"type":"Point"}
}