{
  "type": "Feature",
  "properties": {
    "iso:country":"US",
    "sg:address":"1824 Houston St",
    "sg:city":"Muskogee",
    "sg:classifiers":[
        {
            "category":"Personal",
            "subcategory":"Beauty Salon",
            "type":"Services"
        }
    ],
    "sg:phone":"+1 918 681 2887",
    "sg:postcode":"74403",
    "sg:province":"OK",
    "wof:name":"Studio III & Day Spa",
    "wof:placetype":"venue"
},
  "geometry": {"coordinates":[-95.34258699999999,35.749167],"type":"Point"}
}