{
  "type": "Feature",
  "properties": {
    "addr:full":"1219 N Classen Blvd Oklahoma City OK 73106",
    "addr:housenumber":"1219",
    "addr:postcode":"73106",
    "addr:street":"N Classen Blvd",
    "iso:country":"US",
    "sg:address":"1219 N Classen Blvd",
    "sg:city":"Oklahoma City",
    "sg:classifiers":[
        {
            "category":"Wholesale",
            "subcategory":"Computers",
            "type":"Manufacturing & Wholesale Goods"
        }
    ],
    "sg:phone":"+1 405 528 5270",
    "sg:postcode":"73106",
    "sg:province":"OK",
    "sg:tags":[
        "equipment"
    ],
    "wof:name":"Cherokee Data Cmpt Parts Svcs",
    "wof:placetype":"venue"
},
  "geometry": {"coordinates":[-97.52873099999999,35.480563],"type":"Point"}
}