{
  "type": "Feature",
  "properties": {
    "iso:country":"US",
    "sg:address":"1521 S Denver Ave",
    "sg:city":"Tulsa",
    "sg:classifiers":[
        {
            "category":"Insurance",
            "subcategory":"Hazard Insurance",
            "type":"Services"
        }
    ],
    "sg:phone":"+1 918 583 2977",
    "sg:postcode":"74119",
    "sg:province":"OK",
    "sg:tags":[
        "bond"
    ],
    "wof:name":"Dia Nuevo Fianzas",
    "wof:placetype":"venue"
},
  "geometry": {"coordinates":[-95.9923,36.139907],"type":"Point"}
}