{
  "type": "Feature",
  "properties": {
    "addr:full":"9 Akron Ave Ardmore OK 73401",
    "addr:housenumber":"9",
    "addr:postcode":"73401",
    "addr:street":"Akron Ave",
    "iso:country":"US",
    "sg:address":"9 Akron Ave",
    "sg:city":"Ardmore",
    "sg:classifiers":[
        {
            "category":"Autos & Motor Vehicles",
            "subcategory":"Automobile Sales",
            "type":"Retail Goods"
        }
    ],
    "sg:phone":"+1 580 226 5909",
    "sg:postcode":"73401",
    "sg:province":"OK",
    "sg:tags":[
        "car",
        "dealer"
    ],
    "wof:name":"W & J Auto Sales",
    "wof:placetype":"venue"
},
  "geometry": {"coordinates":[-97.115951,34.200688],"type":"Point"}
}