{
  "type": "Feature",
  "properties": {
    "iso:country":"US",
    "sg:address":"2001 NW 178th St",
    "sg:city":"Edmond",
    "sg:classifiers":[
        {
            "category":"Organizations",
            "subcategory":"Religious Organization",
            "type":"Services"
        }
    ],
    "sg:phone":"+1 405 680 5433",
    "sg:postcode":"73012",
    "sg:province":"OK",
    "wof:name":"Life Covenant Church",
    "wof:placetype":"venue"
},
  "geometry": {"coordinates":[-97.54626399999999,35.653034],"type":"Point"}
}