{
  "type": "Feature",
  "properties": {
    "iso:country":"US",
    "sg:address":"319 SW 25th St",
    "sg:city":"Oklahoma City",
    "sg:classifiers":[
        {
            "category":"Social Services",
            "type":"Services"
        }
    ],
    "sg:phone":"+1 405 232 0199",
    "sg:postcode":"73109",
    "sg:province":"OK",
    "sg:tags":[
        "organization",
        "welfare"
    ],
    "sg:website":"www.caaofokc.org",
    "wof:name":"Community Action Agency",
    "wof:placetype":"venue"
},
  "geometry": {"coordinates":[-97.519577,35.439492],"type":"Point"}
}