{
  "type": "Feature",
  "properties": {
    "iso:country":"US",
    "sg:address":"13337 NE 150th St",
    "sg:city":"Jones",
    "sg:classifiers":[
        {
            "category":"Retail",
            "subcategory":"Repair Shop",
            "type":"Services"
        }
    ],
    "sg:phone":"+1 405 396 2484",
    "sg:postcode":"73049",
    "sg:province":"OK",
    "sg:tags":[
        "electrical"
    ],
    "wof:name":"Parsons Appliance Repair",
    "wof:placetype":"venue"
},
  "geometry": {"coordinates":[-97.294856,35.623649],"type":"Point"}
}