{
  "type": "Feature",
  "properties": {
    "addr:full":"7917 New Sapulpa Rd Tulsa OK 74131",
    "addr:housenumber":"7917",
    "addr:postcode":"74131",
    "addr:street":"New Sapulpa Rd",
    "iso:country":"US",
    "sg:address":"7917 New Sapulpa Rd",
    "sg:city":"Tulsa",
    "sg:classifiers":[
        {
            "category":"Shopping",
            "subcategory":"Stationery & Office Supplies",
            "type":"Retail Goods"
        },
        {
            "category":"Shopping",
            "subcategory":"Gifts & Souvenirs",
            "type":"Retail Goods"
        }
    ],
    "sg:phone":"+1 918 227 4446",
    "sg:postcode":"74131",
    "sg:province":"OK",
    "sg:tags":[
        "shop",
        "store"
    ],
    "wof:name":"Christie's Toy Box",
    "wof:placetype":"venue"
},
  "geometry": {"coordinates":[-96.07658499999999,36.049638],"type":"Point"}
}