{
  "type": "Feature",
  "properties": {
    "iso:country":"US",
    "sg:address":"2609 Hidden Valley Rd",
    "sg:city":"Edmond",
    "sg:classifiers":[
        {
            "category":"Shopping",
            "subcategory":"Gifts & Souvenirs",
            "type":"Retail Goods"
        }
    ],
    "sg:phone":"+1 405 715 0416",
    "sg:postcode":"73013",
    "sg:province":"OK",
    "wof:name":"Elements New Age Gift Shoppe",
    "wof:placetype":"venue"
},
  "geometry": {"coordinates":[-97.468206,35.627866],"type":"Point"}
}