{
  "type": "Feature",
  "properties": {
    "iso:country":"US",
    "sg:address":"3718 N Portland Ave",
    "sg:city":"Oklahoma City",
    "sg:classifiers":[
        {
            "category":"Health Services",
            "subcategory":"Nursing And Care Facility",
            "type":"Services"
        }
    ],
    "sg:phone":"+1 405 942 1014",
    "sg:postcode":"73112",
    "sg:province":"OK",
    "sg:tags":[
        "home",
        "convalescent"
    ],
    "wof:name":"North Winds Living Ctr",
    "wof:placetype":"venue"
},
  "geometry": {"coordinates":[-97.58340699999999,35.508952],"type":"Point"}
}