{
  "type": "Feature",
  "properties": {
    "iso:country":"US",
    "sg:address":"100 6th St",
    "sg:city":"Tupelo",
    "sg:classifiers":[
        {
            "category":"Food & Beverages",
            "subcategory":"Groceries & Convenience Stores",
            "type":"Retail Goods"
        }
    ],
    "sg:phone":"+1 580 845 2478",
    "sg:postcode":"74546",
    "sg:province":"OK",
    "wof:name":"Tupelo Super Stop",
    "wof:placetype":"venue"
},
  "geometry": {"coordinates":[-95.585188,34.848527],"type":"Point"}
}