{
  "type": "Feature",
  "properties": {
    "iso:country":"US",
    "sg:address":"4619 W University Blvd",
    "sg:city":"Durant",
    "sg:classifiers":[
        {
            "category":"Building & Trades",
            "subcategory":"Construction",
            "type":"Services"
        }
    ],
    "sg:phone":"+1 580 924 3037",
    "sg:postcode":"74701",
    "sg:province":"OK",
    "sg:tags":[
        "carpentry",
        "contractor"
    ],
    "wof:name":"Lindley Carpentry & Home Repr",
    "wof:placetype":"venue"
},
  "geometry": {"coordinates":[-96.422325,34.004853],"type":"Point"}
}