{
  "type": "Feature",
  "properties": {
    "addr:full":"11 N Macarthur Blvd Oklahoma City OK 73127",
    "addr:housenumber":"11",
    "addr:postcode":"73127",
    "addr:street":"N Macarthur Blvd",
    "iso:country":"US",
    "sg:address":"11 N Macarthur Blvd",
    "sg:city":"Oklahoma City",
    "sg:classifiers":[
        {
            "category":"Wholesale",
            "subcategory":"Auto Parts",
            "type":"Manufacturing & Wholesale Goods"
        }
    ],
    "sg:phone":"+1 405 787 4075",
    "sg:postcode":"73127",
    "sg:province":"OK",
    "sg:tags":[
        "automobile",
        "supply"
    ],
    "wof:name":"City Jobber Sales",
    "wof:placetype":"venue"
},
  "geometry": {"coordinates":[-97.61898100000001,35.468451],"type":"Point"}
}