{
  "type": "Feature",
  "properties": {
    "iso:country":"US",
    "sg:address":"4301 S I- 35 Svc Rd",
    "sg:city":"Oklahoma City",
    "sg:classifiers":[
        {
            "category":"Wholesale",
            "subcategory":"Chemicals & Plastics",
            "type":"Manufacturing & Wholesale Goods"
        }
    ],
    "sg:phone":"+1 405 672 2030",
    "sg:postcode":"73129",
    "sg:province":"OK",
    "wof:name":"ICP",
    "wof:placetype":"venue"
},
  "geometry": {"coordinates":[-97.488031,35.422572],"type":"Point"}
}