{
  "type": "Feature",
  "properties": {
    "iso:country":"US",
    "sg:address":"8328 Bigwood Dr",
    "sg:city":"Oklahoma City",
    "sg:classifiers":[
        {
            "category":"Shopping",
            "subcategory":"Gifts & Souvenirs",
            "type":"Retail Goods"
        }
    ],
    "sg:phone":"+1 405 412 9443",
    "sg:postcode":"73135",
    "sg:province":"OK",
    "wof:name":"Audreys Hidden Treasures Inc",
    "wof:placetype":"venue"
},
  "geometry": {"coordinates":[-97.424172,35.381486],"type":"Point"}
}