{
  "type": "Feature",
  "properties": {
    "iso:country":"US",
    "sg:address":"1105 N 21st St",
    "sg:city":"Duncan",
    "sg:classifiers":[
        {
            "category":"Building & Trades",
            "subcategory":"Electrical",
            "type":"Services"
        }
    ],
    "sg:phone":"+1 580 252 9508",
    "sg:postcode":"73533",
    "sg:province":"OK",
    "sg:tags":[
        "electrical",
        "contractor"
    ],
    "wof:name":"Taurus Electrical Service",
    "wof:placetype":"venue"
},
  "geometry": {"coordinates":[-97.975222,34.515688],"type":"Point"}
}