{
  "type": "Feature",
  "properties": {
    "iso:country":"US",
    "sg:address":"3348 S Santa Fe Ave",
    "sg:city":"Tulsa",
    "sg:classifiers":[
        {
            "category":"Retail",
            "subcategory":"Auto Repair",
            "type":"Services"
        }
    ],
    "sg:phone":"+1 918 446 4500",
    "sg:postcode":"74107",
    "sg:province":"OK",
    "sg:tags":[
        "body"
    ],
    "wof:name":"Body Word Sales",
    "wof:placetype":"venue"
},
  "geometry": {"coordinates":[-96.009546,36.114981],"type":"Point"}
}