{
  "type": "Feature",
  "properties": {
    "addr:full":"119 Dalton Ave Valliant OK 74764",
    "addr:housenumber":"119",
    "addr:postcode":"74764",
    "addr:street":"Dalton Ave",
    "iso:country":"US",
    "sg:address":"119 Dalton Ave",
    "sg:city":"Valliant",
    "sg:classifiers":[
        {
            "category":"Manufacturing",
            "subcategory":"Printing",
            "type":"Manufacturing & Wholesale Goods"
        }
    ],
    "sg:phone":"+1 580 933 4579",
    "sg:postcode":"74764",
    "sg:province":"OK",
    "sg:tags":[
        "newspaper"
    ],
    "wof:name":"Valliant Leader",
    "wof:placetype":"venue"
},
  "geometry": {"coordinates":[-95.09320700000001,34.004601],"type":"Point"}
}