{
  "type": "Feature",
  "properties": {
    "iso:country":"US",
    "sg:address":"209 S Main St",
    "sg:city":"Hennessey",
    "sg:classifiers":[
        {
            "category":"Shopping",
            "subcategory":"Discount & Variety Stores",
            "type":"Retail Goods"
        }
    ],
    "sg:phone":"+1 405 853 6233",
    "sg:postcode":"73742",
    "sg:province":"OK",
    "wof:name":"Bills Dollar Store 673",
    "wof:placetype":"venue"
},
  "geometry": {"coordinates":[-97.898893,36.108297],"type":"Point"}
}