{
  "type": "Feature",
  "properties": {
    "iso:country":"US",
    "sg:address":"3 Cherokee St",
    "sg:city":"Shawnee",
    "sg:classifiers":[
        {
            "category":"Food & Beverages",
            "subcategory":"Bakery",
            "type":"Retail Goods"
        }
    ],
    "sg:phone":"+1 405 273 5757",
    "sg:postcode":"74801",
    "sg:province":"OK",
    "wof:name":"Sweet Connections",
    "wof:placetype":"venue"
},
  "geometry": {"coordinates":[-96.901083,35.344648],"type":"Point"}
}