{
  "type": "Feature",
  "properties": {
    "iso:country":"US",
    "sg:address":"104 E Illinois Ave",
    "sg:city":"Vinita",
    "sg:classifiers":[
        {
            "category":"Government",
            "subcategory":"Fire Station",
            "type":"Public Place"
        }
    ],
    "sg:phone":"+1 918 000 1111",
    "sg:postcode":"74301",
    "sg:province":"OK",
    "sg:tags":[
        "department"
    ],
    "wof:name":"Vinita Fire Dept",
    "wof:placetype":"venue"
},
  "geometry": {"coordinates":[-95.154376,36.638817],"type":"Point"}
}