{
  "type": "Feature",
  "properties": {
    "addr:full":"6405 Blackberry Rd Edmond OK 73034",
    "addr:housenumber":"6405",
    "addr:postcode":"73034",
    "addr:street":"Blackberry Rd",
    "iso:country":"US",
    "sg:address":"6405 Blackberry Rd",
    "sg:city":"Edmond",
    "sg:classifiers":[
        {
            "category":"Wholesale",
            "subcategory":"Home Furnishings",
            "type":"Manufacturing & Wholesale Goods"
        }
    ],
    "sg:phone":"+1 405 340 4445",
    "sg:postcode":"73034",
    "sg:province":"OK",
    "sg:tags":[
        "floor",
        "vinyl",
        "install",
        "covering"
    ],
    "wof:name":"Floor Specialist",
    "wof:placetype":"venue"
},
  "geometry": {"coordinates":[-97.39970599999999,35.720436],"type":"Point"}
}