{
  "type": "Feature",
  "properties": {
    "iso:country":"US",
    "sg:address":"708 S Vann St",
    "sg:city":"Pryor",
    "sg:classifiers":[
        {
            "category":"Professional",
            "subcategory":"Accounting & Tax Preparation",
            "type":"Services"
        }
    ],
    "sg:phone":"+1 918 825 3680",
    "sg:postcode":"74361",
    "sg:province":"OK",
    "sg:tags":[
        "bookkeeping",
        "return",
        "general"
    ],
    "wof:name":"Annabelle Ironside Tax Service",
    "wof:placetype":"venue"
},
  "geometry": {"coordinates":[-95.318845,36.294953],"type":"Point"}
}