{
  "type": "Feature",
  "properties": {
    "iso:country":"US",
    "sg:address":"400 State Hwy 152",
    "sg:city":"Mustang",
    "sg:classifiers":[
        {
            "category":"Retail",
            "subcategory":"Animal Services",
            "type":"Services"
        }
    ],
    "sg:phone":"+1 405 376 6700",
    "sg:postcode":"73064",
    "sg:province":"OK",
    "wof:name":"Jamies Dog Design",
    "wof:placetype":"venue"
},
  "geometry": {"coordinates":[-97.730427,35.391694],"type":"Point"}
}