{
  "type": "Feature",
  "properties": {
    "addr:full":"2213 NW 59th Cir Oklahoma City OK 73112",
    "addr:housenumber":"2213",
    "addr:postcode":"73112",
    "addr:street":"Nw 59Th Cir",
    "iso:country":"US",
    "sg:address":"2213 NW 59th Cir",
    "sg:city":"Oklahoma City",
    "sg:classifiers":[
        {
            "category":"Professional",
            "subcategory":"Lawyer & Legal Services",
            "type":"Services"
        }
    ],
    "sg:phone":"+1 405 848 2081",
    "sg:postcode":"73112",
    "sg:province":"OK",
    "wof:name":"P M Williams Attorney",
    "wof:placetype":"venue"
},
  "geometry": {"coordinates":[-97.550467,35.532634],"type":"Point"}
}