{
  "type": "Feature",
  "properties": {
    "iso:country":"US",
    "sg:address":"3214 Wayside Dr",
    "sg:city":"Bartlesville",
    "sg:classifiers":[
        {
            "category":"Social Services",
            "type":"Services"
        }
    ],
    "sg:phone":"+1 918 333 9420",
    "sg:postcode":"74006",
    "sg:province":"OK",
    "sg:tags":[
        "organization",
        "welfare"
    ],
    "wof:name":"Mothers Against Drunk Driving",
    "wof:placetype":"venue"
},
  "geometry": {"coordinates":[-95.94180799999999,36.718604],"type":"Point"}
}