{
  "type": "Feature",
  "properties": {
    "addr:full":"104 W Main St Holdenville OK 74848",
    "addr:housenumber":"104",
    "addr:postcode":"74848",
    "addr:street":"W Main St",
    "iso:country":"US",
    "sg:address":"104 W Main St",
    "sg:city":"Holdenville",
    "sg:classifiers":[
        {
            "category":"Home & Garden",
            "subcategory":"Building Materials",
            "type":"Retail Goods"
        }
    ],
    "sg:phone":"+1 405 379 3322",
    "sg:postcode":"74848",
    "sg:province":"OK",
    "sg:tags":[
        "plumbing",
        "fixture",
        "supply"
    ],
    "wof:name":"Kalico Kitchen",
    "wof:placetype":"venue"
},
  "geometry": {"coordinates":[-96.40228500000001,35.083502],"type":"Point"}
}