{
  "type": "Feature",
  "properties": {
    "iso:country":"US",
    "sg:address":"7724 Maehs Ter",
    "sg:city":"Oklahoma City",
    "sg:classifiers":[
        {
            "category":"Professional",
            "subcategory":"Business Services",
            "type":"Services"
        }
    ],
    "sg:phone":"+1 405 728 2985",
    "sg:postcode":"73162",
    "sg:province":"OK",
    "wof:name":"D C Drywall",
    "wof:placetype":"venue"
},
  "geometry": {"coordinates":[-97.65216700000001,35.575961],"type":"Point"}
}