{
  "type": "Feature",
  "properties": {
    "addr:full":"600 W Blue Starr Dr Claremore OK 74017",
    "addr:housenumber":"600",
    "addr:postcode":"74017",
    "addr:street":"W Blue Starr Dr",
    "iso:country":"US",
    "sg:address":"600 W Blue Starr Dr",
    "sg:city":"Claremore",
    "sg:classifiers":[
        {
            "category":"Restaurant",
            "type":"Food & Drink"
        }
    ],
    "sg:menulink":"http://www.allmenus.com/ok/claremore/144531-subway/menu/",
    "sg:phone":"+1 918 341 6933",
    "sg:postcode":"74017",
    "sg:province":"OK",
    "sg:tags":[
        "american",
        "sandwich"
    ],
    "wof:name":"Subway",
    "wof:placetype":"venue"
},
  "geometry": {"coordinates":[-95.610373,36.321839],"type":"Point"}
}