{
  "type": "Feature",
  "properties": {
    "iso:country":"US",
    "sg:address":"27621 E Hwy 51",
    "sg:city":"Coweta",
    "sg:classifiers":[
        {
            "category":"Retail",
            "subcategory":"Repair Shop",
            "type":"Services"
        }
    ],
    "sg:phone":"+1 918 486 4420",
    "sg:postcode":"74429",
    "sg:province":"OK",
    "wof:name":"Brokes Upholstery",
    "wof:placetype":"venue"
},
  "geometry": {"coordinates":[-95.666588,35.981452],"type":"Point"}
}