{
  "type": "Feature",
  "properties": {
    "iso:country":"US",
    "sg:address":"320 N Porter Ave",
    "sg:city":"Norman",
    "sg:classifiers":[
        {
            "category":"Restaurant",
            "type":"Food & Drink"
        }
    ],
    "sg:menulink":"http://www.allmenus.com/ok/norman/239247-vans-pig-stands/menu/",
    "sg:phone":"+1 405 364 0600",
    "sg:postcode":"73071",
    "sg:province":"OK",
    "sg:tags":[
        "barbecue",
        "american"
    ],
    "wof:name":"Van's Pig Stands",
    "wof:placetype":"venue"
},
  "geometry": {"coordinates":[-97.440944,35.22513],"type":"Point"}
}