{
  "type": "Feature",
  "properties": {
    "iso:country":"US",
    "sg:address":"1405 Edmond Rd NE",
    "sg:city":"Piedmont",
    "sg:classifiers":[
        {
            "category":"Farming",
            "subcategory":"Farm",
            "type":"Manufacturing & Wholesale Goods"
        }
    ],
    "sg:phone":"+1 405 373 1187",
    "sg:postcode":"73078",
    "sg:province":"OK",
    "sg:tags":[
        "crop",
        "general"
    ],
    "wof:name":"Luschen Farms Inc",
    "wof:placetype":"venue"
},
  "geometry": {"coordinates":[-97.729737,35.652985],"type":"Point"}
}