{
  "type": "Feature",
  "properties": {
    "addr:full":"10200 NW 10th St Oklahoma City OK 73127",
    "addr:housenumber":"10200",
    "addr:postcode":"73127",
    "addr:street":"Nw 10Th St",
    "iso:country":"US",
    "sg:address":"10200 NW 10th St",
    "sg:city":"Oklahoma City",
    "sg:classifiers":[
        {
            "category":"Building & Trades",
            "subcategory":"Construction",
            "type":"Services"
        }
    ],
    "sg:phone":"+1 405 577 2944",
    "sg:postcode":"73127",
    "sg:province":"OK",
    "wof:name":"All Roads Paving Inc",
    "wof:placetype":"venue"
},
  "geometry": {"coordinates":[-97.69655,35.478822],"type":"Point"}
}