{
  "type": "Feature",
  "properties": {
    "iso:country":"US",
    "sg:address":"5425 E 11th St",
    "sg:city":"Tulsa",
    "sg:classifiers":[
        {
            "category":"Food & Beverages",
            "subcategory":"Groceries & Convenience Stores",
            "type":"Retail Goods"
        }
    ],
    "sg:phone":"+1 918 836 1811",
    "sg:postcode":"74112",
    "sg:province":"OK",
    "sg:tags":[
        "grocer"
    ],
    "wof:name":"Fiesta Mart",
    "wof:placetype":"venue"
},
  "geometry": {"coordinates":[-95.915977,36.147925],"type":"Point"}
}