{
  "type": "Feature",
  "properties": {
    "iso:country":"US",
    "sg:address":"9636 N May Ave",
    "sg:city":"Oklahoma City",
    "sg:classifiers":[
        {
            "category":"Professional",
            "subcategory":"Lawyer & Legal Services",
            "type":"Services"
        }
    ],
    "sg:phone":"+1 405 751 6500",
    "sg:postcode":"73120",
    "sg:province":"OK",
    "wof:name":"Wright Thornton Jr",
    "wof:placetype":"venue"
},
  "geometry": {"coordinates":[-97.567105,35.568627],"type":"Point"}
}