{
  "type": "Feature",
  "properties": {
    "iso:country":"US",
    "sg:address":"1514 SE 44th St",
    "sg:city":"Oklahoma City",
    "sg:classifiers":[
        {
            "category":"Shopping",
            "subcategory":"Tobacco",
            "type":"Retail Goods"
        },
        {
            "category":"Shopping",
            "subcategory":"Gifts & Souvenirs",
            "type":"Retail Goods"
        }
    ],
    "sg:phone":"+1 405 677 7473",
    "sg:postcode":"73129",
    "sg:province":"OK",
    "sg:tags":[
        "item",
        "cigar",
        "dealer",
        "related",
        "cigarette"
    ],
    "wof:name":"Drew's Tobacco World",
    "wof:placetype":"venue"
},
  "geometry": {"coordinates":[-97.484655,35.420755],"type":"Point"}
}