{
  "type": "Feature",
  "properties": {
    "addr:full":"5124 NW 20th St Oklahoma City OK 73127",
    "addr:housenumber":"5124",
    "addr:postcode":"73127",
    "addr:street":"Nw 20Th St",
    "iso:country":"US",
    "sg:address":"5124 NW 20th St",
    "sg:city":"Oklahoma City",
    "sg:classifiers":[
        {
            "category":"Building & Trades",
            "subcategory":"Construction",
            "type":"Services"
        }
    ],
    "sg:phone":"+1 405 946 3358",
    "sg:postcode":"73127",
    "sg:province":"OK",
    "sg:tags":[
        "contractor"
    ],
    "wof:name":"Douglas Todd",
    "wof:placetype":"venue"
},
  "geometry": {"coordinates":[-97.61592,35.491043],"type":"Point"}
}