{
  "type": "Feature",
  "properties": {
    "iso:country":"US",
    "sg:address":"904 Main Ave",
    "sg:city":"Woodward",
    "sg:classifiers":[
        {
            "category":"Social Services",
            "type":"Services"
        }
    ],
    "sg:phone":"+1 580 338 5258",
    "sg:postcode":"73801",
    "sg:province":"OK",
    "sg:tags":[
        "youth",
        "organization",
        "center"
    ],
    "wof:name":"Western Plains Youth",
    "wof:placetype":"venue"
},
  "geometry": {"coordinates":[-99.391895,36.43603],"type":"Point"}
}