{
  "type": "Feature",
  "properties": {
    "addr:full":"626 SW 29th St Oklahoma City OK 73109",
    "addr:housenumber":"626",
    "addr:postcode":"73109",
    "addr:street":"Sw 29Th St",
    "iso:country":"US",
    "sg:address":"626 SW 29th St",
    "sg:city":"Oklahoma City",
    "sg:classifiers":[
        {
            "category":"Autos & Motor Vehicles",
            "subcategory":"Automobile Sales",
            "type":"Retail Goods"
        }
    ],
    "sg:phone":"+1 405 605 4171",
    "sg:postcode":"73109",
    "sg:province":"OK",
    "sg:tags":[
        "car",
        "dealer"
    ],
    "wof:name":"Exclusive Auto Sales",
    "wof:placetype":"venue"
},
  "geometry": {"coordinates":[-97.525446,35.43517],"type":"Point"}
}