{
  "type": "Feature",
  "properties": {
    "iso:country":"US",
    "sg:address":"52000 E 150 Rd",
    "sg:city":"Miami",
    "sg:phone":"+1 918 540 1045",
    "sg:postcode":"74354",
    "sg:province":"OK",
    "sg:tags":[
        "farm",
        "wheat",
        "soybean"
    ],
    "wof:name":"Pioeer Seed Co",
    "wof:placetype":"venue"
},
  "geometry": {"coordinates":[-94.94529900000001,36.801179],"type":"Point"}
}