{
  "type": "Feature",
  "properties": {
    "iso:country":"US",
    "sg:address":"605 W Donehoo St",
    "sg:city":"Madill",
    "sg:classifiers":[
        {
            "category":"Building & Trades",
            "subcategory":"Plumbing",
            "type":"Services"
        }
    ],
    "sg:phone":"+1 580 795 5287",
    "sg:postcode":"73446",
    "sg:province":"OK",
    "sg:tags":[
        "conditioning",
        "air",
        "system",
        "contractor"
    ],
    "wof:name":"Richardson Air Cond & Heating",
    "wof:placetype":"venue"
},
  "geometry": {"coordinates":[-96.776363,34.096597],"type":"Point"}
}