{
  "type": "Feature",
  "properties": {
    "iso:country":"US",
    "sg:address":"2420 E Overholser Dr",
    "sg:city":"Oklahoma City",
    "sg:classifiers":[
        {
            "category":"Organizations",
            "subcategory":"Religious Organization",
            "type":"Services"
        }
    ],
    "sg:phone":"+1 405 769 2212",
    "sg:postcode":"73127",
    "sg:province":"OK",
    "sg:tags":[
        "church"
    ],
    "wof:name":"Nicoma Park Church Of Christ",
    "wof:placetype":"venue"
},
  "geometry": {"coordinates":[-97.66618699999999,35.500248],"type":"Point"}
}