{
  "type": "Feature",
  "properties": {
    "iso:country":"US",
    "sg:address":"10920 NW 10th St",
    "sg:city":"Yukon",
    "sg:classifiers":[
        {
            "category":"Bus Charters",
            "type":"Transportation"
        }
    ],
    "sg:phone":"+1 405 324 9888",
    "sg:postcode":"73127",
    "sg:province":"OK",
    "sg:website":"www.kincaidcoach.com",
    "wof:name":"Kincaid Coach Lines Inc",
    "wof:placetype":"venue"
},
  "geometry": {"coordinates":[-97.707475,35.478923],"type":"Point"}
}