{
  "type": "Feature",
  "properties": {
    "addr:full":"213 W Kenosha St Broken Arrow OK 74012",
    "addr:housenumber":"213",
    "addr:postcode":"74012",
    "addr:street":"W Kenosha St",
    "iso:country":"US",
    "sg:address":"213 W Kenosha St",
    "sg:city":"Broken Arrow",
    "sg:classifiers":[
        {
            "category":"Retail",
            "subcategory":"Auto Repair",
            "type":"Services"
        }
    ],
    "sg:phone":"+1 918 258 0921",
    "sg:postcode":"74012",
    "sg:province":"OK",
    "sg:tags":[
        "repairing",
        "automobile",
        "radiator"
    ],
    "wof:name":"Broken Arrow Radiator Works",
    "wof:placetype":"venue"
},
  "geometry": {"coordinates":[-95.792199,36.061028],"type":"Point"}
}