{
  "type": "Feature",
  "properties": {
    "addr:full":"302 S 5th St Healdton OK 73438",
    "addr:housenumber":"302",
    "addr:postcode":"73438",
    "addr:street":"S 5Th St",
    "iso:country":"US",
    "sg:address":"302 S 5th St",
    "sg:city":"Healdton",
    "sg:classifiers":[
        {
            "category":"Retail",
            "subcategory":"Repair Shop",
            "type":"Services"
        }
    ],
    "sg:phone":"+1 580 229 0550",
    "sg:postcode":"73438",
    "sg:province":"OK",
    "wof:name":"Dales TV & Vcr Repair",
    "wof:placetype":"venue"
},
  "geometry": {"coordinates":[-97.488912,34.230005],"type":"Point"}
}