{
  "type": "Feature",
  "properties": {
    "addr:full":"3001 SE 19th St Oklahoma City OK 73115",
    "addr:housenumber":"3001",
    "addr:postcode":"73115",
    "addr:street":"Se 19Th St",
    "iso:country":"US",
    "sg:address":"3001 SE 19th St",
    "sg:city":"Oklahoma City",
    "sg:classifiers":[
        {
            "category":"Manufacturing",
            "subcategory":"Metals",
            "type":"Manufacturing & Wholesale Goods"
        }
    ],
    "sg:phone":"+1 405 799 4610",
    "sg:postcode":"73115",
    "sg:province":"OK",
    "sg:tags":[
        "fabricated",
        "structural"
    ],
    "wof:name":"Log Concepts Inc",
    "wof:placetype":"venue"
},
  "geometry": {"coordinates":[-97.45752899999999,35.444859],"type":"Point"}
}