{
  "type": "Feature",
  "properties": {
    "addr:full":"525 W Okmulgee Ave Muskogee OK 74401",
    "addr:housenumber":"525",
    "addr:postcode":"74401",
    "addr:street":"W Okmulgee Ave",
    "iso:country":"US",
    "sg:address":"525 W Okmulgee Ave",
    "sg:city":"Muskogee",
    "sg:classifiers":[
        {
            "category":"Organizations",
            "subcategory":"Labor Organization",
            "type":"Services"
        }
    ],
    "sg:phone":"+1 918 687 9819",
    "sg:postcode":"74401",
    "sg:province":"OK",
    "wof:name":"American Postal Workers Union",
    "wof:placetype":"venue"
},
  "geometry": {"coordinates":[-95.373857,35.749523],"type":"Point"}
}