{
  "type": "Feature",
  "properties": {
    "iso:country":"US",
    "sg:address":"7671 Rolling Oak Rd",
    "sg:city":"Jones",
    "sg:classifiers":[
        {
            "category":"Building & Trades",
            "subcategory":"Construction",
            "type":"Services"
        }
    ],
    "sg:phone":"+1 405 640 0684",
    "sg:postcode":"73049",
    "sg:province":"OK",
    "sg:tags":[
        "painter"
    ],
    "wof:name":"B & P Painting & Drywall",
    "wof:placetype":"venue"
},
  "geometry": {"coordinates":[-97.272275,35.551159],"type":"Point"}
}