{
  "type": "Feature",
  "properties": {
    "iso:country":"US",
    "sg:address":"410 E Main St",
    "sg:city":"Cushing",
    "sg:classifiers":[
        {
            "category":"Real Estate",
            "subcategory":"Real Estate Agent",
            "type":"Services"
        }
    ],
    "sg:phone":"+1 918 225 2265",
    "sg:postcode":"74023",
    "sg:province":"OK",
    "wof:name":"Blake Realty",
    "wof:placetype":"venue"
},
  "geometry": {"coordinates":[-96.768826,35.985142],"type":"Point"}
}