{
  "type": "Feature",
  "properties": {
    "iso:country":"US",
    "sg:address":"430 S Birch St",
    "sg:city":"Owasso",
    "sg:classifiers":[
        {
            "category":"Utilities",
            "subcategory":"Refuse",
            "type":"Services"
        }
    ],
    "sg:phone":"+1 918 272 4991",
    "sg:postcode":"74055",
    "sg:province":"OK",
    "sg:tags":[
        "system"
    ],
    "wof:name":"City of Owasso",
    "wof:placetype":"venue"
},
  "geometry": {"coordinates":[-95.85383299999999,36.261535],"type":"Point"}
}