{
  "type": "Feature",
  "properties": {
    "iso:country":"US",
    "sg:address":"1301 W Country Club Rd",
    "sg:city":"Claremore",
    "sg:classifiers":[
        {
            "category":"Personal",
            "type":"Services"
        },
        {
            "category":"Arena",
            "subcategory":"Sports Club",
            "type":"Entertainment"
        }
    ],
    "sg:phone":"+1 918 341 8130",
    "sg:postcode":"74017",
    "sg:province":"OK",
    "sg:tags":[
        "trainer",
        "consultant",
        "physical",
        "health",
        "fitness"
    ],
    "wof:name":"Access Fitness Claremore",
    "wof:placetype":"venue"
},
  "geometry": {"coordinates":[-95.624222,36.292931],"type":"Point"}
}