{
  "type": "Feature",
  "properties": {
    "iso:country":"US",
    "sg:address":"3001 N Broadway St",
    "sg:city":"Poteau",
    "sg:classifiers":[
        {
            "category":"Autos & Motor Vehicles",
            "subcategory":"Automobile Sales",
            "type":"Retail Goods"
        }
    ],
    "sg:phone":"+1 918 647 3223",
    "sg:postcode":"74953",
    "sg:province":"OK",
    "sg:tags":[
        "car",
        "dealer"
    ],
    "sg:website":"www.bobsmedley.com",
    "wof:name":"Brad Fenton General Motors",
    "wof:placetype":"venue"
},
  "geometry": {"coordinates":[-94.628869,35.072034],"type":"Point"}
}