{
  "type": "Feature",
  "properties": {
    "iso:country":"US",
    "sg:address":"211 S Main St",
    "sg:city":"Stillwater",
    "sg:classifiers":[
        {
            "category":"Recreation",
            "type":"Entertainment"
        }
    ],
    "sg:phone":"+1 405 372 2517",
    "sg:postcode":"74074",
    "sg:province":"OK",
    "sg:tags":[
        "martial",
        "arts",
        "instruction"
    ],
    "wof:name":"Master Hans Martial Arts",
    "wof:placetype":"venue"
},
  "geometry": {"coordinates":[-97.058565,36.120466],"type":"Point"}
}