{
  "type": "Feature",
  "properties": {
    "addr:full":"14220 S Meridian Ave Oklahoma City OK 73173",
    "addr:housenumber":"14220",
    "addr:postcode":"73173",
    "addr:street":"S Meridian Ave",
    "iso:country":"US",
    "sg:address":"14220 S Meridian Ave",
    "sg:city":"Oklahoma City",
    "sg:classifiers":[
        {
            "category":"Building & Trades",
            "subcategory":"Construction",
            "type":"Services"
        }
    ],
    "sg:phone":"+1 405 692 2300",
    "sg:postcode":"73173",
    "sg:province":"OK",
    "sg:tags":[
        "roofing",
        "industrial",
        "commercial",
        "contractor"
    ],
    "wof:name":"Zenex International Inc",
    "wof:placetype":"venue"
},
  "geometry": {"coordinates":[-97.600566,35.320354],"type":"Point"}
}