{
  "type": "Feature",
  "properties": {
    "iso:country":"US",
    "sg:address":"3133 Woodside Dr",
    "sg:city":"Ardmore",
    "sg:classifiers":[
        {
            "category":"Organizations",
            "subcategory":"Religious Organization",
            "type":"Services"
        }
    ],
    "sg:phone":"+1 580 223 6996",
    "sg:postcode":"73401",
    "sg:province":"OK",
    "wof:name":"Temple Emeth",
    "wof:placetype":"venue"
},
  "geometry": {"coordinates":[-97.072462,34.175352],"type":"Point"}
}