{
  "type": "Feature",
  "properties": {
    "iso:country":"US",
    "sg:address":"2021 S Lewis Ave",
    "sg:city":"Tulsa",
    "sg:classifiers":[
        {
            "category":"Professional",
            "type":"Services"
        }
    ],
    "sg:phone":"+1 918 579 5005",
    "sg:postcode":"74104",
    "sg:province":"OK",
    "sg:tags":[
        "establishment"
    ],
    "wof:name":"Pro Comp",
    "wof:placetype":"venue"
},
  "geometry": {"coordinates":[-95.95813,36.133419],"type":"Point"}
}