{
  "type": "Feature",
  "properties": {
    "iso:country":"US",
    "sg:address":"1608 Washington St",
    "sg:city":"Edmond",
    "sg:classifiers":[
        {
            "category":"Professional",
            "subcategory":"Management & Consulting",
            "type":"Services"
        }
    ],
    "sg:phone":"+1 405 341 8655",
    "sg:postcode":"73034",
    "sg:province":"OK",
    "sg:tags":[
        "business"
    ],
    "wof:name":"Telecomm Consultants Inc",
    "wof:placetype":"venue"
},
  "geometry": {"coordinates":[-97.471246,35.671451],"type":"Point"}
}