{
  "type": "Feature",
  "properties": {
    "iso:country":"US",
    "sg:address":"1425 W Main St",
    "sg:city":"Durant",
    "sg:classifiers":[
        {
            "category":"Wholesale",
            "subcategory":"Auto Parts",
            "type":"Manufacturing & Wholesale Goods"
        }
    ],
    "sg:phone":"+1 580 924 4634",
    "sg:postcode":"74701",
    "sg:province":"OK",
    "sg:tags":[
        "equipment",
        "truck"
    ],
    "wof:name":"Raymond's Auto Supply",
    "wof:placetype":"venue"
},
  "geometry": {"coordinates":[-96.391932,33.994596],"type":"Point"}
}