{
  "type": "Feature",
  "properties": {
    "iso:country":"US",
    "sg:address":"524 US Hwy 54",
    "sg:city":"Guymon",
    "sg:classifiers":[
        {
            "category":"Insurance",
            "subcategory":"Insurance Agent",
            "type":"Services"
        }
    ],
    "sg:phone":"+1 580 338 8626",
    "sg:postcode":"73942",
    "sg:province":"OK",
    "wof:name":"Linda Hill Crop Insurance",
    "wof:placetype":"venue"
},
  "geometry": {"coordinates":[-101.475866,36.677653],"type":"Point"}
}