{
  "type": "Feature",
  "properties": {
    "iso:country":"US",
    "sg:address":"4136 S 70th East Ave",
    "sg:city":"Tulsa",
    "sg:classifiers":[
        {
            "category":"Autos & Motor Vehicles",
            "subcategory":"Motorcycle Sales",
            "type":"Retail Goods"
        }
    ],
    "sg:phone":"+1 918 660 0095",
    "sg:postcode":"74145",
    "sg:province":"OK",
    "sg:tags":[
        "scooter"
    ],
    "wof:name":"EFX Choppers",
    "wof:placetype":"venue"
},
  "geometry": {"coordinates":[-95.899193,36.100649],"type":"Point"}
}