{
  "type": "Feature",
  "properties": {
    "addr:full":"3401 S Western Ave Oklahoma City OK 73109",
    "addr:housenumber":"3401",
    "addr:postcode":"73109",
    "addr:street":"S Western Ave",
    "iso:country":"US",
    "sg:address":"3401 S Western Ave",
    "sg:city":"Oklahoma City",
    "sg:classifiers":[
        {
            "category":"Banks & Credit Unions",
            "subcategory":"Bank",
            "type":"Services"
        }
    ],
    "sg:phone":"+1 405 635 0900",
    "sg:postcode":"73109",
    "sg:province":"OK",
    "sg:tags":[
        "banker",
        "mortgage"
    ],
    "wof:name":"United Mortgage Group",
    "wof:placetype":"venue"
},
  "geometry": {"coordinates":[-97.530192,35.429806],"type":"Point"}
}