{
  "type": "Feature",
  "properties": {
    "iso:country":"US",
    "sg:address":"1000 SE 19th St",
    "sg:city":"Oklahoma City",
    "sg:classifiers":[
        {
            "category":"Banks & Credit Unions",
            "subcategory":"Financial Services",
            "type":"Services"
        }
    ],
    "sg:phone":"+1 405 912 2377",
    "sg:postcode":"73160",
    "sg:province":"OK",
    "sg:tags":[
        "investor"
    ],
    "wof:name":"Hpg Investment",
    "wof:placetype":"venue"
},
  "geometry": {"coordinates":[-97.475904,35.319674],"type":"Point"}
}