{
  "type": "Feature",
  "properties": {
    "iso:country":"US",
    "sg:address":"35 E 18th St",
    "sg:city":"Tulsa",
    "sg:classifiers":[
        {
            "category":"Manufacturing",
            "subcategory":"Petroleum Products",
            "type":"Manufacturing & Wholesale Goods"
        }
    ],
    "sg:phone":"+1 918 599 8130",
    "sg:postcode":"74119",
    "sg:province":"OK",
    "wof:name":"Bronco Petroleum",
    "wof:placetype":"venue"
},
  "geometry": {"coordinates":[-95.985763,36.136143],"type":"Point"}
}