{
  "type": "Feature",
  "properties": {
    "addr:full":"1730 S Kelly Ave Edmond OK 73013",
    "addr:housenumber":"1730",
    "addr:postcode":"73013",
    "addr:street":"S Kelly Ave",
    "iso:country":"US",
    "sg:address":"1730 S Kelly Ave",
    "sg:city":"Edmond",
    "sg:classifiers":[
        {
            "category":"Professional",
            "subcategory":"Business Services",
            "type":"Services"
        }
    ],
    "sg:phone":"+1 405 844 7883",
    "sg:postcode":"73013",
    "sg:province":"OK",
    "sg:tags":[
        "recording",
        "production"
    ],
    "wof:name":"Hamilton House Studio D",
    "wof:placetype":"venue"
},
  "geometry": {"coordinates":[-97.495919,35.637886],"type":"Point"}
}