{
  "type": "Feature",
  "properties": {
    "iso:country":"US",
    "sg:address":"1601 N 170th East Ave",
    "sg:city":"Tulsa",
    "sg:classifiers":[
        {
            "category":"Freight",
            "type":"Transportation"
        }
    ],
    "sg:phone":"+1 918 234 6001",
    "sg:postcode":"74116",
    "sg:province":"OK",
    "sg:tags":[
        "operator",
        "hauling",
        "trucking"
    ],
    "wof:name":"Trucker's Express Inc",
    "wof:placetype":"venue"
},
  "geometry": {"coordinates":[-95.78544599999999,36.178225],"type":"Point"}
}