{
  "type": "Feature",
  "properties": {
    "iso:country":"US",
    "sg:address":"2336 NW 23rd St",
    "sg:city":"Oklahoma City",
    "sg:classifiers":[
        {
            "category":"Restaurant",
            "type":"Food & Drink"
        }
    ],
    "sg:phone":"+1 405 525 1600",
    "sg:postcode":"73107",
    "sg:province":"OK",
    "sg:tags":[
        "eating"
    ],
    "wof:name":"California Cafe",
    "wof:placetype":"venue"
},
  "geometry": {"coordinates":[-97.552722,35.493166],"type":"Point"}
}