{
  "type": "Feature",
  "properties": {
    "iso:country":"US",
    "sg:address":"2701 S May Ave",
    "sg:city":"Oklahoma City",
    "sg:classifiers":[
        {
            "category":"Wholesale",
            "subcategory":"Furniture",
            "type":"Manufacturing & Wholesale Goods"
        }
    ],
    "sg:phone":"+1 405 682 8653",
    "sg:postcode":"73108",
    "sg:province":"OK",
    "sg:tags":[
        "furnishing",
        "church"
    ],
    "wof:name":"Accent Furniture Upholstery",
    "wof:placetype":"venue"
},
  "geometry": {"coordinates":[-97.565558,35.437193],"type":"Point"}
}