{
  "type": "Feature",
  "properties": {
    "addr:full":"3033 N Walnut Ave Oklahoma City OK 73105",
    "addr:housenumber":"3033",
    "addr:postcode":"73105",
    "addr:street":"N Walnut Ave",
    "iso:country":"US",
    "sg:address":"3033 N Walnut Ave",
    "sg:city":"Oklahoma City",
    "sg:classifiers":[
        {
            "category":"Professional",
            "subcategory":"Testing Lab",
            "type":"Services"
        }
    ],
    "sg:phone":"+1 405 528 9296",
    "sg:postcode":"73105",
    "sg:province":"OK",
    "sg:tags":[
        "laboratory"
    ],
    "wof:name":"Langston University Hiv",
    "wof:placetype":"venue"
},
  "geometry": {"coordinates":[-97.507829,35.499312],"type":"Point"}
}