{
  "type": "Feature",
  "properties": {
    "iso:country":"US",
    "sg:address":"1 N Oklahoma Ave",
    "sg:city":"Oklahoma City",
    "sg:classifiers":[
        {
            "category":"Restaurant",
            "type":"Food & Drink"
        }
    ],
    "sg:menulink":"http://www.allmenus.com/ok/oklahoma-city/4529-bricktown-berwery/menu/",
    "sg:phone":"+1 405 232 2739",
    "sg:postcode":"73104",
    "sg:province":"OK",
    "sg:tags":[
        "american"
    ],
    "wof:name":"Bricktown Berwery",
    "wof:placetype":"venue"
},
  "geometry": {"coordinates":[-97.510642,35.466493],"type":"Point"}
}