{
  "type": "Feature",
  "properties": {
    "addr:full":"1928 S I- 35 Svc Rd Oklahoma City OK 73129",
    "addr:housenumber":"1928;35",
    "addr:postcode":"73129",
    "addr:street":"S I;Rd",
    "iso:country":"US",
    "sg:address":"1928 S I- 35 Svc Rd",
    "sg:city":"Oklahoma City",
    "sg:classifiers":[
        {
            "category":"Retail",
            "subcategory":"Repair Shop",
            "type":"Services"
        }
    ],
    "sg:phone":"+1 405 670 6211",
    "sg:postcode":"73129",
    "sg:province":"OK",
    "sg:tags":[
        "equipment",
        "hydraulic"
    ],
    "wof:name":"CESCO Inc",
    "wof:placetype":"venue"
},
  "geometry": {"coordinates":[-97.487241,35.448028],"type":"Point"}
}