{
  "type": "Feature",
  "properties": {
    "addr:full":"2101 SW Roosevelt Ave Lawton OK 73501",
    "addr:housenumber":"2101",
    "addr:postcode":"73501",
    "addr:street":"Sw Roosevelt Ave",
    "iso:country":"US",
    "sg:address":"2101 SW Roosevelt Ave",
    "sg:city":"Lawton",
    "sg:classifiers":[
        {
            "category":"Organizations",
            "subcategory":"Religious Organization",
            "type":"Services"
        }
    ],
    "sg:phone":"+1 580 355 6763",
    "sg:postcode":"73501",
    "sg:province":"OK",
    "wof:name":"New Zion Baptist Church",
    "wof:placetype":"venue"
},
  "geometry": {"coordinates":[-98.422169,34.588405],"type":"Point"}
}