{
  "type": "Feature",
  "properties": {
    "addr:full":"609 S Kelly Ave Edmond OK 73003",
    "addr:housenumber":"609",
    "addr:postcode":"73003",
    "addr:street":"S Kelly Ave",
    "iso:country":"US",
    "sg:address":"609 S Kelly Ave",
    "sg:city":"Edmond",
    "sg:classifiers":[
        {
            "category":"Shopping",
            "subcategory":"Pharmacy",
            "type":"Retail Goods"
        }
    ],
    "sg:phone":"+1 405 216 8328",
    "sg:postcode":"73003",
    "sg:province":"OK",
    "wof:name":"Silver Leaf Pharmacy",
    "wof:placetype":"venue"
},
  "geometry": {"coordinates":[-97.496084,35.649556],"type":"Point"}
}