{
  "type": "Feature",
  "properties": {
    "iso:country":"US",
    "sg:address":"1803 S 3rd St",
    "sg:city":"Stilwell",
    "sg:classifiers":[
        {
            "category":"Organizations",
            "subcategory":"Religious Organization",
            "type":"Services"
        }
    ],
    "sg:phone":"+1 918 696 5985",
    "sg:postcode":"74960",
    "sg:province":"OK",
    "wof:name":"Central Baptist",
    "wof:placetype":"venue"
},
  "geometry": {"coordinates":[-94.630588,35.796709],"type":"Point"}
}