{
  "type": "Feature",
  "properties": {
    "iso:country":"US",
    "sg:address":"3251 Southwest Blvd",
    "sg:city":"Tulsa",
    "sg:classifiers":[
        {
            "category":"Autos & Motor Vehicles",
            "subcategory":"Automobile Sales",
            "type":"Retail Goods"
        },
        {
            "category":"Wholesale",
            "subcategory":"Motor Vehicles",
            "type":"Manufacturing & Wholesale Goods"
        }
    ],
    "sg:phone":"+1 918 446 0063",
    "sg:postcode":"74107",
    "sg:province":"OK",
    "sg:tags":[
        "truck",
        "semi",
        "trailer"
    ],
    "wof:name":"Brad's Truck & Trailer Sales",
    "wof:placetype":"venue"
},
  "geometry": {"coordinates":[-96.009489,36.113683],"type":"Point"}
}