{
  "type": "Feature",
  "properties": {
    "iso:country":"US",
    "sg:address":"8605 S Elwood Ave",
    "sg:city":"Tulsa",
    "sg:classifiers":[
        {
            "category":"Airport",
            "type":"Transportation"
        }
    ],
    "sg:phone":"+1 918 298 0816",
    "sg:postcode":"74132",
    "sg:province":"OK",
    "sg:tags":[
        "aircraft",
        "maintenance"
    ],
    "wof:name":"WYNN Aviation",
    "wof:placetype":"venue"
},
  "geometry": {"coordinates":[-95.993633,36.036357],"type":"Point"}
}