{
  "type": "Feature",
  "properties": {
    "iso:country":"US",
    "sg:address":"30 G St SW",
    "sg:city":"Miami",
    "sg:classifiers":[
        {
            "category":"Freight",
            "type":"Transportation"
        }
    ],
    "sg:phone":"+1 918 542 6898",
    "sg:postcode":"74354",
    "sg:province":"OK",
    "sg:tags":[
        "operator",
        "local",
        "trucking"
    ],
    "wof:name":"Ray & Son Trucking Inc",
    "wof:placetype":"venue"
},
  "geometry": {"coordinates":[-94.885298,36.874334],"type":"Point"}
}