{
  "type": "Feature",
  "properties": {
    "iso:country":"US",
    "sg:address":"717 SW 59th St",
    "sg:city":"Oklahoma City",
    "sg:classifiers":[
        {
            "category":"Shopping",
            "subcategory":"Used Merchandise",
            "type":"Retail Goods"
        },
        {
            "category":"Shopping",
            "subcategory":"Clothing, Apparel, & Fashions",
            "type":"Retail Goods"
        }
    ],
    "sg:phone":"+1 405 632 7956",
    "sg:postcode":"73109",
    "sg:province":"OK",
    "sg:tags":[
        "leather",
        "antique"
    ],
    "wof:name":"B S Unlimited",
    "wof:placetype":"venue"
},
  "geometry": {"coordinates":[-97.525104,35.4063],"type":"Point"}
}