{
  "type": "Feature",
  "properties": {
    "iso:country":"US",
    "sg:address":"4232 NW 144th St",
    "sg:city":"Oklahoma City",
    "sg:classifiers":[
        {
            "category":"Banks & Credit Unions",
            "subcategory":"Bank",
            "type":"Services"
        }
    ],
    "sg:phone":"+1 405 302 2583",
    "sg:postcode":"73134",
    "sg:province":"OK",
    "sg:tags":[
        "loan",
        "real estate"
    ],
    "wof:name":"Gold Key Financial Svc",
    "wof:placetype":"venue"
},
  "geometry": {"coordinates":[-97.596828,35.618275],"type":"Point"}
}