{
  "type": "Feature",
  "properties": {
    "addr:full":"7350 S Garnett Rd Broken Arrow OK 74012",
    "addr:housenumber":"7350",
    "addr:postcode":"74012",
    "addr:street":"S Garnett Rd",
    "iso:country":"US",
    "sg:address":"7350 S Garnett Rd",
    "sg:city":"Broken Arrow",
    "sg:classifiers":[
        {
            "category":"Building & Trades",
            "subcategory":"Construction",
            "type":"Services"
        }
    ],
    "sg:phone":"+1 918 459 8544",
    "sg:postcode":"74012",
    "sg:province":"OK",
    "sg:tags":[
        "residential"
    ],
    "wof:name":"Echelon At Woodland Park",
    "wof:placetype":"venue"
},
  "geometry": {"coordinates":[-95.851038,36.057517],"type":"Point"}
}