{
  "type": "Feature",
  "properties": {
    "iso:country":"US",
    "sg:address":"2408 Cypress Ave",
    "sg:city":"Norman",
    "sg:classifiers":[
        {
            "category":"Health Services",
            "subcategory":"Health Practitioner",
            "type":"Services"
        }
    ],
    "sg:phone":"+1 405 329 2935",
    "sg:postcode":"73072",
    "sg:province":"OK",
    "wof:name":"Associates In Counseling",
    "wof:placetype":"venue"
},
  "geometry": {"coordinates":[-97.463299,35.195646],"type":"Point"}
}