{
  "type": "Feature",
  "properties": {
    "iso:country":"US",
    "sg:address":"904 SW 4th Pl",
    "sg:city":"Moore",
    "sg:classifiers":[
        {
            "category":"Retail",
            "subcategory":"Laundry & Dry Cleaning",
            "type":"Services"
        }
    ],
    "sg:phone":"+1 405 794 2110",
    "sg:postcode":"73160",
    "sg:province":"OK",
    "sg:tags":[
        "drycleaning",
        "plant",
        "cleaners"
    ],
    "wof:name":"Sunrise Cleaners & Laundry",
    "wof:placetype":"venue"
},
  "geometry": {"coordinates":[-97.508431,35.334836],"type":"Point"}
}