{
  "type": "Feature",
  "properties": {
    "iso:country":"US",
    "sg:address":"521 E Central St",
    "sg:city":"Temple",
    "sg:classifiers":[
        {
            "category":"Wholesale",
            "subcategory":"Meat",
            "type":"Manufacturing & Wholesale Goods"
        }
    ],
    "sg:phone":"+1 580 342 5031",
    "sg:postcode":"73568",
    "sg:province":"OK",
    "sg:tags":[
        "packer"
    ],
    "wof:name":"Temple Custom Slaughter",
    "wof:placetype":"venue"
},
  "geometry": {"coordinates":[-98.22968899999999,34.275237],"type":"Point"}
}