{
  "type": "Feature",
  "properties": {
    "iso:country":"US",
    "sg:address":"1630 S Sunnylane Rd",
    "sg:city":"Oklahoma City",
    "sg:classifiers":[
        {
            "category":"Banks & Credit Unions",
            "subcategory":"Bank",
            "type":"Services"
        }
    ],
    "sg:phone":"+1 405 670 4029",
    "sg:postcode":"73115",
    "sg:province":"OK",
    "sg:tags":[
        "loan",
        "institution",
        "business"
    ],
    "wof:name":"E-Z Loans",
    "wof:placetype":"venue"
},
  "geometry": {"coordinates":[-97.441399,35.449068],"type":"Point"}
}