{
  "type": "Feature",
  "properties": {
    "iso:country":"US",
    "sg:address":"1490 W Blue Starr Dr",
    "sg:city":"Claremore",
    "sg:classifiers":[
        {
            "category":"Social Services",
            "type":"Services"
        }
    ],
    "sg:phone":"+1 918 342 2622",
    "sg:postcode":"74017",
    "sg:province":"OK",
    "sg:tags":[
        "health"
    ],
    "wof:name":"Dr Clayton Rogers",
    "wof:placetype":"venue"
},
  "geometry": {"coordinates":[-95.62528500000001,36.321974],"type":"Point"}
}