{
  "type": "Feature",
  "properties": {
    "addr:full":"528 NW 12th St Oklahoma City OK 73103",
    "addr:housenumber":"528",
    "addr:postcode":"73103",
    "addr:street":"Nw 12Th St",
    "iso:country":"US",
    "sg:address":"528 NW 12th St",
    "sg:city":"Oklahoma City",
    "sg:classifiers":[
        {
            "category":"Professional",
            "subcategory":"Lawyer & Legal Services",
            "type":"Services"
        }
    ],
    "sg:phone":"+1 405 235 7641",
    "sg:postcode":"73103",
    "sg:province":"OK",
    "sg:tags":[
        "attorney"
    ],
    "sg:website":"www.lnjlaw.com",
    "wof:name":"Looney Nichols & Johnson",
    "wof:placetype":"venue"
},
  "geometry": {"coordinates":[-97.52225300000001,35.481191],"type":"Point"}
}