{
  "type": "Feature",
  "properties": {
    "iso:country":"US",
    "sg:address":"900 Lakeview Dr",
    "sg:city":"Woodward",
    "sg:classifiers":[
        {
            "category":"Wholesale",
            "subcategory":"Farm Supplies",
            "type":"Manufacturing & Wholesale Goods"
        }
    ],
    "sg:phone":"+1 580 256 5547",
    "sg:postcode":"73801",
    "sg:province":"OK",
    "sg:tags":[
        "auction",
        "livestock",
        "market"
    ],
    "wof:name":"Woodward Livestock Auction Co",
    "wof:placetype":"venue"
},
  "geometry": {"coordinates":[-99.371534,36.438326],"type":"Point"}
}