{
  "type": "Feature",
  "properties": {
    "iso:country":"US",
    "sg:address":"11119 E 21st St",
    "sg:city":"Tulsa",
    "sg:classifiers":[
        {
            "category":"Personal",
            "subcategory":"Beauty Salon",
            "type":"Services"
        }
    ],
    "sg:phone":"+1 918 437 4355",
    "sg:postcode":"74129",
    "sg:province":"OK",
    "sg:tags":[
        "shop"
    ],
    "wof:name":"Darlene Raglin Salon",
    "wof:placetype":"venue"
},
  "geometry": {"coordinates":[-95.851208,36.133536],"type":"Point"}
}