{
  "type": "Feature",
  "properties": {
    "addr:full":"9743 E 54th St Tulsa OK 74146",
    "addr:housenumber":"9743",
    "addr:postcode":"74146",
    "addr:street":"E 54Th St",
    "iso:country":"US",
    "sg:address":"9743 E 54th St",
    "sg:city":"Tulsa",
    "sg:classifiers":[
        {
            "category":"Transit Center",
            "subcategory":"Freight",
            "type":"Transportation"
        },
        {
            "category":"Freight",
            "type":"Transportation"
        },
        {
            "category":"Taxi",
            "type":"Transportation"
        }
    ],
    "sg:phone":"+1 918 665 8520",
    "sg:postcode":"74146",
    "sg:province":"OK",
    "sg:tags":[
        "delivery",
        "local",
        "trucking-motor",
        "trucking"
    ],
    "wof:name":"A & S Dispatch",
    "wof:placetype":"venue"
},
  "geometry": {"coordinates":[-95.867604,36.086305],"type":"Point"}
}