{
  "type": "Feature",
  "properties": {
    "addr:full":"3929 NW 10th St Oklahoma City OK 73107",
    "addr:housenumber":"3929",
    "addr:postcode":"73107",
    "addr:street":"Nw 10Th St",
    "iso:country":"US",
    "sg:address":"3929 NW 10th St",
    "sg:city":"Oklahoma City",
    "sg:classifiers":[
        {
            "category":"Shopping",
            "subcategory":"Shoes",
            "type":"Retail Goods"
        }
    ],
    "sg:phone":"+1 405 943 2468",
    "sg:postcode":"73107",
    "sg:province":"OK",
    "wof:name":"Hot Spot",
    "wof:placetype":"venue"
},
  "geometry": {"coordinates":[-97.589491,35.478824],"type":"Point"}
}