{
  "type": "Feature",
  "properties": {
    "iso:country":"US",
    "sg:address":"213 Wildflower Cir",
    "sg:city":"Cache",
    "sg:classifiers":[
        {
            "category":"Real Estate",
            "subcategory":"Real Estate Agent",
            "type":"Services"
        }
    ],
    "sg:phone":"+1 580 429 3006",
    "sg:postcode":"73527",
    "sg:province":"OK",
    "wof:name":"Horace W Smith",
    "wof:placetype":"venue"
},
  "geometry": {"coordinates":[-98.597793,34.627646],"type":"Point"}
}