{
  "type": "Feature",
  "properties": {
    "iso:country":"US",
    "sg:address":"4223 NW 10th St",
    "sg:city":"Oklahoma City",
    "sg:classifiers":[
        {
            "category":"Shopping",
            "subcategory":"Tobacco",
            "type":"Retail Goods"
        }
    ],
    "sg:phone":"+1 405 232 0900",
    "sg:postcode":"73107",
    "sg:province":"OK",
    "sg:tags":[
        "product"
    ],
    "wof:name":"Tobacco Depot",
    "wof:placetype":"venue"
},
  "geometry": {"coordinates":[-97.59614,35.478838],"type":"Point"}
}