{
  "type": "Feature",
  "properties": {
    "iso:country":"US",
    "sg:address":"5941 E 11th St",
    "sg:city":"Tulsa",
    "sg:classifiers":[
        {
            "category":"Retail",
            "subcategory":"Auto Repair",
            "type":"Services"
        }
    ],
    "sg:phone":"+1 918 834 6584",
    "sg:postcode":"74112",
    "sg:province":"OK",
    "sg:tags":[
        "repairing",
        "automobile"
    ],
    "wof:name":"Get It In Gear Route 66 Auto",
    "wof:placetype":"venue"
},
  "geometry": {"coordinates":[-95.909789,36.147974],"type":"Point"}
}