{
  "type": "Feature",
  "properties": {
    "iso:country":"US",
    "sg:address":"2128 S Atlanta Pl",
    "sg:city":"Tulsa",
    "sg:classifiers":[
        {
            "category":"Banks & Credit Unions",
            "subcategory":"Bank",
            "type":"Services"
        }
    ],
    "sg:phone":"+1 918 712 7103",
    "sg:postcode":"74114",
    "sg:province":"OK",
    "sg:tags":[
        "loan",
        "real estate"
    ],
    "wof:name":"First Horizon Home Loan Corp",
    "wof:placetype":"venue"
},
  "geometry": {"coordinates":[-95.955097,36.132708],"type":"Point"}
}