{
  "type": "Feature",
  "properties": {
    "iso:country":"US",
    "sg:address":"806 N Main St",
    "sg:city":"Fairview",
    "sg:classifiers":[
        {
            "category":"Shopping",
            "subcategory":"Bicycles & Sporting Goods",
            "type":"Retail Goods"
        }
    ],
    "sg:phone":"+1 580 227 4868",
    "sg:postcode":"73737",
    "sg:province":"OK",
    "wof:name":"Sportsman's Choice",
    "wof:placetype":"venue"
},
  "geometry": {"coordinates":[-98.479771,36.276656],"type":"Point"}
}