{
  "type": "Feature",
  "properties": {
    "addr:full":"7912 E 31st St S Tulsa OK 74145",
    "addr:housenumber":"7912",
    "addr:postcode":"74145",
    "addr:street":"E 31St St",
    "iso:country":"US",
    "sg:address":"7912 E 31st St S",
    "sg:city":"Tulsa",
    "sg:classifiers":[
        {
            "category":"Professional",
            "subcategory":"Lawyer & Legal Services",
            "type":"Services"
        }
    ],
    "sg:phone":"+1 918 628 5878",
    "sg:postcode":"74145",
    "sg:province":"OK",
    "sg:tags":[
        "attorney"
    ],
    "wof:name":"Kurt M Kennedy",
    "wof:placetype":"venue"
},
  "geometry": {"coordinates":[-95.888499,36.118945],"type":"Point"}
}