{
  "type": "Feature",
  "properties": {
    "iso:country":"US",
    "sg:address":"15 Raintree St",
    "sg:city":"Ponca City",
    "sg:classifiers":[
        {
            "category":"Shopping",
            "subcategory":"Stationery & Office Supplies",
            "type":"Retail Goods"
        }
    ],
    "sg:phone":"+1 580 765 9416",
    "sg:postcode":"74604",
    "sg:province":"OK",
    "sg:tags":[
        "video",
        "electronics",
        "presentation"
    ],
    "wof:name":"Amesway",
    "wof:placetype":"venue"
},
  "geometry": {"coordinates":[-97.054216,36.680853],"type":"Point"}
}