{
  "type": "Feature",
  "properties": {
    "addr:full":"3574 E Charter Oak Rd Guthrie OK 73044",
    "addr:housenumber":"3574",
    "addr:postcode":"73044",
    "addr:street":"E Charter Oak Rd",
    "iso:country":"US",
    "sg:address":"3574 E Charter Oak Rd",
    "sg:city":"Guthrie",
    "sg:classifiers":[
        {
            "category":"Building & Trades",
            "subcategory":"Construction",
            "type":"Services"
        }
    ],
    "sg:phone":"+1 405 282 2085",
    "sg:postcode":"73044",
    "sg:province":"OK",
    "sg:tags":[
        "excavation",
        "contractor"
    ],
    "wof:name":"Scroggins Excavation LLC",
    "wof:placetype":"venue"
},
  "geometry": {"coordinates":[-97.37549199999999,35.754346],"type":"Point"}
}