{
  "type": "Feature",
  "properties": {
    "addr:full":"1616 S State St Edmond OK 73013",
    "addr:housenumber":"1616",
    "addr:postcode":"73013",
    "addr:street":"S State St",
    "iso:country":"US",
    "sg:address":"1616 S State St",
    "sg:city":"Edmond",
    "sg:classifiers":[
        {
            "category":"Insurance",
            "subcategory":"Insurance Agent",
            "type":"Services"
        }
    ],
    "sg:phone":"+1 405 340 7323",
    "sg:postcode":"73013",
    "sg:province":"OK",
    "wof:name":"Ron Sykora & Assoc Insurance",
    "wof:placetype":"venue"
},
  "geometry": {"coordinates":[-97.4923,35.637214],"type":"Point"}
}