{
  "type": "Feature",
  "properties": {
    "addr:full":"5821 E 46th St Tulsa OK 74135",
    "addr:housenumber":"5821",
    "addr:postcode":"74135",
    "addr:street":"E 46Th St",
    "iso:country":"US",
    "sg:address":"5821 E 46th St",
    "sg:city":"Tulsa",
    "sg:classifiers":[
        {
            "category":"Shopping",
            "type":"Retail Goods"
        }
    ],
    "sg:phone":"+1 918 665 0118",
    "sg:postcode":"74135",
    "sg:province":"OK",
    "sg:tags":[
        "miscellaneous",
        "store"
    ],
    "sg:website":"www.u2candoitnow.com",
    "wof:name":"V L Smith Enterprises",
    "wof:placetype":"venue"
},
  "geometry": {"coordinates":[-95.91065999999999,36.097258],"type":"Point"}
}