{
  "type": "Feature",
  "properties": {
    "iso:country":"US",
    "sg:address":"6074 E 56th St",
    "sg:city":"Tulsa",
    "sg:classifiers":[
        {
            "category":"Banks & Credit Unions",
            "subcategory":"Investment Brokerage",
            "type":"Services"
        }
    ],
    "sg:phone":"+1 918 494 0409",
    "sg:postcode":"74135",
    "sg:province":"OK",
    "wof:name":"Hazel Investment Co",
    "wof:placetype":"venue"
},
  "geometry": {"coordinates":[-95.904907,36.082958],"type":"Point"}
}