{
  "type": "Feature",
  "properties": {
    "iso:country":"US",
    "sg:address":"2005 S 1st Pl",
    "sg:city":"Broken Arrow",
    "sg:classifiers":[
        {
            "category":"Retail",
            "subcategory":"Animal Services",
            "type":"Services"
        }
    ],
    "sg:phone":"+1 918 455 2055",
    "sg:postcode":"74012",
    "sg:province":"OK",
    "sg:website":"www.allbreedsacademy.com",
    "wof:name":"All Breeds Dog Academy",
    "wof:placetype":"venue"
},
  "geometry": {"coordinates":[-95.788394,36.030895],"type":"Point"}
}