{
  "type": "Feature",
  "properties": {
    "iso:country":"US",
    "sg:address":"218 N Missouri Ave",
    "sg:city":"Claremore",
    "sg:classifiers":[
        {
            "category":"Manufacturing",
            "subcategory":"Signs",
            "type":"Manufacturing & Wholesale Goods"
        }
    ],
    "sg:phone":"+1 918 341 2992",
    "sg:postcode":"74017",
    "sg:province":"OK",
    "sg:tags":[
        "specialty",
        "merchandise",
        "mfg"
    ],
    "wof:name":"Miket ADS Inc",
    "wof:placetype":"venue"
},
  "geometry": {"coordinates":[-95.61375,36.313709],"type":"Point"}
}