{
  "type": "Feature",
  "properties": {
    "iso:country":"US",
    "sg:address":"1004 E Virginia Ave",
    "sg:city":"Stillwater",
    "sg:classifiers":[
        {
            "category":"Autos & Motor Vehicles",
            "subcategory":"Automobile Sales",
            "type":"Retail Goods"
        }
    ],
    "sg:phone":"+1 405 743 8400",
    "sg:postcode":"74075",
    "sg:province":"OK",
    "sg:tags":[
        "car",
        "dealer"
    ],
    "wof:name":"Reliable Auto Export",
    "wof:placetype":"venue"
},
  "geometry": {"coordinates":[-97.046794,36.123398],"type":"Point"}
}