{
  "type": "Feature",
  "properties": {
    "addr:full":"1004 E Virginia Ave Stillwater OK 74075",
    "addr:housenumber":"1004",
    "addr:postcode":"74075",
    "addr:street":"E Virginia Ave",
    "iso:country":"US",
    "sg:address":"1004 E Virginia Ave",
    "sg:city":"Stillwater",
    "sg:classifiers":[
        {
            "category":"Autos & Motor Vehicles",
            "subcategory":"Automobile Sales",
            "type":"Retail Goods"
        }
    ],
    "sg:phone":"+1 405 743 8400",
    "sg:postcode":"74075",
    "sg:province":"OK",
    "sg:tags":[
        "car",
        "dealer"
    ],
    "wof:name":"Reliable Auto Export",
    "wof:placetype":"venue"
},
  "geometry": {"coordinates":[-97.04679400000001,36.123398],"type":"Point"}
}