{
  "type": "Feature",
  "properties": {
    "iso:country":"US",
    "sg:address":"205 SW 3rd St",
    "sg:city":"Lindsay",
    "sg:classifiers":[
        {
            "category":"Autos & Motor Vehicles",
            "subcategory":"Automobile Sales",
            "type":"Retail Goods"
        }
    ],
    "sg:phone":"+1 405 756 8485",
    "sg:postcode":"73052",
    "sg:province":"OK",
    "sg:tags":[
        "used"
    ],
    "wof:name":"McCann Auto Sales",
    "wof:placetype":"venue"
},
  "geometry": {"coordinates":[-97.605529,34.835749],"type":"Point"}
}