{
  "type": "Feature",
  "properties": {
    "iso:country":"US",
    "sg:address":"5309 E Marshall St",
    "sg:city":"Tulsa",
    "sg:classifiers":[
        {
            "category":"Freight",
            "type":"Transportation"
        }
    ],
    "sg:phone":"+1 918 834 7416",
    "sg:postcode":"74115",
    "sg:province":"OK",
    "sg:tags":[
        "trucking"
    ],
    "wof:name":"D & L Trucking",
    "wof:placetype":"venue"
},
  "geometry": {"coordinates":[-95.915977,36.171469],"type":"Point"}
}