{
  "type": "Feature",
  "properties": {
    "iso:country":"US",
    "sg:address":"203 N Main St",
    "sg:city":"Coalgate",
    "sg:classifiers":[
        {
            "category":"Retail",
            "subcategory":"Auto Repair",
            "type":"Services"
        }
    ],
    "sg:phone":"+1 580 927 2729",
    "sg:postcode":"74538",
    "sg:province":"OK",
    "sg:tags":[
        "automotive"
    ],
    "wof:name":"Andys Muffler & Alignment",
    "wof:placetype":"venue"
},
  "geometry": {"coordinates":[-96.21802099999999,34.539942],"type":"Point"}
}