{
  "type": "Feature",
  "properties": {
    "iso:country":"US",
    "sg:address":"124 S Main St",
    "sg:city":"Blackwell",
    "sg:classifiers":[
        {
            "category":"Retail",
            "subcategory":"Animal Services",
            "type":"Services"
        }
    ],
    "sg:phone":"+1 580 363 1207",
    "sg:postcode":"74631",
    "sg:province":"OK",
    "sg:tags":[
        "shelter"
    ],
    "wof:name":"Volunteer Friends Of Animals",
    "wof:placetype":"venue"
},
  "geometry": {"coordinates":[-97.282905,36.80404],"type":"Point"}
}