{
  "type": "Feature",
  "properties": {
    "iso:country":"US",
    "sg:address":"504 N McLish Ave",
    "sg:city":"Tishomingo",
    "sg:classifiers":[
        {
            "category":"Organizations",
            "subcategory":"Religious Organization",
            "type":"Services"
        }
    ],
    "sg:phone":"+1 580 371 3409",
    "sg:postcode":"73460",
    "sg:province":"OK",
    "sg:tags":[
        "church"
    ],
    "wof:name":"Victory Tbrncl United Pent Ch",
    "wof:placetype":"venue"
},
  "geometry": {"coordinates":[-96.670367,34.237292],"type":"Point"}
}