{
  "type": "Feature",
  "properties": {
    "addr:full":"710 W Oakland St Broken Arrow OK 74012",
    "addr:housenumber":"710",
    "addr:postcode":"74012",
    "addr:street":"W Oakland St",
    "iso:country":"US",
    "sg:address":"710 W Oakland St",
    "sg:city":"Broken Arrow",
    "sg:classifiers":[
        {
            "category":"Building & Trades",
            "subcategory":"Cleaning & Sanitation",
            "type":"Services"
        }
    ],
    "sg:phone":"+1 918 251 1222",
    "sg:postcode":"74012",
    "sg:province":"OK",
    "sg:tags":[
        "ventilating",
        "system"
    ],
    "wof:name":"All Ducts In A Row",
    "wof:placetype":"venue"
},
  "geometry": {"coordinates":[-95.797561,36.067253],"type":"Point"}
}