{
  "type": "Feature",
  "properties": {
    "iso:country":"US",
    "sg:address":"627 NW 7th St",
    "sg:city":"Moore",
    "sg:classifiers":[
        {
            "category":"Banks & Credit Unions",
            "subcategory":"Bank",
            "type":"Services"
        }
    ],
    "sg:phone":"+1 405 794 0264",
    "sg:postcode":"73160",
    "sg:province":"OK",
    "sg:tags":[
        "loan"
    ],
    "wof:name":"Payday Loans At Loan Mart",
    "wof:placetype":"venue"
},
  "geometry": {"coordinates":[-97.496047,35.345468],"type":"Point"}
}