{
  "type": "Feature",
  "properties": {
    "addr:full":"2207 Creighton Dr Norman OK 73071",
    "addr:housenumber":"2207",
    "addr:postcode":"73071",
    "addr:street":"Creighton Dr",
    "iso:country":"US",
    "sg:address":"2207 Creighton Dr",
    "sg:city":"Norman",
    "sg:classifiers":[
        {
            "category":"Building & Trades",
            "subcategory":"Construction",
            "type":"Services"
        }
    ],
    "sg:phone":"+1 405 447 4909",
    "sg:postcode":"73071",
    "sg:province":"OK",
    "sg:tags":[
        "elevator"
    ],
    "wof:name":"Mc Cain Engineering",
    "wof:placetype":"venue"
},
  "geometry": {"coordinates":[-97.40778899999999,35.239903],"type":"Point"}
}