{
  "type": "Feature",
  "properties": {
    "addr:full":"11 Country Club Rd Shawnee OK 74801",
    "addr:housenumber":"11",
    "addr:postcode":"74801",
    "addr:street":"Country Club Rd",
    "iso:country":"US",
    "sg:address":"11 Country Club Rd",
    "sg:city":"Shawnee",
    "sg:classifiers":[
        {
            "category":"Wholesale",
            "subcategory":"Metals & Minerals",
            "type":"Manufacturing & Wholesale Goods"
        }
    ],
    "sg:phone":"+1 405 273 6200",
    "sg:postcode":"74801",
    "sg:province":"OK",
    "sg:tags":[
        "center"
    ],
    "wof:name":"Lillard Construction Inc",
    "wof:placetype":"venue"
},
  "geometry": {"coordinates":[-96.888513,35.33315],"type":"Point"}
}