{
  "type": "Feature",
  "properties": {
    "addr:full":"102 N Cedar Dr Fletcher OK 73541",
    "addr:housenumber":"102",
    "addr:postcode":"73541",
    "addr:street":"N Cedar Dr",
    "iso:country":"US",
    "sg:address":"102 N Cedar Dr",
    "sg:city":"Fletcher",
    "sg:classifiers":[
        {
            "category":"Professional",
            "type":"Services"
        }
    ],
    "sg:phone":"+1 580 549 6574",
    "sg:postcode":"73541",
    "sg:province":"OK",
    "sg:tags":[
        "arts",
        "artist"
    ],
    "sg:website":"www.mintonart.com",
    "wof:name":"Minton Art",
    "wof:placetype":"venue"
},
  "geometry": {"coordinates":[-98.232592,34.823914],"type":"Point"}
}