{
  "type": "Feature",
  "properties": {
    "iso:country":"US",
    "sg:address":"21401 SE 149th St",
    "sg:city":"Newalla",
    "sg:classifiers":[
        {
            "category":"Retail",
            "subcategory":"Animal Services",
            "type":"Services"
        }
    ],
    "sg:phone":"+1 405 386 7727",
    "sg:postcode":"74857",
    "sg:province":"OK",
    "wof:name":"Dugas Kennel",
    "wof:placetype":"venue"
},
  "geometry": {"coordinates":[-97.154754,35.318765],"type":"Point"}
}