{
  "type": "Feature",
  "properties": {
    "iso:country":"US",
    "sg:address":"2200 SW 74th St",
    "sg:city":"Oklahoma City",
    "sg:classifiers":[
        {
            "category":"Health Services",
            "subcategory":"Optometrist",
            "type":"Services"
        }
    ],
    "sg:phone":"+1 405 681 4500",
    "sg:postcode":"73159",
    "sg:province":"OK",
    "wof:name":"Bogardus Vision Clinic",
    "wof:placetype":"venue"
},
  "geometry": {"coordinates":[-97.551535,35.391028],"type":"Point"}
}