{
  "type": "Feature",
  "properties": {
    "addr:full":"801 S B St Muskogee OK 74403",
    "addr:housenumber":"801",
    "addr:postcode":"74403",
    "addr:street":"S B St",
    "iso:country":"US",
    "sg:address":"801 S B St",
    "sg:city":"Muskogee",
    "sg:classifiers":[
        {
            "category":"Restaurant",
            "type":"Food & Drink"
        }
    ],
    "sg:phone":"+1 918 682 2455",
    "sg:postcode":"74403",
    "sg:province":"OK",
    "sg:tags":[
        "eating"
    ],
    "wof:name":"Doo Dipsy",
    "wof:placetype":"venue"
},
  "geometry": {"coordinates":[-95.36947600000001,35.740023],"type":"Point"}
}