{
  "type": "Feature",
  "properties": {
    "addr:full":"403 S Cheyenne Ave Tulsa OK 74103",
    "addr:housenumber":"403",
    "addr:postcode":"74103",
    "addr:street":"S Cheyenne Ave",
    "iso:country":"US",
    "sg:address":"403 S Cheyenne Ave",
    "sg:city":"Tulsa",
    "sg:classifiers":[
        {
            "category":"Social Services",
            "type":"Services"
        }
    ],
    "sg:phone":"+1 918 582 3887",
    "sg:postcode":"74103",
    "sg:province":"OK",
    "wof:name":"Shannon McMurray",
    "wof:placetype":"venue"
},
  "geometry": {"coordinates":[-95.992375,36.15065],"type":"Point"}
}