{
  "type": "Feature",
  "properties": {
    "iso:country":"US",
    "sg:address":"10435 S Sandusky Ave",
    "sg:city":"Tulsa",
    "sg:classifiers":[
        {
            "category":"Professional",
            "subcategory":"Management & Consulting",
            "type":"Services"
        }
    ],
    "sg:phone":"+1 918 261 2500",
    "sg:postcode":"74137",
    "sg:province":"OK",
    "sg:tags":[
        "business"
    ],
    "wof:name":"Options Net",
    "wof:placetype":"venue"
},
  "geometry": {"coordinates":[-95.92719,36.012061],"type":"Point"}
}