{
  "type": "Feature",
  "properties": {
    "iso:country":"US",
    "sg:address":"2751 W 111th Pl",
    "sg:city":"Jenks",
    "sg:classifiers":[
        {
            "category":"Retail",
            "subcategory":"Laundry & Dry Cleaning",
            "type":"Services"
        }
    ],
    "sg:phone":"+1 918 298 9100",
    "sg:postcode":"74037",
    "sg:province":"OK",
    "wof:name":"Dannie Interprises Inc",
    "wof:placetype":"venue"
},
  "geometry": {"coordinates":[-96.008106,36.002424],"type":"Point"}
}