{
  "type": "Feature",
  "properties": {
    "addr:full":"4705 S Elm Pl Broken Arrow OK 74011",
    "addr:housenumber":"4705",
    "addr:postcode":"74011",
    "addr:street":"S Elm Pl",
    "iso:country":"US",
    "sg:address":"4705 S Elm Pl",
    "sg:city":"Broken Arrow",
    "sg:classifiers":[
        {
            "category":"Food & Beverages",
            "subcategory":"Groceries & Convenience Stores",
            "type":"Retail Goods"
        }
    ],
    "sg:phone":"+1 918 455 8349",
    "sg:postcode":"74011",
    "sg:province":"OK",
    "sg:website":"www.quiktrip.com",
    "wof:name":"Quik Trip",
    "wof:placetype":"venue"
},
  "geometry": {"coordinates":[-95.797481,36.004186],"type":"Point"}
}