{
  "type": "Feature",
  "properties": {
    "iso:country":"US",
    "sg:address":"11702 E 101st St N",
    "sg:city":"Owasso",
    "sg:classifiers":[
        {
            "category":"Building & Trades",
            "subcategory":"Construction",
            "type":"Services"
        }
    ],
    "sg:phone":"+1 918 274 4740",
    "sg:postcode":"74055",
    "sg:province":"OK",
    "sg:tags":[
        "floor",
        "laying",
        "contractor"
    ],
    "wof:name":"Endurance Hardwood Floors LLC",
    "wof:placetype":"venue"
},
  "geometry": {"coordinates":[-95.845829,36.299993],"type":"Point"}
}