{
  "type": "Feature",
  "properties": {
    "iso:country":"US",
    "sg:address":"27212 S 4170 Rd",
    "sg:city":"Inola",
    "sg:classifiers":[
        {
            "category":"Building & Trades",
            "subcategory":"Plumbing",
            "type":"Services"
        }
    ],
    "sg:phone":"+1 918 663 8677",
    "sg:postcode":"74036",
    "sg:province":"OK",
    "sg:tags":[
        "contractor"
    ],
    "wof:name":"Riggs Heating & Air",
    "wof:placetype":"venue"
},
  "geometry": {"coordinates":[-95.58307000000001,36.217389],"type":"Point"}
}