{
  "type": "Feature",
  "properties": {
    "iso:country":"US",
    "sg:address":"1409 Arlington St",
    "sg:city":"Ada",
    "sg:classifiers":[
        {
            "category":"Building & Trades",
            "subcategory":"Construction",
            "type":"Services"
        }
    ],
    "sg:phone":"+1 580 332 6475",
    "sg:postcode":"74820",
    "sg:province":"OK",
    "sg:tags":[
        "hanging",
        "contractor"
    ],
    "wof:name":"Sunteleo Products",
    "wof:placetype":"venue"
},
  "geometry": {"coordinates":[-96.658411,34.781565],"type":"Point"}
}