{
  "type": "Feature",
  "properties": {
    "iso:country":"US",
    "sg:address":"9119 E 61st St",
    "sg:city":"Tulsa",
    "sg:classifiers":[
        {
            "category":"Organizations",
            "subcategory":"Religious Organization",
            "type":"Services"
        }
    ],
    "sg:phone":"+1 918 252 1220",
    "sg:postcode":"74133",
    "sg:province":"OK",
    "sg:tags":[
        "church"
    ],
    "wof:name":"Woodland Hills Church Christ",
    "wof:placetype":"venue"
},
  "geometry": {"coordinates":[-95.873255,36.075501],"type":"Point"}
}