{
  "type": "Feature",
  "properties": {
    "iso:country":"US",
    "sg:address":"5915 NW 23rd St",
    "sg:city":"Oklahoma City",
    "sg:classifiers":[
        {
            "category":"Organizations",
            "subcategory":"Membership Organization",
            "type":"Services"
        }
    ],
    "sg:phone":"+1 405 495 2732",
    "sg:postcode":"73127",
    "sg:province":"OK",
    "wof:name":"AIDS Information Line",
    "wof:placetype":"venue"
},
  "geometry": {"coordinates":[-97.621545,35.493351],"type":"Point"}
}