{
  "type": "Feature",
  "properties": {
    "iso:country":"US",
    "sg:address":"7101 NW 23rd St",
    "sg:city":"Bethany",
    "sg:classifiers":[
        {
            "category":"Banks & Credit Unions",
            "subcategory":"Bank",
            "type":"Services"
        }
    ],
    "sg:phone":"+1 405 272 2548",
    "sg:postcode":"73008",
    "sg:province":"OK",
    "wof:name":"Bank Of Oklahoma",
    "wof:placetype":"venue"
},
  "geometry": {"coordinates":[-97.641049,35.493387],"type":"Point"}
}