{
  "type": "Feature",
  "properties": {
    "addr:full":"1320 S Broadway Edmond OK 73034",
    "addr:housenumber":"1320",
    "addr:postcode":"73034",
    "addr:street":"S Broadway",
    "iso:country":"US",
    "sg:address":"1320 S Broadway",
    "sg:city":"Edmond",
    "sg:classifiers":[
        {
            "category":"Restaurant",
            "type":"Food & Drink"
        }
    ],
    "sg:phone":"+1 405 340 3871",
    "sg:postcode":"73034",
    "sg:province":"OK",
    "sg:tags":[
        "eating"
    ],
    "wof:name":"Blue Moon Restaurant",
    "wof:placetype":"venue"
},
  "geometry": {"coordinates":[-97.48298200000001,35.639684],"type":"Point"}
}