{
  "type": "Feature",
  "properties": {
    "iso:country":"US",
    "sg:address":"329 NW 4th St",
    "sg:city":"Oklahoma City",
    "sg:classifiers":[
        {
            "category":"Banks & Credit Unions",
            "subcategory":"Bank",
            "type":"Services"
        }
    ],
    "sg:phone":"+1 405 236 3072",
    "sg:postcode":"73102",
    "sg:province":"OK",
    "sg:tags":[
        "loan"
    ],
    "wof:name":"Main Finance Co",
    "wof:placetype":"venue"
},
  "geometry": {"coordinates":[-97.51896600000001,35.472076],"type":"Point"}
}