{
  "type": "Feature",
  "properties": {
    "iso:country":"US",
    "sg:address":"5319 Gaillardia Blvd",
    "sg:city":"Oklahoma City",
    "sg:classifiers":[
        {
            "category":"Education",
            "subcategory":"Special Training",
            "type":"Public Place"
        }
    ],
    "sg:phone":"+1 405 286 4070",
    "sg:postcode":"73142",
    "sg:province":"OK",
    "sg:tags":[
        "center"
    ],
    "wof:name":"Gaillardia Learning Ctr",
    "wof:placetype":"venue"
},
  "geometry": {"coordinates":[-97.617276,35.613305],"type":"Point"}
}