{
  "type": "Feature",
  "properties": {
    "addr:full":"1905 Pamela Ln Weatherford OK 73096",
    "addr:housenumber":"1905",
    "addr:postcode":"73096",
    "addr:street":"Pamela Ln",
    "iso:country":"US",
    "sg:address":"1905 Pamela Ln",
    "sg:city":"Weatherford",
    "sg:classifiers":[
        {
            "category":"Building & Trades",
            "subcategory":"Construction",
            "type":"Services"
        }
    ],
    "sg:phone":"+1 580 772 6485",
    "sg:postcode":"73096",
    "sg:province":"OK",
    "sg:tags":[
        "house"
    ],
    "wof:name":"Cornelson Trim & Cabinets",
    "wof:placetype":"venue"
},
  "geometry": {"coordinates":[-98.68781,35.545824],"type":"Point"}
}