{
  "type": "Feature",
  "properties": {
    "iso:country":"US",
    "sg:address":"3181 S Ranch Dr",
    "sg:city":"Ponca City",
    "sg:classifiers":[
        {
            "category":"Retail",
            "subcategory":"Animal Services",
            "type":"Services"
        }
    ],
    "sg:phone":"+1 580 762 3464",
    "sg:postcode":"74601",
    "sg:province":"OK",
    "wof:name":"Tuck-A-Way",
    "wof:placetype":"venue"
},
  "geometry": {"coordinates":[-97.138677,36.678261],"type":"Point"}
}