{
  "type": "Feature",
  "properties": {
    "addr:full":"1408 S Denver Ave Tulsa OK 74119",
    "addr:housenumber":"1408",
    "addr:postcode":"74119",
    "addr:street":"S Denver Ave",
    "iso:country":"US",
    "sg:address":"1408 S Denver Ave",
    "sg:city":"Tulsa",
    "sg:classifiers":[
        {
            "category":"Banks & Credit Unions",
            "subcategory":"Bank",
            "type":"Services"
        }
    ],
    "sg:phone":"+1 918 877 1424",
    "sg:postcode":"74119",
    "sg:province":"OK",
    "sg:tags":[
        "loan",
        "real estate"
    ],
    "wof:name":"Capital Equity Funding",
    "wof:placetype":"venue"
},
  "geometry": {"coordinates":[-95.99247,36.14181],"type":"Point"}
}