{
  "type": "Feature",
  "properties": {
    "iso:country":"US",
    "sg:address":"1312 S Morgan Rd",
    "sg:city":"Oklahoma City",
    "sg:classifiers":[
        {
            "category":"Food & Beverages",
            "subcategory":"Liquor & Beverages",
            "type":"Retail Goods"
        }
    ],
    "sg:phone":"+1 405 495 8066",
    "sg:postcode":"73128",
    "sg:province":"OK",
    "sg:tags":[
        "alcoholic"
    ],
    "wof:name":"Westbury Liquor",
    "wof:placetype":"venue"
},
  "geometry": {"coordinates":[-97.68910200000001,35.455007],"type":"Point"}
}