{
  "type": "Feature",
  "properties": {
    "addr:full":"1105 N 9th St Blackwell OK 74631",
    "addr:housenumber":"1105",
    "addr:postcode":"74631",
    "addr:street":"N 9Th St",
    "iso:country":"US",
    "sg:address":"1105 N 9th St",
    "sg:city":"Blackwell",
    "sg:classifiers":[
        {
            "category":"Utilities",
            "subcategory":"Cable",
            "type":"Services"
        }
    ],
    "sg:phone":"+1 580 363 1870",
    "sg:postcode":"74631",
    "sg:province":"OK",
    "sg:tags":[
        "television"
    ],
    "wof:name":"Cox Communications",
    "wof:placetype":"venue"
},
  "geometry": {"coordinates":[-97.29635500000001,36.816885],"type":"Point"}
}