{
  "type": "Feature",
  "properties": {
    "iso:country":"US",
    "sg:address":"4900 Richmond Sq",
    "sg:city":"Oklahoma City",
    "sg:classifiers":[
        {
            "category":"Organizations",
            "subcategory":"Non-profit Organization",
            "type":"Services"
        }
    ],
    "sg:phone":"+1 405 842 1200",
    "sg:postcode":"73118",
    "sg:province":"OK",
    "sg:tags":[
        "information",
        "alcoholism",
        "treatment"
    ],
    "wof:name":"A A Area Committee",
    "wof:placetype":"venue"
},
  "geometry": {"coordinates":[-97.539574,35.521752],"type":"Point"}
}