{
  "type": "Feature",
  "properties": {
    "iso:country":"US",
    "sg:address":"400 N Pennsylvania Ave",
    "sg:city":"Mangum",
    "sg:classifiers":[
        {
            "category":"Education",
            "subcategory":"School",
            "type":"Public Place"
        }
    ],
    "sg:phone":"+1 580 782 3371",
    "sg:postcode":"73554",
    "sg:province":"OK",
    "wof:name":"Mangum Superintendent-Schools",
    "wof:placetype":"venue"
},
  "geometry": {"coordinates":[-99.504351,34.878475],"type":"Point"}
}