{
  "type": "Feature",
  "properties": {
    "iso:country":"US",
    "sg:address":"1919 N Willow Ave",
    "sg:city":"Broken Arrow",
    "sg:classifiers":[
        {
            "category":"Shopping",
            "type":"Retail Goods"
        }
    ],
    "sg:phone":"+1 918 294 1777",
    "sg:postcode":"74012",
    "sg:province":"OK",
    "sg:tags":[
        "sell",
        "printer",
        "la",
        "support",
        "equipment",
        "electronic",
        "po"
    ],
    "wof:name":"Bottom Line Solutions",
    "wof:placetype":"venue"
},
  "geometry": {"coordinates":[-95.838619,36.069895],"type":"Point"}
}