{
  "type": "Feature",
  "properties": {
    "iso:country":"US",
    "sg:address":"4820 W Reno Ave",
    "sg:city":"Oklahoma City",
    "sg:classifiers":[
        {
            "category":"Travel",
            "subcategory":"Hotels & Motels",
            "type":"Entertainment"
        }
    ],
    "sg:phone":"+1 405 948 4443",
    "sg:postcode":"73127",
    "sg:province":"OK",
    "wof:name":"Extended Stay America",
    "wof:placetype":"venue"
},
  "geometry": {"coordinates":[-97.604999,35.464069],"type":"Point"}
}