{
  "type": "Feature",
  "properties": {
    "addr:full":"1309 N Youngs Blvd Oklahoma City OK 73107",
    "addr:housenumber":"1309",
    "addr:postcode":"73107",
    "addr:street":"N Youngs Blvd",
    "iso:country":"US",
    "sg:address":"1309 N Youngs Blvd",
    "sg:city":"Oklahoma City",
    "sg:classifiers":[
        {
            "category":"Professional",
            "subcategory":"Management & Consulting",
            "type":"Services"
        }
    ],
    "sg:phone":"+1 405 528 1712",
    "sg:postcode":"73107",
    "sg:province":"OK",
    "sg:tags":[
        "consultant",
        "business"
    ],
    "wof:name":"Red River Consultants",
    "wof:placetype":"venue"
},
  "geometry": {"coordinates":[-97.55221899999999,35.482765],"type":"Point"}
}