{
  "type": "Feature",
  "properties": {
    "iso:country":"US",
    "sg:address":"1441 N Key Blvd",
    "sg:city":"Oklahoma City",
    "sg:classifiers":[
        {
            "category":"Organizations",
            "subcategory":"Professional Association",
            "type":"Services"
        }
    ],
    "sg:phone":"+1 405 737 6788",
    "sg:postcode":"73110",
    "sg:province":"OK",
    "sg:tags":[
        "business"
    ],
    "wof:name":"Midwest Cy Cncil of Grdn Clubs",
    "wof:placetype":"venue"
},
  "geometry": {"coordinates":[-97.392004,35.451164],"type":"Point"}
}