{
  "type": "Feature",
  "properties": {
    "iso:country":"US",
    "sg:address":"502 S Main St",
    "sg:city":"Tulsa",
    "sg:classifiers":[
        {
            "category":"Building & Trades",
            "subcategory":"Construction",
            "type":"Services"
        }
    ],
    "sg:phone":"+1 918 583 3057",
    "sg:postcode":"74103",
    "sg:province":"OK",
    "wof:name":"Ch2m Hill",
    "wof:placetype":"venue"
},
  "geometry": {"coordinates":[-95.989602,36.15049],"type":"Point"}
}