{
  "type": "Feature",
  "properties": {
    "iso:country":"US",
    "sg:address":"110 Worley Creek Ln",
    "sg:city":"Tuttle",
    "sg:classifiers":[
        {
            "category":"Mining & Drilling",
            "type":"Manufacturing & Wholesale Goods"
        }
    ],
    "sg:phone":"+1 405 381 4007",
    "sg:postcode":"73089",
    "sg:province":"OK",
    "sg:tags":[
        "well"
    ],
    "wof:name":"Energy Drilling",
    "wof:placetype":"venue"
},
  "geometry": {"coordinates":[-97.75576700000001,35.293491],"type":"Point"}
}