{
  "type": "Feature",
  "properties": {
    "iso:country":"US",
    "sg:address":"102 S Broadway St",
    "sg:city":"Tecumseh",
    "sg:classifiers":[
        {
            "category":"Shopping",
            "subcategory":"Used Merchandise",
            "type":"Retail Goods"
        }
    ],
    "sg:phone":"+1 405 598 6293",
    "sg:postcode":"74873",
    "sg:province":"OK",
    "sg:tags":[
        "pawnbroker"
    ],
    "wof:name":"R & D Pawn",
    "wof:placetype":"venue"
},
  "geometry": {"coordinates":[-96.936856,35.257646],"type":"Point"}
}