{
  "type": "Feature",
  "properties": {
    "iso:country":"US",
    "sg:address":"119 N Robinson Ave",
    "sg:city":"Oklahoma City",
    "sg:classifiers":[
        {
            "category":"Arena",
            "subcategory":"Sports Club",
            "type":"Entertainment"
        }
    ],
    "sg:phone":"+1 405 684 2237",
    "sg:postcode":"73102",
    "sg:province":"OK",
    "sg:tags":[
        "manager",
        "recruiter",
        "promoter"
    ],
    "wof:name":"Express Sports",
    "wof:placetype":"venue"
},
  "geometry": {"coordinates":[-97.516494,35.468616],"type":"Point"}
}