{
  "type": "Feature",
  "properties": {
    "iso:country":"US",
    "sg:address":"7001 N May Ave",
    "sg:city":"Oklahoma City",
    "sg:classifiers":[
        {
            "category":"Wholesale",
            "subcategory":"Non-durable Goods",
            "type":"Manufacturing & Wholesale Goods"
        }
    ],
    "sg:phone":"+1 405 286 3440",
    "sg:postcode":"73116",
    "sg:province":"OK",
    "sg:tags":[
        "fund",
        "raising",
        "merchandise"
    ],
    "wof:name":"Educational Products Inc",
    "wof:placetype":"venue"
},
  "geometry": {"coordinates":[-97.565753,35.541972],"type":"Point"}
}