{
  "type": "Feature",
  "properties": {
    "iso:country":"US",
    "sg:address":"201 S Main St",
    "sg:city":"Bixby",
    "sg:classifiers":[
        {
            "category":"Education",
            "subcategory":"School",
            "type":"Public Place"
        }
    ],
    "sg:phone":"+1 918 366 2281",
    "sg:postcode":"74008",
    "sg:province":"OK",
    "sg:website":"www.bixbyps.org",
    "wof:name":"Central Elementary",
    "wof:placetype":"venue"
},
  "geometry": {"coordinates":[-95.880823,35.938081],"type":"Point"}
}