{
  "type": "Feature",
  "properties": {
    "iso:country":"US",
    "sg:address":"4045 N Cincinnati Ave",
    "sg:city":"Tulsa",
    "sg:classifiers":[
        {
            "category":"Organizations",
            "subcategory":"Religious Organization",
            "type":"Services"
        }
    ],
    "sg:phone":"+1 918 425 7882",
    "sg:postcode":"74106",
    "sg:province":"OK",
    "sg:tags":[
        "church"
    ],
    "wof:name":"St Aidan's Episcopal Church",
    "wof:placetype":"venue"
},
  "geometry": {"coordinates":[-95.993403,36.208774],"type":"Point"}
}