{
  "type": "Feature",
  "properties": {
    "addr:full":"2117 N Broadway St Poteau OK 74953",
    "addr:housenumber":"2117",
    "addr:postcode":"74953",
    "addr:street":"N Broadway St",
    "iso:country":"US",
    "sg:address":"2117 N Broadway St",
    "sg:city":"Poteau",
    "sg:classifiers":[
        {
            "category":"Autos & Motor Vehicles",
            "subcategory":"Automobile Sales",
            "type":"Retail Goods"
        }
    ],
    "sg:phone":"+1 918 647 8388",
    "sg:postcode":"74953",
    "sg:province":"OK",
    "sg:tags":[
        "car",
        "dealer"
    ],
    "wof:name":"Baker's Auto Sales",
    "wof:placetype":"venue"
},
  "geometry": {"coordinates":[-94.620745,35.063333],"type":"Point"}
}