{
  "type": "Feature",
  "properties": {
    "addr:full":"205 S 6th St Bache OK 74501",
    "addr:housenumber":"205",
    "addr:postcode":"74501",
    "addr:street":"S 6Th St",
    "iso:country":"US",
    "sg:address":"205 S 6th St",
    "sg:city":"Bache",
    "sg:classifiers":[
        {
            "category":"Building & Trades",
            "subcategory":"Equipment Rental",
            "type":"Services"
        }
    ],
    "sg:phone":"+1 918 426 0051",
    "sg:postcode":"74501",
    "sg:province":"OK",
    "sg:tags":[
        "television",
        "appliance",
        "stereo"
    ],
    "wof:name":"Colortyme T V Rental",
    "wof:placetype":"venue"
},
  "geometry": {"coordinates":[-95.762835,34.928196],"type":"Point"}
}