{
  "type": "Feature",
  "properties": {
    "iso:country":"US",
    "sg:address":"2222 Southwest Blvd",
    "sg:city":"Tulsa",
    "sg:classifiers":[
        {
            "category":"Professional",
            "type":"Services"
        }
    ],
    "sg:phone":"+1 918 582 3723",
    "sg:postcode":"74107",
    "sg:province":"OK",
    "sg:tags":[
        "establishment"
    ],
    "wof:name":"Truck Parts & Equipment",
    "wof:placetype":"venue"
},
  "geometry": {"coordinates":[-96.007003,36.131489],"type":"Point"}
}