{
  "type": "Feature",
  "properties": {
    "iso:country":"US",
    "sg:address":"6820 E 57th Pl",
    "sg:city":"Tulsa",
    "sg:classifiers":[
        {
            "category":"Shopping",
            "subcategory":"Books",
            "type":"Retail Goods"
        }
    ],
    "sg:phone":"+1 918 496 6869",
    "sg:postcode":"74145",
    "sg:province":"OK",
    "wof:name":"New Millennium Studio 2",
    "wof:placetype":"venue"
},
  "geometry": {"coordinates":[-95.899567,36.080808],"type":"Point"}
}