{
  "type": "Feature",
  "properties": {
    "iso:country":"US",
    "sg:address":"5314 S Yale Ave",
    "sg:city":"Tulsa",
    "sg:classifiers":[
        {
            "category":"Professional",
            "subcategory":"Lawyer & Legal Services",
            "type":"Services"
        }
    ],
    "sg:phone":"+1 918 496 9258",
    "sg:postcode":"74135",
    "sg:province":"OK",
    "wof:name":"Holtz Lloyd K",
    "wof:placetype":"venue"
},
  "geometry": {"coordinates":[-95.922293,36.088496],"type":"Point"}
}