{
  "type": "Feature",
  "properties": {
    "iso:country":"US",
    "sg:address":"550 E Memorial Rd",
    "sg:city":"Oklahoma City",
    "sg:classifiers":[
        {
            "category":"Food & Beverages",
            "subcategory":"Specialty",
            "type":"Retail Goods"
        }
    ],
    "sg:phone":"+1 405 748 6296",
    "sg:postcode":"73114",
    "sg:province":"OK",
    "sg:tags":[
        "health",
        "diet"
    ],
    "wof:name":"Max Muscle Of Ok",
    "wof:placetype":"venue"
},
  "geometry": {"coordinates":[-97.50421,35.60908],"type":"Point"}
}