{
  "type": "Feature",
  "properties": {
    "iso:country":"US",
    "sg:address":"604 Lakeside Cir",
    "sg:city":"Edmond",
    "sg:classifiers":[
        {
            "category":"Communications",
            "subcategory":"Film & Video Production",
            "type":"Services"
        }
    ],
    "sg:phone":"+1 405 341 3447",
    "sg:postcode":"73012",
    "sg:province":"OK",
    "sg:tags":[
        "motion"
    ],
    "wof:name":"Solid Rock Video Creations",
    "wof:placetype":"venue"
},
  "geometry": {"coordinates":[-97.519285,35.650164],"type":"Point"}
}