{
  "type": "Feature",
  "properties": {
    "addr:full":"233 W 2nd St Hennessey OK 73742",
    "addr:housenumber":"233",
    "addr:postcode":"73742",
    "addr:street":"W 2Nd St",
    "iso:country":"US",
    "sg:address":"233 W 2nd St",
    "sg:city":"Hennessey",
    "sg:classifiers":[
        {
            "category":"Farming",
            "subcategory":"Farm & Veterinary Services",
            "type":"Manufacturing & Wholesale Goods"
        }
    ],
    "sg:phone":"+1 405 853 2244",
    "sg:postcode":"73742",
    "sg:province":"OK",
    "sg:tags":[
        "preparation",
        "crop",
        "for",
        "market"
    ],
    "wof:name":"Eckroat Inc-J Lee",
    "wof:placetype":"venue"
},
  "geometry": {"coordinates":[-97.90138,36.107418],"type":"Point"}
}