{
  "type": "Feature",
  "properties": {
    "iso:country":"US",
    "sg:address":"415 S Birch St",
    "sg:city":"Sapulpa",
    "sg:classifiers":[
        {
            "category":"Food & Beverages",
            "subcategory":"Bakery",
            "type":"Retail Goods"
        }
    ],
    "sg:phone":"+1 918 224 5522",
    "sg:postcode":"74066",
    "sg:province":"OK",
    "sg:tags":[
        "baker"
    ],
    "wof:name":"Will's Bake Shop",
    "wof:placetype":"venue"
},
  "geometry": {"coordinates":[-96.102782,35.993448],"type":"Point"}
}