{
  "type": "Feature",
  "properties": {
    "iso:country":"US",
    "sg:address":"916 W Britton Rd",
    "sg:city":"Oklahoma City",
    "sg:classifiers":[
        {
            "category":"Retail",
            "subcategory":"Repair Shop",
            "type":"Services"
        }
    ],
    "sg:phone":"+1 405 848 0146",
    "sg:postcode":"73114",
    "sg:province":"OK",
    "sg:tags":[
        "upholstery",
        "furniture"
    ],
    "wof:name":"Braggs Upholstery",
    "wof:placetype":"venue"
},
  "geometry": {"coordinates":[-97.529919,35.565468],"type":"Point"}
}