{
  "type": "Feature",
  "properties": {
    "addr:full":"11517 S Portland Ave Oklahoma City OK 73170",
    "addr:housenumber":"11517",
    "addr:postcode":"73170",
    "addr:street":"S Portland Ave",
    "iso:country":"US",
    "sg:address":"11517 S Portland Ave",
    "sg:city":"Oklahoma City",
    "sg:classifiers":[
        {
            "category":"Autos & Motor Vehicles",
            "subcategory":"Recreational Vehicle Sales",
            "type":"Retail Goods"
        }
    ],
    "sg:phone":"+1 405 692 7242",
    "sg:postcode":"73170",
    "sg:province":"OK",
    "sg:tags":[
        "parts",
        "trailer"
    ],
    "sg:website":"www.trailers-parts.com",
    "wof:name":"Trailers Parts Svc",
    "wof:placetype":"venue"
},
  "geometry": {"coordinates":[-97.580035,35.362834],"type":"Point"}
}