{
  "type": "Feature",
  "properties": {
    "addr:full":"2713 Appaloosa Trl Edmond OK 73012",
    "addr:housenumber":"2713",
    "addr:postcode":"73012",
    "addr:street":"Appaloosa Trl",
    "iso:country":"US",
    "sg:address":"2713 Appaloosa Trl",
    "sg:city":"Edmond",
    "sg:classifiers":[
        {
            "category":"Shopping",
            "subcategory":"Gifts & Souvenirs",
            "type":"Retail Goods"
        }
    ],
    "sg:phone":"+1 405 751 3865",
    "sg:postcode":"73012",
    "sg:province":"OK",
    "wof:name":"Dunk Tanks Etc",
    "wof:placetype":"venue"
},
  "geometry": {"coordinates":[-97.52211,35.645099],"type":"Point"}
}