{
  "type": "Feature",
  "properties": {
    "iso:country":"US",
    "sg:address":"1 N Main St",
    "sg:city":"Miami",
    "sg:classifiers":[
        {
            "category":"Shopping",
            "subcategory":"Discount & Variety Stores",
            "type":"Retail Goods"
        }
    ],
    "sg:phone":"+1 918 541 1999",
    "sg:postcode":"74354",
    "sg:province":"OK",
    "sg:tags":[
        "merchandise",
        "general"
    ],
    "wof:name":"Hamilton Auto Sales",
    "wof:placetype":"venue"
},
  "geometry": {"coordinates":[-94.87751,36.87622],"type":"Point"}
}