{
  "type": "Feature",
  "properties": {
    "iso:country":"US",
    "sg:address":"6818 E 65th Pl",
    "sg:city":"Tulsa",
    "sg:classifiers":[
        {
            "category":"Shopping",
            "type":"Retail Goods"
        }
    ],
    "sg:phone":"+1 918 493 2486",
    "sg:postcode":"74133",
    "sg:province":"OK",
    "sg:tags":[
        "picture",
        "frame"
    ],
    "wof:name":"A Matter Of Art",
    "wof:placetype":"venue"
},
  "geometry": {"coordinates":[-95.901887,36.068526],"type":"Point"}
}