{
  "type": "Feature",
  "properties": {
    "iso:country":"US",
    "sg:address":"300 S Madison Blvd",
    "sg:city":"Bartlesville",
    "sg:classifiers":[
        {
            "category":"Organizations",
            "subcategory":"Religious Organization",
            "type":"Services"
        }
    ],
    "sg:phone":"+1 918 335 0560",
    "sg:postcode":"74006",
    "sg:province":"OK",
    "sg:tags":[
        "church"
    ],
    "wof:name":"Our Saviour's Lutheran Church",
    "wof:placetype":"venue"
},
  "geometry": {"coordinates":[-95.917186,36.753009],"type":"Point"}
}