{
  "type": "Feature",
  "properties": {
    "iso:country":"US",
    "sg:address":"4720 N Walnut Ave",
    "sg:city":"Oklahoma City",
    "sg:classifiers":[
        {
            "category":"Professional",
            "subcategory":"Business Services",
            "type":"Services"
        }
    ],
    "sg:phone":"+1 405 521 8214",
    "sg:postcode":"73105",
    "sg:province":"OK",
    "sg:tags":[
        "interior",
        "consultant",
        "design",
        "decorator"
    ],
    "wof:name":"Charles Corken & Assoc Inc",
    "wof:placetype":"venue"
},
  "geometry": {"coordinates":[-97.507622,35.519374],"type":"Point"}
}