{
  "type": "Feature",
  "properties": {
    "iso:country":"US",
    "sg:address":"1127 S Columbia Ave",
    "sg:city":"Tulsa",
    "sg:classifiers":[
        {
            "category":"Education",
            "subcategory":"School",
            "type":"Public Place"
        },
        {
            "category":"Government",
            "subcategory":"Office",
            "type":"Public Place"
        }
    ],
    "sg:phone":"+1 918 833 9340",
    "sg:postcode":"74104",
    "sg:province":"OK",
    "sg:tags":[
        "parish",
        "government-county",
        "middle"
    ],
    "sg:website":"http://www.carnegieelementary.com",
    "wof:name":"Wilson Middle School",
    "wof:placetype":"venue"
},
  "geometry": {"coordinates":[-95.951519,36.14732],"type":"Point"}
}