{
  "type": "Feature",
  "properties": {
    "iso:country":"US",
    "sg:address":"110 Peters St",
    "sg:city":"Poteau",
    "sg:classifiers":[
        {
            "category":"Government",
            "subcategory":"Police Station",
            "type":"Public Place"
        }
    ],
    "sg:phone":"+1 918 647 8620",
    "sg:postcode":"74953",
    "sg:province":"OK",
    "sg:tags":[
        "department",
        "protection"
    ],
    "wof:name":"Poteau Police Department",
    "wof:placetype":"venue"
},
  "geometry": {"coordinates":[-94.622958,35.053267],"type":"Point"}
}