{
  "type": "Feature",
  "properties": {
    "addr:full":"19769 E 114th St Broken Arrow OK 74014",
    "addr:housenumber":"19769",
    "addr:postcode":"74014",
    "addr:street":"E 114Th St",
    "iso:country":"US",
    "sg:address":"19769 E 114th St",
    "sg:city":"Broken Arrow",
    "sg:classifiers":[
        {
            "category":"Professional",
            "subcategory":"Business Services",
            "type":"Services"
        }
    ],
    "sg:phone":"+1 918 451 0871",
    "sg:postcode":"74014",
    "sg:province":"OK",
    "wof:name":"Toto & Co",
    "wof:placetype":"venue"
},
  "geometry": {"coordinates":[-95.75589600000001,35.997644],"type":"Point"}
}