{
  "type": "Feature",
  "properties": {
    "iso:country":"US",
    "sg:address":"1019 Honor Heights Dr",
    "sg:city":"Muskogee",
    "sg:classifiers":[
        {
            "category":"Museum",
            "type":"Entertainment"
        }
    ],
    "sg:phone":"+1 918 683 1701",
    "sg:postcode":"74401",
    "sg:province":"OK",
    "sg:website":"www.fivetribes.com",
    "wof:name":"Five Civilized Tribes Museum",
    "wof:placetype":"venue"
},
  "geometry": {"coordinates":[-95.413212,35.763381],"type":"Point"}
}