{
  "type": "Feature",
  "properties": {
    "iso:country":"US",
    "sg:address":"1609 Robison St NW",
    "sg:city":"Ardmore",
    "sg:classifiers":[
        {
            "category":"Organizations",
            "subcategory":"Religious Organization",
            "type":"Services"
        }
    ],
    "sg:phone":"+1 580 223 1691",
    "sg:postcode":"73401",
    "sg:province":"OK",
    "wof:name":"N W Baptist Church",
    "wof:placetype":"venue"
},
  "geometry": {"coordinates":[-97.138073,34.192538],"type":"Point"}
}