{
  "type": "Feature",
  "properties": {
    "addr:full":"1110 Keystone Expy Sand Springs OK 74063",
    "addr:housenumber":"1110",
    "addr:postcode":"74063",
    "addr:street":"Keystone Expy",
    "iso:country":"US",
    "sg:address":"1110 Keystone Expy",
    "sg:city":"Sand Springs",
    "sg:classifiers":[
        {
            "category":"Autos & Motor Vehicles",
            "subcategory":"Automobile Sales",
            "type":"Retail Goods"
        }
    ],
    "sg:phone":"+1 918 241 6800",
    "sg:postcode":"74063",
    "sg:province":"OK",
    "sg:tags":[
        "performance",
        "race",
        "dealer"
    ],
    "wof:name":"Ozark Legends Racing",
    "wof:placetype":"venue"
},
  "geometry": {"coordinates":[-96.13034500000001,36.141248],"type":"Point"}
}