{
  "type": "Feature",
  "properties": {
    "iso:country":"US",
    "sg:address":"6223 N Meridian Ave",
    "sg:city":"Oklahoma City",
    "sg:classifiers":[
        {
            "category":"Restaurant",
            "type":"Food & Drink"
        }
    ],
    "sg:menulink":"http://www.allmenus.com/ok/oklahoma-city/144541-subway/menu/",
    "sg:phone":"+1 405 773 8103",
    "sg:postcode":"73112",
    "sg:province":"OK",
    "sg:tags":[
        "american",
        "sandwich"
    ],
    "wof:name":"Subway",
    "wof:placetype":"venue"
},
  "geometry": {"coordinates":[-97.601083,35.535207],"type":"Point"}
}