{
  "type": "Feature",
  "properties": {
    "iso:country":"US",
    "sg:address":"524 N Milt Phillips Ave",
    "sg:city":"Seminole",
    "sg:classifiers":[
        {
            "category":"Banks & Credit Unions",
            "subcategory":"Bank",
            "type":"Services"
        }
    ],
    "sg:phone":"+1 405 382 2660",
    "sg:postcode":"74868",
    "sg:province":"OK",
    "sg:tags":[
        "small",
        "loan"
    ],
    "wof:name":"Security Finance Corp Oklahoma",
    "wof:placetype":"venue"
},
  "geometry": {"coordinates":[-96.670968,35.227725],"type":"Point"}
}