{
  "type": "Feature",
  "properties": {
    "iso:country":"US",
    "sg:address":"333 NW 92nd St",
    "sg:city":"Oklahoma City",
    "sg:classifiers":[
        {
            "category":"Government",
            "subcategory":"Fire Station",
            "type":"Public Place"
        }
    ],
    "sg:phone":"+1 405 841 2401",
    "sg:postcode":"73114",
    "sg:province":"OK",
    "sg:tags":[
        "department"
    ],
    "wof:name":"Fire Station 22",
    "wof:placetype":"venue"
},
  "geometry": {"coordinates":[-97.519534,35.564662],"type":"Point"}
}