{
  "type": "Feature",
  "properties": {
    "addr:full":"901 N Veterans Dr Altus OK 73521",
    "addr:housenumber":"901",
    "addr:postcode":"73521",
    "addr:street":"N Veterans Dr",
    "iso:country":"US",
    "sg:address":"901 N Veterans Dr",
    "sg:city":"Altus",
    "sg:classifiers":[
        {
            "category":"Government",
            "subcategory":"Police Station",
            "type":"Public Place"
        }
    ],
    "sg:phone":"+1 580 477 2764",
    "sg:postcode":"73521",
    "sg:province":"OK",
    "sg:tags":[
        "state"
    ],
    "wof:name":"Highway Patrol",
    "wof:placetype":"venue"
},
  "geometry": {"coordinates":[-99.298807,34.64924],"type":"Point"}
}