{
  "type": "Feature",
  "properties": {
    "iso:country":"US",
    "sg:address":"132 N 3rd Ave",
    "sg:city":"Durant",
    "sg:classifiers":[
        {
            "category":"Professional",
            "subcategory":"Employment Agencies",
            "type":"Services"
        }
    ],
    "sg:phone":"+1 580 745 9802",
    "sg:postcode":"74701",
    "sg:province":"OK",
    "sg:tags":[
        "help",
        "supply"
    ],
    "wof:name":"O Double Inc",
    "wof:placetype":"venue"
},
  "geometry": {"coordinates":[-96.378285,33.992096],"type":"Point"}
}