{
  "type": "Feature",
  "properties": {
    "addr:full":"219 S Hudson St Altus OK 73521",
    "addr:housenumber":"219",
    "addr:postcode":"73521",
    "addr:street":"S Hudson St",
    "iso:country":"US",
    "sg:address":"219 S Hudson St",
    "sg:city":"Altus",
    "sg:classifiers":[
        {
            "category":"Retail",
            "subcategory":"Auto Repair",
            "type":"Services"
        }
    ],
    "sg:phone":"+1 580 477 4244",
    "sg:postcode":"73521",
    "sg:province":"OK",
    "sg:tags":[
        "repairing",
        "automobile"
    ],
    "wof:name":"Miranda Auto Clinic",
    "wof:placetype":"venue"
},
  "geometry": {"coordinates":[-99.335313,34.636521],"type":"Point"}
}