{
  "type": "Feature",
  "properties": {
    "iso:country":"US",
    "sg:address":"5904 NW 52nd St",
    "sg:city":"Oklahoma City",
    "sg:classifiers":[
        {
            "category":"Professional",
            "type":"Services"
        }
    ],
    "sg:phone":"+1 405 495 0166",
    "sg:postcode":"73122",
    "sg:province":"OK",
    "wof:name":"Hutchinss Distrbuting",
    "wof:placetype":"venue"
},
  "geometry": {"coordinates":[-97.623232,35.52408],"type":"Point"}
}