{
  "type": "Feature",
  "properties": {
    "addr:full":"4312 S Waco Ave Tulsa OK 74107",
    "addr:housenumber":"4312",
    "addr:postcode":"74107",
    "addr:street":"S Waco Ave",
    "iso:country":"US",
    "sg:address":"4312 S Waco Ave",
    "sg:city":"Tulsa",
    "sg:classifiers":[
        {
            "category":"Building & Trades",
            "subcategory":"Construction",
            "type":"Services"
        }
    ],
    "sg:phone":"+1 918 446 8281",
    "sg:postcode":"74107",
    "sg:province":"OK",
    "sg:tags":[
        "downspouts",
        "gutter"
    ],
    "wof:name":"Accuflow Guttering",
    "wof:placetype":"venue"
},
  "geometry": {"coordinates":[-96.013948,36.098685],"type":"Point"}
}