{
  "type": "Feature",
  "properties": {
    "iso:country":"US",
    "sg:address":"5400 N Grand Blvd",
    "sg:city":"Oklahoma City",
    "sg:classifiers":[
        {
            "category":"Restaurant",
            "type":"Food & Drink"
        }
    ],
    "sg:phone":"+1 405 947 8056",
    "sg:postcode":"73112",
    "sg:province":"OK",
    "sg:tags":[
        "caterer"
    ],
    "wof:name":"French's Grand Centre Deli",
    "wof:placetype":"venue"
},
  "geometry": {"coordinates":[-97.576813,35.525818],"type":"Point"}
}