{
  "type": "Feature",
  "properties": {
    "iso:country":"US",
    "sg:address":"208 N Klein Ave",
    "sg:city":"Oklahoma City",
    "sg:classifiers":[
        {
            "category":"Organizations",
            "subcategory":"Labor Organization",
            "type":"Services"
        }
    ],
    "sg:phone":"+1 405 232 3836",
    "sg:postcode":"73106",
    "sg:province":"OK",
    "wof:name":"Electricians Joint Apprntcshp",
    "wof:placetype":"venue"
},
  "geometry": {"coordinates":[-97.53224400000001,35.469858],"type":"Point"}
}