{
  "type": "Feature",
  "properties": {
    "iso:country":"US",
    "sg:address":"3015 NW Expy",
    "sg:city":"Oklahoma City",
    "sg:classifiers":[
        {
            "category":"Restaurant",
            "type":"Food & Drink"
        }
    ],
    "sg:phone":"+1 405 843 7227",
    "sg:postcode":"73112",
    "sg:province":"OK",
    "wof:name":"Sonic Drive-In",
    "wof:placetype":"venue"
},
  "geometry": {"coordinates":[-97.56829399999999,35.527288],"type":"Point"}
}