{
  "type": "Feature",
  "properties": {
    "addr:full":"1819 Hidden Oaks Dr Stillwater OK 74074",
    "addr:housenumber":"1819",
    "addr:postcode":"74074",
    "addr:street":"Hidden Oaks Dr",
    "iso:country":"US",
    "sg:address":"1819 Hidden Oaks Dr",
    "sg:city":"Stillwater",
    "sg:classifiers":[
        {
            "category":"Building & Trades",
            "subcategory":"Construction",
            "type":"Services"
        }
    ],
    "sg:phone":"+1 405 372 0332",
    "sg:postcode":"74074",
    "sg:province":"OK",
    "sg:tags":[
        "residential"
    ],
    "wof:name":"Jerry Eckels Construction",
    "wof:placetype":"venue"
},
  "geometry": {"coordinates":[-97.14298700000001,36.101469],"type":"Point"}
}