{
  "type": "Feature",
  "properties": {
    "iso:country":"US",
    "sg:address":"308 E Wyandotte Ave",
    "sg:city":"Mcalester",
    "sg:classifiers":[
        {
            "category":"Communications",
            "subcategory":"Radio Station",
            "type":"Services"
        }
    ],
    "sg:phone":"+1 918 420 5369",
    "sg:postcode":"74501",
    "sg:province":"OK",
    "sg:tags":[
        "company",
        "broadcasting"
    ],
    "wof:name":"KFOX 102.5 FM",
    "wof:placetype":"venue"
},
  "geometry": {"coordinates":[-95.767123,34.928358],"type":"Point"}
}