{
  "type": "Feature",
  "properties": {
    "iso:country":"US",
    "sg:address":"402 W Highland St",
    "sg:city":"Tecumseh",
    "sg:classifiers":[
        {
            "category":"Food & Beverages",
            "subcategory":"Specialty",
            "type":"Retail Goods"
        }
    ],
    "sg:phone":"+1 405 598 2131",
    "sg:postcode":"74873",
    "sg:province":"OK",
    "sg:tags":[
        "vitamin"
    ],
    "wof:name":"Sanders Laboratories Inc",
    "wof:placetype":"venue"
},
  "geometry": {"coordinates":[-96.941911,35.253376],"type":"Point"}
}