{
  "type": "Feature",
  "properties": {
    "iso:country":"US",
    "sg:address":"415 E Willow Rd",
    "sg:city":"Enid",
    "sg:classifiers":[
        {
            "category":"Building & Trades",
            "subcategory":"Pest Control",
            "type":"Services"
        }
    ],
    "sg:phone":"+1 580 242 0560",
    "sg:postcode":"73701",
    "sg:province":"OK",
    "wof:name":"Miles Pest Control LLC",
    "wof:placetype":"venue"
},
  "geometry": {"coordinates":[-97.871841,36.419894],"type":"Point"}
}