{
  "type": "Feature",
  "properties": {
    "iso:country":"US",
    "sg:address":"3223 E 31st St",
    "sg:city":"Tulsa",
    "sg:classifiers":[
        {
            "category":"Banks & Credit Unions",
            "subcategory":"Investment Brokerage",
            "type":"Services"
        }
    ],
    "sg:phone":"+1 918 745 9055",
    "sg:postcode":"74105",
    "sg:province":"OK",
    "wof:name":"Vinson Investment Co",
    "wof:placetype":"venue"
},
  "geometry": {"coordinates":[-95.942111,36.118861],"type":"Point"}
}