{
  "type": "Feature",
  "properties": {
    "iso:country":"US",
    "sg:address":"100 Wellston Park Rd",
    "sg:city":"Sand Springs",
    "sg:classifiers":[
        {
            "category":"Manufacturing",
            "subcategory":"Metals",
            "type":"Manufacturing & Wholesale Goods"
        }
    ],
    "sg:phone":"+1 918 245 9922",
    "sg:postcode":"74063",
    "sg:province":"OK",
    "sg:tags":[
        "equipment",
        "oil",
        "coating",
        "field"
    ],
    "wof:name":"WO&w",
    "wof:placetype":"venue"
},
  "geometry": {"coordinates":[-96.131464,36.137281],"type":"Point"}
}