{
  "type": "Feature",
  "properties": {
    "addr:full":"2512 N 15th St Broken Arrow OK 74012",
    "addr:housenumber":"2512",
    "addr:postcode":"74012",
    "addr:street":"N 15Th St",
    "iso:country":"US",
    "sg:address":"2512 N 15th St",
    "sg:city":"Broken Arrow",
    "sg:classifiers":[
        {
            "category":"Professional",
            "subcategory":"Business Services",
            "type":"Services"
        }
    ],
    "sg:phone":"+1 918 355 4242",
    "sg:postcode":"74012",
    "sg:province":"OK",
    "wof:name":"Soccer Showcase",
    "wof:placetype":"venue"
},
  "geometry": {"coordinates":[-95.77120600000001,36.077744],"type":"Point"}
}