{
  "type": "Feature",
  "properties": {
    "iso:country":"US",
    "sg:address":"2500 Refinery Rd",
    "sg:city":"Ardmore",
    "sg:classifiers":[
        {
            "category":"Manufacturing",
            "subcategory":"Petroleum Products",
            "type":"Manufacturing & Wholesale Goods"
        },
        {
            "category":"Wholesale",
            "subcategory":"Construction Materials",
            "type":"Manufacturing & Wholesale Goods"
        }
    ],
    "sg:phone":"+1 580 223 8010",
    "sg:postcode":"73401",
    "sg:province":"OK",
    "sg:tags":[
        "asphalt",
        "mfg"
    ],
    "wof:name":"Koch Materials Co",
    "wof:placetype":"venue"
},
  "geometry": {"coordinates":[-97.116761,34.201887],"type":"Point"}
}