{
  "type": "Feature",
  "properties": {
    "addr:full":"5223 S Division St Guthrie OK 73044",
    "addr:housenumber":"5223",
    "addr:postcode":"73044",
    "addr:street":"S Division St",
    "iso:country":"US",
    "sg:address":"5223 S Division St",
    "sg:city":"Guthrie",
    "sg:classifiers":[
        {
            "category":"Organizations",
            "subcategory":"Community Association",
            "type":"Services"
        }
    ],
    "sg:phone":"+1 405 282 2006",
    "sg:postcode":"73044",
    "sg:province":"OK",
    "sg:tags":[
        "military"
    ],
    "wof:name":"Veterans Of Foreign Wars 4578",
    "wof:placetype":"venue"
},
  "geometry": {"coordinates":[-97.42541199999999,35.82513],"type":"Point"}
}