{
  "type": "Feature",
  "properties": {
    "iso:country":"US",
    "sg:address":"8400 NW 10th St",
    "sg:city":"Oklahoma City",
    "sg:classifiers":[
        {
            "category":"Social Services",
            "subcategory":"Child Care",
            "type":"Services"
        }
    ],
    "sg:phone":"+1 405 787 4720",
    "sg:postcode":"73127",
    "sg:province":"OK",
    "sg:tags":[
        "day"
    ],
    "wof:name":"Sweet Success",
    "wof:placetype":"venue"
},
  "geometry": {"coordinates":[-97.66363699999999,35.478759],"type":"Point"}
}