{
  "type": "Feature",
  "properties": {
    "addr:full":"11921 N Pennsylvania Ave Oklahoma City OK 73120",
    "addr:housenumber":"11921",
    "addr:postcode":"73120",
    "addr:street":"N Pennsylvania Ave",
    "iso:country":"US",
    "sg:address":"11921 N Pennsylvania Ave",
    "sg:city":"Oklahoma City",
    "sg:classifiers":[
        {
            "category":"Restaurant",
            "type":"Food & Drink"
        }
    ],
    "sg:phone":"+1 405 752 5283",
    "sg:postcode":"73120",
    "sg:province":"OK",
    "wof:name":"Cabab N' Curry",
    "wof:placetype":"venue"
},
  "geometry": {"coordinates":[-97.54943799999999,35.592008],"type":"Point"}
}