{
  "type": "Feature",
  "properties": {
    "iso:country":"US",
    "sg:address":"1400 E Downing St",
    "sg:city":"Tahlequah",
    "sg:classifiers":[
        {
            "category":"Building & Trades",
            "subcategory":"Construction",
            "type":"Services"
        }
    ],
    "sg:phone":"+1 918 207 0018",
    "sg:postcode":"74464",
    "sg:province":"OK",
    "sg:tags":[
        "contractor"
    ],
    "wof:name":"Oakridge Builders",
    "wof:placetype":"venue"
},
  "geometry": {"coordinates":[-94.949987,35.915355],"type":"Point"}
}