{
  "type": "Feature",
  "properties": {
    "iso:country":"US",
    "sg:address":"2613 N 54th St",
    "sg:city":"Enid",
    "sg:classifiers":[
        {
            "category":"Farming",
            "subcategory":"Farm",
            "type":"Manufacturing & Wholesale Goods"
        }
    ],
    "sg:phone":"+1 580 234 2796",
    "sg:postcode":"73701",
    "sg:province":"OK",
    "sg:tags":[
        "crop",
        "general"
    ],
    "wof:name":"Herschel Timm",
    "wof:placetype":"venue"
},
  "geometry": {"coordinates":[-97.800863,36.433983],"type":"Point"}
}