{
  "type": "Feature",
  "properties": {
    "iso:country":"US",
    "sg:address":"6016 S Memorial Dr",
    "sg:city":"Tulsa",
    "sg:classifiers":[
        {
            "category":"Manufacturing",
            "subcategory":"Printing",
            "type":"Manufacturing & Wholesale Goods"
        }
    ],
    "sg:phone":"+1 918 622 6221",
    "sg:postcode":"74145",
    "sg:province":"OK",
    "sg:tags":[
        "publisher"
    ],
    "wof:name":"MLS Publishing",
    "wof:placetype":"venue"
},
  "geometry": {"coordinates":[-95.886485,36.075599],"type":"Point"}
}