{
  "type": "Feature",
  "properties": {
    "addr:full":"2500 N Main St Mcalester OK 74501",
    "addr:housenumber":"2500",
    "addr:postcode":"74501",
    "addr:street":"N Main St",
    "iso:country":"US",
    "sg:address":"2500 N Main St",
    "sg:city":"Mcalester",
    "sg:classifiers":[
        {
            "category":"Retail",
            "subcategory":"Auto Rental",
            "type":"Services"
        }
    ],
    "sg:phone":"+1 918 426 5824",
    "sg:postcode":"74501",
    "sg:province":"OK",
    "sg:tags":[
        "renting",
        "truck",
        "leasing"
    ],
    "wof:name":"U-Haul Co",
    "wof:placetype":"venue"
},
  "geometry": {"coordinates":[-95.761246,34.955155],"type":"Point"}
}