{
  "type": "Feature",
  "properties": {
    "iso:country":"US",
    "sg:address":"1831 W Modelle Ave",
    "sg:city":"Clinton",
    "sg:classifiers":[
        {
            "category":"Personal",
            "subcategory":"Beauty Salon",
            "type":"Services"
        }
    ],
    "sg:phone":"+1 580 323 2887",
    "sg:postcode":"73601",
    "sg:province":"OK",
    "sg:tags":[
        "shop"
    ],
    "wof:name":"All About Color",
    "wof:placetype":"venue"
},
  "geometry": {"coordinates":[-98.98238499999999,35.508686],"type":"Point"}
}