{
  "type": "Feature",
  "properties": {
    "iso:country":"US",
    "sg:address":"1224 N Eastern Ave",
    "sg:city":"Oklahoma City",
    "sg:classifiers":[
        {
            "category":"Sports & Exercise",
            "subcategory":"Gym",
            "type":"Entertainment"
        }
    ],
    "sg:phone":"+1 405 794 6200",
    "sg:postcode":"73111",
    "sg:province":"OK",
    "sg:tags":[
        "fitness",
        "physical",
        "facility"
    ],
    "wof:name":"Body Tech",
    "wof:placetype":"venue"
},
  "geometry": {"coordinates":[-97.476726,35.482475],"type":"Point"}
}