{
  "type": "Feature",
  "properties": {
    "iso:country":"US",
    "sg:address":"220 SW 29th St",
    "sg:city":"Oklahoma City",
    "sg:classifiers":[
        {
            "category":"Building & Trades",
            "subcategory":"Construction",
            "type":"Services"
        }
    ],
    "sg:phone":"+1 405 634 1894",
    "sg:postcode":"73109",
    "sg:province":"OK",
    "sg:tags":[
        "concrete",
        "contractor"
    ],
    "wof:name":"Chaffin Concrete Pumping Svc",
    "wof:placetype":"venue"
},
  "geometry": {"coordinates":[-97.517709,35.435155],"type":"Point"}
}