{
  "type": "Feature",
  "properties": {
    "iso:country":"US",
    "sg:address":"1501 W Purdue Ave",
    "sg:city":"Enid",
    "sg:classifiers":[
        {
            "category":"Education",
            "subcategory":"School",
            "type":"Public Place"
        }
    ],
    "sg:phone":"+1 580 234 4500",
    "sg:postcode":"73703",
    "sg:province":"OK",
    "wof:name":"Enid SDA School",
    "wof:placetype":"venue"
},
  "geometry": {"coordinates":[-97.890901,36.434392],"type":"Point"}
}