{
  "type": "Feature",
  "properties": {
    "iso:country":"US",
    "sg:address":"2527 E 36th St N",
    "sg:city":"Tulsa",
    "sg:classifiers":[
        {
            "category":"Social Services",
            "subcategory":"Child Care",
            "type":"Services"
        }
    ],
    "sg:phone":"+1 918 425 1721",
    "sg:postcode":"74110",
    "sg:province":"OK",
    "sg:tags":[
        "day"
    ],
    "wof:name":"Fredas Daycare and Lrng Ctr",
    "wof:placetype":"venue"
},
  "geometry": {"coordinates":[-95.954293,36.20621],"type":"Point"}
}