{
  "type": "Feature",
  "properties": {
    "iso:country":"US",
    "sg:address":"101 N Johnstone Ave",
    "sg:city":"Bartlesville",
    "sg:classifiers":[
        {
            "category":"Manufacturing",
            "subcategory":"Tools & Machinery",
            "type":"Manufacturing & Wholesale Goods"
        }
    ],
    "sg:phone":"+1 918 336 5075",
    "sg:postcode":"74003",
    "sg:province":"OK",
    "sg:tags":[
        "shop",
        "gray",
        "ductile",
        "casting",
        "mfg",
        "light",
        "machine",
        "iron"
    ],
    "wof:name":"Superior Welding Contracting",
    "wof:placetype":"venue"
},
  "geometry": {"coordinates":[-95.97668899999999,36.753921],"type":"Point"}
}