{
  "type": "Feature",
  "properties": {
    "addr:full":"3334 W Main St Norman OK 73072",
    "addr:housenumber":"3334",
    "addr:postcode":"73072",
    "addr:street":"W Main St",
    "iso:country":"US",
    "sg:address":"3334 W Main St",
    "sg:city":"Norman",
    "sg:classifiers":[
        {
            "category":"Professional",
            "subcategory":"Management & Consulting",
            "type":"Services"
        }
    ],
    "sg:phone":"+1 405 573 2054",
    "sg:postcode":"73072",
    "sg:province":"OK",
    "wof:name":"Chem Oil Products Corp",
    "wof:placetype":"venue"
},
  "geometry": {"coordinates":[-97.490796,35.218245],"type":"Point"}
}