{
  "type": "Feature",
  "properties": {
    "addr:full":"2201 S 680 Rd Quapaw OK 74363",
    "addr:housenumber":"2201",
    "addr:postcode":"74363",
    "addr:street":"S 680 Rd",
    "iso:country":"US",
    "sg:address":"2201 S 680 Rd",
    "sg:city":"Quapaw",
    "sg:classifiers":[
        {
            "category":"Travel",
            "subcategory":"Campground",
            "type":"Entertainment"
        }
    ],
    "sg:phone":"+1 918 542 4836",
    "sg:postcode":"74363",
    "sg:province":"OK",
    "sg:tags":[
        "camp"
    ],
    "wof:name":"5 Mile Childrens Camp",
    "wof:placetype":"venue"
},
  "geometry": {"coordinates":[-94.646844,36.985409],"type":"Point"}
}