{
  "type": "Feature",
  "properties": {
    "addr:full":"11804 Silvermoon Dr Oklahoma City OK 73162",
    "addr:housenumber":"11804",
    "addr:postcode":"73162",
    "addr:street":"Silvermoon Dr",
    "iso:country":"US",
    "sg:address":"11804 Silvermoon Dr",
    "sg:city":"Oklahoma City",
    "sg:classifiers":[
        {
            "category":"Professional",
            "subcategory":"Computer Services",
            "type":"Services"
        }
    ],
    "sg:phone":"+1 405 621 2277",
    "sg:postcode":"73162",
    "sg:province":"OK",
    "sg:tags":[
        "website",
        "design"
    ],
    "sg:website":"www.webguy.net",
    "wof:name":"WEBGUY.NET",
    "wof:placetype":"venue"
},
  "geometry": {"coordinates":[-97.671694,35.589374],"type":"Point"}
}