{
  "type": "Feature",
  "properties": {
    "iso:country":"US",
    "sg:address":"2405 NW 10th St",
    "sg:city":"Oklahoma City",
    "sg:classifiers":[
        {
            "category":"Manufacturing",
            "subcategory":"Metals",
            "type":"Manufacturing & Wholesale Goods"
        }
    ],
    "sg:phone":"+1 405 524 4451",
    "sg:postcode":"73107",
    "sg:province":"OK",
    "sg:tags":[
        "equipment",
        "layer",
        "carpet",
        "supply"
    ],
    "wof:name":"C & F Distributors",
    "wof:placetype":"venue"
},
  "geometry": {"coordinates":[-97.55667200000001,35.478743],"type":"Point"}
}