{
  "type": "Feature",
  "properties": {
    "iso:country":"US",
    "sg:address":"227 E 161st St",
    "sg:city":"Glenpool",
    "sg:classifiers":[
        {
            "category":"Freight",
            "type":"Transportation"
        }
    ],
    "sg:phone":"+1 918 322 6270",
    "sg:postcode":"74033",
    "sg:province":"OK",
    "sg:tags":[
        "operator",
        "trucking"
    ],
    "wof:name":"Suttles Truck Leasing LLC",
    "wof:placetype":"venue"
},
  "geometry": {"coordinates":[-95.97596299999999,35.930169],"type":"Point"}
}