{
  "type": "Feature",
  "properties": {
    "iso:country":"US",
    "sg:address":"4810 S Peoria Ave",
    "sg:city":"Tulsa",
    "sg:classifiers":[
        {
            "category":"Autos & Motor Vehicles",
            "subcategory":"Automobile Sales",
            "type":"Retail Goods"
        }
    ],
    "sg:phone":"+1 918 747 1850",
    "sg:postcode":"74105",
    "sg:province":"OK",
    "sg:tags":[
        "used"
    ],
    "wof:name":"Car-Mart",
    "wof:placetype":"venue"
},
  "geometry": {"coordinates":[-95.975799,36.093124],"type":"Point"}
}