{
  "type": "Feature",
  "properties": {
    "addr:full":"5503 NW 50th St Oklahoma City OK 73122",
    "addr:housenumber":"5503",
    "addr:postcode":"73122",
    "addr:street":"Nw 50Th St",
    "iso:country":"US",
    "sg:address":"5503 NW 50th St",
    "sg:city":"Oklahoma City",
    "sg:classifiers":[
        {
            "category":"Food & Beverages",
            "subcategory":"Groceries & Convenience Stores",
            "type":"Retail Goods"
        }
    ],
    "sg:phone":"+1 405 789 5535",
    "sg:postcode":"73122",
    "sg:province":"OK",
    "wof:name":"Short Stop",
    "wof:placetype":"venue"
},
  "geometry": {"coordinates":[-97.61063900000001,35.522383],"type":"Point"}
}