{
  "type": "Feature",
  "properties": {
    "iso:country":"US",
    "sg:address":"9251 N Pennsylvania Ave",
    "sg:city":"Oklahoma City",
    "sg:classifiers":[
        {
            "category":"Professional",
            "type":"Services"
        }
    ],
    "sg:phone":"+1 405 751 3201",
    "sg:postcode":"73120",
    "sg:province":"OK",
    "sg:tags":[
        "establishment"
    ],
    "wof:name":"Pat A Barry Agency",
    "wof:placetype":"venue"
},
  "geometry": {"coordinates":[-97.54933,35.564072],"type":"Point"}
}