{
  "type": "Feature",
  "properties": {
    "addr:full":"2704 N Martin Luther King Ave Oklahoma City OK 73111",
    "addr:housenumber":"2704",
    "addr:postcode":"73111",
    "addr:street":"N Martin Luther King Ave",
    "iso:country":"US",
    "sg:address":"2704 N Martin Luther King Ave",
    "sg:city":"Oklahoma City",
    "sg:classifiers":[
        {
            "category":"Retail",
            "subcategory":"Auto Repair",
            "type":"Services"
        }
    ],
    "sg:phone":"+1 405 427 6745",
    "sg:postcode":"73111",
    "sg:province":"OK",
    "sg:tags":[
        "repairing",
        "automobile"
    ],
    "wof:name":"Robinson's Garage",
    "wof:placetype":"venue"
},
  "geometry": {"coordinates":[-97.476564,35.497592],"type":"Point"}
}