{
  "type": "Feature",
  "properties": {
    "iso:country":"US",
    "sg:address":"614 E Cleveland Dr",
    "sg:city":"Hennessey",
    "sg:phone":"+1 405 853 2708",
    "sg:postcode":"73742",
    "sg:province":"OK",
    "sg:tags":[
        "farm",
        "grain",
        "cash"
    ],
    "wof:name":"Croka Farms Inc",
    "wof:placetype":"venue"
},
  "geometry": {"coordinates":[-97.89094,36.115485],"type":"Point"}
}