{
  "type": "Feature",
  "properties": {
    "iso:country":"US",
    "sg:address":"1145 S Utica Ave Suite 262",
    "sg:city":"Tulsa",
    "sg:classifiers":[
        {
            "category":"Health Services",
            "subcategory":"Doctor",
            "type":"Services"
        },
        {
            "category":"Health Services",
            "subcategory":"Hospital",
            "type":"Services"
        },
        {
            "category":"Health Services",
            "subcategory":"Nursing And Care Facility",
            "type":"Services"
        },
        {
            "category":"Health Services",
            "subcategory":"Health Practitioner",
            "type":"Services"
        },
        {
            "category":"Health Services",
            "subcategory":"Clinic",
            "type":"Services"
        }
    ],
    "sg:phone":"+1 918 579 3070",
    "sg:postcode":"74104",
    "sg:province":"OK",
    "sg:tags":[
        "physician",
        "mental",
        "information",
        "medical",
        "practice-arnp",
        "rehabilitation",
        "therapist",
        "registry",
        "nurses-advanced",
        "home",
        "nurse",
        "surgeon",
        "physical"
    ],
    "sg:website":"http://ad.doubleclick.net/clk;221658646;44587370;r?http://www.uticaparkclinic.com",
    "wof:name":"CHILD & ADOLESCENT NEUROLOGY AT UTICA PARK CLINIC",
    "wof:placetype":"venue"
},
  "geometry": {"coordinates":[-95.967109,36.147],"type":"Point"}
}