{
  "type": "Feature",
  "properties": {
    "iso:country":"US",
    "sg:address":"3621 S Quapah Ave",
    "sg:city":"Oklahoma City",
    "sg:classifiers":[
        {
            "category":"Building & Trades",
            "subcategory":"Pest Control",
            "type":"Services"
        }
    ],
    "sg:phone":"+1 405 681 3534",
    "sg:postcode":"73119",
    "sg:province":"OK",
    "wof:name":"Floyd's Exterminating",
    "wof:placetype":"venue"
},
  "geometry": {"coordinates":[-97.585619,35.428396],"type":"Point"}
}