{
  "type": "Feature",
  "properties": {
    "addr:full":"1414 NW 39th St Oklahoma City OK 73118",
    "addr:housenumber":"1414",
    "addr:postcode":"73118",
    "addr:street":"Nw 39Th St",
    "iso:country":"US",
    "sg:address":"1414 NW 39th St",
    "sg:city":"Oklahoma City",
    "sg:classifiers":[
        {
            "category":"Health Services",
            "subcategory":"Doctor",
            "type":"Services"
        }
    ],
    "sg:phone":"+1 405 524 3356",
    "sg:postcode":"73118",
    "sg:province":"OK",
    "wof:name":"Huyen L Nguyen DDS",
    "wof:placetype":"venue"
},
  "geometry": {"coordinates":[-97.53771999999999,35.511298],"type":"Point"}
}