{
  "type": "Feature",
  "properties": {
    "iso:country":"US",
    "sg:address":"1005 N Kenwood Dr",
    "sg:city":"Broken Arrow",
    "sg:classifiers":[
        {
            "category":"Home & Garden",
            "subcategory":"Carpets & Floor Coverings",
            "type":"Retail Goods"
        }
    ],
    "sg:phone":"+1 918 251 7775",
    "sg:postcode":"74012",
    "sg:province":"OK",
    "sg:tags":[
        "drape"
    ],
    "wof:name":"L & N Carpet Center",
    "wof:placetype":"venue"
},
  "geometry": {"coordinates":[-95.789568,36.064219],"type":"Point"}
}