{
  "type": "Feature",
  "properties": {
    "iso:country":"US",
    "sg:address":"3112 Eagle Pass Ln",
    "sg:city":"Edmond",
    "sg:classifiers":[
        {
            "category":"Professional",
            "subcategory":"Management & Consulting",
            "type":"Services"
        }
    ],
    "sg:phone":"+1 405 478 3312",
    "sg:postcode":"73013",
    "sg:province":"OK",
    "sg:tags":[
        "consultant"
    ],
    "wof:name":"Robert A Brown Inc",
    "wof:placetype":"venue"
},
  "geometry": {"coordinates":[-97.46007899999999,35.604204],"type":"Point"}
}