{
  "type": "Feature",
  "properties": {
    "addr:full":"2909 S Bethel Rd Stillwater OK 74074",
    "addr:housenumber":"2909",
    "addr:postcode":"74074",
    "addr:street":"S Bethel Rd",
    "iso:country":"US",
    "sg:address":"2909 S Bethel Rd",
    "sg:city":"Stillwater",
    "sg:classifiers":[
        {
            "category":"Retail",
            "subcategory":"Repair Shop",
            "type":"Services"
        }
    ],
    "sg:phone":"+1 405 624 1437",
    "sg:postcode":"74074",
    "sg:province":"OK",
    "wof:name":"Mattox Electronics",
    "wof:placetype":"venue"
},
  "geometry": {"coordinates":[-96.89055500000001,36.091284],"type":"Point"}
}