{
  "type": "Feature",
  "properties": {
    "addr:full":"503 S Pine St Ponca City OK 74601",
    "addr:housenumber":"503",
    "addr:postcode":"74601",
    "addr:street":"S Pine St",
    "iso:country":"US",
    "sg:address":"503 S Pine St",
    "sg:city":"Ponca City",
    "sg:classifiers":[
        {
            "category":"Retail",
            "subcategory":"Repair Shop",
            "type":"Services"
        }
    ],
    "sg:phone":"+1 580 762 7621",
    "sg:postcode":"74601",
    "sg:province":"OK",
    "wof:name":"Mike Duran Racing",
    "wof:placetype":"venue"
},
  "geometry": {"coordinates":[-97.086656,36.699505],"type":"Point"}
}