{
  "type": "Feature",
  "properties": {
    "iso:country":"US",
    "sg:address":"1826 Drakestone Ave",
    "sg:city":"Nichols Hills",
    "sg:classifiers":[
        {
            "category":"Professional",
            "subcategory":"Art Services",
            "type":"Services"
        }
    ],
    "sg:phone":"+1 405 749 1439",
    "sg:postcode":"73120",
    "sg:province":"OK",
    "sg:tags":[
        "artist"
    ],
    "wof:name":"Pen & Freehand",
    "wof:placetype":"venue"
},
  "geometry": {"coordinates":[-97.557045,35.557283],"type":"Point"}
}