{
  "type": "Feature",
  "properties": {
    "iso:country":"US",
    "sg:address":"910 NW 57th St",
    "sg:city":"Oklahoma City",
    "sg:classifiers":[
        {
            "category":"Professional",
            "subcategory":"Management & Consulting",
            "type":"Services"
        }
    ],
    "sg:phone":"+1 405 848 7570",
    "sg:postcode":"73118",
    "sg:province":"OK",
    "sg:tags":[
        "construction"
    ],
    "wof:name":"Paris Projects",
    "wof:placetype":"venue"
},
  "geometry": {"coordinates":[-97.52521400000001,35.530982],"type":"Point"}
}