{
  "type": "Feature",
  "properties": {
    "addr:full":"3707 S Granite Ave Tulsa OK 74135",
    "addr:housenumber":"3707",
    "addr:postcode":"74135",
    "addr:street":"S Granite Ave",
    "iso:country":"US",
    "sg:address":"3707 S Granite Ave",
    "sg:city":"Tulsa",
    "sg:classifiers":[
        {
            "category":"Shopping",
            "type":"Retail Goods"
        }
    ],
    "sg:phone":"+1 918 230 3773",
    "sg:postcode":"74135",
    "sg:province":"OK",
    "sg:tags":[
        "telephone",
        "cellular"
    ],
    "sg:website":"www.wallertech.com",
    "wof:name":"Waller Technologies",
    "wof:placetype":"venue"
},
  "geometry": {"coordinates":[-95.91443099999999,36.109173],"type":"Point"}
}