{
  "type": "Feature",
  "properties": {
    "iso:country":"US",
    "sg:address":"3020 S 4th St",
    "sg:city":"Chickasha",
    "sg:classifiers":[
        {
            "category":"Retail",
            "subcategory":"Veterinary Services",
            "type":"Services"
        }
    ],
    "sg:phone":"+1 405 224 1704",
    "sg:postcode":"73018",
    "sg:province":"OK",
    "wof:name":"Blevins E L",
    "wof:placetype":"venue"
},
  "geometry": {"coordinates":[-97.935137,35.018955],"type":"Point"}
}