{
  "type": "Feature",
  "properties": {
    "addr:full":"4698 N Main St Tulsa OK 74126",
    "addr:housenumber":"4698",
    "addr:postcode":"74126",
    "addr:street":"N Main St",
    "iso:country":"US",
    "sg:address":"4698 N Main St",
    "sg:city":"Tulsa",
    "sg:classifiers":[
        {
            "category":"Retail",
            "subcategory":"Laundry & Dry Cleaning",
            "type":"Services"
        }
    ],
    "sg:phone":"+1 918 425 1492",
    "sg:postcode":"74126",
    "sg:province":"OK",
    "sg:tags":[
        "seamstress"
    ],
    "wof:name":"Chube-Did-It",
    "wof:placetype":"venue"
},
  "geometry": {"coordinates":[-95.996143,36.223033],"type":"Point"}
}