{
  "type": "Feature",
  "properties": {
    "addr:full":"809 W Houston St Broken Arrow OK 74012",
    "addr:housenumber":"809",
    "addr:postcode":"74012",
    "addr:street":"W Houston St",
    "iso:country":"US",
    "sg:address":"809 W Houston St",
    "sg:city":"Broken Arrow",
    "sg:classifiers":[
        {
            "category":"Home & Garden",
            "subcategory":"Carpets & Floor Coverings",
            "type":"Retail Goods"
        }
    ],
    "sg:phone":"+1 918 258 9532",
    "sg:postcode":"74012",
    "sg:province":"OK",
    "sg:tags":[
        "dealer",
        "rug"
    ],
    "wof:name":"L & L Carpet & Tile",
    "wof:placetype":"venue"
},
  "geometry": {"coordinates":[-95.80379600000001,36.046516],"type":"Point"}
}