{
  "type": "Feature",
  "properties": {
    "addr:full":"5700 SW 5th St Oklahoma City OK 73128",
    "addr:housenumber":"5700",
    "addr:postcode":"73128",
    "addr:street":"Sw 5Th St",
    "iso:country":"US",
    "sg:address":"5700 SW 5th St",
    "sg:city":"Oklahoma City",
    "sg:classifiers":[
        {
            "category":"Retail",
            "subcategory":"Auto Repair",
            "type":"Services"
        }
    ],
    "sg:phone":"+1 405 943 8536",
    "sg:postcode":"73128",
    "sg:province":"OK",
    "sg:tags":[
        "engine"
    ],
    "wof:name":"Thompson Diesel",
    "wof:placetype":"venue"
},
  "geometry": {"coordinates":[-97.61211900000001,35.459581],"type":"Point"}
}