{
  "type": "Feature",
  "properties": {
    "iso:country":"US",
    "sg:address":"1100 W Main St",
    "sg:city":"Norman",
    "sg:classifiers":[
        {
            "category":"Food & Beverages",
            "subcategory":"Groceries & Convenience Stores",
            "type":"Retail Goods"
        }
    ],
    "sg:phone":"+1 405 364 9244",
    "sg:postcode":"73069",
    "sg:province":"OK",
    "sg:tags":[
        "grocer"
    ],
    "sg:website":"www.homelandstores.com",
    "wof:name":"Homeland",
    "wof:placetype":"venue"
},
  "geometry": {"coordinates":[-97.458389,35.218343],"type":"Point"}
}