{
  "type": "Feature",
  "properties": {
    "iso:country":"US",
    "sg:address":"1601 S Broadway",
    "sg:city":"Edmond",
    "sg:classifiers":[
        {
            "category":"Shopping",
            "subcategory":"Bicycles & Sporting Goods",
            "type":"Retail Goods"
        }
    ],
    "sg:phone":"+1 405 715 1761",
    "sg:postcode":"73013",
    "sg:province":"OK",
    "wof:name":"Fitness Equipment World Inc",
    "wof:placetype":"venue"
},
  "geometry": {"coordinates":[-97.483529,35.636949],"type":"Point"}
}