{
  "type": "Feature",
  "properties": {
    "iso:country":"US",
    "sg:address":"7915 E 71st St",
    "sg:city":"Tulsa",
    "sg:classifiers":[
        {
            "category":"Restaurant",
            "type":"Food & Drink"
        }
    ],
    "sg:phone":"+1 918 252 4499",
    "sg:postcode":"74133",
    "sg:province":"OK",
    "sg:tags":[
        "eating"
    ],
    "wof:name":"Wranglers Bar-B-Q",
    "wof:placetype":"venue"
},
  "geometry": {"coordinates":[-95.887573,36.060963],"type":"Point"}
}