{
  "type": "Feature",
  "properties": {
    "addr:full":"805 N Oseuma Ave Claremore OK 74017",
    "addr:housenumber":"805",
    "addr:postcode":"74017",
    "addr:street":"N Oseuma Ave",
    "iso:country":"US",
    "sg:address":"805 N Oseuma Ave",
    "sg:city":"Claremore",
    "sg:classifiers":[
        {
            "category":"Organizations",
            "subcategory":"Religious Organization",
            "type":"Services"
        }
    ],
    "sg:phone":"+1 918 341 1509",
    "sg:postcode":"74017",
    "sg:province":"OK",
    "sg:tags":[
        "church"
    ],
    "wof:name":"Mt Zion Baptist Church",
    "wof:placetype":"venue"
},
  "geometry": {"coordinates":[-95.617176,36.319563],"type":"Point"}
}