{
  "type": "Feature",
  "properties": {
    "iso:country":"US",
    "sg:address":"2704 Purdue Ave",
    "sg:city":"Oklahoma City",
    "sg:classifiers":[
        {
            "category":"Building & Trades",
            "subcategory":"Equipment Rental",
            "type":"Services"
        }
    ],
    "sg:phone":"+1 405 685 8300",
    "sg:postcode":"73128",
    "sg:province":"OK",
    "sg:tags":[
        "wholesale",
        "hospital",
        "rent"
    ],
    "wof:name":"Universal Hospital Services",
    "wof:placetype":"venue"
},
  "geometry": {"coordinates":[-97.613001,35.439036],"type":"Point"}
}