{
  "type": "Feature",
  "properties": {
    "addr:full":"3908 NW 17th St Oklahoma City OK 73107",
    "addr:housenumber":"3908",
    "addr:postcode":"73107",
    "addr:street":"Nw 17Th St",
    "iso:country":"US",
    "sg:address":"3908 NW 17th St",
    "sg:city":"Oklahoma City",
    "sg:classifiers":[
        {
            "category":"Professional",
            "subcategory":"Engineering",
            "type":"Services"
        }
    ],
    "sg:phone":"+1 405 947 3793",
    "sg:postcode":"73107",
    "sg:province":"OK",
    "sg:tags":[
        "engineer"
    ],
    "wof:name":"Peak Sales & Engineering",
    "wof:placetype":"venue"
},
  "geometry": {"coordinates":[-97.587991,35.487456],"type":"Point"}
}