{
  "type": "Feature",
  "properties": {
    "iso:country":"US",
    "sg:address":"1416 NE 10th St",
    "sg:city":"Oklahoma City",
    "sg:classifiers":[
        {
            "category":"Professional",
            "type":"Services"
        }
    ],
    "sg:phone":"+1 405 232 0968",
    "sg:postcode":"73117",
    "sg:province":"OK",
    "wof:name":"Art Garden Studio",
    "wof:placetype":"venue"
},
  "geometry": {"coordinates":[-97.485379,35.477914],"type":"Point"}
}