{
  "type": "Feature",
  "properties": {
    "iso:country":"US",
    "sg:address":"101 N Coo Y Yah St",
    "sg:city":"Pryor",
    "sg:classifiers":[
        {
            "category":"Wholesale",
            "subcategory":"Stationery",
            "type":"Manufacturing & Wholesale Goods"
        }
    ],
    "sg:phone":"+1 918 825 8440",
    "sg:postcode":"74361",
    "sg:province":"OK",
    "sg:tags":[
        "mill",
        "paper",
        "broker",
        "representative"
    ],
    "wof:name":"Linn Paper Stock Co",
    "wof:placetype":"venue"
},
  "geometry": {"coordinates":[-95.31172,36.310649],"type":"Point"}
}