{
  "type": "Feature",
  "properties": {
    "addr:full":"103 US Hwy 66 Sayre OK 73662",
    "addr:housenumber":"103",
    "addr:postcode":"73662",
    "addr:street":"Us Hwy 66",
    "iso:country":"US",
    "sg:address":"103 US Hwy 66",
    "sg:city":"Sayre",
    "sg:classifiers":[
        {
            "category":"Recreation",
            "type":"Entertainment"
        }
    ],
    "sg:phone":"+1 580 928 3866",
    "sg:postcode":"73662",
    "sg:province":"OK",
    "sg:tags":[
        "skating",
        "rink"
    ],
    "wof:name":"J & K's Rt 66 Roller Rink",
    "wof:placetype":"venue"
},
  "geometry": {"coordinates":[-99.639674,35.307818],"type":"Point"}
}