{
  "type": "Feature",
  "properties": {
    "addr:full":"310 N Washington Ave Weatherford OK 73096",
    "addr:housenumber":"310",
    "addr:postcode":"73096",
    "addr:street":"N Washington Ave",
    "iso:country":"US",
    "sg:address":"310 N Washington Ave",
    "sg:city":"Weatherford",
    "sg:classifiers":[
        {
            "category":"Shopping",
            "subcategory":"Beauty & Cosmetics",
            "type":"Retail Goods"
        }
    ],
    "sg:phone":"+1 580 772 7611",
    "sg:postcode":"73096",
    "sg:province":"OK",
    "sg:tags":[
        "supply"
    ],
    "wof:name":"Beautyco Inc",
    "wof:placetype":"venue"
},
  "geometry": {"coordinates":[-98.694013,35.528224],"type":"Point"}
}