{
  "type": "Feature",
  "properties": {
    "iso:country":"US",
    "sg:address":"301 Williams Ave",
    "sg:city":"Westville",
    "sg:classifiers":[
        {
            "category":"Insurance",
            "subcategory":"Insurance Agent",
            "type":"Services"
        }
    ],
    "sg:phone":"+1 918 723 3353",
    "sg:postcode":"74965",
    "sg:province":"OK",
    "wof:name":"Lewis Insurance",
    "wof:placetype":"venue"
},
  "geometry": {"coordinates":[-94.568237,35.994612],"type":"Point"}
}