{
  "type": "Feature",
  "properties": {
    "iso:country":"US",
    "sg:address":"5115 SW 36th St",
    "sg:city":"Oklahoma City",
    "sg:classifiers":[
        {
            "category":"Professional",
            "type":"Services"
        }
    ],
    "sg:phone":"+1 405 685 2581",
    "sg:postcode":"73179",
    "sg:province":"OK",
    "sg:tags":[
        "establishment"
    ],
    "wof:name":"All American",
    "wof:placetype":"venue"
},
  "geometry": {"coordinates":[-97.606042,35.427975],"type":"Point"}
}