{
  "type": "Feature",
  "properties": {
    "addr:full":"111 Beck Dr Bartlesville OK 74006",
    "addr:housenumber":"111",
    "addr:postcode":"74006",
    "addr:street":"Beck Dr",
    "iso:country":"US",
    "sg:address":"111 Beck Dr",
    "sg:city":"Bartlesville",
    "sg:classifiers":[
        {
            "category":"Farming",
            "subcategory":"Nursery",
            "type":"Manufacturing & Wholesale Goods"
        }
    ],
    "sg:phone":"+1 918 333 3248",
    "sg:postcode":"74006",
    "sg:province":"OK",
    "sg:tags":[
        "ornamental",
        "product"
    ],
    "wof:name":"Evans Nursery",
    "wof:placetype":"venue"
},
  "geometry": {"coordinates":[-95.94612600000001,36.756846],"type":"Point"}
}