{
  "type": "Feature",
  "properties": {
    "iso:country":"US",
    "sg:address":"740 W New Orleans St",
    "sg:city":"Broken Arrow",
    "sg:classifiers":[
        {
            "category":"Restaurant",
            "type":"Food & Drink"
        }
    ],
    "sg:menulink":"http://www.allmenus.com/ok/tulsa/68493-mazzios-pizza/menu/",
    "sg:phone":"+1 918 664 4444",
    "sg:postcode":"74011",
    "sg:province":"OK",
    "sg:tags":[
        "american",
        "pizza"
    ],
    "wof:name":"Mazzio's Pizza",
    "wof:placetype":"venue"
},
  "geometry": {"coordinates":[-95.800527,36.017397],"type":"Point"}
}