{
  "type": "Feature",
  "properties": {
    "addr:full":"525 E Okmulgee St Muskogee OK 74403",
    "addr:housenumber":"525",
    "addr:postcode":"74403",
    "addr:street":"E Okmulgee St",
    "iso:country":"US",
    "sg:address":"525 E Okmulgee St",
    "sg:city":"Muskogee",
    "sg:classifiers":[
        {
            "category":"Government",
            "subcategory":"Post Office",
            "type":"Public Place"
        }
    ],
    "sg:phone":"+1 918 682 7850",
    "sg:postcode":"74403",
    "sg:province":"OK",
    "sg:tags":[
        "postal",
        "us"
    ],
    "wof:name":"US Post Office",
    "wof:placetype":"venue"
},
  "geometry": {"coordinates":[-95.36009900000001,35.744213],"type":"Point"}
}