{
  "type": "Feature",
  "properties": {
    "addr:full":"6303 N Portland Ave Oklahoma City OK 73112",
    "addr:housenumber":"6303",
    "addr:postcode":"73112",
    "addr:street":"N Portland Ave",
    "iso:country":"US",
    "sg:address":"6303 N Portland Ave",
    "sg:city":"Oklahoma City",
    "sg:classifiers":[
        {
            "category":"Banks & Credit Unions",
            "subcategory":"Bank",
            "type":"Services"
        }
    ],
    "sg:phone":"+1 405 942 0336",
    "sg:postcode":"73112",
    "sg:province":"OK",
    "sg:tags":[
        "short",
        "institution",
        "business"
    ],
    "wof:name":"Wells Fargo",
    "wof:placetype":"venue"
},
  "geometry": {"coordinates":[-97.583519,35.536788],"type":"Point"}
}