{
  "type": "Feature",
  "properties": {
    "iso:country":"US",
    "sg:address":"110 E Ash Ave",
    "sg:city":"Fort Gibson",
    "sg:classifiers":[
        {
            "category":"Recreation",
            "type":"Entertainment"
        }
    ],
    "sg:phone":"+1 918 478 4088",
    "sg:postcode":"74434",
    "sg:province":"OK",
    "sg:tags":[
        "parks"
    ],
    "wof:name":"Ft Gibson Military Park",
    "wof:placetype":"venue"
},
  "geometry": {"coordinates":[-95.256235,35.804379],"type":"Point"}
}