{
  "type": "Feature",
  "properties": {
    "addr:full":"719 Lynn Ave Pawhuska OK 74056",
    "addr:housenumber":"719",
    "addr:postcode":"74056",
    "addr:street":"Lynn Ave",
    "iso:country":"US",
    "sg:address":"719 Lynn Ave",
    "sg:city":"Pawhuska",
    "sg:classifiers":[
        {
            "category":"Retail",
            "subcategory":"Auto Repair",
            "type":"Services"
        }
    ],
    "sg:phone":"+1 918 287 1020",
    "sg:postcode":"74056",
    "sg:province":"OK",
    "sg:tags":[
        "repairing",
        "automobile"
    ],
    "wof:name":"Jeff's Auto",
    "wof:placetype":"venue"
},
  "geometry": {"coordinates":[-96.33178599999999,36.664879],"type":"Point"}
}