{
  "type": "Feature",
  "properties": {
    "addr:full":"1512 Melrose Dr Norman OK 73069",
    "addr:housenumber":"1512",
    "addr:postcode":"73069",
    "addr:street":"Melrose Dr",
    "iso:country":"US",
    "sg:address":"1512 Melrose Dr",
    "sg:city":"Norman",
    "sg:classifiers":[
        {
            "category":"Health Services",
            "subcategory":"Doctor",
            "type":"Services"
        }
    ],
    "sg:phone":"+1 405 843 2333",
    "sg:postcode":"73069",
    "sg:province":"OK",
    "wof:name":"Stone Sue Psy D",
    "wof:placetype":"venue"
},
  "geometry": {"coordinates":[-97.46731699999999,35.21524],"type":"Point"}
}