{
  "type": "Feature",
  "properties": {
    "addr:full":"1533 N Harrison Ave Shawnee OK 74804",
    "addr:housenumber":"1533",
    "addr:postcode":"74804",
    "addr:street":"N Harrison Ave",
    "iso:country":"US",
    "sg:address":"1533 N Harrison Ave",
    "sg:city":"Shawnee",
    "sg:classifiers":[
        {
            "category":"Health Services",
            "subcategory":"Doctor",
            "type":"Services"
        }
    ],
    "sg:phone":"+1 405 273 3300",
    "sg:postcode":"74804",
    "sg:province":"OK",
    "sg:tags":[
        "clinic"
    ],
    "wof:name":"Oklahoma Orthopedics & Sports",
    "wof:placetype":"venue"
},
  "geometry": {"coordinates":[-96.911992,35.347598],"type":"Point"}
}