{
  "type": "Feature",
  "properties": {
    "iso:country":"US",
    "sg:address":"1300 SW 44th St",
    "sg:city":"Oklahoma City",
    "sg:classifiers":[
        {
            "category":"Food & Beverages",
            "subcategory":"Groceries & Convenience Stores",
            "type":"Retail Goods"
        }
    ],
    "sg:phone":"+1 405 685 3400",
    "sg:postcode":"73119",
    "sg:province":"OK",
    "wof:name":"Rancho Village Food Mart",
    "wof:placetype":"venue"
},
  "geometry": {"coordinates":[-97.54076499999999,35.42073],"type":"Point"}
}