{
  "type": "Feature",
  "properties": {
    "iso:country":"US",
    "sg:address":"5008 S Georgia Pl",
    "sg:city":"Oklahoma City",
    "sg:classifiers":[
        {
            "category":"Building & Trades",
            "subcategory":"Plumbing",
            "type":"Services"
        }
    ],
    "sg:phone":"+1 405 672 3852",
    "sg:postcode":"73129",
    "sg:province":"OK",
    "sg:tags":[
        "contractor"
    ],
    "wof:name":"Hvac Design",
    "wof:placetype":"venue"
},
  "geometry": {"coordinates":[-97.480509,35.413999],"type":"Point"}
}