{
  "type": "Feature",
  "properties": {
    "addr:full":"524 W Pine St Canton OK 73724",
    "addr:housenumber":"524",
    "addr:postcode":"73724",
    "addr:street":"W Pine St",
    "iso:country":"US",
    "sg:address":"524 W Pine St",
    "sg:city":"Canton",
    "sg:classifiers":[
        {
            "category":"Organizations",
            "subcategory":"Religious Organization",
            "type":"Services"
        }
    ],
    "sg:phone":"+1 580 886 3413",
    "sg:postcode":"73724",
    "sg:province":"OK",
    "wof:name":"Dominican Sisters",
    "wof:placetype":"venue"
},
  "geometry": {"coordinates":[-98.59793999999999,36.057793],"type":"Point"}
}