{
  "type": "Feature",
  "properties": {
    "iso:country":"US",
    "sg:address":"524 W Pine St",
    "sg:city":"Canton",
    "sg:classifiers":[
        {
            "category":"Organizations",
            "subcategory":"Religious Organization",
            "type":"Services"
        }
    ],
    "sg:phone":"+1 580 886 3413",
    "sg:postcode":"73724",
    "sg:province":"OK",
    "wof:name":"Dominican Sisters",
    "wof:placetype":"venue"
},
  "geometry": {"coordinates":[-98.59794,36.057793],"type":"Point"}
}