{
  "type": "Feature",
  "properties": {
    "iso:country":"US",
    "sg:address":"254 Hinton Rd",
    "sg:city":"Mannford",
    "sg:classifiers":[
        {
            "category":"Real Estate",
            "subcategory":"Real Estate Operator",
            "type":"Services"
        }
    ],
    "sg:phone":"+1 918 865 4384",
    "sg:postcode":"74044",
    "sg:province":"OK",
    "sg:tags":[
        "apartment"
    ],
    "wof:name":"Salt Creek Apartments",
    "wof:placetype":"venue"
},
  "geometry": {"coordinates":[-96.3451,36.120581],"type":"Point"}
}