{
  "type": "Feature",
  "properties": {
    "addr:full":"825 NW 58th St Oklahoma City OK 73118",
    "addr:housenumber":"825",
    "addr:postcode":"73118",
    "addr:street":"Nw 58Th St",
    "iso:country":"US",
    "sg:address":"825 NW 58th St",
    "sg:city":"Oklahoma City",
    "sg:classifiers":[
        {
            "category":"Professional",
            "subcategory":"Lawyer & Legal Services",
            "type":"Services"
        }
    ],
    "sg:phone":"+1 405 842 7590",
    "sg:postcode":"73118",
    "sg:province":"OK",
    "sg:tags":[
        "attorney"
    ],
    "wof:name":"Jonathan Burch PC",
    "wof:placetype":"venue"
},
  "geometry": {"coordinates":[-97.524877,35.532028],"type":"Point"}
}