{
  "type": "Feature",
  "properties": {
    "iso:country":"US",
    "sg:address":"9607 E 71st St",
    "sg:city":"Tulsa",
    "sg:classifiers":[
        {
            "category":"Restaurant",
            "type":"Food & Drink"
        }
    ],
    "sg:phone":"+1 918 252 2663",
    "sg:postcode":"74133",
    "sg:province":"OK",
    "sg:tags":[
        "parlor",
        "ice",
        "cream"
    ],
    "wof:name":"Freckles Frozen Custard",
    "wof:placetype":"venue"
},
  "geometry": {"coordinates":[-95.868939,36.060988],"type":"Point"}
}