{
  "type": "Feature",
  "properties": {
    "iso:country":"US",
    "sg:address":"2144 NW 29th St",
    "sg:city":"Oklahoma City",
    "sg:classifiers":[
        {
            "category":"Building & Trades",
            "subcategory":"Construction",
            "type":"Services"
        }
    ],
    "sg:phone":"+1 405 601 5983",
    "sg:postcode":"73107",
    "sg:province":"OK",
    "sg:tags":[
        "gen"
    ],
    "wof:name":"Apple Construction",
    "wof:placetype":"venue"
},
  "geometry": {"coordinates":[-97.549025,35.499417],"type":"Point"}
}