{
  "type": "Feature",
  "properties": {
    "iso:country":"US",
    "sg:address":"733 N Poplar Ln",
    "sg:city":"Oklahoma City",
    "sg:classifiers":[
        {
            "category":"Insurance",
            "subcategory":"Insurance Agent",
            "type":"Services"
        }
    ],
    "sg:phone":"+1 405 259 9069",
    "sg:postcode":"73130",
    "sg:province":"OK",
    "wof:name":"American National",
    "wof:placetype":"venue"
},
  "geometry": {"coordinates":[-97.3489,35.473397],"type":"Point"}
}