{
  "type": "Feature",
  "properties": {
    "iso:country":"US",
    "sg:address":"700 S Robinson Ave",
    "sg:city":"Oklahoma City",
    "sg:classifiers":[
        {
            "category":"Autos & Motor Vehicles",
            "subcategory":"Automobile Sales",
            "type":"Retail Goods"
        }
    ],
    "sg:phone":"+1 405 239 2886",
    "sg:postcode":"73109",
    "sg:province":"OK",
    "sg:tags":[
        "car",
        "dealer"
    ],
    "wof:name":"Blue Dot Autos",
    "wof:placetype":"venue"
},
  "geometry": {"coordinates":[-97.516221,35.457959],"type":"Point"}
}