{
  "type": "Feature",
  "properties": {
    "iso:country":"US",
    "sg:address":"2800 NW 63rd St",
    "sg:city":"Oklahoma City",
    "sg:classifiers":[
        {
            "category":"Wholesale",
            "subcategory":"Medical Equipment & Supplies",
            "type":"Manufacturing & Wholesale Goods"
        }
    ],
    "sg:phone":"+1 405 840 7867",
    "sg:postcode":"73116",
    "sg:province":"OK",
    "sg:tags":[
        "physician",
        "surgeon"
    ],
    "wof:name":"Meyer Medical Supply",
    "wof:placetype":"venue"
},
  "geometry": {"coordinates":[-97.563778,35.536556],"type":"Point"}
}