{
  "type": "Feature",
  "properties": {
    "iso:country":"US",
    "sg:address":"205 N Yale Ave",
    "sg:city":"Tulsa",
    "sg:classifiers":[
        {
            "category":"Freight",
            "type":"Transportation"
        }
    ],
    "sg:phone":"+1 918 836 0833",
    "sg:postcode":"74115",
    "sg:province":"OK",
    "sg:tags":[
        "operator",
        "trucking"
    ],
    "sg:website":"www.beaverexpress.com",
    "wof:name":"Beaver Express Svc LLC",
    "wof:placetype":"venue"
},
  "geometry": {"coordinates":[-95.922446,36.163632],"type":"Point"}
}