{
  "type": "Feature",
  "properties": {
    "addr:full":"4820 N Meridian Ave Oklahoma City OK 73112",
    "addr:housenumber":"4820",
    "addr:postcode":"73112",
    "addr:street":"N Meridian Ave",
    "iso:country":"US",
    "sg:address":"4820 N Meridian Ave",
    "sg:city":"Oklahoma City",
    "sg:classifiers":[
        {
            "category":"Travel",
            "subcategory":"Travel Agent",
            "type":"Entertainment"
        }
    ],
    "sg:phone":"+1 405 948 8642",
    "sg:postcode":"73112",
    "sg:province":"OK",
    "sg:tags":[
        "agency",
        "cruise"
    ],
    "wof:name":"Sunshine Travel Service Inc",
    "wof:placetype":"venue"
},
  "geometry": {"coordinates":[-97.601113,35.519818],"type":"Point"}
}