{
  "type": "Feature",
  "properties": {
    "addr:full":"412 Main St Depew OK 74028",
    "addr:housenumber":"412",
    "addr:postcode":"74028",
    "addr:street":"Main St",
    "iso:country":"US",
    "sg:address":"412 Main St",
    "sg:city":"Depew",
    "sg:classifiers":[
        {
            "category":"Social Services",
            "type":"Services"
        }
    ],
    "sg:phone":"+1 918 324 5485",
    "sg:postcode":"74028",
    "sg:province":"OK",
    "wof:name":"Depew Senior Citizen Center",
    "wof:placetype":"venue"
},
  "geometry": {"coordinates":[-96.50980800000001,35.802995],"type":"Point"}
}