{
  "type": "Feature",
  "properties": {
    "iso:country":"US",
    "sg:address":"214 S Main St",
    "sg:city":"Verden",
    "sg:classifiers":[
        {
            "category":"Social Services",
            "subcategory":"Adult Care",
            "type":"Services"
        }
    ],
    "sg:phone":"+1 405 453 7590",
    "sg:postcode":"73092",
    "sg:province":"OK",
    "sg:tags":[
        "organization",
        "senior",
        "citizen"
    ],
    "wof:name":"Verden Senior Nutrition Ctr",
    "wof:placetype":"venue"
},
  "geometry": {"coordinates":[-98.088282,35.080593],"type":"Point"}
}