{
  "type": "Feature",
  "properties": {
    "iso:country":"US",
    "sg:address":"1005 S Wilson Ave",
    "sg:city":"Cushing",
    "sg:classifiers":[
        {
            "category":"Health Services",
            "subcategory":"Doctor",
            "type":"Services"
        }
    ],
    "sg:phone":"+1 918 225 2450",
    "sg:postcode":"74023",
    "sg:province":"OK",
    "sg:tags":[
        "physician",
        "surgeon"
    ],
    "wof:name":"Dhimmar Clinic",
    "wof:placetype":"venue"
},
  "geometry": {"coordinates":[-96.758823,35.971151],"type":"Point"}
}