{
  "type": "Feature",
  "properties": {
    "iso:country":"US",
    "sg:address":"509 N Orange St",
    "sg:city":"Seiling",
    "sg:classifiers":[
        {
            "category":"Mining & Drilling",
            "type":"Manufacturing & Wholesale Goods"
        }
    ],
    "sg:phone":"+1 580 922 5412",
    "sg:postcode":"73663",
    "sg:province":"OK",
    "sg:tags":[
        "field",
        "oil"
    ],
    "wof:name":"Weeks Blade Svc",
    "wof:placetype":"venue"
},
  "geometry": {"coordinates":[-98.928442,36.150793],"type":"Point"}
}