{
  "type": "Feature",
  "properties": {
    "iso:country":"US",
    "sg:address":"615 S Broadway St",
    "sg:city":"Holdenville",
    "sg:classifiers":[
        {
            "category":"Education",
            "subcategory":"School",
            "type":"Public Place"
        }
    ],
    "sg:phone":"+1 405 379 6618",
    "sg:postcode":"74848",
    "sg:province":"OK",
    "wof:name":"Parkview Elementary School",
    "wof:placetype":"venue"
},
  "geometry": {"coordinates":[-96.40786199999999,35.078803],"type":"Point"}
}