{
  "type": "Feature",
  "properties": {
    "iso:country":"US",
    "sg:address":"4936 E 21st St",
    "sg:city":"Tulsa",
    "sg:classifiers":[
        {
            "category":"Professional",
            "subcategory":"Employment Agencies",
            "type":"Services"
        }
    ],
    "sg:phone":"+1 918 971 5900",
    "sg:postcode":"74114",
    "sg:province":"OK",
    "sg:tags":[
        "opportunity"
    ],
    "wof:name":"Spherion",
    "wof:placetype":"venue"
},
  "geometry": {"coordinates":[-95.920586,36.133266],"type":"Point"}
}