{
  "type": "Feature",
  "properties": {
    "iso:country":"US",
    "sg:address":"801 NE 13th St",
    "sg:city":"Oklahoma City",
    "sg:classifiers":[
        {
            "category":"Education",
            "subcategory":"College",
            "type":"Public Place"
        }
    ],
    "sg:phone":"+1 405 271 6477",
    "sg:postcode":"73104",
    "sg:province":"OK",
    "sg:tags":[
        "medical",
        "school"
    ],
    "wof:name":"Radiological Technology Dept",
    "wof:placetype":"venue"
},
  "geometry": {"coordinates":[-97.496802,35.482299],"type":"Point"}
}