{
  "type": "Feature",
  "properties": {
    "iso:country":"US",
    "sg:address":"1912 Atchison Dr",
    "sg:city":"Norman",
    "sg:classifiers":[
        {
            "category":"Building & Trades",
            "subcategory":"Construction",
            "type":"Services"
        }
    ],
    "sg:phone":"+1 405 364 0022",
    "sg:postcode":"73069",
    "sg:province":"OK",
    "sg:tags":[
        "architectural",
        "manufacturer"
    ],
    "wof:name":"Alpha Omega Woodworks",
    "wof:placetype":"venue"
},
  "geometry": {"coordinates":[-97.470184,35.259069],"type":"Point"}
}