{
  "type": "Feature",
  "properties": {
    "iso:country":"US",
    "sg:address":"410 4th St",
    "sg:city":"Alva",
    "sg:classifiers":[
        {
            "category":"Health Services",
            "subcategory":"Doctor",
            "type":"Services"
        }
    ],
    "sg:phone":"+1 580 327 4533",
    "sg:postcode":"73717",
    "sg:province":"OK",
    "sg:tags":[
        "osteopathic"
    ],
    "wof:name":"Kirt E Bierig Do",
    "wof:placetype":"venue"
},
  "geometry": {"coordinates":[-98.663467,36.804787],"type":"Point"}
}