{
  "type": "Feature",
  "properties": {
    "iso:country":"US",
    "sg:address":"1206 SE Washington St",
    "sg:city":"Idabel",
    "sg:classifiers":[
        {
            "category":"Travel",
            "subcategory":"Hotels & Motels",
            "type":"Entertainment"
        }
    ],
    "sg:phone":"+1 580 286 3381",
    "sg:postcode":"74745",
    "sg:province":"OK",
    "sg:tags":[
        "operation",
        "eating"
    ],
    "wof:name":"Rambler Motel",
    "wof:placetype":"venue"
},
  "geometry": {"coordinates":[-94.814555,33.895468],"type":"Point"}
}