{
  "type": "Feature",
  "properties": {
    "iso:country":"US",
    "sg:address":"1776 S Utica Ave",
    "sg:city":"Tulsa",
    "sg:classifiers":[
        {
            "category":"Banks & Credit Unions",
            "subcategory":"Bank",
            "type":"Services"
        }
    ],
    "sg:phone":"+1 918 747 3331",
    "sg:postcode":"74104",
    "sg:province":"OK",
    "sg:tags":[
        "loan",
        "real estate"
    ],
    "wof:name":"Carteret Mortgage",
    "wof:placetype":"venue"
},
  "geometry": {"coordinates":[-95.967233,36.136759],"type":"Point"}
}