{
  "type": "Feature",
  "properties": {
    "addr:full":"1776 S Utica Ave Tulsa OK 74104",
    "addr:housenumber":"1776",
    "addr:postcode":"74104",
    "addr:street":"S Utica Ave",
    "iso:country":"US",
    "sg:address":"1776 S Utica Ave",
    "sg:city":"Tulsa",
    "sg:classifiers":[
        {
            "category":"Banks & Credit Unions",
            "subcategory":"Bank",
            "type":"Services"
        }
    ],
    "sg:phone":"+1 918 747 3331",
    "sg:postcode":"74104",
    "sg:province":"OK",
    "sg:tags":[
        "loan",
        "real estate"
    ],
    "wof:name":"Carteret Mortgage",
    "wof:placetype":"venue"
},
  "geometry": {"coordinates":[-95.96723299999999,36.136759],"type":"Point"}
}