{
  "type": "Feature",
  "properties": {
    "iso:country":"US",
    "sg:address":"307 W Brooks St",
    "sg:city":"Norman",
    "sg:classifiers":[
        {
            "category":"Education",
            "subcategory":"College",
            "type":"Public Place"
        }
    ],
    "sg:phone":"+1 405 325 3611",
    "sg:postcode":"73069",
    "sg:province":"OK",
    "sg:tags":[
        "admin",
        "for",
        "business"
    ],
    "wof:name":"Michael F Price Cllege Bus ADM",
    "wof:placetype":"venue"
},
  "geometry": {"coordinates":[-97.445354,35.20746],"type":"Point"}
}