{
  "type": "Feature",
  "properties": {
    "addr:full":"15648 Banyan Rd Morris OK 74445",
    "addr:housenumber":"15648",
    "addr:postcode":"74445",
    "addr:street":"Banyan Rd",
    "iso:country":"US",
    "sg:address":"15648 Banyan Rd",
    "sg:city":"Morris",
    "sg:classifiers":[
        {
            "category":"Mining & Drilling",
            "type":"Manufacturing & Wholesale Goods"
        }
    ],
    "sg:phone":"+1 918 756 5308",
    "sg:postcode":"74445",
    "sg:province":"OK",
    "sg:tags":[
        "development",
        "gas",
        "oil",
        "exploration"
    ],
    "wof:name":"GMG Oil & Gas Corp",
    "wof:placetype":"venue"
},
  "geometry": {"coordinates":[-95.91230899999999,35.580744],"type":"Point"}
}