{
  "type": "Feature",
  "properties": {
    "addr:full":"5639 E 41st St Tulsa OK 74135",
    "addr:housenumber":"5639",
    "addr:postcode":"74135",
    "addr:street":"E 41St St",
    "iso:country":"US",
    "sg:address":"5639 E 41st St",
    "sg:city":"Tulsa",
    "sg:classifiers":[
        {
            "category":"Health Services",
            "subcategory":"Dentist",
            "type":"Services"
        }
    ],
    "sg:phone":"+1 918 622 3353",
    "sg:postcode":"74135",
    "sg:province":"OK",
    "sg:tags":[
        "product",
        "whitening",
        "teeth"
    ],
    "wof:name":"Stokes, Kimberly H",
    "wof:placetype":"venue"
},
  "geometry": {"coordinates":[-95.913425,36.104378],"type":"Point"}
}