{
  "type": "Feature",
  "properties": {
    "iso:country":"US",
    "sg:address":"4621 S Peoria Ave",
    "sg:city":"Tulsa",
    "sg:classifiers":[
        {
            "category":"Autos & Motor Vehicles",
            "subcategory":"Auto Supplies",
            "type":"Retail Goods"
        },
        {
            "category":"Wholesale",
            "subcategory":"Auto Parts",
            "type":"Manufacturing & Wholesale Goods"
        }
    ],
    "sg:phone":"+1 918 743 6244",
    "sg:postcode":"74105",
    "sg:province":"OK",
    "sg:tags":[
        "automotive",
        "automobile"
    ],
    "wof:name":"O'Reilly Auto Parts",
    "wof:placetype":"venue"
},
  "geometry": {"coordinates":[-95.975662,36.095435],"type":"Point"}
}