{
  "type": "Feature",
  "properties": {
    "addr:full":"125 N Main St Seminole OK 74868",
    "addr:housenumber":"125",
    "addr:postcode":"74868",
    "addr:street":"N Main St",
    "iso:country":"US",
    "sg:address":"125 N Main St",
    "sg:city":"Seminole",
    "sg:classifiers":[
        {
            "category":"Education",
            "subcategory":"Dance Studio",
            "type":"Public Place"
        }
    ],
    "sg:phone":"+1 405 382 3560",
    "sg:postcode":"74868",
    "sg:province":"OK",
    "sg:tags":[
        "instruction",
        "dancing"
    ],
    "wof:name":"Dance Co",
    "wof:placetype":"venue"
},
  "geometry": {"coordinates":[-96.668595,35.224012],"type":"Point"}
}