{
  "type": "Feature",
  "properties": {
    "iso:country":"US",
    "sg:address":"1846 W David Dr",
    "sg:city":"Mustang",
    "sg:classifiers":[
        {
            "category":"Professional",
            "subcategory":"Accounting & Tax Preparation",
            "type":"Services"
        }
    ],
    "sg:phone":"+1 405 376 1957",
    "sg:postcode":"73064",
    "sg:province":"OK",
    "wof:name":"Michelle Hinkle CPA",
    "wof:placetype":"venue"
},
  "geometry": {"coordinates":[-97.761154,35.380032],"type":"Point"}
}