{
  "type": "Feature",
  "properties": {
    "addr:full":"4407 W Princeton Pl Broken Arrow OK 74012",
    "addr:housenumber":"4407",
    "addr:postcode":"74012",
    "addr:street":"W Princeton Pl",
    "iso:country":"US",
    "sg:address":"4407 W Princeton Pl",
    "sg:city":"Broken Arrow",
    "sg:classifiers":[
        {
            "category":"Food & Beverages",
            "subcategory":"Liquor & Beverages",
            "type":"Retail Goods"
        }
    ],
    "sg:phone":"+1 918 251 2609",
    "sg:postcode":"74012",
    "sg:province":"OK",
    "sg:tags":[
        "alcoholic"
    ],
    "wof:name":"Bee Dry Drive Thru",
    "wof:placetype":"venue"
},
  "geometry": {"coordinates":[-95.84463700000001,36.066877],"type":"Point"}
}