{
  "type": "Feature",
  "properties": {
    "addr:full":"110 S University Blvd Norman OK 73069",
    "addr:housenumber":"110",
    "addr:postcode":"73069",
    "addr:street":"S University Blvd",
    "iso:country":"US",
    "sg:address":"110 S University Blvd",
    "sg:city":"Norman",
    "sg:classifiers":[
        {
            "category":"Manufacturing",
            "subcategory":"Retail Goods",
            "type":"Manufacturing & Wholesale Goods"
        }
    ],
    "sg:phone":"+1 405 329 5143",
    "sg:postcode":"73069",
    "sg:province":"OK",
    "sg:tags":[
        "rubber",
        "stamp",
        "mfg",
        "plate"
    ],
    "wof:name":"Norman Stamp & Seal Co",
    "wof:placetype":"venue"
},
  "geometry": {"coordinates":[-97.447582,35.218021],"type":"Point"}
}