{
  "type": "Feature",
  "properties": {
    "iso:country":"US",
    "sg:address":"3249 N Madison Ave",
    "sg:city":"Tulsa",
    "sg:classifiers":[
        {
            "category":"Social Services",
            "subcategory":"Child Care",
            "type":"Services"
        }
    ],
    "sg:phone":"+1 918 425 2229",
    "sg:postcode":"74106",
    "sg:province":"OK",
    "sg:tags":[
        "day"
    ],
    "wof:name":"Mama Collins Day Care",
    "wof:placetype":"venue"
},
  "geometry": {"coordinates":[-95.978956,36.201658],"type":"Point"}
}