{
  "type": "Feature",
  "properties": {
    "iso:country":"US",
    "sg:address":"931 S Cornwell Dr",
    "sg:city":"Yukon",
    "sg:classifiers":[
        {
            "category":"Shopping",
            "subcategory":"Computers & Home Electronics",
            "type":"Retail Goods"
        }
    ],
    "sg:phone":"+1 405 354 1629",
    "sg:postcode":"73099",
    "sg:province":"OK",
    "sg:tags":[
        "equipment",
        "selling",
        "video",
        "installing"
    ],
    "wof:name":"Video Security Systems",
    "wof:placetype":"venue"
},
  "geometry": {"coordinates":[-97.742451,35.498097],"type":"Point"}
}