{
  "type": "Feature",
  "properties": {
    "addr:full":"425 SW 44th St Oklahoma City OK 73109",
    "addr:housenumber":"425",
    "addr:postcode":"73109",
    "addr:street":"Sw 44Th St",
    "iso:country":"US",
    "sg:address":"425 SW 44th St",
    "sg:city":"Oklahoma City",
    "sg:classifiers":[
        {
            "category":"Professional",
            "subcategory":"Lawyer & Legal Services",
            "type":"Services"
        }
    ],
    "sg:phone":"+1 405 636 0137",
    "sg:postcode":"73109",
    "sg:province":"OK",
    "wof:name":"Ritter Donald Lee",
    "wof:placetype":"venue"
},
  "geometry": {"coordinates":[-97.52103099999999,35.420821],"type":"Point"}
}