{
  "type": "Feature",
  "properties": {
    "iso:country":"US",
    "sg:address":"425 SW 44th St",
    "sg:city":"Oklahoma City",
    "sg:classifiers":[
        {
            "category":"Professional",
            "subcategory":"Lawyer & Legal Services",
            "type":"Services"
        }
    ],
    "sg:phone":"+1 405 636 0137",
    "sg:postcode":"73109",
    "sg:province":"OK",
    "wof:name":"Ritter Donald Lee",
    "wof:placetype":"venue"
},
  "geometry": {"coordinates":[-97.521031,35.420821],"type":"Point"}
}