{
  "type": "Feature",
  "properties": {
    "addr:full":"204 S Capitol Ave Tishomingo OK 73460",
    "addr:housenumber":"204",
    "addr:postcode":"73460",
    "addr:street":"S Capitol Ave",
    "iso:country":"US",
    "sg:address":"204 S Capitol Ave",
    "sg:city":"Tishomingo",
    "sg:classifiers":[
        {
            "category":"Government",
            "subcategory":"Jail",
            "type":"Public Place"
        }
    ],
    "sg:phone":"+1 580 371 3586",
    "sg:postcode":"73460",
    "sg:province":"OK",
    "sg:tags":[
        "govt",
        "state",
        "institution"
    ],
    "wof:name":"Juvenile Affairs Office",
    "wof:placetype":"venue"
},
  "geometry": {"coordinates":[-96.681876,34.235969],"type":"Point"}
}