{
  "type": "Feature",
  "properties": {
    "iso:country":"US",
    "sg:address":"511 Gilliam",
    "sg:city":"Marietta",
    "sg:classifiers":[
        {
            "category":"Retail",
            "subcategory":"Repair Shop",
            "type":"Services"
        }
    ],
    "sg:phone":"+1 580 276 3104",
    "sg:postcode":"73448",
    "sg:province":"OK",
    "wof:name":"Tsw Inc",
    "wof:placetype":"venue"
},
  "geometry": {"coordinates":[-97.122164,33.928601],"type":"Point"}
}