{
  "type": "Feature",
  "properties": {
    "iso:country":"US",
    "sg:address":"2501 E Willow Rd",
    "sg:city":"Enid",
    "sg:classifiers":[
        {
            "category":"Mining & Drilling",
            "type":"Manufacturing & Wholesale Goods"
        }
    ],
    "sg:phone":"+1 580 242 7951",
    "sg:postcode":"73701",
    "sg:province":"OK",
    "sg:tags":[
        "crude",
        "oil"
    ],
    "wof:name":"Sun Refining & Marketing Co",
    "wof:placetype":"venue"
},
  "geometry": {"coordinates":[-97.843318,36.419737],"type":"Point"}
}