{
  "type": "Feature",
  "properties": {
    "addr:full":"3518 W Owen K Garriott Rd Enid OK 73703",
    "addr:housenumber":"3518",
    "addr:postcode":"73703",
    "addr:street":"W Owen K Garriott Rd",
    "iso:country":"US",
    "sg:address":"3518 W Owen K Garriott Rd",
    "sg:city":"Enid",
    "sg:classifiers":[
        {
            "category":"Restaurant",
            "type":"Food & Drink"
        }
    ],
    "sg:menulink":"http://www.allmenus.com/ok/enid/122467-quiznos-sub/menu/",
    "sg:phone":"+1 580 233 7849",
    "sg:postcode":"73703",
    "sg:province":"OK",
    "sg:tags":[
        "wrap",
        "american",
        "sandwich"
    ],
    "wof:name":"Quiznos Sub",
    "wof:placetype":"venue"
},
  "geometry": {"coordinates":[-97.92223199999999,36.390815],"type":"Point"}
}