{
  "type": "Feature",
  "properties": {
    "iso:country":"US",
    "sg:address":"211 N 2nd Ave",
    "sg:city":"Durant",
    "sg:classifiers":[
        {
            "category":"Personal",
            "subcategory":"Beauty Salon",
            "type":"Services"
        }
    ],
    "sg:phone":"+1 580 920 9911",
    "sg:postcode":"74701",
    "sg:province":"OK",
    "wof:name":"Kountry Kuts & Style",
    "wof:placetype":"venue"
},
  "geometry": {"coordinates":[-96.376863,33.993104],"type":"Point"}
}