{
  "type": "Feature",
  "properties": {
    "iso:country":"US",
    "sg:address":"10700 N Rockwell Ave",
    "sg:city":"Oklahoma City",
    "sg:classifiers":[
        {
            "category":"Autos & Motor Vehicles",
            "subcategory":"Auto Supplies",
            "type":"Retail Goods"
        }
    ],
    "sg:phone":"+1 405 720 1750",
    "sg:postcode":"73162",
    "sg:province":"OK",
    "wof:name":"OReilly Automotive Inc",
    "wof:placetype":"venue"
},
  "geometry": {"coordinates":[-97.638366,35.577433],"type":"Point"}
}