{
  "type": "Feature",
  "properties": {
    "iso:country":"US",
    "sg:address":"220 N Harvey Ave",
    "sg:city":"Oklahoma City",
    "sg:classifiers":[
        {
            "category":"Professional",
            "subcategory":"Business Services",
            "type":"Services"
        }
    ],
    "sg:phone":"+1 405 232 1617",
    "sg:postcode":"73102",
    "sg:province":"OK",
    "wof:name":"Shadid & Assoc",
    "wof:placetype":"venue"
},
  "geometry": {"coordinates":[-97.51788,35.468866],"type":"Point"}
}