{
  "type": "Feature",
  "properties": {
    "iso:country":"US",
    "sg:address":"1815 Drakestone Ave",
    "sg:city":"Nichols Hills",
    "sg:classifiers":[
        {
            "category":"Personal",
            "type":"Services"
        },
        {
            "category":"Retail",
            "subcategory":"Animal Services",
            "type":"Services"
        }
    ],
    "sg:phone":"+1 405 842 7297",
    "sg:postcode":"73120",
    "sg:province":"OK",
    "sg:tags":[
        "pet",
        "boarding",
        "sitting"
    ],
    "wof:name":"Happy Tails Pet Sitting",
    "wof:placetype":"venue"
},
  "geometry": {"coordinates":[-97.557702,35.557478],"type":"Point"}
}