{
  "type": "Feature",
  "properties": {
    "iso:country":"US",
    "sg:address":"6112 NW 63rd St",
    "sg:city":"Oklahoma City",
    "sg:classifiers":[
        {
            "category":"Health Services",
            "subcategory":"Doctor",
            "type":"Services"
        }
    ],
    "sg:phone":"+1 405 722 9500",
    "sg:postcode":"73132",
    "sg:province":"OK",
    "sg:tags":[
        "physician",
        "surgeon"
    ],
    "wof:name":"Outpatient Services For Women",
    "wof:placetype":"venue"
},
  "geometry": {"coordinates":[-97.624447,35.536795],"type":"Point"}
}