{
  "type": "Feature",
  "properties": {
    "addr:full":"1830 E 3rd St Tulsa OK 74104",
    "addr:housenumber":"1830",
    "addr:postcode":"74104",
    "addr:street":"E 3Rd St",
    "iso:country":"US",
    "sg:address":"1830 E 3rd St",
    "sg:city":"Tulsa",
    "sg:classifiers":[
        {
            "category":"Retail",
            "subcategory":"Auto Repair",
            "type":"Services"
        }
    ],
    "sg:phone":"+1 918 592 1607",
    "sg:postcode":"74104",
    "sg:province":"OK",
    "sg:tags":[
        "general"
    ],
    "wof:name":"Autohaus Unlimited",
    "wof:placetype":"venue"
},
  "geometry": {"coordinates":[-95.96499,36.156557],"type":"Point"}
}