{
  "type": "Feature",
  "properties": {
    "iso:country":"US",
    "sg:address":"6500 S 49th West Ave",
    "sg:city":"Tulsa",
    "sg:classifiers":[
        {
            "category":"Shopping",
            "subcategory":"Bicycles & Sporting Goods",
            "type":"Retail Goods"
        }
    ],
    "sg:phone":"+1 918 446 5518",
    "sg:postcode":"74131",
    "sg:province":"OK",
    "sg:tags":[
        "equipment",
        "golf",
        "supply"
    ],
    "sg:website":"www.oakscountryclub.com",
    "wof:name":"Golf Shop & Professional",
    "wof:placetype":"venue"
},
  "geometry": {"coordinates":[-96.047494,36.07008],"type":"Point"}
}