{
  "type": "Feature",
  "properties": {
    "addr:full":"2303 Cornerstone Ave Claremore OK 74017",
    "addr:housenumber":"2303",
    "addr:postcode":"74017",
    "addr:street":"Cornerstone Ave",
    "iso:country":"US",
    "sg:address":"2303 Cornerstone Ave",
    "sg:city":"Claremore",
    "sg:classifiers":[
        {
            "category":"Professional",
            "type":"Services"
        }
    ],
    "sg:phone":"+1 918 342 0291",
    "sg:postcode":"74017",
    "sg:province":"OK",
    "sg:tags":[
        "personal"
    ],
    "wof:name":"Remarkarable Lawn Service",
    "wof:placetype":"venue"
},
  "geometry": {"coordinates":[-95.640632,36.331447],"type":"Point"}
}