{
  "type": "Feature",
  "properties": {
    "addr:full":"1908 S Harvard Ave Tulsa OK 74112",
    "addr:housenumber":"1908",
    "addr:postcode":"74112",
    "addr:street":"S Harvard Ave",
    "iso:country":"US",
    "sg:address":"1908 S Harvard Ave",
    "sg:city":"Tulsa",
    "sg:classifiers":[
        {
            "category":"Shopping",
            "subcategory":"Used Merchandise",
            "type":"Retail Goods"
        }
    ],
    "sg:phone":"+1 918 742 5912",
    "sg:postcode":"74112",
    "sg:province":"OK",
    "sg:tags":[
        "antique"
    ],
    "wof:name":"Side Door Antiques & Rfnshng",
    "wof:placetype":"venue"
},
  "geometry": {"coordinates":[-95.94042899999999,36.133312],"type":"Point"}
}