{
  "type": "Feature",
  "properties": {
    "iso:country":"US",
    "sg:address":"356 S Kelly Ave",
    "sg:city":"Edmond",
    "sg:classifiers":[
        {
            "category":"Retail",
            "subcategory":"Animal Services",
            "type":"Services"
        }
    ],
    "sg:phone":"+1 405 359 0601",
    "sg:postcode":"73003",
    "sg:province":"OK",
    "sg:tags":[
        "merchandise"
    ],
    "wof:name":"Blue Ribbon Boutique",
    "wof:placetype":"venue"
},
  "geometry": {"coordinates":[-97.49593,35.651346],"type":"Point"}
}