{
  "type": "Feature",
  "properties": {
    "iso:country":"US",
    "sg:address":"402 N Porter Ave",
    "sg:city":"Norman",
    "sg:classifiers":[
        {
            "category":"Retail",
            "subcategory":"Animal Services",
            "type":"Services"
        }
    ],
    "sg:phone":"+1 405 360 7387",
    "sg:postcode":"73071",
    "sg:province":"OK",
    "sg:tags":[
        "pet",
        "grooming",
        "washing"
    ],
    "wof:name":"Posh Peters Grooming Centre",
    "wof:placetype":"venue"
},
  "geometry": {"coordinates":[-97.441086,35.225667],"type":"Point"}
}