{
  "type": "Feature",
  "properties": {
    "iso:country":"US",
    "sg:address":"120 SW 102nd St",
    "sg:city":"Oklahoma City",
    "sg:classifiers":[
        {
            "category":"Education",
            "subcategory":"Special Training",
            "type":"Public Place"
        }
    ],
    "sg:phone":"+1 405 793 7800",
    "sg:postcode":"73139",
    "sg:province":"OK",
    "wof:name":"Seminars Silva International",
    "wof:placetype":"venue"
},
  "geometry": {"coordinates":[-97.515902,35.365579],"type":"Point"}
}