{
  "type": "Feature",
  "properties": {
    "iso:country":"US",
    "sg:address":"724 NW 21st St",
    "sg:city":"Oklahoma City",
    "sg:classifiers":[
        {
            "category":"Shopping",
            "subcategory":"Used Merchandise",
            "type":"Retail Goods"
        }
    ],
    "sg:phone":"+1 405 524 7821",
    "sg:postcode":"73103",
    "sg:province":"OK",
    "wof:name":"Lamars Antiques",
    "wof:placetype":"venue"
},
  "geometry": {"coordinates":[-97.525451,35.491116],"type":"Point"}
}