{
  "type": "Feature",
  "properties": {
    "iso:country":"US",
    "sg:address":"2117 S Air Depot Blvd",
    "sg:city":"Midwest City",
    "sg:classifiers":[
        {
            "category":"Shopping",
            "subcategory":"Used Merchandise",
            "type":"Retail Goods"
        }
    ],
    "sg:phone":"+1 405 869 9422",
    "sg:postcode":"73110",
    "sg:province":"OK",
    "sg:tags":[
        "pawnbroker"
    ],
    "wof:name":"Big K Pawn Shop",
    "wof:placetype":"venue"
},
  "geometry": {"coordinates":[-97.4061,35.444108],"type":"Point"}
}