{
  "type": "Feature",
  "properties": {
    "addr:full":"1430 N Portland Ave Oklahoma City OK 73107",
    "addr:housenumber":"1430",
    "addr:postcode":"73107",
    "addr:street":"N Portland Ave",
    "iso:country":"US",
    "sg:address":"1430 N Portland Ave",
    "sg:city":"Oklahoma City",
    "sg:classifiers":[
        {
            "category":"Building & Trades",
            "subcategory":"Equipment Rental",
            "type":"Services"
        }
    ],
    "sg:phone":"+1 405 946 0275",
    "sg:postcode":"73107",
    "sg:province":"OK",
    "sg:tags":[
        "contractor"
    ],
    "sg:website":"www.crosslands.com",
    "wof:name":"Crossland's A & A Rent-All Co",
    "wof:placetype":"venue"
},
  "geometry": {"coordinates":[-97.58327300000001,35.483946],"type":"Point"}
}