{
  "type": "Feature",
  "properties": {
    "iso:country":"US",
    "sg:address":"105 N 5th St",
    "sg:city":"Jenks",
    "sg:classifiers":[
        {
            "category":"Shopping",
            "subcategory":"Books",
            "type":"Retail Goods"
        }
    ],
    "sg:phone":"+1 918 296 3392",
    "sg:postcode":"74037",
    "sg:province":"OK",
    "sg:tags":[
        "dealer"
    ],
    "wof:name":"Gospel Station Bookstore",
    "wof:placetype":"venue"
},
  "geometry": {"coordinates":[-95.964623,36.022623],"type":"Point"}
}