{
  "type": "Feature",
  "properties": {
    "iso:country":"US",
    "sg:address":"2700 NE 122nd St",
    "sg:city":"Edmond",
    "sg:classifiers":[
        {
            "category":"Building & Trades",
            "subcategory":"Construction",
            "type":"Services"
        }
    ],
    "sg:phone":"+1 405 478 5050",
    "sg:postcode":"73013",
    "sg:province":"OK",
    "sg:tags":[
        "resurfacing",
        "laying",
        "refinishing",
        "floor"
    ],
    "wof:name":"Gary Hicks Floor Svc",
    "wof:placetype":"venue"
},
  "geometry": {"coordinates":[-97.478245,35.594394],"type":"Point"}
}