{
  "type": "Feature",
  "properties": {
    "iso:country":"US",
    "sg:address":"501 NW 27th St",
    "sg:city":"Moore",
    "sg:classifiers":[
        {
            "category":"Retail",
            "subcategory":"Laundry & Dry Cleaning",
            "type":"Services"
        }
    ],
    "sg:phone":"+1 405 895 7358",
    "sg:postcode":"73160",
    "sg:province":"OK",
    "sg:tags":[
        "cleaners",
        "rug",
        "carpet"
    ],
    "wof:name":"Montgomery Rich Carpet Svc",
    "wof:placetype":"venue"
},
  "geometry": {"coordinates":[-97.500136,35.363384],"type":"Point"}
}