{
  "type": "Feature",
  "properties": {
    "iso:country":"US",
    "sg:address":"1702 S George Nigh Expy",
    "sg:city":"Mcalester",
    "sg:classifiers":[
        {
            "category":"Retail",
            "subcategory":"Auto Rental",
            "type":"Services"
        }
    ],
    "sg:phone":"+1 918 426 1415",
    "sg:postcode":"74501",
    "sg:province":"OK",
    "sg:tags":[
        "renting",
        "truck",
        "leasing"
    ],
    "wof:name":"Budget Truck Rental",
    "wof:placetype":"venue"
},
  "geometry": {"coordinates":[-95.761157,34.897267],"type":"Point"}
}