{
  "type": "Feature",
  "properties": {
    "iso:country":"US",
    "sg:address":"10229 Bradford Way",
    "sg:city":"Yukon",
    "sg:classifiers":[
        {
            "category":"Building & Trades",
            "subcategory":"Cleaning & Sanitation",
            "type":"Services"
        }
    ],
    "sg:phone":"+1 405 760 1750",
    "sg:postcode":"73099",
    "sg:province":"OK",
    "sg:tags":[
        "house"
    ],
    "wof:name":"Krystal Kleen",
    "wof:placetype":"venue"
},
  "geometry": {"coordinates":[-97.702146,35.454579],"type":"Point"}
}