{
  "type": "Feature",
  "properties": {
    "iso:country":"US",
    "sg:address":"5419 E 96th St N",
    "sg:city":"Sperry",
    "sg:classifiers":[
        {
            "category":"Wholesale",
            "subcategory":"Machinery & Supplies",
            "type":"Manufacturing & Wholesale Goods"
        }
    ],
    "sg:phone":"+1 918 288 7719",
    "sg:postcode":"74073",
    "sg:province":"OK",
    "sg:tags":[
        "truck"
    ],
    "wof:name":"Wilson & Assoc",
    "wof:placetype":"venue"
},
  "geometry": {"coordinates":[-95.916632,36.293156],"type":"Point"}
}