{
  "type": "Feature",
  "properties": {
    "iso:country":"US",
    "sg:address":"1105 S Tamarack Ave",
    "sg:city":"Broken Arrow",
    "sg:classifiers":[
        {
            "category":"Professional",
            "subcategory":"Business Services",
            "type":"Services"
        }
    ],
    "sg:phone":"+1 918 254 5197",
    "sg:postcode":"74012",
    "sg:province":"OK",
    "wof:name":"Carruthers Group Ltd",
    "wof:placetype":"venue"
},
  "geometry": {"coordinates":[-95.838511,36.042424],"type":"Point"}
}