{
  "type": "Feature",
  "properties": {
    "iso:country":"US",
    "sg:address":"1300 W Lindsay Ave",
    "sg:city":"Sulphur",
    "sg:classifiers":[
        {
            "category":"Health Services",
            "subcategory":"Nursing And Care Facility",
            "type":"Services"
        }
    ],
    "sg:phone":"+1 580 622 2416",
    "sg:postcode":"73086",
    "sg:province":"OK",
    "wof:name":"Callaway Nursing Home",
    "wof:placetype":"venue"
},
  "geometry": {"coordinates":[-96.984799,34.498174],"type":"Point"}
}