{
  "type": "Feature",
  "properties": {
    "iso:country":"US",
    "sg:address":"311 W Missouri Ave",
    "sg:city":"Walters",
    "sg:classifiers":[
        {
            "category":"Food & Beverages",
            "subcategory":"Groceries & Convenience Stores",
            "type":"Retail Goods"
        }
    ],
    "sg:phone":"+1 580 875 2001",
    "sg:postcode":"73572",
    "sg:province":"OK",
    "wof:name":"Walter's Super Store",
    "wof:placetype":"venue"
},
  "geometry": {"coordinates":[-98.31271700000001,34.362174],"type":"Point"}
}