{
  "type": "Feature",
  "properties": {
    "iso:country":"US",
    "sg:address":"904 W Kenosha St",
    "sg:city":"Broken Arrow",
    "sg:classifiers":[
        {
            "category":"Manufacturing",
            "subcategory":"Electronics",
            "type":"Manufacturing & Wholesale Goods"
        }
    ],
    "sg:phone":"+1 918 251 0477",
    "sg:postcode":"74012",
    "sg:province":"OK",
    "sg:tags":[
        "prerecorded",
        "cassette",
        "cd",
        "video",
        "replication"
    ],
    "wof:name":"Cassette Outlet",
    "wof:placetype":"venue"
},
  "geometry": {"coordinates":[-95.80152,36.061028],"type":"Point"}
}