{
  "type": "Feature",
  "properties": {
    "addr:full":"428 E Wyandotte Ave Mcalester OK 74501",
    "addr:housenumber":"428",
    "addr:postcode":"74501",
    "addr:street":"E Wyandotte Ave",
    "iso:country":"US",
    "sg:address":"428 E Wyandotte Ave",
    "sg:city":"Mcalester",
    "sg:classifiers":[
        {
            "category":"Social Services",
            "type":"Services"
        }
    ],
    "sg:phone":"+1 918 423 6677",
    "sg:postcode":"74501",
    "sg:province":"OK",
    "sg:tags":[
        "organization",
        "welfare"
    ],
    "wof:name":"United Way Of Mc Alester",
    "wof:placetype":"venue"
},
  "geometry": {"coordinates":[-95.765456,34.927923],"type":"Point"}
}