{
  "type": "Feature",
  "properties": {
    "iso:country":"US",
    "sg:address":"2003 W Warner Ave",
    "sg:city":"Guthrie",
    "sg:classifiers":[
        {
            "category":"Health Services",
            "subcategory":"Doctor",
            "type":"Services"
        }
    ],
    "sg:phone":"+1 405 282 9025",
    "sg:postcode":"73044",
    "sg:province":"OK",
    "sg:tags":[
        "clinic"
    ],
    "wof:name":"Cottonwood Community Clinic",
    "wof:placetype":"venue"
},
  "geometry": {"coordinates":[-97.449495,35.880903],"type":"Point"}
}