{
  "type": "Feature",
  "properties": {
    "iso:country":"US",
    "sg:address":"2207 Chandler Rd",
    "sg:city":"Muskogee",
    "sg:classifiers":[
        {
            "category":"Wholesale",
            "subcategory":"Chemicals & Plastics",
            "type":"Manufacturing & Wholesale Goods"
        }
    ],
    "sg:phone":"+1 918 682 3501",
    "sg:postcode":"74403",
    "sg:province":"OK",
    "sg:tags":[
        "oxygen"
    ],
    "wof:name":"Lincare",
    "wof:placetype":"venue"
},
  "geometry": {"coordinates":[-95.343377,35.74051],"type":"Point"}
}