{
  "type": "Feature",
  "properties": {
    "iso:country":"US",
    "sg:address":"308 S 8th Ave",
    "sg:city":"Stroud",
    "sg:phone":"+1 918 968 2134",
    "sg:postcode":"74079",
    "sg:province":"OK",
    "sg:tags":[
        "gas"
    ],
    "wof:name":"MFA Propane",
    "wof:placetype":"venue"
},
  "geometry": {"coordinates":[-96.662892,35.744853],"type":"Point"}
}