{
  "type": "Feature",
  "properties": {
    "iso:country":"US",
    "sg:address":"1516 S Yorktown Pl",
    "sg:city":"Tulsa",
    "sg:classifiers":[
        {
            "category":"Health Services",
            "subcategory":"Medical Lab",
            "type":"Services"
        }
    ],
    "sg:phone":"+1 918 712 8888",
    "sg:postcode":"74104",
    "sg:province":"OK",
    "sg:tags":[
        "laboratory"
    ],
    "wof:name":"David B Minor MD",
    "wof:placetype":"venue"
},
  "geometry": {"coordinates":[-95.96079400000001,36.138215],"type":"Point"}
}