{
  "type": "Feature",
  "properties": {
    "addr:full":"805 S 11th St Broken Arrow OK 74012",
    "addr:housenumber":"805",
    "addr:postcode":"74012",
    "addr:street":"S 11Th St",
    "iso:country":"US",
    "sg:address":"805 S 11th St",
    "sg:city":"Broken Arrow",
    "sg:classifiers":[
        {
            "category":"Professional",
            "type":"Services"
        }
    ],
    "sg:phone":"+1 918 258 2913",
    "sg:postcode":"74012",
    "sg:province":"OK",
    "sg:tags":[
        "establishment"
    ],
    "wof:name":"Meca Enterprises",
    "wof:placetype":"venue"
},
  "geometry": {"coordinates":[-95.77731300000001,36.044664],"type":"Point"}
}