{
  "type": "Feature",
  "properties": {
    "iso:country":"US",
    "sg:address":"439 South Sheridan Road",
    "sg:city":"Tulsa",
    "sg:classifiers":[
        {
            "category":"Retail",
            "subcategory":"Auto Repair",
            "type":"Services"
        }
    ],
    "sg:phone":"+1 918 592 3458",
    "sg:postcode":"74112",
    "sg:province":"OK",
    "sg:tags":[
        "wheel",
        "body",
        "automobile",
        "servicing-automotive",
        "axle",
        "alignment-frame",
        "painting",
        "repairing"
    ],
    "wof:name":"AAA Frame & Body Shop",
    "wof:placetype":"venue"
},
  "geometry": {"coordinates":[-95.904579,36.155771],"type":"Point"}
}