{
  "type": "Feature",
  "properties": {
    "addr:full":"2825 SW 41st St Oklahoma City OK 73119",
    "addr:housenumber":"2825",
    "addr:postcode":"73119",
    "addr:street":"Sw 41St St",
    "iso:country":"US",
    "sg:address":"2825 SW 41st St",
    "sg:city":"Oklahoma City",
    "sg:classifiers":[
        {
            "category":"Social Services",
            "subcategory":"Child Care",
            "type":"Services"
        }
    ],
    "sg:phone":"+1 405 681 1413",
    "sg:postcode":"73119",
    "sg:province":"OK",
    "sg:tags":[
        "day"
    ],
    "wof:name":"Joe's Little Rascals Daycare",
    "wof:placetype":"venue"
},
  "geometry": {"coordinates":[-97.564931,35.423732],"type":"Point"}
}