{
  "type": "Feature",
  "properties": {
    "iso:country":"US",
    "sg:address":"7010 E 41st St",
    "sg:city":"Tulsa",
    "sg:classifiers":[
        {
            "category":"Retail",
            "subcategory":"Auto Repair",
            "type":"Services"
        }
    ],
    "sg:phone":"+1 918 622 6311",
    "sg:postcode":"74145",
    "sg:province":"OK",
    "sg:tags":[
        "repairing",
        "automobile",
        "replacement",
        "glass",
        "general"
    ],
    "sg:website":"www.safelite.com",
    "wof:name":"Safelite Auto Glass",
    "wof:placetype":"venue"
},
  "geometry": {"coordinates":[-95.897395,36.104328],"type":"Point"}
}