{
  "type": "Feature",
  "properties": {
    "iso:country":"US",
    "sg:address":"3520 S Robinson Ave",
    "sg:city":"Oklahoma City",
    "sg:classifiers":[
        {
            "category":"Retail",
            "subcategory":"Auto Repair",
            "type":"Services"
        }
    ],
    "sg:phone":"+1 405 632 3811",
    "sg:postcode":"73109",
    "sg:province":"OK",
    "sg:tags":[
        "repairing",
        "body",
        "shop",
        "automobile",
        "top",
        "paint"
    ],
    "wof:name":"G & G Auto Repair",
    "wof:placetype":"venue"
},
  "geometry": {"coordinates":[-97.516103,35.429388],"type":"Point"}
}