{
  "type": "Feature",
  "properties": {
    "iso:country":"US",
    "sg:address":"4306 Butler Pl",
    "sg:city":"Oklahoma City",
    "sg:classifiers":[
        {
            "category":"Building & Trades",
            "subcategory":"Construction",
            "type":"Services"
        }
    ],
    "sg:phone":"+1 405 948 6024",
    "sg:postcode":"73118",
    "sg:province":"OK",
    "sg:tags":[
        "repairing",
        "remodeling",
        "contractor"
    ],
    "wof:name":"Deck Masters",
    "wof:placetype":"venue"
},
  "geometry": {"coordinates":[-97.535467,35.515924],"type":"Point"}
}