{
  "type": "Feature",
  "properties": {
    "addr:full":"2012 Research Park Blvd Norman OK 73069",
    "addr:housenumber":"2012",
    "addr:postcode":"73069",
    "addr:street":"Research Park Blvd",
    "iso:country":"US",
    "sg:address":"2012 Research Park Blvd",
    "sg:city":"Norman",
    "sg:classifiers":[
        {
            "category":"Shopping",
            "subcategory":"Musical Instruments",
            "type":"Retail Goods"
        }
    ],
    "sg:phone":"+1 405 321 0366",
    "sg:postcode":"73069",
    "sg:province":"OK",
    "sg:tags":[
        "guitar"
    ],
    "wof:name":"Scott's Tube Mixer & Amplifier",
    "wof:placetype":"venue"
},
  "geometry": {"coordinates":[-97.45287399999999,35.245961],"type":"Point"}
}