{
  "type": "Feature",
  "properties": {
    "iso:country":"US",
    "sg:address":"416 S Lewis St",
    "sg:city":"Stillwater",
    "sg:classifiers":[
        {
            "category":"Health Services",
            "subcategory":"Doctor",
            "type":"Services"
        }
    ],
    "sg:phone":"+1 405 372 1177",
    "sg:postcode":"74074",
    "sg:province":"OK",
    "sg:tags":[
        "medical"
    ],
    "wof:name":"Baiba Ercum MD",
    "wof:placetype":"venue"
},
  "geometry": {"coordinates":[-97.05736,36.117663],"type":"Point"}
}