{
  "type": "Feature",
  "properties": {
    "addr:full":"407 E Broadway Ave Mcloud OK 74851",
    "addr:housenumber":"407",
    "addr:postcode":"74851",
    "addr:street":"E Broadway Ave",
    "iso:country":"US",
    "sg:address":"407 E Broadway Ave",
    "sg:city":"Mcloud",
    "sg:classifiers":[
        {
            "category":"Restaurant",
            "type":"Food & Drink"
        }
    ],
    "sg:menulink":"http://www.allmenus.com/ok/shawnee/68005-simple-simons-pizza/menu/",
    "sg:phone":"+1 405 964 5979",
    "sg:postcode":"74851",
    "sg:province":"OK",
    "sg:tags":[
        "american",
        "pizza"
    ],
    "wof:name":"Simple Simon's Pizza",
    "wof:placetype":"venue"
},
  "geometry": {"coordinates":[-97.090746,35.436007],"type":"Point"}
}