{
  "type": "Feature",
  "properties": {
    "iso:country":"US",
    "sg:address":"1147 S Owasso Ave",
    "sg:city":"Tulsa",
    "sg:classifiers":[
        {
            "category":"Manufacturing",
            "subcategory":"Printing",
            "type":"Manufacturing & Wholesale Goods"
        }
    ],
    "sg:phone":"+1 918 271 1414",
    "sg:postcode":"74120",
    "sg:province":"OK",
    "sg:tags":[
        "apparel",
        "plexiglas",
        "plus",
        "a",
        "promotional"
    ],
    "wof:name":"Big House Specialty Prtg Inc",
    "wof:placetype":"venue"
},
  "geometry": {"coordinates":[-95.976769,36.146663],"type":"Point"}
}