{
  "type": "Feature",
  "properties": {
    "addr:full":"109 W Parkland Dr Yukon OK 73099",
    "addr:housenumber":"109",
    "addr:postcode":"73099",
    "addr:street":"W Parkland Dr",
    "iso:country":"US",
    "sg:address":"109 W Parkland Dr",
    "sg:city":"Yukon",
    "sg:classifiers":[
        {
            "category":"Retail",
            "subcategory":"Portrait Studio",
            "type":"Services"
        }
    ],
    "sg:phone":"+1 405 354 7371",
    "sg:postcode":"73099",
    "sg:province":"OK",
    "sg:tags":[
        "photo"
    ],
    "wof:name":"Kelly Holstein Photograph",
    "wof:placetype":"venue"
},
  "geometry": {"coordinates":[-97.74650200000001,35.482329],"type":"Point"}
}