{
  "type": "Feature",
  "properties": {
    "iso:country":"US",
    "sg:address":"3247 W Main St",
    "sg:city":"Norman",
    "sg:classifiers":[
        {
            "category":"Shopping",
            "subcategory":"Clothing, Apparel, & Fashions",
            "type":"Retail Goods"
        }
    ],
    "sg:phone":"+1 405 579 9197",
    "sg:postcode":"73072",
    "sg:province":"OK",
    "wof:name":"Limited Too",
    "wof:placetype":"venue"
},
  "geometry": {"coordinates":[-97.491339,35.218245],"type":"Point"}
}