{
  "type": "Feature",
  "properties": {
    "iso:country":"US",
    "sg:address":"4001 S Narcissus Ave",
    "sg:city":"Broken Arrow",
    "sg:classifiers":[
        {
            "category":"Travel",
            "subcategory":"Travel Agent",
            "type":"Entertainment"
        }
    ],
    "sg:phone":"+1 918 449 1183",
    "sg:postcode":"74011",
    "sg:province":"OK",
    "sg:tags":[
        "agency"
    ],
    "wof:name":"Boston Avenue Travel Inc",
    "wof:placetype":"venue"
},
  "geometry": {"coordinates":[-95.806758,36.012339],"type":"Point"}
}