{
  "type": "Feature",
  "properties": {
    "iso:country":"US",
    "sg:address":"223 E Randolph Ave",
    "sg:city":"Enid",
    "sg:classifiers":[
        {
            "category":"Retail",
            "subcategory":"Repair Shop",
            "type":"Services"
        }
    ],
    "sg:phone":"+1 580 237 2492",
    "sg:postcode":"73701",
    "sg:province":"OK",
    "wof:name":"Bobs TV & Video",
    "wof:placetype":"venue"
},
  "geometry": {"coordinates":[-97.87667999999999,36.397809],"type":"Point"}
}