{
  "type": "Feature",
  "properties": {
    "addr:full":"4910 N Lincoln Blvd Oklahoma City OK 73105",
    "addr:housenumber":"4910",
    "addr:postcode":"73105",
    "addr:street":"N Lincoln Blvd",
    "iso:country":"US",
    "sg:address":"4910 N Lincoln Blvd",
    "sg:city":"Oklahoma City",
    "sg:classifiers":[
        {
            "category":"Restaurant",
            "type":"Food & Drink"
        }
    ],
    "sg:phone":"+1 405 525 8352",
    "sg:postcode":"73105",
    "sg:province":"OK",
    "wof:name":"Jamil's Steakhouse",
    "wof:placetype":"venue"
},
  "geometry": {"coordinates":[-97.502858,35.522099],"type":"Point"}
}