{
  "type": "Feature",
  "properties": {
    "addr:full":"7200 S Mingo Rd Tulsa OK 74133",
    "addr:housenumber":"7200",
    "addr:postcode":"74133",
    "addr:street":"S Mingo Rd",
    "iso:country":"US",
    "sg:address":"7200 S Mingo Rd",
    "sg:city":"Tulsa",
    "sg:classifiers":[
        {
            "category":"Home & Garden",
            "subcategory":"Building Materials",
            "type":"Retail Goods"
        }
    ],
    "sg:phone":"+1 918 250 5445",
    "sg:postcode":"74133",
    "sg:province":"OK",
    "sg:tags":[
        "glass",
        "window",
        "plate"
    ],
    "wof:name":"Safelite At Pep Boys",
    "wof:placetype":"venue"
},
  "geometry": {"coordinates":[-95.868578,36.060762],"type":"Point"}
}