{
  "type": "Feature",
  "properties": {
    "iso:country":"US",
    "sg:address":"2515 S Sheridan Rd",
    "sg:city":"Tulsa",
    "sg:classifiers":[
        {
            "category":"Autos & Motor Vehicles",
            "subcategory":"Auto Supplies",
            "type":"Retail Goods"
        }
    ],
    "sg:phone":"+1 918 836 7708",
    "sg:postcode":"74129",
    "sg:province":"OK",
    "sg:tags":[
        "tire"
    ],
    "wof:name":"Tulsa Tire Specialists",
    "wof:placetype":"venue"
},
  "geometry": {"coordinates":[-95.904491,36.126737],"type":"Point"}
}