{
  "type": "Feature",
  "properties": {
    "iso:country":"US",
    "sg:address":"114 S 5th St",
    "sg:city":"Clinton",
    "sg:classifiers":[
        {
            "category":"Health Services",
            "subcategory":"Doctor",
            "type":"Services"
        }
    ],
    "sg:phone":"+1 580 323 3098",
    "sg:postcode":"73601",
    "sg:province":"OK",
    "wof:name":"Steffen J Michael DDS",
    "wof:placetype":"venue"
},
  "geometry": {"coordinates":[-98.966049,35.514223],"type":"Point"}
}