{
  "type": "Feature",
  "properties": {
    "iso:country":"US",
    "sg:address":"1171 US Hwy 70 Alt",
    "sg:city":"Wilson",
    "sg:classifiers":[
        {
            "category":"Wholesale",
            "subcategory":"Auto Parts",
            "type":"Manufacturing & Wholesale Goods"
        }
    ],
    "sg:phone":"+1 580 668 2457",
    "sg:postcode":"73463",
    "sg:province":"OK",
    "sg:tags":[
        "supply"
    ],
    "wof:name":"Wilson Auto Supply",
    "wof:placetype":"venue"
},
  "geometry": {"coordinates":[-97.430832,34.171093],"type":"Point"}
}