{
  "type": "Feature",
  "properties": {
    "iso:country":"US",
    "sg:address":"1017 17th St",
    "sg:city":"Woodward",
    "sg:classifiers":[
        {
            "category":"Health Services",
            "subcategory":"Doctor",
            "type":"Services"
        }
    ],
    "sg:phone":"+1 580 256 1107",
    "sg:postcode":"73801",
    "sg:province":"OK",
    "sg:tags":[
        "physician",
        "surgeon"
    ],
    "wof:name":"Woodward Women's Health",
    "wof:placetype":"venue"
},
  "geometry": {"coordinates":[-99.40101799999999,36.436968],"type":"Point"}
}