{
  "type": "Feature",
  "properties": {
    "iso:country":"US",
    "sg:address":"3400 192nd Ave SE",
    "sg:city":"Noble",
    "sg:classifiers":[
        {
            "category":"Shopping",
            "subcategory":"Beauty & Cosmetics",
            "type":"Retail Goods"
        }
    ],
    "sg:phone":"+1 405 364 8572",
    "sg:postcode":"73068",
    "sg:province":"OK",
    "sg:tags":[
        "merchandise"
    ],
    "wof:name":"Homestead Soapworks LLC",
    "wof:placetype":"venue"
},
  "geometry": {"coordinates":[-97.159735,35.176141],"type":"Point"}
}