{
  "type": "Feature",
  "properties": {
    "iso:country":"US",
    "sg:address":"16557 NE 23rd St",
    "sg:city":"Choctaw",
    "sg:classifiers":[
        {
            "category":"Home & Garden",
            "subcategory":"Carpets & Floor Coverings",
            "type":"Retail Goods"
        }
    ],
    "sg:phone":"+1 405 390 8453",
    "sg:postcode":"73020",
    "sg:province":"OK",
    "sg:tags":[
        "dealer",
        "rug"
    ],
    "wof:name":"Oklahoma Tile & Carpet Distr",
    "wof:placetype":"venue"
},
  "geometry": {"coordinates":[-97.238012,35.493318],"type":"Point"}
}