{
  "type": "Feature",
  "properties": {
    "iso:country":"US",
    "sg:address":"610 S Main St",
    "sg:city":"Tulsa",
    "sg:classifiers":[
        {
            "category":"Professional",
            "subcategory":"Secretarial Services",
            "type":"Services"
        }
    ],
    "sg:phone":"+1 918 587 2878",
    "sg:postcode":"74119",
    "sg:province":"OK",
    "sg:tags":[
        "reporting",
        "court"
    ],
    "wof:name":"Tulsa Freelance Reporters",
    "wof:placetype":"venue"
},
  "geometry": {"coordinates":[-95.989125,36.14962],"type":"Point"}
}