{
  "type": "Feature",
  "properties": {
    "iso:country":"US",
    "sg:address":"301 S Barker Ave",
    "sg:city":"El Reno",
    "sg:classifiers":[
        {
            "category":"Retail",
            "subcategory":"Auto Repair",
            "type":"Services"
        }
    ],
    "sg:phone":"+1 405 262 0619",
    "sg:postcode":"73036",
    "sg:province":"OK",
    "sg:tags":[
        "body"
    ],
    "wof:name":"York Sport Classic Cars",
    "wof:placetype":"venue"
},
  "geometry": {"coordinates":[-97.951535,35.531389],"type":"Point"}
}