{
  "type": "Feature",
  "properties": {
    "iso:country":"US",
    "sg:address":"3909 24th Ave NW",
    "sg:city":"Norman",
    "sg:classifiers":[
        {
            "category":"Shopping",
            "subcategory":"Clothing, Apparel, & Fashions",
            "type":"Retail Goods"
        }
    ],
    "sg:phone":"+1 405 447 7777",
    "sg:postcode":"73069",
    "sg:province":"OK",
    "sg:tags":[
        "printing",
        "commercial"
    ],
    "wof:name":"Campus Ragz",
    "wof:placetype":"venue"
},
  "geometry": {"coordinates":[-97.47670599999999,35.266234],"type":"Point"}
}