{
  "type": "Feature",
  "properties": {
    "addr:full":"211 SW C Ave Lawton OK 73502",
    "addr:housenumber":"211",
    "addr:postcode":"73502",
    "addr:street":"Sw C Ave",
    "iso:country":"US",
    "sg:address":"211 SW C Ave",
    "sg:city":"Lawton",
    "sg:classifiers":[
        {
            "category":"Home & Garden",
            "subcategory":"Home Furnishings",
            "type":"Retail Goods"
        }
    ],
    "sg:phone":"+1 580 248 9900",
    "sg:postcode":"73502",
    "sg:province":"OK",
    "sg:tags":[
        "accent"
    ],
    "wof:name":"Brass Acorn The",
    "wof:placetype":"venue"
},
  "geometry": {"coordinates":[-98.391904,34.60528],"type":"Point"}
}