{
  "type": "Feature",
  "properties": {
    "iso:country":"US",
    "sg:address":"1480 W Blue Starr Dr",
    "sg:city":"Claremore",
    "sg:classifiers":[
        {
            "category":"Health Services",
            "subcategory":"Doctor",
            "type":"Services"
        }
    ],
    "sg:phone":"+1 918 342 5070",
    "sg:postcode":"74017",
    "sg:province":"OK",
    "sg:tags":[
        "dentist"
    ],
    "wof:name":"Steven R Scott DDS",
    "wof:placetype":"venue"
},
  "geometry": {"coordinates":[-95.625372,36.321974],"type":"Point"}
}