{
  "type": "Feature",
  "properties": {
    "addr:full":"207 N Noble Ave Watonga OK 73772",
    "addr:housenumber":"207",
    "addr:postcode":"73772",
    "addr:street":"N Noble Ave",
    "iso:country":"US",
    "sg:address":"207 N Noble Ave",
    "sg:city":"Watonga",
    "sg:classifiers":[
        {
            "category":"Utilities",
            "subcategory":"Telephone",
            "type":"Services"
        }
    ],
    "sg:phone":"+1 580 623 7332",
    "sg:postcode":"73772",
    "sg:province":"OK",
    "sg:tags":[
        "company"
    ],
    "wof:name":"Pioneer Telephone Cooperative",
    "wof:placetype":"venue"
},
  "geometry": {"coordinates":[-98.413163,35.845879],"type":"Point"}
}