{
  "type": "Feature",
  "properties": {
    "iso:country":"US",
    "sg:address":"7226 NW Hunter Rd",
    "sg:city":"Lawton",
    "sg:classifiers":[
        {
            "category":"Utilities",
            "type":"Services"
        }
    ],
    "sg:phone":"+1 580 531 2255",
    "sg:postcode":"73505",
    "sg:province":"OK",
    "sg:tags":[
        "sanitary",
        "trade",
        "contractor"
    ],
    "wof:name":"Hensons Commercial Sweeping",
    "wof:placetype":"venue"
},
  "geometry": {"coordinates":[-98.482933,34.627115],"type":"Point"}
}