{
  "type": "Feature",
  "properties": {
    "iso:country":"US",
    "sg:address":"322 N 5th St",
    "sg:city":"Okemah",
    "sg:classifiers":[
        {
            "category":"Retail",
            "subcategory":"Auto Repair",
            "type":"Services"
        }
    ],
    "sg:phone":"+1 918 623 0074",
    "sg:postcode":"74859",
    "sg:province":"OK",
    "sg:tags":[
        "repairing",
        "automobile"
    ],
    "wof:name":"Wally's Auto & Tire Svc",
    "wof:placetype":"venue"
},
  "geometry": {"coordinates":[-96.30595099999999,35.434897],"type":"Point"}
}