{
  "type": "Feature",
  "properties": {
    "iso:country":"US",
    "sg:address":"510 N Main St",
    "sg:city":"Kingfisher",
    "sg:classifiers":[
        {
            "category":"Autos & Motor Vehicles",
            "subcategory":"Automobile Sales",
            "type":"Retail Goods"
        }
    ],
    "sg:phone":"+1 405 375 5882",
    "sg:postcode":"73750",
    "sg:province":"OK",
    "sg:tags":[
        "used"
    ],
    "wof:name":"Hiway 81 Used Cars",
    "wof:placetype":"venue"
},
  "geometry": {"coordinates":[-97.93278599999999,35.865832],"type":"Point"}
}