{
  "type": "Feature",
  "properties": {
    "addr:full":"3510 Wynn Cir Edmond OK 73013",
    "addr:housenumber":"3510",
    "addr:postcode":"73013",
    "addr:street":"Wynn Cir",
    "iso:country":"US",
    "sg:address":"3510 Wynn Cir",
    "sg:city":"Edmond",
    "sg:classifiers":[
        {
            "category":"Building & Trades",
            "subcategory":"Construction",
            "type":"Services"
        }
    ],
    "sg:phone":"+1 405 359 6572",
    "sg:postcode":"73013",
    "sg:province":"OK",
    "sg:tags":[
        "hanging",
        "contractor"
    ],
    "wof:name":"Albers Painting & Repai",
    "wof:placetype":"venue"
},
  "geometry": {"coordinates":[-97.48514,35.620454],"type":"Point"}
}