{
  "type": "Feature",
  "properties": {
    "addr:full":"1109 Skelly Ave Guymon OK 73942",
    "addr:housenumber":"1109",
    "addr:postcode":"73942",
    "addr:street":"Skelly Ave",
    "iso:country":"US",
    "sg:address":"1109 Skelly Ave",
    "sg:city":"Guymon",
    "sg:classifiers":[
        {
            "category":"Mining & Drilling",
            "type":"Manufacturing & Wholesale Goods"
        }
    ],
    "sg:phone":"+1 580 338 6820",
    "sg:postcode":"73942",
    "sg:province":"OK",
    "sg:tags":[
        "oil",
        "gas",
        "producer"
    ],
    "wof:name":"Chevron",
    "wof:placetype":"venue"
},
  "geometry": {"coordinates":[-101.47397100000001,36.688441],"type":"Point"}
}