{
  "type": "Feature",
  "properties": {
    "iso:country":"US",
    "sg:address":"3016 Paseo St",
    "sg:city":"Oklahoma City",
    "sg:classifiers":[
        {
            "category":"Professional",
            "subcategory":"Business Services",
            "type":"Services"
        }
    ],
    "sg:phone":"+1 405 521 9727",
    "sg:postcode":"73103",
    "sg:province":"OK",
    "wof:name":"Wilkinsons Recording Co",
    "wof:placetype":"venue"
},
  "geometry": {"coordinates":[-97.523142,35.50033],"type":"Point"}
}