{
  "type": "Feature",
  "properties": {
    "iso:country":"US",
    "sg:address":"406 S Johnstone Ave",
    "sg:city":"Bartlesville",
    "sg:classifiers":[
        {
            "category":"Restaurant",
            "type":"Food & Drink"
        }
    ],
    "sg:phone":"+1 918 336 2000",
    "sg:postcode":"74003",
    "sg:province":"OK",
    "wof:name":"Ian's Catering & Restaurant",
    "wof:placetype":"venue"
},
  "geometry": {"coordinates":[-95.977584,36.749842],"type":"Point"}
}