{
  "type": "Feature",
  "properties": {
    "iso:country":"US",
    "sg:address":"11209 Kingsgate Ter",
    "sg:city":"Oklahoma City",
    "sg:classifiers":[
        {
            "category":"Building & Trades",
            "subcategory":"Landscaping Services",
            "type":"Services"
        }
    ],
    "sg:phone":"+1 405 691 3114",
    "sg:postcode":"73170",
    "sg:province":"OK",
    "sg:tags":[
        "lawn",
        "maintenance",
        "grounds"
    ],
    "wof:name":"Turf Cuts Inc",
    "wof:placetype":"venue"
},
  "geometry": {"coordinates":[-97.539311,35.357136],"type":"Point"}
}