{
  "type": "Feature",
  "properties": {
    "addr:full":"2412 SW 44th St Oklahoma City OK 73119",
    "addr:housenumber":"2412",
    "addr:postcode":"73119",
    "addr:street":"Sw 44Th St",
    "iso:country":"US",
    "sg:address":"2412 SW 44th St",
    "sg:city":"Oklahoma City",
    "sg:classifiers":[
        {
            "category":"Food & Beverages",
            "subcategory":"Groceries & Convenience Stores",
            "type":"Retail Goods"
        }
    ],
    "sg:phone":"+1 405 682 4136",
    "sg:postcode":"73119",
    "sg:province":"OK",
    "wof:name":"Kwik Shop",
    "wof:placetype":"venue"
},
  "geometry": {"coordinates":[-97.55659,35.420627],"type":"Point"}
}