{
  "type": "Feature",
  "properties": {
    "addr:full":"209 Blakeley Ave Rush Springs OK 73082",
    "addr:housenumber":"209",
    "addr:postcode":"73082",
    "addr:street":"Blakeley Ave Rush",
    "iso:country":"US",
    "sg:address":"209 Blakeley Ave",
    "sg:city":"Rush Springs",
    "sg:classifiers":[
        {
            "category":"Home & Garden",
            "subcategory":"Hardware",
            "type":"Retail Goods"
        }
    ],
    "sg:phone":"+1 580 476 3562",
    "sg:postcode":"73082",
    "sg:province":"OK",
    "wof:name":"True Value Hardware",
    "wof:placetype":"venue"
},
  "geometry": {"coordinates":[-97.95474299999999,34.782711],"type":"Point"}
}