{
  "type": "Feature",
  "properties": {
    "iso:country":"US",
    "sg:address":"4111 E 51st St S",
    "sg:city":"Tulsa",
    "sg:classifiers":[
        {
            "category":"Real Estate",
            "subcategory":"Real Estate Operator",
            "type":"Services"
        }
    ],
    "sg:phone":"+1 918 749 0345",
    "sg:postcode":"74135",
    "sg:province":"OK",
    "sg:tags":[
        "building",
        "apartment"
    ],
    "wof:name":"Brownstone Apts",
    "wof:placetype":"venue"
},
  "geometry": {"coordinates":[-95.928994,36.089911],"type":"Point"}
}