{
  "type": "Feature",
  "properties": {
    "iso:country":"US",
    "sg:address":"139 Victory St",
    "sg:city":"Ponca City",
    "sg:classifiers":[
        {
            "category":"Organizations",
            "subcategory":"Religious Organization",
            "type":"Services"
        }
    ],
    "sg:phone":"+1 580 762 7093",
    "sg:postcode":"74604",
    "sg:province":"OK",
    "wof:name":"Glad Tidings Assembly of God",
    "wof:placetype":"venue"
},
  "geometry": {"coordinates":[-97.036595,36.681759],"type":"Point"}
}