{
  "type": "Feature",
  "properties": {
    "addr:full":"6808 S Memorial Dr Tulsa OK 74133",
    "addr:housenumber":"6808",
    "addr:postcode":"74133",
    "addr:street":"S Memorial Dr",
    "iso:country":"US",
    "sg:address":"6808 S Memorial Dr",
    "sg:city":"Tulsa",
    "sg:classifiers":[
        {
            "category":"Shopping",
            "subcategory":"Clothing, Apparel, & Fashions",
            "type":"Retail Goods"
        }
    ],
    "sg:phone":"+1 918 252 9120",
    "sg:postcode":"74133",
    "sg:province":"OK",
    "sg:tags":[
        "wear"
    ],
    "wof:name":"Cambridge LTD",
    "wof:placetype":"venue"
},
  "geometry": {"coordinates":[-95.886394,36.06349],"type":"Point"}
}