{
  "type": "Feature",
  "properties": {
    "addr:full":"9900 N Georgia Ave Oklahoma City OK 73120",
    "addr:housenumber":"9900",
    "addr:postcode":"73120",
    "addr:street":"N Georgia Ave",
    "iso:country":"US",
    "sg:address":"9900 N Georgia Ave",
    "sg:city":"Oklahoma City",
    "sg:classifiers":[
        {
            "category":"Building & Trades",
            "subcategory":"Cleaning & Sanitation",
            "type":"Services"
        }
    ],
    "sg:phone":"+1 405 936 0001",
    "sg:postcode":"73120",
    "sg:province":"OK",
    "sg:tags":[
        "janitor"
    ],
    "wof:name":"James Janitoral",
    "wof:placetype":"venue"
},
  "geometry": {"coordinates":[-97.54287100000001,35.57089],"type":"Point"}
}