{
  "type": "Feature",
  "properties": {
    "iso:country":"US",
    "sg:address":"32 A St SE",
    "sg:city":"Miami",
    "sg:classifiers":[
        {
            "category":"Health Services",
            "subcategory":"Doctor",
            "type":"Services"
        }
    ],
    "sg:phone":"+1 918 540 2592",
    "sg:postcode":"74354",
    "sg:province":"OK",
    "sg:tags":[
        "physician",
        "surgeon",
        "osteopathic"
    ],
    "wof:name":"Lewis J Bamberl Jr DO",
    "wof:placetype":"venue"
},
  "geometry": {"coordinates":[-94.876456,36.874278],"type":"Point"}
}