{
  "type": "Feature",
  "properties": {
    "iso:country":"US",
    "sg:address":"6410 N Santa Fe Ave",
    "sg:city":"Oklahoma City",
    "sg:classifiers":[
        {
            "category":"Mining & Drilling",
            "type":"Manufacturing & Wholesale Goods"
        }
    ],
    "sg:phone":"+1 405 840 9196",
    "sg:postcode":"73116",
    "sg:province":"OK",
    "sg:tags":[
        "development",
        "gas",
        "oil",
        "exploration"
    ],
    "wof:name":"EXOK Inc",
    "wof:placetype":"venue"
},
  "geometry": {"coordinates":[-97.511952,35.537676],"type":"Point"}
}