{
  "type": "Feature",
  "properties": {
    "iso:country":"US",
    "sg:address":"301 N 6th St",
    "sg:city":"Muskogee",
    "sg:classifiers":[
        {
            "category":"Social Services",
            "subcategory":"Child Care",
            "type":"Services"
        }
    ],
    "sg:phone":"+1 918 683 6532",
    "sg:postcode":"74401",
    "sg:province":"OK",
    "wof:name":"Youth Central Childcare",
    "wof:placetype":"venue"
},
  "geometry": {"coordinates":[-95.375,35.752431],"type":"Point"}
}