{
  "type": "Feature",
  "properties": {
    "iso:country":"US",
    "sg:address":"821 S Walnut St",
    "sg:city":"Stillwater",
    "sg:classifiers":[
        {
            "category":"Health Services",
            "subcategory":"Doctor",
            "type":"Services"
        }
    ],
    "sg:phone":"+1 405 372 4646",
    "sg:postcode":"74074",
    "sg:province":"OK",
    "sg:tags":[
        "physician",
        "surgeon"
    ],
    "wof:name":"Catherine E Nieman MD",
    "wof:placetype":"venue"
},
  "geometry": {"coordinates":[-97.07824100000001,36.11317],"type":"Point"}
}