{
  "type": "Feature",
  "properties": {
    "iso:country":"US",
    "sg:address":"1420 Miramar Blvd",
    "sg:city":"Oklahoma City",
    "sg:classifiers":[
        {
            "category":"Organizations",
            "subcategory":"Religious Organization",
            "type":"Services"
        }
    ],
    "sg:phone":"+1 405 424 4659",
    "sg:postcode":"73117",
    "sg:province":"OK",
    "sg:tags":[
        "church"
    ],
    "wof:name":"Trinity Church Of God-Christ",
    "wof:placetype":"venue"
},
  "geometry": {"coordinates":[-97.470331,35.483302],"type":"Point"}
}