{
  "type": "Feature",
  "properties": {
    "iso:country":"US",
    "sg:address":"1524 SE 15th St",
    "sg:city":"Oklahoma City",
    "sg:classifiers":[
        {
            "category":"Restaurant",
            "type":"Food & Drink"
        }
    ],
    "sg:phone":"+1 405 677 7218",
    "sg:postcode":"73129",
    "sg:province":"OK",
    "wof:name":"El Sombrero Mexican Restaurant",
    "wof:placetype":"venue"
},
  "geometry": {"coordinates":[-97.483949,35.449765],"type":"Point"}
}