{
  "type": "Feature",
  "properties": {
    "addr:full":"1651 S 273rd East Ave Catoosa OK 74015",
    "addr:housenumber":"1651",
    "addr:postcode":"74015",
    "addr:street":"S 273Rd East Ave",
    "iso:country":"US",
    "sg:address":"1651 S 273rd East Ave",
    "sg:city":"Catoosa",
    "sg:classifiers":[
        {
            "category":"Retail",
            "subcategory":"Repair Shop",
            "type":"Services"
        }
    ],
    "sg:phone":"+1 918 622 1928",
    "sg:postcode":"74015",
    "sg:province":"OK",
    "sg:tags":[
        "air",
        "refrigeration",
        "conditioning",
        "contractor"
    ],
    "wof:name":"Mc Combs Refrigeration",
    "wof:placetype":"venue"
},
  "geometry": {"coordinates":[-95.672484,36.140485],"type":"Point"}
}