{
  "type": "Feature",
  "properties": {
    "iso:country":"US",
    "sg:address":"2323 N Garfield St",
    "sg:city":"Stillwater",
    "sg:classifiers":[
        {
            "category":"Sports & Exercise",
            "subcategory":"Race Track",
            "type":"Entertainment"
        }
    ],
    "sg:phone":"+1 405 372 7346",
    "sg:postcode":"74075",
    "sg:province":"OK",
    "sg:tags":[
        "operation",
        "racing",
        "or"
    ],
    "wof:name":"Elsi Products",
    "wof:placetype":"venue"
},
  "geometry": {"coordinates":[-97.074792,36.147512],"type":"Point"}
}