{
  "type": "Feature",
  "properties": {
    "addr:full":"202 E 2nd St Owasso OK 74055",
    "addr:housenumber":"202",
    "addr:postcode":"74055",
    "addr:street":"E 2Nd St",
    "iso:country":"US",
    "sg:address":"202 E 2nd St",
    "sg:city":"Owasso",
    "sg:classifiers":[
        {
            "category":"Real Estate",
            "subcategory":"Real Estate Services",
            "type":"Services"
        }
    ],
    "sg:phone":"+1 918 274 8933",
    "sg:postcode":"74055",
    "sg:province":"OK",
    "sg:tags":[
        "abstract",
        "title"
    ],
    "wof:name":"First Amercn Title Abstract Co",
    "wof:placetype":"venue"
},
  "geometry": {"coordinates":[-95.852647,36.268063],"type":"Point"}
}