{
  "type": "Feature",
  "properties": {
    "iso:country":"US",
    "sg:address":"623 W 6th Ave",
    "sg:city":"Stillwater",
    "sg:classifiers":[
        {
            "category":"Real Estate",
            "subcategory":"Real Estate Agent",
            "type":"Services"
        }
    ],
    "sg:phone":"+1 405 385 0405",
    "sg:postcode":"74074",
    "sg:province":"OK",
    "sg:website":"www.unitedcountry.com/stillwaterok",
    "wof:name":"United Country Real Estate",
    "wof:placetype":"venue"
},
  "geometry": {"coordinates":[-97.065811,36.115568],"type":"Point"}
}