{
  "type": "Feature",
  "properties": {
    "iso:country":"US",
    "sg:address":"3601 NW 63rd St",
    "sg:city":"Oklahoma City",
    "sg:classifiers":[
        {
            "category":"Utilities",
            "subcategory":"Mobile Phone",
            "type":"Services"
        }
    ],
    "sg:phone":"+1 405 841 2167",
    "sg:postcode":"73116",
    "sg:province":"OK",
    "sg:tags":[
        "telephone",
        "cellular"
    ],
    "wof:name":"Alltel Information Svc",
    "wof:placetype":"venue"
},
  "geometry": {"coordinates":[-97.580597,35.536843],"type":"Point"}
}