{
  "type": "Feature",
  "properties": {
    "addr:full":"10088 S 49th West Ave Sapulpa OK 74066",
    "addr:housenumber":"10088",
    "addr:postcode":"74066",
    "addr:street":"S 49Th West Ave",
    "iso:country":"US",
    "sg:address":"10088 S 49th West Ave",
    "sg:city":"Sapulpa",
    "sg:classifiers":[
        {
            "category":"Home & Garden",
            "subcategory":"Building Materials",
            "type":"Retail Goods"
        }
    ],
    "sg:phone":"+1 918 227 0322",
    "sg:postcode":"74066",
    "sg:province":"OK",
    "sg:tags":[
        "type",
        "door"
    ],
    "wof:name":"Oklahoma Wholesale Overhead",
    "wof:placetype":"venue"
},
  "geometry": {"coordinates":[-96.04749200000001,36.016029],"type":"Point"}
}