{
  "type": "Feature",
  "properties": {
    "iso:country":"US",
    "sg:address":"4927 E 91st St",
    "sg:city":"Tulsa",
    "sg:classifiers":[
        {
            "category":"Restaurant",
            "type":"Food & Drink"
        }
    ],
    "sg:menulink":"http://www.allmenus.com/ok/tulsa/199430-sonic/menu/",
    "sg:phone":"+1 918 491 7300",
    "sg:postcode":"74137",
    "sg:province":"OK",
    "sg:tags":[
        "burger",
        "american"
    ],
    "wof:name":"Sonic",
    "wof:placetype":"venue"
},
  "geometry": {"coordinates":[-95.920911,36.032327],"type":"Point"}
}