{
  "type": "Feature",
  "properties": {
    "iso:country":"US",
    "sg:address":"16 NW 63rd St",
    "sg:city":"Oklahoma City",
    "sg:classifiers":[
        {
            "category":"Professional",
            "subcategory":"Accounting & Tax Preparation",
            "type":"Services"
        }
    ],
    "sg:phone":"+1 405 419 5541",
    "sg:postcode":"73116",
    "sg:province":"OK",
    "sg:tags":[
        "management",
        "billing",
        "collection"
    ],
    "wof:name":"Oklahoma Management Servic",
    "wof:placetype":"venue"
},
  "geometry": {"coordinates":[-97.513133,35.536739],"type":"Point"}
}