{
  "type": "Feature",
  "properties": {
    "iso:country":"US",
    "sg:address":"7302 E 11th St",
    "sg:city":"Tulsa",
    "sg:classifiers":[
        {
            "category":"Manufacturing",
            "subcategory":"Printing",
            "type":"Manufacturing & Wholesale Goods"
        }
    ],
    "sg:phone":"+1 918 835 6400",
    "sg:postcode":"74112",
    "sg:province":"OK",
    "sg:tags":[
        "commercial"
    ],
    "wof:name":"Fine Arts Engraving Co Inc",
    "wof:placetype":"venue"
},
  "geometry": {"coordinates":[-95.894574,36.147954],"type":"Point"}
}