{
  "type": "Feature",
  "properties": {
    "iso:country":"US",
    "sg:address":"210 S Main St",
    "sg:city":"Bixby",
    "sg:classifiers":[
        {
            "category":"Social Services",
            "subcategory":"Child Care",
            "type":"Services"
        }
    ],
    "sg:phone":"+1 918 366 2770",
    "sg:postcode":"74008",
    "sg:province":"OK",
    "wof:name":"Storybook Inn",
    "wof:placetype":"venue"
},
  "geometry": {"coordinates":[-95.88090200000001,35.938181],"type":"Point"}
}