{
  "type": "Feature",
  "properties": {
    "addr:full":"225 N Aspen Ave Broken Arrow OK 74012",
    "addr:housenumber":"225 n",
    "addr:postcode":"74012",
    "addr:street":"Aspen Ave",
    "iso:country":"US",
    "sg:address":"225 N Aspen Ave",
    "sg:city":"Broken Arrow",
    "sg:classifiers":[
        {
            "category":"Manufacturing",
            "subcategory":"Glass & Minerals",
            "type":"Manufacturing & Wholesale Goods"
        }
    ],
    "sg:phone":"+1 918 258 7533",
    "sg:postcode":"74012",
    "sg:province":"OK",
    "sg:tags":[
        "brick",
        "common"
    ],
    "wof:name":"Boral Bricks Inc",
    "wof:placetype":"venue"
},
  "geometry": {"coordinates":[-95.81525600000001,36.053556],"type":"Point"}
}