{
  "type": "Feature",
  "properties": {
    "iso:country":"US",
    "sg:address":"9720 SE 43rd St",
    "sg:city":"Oklahoma City",
    "sg:classifiers":[
        {
            "category":"Wholesale",
            "subcategory":"Office Equipment",
            "type":"Manufacturing & Wholesale Goods"
        }
    ],
    "sg:phone":"+1 405 741 7233",
    "sg:postcode":"73150",
    "sg:province":"OK",
    "wof:name":"All Keyed Up Lock & Safe",
    "wof:placetype":"venue"
},
  "geometry": {"coordinates":[-97.353421,35.421764],"type":"Point"}
}