{
  "type": "Feature",
  "properties": {
    "addr:full":"33031 Quail Ridge Rd Blanchard OK 73010",
    "addr:housenumber":"33031",
    "addr:postcode":"73010",
    "addr:street":"Quail Ridge Rd",
    "iso:country":"US",
    "sg:address":"33031 Quail Ridge Rd",
    "sg:city":"Blanchard",
    "sg:classifiers":[
        {
            "category":"Building & Trades",
            "subcategory":"Construction",
            "type":"Services"
        }
    ],
    "sg:phone":"+1 405 387 5263",
    "sg:postcode":"73010",
    "sg:province":"OK",
    "sg:tags":[
        "carpentry",
        "contractor"
    ],
    "wof:name":"Wood Carpentry Inc",
    "wof:placetype":"venue"
},
  "geometry": {"coordinates":[-97.663089,35.189634],"type":"Point"}
}