{
  "type": "Feature",
  "properties": {
    "iso:country":"US",
    "sg:address":"120 N Main St",
    "sg:city":"Mulhall",
    "sg:classifiers":[
        {
            "category":"Banks & Credit Unions",
            "subcategory":"Bank",
            "type":"Services"
        }
    ],
    "sg:phone":"+1 405 649 2282",
    "sg:postcode":"73063",
    "sg:province":"OK",
    "sg:website":"www.osbbank.com",
    "wof:name":"Oklahoma State Bank",
    "wof:placetype":"venue"
},
  "geometry": {"coordinates":[-97.407132,36.065719],"type":"Point"}
}