{
  "type": "Feature",
  "properties": {
    "iso:country":"US",
    "sg:address":"308 Heritage Ct",
    "sg:city":"Edmond",
    "sg:classifiers":[
        {
            "category":"Banks & Credit Unions",
            "subcategory":"Investment Brokerage",
            "type":"Services"
        },
        {
            "category":"Professional",
            "subcategory":"Management & Consulting",
            "type":"Services"
        }
    ],
    "sg:phone":"+1 405 359 2290",
    "sg:postcode":"73025",
    "sg:province":"OK",
    "sg:tags":[
        "advisory",
        "financial",
        "business"
    ],
    "wof:name":"Barry Rudy & Assoc LLC",
    "wof:placetype":"venue"
},
  "geometry": {"coordinates":[-97.484388,35.719943],"type":"Point"}
}