{
  "type": "Feature",
  "properties": {
    "iso:country":"US",
    "sg:address":"1828 W Rose Oak Dr",
    "sg:city":"Mustang",
    "sg:classifiers":[
        {
            "category":"Retail",
            "subcategory":"Repair Shop",
            "type":"Services"
        }
    ],
    "sg:phone":"+1 405 376 5612",
    "sg:postcode":"73064",
    "sg:province":"OK",
    "sg:tags":[
        "electrical"
    ],
    "wof:name":"Dougs Appliance Repair",
    "wof:placetype":"venue"
},
  "geometry": {"coordinates":[-97.765788,35.381611],"type":"Point"}
}