{
  "type": "Feature",
  "properties": {
    "iso:country":"US",
    "sg:address":"5510 SW 5th St",
    "sg:city":"Oklahoma City",
    "sg:classifiers":[
        {
            "category":"Shopping",
            "type":"Retail Goods"
        }
    ],
    "sg:phone":"+1 405 917 5390",
    "sg:postcode":"73128",
    "sg:province":"OK",
    "sg:tags":[
        "telephone",
        "cellular"
    ],
    "wof:name":"Wireless Retail Inc",
    "wof:placetype":"venue"
},
  "geometry": {"coordinates":[-97.613885,35.458784],"type":"Point"}
}