{
  "type": "Feature",
  "properties": {
    "addr:full":"907 Garden Grove Yukon OK 73099",
    "addr:housenumber":"907",
    "addr:postcode":"73099",
    "iso:country":"US",
    "sg:address":"907 Garden Grove",
    "sg:city":"Yukon",
    "sg:classifiers":[
        {
            "category":"Professional",
            "subcategory":"Computer Services",
            "type":"Services"
        }
    ],
    "sg:phone":"+1 405 350 5073",
    "sg:postcode":"73099",
    "sg:province":"OK",
    "sg:tags":[
        "programing",
        "custom"
    ],
    "wof:name":"Webwarfarecom",
    "wof:placetype":"venue"
},
  "geometry": {"coordinates":[-97.73138,35.498324],"type":"Point"}
}