{
  "type": "Feature",
  "properties": {
    "addr:full":"4913 Polo Ln Mustang OK 73064",
    "addr:housenumber":"4913",
    "addr:postcode":"73064",
    "addr:street":"Polo Ln",
    "iso:country":"US",
    "sg:address":"4913 Polo Ln",
    "sg:city":"Mustang",
    "sg:classifiers":[
        {
            "category":"Organizations",
            "subcategory":"Religious Organization",
            "type":"Services"
        }
    ],
    "sg:phone":"+1 405 324 7730",
    "sg:postcode":"73064",
    "sg:province":"OK",
    "wof:name":"Temple Ventures LLC",
    "wof:placetype":"venue"
},
  "geometry": {"coordinates":[-97.762889,35.418419],"type":"Point"}
}