{
  "type": "Feature",
  "properties": {
    "addr:full":"6105 NW Maple Ave Lawton OK 73505",
    "addr:housenumber":"6105",
    "addr:postcode":"73505",
    "addr:street":"Nw Maple Ave",
    "iso:country":"US",
    "sg:address":"6105 NW Maple Ave",
    "sg:city":"Lawton",
    "sg:classifiers":[
        {
            "category":"Building & Trades",
            "subcategory":"Construction",
            "type":"Services"
        }
    ],
    "sg:phone":"+1 580 536 2059",
    "sg:postcode":"73505",
    "sg:province":"OK",
    "sg:tags":[
        "hanging",
        "contractor"
    ],
    "wof:name":"Stringer Painting",
    "wof:placetype":"venue"
},
  "geometry": {"coordinates":[-98.467634,34.621523],"type":"Point"}
}