{
  "type": "Feature",
  "properties": {
    "iso:country":"US",
    "sg:address":"110 E Lakeview Rd",
    "sg:city":"Stillwater",
    "sg:classifiers":[
        {
            "category":"Personal",
            "subcategory":"Beauty Salon",
            "type":"Services"
        }
    ],
    "sg:phone":"+1 405 372 3952",
    "sg:postcode":"74075",
    "sg:province":"OK",
    "sg:tags":[
        "shop",
        "manicuring"
    ],
    "wof:name":"Jeanette's Nails",
    "wof:placetype":"venue"
},
  "geometry": {"coordinates":[-97.059698,36.145143],"type":"Point"}
}