{
  "type": "Feature",
  "properties": {
    "iso:country":"US",
    "sg:address":"4132 Will Rogers Pkwy",
    "sg:city":"Oklahoma City",
    "sg:classifiers":[
        {
            "category":"Wholesale",
            "subcategory":"Machinery & Supplies",
            "type":"Manufacturing & Wholesale Goods"
        }
    ],
    "sg:phone":"+1 405 949 1393",
    "sg:postcode":"73108",
    "sg:province":"OK",
    "sg:tags":[
        "equipment",
        "industrial"
    ],
    "wof:name":"Palmer Johnson Distributors",
    "wof:placetype":"venue"
},
  "geometry": {"coordinates":[-97.591143,35.452032],"type":"Point"}
}