{
  "type": "Feature",
  "properties": {
    "addr:full":"1119 S 9th Ave Durant OK 74701",
    "addr:housenumber":"1119",
    "addr:postcode":"74701",
    "addr:street":"S 9Th Ave",
    "iso:country":"US",
    "sg:address":"1119 S 9th Ave",
    "sg:city":"Durant",
    "sg:classifiers":[
        {
            "category":"Autos & Motor Vehicles",
            "subcategory":"Automobile Sales",
            "type":"Retail Goods"
        }
    ],
    "sg:phone":"+1 580 920 0915",
    "sg:postcode":"74701",
    "sg:province":"OK",
    "sg:tags":[
        "car",
        "dealer"
    ],
    "wof:name":"Red's Used Cars",
    "wof:placetype":"venue"
},
  "geometry": {"coordinates":[-96.388901,33.981106],"type":"Point"}
}