{
  "type": "Feature",
  "properties": {
    "iso:country":"US",
    "sg:address":"14200 Mansell Dr",
    "sg:city":"Luther",
    "sg:classifiers":[
        {
            "category":"Building & Trades",
            "subcategory":"Construction",
            "type":"Services"
        }
    ],
    "sg:phone":"+1 405 277 2111",
    "sg:postcode":"73054",
    "sg:province":"OK",
    "sg:tags":[
        "painter"
    ],
    "wof:name":"Mansell Custom Painting Inc",
    "wof:placetype":"venue"
},
  "geometry": {"coordinates":[-97.179391,35.728282],"type":"Point"}
}