{
  "type": "Feature",
  "properties": {
    "iso:country":"US",
    "sg:address":"1613 E 15th St",
    "sg:city":"Tulsa",
    "sg:classifiers":[
        {
            "category":"Manufacturing",
            "subcategory":"Wood Products",
            "type":"Manufacturing & Wholesale Goods"
        }
    ],
    "sg:phone":"+1 918 583 7441",
    "sg:postcode":"74120",
    "sg:province":"OK",
    "sg:tags":[
        "pallet",
        "skid"
    ],
    "wof:name":"Pal Web Corp",
    "wof:placetype":"venue"
},
  "geometry": {"coordinates":[-95.968333,36.140609],"type":"Point"}
}