{
  "type": "Feature",
  "properties": {
    "iso:country":"US",
    "sg:address":"1409 N 7th St",
    "sg:city":"Ponca City",
    "sg:classifiers":[
        {
            "category":"Home & Garden",
            "subcategory":"Garden Supply",
            "type":"Retail Goods"
        }
    ],
    "sg:phone":"+1 580 762 3302",
    "sg:postcode":"74601",
    "sg:province":"OK",
    "wof:name":"Mt Automatics",
    "wof:placetype":"venue"
},
  "geometry": {"coordinates":[-97.075689,36.720634],"type":"Point"}
}