{
  "type": "Feature",
  "properties": {
    "iso:country":"US",
    "sg:address":"251 S 183rd East Ave",
    "sg:city":"Tulsa",
    "sg:classifiers":[
        {
            "category":"Education",
            "subcategory":"Special Training",
            "type":"Public Place"
        },
        {
            "category":"Social Services",
            "subcategory":"Child Care",
            "type":"Services"
        },
        {
            "category":"Education",
            "subcategory":"Preschool",
            "type":"Public Place"
        },
        {
            "category":"Education",
            "subcategory":"School",
            "type":"Public Place"
        }
    ],
    "sg:phone":"+1 918 232 1554",
    "sg:postcode":"74108",
    "sg:province":"OK",
    "sg:tags":[
        "educational",
        "private",
        "kindergarten",
        "nursery",
        "k-",
        "day"
    ],
    "sg:website":"http://preschoolpalsllc.com",
    "wof:name":"Preschool Pals",
    "wof:placetype":"venue"
},
  "geometry": {"coordinates":[-95.772211,36.157074],"type":"Point"}
}