{
  "type": "Feature",
  "properties": {
    "addr:full":"506 S Cedar St Sapulpa OK 74066",
    "addr:housenumber":"506",
    "addr:postcode":"74066",
    "addr:street":"S Cedar St",
    "iso:country":"US",
    "sg:address":"506 S Cedar St",
    "sg:city":"Sapulpa",
    "sg:classifiers":[
        {
            "category":"Building & Trades",
            "subcategory":"Construction",
            "type":"Services"
        }
    ],
    "sg:phone":"+1 918 313 0204",
    "sg:postcode":"74066",
    "sg:province":"OK",
    "sg:tags":[
        "build",
        "fence",
        "deck"
    ],
    "wof:name":"Sapulpa Fence & Deck Co",
    "wof:placetype":"venue"
},
  "geometry": {"coordinates":[-96.11777600000001,35.992437],"type":"Point"}
}