{
  "type": "Feature",
  "properties": {
    "addr:full":"12009 Ashford Dr Yukon OK 73099",
    "addr:housenumber":"12009",
    "addr:postcode":"73099",
    "addr:street":"Ashford Dr",
    "iso:country":"US",
    "sg:address":"12009 Ashford Dr",
    "sg:city":"Yukon",
    "sg:classifiers":[
        {
            "category":"Manufacturing",
            "subcategory":"Paper Products",
            "type":"Manufacturing & Wholesale Goods"
        }
    ],
    "sg:phone":"+1 405 373 9023",
    "sg:postcode":"73099",
    "sg:province":"OK",
    "sg:tags":[
        "mill"
    ],
    "wof:name":"G&P Assoc",
    "wof:placetype":"venue"
},
  "geometry": {"coordinates":[-97.72022,35.59157],"type":"Point"}
}