{
  "type": "Feature",
  "properties": {
    "addr:full":"1700 NE 63rd St Oklahoma City OK 73111",
    "addr:housenumber":"1700",
    "addr:postcode":"73111",
    "addr:street":"Ne 63Rd St",
    "iso:country":"US",
    "sg:address":"1700 NE 63rd St",
    "sg:city":"Oklahoma City",
    "sg:classifiers":[
        {
            "category":"Shopping",
            "subcategory":"News",
            "type":"Retail Goods"
        }
    ],
    "sg:phone":"+1 405 478 6404",
    "sg:postcode":"73111",
    "sg:province":"OK",
    "wof:name":"Persimmon Hill Magazine",
    "wof:placetype":"venue"
},
  "geometry": {"coordinates":[-97.47978999999999,35.53665],"type":"Point"}
}