{
  "type": "Feature",
  "properties": {
    "iso:country":"US",
    "sg:address":"1400 S Wood Dr",
    "sg:city":"Okmulgee",
    "sg:classifiers":[
        {
            "category":"Food & Beverages",
            "subcategory":"Groceries & Convenience Stores",
            "type":"Retail Goods"
        }
    ],
    "sg:phone":"+1 918 758 0979",
    "sg:postcode":"74447",
    "sg:province":"OK",
    "wof:name":"Fastop Stores",
    "wof:placetype":"venue"
},
  "geometry": {"coordinates":[-95.961795,35.60998],"type":"Point"}
}