{
  "type": "Feature",
  "properties": {
    "addr:full":"1700 N Milt Phillips Ave Seminole OK 74868",
    "addr:housenumber":"1700",
    "addr:postcode":"74868",
    "addr:street":"N Milt Phillips Ave",
    "iso:country":"US",
    "sg:address":"1700 N Milt Phillips Ave",
    "sg:city":"Seminole",
    "sg:classifiers":[
        {
            "category":"Restaurant",
            "type":"Food & Drink"
        }
    ],
    "sg:menulink":"http://www.allmenus.com/ok/seminole-north/144398-subway/menu/",
    "sg:phone":"+1 405 382 5533",
    "sg:postcode":"74868",
    "sg:province":"OK",
    "sg:tags":[
        "american",
        "sandwich"
    ],
    "wof:name":"Subway",
    "wof:placetype":"venue"
},
  "geometry": {"coordinates":[-96.670976,35.237498],"type":"Point"}
}