{
  "type": "Feature",
  "properties": {
    "iso:country":"US",
    "sg:address":"2701 SE 44th St",
    "sg:city":"Oklahoma City",
    "sg:classifiers":[
        {
            "category":"Organizations",
            "subcategory":"Religious Organization",
            "type":"Services"
        },
        {
            "category":"Organizations",
            "subcategory":"Professional Association",
            "type":"Services"
        }
    ],
    "sg:phone":"+1 405 672 8262",
    "sg:postcode":"73129",
    "sg:province":"OK",
    "sg:tags":[
        "church"
    ],
    "wof:name":"Vietnamese Buddhist Assn Oklhm",
    "wof:placetype":"venue"
},
  "geometry": {"coordinates":[-97.468012,35.420899],"type":"Point"}
}