{
  "type": "Feature",
  "properties": {
    "iso:country":"US",
    "sg:address":"1750 S Elm Pl",
    "sg:city":"Broken Arrow",
    "sg:classifiers":[
        {
            "category":"Shopping",
            "subcategory":"Discount & Variety Stores",
            "type":"Retail Goods"
        }
    ],
    "sg:phone":"+1 918 259 8797",
    "sg:postcode":"74012",
    "sg:province":"OK",
    "sg:website":"www.biglots.com",
    "wof:name":"Big Lots",
    "wof:placetype":"venue"
},
  "geometry": {"coordinates":[-95.79758200000001,36.035904],"type":"Point"}
}