{
  "type": "Feature",
  "properties": {
    "iso:country":"US",
    "sg:address":"601 E Illinois Ave",
    "sg:city":"Vinita",
    "sg:classifiers":[
        {
            "category":"Wholesale",
            "subcategory":"Painting Supplies",
            "type":"Manufacturing & Wholesale Goods"
        },
        {
            "category":"Retail",
            "subcategory":"Repair Shop",
            "type":"Services"
        },
        {
            "category":"Home & Garden",
            "subcategory":"Hardware",
            "type":"Retail Goods"
        },
        {
            "category":"Home & Garden",
            "subcategory":"Building Materials",
            "type":"Retail Goods"
        },
        {
            "category":"Wholesale",
            "subcategory":"Hardware",
            "type":"Manufacturing & Wholesale Goods"
        },
        {
            "category":"Home & Garden",
            "subcategory":"Garden Supply",
            "type":"Retail Goods"
        }
    ],
    "sg:phone":"+1 918 256 4223",
    "sg:postcode":"74301",
    "sg:province":"OK",
    "sg:tags":[
        "renting",
        "lawn",
        "outdoor",
        "power",
        "equipment",
        "equipment-sales",
        "landscaping",
        "saw",
        "paint",
        "store"
    ],
    "sg:website":"http://www.stihldealer.net/default-dealer-042854.aspx",
    "wof:name":"Ace Town & Country",
    "wof:placetype":"venue"
},
  "geometry": {"coordinates":[-95.160858,36.641201],"type":"Point"}
}