{
  "type": "Feature",
  "properties": {
    "iso:country":"US",
    "sg:address":"920 N Main St",
    "sg:city":"Stillwater",
    "sg:classifiers":[
        {
            "category":"Professional",
            "subcategory":"Accounting & Tax Preparation",
            "type":"Services"
        }
    ],
    "sg:phone":"+1 405 372 3909",
    "sg:postcode":"74075",
    "sg:province":"OK",
    "sg:tags":[
        "accountant"
    ],
    "wof:name":"Dugger & Co",
    "wof:placetype":"venue"
},
  "geometry": {"coordinates":[-97.058786,36.131265],"type":"Point"}
}