{
  "type": "Feature",
  "properties": {
    "iso:country":"US",
    "sg:address":"6 NE 63rd St",
    "sg:city":"Oklahoma City",
    "sg:classifiers":[
        {
            "category":"Organizations",
            "subcategory":"Non-profit Organization",
            "type":"Services"
        }
    ],
    "sg:phone":"+1 405 848 7123",
    "sg:postcode":"73105",
    "sg:province":"OK",
    "sg:tags":[
        "social"
    ],
    "wof:name":"Prevent Blindness Oklahoma",
    "wof:placetype":"venue"
},
  "geometry": {"coordinates":[-97.509558,35.536761],"type":"Point"}
}