{
  "type": "Feature",
  "properties": {
    "iso:country":"US",
    "sg:address":"2311 W 7th Ave",
    "sg:city":"Stillwater",
    "sg:classifiers":[
        {
            "category":"Social Services",
            "type":"Services"
        }
    ],
    "sg:phone":"+1 405 377 0136",
    "sg:postcode":"74074",
    "sg:province":"OK",
    "sg:tags":[
        "organization",
        "welfare"
    ],
    "wof:name":"Community Access Inc",
    "wof:placetype":"venue"
},
  "geometry": {"coordinates":[-97.089242,36.114571],"type":"Point"}
}