{
  "type": "Feature",
  "properties": {
    "iso:country":"US",
    "sg:address":"1706 S 4th St",
    "sg:city":"Chickasha",
    "sg:classifiers":[
        {
            "category":"Shopping",
            "type":"Retail Goods"
        },
        {
            "category":"Shopping",
            "subcategory":"Beauty & Cosmetics",
            "type":"Retail Goods"
        }
    ],
    "sg:phone":"+1 405 224 3959",
    "sg:postcode":"73018",
    "sg:province":"OK",
    "sg:tags":[
        "merchandise",
        "perfume"
    ],
    "wof:name":"Merle Norman Cosmetics",
    "wof:placetype":"venue"
},
  "geometry": {"coordinates":[-97.935007,35.033127],"type":"Point"}
}