{
  "type": "Feature",
  "properties": {
    "iso:country":"US",
    "sg:address":"1701 NW 1st St",
    "sg:city":"Oklahoma City",
    "sg:classifiers":[
        {
            "category":"Wholesale",
            "subcategory":"Construction Materials",
            "type":"Manufacturing & Wholesale Goods"
        }
    ],
    "sg:phone":"+1 405 789 7899",
    "sg:postcode":"73106",
    "sg:province":"OK",
    "sg:tags":[
        "fence"
    ],
    "wof:name":"Cates Custom Fence & Covers",
    "wof:placetype":"venue"
},
  "geometry": {"coordinates":[-97.54552700000001,35.468869],"type":"Point"}
}