{
  "type": "Feature",
  "properties": {
    "iso:country":"US",
    "sg:address":"1115 S Chuckwagon Dr",
    "sg:city":"Mustang",
    "sg:classifiers":[
        {
            "category":"Insurance",
            "subcategory":"Insurance Agent",
            "type":"Services"
        }
    ],
    "sg:phone":"+1 405 376 1040",
    "sg:postcode":"73064",
    "sg:province":"OK",
    "wof:name":"Woodie's Insurance & Finance",
    "wof:placetype":"venue"
},
  "geometry": {"coordinates":[-97.744868,35.381814],"type":"Point"}
}