{
  "type": "Feature",
  "properties": {
    "iso:country":"US",
    "sg:address":"3224 California Ave",
    "sg:city":"Chickasha",
    "sg:classifiers":[
        {
            "category":"Real Estate",
            "subcategory":"Real Estate Agent",
            "type":"Services"
        }
    ],
    "sg:phone":"+1 405 224 7001",
    "sg:postcode":"73018",
    "sg:province":"OK",
    "wof:name":"Wade Appraisals Service",
    "wof:placetype":"venue"
},
  "geometry": {"coordinates":[-97.973373,35.028156],"type":"Point"}
}