{
  "type": "Feature",
  "properties": {
    "iso:country":"US",
    "sg:address":"300 W Lillie Blvd",
    "sg:city":"Madill",
    "sg:classifiers":[
        {
            "category":"Banks & Credit Unions",
            "subcategory":"Bank",
            "type":"Services"
        }
    ],
    "sg:phone":"+1 580 795 3351",
    "sg:postcode":"73446",
    "sg:province":"OK",
    "wof:name":"First United Bank",
    "wof:placetype":"venue"
},
  "geometry": {"coordinates":[-96.77420600000001,34.09081],"type":"Point"}
}