{
  "type": "Feature",
  "properties": {
    "addr:full":"705 S 9th Ave Durant OK 74701",
    "addr:housenumber":"705",
    "addr:postcode":"74701",
    "addr:street":"S 9Th Ave",
    "iso:country":"US",
    "sg:address":"705 S 9th Ave",
    "sg:city":"Durant",
    "sg:classifiers":[
        {
            "category":"Shopping",
            "subcategory":"Used Merchandise",
            "type":"Retail Goods"
        }
    ],
    "sg:phone":"+1 580 924 7733",
    "sg:postcode":"74701",
    "sg:province":"OK",
    "sg:tags":[
        "furniture"
    ],
    "wof:name":"Ninth Street Furniture & Appl",
    "wof:placetype":"venue"
},
  "geometry": {"coordinates":[-96.38756600000001,33.986009],"type":"Point"}
}