{
  "type": "Feature",
  "properties": {
    "iso:country":"US",
    "sg:address":"619 E Main St",
    "sg:city":"Jenks",
    "sg:classifiers":[
        {
            "category":"Health Services",
            "subcategory":"Health Practitioner",
            "type":"Services"
        }
    ],
    "sg:phone":"+1 918 299 4357",
    "sg:postcode":"74037",
    "sg:province":"OK",
    "wof:name":"Center For Cnceling Developing",
    "wof:placetype":"venue"
},
  "geometry": {"coordinates":[-95.96041,36.023564],"type":"Point"}
}