{
  "type": "Feature",
  "properties": {
    "addr:full":"10 N Elwood Ave Tulsa OK 74103",
    "addr:housenumber":"10",
    "addr:postcode":"74103",
    "addr:street":"N Elwood Ave",
    "iso:country":"US",
    "sg:address":"10 N Elwood Ave",
    "sg:city":"Tulsa",
    "sg:classifiers":[
        {
            "category":"Retail",
            "subcategory":"Auto Repair",
            "type":"Services"
        }
    ],
    "sg:phone":"+1 918 585 5571",
    "sg:postcode":"74103",
    "sg:province":"OK",
    "sg:tags":[
        "wrecker",
        "truck"
    ],
    "wof:name":"Storey Wrecker Sales",
    "wof:placetype":"venue"
},
  "geometry": {"coordinates":[-95.997911,36.155565],"type":"Point"}
}