{
  "type": "Feature",
  "properties": {
    "iso:country":"US",
    "sg:address":"777 84th Ave NE",
    "sg:city":"Norman",
    "sg:classifiers":[
        {
            "category":"Organizations",
            "subcategory":"Religious Organization",
            "type":"Services"
        }
    ],
    "sg:phone":"+1 405 364 1510",
    "sg:postcode":"73026",
    "sg:province":"OK",
    "sg:tags":[
        "church"
    ],
    "wof:name":"Victory Church",
    "wof:placetype":"venue"
},
  "geometry": {"coordinates":[-97.317625,35.237665],"type":"Point"}
}