{
  "type": "Feature",
  "properties": {
    "iso:country":"US",
    "sg:address":"4633 N Peoria Ave",
    "sg:city":"Tulsa",
    "sg:classifiers":[
        {
            "category":"Personal",
            "subcategory":"Beauty Salon",
            "type":"Services"
        }
    ],
    "sg:phone":"+1 918 425 0061",
    "sg:postcode":"74126",
    "sg:province":"OK",
    "wof:name":"Beauty Town",
    "wof:placetype":"venue"
},
  "geometry": {"coordinates":[-95.97545599999999,36.221363],"type":"Point"}
}