{
  "type": "Feature",
  "properties": {
    "addr:full":"12349 S 645 Rd Miami OK 74354",
    "addr:housenumber":"12349",
    "addr:postcode":"74354",
    "addr:street":"S 645 Rd",
    "iso:country":"US",
    "sg:address":"12349 S 645 Rd",
    "sg:city":"Miami",
    "sg:classifiers":[
        {
            "category":"Shopping",
            "subcategory":"Bicycles & Sporting Goods",
            "type":"Retail Goods"
        }
    ],
    "sg:phone":"+1 918 678 2641",
    "sg:postcode":"74354",
    "sg:province":"OK",
    "wof:name":"Speers Gun Shop",
    "wof:placetype":"venue"
},
  "geometry": {"coordinates":[-94.723341,36.830962],"type":"Point"}
}