{
  "type": "Feature",
  "properties": {
    "iso:country":"US",
    "sg:address":"4001 NW 10th St",
    "sg:city":"Oklahoma City",
    "sg:classifiers":[
        {
            "category":"Wholesale",
            "subcategory":"Groceries",
            "type":"Manufacturing & Wholesale Goods"
        }
    ],
    "sg:phone":"+1 405 949 2556",
    "sg:postcode":"73107",
    "sg:province":"OK",
    "sg:tags":[
        "baker"
    ],
    "wof:name":"Quality Snacks",
    "wof:placetype":"venue"
},
  "geometry": {"coordinates":[-97.590541,35.478752],"type":"Point"}
}