{
  "type": "Feature",
  "properties": {
    "addr:full":"2200 E 2nd St Edmond OK 73034",
    "addr:housenumber":"2200",
    "addr:postcode":"73034",
    "addr:street":"E 2Nd St",
    "iso:country":"US",
    "sg:address":"2200 E 2nd St",
    "sg:city":"Edmond",
    "sg:classifiers":[
        {
            "category":"Farming",
            "subcategory":"Nursery",
            "type":"Manufacturing & Wholesale Goods"
        }
    ],
    "sg:phone":"+1 405 348 2201",
    "sg:postcode":"73034",
    "sg:province":"OK",
    "sg:tags":[
        "ornamental"
    ],
    "wof:name":"Davisons Grnhse & Fruitstand",
    "wof:placetype":"venue"
},
  "geometry": {"coordinates":[-97.450789,35.652719],"type":"Point"}
}