{
  "type": "Feature",
  "properties": {
    "addr:full":"226 Quadrum Dr Oklahoma City OK 73108",
    "addr:housenumber":"226",
    "addr:postcode":"73108",
    "addr:street":"Quadrum Dr",
    "iso:country":"US",
    "sg:address":"226 Quadrum Dr",
    "sg:city":"Oklahoma City",
    "sg:classifiers":[
        {
            "category":"Building & Trades",
            "subcategory":"Construction",
            "type":"Services"
        }
    ],
    "sg:phone":"+1 405 948 1800",
    "sg:postcode":"73108",
    "sg:province":"OK",
    "sg:tags":[
        "resurfacing",
        "laying",
        "refinishing",
        "floor"
    ],
    "wof:name":"Lumber Liquidators",
    "wof:placetype":"venue"
},
  "geometry": {"coordinates":[-97.58123999999999,35.461926],"type":"Point"}
}