{
  "type": "Feature",
  "properties": {
    "addr:full":"2309 SW 100th St Oklahoma City OK 73159",
    "addr:housenumber":"2309",
    "addr:postcode":"73159",
    "addr:street":"Sw 100Th St",
    "iso:country":"US",
    "sg:address":"2309 SW 100th St",
    "sg:city":"Oklahoma City",
    "sg:classifiers":[
        {
            "category":"Building & Trades",
            "subcategory":"Pest Control",
            "type":"Services"
        }
    ],
    "sg:phone":"+1 405 691 3878",
    "sg:postcode":"73159",
    "sg:province":"OK",
    "wof:name":"National Pest Control Pest",
    "wof:placetype":"venue"
},
  "geometry": {"coordinates":[-97.552306,35.367483],"type":"Point"}
}