{
  "type": "Feature",
  "properties": {
    "iso:country":"US",
    "sg:address":"101 S Main St",
    "sg:city":"Elk City",
    "sg:classifiers":[
        {
            "category":"Shopping",
            "subcategory":"Shoes",
            "type":"Retail Goods"
        }
    ],
    "sg:phone":"+1 580 225 8486",
    "sg:postcode":"73644",
    "sg:province":"OK",
    "wof:name":"Carrol Shoe Corner",
    "wof:placetype":"venue"
},
  "geometry": {"coordinates":[-99.404919,35.410669],"type":"Point"}
}