{
  "type": "Feature",
  "properties": {
    "iso:country":"US",
    "sg:address":"1511 N Main St",
    "sg:city":"Altus",
    "sg:classifiers":[
        {
            "category":"Professional",
            "subcategory":"Employment Agencies",
            "type":"Services"
        }
    ],
    "sg:phone":"+1 580 482 2985",
    "sg:postcode":"73521",
    "sg:province":"OK",
    "wof:name":"Manpower",
    "wof:placetype":"venue"
},
  "geometry": {"coordinates":[-99.334012,34.653338],"type":"Point"}
}