{
  "type": "Feature",
  "properties": {
    "iso:country":"US",
    "sg:address":"2821 NW 57th St",
    "sg:city":"Oklahoma City",
    "sg:classifiers":[
        {
            "category":"Personal",
            "subcategory":"Beauty Salon",
            "type":"Services"
        }
    ],
    "sg:phone":"+1 405 767 1161",
    "sg:postcode":"73112",
    "sg:province":"OK",
    "sg:tags":[
        "spa",
        "day"
    ],
    "wof:name":"Body Solutions",
    "wof:placetype":"venue"
},
  "geometry": {"coordinates":[-97.565136,35.52986],"type":"Point"}
}