{
  "type": "Feature",
  "properties": {
    "iso:country":"US",
    "sg:address":"4323 N Classen Blvd",
    "sg:city":"Oklahoma City",
    "sg:classifiers":[
        {
            "category":"Professional",
            "subcategory":"Detective & Security Services",
            "type":"Services"
        }
    ],
    "sg:phone":"+1 405 524 6814",
    "sg:postcode":"73118",
    "sg:province":"OK",
    "sg:tags":[
        "guard",
        "patrol"
    ],
    "wof:name":"Us Security Assoc Inc",
    "wof:placetype":"venue"
},
  "geometry": {"coordinates":[-97.534322,35.514864],"type":"Point"}
}