{
  "type": "Feature",
  "properties": {
    "iso:country":"US",
    "sg:address":"15325 S Memorial Dr",
    "sg:city":"Bixby",
    "sg:classifiers":[
        {
            "category":"Retail",
            "subcategory":"Auto Repair",
            "type":"Services"
        }
    ],
    "sg:phone":"+1 918 366 1213",
    "sg:postcode":"74008",
    "sg:province":"OK",
    "sg:tags":[
        "wrecker"
    ],
    "wof:name":"South Tulsa Towing",
    "wof:placetype":"venue"
},
  "geometry": {"coordinates":[-95.88643,35.938463],"type":"Point"}
}