{
  "type": "Feature",
  "properties": {
    "iso:country":"US",
    "sg:address":"9815 Moccasin Ln",
    "sg:city":"Harrah",
    "sg:classifiers":[
        {
            "category":"Building & Trades",
            "subcategory":"Construction",
            "type":"Services"
        }
    ],
    "sg:phone":"+1 405 454 2275",
    "sg:postcode":"73045",
    "sg:province":"OK",
    "sg:tags":[
        "general",
        "contractor"
    ],
    "wof:name":"Nichols Construction",
    "wof:placetype":"venue"
},
  "geometry": {"coordinates":[-97.184079,35.565946],"type":"Point"}
}