{
  "type": "Feature",
  "properties": {
    "addr:full":"2837 SW 53rd St Oklahoma City OK 73119",
    "addr:housenumber":"2837",
    "addr:postcode":"73119",
    "addr:street":"Sw 53Rd St",
    "iso:country":"US",
    "sg:address":"2837 SW 53rd St",
    "sg:city":"Oklahoma City",
    "sg:classifiers":[
        {
            "category":"Professional",
            "subcategory":"Detective & Security Services",
            "type":"Services"
        }
    ],
    "sg:phone":"+1 405 681 9700",
    "sg:postcode":"73119",
    "sg:province":"OK",
    "sg:tags":[
        "investigator"
    ],
    "wof:name":"Alan R Ball Investigations",
    "wof:placetype":"venue"
},
  "geometry": {"coordinates":[-97.562956,35.41233],"type":"Point"}
}