{
  "type": "Feature",
  "properties": {
    "addr:full":"1401 W Grand Ave Ponca City OK 74601",
    "addr:housenumber":"1401",
    "addr:postcode":"74601",
    "addr:street":"W Grand Ave",
    "iso:country":"US",
    "sg:address":"1401 W Grand Ave",
    "sg:city":"Ponca City",
    "sg:classifiers":[
        {
            "category":"Education",
            "subcategory":"School",
            "type":"Public Place"
        }
    ],
    "sg:phone":"+1 580 767 8020",
    "sg:postcode":"74601",
    "sg:province":"OK",
    "sg:website":"www.poncacity.k12.ok.us",
    "wof:name":"Ponca City Middle School",
    "wof:placetype":"venue"
},
  "geometry": {"coordinates":[-97.099878,36.704069],"type":"Point"}
}