{
  "type": "Feature",
  "properties": {
    "addr:full":"3502 E 51st St Tulsa OK 74135",
    "addr:housenumber":"3502",
    "addr:postcode":"74135",
    "addr:street":"E 51St St",
    "iso:country":"US",
    "sg:address":"3502 E 51st St",
    "sg:city":"Tulsa",
    "sg:classifiers":[
        {
            "category":"Restaurant",
            "type":"Food & Drink"
        }
    ],
    "sg:menulink":"http://www.allmenus.com/ok/tulsa/144475-subway/menu/",
    "sg:phone":"+1 918 749 4782",
    "sg:postcode":"74135",
    "sg:province":"OK",
    "sg:tags":[
        "american",
        "sandwich"
    ],
    "wof:name":"Subway",
    "wof:placetype":"venue"
},
  "geometry": {"coordinates":[-95.935883,36.088619],"type":"Point"}
}