{
  "type": "Feature",
  "properties": {
    "addr:full":"14524 Britton Rd W Calumet OK 73014",
    "addr:housenumber":"14524",
    "addr:postcode":"73014",
    "addr:street":"Britton Rd W",
    "iso:country":"US",
    "sg:address":"14524 Britton Rd W",
    "sg:city":"Calumet",
    "sg:classifiers":[
        {
            "category":"Freight",
            "type":"Transportation"
        }
    ],
    "sg:phone":"+1 405 262 1483",
    "sg:postcode":"73014",
    "sg:province":"OK",
    "sg:tags":[
        "operator",
        "trucking"
    ],
    "wof:name":"Vernon Ellison Trucking",
    "wof:placetype":"venue"
},
  "geometry": {"coordinates":[-98.118514,35.565907],"type":"Point"}
}