{
  "type": "Feature",
  "properties": {
    "iso:country":"US",
    "sg:address":"508 Clear Creek Rd",
    "sg:city":"Newalla",
    "sg:classifiers":[
        {
            "category":"Real Estate",
            "subcategory":"Real Estate Agent",
            "type":"Services"
        }
    ],
    "sg:phone":"+1 405 360 0937",
    "sg:postcode":"74857",
    "sg:province":"OK",
    "sg:website":"www.web-estates.com",
    "wof:name":"Web Estates Realty",
    "wof:placetype":"venue"
},
  "geometry": {"coordinates":[-97.16583900000001,35.28356],"type":"Point"}
}