{
  "type": "Feature",
  "properties": {
    "iso:country":"US",
    "sg:address":"3516 NW 50th St",
    "sg:city":"Oklahoma City",
    "sg:classifiers":[
        {
            "category":"Social Services",
            "type":"Services"
        }
    ],
    "sg:phone":"+1 405 943 7500",
    "sg:postcode":"73112",
    "sg:province":"OK",
    "sg:tags":[
        "counselor",
        "marriage",
        "family"
    ],
    "wof:name":"Family & Adolescence Support",
    "wof:placetype":"venue"
},
  "geometry": {"coordinates":[-97.580834,35.522171],"type":"Point"}
}