{
  "type": "Feature",
  "properties": {
    "iso:country":"US",
    "sg:address":"500 Riverview Dr",
    "sg:city":"Noble",
    "sg:classifiers":[
        {
            "category":"Building & Trades",
            "subcategory":"Construction",
            "type":"Services"
        }
    ],
    "sg:phone":"+1 405 872 3433",
    "sg:postcode":"73068",
    "sg:province":"OK",
    "sg:tags":[
        "hanging",
        "contractor"
    ],
    "wof:name":"Record Painting",
    "wof:placetype":"venue"
},
  "geometry": {"coordinates":[-97.399159,35.145035],"type":"Point"}
}