{
  "type": "Feature",
  "properties": {
    "addr:full":"1609 E 2nd St Edmond OK 73034",
    "addr:housenumber":"1609",
    "addr:postcode":"73034",
    "addr:street":"E 2Nd St",
    "iso:country":"US",
    "sg:address":"1609 E 2nd St",
    "sg:city":"Edmond",
    "sg:classifiers":[
        {
            "category":"Restaurant",
            "type":"Food & Drink"
        }
    ],
    "sg:menulink":"http://www.allmenus.com/ok/oklahoma-city/211106-kfc---kentucky-fried-chicken/menu/",
    "sg:phone":"+1 405 340 2783",
    "sg:postcode":"73034",
    "sg:province":"OK",
    "sg:tags":[
        "american",
        "chicken"
    ],
    "wof:name":"KFC - Kentucky Fried Chicken",
    "wof:placetype":"venue"
},
  "geometry": {"coordinates":[-97.458527,35.653108],"type":"Point"}
}