{
  "type": "Feature",
  "properties": {
    "iso:country":"US",
    "sg:address":"1401 Brixton Ct",
    "sg:city":"Edmond",
    "sg:classifiers":[
        {
            "category":"Professional",
            "subcategory":"Employment Agencies",
            "type":"Services"
        }
    ],
    "sg:phone":"+1 405 359 9992",
    "sg:postcode":"73034",
    "sg:province":"OK",
    "sg:tags":[
        "consultant"
    ],
    "wof:name":"Placement Assessments",
    "wof:placetype":"venue"
},
  "geometry": {"coordinates":[-97.446675,35.63887],"type":"Point"}
}