{
  "type": "Feature",
  "properties": {
    "iso:country":"US",
    "sg:address":"9211 N Council Rd",
    "sg:city":"Oklahoma City",
    "sg:classifiers":[
        {
            "category":"Wholesale",
            "subcategory":"Construction Materials",
            "type":"Manufacturing & Wholesale Goods"
        }
    ],
    "sg:phone":"+1 405 326 5522",
    "sg:postcode":"73132",
    "sg:province":"OK",
    "sg:tags":[
        "fence"
    ],
    "wof:name":"Upland Fence Construction",
    "wof:placetype":"venue"
},
  "geometry": {"coordinates":[-97.65628700000001,35.564326],"type":"Point"}
}