{
  "type": "Feature",
  "properties": {
    "iso:country":"US",
    "sg:address":"530 E Pine Pl",
    "sg:city":"Tulsa",
    "sg:classifiers":[
        {
            "category":"Professional",
            "subcategory":"Business Services",
            "type":"Services"
        }
    ],
    "sg:phone":"+1 918 582 2740",
    "sg:postcode":"74106",
    "sg:province":"OK",
    "wof:name":"Lonnie Listenbee Bail Bonds",
    "wof:placetype":"venue"
},
  "geometry": {"coordinates":[-95.989155,36.177443],"type":"Point"}
}