{
  "type": "Feature",
  "properties": {
    "addr:full":"3712 NE 143rd St Edmond OK 73013",
    "addr:housenumber":"3712",
    "addr:postcode":"73013",
    "addr:street":"Ne 143Rd St",
    "iso:country":"US",
    "sg:address":"3712 NE 143rd St",
    "sg:city":"Edmond",
    "sg:classifiers":[
        {
            "category":"Building & Trades",
            "subcategory":"Cleaning & Sanitation",
            "type":"Services"
        }
    ],
    "sg:phone":"+1 405 475 5519",
    "sg:postcode":"73013",
    "sg:province":"OK",
    "sg:tags":[
        "house"
    ],
    "wof:name":"Anointed House Keeping Svc",
    "wof:placetype":"venue"
},
  "geometry": {"coordinates":[-97.448973,35.616014],"type":"Point"}
}