{
  "type": "Feature",
  "properties": {
    "iso:country":"US",
    "sg:address":"7023 SE 15th St",
    "sg:city":"Oklahoma City",
    "sg:classifiers":[
        {
            "category":"Banks & Credit Unions",
            "subcategory":"Bank",
            "type":"Services"
        }
    ],
    "sg:phone":"+1 405 733 0727",
    "sg:postcode":"73110",
    "sg:province":"OK",
    "sg:tags":[
        "loan"
    ],
    "wof:name":"A-O-K Loans",
    "wof:placetype":"venue"
},
  "geometry": {"coordinates":[-97.402507,35.449727],"type":"Point"}
}