{
  "type": "Feature",
  "properties": {
    "iso:country":"US",
    "sg:address":"333 W Main St",
    "sg:city":"Ardmore",
    "sg:classifiers":[
        {
            "category":"Professional",
            "subcategory":"Accounting & Tax Preparation",
            "type":"Services"
        }
    ],
    "sg:phone":"+1 580 223 8438",
    "sg:postcode":"73401",
    "sg:province":"OK",
    "wof:name":"Thom C McGuire CPA",
    "wof:placetype":"venue"
},
  "geometry": {"coordinates":[-97.132633,34.173698],"type":"Point"}
}