{
  "type": "Feature",
  "properties": {
    "iso:country":"US",
    "sg:address":"415 College Ave",
    "sg:city":"Alva",
    "sg:classifiers":[
        {
            "category":"Shopping",
            "subcategory":"Gifts & Souvenirs",
            "type":"Retail Goods"
        }
    ],
    "sg:phone":"+1 580 327 1595",
    "sg:postcode":"73717",
    "sg:province":"OK",
    "wof:name":"Happiness House",
    "wof:placetype":"venue"
},
  "geometry": {"coordinates":[-98.666864,36.803931],"type":"Point"}
}