{
  "type": "Feature",
  "properties": {
    "iso:country":"US",
    "sg:address":"2330 Bay Hill Pl",
    "sg:city":"Edmond",
    "sg:classifiers":[
        {
            "category":"Shopping",
            "type":"Retail Goods"
        }
    ],
    "sg:phone":"+1 405 844 6214",
    "sg:postcode":"73034",
    "sg:province":"OK",
    "sg:tags":[
        "miscellaneous",
        "store"
    ],
    "wof:name":"Whimsy Doodle",
    "wof:placetype":"venue"
},
  "geometry": {"coordinates":[-97.449517,35.661389],"type":"Point"}
}