{
  "type": "Feature",
  "properties": {
    "iso:country":"US",
    "sg:address":"6702 Yonkipin Dr",
    "sg:city":"Claremore",
    "sg:classifiers":[
        {
            "category":"Building & Trades",
            "subcategory":"Construction",
            "type":"Services"
        }
    ],
    "sg:phone":"+1 918 749 7100",
    "sg:postcode":"74019",
    "sg:province":"OK",
    "sg:tags":[
        "marking",
        "maintenance",
        "parking"
    ],
    "wof:name":"Global Sealcoating",
    "wof:placetype":"venue"
},
  "geometry": {"coordinates":[-95.71868000000001,36.224823],"type":"Point"}
}