{
  "type": "Feature",
  "properties": {
    "iso:country":"US",
    "sg:address":"1143 S Lewis Pl",
    "sg:city":"Tulsa",
    "sg:classifiers":[
        {
            "category":"Retail",
            "subcategory":"Car Wash",
            "type":"Services"
        }
    ],
    "sg:phone":"+1 918 583 4271",
    "sg:postcode":"74104",
    "sg:province":"OK",
    "sg:tags":[
        "carwash"
    ],
    "wof:name":"Tru Color LLC",
    "wof:placetype":"venue"
},
  "geometry": {"coordinates":[-95.95704600000001,36.146741],"type":"Point"}
}