{
  "type": "Feature",
  "properties": {
    "iso:country":"US",
    "sg:address":"1416 Wewoka St",
    "sg:city":"Muskogee",
    "sg:classifiers":[
        {
            "category":"Organizations",
            "subcategory":"Religious Organization",
            "type":"Services"
        }
    ],
    "sg:phone":"+1 918 687 8776",
    "sg:postcode":"74401",
    "sg:province":"OK",
    "sg:tags":[
        "church"
    ],
    "wof:name":"Christ Holy Mission Church",
    "wof:placetype":"venue"
},
  "geometry": {"coordinates":[-95.381535,35.765339],"type":"Point"}
}