{
  "type": "Feature",
  "properties": {
    "addr:full":"1338 E 15th St Tulsa OK 74120",
    "addr:housenumber":"1338",
    "addr:postcode":"74120",
    "addr:street":"E 15Th St",
    "iso:country":"US",
    "sg:address":"1338 E 15th St",
    "sg:city":"Tulsa",
    "sg:classifiers":[
        {
            "category":"Professional",
            "subcategory":"Advertising",
            "type":"Services"
        }
    ],
    "sg:phone":"+1 918 583 1578",
    "sg:postcode":"74120",
    "sg:province":"OK",
    "sg:tags":[
        "distribution"
    ],
    "wof:name":"Sooner Sounds Distributing",
    "wof:placetype":"venue"
},
  "geometry": {"coordinates":[-95.973738,36.140572],"type":"Point"}
}