{
  "type": "Feature",
  "properties": {
    "addr:full":"1800 Canyon Park Cir Edmond OK 73013",
    "addr:housenumber":"1800",
    "addr:postcode":"73013",
    "addr:street":"Canyon Park Cir",
    "iso:country":"US",
    "sg:address":"1800 Canyon Park Cir",
    "sg:city":"Edmond",
    "sg:classifiers":[
        {
            "category":"Professional",
            "subcategory":"Accounting & Tax Preparation",
            "type":"Services"
        }
    ],
    "sg:phone":"+1 405 348 3310",
    "sg:postcode":"73013",
    "sg:province":"OK",
    "wof:name":"Charles C Stumbaugh",
    "wof:placetype":"venue"
},
  "geometry": {"coordinates":[-97.45819400000001,35.63576],"type":"Point"}
}