{
  "type": "Feature",
  "properties": {
    "addr:full":"108 S Moore Ave Claremore OK 74017",
    "addr:housenumber":"108",
    "addr:postcode":"74017",
    "addr:street":"S Moore Ave",
    "iso:country":"US",
    "sg:address":"108 S Moore Ave",
    "sg:city":"Claremore",
    "sg:classifiers":[
        {
            "category":"Building & Trades",
            "subcategory":"Construction",
            "type":"Services"
        }
    ],
    "sg:phone":"+1 918 341 0050",
    "sg:postcode":"74017",
    "sg:province":"OK",
    "sg:tags":[
        "excavating",
        "contractor"
    ],
    "wof:name":"Hendrix Excavation",
    "wof:placetype":"venue"
},
  "geometry": {"coordinates":[-95.628125,36.317388],"type":"Point"}
}