{
  "type": "Feature",
  "properties": {
    "addr:full":"620 Hwy 76 N Healdton OK 73438",
    "addr:housenumber":"620",
    "addr:postcode":"73438",
    "addr:street":"Hwy 76 N",
    "iso:country":"US",
    "sg:address":"620 Hwy 76 N",
    "sg:city":"Healdton",
    "sg:classifiers":[
        {
            "category":"Retail",
            "subcategory":"Laundry & Dry Cleaning",
            "type":"Services"
        }
    ],
    "sg:phone":"+1 580 229 9906",
    "sg:postcode":"73438",
    "sg:province":"OK",
    "sg:tags":[
        "drycleaning",
        "plant"
    ],
    "wof:name":"Comet Cleaners",
    "wof:placetype":"venue"
},
  "geometry": {"coordinates":[-97.490897,34.232975],"type":"Point"}
}