{
  "type": "Feature",
  "properties": {
    "addr:full":"2912 S Douglas Blvd Oklahoma City OK 73130",
    "addr:housenumber":"2912",
    "addr:postcode":"73130",
    "addr:street":"S Douglas Blvd",
    "iso:country":"US",
    "sg:address":"2912 S Douglas Blvd",
    "sg:city":"Oklahoma City",
    "sg:classifiers":[
        {
            "category":"Banks & Credit Unions",
            "subcategory":"Bank",
            "type":"Services"
        }
    ],
    "sg:phone":"+1 405 733 2600",
    "sg:postcode":"73130",
    "sg:province":"OK",
    "sg:tags":[
        "mortgage",
        "loan",
        "banker",
        "real estate"
    ],
    "wof:name":"American Resource Mortgage Inc",
    "wof:placetype":"venue"
},
  "geometry": {"coordinates":[-97.37070900000001,35.435521],"type":"Point"}
}