{
  "type": "Feature",
  "properties": {
    "iso:country":"US",
    "sg:address":"6700 N Classen Blvd",
    "sg:city":"Oklahoma City",
    "sg:classifiers":[
        {
            "category":"Personal",
            "subcategory":"Beauty Salon",
            "type":"Services"
        }
    ],
    "sg:phone":"+1 405 810 8662",
    "sg:postcode":"73116",
    "sg:province":"OK",
    "sg:tags":[
        "shop"
    ],
    "wof:name":"Final Cut",
    "wof:placetype":"venue"
},
  "geometry": {"coordinates":[-97.526861,35.540483],"type":"Point"}
}