{
  "type": "Feature",
  "properties": {
    "iso:country":"US",
    "sg:address":"1212 E Okmulgee St",
    "sg:city":"Muskogee",
    "sg:classifiers":[
        {
            "category":"Organizations",
            "subcategory":"Labor Organization",
            "type":"Services"
        }
    ],
    "sg:phone":"+1 918 683 6587",
    "sg:postcode":"74403",
    "sg:province":"OK",
    "sg:tags":[
        "union"
    ],
    "wof:name":"Teamster Local Union 516",
    "wof:placetype":"venue"
},
  "geometry": {"coordinates":[-95.355203,35.74264],"type":"Point"}
}