{
  "type": "Feature",
  "properties": {
    "iso:country":"US",
    "sg:address":"12248 E 60th St",
    "sg:city":"Tulsa",
    "sg:classifiers":[
        {
            "category":"Building & Trades",
            "subcategory":"Construction",
            "type":"Services"
        }
    ],
    "sg:phone":"+1 918 249 9327",
    "sg:postcode":"74146",
    "sg:province":"OK",
    "sg:tags":[
        "contractor"
    ],
    "wof:name":"Custom Designers & Builders",
    "wof:placetype":"venue"
},
  "geometry": {"coordinates":[-95.833652,36.077135],"type":"Point"}
}