{
  "type": "Feature",
  "properties": {
    "iso:country":"US",
    "sg:address":"302 N 2nd",
    "sg:city":"Cyril",
    "sg:classifiers":[
        {
            "category":"Insurance",
            "subcategory":"Insurance Agent",
            "type":"Services"
        }
    ],
    "sg:phone":"+1 580 464 2412",
    "sg:postcode":"73029",
    "sg:province":"OK",
    "wof:name":"Heavin Insurance",
    "wof:placetype":"venue"
},
  "geometry": {"coordinates":[-98.201122,34.901691],"type":"Point"}
}