{
  "type": "Feature",
  "properties": {
    "iso:country":"US",
    "sg:address":"303 N McKinley Ave",
    "sg:city":"Sand Springs",
    "sg:classifiers":[
        {
            "category":"Manufacturing",
            "subcategory":"Printing",
            "type":"Manufacturing & Wholesale Goods"
        }
    ],
    "sg:phone":"+1 918 245 6634",
    "sg:postcode":"74063",
    "sg:province":"OK",
    "sg:tags":[
        "newspaper"
    ],
    "wof:name":"Sand Springs Leader",
    "wof:placetype":"venue"
},
  "geometry": {"coordinates":[-96.108836,36.139667],"type":"Point"}
}