{
  "type": "Feature",
  "properties": {
    "iso:country":"US",
    "sg:address":"2200 S Utica Ave",
    "sg:city":"Tulsa",
    "sg:classifiers":[
        {
            "category":"Banks & Credit Unions",
            "subcategory":"Bank",
            "type":"Services"
        }
    ],
    "sg:phone":"+1 918 293 6700",
    "sg:postcode":"74114",
    "sg:province":"OK",
    "sg:tags":[
        "saving",
        "commercial"
    ],
    "sg:website":"http://www.midfirst.com",
    "wof:name":"Midfirst Bank",
    "wof:placetype":"venue"
},
  "geometry": {"coordinates":[-95.967133,36.131962],"type":"Point"}
}