{
  "type": "Feature",
  "properties": {
    "iso:country":"US",
    "sg:address":"1418 E 71st St S",
    "sg:city":"Tulsa",
    "sg:classifiers":[
        {
            "category":"Personal",
            "subcategory":"Adult",
            "type":"Services"
        }
    ],
    "sg:phone":"+1 918 491 0002",
    "sg:postcode":"74136",
    "sg:province":"OK",
    "sg:tags":[
        "dating"
    ],
    "wof:name":"Charlee Enterprises",
    "wof:placetype":"venue"
},
  "geometry": {"coordinates":[-95.974428,36.060588],"type":"Point"}
}