{
  "type": "Feature",
  "properties": {
    "iso:country":"US",
    "sg:address":"10410 N Yale Ave",
    "sg:city":"Sperry",
    "sg:classifiers":[
        {
            "category":"Professional",
            "subcategory":"Business Services",
            "type":"Services"
        }
    ],
    "sg:phone":"+1 918 288 7308",
    "sg:postcode":"74073",
    "sg:province":"OK",
    "sg:tags":[
        "auctioneer"
    ],
    "wof:name":"Thomas Sales Co",
    "wof:placetype":"venue"
},
  "geometry": {"coordinates":[-95.920015,36.304857],"type":"Point"}
}