{
  "type": "Feature",
  "properties": {
    "iso:country":"US",
    "sg:address":"501 S Johnstone Ave",
    "sg:city":"Bartlesville",
    "sg:classifiers":[
        {
            "category":"Professional",
            "subcategory":"Lawyer & Legal Services",
            "type":"Services"
        }
    ],
    "sg:phone":"+1 918 336 1773",
    "sg:postcode":"74003",
    "sg:province":"OK",
    "wof:name":"Heskett & Heskett",
    "wof:placetype":"venue"
},
  "geometry": {"coordinates":[-95.97786000000001,36.748855],"type":"Point"}
}