{
  "type": "Feature",
  "properties": {
    "addr:full":"812 NE 24th St Newcastle OK 73065",
    "addr:housenumber":"812",
    "addr:postcode":"73065",
    "addr:street":"Ne 24Th St",
    "iso:country":"US",
    "sg:address":"812 NE 24th St",
    "sg:city":"Newcastle",
    "sg:classifiers":[
        {
            "category":"Wholesale",
            "subcategory":"Machinery & Supplies",
            "type":"Manufacturing & Wholesale Goods"
        }
    ],
    "sg:phone":"+1 405 387 3300",
    "sg:postcode":"73065",
    "sg:province":"OK",
    "sg:tags":[
        "equipment",
        "veterinarian"
    ],
    "wof:name":"Solidtech Animal Health",
    "wof:placetype":"venue"
},
  "geometry": {"coordinates":[-97.585838,35.276408],"type":"Point"}
}