{
  "type": "Feature",
  "properties": {
    "iso:country":"US",
    "sg:address":"500 S Nickerson St",
    "sg:city":"Waynoka",
    "sg:classifiers":[
        {
            "category":"Organizations",
            "subcategory":"Non-profit Organization",
            "type":"Services"
        },
        {
            "category":"Health Services",
            "subcategory":"Hospital",
            "type":"Services"
        }
    ],
    "sg:phone":"+1 580 824 0674",
    "sg:postcode":"73860",
    "sg:province":"OK",
    "sg:tags":[
        "info",
        "specialty",
        "drug",
        "abuse",
        "treatment",
        "addiction"
    ],
    "wof:name":"Northwest Substance Abuse Trea",
    "wof:placetype":"venue"
},
  "geometry": {"coordinates":[-98.875402,36.57985],"type":"Point"}
}