{
  "type": "Feature",
  "properties": {
    "iso:country":"US",
    "sg:address":"101 S 15th St",
    "sg:city":"Duncan",
    "sg:classifiers":[
        {
            "category":"Manufacturing",
            "subcategory":"Printing",
            "type":"Manufacturing & Wholesale Goods"
        }
    ],
    "sg:phone":"+1 580 475 9000",
    "sg:postcode":"73533",
    "sg:province":"OK",
    "sg:tags":[
        "publisher"
    ],
    "wof:name":"DIGIMEDIA.COM",
    "wof:placetype":"venue"
},
  "geometry": {"coordinates":[-97.967126,34.501622],"type":"Point"}
}