{
  "type": "Feature",
  "properties": {
    "iso:country":"US",
    "sg:address":"32989 US Hwy 69",
    "sg:city":"Big Cabin",
    "sg:classifiers":[
        {
            "category":"Freight",
            "type":"Transportation"
        }
    ],
    "sg:phone":"+1 918 783 5305",
    "sg:postcode":"74332",
    "sg:province":"OK",
    "sg:tags":[
        "trucking"
    ],
    "wof:name":"International Trucking Cnsltnt",
    "wof:placetype":"venue"
},
  "geometry": {"coordinates":[-95.223705,36.539688],"type":"Point"}
}