{
  "type": "Feature",
  "properties": {
    "iso:country":"US",
    "sg:address":"404 E Florida St",
    "sg:city":"Durant",
    "sg:classifiers":[
        {
            "category":"Personal",
            "subcategory":"Beauty Salon",
            "type":"Services"
        }
    ],
    "sg:phone":"+1 580 924 9002",
    "sg:postcode":"74701",
    "sg:province":"OK",
    "sg:tags":[
        "shop"
    ],
    "wof:name":"Donnas Hrstyling For Men Women",
    "wof:placetype":"venue"
},
  "geometry": {"coordinates":[-96.369385,33.989124],"type":"Point"}
}