{
  "type": "Feature",
  "properties": {
    "addr:full":"415 S Dewey Ave Bartlesville OK 74003",
    "addr:housenumber":"415",
    "addr:postcode":"74003",
    "addr:street":"S Dewey Ave",
    "iso:country":"US",
    "sg:address":"415 S Dewey Ave",
    "sg:city":"Bartlesville",
    "sg:classifiers":[
        {
            "category":"Professional",
            "subcategory":"Lawyer & Legal Services",
            "type":"Services"
        }
    ],
    "sg:phone":"+1 918 336 4550",
    "sg:postcode":"74003",
    "sg:province":"OK",
    "sg:tags":[
        "attorney"
    ],
    "wof:name":"Rowland & Rowland",
    "wof:placetype":"venue"
},
  "geometry": {"coordinates":[-95.976377,36.749583],"type":"Point"}
}