{
  "type": "Feature",
  "properties": {
    "addr:full":"1705 Boren Blvd Seminole OK 74868",
    "addr:housenumber":"1705",
    "addr:postcode":"74868",
    "addr:street":"Boren Blvd",
    "iso:country":"US",
    "sg:address":"1705 Boren Blvd",
    "sg:city":"Seminole",
    "sg:classifiers":[
        {
            "category":"Health Services",
            "subcategory":"Nursing And Care Facility",
            "type":"Services"
        }
    ],
    "sg:phone":"+1 405 382 1270",
    "sg:postcode":"74868",
    "sg:province":"OK",
    "sg:tags":[
        "home",
        "convalescent"
    ],
    "wof:name":"Pioneer Nursing Home",
    "wof:placetype":"venue"
},
  "geometry": {"coordinates":[-96.692888,35.237822],"type":"Point"}
}