{
  "type": "Feature",
  "properties": {
    "iso:country":"US",
    "sg:address":"2700 N Hemlock Cir",
    "sg:city":"Broken Arrow",
    "sg:classifiers":[
        {
            "category":"Education",
            "subcategory":"Special Training",
            "type":"Public Place"
        }
    ],
    "sg:phone":"+1 918 251 0500",
    "sg:postcode":"74012",
    "sg:province":"OK",
    "sg:tags":[
        "aircraft",
        "school"
    ],
    "sg:website":"www.flightsafety.com",
    "wof:name":"Flight Safety Intl",
    "wof:placetype":"venue"
},
  "geometry": {"coordinates":[-95.822199,36.076584],"type":"Point"}
}