{
  "type": "Feature",
  "properties": {
    "iso:country":"US",
    "sg:address":"3711 el Pizo Cir",
    "sg:city":"Spencer",
    "sg:classifiers":[
        {
            "category":"Social Services",
            "subcategory":"Adult Care",
            "type":"Services"
        },
        {
            "category":"Health Services",
            "subcategory":"Nursing And Care Facility",
            "type":"Services"
        }
    ],
    "sg:phone":"+1 405 771 8800",
    "sg:postcode":"73084",
    "sg:province":"OK",
    "sg:tags":[
        "home",
        "retirement",
        "community",
        "residential"
    ],
    "wof:name":"Roscoe Dnjee Senior Living Ctr",
    "wof:placetype":"venue"
},
  "geometry": {"coordinates":[-97.378249,35.50865],"type":"Point"}
}