{
  "type": "Feature",
  "properties": {
    "addr:full":"223 S Comanche Ave Bartlesville OK 74003",
    "addr:housenumber":"223",
    "addr:postcode":"74003",
    "addr:street":"S Comanche Ave",
    "iso:country":"US",
    "sg:address":"223 S Comanche Ave",
    "sg:city":"Bartlesville",
    "sg:classifiers":[
        {
            "category":"Restaurant",
            "type":"Food & Drink"
        }
    ],
    "sg:phone":"+1 918 336 0343",
    "sg:postcode":"74003",
    "sg:province":"OK",
    "wof:name":"El Burrito Azteca",
    "wof:placetype":"venue"
},
  "geometry": {"coordinates":[-95.96285399999999,36.75051],"type":"Point"}
}