{
  "type": "Feature",
  "properties": {
    "addr:full":"3919 Oklahoma Ave Woodward OK 73801",
    "addr:housenumber":"3919",
    "addr:postcode":"73801",
    "addr:street":"Oklahoma Ave",
    "iso:country":"US",
    "sg:address":"3919 Oklahoma Ave",
    "sg:city":"Woodward",
    "sg:classifiers":[
        {
            "category":"Shopping",
            "type":"Retail Goods"
        }
    ],
    "sg:phone":"+1 580 256 7227",
    "sg:postcode":"73801",
    "sg:province":"OK",
    "sg:tags":[
        "oilfield",
        "supply"
    ],
    "wof:name":"DWL Sales & Supply",
    "wof:placetype":"venue"
},
  "geometry": {"coordinates":[-99.431573,36.433445],"type":"Point"}
}