{
  "type": "Feature",
  "properties": {
    "iso:country":"US",
    "sg:address":"509 N Redbud Ave",
    "sg:city":"Broken Arrow",
    "sg:classifiers":[
        {
            "category":"Wholesale",
            "subcategory":"Machinery & Supplies",
            "type":"Manufacturing & Wholesale Goods"
        }
    ],
    "sg:phone":"+1 918 251 2661",
    "sg:postcode":"74012",
    "sg:province":"OK",
    "wof:name":"K & B Machinery Inc",
    "wof:placetype":"venue"
},
  "geometry": {"coordinates":[-95.81167499999999,36.05689],"type":"Point"}
}