{
  "type": "Feature",
  "properties": {
    "addr:full":"1111 S 73rd East Ave Tulsa OK 74112",
    "addr:housenumber":"1111",
    "addr:postcode":"74112",
    "addr:street":"S 73Rd;Ave",
    "iso:country":"US",
    "sg:address":"1111 S 73rd East Ave",
    "sg:city":"Tulsa",
    "sg:classifiers":[
        {
            "category":"Retail",
            "subcategory":"Auto Repair",
            "type":"Services"
        }
    ],
    "sg:phone":"+1 918 836 3341",
    "sg:postcode":"74112",
    "sg:province":"OK",
    "sg:tags":[
        "transmission",
        "automotive",
        "general"
    ],
    "wof:name":"Action Transmission Center",
    "wof:placetype":"venue"
},
  "geometry": {"coordinates":[-95.895516,36.146299],"type":"Point"}
}