{
  "type": "Feature",
  "properties": {
    "addr:full":"620 Parrington Oval Norman OK 73069",
    "addr:housenumber":"620",
    "addr:postcode":"73069",
    "addr:street":"Parrington Oval",
    "iso:country":"US",
    "sg:address":"620 Parrington Oval",
    "sg:city":"Norman",
    "sg:classifiers":[
        {
            "category":"Education",
            "subcategory":"College",
            "type":"Public Place"
        }
    ],
    "sg:phone":"+1 405 325 4811",
    "sg:postcode":"73069",
    "sg:province":"OK",
    "wof:name":"Dept of Chemistry",
    "wof:placetype":"venue"
},
  "geometry": {"coordinates":[-97.446048,35.209316],"type":"Point"}
}