{
  "type": "Feature",
  "properties": {
    "iso:country":"US",
    "sg:address":"3721 Spring Hill Dr",
    "sg:city":"Edmond",
    "sg:classifiers":[
        {
            "category":"Building & Trades",
            "subcategory":"Construction",
            "type":"Services"
        }
    ],
    "sg:phone":"+1 405 844 5544",
    "sg:postcode":"73013",
    "sg:province":"OK",
    "sg:tags":[
        "resurfacing",
        "floor",
        "laying",
        "refinishing",
        "contractor"
    ],
    "wof:name":"Rhino Floor Prep Inc",
    "wof:placetype":"venue"
},
  "geometry": {"coordinates":[-97.449937,35.620155],"type":"Point"}
}