{
  "type": "Feature",
  "properties": {
    "iso:country":"US",
    "sg:address":"2309 N Broadway Ave",
    "sg:city":"Oklahoma City",
    "sg:classifiers":[
        {
            "category":"Shopping",
            "subcategory":"Jewelry",
            "type":"Retail Goods"
        }
    ],
    "sg:phone":"+1 405 528 0058",
    "sg:postcode":"73103",
    "sg:province":"OK",
    "wof:name":"Credit Jewelry",
    "wof:placetype":"venue"
},
  "geometry": {"coordinates":[-97.51387099999999,35.492533],"type":"Point"}
}