{
  "type": "Feature",
  "properties": {
    "addr:full":"102 E Main St Shawnee OK 74801",
    "addr:housenumber":"102",
    "addr:postcode":"74801",
    "addr:street":"E Main St",
    "iso:country":"US",
    "sg:address":"102 E Main St",
    "sg:city":"Shawnee",
    "sg:classifiers":[
        {
            "category":"Travel",
            "subcategory":"Travel Agent",
            "type":"Entertainment"
        }
    ],
    "sg:phone":"+1 405 275 9222",
    "sg:postcode":"74801",
    "sg:province":"OK",
    "sg:tags":[
        "agency"
    ],
    "wof:name":"Shawnee Travel Shoppe Inc",
    "wof:placetype":"venue"
},
  "geometry": {"coordinates":[-96.92217100000001,35.327444],"type":"Point"}
}