{
  "type": "Feature",
  "properties": {
    "addr:full":"1010 E Main St Cushing OK 74023",
    "addr:housenumber":"1010",
    "addr:postcode":"74023",
    "addr:street":"E Main St",
    "iso:country":"US",
    "sg:address":"1010 E Main St",
    "sg:city":"Cushing",
    "sg:classifiers":[
        {
            "category":"Personal",
            "subcategory":"Barber",
            "type":"Services"
        }
    ],
    "sg:phone":"+1 918 225 2126",
    "sg:postcode":"74023",
    "sg:province":"OK",
    "wof:name":"Remuda Barber Shop",
    "wof:placetype":"venue"
},
  "geometry": {"coordinates":[-96.758421,35.98508],"type":"Point"}
}