{
  "type": "Feature",
  "properties": {
    "addr:full":"12601 SE 15th St Choctaw OK 73020",
    "addr:housenumber":"12601",
    "addr:postcode":"73020",
    "addr:street":"Se 15Th St",
    "iso:country":"US",
    "sg:address":"12601 SE 15th St",
    "sg:city":"Choctaw",
    "sg:classifiers":[
        {
            "category":"Retail",
            "subcategory":"Animal Services",
            "type":"Services"
        }
    ],
    "sg:phone":"+1 405 769 4108",
    "sg:postcode":"73020",
    "sg:province":"OK",
    "sg:tags":[
        "farm",
        "training",
        "dog",
        "supply"
    ],
    "wof:name":"Deep Fork Retrievers Inc",
    "wof:placetype":"venue"
},
  "geometry": {"coordinates":[-97.307772,35.449982],"type":"Point"}
}