{
  "type": "Feature",
  "properties": {
    "iso:country":"US",
    "sg:address":"200 W Main St",
    "sg:city":"Ardmore",
    "sg:classifiers":[
        {
            "category":"Restaurant",
            "type":"Food & Drink"
        }
    ],
    "sg:phone":"+1 580 226 9090",
    "sg:postcode":"73401",
    "sg:province":"OK",
    "sg:tags":[
        "eating"
    ],
    "wof:name":"Old Time Soda Pop Shop",
    "wof:placetype":"venue"
},
  "geometry": {"coordinates":[-97.13046,34.173041],"type":"Point"}
}