{
  "type": "Feature",
  "properties": {
    "addr:full":"5117 N Shartel Ave Oklahoma City OK 73118",
    "addr:housenumber":"5117",
    "addr:postcode":"73118",
    "addr:street":"N Shartel Ave",
    "iso:country":"US",
    "sg:address":"5117 N Shartel Ave",
    "sg:city":"Oklahoma City",
    "sg:classifiers":[
        {
            "category":"Personal",
            "subcategory":"Beauty Salon",
            "type":"Services"
        }
    ],
    "sg:phone":"+1 405 842 7075",
    "sg:postcode":"73118",
    "sg:province":"OK",
    "wof:name":"Salon Etc",
    "wof:placetype":"venue"
},
  "geometry": {"coordinates":[-97.525603,35.523294],"type":"Point"}
}