{
  "type": "Feature",
  "properties": {
    "iso:country":"US",
    "sg:address":"4828 Creekwood Dr",
    "sg:city":"Oklahoma City",
    "sg:classifiers":[
        {
            "category":"Professional",
            "subcategory":"Business Services",
            "type":"Services"
        }
    ],
    "sg:phone":"+1 405 670 7900",
    "sg:postcode":"73135",
    "sg:province":"OK",
    "sg:tags":[
        "recording",
        "studio"
    ],
    "wof:name":"Strongtower Inc",
    "wof:placetype":"venue"
},
  "geometry": {"coordinates":[-97.454831,35.418032],"type":"Point"}
}