{
  "type": "Feature",
  "properties": {
    "iso:country":"US",
    "sg:address":"612 Cedar St",
    "sg:city":"Perry",
    "sg:classifiers":[
        {
            "category":"Professional",
            "subcategory":"Lawyer & Legal Services",
            "type":"Services"
        }
    ],
    "sg:phone":"+1 580 336 1300",
    "sg:postcode":"73077",
    "sg:province":"OK",
    "sg:tags":[
        "attorney"
    ],
    "wof:name":"Sherry Debord",
    "wof:placetype":"venue"
},
  "geometry": {"coordinates":[-97.286025,36.285956],"type":"Point"}
}