{
  "type": "Feature",
  "properties": {
    "iso:country":"US",
    "sg:address":"10340 E 58th St",
    "sg:city":"Tulsa",
    "sg:classifiers":[
        {
            "category":"Building & Trades",
            "subcategory":"Construction",
            "type":"Services"
        }
    ],
    "sg:phone":"+1 918 663 7770",
    "sg:postcode":"74146",
    "sg:province":"OK",
    "sg:tags":[
        "equipment",
        "casino",
        "installation"
    ],
    "wof:name":"Nova Gaming Inc",
    "wof:placetype":"venue"
},
  "geometry": {"coordinates":[-95.867686,36.079947],"type":"Point"}
}