{
  "type": "Feature",
  "properties": {
    "iso:country":"US",
    "sg:address":"2029 W Kenosha St",
    "sg:city":"Broken Arrow",
    "sg:classifiers":[
        {
            "category":"Banks & Credit Unions",
            "subcategory":"Bank",
            "type":"Services"
        }
    ],
    "sg:phone":"+1 918 631 1000",
    "sg:postcode":"74012",
    "sg:province":"OK",
    "sg:website":"www.arvest.com",
    "wof:name":"Arvest State Bank",
    "wof:placetype":"venue"
},
  "geometry": {"coordinates":[-95.816573,36.06097],"type":"Point"}
}