{
  "type": "Feature",
  "properties": {
    "iso:country":"US",
    "sg:address":"5550 S Garnett Rd",
    "sg:city":"Tulsa",
    "sg:classifiers":[
        {
            "category":"Wholesale",
            "subcategory":"Machinery & Supplies",
            "type":"Manufacturing & Wholesale Goods"
        }
    ],
    "sg:phone":"+1 918 665 3243",
    "sg:postcode":"74146",
    "sg:province":"OK",
    "sg:tags":[
        "heat",
        "exchanger"
    ],
    "wof:name":"Tek-Fins Inc",
    "wof:placetype":"venue"
},
  "geometry": {"coordinates":[-95.851122,36.082709],"type":"Point"}
}