{
  "type": "Feature",
  "properties": {
    "addr:full":"301 W 4th St Ada OK 74820",
    "addr:housenumber":"301",
    "addr:postcode":"74820",
    "addr:street":"W 4Th St",
    "iso:country":"US",
    "sg:address":"301 W 4th St",
    "sg:city":"Ada",
    "sg:classifiers":[
        {
            "category":"Health Services",
            "subcategory":"Hospital",
            "type":"Services"
        }
    ],
    "sg:phone":"+1 580 332 8819",
    "sg:postcode":"74820",
    "sg:province":"OK",
    "sg:tags":[
        "mental"
    ],
    "wof:name":"Socializers",
    "wof:placetype":"venue"
},
  "geometry": {"coordinates":[-96.68346099999999,34.781824],"type":"Point"}
}