{
  "type": "Feature",
  "properties": {
    "iso:country":"US",
    "sg:address":"6973 E 71st St",
    "sg:city":"Tulsa",
    "sg:classifiers":[
        {
            "category":"Restaurant",
            "type":"Food & Drink"
        }
    ],
    "sg:phone":"+1 918 481 7200",
    "sg:postcode":"74133",
    "sg:province":"OK",
    "sg:website":"http://www.senortequilaok.com",
    "wof:name":"Senor Tequila",
    "wof:placetype":"venue"
},
  "geometry": {"coordinates":[-95.898881,36.060939],"type":"Point"}
}