{
  "type": "Feature",
  "properties": {
    "iso:country":"US",
    "sg:address":"301 N 13th St",
    "sg:city":"Frederick",
    "sg:classifiers":[
        {
            "category":"Retail",
            "subcategory":"Car Wash",
            "type":"Services"
        }
    ],
    "sg:phone":"+1 580 335 2416",
    "sg:postcode":"73542",
    "sg:province":"OK",
    "sg:tags":[
        "polishing",
        "washing"
    ],
    "wof:name":"Boyd's Car Washing Detail",
    "wof:placetype":"venue"
},
  "geometry": {"coordinates":[-99.013281,34.393034],"type":"Point"}
}