{
  "type": "Feature",
  "properties": {
    "iso:country":"US",
    "sg:address":"500 N F St",
    "sg:city":"Muskogee",
    "sg:classifiers":[
        {
            "category":"Organizations",
            "subcategory":"Religious Organization",
            "type":"Services"
        }
    ],
    "sg:phone":"+1 918 682 2592",
    "sg:postcode":"74403",
    "sg:province":"OK",
    "sg:tags":[
        "church"
    ],
    "wof:name":"First Church Of The Nazarene",
    "wof:placetype":"venue"
},
  "geometry": {"coordinates":[-95.35911,35.750495],"type":"Point"}
}