{
  "type": "Feature",
  "properties": {
    "iso:country":"US",
    "sg:address":"5507 S Columbia Ave",
    "sg:city":"Tulsa",
    "sg:classifiers":[
        {
            "category":"Building & Trades",
            "subcategory":"Construction",
            "type":"Services"
        }
    ],
    "sg:phone":"+1 918 747 5351",
    "sg:postcode":"74105",
    "sg:province":"OK",
    "sg:tags":[
        "waterproofing",
        "contractor"
    ],
    "wof:name":"Watertight",
    "wof:placetype":"venue"
},
  "geometry": {"coordinates":[-95.95180499999999,36.083618],"type":"Point"}
}