{
  "type": "Feature",
  "properties": {
    "iso:country":"US",
    "sg:address":"116 E McElroy Rd",
    "sg:city":"Stillwater",
    "sg:classifiers":[
        {
            "category":"Restaurant",
            "type":"Food & Drink"
        }
    ],
    "sg:phone":"+1 405 624 2300",
    "sg:postcode":"74075",
    "sg:province":"OK",
    "wof:name":"Taco Mayo",
    "wof:placetype":"venue"
},
  "geometry": {"coordinates":[-97.058178,36.130571],"type":"Point"}
}