{
  "type": "Feature",
  "properties": {
    "iso:country":"US",
    "sg:address":"5500 E Independence St",
    "sg:city":"Tulsa",
    "sg:classifiers":[
        {
            "category":"Manufacturing",
            "subcategory":"Metals",
            "type":"Manufacturing & Wholesale Goods"
        }
    ],
    "sg:phone":"+1 918 835 3126",
    "sg:postcode":"74115",
    "sg:province":"OK",
    "sg:tags":[
        "plate",
        "work",
        "fabricated",
        "mfg"
    ],
    "wof:name":"Heater Specialists LLC",
    "wof:placetype":"venue"
},
  "geometry": {"coordinates":[-95.914,36.166219],"type":"Point"}
}