{
  "type": "Feature",
  "properties": {
    "iso:country":"US",
    "sg:address":"1505 N Rockwell Ave",
    "sg:city":"Oklahoma City",
    "sg:classifiers":[
        {
            "category":"Health Services",
            "subcategory":"Doctor",
            "type":"Services"
        }
    ],
    "sg:phone":"+1 405 848 5325",
    "sg:postcode":"73127",
    "sg:province":"OK",
    "sg:tags":[
        "clinic",
        "medical"
    ],
    "wof:name":"S Sandy Sunbar MD",
    "wof:placetype":"venue"
},
  "geometry": {"coordinates":[-97.636746,35.486075],"type":"Point"}
}