{
  "type": "Feature",
  "properties": {
    "addr:full":"109 Janets Way Elk City OK 73644",
    "addr:housenumber":"109",
    "addr:postcode":"73644",
    "addr:street":"Janets Way",
    "iso:country":"US",
    "sg:address":"109 Janets Way",
    "sg:city":"Elk City",
    "sg:classifiers":[
        {
            "category":"Professional",
            "subcategory":"Management & Consulting",
            "type":"Services"
        }
    ],
    "sg:phone":"+1 580 303 9057",
    "sg:postcode":"73644",
    "sg:province":"OK",
    "sg:tags":[
        "personnel",
        "consultant"
    ],
    "wof:name":"SOS Staffing Svc",
    "wof:placetype":"venue"
},
  "geometry": {"coordinates":[-99.43939399999999,35.410958],"type":"Point"}
}