{
  "type": "Feature",
  "properties": {
    "iso:country":"US",
    "sg:address":"900 S Owens Ave",
    "sg:city":"Tahlequah",
    "sg:classifiers":[
        {
            "category":"Freight",
            "type":"Transportation"
        }
    ],
    "sg:phone":"+1 918 456 3135",
    "sg:postcode":"74464",
    "sg:province":"OK",
    "sg:tags":[
        "operator",
        "local",
        "trucking"
    ],
    "wof:name":"Layne Trucking",
    "wof:placetype":"venue"
},
  "geometry": {"coordinates":[-94.982787,35.904289],"type":"Point"}
}