{
  "type": "Feature",
  "properties": {
    "iso:country":"US",
    "sg:address":"1205 NW 23rd St",
    "sg:city":"Oklahoma City",
    "sg:classifiers":[
        {
            "category":"Education",
            "subcategory":"Dance Studio",
            "type":"Public Place"
        }
    ],
    "sg:phone":"+1 405 528 2737",
    "sg:postcode":"73106",
    "sg:province":"OK",
    "sg:tags":[
        "school"
    ],
    "wof:name":"Macias Dance Center",
    "wof:placetype":"venue"
},
  "geometry": {"coordinates":[-97.531702,35.493313],"type":"Point"}
}