{
  "type": "Feature",
  "properties": {
    "addr:full":"101 W Gary Blvd Clinton OK 73096",
    "addr:housenumber":"101",
    "addr:postcode":"73096",
    "addr:street":"W Gary Blvd",
    "iso:country":"US",
    "sg:address":"101 W Gary Blvd",
    "sg:city":"Clinton",
    "sg:classifiers":[
        {
            "category":"Farming",
            "subcategory":"Dairy Farm",
            "type":"Manufacturing & Wholesale Goods"
        }
    ],
    "sg:phone":"+1 580 323 0404",
    "sg:postcode":"73096",
    "sg:province":"OK",
    "wof:name":"Highland Dairy",
    "wof:placetype":"venue"
},
  "geometry": {"coordinates":[-98.962351,35.515378],"type":"Point"}
}