{
  "type": "Feature",
  "properties": {
    "iso:country":"US",
    "sg:address":"2103 N Broadway St",
    "sg:city":"Poteau",
    "sg:classifiers":[
        {
            "category":"Home & Garden",
            "subcategory":"Carpets & Floor Coverings",
            "type":"Retail Goods"
        }
    ],
    "sg:phone":"+1 918 647 2151",
    "sg:postcode":"74953",
    "sg:province":"OK",
    "sg:tags":[
        "dealer",
        "rug"
    ],
    "wof:name":"Poteau Floors & More",
    "wof:placetype":"venue"
},
  "geometry": {"coordinates":[-94.620852,35.063471],"type":"Point"}
}