{
  "type": "Feature",
  "properties": {
    "addr:full":"44602 E Macarthur St Shawnee OK 74804",
    "addr:housenumber":"44602",
    "addr:postcode":"74804",
    "addr:street":"E Macarthur St",
    "iso:country":"US",
    "sg:address":"44602 E Macarthur St",
    "sg:city":"Shawnee",
    "sg:classifiers":[
        {
            "category":"Communications",
            "subcategory":"Film & Video Production",
            "type":"Services"
        }
    ],
    "sg:phone":"+1 405 273 1994",
    "sg:postcode":"74804",
    "sg:province":"OK",
    "sg:tags":[
        "taping"
    ],
    "wof:name":"Jesus Christ Video Co",
    "wof:placetype":"venue"
},
  "geometry": {"coordinates":[-96.866106,35.361654],"type":"Point"}
}