{
  "type": "Feature",
  "properties": {
    "iso:country":"US",
    "sg:address":"630 E Steve Owens Blvd",
    "sg:city":"Miami",
    "sg:classifiers":[
        {
            "category":"Professional",
            "type":"Services"
        }
    ],
    "sg:phone":"+1 918 542 6423",
    "sg:postcode":"74354",
    "sg:province":"OK",
    "sg:tags":[
        "natural",
        "conservation",
        "resource"
    ],
    "wof:name":"Ottawa County Conservation Dst",
    "wof:placetype":"venue"
},
  "geometry": {"coordinates":[-94.870878,36.870927],"type":"Point"}
}