{
  "type": "Feature",
  "properties": {
    "addr:full":"1201 W Noble Ave Guthrie OK 73044",
    "addr:housenumber":"1201",
    "addr:postcode":"73044",
    "addr:street":"W Noble Ave",
    "iso:country":"US",
    "sg:address":"1201 W Noble Ave",
    "sg:city":"Guthrie",
    "sg:classifiers":[
        {
            "category":"Organizations",
            "subcategory":"Religious Organization",
            "type":"Services"
        }
    ],
    "sg:phone":"+1 405 282 1300",
    "sg:postcode":"73044",
    "sg:province":"OK",
    "sg:tags":[
        "church"
    ],
    "wof:name":"West Guthrie United Methodist",
    "wof:placetype":"venue"
},
  "geometry": {"coordinates":[-97.44055,35.880064],"type":"Point"}
}