{
  "type": "Feature",
  "properties": {
    "iso:country":"US",
    "sg:address":"318 NW 65th St",
    "sg:city":"Lawton",
    "sg:classifiers":[
        {
            "category":"Professional",
            "subcategory":"Business Services",
            "type":"Services"
        }
    ],
    "sg:phone":"+1 580 536 3492",
    "sg:postcode":"73505",
    "sg:province":"OK",
    "sg:tags":[
        "contracting"
    ],
    "wof:name":"Exceptional People",
    "wof:placetype":"venue"
},
  "geometry": {"coordinates":[-98.471773,34.614022],"type":"Point"}
}