{
  "type": "Feature",
  "properties": {
    "iso:country":"US",
    "sg:address":"333 S 38th St",
    "sg:city":"Muskogee",
    "sg:classifiers":[
        {
            "category":"Health Services",
            "subcategory":"Doctor",
            "type":"Services"
        }
    ],
    "sg:phone":"+1 918 682 8087",
    "sg:postcode":"74401",
    "sg:province":"OK",
    "sg:tags":[
        "physician",
        "surgeon"
    ],
    "wof:name":"Neurological Associates",
    "wof:placetype":"venue"
},
  "geometry": {"coordinates":[-95.409429,35.752618],"type":"Point"}
}