{
  "type": "Feature",
  "properties": {
    "iso:country":"US",
    "sg:address":"300 S Custer St",
    "sg:city":"Weatherford",
    "sg:classifiers":[
        {
            "category":"Home & Garden",
            "subcategory":"Hardware",
            "type":"Retail Goods"
        }
    ],
    "sg:phone":"+1 580 772 7781",
    "sg:postcode":"73096",
    "sg:province":"OK",
    "wof:name":"Weatherford Ace Home Ctr",
    "wof:placetype":"venue"
},
  "geometry": {"coordinates":[-98.70772700000001,35.523938],"type":"Point"}
}