{
  "type": "Feature",
  "properties": {
    "iso:country":"US",
    "sg:address":"7823 NW 23rd St",
    "sg:city":"Bethany",
    "sg:classifiers":[
        {
            "category":"Arts & Performance",
            "subcategory":"Theater",
            "type":"Entertainment"
        }
    ],
    "sg:phone":"+1 405 691 8788",
    "sg:postcode":"73008",
    "sg:province":"OK",
    "sg:tags":[
        "dance",
        "company"
    ],
    "wof:name":"Dance Authority By Darcy",
    "wof:placetype":"venue"
},
  "geometry": {"coordinates":[-97.651134,35.493385],"type":"Point"}
}