{
  "type": "Feature",
  "properties": {
    "addr:full":"5343 E Xyler St Tulsa OK 74115",
    "addr:housenumber":"5343",
    "addr:postcode":"74115",
    "addr:street":"E Xyler St",
    "iso:country":"US",
    "sg:address":"5343 E Xyler St",
    "sg:city":"Tulsa",
    "sg:classifiers":[
        {
            "category":"Building & Trades",
            "subcategory":"Plumbing",
            "type":"Services"
        }
    ],
    "sg:phone":"+1 918 835 8562",
    "sg:postcode":"74115",
    "sg:province":"OK",
    "sg:tags":[
        "plumbing",
        "contractor"
    ],
    "wof:name":"Dean Tull Plumbing Heating",
    "wof:placetype":"venue"
},
  "geometry": {"coordinates":[-95.91776299999999,36.187427],"type":"Point"}
}