{
  "type": "Feature",
  "properties": {
    "iso:country":"US",
    "sg:address":"103 N Cherokee Ave",
    "sg:city":"Claremore",
    "sg:classifiers":[
        {
            "category":"Shopping",
            "type":"Retail Goods"
        }
    ],
    "sg:phone":"+1 918 342 2646",
    "sg:postcode":"74017",
    "sg:province":"OK",
    "sg:tags":[
        "cards",
        "sport",
        "baseball",
        "memorabilia"
    ],
    "wof:name":"First Place Sports Cards",
    "wof:placetype":"venue"
},
  "geometry": {"coordinates":[-95.61353699999999,36.312109],"type":"Point"}
}