{
  "type": "Feature",
  "properties": {
    "addr:full":"120 NW 10th St Guymon OK 73942",
    "addr:housenumber":"120",
    "addr:postcode":"73942",
    "addr:street":"Nw 10Th St",
    "iso:country":"US",
    "sg:address":"120 NW 10th St",
    "sg:city":"Guymon",
    "sg:classifiers":[
        {
            "category":"Shopping",
            "subcategory":"Florist",
            "type":"Retail Goods"
        }
    ],
    "sg:phone":"+1 580 338 8084",
    "sg:postcode":"73942",
    "sg:province":"OK",
    "wof:name":"Myrene's House Of Flowers",
    "wof:placetype":"venue"
},
  "geometry": {"coordinates":[-101.48200199999999,36.687967],"type":"Point"}
}