{
  "type": "Feature",
  "properties": {
    "addr:full":"1412 SE Washington Blvd Bartlesville OK 74006",
    "addr:housenumber":"1412",
    "addr:postcode":"74006",
    "addr:street":"Se Washington Blvd",
    "iso:country":"US",
    "sg:address":"1412 SE Washington Blvd",
    "sg:city":"Bartlesville",
    "sg:classifiers":[
        {
            "category":"Restaurant",
            "type":"Food & Drink"
        }
    ],
    "sg:phone":"+1 918 335 1325",
    "sg:postcode":"74006",
    "sg:province":"OK",
    "sg:tags":[
        "eating"
    ],
    "wof:name":"Subway",
    "wof:placetype":"venue"
},
  "geometry": {"coordinates":[-95.935148,36.733319],"type":"Point"}
}