{
  "type": "Feature",
  "properties": {
    "iso:country":"US",
    "sg:address":"205 N Trade Center Ter",
    "sg:city":"Mustang",
    "sg:classifiers":[
        {
            "category":"Food & Beverages",
            "subcategory":"Bakery",
            "type":"Retail Goods"
        }
    ],
    "sg:phone":"+1 405 376 9020",
    "sg:postcode":"73064",
    "sg:province":"OK",
    "wof:name":"Mustang Munchies",
    "wof:placetype":"venue"
},
  "geometry": {"coordinates":[-97.72142599999999,35.392449],"type":"Point"}
}