{
  "type": "Feature",
  "properties": {
    "iso:country":"US",
    "sg:address":"115 W Elm Ave",
    "sg:city":"Fairfax",
    "sg:classifiers":[
        {
            "category":"Restaurant",
            "type":"Food & Drink"
        }
    ],
    "sg:phone":"+1 918 642 4444",
    "sg:postcode":"74637",
    "sg:province":"OK",
    "sg:website":"www.elmstreetcafe.com",
    "wof:name":"Elm Street Cafe",
    "wof:placetype":"venue"
},
  "geometry": {"coordinates":[-96.705493,36.573499],"type":"Point"}
}