{
  "type": "Feature",
  "properties": {
    "iso:country":"US",
    "sg:address":"324 S Main St",
    "sg:city":"Tulsa",
    "sg:classifiers":[
        {
            "category":"Professional",
            "subcategory":"Employment Agencies",
            "type":"Services"
        }
    ],
    "sg:phone":"+1 918 584 1097",
    "sg:postcode":"74103",
    "sg:province":"OK",
    "sg:tags":[
        "opportunity"
    ],
    "wof:name":"Attorney Resource",
    "wof:placetype":"venue"
},
  "geometry": {"coordinates":[-95.990829,36.152588],"type":"Point"}
}