{
  "type": "Feature",
  "properties": {
    "addr:full":"12264 NE 23rd St Choctaw OK 73020",
    "addr:housenumber":"12264",
    "addr:postcode":"73020",
    "addr:street":"Ne 23Rd St",
    "iso:country":"US",
    "sg:address":"12264 NE 23rd St",
    "sg:city":"Choctaw",
    "sg:classifiers":[
        {
            "category":"Professional",
            "subcategory":"Business Services",
            "type":"Services"
        }
    ],
    "sg:phone":"+1 405 769 1102",
    "sg:postcode":"73020",
    "sg:province":"OK",
    "sg:tags":[
        "repossessing"
    ],
    "wof:name":"Single Source Financial Adjust",
    "wof:placetype":"venue"
},
  "geometry": {"coordinates":[-97.31582299999999,35.493157],"type":"Point"}
}