{
  "type": "Feature",
  "properties": {
    "addr:full":"1200 Holly St Ardmore OK 73401",
    "addr:housenumber":"1200",
    "addr:postcode":"73401",
    "addr:street":"Holly St",
    "iso:country":"US",
    "sg:address":"1200 Holly St",
    "sg:city":"Ardmore",
    "sg:classifiers":[
        {
            "category":"Professional",
            "type":"Services"
        }
    ],
    "sg:phone":"+1 580 226 5549",
    "sg:postcode":"73401",
    "sg:province":"OK",
    "wof:name":"Mark Silverman",
    "wof:placetype":"venue"
},
  "geometry": {"coordinates":[-97.14816999999999,34.157871],"type":"Point"}
}