{
  "type": "Feature",
  "properties": {
    "addr:full":"8359 N Rockwell Ave Oklahoma City OK 73132",
    "addr:housenumber":"8359",
    "addr:postcode":"73132",
    "addr:street":"N Rockwell Ave",
    "iso:country":"US",
    "sg:address":"8359 N Rockwell Ave",
    "sg:city":"Oklahoma City",
    "sg:classifiers":[
        {
            "category":"Personal",
            "subcategory":"Beauty Salon",
            "type":"Services"
        }
    ],
    "sg:phone":"+1 405 720 9944",
    "sg:postcode":"73132",
    "sg:province":"OK",
    "wof:name":"Hair It Is",
    "wof:placetype":"venue"
},
  "geometry": {"coordinates":[-97.63847699999999,35.55664],"type":"Point"}
}