{
  "type": "Feature",
  "properties": {
    "iso:country":"US",
    "sg:address":"5116 N Macarthur Blvd",
    "sg:city":"Warr Acres",
    "sg:classifiers":[
        {
            "category":"Shopping",
            "subcategory":"Clothing, Apparel, & Fashions",
            "type":"Retail Goods"
        }
    ],
    "sg:phone":"+1 405 787 1155",
    "sg:postcode":"73122",
    "sg:province":"OK",
    "wof:name":"India Boutique",
    "wof:placetype":"venue"
},
  "geometry": {"coordinates":[-97.618897,35.523442],"type":"Point"}
}