{
  "type": "Feature",
  "properties": {
    "addr:full":"202 S Broadway St Walters OK 73572",
    "addr:housenumber":"202",
    "addr:postcode":"73572",
    "addr:street":"S Broadway St",
    "iso:country":"US",
    "sg:address":"202 S Broadway St",
    "sg:city":"Walters",
    "sg:classifiers":[
        {
            "category":"Retail",
            "subcategory":"Auto Repair",
            "type":"Services"
        },
        {
            "category":"Retail",
            "subcategory":"Auto Rental",
            "type":"Services"
        }
    ],
    "sg:phone":"+1 580 875 2699",
    "sg:postcode":"73572",
    "sg:province":"OK",
    "sg:tags":[
        "repairing",
        "automobile",
        "passenger",
        "car"
    ],
    "wof:name":"Scooter's One Stop",
    "wof:placetype":"venue"
},
  "geometry": {"coordinates":[-98.309207,34.356868],"type":"Point"}
}