{
  "type": "Feature",
  "properties": {
    "addr:full":"6715 N May Ave Oklahoma City OK 73116",
    "addr:housenumber":"6715",
    "addr:postcode":"73116",
    "addr:street":"N May Ave",
    "iso:country":"US",
    "sg:address":"6715 N May Ave",
    "sg:city":"Oklahoma City",
    "sg:classifiers":[
        {
            "category":"Insurance",
            "subcategory":"Insurance Agent",
            "type":"Services"
        }
    ],
    "sg:phone":"+1 405 842 3311",
    "sg:postcode":"73116",
    "sg:province":"OK",
    "wof:name":"Central Insurance Inc",
    "wof:placetype":"venue"
},
  "geometry": {"coordinates":[-97.565759,35.539771],"type":"Point"}
}