{
  "type": "Feature",
  "properties": {
    "iso:country":"US",
    "sg:address":"6363 E 31st St",
    "sg:city":"Tulsa",
    "sg:classifiers":[
        {
            "category":"Organizations",
            "subcategory":"Labor Organization",
            "type":"Services"
        }
    ],
    "sg:phone":"+1 918 838 1225",
    "sg:postcode":"74135",
    "sg:province":"OK",
    "wof:name":"Oklahoma Operating Engineers",
    "wof:placetype":"venue"
},
  "geometry": {"coordinates":[-95.906549,36.118964],"type":"Point"}
}