{
  "type": "Feature",
  "properties": {
    "iso:country":"US",
    "sg:address":"2112 SW 29th St",
    "sg:city":"Oklahoma City",
    "sg:classifiers":[
        {
            "category":"Retail",
            "subcategory":"Auto Repair",
            "type":"Services"
        }
    ],
    "sg:phone":"+1 405 634 3606",
    "sg:postcode":"73119",
    "sg:province":"OK",
    "sg:tags":[
        "transmission"
    ],
    "wof:name":"Atco Transmissions",
    "wof:placetype":"venue"
},
  "geometry": {"coordinates":[-97.549404,35.435041],"type":"Point"}
}