{
  "type": "Feature",
  "properties": {
    "iso:country":"US",
    "sg:address":"115 Main St",
    "sg:city":"Boise City",
    "sg:classifiers":[
        {
            "category":"Autos & Motor Vehicles",
            "subcategory":"Fuel & Gas Station",
            "type":"Retail Goods"
        }
    ],
    "sg:phone":"+1 580 544 2441",
    "sg:postcode":"73933",
    "sg:province":"OK",
    "sg:tags":[
        "oil"
    ],
    "wof:name":"West Texas Gas",
    "wof:placetype":"venue"
},
  "geometry": {"coordinates":[-102.511635,36.729596],"type":"Point"}
}