{
  "type": "Feature",
  "properties": {
    "addr:full":"1722 S Carson Ave Tulsa OK 74119",
    "addr:housenumber":"1722",
    "addr:postcode":"74119",
    "addr:street":"S Carson Ave",
    "iso:country":"US",
    "sg:address":"1722 S Carson Ave",
    "sg:city":"Tulsa",
    "sg:classifiers":[
        {
            "category":"Building & Trades",
            "subcategory":"Cleaning & Sanitation",
            "type":"Services"
        }
    ],
    "sg:phone":"+1 918 582 4017",
    "sg:postcode":"74119",
    "sg:province":"OK",
    "sg:tags":[
        "maintenance"
    ],
    "wof:name":"Myriad Prperty Svcs Consulting",
    "wof:placetype":"venue"
},
  "geometry": {"coordinates":[-95.990758,36.137782],"type":"Point"}
}