{
  "type": "Feature",
  "properties": {
    "addr:full":"301 Indian Rd Idabel OK 74745",
    "addr:housenumber":"301",
    "addr:postcode":"74745",
    "addr:street":"Indian Rd",
    "iso:country":"US",
    "sg:address":"301 Indian Rd",
    "sg:city":"Idabel",
    "sg:classifiers":[
        {
            "category":"Retail",
            "subcategory":"Veterinary Services",
            "type":"Services"
        }
    ],
    "sg:phone":"+1 580 286 3764",
    "sg:postcode":"74745",
    "sg:province":"OK",
    "sg:tags":[
        "hospital",
        "animal"
    ],
    "wof:name":"Pet & Livestock Hospital",
    "wof:placetype":"venue"
},
  "geometry": {"coordinates":[-94.791777,33.897227],"type":"Point"}
}