{
  "type": "Feature",
  "properties": {
    "iso:country":"US",
    "sg:address":"1341 SW 25th St",
    "sg:city":"Oklahoma City",
    "sg:classifiers":[
        {
            "category":"Building & Trades",
            "subcategory":"Electrical",
            "type":"Services"
        }
    ],
    "sg:phone":"+1 405 632 7767",
    "sg:postcode":"73108",
    "sg:province":"OK",
    "sg:tags":[
        "electrical",
        "contractor"
    ],
    "wof:name":"Bell Electric",
    "wof:placetype":"venue"
},
  "geometry": {"coordinates":[-97.540486,35.439482],"type":"Point"}
}