{
  "type": "Feature",
  "properties": {
    "iso:country":"US",
    "sg:address":"3710 Oklahoma Ave",
    "sg:city":"Woodward",
    "sg:classifiers":[
        {
            "category":"Autos & Motor Vehicles",
            "subcategory":"Fuel & Gas Station",
            "type":"Retail Goods"
        }
    ],
    "sg:phone":"+1 580 256 2650",
    "sg:postcode":"73801",
    "sg:province":"OK",
    "sg:tags":[
        "plaza",
        "truck",
        "stops"
    ],
    "wof:name":"Hutch's 113",
    "wof:placetype":"venue"
},
  "geometry": {"coordinates":[-99.429225,36.433593],"type":"Point"}
}