{
  "type": "Feature",
  "properties": {
    "iso:country":"US",
    "sg:address":"2008 Mission Rd",
    "sg:city":"Edmond",
    "sg:phone":"+1 405 340 5077",
    "sg:postcode":"73034",
    "sg:province":"OK",
    "sg:tags":[
        "product",
        "petroleum"
    ],
    "wof:name":"Murphy Sj Oil Gas Inc",
    "wof:placetype":"venue"
},
  "geometry": {"coordinates":[-97.444856,35.676021],"type":"Point"}
}