{
  "type": "Feature",
  "properties": {
    "iso:country":"US",
    "sg:address":"325 Piedmont Rd N",
    "sg:city":"Piedmont",
    "sg:classifiers":[
        {
            "category":"Government",
            "subcategory":"Police Station",
            "type":"Public Place"
        }
    ],
    "sg:phone":"+1 405 373 1334",
    "sg:postcode":"73078",
    "sg:province":"OK",
    "sg:tags":[
        "department"
    ],
    "wof:name":"Piedmont Police Dept",
    "wof:placetype":"venue"
},
  "geometry": {"coordinates":[-97.745169,35.638444],"type":"Point"}
}