{
  "type": "Feature",
  "properties": {
    "iso:country":"US",
    "sg:address":"7 SW 17th St",
    "sg:city":"Lawton",
    "sg:classifiers":[
        {
            "category":"Utilities",
            "subcategory":"Telephone",
            "type":"Services"
        }
    ],
    "sg:phone":"+1 580 477 4495",
    "sg:postcode":"73501",
    "sg:province":"OK",
    "sg:tags":[
        "communications"
    ],
    "wof:name":"Southwestern Bell Telephone LP",
    "wof:placetype":"venue"
},
  "geometry": {"coordinates":[-98.413584,34.608134],"type":"Point"}
}