{
  "type": "Feature",
  "properties": {
    "iso:country":"US",
    "sg:address":"12654 E 86th Pl N",
    "sg:city":"Owasso",
    "sg:classifiers":[
        {
            "category":"Retail",
            "subcategory":"Portrait Studio",
            "type":"Services"
        }
    ],
    "sg:phone":"+1 918 376 9798",
    "sg:postcode":"74055",
    "sg:province":"OK",
    "sg:tags":[
        "photographer"
    ],
    "wof:name":"Colorview Portraits",
    "wof:placetype":"venue"
},
  "geometry": {"coordinates":[-95.832579,36.279439],"type":"Point"}
}