{
  "type": "Feature",
  "properties": {
    "iso:country":"US",
    "sg:address":"121 SW B Ave",
    "sg:city":"Lawton",
    "sg:classifiers":[
        {
            "category":"Shopping",
            "subcategory":"Bicycles & Sporting Goods",
            "type":"Retail Goods"
        }
    ],
    "sg:phone":"+1 580 695 9704",
    "sg:postcode":"73501",
    "sg:province":"OK",
    "sg:tags":[
        "gun",
        "gunsmith"
    ],
    "wof:name":"Ten-Ring Precision Gunsmithing",
    "wof:placetype":"venue"
},
  "geometry": {"coordinates":[-98.390151,34.606445],"type":"Point"}
}