{
  "type": "Feature",
  "properties": {
    "addr:full":"1114 W 41st St Tulsa OK 74107",
    "addr:housenumber":"1114",
    "addr:postcode":"74107",
    "addr:street":"W 41St St",
    "iso:country":"US",
    "sg:address":"1114 W 41st St",
    "sg:city":"Tulsa",
    "sg:classifiers":[
        {
            "category":"Autos & Motor Vehicles",
            "subcategory":"Auto Supplies",
            "type":"Retail Goods"
        },
        {
            "category":"Retail",
            "subcategory":"Auto Repair",
            "type":"Services"
        }
    ],
    "sg:phone":"+1 918 446 3019",
    "sg:postcode":"74107",
    "sg:province":"OK",
    "sg:tags":[
        "automobile",
        "equipment",
        "car",
        "performance",
        "sport",
        "racing"
    ],
    "sg:website":"http://www.fastchip.com",
    "wof:name":"Wright Ed Automotive",
    "wof:placetype":"venue"
},
  "geometry": {"coordinates":[-96.007192,36.104359],"type":"Point"}
}