{
  "type": "Feature",
  "properties": {
    "addr:full":"223 S Jardot Rd Stillwater OK 74074",
    "addr:housenumber":"223",
    "addr:postcode":"74074",
    "addr:street":"S Jardot Rd",
    "iso:country":"US",
    "sg:address":"223 S Jardot Rd",
    "sg:city":"Stillwater",
    "sg:classifiers":[
        {
            "category":"Professional",
            "subcategory":"Computer Services",
            "type":"Services"
        }
    ],
    "sg:phone":"+1 405 372 7308",
    "sg:postcode":"74074",
    "sg:province":"OK",
    "sg:tags":[
        "datum"
    ],
    "wof:name":"Fastpipe Media Inc",
    "wof:placetype":"venue"
},
  "geometry": {"coordinates":[-97.033529,36.121393],"type":"Point"}
}