{
  "type": "Feature",
  "properties": {
    "iso:country":"US",
    "sg:address":"208 Seminole",
    "sg:city":"Taft",
    "sg:classifiers":[
        {
            "category":"Organizations",
            "subcategory":"Religious Organization",
            "type":"Services"
        }
    ],
    "sg:phone":"+1 918 682 7297",
    "sg:postcode":"74463",
    "sg:province":"OK",
    "sg:tags":[
        "church"
    ],
    "wof:name":"Cummings-COLE CME",
    "wof:placetype":"venue"
},
  "geometry": {"coordinates":[-95.544865,35.761707],"type":"Point"}
}