{
  "type": "Feature",
  "properties": {
    "iso:country":"US",
    "sg:address":"17015 S Memorial Dr",
    "sg:city":"Bixby",
    "sg:classifiers":[
        {
            "category":"Organizations",
            "subcategory":"Religious Organization",
            "type":"Services"
        }
    ],
    "sg:phone":"+1 918 366 9216",
    "sg:postcode":"74008",
    "sg:province":"OK",
    "sg:tags":[
        "church"
    ],
    "wof:name":"Jehovah's Witnesses",
    "wof:placetype":"venue"
},
  "geometry": {"coordinates":[-95.886499,35.920305],"type":"Point"}
}