{
  "type": "Feature",
  "properties": {
    "addr:full":"3517 River Downs Dr Edmond OK 73034",
    "addr:housenumber":"3517",
    "addr:postcode":"73034",
    "addr:street":"River Downs Dr",
    "iso:country":"US",
    "sg:address":"3517 River Downs Dr",
    "sg:city":"Edmond",
    "sg:classifiers":[
        {
            "category":"Professional",
            "subcategory":"Business Services",
            "type":"Services"
        }
    ],
    "sg:phone":"+1 405 330 6816",
    "sg:postcode":"73034",
    "sg:province":"OK",
    "wof:name":"Marigold Group Partnership",
    "wof:placetype":"venue"
},
  "geometry": {"coordinates":[-97.45020599999999,35.69305],"type":"Point"}
}