{
  "type": "Feature",
  "properties": {
    "iso:country":"US",
    "sg:address":"206 SW 44th St",
    "sg:city":"Oklahoma City",
    "sg:classifiers":[
        {
            "category":"Personal",
            "subcategory":"Barber",
            "type":"Services"
        }
    ],
    "sg:phone":"+1 405 632 5456",
    "sg:postcode":"73109",
    "sg:province":"OK",
    "sg:tags":[
        "shop"
    ],
    "wof:name":"Golden Touch",
    "wof:placetype":"venue"
},
  "geometry": {"coordinates":[-97.516741,35.420669],"type":"Point"}
}