{
  "type": "Feature",
  "properties": {
    "iso:country":"US",
    "sg:address":"719 SE 29th St",
    "sg:city":"Oklahoma City",
    "sg:classifiers":[
        {
            "category":"Retail",
            "subcategory":"Auto Repair",
            "type":"Services"
        }
    ],
    "sg:phone":"+1 405 634 4401",
    "sg:postcode":"73129",
    "sg:province":"OK",
    "sg:tags":[
        "repairing",
        "automotive",
        "automobile"
    ],
    "wof:name":"Walls Les Wheel Aligning",
    "wof:placetype":"venue"
},
  "geometry": {"coordinates":[-97.497312,35.435383],"type":"Point"}
}