{
  "type": "Feature",
  "properties": {
    "addr:full":"5590 S Garnett Rd Tulsa OK 74146",
    "addr:housenumber":"5590",
    "addr:postcode":"74146",
    "addr:street":"S Garnett Rd",
    "iso:country":"US",
    "sg:address":"5590 S Garnett Rd",
    "sg:city":"Tulsa",
    "sg:classifiers":[
        {
            "category":"Coffee & Tea",
            "type":"Food & Drink"
        },
        {
            "category":"Bakery",
            "type":"Food & Drink"
        },
        {
            "category":"Donuts",
            "type":"Food & Drink"
        }
    ],
    "sg:menulink":"http://www.allmenus.com/ok/tulsa/231126-daylight-donuts/menu/",
    "sg:phone":"+1 918 294 0007",
    "sg:postcode":"74146",
    "sg:province":"OK",
    "sg:tags":[
        "american",
        "pastry"
    ],
    "wof:name":"Daylight Donuts",
    "wof:placetype":"venue"
},
  "geometry": {"coordinates":[-95.851519,36.082084],"type":"Point"}
}