{
  "type": "Feature",
  "properties": {
    "addr:full":"67501 E 100 Rd Wyandotte OK 74370",
    "addr:housenumber":"67501",
    "addr:postcode":"74370",
    "addr:street":"E 100 Rd",
    "iso:country":"US",
    "sg:address":"67501 E 100 Rd",
    "sg:city":"Wyandotte",
    "sg:classifiers":[
        {
            "category":"Building & Trades",
            "subcategory":"Electrical",
            "type":"Services"
        }
    ],
    "sg:phone":"+1 918 666 3259",
    "sg:postcode":"74370",
    "sg:province":"OK",
    "sg:tags":[
        "electrician"
    ],
    "wof:name":"Cline's Electric Heating & A/C",
    "wof:placetype":"venue"
},
  "geometry": {"coordinates":[-94.629677,36.869068],"type":"Point"}
}