{
  "type": "Feature",
  "properties": {
    "iso:country":"US",
    "sg:address":"636 SW 59th St",
    "sg:city":"Oklahoma City",
    "sg:classifiers":[
        {
            "category":"Manufacturing",
            "subcategory":"Printing",
            "type":"Manufacturing & Wholesale Goods"
        }
    ],
    "sg:phone":"+1 405 636 0400",
    "sg:postcode":"73109",
    "sg:province":"OK",
    "sg:tags":[
        "printer"
    ],
    "wof:name":"C J Graphics",
    "wof:placetype":"venue"
},
  "geometry": {"coordinates":[-97.524491,35.406149],"type":"Point"}
}