{
  "type": "Feature",
  "properties": {
    "iso:country":"US",
    "sg:address":"913 W Utica St",
    "sg:city":"Broken Arrow",
    "sg:classifiers":[
        {
            "category":"Building & Trades",
            "subcategory":"Construction",
            "type":"Services"
        }
    ],
    "sg:phone":"+1 918 455 8855",
    "sg:postcode":"74011",
    "sg:province":"OK",
    "sg:tags":[
        "contractor"
    ],
    "wof:name":"R E S Drywall",
    "wof:placetype":"venue"
},
  "geometry": {"coordinates":[-95.80031200000001,36.010652],"type":"Point"}
}