{
  "type": "Feature",
  "properties": {
    "iso:country":"US",
    "sg:address":"9977 E 330 Rd",
    "sg:city":"Talala",
    "sg:classifiers":[
        {
            "category":"Building & Trades",
            "subcategory":"Construction",
            "type":"Services"
        }
    ],
    "sg:phone":"+1 918 275 4293",
    "sg:postcode":"74080",
    "sg:province":"OK",
    "sg:tags":[
        "excavating",
        "contractor"
    ],
    "wof:name":"Stanford Backhoe Svc",
    "wof:placetype":"venue"
},
  "geometry": {"coordinates":[-95.65488000000001,36.539296],"type":"Point"}
}