{
  "type": "Feature",
  "properties": {
    "iso:country":"US",
    "sg:address":"15296 Pheasant Run",
    "sg:city":"Choctaw",
    "sg:classifiers":[
        {
            "category":"Wholesale",
            "subcategory":"Machinery & Supplies",
            "type":"Manufacturing & Wholesale Goods"
        }
    ],
    "sg:phone":"+1 405 390 4142",
    "sg:postcode":"73020",
    "sg:province":"OK",
    "sg:tags":[
        "equipment",
        "industrial"
    ],
    "wof:name":"Better Power Wash A",
    "wof:placetype":"venue"
},
  "geometry": {"coordinates":[-97.2574,35.459643],"type":"Point"}
}