{
  "type": "Feature",
  "properties": {
    "iso:country":"US",
    "sg:address":"4710 N Grove Ave",
    "sg:city":"Warr Acres",
    "sg:classifiers":[
        {
            "category":"Wholesale",
            "subcategory":"Metals & Minerals",
            "type":"Manufacturing & Wholesale Goods"
        }
    ],
    "sg:phone":"+1 405 787 8009",
    "sg:postcode":"73122",
    "sg:province":"OK",
    "sg:tags":[
        "steel",
        "warehouse"
    ],
    "wof:name":"Collins Metal Co",
    "wof:placetype":"venue"
},
  "geometry": {"coordinates":[-97.614462,35.518906],"type":"Point"}
}