{
  "type": "Feature",
  "properties": {
    "iso:country":"US",
    "sg:address":"1302 E Central Blvd",
    "sg:city":"Ada",
    "sg:classifiers":[
        {
            "category":"Building & Trades",
            "subcategory":"Construction",
            "type":"Services"
        }
    ],
    "sg:phone":"+1 580 332 9142",
    "sg:postcode":"74820",
    "sg:province":"OK",
    "sg:tags":[
        "general",
        "contractor"
    ],
    "wof:name":"Winters Construction Co",
    "wof:placetype":"venue"
},
  "geometry": {"coordinates":[-96.66176,34.765413],"type":"Point"}
}