{
  "type": "Feature",
  "properties": {
    "addr:full":"4000 W Indian Hills Rd Norman OK 73072",
    "addr:housenumber":"4000",
    "addr:postcode":"73072",
    "addr:street":"W Indian Hills Rd",
    "iso:country":"US",
    "sg:address":"4000 W Indian Hills Rd",
    "sg:city":"Norman",
    "sg:classifiers":[
        {
            "category":"Professional",
            "subcategory":"Advertising",
            "type":"Services"
        }
    ],
    "sg:phone":"+1 405 360 7000",
    "sg:postcode":"73072",
    "sg:province":"OK",
    "wof:name":"WWLS",
    "wof:placetype":"venue"
},
  "geometry": {"coordinates":[-97.504458,35.290694],"type":"Point"}
}