{
  "type": "Feature",
  "properties": {
    "addr:full":"921 NE 12th St Oklahoma City OK 73160",
    "addr:housenumber":"921",
    "addr:postcode":"73160",
    "addr:street":"Ne 12Th St",
    "iso:country":"US",
    "sg:address":"921 NE 12th St",
    "sg:city":"Oklahoma City",
    "sg:classifiers":[
        {
            "category":"Real Estate",
            "subcategory":"Developer",
            "type":"Services"
        }
    ],
    "sg:phone":"+1 405 759 3374",
    "sg:postcode":"73160",
    "sg:province":"OK",
    "wof:name":"O L Inc",
    "wof:placetype":"venue"
},
  "geometry": {"coordinates":[-97.475133,35.348842],"type":"Point"}
}