{
  "type": "Feature",
  "properties": {
    "addr:full":"1203 W Summit Ave Ponca City OK 74601",
    "addr:housenumber":"1203",
    "addr:postcode":"74601",
    "addr:street":"W Summit Ave",
    "iso:country":"US",
    "sg:address":"1203 W Summit Ave",
    "sg:city":"Ponca City",
    "sg:classifiers":[
        {
            "category":"Farming",
            "subcategory":"Dairy Farm",
            "type":"Manufacturing & Wholesale Goods"
        }
    ],
    "sg:phone":"+1 580 762 1606",
    "sg:postcode":"74601",
    "sg:province":"OK",
    "wof:name":"Hiland Dairy Co",
    "wof:placetype":"venue"
},
  "geometry": {"coordinates":[-97.10322499999999,36.711737],"type":"Point"}
}