{
  "type": "Feature",
  "properties": {
    "iso:country":"US",
    "sg:address":"3405 E 66th Pl",
    "sg:city":"Tulsa",
    "sg:classifiers":[
        {
            "category":"Professional",
            "subcategory":"Business Services",
            "type":"Services"
        }
    ],
    "sg:phone":"+1 918 523 9997",
    "sg:postcode":"74136",
    "sg:province":"OK",
    "wof:name":"Southern Contract Interiors",
    "wof:placetype":"venue"
},
  "geometry": {"coordinates":[-95.938593,36.067607],"type":"Point"}
}