{
  "type": "Feature",
  "properties": {
    "addr:full":"1937 County Rd Verden OK 73045",
    "addr:housenumber":"1937",
    "addr:postcode":"73045",
    "addr:street":"County Rd",
    "iso:country":"US",
    "sg:address":"1937 County Rd",
    "sg:city":"Verden",
    "sg:classifiers":[
        {
            "category":"Shopping",
            "subcategory":"Gifts & Souvenirs",
            "type":"Retail Goods"
        }
    ],
    "sg:phone":"+1 405 222 1663",
    "sg:postcode":"73045",
    "sg:province":"OK",
    "wof:name":"Straight From Heart",
    "wof:placetype":"venue"
},
  "geometry": {"coordinates":[-97.15911800000001,35.488494],"type":"Point"}
}