{
  "type": "Feature",
  "properties": {
    "iso:country":"US",
    "sg:address":"125 Park Ave",
    "sg:city":"Oklahoma City",
    "sg:classifiers":[
        {
            "category":"Insurance",
            "subcategory":"Insurance Agent",
            "type":"Services"
        }
    ],
    "sg:phone":"+1 405 232 2177",
    "sg:postcode":"73102",
    "sg:province":"OK",
    "wof:name":"Benchmark Insurance Company",
    "wof:placetype":"venue"
},
  "geometry": {"coordinates":[-97.515942,35.468873],"type":"Point"}
}