{
  "type": "Feature",
  "properties": {
    "iso:country":"US",
    "sg:address":"9600 State Hwy 33",
    "sg:city":"Guthrie",
    "sg:classifiers":[
        {
            "category":"Shopping",
            "subcategory":"Used Merchandise",
            "type":"Retail Goods"
        }
    ],
    "sg:phone":"+1 405 282 4241",
    "sg:postcode":"73044",
    "sg:province":"OK",
    "sg:tags":[
        "antique"
    ],
    "wof:name":"Pleasant Valley Farms Trading",
    "wof:placetype":"venue"
},
  "geometry": {"coordinates":[-97.545062,35.871277],"type":"Point"}
}