{
  "type": "Feature",
  "properties": {
    "addr:full":"2601 Boxwood Ave Norman OK 73072",
    "addr:housenumber":"2601",
    "addr:postcode":"73072",
    "addr:street":"Boxwood Ave",
    "iso:country":"US",
    "sg:address":"2601 Boxwood Ave",
    "sg:city":"Norman",
    "sg:classifiers":[
        {
            "category":"Professional",
            "subcategory":"Lawyer & Legal Services",
            "type":"Services"
        }
    ],
    "sg:phone":"+1 405 321 4544",
    "sg:postcode":"73072",
    "sg:province":"OK",
    "wof:name":"Jack R Green",
    "wof:placetype":"venue"
},
  "geometry": {"coordinates":[-97.462324,35.193273],"type":"Point"}
}