{
  "type": "Feature",
  "properties": {
    "iso:country":"US",
    "sg:address":"1800 E 161st St S",
    "sg:city":"Bixby",
    "sg:classifiers":[
        {
            "category":"Building & Trades",
            "subcategory":"Construction",
            "type":"Services"
        }
    ],
    "sg:phone":"+1 918 742 5218",
    "sg:postcode":"74008",
    "sg:province":"OK",
    "sg:tags":[
        "contractor"
    ],
    "wof:name":"Jacob Graybill",
    "wof:placetype":"venue"
},
  "geometry": {"coordinates":[-95.958905,35.930144],"type":"Point"}
}