{
  "type": "Feature",
  "properties": {
    "iso:country":"US",
    "sg:address":"1508 SW 136th St",
    "sg:city":"Oklahoma City",
    "sg:classifiers":[
        {
            "category":"Building & Trades",
            "subcategory":"Construction",
            "type":"Services"
        }
    ],
    "sg:phone":"+1 405 275 3555",
    "sg:postcode":"73170",
    "sg:province":"OK",
    "sg:tags":[
        "home",
        "builder"
    ],
    "wof:name":"Prestige Home Builders Inc",
    "wof:placetype":"venue"
},
  "geometry": {"coordinates":[-97.542266,35.332555],"type":"Point"}
}