{
  "type": "Feature",
  "properties": {
    "addr:full":"1050 Ed Noble Pkwy Norman OK 73072",
    "addr:housenumber":"1050",
    "addr:postcode":"73072",
    "addr:street":"Ed Noble Pkwy",
    "iso:country":"US",
    "sg:address":"1050 Ed Noble Pkwy",
    "sg:city":"Norman",
    "sg:classifiers":[
        {
            "category":"Restaurant",
            "type":"Food & Drink"
        }
    ],
    "sg:menulink":"http://www.allmenus.com/ok/norman/8807-red-robin/menu/",
    "sg:phone":"+1 405 321 0440",
    "sg:postcode":"73072",
    "sg:province":"OK",
    "sg:tags":[
        "american"
    ],
    "wof:name":"Red Robin",
    "wof:placetype":"venue"
},
  "geometry": {"coordinates":[-97.48299900000001,35.205354],"type":"Point"}
}