{
  "type": "Feature",
  "properties": {
    "iso:country":"US",
    "sg:address":"1901 S Garnett Rd",
    "sg:city":"Tulsa",
    "sg:classifiers":[
        {
            "category":"Organizations",
            "subcategory":"Membership Organization",
            "type":"Services"
        }
    ],
    "sg:phone":"+1 918 438 1440",
    "sg:postcode":"74128",
    "sg:province":"OK",
    "wof:name":"Okla Farm Bur Dist Claims Ofc",
    "wof:placetype":"venue"
},
  "geometry": {"coordinates":[-95.851038,36.13697],"type":"Point"}
}