{
  "type": "Feature",
  "properties": {
    "iso:country":"US",
    "sg:address":"17615 E Memorial Rd",
    "sg:city":"Luther",
    "sg:classifiers":[
        {
            "category":"Building & Trades",
            "subcategory":"Electrical",
            "type":"Services"
        }
    ],
    "sg:phone":"+1 405 341 6992",
    "sg:postcode":"73054",
    "sg:province":"OK",
    "sg:tags":[
        "electrical",
        "contractor"
    ],
    "wof:name":"State Electrical Contractors",
    "wof:placetype":"venue"
},
  "geometry": {"coordinates":[-97.216785,35.608849],"type":"Point"}
}