{
  "type": "Feature",
  "properties": {
    "iso:country":"US",
    "sg:address":"1004 N Lincoln Ave",
    "sg:city":"Sand Springs",
    "sg:classifiers":[
        {
            "category":"Home & Garden",
            "subcategory":"Building Materials",
            "type":"Retail Goods"
        }
    ],
    "sg:phone":"+1 918 698 3454",
    "sg:postcode":"74063",
    "sg:province":"OK",
    "sg:tags":[
        "type",
        "door"
    ],
    "wof:name":"Affordable Garage Doors",
    "wof:placetype":"venue"
},
  "geometry": {"coordinates":[-96.107742,36.148246],"type":"Point"}
}