{
  "type": "Feature",
  "properties": {
    "iso:country":"US",
    "sg:address":"1330 E 71st St",
    "sg:city":"Tulsa",
    "sg:classifiers":[
        {
            "category":"Restaurant",
            "type":"Food & Drink"
        }
    ],
    "sg:phone":"+1 918 492 6888",
    "sg:postcode":"74136",
    "sg:province":"OK",
    "wof:name":"China King",
    "wof:placetype":"venue"
},
  "geometry": {"coordinates":[-95.975266,36.060599],"type":"Point"}
}