{
  "type": "Feature",
  "properties": {
    "addr:full":"202 Petty Ln Clinton OK 73601",
    "addr:housenumber":"202",
    "addr:postcode":"73601",
    "addr:street":"Petty Ln",
    "iso:country":"US",
    "sg:address":"202 Petty Ln",
    "sg:city":"Clinton",
    "sg:classifiers":[
        {
            "category":"Building & Trades",
            "subcategory":"Construction",
            "type":"Services"
        }
    ],
    "sg:phone":"+1 580 323 3100",
    "sg:postcode":"73601",
    "sg:province":"OK",
    "sg:tags":[
        "roofing",
        "contractor"
    ],
    "wof:name":"Orville Locklear Roofing Co",
    "wof:placetype":"venue"
},
  "geometry": {"coordinates":[-98.979834,35.486953],"type":"Point"}
}