{
  "type": "Feature",
  "properties": {
    "addr:full":"1601 N Peoria Ave Tulsa OK 74106",
    "addr:housenumber":"1601",
    "addr:postcode":"74106",
    "addr:street":"N Peoria Ave",
    "iso:country":"US",
    "sg:address":"1601 N Peoria Ave",
    "sg:city":"Tulsa",
    "sg:classifiers":[
        {
            "category":"Restaurant",
            "type":"Food & Drink"
        }
    ],
    "sg:menulink":"http://www.allmenus.com/ok/tulsa/106956-soup-man/menu/",
    "sg:phone":"+1 918 582 5990",
    "sg:postcode":"74106",
    "sg:province":"OK",
    "sg:tags":[
        "soup",
        "american",
        "salad"
    ],
    "wof:name":"Soup Man",
    "wof:placetype":"venue"
},
  "geometry": {"coordinates":[-95.97435900000001,36.178874],"type":"Point"}
}