{
  "type": "Feature",
  "properties": {
    "iso:country":"US",
    "sg:address":"213 N Main St",
    "sg:city":"Fairfax",
    "sg:classifiers":[
        {
            "category":"Food & Beverages",
            "subcategory":"Groceries & Convenience Stores",
            "type":"Retail Goods"
        }
    ],
    "sg:phone":"+1 918 642 5015",
    "sg:postcode":"74637",
    "sg:province":"OK",
    "sg:tags":[
        "grocer"
    ],
    "wof:name":"Palace Affiliated Grocery",
    "wof:placetype":"venue"
},
  "geometry": {"coordinates":[-96.704402,36.573269],"type":"Point"}
}