{
  "type": "Feature",
  "properties": {
    "iso:country":"US",
    "sg:address":"12121 E 51st St",
    "sg:city":"Tulsa",
    "sg:classifiers":[
        {
            "category":"Health Services",
            "subcategory":"Nursing And Care Facility",
            "type":"Services"
        }
    ],
    "sg:phone":"+1 918 250 7051",
    "sg:postcode":"74146",
    "sg:province":"OK",
    "sg:tags":[
        "home",
        "convalescent"
    ],
    "wof:name":"Care Source",
    "wof:placetype":"venue"
},
  "geometry": {"coordinates":[-95.843017,36.090035],"type":"Point"}
}