{
  "type": "Feature",
  "properties": {
    "iso:country":"US",
    "sg:address":"101 N Porter Ave",
    "sg:city":"Norman",
    "sg:classifiers":[
        {
            "category":"Food & Beverages",
            "subcategory":"Groceries & Convenience Stores",
            "type":"Retail Goods"
        }
    ],
    "sg:phone":"+1 405 292 2276",
    "sg:postcode":"73071",
    "sg:province":"OK",
    "wof:name":"Sooner Food Mart",
    "wof:placetype":"venue"
},
  "geometry": {"coordinates":[-97.43974300000001,35.223656],"type":"Point"}
}