{
  "type": "Feature",
  "properties": {
    "addr:full":"410 S Dewey Ave Wagoner OK 74467",
    "addr:housenumber":"410",
    "addr:postcode":"74467",
    "addr:street":"S Dewey Ave",
    "iso:country":"US",
    "sg:address":"410 S Dewey Ave",
    "sg:city":"Wagoner",
    "sg:classifiers":[
        {
            "category":"Utilities",
            "subcategory":"Mobile Phone",
            "type":"Services"
        }
    ],
    "sg:phone":"+1 918 485 1984",
    "sg:postcode":"74467",
    "sg:province":"OK",
    "sg:tags":[
        "telephone",
        "cellular"
    ],
    "wof:name":"US Cellular",
    "wof:placetype":"venue"
},
  "geometry": {"coordinates":[-95.395214,35.957493],"type":"Point"}
}