{
  "type": "Feature",
  "properties": {
    "iso:country":"US",
    "sg:address":"2708 NW 119th St",
    "sg:city":"Oklahoma City",
    "sg:classifiers":[
        {
            "category":"Professional",
            "subcategory":"Lawyer & Legal Services",
            "type":"Services"
        }
    ],
    "sg:phone":"+1 405 755 0097",
    "sg:postcode":"73120",
    "sg:province":"OK",
    "wof:name":"Murphy Linda Williams",
    "wof:placetype":"venue"
},
  "geometry": {"coordinates":[-97.564587,35.591205],"type":"Point"}
}