{
  "type": "Feature",
  "properties": {
    "addr:full":"2 SW C Ave Lawton OK 73501",
    "addr:housenumber":"2",
    "addr:postcode":"73501",
    "addr:street":"Sw C Ave",
    "iso:country":"US",
    "sg:address":"2 SW C Ave",
    "sg:city":"Lawton",
    "sg:classifiers":[
        {
            "category":"Freight",
            "type":"Transportation"
        }
    ],
    "sg:phone":"+1 580 351 2929",
    "sg:postcode":"73501",
    "sg:province":"OK",
    "sg:tags":[
        "disposal",
        "garbage",
        "collection"
    ],
    "wof:name":"Speedaway Containers",
    "wof:placetype":"venue"
},
  "geometry": {"coordinates":[-98.388756,34.605227],"type":"Point"}
}