{
  "type": "Feature",
  "properties": {
    "addr:full":"1014 NW 1st St Oklahoma City OK 73106",
    "addr:housenumber":"1014",
    "addr:postcode":"73106",
    "addr:street":"Nw 1St St",
    "iso:country":"US",
    "sg:address":"1014 NW 1st St",
    "sg:city":"Oklahoma City",
    "sg:classifiers":[
        {
            "category":"Shopping",
            "subcategory":"Clothing, Apparel, & Fashions",
            "type":"Retail Goods"
        }
    ],
    "sg:phone":"+1 405 239 7547",
    "sg:postcode":"73106",
    "sg:province":"OK",
    "sg:tags":[
        "spec",
        "mfg"
    ],
    "wof:name":"Skis Tees",
    "wof:placetype":"venue"
},
  "geometry": {"coordinates":[-97.53005400000001,35.468827],"type":"Point"}
}