{
  "type": "Feature",
  "properties": {
    "iso:country":"US",
    "sg:address":"702 N Porter Ave",
    "sg:city":"Norman",
    "sg:classifiers":[
        {
            "category":"Restaurant",
            "type":"Food & Drink"
        }
    ],
    "sg:phone":"+1 405 360 8070",
    "sg:postcode":"73071",
    "sg:province":"OK",
    "wof:name":"Tarahumara's Mexican Cafe",
    "wof:placetype":"venue"
},
  "geometry": {"coordinates":[-97.441162,35.228162],"type":"Point"}
}