{
  "type": "Feature",
  "properties": {
    "iso:country":"US",
    "sg:address":"2 W 2nd St",
    "sg:city":"Tulsa",
    "sg:classifiers":[
        {
            "category":"Mining & Drilling",
            "type":"Manufacturing & Wholesale Goods"
        }
    ],
    "sg:phone":"+1 918 583 1791",
    "sg:postcode":"74103",
    "sg:province":"OK",
    "sg:tags":[
        "oil",
        "producer",
        "gas",
        "production",
        "exploration",
        "marketer"
    ],
    "sg:website":"www.samsonind.com",
    "wof:name":"Samson Investment Company",
    "wof:placetype":"venue"
},
  "geometry": {"coordinates":[-95.99279199999999,36.15399],"type":"Point"}
}