{
  "type": "Feature",
  "properties": {
    "iso:country":"US",
    "sg:address":"10209 141st Ave NE",
    "sg:city":"Newalla",
    "sg:classifiers":[
        {
            "category":"Manufacturing",
            "subcategory":"Motor Vehicles & Parts",
            "type":"Manufacturing & Wholesale Goods"
        }
    ],
    "sg:phone":"+1 405 386 3171",
    "sg:postcode":"74857",
    "sg:province":"OK",
    "sg:tags":[
        "body",
        "mfg"
    ],
    "wof:name":"Responsible Breeders",
    "wof:placetype":"venue"
},
  "geometry": {"coordinates":[-97.236876,35.33889],"type":"Point"}
}