{
  "type": "Feature",
  "properties": {
    "iso:country":"US",
    "sg:address":"1248 S Marion Ave",
    "sg:city":"Tulsa",
    "sg:classifiers":[
        {
            "category":"Arts & Performance",
            "subcategory":"Theater",
            "type":"Entertainment"
        }
    ],
    "sg:phone":"+1 918 857 9154",
    "sg:postcode":"74112",
    "sg:province":"OK",
    "wof:name":"Theatre Club",
    "wof:placetype":"venue"
},
  "geometry": {"coordinates":[-95.934855,36.1462],"type":"Point"}
}