{
  "type": "Feature",
  "properties": {
    "addr:full":"113 N Dean A McGee Ave Wynnewood OK 73098",
    "addr:housenumber":"113",
    "addr:postcode":"73098",
    "addr:street":"N Dean A Mcgee Ave",
    "iso:country":"US",
    "sg:address":"113 N Dean A McGee Ave",
    "sg:city":"Wynnewood",
    "sg:classifiers":[
        {
            "category":"Restaurant",
            "type":"Food & Drink"
        }
    ],
    "sg:phone":"+1 405 665 9250",
    "sg:postcode":"73098",
    "sg:province":"OK",
    "sg:tags":[
        "cafe"
    ],
    "wof:name":"Ma's Bakery & Cafe",
    "wof:placetype":"venue"
},
  "geometry": {"coordinates":[-97.17045299999999,34.643579],"type":"Point"}
}