{
  "type": "Feature",
  "properties": {
    "iso:country":"US",
    "sg:address":"202 D St NE",
    "sg:city":"Miami",
    "sg:classifiers":[
        {
            "category":"Real Estate",
            "subcategory":"Real Estate Agent",
            "type":"Services"
        }
    ],
    "sg:phone":"+1 918 542 8175",
    "sg:postcode":"74354",
    "sg:province":"OK",
    "wof:name":"Modoc Tribes",
    "wof:placetype":"venue"
},
  "geometry": {"coordinates":[-94.873305,36.878993],"type":"Point"}
}