{
  "type": "Feature",
  "properties": {
    "iso:country":"US",
    "sg:address":"5716 Industrial Blvd",
    "sg:city":"Edmond",
    "sg:classifiers":[
        {
            "category":"Retail",
            "subcategory":"Auto Repair",
            "type":"Services"
        }
    ],
    "sg:phone":"+1 405 348 7759",
    "sg:postcode":"73034",
    "sg:province":"OK",
    "sg:tags":[
        "body",
        "automobile",
        "used",
        "painting"
    ],
    "wof:name":"Stout's Body Shop",
    "wof:placetype":"venue"
},
  "geometry": {"coordinates":[-97.415753,35.715435],"type":"Point"}
}