{
  "type": "Feature",
  "properties": {
    "addr:full":"2105 S Division St Guthrie OK 73044",
    "addr:housenumber":"2105",
    "addr:postcode":"73044",
    "addr:street":"S Division St",
    "iso:country":"US",
    "sg:address":"2105 S Division St",
    "sg:city":"Guthrie",
    "sg:classifiers":[
        {
            "category":"Insurance",
            "subcategory":"Insurance Agent",
            "type":"Services"
        }
    ],
    "sg:phone":"+1 405 282 0519",
    "sg:postcode":"73044",
    "sg:province":"OK",
    "wof:name":"Allstate Insurance",
    "wof:placetype":"venue"
},
  "geometry": {"coordinates":[-97.425483,35.858144],"type":"Point"}
}