{
  "type": "Feature",
  "properties": {
    "addr:full":"2124 E 60th Ct Tulsa OK 74105",
    "addr:housenumber":"2124",
    "addr:postcode":"74105",
    "addr:street":"E 60Th Ct",
    "iso:country":"US",
    "sg:address":"2124 E 60th Ct",
    "sg:city":"Tulsa",
    "sg:classifiers":[
        {
            "category":"Food & Beverages",
            "subcategory":"Specialty",
            "type":"Retail Goods"
        }
    ],
    "sg:phone":"+1 918 742 6689",
    "sg:postcode":"74105",
    "sg:province":"OK",
    "wof:name":"Quota International Inc",
    "wof:placetype":"venue"
},
  "geometry": {"coordinates":[-95.960613,36.076468],"type":"Point"}
}