{
  "type": "Feature",
  "properties": {
    "iso:country":"US",
    "sg:address":"119 9th St",
    "sg:city":"Canute",
    "sg:classifiers":[
        {
            "category":"Travel",
            "subcategory":"Hotels & Motels",
            "type":"Entertainment"
        }
    ],
    "sg:phone":"+1 580 472 3141",
    "sg:postcode":"73626",
    "sg:province":"OK",
    "wof:name":"Sunset Inn",
    "wof:placetype":"venue"
},
  "geometry": {"coordinates":[-99.275854,35.420507],"type":"Point"}
}