{
  "type": "Feature",
  "properties": {
    "iso:country":"US",
    "sg:address":"725 E Memorial Rd",
    "sg:city":"Oklahoma City",
    "sg:classifiers":[
        {
            "category":"Retail",
            "subcategory":"Auto Rental",
            "type":"Services"
        }
    ],
    "sg:phone":"+1 405 751 7625",
    "sg:postcode":"73114",
    "sg:province":"OK",
    "sg:tags":[
        "renting",
        "automobile"
    ],
    "wof:name":"ABC Rent A Car",
    "wof:placetype":"venue"
},
  "geometry": {"coordinates":[-97.502278,35.609223],"type":"Point"}
}