{
  "type": "Feature",
  "properties": {
    "addr:full":"2343 E 71st St Tulsa OK 74136",
    "addr:housenumber":"2343",
    "addr:postcode":"74136",
    "addr:street":"E 71St St",
    "iso:country":"US",
    "sg:address":"2343 E 71st St",
    "sg:city":"Tulsa",
    "sg:classifiers":[
        {
            "category":"Deli",
            "type":"Food & Drink"
        }
    ],
    "sg:menulink":"http://www.allmenus.com/ok/tulsa/99736-schlotzskys/menu/",
    "sg:phone":"+1 918 496 4663",
    "sg:postcode":"74136",
    "sg:province":"OK",
    "sg:tags":[
        "wrap",
        "american",
        "sandwich",
        "pizza"
    ],
    "wof:name":"Schlotzsky's",
    "wof:placetype":"venue"
},
  "geometry": {"coordinates":[-95.958643,36.060896],"type":"Point"}
}