{
  "type": "Feature",
  "properties": {
    "iso:country":"US",
    "sg:address":"142 SE Morningside Ave",
    "sg:city":"Bartlesville",
    "sg:classifiers":[
        {
            "category":"Building & Trades",
            "subcategory":"Construction",
            "type":"Services"
        }
    ],
    "sg:phone":"+1 918 335 3925",
    "sg:postcode":"74006",
    "sg:province":"OK",
    "sg:tags":[
        "painter"
    ],
    "wof:name":"Under The Son",
    "wof:placetype":"venue"
},
  "geometry": {"coordinates":[-95.941948,36.756272],"type":"Point"}
}