{
  "type": "Feature",
  "properties": {
    "addr:full":"321 N Hartman Ave Cushing OK 74023",
    "addr:housenumber":"321",
    "addr:postcode":"74023",
    "addr:street":"N Hartman Ave",
    "iso:country":"US",
    "sg:address":"321 N Hartman Ave",
    "sg:city":"Cushing",
    "sg:classifiers":[
        {
            "category":"Organizations",
            "subcategory":"Religious Organization",
            "type":"Services"
        }
    ],
    "sg:phone":"+1 918 225 3941",
    "sg:postcode":"74023",
    "sg:province":"OK",
    "sg:tags":[
        "church"
    ],
    "wof:name":"Park Place Baptist Church",
    "wof:placetype":"venue"
},
  "geometry": {"coordinates":[-96.78335300000001,35.982361],"type":"Point"}
}