{
  "type": "Feature",
  "properties": {
    "iso:country":"US",
    "sg:address":"615 W Broadway St",
    "sg:city":"Ardmore",
    "sg:classifiers":[
        {
            "category":"Wholesale",
            "subcategory":"Machinery & Supplies",
            "type":"Manufacturing & Wholesale Goods"
        }
    ],
    "sg:phone":"+1 580 226 5083",
    "sg:postcode":"73401",
    "sg:province":"OK",
    "sg:tags":[
        "construction",
        "fastener",
        "industrial",
        "suppl",
        "threaded"
    ],
    "wof:name":"Fastenal Company",
    "wof:placetype":"venue"
},
  "geometry": {"coordinates":[-97.13529200000001,34.174933],"type":"Point"}
}