{
  "type": "Feature",
  "properties": {
    "iso:country":"US",
    "sg:address":"809 Main Ave",
    "sg:city":"Woodward",
    "sg:classifiers":[
        {
            "category":"Restaurant",
            "type":"Food & Drink"
        }
    ],
    "sg:phone":"+1 580 254 9788",
    "sg:postcode":"73801",
    "sg:province":"OK",
    "wof:name":"Heavenly Scents",
    "wof:placetype":"venue"
},
  "geometry": {"coordinates":[-99.390538,36.435873],"type":"Point"}
}