{
  "type": "Feature",
  "properties": {
    "addr:full":"2001 N Sioux Ave Claremore OK 74017",
    "addr:housenumber":"2001",
    "addr:postcode":"74017",
    "addr:street":"N Sioux Ave",
    "iso:country":"US",
    "sg:address":"2001 N Sioux Ave",
    "sg:city":"Claremore",
    "sg:classifiers":[
        {
            "category":"Education",
            "subcategory":"School",
            "type":"Public Place"
        }
    ],
    "sg:phone":"+1 918 341 5242",
    "sg:postcode":"74017",
    "sg:province":"OK",
    "sg:website":"www.claremore.k12.ok.us",
    "wof:name":"Roosa Elementary School",
    "wof:placetype":"venue"
},
  "geometry": {"coordinates":[-95.59684900000001,36.33273],"type":"Point"}
}