{
  "type": "Feature",
  "properties": {
    "iso:country":"US",
    "sg:address":"515 S Peoria Ave",
    "sg:city":"Tulsa",
    "sg:classifiers":[
        {
            "category":"Banks & Credit Unions",
            "subcategory":"Bank",
            "type":"Services"
        }
    ],
    "sg:phone":"+1 918 664 6000",
    "sg:postcode":"74120",
    "sg:province":"OK",
    "wof:name":"Oklahoma Central Credit Union",
    "wof:placetype":"venue"
},
  "geometry": {"coordinates":[-95.975537,36.154317],"type":"Point"}
}