{
  "type": "Feature",
  "properties": {
    "addr:full":"3604 N May Ave Oklahoma City OK 73112",
    "addr:housenumber":"3604",
    "addr:postcode":"73112",
    "addr:street":"N May Ave",
    "iso:country":"US",
    "sg:address":"3604 N May Ave",
    "sg:city":"Oklahoma City",
    "sg:classifiers":[
        {
            "category":"Restaurant",
            "type":"Food & Drink"
        }
    ],
    "sg:menulink":"http://www.allmenus.com/ok/oklahoma-city/224732-all-seasons-pizza--grill/menu/",
    "sg:phone":"+1 405 843 3344",
    "sg:postcode":"73112",
    "sg:province":"OK",
    "sg:tags":[
        "american"
    ],
    "wof:name":"All Seasons Pizza & Grill",
    "wof:placetype":"venue"
},
  "geometry": {"coordinates":[-97.565675,35.506229],"type":"Point"}
}