{
  "type": "Feature",
  "properties": {
    "addr:full":"900 E Britton Rd Oklahoma City OK 73114",
    "addr:housenumber":"900",
    "addr:postcode":"73114",
    "addr:street":"E Britton Rd",
    "iso:country":"US",
    "sg:address":"900 E Britton Rd",
    "sg:city":"Oklahoma City",
    "sg:classifiers":[
        {
            "category":"Retail",
            "subcategory":"Auto Repair",
            "type":"Services"
        }
    ],
    "sg:phone":"+1 405 478 0453",
    "sg:postcode":"73114",
    "sg:province":"OK",
    "sg:tags":[
        "repairing",
        "automobile"
    ],
    "wof:name":"Sebring Service Ctr",
    "wof:placetype":"venue"
},
  "geometry": {"coordinates":[-97.495921,35.565608],"type":"Point"}
}