{
  "type": "Feature",
  "properties": {
    "addr:full":"13161 S Memorial Dr Bixby OK 74008",
    "addr:housenumber":"13161",
    "addr:postcode":"74008",
    "addr:street":"S Memorial Dr",
    "iso:country":"US",
    "sg:address":"13161 S Memorial Dr",
    "sg:city":"Bixby",
    "sg:classifiers":[
        {
            "category":"Professional",
            "subcategory":"Management & Consulting",
            "type":"Services"
        }
    ],
    "sg:phone":"+1 918 369 6700",
    "sg:postcode":"74008",
    "sg:province":"OK",
    "sg:tags":[
        "consultant",
        "business"
    ],
    "wof:name":"Advance Financial Svc",
    "wof:placetype":"venue"
},
  "geometry": {"coordinates":[-95.886515,35.973055],"type":"Point"}
}