{
  "type": "Feature",
  "properties": {
    "addr:full":"3304 W Jones Rd El Reno OK 73014",
    "addr:housenumber":"3304",
    "addr:postcode":"73014",
    "addr:street":"W Jones Rd",
    "iso:country":"US",
    "sg:address":"3304 W Jones Rd",
    "sg:city":"El Reno",
    "sg:classifiers":[
        {
            "category":"Building & Trades",
            "subcategory":"Construction",
            "type":"Services"
        }
    ],
    "sg:phone":"+1 405 262 9394",
    "sg:postcode":"73014",
    "sg:province":"OK",
    "sg:tags":[
        "contractor"
    ],
    "wof:name":"Trishane Inc",
    "wof:placetype":"venue"
},
  "geometry": {"coordinates":[-97.97765699999999,35.551261],"type":"Point"}
}