{
  "type": "Feature",
  "properties": {
    "iso:country":"US",
    "sg:address":"209 E Main St",
    "sg:city":"Antlers",
    "sg:classifiers":[
        {
            "category":"Real Estate",
            "subcategory":"Real Estate Agent",
            "type":"Services"
        }
    ],
    "sg:phone":"+1 580 298 3347",
    "sg:postcode":"74523",
    "sg:province":"OK",
    "wof:name":"John H Cocke Real Estate Agcy",
    "wof:placetype":"venue"
},
  "geometry": {"coordinates":[-95.618161,34.23157],"type":"Point"}
}