{
  "type": "Feature",
  "properties": {
    "iso:country":"US",
    "sg:address":"201 N Broadway",
    "sg:city":"Marlow",
    "sg:classifiers":[
        {
            "category":"Shopping",
            "subcategory":"Pharmacy",
            "type":"Retail Goods"
        }
    ],
    "sg:phone":"+1 580 658 5634",
    "sg:postcode":"73055",
    "sg:province":"OK",
    "sg:tags":[
        "cards",
        "drug",
        "gift",
        "greeting"
    ],
    "wof:name":"Medicine Chest",
    "wof:placetype":"venue"
},
  "geometry": {"coordinates":[-97.957814,34.650017],"type":"Point"}
}