{
  "type": "Feature",
  "properties": {
    "addr:full":"510 S Ohio Ave Drumright OK 74030",
    "addr:housenumber":"510",
    "addr:postcode":"74030",
    "addr:street":"S Ohio Ave",
    "iso:country":"US",
    "sg:address":"510 S Ohio Ave",
    "sg:city":"Drumright",
    "sg:classifiers":[
        {
            "category":"Social Services",
            "type":"Services"
        }
    ],
    "sg:phone":"+1 918 352 9407",
    "sg:postcode":"74030",
    "sg:province":"OK",
    "sg:tags":[
        "executive"
    ],
    "wof:name":"Sodexho Marriott Senior Ntrtn",
    "wof:placetype":"venue"
},
  "geometry": {"coordinates":[-96.599799,35.985021],"type":"Point"}
}