{
  "type": "Feature",
  "properties": {
    "iso:country":"US",
    "sg:address":"5918 NW 45th St",
    "sg:city":"Oklahoma City",
    "sg:classifiers":[
        {
            "category":"Building & Trades",
            "subcategory":"Plumbing",
            "type":"Services"
        }
    ],
    "sg:phone":"+1 405 789 4476",
    "sg:postcode":"73122",
    "sg:province":"OK",
    "sg:tags":[
        "contractor"
    ],
    "wof:name":"Central Plumbing Service",
    "wof:placetype":"venue"
},
  "geometry": {"coordinates":[-97.619871,35.517367],"type":"Point"}
}