{
  "type": "Feature",
  "properties": {
    "addr:full":"2317 Buckhorn Dr Norman OK 73072",
    "addr:housenumber":"2317",
    "addr:postcode":"73072",
    "addr:street":"Buckhorn Dr",
    "iso:country":"US",
    "sg:address":"2317 Buckhorn Dr",
    "sg:city":"Norman",
    "sg:classifiers":[
        {
            "category":"Professional",
            "type":"Services"
        }
    ],
    "sg:phone":"+1 405 364 6631",
    "sg:postcode":"73072",
    "sg:province":"OK",
    "wof:name":"Ww Designs Inc",
    "wof:placetype":"venue"
},
  "geometry": {"coordinates":[-97.490194,35.245447],"type":"Point"}
}