{
  "type": "Feature",
  "properties": {
    "iso:country":"US",
    "sg:address":"9 N Central Ave",
    "sg:city":"Idabel",
    "sg:classifiers":[
        {
            "category":"Banks & Credit Unions",
            "subcategory":"Bank",
            "type":"Services"
        }
    ],
    "sg:phone":"+1 580 286 5562",
    "sg:postcode":"74745",
    "sg:province":"OK",
    "sg:tags":[
        "institution",
        "business"
    ],
    "wof:name":"Courtesy Loans",
    "wof:placetype":"venue"
},
  "geometry": {"coordinates":[-94.82793700000001,33.894865],"type":"Point"}
}