{
  "type": "Feature",
  "properties": {
    "iso:country":"US",
    "sg:address":"5811 E 79th Pl",
    "sg:city":"Tulsa",
    "sg:classifiers":[
        {
            "category":"Autos & Motor Vehicles",
            "subcategory":"Automobile Sales",
            "type":"Retail Goods"
        }
    ],
    "sg:phone":"+1 918 493 3148",
    "sg:postcode":"74136",
    "sg:province":"OK",
    "sg:tags":[
        "new",
        "car"
    ],
    "wof:name":"Ford Finds Inc",
    "wof:placetype":"venue"
},
  "geometry": {"coordinates":[-95.909418,36.048671],"type":"Point"}
}