{
  "type": "Feature",
  "properties": {
    "addr:full":"401 Main St Maysville OK 73057",
    "addr:housenumber":"401",
    "addr:postcode":"73057",
    "addr:street":"Main St",
    "iso:country":"US",
    "sg:address":"401 Main St",
    "sg:city":"Maysville",
    "sg:classifiers":[
        {
            "category":"Government",
            "subcategory":"Fire Station",
            "type":"Public Place"
        }
    ],
    "sg:phone":"+1 405 867 4447",
    "sg:postcode":"73057",
    "sg:province":"OK",
    "sg:tags":[
        "department"
    ],
    "wof:name":"Maysville Fire Dept",
    "wof:placetype":"venue"
},
  "geometry": {"coordinates":[-97.406584,34.817827],"type":"Point"}
}