{
  "type": "Feature",
  "properties": {
    "addr:full":"1913 Tiffany Dr Norman OK 73071",
    "addr:housenumber":"1913",
    "addr:postcode":"73071",
    "addr:street":"Tiffany Dr",
    "iso:country":"US",
    "sg:address":"1913 Tiffany Dr",
    "sg:city":"Norman",
    "sg:classifiers":[
        {
            "category":"Building & Trades",
            "subcategory":"Construction",
            "type":"Services"
        }
    ],
    "sg:phone":"+1 405 360 7917",
    "sg:postcode":"73071",
    "sg:province":"OK",
    "sg:tags":[
        "excavating",
        "contractor"
    ],
    "wof:name":"MKI Backhole Loader Svc",
    "wof:placetype":"venue"
},
  "geometry": {"coordinates":[-97.408642,35.195009],"type":"Point"}
}