{
  "type": "Feature",
  "properties": {
    "iso:country":"US",
    "sg:address":"3500 S Boulevard St",
    "sg:city":"Edmond",
    "sg:classifiers":[
        {
            "category":"Mining & Drilling",
            "type":"Manufacturing & Wholesale Goods"
        }
    ],
    "sg:phone":"+1 405 340 4300",
    "sg:postcode":"73013",
    "sg:province":"OK",
    "sg:tags":[
        "development",
        "gas",
        "oil",
        "exploration"
    ],
    "wof:name":"Midwestern Exploration Co",
    "wof:placetype":"venue"
},
  "geometry": {"coordinates":[-97.478145,35.620556],"type":"Point"}
}