{
  "type": "Feature",
  "properties": {
    "iso:country":"US",
    "sg:address":"2653 Bringham Rd",
    "sg:city":"Colbert",
    "sg:classifiers":[
        {
            "category":"Building & Trades",
            "subcategory":"Construction",
            "type":"Services"
        }
    ],
    "sg:phone":"+1 580 296 2607",
    "sg:postcode":"74733",
    "sg:province":"OK",
    "sg:tags":[
        "nonresidential"
    ],
    "wof:name":"Nunley Construction",
    "wof:placetype":"venue"
},
  "geometry": {"coordinates":[-96.500744,33.816582],"type":"Point"}
}