{
  "type": "Feature",
  "properties": {
    "addr:full":"1110 N 2nd St Sayre OK 73662",
    "addr:housenumber":"1110",
    "addr:postcode":"73662",
    "addr:street":"N 2Nd St",
    "iso:country":"US",
    "sg:address":"1110 N 2nd St",
    "sg:city":"Sayre",
    "sg:classifiers":[
        {
            "category":"Social Services",
            "subcategory":"Child Care",
            "type":"Services"
        }
    ],
    "sg:phone":"+1 580 928 2331",
    "sg:postcode":"73662",
    "sg:province":"OK",
    "wof:name":"Little Angels",
    "wof:placetype":"venue"
},
  "geometry": {"coordinates":[-99.635845,35.30169],"type":"Point"}
}