{
  "type": "Feature",
  "properties": {
    "iso:country":"US",
    "sg:address":"15 1st Ave NE",
    "sg:city":"Miami",
    "sg:classifiers":[
        {
            "category":"Organizations",
            "subcategory":"Non-profit Organization",
            "type":"Services"
        },
        {
            "category":"Organizations",
            "subcategory":"Community Association",
            "type":"Services"
        }
    ],
    "sg:phone":"+1 918 542 1590",
    "sg:postcode":"74354",
    "sg:province":"OK",
    "sg:tags":[
        "social"
    ],
    "wof:name":"Miami Main Street Inc",
    "wof:placetype":"venue"
},
  "geometry": {"coordinates":[-94.87738400000001,36.876295],"type":"Point"}
}