{
  "type": "Feature",
  "properties": {
    "addr:full":"603 S Choctaw Ave Mill Creek OK 74856",
    "addr:housenumber":"603",
    "addr:postcode":"74856",
    "addr:street":"S Choctaw Ave",
    "iso:country":"US",
    "sg:address":"603 S Choctaw Ave",
    "sg:city":"Mill Creek",
    "sg:classifiers":[
        {
            "category":"Education",
            "subcategory":"School",
            "type":"Public Place"
        }
    ],
    "sg:phone":"+1 580 384 5333",
    "sg:postcode":"74856",
    "sg:province":"OK",
    "wof:name":"Mill Creek Headstart",
    "wof:placetype":"venue"
},
  "geometry": {"coordinates":[-96.825731,34.398228],"type":"Point"}
}