{
  "type": "Feature",
  "properties": {
    "addr:full":"306 W Oklahoma Ave Guthrie OK 73044",
    "addr:housenumber":"306",
    "addr:postcode":"73044",
    "addr:street":"W Oklahoma Ave",
    "iso:country":"US",
    "sg:address":"306 W Oklahoma Ave",
    "sg:city":"Guthrie",
    "sg:classifiers":[
        {
            "category":"Government",
            "subcategory":"Police Station",
            "type":"Public Place"
        }
    ],
    "sg:phone":"+1 405 282 3535",
    "sg:postcode":"73044",
    "sg:province":"OK",
    "sg:tags":[
        "department"
    ],
    "wof:name":"Guthrie Police Dept",
    "wof:placetype":"venue"
},
  "geometry": {"coordinates":[-97.428955,35.878098],"type":"Point"}
}