{
  "type": "Feature",
  "properties": {
    "iso:country":"US",
    "sg:address":"1536 SW 93rd St",
    "sg:city":"Oklahoma City",
    "sg:classifiers":[
        {
            "category":"Autos & Motor Vehicles",
            "subcategory":"Automobile Sales",
            "type":"Retail Goods"
        }
    ],
    "sg:phone":"+1 405 692 7289",
    "sg:postcode":"73159",
    "sg:province":"OK",
    "wof:name":"Paraspace Aviation LLC",
    "wof:placetype":"venue"
},
  "geometry": {"coordinates":[-97.54684,35.374191],"type":"Point"}
}