{
  "type": "Feature",
  "properties": {
    "addr:full":"1315 SW Cornish Ave Lawton OK 73505",
    "addr:housenumber":"1315",
    "addr:postcode":"73505",
    "addr:street":"Sw Cornish Ave",
    "iso:country":"US",
    "sg:address":"1315 SW Cornish Ave",
    "sg:city":"Lawton",
    "sg:classifiers":[
        {
            "category":"Professional",
            "subcategory":"Management & Consulting",
            "type":"Services"
        }
    ],
    "sg:phone":"+1 580 595 9632",
    "sg:postcode":"73505",
    "sg:province":"OK",
    "sg:tags":[
        "construction"
    ],
    "wof:name":"Sdj Management  Inc",
    "wof:placetype":"venue"
},
  "geometry": {"coordinates":[-98.42836200000001,34.593249],"type":"Point"}
}