{
  "type": "Feature",
  "properties": {
    "addr:full":"615 SE Frank Phillips Blvd Bartlesville OK 74006",
    "addr:housenumber":"615",
    "addr:postcode":"74006",
    "addr:street":"Se Frank Phillips Blvd",
    "iso:country":"US",
    "sg:address":"615 SE Frank Phillips Blvd",
    "sg:city":"Bartlesville",
    "sg:classifiers":[
        {
            "category":"Social Services",
            "type":"Services"
        }
    ],
    "sg:phone":"+1 918 336 1188",
    "sg:postcode":"74006",
    "sg:province":"OK",
    "sg:tags":[
        "crisis",
        "intervention"
    ],
    "wof:name":"Family Crisis & Counseling Svc",
    "wof:placetype":"venue"
},
  "geometry": {"coordinates":[-95.971102,36.750609],"type":"Point"}
}