{
  "type": "Feature",
  "properties": {
    "addr:full":"524 N 7th Ave Fairview OK 73737",
    "addr:housenumber":"524",
    "addr:postcode":"73737",
    "addr:street":"N 7Th Ave",
    "iso:country":"US",
    "sg:address":"524 N 7th Ave",
    "sg:city":"Fairview",
    "sg:classifiers":[
        {
            "category":"Organizations",
            "subcategory":"Religious Organization",
            "type":"Services"
        }
    ],
    "sg:phone":"+1 580 227 4606",
    "sg:postcode":"73737",
    "sg:province":"OK",
    "sg:tags":[
        "church"
    ],
    "wof:name":"Church Of Christ",
    "wof:placetype":"venue"
},
  "geometry": {"coordinates":[-98.477245,36.273878],"type":"Point"}
}