{
  "type": "Feature",
  "properties": {
    "addr:full":"3210 E 21st St Tulsa OK 74114",
    "addr:housenumber":"3210",
    "addr:postcode":"74114",
    "addr:street":"E 21St St",
    "iso:country":"US",
    "sg:address":"3210 E 21st St",
    "sg:city":"Tulsa",
    "sg:classifiers":[
        {
            "category":"Health Services",
            "subcategory":"Doctor",
            "type":"Services"
        }
    ],
    "sg:phone":"+1 918 742 5521",
    "sg:postcode":"74114",
    "sg:province":"OK",
    "wof:name":"Monty M Thames DDS",
    "wof:placetype":"venue"
},
  "geometry": {"coordinates":[-95.941886,36.13319],"type":"Point"}
}