{
  "type": "Feature",
  "properties": {
    "addr:full":"112 S Meridian St Waurika OK 73573",
    "addr:housenumber":"112",
    "addr:postcode":"73573",
    "addr:street":"S Meridian St",
    "iso:country":"US",
    "sg:address":"112 S Meridian St",
    "sg:city":"Waurika",
    "sg:classifiers":[
        {
            "category":"Retail",
            "subcategory":"Auto Repair",
            "type":"Services"
        }
    ],
    "sg:phone":"+1 580 228 3393",
    "sg:postcode":"73573",
    "sg:province":"OK",
    "sg:tags":[
        "repairing",
        "automobile"
    ],
    "wof:name":"Waurika Auto Svc",
    "wof:placetype":"venue"
},
  "geometry": {"coordinates":[-97.999742,34.162948],"type":"Point"}
}