{
  "type": "Feature",
  "properties": {
    "iso:country":"US",
    "sg:address":"14453 NE 23rd St",
    "sg:city":"Choctaw",
    "sg:classifiers":[
        {
            "category":"Banks & Credit Unions",
            "subcategory":"Bank",
            "type":"Services"
        }
    ],
    "sg:phone":"+1 405 732 0324",
    "sg:postcode":"73020",
    "sg:province":"OK",
    "wof:name":"Tinker Credit Union",
    "wof:placetype":"venue"
},
  "geometry": {"coordinates":[-97.281744,35.493212],"type":"Point"}
}