{
  "type": "Feature",
  "properties": {
    "addr:full":"1312 Beaumont St Norman OK 73071",
    "addr:housenumber":"1312",
    "addr:postcode":"73071",
    "addr:street":"Beaumont St",
    "iso:country":"US",
    "sg:address":"1312 Beaumont St",
    "sg:city":"Norman",
    "sg:classifiers":[
        {
            "category":"Retail",
            "subcategory":"Repair Shop",
            "type":"Services"
        }
    ],
    "sg:phone":"+1 405 364 8585",
    "sg:postcode":"73071",
    "sg:province":"OK",
    "sg:tags":[
        "appliance"
    ],
    "wof:name":"Mike's Washer & Dryer Svc",
    "wof:placetype":"venue"
},
  "geometry": {"coordinates":[-97.42007599999999,35.209838],"type":"Point"}
}