{
  "type": "Feature",
  "properties": {
    "addr:full":"601 Green Country Dr Tahlequah OK 74464",
    "addr:housenumber":"601",
    "addr:postcode":"74464",
    "addr:street":"Green Country Dr",
    "iso:country":"US",
    "sg:address":"601 Green Country Dr",
    "sg:city":"Tahlequah",
    "sg:classifiers":[
        {
            "category":"Personal",
            "subcategory":"Beauty Salon",
            "type":"Services"
        }
    ],
    "sg:phone":"+1 918 456 5601",
    "sg:postcode":"74464",
    "sg:province":"OK",
    "sg:tags":[
        "shop"
    ],
    "wof:name":"Gerrys Beauty Salon",
    "wof:placetype":"venue"
},
  "geometry": {"coordinates":[-94.986108,35.870428],"type":"Point"}
}