{
  "type": "Feature",
  "properties": {
    "addr:full":"601 NW 2nd St Lawton OK 73507",
    "addr:housenumber":"601",
    "addr:postcode":"73507",
    "addr:street":"Nw 2Nd St",
    "iso:country":"US",
    "sg:address":"601 NW 2nd St",
    "sg:city":"Lawton",
    "sg:classifiers":[
        {
            "category":"Bars & Pubs",
            "type":"Food & Drink"
        }
    ],
    "sg:phone":"+1 580 595 4892",
    "sg:postcode":"73507",
    "sg:province":"OK",
    "sg:tags":[
        "drinking"
    ],
    "wof:name":"Harlows Lawton Inc",
    "wof:placetype":"venue"
},
  "geometry": {"coordinates":[-98.39048099999999,34.616741],"type":"Point"}
}