{
  "type": "Feature",
  "properties": {
    "iso:country":"US",
    "sg:address":"601 NW 2nd St",
    "sg:city":"Lawton",
    "sg:classifiers":[
        {
            "category":"Bars & Pubs",
            "type":"Food & Drink"
        }
    ],
    "sg:phone":"+1 580 595 4892",
    "sg:postcode":"73507",
    "sg:province":"OK",
    "sg:tags":[
        "drinking"
    ],
    "wof:name":"Harlows Lawton Inc",
    "wof:placetype":"venue"
},
  "geometry": {"coordinates":[-98.390481,34.616741],"type":"Point"}
}