{
  "type": "Feature",
  "properties": {
    "addr:full":"505 W Illinois Ave Enid OK 73701",
    "addr:housenumber":"505",
    "addr:postcode":"73701",
    "addr:street":"W Illinois Ave",
    "iso:country":"US",
    "sg:address":"505 W Illinois Ave",
    "sg:city":"Enid",
    "sg:classifiers":[
        {
            "category":"Building & Trades",
            "subcategory":"Landscaping Services",
            "type":"Services"
        }
    ],
    "sg:phone":"+1 580 249 8359",
    "sg:postcode":"73701",
    "sg:province":"OK",
    "sg:tags":[
        "landscape",
        "contractor"
    ],
    "wof:name":"Vintage Landscape Designs",
    "wof:placetype":"venue"
},
  "geometry": {"coordinates":[-97.885204,36.385605],"type":"Point"}
}