{
  "type": "Feature",
  "properties": {
    "iso:country":"US",
    "sg:address":"2534 S Robinson Ave",
    "sg:city":"Oklahoma City",
    "sg:classifiers":[
        {
            "category":"Restaurant",
            "type":"Food & Drink"
        }
    ],
    "sg:phone":"+1 405 290 7659",
    "sg:postcode":"73109",
    "sg:province":"OK",
    "wof:name":"Taqueria San Martin",
    "wof:placetype":"venue"
},
  "geometry": {"coordinates":[-97.51603299999999,35.439781],"type":"Point"}
}