{
  "type": "Feature",
  "properties": {
    "addr:full":"2905 N Divis Ave Bethany OK 73008",
    "addr:housenumber":"2905",
    "addr:postcode":"73008",
    "addr:street":"N Divis Ave",
    "iso:country":"US",
    "sg:address":"2905 N Divis Ave",
    "sg:city":"Bethany",
    "sg:classifiers":[
        {
            "category":"Retail",
            "subcategory":"Repair Shop",
            "type":"Services"
        }
    ],
    "sg:phone":"+1 405 521 1200",
    "sg:postcode":"73008",
    "sg:province":"OK",
    "sg:tags":[
        "equipment"
    ],
    "wof:name":"Northwest Medical Eqp Svc",
    "wof:placetype":"venue"
},
  "geometry": {"coordinates":[-97.638907,35.499327],"type":"Point"}
}