{
  "type": "Feature",
  "properties": {
    "iso:country":"US",
    "sg:address":"937 S Santa Fe",
    "sg:city":"Mooreland",
    "sg:classifiers":[
        {
            "category":"Building & Trades",
            "subcategory":"Landscaping Services",
            "type":"Services"
        }
    ],
    "sg:phone":"+1 580 994 5927",
    "sg:postcode":"73852",
    "sg:province":"OK",
    "wof:name":"Excel Lawn Service",
    "wof:placetype":"venue"
},
  "geometry": {"coordinates":[-99.20993,36.431197],"type":"Point"}
}