{
  "type": "Feature",
  "properties": {
    "iso:country":"US",
    "sg:address":"2100 Raintree Rd",
    "sg:city":"Edmond",
    "sg:classifiers":[
        {
            "category":"Mining & Drilling",
            "type":"Manufacturing & Wholesale Goods"
        }
    ],
    "sg:phone":"+1 405 340 1225",
    "sg:postcode":"73013",
    "sg:province":"OK",
    "sg:tags":[
        "field"
    ],
    "wof:name":"Csw Corp",
    "wof:placetype":"venue"
},
  "geometry": {"coordinates":[-97.456555,35.631294],"type":"Point"}
}