{
  "type": "Feature",
  "properties": {
    "iso:country":"US",
    "sg:address":"9204 S Pennsylvania Ave",
    "sg:city":"Oklahoma City",
    "sg:classifiers":[
        {
            "category":"Restaurant",
            "type":"Food & Drink"
        }
    ],
    "sg:phone":"+1 405 692 2559",
    "sg:postcode":"73159",
    "sg:province":"OK",
    "wof:name":"China King",
    "wof:placetype":"venue"
},
  "geometry": {"coordinates":[-97.54777,35.37648],"type":"Point"}
}