{
  "type": "Feature",
  "properties": {
    "iso:country":"US",
    "sg:address":"7051 E 58th Pl",
    "sg:city":"Tulsa",
    "sg:classifiers":[
        {
            "category":"Sports & Exercise",
            "subcategory":"Gym",
            "type":"Entertainment"
        }
    ],
    "sg:phone":"+1 918 946 1743",
    "sg:postcode":"74145",
    "sg:province":"OK",
    "sg:tags":[
        "spa",
        "health"
    ],
    "wof:name":"All Leaders Unlimited Inc",
    "wof:placetype":"venue"
},
  "geometry": {"coordinates":[-95.896407,36.079393],"type":"Point"}
}