{
  "type": "Feature",
  "properties": {
    "iso:country":"US",
    "sg:address":"15904 E 167th St S",
    "sg:city":"Leonard",
    "sg:phone":"+1 918 366 8673",
    "sg:postcode":"74008",
    "sg:province":"OK",
    "sg:tags":[
        "oil",
        "gasoline"
    ],
    "wof:name":"Basil Ethridge Wholesale Gas",
    "wof:placetype":"venue"
},
  "geometry": {"coordinates":[-95.798339,35.9208],"type":"Point"}
}