{
  "type": "Feature",
  "properties": {
    "iso:country":"US",
    "sg:address":"8306 E 108th St",
    "sg:city":"Tulsa",
    "sg:classifiers":[
        {
            "category":"Retail",
            "subcategory":"Repair Shop",
            "type":"Services"
        }
    ],
    "sg:phone":"+1 918 369 3886",
    "sg:postcode":"74133",
    "sg:province":"OK",
    "wof:name":"Electronic Keyboard Repair",
    "wof:placetype":"venue"
},
  "geometry": {"coordinates":[-95.882206,36.007178],"type":"Point"}
}