{
  "type": "Feature",
  "properties": {
    "iso:country":"US",
    "sg:address":"11937 S Gum Ave",
    "sg:city":"Jenks",
    "sg:classifiers":[
        {
            "category":"Shopping",
            "subcategory":"Beauty & Cosmetics",
            "type":"Retail Goods"
        }
    ],
    "sg:phone":"+1 918 296 3061",
    "sg:postcode":"74037",
    "sg:province":"OK",
    "sg:tags":[
        "merchandise"
    ],
    "wof:name":"Bathables",
    "wof:placetype":"venue"
},
  "geometry": {"coordinates":[-95.97995400000001,35.990598],"type":"Point"}
}