{
  "type": "Feature",
  "properties": {
    "iso:country":"US",
    "sg:address":"2420 Richmond Rd",
    "sg:city":"Woodward",
    "sg:classifiers":[
        {
            "category":"Retail",
            "subcategory":"Auto Repair",
            "type":"Services"
        }
    ],
    "sg:phone":"+1 580 256 7674",
    "sg:postcode":"73801",
    "sg:province":"OK",
    "sg:tags":[
        "radiator"
    ],
    "wof:name":"Oilfield Radiator Repair Inc",
    "wof:placetype":"venue"
},
  "geometry": {"coordinates":[-99.40778,36.407379],"type":"Point"}
}