{
  "type": "Feature",
  "properties": {
    "iso:country":"US",
    "sg:address":"2015 Allenhurst St",
    "sg:city":"Norman",
    "sg:classifiers":[
        {
            "category":"Retail",
            "subcategory":"Laundry & Dry Cleaning",
            "type":"Services"
        }
    ],
    "sg:phone":"+1 405 321 1732",
    "sg:postcode":"73071",
    "sg:province":"OK",
    "sg:tags":[
        "cleaners",
        "rug",
        "carpet"
    ],
    "wof:name":"Norman's Best",
    "wof:placetype":"venue"
},
  "geometry": {"coordinates":[-97.40906,35.201809],"type":"Point"}
}