{
  "type": "Feature",
  "properties": {
    "addr:full":"513 W Oak St Collinsville OK 74021",
    "addr:housenumber":"513",
    "addr:postcode":"74021",
    "addr:street":"W Oak St",
    "iso:country":"US",
    "sg:address":"513 W Oak St",
    "sg:city":"Collinsville",
    "sg:classifiers":[
        {
            "category":"Retail",
            "subcategory":"Auto Repair",
            "type":"Services"
        }
    ],
    "sg:phone":"+1 918 371 3252",
    "sg:postcode":"74021",
    "sg:province":"OK",
    "sg:tags":[
        "repairing",
        "automobile",
        "general"
    ],
    "wof:name":"Clean Auto Repair Inc",
    "wof:placetype":"venue"
},
  "geometry": {"coordinates":[-95.831256,36.366515],"type":"Point"}
}