{
  "type": "Feature",
  "properties": {
    "addr:full":"711 E Broadway St Waynoka OK 73860",
    "addr:housenumber":"711",
    "addr:postcode":"73860",
    "addr:street":"E Broadway St",
    "iso:country":"US",
    "sg:address":"711 E Broadway St",
    "sg:city":"Waynoka",
    "sg:classifiers":[
        {
            "category":"Health Services",
            "subcategory":"Nursing And Care Facility",
            "type":"Services"
        }
    ],
    "sg:phone":"+1 580 824 5661",
    "sg:postcode":"73860",
    "sg:province":"OK",
    "sg:tags":[
        "home",
        "convalescent"
    ],
    "wof:name":"Waynoka Nursing Ctr",
    "wof:placetype":"venue"
},
  "geometry": {"coordinates":[-98.872106,36.58608],"type":"Point"}
}