{
  "type": "Feature",
  "properties": {
    "addr:full":"401 S Lewis Ave Tulsa OK 74104",
    "addr:housenumber":"401",
    "addr:postcode":"74104",
    "addr:street":"S Lewis Ave",
    "iso:country":"US",
    "sg:address":"401 S Lewis Ave",
    "sg:city":"Tulsa",
    "sg:classifiers":[
        {
            "category":"Shopping",
            "subcategory":"Discount & Variety Stores",
            "type":"Retail Goods"
        }
    ],
    "sg:phone":"+1 918 583 7930",
    "sg:postcode":"74104",
    "sg:province":"OK",
    "wof:name":"Dollar General",
    "wof:placetype":"venue"
},
  "geometry": {"coordinates":[-95.958186,36.154677],"type":"Point"}
}