{
  "type": "Feature",
  "properties": {
    "addr:full":"3600 NW 50th St Oklahoma City OK 73112",
    "addr:housenumber":"3600",
    "addr:postcode":"73112",
    "addr:street":"Nw 50Th St",
    "iso:country":"US",
    "sg:address":"3600 NW 50th St",
    "sg:city":"Oklahoma City",
    "sg:classifiers":[
        {
            "category":"Real Estate",
            "subcategory":"Surveying",
            "type":"Services"
        }
    ],
    "sg:phone":"+1 405 947 7207",
    "sg:postcode":"73112",
    "sg:province":"OK",
    "sg:tags":[
        "surveyor"
    ],
    "wof:name":"Land Graphics",
    "wof:placetype":"venue"
},
  "geometry": {"coordinates":[-97.58343499999999,35.522278],"type":"Point"}
}