{
  "type": "Feature",
  "properties": {
    "iso:country":"US",
    "sg:address":"301 E Dale St",
    "sg:city":"Norman",
    "sg:classifiers":[
        {
            "category":"Health Services",
            "subcategory":"Nursing And Care Facility",
            "type":"Services"
        }
    ],
    "sg:phone":"+1 405 321 7932",
    "sg:postcode":"73069",
    "sg:province":"OK",
    "sg:tags":[
        "home"
    ],
    "wof:name":"Holiday Heights Nursing Home",
    "wof:placetype":"venue"
},
  "geometry": {"coordinates":[-97.44107200000001,35.234002],"type":"Point"}
}