{
  "type": "Feature",
  "properties": {
    "addr:full":"2020 S 28th St Clinton OK 73601",
    "addr:housenumber":"2020",
    "addr:postcode":"73601",
    "addr:street":"S 28Th St",
    "iso:country":"US",
    "sg:address":"2020 S 28th St",
    "sg:city":"Clinton",
    "sg:classifiers":[
        {
            "category":"Building & Trades",
            "subcategory":"Construction",
            "type":"Services"
        }
    ],
    "sg:phone":"+1 580 323 0930",
    "sg:postcode":"73601",
    "sg:province":"OK",
    "sg:tags":[
        "home",
        "improvement"
    ],
    "wof:name":"Roy Jones Jr Construction",
    "wof:placetype":"venue"
},
  "geometry": {"coordinates":[-98.993664,35.469261],"type":"Point"}
}