{
  "type": "Feature",
  "properties": {
    "addr:full":"615 E St Snyder OK 73566",
    "addr:housenumber":"615",
    "addr:postcode":"73566",
    "addr:street":"E St",
    "iso:country":"US",
    "sg:address":"615 E St",
    "sg:city":"Snyder",
    "sg:classifiers":[
        {
            "category":"Freight",
            "type":"Transportation"
        }
    ],
    "sg:phone":"+1 580 569 4095",
    "sg:postcode":"73566",
    "sg:province":"OK",
    "sg:tags":[
        "commercial",
        "storage"
    ],
    "wof:name":"Snyder Rental Storage",
    "wof:placetype":"venue"
},
  "geometry": {"coordinates":[-98.951965,34.659776],"type":"Point"}
}