{
  "type": "Feature",
  "properties": {
    "iso:country":"US",
    "sg:address":"1415 S Muskogee Ave",
    "sg:city":"Claremore",
    "sg:classifiers":[
        {
            "category":"Manufacturing",
            "subcategory":"Leather Goods",
            "type":"Manufacturing & Wholesale Goods"
        }
    ],
    "sg:phone":"+1 918 342 0642",
    "sg:postcode":"74017",
    "sg:province":"OK",
    "sg:tags":[
        "repair",
        "sporting",
        "se",
        "mfg"
    ],
    "wof:name":"Benefield Saddlery",
    "wof:placetype":"venue"
},
  "geometry": {"coordinates":[-95.61493299999999,36.295661],"type":"Point"}
}