{
  "type": "Feature",
  "properties": {
    "iso:country":"US",
    "sg:address":"520 N Main St",
    "sg:city":"Altus",
    "sg:classifiers":[
        {
            "category":"Autos & Motor Vehicles",
            "subcategory":"Automobile Sales",
            "type":"Retail Goods"
        }
    ],
    "sg:phone":"+1 580 482 3000",
    "sg:postcode":"73521",
    "sg:province":"OK",
    "sg:tags":[
        "car",
        "dealer"
    ],
    "wof:name":"Ok Auto Sales",
    "wof:placetype":"venue"
},
  "geometry": {"coordinates":[-99.333832,34.643086],"type":"Point"}
}