{
  "type": "Feature",
  "properties": {
    "iso:country":"US",
    "sg:address":"12613 Arrowhead Dr",
    "sg:city":"Oklahoma City",
    "sg:classifiers":[
        {
            "category":"Shopping",
            "subcategory":"Clothing, Apparel, & Fashions",
            "type":"Retail Goods"
        }
    ],
    "sg:phone":"+1 405 755 2135",
    "sg:postcode":"73120",
    "sg:province":"OK",
    "wof:name":"Oakes Enterprises",
    "wof:placetype":"venue"
},
  "geometry": {"coordinates":[-97.593546,35.598127],"type":"Point"}
}