{
  "type": "Feature",
  "properties": {
    "iso:country":"US",
    "sg:address":"3324 Enterprise Blvd",
    "sg:city":"Durant",
    "sg:classifiers":[
        {
            "category":"Organizations",
            "subcategory":"Non-profit Organization",
            "type":"Services"
        }
    ],
    "sg:phone":"+1 580 924 8509",
    "sg:postcode":"74701",
    "sg:province":"OK",
    "sg:tags":[
        "disability"
    ],
    "wof:name":"Sheltered Work Opportunities",
    "wof:placetype":"venue"
},
  "geometry": {"coordinates":[-96.412419,33.965344],"type":"Point"}
}