{
  "type": "Feature",
  "properties": {
    "addr:full":"611 E Eula St Hollis OK 73550",
    "addr:housenumber":"611",
    "addr:postcode":"73550",
    "addr:street":"E Eula St",
    "iso:country":"US",
    "sg:address":"611 E Eula St",
    "sg:city":"Hollis",
    "sg:classifiers":[
        {
            "category":"Real Estate",
            "subcategory":"Real Estate Operator",
            "type":"Services"
        }
    ],
    "sg:phone":"+1 580 688 2686",
    "sg:postcode":"73550",
    "sg:province":"OK",
    "sg:tags":[
        "property",
        "lessor"
    ],
    "wof:name":"Doug Burns Trust",
    "wof:placetype":"venue"
},
  "geometry": {"coordinates":[-99.912122,34.685841],"type":"Point"}
}