{
  "type": "Feature",
  "properties": {
    "addr:full":"6333 S Memorial Dr Tulsa OK 74133",
    "addr:housenumber":"6333",
    "addr:postcode":"74133",
    "addr:street":"S Memorial Dr",
    "iso:country":"US",
    "sg:address":"6333 S Memorial Dr",
    "sg:city":"Tulsa",
    "sg:classifiers":[
        {
            "category":"Professional",
            "type":"Services"
        }
    ],
    "sg:phone":"+1 918 249 0304",
    "sg:postcode":"74133",
    "sg:province":"OK",
    "sg:tags":[
        "establishment"
    ],
    "wof:name":"Gregory Pitts Agency",
    "wof:placetype":"venue"
},
  "geometry": {"coordinates":[-95.88634399999999,36.073319],"type":"Point"}
}