{
  "type": "Feature",
  "properties": {
    "iso:country":"US",
    "sg:address":"1509 W Montgomery St",
    "sg:city":"Broken Arrow",
    "sg:classifiers":[
        {
            "category":"Building & Trades",
            "subcategory":"Cleaning & Sanitation",
            "type":"Services"
        }
    ],
    "sg:phone":"+1 918 234 5901",
    "sg:postcode":"74012",
    "sg:province":"OK",
    "sg:tags":[
        "janitorial",
        "contract"
    ],
    "wof:name":"Spankin Clean",
    "wof:placetype":"venue"
},
  "geometry": {"coordinates":[-95.809861,36.017847],"type":"Point"}
}