{
  "type": "Feature",
  "properties": {
    "iso:country":"US",
    "sg:address":"1409 S Main St",
    "sg:city":"Tulsa",
    "sg:classifiers":[
        {
            "category":"Communications",
            "type":"Services"
        }
    ],
    "sg:phone":"+1 918 584 2431",
    "sg:postcode":"74119",
    "sg:province":"OK",
    "wof:name":"Communication Service Co",
    "wof:placetype":"venue"
},
  "geometry": {"coordinates":[-95.98727599999999,36.14075],"type":"Point"}
}