{
  "type": "Feature",
  "properties": {
    "iso:country":"US",
    "sg:address":"720 Moore St SW",
    "sg:city":"Ardmore",
    "sg:classifiers":[
        {
            "category":"Wholesale",
            "subcategory":"Electrical",
            "type":"Manufacturing & Wholesale Goods"
        }
    ],
    "sg:phone":"+1 580 223 4784",
    "sg:postcode":"73401",
    "sg:province":"OK",
    "sg:tags":[
        "equipment",
        "testing",
        "electronic"
    ],
    "wof:name":"Slaughter Co",
    "wof:placetype":"venue"
},
  "geometry": {"coordinates":[-97.138716,34.164504],"type":"Point"}
}