{
  "type": "Feature",
  "properties": {
    "iso:country":"US",
    "sg:address":"57500 E Hwy 59",
    "sg:city":"Fairland",
    "sg:classifiers":[
        {
            "category":"Retail",
            "subcategory":"Veterinary Services",
            "type":"Services"
        }
    ],
    "sg:phone":"+1 918 257 5345",
    "sg:postcode":"74343",
    "sg:province":"OK",
    "wof:name":"Tony D Small Dvm",
    "wof:placetype":"venue"
},
  "geometry": {"coordinates":[-94.847386,36.674608],"type":"Point"}
}