{
  "type": "Feature",
  "properties": {
    "iso:country":"US",
    "sg:address":"118 S 21st Ave",
    "sg:city":"Durant",
    "sg:classifiers":[
        {
            "category":"Food & Beverages",
            "subcategory":"Liquor & Beverages",
            "type":"Retail Goods"
        }
    ],
    "sg:phone":"+1 580 924 4400",
    "sg:postcode":"74701",
    "sg:province":"OK",
    "sg:tags":[
        "alcoholic"
    ],
    "wof:name":"Westside Discount Liquor",
    "wof:placetype":"venue"
},
  "geometry": {"coordinates":[-96.40109099999999,33.99675],"type":"Point"}
}