{
  "type": "Feature",
  "properties": {
    "addr:full":"1507 W Main St Duncan OK 73533",
    "addr:housenumber":"1507",
    "addr:postcode":"73533",
    "addr:street":"W Main St",
    "iso:country":"US",
    "sg:address":"1507 W Main St",
    "sg:city":"Duncan",
    "sg:classifiers":[
        {
            "category":"Retail",
            "subcategory":"Car Wash",
            "type":"Services"
        }
    ],
    "sg:phone":"+1 580 252 2374",
    "sg:postcode":"73533",
    "sg:province":"OK",
    "sg:tags":[
        "polishing",
        "washing"
    ],
    "wof:name":"Main Street Dirt Busters",
    "wof:placetype":"venue"
},
  "geometry": {"coordinates":[-97.968169,34.502888],"type":"Point"}
}