{
  "type": "Feature",
  "properties": {
    "iso:country":"US",
    "sg:address":"2324 County Rd",
    "sg:city":"Chickasha",
    "sg:classifiers":[
        {
            "category":"Real Estate",
            "subcategory":"Real Estate Agent",
            "type":"Services"
        }
    ],
    "sg:phone":"+1 405 222 3200",
    "sg:postcode":"73045",
    "sg:province":"OK",
    "sg:tags":[
        "appraiser"
    ],
    "wof:name":"Heartland Appraisal Svc",
    "wof:placetype":"venue"
},
  "geometry": {"coordinates":[-97.160413,35.492719],"type":"Point"}
}