{
  "type": "Feature",
  "properties": {
    "iso:country":"US",
    "sg:address":"1601 1/2 N Harrison St",
    "sg:city":"Shawnee",
    "sg:classifiers":[
        {
            "category":"Personal",
            "subcategory":"Beauty Salon",
            "type":"Services"
        }
    ],
    "sg:phone":"+1 405 275 2363",
    "sg:postcode":"74804",
    "sg:province":"OK",
    "wof:name":"Styles By Expressions",
    "wof:placetype":"venue"
},
  "geometry": {"coordinates":[-96.912148,35.349239],"type":"Point"}
}