{
  "type": "Feature",
  "properties": {
    "addr:full":"2346 N Interstate Dr Norman OK 73072",
    "addr:housenumber":"2346",
    "addr:postcode":"73072",
    "addr:street":"N Interstate Dr",
    "iso:country":"US",
    "sg:address":"2346 N Interstate Dr",
    "sg:city":"Norman",
    "sg:classifiers":[
        {
            "category":"Personal",
            "subcategory":"Beauty Salon",
            "type":"Services"
        }
    ],
    "sg:phone":"+1 405 292 4247",
    "sg:postcode":"73072",
    "sg:province":"OK",
    "wof:name":"Salon",
    "wof:placetype":"venue"
},
  "geometry": {"coordinates":[-97.485902,35.247231],"type":"Point"}
}