{
  "type": "Feature",
  "properties": {
    "iso:country":"US",
    "sg:address":"1201 Oklahoma Ave",
    "sg:city":"Woodward",
    "sg:classifiers":[
        {
            "category":"Shopping",
            "subcategory":"Tobacco",
            "type":"Retail Goods"
        }
    ],
    "sg:phone":"+1 580 254 5889",
    "sg:postcode":"73801",
    "sg:province":"OK",
    "sg:tags":[
        "cigarette",
        "cigar",
        "dealer"
    ],
    "wof:name":"Cigarette Outlet",
    "wof:placetype":"venue"
},
  "geometry": {"coordinates":[-99.395793,36.433637],"type":"Point"}
}