{
  "type": "Feature",
  "properties": {
    "iso:country":"US",
    "sg:address":"516 3rd Ave NW",
    "sg:city":"Miami",
    "sg:classifiers":[
        {
            "category":"Personal",
            "subcategory":"Beauty Salon",
            "type":"Services"
        }
    ],
    "sg:phone":"+1 918 542 4068",
    "sg:postcode":"74354",
    "sg:province":"OK",
    "wof:name":"Virginia's Beauty Salon",
    "wof:placetype":"venue"
},
  "geometry": {"coordinates":[-94.883443,36.879118],"type":"Point"}
}