{
  "type": "Feature",
  "properties": {
    "iso:country":"US",
    "sg:address":"1427 S 1st St",
    "sg:city":"Chickasha",
    "sg:classifiers":[
        {
            "category":"Organizations",
            "subcategory":"Religious Organization",
            "type":"Services"
        }
    ],
    "sg:phone":"+1 405 224 0892",
    "sg:postcode":"73018",
    "sg:province":"OK",
    "sg:tags":[
        "church"
    ],
    "wof:name":"New Hope Baptist Church",
    "wof:placetype":"venue"
},
  "geometry": {"coordinates":[-97.932479,35.036425],"type":"Point"}
}