{
  "type": "Feature",
  "properties": {
    "iso:country":"US",
    "sg:address":"404 W Country Club Rd",
    "sg:city":"Chickasha",
    "sg:classifiers":[
        {
            "category":"Food & Beverages",
            "subcategory":"Liquor & Beverages",
            "type":"Retail Goods"
        }
    ],
    "sg:phone":"+1 405 222 1825",
    "sg:postcode":"73018",
    "sg:province":"OK",
    "wof:name":"Next Door Liquour Store",
    "wof:placetype":"venue"
},
  "geometry": {"coordinates":[-97.93489599999999,35.015107],"type":"Point"}
}