{
  "type": "Feature",
  "properties": {
    "addr:full":"2011 NW Smith Ave Lawton OK 73507",
    "addr:housenumber":"2011",
    "addr:postcode":"73507",
    "addr:street":"Nw Smith Ave",
    "iso:country":"US",
    "sg:address":"2011 NW Smith Ave",
    "sg:city":"Lawton",
    "sg:classifiers":[
        {
            "category":"Personal",
            "subcategory":"Barber",
            "type":"Services"
        }
    ],
    "sg:phone":"+1 580 355 5455",
    "sg:postcode":"73507",
    "sg:province":"OK",
    "sg:tags":[
        "shop"
    ],
    "wof:name":"K P's Barber & Style Shop",
    "wof:placetype":"venue"
},
  "geometry": {"coordinates":[-98.422043,34.632593],"type":"Point"}
}