{
  "type": "Feature",
  "properties": {
    "iso:country":"US",
    "sg:address":"122 E Moses St",
    "sg:city":"Cushing",
    "sg:classifiers":[
        {
            "category":"Banks & Credit Unions",
            "subcategory":"Bank",
            "type":"Services"
        }
    ],
    "sg:phone":"+1 918 225 3301",
    "sg:postcode":"74023",
    "sg:province":"OK",
    "sg:tags":[
        "loan",
        "short",
        "institution",
        "business"
    ],
    "wof:name":"Tower Loans",
    "wof:placetype":"venue"
},
  "geometry": {"coordinates":[-96.772454,35.981132],"type":"Point"}
}