{
  "type": "Feature",
  "properties": {
    "addr:full":"117 NE de Bell Ave Bartlesville OK 74006",
    "addr:housenumber":"117",
    "addr:postcode":"74006",
    "addr:street":"Ne De Bell Ave",
    "iso:country":"US",
    "sg:address":"117 NE de Bell Ave",
    "sg:city":"Bartlesville",
    "sg:classifiers":[
        {
            "category":"Organizations",
            "subcategory":"Religious Organization",
            "type":"Services"
        }
    ],
    "sg:phone":"+1 918 333 3598",
    "sg:postcode":"74006",
    "sg:province":"OK",
    "wof:name":"Billye Brim Ministries",
    "wof:placetype":"venue"
},
  "geometry": {"coordinates":[-95.937817,36.757984],"type":"Point"}
}