{
  "type": "Feature",
  "properties": {
    "iso:country":"US",
    "sg:address":"5312 E 26th St",
    "sg:city":"Tulsa",
    "sg:classifiers":[
        {
            "category":"Manufacturing",
            "subcategory":"Tools & Machinery",
            "type":"Manufacturing & Wholesale Goods"
        }
    ],
    "sg:phone":"+1 918 744 8129",
    "sg:postcode":"74114",
    "sg:province":"OK",
    "sg:tags":[
        "field",
        "mfg"
    ],
    "wof:name":"Crowley Oil & Mfg",
    "wof:placetype":"venue"
},
  "geometry": {"coordinates":[-95.913625,36.125601],"type":"Point"}
}