{
  "type": "Feature",
  "properties": {
    "iso:country":"US",
    "sg:address":"20 Lemonhill Rd",
    "sg:city":"Colbert",
    "sg:classifiers":[
        {
            "category":"Utilities",
            "subcategory":"Electric",
            "type":"Services"
        }
    ],
    "sg:phone":"+1 580 296 2529",
    "sg:postcode":"74730",
    "sg:province":"OK",
    "sg:tags":[
        "company"
    ],
    "wof:name":"Sutterfield Electric Co",
    "wof:placetype":"venue"
},
  "geometry": {"coordinates":[-96.500674,33.875124],"type":"Point"}
}