{
  "type": "Feature",
  "properties": {
    "iso:country":"US",
    "sg:address":"11 E 21st St",
    "sg:city":"Edmond",
    "sg:classifiers":[
        {
            "category":"Retail",
            "subcategory":"Animal Services",
            "type":"Services"
        }
    ],
    "sg:phone":"+1 405 341 2291",
    "sg:postcode":"73013",
    "sg:province":"OK",
    "sg:tags":[
        "pet",
        "grooming",
        "washing"
    ],
    "wof:name":"Mary's Barking Lot",
    "wof:placetype":"venue"
},
  "geometry": {"coordinates":[-97.483511,35.632529],"type":"Point"}
}