{
  "type": "Feature",
  "properties": {
    "iso:country":"US",
    "sg:address":"122 E Jackson St",
    "sg:city":"Hugo",
    "sg:classifiers":[
        {
            "category":"Professional",
            "subcategory":"Accounting & Tax Preparation",
            "type":"Services"
        }
    ],
    "sg:phone":"+1 580 326 9618",
    "sg:postcode":"74743",
    "sg:province":"OK",
    "sg:tags":[
        "return"
    ],
    "wof:name":"H & R Block",
    "wof:placetype":"venue"
},
  "geometry": {"coordinates":[-95.512604,34.010794],"type":"Point"}
}