{
  "type": "Feature",
  "properties": {
    "addr:full":"1205 E Robinson St Norman OK 73071",
    "addr:housenumber":"1205",
    "addr:postcode":"73071",
    "addr:street":"E Robinson St",
    "iso:country":"US",
    "sg:address":"1205 E Robinson St",
    "sg:city":"Norman",
    "sg:classifiers":[
        {
            "category":"Retail",
            "subcategory":"Car Wash",
            "type":"Services"
        }
    ],
    "sg:phone":"+1 405 360 6969",
    "sg:postcode":"73071",
    "sg:province":"OK",
    "sg:tags":[
        "carwash"
    ],
    "wof:name":"Advanced Cleaning Solutions",
    "wof:placetype":"venue"
},
  "geometry": {"coordinates":[-97.422945,35.232923],"type":"Point"}
}