{
  "type": "Feature",
  "properties": {
    "iso:country":"US",
    "sg:address":"2944 NW 50th St",
    "sg:city":"Oklahoma City",
    "sg:classifiers":[
        {
            "category":"Professional",
            "subcategory":"Business Services",
            "type":"Services"
        }
    ],
    "sg:phone":"+1 405 942 2299",
    "sg:postcode":"73112",
    "sg:province":"OK",
    "sg:tags":[
        "appraiser"
    ],
    "wof:name":"Caesar Appraisal Co",
    "wof:placetype":"venue"
},
  "geometry": {"coordinates":[-97.566681,35.522004],"type":"Point"}
}