{
  "type": "Feature",
  "properties": {
    "addr:full":"400 S Broadway Ave Hobart OK 73651",
    "addr:housenumber":"400",
    "addr:postcode":"73651",
    "addr:street":"S Broadway Ave",
    "iso:country":"US",
    "sg:address":"400 S Broadway Ave",
    "sg:city":"Hobart",
    "sg:classifiers":[
        {
            "category":"Restaurant",
            "type":"Food & Drink"
        }
    ],
    "sg:phone":"+1 580 726 5455",
    "sg:postcode":"73651",
    "sg:province":"OK",
    "wof:name":"Subway Sandwiches & Salads",
    "wof:placetype":"venue"
},
  "geometry": {"coordinates":[-99.09595299999999,35.024473],"type":"Point"}
}