{
  "type": "Feature",
  "properties": {
    "iso:country":"US",
    "sg:address":"400 S Broadway Ave",
    "sg:city":"Hobart",
    "sg:classifiers":[
        {
            "category":"Restaurant",
            "type":"Food & Drink"
        }
    ],
    "sg:phone":"+1 580 726 5455",
    "sg:postcode":"73651",
    "sg:province":"OK",
    "wof:name":"Subway Sandwiches & Salads",
    "wof:placetype":"venue"
},
  "geometry": {"coordinates":[-99.095953,35.024473],"type":"Point"}
}