{
  "type": "Feature",
  "properties": {
    "addr:full":"1408 S Harvard Ave Tulsa OK 74112",
    "addr:housenumber":"1408",
    "addr:postcode":"74112",
    "addr:street":"S Harvard Ave",
    "iso:country":"US",
    "sg:address":"1408 S Harvard Ave",
    "sg:city":"Tulsa",
    "sg:classifiers":[
        {
            "category":"Professional",
            "subcategory":"Lawyer & Legal Services",
            "type":"Services"
        }
    ],
    "sg:phone":"+1 918 813 1710",
    "sg:postcode":"74112",
    "sg:province":"OK",
    "sg:tags":[
        "attorney"
    ],
    "sg:website":"http://www.gblaw.org",
    "wof:name":"The Barkett Law Firm PLLC",
    "wof:placetype":"venue"
},
  "geometry": {"coordinates":[-95.940388,36.142195],"type":"Point"}
}