{
  "type": "Feature",
  "properties": {
    "iso:country":"US",
    "sg:address":"4200 E Skelly Dr",
    "sg:city":"Tulsa",
    "sg:classifiers":[
        {
            "category":"Health Services",
            "subcategory":"Nursing And Care Facility",
            "type":"Services"
        }
    ],
    "sg:phone":"+1 918 745 0222",
    "sg:postcode":"74135",
    "sg:province":"OK",
    "sg:tags":[
        "hospice",
        "skilled"
    ],
    "wof:name":"Seasons Hospice Inc",
    "wof:placetype":"venue"
},
  "geometry": {"coordinates":[-95.927837,36.091837],"type":"Point"}
}