{
  "type": "Feature",
  "properties": {
    "addr:full":"206 E Main St Porum OK 74421",
    "addr:housenumber":"206",
    "addr:postcode":"74421",
    "addr:street":"E Main St",
    "iso:country":"US",
    "sg:address":"206 E Main St",
    "sg:city":"Porum",
    "sg:classifiers":[
        {
            "category":"Food & Beverages",
            "subcategory":"Bakery",
            "type":"Retail Goods"
        }
    ],
    "sg:phone":"+1 918 484 5369",
    "sg:postcode":"74421",
    "sg:province":"OK",
    "sg:tags":[
        "doughnut"
    ],
    "wof:name":"Paradise Donuts",
    "wof:placetype":"venue"
},
  "geometry": {"coordinates":[-96.068629,35.742643],"type":"Point"}
}