{
  "type": "Feature",
  "properties": {
    "iso:country":"US",
    "sg:address":"110 E Broadway St",
    "sg:city":"Ardmore",
    "sg:classifiers":[
        {
            "category":"Building & Trades",
            "subcategory":"Construction",
            "type":"Services"
        }
    ],
    "sg:phone":"+1 580 223 3432",
    "sg:postcode":"73401",
    "sg:province":"OK",
    "sg:tags":[
        "contractor",
        "metalwork",
        "sheet",
        "mfg"
    ],
    "wof:name":"Mathes Sheet Metal",
    "wof:placetype":"venue"
},
  "geometry": {"coordinates":[-97.12705200000001,34.17398],"type":"Point"}
}