{
  "type": "Feature",
  "properties": {
    "iso:country":"US",
    "sg:address":"5401 E Tecumseh St",
    "sg:city":"Tulsa",
    "sg:classifiers":[
        {
            "category":"Wholesale",
            "subcategory":"Fruits & Vegetables",
            "type":"Manufacturing & Wholesale Goods"
        }
    ],
    "sg:phone":"+1 918 832 1157",
    "sg:postcode":"74115",
    "sg:province":"OK",
    "wof:name":"Superior Produce",
    "wof:placetype":"venue"
},
  "geometry": {"coordinates":[-95.915016,36.181598],"type":"Point"}
}