{
  "type": "Feature",
  "properties": {
    "addr:full":"3600 NW Expy Oklahoma City OK 73112",
    "addr:housenumber":"3600",
    "addr:postcode":"73112",
    "addr:street":"Nw Expy",
    "iso:country":"US",
    "sg:address":"3600 NW Expy",
    "sg:city":"Oklahoma City",
    "sg:classifiers":[
        {
            "category":"Organizations",
            "subcategory":"Religious Organization",
            "type":"Services"
        }
    ],
    "sg:phone":"+1 405 946 0371",
    "sg:postcode":"73112",
    "sg:province":"OK",
    "sg:website":"www.messiahokc.org",
    "wof:name":"Messiah Lutheran Church",
    "wof:placetype":"venue"
},
  "geometry": {"coordinates":[-97.582404,35.533381],"type":"Point"}
}