{
  "type": "Feature",
  "properties": {
    "addr:full":"105 N Green Ave Purcell OK 73080",
    "addr:housenumber":"105",
    "addr:postcode":"73080",
    "addr:street":"N Green Ave",
    "iso:country":"US",
    "sg:address":"105 N Green Ave",
    "sg:city":"Purcell",
    "sg:classifiers":[
        {
            "category":"Insurance",
            "subcategory":"Insurance Agent",
            "type":"Services"
        }
    ],
    "sg:phone":"+1 405 527 6161",
    "sg:postcode":"73080",
    "sg:province":"OK",
    "wof:name":"Farmers Insurance Group",
    "wof:placetype":"venue"
},
  "geometry": {"coordinates":[-97.366163,35.013046],"type":"Point"}
}