{
  "type": "Feature",
  "properties": {
    "iso:country":"US",
    "sg:address":"6810 E 41st St",
    "sg:city":"Tulsa",
    "sg:classifiers":[
        {
            "category":"Shopping",
            "type":"Retail Goods"
        }
    ],
    "sg:phone":"+1 918 280 1200",
    "sg:postcode":"74145",
    "sg:province":"OK",
    "sg:tags":[
        "telephone",
        "cellular"
    ],
    "wof:name":"Freedom Communications",
    "wof:placetype":"venue"
},
  "geometry": {"coordinates":[-95.899171,36.104307],"type":"Point"}
}