{
  "type": "Feature",
  "properties": {
    "iso:country":"US",
    "sg:address":"105 E Main St",
    "sg:city":"Marlow",
    "sg:classifiers":[
        {
            "category":"Wholesale",
            "subcategory":"Farm Supplies",
            "type":"Manufacturing & Wholesale Goods"
        }
    ],
    "sg:phone":"+1 580 658 3615",
    "sg:postcode":"73055",
    "sg:province":"OK",
    "wof:name":"Mitchell & Mitchell Inc",
    "wof:placetype":"venue"
},
  "geometry": {"coordinates":[-97.95363500000001,34.647702],"type":"Point"}
}