{
  "type": "Feature",
  "properties": {
    "addr:full":"119 SE Washington Blvd Bartlesville OK 74006",
    "addr:housenumber":"119",
    "addr:postcode":"74006",
    "addr:street":"Se Washington Blvd",
    "iso:country":"US",
    "sg:address":"119 SE Washington Blvd",
    "sg:city":"Bartlesville",
    "sg:classifiers":[
        {
            "category":"Shopping",
            "type":"Retail Goods"
        }
    ],
    "sg:phone":"+1 918 333 7944",
    "sg:postcode":"74006",
    "sg:province":"OK",
    "sg:tags":[
        "pet",
        "shop",
        "merchandise"
    ],
    "wof:name":"Classic Pet Center",
    "wof:placetype":"venue"
},
  "geometry": {"coordinates":[-95.935574,36.756658],"type":"Point"}
}