{
  "type": "Feature",
  "properties": {
    "iso:country":"US",
    "sg:address":"5601 S 122nd East Ave",
    "sg:city":"Tulsa",
    "sg:classifiers":[
        {
            "category":"Building & Trades",
            "subcategory":"Construction",
            "type":"Services"
        }
    ],
    "sg:phone":"+1 918 878 3498",
    "sg:postcode":"74146",
    "sg:province":"OK",
    "sg:tags":[
        "concrete",
        "contractor"
    ],
    "wof:name":"Cantera Concrete Company LLC",
    "wof:placetype":"venue"
},
  "geometry": {"coordinates":[-95.840397,36.081065],"type":"Point"}
}