{
  "type": "Feature",
  "properties": {
    "addr:full":"1013 SE 26th St Oklahoma City OK 73129",
    "addr:housenumber":"1013",
    "addr:postcode":"73129",
    "addr:street":"Se 26Th St",
    "iso:country":"US",
    "sg:address":"1013 SE 26th St",
    "sg:city":"Oklahoma City",
    "sg:classifiers":[
        {
            "category":"Manufacturing",
            "subcategory":"Metals",
            "type":"Manufacturing & Wholesale Goods"
        }
    ],
    "sg:phone":"+1 405 677 2222",
    "sg:postcode":"73129",
    "sg:province":"OK",
    "sg:tags":[
        "plating",
        "electroplating"
    ],
    "wof:name":"American Plater Corporation",
    "wof:placetype":"venue"
},
  "geometry": {"coordinates":[-97.49214600000001,35.438326],"type":"Point"}
}