{
  "type": "Feature",
  "properties": {
    "iso:country":"US",
    "sg:address":"124 N Main St",
    "sg:city":"Coalgate",
    "sg:classifiers":[
        {
            "category":"Restaurant",
            "type":"Food & Drink"
        }
    ],
    "sg:phone":"+1 580 927 9890",
    "sg:postcode":"74538",
    "sg:province":"OK",
    "sg:tags":[
        "eating"
    ],
    "wof:name":"Ole Coaly Cafe",
    "wof:placetype":"venue"
},
  "geometry": {"coordinates":[-96.21808,34.539567],"type":"Point"}
}