{
  "type": "Feature",
  "properties": {
    "addr:full":"2006 E 7th Pl Tulsa OK 74104",
    "addr:housenumber":"2006",
    "addr:postcode":"74104",
    "addr:street":"E 7Th Pl",
    "iso:country":"US",
    "sg:address":"2006 E 7th Pl",
    "sg:city":"Tulsa",
    "sg:classifiers":[
        {
            "category":"Wholesale",
            "subcategory":"Construction Materials",
            "type":"Manufacturing & Wholesale Goods"
        }
    ],
    "sg:phone":"+1 918 584 4373",
    "sg:postcode":"74104",
    "sg:province":"OK",
    "sg:tags":[
        "building",
        "lumber",
        "other"
    ],
    "wof:name":"White & Son Hardwoods",
    "wof:placetype":"venue"
},
  "geometry": {"coordinates":[-95.96285899999999,36.150465],"type":"Point"}
}