{
  "type": "Feature",
  "properties": {
    "iso:country":"US",
    "sg:address":"221 SW 29th St",
    "sg:city":"Oklahoma City",
    "sg:classifiers":[
        {
            "category":"Autos & Motor Vehicles",
            "subcategory":"Automobile Sales",
            "type":"Retail Goods"
        }
    ],
    "sg:phone":"+1 405 272 0202",
    "sg:postcode":"73109",
    "sg:province":"OK",
    "sg:tags":[
        "used"
    ],
    "wof:name":"Ballpark Auto Sales",
    "wof:placetype":"venue"
},
  "geometry": {"coordinates":[-97.517708,35.435305],"type":"Point"}
}