{
  "type": "Feature",
  "properties": {
    "iso:country":"US",
    "sg:address":"912 W Caddo St",
    "sg:city":"Cleveland",
    "sg:classifiers":[
        {
            "category":"Shopping",
            "subcategory":"Used Merchandise",
            "type":"Retail Goods"
        }
    ],
    "sg:phone":"+1 918 358 2402",
    "sg:postcode":"74020",
    "sg:province":"OK",
    "sg:tags":[
        "furniture"
    ],
    "wof:name":"Attic Memories",
    "wof:placetype":"venue"
},
  "geometry": {"coordinates":[-96.475019,36.305547],"type":"Point"}
}