{
  "type": "Feature",
  "properties": {
    "iso:country":"US",
    "sg:address":"9212 N Rockwell Ave",
    "sg:city":"Oklahoma City",
    "sg:classifiers":[
        {
            "category":"Professional",
            "subcategory":"Accounting & Tax Preparation",
            "type":"Services"
        }
    ],
    "sg:phone":"+1 405 721 8558",
    "sg:postcode":"73132",
    "sg:province":"OK",
    "sg:tags":[
        "accountant"
    ],
    "wof:name":"David F Bott CPA",
    "wof:placetype":"venue"
},
  "geometry": {"coordinates":[-97.638321,35.564679],"type":"Point"}
}