{
  "type": "Feature",
  "properties": {
    "iso:country":"US",
    "sg:address":"6585 S Yale Ave",
    "sg:city":"Tulsa",
    "sg:classifiers":[
        {
            "category":"Social Services",
            "subcategory":"Job Training",
            "type":"Services"
        }
    ],
    "sg:phone":"+1 918 481 2999",
    "sg:postcode":"74136",
    "sg:province":"OK",
    "sg:tags":[
        "counseling"
    ],
    "wof:name":"Saint Francis Hosp Empl Asst",
    "wof:placetype":"venue"
},
  "geometry": {"coordinates":[-95.922045,36.069451],"type":"Point"}
}