{
  "type": "Feature",
  "properties": {
    "iso:country":"US",
    "sg:address":"12810 E 24th St",
    "sg:city":"Tulsa",
    "sg:classifiers":[
        {
            "category":"Building & Trades",
            "subcategory":"Landscaping Services",
            "type":"Services"
        }
    ],
    "sg:phone":"+1 918 234 0383",
    "sg:postcode":"74129",
    "sg:province":"OK",
    "sg:tags":[
        "landscape",
        "contractor"
    ],
    "wof:name":"Jeff Harley Pro Landscaping",
    "wof:placetype":"venue"
},
  "geometry": {"coordinates":[-95.833446,36.12968],"type":"Point"}
}