{
  "type": "Feature",
  "properties": {
    "iso:country":"US",
    "sg:address":"3301 W Main St",
    "sg:city":"Norman",
    "sg:classifiers":[
        {
            "category":"Shopping",
            "subcategory":"Jewelry",
            "type":"Retail Goods"
        }
    ],
    "sg:phone":"+1 405 579 0316",
    "sg:postcode":"73072",
    "sg:province":"OK",
    "wof:name":"Friedmans Jewelers 5375",
    "wof:placetype":"venue"
},
  "geometry": {"coordinates":[-97.491002,35.218245],"type":"Point"}
}