{
  "type": "Feature",
  "properties": {
    "iso:country":"US",
    "sg:address":"2500 Quail Run St",
    "sg:city":"Clinton",
    "sg:classifiers":[
        {
            "category":"Real Estate",
            "subcategory":"Real Estate Operator",
            "type":"Services"
        }
    ],
    "sg:phone":"+1 580 323 7189",
    "sg:postcode":"73601",
    "sg:province":"OK",
    "sg:tags":[
        "property",
        "lessor"
    ],
    "wof:name":"Elmer Quiring",
    "wof:placetype":"venue"
},
  "geometry": {"coordinates":[-98.987352,35.516494],"type":"Point"}
}