{
  "type": "Feature",
  "properties": {
    "iso:country":"US",
    "sg:address":"102 K St NW",
    "sg:city":"Ardmore",
    "sg:classifiers":[
        {
            "category":"Personal",
            "subcategory":"Beauty Salon",
            "type":"Services"
        }
    ],
    "sg:phone":"+1 580 226 0400",
    "sg:postcode":"73401",
    "sg:province":"OK",
    "sg:tags":[
        "shop"
    ],
    "wof:name":"Hair Etc",
    "wof:placetype":"venue"
},
  "geometry": {"coordinates":[-97.139926,34.177053],"type":"Point"}
}