{
  "type": "Feature",
  "properties": {
    "iso:country":"US",
    "sg:address":"3925 N Lincoln Blvd",
    "sg:city":"Oklahoma City",
    "sg:classifiers":[
        {
            "category":"Retail",
            "subcategory":"Laundry & Dry Cleaning",
            "type":"Services"
        }
    ],
    "sg:phone":"+1 405 525 2020",
    "sg:postcode":"73105",
    "sg:province":"OK",
    "sg:tags":[
        "drycleaning",
        "plant"
    ],
    "wof:name":"Capitol Cleaners & Laundry",
    "wof:placetype":"venue"
},
  "geometry": {"coordinates":[-97.50323299999999,35.511389],"type":"Point"}
}