{
  "type": "Feature",
  "properties": {
    "iso:country":"US",
    "sg:address":"1223 N Gardner Ave",
    "sg:city":"Oklahoma City",
    "sg:classifiers":[
        {
            "category":"Building & Trades",
            "subcategory":"Plumbing",
            "type":"Services"
        }
    ],
    "sg:phone":"+1 405 613 9897",
    "sg:postcode":"73127",
    "sg:province":"OK",
    "sg:tags":[
        "conditioning",
        "air",
        "system",
        "contractor"
    ],
    "wof:name":"Cain Heating Air Conditioning",
    "wof:placetype":"venue"
},
  "geometry": {"coordinates":[-97.630106,35.482033],"type":"Point"}
}