{
  "type": "Feature",
  "properties": {
    "addr:full":"7134 S Yale Ave Tulsa OK 74136",
    "addr:housenumber":"7134",
    "addr:postcode":"74136",
    "addr:street":"S Yale Ave",
    "iso:country":"US",
    "sg:address":"7134 S Yale Ave",
    "sg:city":"Tulsa",
    "sg:classifiers":[
        {
            "category":"Banks & Credit Unions",
            "subcategory":"Financial Services",
            "type":"Services"
        }
    ],
    "sg:phone":"+1 918 712 1866",
    "sg:postcode":"74136",
    "sg:province":"OK",
    "sg:tags":[
        "financing",
        "form",
        "for",
        "provide",
        "manage",
        "project",
        "to"
    ],
    "wof:name":"I4ei",
    "wof:placetype":"venue"
},
  "geometry": {"coordinates":[-95.922156,36.060497],"type":"Point"}
}