{
  "type": "Feature",
  "properties": {
    "iso:country":"US",
    "sg:address":"3315 S I- 35 Svc Rd",
    "sg:city":"Oklahoma City",
    "sg:classifiers":[
        {
            "category":"Home & Garden",
            "subcategory":"Furniture",
            "type":"Retail Goods"
        }
    ],
    "sg:phone":"+1 405 799 3000",
    "sg:postcode":"73129",
    "sg:province":"OK",
    "wof:name":"Statuary World Patio-Fireside",
    "wof:placetype":"venue"
},
  "geometry": {"coordinates":[-97.48660099999999,35.430606],"type":"Point"}
}