{
  "type": "Feature",
  "properties": {
    "iso:country":"US",
    "sg:address":"5147 S 94th East Ave",
    "sg:city":"Tulsa",
    "sg:classifiers":[
        {
            "category":"Retail",
            "subcategory":"Repair Shop",
            "type":"Services"
        }
    ],
    "sg:phone":"+1 918 622 1140",
    "sg:postcode":"74145",
    "sg:province":"OK",
    "sg:tags":[
        "equipment",
        "electronic",
        "supply"
    ],
    "wof:name":"Central Instrument Laboratory",
    "wof:placetype":"venue"
},
  "geometry": {"coordinates":[-95.872241,36.089024],"type":"Point"}
}