{
  "type": "Feature",
  "properties": {
    "iso:country":"US",
    "sg:address":"300 S 17th St",
    "sg:city":"Frederick",
    "sg:classifiers":[
        {
            "category":"Recreation",
            "type":"Entertainment"
        }
    ],
    "sg:phone":"+1 580 335 3671",
    "sg:postcode":"73542",
    "sg:province":"OK",
    "sg:tags":[
        "pool",
        "swimming"
    ],
    "wof:name":"Frederick Swimming Pool",
    "wof:placetype":"venue"
},
  "geometry": {"coordinates":[-99.008338,34.387389],"type":"Point"}
}