{
  "type": "Feature",
  "properties": {
    "addr:full":"5400 NW 23rd St Oklahoma City OK 73127",
    "addr:housenumber":"5400",
    "addr:postcode":"73127",
    "addr:street":"Nw 23Rd St",
    "iso:country":"US",
    "sg:address":"5400 NW 23rd St",
    "sg:city":"Oklahoma City",
    "sg:classifiers":[
        {
            "category":"Banks & Credit Unions",
            "subcategory":"Bank",
            "type":"Services"
        }
    ],
    "sg:phone":"+1 405 947 8100",
    "sg:postcode":"73127",
    "sg:province":"OK",
    "sg:tags":[
        "loan",
        "real estate"
    ],
    "wof:name":"Merchants Mortgage Banque",
    "wof:placetype":"venue"
},
  "geometry": {"coordinates":[-97.61042500000001,35.493211],"type":"Point"}
}