{
  "type": "Feature",
  "properties": {
    "addr:full":"511 College Ave Alva OK 73717",
    "addr:housenumber":"511",
    "addr:postcode":"73717",
    "addr:street":"College Ave",
    "iso:country":"US",
    "sg:address":"511 College Ave",
    "sg:city":"Alva",
    "sg:classifiers":[
        {
            "category":"Professional",
            "subcategory":"Accounting & Tax Preparation",
            "type":"Services"
        }
    ],
    "sg:phone":"+1 580 327 3580",
    "sg:postcode":"73717",
    "sg:province":"OK",
    "sg:tags":[
        "return",
        "filing"
    ],
    "wof:name":"H & R Block Tax Svc",
    "wof:placetype":"venue"
},
  "geometry": {"coordinates":[-98.666866,36.803636],"type":"Point"}
}