{
  "type": "Feature",
  "properties": {
    "addr:full":"721 N Perkins Rd Stillwater OK 74075",
    "addr:housenumber":"721",
    "addr:postcode":"74075",
    "addr:street":"N Perkins Rd",
    "iso:country":"US",
    "sg:address":"721 N Perkins Rd",
    "sg:city":"Stillwater",
    "sg:classifiers":[
        {
            "category":"Shopping",
            "subcategory":"Pharmacy",
            "type":"Retail Goods"
        }
    ],
    "sg:phone":"+1 405 624 8585",
    "sg:postcode":"74075",
    "sg:province":"OK",
    "wof:name":"May's Drug Store",
    "wof:placetype":"venue"
},
  "geometry": {"coordinates":[-97.051401,36.130367],"type":"Point"}
}