{
  "type": "Feature",
  "properties": {
    "iso:country":"US",
    "sg:address":"1703 Kingsbury Ln",
    "sg:city":"Oklahoma City",
    "sg:classifiers":[
        {
            "category":"Mining & Drilling",
            "type":"Manufacturing & Wholesale Goods"
        }
    ],
    "sg:phone":"+1 405 236 5175",
    "sg:postcode":"73116",
    "sg:province":"OK",
    "sg:tags":[
        "automobile",
        "gas",
        "parking"
    ],
    "wof:name":"City Parking",
    "wof:placetype":"venue"
},
  "geometry": {"coordinates":[-97.54849299999999,35.543988],"type":"Point"}
}