{
  "type": "Feature",
  "properties": {
    "addr:full":"2813 Pembroke Ter Oklahoma City OK 73116",
    "addr:housenumber":"2813",
    "addr:postcode":"73116",
    "addr:street":"Pembroke Ter",
    "iso:country":"US",
    "sg:address":"2813 Pembroke Ter",
    "sg:city":"Oklahoma City",
    "sg:classifiers":[
        {
            "category":"Building & Trades",
            "subcategory":"Construction",
            "type":"Services"
        }
    ],
    "sg:phone":"+1 405 840 2263",
    "sg:postcode":"73116",
    "sg:province":"OK",
    "sg:tags":[
        "glass",
        "work",
        "glazing"
    ],
    "wof:name":"Performance Technical Services",
    "wof:placetype":"venue"
},
  "geometry": {"coordinates":[-97.565434,35.546278],"type":"Point"}
}