{
  "type": "Feature",
  "properties": {
    "iso:country":"US",
    "sg:address":"4001 N Lincoln Blvd",
    "sg:city":"Oklahoma City",
    "sg:classifiers":[
        {
            "category":"Professional",
            "subcategory":"Accounting & Tax Preparation",
            "type":"Services"
        }
    ],
    "sg:phone":"+1 405 525 7705",
    "sg:postcode":"73105",
    "sg:province":"OK",
    "sg:tags":[
        "accountant"
    ],
    "wof:name":"Elizabeth's Business Svc",
    "wof:placetype":"venue"
},
  "geometry": {"coordinates":[-97.50313,35.512329],"type":"Point"}
}