{
  "type": "Feature",
  "properties": {
    "iso:country":"US",
    "sg:address":"117 E Davis Ave",
    "sg:city":"Weatherford",
    "sg:classifiers":[
        {
            "category":"Personal",
            "subcategory":"Beauty Salon",
            "type":"Services"
        }
    ],
    "sg:phone":"+1 580 774 2733",
    "sg:postcode":"73096",
    "sg:province":"OK",
    "wof:name":"Tips & Tangles",
    "wof:placetype":"venue"
},
  "geometry": {"coordinates":[-98.706981,35.537019],"type":"Point"}
}