{
  "type": "Feature",
  "properties": {
    "iso:country":"US",
    "sg:address":"8605 Gateway Ter",
    "sg:city":"Oklahoma City",
    "sg:classifiers":[
        {
            "category":"Building & Trades",
            "subcategory":"Construction",
            "type":"Services"
        }
    ],
    "sg:phone":"+1 405 636 1914",
    "sg:postcode":"73149",
    "sg:province":"OK",
    "sg:tags":[
        "fabricator",
        "metal"
    ],
    "wof:name":"Allstate Sheet Metal Inc",
    "wof:placetype":"venue"
},
  "geometry": {"coordinates":[-97.498333,35.37886],"type":"Point"}
}