{
  "type": "Feature",
  "properties": {
    "iso:country":"US",
    "sg:address":"1310 NW 47th St",
    "sg:city":"Lawton",
    "sg:classifiers":[
        {
            "category":"Personal",
            "subcategory":"Barber",
            "type":"Services"
        }
    ],
    "sg:phone":"+1 580 355 8926",
    "sg:postcode":"73505",
    "sg:province":"OK",
    "sg:tags":[
        "shop"
    ],
    "wof:name":"Astro Barber Shop",
    "wof:placetype":"venue"
},
  "geometry": {"coordinates":[-98.448671,34.623348],"type":"Point"}
}