{
  "type": "Feature",
  "properties": {
    "iso:country":"US",
    "sg:address":"501 N Main St",
    "sg:city":"Muskogee",
    "sg:classifiers":[
        {
            "category":"Food & Beverages",
            "subcategory":"Candy",
            "type":"Retail Goods"
        }
    ],
    "sg:phone":"+1 918 682 6831",
    "sg:postcode":"74401",
    "sg:province":"OK",
    "sg:tags":[
        "confectionery"
    ],
    "wof:name":"Candy Craze",
    "wof:placetype":"venue"
},
  "geometry": {"coordinates":[-95.366723,35.752663],"type":"Point"}
}