{
  "type": "Feature",
  "properties": {
    "iso:country":"US",
    "sg:address":"1414 E 71st St",
    "sg:city":"Tulsa",
    "sg:classifiers":[
        {
            "category":"Banks & Credit Unions",
            "subcategory":"Bank",
            "type":"Services"
        }
    ],
    "sg:phone":"+1 918 481 9600",
    "sg:postcode":"74136",
    "sg:province":"OK",
    "sg:tags":[
        "loan",
        "real estate"
    ],
    "wof:name":"Mortgage Capital Lending Inc",
    "wof:placetype":"venue"
},
  "geometry": {"coordinates":[-95.974378,36.060592],"type":"Point"}
}