{
  "type": "Feature",
  "properties": {
    "iso:country":"US",
    "sg:address":"606 W Main St",
    "sg:city":"Stigler",
    "sg:classifiers":[
        {
            "category":"Autos & Motor Vehicles",
            "subcategory":"Auto Supplies",
            "type":"Retail Goods"
        }
    ],
    "sg:phone":"+1 918 967 4491",
    "sg:postcode":"74462",
    "sg:province":"OK",
    "sg:tags":[
        "tire"
    ],
    "wof:name":"Stigler Tire",
    "wof:placetype":"venue"
},
  "geometry": {"coordinates":[-95.132527,35.255808],"type":"Point"}
}