{
  "type": "Feature",
  "properties": {
    "addr:full":"207 N Main St Bristow OK 74010",
    "addr:housenumber":"207",
    "addr:postcode":"74010",
    "addr:street":"N Main St",
    "iso:country":"US",
    "sg:address":"207 N Main St",
    "sg:city":"Bristow",
    "sg:classifiers":[
        {
            "category":"Shopping",
            "subcategory":"Discount & Variety Stores",
            "type":"Retail Goods"
        }
    ],
    "sg:phone":"+1 918 367 3100",
    "sg:postcode":"74010",
    "sg:province":"OK",
    "wof:name":"Dollar General",
    "wof:placetype":"venue"
},
  "geometry": {"coordinates":[-96.390912,35.834756],"type":"Point"}
}