{
  "type": "Feature",
  "properties": {
    "iso:country":"US",
    "sg:address":"322 N Greenwood Ave",
    "sg:city":"Tulsa",
    "sg:classifiers":[
        {
            "category":"Organizations",
            "subcategory":"Community Association",
            "type":"Services"
        }
    ],
    "sg:phone":"+1 918 596 1020",
    "sg:postcode":"74120",
    "sg:province":"OK",
    "sg:tags":[
        "cultural",
        "center"
    ],
    "wof:name":"Greenwood Cultural Center Inc",
    "wof:placetype":"venue"
},
  "geometry": {"coordinates":[-95.986565,36.162624],"type":"Point"}
}