{
  "type": "Feature",
  "properties": {
    "iso:country":"US",
    "sg:address":"4240 NW 23rd St",
    "sg:city":"Oklahoma City",
    "sg:classifiers":[
        {
            "category":"Personal",
            "subcategory":"Tanning Parlor",
            "type":"Services"
        }
    ],
    "sg:phone":"+1 405 948 9150",
    "sg:postcode":"73107",
    "sg:province":"OK",
    "sg:tags":[
        "salon"
    ],
    "wof:name":"Totally Tan",
    "wof:placetype":"venue"
},
  "geometry": {"coordinates":[-97.595618,35.493242],"type":"Point"}
}