{
  "type": "Feature",
  "properties": {
    "addr:full":"102 N 6th St Duncan OK 73533",
    "addr:housenumber":"102",
    "addr:postcode":"73533",
    "addr:street":"N 6Th St",
    "iso:country":"US",
    "sg:address":"102 N 6th St",
    "sg:city":"Duncan",
    "sg:classifiers":[
        {
            "category":"Retail",
            "subcategory":"Auto Repair",
            "type":"Services"
        }
    ],
    "sg:phone":"+1 580 255 6332",
    "sg:postcode":"73533",
    "sg:province":"OK",
    "sg:tags":[
        "wrecker"
    ],
    "wof:name":"Hall's Towing & Recovery",
    "wof:placetype":"venue"
},
  "geometry": {"coordinates":[-97.95377999999999,34.503516],"type":"Point"}
}