{
  "type": "Feature",
  "properties": {
    "addr:full":"706 S Berry Rd Norman OK 73069",
    "addr:housenumber":"706",
    "addr:postcode":"73069",
    "addr:street":"S Berry Rd",
    "iso:country":"US",
    "sg:address":"706 S Berry Rd",
    "sg:city":"Norman",
    "sg:classifiers":[
        {
            "category":"Health Services",
            "subcategory":"Doctor",
            "type":"Services"
        }
    ],
    "sg:phone":"+1 405 366 8207",
    "sg:postcode":"73069",
    "sg:province":"OK",
    "sg:tags":[
        "physician",
        "surgeon"
    ],
    "wof:name":"Haralson & Haralson Inc",
    "wof:placetype":"venue"
},
  "geometry": {"coordinates":[-97.459068,35.210544],"type":"Point"}
}