{
  "type": "Feature",
  "properties": {
    "addr:full":"1011 W Broadway St Ardmore OK 73401",
    "addr:housenumber":"1011",
    "addr:postcode":"73401",
    "addr:street":"W Broadway St",
    "iso:country":"US",
    "sg:address":"1011 W Broadway St",
    "sg:city":"Ardmore",
    "sg:classifiers":[
        {
            "category":"Shopping",
            "subcategory":"Clothing, Apparel, & Fashions",
            "type":"Retail Goods"
        }
    ],
    "sg:phone":"+1 580 223 2411",
    "sg:postcode":"73401",
    "sg:province":"OK",
    "sg:tags":[
        "wear"
    ],
    "wof:name":"Kiddie Land",
    "wof:placetype":"venue"
},
  "geometry": {"coordinates":[-97.141452,34.174587],"type":"Point"}
}