{
  "type": "Feature",
  "properties": {
    "iso:country":"US",
    "sg:address":"714 S 4th St",
    "sg:city":"Clinton",
    "sg:classifiers":[
        {
            "category":"Autos & Motor Vehicles",
            "subcategory":"Auto Supplies",
            "type":"Retail Goods"
        }
    ],
    "sg:phone":"+1 580 323 0807",
    "sg:postcode":"73601",
    "sg:province":"OK",
    "wof:name":"Weldon Parts Inc",
    "wof:placetype":"venue"
},
  "geometry": {"coordinates":[-98.96484700000001,35.50843],"type":"Point"}
}