{
  "type": "Feature",
  "properties": {
    "iso:country":"US",
    "sg:address":"402 E Main St",
    "sg:city":"Cordell",
    "sg:classifiers":[
        {
            "category":"Retail",
            "subcategory":"Repair Shop",
            "type":"Services"
        }
    ],
    "sg:phone":"+1 580 832 5213",
    "sg:postcode":"73632",
    "sg:province":"OK",
    "sg:tags":[
        "welding"
    ],
    "wof:name":"Western Welding",
    "wof:placetype":"venue"
},
  "geometry": {"coordinates":[-98.986365,35.291198],"type":"Point"}
}