{
  "type": "Feature",
  "properties": {
    "iso:country":"US",
    "sg:address":"6901 NW 23rd St",
    "sg:city":"Bethany",
    "sg:classifiers":[
        {
            "category":"Home & Garden",
            "subcategory":"Building Materials",
            "type":"Retail Goods"
        }
    ],
    "sg:phone":"+1 405 787 8847",
    "sg:postcode":"73127",
    "sg:province":"OK",
    "sg:tags":[
        "door"
    ],
    "wof:name":"Tailored Tuff",
    "wof:placetype":"venue"
},
  "geometry": {"coordinates":[-97.63453699999999,35.493356],"type":"Point"}
}