{
  "type": "Feature",
  "properties": {
    "iso:country":"US",
    "sg:address":"11115 E 109th St N",
    "sg:city":"Owasso",
    "sg:classifiers":[
        {
            "category":"Professional",
            "type":"Services"
        }
    ],
    "sg:phone":"+1 918 274 9922",
    "sg:postcode":"74055",
    "sg:province":"OK",
    "sg:tags":[
        "establishment"
    ],
    "wof:name":"Invision LLC",
    "wof:placetype":"venue"
},
  "geometry": {"coordinates":[-95.848989,36.312169],"type":"Point"}
}