{
  "type": "Feature",
  "properties": {
    "addr:full":"710 Valley Dr Sand Springs OK 74063",
    "addr:housenumber":"710",
    "addr:postcode":"74063",
    "addr:street":"Valley Dr",
    "iso:country":"US",
    "sg:address":"710 Valley Dr",
    "sg:city":"Sand Springs",
    "sg:classifiers":[
        {
            "category":"Building & Trades",
            "subcategory":"Construction",
            "type":"Services"
        }
    ],
    "sg:phone":"+1 918 245 8613",
    "sg:postcode":"74063",
    "sg:province":"OK",
    "sg:tags":[
        "c"
    ],
    "wof:name":"Graves Plumbing",
    "wof:placetype":"venue"
},
  "geometry": {"coordinates":[-96.121606,36.145217],"type":"Point"}
}