{
  "type": "Feature",
  "properties": {
    "iso:country":"US",
    "sg:address":"127 E Choctaw Ave",
    "sg:city":"Sallisaw",
    "sg:classifiers":[
        {
            "category":"Travel",
            "subcategory":"Hotels & Motels",
            "type":"Entertainment"
        }
    ],
    "sg:phone":"+1 918 775 7981",
    "sg:postcode":"74955",
    "sg:province":"OK",
    "wof:name":"Econo Lodge",
    "wof:placetype":"venue"
},
  "geometry": {"coordinates":[-94.789812,35.459597],"type":"Point"}
}