{
  "type": "Feature",
  "properties": {
    "iso:country":"US",
    "sg:address":"617 Vine St",
    "sg:city":"Chelsea",
    "sg:classifiers":[
        {
            "category":"Organizations",
            "subcategory":"Religious Organization",
            "type":"Services"
        }
    ],
    "sg:phone":"+1 918 789 5098",
    "sg:postcode":"74016",
    "sg:province":"OK",
    "sg:tags":[
        "church"
    ],
    "wof:name":"Church Of The Nazarene",
    "wof:placetype":"venue"
},
  "geometry": {"coordinates":[-95.433657,36.536175],"type":"Point"}
}