{
  "type": "Feature",
  "properties": {
    "iso:country":"US",
    "sg:address":"1001 W Wilshire Blvd",
    "sg:city":"Oklahoma City",
    "sg:classifiers":[
        {
            "category":"Banks & Credit Unions",
            "subcategory":"Bank",
            "type":"Services"
        }
    ],
    "sg:phone":"+1 405 842 3827",
    "sg:postcode":"73116",
    "sg:province":"OK",
    "sg:tags":[
        "state",
        "commercial"
    ],
    "wof:name":"American Bnk Trust of Edmond",
    "wof:placetype":"venue"
},
  "geometry": {"coordinates":[-97.531459,35.551114],"type":"Point"}
}