{
  "type": "Feature",
  "properties": {
    "addr:full":"4515 NW 10th St Oklahoma City OK 73127",
    "addr:housenumber":"4515",
    "addr:postcode":"73127",
    "addr:street":"Nw 10Th St",
    "iso:country":"US",
    "sg:address":"4515 NW 10th St",
    "sg:city":"Oklahoma City",
    "sg:classifiers":[
        {
            "category":"Shopping",
            "subcategory":"Used Merchandise",
            "type":"Retail Goods"
        }
    ],
    "sg:phone":"+1 405 917 5999",
    "sg:postcode":"73127",
    "sg:province":"OK",
    "sg:tags":[
        "shop",
        "thrift"
    ],
    "wof:name":"St Vincent De Paul Thrift",
    "wof:placetype":"venue"
},
  "geometry": {"coordinates":[-97.603075,35.47885],"type":"Point"}
}