{
  "type": "Feature",
  "properties": {
    "iso:country":"US",
    "sg:address":"15101 S Peebly Rd",
    "sg:city":"Newalla",
    "sg:classifiers":[
        {
            "category":"Organizations",
            "subcategory":"Community Association",
            "type":"Services"
        }
    ],
    "sg:phone":"+1 405 386 3506",
    "sg:postcode":"74857",
    "sg:province":"OK",
    "sg:tags":[
        "club",
        "restaurant"
    ],
    "wof:name":"Country Lounge Saloon",
    "wof:placetype":"venue"
},
  "geometry": {"coordinates":[-97.21248199999999,35.318228],"type":"Point"}
}