{
  "type": "Feature",
  "properties": {
    "addr:full":"6315 SW 3rd St Oklahoma City OK 73128",
    "addr:housenumber":"6315",
    "addr:postcode":"73128",
    "addr:street":"Sw 3Rd St",
    "iso:country":"US",
    "sg:address":"6315 SW 3rd St",
    "sg:city":"Oklahoma City",
    "sg:classifiers":[
        {
            "category":"Shopping",
            "subcategory":"Shoes",
            "type":"Retail Goods"
        }
    ],
    "sg:phone":"+1 405 787 1653",
    "sg:postcode":"73128",
    "sg:province":"OK",
    "wof:name":"Shoe Carnival",
    "wof:placetype":"venue"
},
  "geometry": {"coordinates":[-97.62336500000001,35.461467],"type":"Point"}
}