{
  "type": "Feature",
  "properties": {
    "addr:full":"9116 NE 23rd St Oklahoma City OK 73141",
    "addr:housenumber":"9116",
    "addr:postcode":"73141",
    "addr:street":"Ne 23Rd St",
    "iso:country":"US",
    "sg:address":"9116 NE 23rd St",
    "sg:city":"Oklahoma City",
    "sg:classifiers":[
        {
            "category":"Autos & Motor Vehicles",
            "subcategory":"Auto Supplies",
            "type":"Retail Goods"
        }
    ],
    "sg:phone":"+1 405 769 2073",
    "sg:postcode":"73141",
    "sg:province":"OK",
    "sg:tags":[
        "automobile",
        "parts"
    ],
    "wof:name":"Autozone",
    "wof:placetype":"venue"
},
  "geometry": {"coordinates":[-97.36808000000001,35.492971],"type":"Point"}
}