{
  "type": "Feature",
  "properties": {
    "iso:country":"US",
    "sg:address":"6912 S Forest Ridge Blvd",
    "sg:city":"Broken Arrow",
    "sg:classifiers":[
        {
            "category":"Professional",
            "subcategory":"Accounting & Tax Preparation",
            "type":"Services"
        }
    ],
    "sg:phone":"+1 918 357 3165",
    "sg:postcode":"74014",
    "sg:province":"OK",
    "wof:name":"Kraig Kannard Accounting",
    "wof:placetype":"venue"
},
  "geometry": {"coordinates":[-95.70292499999999,36.047174],"type":"Point"}
}