{
  "type": "Feature",
  "properties": {
    "iso:country":"US",
    "sg:address":"1325 E Boone St",
    "sg:city":"Tahlequah",
    "sg:classifiers":[
        {
            "category":"Social Services",
            "type":"Services"
        }
    ],
    "sg:phone":"+1 918 456 3188",
    "sg:postcode":"74464",
    "sg:province":"OK",
    "sg:tags":[
        "counselor",
        "marriage",
        "family"
    ],
    "wof:name":"Mark Jones",
    "wof:placetype":"venue"
},
  "geometry": {"coordinates":[-94.95198,35.912677],"type":"Point"}
}