{
  "type": "Feature",
  "properties": {
    "addr:full":"508 Freedom Rd Edmond OK 73025",
    "addr:housenumber":"508",
    "addr:postcode":"73025",
    "addr:street":"Freedom Rd",
    "iso:country":"US",
    "sg:address":"508 Freedom Rd",
    "sg:city":"Edmond",
    "sg:classifiers":[
        {
            "category":"Building & Trades",
            "subcategory":"Construction",
            "type":"Services"
        }
    ],
    "sg:phone":"+1 405 340 8109",
    "sg:postcode":"73025",
    "sg:province":"OK",
    "sg:tags":[
        "house"
    ],
    "wof:name":"Aldrich Construction",
    "wof:placetype":"venue"
},
  "geometry": {"coordinates":[-97.49245000000001,35.75529],"type":"Point"}
}