{
  "type": "Feature",
  "properties": {
    "iso:country":"US",
    "sg:address":"1020 S D St",
    "sg:city":"Muskogee",
    "sg:classifiers":[
        {
            "category":"Retail",
            "subcategory":"Repair Shop",
            "type":"Services"
        }
    ],
    "sg:phone":"+1 918 682 0855",
    "sg:postcode":"74403",
    "sg:province":"OK",
    "sg:tags":[
        "appliance"
    ],
    "wof:name":"Tito's Appliance",
    "wof:placetype":"venue"
},
  "geometry": {"coordinates":[-95.368512,35.735963],"type":"Point"}
}