{
  "type": "Feature",
  "properties": {
    "addr:full":"3830 W N Ave Ponca City OK 74601",
    "addr:housenumber":"3830",
    "addr:postcode":"74601",
    "addr:street":"W N Ave",
    "iso:country":"US",
    "sg:address":"3830 W N Ave",
    "sg:city":"Ponca City",
    "sg:classifiers":[
        {
            "category":"Manufacturing",
            "subcategory":"Signs",
            "type":"Manufacturing & Wholesale Goods"
        }
    ],
    "sg:phone":"+1 580 765 5000",
    "sg:postcode":"74601",
    "sg:province":"OK",
    "sg:tags":[
        "equipment",
        "specialty",
        "mfg"
    ],
    "wof:name":"Combs Auction & Signs",
    "wof:placetype":"venue"
},
  "geometry": {"coordinates":[-97.135459,36.680781],"type":"Point"}
}