{
  "type": "Feature",
  "properties": {
    "iso:country":"US",
    "sg:address":"532 E Seminole St",
    "sg:city":"Tulsa",
    "sg:classifiers":[
        {
            "category":"Restaurant",
            "type":"Food & Drink"
        }
    ],
    "sg:phone":"+1 918 583 6971",
    "sg:postcode":"74106",
    "sg:province":"OK",
    "sg:tags":[
        "eating"
    ],
    "wof:name":"Tes Place Inc",
    "wof:placetype":"venue"
},
  "geometry": {"coordinates":[-95.98868,36.180439],"type":"Point"}
}