{
  "type": "Feature",
  "properties": {
    "addr:full":"641 Harrison St Pawnee OK 74058",
    "addr:housenumber":"641",
    "addr:postcode":"74058",
    "addr:street":"Harrison St",
    "iso:country":"US",
    "sg:address":"641 Harrison St",
    "sg:city":"Pawnee",
    "sg:classifiers":[
        {
            "category":"Home & Garden",
            "subcategory":"Furniture",
            "type":"Retail Goods"
        }
    ],
    "sg:phone":"+1 918 762 3174",
    "sg:postcode":"74058",
    "sg:province":"OK",
    "sg:tags":[
        "ha",
        "household",
        "floor",
        "appliance",
        "covering"
    ],
    "wof:name":"Spears Furniture Inc",
    "wof:placetype":"venue"
},
  "geometry": {"coordinates":[-96.804602,36.337817],"type":"Point"}
}