{
  "type": "Feature",
  "properties": {
    "addr:full":"515 S Santa Fe Ave Edmond OK 73003",
    "addr:housenumber":"515",
    "addr:postcode":"73003",
    "addr:street":"S Santa Fe Ave",
    "iso:country":"US",
    "sg:address":"515 S Santa Fe Ave",
    "sg:city":"Edmond",
    "sg:classifiers":[
        {
            "category":"Professional",
            "subcategory":"Detective & Security Services",
            "type":"Services"
        }
    ],
    "sg:phone":"+1 405 359 0514",
    "sg:postcode":"73003",
    "sg:province":"OK",
    "sg:tags":[
        "development",
        "asset",
        "real estate"
    ],
    "wof:name":"Real Estate Interest LLC",
    "wof:placetype":"venue"
},
  "geometry": {"coordinates":[-97.51397299999999,35.649396],"type":"Point"}
}