{
  "type": "Feature",
  "properties": {
    "iso:country":"US",
    "sg:address":"7628 E 46th St",
    "sg:city":"Tulsa",
    "sg:classifiers":[
        {
            "category":"Building & Trades",
            "subcategory":"Construction",
            "type":"Services"
        }
    ],
    "sg:phone":"+1 918 621 1020",
    "sg:postcode":"74145",
    "sg:province":"OK",
    "sg:tags":[
        "repairing",
        "remodeling",
        "contractor"
    ],
    "wof:name":"Residential Repair Inc",
    "wof:placetype":"venue"
},
  "geometry": {"coordinates":[-95.886778,36.097715],"type":"Point"}
}