{
  "type": "Feature",
  "properties": {
    "iso:country":"US",
    "sg:address":"3621 NW 50th St",
    "sg:city":"Oklahoma City",
    "sg:classifiers":[
        {
            "category":"Retail",
            "subcategory":"Portrait Studio",
            "type":"Services"
        }
    ],
    "sg:phone":"+1 405 942 5135",
    "sg:postcode":"73112",
    "sg:province":"OK",
    "sg:tags":[
        "photo",
        "photography"
    ],
    "wof:name":"Gordon Dinsmore Studio Inc",
    "wof:placetype":"venue"
},
  "geometry": {"coordinates":[-97.582358,35.522338],"type":"Point"}
}