{
  "type": "Feature",
  "properties": {
    "addr:full":"2472 N Yale Ave Tulsa OK 74115",
    "addr:housenumber":"2472",
    "addr:postcode":"74115",
    "addr:street":"N Yale Ave",
    "iso:country":"US",
    "sg:address":"2472 N Yale Ave",
    "sg:city":"Tulsa",
    "sg:classifiers":[
        {
            "category":"Food & Beverages",
            "subcategory":"Liquor & Beverages",
            "type":"Retail Goods"
        }
    ],
    "sg:phone":"+1 918 834 1318",
    "sg:postcode":"74115",
    "sg:province":"OK",
    "sg:tags":[
        "alcoholic"
    ],
    "wof:name":"Apache Junction Liquor Store",
    "wof:placetype":"venue"
},
  "geometry": {"coordinates":[-95.922614,36.188245],"type":"Point"}
}