{
  "type": "Feature",
  "properties": {
    "iso:country":"US",
    "sg:address":"701 N Broadway Ave",
    "sg:city":"Oklahoma City",
    "sg:classifiers":[
        {
            "category":"Professional",
            "subcategory":"Lawyer & Legal Services",
            "type":"Services"
        }
    ],
    "sg:phone":"+1 405 232 8185",
    "sg:postcode":"73102",
    "sg:province":"OK",
    "sg:tags":[
        "attorney"
    ],
    "wof:name":"Doug Aldridge",
    "wof:placetype":"venue"
},
  "geometry": {"coordinates":[-97.51419799999999,35.475025],"type":"Point"}
}