{
  "type": "Feature",
  "properties": {
    "iso:country":"US",
    "sg:address":"16 S 8th St",
    "sg:city":"Duncan",
    "sg:classifiers":[
        {
            "category":"Social Services",
            "type":"Services"
        }
    ],
    "sg:phone":"+1 580 255 3648",
    "sg:postcode":"73533",
    "sg:province":"OK",
    "sg:tags":[
        "organization",
        "welfare"
    ],
    "wof:name":"United Way",
    "wof:placetype":"venue"
},
  "geometry": {"coordinates":[-97.956681,34.501621],"type":"Point"}
}