{
  "type": "Feature",
  "properties": {
    "addr:full":"100 Wolf St Valliant OK 74764",
    "addr:housenumber":"100",
    "addr:postcode":"74764",
    "addr:street":"Wolf St",
    "iso:country":"US",
    "sg:address":"100 Wolf St",
    "sg:city":"Valliant",
    "sg:classifiers":[
        {
            "category":"Real Estate",
            "subcategory":"Real Estate Operator",
            "type":"Services"
        }
    ],
    "sg:phone":"+1 580 933 7525",
    "sg:postcode":"74764",
    "sg:province":"OK",
    "sg:tags":[
        "apartment"
    ],
    "wof:name":"Valliant Apartments",
    "wof:placetype":"venue"
},
  "geometry": {"coordinates":[-95.09187300000001,34.000687],"type":"Point"}
}