{
  "type": "Feature",
  "properties": {
    "iso:country":"US",
    "sg:address":"510 W Rogers Blvd",
    "sg:city":"Skiatook",
    "sg:classifiers":[
        {
            "category":"Home & Garden",
            "subcategory":"Household Appliances",
            "type":"Retail Goods"
        }
    ],
    "sg:phone":"+1 918 396 1008",
    "sg:postcode":"74070",
    "sg:province":"OK",
    "wof:name":"Lake Country Appl & Sleep Ctr",
    "wof:placetype":"venue"
},
  "geometry": {"coordinates":[-96.008312,36.368668],"type":"Point"}
}