{
  "type": "Feature",
  "properties": {
    "addr:full":"401 W Main St Norman OK 73069",
    "addr:housenumber":"401",
    "addr:postcode":"73069",
    "addr:street":"W Main St",
    "iso:country":"US",
    "sg:address":"401 W Main St",
    "sg:city":"Norman",
    "sg:classifiers":[
        {
            "category":"Building & Trades",
            "subcategory":"Equipment Rental",
            "type":"Services"
        }
    ],
    "sg:phone":"+1 405 321 4600",
    "sg:postcode":"73069",
    "sg:province":"OK",
    "sg:tags":[
        "leasing"
    ],
    "wof:name":"Republic Bank & Trust",
    "wof:placetype":"venue"
},
  "geometry": {"coordinates":[-97.449479,35.21837],"type":"Point"}
}