{
  "type": "Feature",
  "properties": {
    "addr:full":"421 W 5th Ave Stillwater OK 74074",
    "addr:housenumber":"421",
    "addr:postcode":"74074",
    "addr:street":"W 5Th Ave",
    "iso:country":"US",
    "sg:address":"421 W 5th Ave",
    "sg:city":"Stillwater",
    "sg:classifiers":[
        {
            "category":"Professional",
            "subcategory":"Business Services",
            "type":"Services"
        }
    ],
    "sg:phone":"+1 405 377 5609",
    "sg:postcode":"74074",
    "sg:province":"OK",
    "sg:tags":[
        "organization",
        "membership"
    ],
    "wof:name":"International Society Inc",
    "wof:placetype":"venue"
},
  "geometry": {"coordinates":[-97.062909,36.116659],"type":"Point"}
}