{
  "type": "Feature",
  "properties": {
    "iso:country":"US",
    "sg:address":"3131 N Macarthur Blvd",
    "sg:city":"Oklahoma City",
    "sg:classifiers":[
        {
            "category":"Social Services",
            "type":"Services"
        }
    ],
    "sg:phone":"+1 405 495 9500",
    "sg:postcode":"73122",
    "sg:province":"OK",
    "sg:tags":[
        "stress",
        "management"
    ],
    "wof:name":"Break-Through",
    "wof:placetype":"venue"
},
  "geometry": {"coordinates":[-97.619063,35.501204],"type":"Point"}
}