{
  "type": "Feature",
  "properties": {
    "iso:country":"US",
    "sg:address":"136 S Wilson St",
    "sg:city":"Vinita",
    "sg:classifiers":[
        {
            "category":"Shopping",
            "subcategory":"Gifts & Souvenirs",
            "type":"Retail Goods"
        }
    ],
    "sg:phone":"+1 918 256 2233",
    "sg:postcode":"74301",
    "sg:province":"OK",
    "sg:tags":[
        "novelty"
    ],
    "wof:name":"Jannets Gifts",
    "wof:placetype":"venue"
},
  "geometry": {"coordinates":[-95.15475,36.638063],"type":"Point"}
}