{
  "type": "Feature",
  "properties": {
    "iso:country":"US",
    "sg:address":"701 S Broadway",
    "sg:city":"Edmond",
    "sg:classifiers":[
        {
            "category":"Health Services",
            "subcategory":"Optometrist",
            "type":"Services"
        }
    ],
    "sg:phone":"+1 405 341 7055",
    "sg:postcode":"73034",
    "sg:province":"OK",
    "wof:name":"Sight To See Vision Assoc",
    "wof:placetype":"venue"
},
  "geometry": {"coordinates":[-97.482207,35.64694],"type":"Point"}
}