{
  "type": "Feature",
  "properties": {
    "addr:full":"4602 Fairfield Dr Stillwater OK 74074",
    "addr:housenumber":"4602",
    "addr:postcode":"74074",
    "addr:street":"Fairfield Dr",
    "iso:country":"US",
    "sg:address":"4602 Fairfield Dr",
    "sg:city":"Stillwater",
    "sg:classifiers":[
        {
            "category":"Real Estate",
            "subcategory":"Real Estate Agent",
            "type":"Services"
        }
    ],
    "sg:phone":"+1 405 743 0096",
    "sg:postcode":"74074",
    "sg:province":"OK",
    "wof:name":"Mtr Property",
    "wof:placetype":"venue"
},
  "geometry": {"coordinates":[-97.12025,36.103908],"type":"Point"}
}