{
  "type": "Feature",
  "properties": {
    "addr:full":"1905 S Eastern Ave Oklahoma City OK 73129",
    "addr:housenumber":"1905",
    "addr:postcode":"73129",
    "addr:street":"S Eastern Ave",
    "iso:country":"US",
    "sg:address":"1905 S Eastern Ave",
    "sg:city":"Oklahoma City",
    "sg:classifiers":[
        {
            "category":"Professional",
            "subcategory":"Testing Lab",
            "type":"Services"
        }
    ],
    "sg:phone":"+1 405 912 8908",
    "sg:postcode":"73129",
    "sg:province":"OK",
    "sg:tags":[
        "asbestos"
    ],
    "wof:name":"Air & Earth",
    "wof:placetype":"venue"
},
  "geometry": {"coordinates":[-97.47701499999999,35.44256],"type":"Point"}
}