{
  "type": "Feature",
  "properties": {
    "iso:country":"US",
    "sg:address":"3714 N Portland Ave",
    "sg:city":"Oklahoma City",
    "sg:classifiers":[
        {
            "category":"Health Services",
            "subcategory":"Nursing And Care Facility",
            "type":"Services"
        }
    ],
    "sg:phone":"+1 405 942 8999",
    "sg:postcode":"73112",
    "sg:province":"OK",
    "sg:tags":[
        "hospice"
    ],
    "wof:name":"City Hospice",
    "wof:placetype":"venue"
},
  "geometry": {"coordinates":[-97.58333,35.50795],"type":"Point"}
}