{
  "type": "Feature",
  "properties": {
    "iso:country":"US",
    "sg:address":"905 W Main St",
    "sg:city":"Duncan",
    "sg:classifiers":[
        {
            "category":"Wholesale",
            "subcategory":"Jewelry",
            "type":"Manufacturing & Wholesale Goods"
        }
    ],
    "sg:phone":"+1 580 252 4949",
    "sg:postcode":"73533",
    "sg:province":"OK",
    "sg:tags":[
        "jeweler"
    ],
    "wof:name":"Diana's Wholesale Jewelry",
    "wof:placetype":"venue"
},
  "geometry": {"coordinates":[-97.959742,34.502133],"type":"Point"}
}