{
  "type": "Feature",
  "properties": {
    "iso:country":"US",
    "sg:address":"12200 E 86th St N",
    "sg:city":"Owasso",
    "sg:classifiers":[
        {
            "category":"Social Services",
            "subcategory":"Child Care",
            "type":"Services"
        }
    ],
    "sg:phone":"+1 918 272 2560",
    "sg:postcode":"74055",
    "sg:province":"OK",
    "sg:tags":[
        "kindergarten",
        "academic",
        "school"
    ],
    "wof:name":"Our Little Saints",
    "wof:placetype":"venue"
},
  "geometry": {"coordinates":[-95.838486,36.278419],"type":"Point"}
}