{
  "type": "Feature",
  "properties": {
    "addr:full":"1234 Locust St Alva OK 73717",
    "addr:housenumber":"1234",
    "addr:postcode":"73717",
    "addr:street":"Locust St",
    "iso:country":"US",
    "sg:address":"1234 Locust St",
    "sg:city":"Alva",
    "sg:phone":"+1 580 327 5706",
    "sg:postcode":"73717",
    "sg:province":"OK",
    "sg:tags":[
        "farm",
        "wheat",
        "beef",
        "feedlot",
        "cattle"
    ],
    "wof:name":"Benders Farms",
    "wof:placetype":"venue"
},
  "geometry": {"coordinates":[-98.677031,36.800179],"type":"Point"}
}