{
  "type": "Feature",
  "properties": {
    "iso:country":"US",
    "sg:address":"4111 S Darlington Ave",
    "sg:city":"Tulsa",
    "sg:classifiers":[
        {
            "category":"Professional",
            "subcategory":"Lawyer & Legal Services",
            "type":"Services"
        }
    ],
    "sg:phone":"+1 918 660 0400",
    "sg:postcode":"74135",
    "sg:province":"OK",
    "sg:tags":[
        "attorney"
    ],
    "sg:website":"www.bbl.cc",
    "wof:name":"Boettcher Boettcher & Lobaugh",
    "wof:placetype":"venue"
},
  "geometry": {"coordinates":[-95.917178,36.103459],"type":"Point"}
}