{
  "type": "Feature",
  "properties": {
    "addr:full":"2213 N Key Blvd Midwest City OK 73110",
    "addr:housenumber":"2213",
    "addr:postcode":"73110",
    "addr:street":"N Key Blvd",
    "iso:country":"US",
    "sg:address":"2213 N Key Blvd",
    "sg:city":"Midwest City",
    "sg:classifiers":[
        {
            "category":"Professional",
            "subcategory":"Detective & Security Services",
            "type":"Services"
        }
    ],
    "sg:phone":"+1 405 741 2107",
    "sg:postcode":"73110",
    "sg:province":"OK",
    "sg:tags":[
        "guard",
        "patrol"
    ],
    "wof:name":"Barham Security & Invstgtn",
    "wof:placetype":"venue"
},
  "geometry": {"coordinates":[-97.397935,35.459694],"type":"Point"}
}