{
  "type": "Feature",
  "properties": {
    "iso:country":"US",
    "sg:address":"601 S 4th St",
    "sg:city":"Chickasha",
    "sg:classifiers":[
        {
            "category":"Food & Beverages",
            "subcategory":"Bakery",
            "type":"Retail Goods"
        }
    ],
    "sg:phone":"+1 405 224 2907",
    "sg:postcode":"73018",
    "sg:province":"OK",
    "sg:tags":[
        "product",
        "mfg"
    ],
    "wof:name":"Paradise Doughnuts",
    "wof:placetype":"venue"
},
  "geometry": {"coordinates":[-97.936863,35.045215],"type":"Point"}
}