{
  "type": "Feature",
  "properties": {
    "addr:full":"605 E Tyler Dr Tuttle OK 73089",
    "addr:housenumber":"605",
    "addr:postcode":"73089",
    "addr:street":"E Tyler Dr",
    "iso:country":"US",
    "sg:address":"605 E Tyler Dr",
    "sg:city":"Tuttle",
    "sg:classifiers":[
        {
            "category":"Home & Garden",
            "subcategory":"Building Materials",
            "type":"Retail Goods"
        }
    ],
    "sg:phone":"+1 405 381 3802",
    "sg:postcode":"73089",
    "sg:province":"OK",
    "wof:name":"Plumbline",
    "wof:placetype":"venue"
},
  "geometry": {"coordinates":[-97.801053,35.305422],"type":"Point"}
}