{
  "type": "Feature",
  "properties": {
    "iso:country":"US",
    "sg:address":"923 W University Ave",
    "sg:city":"Stillwater",
    "sg:classifiers":[
        {
            "category":"Travel",
            "subcategory":"Hotels & Motels",
            "type":"Entertainment"
        }
    ],
    "sg:phone":"+1 405 372 6689",
    "sg:postcode":"74074",
    "sg:province":"OK",
    "sg:tags":[
        "membership",
        "association",
        "lodging"
    ],
    "wof:name":"Lambda Chi Alpha Fraternity",
    "wof:placetype":"venue"
},
  "geometry": {"coordinates":[-97.070364,36.119614],"type":"Point"}
}