{
  "type": "Feature",
  "properties": {
    "addr:full":"4101 S Garnett Rd Tulsa OK 74146",
    "addr:housenumber":"4101",
    "addr:postcode":"74146",
    "addr:street":"S Garnett Rd",
    "iso:country":"US",
    "sg:address":"4101 S Garnett Rd",
    "sg:city":"Tulsa",
    "sg:classifiers":[
        {
            "category":"Banks & Credit Unions",
            "subcategory":"Bank",
            "type":"Services"
        }
    ],
    "sg:phone":"+1 918 586 8930",
    "sg:postcode":"74146",
    "sg:province":"OK",
    "sg:tags":[
        "national"
    ],
    "sg:website":"www.bankone.com",
    "wof:name":"Bank One",
    "wof:placetype":"venue"
},
  "geometry": {"coordinates":[-95.851044,36.101773],"type":"Point"}
}