{
  "type": "Feature",
  "properties": {
    "addr:full":"119 S Elm Afton OK 74331",
    "addr:housenumber":"119",
    "addr:postcode":"74331",
    "addr:street":"S Elm",
    "iso:country":"US",
    "sg:address":"119 S Elm",
    "sg:city":"Afton",
    "sg:classifiers":[
        {
            "category":"Professional",
            "type":"Services"
        }
    ],
    "sg:phone":"+1 918 256 2772",
    "sg:postcode":"74331",
    "sg:province":"OK",
    "wof:name":"Cimaron Protective Svc",
    "wof:placetype":"venue"
},
  "geometry": {"coordinates":[-94.958573,36.694704],"type":"Point"}
}