{
  "type": "Feature",
  "properties": {
    "addr:full":"4825 S Peoria Ave Tulsa OK 74105",
    "addr:housenumber":"4825",
    "addr:postcode":"74105",
    "addr:street":"S Peoria Ave",
    "iso:country":"US",
    "sg:address":"4825 S Peoria Ave",
    "sg:city":"Tulsa",
    "sg:classifiers":[
        {
            "category":"Communications",
            "subcategory":"Film & Video Production",
            "type":"Services"
        }
    ],
    "sg:phone":"+1 918 743 3600",
    "sg:postcode":"74105",
    "sg:province":"OK",
    "sg:tags":[
        "audio"
    ],
    "wof:name":"White Graphics Inc",
    "wof:placetype":"venue"
},
  "geometry": {"coordinates":[-95.97565400000001,36.093386],"type":"Point"}
}