{
  "type": "Feature",
  "properties": {
    "iso:country":"US",
    "sg:address":"406 Maple Ave",
    "sg:city":"Yukon",
    "sg:classifiers":[
        {
            "category":"Professional",
            "subcategory":"Management & Consulting",
            "type":"Services"
        }
    ],
    "sg:phone":"+1 405 350 9582",
    "sg:postcode":"73099",
    "sg:province":"OK",
    "sg:tags":[
        "consultant",
        "business"
    ],
    "wof:name":"Professional Resources Inc",
    "wof:placetype":"venue"
},
  "geometry": {"coordinates":[-97.750504,35.505676],"type":"Point"}
}