{
  "type": "Feature",
  "properties": {
    "addr:full":"18237 W Jones Rd Tahlequah OK 74464",
    "addr:housenumber":"18237",
    "addr:postcode":"74464",
    "addr:street":"W Jones Rd",
    "iso:country":"US",
    "sg:address":"18237 W Jones Rd",
    "sg:city":"Tahlequah",
    "sg:classifiers":[
        {
            "category":"Retail",
            "subcategory":"Auto Repair",
            "type":"Services"
        },
        {
            "category":"Wholesale",
            "subcategory":"Auto Parts",
            "type":"Manufacturing & Wholesale Goods"
        }
    ],
    "sg:phone":"+1 918 458 0837",
    "sg:postcode":"74464",
    "sg:province":"OK",
    "sg:tags":[
        "body",
        "automobile",
        "used",
        "painting"
    ],
    "wof:name":"Mast Auto Salvage",
    "wof:placetype":"venue"
},
  "geometry": {"coordinates":[-94.97066700000001,35.973315],"type":"Point"}
}