{
  "type": "Feature",
  "properties": {
    "addr:full":"5500 Douglas Ln Bartlesville OK 74006",
    "addr:housenumber":"5500",
    "addr:postcode":"74006",
    "addr:street":"Douglas Ln",
    "iso:country":"US",
    "sg:address":"5500 Douglas Ln",
    "sg:city":"Bartlesville",
    "sg:classifiers":[
        {
            "category":"Organizations",
            "subcategory":"Religious Organization",
            "type":"Services"
        }
    ],
    "sg:phone":"+1 918 335 0844",
    "sg:postcode":"74006",
    "sg:province":"OK",
    "sg:tags":[
        "church"
    ],
    "wof:name":"Saint James Catholic Church",
    "wof:placetype":"venue"
},
  "geometry": {"coordinates":[-95.915466,36.733426],"type":"Point"}
}