{
  "type": "Feature",
  "properties": {
    "addr:full":"1742 N Beaver St Guymon OK 73942",
    "addr:housenumber":"1742",
    "addr:postcode":"73942",
    "addr:street":"N Beaver St",
    "iso:country":"US",
    "sg:address":"1742 N Beaver St",
    "sg:city":"Guymon",
    "sg:classifiers":[
        {
            "category":"Building & Trades",
            "subcategory":"Plumbing",
            "type":"Services"
        }
    ],
    "sg:phone":"+1 580 338 5487",
    "sg:postcode":"73942",
    "sg:province":"OK",
    "sg:tags":[
        "contractor"
    ],
    "wof:name":"Purdys Sprinkler System",
    "wof:placetype":"venue"
},
  "geometry": {"coordinates":[-101.488135,36.697758],"type":"Point"}
}