{
  "type": "Feature",
  "properties": {
    "iso:country":"US",
    "sg:address":"1013 E 8th St",
    "sg:city":"Okmulgee",
    "sg:classifiers":[
        {
            "category":"Insurance",
            "subcategory":"Insurance Agent",
            "type":"Services"
        }
    ],
    "sg:phone":"+1 918 756 5000",
    "sg:postcode":"74447",
    "sg:province":"OK",
    "wof:name":"Jon J Giddings Insurance",
    "wof:placetype":"venue"
},
  "geometry": {"coordinates":[-95.9602,35.621394],"type":"Point"}
}