{
  "type": "Feature",
  "properties": {
    "iso:country":"US",
    "sg:address":"2836 NW 68th St",
    "sg:city":"Oklahoma City",
    "sg:classifiers":[
        {
            "category":"Restaurant",
            "type":"Food & Drink"
        }
    ],
    "sg:phone":"+1 405 848 8337",
    "sg:postcode":"73116",
    "sg:province":"OK",
    "wof:name":"Ted's Cafe Escondido",
    "wof:placetype":"venue"
},
  "geometry": {"coordinates":[-97.56450599999999,35.540496],"type":"Point"}
}