{
  "type": "Feature",
  "properties": {
    "iso:country":"US",
    "sg:address":"2710 Hilltop Ave",
    "sg:city":"Muskogee",
    "sg:classifiers":[
        {
            "category":"Professional",
            "subcategory":"Business Services",
            "type":"Services"
        }
    ],
    "sg:phone":"+1 918 687 4755",
    "sg:postcode":"74403",
    "sg:province":"OK",
    "wof:name":"Specialty Snacks Distributing",
    "wof:placetype":"venue"
},
  "geometry": {"coordinates":[-95.334703,35.732027],"type":"Point"}
}