{
  "type": "Feature",
  "properties": {
    "addr:full":"4631 S Quincy Pl Tulsa OK 74105",
    "addr:housenumber":"4631",
    "addr:postcode":"74105",
    "addr:street":"S Quincy Pl",
    "iso:country":"US",
    "sg:address":"4631 S Quincy Pl",
    "sg:city":"Tulsa",
    "sg:classifiers":[
        {
            "category":"Banks & Credit Unions",
            "subcategory":"Financial Services",
            "type":"Services"
        }
    ],
    "sg:phone":"+1 918 743 0569",
    "sg:postcode":"74105",
    "sg:province":"OK",
    "sg:tags":[
        "investor"
    ],
    "wof:name":"Proffitts Land & Inv LLC",
    "wof:placetype":"venue"
},
  "geometry": {"coordinates":[-95.971763,36.095403],"type":"Point"}
}