{
  "type": "Feature",
  "properties": {
    "iso:country":"US",
    "sg:address":"310 W Cleveland Ave",
    "sg:city":"Ponca City",
    "sg:classifiers":[
        {
            "category":"Insurance",
            "subcategory":"Insurance Agent",
            "type":"Services"
        }
    ],
    "sg:phone":"+1 580 762 8351",
    "sg:postcode":"74601",
    "sg:province":"OK",
    "wof:name":"Whitlock Insurance",
    "wof:placetype":"venue"
},
  "geometry": {"coordinates":[-97.087817,36.704789],"type":"Point"}
}