{
  "type": "Feature",
  "properties": {
    "addr:full":"2026 W Skelly Dr Tulsa OK 74107",
    "addr:housenumber":"2026",
    "addr:postcode":"74107",
    "addr:street":"W Skelly Dr",
    "iso:country":"US",
    "sg:address":"2026 W Skelly Dr",
    "sg:city":"Tulsa",
    "sg:classifiers":[
        {
            "category":"Social Services",
            "type":"Services"
        }
    ],
    "sg:phone":"+1 918 447 0880",
    "sg:postcode":"74107",
    "sg:province":"OK",
    "sg:tags":[
        "center",
        "community"
    ],
    "wof:name":"Relations Group Home",
    "wof:placetype":"venue"
},
  "geometry": {"coordinates":[-96.018928,36.088651],"type":"Point"}
}