{
  "type": "Feature",
  "properties": {
    "iso:country":"US",
    "sg:address":"110 W 141st St",
    "sg:city":"Glenpool",
    "sg:classifiers":[
        {
            "category":"Restaurant",
            "type":"Food & Drink"
        }
    ],
    "sg:menulink":"http://www.allmenus.com/ok/south-tulsa/196748-mcdonalds/menu/",
    "sg:postcode":"74033",
    "sg:province":"OK",
    "sg:tags":[
        "burger",
        "american"
    ],
    "wof:name":"McDonald's",
    "wof:placetype":"venue"
},
  "geometry": {"coordinates":[-96.009608,35.958672],"type":"Point"}
}