{
  "type": "Feature",
  "properties": {
    "addr:full":"2709 S Aspen Ct Broken Arrow OK 74012",
    "addr:housenumber":"2709",
    "addr:postcode":"74012",
    "addr:street":"S Aspen Ct",
    "iso:country":"US",
    "sg:address":"2709 S Aspen Ct",
    "sg:city":"Broken Arrow",
    "sg:classifiers":[
        {
            "category":"Retail",
            "subcategory":"Repair Shop",
            "type":"Services"
        }
    ],
    "sg:phone":"+1 918 449 9822",
    "sg:postcode":"74012",
    "sg:province":"OK",
    "wof:name":"Beckys Bucket N Brooms",
    "wof:placetype":"venue"
},
  "geometry": {"coordinates":[-95.815956,36.027006],"type":"Point"}
}