{
  "type": "Feature",
  "properties": {
    "iso:country":"US",
    "sg:address":"14617 N Pennsylvania Ave",
    "sg:city":"Oklahoma City",
    "sg:classifiers":[
        {
            "category":"Organizations",
            "subcategory":"Religious Organization",
            "type":"Services"
        }
    ],
    "sg:phone":"+1 405 755 9477",
    "sg:postcode":"73134",
    "sg:province":"OK",
    "sg:tags":[
        "church"
    ],
    "sg:website":"www.qsumc.org",
    "wof:name":"Quail Springs United Methodist",
    "wof:placetype":"venue"
},
  "geometry": {"coordinates":[-97.549584,35.618238],"type":"Point"}
}