{
  "type": "Feature",
  "properties": {
    "iso:country":"US",
    "sg:address":"3408 French Park Dr",
    "sg:city":"Edmond",
    "sg:classifiers":[
        {
            "category":"Mining & Drilling",
            "type":"Manufacturing & Wholesale Goods"
        }
    ],
    "sg:phone":"+1 405 844 1991",
    "sg:postcode":"73034",
    "sg:province":"OK",
    "sg:tags":[
        "development",
        "gas",
        "oil",
        "exploration"
    ],
    "wof:name":"Aexco Petroleum Inc",
    "wof:placetype":"venue"
},
  "geometry": {"coordinates":[-97.436319,35.651898],"type":"Point"}
}