{
  "type": "Feature",
  "properties": {
    "addr:full":"830 Grand Ave NW Ardmore OK 73401",
    "addr:housenumber":"830",
    "addr:postcode":"73401",
    "addr:street":"Grand Ave Nw",
    "iso:country":"US",
    "sg:address":"830 Grand Ave NW",
    "sg:city":"Ardmore",
    "sg:classifiers":[
        {
            "category":"Building & Trades",
            "subcategory":"Equipment Rental",
            "type":"Services"
        }
    ],
    "sg:phone":"+1 580 226 7878",
    "sg:postcode":"73401",
    "sg:province":"OK",
    "sg:tags":[
        "medical"
    ],
    "wof:name":"Lincare Homecare Med Systems",
    "wof:placetype":"venue"
},
  "geometry": {"coordinates":[-97.13808400000001,34.178937],"type":"Point"}
}