{
  "type": "Feature",
  "properties": {
    "iso:country":"US",
    "sg:address":"507 E Crisler Ave",
    "sg:city":"Mcalester",
    "sg:classifiers":[
        {
            "category":"Insurance",
            "subcategory":"Hazard Insurance",
            "type":"Services"
        }
    ],
    "sg:phone":"+1 918 423 6355",
    "sg:postcode":"74501",
    "sg:province":"OK",
    "sg:tags":[
        "bond"
    ],
    "wof:name":"Kathy Rae's Bail Bonds",
    "wof:placetype":"venue"
},
  "geometry": {"coordinates":[-95.757649,34.949556],"type":"Point"}
}