{
  "type": "Feature",
  "properties": {
    "iso:country":"US",
    "sg:address":"15606 S Memorial Dr",
    "sg:city":"Bixby",
    "sg:classifiers":[
        {
            "category":"Retail",
            "subcategory":"Veterinary Services",
            "type":"Services"
        }
    ],
    "sg:phone":"+1 918 366 3330",
    "sg:postcode":"74008",
    "sg:province":"OK",
    "sg:tags":[
        "veterinarian"
    ],
    "wof:name":"Cottom Veterinary Clinic",
    "wof:placetype":"venue"
},
  "geometry": {"coordinates":[-95.886593,35.937252],"type":"Point"}
}