{
  "type": "Feature",
  "properties": {
    "iso:country":"US",
    "sg:address":"11087 W 81st St S",
    "sg:city":"Sapulpa",
    "sg:classifiers":[
        {
            "category":"Professional",
            "subcategory":"Art Services",
            "type":"Services"
        }
    ],
    "sg:phone":"+1 817 846 8526",
    "sg:postcode":"74066",
    "sg:province":"OK",
    "sg:tags":[
        "commercial",
        "design"
    ],
    "wof:name":"Lawsons Designs",
    "wof:placetype":"venue"
},
  "geometry": {"coordinates":[-96.11636799999999,36.046545],"type":"Point"}
}