{
  "type": "Feature",
  "properties": {
    "iso:country":"US",
    "sg:address":"3925 SE 29th St",
    "sg:city":"Oklahoma City",
    "sg:classifiers":[
        {
            "category":"Organizations",
            "subcategory":"Community Association",
            "type":"Services"
        }
    ],
    "sg:phone":"+1 405 677 3174",
    "sg:postcode":"73115",
    "sg:province":"OK",
    "sg:tags":[
        "club"
    ],
    "wof:name":"Del City Lions Club",
    "wof:placetype":"venue"
},
  "geometry": {"coordinates":[-97.444316,35.435231],"type":"Point"}
}