{
  "type": "Feature",
  "properties": {
    "iso:country":"US",
    "sg:address":"4409 Hidden Hill Rd",
    "sg:city":"Norman",
    "sg:classifiers":[
        {
            "category":"Professional",
            "subcategory":"Business Services",
            "type":"Services"
        }
    ],
    "sg:phone":"+1 405 329 7500",
    "sg:postcode":"73072",
    "sg:province":"OK",
    "wof:name":"Woodrow K Glass",
    "wof:placetype":"venue"
},
  "geometry": {"coordinates":[-97.506484,35.241642],"type":"Point"}
}