{
  "type": "Feature",
  "properties": {
    "addr:full":"524 W Will Rogers Blvd Claremore OK 74017",
    "addr:housenumber":"524",
    "addr:postcode":"74017",
    "addr:street":"W Will Rogers Blvd",
    "iso:country":"US",
    "sg:address":"524 W Will Rogers Blvd",
    "sg:city":"Claremore",
    "sg:classifiers":[
        {
            "category":"Social Services",
            "type":"Services"
        }
    ],
    "sg:phone":"+1 918 343 2960",
    "sg:postcode":"74017",
    "sg:province":"OK",
    "sg:tags":[
        "organization",
        "welfare"
    ],
    "wof:name":"Community Action Head Start",
    "wof:placetype":"venue"
},
  "geometry": {"coordinates":[-95.61572,36.312506],"type":"Point"}
}