{
  "type": "Feature",
  "properties": {
    "iso:country":"US",
    "sg:address":"4922 NW 23rd St",
    "sg:city":"Oklahoma City",
    "sg:classifiers":[
        {
            "category":"Retail",
            "subcategory":"Repair Shop",
            "type":"Services"
        }
    ],
    "sg:phone":"+1 405 524 6366",
    "sg:postcode":"73127",
    "sg:province":"OK",
    "sg:tags":[
        "sign"
    ],
    "wof:name":"Signfxr-Neonfxr & Lighting Svc",
    "wof:placetype":"venue"
},
  "geometry": {"coordinates":[-97.612202,35.493207],"type":"Point"}
}