{
  "type": "Feature",
  "properties": {
    "addr:full":"8500 E 2nd St Edmond OK 73034",
    "addr:housenumber":"8500",
    "addr:postcode":"73034",
    "addr:street":"E 2Nd St",
    "iso:country":"US",
    "sg:address":"8500 E 2nd St",
    "sg:city":"Edmond",
    "sg:classifiers":[
        {
            "category":"Government",
            "subcategory":"Office",
            "type":"Public Place"
        }
    ],
    "sg:phone":"+1 405 396 8026",
    "sg:postcode":"73034",
    "sg:province":"OK",
    "sg:tags":[
        "federal"
    ],
    "wof:name":"US Army Corps Of Engineers",
    "wof:placetype":"venue"
},
  "geometry": {"coordinates":[-97.367277,35.652625],"type":"Point"}
}