{
  "type": "Feature",
  "properties": {
    "iso:country":"US",
    "sg:address":"207 E Highland Ave",
    "sg:city":"Ponca City",
    "sg:classifiers":[
        {
            "category":"Food & Beverages",
            "subcategory":"Groceries & Convenience Stores",
            "type":"Retail Goods"
        }
    ],
    "sg:phone":"+1 580 765 9678",
    "sg:postcode":"74601",
    "sg:province":"OK",
    "wof:name":"K & O Quickshop",
    "wof:placetype":"venue"
},
  "geometry": {"coordinates":[-97.082204,36.709801],"type":"Point"}
}