{
  "type": "Feature",
  "properties": {
    "addr:full":"12101 N Macarthur Blvd Oklahoma City OK 73162",
    "addr:housenumber":"12101",
    "addr:postcode":"73162",
    "addr:street":"N Macarthur Blvd",
    "iso:country":"US",
    "sg:address":"12101 N Macarthur Blvd",
    "sg:city":"Oklahoma City",
    "sg:classifiers":[
        {
            "category":"Personal",
            "type":"Services"
        }
    ],
    "sg:phone":"+1 405 773 1146",
    "sg:postcode":"73162",
    "sg:province":"OK",
    "wof:name":"Catspajamas At Home Inc",
    "wof:placetype":"venue"
},
  "geometry": {"coordinates":[-97.620689,35.592964],"type":"Point"}
}