{
  "type": "Feature",
  "properties": {
    "iso:country":"US",
    "sg:address":"15 E 4th St",
    "sg:city":"Edmond",
    "sg:classifiers":[
        {
            "category":"Personal",
            "subcategory":"Beauty Salon",
            "type":"Services"
        }
    ],
    "sg:phone":"+1 405 340 9700",
    "sg:postcode":"73034",
    "sg:province":"OK",
    "wof:name":"Dream Weaver Spa Salon",
    "wof:placetype":"venue"
},
  "geometry": {"coordinates":[-97.480331,35.651059],"type":"Point"}
}