{
  "type": "Feature",
  "properties": {
    "addr:full":"1140 SE 29th St Oklahoma City OK 73129",
    "addr:housenumber":"1140",
    "addr:postcode":"73129",
    "addr:street":"Se 29Th St",
    "iso:country":"US",
    "sg:address":"1140 SE 29th St",
    "sg:city":"Oklahoma City",
    "sg:classifiers":[
        {
            "category":"Retail",
            "subcategory":"Repair Shop",
            "type":"Services"
        },
        {
            "category":"Wholesale",
            "subcategory":"Electrical",
            "type":"Manufacturing & Wholesale Goods"
        }
    ],
    "sg:phone":"+1 405 672 3616",
    "sg:postcode":"73129",
    "sg:province":"OK",
    "sg:tags":[
        "equipment",
        "industrial",
        "meter"
    ],
    "wof:name":"Morris Instruments and Contrls",
    "wof:placetype":"venue"
},
  "geometry": {"coordinates":[-97.49447499999999,35.435249],"type":"Point"}
}