{
  "type": "Feature",
  "properties": {
    "iso:country":"US",
    "sg:address":"2828 NW 57th St",
    "sg:city":"Oklahoma City",
    "sg:classifiers":[
        {
            "category":"Professional",
            "subcategory":"Management & Consulting",
            "type":"Services"
        }
    ],
    "sg:phone":"+1 405 858 4995",
    "sg:postcode":"73112",
    "sg:province":"OK",
    "sg:tags":[
        "employee",
        "consultant",
        "benefit"
    ],
    "wof:name":"Covenant Benefits Group",
    "wof:placetype":"venue"
},
  "geometry": {"coordinates":[-97.564968,35.529711],"type":"Point"}
}