{
  "type": "Feature",
  "properties": {
    "addr:full":"825 N Broadway Ave Oklahoma City OK 73102",
    "addr:housenumber":"825",
    "addr:postcode":"73102",
    "addr:street":"N Broadway Ave",
    "iso:country":"US",
    "sg:address":"825 N Broadway Ave",
    "sg:city":"Oklahoma City",
    "sg:classifiers":[
        {
            "category":"Professional",
            "subcategory":"Management & Consulting",
            "type":"Services"
        }
    ],
    "sg:phone":"+1 405 235 3500",
    "sg:postcode":"73102",
    "sg:province":"OK",
    "sg:tags":[
        "public",
        "relations"
    ],
    "wof:name":"Automobile Alley Main Street",
    "wof:placetype":"venue"
},
  "geometry": {"coordinates":[-97.51424299999999,35.475815],"type":"Point"}
}