{
  "type": "Feature",
  "properties": {
    "iso:country":"US",
    "sg:address":"3600 SW 104th St",
    "sg:city":"Oklahoma City",
    "sg:classifiers":[
        {
            "category":"Restaurant",
            "type":"Food & Drink"
        }
    ],
    "sg:phone":"+1 405 691 2484",
    "sg:postcode":"73159",
    "sg:province":"OK",
    "wof:name":"Hi-Way Grill",
    "wof:placetype":"venue"
},
  "geometry": {"coordinates":[-97.580653,35.363062],"type":"Point"}
}