{
  "type": "Feature",
  "properties": {
    "iso:country":"US",
    "sg:address":"4252 S 74th East Ave",
    "sg:city":"Tulsa",
    "sg:classifiers":[
        {
            "category":"Building & Trades",
            "subcategory":"Electrical",
            "type":"Services"
        }
    ],
    "sg:phone":"+1 918 622 0334",
    "sg:postcode":"74145",
    "sg:province":"OK",
    "sg:tags":[
        "electric",
        "contractor"
    ],
    "wof:name":"Meek's Electrical Svc Inc",
    "wof:placetype":"venue"
},
  "geometry": {"coordinates":[-95.894715,36.101519],"type":"Point"}
}