{
  "type": "Feature",
  "properties": {
    "addr:full":"1030 W 7th St Elk City OK 73644",
    "addr:housenumber":"1030",
    "addr:postcode":"73644",
    "addr:street":"W 7Th St",
    "iso:country":"US",
    "sg:address":"1030 W 7th St",
    "sg:city":"Elk City",
    "sg:classifiers":[
        {
            "category":"Travel",
            "subcategory":"Hotels & Motels",
            "type":"Entertainment"
        }
    ],
    "sg:phone":"+1 580 225 3048",
    "sg:postcode":"73644",
    "sg:province":"OK",
    "sg:tags":[
        "breakfast",
        "accommodation",
        "bed"
    ],
    "wof:name":"Standifer House Bed",
    "wof:placetype":"venue"
},
  "geometry": {"coordinates":[-99.415628,35.407379],"type":"Point"}
}