{
  "type": "Feature",
  "properties": {
    "iso:country":"US",
    "sg:address":"5805 E 68th St",
    "sg:city":"Stillwater",
    "sg:classifiers":[
        {
            "category":"Building & Trades",
            "subcategory":"Landscaping Services",
            "type":"Services"
        }
    ],
    "sg:phone":"+1 405 377 0909",
    "sg:postcode":"74074",
    "sg:province":"OK",
    "sg:tags":[
        "topsoil"
    ],
    "wof:name":"Joe Brown Sand & Gravel",
    "wof:placetype":"venue"
},
  "geometry": {"coordinates":[-96.980188,36.043589],"type":"Point"}
}