{
  "type": "Feature",
  "properties": {
    "iso:country":"US",
    "sg:address":"9214 S 46th W Ave",
    "sg:city":"Tulsa",
    "sg:classifiers":[
        {
            "category":"Manufacturing",
            "subcategory":"Printing",
            "type":"Manufacturing & Wholesale Goods"
        }
    ],
    "sg:phone":"+1 918 227 3082",
    "sg:postcode":"74132",
    "sg:province":"OK",
    "sg:tags":[
        "book"
    ],
    "wof:name":"Natural Meals In Minutes",
    "wof:placetype":"venue"
},
  "geometry": {"coordinates":[-96.043483,36.031926],"type":"Point"}
}