{
  "type": "Feature",
  "properties": {
    "iso:country":"US",
    "sg:address":"5555 N Grand Blvd",
    "sg:city":"Oklahoma City",
    "sg:classifiers":[
        {
            "category":"Insurance",
            "subcategory":"Life Insurance",
            "type":"Services"
        }
    ],
    "sg:phone":"+1 405 948 4460",
    "sg:postcode":"73112",
    "sg:province":"OK",
    "sg:tags":[
        "carrier"
    ],
    "wof:name":"Ing Life Insur & Annuity Co",
    "wof:placetype":"venue"
},
  "geometry": {"coordinates":[-97.577898,35.525823],"type":"Point"}
}