{
  "type": "Feature",
  "properties": {
    "iso:country":"US",
    "sg:address":"502 E K Pl",
    "sg:city":"Jenks",
    "sg:classifiers":[
        {
            "category":"Social Services",
            "type":"Services"
        }
    ],
    "sg:phone":"+1 918 298 3785",
    "sg:postcode":"74037",
    "sg:province":"OK",
    "sg:tags":[
        "youth",
        "organization",
        "center"
    ],
    "wof:name":"Jenks Baseball Inc",
    "wof:placetype":"venue"
},
  "geometry": {"coordinates":[-95.962611,36.031989],"type":"Point"}
}