{
  "type": "Feature",
  "properties": {
    "addr:full":"5930 NW 39th St Oklahoma City OK 73122",
    "addr:housenumber":"5930",
    "addr:postcode":"73122",
    "addr:street":"Nw 39Th St",
    "iso:country":"US",
    "sg:address":"5930 NW 39th St",
    "sg:city":"Oklahoma City",
    "sg:classifiers":[
        {
            "category":"Retail",
            "subcategory":"Veterinary Services",
            "type":"Services"
        }
    ],
    "sg:phone":"+1 405 789 3646",
    "sg:postcode":"73122",
    "sg:province":"OK",
    "wof:name":"Spay Clinic",
    "wof:placetype":"venue"
},
  "geometry": {"coordinates":[-97.621216,35.511091],"type":"Point"}
}