{
  "type": "Feature",
  "properties": {
    "addr:full":"3005 Forestridge Pl Enid OK 73701",
    "addr:housenumber":"3005",
    "addr:postcode":"73701",
    "addr:street":"Forestridge Pl",
    "iso:country":"US",
    "sg:address":"3005 Forestridge Pl",
    "sg:city":"Enid",
    "sg:classifiers":[
        {
            "category":"Professional",
            "type":"Services"
        }
    ],
    "sg:phone":"+1 580 237 7163",
    "sg:postcode":"73701",
    "sg:province":"OK",
    "wof:name":"Aid Assoc For Lutherans",
    "wof:placetype":"venue"
},
  "geometry": {"coordinates":[-97.834636,36.384777],"type":"Point"}
}