{
  "type": "Feature",
  "properties": {
    "iso:country":"US",
    "sg:address":"2200 S 1st St",
    "sg:city":"Broken Arrow",
    "sg:classifiers":[
        {
            "category":"Organizations",
            "subcategory":"Religious Organization",
            "type":"Services"
        }
    ],
    "sg:phone":"+1 918 451 0226",
    "sg:postcode":"74012",
    "sg:province":"OK",
    "sg:tags":[
        "church"
    ],
    "wof:name":"Kingdom Hall-Jehovahs Witness",
    "wof:placetype":"venue"
},
  "geometry": {"coordinates":[-95.790039,36.026256],"type":"Point"}
}