{
  "type": "Feature",
  "properties": {
    "addr:full":"9501 NE 16th St Midwest City OK 73130",
    "addr:housenumber":"9501",
    "addr:postcode":"73130",
    "addr:street":"Ne 16Th St",
    "iso:country":"US",
    "sg:address":"9501 NE 16th St",
    "sg:city":"Midwest City",
    "sg:classifiers":[
        {
            "category":"Professional",
            "subcategory":"Business Services",
            "type":"Services"
        }
    ],
    "sg:phone":"+1 405 737 0511",
    "sg:postcode":"73130",
    "sg:province":"OK",
    "sg:tags":[
        "notary"
    ],
    "wof:name":"A Traveling Notary Service",
    "wof:placetype":"venue"
},
  "geometry": {"coordinates":[-97.361253,35.485876],"type":"Point"}
}