{
  "type": "Feature",
  "properties": {
    "addr:full":"556 N Denver Ave Tulsa OK 74103",
    "addr:housenumber":"556",
    "addr:postcode":"74103",
    "addr:street":"N Denver Ave",
    "iso:country":"US",
    "sg:address":"556 N Denver Ave",
    "sg:city":"Tulsa",
    "sg:classifiers":[
        {
            "category":"Retail",
            "subcategory":"Laundry & Dry Cleaning",
            "type":"Services"
        }
    ],
    "sg:phone":"+1 918 584 7612",
    "sg:postcode":"74103",
    "sg:province":"OK",
    "sg:tags":[
        "cleaners"
    ],
    "wof:name":"Denver Cleaners",
    "wof:placetype":"venue"
},
  "geometry": {"coordinates":[-95.999515,36.162087],"type":"Point"}
}