{
  "type": "Feature",
  "properties": {
    "addr:full":"1535 E Marshall St Tulsa OK 74106",
    "addr:housenumber":"1535",
    "addr:postcode":"74106",
    "addr:street":"E Marshall St",
    "iso:country":"US",
    "sg:address":"1535 E Marshall St",
    "sg:city":"Tulsa",
    "sg:classifiers":[
        {
            "category":"Manufacturing",
            "subcategory":"Tools & Machinery",
            "type":"Manufacturing & Wholesale Goods"
        }
    ],
    "sg:phone":"+1 918 582 2616",
    "sg:postcode":"74106",
    "sg:province":"OK",
    "sg:tags":[
        "machine",
        "shop"
    ],
    "wof:name":"Space Tech Inc",
    "wof:placetype":"venue"
},
  "geometry": {"coordinates":[-95.96957399999999,36.172094],"type":"Point"}
}