{
  "type": "Feature",
  "properties": {
    "addr:full":"11020 E 166th St N Collinsville OK 74021",
    "addr:housenumber":"11020",
    "addr:postcode":"74021",
    "addr:street":"E 166Th St N",
    "iso:country":"US",
    "sg:address":"11020 E 166th St N",
    "sg:city":"Collinsville",
    "sg:classifiers":[
        {
            "category":"Manufacturing",
            "subcategory":"Tools & Machinery",
            "type":"Manufacturing & Wholesale Goods"
        }
    ],
    "sg:phone":"+1 918 371 4153",
    "sg:postcode":"74021",
    "sg:province":"OK",
    "sg:tags":[
        "shop",
        "repair",
        "industrial",
        "mfg",
        "machine",
        "welding"
    ],
    "wof:name":"S & S Machine Shop Inc",
    "wof:placetype":"venue"
},
  "geometry": {"coordinates":[-95.852591,36.394576],"type":"Point"}
}