{
  "type": "Feature",
  "properties": {
    "addr:full":"304 S Hayes Ave Wagoner OK 74467",
    "addr:housenumber":"304",
    "addr:postcode":"74467",
    "addr:street":"S Hayes Ave",
    "iso:country":"US",
    "sg:address":"304 S Hayes Ave",
    "sg:city":"Wagoner",
    "sg:classifiers":[
        {
            "category":"Professional",
            "subcategory":"Accounting & Tax Preparation",
            "type":"Services"
        }
    ],
    "sg:phone":"+1 918 485 2733",
    "sg:postcode":"74467",
    "sg:province":"OK",
    "sg:tags":[
        "return"
    ],
    "wof:name":"Sam Alexander CPA",
    "wof:placetype":"venue"
},
  "geometry": {"coordinates":[-95.393911,35.957874],"type":"Point"}
}