{
  "type": "Feature",
  "properties": {
    "addr:full":"126 State Hwy 152 Mustang OK 73064",
    "addr:housenumber":"126",
    "addr:postcode":"73064",
    "addr:street":"State Hwy 152",
    "iso:country":"US",
    "sg:address":"126 State Hwy 152",
    "sg:city":"Mustang",
    "sg:classifiers":[
        {
            "category":"Retail",
            "subcategory":"Repair Shop",
            "type":"Services"
        }
    ],
    "sg:phone":"+1 405 376 0548",
    "sg:postcode":"73064",
    "sg:province":"OK",
    "wof:name":"Out West Taxidermy",
    "wof:placetype":"venue"
},
  "geometry": {"coordinates":[-97.723664,35.391678],"type":"Point"}
}