{
  "type": "Feature",
  "properties": {
    "iso:country":"US",
    "sg:address":"2902 S Yale Ave",
    "sg:city":"Tulsa",
    "sg:classifiers":[
        {
            "category":"Organizations",
            "subcategory":"Religious Organization",
            "type":"Services"
        }
    ],
    "sg:phone":"+1 918 744 6895",
    "sg:postcode":"74114",
    "sg:province":"OK",
    "sg:tags":[
        "church"
    ],
    "wof:name":"Memorial Baptist Church Actvty",
    "wof:placetype":"venue"
},
  "geometry": {"coordinates":[-95.922446,36.119853],"type":"Point"}
}