{
  "type": "Feature",
  "properties": {
    "iso:country":"US",
    "sg:address":"21 Slagle Rd",
    "sg:city":"Newalla",
    "sg:classifiers":[
        {
            "category":"Retail",
            "subcategory":"Animal Services",
            "type":"Services"
        }
    ],
    "sg:phone":"+1 405 391 4869",
    "sg:postcode":"74857",
    "sg:province":"OK",
    "sg:tags":[
        "pet",
        "grooming",
        "washing"
    ],
    "wof:name":"Impression Pet Grooming",
    "wof:placetype":"venue"
},
  "geometry": {"coordinates":[-97.203835,35.442081],"type":"Point"}
}