{
  "type": "Feature",
  "properties": {
    "iso:country":"US",
    "sg:address":"5400 N May Ave",
    "sg:city":"Oklahoma City",
    "sg:classifiers":[
        {
            "category":"Retail",
            "subcategory":"Photofinishing",
            "type":"Services"
        }
    ],
    "sg:phone":"+1 405 942 0189",
    "sg:postcode":"73112",
    "sg:province":"OK",
    "sg:tags":[
        "photo",
        "finishing"
    ],
    "wof:name":"Qualex T-43 One Hour Photo Lab",
    "wof:placetype":"venue"
},
  "geometry": {"coordinates":[-97.565552,35.524858],"type":"Point"}
}