{
  "type": "Feature",
  "properties": {
    "addr:full":"201 S Adair St Pryor OK 74361",
    "addr:housenumber":"201",
    "addr:postcode":"74361",
    "addr:street":"S Adair St",
    "iso:country":"US",
    "sg:address":"201 S Adair St",
    "sg:city":"Pryor",
    "sg:classifiers":[
        {
            "category":"Professional",
            "subcategory":"Accounting & Tax Preparation",
            "type":"Services"
        }
    ],
    "sg:phone":"+1 918 825 3332",
    "sg:postcode":"74361",
    "sg:province":"OK",
    "sg:tags":[
        "return",
        "filing"
    ],
    "wof:name":"H & R Block Tax Svc",
    "wof:placetype":"venue"
},
  "geometry": {"coordinates":[-95.31844,36.303999],"type":"Point"}
}