{
  "type": "Feature",
  "properties": {
    "iso:country":"US",
    "sg:address":"124 S Franklin St",
    "sg:city":"Colbert",
    "sg:classifiers":[
        {
            "category":"Personal",
            "subcategory":"Barber",
            "type":"Services"
        }
    ],
    "sg:phone":"+1 580 296 2600",
    "sg:postcode":"74733",
    "sg:province":"OK",
    "sg:tags":[
        "shop"
    ],
    "wof:name":"Angies Hair Studio",
    "wof:placetype":"venue"
},
  "geometry": {"coordinates":[-96.502923,33.853054],"type":"Point"}
}