{
  "type": "Feature",
  "properties": {
    "iso:country":"US",
    "sg:address":"808 N 15th St",
    "sg:city":"Broken Arrow",
    "sg:classifiers":[
        {
            "category":"Shopping",
            "type":"Retail Goods"
        }
    ],
    "sg:phone":"+1 918 258 7727",
    "sg:postcode":"74012",
    "sg:province":"OK",
    "sg:tags":[
        "spa",
        "housing",
        "family",
        "contractor"
    ],
    "wof:name":"Spas-N-Such",
    "wof:placetype":"venue"
},
  "geometry": {"coordinates":[-95.770687,36.059132],"type":"Point"}
}