{
  "type": "Feature",
  "properties": {
    "iso:country":"US",
    "sg:address":"2704 S Meridian Ave",
    "sg:city":"Oklahoma City",
    "sg:classifiers":[
        {
            "category":"Retail",
            "subcategory":"Auto Rental",
            "type":"Services"
        }
    ],
    "sg:phone":"+1 405 685 4340",
    "sg:postcode":"73108",
    "sg:province":"OK",
    "sg:tags":[
        "renting",
        "automobile"
    ],
    "wof:name":"Budget Rent A Car",
    "wof:placetype":"venue"
},
  "geometry": {"coordinates":[-97.60097,35.437654],"type":"Point"}
}