{
  "type": "Feature",
  "properties": {
    "addr:full":"115 S 2nd Ave Purcell OK 73080",
    "addr:housenumber":"115",
    "addr:postcode":"73080",
    "addr:street":"S 2Nd Ave",
    "iso:country":"US",
    "sg:address":"115 S 2nd Ave",
    "sg:city":"Purcell",
    "sg:classifiers":[
        {
            "category":"Education",
            "subcategory":"Dance Studio",
            "type":"Public Place"
        }
    ],
    "sg:phone":"+1 405 527 0566",
    "sg:postcode":"73080",
    "sg:province":"OK",
    "sg:tags":[
        "instruction",
        "dancing"
    ],
    "wof:name":"Purcell Dance Ctr",
    "wof:placetype":"venue"
},
  "geometry": {"coordinates":[-97.36118500000001,35.012024],"type":"Point"}
}