{
  "type": "Feature",
  "properties": {
    "iso:country":"US",
    "sg:address":"3501 N 14th St",
    "sg:city":"Ponca City",
    "sg:classifiers":[
        {
            "category":"Autos & Motor Vehicles",
            "subcategory":"Automobile Sales",
            "type":"Retail Goods"
        }
    ],
    "sg:phone":"+1 580 765 2511",
    "sg:postcode":"74604",
    "sg:province":"OK",
    "wof:name":"Davis Moore Auto Group Inc",
    "wof:placetype":"venue"
},
  "geometry": {"coordinates":[-97.067275,36.745875],"type":"Point"}
}