{
  "type": "Feature",
  "properties": {
    "addr:full":"8703 W 81st St S Tulsa OK 74131",
    "addr:housenumber":"8703",
    "addr:postcode":"74131",
    "addr:street":"W 81St St",
    "iso:country":"US",
    "sg:address":"8703 W 81st St S",
    "sg:city":"Tulsa",
    "sg:classifiers":[
        {
            "category":"Real Estate",
            "subcategory":"Real Estate Operator",
            "type":"Services"
        }
    ],
    "sg:phone":"+1 918 224 7704",
    "sg:postcode":"74131",
    "sg:province":"OK",
    "sg:tags":[
        "mobile",
        "home",
        "site"
    ],
    "wof:name":"Windmill Properties Inc",
    "wof:placetype":"venue"
},
  "geometry": {"coordinates":[-96.087209,36.04659],"type":"Point"}
}