{
  "type": "Feature",
  "properties": {
    "iso:country":"US",
    "sg:address":"203 N Crumley St",
    "sg:city":"Guymon",
    "sg:classifiers":[
        {
            "category":"Autos & Motor Vehicles",
            "subcategory":"Auto Supplies",
            "type":"Retail Goods"
        }
    ],
    "sg:phone":"+1 580 338 6960",
    "sg:postcode":"73942",
    "sg:province":"OK",
    "sg:tags":[
        "automobile",
        "parts"
    ],
    "wof:name":"Ralstin's Parts Drive In",
    "wof:placetype":"venue"
},
  "geometry": {"coordinates":[-101.478888,36.679924],"type":"Point"}
}