{
  "type": "Feature",
  "properties": {
    "iso:country":"US",
    "sg:address":"110 N Elm St",
    "sg:city":"Sallisaw",
    "sg:classifiers":[
        {
            "category":"Utilities",
            "subcategory":"Natural Gas",
            "type":"Services"
        }
    ],
    "sg:phone":"+1 918 775 6275",
    "sg:postcode":"74955",
    "sg:province":"OK",
    "wof:name":"A O G",
    "wof:placetype":"venue"
},
  "geometry": {"coordinates":[-94.790162,35.459411],"type":"Point"}
}