{
  "type": "Feature",
  "properties": {
    "iso:country":"US",
    "sg:address":"410 NE 12th St",
    "sg:city":"Guymon",
    "sg:classifiers":[
        {
            "category":"Health Services",
            "subcategory":"Doctor",
            "type":"Services"
        }
    ],
    "sg:phone":"+1 580 338 5500",
    "sg:postcode":"73942",
    "sg:province":"OK",
    "sg:tags":[
        "clinic"
    ],
    "wof:name":"Internal Medicine Clinic",
    "wof:placetype":"venue"
},
  "geometry": {"coordinates":[-101.476499,36.68959],"type":"Point"}
}