{
  "type": "Feature",
  "properties": {
    "iso:country":"US",
    "sg:address":"1602 NW Lawton Ave",
    "sg:city":"Lawton",
    "sg:classifiers":[
        {
            "category":"Government",
            "subcategory":"Office",
            "type":"Public Place"
        }
    ],
    "sg:phone":"+1 580 248 8440",
    "sg:postcode":"73507",
    "sg:province":"OK",
    "sg:tags":[
        "state",
        "taxation"
    ],
    "wof:name":"Tax Commission",
    "wof:placetype":"venue"
},
  "geometry": {"coordinates":[-98.415245,34.62419],"type":"Point"}
}