{
  "type": "Feature",
  "properties": {
    "addr:full":"1410 E 3rd Ave Stillwater OK 74074",
    "addr:housenumber":"1410",
    "addr:postcode":"74074",
    "addr:street":"E 3Rd Ave",
    "iso:country":"US",
    "sg:address":"1410 E 3rd Ave",
    "sg:city":"Stillwater",
    "sg:classifiers":[
        {
            "category":"Building & Trades",
            "subcategory":"Plumbing",
            "type":"Services"
        }
    ],
    "sg:phone":"+1 405 743 0231",
    "sg:postcode":"74074",
    "sg:province":"OK",
    "sg:tags":[
        "contractor"
    ],
    "wof:name":"Eikenbary Service & Repair",
    "wof:placetype":"venue"
},
  "geometry": {"coordinates":[-97.04153599999999,36.119662],"type":"Point"}
}