{
  "type": "Feature",
  "properties": {
    "iso:country":"US",
    "sg:address":"9720 S Granite Ave",
    "sg:city":"Tulsa",
    "sg:classifiers":[
        {
            "category":"Professional",
            "subcategory":"Employment Agencies",
            "type":"Services"
        }
    ],
    "sg:phone":"+1 918 641 0900",
    "sg:postcode":"74137",
    "sg:province":"OK",
    "sg:tags":[
        "help",
        "supply"
    ],
    "wof:name":"A F C",
    "wof:placetype":"venue"
},
  "geometry": {"coordinates":[-95.914542,36.023601],"type":"Point"}
}