{
  "type": "Feature",
  "properties": {
    "iso:country":"US",
    "sg:address":"300 S Church St",
    "sg:city":"Poteau",
    "sg:classifiers":[
        {
            "category":"Professional",
            "subcategory":"Lawyer & Legal Services",
            "type":"Services"
        }
    ],
    "sg:phone":"+1 918 647 2299",
    "sg:postcode":"74953",
    "sg:province":"OK",
    "sg:tags":[
        "attorney"
    ],
    "wof:name":"Michael P Dunagan",
    "wof:placetype":"venue"
},
  "geometry": {"coordinates":[-94.625605,35.053596],"type":"Point"}
}