{
  "type": "Feature",
  "properties": {
    "iso:country":"US",
    "sg:address":"724 Fairway Dr",
    "sg:city":"Norman",
    "sg:classifiers":[
        {
            "category":"Organizations",
            "subcategory":"Religious Organization",
            "type":"Services"
        }
    ],
    "sg:phone":"+1 405 321 6917",
    "sg:postcode":"73069",
    "sg:province":"OK",
    "sg:tags":[
        "church"
    ],
    "wof:name":"Westwood Baptist Church",
    "wof:placetype":"venue"
},
  "geometry": {"coordinates":[-97.476555,35.226528],"type":"Point"}
}