{
  "type": "Feature",
  "properties": {
    "addr:full":"6601 Boucher Dr Edmond OK 73034",
    "addr:housenumber":"6601",
    "addr:postcode":"73034",
    "addr:street":"Boucher Dr",
    "iso:country":"US",
    "sg:address":"6601 Boucher Dr",
    "sg:city":"Edmond",
    "sg:classifiers":[
        {
            "category":"Building & Trades",
            "subcategory":"Construction",
            "type":"Services"
        }
    ],
    "sg:phone":"+1 405 330 3950",
    "sg:postcode":"73034",
    "sg:province":"OK",
    "sg:tags":[
        "waterproofing",
        "contractor"
    ],
    "wof:name":"Restek",
    "wof:placetype":"venue"
},
  "geometry": {"coordinates":[-97.419782,35.722632],"type":"Point"}
}