{
  "type": "Feature",
  "properties": {
    "iso:country":"US",
    "sg:address":"1604 S 110th East Pl",
    "sg:city":"Tulsa",
    "sg:classifiers":[
        {
            "category":"Professional",
            "subcategory":"Management & Consulting",
            "type":"Services"
        }
    ],
    "sg:phone":"+1 918 438 5226",
    "sg:postcode":"74128",
    "sg:province":"OK",
    "sg:tags":[
        "general",
        "ergonomics",
        "for",
        "contractor"
    ],
    "wof:name":"Global Ergonomic Systems",
    "wof:placetype":"venue"
},
  "geometry": {"coordinates":[-95.853748,36.138007],"type":"Point"}
}