{
  "type": "Feature",
  "properties": {
    "addr:full":"804 E Richmond Pl Broken Arrow OK 74012",
    "addr:housenumber":"804",
    "addr:postcode":"74012",
    "addr:street":"E Richmond Pl",
    "iso:country":"US",
    "sg:address":"804 E Richmond Pl",
    "sg:city":"Broken Arrow",
    "sg:classifiers":[
        {
            "category":"Local Transit",
            "type":"Transportation"
        }
    ],
    "sg:phone":"+1 918 251 6233",
    "sg:postcode":"74012",
    "sg:province":"OK",
    "sg:tags":[
        "passenger"
    ],
    "wof:name":"UNI International America Corp",
    "wof:placetype":"venue"
},
  "geometry": {"coordinates":[-95.781887,36.036306],"type":"Point"}
}