{
  "type": "Feature",
  "properties": {
    "iso:country":"US",
    "sg:address":"310 E Memorial St",
    "sg:city":"Broken Bow",
    "sg:classifiers":[
        {
            "category":"Manufacturing",
            "subcategory":"Lumber",
            "type":"Manufacturing & Wholesale Goods"
        }
    ],
    "sg:phone":"+1 580 584 6233",
    "sg:postcode":"74728",
    "sg:province":"OK",
    "sg:tags":[
        "forester"
    ],
    "wof:name":"Mark G Guthrie",
    "wof:placetype":"venue"
},
  "geometry": {"coordinates":[-94.733755,34.01168],"type":"Point"}
}