{
  "type": "Feature",
  "properties": {
    "iso:country":"US",
    "sg:address":"104 W Cherokee St",
    "sg:city":"Lindsay",
    "sg:classifiers":[
        {
            "category":"Insurance",
            "subcategory":"Insurance Agent",
            "type":"Services"
        }
    ],
    "sg:phone":"+1 405 756 2191",
    "sg:postcode":"73052",
    "sg:province":"OK",
    "sg:tags":[
        "broker"
    ],
    "wof:name":"Farm Bureau Insurance",
    "wof:placetype":"venue"
},
  "geometry": {"coordinates":[-97.60278,34.836847],"type":"Point"}
}