{
  "type": "Feature",
  "properties": {
    "iso:country":"US",
    "sg:address":"8101 E Skelly Dr",
    "sg:city":"Tulsa",
    "sg:classifiers":[
        {
            "category":"Autos & Motor Vehicles",
            "subcategory":"Fuel & Gas Station",
            "type":"Retail Goods"
        }
    ],
    "sg:phone":"+1 918 663 2193",
    "sg:postcode":"74129",
    "sg:province":"OK",
    "sg:tags":[
        "station",
        "gasoline"
    ],
    "wof:name":"I-44 Service",
    "wof:placetype":"venue"
},
  "geometry": {"coordinates":[-95.885235,36.122074],"type":"Point"}
}