{
  "type": "Feature",
  "properties": {
    "iso:country":"US",
    "sg:address":"405 N Ellison St",
    "sg:city":"Guymon",
    "sg:classifiers":[
        {
            "category":"Social Services",
            "type":"Services"
        }
    ],
    "sg:phone":"+1 580 338 5388",
    "sg:postcode":"73942",
    "sg:province":"OK",
    "sg:tags":[
        "organization",
        "welfare"
    ],
    "wof:name":"Opportunities Inc",
    "wof:placetype":"venue"
},
  "geometry": {"coordinates":[-101.48018,36.681869],"type":"Point"}
}