{
  "type": "Feature",
  "properties": {
    "addr:full":"10925 SE 59th St Oklahoma City OK 73150",
    "addr:housenumber":"10925",
    "addr:postcode":"73150",
    "addr:street":"Se 59Th St",
    "iso:country":"US",
    "sg:address":"10925 SE 59th St",
    "sg:city":"Oklahoma City",
    "sg:classifiers":[
        {
            "category":"Building & Trades",
            "subcategory":"Construction",
            "type":"Services"
        }
    ],
    "sg:phone":"+1 405 733 2569",
    "sg:postcode":"73150",
    "sg:province":"OK",
    "sg:tags":[
        "dry wall",
        "contractor"
    ],
    "wof:name":"Breeden Enterprises",
    "wof:placetype":"venue"
},
  "geometry": {"coordinates":[-97.33683000000001,35.406383],"type":"Point"}
}