{
  "type": "Feature",
  "properties": {
    "iso:country":"US",
    "sg:address":"515 S Broadway Ave",
    "sg:city":"Oklahoma City",
    "sg:classifiers":[
        {
            "category":"Retail",
            "subcategory":"Repair Shop",
            "type":"Services"
        }
    ],
    "sg:phone":"+1 405 235 3318",
    "sg:postcode":"73109",
    "sg:province":"OK",
    "sg:tags":[
        "equipment",
        "hydraulic"
    ],
    "wof:name":"Hydraulic Equipment Co",
    "wof:placetype":"venue"
},
  "geometry": {"coordinates":[-97.514717,35.460238],"type":"Point"}
}