{
  "type": "Feature",
  "properties": {
    "addr:full":"116 W Randolph Ave Enid OK 73701",
    "addr:housenumber":"116",
    "addr:postcode":"73701",
    "addr:street":"W Randolph Ave",
    "iso:country":"US",
    "sg:address":"116 W Randolph Ave",
    "sg:city":"Enid",
    "sg:classifiers":[
        {
            "category":"Shopping",
            "subcategory":"Clothing, Apparel, & Fashions",
            "type":"Retail Goods"
        }
    ],
    "sg:phone":"+1 580 242 7278",
    "sg:postcode":"73701",
    "sg:province":"OK",
    "wof:name":"SASU",
    "wof:placetype":"venue"
},
  "geometry": {"coordinates":[-97.879628,36.397874],"type":"Point"}
}