{
  "type": "Feature",
  "properties": {
    "iso:country":"US",
    "sg:address":"815 S York St",
    "sg:city":"Muskogee",
    "sg:classifiers":[
        {
            "category":"Restaurant",
            "type":"Food & Drink"
        }
    ],
    "sg:phone":"+1 918 683 8880",
    "sg:postcode":"74403",
    "sg:province":"OK",
    "wof:name":"Panda Express",
    "wof:placetype":"venue"
},
  "geometry": {"coordinates":[-95.34045399999999,35.733124],"type":"Point"}
}