{
  "type": "Feature",
  "properties": {
    "iso:country":"US",
    "sg:address":"7002 NW Expy",
    "sg:city":"Oklahoma City",
    "sg:classifiers":[
        {
            "category":"Personal",
            "subcategory":"Beauty Salon",
            "type":"Services"
        }
    ],
    "sg:phone":"+1 405 721 0694",
    "sg:postcode":"73132",
    "sg:province":"OK",
    "sg:tags":[
        "shop"
    ],
    "wof:name":"Fantastic Sam's",
    "wof:placetype":"venue"
},
  "geometry": {"coordinates":[-97.63735699999999,35.557338],"type":"Point"}
}