{
  "type": "Feature",
  "properties": {
    "iso:country":"US",
    "sg:address":"12818 S Memorial Dr",
    "sg:city":"Bixby",
    "sg:classifiers":[
        {
            "category":"Building & Trades",
            "subcategory":"Landscaping Services",
            "type":"Services"
        }
    ],
    "sg:phone":"+1 918 369 4434",
    "sg:postcode":"74008",
    "sg:province":"OK",
    "sg:tags":[
        "landscape",
        "contractor"
    ],
    "wof:name":"Greenway Lawn Service",
    "wof:placetype":"venue"
},
  "geometry": {"coordinates":[-95.886586,35.977541],"type":"Point"}
}