{
  "type": "Feature",
  "properties": {
    "addr:full":"1704 Kansas Ave Woodward OK 73801",
    "addr:housenumber":"1704",
    "addr:postcode":"73801",
    "addr:street":"Kansas Ave",
    "iso:country":"US",
    "sg:address":"1704 Kansas Ave",
    "sg:city":"Woodward",
    "sg:classifiers":[
        {
            "category":"Organizations",
            "subcategory":"Religious Organization",
            "type":"Services"
        }
    ],
    "sg:phone":"+1 580 256 2117",
    "sg:postcode":"73801",
    "sg:province":"OK",
    "sg:tags":[
        "church"
    ],
    "wof:name":"First Free Methodist Church",
    "wof:placetype":"venue"
},
  "geometry": {"coordinates":[-99.401546,36.437242],"type":"Point"}
}