{
  "type": "Feature",
  "properties": {
    "addr:full":"5003 S 101st East Ave Tulsa OK 74146",
    "addr:housenumber":"5003",
    "addr:postcode":"74146",
    "addr:street":"S 101St;Ave",
    "iso:country":"US",
    "sg:address":"5003 S 101st East Ave",
    "sg:city":"Tulsa",
    "sg:classifiers":[
        {
            "category":"Wholesale",
            "subcategory":"Electrical",
            "type":"Manufacturing & Wholesale Goods"
        }
    ],
    "sg:phone":"+1 918 627 5483",
    "sg:postcode":"74146",
    "sg:province":"OK",
    "sg:tags":[
        "light",
        "tube",
        "bulb"
    ],
    "wof:name":"First Light Of Tulsa",
    "wof:placetype":"venue"
},
  "geometry": {"coordinates":[-95.863681,36.090927],"type":"Point"}
}