{
  "type": "Feature",
  "properties": {
    "iso:country":"US",
    "sg:address":"326 S Maple Ave",
    "sg:city":"Afton",
    "sg:classifiers":[
        {
            "category":"Real Estate",
            "subcategory":"Real Estate Operator",
            "type":"Services"
        }
    ],
    "sg:phone":"+1 918 257 8798",
    "sg:postcode":"74331",
    "sg:province":"OK",
    "sg:tags":[
        "apartment"
    ],
    "wof:name":"Village Terrace",
    "wof:placetype":"venue"
},
  "geometry": {"coordinates":[-94.963823,36.688493],"type":"Point"}
}