{
  "type": "Feature",
  "properties": {
    "iso:country":"US",
    "sg:address":"1402 Main Ave",
    "sg:city":"Woodward",
    "sg:classifiers":[
        {
            "category":"Retail",
            "subcategory":"Repair Shop",
            "type":"Services"
        }
    ],
    "sg:phone":"+1 580 571 2838",
    "sg:postcode":"73801",
    "sg:province":"OK",
    "sg:tags":[
        "welding"
    ],
    "wof:name":"Timmy Wright Welding",
    "wof:placetype":"venue"
},
  "geometry": {"coordinates":[-99.398342,36.436044],"type":"Point"}
}