{
  "type": "Feature",
  "properties": {
    "iso:country":"US",
    "sg:address":"6663 E Newton Pl",
    "sg:city":"Tulsa",
    "sg:classifiers":[
        {
            "category":"Building & Trades",
            "subcategory":"Construction",
            "type":"Services"
        }
    ],
    "sg:phone":"+1 918 836 8811",
    "sg:postcode":"74115",
    "sg:province":"OK",
    "wof:name":"T Nt Metal Bldg Erection & Rpr",
    "wof:placetype":"venue"
},
  "geometry": {"coordinates":[-95.900655,36.174025],"type":"Point"}
}