{
  "type": "Feature",
  "properties": {
    "addr:full":"8143 E 11th St Tulsa OK 74112",
    "addr:housenumber":"8143",
    "addr:postcode":"74112",
    "addr:street":"E 11Th St",
    "iso:country":"US",
    "sg:address":"8143 E 11th St",
    "sg:city":"Tulsa",
    "sg:classifiers":[
        {
            "category":"Social Services",
            "subcategory":"Child Care",
            "type":"Services"
        }
    ],
    "sg:phone":"+1 918 835 0131",
    "sg:postcode":"74112",
    "sg:province":"OK",
    "wof:name":"Kaylee's Daycare",
    "wof:placetype":"venue"
},
  "geometry": {"coordinates":[-95.88585999999999,36.148062],"type":"Point"}
}