{
  "type": "Feature",
  "properties": {
    "addr:full":"323 N Main St Noble OK 73068",
    "addr:housenumber":"323",
    "addr:postcode":"73068",
    "addr:street":"N Main St",
    "iso:country":"US",
    "sg:address":"323 N Main St",
    "sg:city":"Noble",
    "sg:classifiers":[
        {
            "category":"Shopping",
            "subcategory":"Gifts & Souvenirs",
            "type":"Retail Goods"
        }
    ],
    "sg:phone":"+1 405 872 5908",
    "sg:postcode":"73068",
    "sg:province":"OK",
    "sg:tags":[
        "shop"
    ],
    "wof:name":"Pals Two Gift Shop",
    "wof:placetype":"venue"
},
  "geometry": {"coordinates":[-97.39455100000001,35.143069],"type":"Point"}
}