{
  "type": "Feature",
  "properties": {
    "addr:full":"2100 W Grandstaff Rd Cushing OK 74023",
    "addr:housenumber":"2100",
    "addr:postcode":"74023",
    "addr:street":"W Grandstaff Rd",
    "iso:country":"US",
    "sg:address":"2100 W Grandstaff Rd",
    "sg:city":"Cushing",
    "sg:classifiers":[
        {
            "category":"Building & Trades",
            "subcategory":"Construction",
            "type":"Services"
        }
    ],
    "sg:phone":"+1 918 225 3988",
    "sg:postcode":"74023",
    "sg:province":"OK",
    "sg:tags":[
        "contractor"
    ],
    "wof:name":"Mike Leverich",
    "wof:placetype":"venue"
},
  "geometry": {"coordinates":[-96.796815,36.000287],"type":"Point"}
}