{
  "type": "Feature",
  "properties": {
    "iso:country":"US",
    "sg:address":"3317 Greenwood Dr",
    "sg:city":"Norman",
    "sg:classifiers":[
        {
            "category":"Manufacturing",
            "subcategory":"Chemicals & Compounds",
            "type":"Manufacturing & Wholesale Goods"
        }
    ],
    "sg:phone":"+1 405 329 6467",
    "sg:postcode":"73072",
    "sg:province":"OK",
    "sg:tags":[
        "preparation",
        "mfg"
    ],
    "wof:name":"Industrial Chemist Inc",
    "wof:placetype":"venue"
},
  "geometry": {"coordinates":[-97.49086,35.235506],"type":"Point"}
}