{
  "type": "Feature",
  "properties": {
    "addr:full":"4141 N Harrison Ave Shawnee OK 74804",
    "addr:housenumber":"4141",
    "addr:postcode":"74804",
    "addr:street":"N Harrison Ave",
    "iso:country":"US",
    "sg:address":"4141 N Harrison Ave",
    "sg:city":"Shawnee",
    "sg:classifiers":[
        {
            "category":"Autos & Motor Vehicles",
            "subcategory":"Automobile Sales",
            "type":"Retail Goods"
        }
    ],
    "sg:phone":"+1 405 273 6343",
    "sg:postcode":"74804",
    "sg:province":"OK",
    "sg:tags":[
        "car",
        "dealer"
    ],
    "wof:name":"Automax Dodge Chrysler Jeep",
    "wof:placetype":"venue"
},
  "geometry": {"coordinates":[-96.911997,35.374617],"type":"Point"}
}