{
  "type": "Feature",
  "properties": {
    "iso:country":"US",
    "sg:address":"315 W 6th Ave",
    "sg:city":"Stillwater",
    "sg:classifiers":[
        {
            "category":"Government",
            "subcategory":"Office",
            "type":"Public Place"
        }
    ],
    "sg:phone":"+1 405 624 9411",
    "sg:postcode":"74074",
    "sg:province":"OK",
    "sg:tags":[
        "county",
        "treasurer",
        "taxation"
    ],
    "wof:name":"Payne County Treasurer",
    "wof:placetype":"venue"
},
  "geometry": {"coordinates":[-97.061596,36.115611],"type":"Point"}
}