{
  "type": "Feature",
  "properties": {
    "iso:country":"US",
    "sg:address":"2121 E 69th St",
    "sg:city":"Tulsa",
    "sg:classifiers":[
        {
            "category":"Sports & Exercise",
            "subcategory":"Gym",
            "type":"Entertainment"
        }
    ],
    "sg:phone":"+1 918 494 3644",
    "sg:postcode":"74136",
    "sg:province":"OK",
    "sg:tags":[
        "club",
        "health",
        "studio",
        "gymnasium"
    ],
    "sg:website":"www.allamericanfitness.net",
    "wof:name":"All American Fitness Ctr",
    "wof:placetype":"venue"
},
  "geometry": {"coordinates":[-95.958082,36.063739],"type":"Point"}
}