{
  "type": "Feature",
  "properties": {
    "iso:country":"US",
    "sg:address":"9402 Hillcrest Dr",
    "sg:city":"Broken Arrow",
    "sg:classifiers":[
        {
            "category":"Autos & Motor Vehicles",
            "subcategory":"Automobile Sales",
            "type":"Retail Goods"
        }
    ],
    "sg:phone":"+1 918 251 3179",
    "sg:postcode":"74014",
    "sg:province":"OK",
    "sg:tags":[
        "used"
    ],
    "wof:name":"Nevins Auto Sales",
    "wof:placetype":"venue"
},
  "geometry": {"coordinates":[-95.722723,36.026105],"type":"Point"}
}