{
  "type": "Feature",
  "properties": {
    "iso:country":"US",
    "sg:address":"11405 S Maplewood Ave",
    "sg:city":"Tulsa",
    "sg:classifiers":[
        {
            "category":"Professional",
            "subcategory":"Management & Consulting",
            "type":"Services"
        }
    ],
    "sg:phone":"+1 918 296 0111",
    "sg:postcode":"74137",
    "sg:province":"OK",
    "sg:tags":[
        "public",
        "relations"
    ],
    "wof:name":"Young Lion",
    "wof:placetype":"venue"
},
  "geometry": {"coordinates":[-95.906053,35.997033],"type":"Point"}
}