{
  "type": "Feature",
  "properties": {
    "addr:full":"612 W Georgia Ave Anadarko OK 73005",
    "addr:housenumber":"612",
    "addr:postcode":"73005",
    "addr:street":"W Georgia Ave",
    "iso:country":"US",
    "sg:address":"612 W Georgia Ave",
    "sg:city":"Anadarko",
    "sg:classifiers":[
        {
            "category":"Professional",
            "subcategory":"Business Services",
            "type":"Services"
        }
    ],
    "sg:phone":"+1 405 247 5150",
    "sg:postcode":"73005",
    "sg:province":"OK",
    "wof:name":"Laura S Jarvis",
    "wof:placetype":"venue"
},
  "geometry": {"coordinates":[-98.25278400000001,35.069396],"type":"Point"}
}