{
  "type": "Feature",
  "properties": {
    "iso:country":"US",
    "sg:address":"1215 E Lockheed Dr",
    "sg:city":"Midwest City",
    "sg:classifiers":[
        {
            "category":"Retail",
            "subcategory":"Veterinary Services",
            "type":"Services"
        }
    ],
    "sg:phone":"+1 405 733 4649",
    "sg:postcode":"73110",
    "sg:province":"OK",
    "sg:tags":[
        "veterinarian"
    ],
    "wof:name":"Pet-Vet Animal Clinic",
    "wof:placetype":"venue"
},
  "geometry": {"coordinates":[-97.402182,35.449599],"type":"Point"}
}