{
  "type": "Feature",
  "properties": {
    "iso:country":"US",
    "sg:address":"5901 NW 39th St",
    "sg:city":"Oklahoma City",
    "sg:classifiers":[
        {
            "category":"Shopping",
            "subcategory":"Pharmacy",
            "type":"Retail Goods"
        }
    ],
    "sg:phone":"+1 405 495 8243",
    "sg:postcode":"73122",
    "sg:province":"OK",
    "wof:name":"Walgreens",
    "wof:placetype":"venue"
},
  "geometry": {"coordinates":[-97.622994,35.511162],"type":"Point"}
}