{
  "type": "Feature",
  "properties": {
    "iso:country":"US",
    "sg:address":"124 N Brookside Ave",
    "sg:city":"Tahlequah",
    "sg:classifiers":[
        {
            "category":"Recreation",
            "type":"Entertainment"
        }
    ],
    "sg:phone":"+1 918 456 1048",
    "sg:postcode":"74464",
    "sg:province":"OK",
    "sg:tags":[
        "pool",
        "swimming"
    ],
    "wof:name":"Tahlequah Swimming Pool",
    "wof:placetype":"venue"
},
  "geometry": {"coordinates":[-94.968238,35.913482],"type":"Point"}
}