{
  "type": "Feature",
  "properties": {
    "addr:full":"1412 Fir St Perry OK 73077",
    "addr:housenumber":"1412",
    "addr:postcode":"73077",
    "addr:street":"Fir St",
    "iso:country":"US",
    "sg:address":"1412 Fir St",
    "sg:city":"Perry",
    "sg:classifiers":[
        {
            "category":"Health Services",
            "subcategory":"Doctor",
            "type":"Services"
        }
    ],
    "sg:phone":"+1 580 336 3511",
    "sg:postcode":"73077",
    "sg:province":"OK",
    "sg:tags":[
        "osteopathic"
    ],
    "wof:name":"Dr Richard Seal",
    "wof:placetype":"venue"
},
  "geometry": {"coordinates":[-97.30085699999999,36.28959],"type":"Point"}
}