{
  "type": "Feature",
  "properties": {
    "iso:country":"US",
    "sg:address":"2009 Central St",
    "sg:city":"Poteau",
    "sg:classifiers":[
        {
            "category":"Building & Trades",
            "subcategory":"Construction",
            "type":"Services"
        }
    ],
    "sg:phone":"+1 918 647 3434",
    "sg:postcode":"74953",
    "sg:province":"OK",
    "sg:tags":[
        "porch",
        "enclosure",
        "patio",
        "deck"
    ],
    "wof:name":"John Doyle's Quality Cover",
    "wof:placetype":"venue"
},
  "geometry": {"coordinates":[-94.620367,35.06909],"type":"Point"}
}