{
  "type": "Feature",
  "properties": {
    "addr:full":"4622 Parker Rd Oklahoma City OK 73127",
    "addr:housenumber":"4622",
    "addr:postcode":"73127",
    "addr:street":"Parker Rd",
    "iso:country":"US",
    "sg:address":"4622 Parker Rd",
    "sg:city":"Oklahoma City",
    "sg:classifiers":[
        {
            "category":"Home & Garden",
            "subcategory":"Building Materials",
            "type":"Retail Goods"
        }
    ],
    "sg:phone":"+1 405 946 6008",
    "sg:postcode":"73127",
    "sg:province":"OK",
    "sg:tags":[
        "door"
    ],
    "wof:name":"Accurate Garage Door",
    "wof:placetype":"venue"
},
  "geometry": {"coordinates":[-97.60553,35.474597],"type":"Point"}
}