{
  "type": "Feature",
  "properties": {
    "iso:country":"US",
    "sg:address":"123 S Hudson Ave",
    "sg:city":"Oklahoma City",
    "sg:classifiers":[
        {
            "category":"Mining & Drilling",
            "type":"Manufacturing & Wholesale Goods"
        }
    ],
    "sg:phone":"+1 405 231 2476",
    "sg:postcode":"73102",
    "sg:province":"OK",
    "sg:tags":[
        "development",
        "gas",
        "oil",
        "exploration"
    ],
    "wof:name":"Indian Exploration Co",
    "wof:placetype":"venue"
},
  "geometry": {"coordinates":[-97.519598,35.464513],"type":"Point"}
}