{
  "type": "Feature",
  "properties": {
    "iso:country":"US",
    "sg:address":"1006 S Mission St",
    "sg:city":"Anadarko",
    "sg:classifiers":[
        {
            "category":"Professional",
            "type":"Services"
        }
    ],
    "sg:phone":"+1 405 247 5736",
    "sg:postcode":"73005",
    "sg:province":"OK",
    "sg:tags":[
        "establishment"
    ],
    "wof:name":"Tingley's Drive Thru II",
    "wof:placetype":"venue"
},
  "geometry": {"coordinates":[-98.25148799999999,35.067379],"type":"Point"}
}