{
  "type": "Feature",
  "properties": {
    "iso:country":"US",
    "sg:address":"804 W Twin Oaks Dr",
    "sg:city":"Broken Arrow",
    "sg:classifiers":[
        {
            "category":"Professional",
            "subcategory":"Business Services",
            "type":"Services"
        }
    ],
    "sg:phone":"+1 918 451 6151",
    "sg:postcode":"74011",
    "sg:province":"OK",
    "wof:name":"Watts Designs",
    "wof:placetype":"venue"
},
  "geometry": {"coordinates":[-95.79954499999999,36.011297],"type":"Point"}
}