{
  "type": "Feature",
  "properties": {
    "iso:country":"US",
    "sg:address":"521 N Perkins Rd",
    "sg:city":"Stillwater",
    "sg:classifiers":[
        {
            "category":"Shopping",
            "type":"Retail Goods"
        }
    ],
    "sg:phone":"+1 405 624 9065",
    "sg:postcode":"74075",
    "sg:province":"OK",
    "sg:tags":[
        "sewing",
        "ho",
        "merchandise"
    ],
    "wof:name":"Hobby Lobby 5",
    "wof:placetype":"venue"
},
  "geometry": {"coordinates":[-97.051363,36.127688],"type":"Point"}
}