{
  "type": "Feature",
  "properties": {
    "iso:country":"US",
    "sg:address":"10106 E 95th Ct N",
    "sg:city":"Owasso",
    "sg:classifiers":[
        {
            "category":"Professional",
            "subcategory":"Business Services",
            "type":"Services"
        }
    ],
    "sg:phone":"+1 918 274 4194",
    "sg:postcode":"74055",
    "sg:province":"OK",
    "wof:name":"Key Claims of Liberal",
    "wof:placetype":"venue"
},
  "geometry": {"coordinates":[-95.860242,36.292641],"type":"Point"}
}