{
  "type": "Feature",
  "properties": {
    "iso:country":"US",
    "sg:address":"701 N Cemetery Rd",
    "sg:city":"Yukon",
    "sg:classifiers":[
        {
            "category":"Organizations",
            "subcategory":"Religious Organization",
            "type":"Services"
        }
    ],
    "sg:phone":"+1 405 324 9000",
    "sg:postcode":"73099",
    "sg:province":"OK",
    "sg:tags":[
        "church"
    ],
    "wof:name":"New Dimensions Church",
    "wof:placetype":"venue"
},
  "geometry": {"coordinates":[-97.760157,35.475561],"type":"Point"}
}