{
  "type": "Feature",
  "properties": {
    "addr:full":"711 Kaylin Cir Blackwell OK 74631",
    "addr:housenumber":"711",
    "addr:postcode":"74631",
    "addr:street":"Kaylin Cir",
    "iso:country":"US",
    "sg:address":"711 Kaylin Cir",
    "sg:city":"Blackwell",
    "sg:phone":"+1 580 363 4014",
    "sg:postcode":"74631",
    "sg:province":"OK",
    "sg:tags":[
        "farm",
        "wheat"
    ],
    "wof:name":"Shepherd Farm",
    "wof:placetype":"venue"
},
  "geometry": {"coordinates":[-97.293014,36.788724],"type":"Point"}
}