{
  "type": "Feature",
  "properties": {
    "addr:full":"9908 E 142nd St N Collinsville OK 74021",
    "addr:housenumber":"9908",
    "addr:postcode":"74021",
    "addr:street":"E 142Nd St N",
    "iso:country":"US",
    "sg:address":"9908 E 142nd St N",
    "sg:city":"Collinsville",
    "sg:classifiers":[
        {
            "category":"Building & Trades",
            "subcategory":"Construction",
            "type":"Services"
        }
    ],
    "sg:phone":"+1 918 371 3381",
    "sg:postcode":"74021",
    "sg:province":"OK",
    "sg:tags":[
        "floor",
        "laying",
        "contractor"
    ],
    "wof:name":"Jerry F Delozier",
    "wof:placetype":"venue"
},
  "geometry": {"coordinates":[-95.86476399999999,36.359836],"type":"Point"}
}