{
  "type": "Feature",
  "properties": {
    "iso:country":"US",
    "sg:address":"207 Mimosa Ln",
    "sg:city":"Tahlequah",
    "sg:classifiers":[
        {
            "category":"Shopping",
            "subcategory":"Used Merchandise",
            "type":"Retail Goods"
        }
    ],
    "sg:phone":"+1 918 456 4339",
    "sg:postcode":"74464",
    "sg:province":"OK",
    "sg:tags":[
        "instrument",
        "musical"
    ],
    "wof:name":"N Tune Tahlequah's Music Ctr",
    "wof:placetype":"venue"
},
  "geometry": {"coordinates":[-94.976013,35.892276],"type":"Point"}
}