{
  "type": "Feature",
  "properties": {
    "iso:country":"US",
    "sg:address":"1101 S 61st St W",
    "sg:city":"Muskogee",
    "sg:classifiers":[
        {
            "category":"Autos & Motor Vehicles",
            "subcategory":"Automobile Sales",
            "type":"Retail Goods"
        }
    ],
    "sg:phone":"+1 918 683 6818",
    "sg:postcode":"74401",
    "sg:province":"OK",
    "sg:tags":[
        "used"
    ],
    "wof:name":"Gibson Street Motors",
    "wof:placetype":"venue"
},
  "geometry": {"coordinates":[-95.44059300000001,35.742316],"type":"Point"}
}