{
  "type": "Feature",
  "properties": {
    "iso:country":"US",
    "sg:address":"5138 S Peoria Ave",
    "sg:city":"Tulsa",
    "sg:classifiers":[
        {
            "category":"Shopping",
            "subcategory":"Stationery & Office Supplies",
            "type":"Retail Goods"
        },
        {
            "category":"Manufacturing",
            "subcategory":"Rubber & Plastics",
            "type":"Manufacturing & Wholesale Goods"
        }
    ],
    "sg:phone":"+1 918 742 7930",
    "sg:postcode":"74105",
    "sg:province":"OK",
    "sg:tags":[
        "marking",
        "mfg",
        "stamp",
        "product",
        "devices",
        "fabricated"
    ],
    "wof:name":"Fast Rubber Stamp Service",
    "wof:placetype":"venue"
},
  "geometry": {"coordinates":[-95.975816,36.087381],"type":"Point"}
}