{
  "type": "Feature",
  "properties": {
    "iso:country":"US",
    "sg:address":"2001 S Country Club Rd",
    "sg:city":"El Reno",
    "sg:classifiers":[
        {
            "category":"Freight",
            "type":"Transportation"
        }
    ],
    "sg:phone":"+1 405 262 0400",
    "sg:postcode":"73036",
    "sg:province":"OK",
    "sg:tags":[
        "trucking"
    ],
    "wof:name":"Gurkaren Trucking",
    "wof:placetype":"venue"
},
  "geometry": {"coordinates":[-97.972572,35.513941],"type":"Point"}
}