{
  "type": "Feature",
  "properties": {
    "addr:full":"128 N Pennsylvania Ave Mangum OK 73554",
    "addr:housenumber":"128",
    "addr:postcode":"73554",
    "addr:street":"N Pennsylvania Ave",
    "iso:country":"US",
    "sg:address":"128 N Pennsylvania Ave",
    "sg:city":"Mangum",
    "sg:classifiers":[
        {
            "category":"Organizations",
            "subcategory":"Religious Organization",
            "type":"Services"
        }
    ],
    "sg:phone":"+1 580 782 3294",
    "sg:postcode":"73554",
    "sg:province":"OK",
    "wof:name":"Central Christian Church",
    "wof:placetype":"venue"
},
  "geometry": {"coordinates":[-99.50430799999999,34.873889],"type":"Point"}
}