{
  "type": "Feature",
  "properties": {
    "iso:country":"US",
    "sg:address":"605 E Highland St",
    "sg:city":"Hugo",
    "sg:classifiers":[
        {
            "category":"Retail",
            "subcategory":"Auto Repair",
            "type":"Services"
        }
    ],
    "sg:phone":"+1 580 326 2553",
    "sg:postcode":"74743",
    "sg:province":"OK",
    "sg:tags":[
        "body",
        "automobile",
        "painting"
    ],
    "wof:name":"Springs Body Shop",
    "wof:placetype":"venue"
},
  "geometry": {"coordinates":[-95.506468,33.997987],"type":"Point"}
}