{
  "type": "Feature",
  "properties": {
    "addr:full":"4601 N Post Rd Guthrie OK 73044",
    "addr:housenumber":"4601",
    "addr:postcode":"73044",
    "addr:street":"N Post Rd",
    "iso:country":"US",
    "sg:address":"4601 N Post Rd",
    "sg:city":"Guthrie",
    "sg:classifiers":[
        {
            "category":"Building & Trades",
            "subcategory":"Construction",
            "type":"Services"
        }
    ],
    "sg:phone":"+1 405 282 2586",
    "sg:postcode":"73044",
    "sg:province":"OK",
    "sg:tags":[
        "nonresidential"
    ],
    "wof:name":"Randy Montgomery Construction",
    "wof:placetype":"venue"
},
  "geometry": {"coordinates":[-97.353945,35.924925],"type":"Point"}
}