{
  "type": "Feature",
  "properties": {
    "addr:full":"320 S Boston Ave Tulsa OK 74103",
    "addr:housenumber":"320",
    "addr:postcode":"74103",
    "addr:street":"S Boston Ave",
    "iso:country":"US",
    "sg:address":"320 S Boston Ave",
    "sg:city":"Tulsa",
    "sg:classifiers":[
        {
            "category":"Insurance",
            "subcategory":"Insurance Agent",
            "type":"Services"
        }
    ],
    "sg:phone":"+1 918 582 8206",
    "sg:postcode":"74103",
    "sg:province":"OK",
    "sg:tags":[
        "agency"
    ],
    "wof:name":"Fred Daniel & Sons Inc",
    "wof:placetype":"venue"
},
  "geometry": {"coordinates":[-95.989625,36.152967],"type":"Point"}
}