{
  "type": "Feature",
  "properties": {
    "iso:country":"US",
    "sg:address":"1429 SW 84th St",
    "sg:city":"Oklahoma City",
    "sg:classifiers":[
        {
            "category":"Retail",
            "subcategory":"Repair Shop",
            "type":"Services"
        }
    ],
    "sg:phone":"+1 405 682 3915",
    "sg:postcode":"73159",
    "sg:province":"OK",
    "sg:tags":[
        "appliance"
    ],
    "wof:name":"Midwest Appliance Service",
    "wof:placetype":"venue"
},
  "geometry": {"coordinates":[-97.543257,35.381698],"type":"Point"}
}