{
  "type": "Feature",
  "properties": {
    "addr:full":"924 NW 20th St Oklahoma City OK 73160",
    "addr:housenumber":"924",
    "addr:postcode":"73160",
    "addr:street":"Nw 20Th St",
    "iso:country":"US",
    "sg:address":"924 NW 20th St",
    "sg:city":"Oklahoma City",
    "sg:classifiers":[
        {
            "category":"Building & Trades",
            "subcategory":"Construction",
            "type":"Services"
        }
    ],
    "sg:phone":"+1 405 794 2801",
    "sg:postcode":"73160",
    "sg:province":"OK",
    "sg:tags":[
        "housing"
    ],
    "wof:name":"Jason Byrd",
    "wof:placetype":"venue"
},
  "geometry": {"coordinates":[-97.50796800000001,35.356522],"type":"Point"}
}