{
  "type": "Feature",
  "properties": {
    "iso:country":"US",
    "sg:address":"7137 NW 10th St",
    "sg:city":"Oklahoma City",
    "sg:classifiers":[
        {
            "category":"Home & Garden",
            "subcategory":"Building Materials",
            "type":"Retail Goods"
        },
        {
            "category":"Home & Garden",
            "subcategory":"Furniture",
            "type":"Retail Goods"
        }
    ],
    "sg:phone":"+1 405 782 0480",
    "sg:postcode":"73127",
    "sg:province":"OK",
    "sg:tags":[
        "cabinet"
    ],
    "wof:name":"Builders Warehouse Inc",
    "wof:placetype":"venue"
},
  "geometry": {"coordinates":[-97.640923,35.47891],"type":"Point"}
}