{
  "type": "Feature",
  "properties": {
    "addr:full":"111 E Chestnut St Coweta OK 74429",
    "addr:housenumber":"111",
    "addr:postcode":"74429",
    "addr:street":"E Chestnut St",
    "iso:country":"US",
    "sg:address":"111 E Chestnut St",
    "sg:city":"Coweta",
    "sg:classifiers":[
        {
            "category":"Building & Trades",
            "subcategory":"Pest Control",
            "type":"Services"
        }
    ],
    "sg:phone":"+1 918 279 8656",
    "sg:postcode":"74429",
    "sg:province":"OK",
    "wof:name":"Sooner Pest Control",
    "wof:placetype":"venue"
},
  "geometry": {"coordinates":[-95.649947,35.952027],"type":"Point"}
}