{
  "type": "Feature",
  "properties": {
    "addr:full":"2509 Wildwood Ln Norman OK 73071",
    "addr:housenumber":"2509",
    "addr:postcode":"73071",
    "addr:street":"Wildwood Ln",
    "iso:country":"US",
    "sg:address":"2509 Wildwood Ln",
    "sg:city":"Norman",
    "sg:classifiers":[
        {
            "category":"Shopping",
            "subcategory":"Bicycles & Sporting Goods",
            "type":"Retail Goods"
        }
    ],
    "sg:phone":"+1 405 321 5631",
    "sg:postcode":"73071",
    "sg:province":"OK",
    "wof:name":"Dillon Trading Co",
    "wof:placetype":"venue"
},
  "geometry": {"coordinates":[-97.43231900000001,35.249768],"type":"Point"}
}