{
  "type": "Feature",
  "properties": {
    "addr:full":"3100 W 40th St N Muskogee OK 74401",
    "addr:housenumber":"3100",
    "addr:postcode":"74401",
    "addr:street":"W 40Th St N",
    "iso:country":"US",
    "sg:address":"3100 W 40th St N",
    "sg:city":"Muskogee",
    "sg:classifiers":[
        {
            "category":"Professional",
            "type":"Services"
        }
    ],
    "sg:phone":"+1 918 681 1818",
    "sg:postcode":"74401",
    "sg:province":"OK",
    "sg:tags":[
        "establishment"
    ],
    "wof:name":"Curt Shop",
    "wof:placetype":"venue"
},
  "geometry": {"coordinates":[-95.39905899999999,35.798517],"type":"Point"}
}