{
  "type": "Feature",
  "properties": {
    "iso:country":"US",
    "sg:address":"304 S Kelly Ave",
    "sg:city":"Edmond",
    "sg:classifiers":[
        {
            "category":"Restaurant",
            "type":"Food & Drink"
        }
    ],
    "sg:phone":"+1 405 330 2551",
    "sg:postcode":"73003",
    "sg:province":"OK",
    "sg:tags":[
        "eating"
    ],
    "wof:name":"Del Rancho Restaurants",
    "wof:placetype":"venue"
},
  "geometry": {"coordinates":[-97.495929,35.650824],"type":"Point"}
}