{
  "type": "Feature",
  "properties": {
    "iso:country":"US",
    "sg:address":"407 SW 4th St",
    "sg:city":"Tuttle",
    "sg:classifiers":[
        {
            "category":"Home & Garden",
            "subcategory":"Building Materials",
            "type":"Retail Goods"
        }
    ],
    "sg:phone":"+1 405 381 2772",
    "sg:postcode":"73089",
    "sg:province":"OK",
    "wof:name":"All National Garage Door Svcs",
    "wof:placetype":"venue"
},
  "geometry": {"coordinates":[-97.817231,35.287172],"type":"Point"}
}