{
  "type": "Feature",
  "properties": {
    "addr:full":"625 N Monte Vista St Ada OK 74820",
    "addr:housenumber":"625",
    "addr:postcode":"74820",
    "addr:street":"N Monte Vista St",
    "iso:country":"US",
    "sg:address":"625 N Monte Vista St",
    "sg:city":"Ada",
    "sg:classifiers":[
        {
            "category":"Health Services",
            "subcategory":"Doctor",
            "type":"Services"
        }
    ],
    "sg:phone":"+1 580 332 3211",
    "sg:postcode":"74820",
    "sg:province":"OK",
    "sg:tags":[
        "physician",
        "surgeon"
    ],
    "wof:name":"Ada Internal Medicine",
    "wof:placetype":"venue"
},
  "geometry": {"coordinates":[-96.63484699999999,34.780286],"type":"Point"}
}