{
  "type": "Feature",
  "properties": {
    "iso:country":"US",
    "sg:address":"339 N Adair St",
    "sg:city":"Vinita",
    "sg:classifiers":[
        {
            "category":"Building & Trades",
            "subcategory":"Construction",
            "type":"Services"
        }
    ],
    "sg:phone":"+1 918 256 3229",
    "sg:postcode":"74301",
    "sg:province":"OK",
    "sg:tags":[
        "contractor"
    ],
    "wof:name":"Leisure Construction Co",
    "wof:placetype":"venue"
},
  "geometry": {"coordinates":[-95.164406,36.647672],"type":"Point"}
}