{
  "type": "Feature",
  "properties": {
    "iso:country":"US",
    "sg:address":"205 S Broadway St",
    "sg:city":"Coweta",
    "sg:classifiers":[
        {
            "category":"Real Estate",
            "subcategory":"Real Estate Agent",
            "type":"Services"
        }
    ],
    "sg:phone":"+1 918 486 2173",
    "sg:postcode":"74429",
    "sg:province":"OK",
    "wof:name":"Sanders Ralph Realtors",
    "wof:placetype":"venue"
},
  "geometry": {"coordinates":[-95.650433,35.948949],"type":"Point"}
}