{
  "type": "Feature",
  "properties": {
    "iso:country":"US",
    "sg:address":"5801 Blackjack Ridge Rd",
    "sg:city":"Oklahoma City",
    "sg:classifiers":[
        {
            "category":"Building & Trades",
            "subcategory":"Plumbing",
            "type":"Services"
        }
    ],
    "sg:phone":"+1 405 737 2404",
    "sg:postcode":"73150",
    "sg:province":"OK",
    "sg:tags":[
        "plumbing",
        "contractor"
    ],
    "wof:name":"J C Gore Plumbing Co",
    "wof:placetype":"venue"
},
  "geometry": {"coordinates":[-97.344063,35.412699],"type":"Point"}
}