{
  "type": "Feature",
  "properties": {
    "addr:full":"11100 N Pennsylvania Ave Oklahoma City OK 73120",
    "addr:housenumber":"11100",
    "addr:postcode":"73120",
    "addr:street":"N Pennsylvania Ave",
    "iso:country":"US",
    "sg:address":"11100 N Pennsylvania Ave",
    "sg:city":"Oklahoma City",
    "sg:classifiers":[
        {
            "category":"Professional",
            "subcategory":"Accounting & Tax Preparation",
            "type":"Services"
        }
    ],
    "sg:phone":"+1 405 755 6022",
    "sg:postcode":"73120",
    "sg:province":"OK",
    "sg:tags":[
        "return",
        "filing"
    ],
    "wof:name":"H & R Block Tax Svc",
    "wof:placetype":"venue"
},
  "geometry": {"coordinates":[-97.54924,35.582309],"type":"Point"}
}