{
  "type": "Feature",
  "properties": {
    "iso:country":"US",
    "sg:address":"2001 N 69th East Ave",
    "sg:city":"Tulsa",
    "sg:classifiers":[
        {
            "category":"Manufacturing",
            "subcategory":"Metals",
            "type":"Manufacturing & Wholesale Goods"
        }
    ],
    "sg:phone":"+1 918 836 3971",
    "sg:postcode":"74115",
    "sg:province":"OK",
    "sg:tags":[
        "fitting",
        "fluid",
        "power"
    ],
    "wof:name":"Horton Industries Inc",
    "wof:placetype":"venue"
},
  "geometry": {"coordinates":[-95.900204,36.184336],"type":"Point"}
}