{
  "type": "Feature",
  "properties": {
    "iso:country":"US",
    "sg:address":"329 S Oklahoma Ave",
    "sg:city":"Mangum",
    "sg:phone":"+1 580 782 2050",
    "sg:postcode":"73554",
    "sg:province":"OK",
    "sg:tags":[
        "farm",
        "wheat"
    ],
    "wof:name":"Holt Danny & Lanna",
    "wof:placetype":"venue"
},
  "geometry": {"coordinates":[-99.506159,34.87021],"type":"Point"}
}