{
  "type": "Feature",
  "properties": {
    "iso:country":"US",
    "sg:address":"3120 Sheridan Rd",
    "sg:city":"Bartlesville",
    "sg:classifiers":[
        {
            "category":"Organizations",
            "subcategory":"Community Association",
            "type":"Services"
        }
    ],
    "sg:phone":"+1 918 333 7317",
    "sg:postcode":"74006",
    "sg:province":"OK",
    "wof:name":"Civitan International",
    "wof:placetype":"venue"
},
  "geometry": {"coordinates":[-95.94305300000001,36.729173],"type":"Point"}
}