{
  "type": "Feature",
  "properties": {
    "iso:country":"US",
    "sg:address":"407 Whitebird St",
    "sg:city":"Quapaw",
    "sg:classifiers":[
        {
            "category":"Social Services",
            "subcategory":"Adult Care",
            "type":"Services"
        }
    ],
    "sg:phone":"+1 918 674 2233",
    "sg:postcode":"74363",
    "sg:province":"OK",
    "sg:tags":[
        "home",
        "residential"
    ],
    "wof:name":"Higher Call Nursing Ctr",
    "wof:placetype":"venue"
},
  "geometry": {"coordinates":[-94.785698,36.953675],"type":"Point"}
}