{
  "type": "Feature",
  "properties": {
    "iso:country":"US",
    "sg:address":"3644 E 36th St S",
    "sg:city":"Muskogee",
    "sg:classifiers":[
        {
            "category":"Building & Trades",
            "subcategory":"Electrical",
            "type":"Services"
        }
    ],
    "sg:phone":"+1 918 682 4961",
    "sg:postcode":"74403",
    "sg:province":"OK",
    "sg:tags":[
        "electric",
        "contractor"
    ],
    "wof:name":"Clark Electric Co",
    "wof:placetype":"venue"
},
  "geometry": {"coordinates":[-95.322661,35.706081],"type":"Point"}
}