{
  "type": "Feature",
  "properties": {
    "iso:country":"US",
    "sg:address":"413 S Cleveland St",
    "sg:city":"Waynoka",
    "sg:classifiers":[
        {
            "category":"Food & Beverages",
            "subcategory":"Fruits & Vegetables",
            "type":"Retail Goods"
        }
    ],
    "sg:phone":"+1 580 824 0915",
    "sg:postcode":"73860",
    "sg:province":"OK",
    "sg:tags":[
        "produce"
    ],
    "wof:name":"Gemini Private Security",
    "wof:placetype":"venue"
},
  "geometry": {"coordinates":[-98.88272,36.580884],"type":"Point"}
}