{
  "type": "Feature",
  "properties": {
    "iso:country":"US",
    "sg:address":"20902 SE 29th St",
    "sg:city":"Harrah",
    "sg:classifiers":[
        {
            "category":"Retail",
            "subcategory":"Auto Repair",
            "type":"Services"
        }
    ],
    "sg:phone":"+1 405 391 5646",
    "sg:postcode":"73045",
    "sg:province":"OK",
    "sg:tags":[
        "repairing",
        "automobile"
    ],
    "wof:name":"Newalla Automotive",
    "wof:placetype":"venue"
},
  "geometry": {"coordinates":[-97.159921,35.434946],"type":"Point"}
}