{
  "type": "Feature",
  "properties": {
    "iso:country":"US",
    "sg:address":"210 Cimarron Dr",
    "sg:city":"Fairview",
    "sg:classifiers":[
        {
            "category":"Farming",
            "subcategory":"Livestock Farm",
            "type":"Manufacturing & Wholesale Goods"
        }
    ],
    "sg:phone":"+1 580 227 2439",
    "sg:postcode":"73737",
    "sg:province":"OK",
    "sg:tags":[
        "beef",
        "feedlot",
        "cattle"
    ],
    "wof:name":"Cravens Ranch Inc",
    "wof:placetype":"venue"
},
  "geometry": {"coordinates":[-98.477889,36.279172],"type":"Point"}
}