{
  "type": "Feature",
  "properties": {
    "iso:country":"US",
    "sg:address":"824 N Milt Phillips Ave",
    "sg:city":"Seminole",
    "sg:classifiers":[
        {
            "category":"Banks & Credit Unions",
            "subcategory":"Bank",
            "type":"Services"
        }
    ],
    "sg:phone":"+1 405 303 2265",
    "sg:postcode":"74868",
    "sg:province":"OK",
    "wof:name":"Security State Bank",
    "wof:placetype":"venue"
},
  "geometry": {"coordinates":[-96.67096600000001,35.23069],"type":"Point"}
}