{
  "type": "Feature",
  "properties": {
    "iso:country":"US",
    "sg:address":"10 Valley Ridge Dr",
    "sg:city":"Lawton",
    "sg:classifiers":[
        {
            "category":"Farming",
            "subcategory":"Livestock Farm",
            "type":"Manufacturing & Wholesale Goods"
        }
    ],
    "sg:phone":"+1 580 536 9950",
    "sg:postcode":"73505",
    "sg:province":"OK",
    "sg:tags":[
        "animal",
        "general"
    ],
    "wof:name":"Double Jj Ranch",
    "wof:placetype":"venue"
},
  "geometry": {"coordinates":[-98.526597,34.624902],"type":"Point"}
}