{
  "type": "Feature",
  "properties": {
    "iso:country":"US",
    "sg:address":"2901 E 176th St N",
    "sg:city":"Skiatook",
    "sg:classifiers":[
        {
            "category":"Building & Trades",
            "subcategory":"Electrical",
            "type":"Services"
        }
    ],
    "sg:phone":"+1 918 396 0284",
    "sg:postcode":"74070",
    "sg:province":"OK",
    "sg:tags":[
        "electrical",
        "contractor"
    ],
    "wof:name":"Oleson Enterprises Inc",
    "wof:placetype":"venue"
},
  "geometry": {"coordinates":[-95.938232,36.409236],"type":"Point"}
}