{
  "type": "Feature",
  "properties": {
    "iso:country":"US",
    "sg:address":"1521 N Grand Ave",
    "sg:city":"Enid",
    "sg:classifiers":[
        {
            "category":"Retail",
            "subcategory":"Auto Repair",
            "type":"Services"
        }
    ],
    "sg:phone":"+1 580 234 1522",
    "sg:postcode":"73701",
    "sg:province":"OK",
    "sg:tags":[
        "transmission"
    ],
    "wof:name":"Smith Transmission & Machine",
    "wof:placetype":"venue"
},
  "geometry": {"coordinates":[-97.878257,36.412224],"type":"Point"}
}