{
  "type": "Feature",
  "properties": {
    "iso:country":"US",
    "sg:address":"901 N Main St",
    "sg:city":"Elk City",
    "sg:classifiers":[
        {
            "category":"Shopping",
            "subcategory":"Optical Goods",
            "type":"Retail Goods"
        }
    ],
    "sg:phone":"+1 580 243 1121",
    "sg:postcode":"73644",
    "sg:province":"OK",
    "sg:tags":[
        "contact",
        "lense"
    ],
    "sg:website":"www.drdanbintz.com",
    "wof:name":"Vision Source",
    "wof:placetype":"venue"
},
  "geometry": {"coordinates":[-99.404927,35.418356],"type":"Point"}
}