{
  "type": "Feature",
  "properties": {
    "iso:country":"US",
    "sg:address":"2615 W 78th St",
    "sg:city":"Tulsa",
    "sg:classifiers":[
        {
            "category":"Professional",
            "subcategory":"Management & Consulting",
            "type":"Services"
        }
    ],
    "sg:phone":"+1 918 445 5121",
    "sg:postcode":"74132",
    "sg:province":"OK",
    "sg:tags":[
        "consultant",
        "business"
    ],
    "wof:name":"Hudelson Group Inc",
    "wof:placetype":"venue"
},
  "geometry": {"coordinates":[-96.024102,36.051065],"type":"Point"}
}