{
  "type": "Feature",
  "properties": {
    "addr:full":"107 W Cleveland Ave Guthrie OK 73044",
    "addr:housenumber":"107",
    "addr:postcode":"73044",
    "addr:street":"W Cleveland Ave",
    "iso:country":"US",
    "sg:address":"107 W Cleveland Ave",
    "sg:city":"Guthrie",
    "sg:classifiers":[
        {
            "category":"Professional",
            "subcategory":"Business Services",
            "type":"Services"
        }
    ],
    "sg:phone":"+1 405 282 8881",
    "sg:postcode":"73044",
    "sg:province":"OK",
    "sg:tags":[
        "paging",
        "answering"
    ],
    "wof:name":"Terracom TCI",
    "wof:placetype":"venue"
},
  "geometry": {"coordinates":[-97.426501,35.878996],"type":"Point"}
}