{
  "type": "Feature",
  "properties": {
    "iso:country":"US",
    "sg:address":"10820 S Jardot Rd",
    "sg:city":"Perkins",
    "sg:classifiers":[
        {
            "category":"Education",
            "subcategory":"School",
            "type":"Public Place"
        }
    ],
    "sg:phone":"+1 405 547 2672",
    "sg:postcode":"74059",
    "sg:province":"OK",
    "wof:name":"Horticultural Research",
    "wof:placetype":"venue"
},
  "geometry": {"coordinates":[-97.03378,35.993853],"type":"Point"}
}