{
  "type": "Feature",
  "properties": {
    "addr:full":"6710 E Pine St Tulsa OK 74115",
    "addr:housenumber":"6710",
    "addr:postcode":"74115",
    "addr:street":"E Pine St",
    "iso:country":"US",
    "sg:address":"6710 E Pine St",
    "sg:city":"Tulsa",
    "sg:classifiers":[
        {
            "category":"Retail",
            "subcategory":"Repair Shop",
            "type":"Services"
        }
    ],
    "sg:phone":"+1 918 836 6999",
    "sg:postcode":"74115",
    "sg:province":"OK",
    "sg:tags":[
        "scooter",
        "motorcycle",
        "motor"
    ],
    "wof:name":"Total Performance Racers Inc",
    "wof:placetype":"venue"
},
  "geometry": {"coordinates":[-95.90106900000001,36.177018],"type":"Point"}
}