{
  "type": "Feature",
  "properties": {
    "addr:full":"809 S Agnew Ave Oklahoma City OK 73108",
    "addr:housenumber":"809",
    "addr:postcode":"73108",
    "addr:street":"S Agnew Ave",
    "iso:country":"US",
    "sg:address":"809 S Agnew Ave",
    "sg:city":"Oklahoma City",
    "sg:classifiers":[
        {
            "category":"Wholesale",
            "subcategory":"Auto Parts",
            "type":"Manufacturing & Wholesale Goods"
        }
    ],
    "sg:phone":"+1 405 236 3215",
    "sg:postcode":"73108",
    "sg:province":"OK",
    "sg:tags":[
        "truck",
        "accessory"
    ],
    "sg:website":"www.mrpickupdist.com",
    "wof:name":"Mr Pickup Distributing",
    "wof:placetype":"venue"
},
  "geometry": {"coordinates":[-97.55472,35.457041],"type":"Point"}
}