{
  "type": "Feature",
  "properties": {
    "iso:country":"US",
    "sg:address":"1510 W Main St",
    "sg:city":"Duncan",
    "sg:classifiers":[
        {
            "category":"Real Estate",
            "subcategory":"Real Estate Operator",
            "type":"Services"
        }
    ],
    "sg:phone":"+1 580 255 3933",
    "sg:postcode":"73533",
    "sg:province":"OK",
    "sg:tags":[
        "boarding",
        "house"
    ],
    "wof:name":"Duncan Community Residence Inc",
    "wof:placetype":"venue"
},
  "geometry": {"coordinates":[-97.968142,34.502735],"type":"Point"}
}