{
  "type": "Feature",
  "properties": {
    "addr:full":"409 N Lynn Riggs Blvd Claremore OK 74017",
    "addr:housenumber":"409",
    "addr:postcode":"74017",
    "addr:street":"N Lynn Riggs Blvd",
    "iso:country":"US",
    "sg:address":"409 N Lynn Riggs Blvd",
    "sg:city":"Claremore",
    "sg:classifiers":[
        {
            "category":"Food & Beverages",
            "subcategory":"Liquor & Beverages",
            "type":"Retail Goods"
        }
    ],
    "sg:phone":"+1 918 342 2362",
    "sg:postcode":"74017",
    "sg:province":"OK",
    "sg:tags":[
        "alcoholic"
    ],
    "wof:name":"Spirits Of 66",
    "wof:placetype":"venue"
},
  "geometry": {"coordinates":[-95.613805,36.316187],"type":"Point"}
}