{
  "type": "Feature",
  "properties": {
    "iso:country":"US",
    "sg:address":"823 NE 12th St",
    "sg:city":"Guymon",
    "sg:classifiers":[
        {
            "category":"Autos & Motor Vehicles",
            "subcategory":"Automobile Sales",
            "type":"Retail Goods"
        }
    ],
    "sg:phone":"+1 580 338 0471",
    "sg:postcode":"73942",
    "sg:province":"OK",
    "sg:tags":[
        "car",
        "dealer"
    ],
    "wof:name":"Robert Carter Chevrolet",
    "wof:placetype":"venue"
},
  "geometry": {"coordinates":[-101.471101,36.689412],"type":"Point"}
}