{
  "type": "Feature",
  "properties": {
    "iso:country":"US",
    "sg:address":"8517 E Reno Ave",
    "sg:city":"Oklahoma City",
    "sg:classifiers":[
        {
            "category":"Real Estate",
            "subcategory":"Real Estate Operator",
            "type":"Services"
        }
    ],
    "sg:phone":"+1 405 737 4828",
    "sg:postcode":"73110",
    "sg:province":"OK",
    "sg:tags":[
        "apartment",
        "complex"
    ],
    "wof:name":"Woodside Apartments",
    "wof:placetype":"venue"
},
  "geometry": {"coordinates":[-97.37869000000001,35.464131],"type":"Point"}
}