{
  "type": "Feature",
  "properties": {
    "iso:country":"US",
    "sg:address":"4420 Colonial Dr",
    "sg:city":"Sapulpa",
    "sg:classifiers":[
        {
            "category":"Retail",
            "subcategory":"Car Wash",
            "type":"Services"
        }
    ],
    "sg:phone":"+1 918 227 2220",
    "sg:postcode":"74066",
    "sg:province":"OK",
    "sg:tags":[
        "carwash"
    ],
    "wof:name":"Hydro Spray Carwash",
    "wof:placetype":"venue"
},
  "geometry": {"coordinates":[-96.04225,35.992846],"type":"Point"}
}