{
  "type": "Feature",
  "properties": {
    "iso:country":"US",
    "sg:address":"6740 S Oswego Ave",
    "sg:city":"Tulsa",
    "sg:classifiers":[
        {
            "category":"Shopping",
            "subcategory":"Gifts & Souvenirs",
            "type":"Retail Goods"
        }
    ],
    "sg:phone":"+1 918 492 5492",
    "sg:postcode":"74136",
    "sg:province":"OK",
    "sg:tags":[
        "cards",
        "greeting"
    ],
    "wof:name":"Christi Peye Designs",
    "wof:placetype":"venue"
},
  "geometry": {"coordinates":[-95.931641,36.064715],"type":"Point"}
}