{
  "type": "Feature",
  "properties": {
    "iso:country":"US",
    "sg:address":"33 N Greenmore Dr",
    "sg:city":"Edmond",
    "sg:classifiers":[
        {
            "category":"Mining & Drilling",
            "type":"Manufacturing & Wholesale Goods"
        }
    ],
    "sg:phone":"+1 405 330 5732",
    "sg:postcode":"73034",
    "sg:province":"OK",
    "sg:tags":[
        "exploration"
    ],
    "wof:name":"Gary Rumsey",
    "wof:placetype":"venue"
},
  "geometry": {"coordinates":[-97.405858,35.655002],"type":"Point"}
}