{
  "type": "Feature",
  "properties": {
    "iso:country":"US",
    "sg:address":"805 N Broadway Ave",
    "sg:city":"Ada",
    "sg:classifiers":[
        {
            "category":"Building & Trades",
            "subcategory":"Equipment Rental",
            "type":"Services"
        }
    ],
    "sg:phone":"+1 580 332 3900",
    "sg:postcode":"74820",
    "sg:province":"OK",
    "sg:tags":[
        "leasing",
        "furniture"
    ],
    "wof:name":"Aarons Sales & Lease Ownership",
    "wof:placetype":"venue"
},
  "geometry": {"coordinates":[-96.678827,34.78278],"type":"Point"}
}