{
  "type": "Feature",
  "properties": {
    "addr:full":"704 W Silver Meadow Dr Oklahoma City OK 73110",
    "addr:housenumber":"704",
    "addr:postcode":"73110",
    "addr:street":"W Silver Meadow Dr",
    "iso:country":"US",
    "sg:address":"704 W Silver Meadow Dr",
    "sg:city":"Oklahoma City",
    "sg:classifiers":[
        {
            "category":"Building & Trades",
            "subcategory":"Construction",
            "type":"Services"
        }
    ],
    "sg:phone":"+1 405 737 6386",
    "sg:postcode":"73110",
    "sg:province":"OK",
    "sg:tags":[
        "marking",
        "maintenance",
        "parking"
    ],
    "wof:name":"Dean's Sweeping & Striping Svc",
    "wof:placetype":"venue"
},
  "geometry": {"coordinates":[-97.41158299999999,35.471789],"type":"Point"}
}