{
  "type": "Feature",
  "properties": {
    "iso:country":"US",
    "sg:address":"729 Overland Trl",
    "sg:city":"Enid",
    "sg:classifiers":[
        {
            "category":"Government",
            "subcategory":"Office",
            "type":"Public Place"
        }
    ],
    "sg:phone":"+1 580 237 1081",
    "sg:postcode":"73703",
    "sg:province":"OK",
    "sg:tags":[
        "a",
        "department",
        "as",
        "human",
        "operates"
    ],
    "wof:name":"Human Services Oklahoma Dept",
    "wof:placetype":"venue"
},
  "geometry": {"coordinates":[-97.921289,36.390301],"type":"Point"}
}