{
  "type": "Feature",
  "properties": {
    "addr:full":"1235 E 24th Pl Tulsa OK 74114",
    "addr:housenumber":"1235",
    "addr:postcode":"74114",
    "addr:street":"E 24Th Pl",
    "iso:country":"US",
    "sg:address":"1235 E 24th Pl",
    "sg:city":"Tulsa",
    "sg:classifiers":[
        {
            "category":"Wholesale",
            "subcategory":"Medical Equipment & Supplies",
            "type":"Manufacturing & Wholesale Goods"
        }
    ],
    "sg:phone":"+1 918 749 5699",
    "sg:postcode":"74114",
    "sg:province":"OK",
    "wof:name":"Thomas Pruitt",
    "wof:placetype":"venue"
},
  "geometry": {"coordinates":[-95.975759,36.129795],"type":"Point"}
}