{
  "type": "Feature",
  "properties": {
    "iso:country":"US",
    "sg:address":"1503 NW Horton Blvd",
    "sg:city":"Lawton",
    "sg:classifiers":[
        {
            "category":"Professional",
            "subcategory":"Management & Consulting",
            "type":"Services"
        }
    ],
    "sg:phone":"+1 580 248 0942",
    "sg:postcode":"73505",
    "sg:province":"OK",
    "sg:tags":[
        "business"
    ],
    "wof:name":"Jo Vickers",
    "wof:placetype":"venue"
},
  "geometry": {"coordinates":[-98.468615,34.625087],"type":"Point"}
}