{
  "type": "Feature",
  "properties": {
    "iso:country":"US",
    "sg:address":"1324 W Oklahoma St",
    "sg:city":"Claremore",
    "sg:classifiers":[
        {
            "category":"Building & Trades",
            "subcategory":"Construction",
            "type":"Services"
        }
    ],
    "sg:phone":"+1 918 341 4210",
    "sg:postcode":"74017",
    "sg:province":"OK",
    "sg:tags":[
        "operator",
        "home",
        "general",
        "contractor"
    ],
    "wof:name":"Stimson Brothers Construction",
    "wof:placetype":"venue"
},
  "geometry": {"coordinates":[-95.625682,36.315598],"type":"Point"}
}