{
  "type": "Feature",
  "properties": {
    "iso:country":"US",
    "sg:address":"501 Westland Dr",
    "sg:city":"Edmond",
    "sg:classifiers":[
        {
            "category":"Building & Trades",
            "subcategory":"Construction",
            "type":"Services"
        }
    ],
    "sg:phone":"+1 405 330 0025",
    "sg:postcode":"73013",
    "sg:province":"OK",
    "sg:tags":[
        "roofing",
        "contractor"
    ],
    "sg:website":"www.redriverrfg.com",
    "wof:name":"Red River Roofing",
    "wof:placetype":"venue"
},
  "geometry": {"coordinates":[-97.490845,35.630136],"type":"Point"}
}