{
  "type": "Feature",
  "properties": {
    "iso:country":"US",
    "sg:address":"602 Barta Ave",
    "sg:city":"Chandler",
    "sg:classifiers":[
        {
            "category":"Home & Garden",
            "subcategory":"Building Materials",
            "type":"Retail Goods"
        }
    ],
    "sg:phone":"+1 405 567 4411",
    "sg:postcode":"74864",
    "sg:province":"OK",
    "sg:tags":[
        "glass",
        "window",
        "plate"
    ],
    "wof:name":"Melton Glass Co",
    "wof:placetype":"venue"
},
  "geometry": {"coordinates":[-96.68333699999999,35.482585],"type":"Point"}
}