{
  "type": "Feature",
  "properties": {
    "iso:country":"US",
    "sg:address":"707 Centennial Blvd",
    "sg:city":"Edmond",
    "sg:classifiers":[
        {
            "category":"Recreation",
            "type":"Entertainment"
        }
    ],
    "sg:phone":"+1 405 341 1175",
    "sg:postcode":"73013",
    "sg:province":"OK",
    "sg:tags":[
        "instruction",
        "gymnastic"
    ],
    "wof:name":"Oklahoma Gold Gymnastics",
    "wof:placetype":"venue"
},
  "geometry": {"coordinates":[-97.492952,35.628378],"type":"Point"}
}