{
  "type": "Feature",
  "properties": {
    "iso:country":"US",
    "sg:address":"221 W Division St",
    "sg:city":"Stilwell",
    "sg:classifiers":[
        {
            "category":"Professional",
            "subcategory":"Lawyer & Legal Services",
            "type":"Services"
        }
    ],
    "sg:phone":"+1 918 696 6227",
    "sg:postcode":"74960",
    "sg:province":"OK",
    "sg:tags":[
        "information",
        "attorney",
        "practice",
        "referral"
    ],
    "wof:name":"Morton Law Office",
    "wof:placetype":"venue"
},
  "geometry": {"coordinates":[-94.628687,35.814564],"type":"Point"}
}