{
  "type": "Feature",
  "properties": {
    "iso:country":"US",
    "sg:address":"10547 E 161st St S",
    "sg:city":"Bixby",
    "sg:phone":"+1 918 366 8289",
    "sg:postcode":"74008",
    "sg:province":"OK",
    "sg:tags":[
        "farm",
        "field",
        "soybean",
        "crop"
    ],
    "wof:name":"Helen Bolton",
    "wof:placetype":"venue"
},
  "geometry": {"coordinates":[-95.85748700000001,35.930216],"type":"Point"}
}