{
  "type": "Feature",
  "properties": {
    "iso:country":"US",
    "sg:address":"101 W 32nd Pl",
    "sg:city":"Sand Springs",
    "sg:classifiers":[
        {
            "category":"Building & Trades",
            "subcategory":"Plumbing",
            "type":"Services"
        }
    ],
    "sg:phone":"+1 918 241 4378",
    "sg:postcode":"74063",
    "sg:province":"OK",
    "sg:tags":[
        "plumbing",
        "contractor"
    ],
    "wof:name":"Stamper Plumbing & Heating",
    "wof:placetype":"venue"
},
  "geometry": {"coordinates":[-96.121602,36.115898],"type":"Point"}
}