{
  "type": "Feature",
  "properties": {
    "iso:country":"US",
    "sg:address":"204 Pleasant Ln",
    "sg:city":"Chickasha",
    "sg:phone":"+1 405 224 9522",
    "sg:postcode":"73018",
    "sg:province":"OK",
    "sg:tags":[
        "farm",
        "wheat",
        "beef",
        "feedlot",
        "cattle"
    ],
    "wof:name":"Pike Farm",
    "wof:placetype":"venue"
},
  "geometry": {"coordinates":[-97.960183,35.009677],"type":"Point"}
}