{
  "type": "Feature",
  "properties": {
    "addr:full":"6528 E 101st St S Tulsa OK 74133",
    "addr:housenumber":"6528",
    "addr:postcode":"74133",
    "addr:street":"E 101St St",
    "iso:country":"US",
    "sg:address":"6528 E 101st St S",
    "sg:city":"Tulsa",
    "sg:classifiers":[
        {
            "category":"Building & Trades",
            "subcategory":"Landscaping Services",
            "type":"Services"
        }
    ],
    "sg:phone":"+1 918 369 0330",
    "sg:postcode":"74133",
    "sg:province":"OK",
    "sg:tags":[
        "landscape"
    ],
    "wof:name":"American Sun Lwn Lndscp Svcs",
    "wof:placetype":"venue"
},
  "geometry": {"coordinates":[-95.90161500000001,36.01731],"type":"Point"}
}