{
  "type": "Feature",
  "properties": {
    "iso:country":"US",
    "sg:address":"707 NW 32nd Pl",
    "sg:city":"Newcastle",
    "sg:classifiers":[
        {
            "category":"Restaurant",
            "type":"Food & Drink"
        }
    ],
    "sg:menulink":"http://www.allmenus.com/ok/blanchard/86383-little-caesars-pizza/menu/",
    "sg:phone":"+1 405 387 3212",
    "sg:postcode":"73065",
    "sg:province":"OK",
    "sg:tags":[
        "american",
        "pizza"
    ],
    "wof:name":"Little Caesar's Pizza",
    "wof:placetype":"venue"
},
  "geometry": {"coordinates":[-97.609466,35.290977],"type":"Point"}
}