{
  "type": "Feature",
  "properties": {
    "iso:country":"US",
    "sg:address":"2429 S 129th E Ave",
    "sg:city":"Tulsa",
    "sg:classifiers":[
        {
            "category":"Organizations",
            "subcategory":"Community Association",
            "type":"Services"
        }
    ],
    "sg:phone":"+1 918 437 2434",
    "sg:postcode":"74134",
    "sg:province":"OK",
    "wof:name":"Sertoma International",
    "wof:placetype":"venue"
},
  "geometry": {"coordinates":[-95.833195,36.128514],"type":"Point"}
}