{
  "type": "Feature",
  "properties": {
    "iso:country":"US",
    "sg:address":"309 S Peters Ave",
    "sg:city":"Norman",
    "sg:classifiers":[
        {
            "category":"Professional",
            "subcategory":"Lawyer & Legal Services",
            "type":"Services"
        }
    ],
    "sg:phone":"+1 405 366 8036",
    "sg:postcode":"73069",
    "sg:province":"OK",
    "wof:name":"David E Ponder Atty",
    "wof:placetype":"venue"
},
  "geometry": {"coordinates":[-97.440066,35.218842],"type":"Point"}
}