{
  "type": "Feature",
  "properties": {
    "addr:full":"17803 Ranch Rd Collinsville OK 74021",
    "addr:housenumber":"17803",
    "addr:postcode":"74021",
    "addr:street":"Ranch Rd",
    "iso:country":"US",
    "sg:address":"17803 Ranch Rd",
    "sg:city":"Collinsville",
    "sg:classifiers":[
        {
            "category":"Manufacturing",
            "subcategory":"Apparel",
            "type":"Manufacturing & Wholesale Goods"
        }
    ],
    "sg:phone":"+1 918 371 9476",
    "sg:postcode":"74021",
    "sg:province":"OK",
    "wof:name":"Classic Designs",
    "wof:placetype":"venue"
},
  "geometry": {"coordinates":[-95.771621,36.331788],"type":"Point"}
}