{
  "type": "Feature",
  "properties": {
    "addr:full":"3732 E 44th St Tulsa OK 74135",
    "addr:housenumber":"3732",
    "addr:postcode":"74135",
    "addr:street":"E 44Th St",
    "iso:country":"US",
    "sg:address":"3732 E 44th St",
    "sg:city":"Tulsa",
    "sg:classifiers":[
        {
            "category":"Professional",
            "subcategory":"Business Services",
            "type":"Services"
        }
    ],
    "sg:phone":"+1 918 743 1026",
    "sg:postcode":"74135",
    "sg:province":"OK",
    "sg:tags":[
        "real estate"
    ],
    "wof:name":"Patio Company",
    "wof:placetype":"venue"
},
  "geometry": {"coordinates":[-95.93398000000001,36.100696],"type":"Point"}
}