{
  "type": "Feature",
  "properties": {
    "addr:full":"2021 S Cherokee St Catoosa OK 74015",
    "addr:housenumber":"2021",
    "addr:postcode":"74015",
    "addr:street":"S Cherokee St",
    "iso:country":"US",
    "sg:address":"2021 S Cherokee St",
    "sg:city":"Catoosa",
    "sg:classifiers":[
        {
            "category":"Restaurant",
            "type":"Food & Drink"
        }
    ],
    "sg:menulink":"http://www.allmenus.com/ok/catoosa/164451-wendys/menu/",
    "sg:phone":"+1 918 266 5335",
    "sg:postcode":"74015",
    "sg:province":"OK",
    "sg:tags":[
        "burger",
        "american",
        "soup"
    ],
    "wof:name":"Wendy's",
    "wof:placetype":"venue"
},
  "geometry": {"coordinates":[-95.760398,36.167204],"type":"Point"}
}