{
  "type": "Feature",
  "properties": {
    "iso:country":"US",
    "sg:address":"19500 Yearling Way",
    "sg:city":"Edmond",
    "sg:classifiers":[
        {
            "category":"Autos & Motor Vehicles",
            "subcategory":"Auto Supplies",
            "type":"Retail Goods"
        }
    ],
    "sg:phone":"+1 405 844 6205",
    "sg:postcode":"73012",
    "sg:province":"OK",
    "wof:name":"Frazier Tire Co",
    "wof:placetype":"venue"
},
  "geometry": {"coordinates":[-97.53986,35.669503],"type":"Point"}
}