{
  "type": "Feature",
  "properties": {
    "iso:country":"US",
    "sg:address":"1414 S Wood Dr",
    "sg:city":"Okmulgee",
    "sg:classifiers":[
        {
            "category":"Restaurant",
            "type":"Food & Drink"
        }
    ],
    "sg:menulink":"http://www.allmenus.com/ok/okmulgee/68529-mazzios-pizza/menu/",
    "sg:phone":"+1 918 664 4444",
    "sg:postcode":"74447",
    "sg:province":"OK",
    "sg:tags":[
        "american",
        "pizza"
    ],
    "wof:name":"Mazzio's Pizza",
    "wof:placetype":"venue"
},
  "geometry": {"coordinates":[-95.961798,35.60984],"type":"Point"}
}