{
  "type": "Feature",
  "properties": {
    "addr:full":"115 E Carl Albert Pkwy Mcalester OK 74501",
    "addr:housenumber":"115",
    "addr:postcode":"74501",
    "addr:street":"E Carl Albert Pkwy",
    "iso:country":"US",
    "sg:address":"115 E Carl Albert Pkwy",
    "sg:city":"Mcalester",
    "sg:classifiers":[
        {
            "category":"Government",
            "subcategory":"Court House",
            "type":"Public Place"
        }
    ],
    "sg:phone":"+1 918 423 6479",
    "sg:postcode":"74501",
    "sg:province":"OK",
    "sg:tags":[
        "county"
    ],
    "wof:name":"Pittsburg County Assoc Judge",
    "wof:placetype":"venue"
},
  "geometry": {"coordinates":[-95.769492,34.933451],"type":"Point"}
}