{
  "type": "Feature",
  "properties": {
    "iso:country":"US",
    "sg:address":"14600 Coyote Trl",
    "sg:city":"Oklahoma City",
    "sg:classifiers":[
        {
            "category":"Building & Trades",
            "subcategory":"Construction",
            "type":"Services"
        }
    ],
    "sg:phone":"+1 405 799 9100",
    "sg:postcode":"73165",
    "sg:province":"OK",
    "sg:tags":[
        "nonresidential"
    ],
    "wof:name":"R D 2 Inc",
    "wof:placetype":"venue"
},
  "geometry": {"coordinates":[-97.312341,35.325168],"type":"Point"}
}