{
  "type": "Feature",
  "properties": {
    "iso:country":"US",
    "sg:address":"3727 N 29th St",
    "sg:city":"Broken Arrow",
    "sg:classifiers":[
        {
            "category":"Retail",
            "subcategory":"Portrait Studio",
            "type":"Services"
        }
    ],
    "sg:phone":"+1 918 355 5835",
    "sg:postcode":"74014",
    "sg:province":"OK",
    "sg:tags":[
        "photo"
    ],
    "wof:name":"Dave Crowley",
    "wof:placetype":"venue"
},
  "geometry": {"coordinates":[-95.755024,36.089391],"type":"Point"}
}