{
  "type": "Feature",
  "properties": {
    "iso:country":"US",
    "sg:address":"1004 Lonnie Abbott Blvd",
    "sg:city":"Ada",
    "sg:classifiers":[
        {
            "category":"Restaurant",
            "type":"Food & Drink"
        }
    ],
    "sg:phone":"+1 580 310 0300",
    "sg:postcode":"74820",
    "sg:province":"OK",
    "sg:tags":[
        "eating"
    ],
    "wof:name":"Papas Pizzeria",
    "wof:placetype":"venue"
},
  "geometry": {"coordinates":[-96.665369,34.790164],"type":"Point"}
}