{
  "type": "Feature",
  "properties": {
    "iso:country":"US",
    "sg:address":"307 S Dewey Ave",
    "sg:city":"Bartlesville",
    "sg:classifiers":[
        {
            "category":"Retail",
            "subcategory":"Repair Shop",
            "type":"Services"
        }
    ],
    "sg:phone":"+1 918 336 7053",
    "sg:postcode":"74003",
    "sg:province":"OK",
    "sg:tags":[
        "lock",
        "locksmith"
    ],
    "wof:name":"Indian Lock & Key Shop",
    "wof:placetype":"venue"
},
  "geometry": {"coordinates":[-95.976068,36.751006],"type":"Point"}
}