{
  "type": "Feature",
  "properties": {
    "iso:country":"US",
    "sg:address":"515 Center Pt Rd",
    "sg:city":"Wilburton",
    "sg:classifiers":[
        {
            "category":"Social Services",
            "type":"Services"
        }
    ],
    "sg:phone":"+1 918 465 2389",
    "sg:postcode":"74578",
    "sg:province":"OK",
    "wof:name":"Choctaw Ntion Tribal Field Off",
    "wof:placetype":"venue"
},
  "geometry": {"coordinates":[-95.320156,34.930974],"type":"Point"}
}