{
  "type": "Feature",
  "properties": {
    "iso:country":"US",
    "sg:address":"513 Main Ave",
    "sg:city":"Woodward",
    "sg:classifiers":[
        {
            "category":"Home & Garden",
            "subcategory":"Garden Supply",
            "type":"Retail Goods"
        }
    ],
    "sg:phone":"+1 580 256 3001",
    "sg:postcode":"73801",
    "sg:province":"OK",
    "sg:tags":[
        "lawn",
        "mower"
    ],
    "wof:name":"Lawnmower Shop",
    "wof:placetype":"venue"
},
  "geometry": {"coordinates":[-99.387051,36.435707],"type":"Point"}
}