{
  "type": "Feature",
  "properties": {
    "addr:full":"3141 NW Expy Oklahoma City OK 73112",
    "addr:housenumber":"3141",
    "addr:postcode":"73112",
    "addr:street":"Nw Expy",
    "iso:country":"US",
    "sg:address":"3141 NW Expy",
    "sg:city":"Oklahoma City",
    "sg:classifiers":[
        {
            "category":"Travel",
            "subcategory":"Hotels & Motels",
            "type":"Entertainment"
        }
    ],
    "sg:phone":"+1 405 843 2002",
    "sg:postcode":"73112",
    "sg:province":"OK",
    "wof:name":"Country Inn & Suites",
    "wof:placetype":"venue"
},
  "geometry": {"coordinates":[-97.57063100000001,35.528306],"type":"Point"}
}