{
  "type": "Feature",
  "properties": {
    "iso:country":"US",
    "sg:address":"16200 Deer Ct",
    "sg:city":"Oklahoma City",
    "sg:classifiers":[
        {
            "category":"Building & Trades",
            "subcategory":"Construction",
            "type":"Services"
        }
    ],
    "sg:phone":"+1 405 794 6541",
    "sg:postcode":"73165",
    "sg:province":"OK",
    "sg:tags":[
        "hanging",
        "contractor"
    ],
    "wof:name":"Knutson Painting Linda",
    "wof:placetype":"venue"
},
  "geometry": {"coordinates":[-97.30223100000001,35.307354],"type":"Point"}
}