{
  "type": "Feature",
  "properties": {
    "addr:full":"1020 W Main St Ada OK 74820",
    "addr:housenumber":"1020",
    "addr:postcode":"74820",
    "addr:street":"W Main St",
    "iso:country":"US",
    "sg:address":"1020 W Main St",
    "sg:city":"Ada",
    "sg:classifiers":[
        {
            "category":"Wholesale",
            "subcategory":"Machinery & Supplies",
            "type":"Manufacturing & Wholesale Goods"
        }
    ],
    "sg:phone":"+1 580 332 2304",
    "sg:postcode":"74820",
    "sg:province":"OK",
    "sg:tags":[
        "propane",
        "equipment",
        "gas"
    ],
    "wof:name":"Rural Gas",
    "wof:placetype":"venue"
},
  "geometry": {"coordinates":[-96.693276,34.774576],"type":"Point"}
}