{
  "type": "Feature",
  "properties": {
    "addr:full":"114 Belmont Dr Chickasha OK 73018",
    "addr:housenumber":"114",
    "addr:postcode":"73018",
    "addr:street":"Belmont Dr",
    "iso:country":"US",
    "sg:address":"114 Belmont Dr",
    "sg:city":"Chickasha",
    "sg:classifiers":[
        {
            "category":"Retail",
            "subcategory":"Animal Services",
            "type":"Services"
        }
    ],
    "sg:phone":"+1 405 222 0394",
    "sg:postcode":"73018",
    "sg:province":"OK",
    "wof:name":"Happy Tails",
    "wof:placetype":"venue"
},
  "geometry": {"coordinates":[-97.940245,35.017255],"type":"Point"}
}