{
  "type": "Feature",
  "properties": {
    "iso:country":"US",
    "sg:address":"305 S Main St",
    "sg:city":"Yale",
    "sg:classifiers":[
        {
            "category":"Manufacturing",
            "subcategory":"Tools & Machinery",
            "type":"Manufacturing & Wholesale Goods"
        }
    ],
    "sg:phone":"+1 918 387 2036",
    "sg:postcode":"74085",
    "sg:province":"OK",
    "sg:tags":[
        "field",
        "mfg",
        "metal",
        "structural"
    ],
    "wof:name":"Supreme Mch & Stl Fabrication",
    "wof:placetype":"venue"
},
  "geometry": {"coordinates":[-96.69957700000001,36.112035],"type":"Point"}
}