{
  "type": "Feature",
  "properties": {
    "iso:country":"US",
    "sg:address":"965 W Will Rogers Blvd",
    "sg:city":"Claremore",
    "sg:classifiers":[
        {
            "category":"Shopping",
            "subcategory":"Stationery & Office Supplies",
            "type":"Retail Goods"
        },
        {
            "category":"Shopping",
            "subcategory":"Hobbies, Toys, & Games",
            "type":"Retail Goods"
        }
    ],
    "sg:phone":"+1 918 343 5553",
    "sg:postcode":"74017",
    "sg:province":"OK",
    "sg:tags":[
        "album",
        "scrapbook"
    ],
    "wof:name":"Simply Scrapbooks",
    "wof:placetype":"venue"
},
  "geometry": {"coordinates":[-95.621846,36.314873],"type":"Point"}
}