{
  "type": "Feature",
  "properties": {
    "iso:country":"US",
    "sg:address":"118 W Ferry St",
    "sg:city":"Salina",
    "sg:classifiers":[
        {
            "category":"Shopping",
            "subcategory":"Shoes",
            "type":"Retail Goods"
        }
    ],
    "sg:phone":"+1 918 434 5505",
    "sg:postcode":"74365",
    "sg:province":"OK",
    "wof:name":"Green Country Shoes & Boots",
    "wof:placetype":"venue"
},
  "geometry": {"coordinates":[-95.154333,36.292788],"type":"Point"}
}