{
  "type": "Feature",
  "properties": {
    "iso:country":"US",
    "sg:address":"450 S George Nigh Expy",
    "sg:city":"Bache",
    "sg:classifiers":[
        {
            "category":"Autos & Motor Vehicles",
            "subcategory":"Fuel & Gas Station",
            "type":"Retail Goods"
        }
    ],
    "sg:phone":"+1 918 429 0810",
    "sg:postcode":"74501",
    "sg:province":"OK",
    "sg:tags":[
        "station",
        "gasoline",
        "oil"
    ],
    "wof:name":"Murphy Oil USA Inc",
    "wof:placetype":"venue"
},
  "geometry": {"coordinates":[-95.74510100000001,34.913061],"type":"Point"}
}