{
  "type": "Feature",
  "properties": {
    "iso:country":"US",
    "sg:address":"1120 S Utica Ave",
    "sg:city":"Tulsa",
    "sg:classifiers":[
        {
            "category":"Shopping",
            "subcategory":"Gifts & Souvenirs",
            "type":"Retail Goods"
        }
    ],
    "sg:phone":"+1 918 579 7787",
    "sg:postcode":"74104",
    "sg:province":"OK",
    "sg:tags":[
        "shop"
    ],
    "wof:name":"Hillcrest Gift Shop",
    "wof:placetype":"venue"
},
  "geometry": {"coordinates":[-95.967242,36.146266],"type":"Point"}
}