{
  "type": "Feature",
  "properties": {
    "iso:country":"US",
    "sg:address":"3300 S 24th St W",
    "sg:city":"Muskogee",
    "sg:classifiers":[
        {
            "category":"Retail",
            "subcategory":"Laundry & Dry Cleaning",
            "type":"Services"
        }
    ],
    "sg:phone":"+1 918 682 1391",
    "sg:postcode":"74401",
    "sg:province":"OK",
    "sg:tags":[
        "linen",
        "supply"
    ],
    "wof:name":"Superior Linen Service Inc",
    "wof:placetype":"venue"
},
  "geometry": {"coordinates":[-95.393703,35.719385],"type":"Point"}
}