{
  "type": "Feature",
  "properties": {
    "iso:country":"US",
    "sg:address":"8429 NW 91st St",
    "sg:city":"Oklahoma City",
    "sg:classifiers":[
        {
            "category":"Professional",
            "type":"Services"
        }
    ],
    "sg:phone":"+1 405 722 7713",
    "sg:postcode":"73132",
    "sg:province":"OK",
    "wof:name":"Esperanza Burlison",
    "wof:placetype":"venue"
},
  "geometry": {"coordinates":[-97.663439,35.564347],"type":"Point"}
}