{
  "type": "Feature",
  "properties": {
    "iso:country":"US",
    "sg:address":"424 S Squires St",
    "sg:city":"Stillwater",
    "sg:classifiers":[
        {
            "category":"Communications",
            "subcategory":"Film & Video Production",
            "type":"Services"
        }
    ],
    "sg:phone":"+1 405 377 4699",
    "sg:postcode":"74074",
    "sg:province":"OK",
    "sg:tags":[
        "taping"
    ],
    "wof:name":"Big Productions",
    "wof:placetype":"venue"
},
  "geometry": {"coordinates":[-97.120088,36.116357],"type":"Point"}
}