{
  "type": "Feature",
  "properties": {
    "addr:full":"605 E Lindsey St Elmore City OK 73433",
    "addr:housenumber":"605",
    "addr:postcode":"73433",
    "addr:street":"E Lindsey St",
    "iso:country":"US",
    "sg:address":"605 E Lindsey St",
    "sg:city":"Elmore City",
    "sg:classifiers":[
        {
            "category":"Freight",
            "type":"Transportation"
        }
    ],
    "sg:phone":"+1 405 830 7904",
    "sg:postcode":"73433",
    "sg:province":"OK",
    "sg:tags":[
        "local",
        "trucking"
    ],
    "wof:name":"R and S Trucking LLC",
    "wof:placetype":"venue"
},
  "geometry": {"coordinates":[-97.390062,34.622983],"type":"Point"}
}