{
  "type": "Feature",
  "properties": {
    "iso:country":"US",
    "sg:address":"7326 W Gassaway Rd",
    "sg:city":"Hulbert",
    "sg:classifiers":[
        {
            "category":"Personal",
            "subcategory":"Barber",
            "type":"Services"
        }
    ],
    "sg:phone":"+1 918 772 2700",
    "sg:postcode":"74441",
    "sg:province":"OK",
    "sg:tags":[
        "shop"
    ],
    "wof:name":"Head To Toe",
    "wof:placetype":"venue"
},
  "geometry": {"coordinates":[-95.166701,35.944228],"type":"Point"}
}