{
  "type": "Feature",
  "properties": {
    "addr:full":"11003 E 41st St Tulsa OK 74146",
    "addr:housenumber":"11003",
    "addr:postcode":"74146",
    "addr:street":"E 41St St",
    "iso:country":"US",
    "sg:address":"11003 E 41st St",
    "sg:city":"Tulsa",
    "sg:classifiers":[
        {
            "category":"Banks & Credit Unions",
            "subcategory":"Bank",
            "type":"Services"
        }
    ],
    "sg:phone":"+1 918 628 1076",
    "sg:postcode":"74146",
    "sg:province":"OK",
    "sg:tags":[
        "loan"
    ],
    "wof:name":"Loan Mart-Payday Loans",
    "wof:placetype":"venue"
},
  "geometry": {"coordinates":[-95.852029,36.104559],"type":"Point"}
}