{
  "type": "Feature",
  "properties": {
    "addr:full":"2315 W Edison St Tulsa OK 74127",
    "addr:housenumber":"2315",
    "addr:postcode":"74127",
    "addr:street":"W Edison St",
    "iso:country":"US",
    "sg:address":"2315 W Edison St",
    "sg:city":"Tulsa",
    "sg:classifiers":[
        {
            "category":"Shopping",
            "type":"Retail Goods"
        }
    ],
    "sg:phone":"+1 918 599 9226",
    "sg:postcode":"74127",
    "sg:province":"OK",
    "sg:tags":[
        "telephone",
        "cellular"
    ],
    "wof:name":"Gilcrease Hills Retail",
    "wof:placetype":"venue"
},
  "geometry": {"coordinates":[-96.018311,36.161352],"type":"Point"}
}