{
  "type": "Feature",
  "properties": {
    "iso:country":"US",
    "sg:address":"4522 Oklahoma Ave",
    "sg:city":"Woodward",
    "sg:classifiers":[
        {
            "category":"Manufacturing",
            "subcategory":"Glass & Minerals",
            "type":"Manufacturing & Wholesale Goods"
        }
    ],
    "sg:phone":"+1 580 256 9462",
    "sg:postcode":"73801",
    "sg:province":"OK",
    "sg:tags":[
        "concrete",
        "brick",
        "prod",
        "block"
    ],
    "wof:name":"S & S Precast Concrete & Crane",
    "wof:placetype":"venue"
},
  "geometry": {"coordinates":[-99.438767,36.433627],"type":"Point"}
}