{
  "type": "Feature",
  "properties": {
    "iso:country":"US",
    "sg:address":"3320 SE 15th St",
    "sg:city":"Oklahoma City",
    "sg:classifiers":[
        {
            "category":"Education",
            "subcategory":"Special Training",
            "type":"Public Place"
        }
    ],
    "sg:phone":"+1 405 672 6114",
    "sg:postcode":"73115",
    "sg:province":"OK",
    "sg:tags":[
        "center"
    ],
    "wof:name":"Shekinah Learning Ctr",
    "wof:placetype":"venue"
},
  "geometry": {"coordinates":[-97.452362,35.44966],"type":"Point"}
}