{
  "type": "Feature",
  "properties": {
    "iso:country":"US",
    "sg:address":"5804 N Macarthur Blvd",
    "sg:city":"Oklahoma City",
    "sg:classifiers":[
        {
            "category":"Shopping",
            "type":"Retail Goods"
        },
        {
            "category":"Retail",
            "subcategory":"Animal Services",
            "type":"Services"
        }
    ],
    "sg:phone":"+1 405 722 2533",
    "sg:postcode":"73122",
    "sg:province":"OK",
    "sg:tags":[
        "pet",
        "grooming",
        "washing",
        "merchandise"
    ],
    "wof:name":"Cindy's Dog Grooming",
    "wof:placetype":"venue"
},
  "geometry": {"coordinates":[-97.618909,35.52954],"type":"Point"}
}