{
  "type": "Feature",
  "properties": {
    "addr:full":"3401 S Lightner Ln Oklahoma City OK 73179",
    "addr:housenumber":"3401",
    "addr:postcode":"73179",
    "addr:street":"S Lightner Ln",
    "iso:country":"US",
    "sg:address":"3401 S Lightner Ln",
    "sg:city":"Oklahoma City",
    "sg:classifiers":[
        {
            "category":"Retail",
            "subcategory":"Repair Shop",
            "type":"Services"
        }
    ],
    "sg:phone":"+1 405 745 4444",
    "sg:postcode":"73179",
    "sg:province":"OK",
    "wof:name":"Ricks Repair",
    "wof:placetype":"venue"
},
  "geometry": {"coordinates":[-97.65988299999999,35.433445],"type":"Point"}
}