{
  "type": "Feature",
  "properties": {
    "addr:full":"1211 N 9th St Sapulpa OK 74066",
    "addr:housenumber":"1211",
    "addr:postcode":"74066",
    "addr:street":"N 9Th St",
    "iso:country":"US",
    "sg:address":"1211 N 9th St",
    "sg:city":"Sapulpa",
    "sg:classifiers":[
        {
            "category":"Wholesale",
            "subcategory":"Tobacco Products",
            "type":"Manufacturing & Wholesale Goods"
        }
    ],
    "sg:phone":"+1 918 224 7777",
    "sg:postcode":"74066",
    "sg:province":"OK",
    "sg:tags":[
        "cigarette",
        "cigar",
        "dealer"
    ],
    "wof:name":"Standard Tobacco Co",
    "wof:placetype":"venue"
},
  "geometry": {"coordinates":[-96.111811,36.012626],"type":"Point"}
}