{
  "type": "Feature",
  "properties": {
    "iso:country":"US",
    "sg:address":"9726 E 42nd St",
    "sg:city":"Tulsa",
    "sg:classifiers":[
        {
            "category":"Building & Trades",
            "subcategory":"Construction",
            "type":"Services"
        }
    ],
    "sg:phone":"+1 918 834 1579",
    "sg:postcode":"74146",
    "sg:province":"OK",
    "sg:tags":[
        "excavating",
        "contractor"
    ],
    "wof:name":"Wilson Paving & Excavating",
    "wof:placetype":"venue"
},
  "geometry": {"coordinates":[-95.866284,36.101935],"type":"Point"}
}