{
  "type": "Feature",
  "properties": {
    "iso:country":"US",
    "sg:address":"9310 S Eastern Ave",
    "sg:city":"Oklahoma City",
    "sg:classifiers":[
        {
            "category":"Building & Trades",
            "subcategory":"Construction",
            "type":"Services"
        }
    ],
    "sg:phone":"+1 405 794 2729",
    "sg:postcode":"73160",
    "sg:province":"OK",
    "sg:tags":[
        "floor",
        "laying",
        "contractor"
    ],
    "wof:name":"Custom Floor Design Inc",
    "wof:placetype":"venue"
},
  "geometry": {"coordinates":[-97.476892,35.375393],"type":"Point"}
}