{
  "type": "Feature",
  "properties": {
    "addr:full":"600 E 1st St Pawhuska OK 74056",
    "addr:housenumber":"600",
    "addr:postcode":"74056",
    "addr:street":"E 1St St",
    "iso:country":"US",
    "sg:address":"600 E 1st St",
    "sg:city":"Pawhuska",
    "sg:classifiers":[
        {
            "category":"Local Transit",
            "type":"Transportation"
        }
    ],
    "sg:phone":"+1 918 287 1341",
    "sg:postcode":"74056",
    "sg:province":"OK",
    "sg:tags":[
        "passenger"
    ],
    "wof:name":"Mercy Ambulance Service",
    "wof:placetype":"venue"
},
  "geometry": {"coordinates":[-96.33296199999999,36.658327],"type":"Point"}
}