{
  "type": "Feature",
  "properties": {
    "iso:country":"US",
    "sg:address":"1714 S Boston Ave",
    "sg:city":"Tulsa",
    "sg:classifiers":[
        {
            "category":"Retail",
            "subcategory":"Repair Shop",
            "type":"Services"
        }
    ],
    "sg:phone":"+1 918 592 2581",
    "sg:postcode":"74119",
    "sg:province":"OK",
    "sg:tags":[
        "related"
    ],
    "wof:name":"Southwest Transportation",
    "wof:placetype":"venue"
},
  "geometry": {"coordinates":[-95.985162,36.136352],"type":"Point"}
}