{
  "type": "Feature",
  "properties": {
    "addr:full":"1720 E 14th Pl Tulsa OK 74104",
    "addr:housenumber":"1720",
    "addr:postcode":"74104",
    "addr:street":"E 14Th Pl",
    "iso:country":"US",
    "sg:address":"1720 E 14th Pl",
    "sg:city":"Tulsa",
    "sg:classifiers":[
        {
            "category":"Professional",
            "subcategory":"Lawyer & Legal Services",
            "type":"Services"
        }
    ],
    "sg:phone":"+1 918 742 3600",
    "sg:postcode":"74104",
    "sg:province":"OK",
    "sg:tags":[
        "attorney"
    ],
    "wof:name":"William R Mc Mahon",
    "wof:placetype":"venue"
},
  "geometry": {"coordinates":[-95.962898,36.141468],"type":"Point"}
}