{
  "type": "Feature",
  "properties": {
    "iso:country":"US",
    "sg:address":"14733 S Casper St",
    "sg:city":"Glenpool",
    "sg:classifiers":[
        {
            "category":"Autos & Motor Vehicles",
            "subcategory":"Automobile Sales",
            "type":"Retail Goods"
        }
    ],
    "sg:phone":"+1 918 321 5900",
    "sg:postcode":"74033",
    "sg:province":"OK",
    "sg:tags":[
        "car",
        "dealer"
    ],
    "wof:name":"B Line Motors",
    "wof:placetype":"venue"
},
  "geometry": {"coordinates":[-96.011451,35.953858],"type":"Point"}
}