{
  "type": "Feature",
  "properties": {
    "iso:country":"US",
    "sg:address":"2447 E 26th Pl",
    "sg:city":"Tulsa",
    "sg:classifiers":[
        {
            "category":"Professional",
            "subcategory":"Business Services",
            "type":"Services"
        }
    ],
    "sg:phone":"+1 918 749 7832",
    "sg:postcode":"74114",
    "sg:province":"OK",
    "sg:tags":[
        "interior",
        "decorating"
    ],
    "wof:name":"Accessories By Anne LLC",
    "wof:placetype":"venue"
},
  "geometry": {"coordinates":[-95.953696,36.125116],"type":"Point"}
}