{
  "type": "Feature",
  "properties": {
    "addr:full":"223 N Trade Center Ter Mustang OK 73064",
    "addr:housenumber":"223",
    "addr:postcode":"73064",
    "addr:street":"N Trade Center Ter",
    "iso:country":"US",
    "sg:address":"223 N Trade Center Ter",
    "sg:city":"Mustang",
    "sg:classifiers":[
        {
            "category":"Education",
            "subcategory":"Dance Studio",
            "type":"Public Place"
        }
    ],
    "sg:phone":"+1 405 376 5285",
    "sg:postcode":"73064",
    "sg:province":"OK",
    "sg:tags":[
        "school"
    ],
    "wof:name":"Grantham School Of Dance",
    "wof:placetype":"venue"
},
  "geometry": {"coordinates":[-97.721425,35.392542],"type":"Point"}
}