{
  "type": "Feature",
  "properties": {
    "iso:country":"US",
    "sg:address":"3302 Craftsman Dr",
    "sg:city":"Enid",
    "sg:classifiers":[
        {
            "category":"Shopping",
            "subcategory":"Clothing, Apparel, & Fashions",
            "type":"Retail Goods"
        }
    ],
    "sg:phone":"+1 580 237 3100",
    "sg:postcode":"73703",
    "sg:province":"OK",
    "sg:tags":[
        "uniform"
    ],
    "wof:name":"Uniform Stop",
    "wof:placetype":"venue"
},
  "geometry": {"coordinates":[-97.920568,36.388259],"type":"Point"}
}