{
  "type": "Feature",
  "properties": {
    "iso:country":"US",
    "sg:address":"9717 Castle Rd",
    "sg:city":"Oklahoma City",
    "sg:classifiers":[
        {
            "category":"Shopping",
            "subcategory":"Hobbies, Toys, & Games",
            "type":"Retail Goods"
        }
    ],
    "sg:phone":"+1 405 721 0165",
    "sg:postcode":"73162",
    "sg:province":"OK",
    "sg:tags":[
        "craft"
    ],
    "wof:name":"Freeman Enterprises",
    "wof:placetype":"venue"
},
  "geometry": {"coordinates":[-97.63553,35.569586],"type":"Point"}
}