{
  "type": "Feature",
  "properties": {
    "iso:country":"US",
    "sg:address":"4367 S Jamestown Ave",
    "sg:city":"Tulsa",
    "sg:classifiers":[
        {
            "category":"Professional",
            "subcategory":"Accounting & Tax Preparation",
            "type":"Services"
        }
    ],
    "sg:phone":"+1 918 745 2013",
    "sg:postcode":"74135",
    "sg:province":"OK",
    "wof:name":"Bottom Line Solutions",
    "wof:placetype":"venue"
},
  "geometry": {"coordinates":[-95.937823,36.100788],"type":"Point"}
}