{
  "type": "Feature",
  "properties": {
    "iso:country":"US",
    "sg:address":"15701 78th St",
    "sg:city":"Lexington",
    "sg:classifiers":[
        {
            "category":"Mining & Drilling",
            "type":"Manufacturing & Wholesale Goods"
        }
    ],
    "sg:phone":"+1 405 756 4061",
    "sg:postcode":"73051",
    "sg:province":"OK",
    "sg:tags":[
        "field"
    ],
    "wof:name":"Mikes Oilfield Service",
    "wof:placetype":"venue"
},
  "geometry": {"coordinates":[-97.325317,35.027862],"type":"Point"}
}