{
  "type": "Feature",
  "properties": {
    "iso:country":"US",
    "sg:address":"800 S 9th St",
    "sg:city":"Broken Arrow",
    "sg:classifiers":[
        {
            "category":"Freight",
            "type":"Transportation"
        }
    ],
    "sg:phone":"+1 918 258 0344",
    "sg:postcode":"74012",
    "sg:province":"OK",
    "sg:tags":[
        "delivery"
    ],
    "wof:name":"Professional Delivery Svc",
    "wof:placetype":"venue"
},
  "geometry": {"coordinates":[-95.77957000000001,36.043777],"type":"Point"}
}