{
  "type": "Feature",
  "properties": {
    "addr:full":"3107 S High Ave Oklahoma City OK 73129",
    "addr:housenumber":"3107",
    "addr:postcode":"73129",
    "addr:street":"S High Ave",
    "iso:country":"US",
    "sg:address":"3107 S High Ave",
    "sg:city":"Oklahoma City",
    "sg:classifiers":[
        {
            "category":"Building & Trades",
            "subcategory":"Construction",
            "type":"Services"
        }
    ],
    "sg:phone":"+1 405 672 3397",
    "sg:postcode":"73129",
    "sg:province":"OK",
    "sg:tags":[
        "roofing",
        "contractor"
    ],
    "wof:name":"De Hart Roofing & Sheet Metal",
    "wof:placetype":"venue"
},
  "geometry": {"coordinates":[-97.49482999999999,35.433529],"type":"Point"}
}