{
  "type": "Feature",
  "properties": {
    "iso:country":"US",
    "sg:address":"6998 S 145th E Ave",
    "sg:city":"Broken Arrow",
    "sg:classifiers":[
        {
            "category":"Professional",
            "subcategory":"Business Services",
            "type":"Services"
        },
        {
            "category":"Building & Trades",
            "subcategory":"Landscaping Services",
            "type":"Services"
        }
    ],
    "sg:phone":"+1 918 258 6420",
    "sg:postcode":"74012",
    "sg:province":"OK",
    "sg:tags":[
        "lawn",
        "landscape",
        "maintenance",
        "contractor"
    ],
    "wof:name":"Tulsa Grounds Keeper",
    "wof:placetype":"venue"
},
  "geometry": {"coordinates":[-95.81528299999999,36.06246],"type":"Point"}
}