{
  "type": "Feature",
  "properties": {
    "iso:country":"US",
    "sg:address":"609 N Harrison Ave",
    "sg:city":"Shawnee",
    "sg:classifiers":[
        {
            "category":"Shopping",
            "subcategory":"Used Merchandise",
            "type":"Retail Goods"
        }
    ],
    "sg:phone":"+1 405 395 9757",
    "sg:postcode":"74801",
    "sg:province":"OK",
    "wof:name":"Shawnee Auto Pawn",
    "wof:placetype":"venue"
},
  "geometry": {"coordinates":[-96.912037,35.334183],"type":"Point"}
}