{
  "type": "Feature",
  "properties": {
    "iso:country":"US",
    "sg:address":"8221 E 63rd Pl",
    "sg:city":"Tulsa",
    "sg:classifiers":[
        {
            "category":"Professional",
            "subcategory":"Employment Agencies",
            "type":"Services"
        }
    ],
    "sg:phone":"+1 918 250 0953",
    "sg:postcode":"74133",
    "sg:province":"OK",
    "sg:tags":[
        "help",
        "supply"
    ],
    "wof:name":"Medical Staffers Inc",
    "wof:placetype":"venue"
},
  "geometry": {"coordinates":[-95.88622599999999,36.071682],"type":"Point"}
}