{
  "type": "Feature",
  "properties": {
    "addr:full":"538 N Westminster Rd Oklahoma City OK 73130",
    "addr:housenumber":"538",
    "addr:postcode":"73130",
    "addr:street":"N Westminster Rd",
    "iso:country":"US",
    "sg:address":"538 N Westminster Rd",
    "sg:city":"Oklahoma City",
    "sg:classifiers":[
        {
            "category":"Wholesale",
            "subcategory":"Auto Parts",
            "type":"Manufacturing & Wholesale Goods"
        }
    ],
    "sg:phone":"+1 405 769 8366",
    "sg:postcode":"73130",
    "sg:province":"OK",
    "sg:tags":[
        "automobile",
        "rebuilt"
    ],
    "wof:name":"Barber's Auto & Pick-Up Slvg",
    "wof:placetype":"venue"
},
  "geometry": {"coordinates":[-97.335504,35.469743],"type":"Point"}
}