{
  "type": "Feature",
  "properties": {
    "iso:country":"US",
    "sg:address":"10820 E 45th St",
    "sg:city":"Tulsa",
    "sg:classifiers":[
        {
            "category":"Professional",
            "type":"Services"
        }
    ],
    "sg:phone":"+1 918 665 1691",
    "sg:postcode":"74146",
    "sg:province":"OK",
    "sg:tags":[
        "establishment"
    ],
    "wof:name":"Ameri-Ck Inc",
    "wof:placetype":"venue"
},
  "geometry": {"coordinates":[-95.855773,36.099733],"type":"Point"}
}