{
  "type": "Feature",
  "properties": {
    "iso:country":"US",
    "sg:address":"133 Ed Noble Pkwy",
    "sg:city":"Norman",
    "sg:classifiers":[
        {
            "category":"Utilities",
            "subcategory":"Mobile Phone",
            "type":"Services"
        }
    ],
    "sg:phone":"+1 405 579 2807",
    "sg:postcode":"73072",
    "sg:province":"OK",
    "sg:tags":[
        "telephone",
        "cellular"
    ],
    "wof:name":"Sprint",
    "wof:placetype":"venue"
},
  "geometry": {"coordinates":[-97.48988799999999,35.218225],"type":"Point"}
}