{
  "type": "Feature",
  "properties": {
    "iso:country":"US",
    "sg:address":"2525 E 21st St",
    "sg:city":"Tulsa",
    "sg:classifiers":[
        {
            "category":"Insurance",
            "subcategory":"Insurance Agent",
            "type":"Services"
        }
    ],
    "sg:phone":"+1 918 743 1344",
    "sg:postcode":"74114",
    "sg:province":"OK",
    "wof:name":"Bondpro Surety Specialist",
    "wof:placetype":"venue"
},
  "geometry": {"coordinates":[-95.953951,36.133323],"type":"Point"}
}