{
  "type": "Feature",
  "properties": {
    "iso:country":"US",
    "sg:address":"200 E Carl Albert Pkwy",
    "sg:city":"Bache",
    "sg:classifiers":[
        {
            "category":"Personal",
            "subcategory":"Beauty Salon",
            "type":"Services"
        }
    ],
    "sg:phone":"+1 918 426 4385",
    "sg:postcode":"74501",
    "sg:province":"OK",
    "sg:tags":[
        "shop"
    ],
    "wof:name":"Seventh Heaven",
    "wof:placetype":"venue"
},
  "geometry": {"coordinates":[-95.768253,34.933074],"type":"Point"}
}