{
  "type": "Feature",
  "properties": {
    "iso:country":"US",
    "sg:address":"1201 W Evergreen St",
    "sg:city":"Durant",
    "sg:classifiers":[
        {
            "category":"Health Services",
            "subcategory":"Chiropractor",
            "type":"Services"
        }
    ],
    "sg:phone":"+1 580 924 0781",
    "sg:postcode":"74701",
    "sg:province":"OK",
    "wof:name":"Meadows Clinic",
    "wof:placetype":"venue"
},
  "geometry": {"coordinates":[-96.389122,33.995231],"type":"Point"}
}