{
  "type": "Feature",
  "properties": {
    "iso:country":"US",
    "sg:address":"429 E Barnes Ave",
    "sg:city":"Alva",
    "sg:classifiers":[
        {
            "category":"Health Services",
            "subcategory":"Hospital",
            "type":"Services"
        }
    ],
    "sg:phone":"+1 580 327 0565",
    "sg:postcode":"73717",
    "sg:province":"OK",
    "sg:tags":[
        "mental"
    ],
    "wof:name":"Childrens Initiative Network",
    "wof:placetype":"venue"
},
  "geometry": {"coordinates":[-98.652675,36.803494],"type":"Point"}
}