{
  "type": "Feature",
  "properties": {
    "addr:full":"4901 Richmond Square Dr Oklahoma City OK 73118",
    "addr:housenumber":"4901",
    "addr:postcode":"73118",
    "addr:street":"Richmond Square Dr",
    "iso:country":"US",
    "sg:address":"4901 Richmond Square Dr",
    "sg:city":"Oklahoma City",
    "sg:classifiers":[
        {
            "category":"Professional",
            "subcategory":"Lawyer & Legal Services",
            "type":"Services"
        }
    ],
    "sg:phone":"+1 405 840 1929",
    "sg:postcode":"73118",
    "sg:province":"OK",
    "wof:name":"Harris Jnathan Attorney At Law",
    "wof:placetype":"venue"
},
  "geometry": {"coordinates":[-97.539576,35.521602],"type":"Point"}
}