{
  "type": "Feature",
  "properties": {
    "iso:country":"US",
    "sg:address":"2915 US Hwy 81",
    "sg:city":"Duncan",
    "sg:classifiers":[
        {
            "category":"Autos & Motor Vehicles",
            "subcategory":"Automobile Sales",
            "type":"Retail Goods"
        }
    ],
    "sg:phone":"+1 580 252 0441",
    "sg:postcode":"73533",
    "sg:province":"OK",
    "sg:tags":[
        "used",
        "supply"
    ],
    "wof:name":"Mangum Auto Sales",
    "wof:placetype":"venue"
},
  "geometry": {"coordinates":[-97.966874,34.539274],"type":"Point"}
}