{
  "type": "Feature",
  "properties": {
    "iso:country":"US",
    "sg:address":"21286 E 570 Rd",
    "sg:city":"Inola",
    "sg:classifiers":[
        {
            "category":"Farming",
            "subcategory":"Livestock Farm",
            "type":"Manufacturing & Wholesale Goods"
        }
    ],
    "sg:phone":"+1 918 543 2798",
    "sg:postcode":"74036",
    "sg:province":"OK",
    "sg:tags":[
        "beef",
        "feedlot",
        "cattle"
    ],
    "wof:name":"Alvin Froese",
    "wof:placetype":"venue"
},
  "geometry": {"coordinates":[-95.45301000000001,36.191405],"type":"Point"}
}