{
  "type": "Feature",
  "properties": {
    "iso:country":"US",
    "sg:address":"503 S 101st East Ave",
    "sg:city":"Tulsa",
    "sg:classifiers":[
        {
            "category":"Building & Trades",
            "subcategory":"Cleaning & Sanitation",
            "type":"Services"
        }
    ],
    "sg:phone":"+1 918 628 1547",
    "sg:postcode":"74128",
    "sg:province":"OK",
    "sg:tags":[
        "house"
    ],
    "wof:name":"Maid To Order",
    "wof:placetype":"venue"
},
  "geometry": {"coordinates":[-95.864671,36.153161],"type":"Point"}
}