{
  "type": "Feature",
  "properties": {
    "iso:country":"US",
    "sg:address":"7525 N May Ave",
    "sg:city":"Oklahoma City",
    "sg:classifiers":[
        {
            "category":"Personal",
            "subcategory":"Beauty Salon",
            "type":"Services"
        }
    ],
    "sg:phone":"+1 405 840 7885",
    "sg:postcode":"73116",
    "sg:province":"OK",
    "sg:tags":[
        "manicuring"
    ],
    "wof:name":"Vivi Nails",
    "wof:placetype":"venue"
},
  "geometry": {"coordinates":[-97.56574000000001,35.546814],"type":"Point"}
}