{
  "type": "Feature",
  "properties": {
    "addr:full":"1820 Travis Dr El Reno OK 73036",
    "addr:housenumber":"1820",
    "addr:postcode":"73036",
    "addr:street":"Travis Dr",
    "iso:country":"US",
    "sg:address":"1820 Travis Dr",
    "sg:city":"El Reno",
    "sg:classifiers":[
        {
            "category":"Retail",
            "subcategory":"Auto Repair",
            "type":"Services"
        }
    ],
    "sg:phone":"+1 405 262 9090",
    "sg:postcode":"73036",
    "sg:province":"OK",
    "sg:tags":[
        "repairing",
        "automobile"
    ],
    "wof:name":"United Auto & Truck Svc",
    "wof:placetype":"venue"
},
  "geometry": {"coordinates":[-97.93616299999999,35.518381],"type":"Point"}
}