{
  "type": "Feature",
  "properties": {
    "addr:full":"401 S 6th St Bache OK 74501",
    "addr:housenumber":"401",
    "addr:postcode":"74501",
    "addr:street":"S 6Th St",
    "iso:country":"US",
    "sg:address":"401 S 6th St",
    "sg:city":"Bache",
    "sg:classifiers":[
        {
            "category":"Shopping",
            "subcategory":"Florist",
            "type":"Retail Goods"
        }
    ],
    "sg:phone":"+1 918 423 5601",
    "sg:postcode":"74501",
    "sg:province":"OK",
    "wof:name":"Foster's Flowers",
    "wof:placetype":"venue"
},
  "geometry": {"coordinates":[-95.763453,34.926485],"type":"Point"}
}