{
  "type": "Feature",
  "properties": {
    "iso:country":"US",
    "sg:address":"406 W Branches Way",
    "sg:city":"Mustang",
    "sg:classifiers":[
        {
            "category":"Building & Trades",
            "subcategory":"Construction",
            "type":"Services"
        }
    ],
    "sg:phone":"+1 405 834 8907",
    "sg:postcode":"73064",
    "sg:province":"OK",
    "sg:tags":[
        "nonresidential"
    ],
    "wof:name":"Shane Kelly Construction",
    "wof:placetype":"venue"
},
  "geometry": {"coordinates":[-97.731828,35.397089],"type":"Point"}
}