{
  "type": "Feature",
  "properties": {
    "iso:country":"US",
    "sg:address":"18444 NE 23rd St",
    "sg:city":"Harrah",
    "sg:classifiers":[
        {
            "category":"Freight",
            "type":"Transportation"
        }
    ],
    "sg:phone":"+1 405 454 3841",
    "sg:postcode":"73045",
    "sg:province":"OK",
    "sg:tags":[
        "haulage",
        "truck",
        "dump"
    ],
    "wof:name":"Harrah Country Trucking Lc",
    "wof:placetype":"venue"
},
  "geometry": {"coordinates":[-97.204532,35.493109],"type":"Point"}
}