{
  "type": "Feature",
  "properties": {
    "iso:country":"US",
    "sg:address":"417 E Don Tyler Ave",
    "sg:city":"Dewey",
    "sg:classifiers":[
        {
            "category":"Health Services",
            "subcategory":"Doctor",
            "type":"Services"
        }
    ],
    "sg:phone":"+1 918 534 3170",
    "sg:postcode":"74029",
    "sg:province":"OK",
    "sg:tags":[
        "dentist"
    ],
    "wof:name":"Le Roy Place Inc",
    "wof:placetype":"venue"
},
  "geometry": {"coordinates":[-95.9367,36.799204],"type":"Point"}
}