{
  "type": "Feature",
  "properties": {
    "addr:full":"705 Main Ave Woodward OK 73801",
    "addr:housenumber":"705",
    "addr:postcode":"73801",
    "addr:street":"Main Ave",
    "iso:country":"US",
    "sg:address":"705 Main Ave",
    "sg:city":"Woodward",
    "sg:classifiers":[
        {
            "category":"Shopping",
            "type":"Retail Goods"
        }
    ],
    "sg:phone":"+1 580 337 6767",
    "sg:postcode":"73801",
    "sg:province":"OK",
    "sg:tags":[
        "art",
        "gallery",
        "dealer"
    ],
    "wof:name":"Kachina Gallery",
    "wof:placetype":"venue"
},
  "geometry": {"coordinates":[-99.38933299999999,36.435863],"type":"Point"}
}