{
  "type": "Feature",
  "properties": {
    "addr:full":"2620 S Meridian Ave Norman OK 73065",
    "addr:housenumber":"2620",
    "addr:postcode":"73065",
    "addr:street":"S Meridian Ave",
    "iso:country":"US",
    "sg:address":"2620 S Meridian Ave",
    "sg:city":"Norman",
    "sg:classifiers":[
        {
            "category":"Building & Trades",
            "subcategory":"Plumbing",
            "type":"Services"
        }
    ],
    "sg:phone":"+1 405 360 3517",
    "sg:postcode":"73065",
    "sg:province":"OK",
    "sg:tags":[
        "contractor"
    ],
    "wof:name":"Roto Rooter Plumbing Sewer & D",
    "wof:placetype":"venue"
},
  "geometry": {"coordinates":[-97.5998,35.226179],"type":"Point"}
}