{
  "type": "Feature",
  "properties": {
    "iso:country":"US",
    "sg:address":"10982 E 23rd St",
    "sg:city":"Tulsa",
    "sg:classifiers":[
        {
            "category":"Wholesale",
            "subcategory":"Machinery & Supplies",
            "type":"Manufacturing & Wholesale Goods"
        }
    ],
    "sg:phone":"+1 918 663 0690",
    "sg:postcode":"74129",
    "sg:province":"OK",
    "sg:tags":[
        "equipment"
    ],
    "wof:name":"E F C O",
    "wof:placetype":"venue"
},
  "geometry": {"coordinates":[-95.851792,36.130153],"type":"Point"}
}