{
  "type": "Feature",
  "properties": {
    "iso:country":"US",
    "sg:address":"721 3rd St",
    "sg:city":"Okeene",
    "sg:classifiers":[
        {
            "category":"Freight",
            "type":"Transportation"
        }
    ],
    "sg:phone":"+1 580 822 4125",
    "sg:postcode":"73763",
    "sg:province":"OK",
    "sg:tags":[
        "operator",
        "local",
        "trucking"
    ],
    "wof:name":"Yost Trucking",
    "wof:placetype":"venue"
},
  "geometry": {"coordinates":[-98.318366,36.123002],"type":"Point"}
}