{
  "type": "Feature",
  "properties": {
    "addr:full":"6143 E Admiral Pl Tulsa OK 74115",
    "addr:housenumber":"6143",
    "addr:postcode":"74115",
    "addr:street":"E Admiral Pl",
    "iso:country":"US",
    "sg:address":"6143 E Admiral Pl",
    "sg:city":"Tulsa",
    "sg:classifiers":[
        {
            "category":"Retail",
            "subcategory":"Repair Shop",
            "type":"Services"
        }
    ],
    "sg:phone":"+1 918 832 0604",
    "sg:postcode":"74115",
    "sg:province":"OK",
    "wof:name":"Joy Rileys Bookkeeping",
    "wof:placetype":"venue"
},
  "geometry": {"coordinates":[-95.90718699999999,36.160824],"type":"Point"}
}