{
  "type": "Feature",
  "properties": {
    "iso:country":"US",
    "sg:address":"4504 W Gore Blvd",
    "sg:city":"Lawton",
    "sg:classifiers":[
        {
            "category":"Farming",
            "subcategory":"Livestock Farm",
            "type":"Manufacturing & Wholesale Goods"
        }
    ],
    "sg:phone":"+1 580 357 1682",
    "sg:postcode":"73505",
    "sg:province":"OK",
    "sg:tags":[
        "beef",
        "feedlot",
        "cattle"
    ],
    "wof:name":"D Devilbiss",
    "wof:placetype":"venue"
},
  "geometry": {"coordinates":[-98.449251,34.608862],"type":"Point"}
}