{
  "type": "Feature",
  "properties": {
    "iso:country":"US",
    "sg:address":"3 N Shamrock Cir",
    "sg:city":"Shawnee",
    "sg:classifiers":[
        {
            "category":"Manufacturing",
            "subcategory":"Glass & Minerals",
            "type":"Manufacturing & Wholesale Goods"
        }
    ],
    "sg:phone":"+1 405 214 9366",
    "sg:postcode":"74804",
    "sg:province":"OK",
    "sg:tags":[
        "ready",
        "concrete",
        "product",
        "mfg"
    ],
    "wof:name":"Concrete Supply House LLC",
    "wof:placetype":"venue"
},
  "geometry": {"coordinates":[-96.927991,35.371516],"type":"Point"}
}