{
  "type": "Feature",
  "properties": {
    "iso:country":"US",
    "sg:address":"4306 S Peoria Ave",
    "sg:city":"Tulsa",
    "sg:classifiers":[
        {
            "category":"Education",
            "subcategory":"Special Training",
            "type":"Public Place"
        }
    ],
    "sg:phone":"+1 918 610 8122",
    "sg:postcode":"74105",
    "sg:province":"OK",
    "sg:tags":[
        "arcade",
        "amusement"
    ],
    "wof:name":"Huffy The Clown",
    "wof:placetype":"venue"
},
  "geometry": {"coordinates":[-95.9757,36.100494],"type":"Point"}
}