{
  "type": "Feature",
  "properties": {
    "iso:country":"US",
    "sg:address":"808 E Taft Ave",
    "sg:city":"Sapulpa",
    "sg:classifiers":[
        {
            "category":"Personal",
            "subcategory":"Beauty Salon",
            "type":"Services"
        }
    ],
    "sg:phone":"+1 918 224 8729",
    "sg:postcode":"74066",
    "sg:province":"OK",
    "sg:tags":[
        "shop"
    ],
    "wof:name":"Creative Touch Style Shop",
    "wof:placetype":"venue"
},
  "geometry": {"coordinates":[-96.102316,35.988293],"type":"Point"}
}