{
  "type": "Feature",
  "properties": {
    "addr:full":"320 E Main St Jenks OK 74037",
    "addr:housenumber":"320",
    "addr:postcode":"74037",
    "addr:street":"E Main St",
    "iso:country":"US",
    "sg:address":"320 E Main St",
    "sg:city":"Jenks",
    "sg:classifiers":[
        {
            "category":"Autos & Motor Vehicles",
            "subcategory":"Automobile Sales",
            "type":"Retail Goods"
        }
    ],
    "sg:phone":"+1 918 299 5955",
    "sg:postcode":"74037",
    "sg:province":"OK",
    "sg:tags":[
        "used"
    ],
    "wof:name":"Eagle Auto Sales",
    "wof:placetype":"venue"
},
  "geometry": {"coordinates":[-95.966082,36.022493],"type":"Point"}
}