{
  "type": "Feature",
  "properties": {
    "iso:country":"US",
    "sg:address":"1444 SE Washington Blvd",
    "sg:city":"Bartlesville",
    "sg:classifiers":[
        {
            "category":"Bars & Pubs",
            "type":"Food & Drink"
        }
    ],
    "sg:phone":"+1 918 333 0244",
    "sg:postcode":"74006",
    "sg:province":"OK",
    "sg:tags":[
        "club",
        "night"
    ],
    "wof:name":"Iguana Mirage Night Club",
    "wof:placetype":"venue"
},
  "geometry": {"coordinates":[-95.935145,36.732743],"type":"Point"}
}