{
  "type": "Feature",
  "properties": {
    "iso:country":"US",
    "sg:address":"5350 E 46th St",
    "sg:city":"Tulsa",
    "sg:classifiers":[
        {
            "category":"Wholesale",
            "subcategory":"Machinery & Supplies",
            "type":"Manufacturing & Wholesale Goods"
        }
    ],
    "sg:phone":"+1 918 627 5112",
    "sg:postcode":"74135",
    "sg:province":"OK",
    "sg:tags":[
        "actuator",
        "valve"
    ],
    "wof:name":"Mov LTD",
    "wof:placetype":"venue"
},
  "geometry": {"coordinates":[-95.916072,36.097019],"type":"Point"}
}