{
  "type": "Feature",
  "properties": {
    "iso:country":"US",
    "sg:address":"3216 S Rankin St",
    "sg:city":"Edmond",
    "sg:classifiers":[
        {
            "category":"Personal",
            "subcategory":"Beauty Salon",
            "type":"Services"
        }
    ],
    "sg:phone":"+1 405 330 0709",
    "sg:postcode":"73013",
    "sg:province":"OK",
    "sg:tags":[
        "shop"
    ],
    "wof:name":"Craig Compton's Studio Salon",
    "wof:placetype":"venue"
},
  "geometry": {"coordinates":[-97.474901,35.626445],"type":"Point"}
}