{
  "type": "Feature",
  "properties": {
    "iso:country":"US",
    "sg:address":"5565 Quail Dr",
    "sg:city":"Duncan",
    "sg:classifiers":[
        {
            "category":"Retail",
            "subcategory":"Repair Shop",
            "type":"Services"
        }
    ],
    "sg:phone":"+1 580 252 1132",
    "sg:postcode":"73533",
    "sg:province":"OK",
    "sg:tags":[
        "welding"
    ],
    "wof:name":"Jerrys Welding",
    "wof:placetype":"venue"
},
  "geometry": {"coordinates":[-97.961427,34.56494],"type":"Point"}
}