{
  "type": "Feature",
  "properties": {
    "addr:full":"908 E 12th Ave Stillwater OK 74074",
    "addr:housenumber":"908",
    "addr:postcode":"74074",
    "addr:street":"E 12Th Ave",
    "iso:country":"US",
    "sg:address":"908 E 12th Ave",
    "sg:city":"Stillwater",
    "sg:classifiers":[
        {
            "category":"Social Services",
            "subcategory":"Adult Care",
            "type":"Services"
        }
    ],
    "sg:phone":"+1 405 377 2439",
    "sg:postcode":"74074",
    "sg:province":"OK",
    "sg:tags":[
        "home",
        "residential"
    ],
    "wof:name":"Early Autumns Inc",
    "wof:placetype":"venue"
},
  "geometry": {"coordinates":[-97.04830699999999,36.108831],"type":"Point"}
}