{
  "type": "Feature",
  "properties": {
    "iso:country":"US",
    "sg:address":"2000 NE 23rd St",
    "sg:city":"Oklahoma City",
    "sg:classifiers":[
        {
            "category":"Education",
            "subcategory":"Library",
            "type":"Public Place"
        }
    ],
    "sg:phone":"+1 405 424 1437",
    "sg:postcode":"73111",
    "sg:province":"OK",
    "wof:name":"Ralph Ellison Library",
    "wof:placetype":"venue"
},
  "geometry": {"coordinates":[-97.474251,35.493128],"type":"Point"}
}