{
  "type": "Feature",
  "properties": {
    "iso:country":"US",
    "sg:address":"1318 NW 20th St",
    "sg:city":"Oklahoma City",
    "sg:classifiers":[
        {
            "category":"Shopping",
            "subcategory":"Shoes",
            "type":"Retail Goods"
        }
    ],
    "sg:phone":"+1 405 524 0584",
    "sg:postcode":"73106",
    "sg:province":"OK",
    "sg:tags":[
        "woman"
    ],
    "wof:name":"After 9 Shoes",
    "wof:placetype":"venue"
},
  "geometry": {"coordinates":[-97.53408,35.490096],"type":"Point"}
}