{
  "type": "Feature",
  "properties": {
    "addr:full":"123 S Park St Sapulpa OK 74066",
    "addr:housenumber":"123",
    "addr:postcode":"74066",
    "addr:street":"S Park St",
    "iso:country":"US",
    "sg:address":"123 S Park St",
    "sg:city":"Sapulpa",
    "sg:classifiers":[
        {
            "category":"Social Services",
            "subcategory":"Child Care",
            "type":"Services"
        }
    ],
    "sg:phone":"+1 918 224 9686",
    "sg:postcode":"74066",
    "sg:province":"OK",
    "sg:tags":[
        "kindergarten",
        "academic",
        "school"
    ],
    "wof:name":"Little Friends Pre-School",
    "wof:placetype":"venue"
},
  "geometry": {"coordinates":[-96.11132499999999,35.996712],"type":"Point"}
}