{
  "type": "Feature",
  "properties": {
    "iso:country":"US",
    "sg:address":"3033 N Walnut Ave",
    "sg:city":"Oklahoma City",
    "sg:classifiers":[
        {
            "category":"Professional",
            "subcategory":"Management & Consulting",
            "type":"Services"
        }
    ],
    "sg:phone":"+1 405 706 7329",
    "sg:postcode":"73105",
    "sg:province":"OK",
    "sg:tags":[
        "consultant",
        "business"
    ],
    "wof:name":"Evaluation Research Institute",
    "wof:placetype":"venue"
},
  "geometry": {"coordinates":[-97.507829,35.499312],"type":"Point"}
}