{
  "type": "Feature",
  "properties": {
    "iso:country":"US",
    "sg:address":"1112 Skelly Ave",
    "sg:city":"Guymon",
    "sg:classifiers":[
        {
            "category":"Professional",
            "type":"Services"
        }
    ],
    "sg:phone":"+1 580 468 5555",
    "sg:postcode":"73942",
    "sg:province":"OK",
    "sg:tags":[
        "establishment"
    ],
    "wof:name":"Total Body Therapy",
    "wof:placetype":"venue"
},
  "geometry": {"coordinates":[-101.474121,36.688486],"type":"Point"}
}