{
  "type": "Feature",
  "properties": {
    "iso:country":"US",
    "sg:address":"15190 NW Expressway St",
    "sg:city":"Piedmont",
    "sg:classifiers":[
        {
            "category":"Manufacturing",
            "subcategory":"Tools & Machinery",
            "type":"Manufacturing & Wholesale Goods"
        }
    ],
    "sg:phone":"+1 405 373 9001",
    "sg:postcode":"73078",
    "sg:province":"OK",
    "sg:tags":[
        "equipment",
        "oilfield",
        "mfg"
    ],
    "wof:name":"Design Service International",
    "wof:placetype":"venue"
},
  "geometry": {"coordinates":[-97.811989,35.634099],"type":"Point"}
}