{
  "type": "Feature",
  "properties": {
    "iso:country":"US",
    "sg:address":"2120 N Yellowood Ave",
    "sg:city":"Broken Arrow",
    "sg:classifiers":[
        {
            "category":"Communications",
            "subcategory":"Television Station",
            "type":"Services"
        }
    ],
    "sg:phone":"+1 918 250 0777",
    "sg:postcode":"74012",
    "sg:province":"OK",
    "sg:tags":[
        "broadcasting",
        "co"
    ],
    "sg:website":"www.tbn.org",
    "wof:name":"KDOR TV 17-Tbn",
    "wof:placetype":"venue"
},
  "geometry": {"coordinates":[-95.840649,36.071622],"type":"Point"}
}