{
  "type": "Feature",
  "properties": {
    "iso:country":"US",
    "sg:address":"421 E Ozark St",
    "sg:city":"Morris",
    "sg:classifiers":[
        {
            "category":"Manufacturing",
            "subcategory":"Printing",
            "type":"Manufacturing & Wholesale Goods"
        }
    ],
    "sg:phone":"+1 918 733 4898",
    "sg:postcode":"74445",
    "sg:province":"OK",
    "sg:tags":[
        "newspaper"
    ],
    "wof:name":"Morris News",
    "wof:placetype":"venue"
},
  "geometry": {"coordinates":[-95.859218,35.607593],"type":"Point"}
}