{
  "type": "Feature",
  "properties": {
    "iso:country":"US",
    "sg:address":"4609 Old Towne Rd",
    "sg:city":"Sand Springs",
    "sg:classifiers":[
        {
            "category":"Professional",
            "subcategory":"Secretarial Services",
            "type":"Services"
        }
    ],
    "sg:phone":"+1 918 241 3434",
    "sg:postcode":"74063",
    "sg:province":"OK",
    "sg:tags":[
        "reporting"
    ],
    "wof:name":"Eckles Tammy Reporting Service",
    "wof:placetype":"venue"
},
  "geometry": {"coordinates":[-96.197727,36.200457],"type":"Point"}
}