{
  "type": "Feature",
  "properties": {
    "iso:country":"US",
    "sg:address":"2430 SW 14th St",
    "sg:city":"Oklahoma City",
    "sg:classifiers":[
        {
            "category":"Food & Beverages",
            "subcategory":"Specialty",
            "type":"Retail Goods"
        }
    ],
    "sg:phone":"+1 405 234 8272",
    "sg:postcode":"73108",
    "sg:province":"OK",
    "sg:tags":[
        "tea",
        "coffee"
    ],
    "wof:name":"Those Guys Coffee & Slush",
    "wof:placetype":"venue"
},
  "geometry": {"coordinates":[-97.556675,35.450714],"type":"Point"}
}