{
  "type": "Feature",
  "properties": {
    "iso:country":"US",
    "sg:address":"231 E Main St",
    "sg:city":"Ada",
    "sg:classifiers":[
        {
            "category":"Government",
            "subcategory":"Office",
            "type":"Public Place"
        }
    ],
    "sg:phone":"+1 580 421 9664",
    "sg:postcode":"74820",
    "sg:province":"OK",
    "wof:name":"Rhoades For Senate",
    "wof:placetype":"venue"
},
  "geometry": {"coordinates":[-96.67653,34.774436],"type":"Point"}
}