{
  "type": "Feature",
  "properties": {
    "iso:country":"US",
    "sg:address":"5211 S Sheridan Rd",
    "sg:city":"Tulsa",
    "sg:classifiers":[
        {
            "category":"Shopping",
            "subcategory":"Crafts & Fabrics",
            "type":"Retail Goods"
        }
    ],
    "sg:phone":"+1 918 663 0003",
    "sg:postcode":"74145",
    "sg:province":"OK",
    "sg:tags":[
        "shop"
    ],
    "wof:name":"Decorator Fabric Showcase",
    "wof:placetype":"venue"
},
  "geometry": {"coordinates":[-95.90432300000001,36.08782],"type":"Point"}
}