{
  "type": "Feature",
  "properties": {
    "addr:full":"501 SE Frank Phillips Blvd Bartlesville OK 74006",
    "addr:housenumber":"501",
    "addr:postcode":"74006",
    "addr:street":"Se Frank Phillips Blvd",
    "iso:country":"US",
    "sg:address":"501 SE Frank Phillips Blvd",
    "sg:city":"Bartlesville",
    "sg:classifiers":[
        {
            "category":"Professional",
            "subcategory":"Lawyer & Legal Services",
            "type":"Services"
        }
    ],
    "sg:phone":"+1 918 336 0600",
    "sg:postcode":"74006",
    "sg:province":"OK",
    "wof:name":"Riseling & Assoc",
    "wof:placetype":"venue"
},
  "geometry": {"coordinates":[-95.971897,36.750662],"type":"Point"}
}