{
  "type": "Feature",
  "properties": {
    "iso:country":"US",
    "sg:address":"2223 E Main St",
    "sg:city":"Cushing",
    "sg:classifiers":[
        {
            "category":"Retail",
            "subcategory":"Auto Repair",
            "type":"Services"
        }
    ],
    "sg:phone":"+1 918 225 0760",
    "sg:postcode":"74023",
    "sg:province":"OK",
    "sg:tags":[
        "exhaust"
    ],
    "wof:name":"Discount Muffler",
    "wof:placetype":"venue"
},
  "geometry": {"coordinates":[-96.736546,35.985539],"type":"Point"}
}