{
  "type": "Feature",
  "properties": {
    "iso:country":"US",
    "sg:address":"6726 S Knoxville Ave",
    "sg:city":"Tulsa",
    "sg:classifiers":[
        {
            "category":"Shopping",
            "subcategory":"Gifts & Souvenirs",
            "type":"Retail Goods"
        }
    ],
    "sg:phone":"+1 918 664 0022",
    "sg:postcode":"74136",
    "sg:province":"OK",
    "sg:tags":[
        "cards",
        "greeting"
    ],
    "wof:name":"Shermans Hallmark Shop",
    "wof:placetype":"venue"
},
  "geometry": {"coordinates":[-95.936118,36.066514],"type":"Point"}
}