{
  "type": "Feature",
  "properties": {
    "iso:country":"US",
    "sg:address":"203 S Adair St",
    "sg:city":"Pryor",
    "sg:classifiers":[
        {
            "category":"Health Services",
            "subcategory":"Doctor",
            "type":"Services"
        }
    ],
    "sg:phone":"+1 918 825 9200",
    "sg:postcode":"74361",
    "sg:province":"OK",
    "sg:tags":[
        "physician",
        "surgeon"
    ],
    "wof:name":"Samule J Pangburn DO",
    "wof:placetype":"venue"
},
  "geometry": {"coordinates":[-95.31838,36.303939],"type":"Point"}
}