{
  "type": "Feature",
  "properties": {
    "addr:full":"210 N 4th St Seminole OK 74868",
    "addr:housenumber":"210",
    "addr:postcode":"74868",
    "addr:street":"N 4Th St",
    "iso:country":"US",
    "sg:address":"210 N 4th St",
    "sg:city":"Seminole",
    "sg:classifiers":[
        {
            "category":"Building & Trades",
            "subcategory":"Plumbing",
            "type":"Services"
        }
    ],
    "sg:phone":"+1 405 382 7363",
    "sg:postcode":"74868",
    "sg:province":"OK",
    "sg:tags":[
        "humidifying",
        "apparatus"
    ],
    "wof:name":"Combs Heating & Air",
    "wof:placetype":"venue"
},
  "geometry": {"coordinates":[-96.66712200000001,35.225379],"type":"Point"}
}