{
  "type": "Feature",
  "properties": {
    "iso:country":"US",
    "sg:address":"1336 SE 25th St",
    "sg:city":"Oklahoma City",
    "sg:classifiers":[
        {
            "category":"Autos & Motor Vehicles",
            "subcategory":"Auto Supplies",
            "type":"Retail Goods"
        }
    ],
    "sg:phone":"+1 405 670 9020",
    "sg:postcode":"73129",
    "sg:province":"OK",
    "sg:tags":[
        "automobile",
        "parts"
    ],
    "wof:name":"Carquest Auto Parts",
    "wof:placetype":"venue"
},
  "geometry": {"coordinates":[-97.487208,35.439004],"type":"Point"}
}