{
  "type": "Feature",
  "properties": {
    "iso:country":"US",
    "sg:address":"949 S 91st East Ave",
    "sg:city":"Tulsa",
    "sg:classifiers":[
        {
            "category":"Organizations",
            "subcategory":"Religious Organization",
            "type":"Services"
        }
    ],
    "sg:phone":"+1 918 836 8686",
    "sg:postcode":"74112",
    "sg:province":"OK",
    "sg:tags":[
        "real",
        "property",
        "book",
        "e",
        "lessor"
    ],
    "wof:name":"Eastwood Baptist Church",
    "wof:placetype":"venue"
},
  "geometry": {"coordinates":[-95.874878,36.148321],"type":"Point"}
}