{
  "type": "Feature",
  "properties": {
    "iso:country":"US",
    "sg:address":"104 NE A Ave",
    "sg:city":"Idabel",
    "sg:classifiers":[
        {
            "category":"Health Services",
            "subcategory":"Hospital",
            "type":"Services"
        }
    ],
    "sg:phone":"+1 580 286 3301",
    "sg:postcode":"74745",
    "sg:province":"OK",
    "sg:tags":[
        "specialty"
    ],
    "wof:name":"Kiamichi Council",
    "wof:placetype":"venue"
},
  "geometry": {"coordinates":[-94.827045,33.896025],"type":"Point"}
}