{
  "type": "Feature",
  "properties": {
    "addr:full":"230 W Wilshire Blvd Oklahoma City OK 73116",
    "addr:housenumber":"230",
    "addr:postcode":"73116",
    "addr:street":"W Wilshire Blvd",
    "iso:country":"US",
    "sg:address":"230 W Wilshire Blvd",
    "sg:city":"Oklahoma City",
    "sg:classifiers":[
        {
            "category":"Wholesale",
            "subcategory":"Drugs",
            "type":"Manufacturing & Wholesale Goods"
        }
    ],
    "sg:phone":"+1 405 843 0405",
    "sg:postcode":"73116",
    "sg:province":"OK",
    "sg:tags":[
        "pharmaceutical",
        "product"
    ],
    "sg:website":"www.cardinal.com",
    "wof:name":"Cardinal Health",
    "wof:placetype":"venue"
},
  "geometry": {"coordinates":[-97.51645000000001,35.551051],"type":"Point"}
}