{
  "type": "Feature",
  "properties": {
    "iso:country":"US",
    "sg:address":"2701 Keetoowah Trl",
    "sg:city":"Muskogee",
    "sg:classifiers":[
        {
            "category":"Social Services",
            "subcategory":"Child Care",
            "type":"Services"
        }
    ],
    "sg:phone":"+1 918 683 4116",
    "sg:postcode":"74403",
    "sg:province":"OK",
    "sg:tags":[
        "day"
    ],
    "wof:name":"Downs Schuler Inc",
    "wof:placetype":"venue"
},
  "geometry": {"coordinates":[-95.337125,35.781808],"type":"Point"}
}