{
  "type": "Feature",
  "properties": {
    "addr:full":"130 E 2nd St Ada OK 74820",
    "addr:housenumber":"130",
    "addr:postcode":"74820",
    "addr:street":"E 2Nd St",
    "iso:country":"US",
    "sg:address":"130 E 2nd St",
    "sg:city":"Ada",
    "sg:classifiers":[
        {
            "category":"Freight",
            "type":"Transportation"
        }
    ],
    "sg:phone":"+1 580 436 2073",
    "sg:postcode":"74820",
    "sg:province":"OK",
    "sg:tags":[
        "commercial",
        "storage"
    ],
    "wof:name":"Econo Mini Storage",
    "wof:placetype":"venue"
},
  "geometry": {"coordinates":[-96.67829999999999,34.783961],"type":"Point"}
}