{
  "type": "Feature",
  "properties": {
    "iso:country":"US",
    "sg:address":"203 Red Bud Ln",
    "sg:city":"Gore",
    "sg:classifiers":[
        {
            "category":"Freight",
            "type":"Transportation"
        }
    ],
    "sg:phone":"+1 918 489 2824",
    "sg:postcode":"74435",
    "sg:province":"OK",
    "sg:tags":[
        "commercial",
        "storage"
    ],
    "wof:name":"Gore Boat Rv & Mini Storage",
    "wof:placetype":"venue"
},
  "geometry": {"coordinates":[-95.109329,35.53682],"type":"Point"}
}