{
  "type": "Feature",
  "properties": {
    "iso:country":"US",
    "sg:address":"1000 E Fairlawn Rd",
    "sg:city":"Cushing",
    "sg:classifiers":[
        {
            "category":"Retail",
            "subcategory":"Auto Repair",
            "type":"Services"
        }
    ],
    "sg:phone":"+1 918 285 5165",
    "sg:postcode":"74023",
    "sg:province":"OK",
    "sg:tags":[
        "general"
    ],
    "wof:name":"Dales Import Auto Service",
    "wof:placetype":"venue"
},
  "geometry": {"coordinates":[-96.758172,36.029247],"type":"Point"}
}