{
  "type": "Feature",
  "properties": {
    "iso:country":"US",
    "sg:address":"101 E Ash St",
    "sg:city":"Fairview",
    "sg:classifiers":[
        {
            "category":"Professional",
            "subcategory":"Accounting & Tax Preparation",
            "type":"Services"
        }
    ],
    "sg:phone":"+1 580 227 3749",
    "sg:postcode":"73737",
    "sg:province":"OK",
    "sg:tags":[
        "accountant"
    ],
    "wof:name":"Moose & Stewart",
    "wof:placetype":"venue"
},
  "geometry": {"coordinates":[-98.47986899999999,36.272117],"type":"Point"}
}