{
  "type": "Feature",
  "properties": {
    "iso:country":"US",
    "sg:address":"5201 S Pennsylvania Ave",
    "sg:city":"Oklahoma City",
    "sg:classifiers":[
        {
            "category":"Food & Beverages",
            "subcategory":"Groceries & Convenience Stores",
            "type":"Retail Goods"
        }
    ],
    "sg:phone":"+1 405 686 7976",
    "sg:postcode":"73119",
    "sg:province":"OK",
    "wof:name":"P N Quick Stop",
    "wof:placetype":"venue"
},
  "geometry": {"coordinates":[-97.547936,35.412967],"type":"Point"}
}