{
  "type": "Feature",
  "properties": {
    "iso:country":"US",
    "sg:address":"10400 E 86th St N",
    "sg:city":"Owasso",
    "sg:classifiers":[
        {
            "category":"Freight",
            "type":"Transportation"
        }
    ],
    "sg:phone":"+1 918 272 2300",
    "sg:postcode":"74055",
    "sg:province":"OK",
    "sg:tags":[
        "commercial",
        "storage",
        "special"
    ],
    "wof:name":"Doc's Hideaway Mini Storage",
    "wof:placetype":"venue"
},
  "geometry": {"coordinates":[-95.857574,36.278449],"type":"Point"}
}