{
  "type": "Feature",
  "properties": {
    "addr:full":"2640 N Highway 167 Catoosa OK 74015",
    "addr:housenumber":"2640",
    "addr:postcode":"74015",
    "addr:street":"N Highway 167",
    "iso:country":"US",
    "sg:address":"2640 N Highway 167",
    "sg:city":"Catoosa",
    "sg:classifiers":[
        {
            "category":"Building & Trades",
            "subcategory":"Construction",
            "type":"Services"
        }
    ],
    "sg:phone":"+1 918 230 1889",
    "sg:postcode":"74015",
    "sg:province":"OK",
    "sg:tags":[
        "system",
        "specialty",
        "heating",
        "contractor",
        "air conditioning"
    ],
    "wof:name":"Arrowhead Geothermal Inc",
    "wof:placetype":"venue"
},
  "geometry": {"coordinates":[-95.758281,36.191677],"type":"Point"}
}