{
  "type": "Feature",
  "properties": {
    "addr:full":"5101 SE 54th St Oklahoma City OK 73135",
    "addr:housenumber":"5101",
    "addr:postcode":"73135",
    "addr:street":"Se 54Th St",
    "iso:country":"US",
    "sg:address":"5101 SE 54th St",
    "sg:city":"Oklahoma City",
    "sg:classifiers":[
        {
            "category":"Education",
            "subcategory":"Special Training",
            "type":"Public Place"
        }
    ],
    "sg:phone":"+1 405 672 2878",
    "sg:postcode":"73135",
    "sg:province":"OK",
    "sg:tags":[
        "educational"
    ],
    "wof:name":"Tommy Harmon",
    "wof:placetype":"venue"
},
  "geometry": {"coordinates":[-97.42738799999999,35.410837],"type":"Point"}
}