{
  "type": "Feature",
  "properties": {
    "iso:country":"US",
    "sg:address":"2515 SW Grand Blvd",
    "sg:city":"Oklahoma City",
    "sg:classifiers":[
        {
            "category":"Organizations",
            "subcategory":"Religious Organization",
            "type":"Services"
        }
    ],
    "sg:phone":"+1 405 685 4823",
    "sg:postcode":"73119",
    "sg:province":"OK",
    "wof:name":"Rockwood Baptist Chrh",
    "wof:placetype":"venue"
},
  "geometry": {"coordinates":[-97.557926,35.427797],"type":"Point"}
}