{
  "type": "Feature",
  "properties": {
    "iso:country":"US",
    "sg:address":"2215 N Main St",
    "sg:city":"Miami",
    "sg:classifiers":[
        {
            "category":"Autos & Motor Vehicles",
            "subcategory":"Auto Supplies",
            "type":"Retail Goods"
        }
    ],
    "sg:phone":"+1 918 542 2330",
    "sg:postcode":"74354",
    "sg:province":"OK",
    "sg:tags":[
        "tire"
    ],
    "wof:name":"Burggraf Tire Svc",
    "wof:placetype":"venue"
},
  "geometry": {"coordinates":[-94.877586,36.901473],"type":"Point"}
}