{
  "type": "Feature",
  "properties": {
    "iso:country":"US",
    "sg:address":"6701 S Bullard Chapel Rd",
    "sg:city":"Tishomingo",
    "sg:classifiers":[
        {
            "category":"Farming",
            "subcategory":"Dairy Farm",
            "type":"Manufacturing & Wholesale Goods"
        }
    ],
    "sg:phone":"+1 580 371 3619",
    "sg:postcode":"73460",
    "sg:province":"OK",
    "wof:name":"Warden Dairy",
    "wof:placetype":"venue"
},
  "geometry": {"coordinates":[-96.618633,34.278549],"type":"Point"}
}