{
  "type": "Feature",
  "properties": {
    "addr:full":"12200 SE 59th St Oklahoma City OK 73150",
    "addr:postcode":"12200;73150",
    "addr:street":"Se 59Th St",
    "iso:country":"US",
    "sg:address":"12200 SE 59th St",
    "sg:city":"Oklahoma City",
    "sg:classifiers":[
        {
            "category":"Real Estate",
            "subcategory":"Real Estate Agent",
            "type":"Services"
        }
    ],
    "sg:phone":"+1 405 692 6395",
    "sg:postcode":"73150",
    "sg:province":"OK",
    "wof:name":"Freemark Enterprises",
    "wof:placetype":"venue"
},
  "geometry": {"coordinates":[-97.303748,35.406277],"type":"Point"}
}