{
  "type": "Feature",
  "properties": {
    "iso:country":"US",
    "sg:address":"203 SW C Ave",
    "sg:city":"Lawton",
    "sg:classifiers":[
        {
            "category":"Personal",
            "subcategory":"Beauty Salon",
            "type":"Services"
        }
    ],
    "sg:phone":"+1 580 250 0926",
    "sg:postcode":"73502",
    "sg:province":"OK",
    "sg:tags":[
        "shop"
    ],
    "wof:name":"Studio Nail",
    "wof:placetype":"venue"
},
  "geometry": {"coordinates":[-98.392014,34.605282],"type":"Point"}
}