{
  "type": "Feature",
  "properties": {
    "iso:country":"US",
    "sg:address":"11915 E 51st St",
    "sg:city":"Tulsa",
    "sg:classifiers":[
        {
            "category":"Home & Garden",
            "subcategory":"Carpets & Floor Coverings",
            "type":"Retail Goods"
        }
    ],
    "sg:phone":"+1 918 254 2473",
    "sg:postcode":"74146",
    "sg:province":"OK",
    "sg:tags":[
        "material"
    ],
    "wof:name":"General Distributors",
    "wof:placetype":"venue"
},
  "geometry": {"coordinates":[-95.84072,36.090002],"type":"Point"}
}