{
  "type": "Feature",
  "properties": {
    "iso:country":"US",
    "sg:address":"803 S 3rd St",
    "sg:city":"Hugo",
    "sg:classifiers":[
        {
            "category":"Organizations",
            "subcategory":"Religious Organization",
            "type":"Services"
        }
    ],
    "sg:phone":"+1 580 326 3644",
    "sg:postcode":"74743",
    "sg:province":"OK",
    "sg:tags":[
        "church"
    ],
    "wof:name":"St Marks Episcopal Church",
    "wof:placetype":"venue"
},
  "geometry": {"coordinates":[-95.510204,34.002855],"type":"Point"}
}