{
  "type": "Feature",
  "properties": {
    "iso:country":"US",
    "sg:address":"136 State Hwy 152",
    "sg:city":"Mustang",
    "sg:classifiers":[
        {
            "category":"Health Services",
            "subcategory":"Doctor",
            "type":"Services"
        }
    ],
    "sg:phone":"+1 405 376 9414",
    "sg:postcode":"73064",
    "sg:province":"OK",
    "sg:tags":[
        "medical"
    ],
    "wof:name":"Janet Rodgers MD",
    "wof:placetype":"venue"
},
  "geometry": {"coordinates":[-97.723105,35.391602],"type":"Point"}
}