{
  "type": "Feature",
  "properties": {
    "iso:country":"US",
    "sg:address":"449 S Sheridan Rd",
    "sg:city":"Tulsa",
    "sg:classifiers":[
        {
            "category":"Food & Beverages",
            "subcategory":"Groceries & Convenience Stores",
            "type":"Retail Goods"
        }
    ],
    "sg:phone":"+1 918 836 7444",
    "sg:postcode":"74112",
    "sg:province":"OK",
    "wof:name":"Corner Stop",
    "wof:placetype":"venue"
},
  "geometry": {"coordinates":[-95.904482,36.155714],"type":"Point"}
}