{
  "type": "Feature",
  "properties": {
    "iso:country":"US",
    "sg:address":"8921 NW Expy",
    "sg:city":"Oklahoma City",
    "sg:classifiers":[
        {
            "category":"Autos & Motor Vehicles",
            "subcategory":"Automobile Sales",
            "type":"Retail Goods"
        }
    ],
    "sg:phone":"+1 405 720 8082",
    "sg:postcode":"73162",
    "sg:province":"OK",
    "sg:tags":[
        "car",
        "dealer"
    ],
    "wof:name":"Tom Tansel Motors LLC",
    "wof:placetype":"venue"
},
  "geometry": {"coordinates":[-97.664259,35.56921],"type":"Point"}
}