{
  "type": "Feature",
  "properties": {
    "iso:country":"US",
    "sg:address":"321 SE 5th St",
    "sg:city":"Oklahoma City",
    "sg:classifiers":[
        {
            "category":"Wholesale",
            "subcategory":"Medical Equipment & Supplies",
            "type":"Manufacturing & Wholesale Goods"
        }
    ],
    "sg:phone":"+1 405 799 8877",
    "sg:postcode":"73160",
    "sg:province":"OK",
    "sg:tags":[
        "physician",
        "surgeon"
    ],
    "wof:name":"Hossco",
    "wof:placetype":"venue"
},
  "geometry": {"coordinates":[-97.480677,35.333106],"type":"Point"}
}