{
  "type": "Feature",
  "properties": {
    "iso:country":"US",
    "sg:address":"1012 S Main St",
    "sg:city":"Stillwater",
    "sg:classifiers":[
        {
            "category":"Professional",
            "subcategory":"Computer Services",
            "type":"Services"
        }
    ],
    "sg:phone":"+1 405 743 3332",
    "sg:postcode":"74074",
    "sg:province":"OK",
    "sg:tags":[
        "repair"
    ],
    "wof:name":"City Computer Sales & Svc",
    "wof:placetype":"venue"
},
  "geometry": {"coordinates":[-97.058647,36.111114],"type":"Point"}
}