{
  "type": "Feature",
  "properties": {
    "addr:full":"102 6th St Kremlin OK 73753",
    "addr:housenumber":"102",
    "addr:postcode":"73753",
    "addr:street":"6Th St",
    "iso:country":"US",
    "sg:address":"102 6th St",
    "sg:city":"Kremlin",
    "sg:classifiers":[
        {
            "category":"Banks & Credit Unions",
            "subcategory":"Financial Services",
            "type":"Services"
        }
    ],
    "sg:phone":"+1 580 874 2244",
    "sg:postcode":"73753",
    "sg:province":"OK",
    "sg:tags":[
        "company",
        "holding"
    ],
    "wof:name":"Kremlin Bancshares",
    "wof:placetype":"venue"
},
  "geometry": {"coordinates":[-97.829131,36.550134],"type":"Point"}
}