{
  "type": "Feature",
  "properties": {
    "iso:country":"US",
    "sg:address":"1101 SE 26th St",
    "sg:city":"Oklahoma City",
    "sg:classifiers":[
        {
            "category":"Manufacturing",
            "subcategory":"Tools & Machinery",
            "type":"Manufacturing & Wholesale Goods"
        }
    ],
    "sg:phone":"+1 405 677 3391",
    "sg:postcode":"73129",
    "sg:province":"OK",
    "sg:tags":[
        "polishing",
        "car",
        "washing",
        "equipment"
    ],
    "wof:name":"Berkshire Corp",
    "wof:placetype":"venue"
},
  "geometry": {"coordinates":[-97.49091,35.438447],"type":"Point"}
}