{
  "type": "Feature",
  "properties": {
    "iso:country":"US",
    "sg:address":"1701 NW 177th Ter",
    "sg:city":"Edmond",
    "sg:classifiers":[
        {
            "category":"Retail",
            "subcategory":"Repair Shop",
            "type":"Services"
        }
    ],
    "sg:phone":"+1 405 359 9122",
    "sg:postcode":"73012",
    "sg:province":"OK",
    "sg:tags":[
        "watch"
    ],
    "wof:name":"Mullican Watch Repair Inc",
    "wof:placetype":"venue"
},
  "geometry": {"coordinates":[-97.546138,35.652485],"type":"Point"}
}