{
  "type": "Feature",
  "properties": {
    "addr:full":"7433 NW 101st St Oklahoma City OK 73162",
    "addr:housenumber":"7433",
    "addr:postcode":"73162",
    "addr:street":"Nw 101St St",
    "iso:country":"US",
    "sg:address":"7433 NW 101st St",
    "sg:city":"Oklahoma City",
    "sg:classifiers":[
        {
            "category":"Personal",
            "type":"Services"
        }
    ],
    "sg:phone":"+1 405 721 1784",
    "sg:postcode":"73162",
    "sg:province":"OK",
    "wof:name":"Handyman & More",
    "wof:placetype":"venue"
},
  "geometry": {"coordinates":[-97.646541,35.573555],"type":"Point"}
}