{
  "type": "Feature",
  "properties": {
    "addr:full":"2082 Windmill Ln Enid OK 73703",
    "addr:housenumber":"2082",
    "addr:postcode":"73703",
    "addr:street":"Windmill Ln",
    "iso:country":"US",
    "sg:address":"2082 Windmill Ln",
    "sg:city":"Enid",
    "sg:classifiers":[
        {
            "category":"Professional",
            "type":"Services"
        }
    ],
    "sg:phone":"+1 580 233 0107",
    "sg:postcode":"73703",
    "sg:province":"OK",
    "wof:name":"Carlos Lindo",
    "wof:placetype":"venue"
},
  "geometry": {"coordinates":[-97.905293,36.423844],"type":"Point"}
}