{
  "type": "Feature",
  "properties": {
    "iso:country":"US",
    "sg:address":"2501 Crystal Dr",
    "sg:city":"Oklahoma City",
    "sg:classifiers":[
        {
            "category":"Wholesale",
            "subcategory":"Home Furnishings",
            "type":"Manufacturing & Wholesale Goods"
        }
    ],
    "sg:phone":"+1 817 466 8432",
    "sg:postcode":"73160",
    "sg:province":"OK",
    "sg:tags":[
        "decor",
        "rug"
    ],
    "wof:name":"Solomon S Artifacts",
    "wof:placetype":"venue"
},
  "geometry": {"coordinates":[-97.486143,35.315322],"type":"Point"}
}