{
  "type": "Feature",
  "properties": {
    "iso:country":"US",
    "sg:address":"1601 W Fox Dr",
    "sg:city":"Enid",
    "sg:classifiers":[
        {
            "category":"Retail",
            "subcategory":"Laundry & Dry Cleaning",
            "type":"Services"
        }
    ],
    "sg:phone":"+1 580 233 6347",
    "sg:postcode":"73703",
    "sg:province":"OK",
    "sg:tags":[
        "cleaners"
    ],
    "wof:name":"Vance AFB Laundry & Dry",
    "wof:placetype":"venue"
},
  "geometry": {"coordinates":[-97.897844,36.347224],"type":"Point"}
}