{
  "type": "Feature",
  "properties": {
    "iso:country":"US",
    "sg:address":"3001 NW 73rd St",
    "sg:city":"Oklahoma City",
    "sg:classifiers":[
        {
            "category":"Education",
            "subcategory":"Dance Studio",
            "type":"Public Place"
        }
    ],
    "sg:phone":"+1 405 848 6232",
    "sg:postcode":"73116",
    "sg:province":"OK",
    "sg:tags":[
        "instruction",
        "dancing"
    ],
    "wof:name":"Oklahoma Community Dance Allnc",
    "wof:placetype":"venue"
},
  "geometry": {"coordinates":[-97.57077700000001,35.543397],"type":"Point"}
}