{
  "type": "Feature",
  "properties": {
    "iso:country":"US",
    "sg:address":"1413 SW Lee Blvd",
    "sg:city":"Lawton",
    "sg:classifiers":[
        {
            "category":"Retail",
            "subcategory":"Repair Shop",
            "type":"Services"
        }
    ],
    "sg:phone":"+1 580 357 0005",
    "sg:postcode":"73501",
    "sg:province":"OK",
    "sg:tags":[
        "television",
        "radio"
    ],
    "wof:name":"Matthews TV Sales & Svc",
    "wof:placetype":"venue"
},
  "geometry": {"coordinates":[-98.410687,34.594397],"type":"Point"}
}