{
  "type": "Feature",
  "properties": {
    "iso:country":"US",
    "sg:address":"11407 N May Ave",
    "sg:city":"Oklahoma City",
    "sg:classifiers":[
        {
            "category":"Personal",
            "subcategory":"Adult",
            "type":"Services"
        }
    ],
    "sg:phone":"+1 405 748 7050",
    "sg:postcode":"73120",
    "sg:province":"OK",
    "sg:tags":[
        "escort"
    ],
    "wof:name":"Around The World Escorts",
    "wof:placetype":"venue"
},
  "geometry": {"coordinates":[-97.56726500000001,35.587284],"type":"Point"}
}