{
  "type": "Feature",
  "properties": {
    "iso:country":"US",
    "sg:address":"200 S Westminster Rd",
    "sg:city":"Midwest City",
    "sg:classifiers":[
        {
            "category":"Wholesale",
            "subcategory":"Machinery & Supplies",
            "type":"Manufacturing & Wholesale Goods"
        },
        {
            "category":"Building & Trades",
            "subcategory":"Construction",
            "type":"Services"
        }
    ],
    "sg:phone":"+1 405 769 3545",
    "sg:postcode":"73130",
    "sg:province":"OK",
    "sg:tags":[
        "water",
        "repair",
        "pump",
        "well",
        "drilling"
    ],
    "wof:name":"Busby Pump & Well Service",
    "wof:placetype":"venue"
},
  "geometry": {"coordinates":[-97.335558,35.462913],"type":"Point"}
}