{
  "type": "Feature",
  "properties": {
    "addr:full":"1500 N Louis Tittle Ave Mangum OK 73554",
    "addr:housenumber":"1500",
    "addr:postcode":"73554",
    "addr:street":"N Louis Tittle Ave",
    "iso:country":"US",
    "sg:address":"1500 N Louis Tittle Ave",
    "sg:city":"Mangum",
    "sg:classifiers":[
        {
            "category":"Shopping",
            "subcategory":"Discount & Variety Stores",
            "type":"Retail Goods"
        }
    ],
    "sg:phone":"+1 580 782 2411",
    "sg:postcode":"73554",
    "sg:province":"OK",
    "wof:name":"Dollar General",
    "wof:placetype":"venue"
},
  "geometry": {"coordinates":[-99.502465,34.886647],"type":"Point"}
}