{
  "type": "Feature",
  "properties": {
    "addr:full":"77 E Breckenridge Ave Bixby OK 74008",
    "addr:housenumber":"77",
    "addr:postcode":"74008",
    "addr:street":"E Breckenridge Ave",
    "iso:country":"US",
    "sg:address":"77 E Breckenridge Ave",
    "sg:city":"Bixby",
    "sg:classifiers":[
        {
            "category":"Organizations",
            "subcategory":"Religious Organization",
            "type":"Services"
        }
    ],
    "sg:phone":"+1 918 366 4463",
    "sg:postcode":"74008",
    "sg:province":"OK",
    "sg:tags":[
        "church"
    ],
    "wof:name":"First United Methodist Church",
    "wof:placetype":"venue"
},
  "geometry": {"coordinates":[-95.88320299999999,35.941461],"type":"Point"}
}