{
  "type": "Feature",
  "properties": {
    "addr:full":"4984 S Memorial Dr Tulsa OK 74145",
    "addr:housenumber":"4984",
    "addr:postcode":"74145",
    "addr:street":"S Memorial Dr",
    "iso:country":"US",
    "sg:address":"4984 S Memorial Dr",
    "sg:city":"Tulsa",
    "sg:classifiers":[
        {
            "category":"Shopping",
            "subcategory":"Books",
            "type":"Retail Goods"
        }
    ],
    "sg:phone":"+1 918 663 9885",
    "sg:postcode":"74145",
    "sg:province":"OK",
    "sg:tags":[
        "religious",
        "store"
    ],
    "wof:name":"Cokesbury Book Store",
    "wof:placetype":"venue"
},
  "geometry": {"coordinates":[-95.886594,36.092938],"type":"Point"}
}