{
  "type": "Feature",
  "properties": {
    "addr:full":"9622 N May Ave Oklahoma City OK 73120",
    "addr:housenumber":"9622",
    "addr:postcode":"73120",
    "addr:street":"N May Ave",
    "iso:country":"US",
    "sg:address":"9622 N May Ave",
    "sg:city":"Oklahoma City",
    "sg:classifiers":[
        {
            "category":"Restaurant",
            "type":"Food & Drink"
        }
    ],
    "sg:phone":"+1 405 755 3577",
    "sg:postcode":"73120",
    "sg:province":"OK",
    "wof:name":"Caffe' Pranzo",
    "wof:placetype":"venue"
},
  "geometry": {"coordinates":[-97.567105,35.568742],"type":"Point"}
}