{
  "type": "Feature",
  "properties": {
    "iso:country":"US",
    "sg:address":"1517 US Hwy 81",
    "sg:city":"Duncan",
    "sg:classifiers":[
        {
            "category":"Food & Beverages",
            "subcategory":"Specialty",
            "type":"Retail Goods"
        }
    ],
    "sg:phone":"+1 580 252 1084",
    "sg:postcode":"73533",
    "sg:province":"OK",
    "sg:tags":[
        "health",
        "diet"
    ],
    "wof:name":"General Nutrition Ctr",
    "wof:placetype":"venue"
},
  "geometry": {"coordinates":[-97.96682,34.521605],"type":"Point"}
}