{
  "type": "Feature",
  "properties": {
    "addr:full":"131 W Willow Rd Enid OK 73701",
    "addr:housenumber":"131",
    "addr:postcode":"73701",
    "addr:street":"W Willow Rd",
    "iso:country":"US",
    "sg:address":"131 W Willow Rd",
    "sg:city":"Enid",
    "sg:classifiers":[
        {
            "category":"Shopping",
            "type":"Retail Goods"
        }
    ],
    "sg:phone":"+1 580 237 1118",
    "sg:postcode":"73701",
    "sg:province":"OK",
    "sg:tags":[
        "merchandise"
    ],
    "wof:name":"Pellow Monuments",
    "wof:placetype":"venue"
},
  "geometry": {"coordinates":[-97.879616,36.419853],"type":"Point"}
}