{
  "type": "Feature",
  "properties": {
    "iso:country":"US",
    "sg:address":"20 S Sheridan Rd",
    "sg:city":"Tulsa",
    "sg:classifiers":[
        {
            "category":"Banks & Credit Unions",
            "subcategory":"Bank",
            "type":"Services"
        }
    ],
    "sg:phone":"+1 918 583 1771",
    "sg:postcode":"74112",
    "sg:province":"OK",
    "sg:tags":[
        "cashing",
        "check"
    ],
    "wof:name":"Cash In A Flash",
    "wof:placetype":"venue"
},
  "geometry": {"coordinates":[-95.904647,36.160429],"type":"Point"}
}