{
  "type": "Feature",
  "properties": {
    "iso:country":"US",
    "sg:address":"803 4th St",
    "sg:city":"Alva",
    "sg:classifiers":[
        {
            "category":"Wholesale",
            "subcategory":"Machinery & Supplies",
            "type":"Manufacturing & Wholesale Goods"
        }
    ],
    "sg:phone":"+1 580 327 4000",
    "sg:postcode":"73717",
    "sg:province":"OK",
    "wof:name":"Sternberger & Baker Feed Yard",
    "wof:placetype":"venue"
},
  "geometry": {"coordinates":[-98.66365,36.800024],"type":"Point"}
}