{
  "type": "Feature",
  "properties": {
    "addr:full":"709 S 13th St Ponca City OK 74601",
    "addr:housenumber":"709",
    "addr:postcode":"74601",
    "addr:street":"S 13Th St",
    "iso:country":"US",
    "sg:address":"709 S 13th St",
    "sg:city":"Ponca City",
    "sg:classifiers":[
        {
            "category":"Personal",
            "subcategory":"Beauty Salon",
            "type":"Services"
        }
    ],
    "sg:phone":"+1 580 762 7336",
    "sg:postcode":"74601",
    "sg:province":"OK",
    "sg:tags":[
        "shop",
        "barber"
    ],
    "wof:name":"Ricks Beauty Shop",
    "wof:placetype":"venue"
},
  "geometry": {"coordinates":[-97.06842399999999,36.696948],"type":"Point"}
}