{
  "type": "Feature",
  "properties": {
    "addr:full":"205 W Kiowa Ave Marlow OK 73055",
    "addr:housenumber":"205",
    "addr:postcode":"73055",
    "addr:street":"W Kiowa Ave",
    "iso:country":"US",
    "sg:address":"205 W Kiowa Ave",
    "sg:city":"Marlow",
    "sg:classifiers":[
        {
            "category":"Personal",
            "subcategory":"Beauty Salon",
            "type":"Services"
        }
    ],
    "sg:phone":"+1 580 658 2962",
    "sg:postcode":"73055",
    "sg:province":"OK",
    "sg:tags":[
        "shop"
    ],
    "wof:name":"Tangles Hair & Nail Salon",
    "wof:placetype":"venue"
},
  "geometry": {"coordinates":[-97.95701099999999,34.648918],"type":"Point"}
}