{
  "type": "Feature",
  "properties": {
    "addr:full":"2024 NE 14th St Oklahoma City OK 73117",
    "addr:housenumber":"2024",
    "addr:postcode":"73117",
    "addr:street":"Ne 14Th St",
    "iso:country":"US",
    "sg:address":"2024 NE 14th St",
    "sg:city":"Oklahoma City",
    "sg:classifiers":[
        {
            "category":"Personal",
            "subcategory":"Beauty Salon",
            "type":"Services"
        }
    ],
    "sg:phone":"+1 405 427 3190",
    "sg:postcode":"73117",
    "sg:province":"OK",
    "wof:name":"Jimmie's Beauty Shop",
    "wof:placetype":"venue"
},
  "geometry": {"coordinates":[-97.47528200000001,35.483421],"type":"Point"}
}