{
  "type": "Feature",
  "properties": {
    "iso:country":"US",
    "sg:address":"4140 S 87th East Ave",
    "sg:city":"Tulsa",
    "sg:classifiers":[
        {
            "category":"Wholesale",
            "subcategory":"Machinery & Supplies",
            "type":"Manufacturing & Wholesale Goods"
        }
    ],
    "sg:phone":"+1 918 622 1477",
    "sg:postcode":"74145",
    "sg:province":"OK",
    "wof:name":"Scott Macon Eqpt Tulsa Inc",
    "wof:placetype":"venue"
},
  "geometry": {"coordinates":[-95.879904,36.102508],"type":"Point"}
}