{
  "type": "Feature",
  "properties": {
    "iso:country":"US",
    "sg:address":"6312 E Reno Ave",
    "sg:city":"Midwest City",
    "sg:classifiers":[
        {
            "category":"Banks & Credit Unions",
            "subcategory":"Bank",
            "type":"Services"
        }
    ],
    "sg:phone":"+1 405 732 4848",
    "sg:postcode":"73110",
    "sg:province":"OK",
    "wof:name":"Credit Union Svc Ctr",
    "wof:placetype":"venue"
},
  "geometry": {"coordinates":[-97.415016,35.46399],"type":"Point"}
}