{
  "type": "Feature",
  "properties": {
    "iso:country":"US",
    "sg:address":"1230 E Lindsey St",
    "sg:city":"Norman",
    "sg:classifiers":[
        {
            "category":"Food & Beverages",
            "subcategory":"Groceries & Convenience Stores",
            "type":"Retail Goods"
        }
    ],
    "sg:phone":"+1 405 360 4911",
    "sg:postcode":"73071",
    "sg:province":"OK",
    "wof:name":"Mr Shortstop",
    "wof:placetype":"venue"
},
  "geometry": {"coordinates":[-97.422195,35.203756],"type":"Point"}
}