{
  "type": "Feature",
  "properties": {
    "addr:full":"301 E Main St Marlow OK 73055",
    "addr:housenumber":"301",
    "addr:postcode":"73055",
    "addr:street":"E Main St",
    "iso:country":"US",
    "sg:address":"301 E Main St",
    "sg:city":"Marlow",
    "sg:classifiers":[
        {
            "category":"Banks & Credit Unions",
            "subcategory":"Financial Services",
            "type":"Services"
        }
    ],
    "sg:phone":"+1 580 658 5458",
    "sg:postcode":"73055",
    "sg:province":"OK",
    "sg:tags":[
        "company",
        "bank",
        "holding"
    ],
    "wof:name":"Leader First Bancorp Inc",
    "wof:placetype":"venue"
},
  "geometry": {"coordinates":[-97.951149,34.647624],"type":"Point"}
}