{
  "type": "Feature",
  "properties": {
    "iso:country":"US",
    "sg:address":"13301 Hawk Dr",
    "sg:city":"Oklahoma City",
    "sg:classifiers":[
        {
            "category":"Home & Garden",
            "subcategory":"Household Appliances",
            "type":"Retail Goods"
        }
    ],
    "sg:phone":"+1 405 732 6104",
    "sg:postcode":"73150",
    "sg:province":"OK",
    "wof:name":"S&D Car Wash Inc",
    "wof:placetype":"venue"
},
  "geometry": {"coordinates":[-97.29916900000001,35.399214],"type":"Point"}
}