{
  "type": "Feature",
  "properties": {
    "addr:full":"515 S Broadway Edmond OK 73034",
    "addr:housenumber":"515",
    "addr:postcode":"73034",
    "addr:street":"S Broadway",
    "iso:country":"US",
    "sg:address":"515 S Broadway",
    "sg:city":"Edmond",
    "sg:classifiers":[
        {
            "category":"Health Services",
            "subcategory":"Doctor",
            "type":"Services"
        }
    ],
    "sg:phone":"+1 405 340 5150",
    "sg:postcode":"73034",
    "sg:province":"OK",
    "sg:tags":[
        "clinic"
    ],
    "wof:name":"Gentle Dental",
    "wof:placetype":"venue"
},
  "geometry": {"coordinates":[-97.481988,35.649544],"type":"Point"}
}