{
  "type": "Feature",
  "properties": {
    "addr:full":"2986 W N Ave Ponca City OK 74601",
    "addr:housenumber":"2986",
    "addr:postcode":"74601",
    "addr:street":"W N Ave",
    "iso:country":"US",
    "sg:address":"2986 W N Ave",
    "sg:city":"Ponca City",
    "sg:classifiers":[
        {
            "category":"Wholesale",
            "subcategory":"Scrap",
            "type":"Manufacturing & Wholesale Goods"
        }
    ],
    "sg:phone":"+1 580 765 6554",
    "sg:postcode":"74601",
    "sg:province":"OK",
    "sg:tags":[
        "metal",
        "iron"
    ],
    "wof:name":"W W Recycling Inc",
    "wof:placetype":"venue"
},
  "geometry": {"coordinates":[-97.119022,36.680909],"type":"Point"}
}