{
  "type": "Feature",
  "properties": {
    "addr:full":"3113 N Downing Ct Bethany OK 73008",
    "addr:housenumber":"3113",
    "addr:postcode":"73008",
    "addr:street":"N Downing Ct",
    "iso:country":"US",
    "sg:address":"3113 N Downing Ct",
    "sg:city":"Bethany",
    "sg:classifiers":[
        {
            "category":"Autos & Motor Vehicles",
            "subcategory":"Recreational Vehicle Sales",
            "type":"Retail Goods"
        }
    ],
    "sg:phone":"+1 405 789 9168",
    "sg:postcode":"73008",
    "sg:province":"OK",
    "wof:name":"R V Shows Inc",
    "wof:placetype":"venue"
},
  "geometry": {"coordinates":[-97.662334,35.50098],"type":"Point"}
}