{
  "type": "Feature",
  "properties": {
    "iso:country":"US",
    "sg:address":"1820 SE 22nd St",
    "sg:city":"Oklahoma City",
    "sg:classifiers":[
        {
            "category":"Wholesale",
            "subcategory":"Machinery & Supplies",
            "type":"Manufacturing & Wholesale Goods"
        }
    ],
    "sg:phone":"+1 405 619 9311",
    "sg:postcode":"73129",
    "sg:province":"OK",
    "sg:tags":[
        "compressor",
        "gas"
    ],
    "wof:name":"Gas Compression Tech LLC",
    "wof:placetype":"venue"
},
  "geometry": {"coordinates":[-97.480371,35.442506],"type":"Point"}
}