{
  "type": "Feature",
  "properties": {
    "addr:full":"6606 S Yale Ave Tulsa OK 74136",
    "addr:housenumber":"6606",
    "addr:postcode":"74136",
    "addr:street":"S Yale Ave",
    "iso:country":"US",
    "sg:address":"6606 S Yale Ave",
    "sg:city":"Tulsa",
    "sg:classifiers":[
        {
            "category":"Health Services",
            "subcategory":"Doctor",
            "type":"Services"
        }
    ],
    "sg:phone":"+1 918 481 2796",
    "sg:postcode":"74136",
    "sg:province":"OK",
    "sg:tags":[
        "physician",
        "surgeon"
    ],
    "sg:website":"www.pediatriceyeassociates.com",
    "wof:name":"Kid's Point Of View",
    "wof:placetype":"venue"
},
  "geometry": {"coordinates":[-95.922203,36.066782],"type":"Point"}
}