{
  "type": "Feature",
  "properties": {
    "iso:country":"US",
    "sg:address":"5350 E 46th St",
    "sg:city":"Tulsa",
    "sg:classifiers":[
        {
            "category":"Education",
            "subcategory":"Special Training",
            "type":"Public Place"
        }
    ],
    "sg:phone":"+1 918 481 6200",
    "sg:postcode":"74135",
    "sg:province":"OK",
    "sg:tags":[
        "school"
    ],
    "wof:name":"Cooking With Ken",
    "wof:placetype":"venue"
},
  "geometry": {"coordinates":[-95.916072,36.097019],"type":"Point"}
}