{
  "type": "Feature",
  "properties": {
    "iso:country":"US",
    "sg:address":"918 E St",
    "sg:city":"Snyder",
    "sg:classifiers":[
        {
            "category":"Organizations",
            "subcategory":"Religious Organization",
            "type":"Services"
        }
    ],
    "sg:phone":"+1 580 569 2734",
    "sg:postcode":"73566",
    "sg:province":"OK",
    "wof:name":"Snyder Frst Untd Mthdst Church",
    "wof:placetype":"venue"
},
  "geometry": {"coordinates":[-98.951784,34.656567],"type":"Point"}
}