{
  "type": "Feature",
  "properties": {
    "iso:country":"US",
    "sg:address":"102 S Broadway",
    "sg:city":"Edmond",
    "sg:classifiers":[
        {
            "category":"Professional",
            "subcategory":"Lawyer & Legal Services",
            "type":"Services"
        }
    ],
    "sg:phone":"+1 405 341 4442",
    "sg:postcode":"73034",
    "sg:province":"OK",
    "sg:tags":[
        "attorney"
    ],
    "wof:name":"Richard & Combs",
    "wof:placetype":"venue"
},
  "geometry": {"coordinates":[-97.48139500000001,35.653548],"type":"Point"}
}