{
  "type": "Feature",
  "properties": {
    "iso:country":"US",
    "sg:address":"9409 N May Ave",
    "sg:city":"Oklahoma City",
    "sg:classifiers":[
        {
            "category":"Shopping",
            "subcategory":"Florist",
            "type":"Retail Goods"
        }
    ],
    "sg:phone":"+1 405 755 3980",
    "sg:postcode":"73120",
    "sg:province":"OK",
    "wof:name":"Caesar Florist",
    "wof:placetype":"venue"
},
  "geometry": {"coordinates":[-97.567254,35.567017],"type":"Point"}
}