{
  "type": "Feature",
  "properties": {
    "iso:country":"US",
    "sg:address":"130 N Main St",
    "sg:city":"Newkirk",
    "sg:classifiers":[
        {
            "category":"Retail",
            "subcategory":"Auto Repair",
            "type":"Services"
        }
    ],
    "sg:phone":"+1 580 362 2494",
    "sg:postcode":"74647",
    "sg:province":"OK",
    "sg:tags":[
        "body",
        "shop",
        "top",
        "paint"
    ],
    "wof:name":"Newkirk Body & Paint",
    "wof:placetype":"venue"
},
  "geometry": {"coordinates":[-97.053541,36.883328],"type":"Point"}
}