{
  "type": "Feature",
  "properties": {
    "iso:country":"US",
    "sg:address":"107 N Broadway St",
    "sg:city":"Cleveland",
    "sg:classifiers":[
        {
            "category":"Cinema",
            "subcategory":"Movie Rental",
            "type":"Entertainment"
        }
    ],
    "sg:phone":"+1 918 358 2396",
    "sg:postcode":"74020",
    "sg:province":"OK",
    "sg:tags":[
        "video",
        "tape"
    ],
    "wof:name":"Video Showcase",
    "wof:placetype":"venue"
},
  "geometry": {"coordinates":[-96.463968,36.309978],"type":"Point"}
}