{
  "type": "Feature",
  "properties": {
    "iso:country":"US",
    "sg:address":"1003 S 106th Ln",
    "sg:city":"Kaw City",
    "sg:phone":"+1 580 269 2245",
    "sg:postcode":"74641",
    "sg:province":"OK",
    "sg:tags":[
        "farm",
        "wheat"
    ],
    "wof:name":"Arlin Cales",
    "wof:placetype":"venue"
},
  "geometry": {"coordinates":[-96.888395,36.808465],"type":"Point"}
}