{
  "type": "Feature",
  "properties": {
    "iso:country":"US",
    "sg:address":"6444 NW Expy",
    "sg:city":"Oklahoma City",
    "sg:classifiers":[
        {
            "category":"Wholesale",
            "subcategory":"Sporting Goods",
            "type":"Manufacturing & Wholesale Goods"
        }
    ],
    "sg:phone":"+1 405 728 9140",
    "sg:postcode":"73132",
    "sg:province":"OK",
    "sg:tags":[
        "salon",
        "tanning",
        "supply"
    ],
    "wof:name":"Sun Consultants",
    "wof:placetype":"venue"
},
  "geometry": {"coordinates":[-97.62545900000001,35.55204],"type":"Point"}
}