{
  "type": "Feature",
  "properties": {
    "addr:full":"2205 N Broadway St Poteau OK 74953",
    "addr:housenumber":"2205",
    "addr:postcode":"74953",
    "addr:street":"N Broadway St",
    "iso:country":"US",
    "sg:address":"2205 N Broadway St",
    "sg:city":"Poteau",
    "sg:classifiers":[
        {
            "category":"Real Estate",
            "subcategory":"Real Estate Services",
            "type":"Services"
        },
        {
            "category":"Real Estate",
            "subcategory":"Real Estate Agent",
            "type":"Services"
        }
    ],
    "sg:phone":"+1 918 647 3131",
    "sg:postcode":"74953",
    "sg:province":"OK",
    "sg:tags":[
        "buyer",
        "management",
        "broker"
    ],
    "wof:name":"Kay Sullivan Real Estate",
    "wof:placetype":"venue"
},
  "geometry": {"coordinates":[-94.628952,35.072768],"type":"Point"}
}