{
  "type": "Feature",
  "properties": {
    "addr:full":"555 S Zunis Ave Tulsa OK 74104",
    "addr:housenumber":"555",
    "addr:postcode":"74104",
    "addr:street":"S Zunis Ave",
    "iso:country":"US",
    "sg:address":"555 S Zunis Ave",
    "sg:city":"Tulsa",
    "sg:classifiers":[
        {
            "category":"Shopping",
            "subcategory":"Hobbies, Toys, & Games",
            "type":"Retail Goods"
        }
    ],
    "sg:phone":"+1 918 588 3456",
    "sg:postcode":"74104",
    "sg:province":"OK",
    "sg:tags":[
        "model",
        "supply"
    ],
    "wof:name":"Tulsa Toy Trains",
    "wof:placetype":"venue"
},
  "geometry": {"coordinates":[-95.960967,36.154109],"type":"Point"}
}