{
  "type": "Feature",
  "properties": {
    "addr:full":"3102 N Classen Blvd Oklahoma City OK 73118",
    "addr:housenumber":"3102",
    "addr:postcode":"73118",
    "addr:street":"N Classen Blvd",
    "iso:country":"US",
    "sg:address":"3102 N Classen Blvd",
    "sg:city":"Oklahoma City",
    "sg:classifiers":[
        {
            "category":"Shopping",
            "subcategory":"Gifts & Souvenirs",
            "type":"Retail Goods"
        }
    ],
    "sg:phone":"+1 405 525 2493",
    "sg:postcode":"73118",
    "sg:province":"OK",
    "wof:name":"Once Upon A Silver Moon",
    "wof:placetype":"venue"
},
  "geometry": {"coordinates":[-97.53414600000001,35.501694],"type":"Point"}
}