{
  "type": "Feature",
  "properties": {
    "iso:country":"US",
    "sg:address":"1107 Main Ave",
    "sg:city":"Woodward",
    "sg:classifiers":[
        {
            "category":"Sports & Exercise",
            "subcategory":"Gym",
            "type":"Entertainment"
        }
    ],
    "sg:phone":"+1 580 256 6495",
    "sg:postcode":"73801",
    "sg:province":"OK",
    "sg:tags":[
        "fitness",
        "physical",
        "facility"
    ],
    "wof:name":"Sleek Images",
    "wof:placetype":"venue"
},
  "geometry": {"coordinates":[-99.39434799999999,36.435875],"type":"Point"}
}