{
  "type": "Feature",
  "properties": {
    "iso:country":"US",
    "sg:address":"2525 NW Expwy Svc Rd",
    "sg:city":"Oklahoma City",
    "sg:classifiers":[
        {
            "category":"Professional",
            "subcategory":"Accounting & Tax Preparation",
            "type":"Services"
        }
    ],
    "sg:phone":"+1 405 842 6477",
    "sg:postcode":"73112",
    "sg:province":"OK",
    "sg:tags":[
        "bookkeeping",
        "payroll"
    ],
    "wof:name":"Cooper Executive Services",
    "wof:placetype":"venue"
},
  "geometry": {"coordinates":[-97.558156,35.524536],"type":"Point"}
}