{
  "type": "Feature",
  "properties": {
    "addr:full":"2420 Knox Dr Oklahoma City OK 73115",
    "addr:housenumber":"2420",
    "addr:postcode":"73115",
    "addr:street":"Knox Dr",
    "iso:country":"US",
    "sg:address":"2420 Knox Dr",
    "sg:city":"Oklahoma City",
    "sg:classifiers":[
        {
            "category":"Banks & Credit Unions",
            "subcategory":"Bank",
            "type":"Services"
        }
    ],
    "sg:phone":"+1 405 601 0029",
    "sg:postcode":"73115",
    "sg:province":"OK",
    "sg:tags":[
        "loan"
    ],
    "wof:name":"Gateway Mortgage",
    "wof:placetype":"venue"
},
  "geometry": {"coordinates":[-97.454087,35.437284],"type":"Point"}
}