{
  "type": "Feature",
  "properties": {
    "addr:full":"2510 Elliot St Muskogee OK 74403",
    "addr:housenumber":"2510",
    "addr:postcode":"74403",
    "addr:street":"Elliot St",
    "iso:country":"US",
    "sg:address":"2510 Elliot St",
    "sg:city":"Muskogee",
    "sg:classifiers":[
        {
            "category":"Utilities",
            "subcategory":"Cable",
            "type":"Services"
        }
    ],
    "sg:phone":"+1 918 687 7511",
    "sg:postcode":"74403",
    "sg:province":"OK",
    "sg:tags":[
        "television"
    ],
    "wof:name":"Cox Communications",
    "wof:placetype":"venue"
},
  "geometry": {"coordinates":[-95.339477,35.742369],"type":"Point"}
}