{
  "type": "Feature",
  "properties": {
    "iso:country":"US",
    "sg:address":"6001 N Brookline Ave",
    "sg:city":"Oklahoma City",
    "sg:classifiers":[
        {
            "category":"Professional",
            "subcategory":"Testing Lab",
            "type":"Services"
        }
    ],
    "sg:phone":"+1 405 848 9950",
    "sg:postcode":"73112",
    "sg:province":"OK",
    "sg:tags":[
        "laboratory"
    ],
    "wof:name":"Vance Veterinary Laboratory",
    "wof:placetype":"venue"
},
  "geometry": {"coordinates":[-97.567728,35.534955],"type":"Point"}
}