{
  "type": "Feature",
  "properties": {
    "addr:full":"100 N Rockwell Ave Oklahoma City OK 73127",
    "addr:housenumber":"100",
    "addr:postcode":"73127",
    "addr:street":"N Rockwell Ave",
    "iso:country":"US",
    "sg:address":"100 N Rockwell Ave",
    "sg:city":"Oklahoma City",
    "sg:classifiers":[
        {
            "category":"Retail",
            "subcategory":"Repair Shop",
            "type":"Services"
        }
    ],
    "sg:phone":"+1 405 360 3334",
    "sg:postcode":"73127",
    "sg:province":"OK",
    "sg:tags":[
        "lock",
        "locksmith"
    ],
    "wof:name":"Pop-A-Lock",
    "wof:placetype":"venue"
},
  "geometry": {"coordinates":[-97.63653600000001,35.465914],"type":"Point"}
}