{
  "type": "Feature",
  "properties": {
    "iso:country":"US",
    "sg:address":"406 4th St",
    "sg:city":"Pawnee",
    "sg:classifiers":[
        {
            "category":"Real Estate",
            "subcategory":"Real Estate Agent",
            "type":"Services"
        }
    ],
    "sg:phone":"+1 918 762 3316",
    "sg:postcode":"74058",
    "sg:province":"OK",
    "sg:tags":[
        "authorities",
        "housing"
    ],
    "wof:name":"Pawnee Housing Authority",
    "wof:placetype":"venue"
},
  "geometry": {"coordinates":[-96.800431,36.340203],"type":"Point"}
}