{
  "type": "Feature",
  "properties": {
    "iso:country":"US",
    "sg:address":"1229 N Utah Ave",
    "sg:city":"Oklahoma City",
    "sg:classifiers":[
        {
            "category":"Health Services",
            "subcategory":"Chiropractor",
            "type":"Services"
        }
    ],
    "sg:phone":"+1 405 946 5605",
    "sg:postcode":"73107",
    "sg:province":"OK",
    "sg:tags":[
        "physician"
    ],
    "wof:name":"Cozart Chiropractic Clinic",
    "wof:placetype":"venue"
},
  "geometry": {"coordinates":[-97.594522,35.481927],"type":"Point"}
}