{
  "type": "Feature",
  "properties": {
    "iso:country":"US",
    "sg:address":"11201 NE 23rd St",
    "sg:city":"Choctaw",
    "sg:classifiers":[
        {
            "category":"Restaurant",
            "type":"Food & Drink"
        }
    ],
    "sg:phone":"+1 405 769 7676",
    "sg:postcode":"73020",
    "sg:province":"OK",
    "wof:name":"All American Diner",
    "wof:placetype":"venue"
},
  "geometry": {"coordinates":[-97.335318,35.493106],"type":"Point"}
}