{
  "type": "Feature",
  "properties": {
    "iso:country":"US",
    "sg:address":"2501 Exchange Ave",
    "sg:city":"Oklahoma City",
    "sg:classifiers":[
        {
            "category":"Wholesale",
            "subcategory":"Farm Supplies",
            "type":"Manufacturing & Wholesale Goods"
        }
    ],
    "sg:phone":"+1 405 236 1619",
    "sg:postcode":"73108",
    "sg:province":"OK",
    "sg:tags":[
        "commission",
        "livestock"
    ],
    "wof:name":"Farmers Commission Co",
    "wof:placetype":"venue"
},
  "geometry": {"coordinates":[-97.561841,35.452845],"type":"Point"}
}