{
  "type": "Feature",
  "properties": {
    "iso:country":"US",
    "sg:address":"1802 SW Sheridan Rd",
    "sg:city":"Lawton",
    "sg:classifiers":[
        {
            "category":"Building & Trades",
            "subcategory":"Landscaping Services",
            "type":"Services"
        }
    ],
    "sg:phone":"+1 580 357 3366",
    "sg:postcode":"73505",
    "sg:province":"OK",
    "sg:tags":[
        "lawn",
        "including",
        "fertilizing",
        "care"
    ],
    "wof:name":"Sterling Services Inc",
    "wof:placetype":"venue"
},
  "geometry": {"coordinates":[-98.422105,34.58893],"type":"Point"}
}