{
  "type": "Feature",
  "properties": {
    "iso:country":"US",
    "sg:address":"2313 W 6th Ave",
    "sg:city":"Stillwater",
    "sg:classifiers":[
        {
            "category":"Wholesale",
            "subcategory":"Computers",
            "type":"Manufacturing & Wholesale Goods"
        }
    ],
    "sg:phone":"+1 405 743 1995",
    "sg:postcode":"74074",
    "sg:province":"OK",
    "sg:tags":[
        "new",
        "value",
        "reseller"
    ],
    "wof:name":"Discount Computers",
    "wof:placetype":"venue"
},
  "geometry": {"coordinates":[-97.08928400000001,36.115746],"type":"Point"}
}