{
  "type": "Feature",
  "properties": {
    "iso:country":"US",
    "sg:address":"237 NW 61st St",
    "sg:city":"Oklahoma City",
    "sg:classifiers":[
        {
            "category":"Professional",
            "subcategory":"Advertising",
            "type":"Services"
        }
    ],
    "sg:phone":"+1 405 843 3185",
    "sg:postcode":"73118",
    "sg:province":"OK",
    "sg:tags":[
        "mailing",
        "shipping"
    ],
    "sg:website":"www.accesscomtech.com",
    "wof:name":"Comtech Marketing & Mailing",
    "wof:placetype":"venue"
},
  "geometry": {"coordinates":[-97.51747899999999,35.535095],"type":"Point"}
}