{
  "type": "Feature",
  "properties": {
    "iso:country":"US",
    "sg:address":"404 State Hwy 99",
    "sg:city":"Cushing",
    "sg:classifiers":[
        {
            "category":"Building & Trades",
            "subcategory":"Construction",
            "type":"Services"
        }
    ],
    "sg:phone":"+1 918 225 7793",
    "sg:postcode":"74023",
    "sg:province":"OK",
    "sg:tags":[
        "house"
    ],
    "wof:name":"J & L Builders",
    "wof:placetype":"venue"
},
  "geometry": {"coordinates":[-96.65213,35.984543],"type":"Point"}
}