{
  "type": "Feature",
  "properties": {
    "addr:full":"3303 S Harvard Ave Ste E Tulsa OK 74135",
    "addr:housenumber":"3303",
    "addr:postcode":"74135",
    "addr:street":"S Harvard Ave Ste E",
    "iso:country":"US",
    "sg:address":"3303 S Harvard Ave Ste E",
    "sg:city":"Tulsa",
    "sg:classifiers":[
        {
            "category":"Home & Garden",
            "subcategory":"Home Furnishings",
            "type":"Retail Goods"
        },
        {
            "category":"Shopping",
            "type":"Retail Goods"
        },
        {
            "category":"Home & Garden",
            "subcategory":"Furniture",
            "type":"Retail Goods"
        }
    ],
    "sg:phone":"+1 918 742 3032",
    "sg:postcode":"74135",
    "sg:province":"OK",
    "sg:tags":[
        "house",
        "merchandise",
        "store"
    ],
    "wof:name":"Jetta Corp",
    "wof:placetype":"venue"
},
  "geometry": {"coordinates":[-95.940262,36.115151],"type":"Point"}
}