{
  "type": "Feature",
  "properties": {
    "addr:full":"1219 W Will Rogers Blvd Claremore OK 74017",
    "addr:housenumber":"1219",
    "addr:postcode":"74017",
    "addr:street":"W Will Rogers Blvd",
    "iso:country":"US",
    "sg:address":"1219 W Will Rogers Blvd",
    "sg:city":"Claremore",
    "sg:classifiers":[
        {
            "category":"Insurance",
            "subcategory":"Hazard Insurance",
            "type":"Services"
        }
    ],
    "sg:phone":"+1 918 341 5644",
    "sg:postcode":"74017",
    "sg:province":"OK",
    "sg:tags":[
        "commercial",
        "business"
    ],
    "wof:name":"John Wiley Agency",
    "wof:placetype":"venue"
},
  "geometry": {"coordinates":[-95.623672,36.318272],"type":"Point"}
}