{
  "type": "Feature",
  "properties": {
    "iso:country":"US",
    "sg:address":"100 N Broadway Ave",
    "sg:city":"Oklahoma City",
    "sg:classifiers":[
        {
            "category":"Mining & Drilling",
            "type":"Manufacturing & Wholesale Goods"
        }
    ],
    "sg:phone":"+1 405 235 6664",
    "sg:postcode":"73102",
    "sg:province":"OK",
    "sg:tags":[
        "exploration"
    ],
    "wof:name":"Exploration Associates II LLC",
    "wof:placetype":"venue"
},
  "geometry": {"coordinates":[-97.514433,35.468762],"type":"Point"}
}