{
  "type": "Feature",
  "properties": {
    "iso:country":"US",
    "sg:address":"4409 S 43rd West Ave",
    "sg:city":"Tulsa",
    "sg:classifiers":[
        {
            "category":"Personal",
            "type":"Services"
        }
    ],
    "sg:phone":"+1 918 446 9641",
    "sg:postcode":"74107",
    "sg:province":"OK",
    "wof:name":"Ratliff Enterprises",
    "wof:placetype":"venue"
},
  "geometry": {"coordinates":[-96.040619,36.100021],"type":"Point"}
}