{
  "type": "Feature",
  "properties": {
    "iso:country":"US",
    "sg:address":"2316 E Renee Rd",
    "sg:city":"Claremore",
    "sg:classifiers":[
        {
            "category":"Professional",
            "subcategory":"Business Services",
            "type":"Services"
        }
    ],
    "sg:phone":"+1 918 343 9307",
    "sg:postcode":"74017",
    "sg:province":"OK",
    "wof:name":"Mitchell Sales Co",
    "wof:placetype":"venue"
},
  "geometry": {"coordinates":[-95.44834,36.30921],"type":"Point"}
}