{
  "type": "Feature",
  "properties": {
    "iso:country":"US",
    "sg:address":"204 E Broadway St",
    "sg:city":"Cushing",
    "sg:classifiers":[
        {
            "category":"Shopping",
            "subcategory":"Jewelry",
            "type":"Retail Goods"
        }
    ],
    "sg:phone":"+1 918 225 2869",
    "sg:postcode":"74023",
    "sg:province":"OK",
    "sg:tags":[
        "jeweler"
    ],
    "wof:name":"Mac's Jewelry & Goldsmith",
    "wof:placetype":"venue"
},
  "geometry": {"coordinates":[-96.771387,35.980048],"type":"Point"}
}