{
  "type": "Feature",
  "properties": {
    "addr:full":"2134 S 109th East Ave Tulsa OK 74129",
    "addr:housenumber":"2134",
    "addr:postcode":"74129",
    "addr:street":"S 109Th;Ave",
    "iso:country":"US",
    "sg:address":"2134 S 109th East Ave",
    "sg:city":"Tulsa",
    "sg:classifiers":[
        {
            "category":"Social Services",
            "subcategory":"Child Care",
            "type":"Services"
        }
    ],
    "sg:phone":"+1 918 622 4041",
    "sg:postcode":"74129",
    "sg:province":"OK",
    "sg:tags":[
        "day"
    ],
    "wof:name":"Shamrock Child Dev Center Inc",
    "wof:placetype":"venue"
},
  "geometry": {"coordinates":[-95.855091,36.13238],"type":"Point"}
}