{
  "type": "Feature",
  "properties": {
    "iso:country":"US",
    "sg:address":"27761 E 61st St",
    "sg:city":"Broken Arrow",
    "sg:classifiers":[
        {
            "category":"Health Services",
            "subcategory":"Health Practitioner",
            "type":"Services"
        }
    ],
    "sg:phone":"+1 918 357 1501",
    "sg:postcode":"74014",
    "sg:province":"OK",
    "sg:tags":[
        "nutritionist"
    ],
    "wof:name":"Nutrition Management",
    "wof:placetype":"venue"
},
  "geometry": {"coordinates":[-95.671459,36.075384],"type":"Point"}
}