{
  "type": "Feature",
  "properties": {
    "iso:country":"US",
    "sg:address":"8236 W I- 40 Svc Rd",
    "sg:city":"Oklahoma City",
    "sg:classifiers":[
        {
            "category":"Home & Garden",
            "subcategory":"Building Materials",
            "type":"Retail Goods"
        }
    ],
    "sg:phone":"+1 405 440 1968",
    "sg:postcode":"73128",
    "sg:province":"OK",
    "sg:tags":[
        "glass",
        "window",
        "plate"
    ],
    "wof:name":"Glass Express Inc",
    "wof:placetype":"venue"
},
  "geometry": {"coordinates":[-97.667542,35.46036],"type":"Point"}
}