{
  "type": "Feature",
  "properties": {
    "iso:country":"US",
    "sg:address":"1140 NW 63rd St",
    "sg:city":"Oklahoma City",
    "sg:classifiers":[
        {
            "category":"Health Services",
            "subcategory":"Doctor",
            "type":"Services"
        }
    ],
    "sg:phone":"+1 405 843 0610",
    "sg:postcode":"73116",
    "sg:province":"OK",
    "sg:tags":[
        "physician",
        "medical",
        "surgeon"
    ],
    "wof:name":"Andrew C John MD Inc",
    "wof:placetype":"venue"
},
  "geometry": {"coordinates":[-97.532231,35.536786],"type":"Point"}
}