{
  "type": "Feature",
  "properties": {
    "iso:country":"US",
    "sg:address":"6111 New Sapulpa Rd",
    "sg:city":"Tulsa",
    "sg:classifiers":[
        {
            "category":"Manufacturing",
            "subcategory":"Tools & Machinery",
            "type":"Manufacturing & Wholesale Goods"
        }
    ],
    "sg:phone":"+1 918 582 6121",
    "sg:postcode":"74131",
    "sg:province":"OK",
    "sg:tags":[
        "fire",
        "equipment",
        "protection"
    ],
    "sg:website":"www.simplexgrinnell.com",
    "wof:name":"Simplex Grinnell",
    "wof:placetype":"venue"
},
  "geometry": {"coordinates":[-96.052892,36.075303],"type":"Point"}
}