{
  "type": "Feature",
  "properties": {
    "iso:country":"US",
    "sg:address":"405 S Sunset Ln",
    "sg:city":"Guymon",
    "sg:classifiers":[
        {
            "category":"Autos & Motor Vehicles",
            "subcategory":"Automobile Sales",
            "type":"Retail Goods"
        }
    ],
    "sg:phone":"+1 580 338 3877",
    "sg:postcode":"73942",
    "sg:province":"OK",
    "sg:tags":[
        "used"
    ],
    "wof:name":"Big Boys Used Cars Inc",
    "wof:placetype":"venue"
},
  "geometry": {"coordinates":[-101.492115,36.67549],"type":"Point"}
}