{
  "type": "Feature",
  "properties": {
    "iso:country":"US",
    "sg:address":"309 S Wewoka Ave",
    "sg:city":"Wewoka",
    "sg:classifiers":[
        {
            "category":"Shopping",
            "subcategory":"Pharmacy",
            "type":"Retail Goods"
        }
    ],
    "sg:phone":"+1 405 257 3388",
    "sg:postcode":"74884",
    "sg:province":"OK",
    "wof:name":"Roberts Drug Store",
    "wof:placetype":"venue"
},
  "geometry": {"coordinates":[-96.491508,35.156564],"type":"Point"}
}