{
  "type": "Feature",
  "properties": {
    "addr:full":"2301 W Country Club Rd Chickasha OK 73018",
    "addr:housenumber":"2301",
    "addr:postcode":"73018",
    "addr:street":"W Country Club Rd",
    "iso:country":"US",
    "sg:address":"2301 W Country Club Rd",
    "sg:city":"Chickasha",
    "sg:classifiers":[
        {
            "category":"Farming",
            "subcategory":"Farm & Veterinary Services",
            "type":"Manufacturing & Wholesale Goods"
        }
    ],
    "sg:phone":"+1 405 224 0102",
    "sg:postcode":"73018",
    "sg:province":"OK",
    "sg:tags":[
        "mfg",
        "marketing",
        "crop",
        "truck",
        "operator",
        "prep"
    ],
    "wof:name":"Hart Feeds Inc",
    "wof:placetype":"venue"
},
  "geometry": {"coordinates":[-97.963252,35.014959],"type":"Point"}
}