{
  "type": "Feature",
  "properties": {
    "iso:country":"US",
    "sg:address":"573 S Peoria Ave",
    "sg:city":"Tulsa",
    "sg:classifiers":[
        {
            "category":"Retail",
            "subcategory":"Auto Repair",
            "type":"Services"
        }
    ],
    "sg:phone":"+1 918 587 2829",
    "sg:postcode":"74120",
    "sg:province":"OK",
    "sg:tags":[
        "repairing",
        "automobile"
    ],
    "wof:name":"Bud's Import Automotive",
    "wof:placetype":"venue"
},
  "geometry": {"coordinates":[-95.975536,36.153567],"type":"Point"}
}