{
  "type": "Feature",
  "properties": {
    "addr:full":"573 S Peoria Ave Tulsa OK 74120",
    "addr:housenumber":"573",
    "addr:postcode":"74120",
    "addr:street":"S Peoria Ave",
    "iso:country":"US",
    "sg:address":"573 S Peoria Ave",
    "sg:city":"Tulsa",
    "sg:classifiers":[
        {
            "category":"Retail",
            "subcategory":"Auto Repair",
            "type":"Services"
        }
    ],
    "sg:phone":"+1 918 587 2829",
    "sg:postcode":"74120",
    "sg:province":"OK",
    "sg:tags":[
        "repairing",
        "automobile"
    ],
    "wof:name":"Bud's Import Automotive",
    "wof:placetype":"venue"
},
  "geometry": {"coordinates":[-95.97553600000001,36.153567],"type":"Point"}
}