{
  "type": "Feature",
  "properties": {
    "iso:country":"US",
    "sg:address":"4111 S 70th East Ave",
    "sg:city":"Tulsa",
    "sg:classifiers":[
        {
            "category":"Shopping",
            "subcategory":"Party Supplies",
            "type":"Retail Goods"
        },
        {
            "category":"Personal",
            "type":"Services"
        }
    ],
    "sg:phone":"+1 918 622 8102",
    "sg:postcode":"74145",
    "sg:province":"OK",
    "sg:tags":[
        "favors",
        "decoration",
        "planning",
        "wedding",
        "rental",
        "event"
    ],
    "wof:name":"Party Pro Rents",
    "wof:placetype":"venue"
},
  "geometry": {"coordinates":[-95.89911499999999,36.104184],"type":"Point"}
}