{
  "type": "Feature",
  "properties": {
    "iso:country":"US",
    "sg:address":"1309 Lindsey Dr",
    "sg:city":"Norman",
    "sg:classifiers":[
        {
            "category":"Restaurant",
            "type":"Food & Drink"
        }
    ],
    "sg:phone":"+1 405 579 3400",
    "sg:postcode":"73072",
    "sg:province":"OK",
    "sg:tags":[
        "eating"
    ],
    "wof:name":"Buzzs Subs",
    "wof:placetype":"venue"
},
  "geometry": {"coordinates":[-97.476175,35.202118],"type":"Point"}
}