{
  "type": "Feature",
  "properties": {
    "iso:country":"US",
    "sg:address":"1514 Sunrise Cir",
    "sg:city":"Norman",
    "sg:classifiers":[
        {
            "category":"Professional",
            "type":"Services"
        }
    ],
    "sg:phone":"+1 405 579 3535",
    "sg:postcode":"73071",
    "sg:province":"OK",
    "wof:name":"C&R Ticket Service LLC",
    "wof:placetype":"venue"
},
  "geometry": {"coordinates":[-97.418772,35.212229],"type":"Point"}
}