{
  "type": "Feature",
  "properties": {
    "iso:country":"US",
    "sg:address":"2716 N Kenosha Ave",
    "sg:city":"Tulsa",
    "sg:classifiers":[
        {
            "category":"Retail",
            "subcategory":"Car Wash",
            "type":"Services"
        }
    ],
    "sg:phone":"+1 918 428 7550",
    "sg:postcode":"74106",
    "sg:province":"OK",
    "sg:tags":[
        "carwash"
    ],
    "wof:name":"Zip Wash Detail Service",
    "wof:placetype":"venue"
},
  "geometry": {"coordinates":[-95.982303,36.194896],"type":"Point"}
}