{
  "type": "Feature",
  "properties": {
    "iso:country":"US",
    "sg:address":"28 W 8th St",
    "sg:city":"Edmond",
    "sg:classifiers":[
        {
            "category":"Retail",
            "subcategory":"Auto Repair",
            "type":"Services"
        }
    ],
    "sg:phone":"+1 405 341 1816",
    "sg:postcode":"73003",
    "sg:province":"OK",
    "sg:tags":[
        "automotive",
        "general"
    ],
    "wof:name":"Edmond Auto Electric",
    "wof:placetype":"venue"
},
  "geometry": {"coordinates":[-97.482893,35.646918],"type":"Point"}
}