{
  "type": "Feature",
  "properties": {
    "addr:full":"520 SW 102nd St Oklahoma City OK 73139",
    "addr:housenumber":"520",
    "addr:postcode":"73139",
    "addr:street":"Sw 102Nd St",
    "iso:country":"US",
    "sg:address":"520 SW 102nd St",
    "sg:city":"Oklahoma City",
    "sg:classifiers":[
        {
            "category":"Building & Trades",
            "subcategory":"Construction",
            "type":"Services"
        }
    ],
    "sg:phone":"+1 405 692 1892",
    "sg:postcode":"73139",
    "sg:province":"OK",
    "sg:tags":[
        "carpentry",
        "contractor"
    ],
    "wof:name":"Bacon Framing Contractor",
    "wof:placetype":"venue"
},
  "geometry": {"coordinates":[-97.523538,35.366427],"type":"Point"}
}