{
  "type": "Feature",
  "properties": {
    "iso:country":"US",
    "sg:address":"621 Harrison St",
    "sg:city":"Pawnee",
    "sg:classifiers":[
        {
            "category":"Personal",
            "type":"Services"
        }
    ],
    "sg:phone":"+1 918 762 3784",
    "sg:postcode":"74058",
    "sg:province":"OK",
    "sg:tags":[
        "department",
        "motor",
        "vehicle"
    ],
    "wof:name":"Pawnee Tag Agency",
    "wof:placetype":"venue"
},
  "geometry": {"coordinates":[-96.804333,36.337814],"type":"Point"}
}