{
  "type": "Feature",
  "properties": {
    "iso:country":"US",
    "sg:address":"714 W 3rd St",
    "sg:city":"Watonga",
    "sg:classifiers":[
        {
            "category":"Real Estate",
            "subcategory":"Real Estate Agent",
            "type":"Services"
        }
    ],
    "sg:phone":"+1 580 623 8669",
    "sg:postcode":"73772",
    "sg:province":"OK",
    "sg:tags":[
        "appraiser"
    ],
    "wof:name":"Tony KOHL Appraisal LLC",
    "wof:placetype":"venue"
},
  "geometry": {"coordinates":[-98.420817,35.847652],"type":"Point"}
}