{
  "type": "Feature",
  "properties": {
    "addr:full":"8827 S Pennsylvania Ave Oklahoma City OK 73159",
    "addr:housenumber":"8827",
    "addr:postcode":"73159",
    "addr:street":"S Pennsylvania Ave",
    "iso:country":"US",
    "sg:address":"8827 S Pennsylvania Ave",
    "sg:city":"Oklahoma City",
    "sg:classifiers":[
        {
            "category":"Social Services",
            "type":"Services"
        }
    ],
    "sg:phone":"+1 405 688 5388",
    "sg:postcode":"73159",
    "sg:province":"OK",
    "sg:tags":[
        "care",
        "center",
        "day"
    ],
    "wof:name":"Daily Living Ctr Inc",
    "wof:placetype":"venue"
},
  "geometry": {"coordinates":[-97.547999,35.377407],"type":"Point"}
}