{
  "type": "Feature",
  "properties": {
    "addr:full":"13877 E Anderson Dr Claremore OK 74017",
    "addr:housenumber":"13877",
    "addr:postcode":"74017",
    "addr:street":"E Anderson Dr",
    "iso:country":"US",
    "sg:address":"13877 E Anderson Dr",
    "sg:city":"Claremore",
    "sg:classifiers":[
        {
            "category":"Real Estate",
            "subcategory":"Real Estate Operator",
            "type":"Services"
        }
    ],
    "sg:phone":"+1 918 341 2224",
    "sg:postcode":"74017",
    "sg:province":"OK",
    "sg:tags":[
        "building",
        "nonresidential"
    ],
    "wof:name":"Dyer Properties",
    "wof:placetype":"venue"
},
  "geometry": {"coordinates":[-95.57988899999999,36.309],"type":"Point"}
}