{
  "type": "Feature",
  "properties": {
    "iso:country":"US",
    "sg:address":"203 E Wade St",
    "sg:city":"El Reno",
    "sg:classifiers":[
        {
            "category":"Professional",
            "subcategory":"Accounting & Tax Preparation",
            "type":"Services"
        }
    ],
    "sg:phone":"+1 405 262 9091",
    "sg:postcode":"73036",
    "sg:province":"OK",
    "sg:tags":[
        "accountant"
    ],
    "wof:name":"Mc Gee Chronister & Clouse",
    "wof:placetype":"venue"
},
  "geometry": {"coordinates":[-97.952663,35.531454],"type":"Point"}
}