{
  "type": "Feature",
  "properties": {
    "iso:country":"US",
    "sg:address":"1117 NW Cache Rd",
    "sg:city":"Lawton",
    "sg:classifiers":[
        {
            "category":"Shopping",
            "subcategory":"Clothing, Apparel, & Fashions",
            "type":"Retail Goods"
        }
    ],
    "sg:phone":"+1 580 581 7202",
    "sg:postcode":"73507",
    "sg:province":"OK",
    "wof:name":"High Fashion Suits",
    "wof:placetype":"venue"
},
  "geometry": {"coordinates":[-98.404949,34.623446],"type":"Point"}
}