{
  "type": "Feature",
  "properties": {
    "addr:full":"12025 S Western Ave Oklahoma City OK 73170",
    "addr:housenumber":"12025",
    "addr:postcode":"73170",
    "addr:street":"S Western Ave",
    "iso:country":"US",
    "sg:address":"12025 S Western Ave",
    "sg:city":"Oklahoma City",
    "sg:classifiers":[
        {
            "category":"Retail",
            "subcategory":"Auto Repair",
            "type":"Services"
        }
    ],
    "sg:phone":"+1 405 692 1460",
    "sg:postcode":"73170",
    "sg:province":"OK",
    "sg:tags":[
        "tire",
        "supply"
    ],
    "wof:name":"Big O Tires",
    "wof:placetype":"venue"
},
  "geometry": {"coordinates":[-97.53,35.341371],"type":"Point"}
}