{
  "type": "Feature",
  "properties": {
    "iso:country":"US",
    "sg:address":"8536 S 89th West Ave",
    "sg:city":"Tulsa",
    "sg:classifiers":[
        {
            "category":"Wholesale",
            "subcategory":"Metals & Minerals",
            "type":"Manufacturing & Wholesale Goods"
        }
    ],
    "sg:phone":"+1 918 227 2830",
    "sg:postcode":"74131",
    "sg:province":"OK",
    "sg:tags":[
        "steel",
        "warehouse"
    ],
    "wof:name":"Lokey Iron & Alloy",
    "wof:placetype":"venue"
},
  "geometry": {"coordinates":[-96.091144,36.040479],"type":"Point"}
}