{
  "type": "Feature",
  "properties": {
    "iso:country":"US",
    "sg:address":"4511 US Hwy 81",
    "sg:city":"Enid",
    "sg:classifiers":[
        {
            "category":"Farming",
            "subcategory":"Farm & Veterinary Services",
            "type":"Manufacturing & Wholesale Goods"
        }
    ],
    "sg:phone":"+1 580 237 0294",
    "sg:postcode":"73701",
    "sg:province":"OK",
    "sg:tags":[
        "crop"
    ],
    "wof:name":"Madison Spraying & Right Way",
    "wof:placetype":"venue"
},
  "geometry": {"coordinates":[-97.87864399999999,36.439116],"type":"Point"}
}