{
  "type": "Feature",
  "properties": {
    "iso:country":"US",
    "sg:address":"3501 N Santa Fe Ave",
    "sg:city":"Oklahoma City",
    "sg:classifiers":[
        {
            "category":"Wholesale",
            "subcategory":"Auto Parts",
            "type":"Manufacturing & Wholesale Goods"
        }
    ],
    "sg:phone":"+1 405 525 4400",
    "sg:postcode":"73118",
    "sg:province":"OK",
    "sg:tags":[
        "automobile",
        "supply"
    ],
    "sg:website":"www.bobhoward.com",
    "wof:name":"Bob Howard WHOL Parts Dstrbtn",
    "wof:placetype":"venue"
},
  "geometry": {"coordinates":[-97.512143,35.507806],"type":"Point"}
}