{
  "type": "Feature",
  "properties": {
    "iso:country":"US",
    "sg:address":"300 S Broadway St",
    "sg:city":"Cleveland",
    "sg:classifiers":[
        {
            "category":"Cinema",
            "subcategory":"Movie Theater",
            "type":"Entertainment"
        }
    ],
    "sg:phone":"+1 918 358 2282",
    "sg:postcode":"74020",
    "sg:province":"OK",
    "wof:name":"Broadway Twin Theatre",
    "wof:placetype":"venue"
},
  "geometry": {"coordinates":[-96.463908,36.306582],"type":"Point"}
}