{
  "type": "Feature",
  "properties": {
    "iso:country":"US",
    "sg:address":"3637 NW 51st St",
    "sg:city":"Oklahoma City",
    "sg:classifiers":[
        {
            "category":"Personal",
            "subcategory":"Beauty Salon",
            "type":"Services"
        }
    ],
    "sg:phone":"+1 405 947 8084",
    "sg:postcode":"73112",
    "sg:province":"OK",
    "sg:tags":[
        "shop"
    ],
    "wof:name":"Heads Beauty Salon",
    "wof:placetype":"venue"
},
  "geometry": {"coordinates":[-97.580791,35.523298],"type":"Point"}
}