{
  "type": "Feature",
  "properties": {
    "iso:country":"US",
    "sg:address":"208 W Main St",
    "sg:city":"Duncan",
    "sg:classifiers":[
        {
            "category":"Shopping",
            "subcategory":"Discount & Variety Stores",
            "type":"Retail Goods"
        }
    ],
    "sg:phone":"+1 580 251 5283",
    "sg:postcode":"73533",
    "sg:province":"OK",
    "sg:tags":[
        "merchandise",
        "general"
    ],
    "wof:name":"Anything Goes",
    "wof:placetype":"venue"
},
  "geometry": {"coordinates":[-97.949198,34.501025],"type":"Point"}
}