{
  "type": "Feature",
  "properties": {
    "iso:country":"US",
    "sg:address":"316 Eastgate Blvd",
    "sg:city":"Miami",
    "sg:classifiers":[
        {
            "category":"Social Services",
            "type":"Services"
        }
    ],
    "sg:phone":"+1 918 542 5683",
    "sg:postcode":"74354",
    "sg:province":"OK",
    "sg:tags":[
        "mission"
    ],
    "wof:name":"Harbor",
    "wof:placetype":"venue"
},
  "geometry": {"coordinates":[-94.838087,36.870529],"type":"Point"}
}