{
  "type": "Feature",
  "properties": {
    "iso:country":"US",
    "sg:address":"206 N Armstrong St",
    "sg:city":"Bixby",
    "sg:classifiers":[
        {
            "category":"Manufacturing",
            "subcategory":"Signs",
            "type":"Manufacturing & Wholesale Goods"
        }
    ],
    "sg:phone":"+1 918 366 4453",
    "sg:postcode":"74008",
    "sg:province":"OK",
    "sg:website":"www.epessoftware.com",
    "wof:name":"Cap Co",
    "wof:placetype":"venue"
},
  "geometry": {"coordinates":[-95.883237,35.943771],"type":"Point"}
}