{
  "type": "Feature",
  "properties": {
    "addr:full":"206 N Armstrong St Bixby OK 74008",
    "addr:housenumber":"206",
    "addr:postcode":"74008",
    "addr:street":"N Armstrong St",
    "iso:country":"US",
    "sg:address":"206 N Armstrong St",
    "sg:city":"Bixby",
    "sg:classifiers":[
        {
            "category":"Manufacturing",
            "subcategory":"Signs",
            "type":"Manufacturing & Wholesale Goods"
        }
    ],
    "sg:phone":"+1 918 366 4453",
    "sg:postcode":"74008",
    "sg:province":"OK",
    "sg:website":"www.epessoftware.com",
    "wof:name":"Cap Co",
    "wof:placetype":"venue"
},
  "geometry": {"coordinates":[-95.88323699999999,35.943771],"type":"Point"}
}