{
  "type": "Feature",
  "properties": {
    "iso:country":"US",
    "sg:address":"3702 E 51st St",
    "sg:city":"Tulsa",
    "sg:classifiers":[
        {
            "category":"Health Services",
            "subcategory":"Health Practitioner",
            "type":"Services"
        }
    ],
    "sg:phone":"+1 918 748 1715",
    "sg:postcode":"74135",
    "sg:province":"OK",
    "wof:name":"Catie McGoldrick",
    "wof:placetype":"venue"
},
  "geometry": {"coordinates":[-95.938057,36.089717],"type":"Point"}
}