{
  "type": "Feature",
  "properties": {
    "iso:country":"US",
    "sg:address":"6450 S Lewis Ave",
    "sg:city":"Tulsa",
    "sg:classifiers":[
        {
            "category":"Wholesale",
            "subcategory":"Machinery & Supplies",
            "type":"Manufacturing & Wholesale Goods"
        }
    ],
    "sg:phone":"+1 918 712 4340",
    "sg:postcode":"74136",
    "sg:province":"OK",
    "sg:tags":[
        "equipment",
        "industrial"
    ],
    "sg:website":"www.mscdirect.com",
    "wof:name":"MSC Industrial Supply Co",
    "wof:placetype":"venue"
},
  "geometry": {"coordinates":[-95.958034,36.072986],"type":"Point"}
}