{
  "type": "Feature",
  "properties": {
    "iso:country":"US",
    "sg:address":"2808 E 15th St",
    "sg:city":"Tulsa",
    "sg:classifiers":[
        {
            "category":"Home & Garden",
            "subcategory":"Home Furnishings",
            "type":"Retail Goods"
        },
        {
            "category":"Shopping",
            "subcategory":"Antiques",
            "type":"Retail Goods"
        },
        {
            "category":"Home & Garden",
            "subcategory":"Furniture",
            "type":"Retail Goods"
        }
    ],
    "sg:phone":"+1 918 510 0700",
    "sg:postcode":"74129",
    "sg:province":"OK",
    "sg:tags":[
        "decor",
        "store"
    ],
    "wof:name":"L'hirtoire",
    "wof:placetype":"venue"
},
  "geometry": {"coordinates":[-95.841421,36.123216],"type":"Point"}
}