{
  "type": "Feature",
  "properties": {
    "iso:country":"US",
    "sg:address":"23379 E 878 Rd",
    "sg:city":"Park Hill",
    "sg:classifiers":[
        {
            "category":"Personal",
            "subcategory":"Beauty Salon",
            "type":"Services"
        }
    ],
    "sg:phone":"+1 918 457 4401",
    "sg:postcode":"74451",
    "sg:province":"OK",
    "sg:tags":[
        "shop"
    ],
    "wof:name":"Kathy S Hair Salon",
    "wof:placetype":"venue"
},
  "geometry": {"coordinates":[-94.891169,35.749768],"type":"Point"}
}