{
  "type": "Feature",
  "properties": {
    "addr:full":"4802 S Muskogee Ave Tahlequah OK 74464",
    "addr:housenumber":"4802",
    "addr:postcode":"74464",
    "addr:street":"S Muskogee Ave",
    "iso:country":"US",
    "sg:address":"4802 S Muskogee Ave",
    "sg:city":"Tahlequah",
    "sg:classifiers":[
        {
            "category":"Shopping",
            "type":"Retail Goods"
        }
    ],
    "sg:phone":"+1 918 456 8915",
    "sg:postcode":"74464",
    "sg:province":"OK",
    "sg:tags":[
        "merchandise"
    ],
    "wof:name":"Alltel",
    "wof:placetype":"venue"
},
  "geometry": {"coordinates":[-94.976141,35.869284],"type":"Point"}
}