{
  "type": "Feature",
  "properties": {
    "iso:country":"US",
    "sg:address":"24208 E 116th St",
    "sg:city":"Broken Arrow",
    "sg:classifiers":[
        {
            "category":"Wholesale",
            "subcategory":"Hardware",
            "type":"Manufacturing & Wholesale Goods"
        }
    ],
    "sg:phone":"+1 918 451 1616",
    "sg:postcode":"74014",
    "sg:province":"OK",
    "wof:name":"Best Way Air Filters",
    "wof:placetype":"venue"
},
  "geometry": {"coordinates":[-95.706172,35.994998],"type":"Point"}
}