{
  "type": "Feature",
  "properties": {
    "iso:country":"US",
    "sg:address":"408 S Washington St",
    "sg:city":"Stillwater",
    "sg:classifiers":[
        {
            "category":"Bars & Pubs",
            "type":"Food & Drink"
        }
    ],
    "sg:phone":"+1 405 624 9799",
    "sg:postcode":"74074",
    "sg:province":"OK",
    "wof:name":"Copper Penny",
    "wof:placetype":"venue"
},
  "geometry": {"coordinates":[-97.069416,36.117614],"type":"Point"}
}