{
  "type": "Feature",
  "properties": {
    "iso:country":"US",
    "sg:address":"67150 E 175 Rd",
    "sg:city":"Wyandotte",
    "sg:classifiers":[
        {
            "category":"Autos & Motor Vehicles",
            "subcategory":"Automobile Sales",
            "type":"Retail Goods"
        }
    ],
    "sg:phone":"+1 918 678 3210",
    "sg:postcode":"74370",
    "sg:province":"OK",
    "sg:tags":[
        "car",
        "used"
    ],
    "wof:name":"Dewayne A Convirs",
    "wof:placetype":"venue"
},
  "geometry": {"coordinates":[-94.659987,36.764361],"type":"Point"}
}