{
  "type": "Feature",
  "properties": {
    "addr:full":"2513 Canterbury Ave Ponca City OK 74604",
    "addr:housenumber":"2513",
    "addr:postcode":"74604",
    "addr:street":"Canterbury Ave",
    "iso:country":"US",
    "sg:address":"2513 Canterbury Ave",
    "sg:city":"Ponca City",
    "sg:classifiers":[
        {
            "category":"Building & Trades",
            "subcategory":"Construction",
            "type":"Services"
        }
    ],
    "sg:phone":"+1 580 765 4616",
    "sg:postcode":"74604",
    "sg:province":"OK",
    "sg:tags":[
        "excavation",
        "contractor"
    ],
    "wof:name":"Krs Lawn Sprinklers",
    "wof:placetype":"venue"
},
  "geometry": {"coordinates":[-97.04945499999999,36.722581],"type":"Point"}
}