{
  "type": "Feature",
  "properties": {
    "addr:full":"13144 N May Ave Oklahoma City OK 73120",
    "addr:housenumber":"13144",
    "addr:postcode":"73120",
    "addr:street":"N May Ave",
    "iso:country":"US",
    "sg:address":"13144 N May Ave",
    "sg:city":"Oklahoma City",
    "sg:classifiers":[
        {
            "category":"Restaurant",
            "type":"Food & Drink"
        }
    ],
    "sg:phone":"+1 405 751 8882",
    "sg:postcode":"73120",
    "sg:province":"OK",
    "wof:name":"Pizza Hut",
    "wof:placetype":"venue"
},
  "geometry": {"coordinates":[-97.567103,35.602813],"type":"Point"}
}