{
  "type": "Feature",
  "properties": {
    "addr:full":"1201 NW Cache Rd Lawton OK 73507",
    "addr:housenumber":"1201",
    "addr:postcode":"73507",
    "addr:street":"Nw Cache Rd",
    "iso:country":"US",
    "sg:address":"1201 NW Cache Rd",
    "sg:city":"Lawton",
    "sg:classifiers":[
        {
            "category":"Travel",
            "subcategory":"Hotels & Motels",
            "type":"Entertainment"
        }
    ],
    "sg:phone":"+1 580 248 7099",
    "sg:postcode":"73507",
    "sg:province":"OK",
    "sg:tags":[
        "operation"
    ],
    "wof:name":"Super 9 Motel",
    "wof:placetype":"venue"
},
  "geometry": {"coordinates":[-98.406494,34.623369],"type":"Point"}
}