{
  "type": "Feature",
  "properties": {
    "addr:full":"1522 N Harrison Ave Shawnee OK 74804",
    "addr:housenumber":"1522",
    "addr:postcode":"74804",
    "addr:street":"N Harrison Ave",
    "iso:country":"US",
    "sg:address":"1522 N Harrison Ave",
    "sg:city":"Shawnee",
    "sg:classifiers":[
        {
            "category":"Banks & Credit Unions",
            "subcategory":"Financial Services",
            "type":"Services"
        }
    ],
    "sg:phone":"+1 405 273 6752",
    "sg:postcode":"74804",
    "sg:province":"OK",
    "sg:tags":[
        "company",
        "holding"
    ],
    "wof:name":"Eddy Family Holdings",
    "wof:placetype":"venue"
},
  "geometry": {"coordinates":[-96.912144,35.347792],"type":"Point"}
}