{
  "type": "Feature",
  "properties": {
    "iso:country":"US",
    "sg:address":"6462 Avondale Dr",
    "sg:city":"Nichols Hills",
    "sg:classifiers":[
        {
            "category":"Shopping",
            "subcategory":"Gifts & Souvenirs",
            "type":"Retail Goods"
        }
    ],
    "sg:phone":"+1 405 840 5967",
    "sg:postcode":"73116",
    "sg:province":"OK",
    "sg:tags":[
        "shop"
    ],
    "wof:name":"Body Source",
    "wof:placetype":"venue"
},
  "geometry": {"coordinates":[-97.53205699999999,35.539045],"type":"Point"}
}