{
  "type": "Feature",
  "properties": {
    "iso:country":"US",
    "sg:address":"8401 N I- 35 Svc Rd",
    "sg:city":"Oklahoma City",
    "sg:classifiers":[
        {
            "category":"Home & Garden",
            "subcategory":"Furniture",
            "type":"Retail Goods"
        }
    ],
    "sg:phone":"+1 405 478 7000",
    "sg:postcode":"73131",
    "sg:province":"OK",
    "wof:name":"Statuary World Patio & Frsde",
    "wof:placetype":"venue"
},
  "geometry": {"coordinates":[-97.455459,35.555552],"type":"Point"}
}