{
  "type": "Feature",
  "properties": {
    "addr:full":"12336 E 86th St N Owasso OK 74055",
    "addr:housenumber":"12336",
    "addr:postcode":"74055",
    "addr:street":"E 86Th St N",
    "iso:country":"US",
    "sg:address":"12336 E 86th St N",
    "sg:city":"Owasso",
    "sg:classifiers":[
        {
            "category":"Shopping",
            "subcategory":"Musical Instruments",
            "type":"Retail Goods"
        }
    ],
    "sg:phone":"+1 918 274 8880",
    "sg:postcode":"74055",
    "sg:province":"OK",
    "sg:tags":[
        "guitar"
    ],
    "wof:name":"All About Music",
    "wof:placetype":"venue"
},
  "geometry": {"coordinates":[-95.836454,36.278412],"type":"Point"}
}