{
  "type": "Feature",
  "properties": {
    "iso:country":"US",
    "sg:address":"5403 E 35th St",
    "sg:city":"Tulsa",
    "sg:classifiers":[
        {
            "category":"Professional",
            "subcategory":"Accounting & Tax Preparation",
            "type":"Services"
        }
    ],
    "sg:phone":"+1 918 749 5347",
    "sg:postcode":"74135",
    "sg:province":"OK",
    "sg:tags":[
        "return"
    ],
    "wof:name":"Doyle Knowles",
    "wof:placetype":"venue"
},
  "geometry": {"coordinates":[-95.91572499999999,36.113508],"type":"Point"}
}