{
  "type": "Feature",
  "properties": {
    "iso:country":"US",
    "sg:address":"828 E Tahlequah Ave",
    "sg:city":"Vinita",
    "sg:classifiers":[
        {
            "category":"Manufacturing",
            "subcategory":"Metals",
            "type":"Manufacturing & Wholesale Goods"
        }
    ],
    "sg:phone":"+1 918 256 3383",
    "sg:postcode":"74301",
    "sg:province":"OK",
    "sg:tags":[
        "treating",
        "heat"
    ],
    "wof:name":"Royal Treat Inc",
    "wof:placetype":"venue"
},
  "geometry": {"coordinates":[-95.142639,36.640414],"type":"Point"}
}