{
  "type": "Feature",
  "properties": {
    "addr:full":"7435 E Reading St Tulsa OK 74115",
    "addr:housenumber":"7435",
    "addr:postcode":"74115",
    "addr:street":"E Reading",
    "iso:country":"US",
    "sg:address":"7435 E Reading St",
    "sg:city":"Tulsa",
    "sg:classifiers":[
        {
            "category":"Autos & Motor Vehicles",
            "subcategory":"Auto Supplies",
            "type":"Retail Goods"
        }
    ],
    "sg:phone":"+1 918 835 1179",
    "sg:postcode":"74115",
    "sg:province":"OK",
    "sg:tags":[
        "filter",
        "gas"
    ],
    "wof:name":"Southwest Filter Co",
    "wof:placetype":"venue"
},
  "geometry": {"coordinates":[-95.893597,36.178959],"type":"Point"}
}