{
  "type": "Feature",
  "properties": {
    "iso:country":"US",
    "sg:address":"515 S Pennsylvania Ave",
    "sg:city":"Mangum",
    "sg:classifiers":[
        {
            "category":"Building & Trades",
            "subcategory":"Pest Control",
            "type":"Services"
        }
    ],
    "sg:phone":"+1 580 782 2339",
    "sg:postcode":"73554",
    "sg:province":"OK",
    "wof:name":"Western A G Services",
    "wof:placetype":"venue"
},
  "geometry": {"coordinates":[-99.504552,34.867453],"type":"Point"}
}