{
  "type": "Feature",
  "properties": {
    "iso:country":"US",
    "sg:address":"14250 S 277th East Ave",
    "sg:city":"Coweta",
    "sg:classifiers":[
        {
            "category":"Personal",
            "subcategory":"Barber",
            "type":"Services"
        }
    ],
    "sg:phone":"+1 918 279 8305",
    "sg:postcode":"74429",
    "sg:province":"OK",
    "sg:tags":[
        "shop"
    ],
    "wof:name":"Gifted By His Grace Inc",
    "wof:placetype":"venue"
},
  "geometry": {"coordinates":[-95.66756700000001,35.958482],"type":"Point"}
}