{
  "type": "Feature",
  "properties": {
    "iso:country":"US",
    "sg:address":"1125 S Peoria Ave",
    "sg:city":"Tulsa",
    "sg:classifiers":[
        {
            "category":"Freight",
            "type":"Transportation"
        }
    ],
    "sg:phone":"+1 918 584 7000",
    "sg:postcode":"74120",
    "sg:province":"OK",
    "sg:tags":[
        "commercial",
        "storage"
    ],
    "wof:name":"KOOL Storage",
    "wof:placetype":"venue"
},
  "geometry": {"coordinates":[-95.975602,36.147889],"type":"Point"}
}