{
  "type": "Feature",
  "properties": {
    "addr:full":"5510 W 21st St Tulsa OK 74107",
    "addr:housenumber":"5510",
    "addr:postcode":"74107",
    "addr:street":"W 21St St",
    "iso:country":"US",
    "sg:address":"5510 W 21st St",
    "sg:city":"Tulsa",
    "sg:classifiers":[
        {
            "category":"Building & Trades",
            "subcategory":"Construction",
            "type":"Services"
        }
    ],
    "sg:phone":"+1 918 446 6738",
    "sg:postcode":"74107",
    "sg:province":"OK",
    "sg:tags":[
        "concrete",
        "contractor"
    ],
    "wof:name":"Gibson Prefab Concrete Prod Co",
    "wof:placetype":"venue"
},
  "geometry": {"coordinates":[-96.05333,36.133466],"type":"Point"}
}