{
  "type": "Feature",
  "properties": {
    "iso:country":"US",
    "sg:address":"1400 NW Sheridan Rd",
    "sg:city":"Lawton",
    "sg:classifiers":[
        {
            "category":"Banks & Credit Unions",
            "subcategory":"Bank",
            "type":"Services"
        }
    ],
    "sg:phone":"+1 580 355 1201",
    "sg:postcode":"73505",
    "sg:province":"OK",
    "sg:tags":[
        "personal",
        "institution"
    ],
    "wof:name":"Checkmate",
    "wof:placetype":"venue"
},
  "geometry": {"coordinates":[-98.422389,34.623357],"type":"Point"}
}