{
  "type": "Feature",
  "properties": {
    "addr:full":"608 W Wood St Okemah OK 74801",
    "addr:housenumber":"608",
    "addr:postcode":"74801",
    "addr:street":"W Wood St",
    "iso:country":"US",
    "sg:address":"608 W Wood St",
    "sg:city":"Okemah",
    "sg:classifiers":[
        {
            "category":"Restaurant",
            "type":"Food & Drink"
        }
    ],
    "sg:phone":"+1 918 623 1600",
    "sg:postcode":"74801",
    "sg:province":"OK",
    "wof:name":"Yellow Rose",
    "wof:placetype":"venue"
},
  "geometry": {"coordinates":[-96.933909,35.337682],"type":"Point"}
}