{
  "type": "Feature",
  "properties": {
    "iso:country":"US",
    "sg:address":"11107 Stewart Ave",
    "sg:city":"Choctaw",
    "sg:classifiers":[
        {
            "category":"Wholesale",
            "subcategory":"Machinery & Supplies",
            "type":"Manufacturing & Wholesale Goods"
        }
    ],
    "sg:phone":"+1 405 769 5726",
    "sg:postcode":"73020",
    "sg:province":"OK",
    "sg:tags":[
        "building",
        "equipment",
        "road"
    ],
    "wof:name":"Millco",
    "wof:placetype":"venue"
},
  "geometry": {"coordinates":[-97.333605,35.497677],"type":"Point"}
}