{
  "type": "Feature",
  "properties": {
    "addr:full":"3020 S Western Ave Oklahoma City OK 73109",
    "addr:housenumber":"3020",
    "addr:postcode":"73109",
    "addr:street":"S Western Ave",
    "iso:country":"US",
    "sg:address":"3020 S Western Ave",
    "sg:city":"Oklahoma City",
    "sg:classifiers":[
        {
            "category":"Retail",
            "subcategory":"Laundry & Dry Cleaning",
            "type":"Services"
        }
    ],
    "sg:phone":"+1 405 632 5106",
    "sg:postcode":"73109",
    "sg:province":"OK",
    "sg:tags":[
        "cleaners"
    ],
    "wof:name":"Gene's Cleaners",
    "wof:placetype":"venue"
},
  "geometry": {"coordinates":[-97.530102,35.433648],"type":"Point"}
}