{
  "type": "Feature",
  "properties": {
    "addr:full":"19350 E 116th St N Collinsville OK 74021",
    "addr:housenumber":"19350",
    "addr:postcode":"74021",
    "addr:street":"E 116Th St N",
    "iso:country":"US",
    "sg:address":"19350 E 116th St N",
    "sg:city":"Collinsville",
    "sg:classifiers":[
        {
            "category":"Organizations",
            "subcategory":"Religious Organization",
            "type":"Services"
        }
    ],
    "sg:phone":"+1 918 371 2619",
    "sg:postcode":"74021",
    "sg:province":"OK",
    "wof:name":"Meadowview Baptist Church",
    "wof:placetype":"venue"
},
  "geometry": {"coordinates":[-95.762157,36.321785],"type":"Point"}
}