{
  "type": "Feature",
  "properties": {
    "iso:country":"US",
    "sg:address":"2300 N Lincoln Blvd",
    "sg:city":"Oklahoma City",
    "sg:classifiers":[
        {
            "category":"Government",
            "subcategory":"Office",
            "type":"Public Place"
        }
    ],
    "sg:phone":"+1 405 521 2161",
    "sg:postcode":"73105",
    "sg:province":"OK",
    "sg:tags":[
        "executive"
    ],
    "wof:name":"Lieutenant Governor  Oklahoma",
    "wof:placetype":"venue"
},
  "geometry": {"coordinates":[-97.501167,35.493508],"type":"Point"}
}