{
  "type": "Feature",
  "properties": {
    "addr:full":"12211 N Pennsylvania Ave Oklahoma City OK 73120",
    "addr:housenumber":"12211",
    "addr:postcode":"73120",
    "addr:street":"N Pennsylvania Ave",
    "iso:country":"US",
    "sg:address":"12211 N Pennsylvania Ave",
    "sg:city":"Oklahoma City",
    "sg:classifiers":[
        {
            "category":"Personal",
            "type":"Services"
        }
    ],
    "sg:phone":"+1 405 286 0844",
    "sg:postcode":"73120",
    "sg:province":"OK",
    "sg:tags":[
        "control",
        "weight"
    ],
    "wof:name":"Inches A Weigh",
    "wof:placetype":"venue"
},
  "geometry": {"coordinates":[-97.54944500000001,35.593219],"type":"Point"}
}