{
  "type": "Feature",
  "properties": {
    "addr:full":"5 N Broadway Ave Inola OK 74036",
    "addr:housenumber":"5",
    "addr:postcode":"74036",
    "addr:street":"N Broadway Ave",
    "iso:country":"US",
    "sg:address":"5 N Broadway Ave",
    "sg:city":"Inola",
    "sg:classifiers":[
        {
            "category":"Shopping",
            "subcategory":"Gifts & Souvenirs",
            "type":"Retail Goods"
        }
    ],
    "sg:phone":"+1 918 543 6359",
    "sg:postcode":"74036",
    "sg:province":"OK",
    "wof:name":"Pocket Full Of Posies",
    "wof:placetype":"venue"
},
  "geometry": {"coordinates":[-95.510391,36.152315],"type":"Point"}
}