{
  "type": "Feature",
  "properties": {
    "iso:country":"US",
    "sg:address":"108 W 1st Ave",
    "sg:city":"Owasso",
    "sg:classifiers":[
        {
            "category":"Personal",
            "subcategory":"Beauty Salon",
            "type":"Services"
        }
    ],
    "sg:phone":"+1 918 272 1083",
    "sg:postcode":"74055",
    "sg:province":"OK",
    "sg:tags":[
        "shop",
        "building",
        "operator",
        "nonresidential"
    ],
    "wof:name":"Owasso Beauty School",
    "wof:placetype":"venue"
},
  "geometry": {"coordinates":[-95.855079,36.264992],"type":"Point"}
}