{
  "type": "Feature",
  "properties": {
    "addr:full":"428 W Colorado Ave Chickasha OK 73018",
    "addr:housenumber":"428",
    "addr:postcode":"73018",
    "addr:street":"W Colorado Ave",
    "iso:country":"US",
    "sg:address":"428 W Colorado Ave",
    "sg:city":"Chickasha",
    "sg:classifiers":[
        {
            "category":"Organizations",
            "subcategory":"Religious Organization",
            "type":"Services"
        }
    ],
    "sg:phone":"+1 405 222 5433",
    "sg:postcode":"73018",
    "sg:province":"OK",
    "sg:tags":[
        "church"
    ],
    "sg:website":"www.nlccchickasha.com",
    "wof:name":"New Life Christian Church",
    "wof:placetype":"venue"
},
  "geometry": {"coordinates":[-97.937197,35.048831],"type":"Point"}
}