{
  "type": "Feature",
  "properties": {
    "addr:full":"302 E 5th Ave Owasso OK 74055",
    "addr:housenumber":"302",
    "addr:postcode":"74055",
    "addr:street":"E 5Th Ave",
    "iso:country":"US",
    "sg:address":"302 E 5th Ave",
    "sg:city":"Owasso",
    "sg:classifiers":[
        {
            "category":"Building & Trades",
            "subcategory":"Equipment Rental",
            "type":"Services"
        }
    ],
    "sg:phone":"+1 918 274 0023",
    "sg:postcode":"74055",
    "sg:province":"OK",
    "sg:tags":[
        "boiler"
    ],
    "wof:name":"Victory Energy Operations",
    "wof:placetype":"venue"
},
  "geometry": {"coordinates":[-95.85069,36.258937],"type":"Point"}
}