{
  "type": "Feature",
  "properties": {
    "iso:country":"US",
    "sg:address":"107 S Broadway St",
    "sg:city":"Coweta",
    "sg:classifiers":[
        {
            "category":"Professional",
            "subcategory":"Business Services",
            "type":"Services"
        }
    ],
    "sg:phone":"+1 918 279 1731",
    "sg:postcode":"74429",
    "sg:province":"OK",
    "sg:tags":[
        "embroidery"
    ],
    "wof:name":"Dana Designs",
    "wof:placetype":"venue"
},
  "geometry": {"coordinates":[-95.650445,35.949985],"type":"Point"}
}