{
  "type": "Feature",
  "properties": {
    "addr:full":"225 N Broadway St Konawa OK 74849",
    "addr:housenumber":"225",
    "addr:postcode":"74849",
    "addr:street":"N Broadway St",
    "iso:country":"US",
    "sg:address":"225 N Broadway St",
    "sg:city":"Konawa",
    "sg:classifiers":[
        {
            "category":"Home & Garden",
            "subcategory":"Building Materials",
            "type":"Retail Goods"
        }
    ],
    "sg:phone":"+1 580 925 3765",
    "sg:postcode":"74849",
    "sg:province":"OK",
    "sg:tags":[
        "feed",
        "lumber"
    ],
    "wof:name":"Khoury Daniel D",
    "wof:placetype":"venue"
},
  "geometry": {"coordinates":[-96.75212999999999,34.959138],"type":"Point"}
}