{
  "type": "Feature",
  "properties": {
    "iso:country":"US",
    "sg:address":"6051 N Brookline Ave",
    "sg:city":"Oklahoma City",
    "sg:classifiers":[
        {
            "category":"Professional",
            "type":"Services"
        }
    ],
    "sg:phone":"+1 405 842 6404",
    "sg:postcode":"73112",
    "sg:province":"OK",
    "sg:tags":[
        "establishment"
    ],
    "wof:name":"Ricks Ran Production",
    "wof:placetype":"venue"
},
  "geometry": {"coordinates":[-97.567807,35.53421],"type":"Point"}
}