{
  "type": "Feature",
  "properties": {
    "iso:country":"US",
    "sg:address":"2512 Smoking Oak Rd",
    "sg:city":"Norman",
    "sg:classifiers":[
        {
            "category":"Shopping",
            "subcategory":"Used Merchandise",
            "type":"Retail Goods"
        }
    ],
    "sg:phone":"+1 405 321 8484",
    "sg:postcode":"73072",
    "sg:province":"OK",
    "wof:name":"Hopechest Antiques",
    "wof:placetype":"venue"
},
  "geometry": {"coordinates":[-97.46633,35.193741],"type":"Point"}
}