{
  "type": "Feature",
  "properties": {
    "iso:country":"US",
    "sg:address":"2421 N Westminster Rd",
    "sg:city":"Spencer",
    "sg:classifiers":[
        {
            "category":"Manufacturing",
            "subcategory":"Building Materials",
            "type":"Manufacturing & Wholesale Goods"
        }
    ],
    "sg:phone":"+1 405 769 5618",
    "sg:postcode":"73084",
    "sg:province":"OK",
    "wof:name":"Thomas Miles Millwork Inc",
    "wof:placetype":"venue"
},
  "geometry": {"coordinates":[-97.335735,35.49375],"type":"Point"}
}