{
  "type": "Feature",
  "properties": {
    "iso:country":"US",
    "sg:address":"922 NE 4th Ave",
    "sg:city":"Durant",
    "sg:classifiers":[
        {
            "category":"Building & Trades",
            "subcategory":"Construction",
            "type":"Services"
        }
    ],
    "sg:phone":"+1 580 924 2850",
    "sg:postcode":"74701",
    "sg:province":"OK",
    "sg:tags":[
        "woodworker"
    ],
    "wof:name":"J & A Nicknacks & Woodshop",
    "wof:placetype":"venue"
},
  "geometry": {"coordinates":[-96.36706,33.997665],"type":"Point"}
}