{
  "type": "Feature",
  "properties": {
    "addr:full":"3 Hospital Dr Madill OK 73446",
    "addr:housenumber":"3",
    "addr:postcode":"73446",
    "addr:street":"Hospital",
    "iso:country":"US",
    "sg:address":"3 Hospital Dr",
    "sg:city":"Madill",
    "sg:classifiers":[
        {
            "category":"Health Services",
            "subcategory":"Doctor",
            "type":"Services"
        }
    ],
    "sg:phone":"+1 580 677 9700",
    "sg:postcode":"73446",
    "sg:province":"OK",
    "sg:tags":[
        "physician",
        "surgeon"
    ],
    "wof:name":"Texoma Heart Group",
    "wof:placetype":"venue"
},
  "geometry": {"coordinates":[-96.778319,34.080426],"type":"Point"}
}