{
  "type": "Feature",
  "properties": {
    "iso:country":"US",
    "sg:address":"520 Parrington Oval",
    "sg:city":"Norman",
    "sg:classifiers":[
        {
            "category":"Education",
            "subcategory":"College",
            "type":"Public Place"
        }
    ],
    "sg:phone":"+1 405 325 2691",
    "sg:postcode":"73069",
    "sg:province":"OK",
    "sg:tags":[
        "university",
        "arts",
        "school"
    ],
    "wof:name":"School of Arts",
    "wof:placetype":"venue"
},
  "geometry": {"coordinates":[-97.44529799999999,35.210693],"type":"Point"}
}