{
  "type": "Feature",
  "properties": {
    "addr:full":"132 S Ash St Nowata OK 74048",
    "addr:housenumber":"132",
    "addr:postcode":"74048",
    "addr:street":"S Ash St",
    "iso:country":"US",
    "sg:address":"132 S Ash St",
    "sg:city":"Nowata",
    "sg:classifiers":[
        {
            "category":"Restaurant",
            "type":"Food & Drink"
        }
    ],
    "sg:phone":"+1 918 273 1844",
    "sg:postcode":"74048",
    "sg:province":"OK",
    "wof:name":"Bliss Restaurant",
    "wof:placetype":"venue"
},
  "geometry": {"coordinates":[-95.629688,36.698755],"type":"Point"}
}