{
  "type": "Feature",
  "properties": {
    "addr:full":"6104 E 71st St Tulsa OK 74136",
    "addr:housenumber":"6104",
    "addr:postcode":"74136",
    "addr:street":"E 71St St",
    "iso:country":"US",
    "sg:address":"6104 E 71st St",
    "sg:city":"Tulsa",
    "sg:classifiers":[
        {
            "category":"Personal",
            "type":"Services"
        }
    ],
    "sg:phone":"+1 918 497 1001",
    "sg:postcode":"74136",
    "sg:province":"OK",
    "sg:tags":[
        "control",
        "weight"
    ],
    "wof:name":"Inches A Weigh Nutrition",
    "wof:placetype":"venue"
},
  "geometry": {"coordinates":[-95.905573,36.060769],"type":"Point"}
}