{
  "type": "Feature",
  "properties": {
    "addr:full":"2725 Lancaster Ln Oklahoma City OK 73116",
    "addr:housenumber":"2725",
    "addr:postcode":"73116",
    "addr:street":"Lancaster Ln",
    "iso:country":"US",
    "sg:address":"2725 Lancaster Ln",
    "sg:city":"Oklahoma City",
    "sg:classifiers":[
        {
            "category":"Building & Trades",
            "subcategory":"Construction",
            "type":"Services"
        }
    ],
    "sg:phone":"+1 405 840 2388",
    "sg:postcode":"73116",
    "sg:province":"OK",
    "sg:tags":[
        "house"
    ],
    "wof:name":"Codys Construction",
    "wof:placetype":"venue"
},
  "geometry": {"coordinates":[-97.56043699999999,35.543478],"type":"Point"}
}