{
  "type": "Feature",
  "properties": {
    "iso:country":"US",
    "sg:address":"300 S Main St",
    "sg:city":"Newcastle",
    "sg:classifiers":[
        {
            "category":"Health Services",
            "subcategory":"Doctor",
            "type":"Services"
        }
    ],
    "sg:phone":"+1 405 387 3120",
    "sg:postcode":"73065",
    "sg:province":"OK",
    "sg:tags":[
        "physician",
        "surgeon"
    ],
    "wof:name":"Newcastle Family Medicine",
    "wof:placetype":"venue"
},
  "geometry": {"coordinates":[-97.600061,35.244228],"type":"Point"}
}