{
  "type": "Feature",
  "properties": {
    "iso:country":"US",
    "sg:address":"5943 S Lewis Ave",
    "sg:city":"Tulsa",
    "sg:classifiers":[
        {
            "category":"Personal",
            "subcategory":"Beauty Salon",
            "type":"Services"
        }
    ],
    "sg:phone":"+1 918 712 1862",
    "sg:postcode":"74105",
    "sg:province":"OK",
    "sg:tags":[
        "shop"
    ],
    "wof:name":"Montezuma Beauty Salon",
    "wof:placetype":"venue"
},
  "geometry": {"coordinates":[-95.957888,36.077852],"type":"Point"}
}