{
  "type": "Feature",
  "properties": {
    "iso:country":"US",
    "sg:address":"2118 W Edmond Rd",
    "sg:city":"Edmond",
    "sg:classifiers":[
        {
            "category":"Tea Room",
            "type":"Food & Drink"
        }
    ],
    "sg:menulink":"http://www.allmenus.com/ok/oklahoma-city/277258-inspirations-tea-room/menu/",
    "sg:phone":"+1 405 715 2525",
    "sg:postcode":"73003",
    "sg:province":"OK",
    "sg:tags":[
        "coffee",
        "american"
    ],
    "wof:name":"Inspirations Tea Room",
    "wof:placetype":"venue"
},
  "geometry": {"coordinates":[-97.511416,35.652839],"type":"Point"}
}