{
  "type": "Feature",
  "properties": {
    "addr:full":"2222 N 73rd East Ave Tulsa OK 74115",
    "addr:housenumber":"2222",
    "addr:postcode":"74115",
    "addr:street":"N 73Rd;Ave",
    "iso:country":"US",
    "sg:address":"2222 N 73rd East Ave",
    "sg:city":"Tulsa",
    "sg:classifiers":[
        {
            "category":"Retail",
            "subcategory":"Auto Rental",
            "type":"Services"
        }
    ],
    "sg:phone":"+1 918 835 8673",
    "sg:postcode":"74115",
    "sg:province":"OK",
    "sg:tags":[
        "car",
        "truck"
    ],
    "sg:website":"http://www.enterprise.com",
    "wof:name":"Enterprise Rent-A-Car",
    "wof:placetype":"venue"
},
  "geometry": {"coordinates":[-95.895611,36.186662],"type":"Point"}
}