{
  "type": "Feature",
  "properties": {
    "iso:country":"US",
    "sg:address":"12545 E 21st St",
    "sg:city":"Tulsa",
    "sg:classifiers":[
        {
            "category":"Retail",
            "subcategory":"Auto Repair",
            "type":"Services"
        }
    ],
    "sg:phone":"+1 918 437 2721",
    "sg:postcode":"74129",
    "sg:province":"OK",
    "wof:name":"Bush Auto Werkz",
    "wof:placetype":"venue"
},
  "geometry": {"coordinates":[-95.835319,36.133637],"type":"Point"}
}