{
  "type": "Feature",
  "properties": {
    "iso:country":"US",
    "sg:address":"1415 SW Frank Phillips Blvd",
    "sg:city":"Bartlesville",
    "sg:classifiers":[
        {
            "category":"Autos & Motor Vehicles",
            "subcategory":"Auto Supplies",
            "type":"Retail Goods"
        }
    ],
    "sg:phone":"+1 918 336 2328",
    "sg:postcode":"74003",
    "sg:province":"OK",
    "sg:tags":[
        "automobile",
        "parts"
    ],
    "sg:website":"www.oreilly.com",
    "wof:name":"O'Reilly Auto Parts",
    "wof:placetype":"venue"
},
  "geometry": {"coordinates":[-95.99383899999999,36.75153],"type":"Point"}
}