{
  "type": "Feature",
  "properties": {
    "addr:full":"1013 E 38th Pl Tulsa OK 74105",
    "addr:housenumber":"1013",
    "addr:postcode":"74105",
    "addr:street":"E 38Th Pl",
    "iso:country":"US",
    "sg:address":"1013 E 38th Pl",
    "sg:city":"Tulsa",
    "sg:classifiers":[
        {
            "category":"Shopping",
            "subcategory":"Computers & Home Electronics",
            "type":"Retail Goods"
        }
    ],
    "sg:phone":"+1 918 742 8820",
    "sg:postcode":"74105",
    "sg:province":"OK",
    "sg:tags":[
        "repair"
    ],
    "wof:name":"AAA TV & Satellite",
    "wof:placetype":"venue"
},
  "geometry": {"coordinates":[-95.97822499999999,36.107169],"type":"Point"}
}