{
  "type": "Feature",
  "properties": {
    "addr:full":"6420 N Western Ave Oklahoma City OK 73116",
    "addr:housenumber":"6420",
    "addr:postcode":"73116",
    "addr:street":"N Western Ave",
    "iso:country":"US",
    "sg:address":"6420 N Western Ave",
    "sg:city":"Oklahoma City",
    "sg:classifiers":[
        {
            "category":"Retail",
            "subcategory":"Portrait Studio",
            "type":"Services"
        }
    ],
    "sg:phone":"+1 405 286 1463",
    "sg:postcode":"73116",
    "sg:province":"OK",
    "sg:tags":[
        "photographer"
    ],
    "wof:name":"Wyndham Leigh Portraiture",
    "wof:placetype":"venue"
},
  "geometry": {"coordinates":[-97.52971599999999,35.53723],"type":"Point"}
}