{
  "type": "Feature",
  "properties": {
    "iso:country":"US",
    "sg:address":"1400 State Hwy 3",
    "sg:city":"Guymon",
    "sg:classifiers":[
        {
            "category":"Building & Trades",
            "subcategory":"Plumbing",
            "type":"Services"
        }
    ],
    "sg:phone":"+1 580 468 3740",
    "sg:postcode":"73942",
    "sg:province":"OK",
    "sg:tags":[
        "plumbing",
        "contractor"
    ],
    "wof:name":"Allied Plumbing Inc",
    "wof:placetype":"venue"
},
  "geometry": {"coordinates":[-101.481573,36.69188],"type":"Point"}
}