{
  "type": "Feature",
  "properties": {
    "iso:country":"US",
    "sg:address":"4302 S Garnett Rd",
    "sg:city":"Tulsa",
    "sg:classifiers":[
        {
            "category":"Real Estate",
            "subcategory":"Real Estate Agent",
            "type":"Services"
        }
    ],
    "sg:phone":"+1 918 664 4334",
    "sg:postcode":"74146",
    "sg:province":"OK",
    "sg:tags":[
        "building",
        "apartment",
        "management"
    ],
    "wof:name":"Garden Courtyards",
    "wof:placetype":"venue"
},
  "geometry": {"coordinates":[-95.851125,36.103574],"type":"Point"}
}