{
  "type": "Feature",
  "properties": {
    "iso:country":"US",
    "sg:address":"2025 Gordon Cooper Dr",
    "sg:city":"Shawnee",
    "sg:classifiers":[
        {
            "category":"Social Services",
            "subcategory":"Child Care",
            "type":"Services"
        }
    ],
    "sg:phone":"+1 405 275 0663",
    "sg:postcode":"74801",
    "sg:province":"OK",
    "sg:tags":[
        "day"
    ],
    "wof:name":"Ctsa Head Start",
    "wof:placetype":"venue"
},
  "geometry": {"coordinates":[-96.924286,35.293946],"type":"Point"}
}