{
  "type": "Feature",
  "properties": {
    "iso:country":"US",
    "sg:address":"10725 NE 55th St",
    "sg:city":"Spencer",
    "sg:classifiers":[
        {
            "category":"Organizations",
            "subcategory":"Religious Organization",
            "type":"Services"
        }
    ],
    "sg:phone":"+1 405 769 4473",
    "sg:postcode":"73084",
    "sg:province":"OK",
    "sg:tags":[
        "church"
    ],
    "wof:name":"St Paul's Baptist Church",
    "wof:placetype":"venue"
},
  "geometry": {"coordinates":[-97.343305,35.528456],"type":"Point"}
}