{
  "type": "Feature",
  "properties": {
    "iso:country":"US",
    "sg:address":"4140 S Galveston Ave",
    "sg:city":"Tulsa",
    "sg:classifiers":[
        {
            "category":"Shopping",
            "subcategory":"Discount & Variety Stores",
            "type":"Retail Goods"
        }
    ],
    "sg:phone":"+1 918 445 7744",
    "sg:postcode":"74107",
    "sg:province":"OK",
    "sg:tags":[
        "merchandise",
        "general"
    ],
    "wof:name":"Shaw Alloy Piping Products",
    "wof:placetype":"venue"
},
  "geometry": {"coordinates":[-95.995836,36.101345],"type":"Point"}
}