{
  "type": "Feature",
  "properties": {
    "iso:country":"US",
    "sg:address":"15166 S 293rd East Ave",
    "sg:city":"Coweta",
    "sg:classifiers":[
        {
            "category":"Social Services",
            "subcategory":"Child Care",
            "type":"Services"
        }
    ],
    "sg:phone":"+1 918 486 3861",
    "sg:postcode":"74429",
    "sg:province":"OK",
    "sg:tags":[
        "day"
    ],
    "wof:name":"Bright Beginnings L C",
    "wof:placetype":"venue"
},
  "geometry": {"coordinates":[-95.646758,36.134992],"type":"Point"}
}