{
  "type": "Feature",
  "properties": {
    "iso:country":"US",
    "sg:address":"3324 E I- 240 Svc Rd",
    "sg:city":"Oklahoma City",
    "sg:classifiers":[
        {
            "category":"Shopping",
            "subcategory":"Discount & Variety Stores",
            "type":"Retail Goods"
        }
    ],
    "sg:phone":"+1 405 671 8750",
    "sg:postcode":"73135",
    "sg:province":"OK",
    "sg:tags":[
        "merchandise",
        "general"
    ],
    "wof:name":"Coldiron Equipment Sales",
    "wof:placetype":"venue"
},
  "geometry": {"coordinates":[-97.453666,35.391594],"type":"Point"}
}