{
  "type": "Feature",
  "properties": {
    "iso:country":"US",
    "sg:address":"1 SW Sheridan Rd",
    "sg:city":"Lawton",
    "sg:classifiers":[
        {
            "category":"Retail",
            "subcategory":"Auto Repair",
            "type":"Services"
        }
    ],
    "sg:phone":"+1 580 353 1664",
    "sg:postcode":"73505",
    "sg:province":"OK",
    "sg:tags":[
        "general"
    ],
    "wof:name":"Chiefs Auto Repair",
    "wof:placetype":"venue"
},
  "geometry": {"coordinates":[-98.422347,34.607597],"type":"Point"}
}