{
  "type": "Feature",
  "properties": {
    "iso:country":"US",
    "sg:address":"114 NW 6th St",
    "sg:city":"Oklahoma City",
    "sg:classifiers":[
        {
            "category":"Professional",
            "subcategory":"Lawyer & Legal Services",
            "type":"Services"
        }
    ],
    "sg:phone":"+1 405 606 8080",
    "sg:postcode":"73102",
    "sg:province":"OK",
    "sg:tags":[
        "attorney"
    ],
    "wof:name":"Horton & Neighbors PC",
    "wof:placetype":"venue"
},
  "geometry": {"coordinates":[-97.515989,35.473944],"type":"Point"}
}