{
  "type": "Feature",
  "properties": {
    "iso:country":"US",
    "sg:address":"1301 SW 115th Pl",
    "sg:city":"Oklahoma City",
    "sg:classifiers":[
        {
            "category":"Real Estate",
            "subcategory":"Real Estate Agent",
            "type":"Services"
        }
    ],
    "sg:phone":"+1 405 691 9292",
    "sg:postcode":"73170",
    "sg:province":"OK",
    "wof:name":"Jerry Elman Company Inc",
    "wof:placetype":"venue"
},
  "geometry": {"coordinates":[-97.539396,35.35326],"type":"Point"}
}