{
  "type": "Feature",
  "properties": {
    "iso:country":"US",
    "sg:address":"220 State St",
    "sg:city":"Muskogee",
    "sg:classifiers":[
        {
            "category":"Professional",
            "type":"Services"
        }
    ],
    "sg:phone":"+1 918 686 8199",
    "sg:postcode":"74401",
    "sg:province":"OK",
    "sg:tags":[
        "establishment"
    ],
    "wof:name":"Casa For Children Inc",
    "wof:placetype":"venue"
},
  "geometry": {"coordinates":[-95.372785,35.75047],"type":"Point"}
}