{
  "type": "Feature",
  "properties": {
    "iso:country":"US",
    "sg:address":"3500 NW 50th St",
    "sg:city":"Oklahoma City",
    "sg:classifiers":[
        {
            "category":"Organizations",
            "subcategory":"Religious Organization",
            "type":"Services"
        }
    ],
    "sg:phone":"+1 405 943 8581",
    "sg:postcode":"73112",
    "sg:province":"OK",
    "wof:name":"Lake View Pk Chrch of Nazarene",
    "wof:placetype":"venue"
},
  "geometry": {"coordinates":[-97.58111700000001,35.522251],"type":"Point"}
}