{
  "type": "Feature",
  "properties": {
    "iso:country":"US",
    "sg:address":"403 Redbud",
    "sg:city":"Chelsea",
    "sg:classifiers":[
        {
            "category":"Health Services",
            "subcategory":"Doctor",
            "type":"Services"
        }
    ],
    "sg:phone":"+1 918 789 3146",
    "sg:postcode":"74016",
    "sg:province":"OK",
    "sg:tags":[
        "clinic"
    ],
    "wof:name":"Chelsea Family Medical Clinic",
    "wof:placetype":"venue"
},
  "geometry": {"coordinates":[-95.437834,36.539164],"type":"Point"}
}