{
  "type": "Feature",
  "properties": {
    "addr:full":"7002 Bryant Rd Weleetka OK 74880",
    "addr:housenumber":"7002",
    "addr:postcode":"74880",
    "addr:street":"Bryant Rd",
    "iso:country":"US",
    "sg:address":"7002 Bryant Rd",
    "sg:city":"Weleetka",
    "sg:classifiers":[
        {
            "category":"Farming",
            "subcategory":"Farm",
            "type":"Manufacturing & Wholesale Goods"
        }
    ],
    "sg:phone":"+1 918 650 9737",
    "sg:postcode":"74880",
    "sg:province":"OK",
    "sg:tags":[
        "crop",
        "general"
    ],
    "wof:name":"Chancey Bad Creek Farm LLC",
    "wof:placetype":"venue"
},
  "geometry": {"coordinates":[-96.062697,35.391265],"type":"Point"}
}