{
  "type": "Feature",
  "properties": {
    "iso:country":"US",
    "sg:address":"152 Vernon Rd",
    "sg:city":"Cartwright",
    "sg:classifiers":[
        {
            "category":"Retail",
            "subcategory":"Auto Repair",
            "type":"Services"
        }
    ],
    "sg:phone":"+1 580 965 4750",
    "sg:postcode":"74731",
    "sg:province":"OK",
    "sg:tags":[
        "body"
    ],
    "wof:name":"Kern Paint Body",
    "wof:placetype":"venue"
},
  "geometry": {"coordinates":[-96.554984,33.882113],"type":"Point"}
}