{
  "type": "Feature",
  "properties": {
    "iso:country":"US",
    "sg:address":"4149 Highline Blvd",
    "sg:city":"Oklahoma City",
    "sg:classifiers":[
        {
            "category":"Banks & Credit Unions",
            "subcategory":"Investment Brokerage",
            "type":"Services"
        }
    ],
    "sg:phone":"+1 405 948 6900",
    "sg:postcode":"73108",
    "sg:province":"OK",
    "sg:tags":[
        "advisory",
        "financial"
    ],
    "sg:website":"www.midamericanmortgagegroup.com",
    "wof:name":"Mid America Mortgage Group",
    "wof:placetype":"venue"
},
  "geometry": {"coordinates":[-97.59424,35.457082],"type":"Point"}
}