{
  "type": "Feature",
  "properties": {
    "iso:country":"US",
    "sg:address":"2709 NW 119th St",
    "sg:city":"Oklahoma City",
    "sg:classifiers":[
        {
            "category":"Professional",
            "type":"Services"
        }
    ],
    "sg:phone":"+1 405 748 2825",
    "sg:postcode":"73120",
    "sg:province":"OK",
    "sg:tags":[
        "arts",
        "artist"
    ],
    "wof:name":"Gilbert Tampkins Art Studio",
    "wof:placetype":"venue"
},
  "geometry": {"coordinates":[-97.564587,35.591355],"type":"Point"}
}