{
  "type": "Feature",
  "properties": {
    "iso:country":"US",
    "sg:address":"2236 NW 20th St",
    "sg:city":"Oklahoma City",
    "sg:classifiers":[
        {
            "category":"Shopping",
            "type":"Retail Goods"
        }
    ],
    "sg:phone":"+1 405 528 2080",
    "sg:postcode":"73107",
    "sg:province":"OK",
    "sg:tags":[
        "foot",
        "appliance"
    ],
    "wof:name":"Natural Arches Foot Correctors",
    "wof:placetype":"venue"
},
  "geometry": {"coordinates":[-97.55216,35.490024],"type":"Point"}
}