{
  "type": "Feature",
  "properties": {
    "addr:full":"322 N Walker Ave Oklahoma City OK 73102",
    "addr:housenumber":"322",
    "addr:postcode":"73102",
    "addr:street":"N Walker Ave",
    "iso:country":"US",
    "sg:address":"322 N Walker Ave",
    "sg:city":"Oklahoma City",
    "sg:classifiers":[
        {
            "category":"Autos & Motor Vehicles",
            "subcategory":"Auto Supplies",
            "type":"Retail Goods"
        }
    ],
    "sg:phone":"+1 405 232 6185",
    "sg:postcode":"73102",
    "sg:province":"OK",
    "sg:tags":[
        "tire"
    ],
    "wof:name":"Goodyear Downtown Auto Repair",
    "wof:placetype":"venue"
},
  "geometry": {"coordinates":[-97.52122,35.470789],"type":"Point"}
}