{
  "type": "Feature",
  "properties": {
    "addr:full":"4801 SE 29th St Oklahoma City OK 73115",
    "addr:housenumber":"4801",
    "addr:postcode":"73115",
    "addr:street":"Se 29Th St",
    "iso:country":"US",
    "sg:address":"4801 SE 29th St",
    "sg:city":"Oklahoma City",
    "sg:classifiers":[
        {
            "category":"Restaurant",
            "type":"Food & Drink"
        }
    ],
    "sg:menulink":"http://www.allmenus.com/ok/oklahoma-city/175303-arbys/menu/",
    "sg:phone":"+1 405 672 1727",
    "sg:postcode":"73115",
    "sg:province":"OK",
    "sg:tags":[
        "burger",
        "american"
    ],
    "wof:name":"Arby's",
    "wof:placetype":"venue"
},
  "geometry": {"coordinates":[-97.428757,35.435623],"type":"Point"}
}