{
  "type": "Feature",
  "properties": {
    "iso:country":"US",
    "sg:address":"734 N Ridgeway St",
    "sg:city":"Sapulpa",
    "sg:classifiers":[
        {
            "category":"Health Services",
            "subcategory":"Doctor",
            "type":"Services"
        }
    ],
    "sg:phone":"+1 918 224 3988",
    "sg:postcode":"74066",
    "sg:province":"OK",
    "sg:tags":[
        "physician",
        "surgeon"
    ],
    "wof:name":"Praise Fellowship",
    "wof:placetype":"venue"
},
  "geometry": {"coordinates":[-96.0967,36.009895],"type":"Point"}
}