{
  "type": "Feature",
  "properties": {
    "iso:country":"US",
    "sg:address":"4520 S Harvard Ave",
    "sg:city":"Tulsa",
    "sg:classifiers":[
        {
            "category":"Professional",
            "subcategory":"Lawyer & Legal Services",
            "type":"Services"
        }
    ],
    "sg:phone":"+1 918 744 6591",
    "sg:postcode":"74135",
    "sg:province":"OK",
    "sg:tags":[
        "attorney"
    ],
    "wof:name":"Carr & Carr Attorneys",
    "wof:placetype":"venue"
},
  "geometry": {"coordinates":[-95.94026100000001,36.097442],"type":"Point"}
}