{
  "type": "Feature",
  "properties": {
    "iso:country":"US",
    "sg:address":"1001 SE 15th St",
    "sg:city":"Oklahoma City",
    "sg:classifiers":[
        {
            "category":"Autos & Motor Vehicles",
            "subcategory":"Automobile Sales",
            "type":"Retail Goods"
        }
    ],
    "sg:phone":"+1 405 672 9205",
    "sg:postcode":"73129",
    "sg:province":"OK",
    "sg:tags":[
        "car",
        "dealer"
    ],
    "wof:name":"Royal Auto Sales",
    "wof:placetype":"venue"
},
  "geometry": {"coordinates":[-97.492529,35.449936],"type":"Point"}
}