{
  "type": "Feature",
  "properties": {
    "addr:full":"1022 W Grant St Purcell OK 73080",
    "addr:housenumber":"1022",
    "addr:postcode":"73080",
    "addr:street":"W Grant St",
    "iso:country":"US",
    "sg:address":"1022 W Grant St",
    "sg:city":"Purcell",
    "sg:classifiers":[
        {
            "category":"Social Services",
            "subcategory":"Child Care",
            "type":"Services"
        }
    ],
    "sg:phone":"+1 405 527 2415",
    "sg:postcode":"73080",
    "sg:province":"OK",
    "sg:tags":[
        "day"
    ],
    "wof:name":"Charlottes Webb Day Care Inc",
    "wof:placetype":"venue"
},
  "geometry": {"coordinates":[-97.375343,35.029589],"type":"Point"}
}