{
  "type": "Feature",
  "properties": {
    "iso:country":"US",
    "sg:address":"6412 Melrose Ln",
    "sg:city":"Oklahoma City",
    "sg:classifiers":[
        {
            "category":"Manufacturing",
            "subcategory":"Metals",
            "type":"Manufacturing & Wholesale Goods"
        }
    ],
    "sg:phone":"+1 405 787 7620",
    "sg:postcode":"73127",
    "sg:province":"OK",
    "sg:tags":[
        "steel",
        "fabrication",
        "custom"
    ],
    "wof:name":"Five Star Steel Inc",
    "wof:placetype":"venue"
},
  "geometry": {"coordinates":[-97.623341,35.471559],"type":"Point"}
}