{
  "type": "Feature",
  "properties": {
    "iso:country":"US",
    "sg:address":"100 S Pioneer Rd",
    "sg:city":"Elk City",
    "sg:classifiers":[
        {
            "category":"Real Estate",
            "subcategory":"Real Estate Operator",
            "type":"Services"
        }
    ],
    "sg:phone":"+1 580 225 0960",
    "sg:postcode":"73644",
    "sg:province":"OK",
    "sg:tags":[
        "mobile",
        "home",
        "site",
        "community"
    ],
    "wof:name":"Westwood Mobile Home Park",
    "wof:placetype":"venue"
},
  "geometry": {"coordinates":[-99.43494699999999,35.410751],"type":"Point"}
}