{
  "type": "Feature",
  "properties": {
    "addr:full":"11700 Twisted Oak Rd Oklahoma City OK 73120",
    "addr:housenumber":"11700",
    "addr:postcode":"73120",
    "addr:street":"Twisted Oak Rd",
    "iso:country":"US",
    "sg:address":"11700 Twisted Oak Rd",
    "sg:city":"Oklahoma City",
    "sg:classifiers":[
        {
            "category":"Professional",
            "subcategory":"Business Services",
            "type":"Services"
        }
    ],
    "sg:phone":"+1 405 752 8923",
    "sg:postcode":"73120",
    "sg:province":"OK",
    "wof:name":"Test Universe Inc",
    "wof:placetype":"venue"
},
  "geometry": {"coordinates":[-97.578035,35.591801],"type":"Point"}
}