{
  "type": "Feature",
  "properties": {
    "iso:country":"US",
    "sg:address":"400 S Chestnut Ave",
    "sg:city":"Broken Arrow",
    "sg:classifiers":[
        {
            "category":"Shopping",
            "subcategory":"Clothing, Apparel, & Fashions",
            "type":"Retail Goods"
        }
    ],
    "sg:phone":"+1 918 258 0355",
    "sg:postcode":"74012",
    "sg:province":"OK",
    "wof:name":"Sophisticated Images",
    "wof:placetype":"venue"
},
  "geometry": {"coordinates":[-95.817807,36.04948],"type":"Point"}
}