{
  "type": "Feature",
  "properties": {
    "addr:full":"929 SW 59th St Oklahoma City OK 73109",
    "addr:housenumber":"929",
    "addr:postcode":"73109",
    "addr:street":"Sw 59Th St",
    "iso:country":"US",
    "sg:address":"929 SW 59th St",
    "sg:city":"Oklahoma City",
    "sg:classifiers":[
        {
            "category":"Shopping",
            "subcategory":"Clothing, Apparel, & Fashions",
            "type":"Retail Goods"
        }
    ],
    "sg:phone":"+1 405 635 1700",
    "sg:postcode":"73109",
    "sg:province":"OK",
    "sg:tags":[
        "baby",
        "accessory"
    ],
    "wof:name":"Diaper Outlet Inc",
    "wof:placetype":"venue"
},
  "geometry": {"coordinates":[-97.531835,35.406306],"type":"Point"}
}