{
  "type": "Feature",
  "properties": {
    "iso:country":"US",
    "sg:address":"604 N Van Buren Ave",
    "sg:city":"Elk City",
    "sg:classifiers":[
        {
            "category":"Wholesale",
            "subcategory":"Machinery & Supplies",
            "type":"Manufacturing & Wholesale Goods"
        }
    ],
    "sg:phone":"+1 580 225 4538",
    "sg:postcode":"73644",
    "sg:province":"OK",
    "sg:tags":[
        "instrumentation",
        "fitting",
        "industrial",
        "valve"
    ],
    "wof:name":"Jet Specialty",
    "wof:placetype":"venue"
},
  "geometry": {"coordinates":[-99.399608,35.417225],"type":"Point"}
}