{
  "type": "Feature",
  "properties": {
    "iso:country":"US",
    "sg:address":"777 NW Grand Blvd",
    "sg:city":"Oklahoma City",
    "sg:classifiers":[
        {
            "category":"Banks & Credit Unions",
            "subcategory":"Financial Services",
            "type":"Services"
        }
    ],
    "sg:phone":"+1 405 843 7741",
    "sg:postcode":"73118",
    "sg:province":"OK",
    "sg:tags":[
        "royalty",
        "oil"
    ],
    "wof:name":"M C Mineral Co",
    "wof:placetype":"venue"
},
  "geometry": {"coordinates":[-97.524848,35.528669],"type":"Point"}
}