{
  "type": "Feature",
  "properties": {
    "iso:country":"US",
    "sg:address":"5980 S 49th W Ave",
    "sg:city":"Tulsa",
    "sg:classifiers":[
        {
            "category":"Restaurant",
            "type":"Food & Drink"
        }
    ],
    "sg:phone":"+1 918 445 6835",
    "sg:postcode":"74107",
    "sg:province":"OK",
    "sg:tags":[
        "eating"
    ],
    "wof:name":"Arbys",
    "wof:placetype":"venue"
},
  "geometry": {"coordinates":[-96.04746900000001,36.075452],"type":"Point"}
}