{
  "type": "Feature",
  "properties": {
    "iso:country":"US",
    "sg:address":"3801 N Classen Blvd",
    "sg:city":"Oklahoma City",
    "sg:classifiers":[
        {
            "category":"Building & Trades",
            "subcategory":"Construction",
            "type":"Services"
        }
    ],
    "sg:phone":"+1 405 942 7510",
    "sg:postcode":"73118",
    "sg:province":"OK",
    "sg:tags":[
        "house",
        "siding",
        "contractor"
    ],
    "wof:name":"Commander Home Improvement Co",
    "wof:placetype":"venue"
},
  "geometry": {"coordinates":[-97.534334,35.51018],"type":"Point"}
}