{
  "type": "Feature",
  "properties": {
    "addr:full":"4237 Southwest Blvd Tulsa OK 74107",
    "addr:housenumber":"4237",
    "addr:postcode":"74107",
    "addr:street":"Southwest Blvd",
    "iso:country":"US",
    "sg:address":"4237 Southwest Blvd",
    "sg:city":"Tulsa",
    "sg:classifiers":[
        {
            "category":"Shopping",
            "subcategory":"Pharmacy",
            "type":"Retail Goods"
        }
    ],
    "sg:phone":"+1 918 446 3541",
    "sg:postcode":"74107",
    "sg:province":"OK",
    "sg:tags":[
        "drug",
        "store"
    ],
    "wof:name":"Med X Drug 4",
    "wof:placetype":"venue"
},
  "geometry": {"coordinates":[-96.02711600000001,36.10176],"type":"Point"}
}