{
  "type": "Feature",
  "properties": {
    "iso:country":"US",
    "sg:address":"101 S 2nd St",
    "sg:city":"Ponca City",
    "sg:classifiers":[
        {
            "category":"Insurance",
            "subcategory":"Insurance Agent",
            "type":"Services"
        }
    ],
    "sg:phone":"+1 580 762 1414",
    "sg:postcode":"74601",
    "sg:province":"OK",
    "wof:name":"Bellinghausen Agency",
    "wof:placetype":"venue"
},
  "geometry": {"coordinates":[-97.082501,36.703654],"type":"Point"}
}