{
  "type": "Feature",
  "properties": {
    "addr:full":"3701 SE 89th St Oklahoma City OK 73135",
    "addr:housenumber":"3701",
    "addr:postcode":"73135",
    "addr:street":"Se 89Th St",
    "iso:country":"US",
    "sg:address":"3701 SE 89th St",
    "sg:city":"Oklahoma City",
    "sg:classifiers":[
        {
            "category":"Building & Trades",
            "subcategory":"Construction",
            "type":"Services"
        }
    ],
    "sg:phone":"+1 405 619 5600",
    "sg:postcode":"73135",
    "sg:province":"OK",
    "sg:tags":[
        "sandblasting"
    ],
    "sg:website":"www.midwestcoatings.com",
    "wof:name":"Midwest Coatings",
    "wof:placetype":"venue"
},
  "geometry": {"coordinates":[-97.441233,35.377198],"type":"Point"}
}