{
  "type": "Feature",
  "properties": {
    "iso:country":"US",
    "sg:address":"11414 E 68th St",
    "sg:city":"Ripley",
    "sg:classifiers":[
        {
            "category":"Wholesale",
            "subcategory":"Chemicals & Plastics",
            "type":"Manufacturing & Wholesale Goods"
        }
    ],
    "sg:phone":"+1 918 372 4688",
    "sg:postcode":"74062",
    "sg:province":"OK",
    "wof:name":"Sandoz Corp Protection",
    "wof:placetype":"venue"
},
  "geometry": {"coordinates":[-96.89618,36.044167],"type":"Point"}
}