{
  "type": "Feature",
  "properties": {
    "addr:full":"7113 N Bryant Ave Oklahoma City OK 73121",
    "addr:housenumber":"7113",
    "addr:postcode":"73121",
    "addr:street":"N Bryant Ave",
    "iso:country":"US",
    "sg:address":"7113 N Bryant Ave",
    "sg:city":"Oklahoma City",
    "sg:classifiers":[
        {
            "category":"Building & Trades",
            "subcategory":"Construction",
            "type":"Services"
        }
    ],
    "sg:phone":"+1 405 478 5370",
    "sg:postcode":"73121",
    "sg:province":"OK",
    "sg:tags":[
        "line",
        "utility",
        "contractor"
    ],
    "wof:name":"Urban Contractors Inc",
    "wof:placetype":"venue"
},
  "geometry": {"coordinates":[-97.457429,35.545108],"type":"Point"}
}