{
  "type": "Feature",
  "properties": {
    "iso:country":"US",
    "sg:address":"6320 W 22nd St N",
    "sg:city":"Muskogee",
    "sg:classifiers":[
        {
            "category":"Shopping",
            "subcategory":"Gifts & Souvenirs",
            "type":"Retail Goods"
        }
    ],
    "sg:phone":"+1 918 687 0909",
    "sg:postcode":"74401",
    "sg:province":"OK",
    "sg:tags":[
        "shop"
    ],
    "wof:name":"Sisters Heaven",
    "wof:placetype":"venue"
},
  "geometry": {"coordinates":[-95.444671,35.771064],"type":"Point"}
}