{
  "type": "Feature",
  "properties": {
    "iso:country":"US",
    "sg:address":"2615 4th St",
    "sg:city":"Woodward",
    "sg:classifiers":[
        {
            "category":"Building & Trades",
            "subcategory":"Construction",
            "type":"Services"
        }
    ],
    "sg:phone":"+1 580 256 5326",
    "sg:postcode":"73801",
    "sg:province":"OK",
    "sg:tags":[
        "residential"
    ],
    "wof:name":"Richard Wise Construction",
    "wof:placetype":"venue"
},
  "geometry": {"coordinates":[-99.384172,36.420934],"type":"Point"}
}