{
  "type": "Feature",
  "properties": {
    "iso:country":"US",
    "sg:address":"1515 E 71st St #200",
    "sg:city":"Tulsa",
    "sg:classifiers":[
        {
            "category":"Insurance",
            "subcategory":"Hazard Insurance",
            "type":"Services"
        },
        {
            "category":"Insurance",
            "subcategory":"Insurance Agent",
            "type":"Services"
        },
        {
            "category":"Insurance",
            "subcategory":"Life Insurance",
            "type":"Services"
        },
        {
            "category":"Insurance",
            "subcategory":"Title Insurance",
            "type":"Services"
        }
    ],
    "sg:phone":"+1 918 492 8282",
    "sg:postcode":"74136",
    "sg:province":"OK",
    "sg:tags":[
        "auto",
        "commercial",
        "business",
        "homeowner"
    ],
    "sg:website":"http://www.farmers.com",
    "wof:name":"John Roush - Farmers Insurance",
    "wof:placetype":"venue"
},
  "geometry": {"coordinates":[-95.970539,36.060809],"type":"Point"}
}