{
  "type": "Feature",
  "properties": {
    "addr:full":"5601 S 122nd East Ave Tulsa OK 74146",
    "addr:housenumber":"5601",
    "addr:postcode":"74146",
    "addr:street":"S 122Nd;Ave",
    "iso:country":"US",
    "sg:address":"5601 S 122nd East Ave",
    "sg:city":"Tulsa",
    "sg:classifiers":[
        {
            "category":"Building & Trades",
            "subcategory":"Construction",
            "type":"Services"
        }
    ],
    "sg:phone":"+1 918 583 6900",
    "sg:postcode":"74146",
    "sg:province":"OK",
    "sg:tags":[
        "contractor"
    ],
    "wof:name":"Manhattan Construction Co",
    "wof:placetype":"venue"
},
  "geometry": {"coordinates":[-95.840397,36.081065],"type":"Point"}
}