{
  "type": "Feature",
  "properties": {
    "iso:country":"US",
    "sg:address":"123 N Division St",
    "sg:city":"Guthrie",
    "sg:classifiers":[
        {
            "category":"Banks & Credit Unions",
            "subcategory":"Bank",
            "type":"Services"
        }
    ],
    "sg:phone":"+1 405 282 4525",
    "sg:postcode":"73044",
    "sg:province":"OK",
    "sg:tags":[
        "loan"
    ],
    "wof:name":"Community Loans Inc",
    "wof:placetype":"venue"
},
  "geometry": {"coordinates":[-97.425431,35.878317],"type":"Point"}
}