{
  "type": "Feature",
  "properties": {
    "iso:country":"US",
    "sg:address":"1100 S Oklahoma Ave",
    "sg:city":"Cherokee",
    "sg:classifiers":[
        {
            "category":"Organizations",
            "subcategory":"Religious Organization",
            "type":"Services"
        }
    ],
    "sg:phone":"+1 580 596 3067",
    "sg:postcode":"73728",
    "sg:province":"OK",
    "wof:name":"Bethel Baptist Church",
    "wof:placetype":"venue"
},
  "geometry": {"coordinates":[-98.358317,36.747724],"type":"Point"}
}