{
  "type": "Feature",
  "properties": {
    "iso:country":"US",
    "sg:address":"120 E Sheridan Ave",
    "sg:city":"Oklahoma City",
    "sg:classifiers":[
        {
            "category":"Real Estate",
            "subcategory":"Real Estate Agent",
            "type":"Services"
        }
    ],
    "sg:phone":"+1 405 843 8843",
    "sg:postcode":"73104",
    "sg:province":"OK",
    "wof:name":"Mize Real Estate Group",
    "wof:placetype":"venue"
},
  "geometry": {"coordinates":[-97.509426,35.466396],"type":"Point"}
}