{
  "type": "Feature",
  "properties": {
    "addr:full":"1400 Milam Ct Oklahoma City OK 73111",
    "addr:housenumber":"1400",
    "addr:postcode":"73111",
    "addr:street":"Milam Ct",
    "iso:country":"US",
    "sg:address":"1400 Milam Ct",
    "sg:city":"Oklahoma City",
    "sg:classifiers":[
        {
            "category":"Organizations",
            "subcategory":"Religious Organization",
            "type":"Services"
        }
    ],
    "sg:phone":"+1 405 424 2017",
    "sg:postcode":"73111",
    "sg:province":"OK",
    "wof:name":"Christ Evnglst Baptist Church",
    "wof:placetype":"venue"
},
  "geometry": {"coordinates":[-97.486829,35.494777],"type":"Point"}
}