{
  "type": "Feature",
  "properties": {
    "addr:full":"1133 S Memorial Dr Tulsa OK 74112",
    "addr:housenumber":"1133",
    "addr:postcode":"74112",
    "addr:street":"S Memorial Dr",
    "iso:country":"US",
    "sg:address":"1133 S Memorial Dr",
    "sg:city":"Tulsa",
    "sg:classifiers":[
        {
            "category":"Bakery",
            "type":"Food & Drink"
        },
        {
            "category":"Coffee & Tea",
            "type":"Food & Drink"
        },
        {
            "category":"Restaurant",
            "type":"Food & Drink"
        },
        {
            "category":"Food & Beverages",
            "subcategory":"Bakery",
            "type":"Retail Goods"
        },
        {
            "category":"Donuts",
            "type":"Food & Drink"
        }
    ],
    "sg:menulink":"http://www.allmenus.com/ok/tulsa/230914-daylight-donuts/menu/",
    "sg:phone":"+1 918 834 5683",
    "sg:postcode":"74112",
    "sg:province":"OK",
    "sg:tags":[
        "tea",
        "coffee",
        "bakery",
        "american",
        "pastry"
    ],
    "wof:name":"Daylight Donuts",
    "wof:placetype":"venue"
},
  "geometry": {"coordinates":[-95.886155,36.146643],"type":"Point"}
}