{
  "type": "Feature",
  "properties": {
    "iso:country":"US",
    "sg:address":"5151 E 51st St",
    "sg:city":"Tulsa",
    "sg:classifiers":[
        {
            "category":"Health Services",
            "subcategory":"Health Practitioner",
            "type":"Services"
        }
    ],
    "sg:phone":"+1 918 622 8494",
    "sg:postcode":"74135",
    "sg:province":"OK",
    "sg:tags":[
        "psychologist"
    ],
    "wof:name":"Allen W Sweet PHD",
    "wof:placetype":"venue"
},
  "geometry": {"coordinates":[-95.918229,36.089951],"type":"Point"}
}