{
  "type": "Feature",
  "properties": {
    "iso:country":"US",
    "sg:address":"6840 E Admiral Pl",
    "sg:city":"Tulsa",
    "sg:classifiers":[
        {
            "category":"Retail",
            "subcategory":"Auto Repair",
            "type":"Services"
        }
    ],
    "sg:phone":"+1 918 838 3271",
    "sg:postcode":"74115",
    "sg:province":"OK",
    "sg:tags":[
        "transmission"
    ],
    "wof:name":"Roys Transmission Service",
    "wof:placetype":"venue"
},
  "geometry": {"coordinates":[-95.900786,36.160676],"type":"Point"}
}