{
  "type": "Feature",
  "properties": {
    "iso:country":"US",
    "sg:address":"115 W Rogers Blvd",
    "sg:city":"Skiatook",
    "sg:classifiers":[
        {
            "category":"Retail",
            "subcategory":"Auto Repair",
            "type":"Services"
        }
    ],
    "sg:phone":"+1 918 396 2100",
    "sg:postcode":"74070",
    "sg:province":"OK",
    "sg:tags":[
        "automotive"
    ],
    "wof:name":"Skiatook Auto Lube",
    "wof:placetype":"venue"
},
  "geometry": {"coordinates":[-96.001479,36.368597],"type":"Point"}
}