{
  "type": "Feature",
  "properties": {
    "iso:country":"US",
    "sg:address":"820 McGee Dr",
    "sg:city":"Norman",
    "sg:classifiers":[
        {
            "category":"Social Services",
            "type":"Services"
        }
    ],
    "sg:phone":"+1 405 360 2124",
    "sg:postcode":"73069",
    "sg:province":"OK",
    "sg:tags":[
        "organization",
        "welfare"
    ],
    "wof:name":"Saint Stephens Headstart",
    "wof:placetype":"venue"
},
  "geometry": {"coordinates":[-97.46786299999999,35.207587],"type":"Point"}
}