{
  "type": "Feature",
  "properties": {
    "addr:full":"100 Park Ave Oklahoma City OK 73102",
    "addr:housenumber":"100",
    "addr:postcode":"73102",
    "addr:street":"Park Ave",
    "iso:country":"US",
    "sg:address":"100 Park Ave",
    "sg:city":"Oklahoma City",
    "sg:classifiers":[
        {
            "category":"Banks & Credit Unions",
            "subcategory":"Investment Brokerage",
            "type":"Services"
        }
    ],
    "sg:phone":"+1 405 232 6400",
    "sg:postcode":"73102",
    "sg:province":"OK",
    "sg:tags":[
        "advisory",
        "security"
    ],
    "wof:name":"Td Waterhouse Investor Svcs",
    "wof:placetype":"venue"
},
  "geometry": {"coordinates":[-97.516413,35.46881],"type":"Point"}
}