{
  "type": "Feature",
  "properties": {
    "iso:country":"US",
    "sg:address":"5301 N Meridian Ave",
    "sg:city":"Oklahoma City",
    "sg:classifiers":[
        {
            "category":"Organizations",
            "subcategory":"Membership Organization",
            "type":"Services"
        }
    ],
    "sg:phone":"+1 405 789 3202",
    "sg:postcode":"73112",
    "sg:province":"OK",
    "wof:name":"Salvation Army",
    "wof:placetype":"venue"
},
  "geometry": {"coordinates":[-97.601191,35.522329],"type":"Point"}
}