{
  "type": "Feature",
  "properties": {
    "iso:country":"US",
    "sg:address":"5601 NW 72nd St",
    "sg:city":"Oklahoma City",
    "sg:classifiers":[
        {
            "category":"Building & Trades",
            "subcategory":"Equipment Rental",
            "type":"Services"
        }
    ],
    "sg:phone":"+1 405 948 1115",
    "sg:postcode":"73132",
    "sg:province":"OK",
    "wof:name":"Hydra Pools Inc",
    "wof:placetype":"venue"
},
  "geometry": {"coordinates":[-97.61313,35.545321],"type":"Point"}
}