{
  "type": "Feature",
  "properties": {
    "addr:full":"2212 W Nashville St Broken Arrow OK 74012",
    "addr:housenumber":"2212",
    "addr:postcode":"74012",
    "addr:street":"W Nashville St",
    "iso:country":"US",
    "sg:address":"2212 W Nashville St",
    "sg:city":"Broken Arrow",
    "sg:classifiers":[
        {
            "category":"Utilities",
            "subcategory":"Mobile Phone",
            "type":"Services"
        }
    ],
    "sg:phone":"+1 918 251 4007",
    "sg:postcode":"74012",
    "sg:province":"OK",
    "sg:tags":[
        "communication",
        "radiotelephone"
    ],
    "wof:name":"Motorola",
    "wof:placetype":"venue"
},
  "geometry": {"coordinates":[-95.81709499999999,36.041031],"type":"Point"}
}