{
  "type": "Feature",
  "properties": {
    "iso:country":"US",
    "sg:address":"6767 E Reno Ave",
    "sg:city":"Oklahoma City",
    "sg:classifiers":[
        {
            "category":"Shopping",
            "subcategory":"Jewelry",
            "type":"Retail Goods"
        }
    ],
    "sg:phone":"+1 405 737 5626",
    "sg:postcode":"73110",
    "sg:province":"OK",
    "sg:tags":[
        "jeweler"
    ],
    "wof:name":"Zales Jewelers",
    "wof:placetype":"venue"
},
  "geometry": {"coordinates":[-97.408495,35.46412],"type":"Point"}
}