{
  "type": "Feature",
  "properties": {
    "iso:country":"US",
    "sg:address":"709 E Benton Ave",
    "sg:city":"Davis",
    "sg:classifiers":[
        {
            "category":"Education",
            "subcategory":"School",
            "type":"Public Place"
        }
    ],
    "sg:phone":"+1 580 369 3266",
    "sg:postcode":"73030",
    "sg:province":"OK",
    "wof:name":"Davis Headstart School",
    "wof:placetype":"venue"
},
  "geometry": {"coordinates":[-97.114329,34.507469],"type":"Point"}
}