{
  "type": "Feature",
  "properties": {
    "iso:country":"US",
    "sg:address":"129 E Washington Ave",
    "sg:city":"Walters",
    "sg:classifiers":[
        {
            "category":"Education",
            "subcategory":"School",
            "type":"Public Place"
        }
    ],
    "sg:phone":"+1 580 875 3214",
    "sg:postcode":"73572",
    "sg:province":"OK",
    "wof:name":"Walters Middle School",
    "wof:placetype":"venue"
},
  "geometry": {"coordinates":[-98.30876000000001,34.353909],"type":"Point"}
}