{
  "type": "Feature",
  "properties": {
    "iso:country":"US",
    "sg:address":"110 N Choctaw Rd",
    "sg:city":"Skiatook",
    "sg:classifiers":[
        {
            "category":"Professional",
            "subcategory":"Management & Consulting",
            "type":"Services"
        }
    ],
    "sg:phone":"+1 918 396 7999",
    "sg:postcode":"74070",
    "sg:province":"OK",
    "sg:tags":[
        "consultant"
    ],
    "wof:name":"Cherokee Consulting",
    "wof:placetype":"venue"
},
  "geometry": {"coordinates":[-96.024439,36.369099],"type":"Point"}
}