{
  "type": "Feature",
  "properties": {
    "iso:country":"US",
    "sg:address":"3000 NW 13th St",
    "sg:city":"Oklahoma City",
    "sg:classifiers":[
        {
            "category":"Real Estate",
            "subcategory":"Surveying",
            "type":"Services"
        }
    ],
    "sg:phone":"+1 405 947 2492",
    "sg:postcode":"73107",
    "sg:province":"OK",
    "sg:tags":[
        "surveyor"
    ],
    "wof:name":"Mitchell Surveying Co",
    "wof:placetype":"venue"
},
  "geometry": {"coordinates":[-97.56797400000001,35.483106],"type":"Point"}
}