{
  "type": "Feature",
  "properties": {
    "iso:country":"US",
    "sg:address":"5934 NW 122nd St",
    "sg:city":"Oklahoma City",
    "sg:classifiers":[
        {
            "category":"Restaurant",
            "type":"Food & Drink"
        }
    ],
    "sg:phone":"+1 405 728 1949",
    "sg:postcode":"73142",
    "sg:province":"OK",
    "sg:tags":[
        "eating"
    ],
    "wof:name":"Golden Dragon Chinese Rest",
    "wof:placetype":"venue"
},
  "geometry": {"coordinates":[-97.621008,35.594559],"type":"Point"}
}