{
  "type": "Feature",
  "properties": {
    "addr:full":"807 NW Sheridan Rd Lawton OK 73505",
    "addr:housenumber":"807",
    "addr:postcode":"73505",
    "addr:street":"Nw Sheridan Rd",
    "iso:country":"US",
    "sg:address":"807 NW Sheridan Rd",
    "sg:city":"Lawton",
    "sg:classifiers":[
        {
            "category":"Autos & Motor Vehicles",
            "subcategory":"Automobile Sales",
            "type":"Retail Goods"
        }
    ],
    "sg:phone":"+1 580 355 3280",
    "sg:postcode":"73505",
    "sg:province":"OK",
    "wof:name":"Aubrey Chevrolet",
    "wof:placetype":"venue"
},
  "geometry": {"coordinates":[-98.422118,34.619592],"type":"Point"}
}