{
  "type": "Feature",
  "properties": {
    "iso:country":"US",
    "sg:address":"405 W Ash Ave",
    "sg:city":"Fairfax",
    "sg:classifiers":[
        {
            "category":"Restaurant",
            "type":"Food & Drink"
        }
    ],
    "sg:phone":"+1 918 642 5527",
    "sg:postcode":"74637",
    "sg:province":"OK",
    "sg:tags":[
        "eating"
    ],
    "wof:name":"Lazy S Bbq",
    "wof:placetype":"venue"
},
  "geometry": {"coordinates":[-96.708589,36.568606],"type":"Point"}
}