{
  "type": "Feature",
  "properties": {
    "iso:country":"US",
    "sg:address":"12212 E 450 Rd",
    "sg:city":"Claremore",
    "sg:classifiers":[
        {
            "category":"Real Estate",
            "subcategory":"Real Estate Agent",
            "type":"Services"
        }
    ],
    "sg:phone":"+1 918 342 4533",
    "sg:postcode":"74017",
    "sg:province":"OK",
    "wof:name":"Gedd LLC",
    "wof:placetype":"venue"
},
  "geometry": {"coordinates":[-95.61438800000001,36.365257],"type":"Point"}
}