{
  "type": "Feature",
  "properties": {
    "addr:full":"5710 SW 63rd St Oklahoma City OK 73169",
    "addr:housenumber":"5710",
    "addr:postcode":"73169",
    "addr:street":"Sw 63Rd St",
    "iso:country":"US",
    "sg:address":"5710 SW 63rd St",
    "sg:city":"Oklahoma City",
    "sg:classifiers":[
        {
            "category":"Banks & Credit Unions",
            "subcategory":"Bank",
            "type":"Services"
        }
    ],
    "sg:phone":"+1 405 685 7637",
    "sg:postcode":"73169",
    "sg:province":"OK",
    "wof:name":"FAA Employees Credit Union",
    "wof:placetype":"venue"
},
  "geometry": {"coordinates":[-97.618537,35.400205],"type":"Point"}
}