{
  "type": "Feature",
  "properties": {
    "iso:country":"US",
    "sg:address":"110 W Ferry St",
    "sg:city":"Salina",
    "sg:classifiers":[
        {
            "category":"Professional",
            "subcategory":"Business Services",
            "type":"Services"
        }
    ],
    "sg:phone":"+1 918 434 3141",
    "sg:postcode":"74365",
    "sg:province":"OK",
    "sg:tags":[
        "embroidery"
    ],
    "wof:name":"Stitch & Soul",
    "wof:placetype":"venue"
},
  "geometry": {"coordinates":[-95.154415,36.292787],"type":"Point"}
}