{
  "type": "Feature",
  "properties": {
    "iso:country":"US",
    "sg:address":"1105 Ono Ct",
    "sg:city":"Mcalester",
    "sg:classifiers":[
        {
            "category":"Professional",
            "subcategory":"Management & Consulting",
            "type":"Services"
        }
    ],
    "sg:phone":"+1 918 426 1417",
    "sg:postcode":"74501",
    "sg:province":"OK",
    "sg:tags":[
        "consultant",
        "business"
    ],
    "wof:name":"John M Freeman & Assoc Inc",
    "wof:placetype":"venue"
},
  "geometry": {"coordinates":[-95.759445,34.908505],"type":"Point"}
}