{
  "type": "Feature",
  "properties": {
    "addr:full":"410 W Quanah Pl Broken Arrow OK 74011",
    "addr:housenumber":"410",
    "addr:postcode":"74011",
    "addr:street":"W Quanah Pl",
    "iso:country":"US",
    "sg:address":"410 W Quanah Pl",
    "sg:city":"Broken Arrow",
    "sg:classifiers":[
        {
            "category":"Professional",
            "subcategory":"Computer Services",
            "type":"Services"
        }
    ],
    "sg:phone":"+1 918 455 4894",
    "sg:postcode":"74011",
    "sg:province":"OK",
    "sg:tags":[
        "programing",
        "custom"
    ],
    "wof:name":"McK Services Inc",
    "wof:placetype":"venue"
},
  "geometry": {"coordinates":[-95.793604,35.990753],"type":"Point"}
}