{
  "type": "Feature",
  "properties": {
    "iso:country":"US",
    "sg:address":"1416 N Park Ln",
    "sg:city":"Altus",
    "sg:classifiers":[
        {
            "category":"Real Estate",
            "subcategory":"Real Estate Agent",
            "type":"Services"
        }
    ],
    "sg:phone":"+1 580 477 0047",
    "sg:postcode":"73521",
    "sg:province":"OK",
    "wof:name":"Carolyn Duff American Realty",
    "wof:placetype":"venue"
},
  "geometry": {"coordinates":[-99.31634099999999,34.652628],"type":"Point"}
}