{
  "type": "Feature",
  "properties": {
    "iso:country":"US",
    "sg:address":"1100 S Meridian Ave",
    "sg:city":"Oklahoma City",
    "sg:classifiers":[
        {
            "category":"Restaurant",
            "type":"Food & Drink"
        }
    ],
    "sg:phone":"+1 405 942 1360",
    "sg:postcode":"73108",
    "sg:province":"OK",
    "wof:name":"Logans",
    "wof:placetype":"venue"
},
  "geometry": {"coordinates":[-97.601027,35.455986],"type":"Point"}
}