{
  "type": "Feature",
  "properties": {
    "addr:full":"822 W 12th St Sulphur OK 73086",
    "addr:housenumber":"822",
    "addr:postcode":"73086",
    "addr:street":"W 12Th St",
    "iso:country":"US",
    "sg:address":"822 W 12th St",
    "sg:city":"Sulphur",
    "sg:classifiers":[
        {
            "category":"Professional",
            "subcategory":"Accounting & Tax Preparation",
            "type":"Services"
        }
    ],
    "sg:phone":"+1 580 622 6759",
    "sg:postcode":"73086",
    "sg:province":"OK",
    "sg:tags":[
        "return"
    ],
    "wof:name":"H & R Block",
    "wof:placetype":"venue"
},
  "geometry": {"coordinates":[-96.982088,34.505582],"type":"Point"}
}