{
  "type": "Feature",
  "properties": {
    "iso:country":"US",
    "sg:address":"2117 Tanglewood Dr",
    "sg:city":"Edmond",
    "sg:classifiers":[
        {
            "category":"Utilities",
            "subcategory":"Telephone",
            "type":"Services"
        }
    ],
    "sg:phone":"+1 405 340 2117",
    "sg:postcode":"73013",
    "sg:province":"OK",
    "sg:tags":[
        "communications"
    ],
    "wof:name":"Tiger-Wing Incentive",
    "wof:placetype":"venue"
},
  "geometry": {"coordinates":[-97.509314,35.633612],"type":"Point"}
}