{
  "type": "Feature",
  "properties": {
    "iso:country":"US",
    "sg:address":"2040 E Seward Rd",
    "sg:city":"Guthrie",
    "sg:classifiers":[
        {
            "category":"Building & Trades",
            "subcategory":"Construction",
            "type":"Services"
        }
    ],
    "sg:phone":"+1 405 340 8375",
    "sg:postcode":"73044",
    "sg:province":"OK",
    "sg:tags":[
        "insulation",
        "heat",
        "contractor"
    ],
    "wof:name":"Reliable Insulation",
    "wof:placetype":"venue"
},
  "geometry": {"coordinates":[-97.400499,35.797999],"type":"Point"}
}