{
  "type": "Feature",
  "properties": {
    "iso:country":"US",
    "sg:address":"2121 SW 119th St",
    "sg:city":"Oklahoma City",
    "sg:classifiers":[
        {
            "category":"Farming",
            "subcategory":"Nursery",
            "type":"Manufacturing & Wholesale Goods"
        }
    ],
    "sg:phone":"+1 405 691 9100",
    "sg:postcode":"73170",
    "sg:province":"OK",
    "sg:tags":[
        "greenhouse"
    ],
    "sg:website":"www.marcumsnursery.com",
    "wof:name":"Marcum's Nursery",
    "wof:placetype":"venue"
},
  "geometry": {"coordinates":[-97.549564,35.348848],"type":"Point"}
}