{
  "type": "Feature",
  "properties": {
    "iso:country":"US",
    "sg:address":"303 Martin Dale Ln",
    "sg:city":"Pocola",
    "sg:classifiers":[
        {
            "category":"Organizations",
            "subcategory":"Religious Organization",
            "type":"Services"
        }
    ],
    "sg:phone":"+1 918 436 7012",
    "sg:postcode":"74902",
    "sg:province":"OK",
    "sg:tags":[
        "church"
    ],
    "wof:name":"First Baptist Church",
    "wof:placetype":"venue"
},
  "geometry": {"coordinates":[-94.487109,35.22708],"type":"Point"}
}