{
  "type": "Feature",
  "properties": {
    "iso:country":"US",
    "sg:address":"60597 E 130 Rd",
    "sg:city":"Miami",
    "sg:classifiers":[
        {
            "category":"Organizations",
            "subcategory":"Religious Organization",
            "type":"Services"
        }
    ],
    "sg:phone":"+1 918 542 2489",
    "sg:postcode":"74354",
    "sg:province":"OK",
    "wof:name":"Whispering Hills Church Christ",
    "wof:placetype":"venue"
},
  "geometry": {"coordinates":[-94.795063,36.827653],"type":"Point"}
}