{
  "type": "Feature",
  "properties": {
    "addr:full":"121 SW 5th St Guymon OK 73942",
    "addr:housenumber":"121",
    "addr:postcode":"73942",
    "addr:street":"Sw 5Th St",
    "iso:country":"US",
    "sg:address":"121 SW 5th St",
    "sg:city":"Guymon",
    "sg:classifiers":[
        {
            "category":"Retail",
            "subcategory":"Auto Repair",
            "type":"Services"
        },
        {
            "category":"Autos & Motor Vehicles",
            "subcategory":"Auto Supplies",
            "type":"Retail Goods"
        }
    ],
    "sg:phone":"+1 580 338 7453",
    "sg:postcode":"73942",
    "sg:province":"OK",
    "sg:tags":[
        "exhaust",
        "tire"
    ],
    "wof:name":"Fenton Ralph Muffler & Tire",
    "wof:placetype":"venue"
},
  "geometry": {"coordinates":[-101.481961,36.67486],"type":"Point"}
}