{
  "type": "Feature",
  "properties": {
    "addr:full":"461 N Wilson St Vinita OK 74301",
    "addr:housenumber":"461",
    "addr:postcode":"74301",
    "addr:street":"N Wilson St",
    "iso:country":"US",
    "sg:address":"461 N Wilson St",
    "sg:city":"Vinita",
    "sg:classifiers":[
        {
            "category":"Retail",
            "subcategory":"Car Wash",
            "type":"Services"
        }
    ],
    "sg:phone":"+1 918 256 3157",
    "sg:postcode":"74301",
    "sg:province":"OK",
    "sg:tags":[
        "polishing",
        "washing"
    ],
    "wof:name":"Mc Spadden Car Wash",
    "wof:placetype":"venue"
},
  "geometry": {"coordinates":[-95.15029199999999,36.64605],"type":"Point"}
}