{
  "type": "Feature",
  "properties": {
    "iso:country":"US",
    "sg:address":"2918 N Macarthur Blvd",
    "sg:city":"Oklahoma City",
    "sg:classifiers":[
        {
            "category":"Personal",
            "subcategory":"Beauty Salon",
            "type":"Services"
        }
    ],
    "sg:phone":"+1 405 949 2002",
    "sg:postcode":"73127",
    "sg:province":"OK",
    "sg:tags":[
        "shop"
    ],
    "wof:name":"Hair Odyssey 2002",
    "wof:placetype":"venue"
},
  "geometry": {"coordinates":[-97.618932,35.499397],"type":"Point"}
}