{
  "type": "Feature",
  "properties": {
    "iso:country":"US",
    "sg:address":"117 W Main St",
    "sg:city":"Chouteau",
    "sg:classifiers":[
        {
            "category":"Personal",
            "subcategory":"Beauty Salon",
            "type":"Services"
        }
    ],
    "sg:phone":"+1 918 476 8421",
    "sg:postcode":"74337",
    "sg:province":"OK",
    "sg:tags":[
        "shop"
    ],
    "wof:name":"Gail's Beauty Shop",
    "wof:placetype":"venue"
},
  "geometry": {"coordinates":[-95.34552,36.186573],"type":"Point"}
}