{
  "type": "Feature",
  "properties": {
    "iso:country":"US",
    "sg:address":"233 E 10th Street Plz",
    "sg:city":"Edmond",
    "sg:classifiers":[
        {
            "category":"Health Services",
            "subcategory":"Doctor",
            "type":"Services"
        }
    ],
    "sg:phone":"+1 405 341 6134",
    "sg:postcode":"73034",
    "sg:province":"OK",
    "sg:tags":[
        "clinic"
    ],
    "wof:name":"W Scott Waugh Inc",
    "wof:placetype":"venue"
},
  "geometry": {"coordinates":[-97.47715599999999,35.642939],"type":"Point"}
}