{
  "type": "Feature",
  "properties": {
    "addr:full":"1146 NW Cache Rd Lawton OK 73507",
    "addr:housenumber":"1146",
    "addr:postcode":"73507",
    "addr:street":"Nw Cache Rd",
    "iso:country":"US",
    "sg:address":"1146 NW Cache Rd",
    "sg:city":"Lawton",
    "sg:classifiers":[
        {
            "category":"Banks & Credit Unions",
            "subcategory":"Bank",
            "type":"Services"
        }
    ],
    "sg:phone":"+1 580 248 3723",
    "sg:postcode":"73507",
    "sg:province":"OK",
    "sg:tags":[
        "mortgage"
    ],
    "wof:name":"Wells Fargo",
    "wof:placetype":"venue"
},
  "geometry": {"coordinates":[-98.40975899999999,34.623129],"type":"Point"}
}