{
  "type": "Feature",
  "properties": {
    "iso:country":"US",
    "sg:address":"2200 Tanglewood Dr",
    "sg:city":"Edmond",
    "sg:classifiers":[
        {
            "category":"Shopping",
            "subcategory":"Used Merchandise",
            "type":"Retail Goods"
        }
    ],
    "sg:phone":"+1 405 919 8590",
    "sg:postcode":"73013",
    "sg:province":"OK",
    "sg:tags":[
        "commerce",
        "e",
        "reseller",
        "to",
        "computer",
        "profits"
    ],
    "wof:name":"Nwm Enterprises LLC",
    "wof:placetype":"venue"
},
  "geometry": {"coordinates":[-97.509165,35.632928],"type":"Point"}
}