{
  "type": "Feature",
  "properties": {
    "iso:country":"US",
    "sg:address":"4509 SW Cherokee Ave",
    "sg:city":"Lawton",
    "sg:classifiers":[
        {
            "category":"Building & Trades",
            "subcategory":"Construction",
            "type":"Services"
        }
    ],
    "sg:phone":"+1 580 248 9630",
    "sg:postcode":"73505",
    "sg:province":"OK",
    "sg:tags":[
        "hanging",
        "contractor"
    ],
    "wof:name":"Sunray Painting Company",
    "wof:placetype":"venue"
},
  "geometry": {"coordinates":[-98.45131499999999,34.603889],"type":"Point"}
}