{
  "type": "Feature",
  "properties": {
    "addr:full":"2444 N Columbia Pl Tulsa OK 74110",
    "addr:housenumber":"2444",
    "addr:postcode":"74110",
    "addr:street":"N Columbia Pl",
    "iso:country":"US",
    "sg:address":"2444 N Columbia Pl",
    "sg:city":"Tulsa",
    "sg:classifiers":[
        {
            "category":"Manufacturing",
            "subcategory":"Tools & Machinery",
            "type":"Manufacturing & Wholesale Goods"
        }
    ],
    "sg:phone":"+1 918 835 4111",
    "sg:postcode":"74110",
    "sg:province":"OK",
    "sg:tags":[
        "machine",
        "shop"
    ],
    "sg:website":"www.specialtycomp.com",
    "wof:name":"Specialty Components Inc",
    "wof:placetype":"venue"
},
  "geometry": {"coordinates":[-95.950478,36.188288],"type":"Point"}
}