{
  "type": "Feature",
  "properties": {
    "iso:country":"US",
    "sg:address":"8166 E 44th St",
    "sg:city":"Tulsa",
    "sg:classifiers":[
        {
            "category":"Professional",
            "subcategory":"Computer Services",
            "type":"Services"
        }
    ],
    "sg:phone":"+1 918 622 1919",
    "sg:postcode":"74145",
    "sg:province":"OK",
    "sg:tags":[
        "consultant",
        "designer"
    ],
    "wof:name":"Infinite Business Solutions",
    "wof:placetype":"venue"
},
  "geometry": {"coordinates":[-95.881474,36.09936],"type":"Point"}
}