{
  "type": "Feature",
  "properties": {
    "iso:country":"US",
    "sg:address":"3439 W Main St",
    "sg:city":"Norman",
    "sg:classifiers":[
        {
            "category":"Restaurant",
            "type":"Food & Drink"
        }
    ],
    "sg:menulink":"http://www.allmenus.com/ok/norman/4640-el-chico/menu/",
    "sg:phone":"+1 405 360 2146",
    "sg:postcode":"73072",
    "sg:province":"OK",
    "sg:tags":[
        "american",
        "mexican",
        "tex-mex"
    ],
    "wof:name":"El Chico",
    "wof:placetype":"venue"
},
  "geometry": {"coordinates":[-97.49221900000001,35.218494],"type":"Point"}
}