{
  "type": "Feature",
  "properties": {
    "iso:country":"US",
    "sg:address":"5405 E 13th St",
    "sg:city":"Tulsa",
    "sg:classifiers":[
        {
            "category":"Building & Trades",
            "subcategory":"Pest Control",
            "type":"Services"
        }
    ],
    "sg:phone":"+1 918 832 0439",
    "sg:postcode":"74112",
    "sg:province":"OK",
    "wof:name":"Bladerunner Lawn & Landscape",
    "wof:placetype":"venue"
},
  "geometry": {"coordinates":[-95.915793,36.144281],"type":"Point"}
}