{
  "type": "Feature",
  "properties": {
    "iso:country":"US",
    "sg:address":"205 S Santa Fe Ave",
    "sg:city":"Edmond",
    "sg:classifiers":[
        {
            "category":"Professional",
            "subcategory":"Business Services",
            "type":"Services"
        }
    ],
    "sg:phone":"+1 405 216 8644",
    "sg:postcode":"73003",
    "sg:province":"OK",
    "sg:tags":[
        "interior",
        "consultant",
        "design",
        "decorator"
    ],
    "wof:name":"JCAT Home Decor",
    "wof:placetype":"venue"
},
  "geometry": {"coordinates":[-97.514025,35.652465],"type":"Point"}
}