{
  "type": "Feature",
  "properties": {
    "iso:country":"US",
    "sg:address":"1913 W Tacoma St",
    "sg:city":"Broken Arrow",
    "sg:classifiers":[
        {
            "category":"Building & Trades",
            "subcategory":"Equipment Rental",
            "type":"Services"
        }
    ],
    "sg:phone":"+1 918 251 1037",
    "sg:postcode":"74012",
    "sg:province":"OK",
    "sg:tags":[
        "leasing"
    ],
    "wof:name":"Transco Lines Inc",
    "wof:placetype":"venue"
},
  "geometry": {"coordinates":[-95.812839,36.071105],"type":"Point"}
}