{
  "type": "Feature",
  "properties": {
    "iso:country":"US",
    "sg:address":"1325 N Janeway Ave",
    "sg:city":"Moore",
    "sg:classifiers":[
        {
            "category":"Restaurant",
            "type":"Food & Drink"
        }
    ],
    "sg:phone":"+1 405 794 7556",
    "sg:postcode":"73160",
    "sg:province":"OK",
    "sg:tags":[
        "parlor",
        "ice",
        "cream"
    ],
    "wof:name":"Summer Snow",
    "wof:placetype":"venue"
},
  "geometry": {"coordinates":[-97.503088,35.34984],"type":"Point"}
}