{
  "type": "Feature",
  "properties": {
    "addr:full":"2416 N Quaker Ave Tulsa OK 74106",
    "addr:housenumber":"2416",
    "addr:postcode":"74106",
    "addr:street":"N Quaker Ave",
    "iso:country":"US",
    "sg:address":"2416 N Quaker Ave",
    "sg:city":"Tulsa",
    "sg:classifiers":[
        {
            "category":"Shopping",
            "subcategory":"Beauty & Cosmetics",
            "type":"Retail Goods"
        }
    ],
    "sg:phone":"+1 918 428 1175",
    "sg:postcode":"74106",
    "sg:province":"OK",
    "sg:tags":[
        "hair",
        "aid",
        "product"
    ],
    "wof:name":"Legacy Beauty Supply",
    "wof:placetype":"venue"
},
  "geometry": {"coordinates":[-95.97451,36.189358],"type":"Point"}
}