{
  "type": "Feature",
  "properties": {
    "iso:country":"US",
    "sg:address":"6901 S Yorktown Ave",
    "sg:city":"Tulsa",
    "sg:classifiers":[
        {
            "category":"Professional",
            "subcategory":"Lawyer & Legal Services",
            "type":"Services"
        }
    ],
    "sg:phone":"+1 918 743 1912",
    "sg:postcode":"74136",
    "sg:province":"OK",
    "sg:tags":[
        "attorney"
    ],
    "wof:name":"Matthews & Assoc Attys PC",
    "wof:placetype":"venue"
},
  "geometry": {"coordinates":[-95.960697,36.06081],"type":"Point"}
}