{
  "type": "Feature",
  "properties": {
    "addr:full":"452 E Indiana Ave Enid OK 73701",
    "addr:housenumber":"452",
    "addr:postcode":"73701",
    "addr:street":"E Indiana Ave",
    "iso:country":"US",
    "sg:address":"452 E Indiana Ave",
    "sg:city":"Enid",
    "sg:classifiers":[
        {
            "category":"Organizations",
            "subcategory":"Religious Organization",
            "type":"Services"
        }
    ],
    "sg:phone":"+1 580 234 4461",
    "sg:postcode":"73701",
    "sg:province":"OK",
    "sg:tags":[
        "church"
    ],
    "wof:name":"New Light Baptist Church",
    "wof:placetype":"venue"
},
  "geometry": {"coordinates":[-97.87125899999999,36.3872],"type":"Point"}
}