{
  "type": "Feature",
  "properties": {
    "iso:country":"US",
    "sg:address":"10 N Broadway St",
    "sg:city":"Broken Bow",
    "sg:classifiers":[
        {
            "category":"Wholesale",
            "subcategory":"Construction Materials",
            "type":"Manufacturing & Wholesale Goods"
        }
    ],
    "sg:phone":"+1 580 584 7263",
    "sg:postcode":"74728",
    "sg:province":"OK",
    "sg:tags":[
        "sand",
        "gravel"
    ],
    "wof:name":"Broken Bow Sand & Gravel Inc",
    "wof:placetype":"venue"
},
  "geometry": {"coordinates":[-94.73824999999999,34.027292],"type":"Point"}
}