{
  "type": "Feature",
  "properties": {
    "iso:country":"US",
    "sg:address":"101 W Main St",
    "sg:city":"Holdenville",
    "sg:classifiers":[
        {
            "category":"Banks & Credit Unions",
            "subcategory":"Bank",
            "type":"Services"
        }
    ],
    "sg:phone":"+1 405 379 7201",
    "sg:postcode":"74848",
    "sg:province":"OK",
    "sg:tags":[
        "loan"
    ],
    "wof:name":"Security Finance Corp",
    "wof:placetype":"venue"
},
  "geometry": {"coordinates":[-96.402249,35.08358],"type":"Point"}
}