{
  "type": "Feature",
  "properties": {
    "addr:full":"3400 E Frank Phillips Blvd Bartlesville OK 74006",
    "addr:housenumber":"3400",
    "addr:postcode":"74006",
    "addr:street":"E Frank Phillips Blvd",
    "iso:country":"US",
    "sg:address":"3400 E Frank Phillips Blvd",
    "sg:city":"Bartlesville",
    "sg:classifiers":[
        {
            "category":"Health Services",
            "subcategory":"Doctor",
            "type":"Services"
        }
    ],
    "sg:phone":"+1 918 333 9388",
    "sg:postcode":"74006",
    "sg:province":"OK",
    "sg:tags":[
        "physician",
        "surgeon"
    ],
    "wof:name":"Eric J Fu Inc",
    "wof:placetype":"venue"
},
  "geometry": {"coordinates":[-95.940699,36.750618],"type":"Point"}
}