{
  "type": "Feature",
  "properties": {
    "addr:full":"4902 S Sheridan Rd Tulsa OK 74145",
    "addr:housenumber":"4902",
    "addr:postcode":"74145",
    "addr:street":"S Sheridan Rd",
    "iso:country":"US",
    "sg:address":"4902 S Sheridan Rd",
    "sg:city":"Tulsa",
    "sg:classifiers":[
        {
            "category":"Bars & Pubs",
            "type":"Food & Drink"
        }
    ],
    "sg:phone":"+1 918 664 6800",
    "sg:postcode":"74145",
    "sg:province":"OK",
    "wof:name":"Uncle Bentley's Pub & Grill",
    "wof:placetype":"venue"
},
  "geometry": {"coordinates":[-95.904437,36.090298],"type":"Point"}
}