{
  "type": "Feature",
  "properties": {
    "iso:country":"US",
    "sg:address":"715 N Main St",
    "sg:city":"Guymon",
    "sg:classifiers":[
        {
            "category":"Home & Garden",
            "subcategory":"Carpets & Floor Coverings",
            "type":"Retail Goods"
        }
    ],
    "sg:phone":"+1 580 338 7154",
    "sg:postcode":"73942",
    "sg:province":"OK",
    "sg:tags":[
        "furniture"
    ],
    "wof:name":"EDS Carpetland Inc",
    "wof:placetype":"venue"
},
  "geometry": {"coordinates":[-101.48150800000001,36.685058],"type":"Point"}
}