{
  "type": "Feature",
  "properties": {
    "iso:country":"US",
    "sg:address":"908 N Sherry Ave",
    "sg:city":"Norman",
    "sg:classifiers":[
        {
            "category":"Professional",
            "subcategory":"Secretarial Services",
            "type":"Services"
        }
    ],
    "sg:phone":"+1 405 573 9171",
    "sg:postcode":"73069",
    "sg:province":"OK",
    "sg:tags":[
        "reporting"
    ],
    "wof:name":"Carols Med Transcription Svc",
    "wof:placetype":"venue"
},
  "geometry": {"coordinates":[-97.46789099999999,35.229555],"type":"Point"}
}