{
  "type": "Feature",
  "properties": {
    "addr:full":"1016 S Lynn Riggs Blvd Claremore OK 74017",
    "addr:housenumber":"1016",
    "addr:postcode":"74017",
    "addr:street":"S Lynn Riggs Blvd",
    "iso:country":"US",
    "sg:address":"1016 S Lynn Riggs Blvd",
    "sg:city":"Claremore",
    "sg:classifiers":[
        {
            "category":"Shopping",
            "subcategory":"Bicycles & Sporting Goods",
            "type":"Retail Goods"
        },
        {
            "category":"Banks & Credit Unions",
            "subcategory":"Bank",
            "type":"Services"
        }
    ],
    "sg:phone":"+1 918 341 5388",
    "sg:postcode":"74017",
    "sg:province":"OK",
    "sg:tags":[
        "personal",
        "gun",
        "institution",
        "gunsmith"
    ],
    "wof:name":"Bill's Sporting Goods",
    "wof:placetype":"venue"
},
  "geometry": {"coordinates":[-95.625749,36.300094],"type":"Point"}
}