{
  "type": "Feature",
  "properties": {
    "addr:full":"820 W 6th St Skiatook OK 74070",
    "addr:housenumber":"820",
    "addr:postcode":"74070",
    "addr:street":"W 6Th St",
    "iso:country":"US",
    "sg:address":"820 W 6th St",
    "sg:city":"Skiatook",
    "sg:classifiers":[
        {
            "category":"Shopping",
            "subcategory":"Jewelry",
            "type":"Retail Goods"
        }
    ],
    "sg:phone":"+1 918 396 9815",
    "sg:postcode":"74070",
    "sg:province":"OK",
    "wof:name":"Jewelry By Cork",
    "wof:placetype":"venue"
},
  "geometry": {"coordinates":[-96.01262199999999,36.364477],"type":"Point"}
}