{
  "type": "Feature",
  "properties": {
    "iso:country":"US",
    "sg:address":"8 S Adair St",
    "sg:city":"Pryor",
    "sg:classifiers":[
        {
            "category":"Shopping",
            "subcategory":"Used Merchandise",
            "type":"Retail Goods"
        }
    ],
    "sg:phone":"+1 918 825 2747",
    "sg:postcode":"74361",
    "sg:province":"OK",
    "sg:tags":[
        "shop",
        "consignment"
    ],
    "wof:name":"Bran Spankun Uzed",
    "wof:placetype":"venue"
},
  "geometry": {"coordinates":[-95.317129,36.307691],"type":"Point"}
}