{
  "type": "Feature",
  "properties": {
    "addr:full":"5940 Epperly Dr Oklahoma City OK 73135",
    "addr:housenumber":"5940",
    "addr:postcode":"73135",
    "addr:street":"Epperly Dr",
    "iso:country":"US",
    "sg:address":"5940 Epperly Dr",
    "sg:city":"Oklahoma City",
    "sg:classifiers":[
        {
            "category":"Building & Trades",
            "subcategory":"Construction",
            "type":"Services"
        }
    ],
    "sg:phone":"+1 405 672 9100",
    "sg:postcode":"73135",
    "sg:province":"OK",
    "sg:tags":[
        "general",
        "contractor"
    ],
    "wof:name":"L G Construction Co Inc",
    "wof:placetype":"venue"
},
  "geometry": {"coordinates":[-97.43631999999999,35.408426],"type":"Point"}
}