{
  "type": "Feature",
  "properties": {
    "iso:country":"US",
    "sg:address":"1205 Garth Brooks Blvd",
    "sg:city":"Yukon",
    "sg:classifiers":[
        {
            "category":"Restaurant",
            "type":"Food & Drink"
        }
    ],
    "sg:phone":"+1 405 354 6621",
    "sg:postcode":"73099",
    "sg:province":"OK",
    "wof:name":"Harrys American Bar and Grill",
    "wof:placetype":"venue"
},
  "geometry": {"coordinates":[-97.760161,35.496288],"type":"Point"}
}