{
  "type": "Feature",
  "properties": {
    "iso:country":"US",
    "sg:address":"4000 N Rockwell Ave",
    "sg:city":"Bethany",
    "sg:classifiers":[
        {
            "category":"Bars & Pubs",
            "type":"Food & Drink"
        }
    ],
    "sg:menulink":"http://www.allmenus.com/ok/oklahoma-city/219476-swadleys-bar-b-q/menu/",
    "sg:phone":"+1 405 495 5336",
    "sg:postcode":"73008",
    "sg:province":"OK",
    "sg:tags":[
        "barbecue",
        "american"
    ],
    "wof:name":"Swadley's Bar-b-q",
    "wof:placetype":"venue"
},
  "geometry": {"coordinates":[-97.63658700000001,35.511917],"type":"Point"}
}