{
  "type": "Feature",
  "properties": {
    "addr:full":"8209 S New Haven Ave Tulsa OK 74137",
    "addr:housenumber":"8209",
    "addr:postcode":"74137",
    "addr:street":"S New Haven Ave",
    "iso:country":"US",
    "sg:address":"8209 S New Haven Ave",
    "sg:city":"Tulsa",
    "sg:classifiers":[
        {
            "category":"Retail",
            "subcategory":"Auto Repair",
            "type":"Services"
        }
    ],
    "sg:phone":"+1 918 492 3223",
    "sg:postcode":"74137",
    "sg:province":"OK",
    "sg:tags":[
        "equipment",
        "steering",
        "system"
    ],
    "wof:name":"Steering Columns Rebuilt",
    "wof:placetype":"venue"
},
  "geometry": {"coordinates":[-95.933674,36.04238],"type":"Point"}
}