{
  "type": "Feature",
  "properties": {
    "iso:country":"US",
    "sg:address":"6927 E 71st St",
    "sg:city":"Tulsa",
    "sg:classifiers":[
        {
            "category":"Utilities",
            "subcategory":"Mobile Phone",
            "type":"Services"
        },
        {
            "category":"Shopping",
            "type":"Retail Goods"
        }
    ],
    "sg:phone":"+1 918 491 1000",
    "sg:postcode":"74133",
    "sg:province":"OK",
    "sg:tags":[
        "cellular",
        "telephone",
        "merchandise"
    ],
    "wof:name":"Digicom Wireless",
    "wof:placetype":"venue"
},
  "geometry": {"coordinates":[-95.898511,36.060973],"type":"Point"}
}