{
  "type": "Feature",
  "properties": {
    "iso:country":"US",
    "sg:address":"233 S Detroit Ave",
    "sg:city":"Tulsa",
    "sg:classifiers":[
        {
            "category":"Freight",
            "type":"Transportation"
        }
    ],
    "sg:phone":"+1 918 582 2376",
    "sg:postcode":"74120",
    "sg:province":"OK",
    "sg:tags":[
        "trucking"
    ],
    "wof:name":"Ellsworth Motor Freight Lines",
    "wof:placetype":"venue"
},
  "geometry": {"coordinates":[-95.98763,36.154956],"type":"Point"}
}