{
  "type": "Feature",
  "properties": {
    "iso:country":"US",
    "sg:address":"400 S Crawford Ave",
    "sg:city":"Norman",
    "sg:classifiers":[
        {
            "category":"Professional",
            "subcategory":"Lawyer & Legal Services",
            "type":"Services"
        }
    ],
    "sg:phone":"+1 405 364 5551",
    "sg:postcode":"73069",
    "sg:province":"OK",
    "wof:name":"Geronimo Inc",
    "wof:placetype":"venue"
},
  "geometry": {"coordinates":[-97.438096,35.218323],"type":"Point"}
}