{
  "type": "Feature",
  "properties": {
    "iso:country":"US",
    "sg:address":"5115 S Harvard Ave",
    "sg:city":"Tulsa",
    "sg:classifiers":[
        {
            "category":"Coffee & Tea",
            "type":"Food & Drink"
        }
    ],
    "sg:menulink":"http://www.allmenus.com/ok/tulsa/119199-starbucks-coffee/menu/",
    "sg:phone":"+1 918 293 1016",
    "sg:postcode":"74135",
    "sg:province":"OK",
    "sg:tags":[
        "american"
    ],
    "wof:name":"Starbucks Coffee",
    "wof:placetype":"venue"
},
  "geometry": {"coordinates":[-95.939708,36.089014],"type":"Point"}
}