{
  "type": "Feature",
  "properties": {
    "addr:full":"119 W Trudgeon St Henryetta OK 74437",
    "addr:housenumber":"119",
    "addr:postcode":"74437",
    "addr:street":"W Trudgeon St",
    "iso:country":"US",
    "sg:address":"119 W Trudgeon St",
    "sg:city":"Henryetta",
    "sg:classifiers":[
        {
            "category":"Food & Beverages",
            "subcategory":"Liquor & Beverages",
            "type":"Retail Goods"
        }
    ],
    "sg:phone":"+1 918 652 7422",
    "sg:postcode":"74437",
    "sg:province":"OK",
    "wof:name":"Rainbow Liquor Store",
    "wof:placetype":"venue"
},
  "geometry": {"coordinates":[-95.982161,35.440812],"type":"Point"}
}