{
  "type": "Feature",
  "properties": {
    "iso:country":"US",
    "sg:address":"7 N Washington St",
    "sg:city":"Ardmore",
    "sg:classifiers":[
        {
            "category":"Banks & Credit Unions",
            "subcategory":"Bank",
            "type":"Services"
        }
    ],
    "sg:phone":"+1 580 226 2300",
    "sg:postcode":"73401",
    "sg:province":"OK",
    "sg:tags":[
        "loan",
        "institution",
        "business"
    ],
    "wof:name":"King Finance Co",
    "wof:placetype":"venue"
},
  "geometry": {"coordinates":[-97.127711,34.17413],"type":"Point"}
}