{
  "type": "Feature",
  "properties": {
    "iso:country":"US",
    "sg:address":"3752 W 45th Pl",
    "sg:city":"Tulsa",
    "sg:classifiers":[
        {
            "category":"Building & Trades",
            "subcategory":"Construction",
            "type":"Services"
        }
    ],
    "sg:phone":"+1 918 446 1776",
    "sg:postcode":"74107",
    "sg:province":"OK",
    "sg:tags":[
        "contractor"
    ],
    "wof:name":"Ostrander Construction",
    "wof:placetype":"venue"
},
  "geometry": {"coordinates":[-96.036573,36.097612],"type":"Point"}
}