{
  "type": "Feature",
  "properties": {
    "iso:country":"US",
    "sg:address":"12225 Westgate Dr",
    "sg:city":"Yukon",
    "sg:classifiers":[
        {
            "category":"Sports & Exercise",
            "subcategory":"Race Track",
            "type":"Entertainment"
        }
    ],
    "sg:phone":"+1 405 324 8380",
    "sg:postcode":"73099",
    "sg:province":"OK",
    "sg:tags":[
        "operation",
        "racing",
        "or",
        "supply"
    ],
    "wof:name":"Miller Motor Sports",
    "wof:placetype":"venue"
},
  "geometry": {"coordinates":[-97.749173,35.453654],"type":"Point"}
}