{
  "type": "Feature",
  "properties": {
    "iso:country":"US",
    "sg:address":"207 W Division St",
    "sg:city":"Stilwell",
    "sg:classifiers":[
        {
            "category":"Real Estate",
            "subcategory":"Real Estate Services",
            "type":"Services"
        }
    ],
    "sg:phone":"+1 918 696 7796",
    "sg:postcode":"74960",
    "sg:province":"OK",
    "sg:tags":[
        "management"
    ],
    "wof:name":"Langley Insurance",
    "wof:placetype":"venue"
},
  "geometry": {"coordinates":[-94.628509,35.81454],"type":"Point"}
}