{
  "type": "Feature",
  "properties": {
    "addr:full":"528 SW D Ave Lawton OK 73501",
    "addr:housenumber":"528",
    "addr:postcode":"73501",
    "addr:street":"Sw D Ave",
    "iso:country":"US",
    "sg:address":"528 SW D Ave",
    "sg:city":"Lawton",
    "sg:classifiers":[
        {
            "category":"Manufacturing",
            "subcategory":"Tools & Machinery",
            "type":"Manufacturing & Wholesale Goods"
        }
    ],
    "sg:phone":"+1 580 357 5060",
    "sg:postcode":"73501",
    "sg:province":"OK",
    "sg:tags":[
        "industry",
        "aerospace"
    ],
    "wof:name":"Lockheed Martin Corp",
    "wof:placetype":"venue"
},
  "geometry": {"coordinates":[-98.39637,34.60394],"type":"Point"}
}