{
  "type": "Feature",
  "properties": {
    "iso:country":"US",
    "sg:address":"101 E Walnut St",
    "sg:city":"Tecumseh",
    "sg:classifiers":[
        {
            "category":"Restaurant",
            "type":"Food & Drink"
        }
    ],
    "sg:menulink":"http://www.allmenus.com/ok/shawnee/144321-subway/menu/",
    "sg:phone":"+1 405 598 2630",
    "sg:postcode":"74873",
    "sg:province":"OK",
    "sg:tags":[
        "american",
        "sandwich"
    ],
    "wof:name":"Subway",
    "wof:placetype":"venue"
},
  "geometry": {"coordinates":[-96.93678199999999,35.260737],"type":"Point"}
}