{
  "type": "Feature",
  "properties": {
    "addr:full":"7613 E 181st St S Bixby OK 74008",
    "addr:housenumber":"7613",
    "addr:postcode":"74008",
    "addr:street":"E 181St St S",
    "iso:country":"US",
    "sg:address":"7613 E 181st St S",
    "sg:city":"Bixby",
    "sg:classifiers":[
        {
            "category":"Home & Garden",
            "subcategory":"Building Materials",
            "type":"Retail Goods"
        }
    ],
    "sg:phone":"+1 918 366 3520",
    "sg:postcode":"74008",
    "sg:province":"OK",
    "sg:tags":[
        "glass",
        "window",
        "plate"
    ],
    "wof:name":"Southside Supply",
    "wof:placetype":"venue"
},
  "geometry": {"coordinates":[-95.89604,35.901194],"type":"Point"}
}