{
  "type": "Feature",
  "properties": {
    "iso:country":"US",
    "sg:address":"209 Mohawk Blvd",
    "sg:city":"Tulsa",
    "sg:classifiers":[
        {
            "category":"Personal",
            "subcategory":"Beauty Salon",
            "type":"Services"
        }
    ],
    "sg:phone":"+1 918 430 1500",
    "sg:postcode":"74106",
    "sg:province":"OK",
    "wof:name":"Krashawn N Friends Style Shop",
    "wof:placetype":"venue"
},
  "geometry": {"coordinates":[-95.989093,36.192579],"type":"Point"}
}