{
  "type": "Feature",
  "properties": {
    "iso:country":"US",
    "sg:address":"6775 Boucher Dr",
    "sg:city":"Edmond",
    "sg:classifiers":[
        {
            "category":"Retail",
            "subcategory":"Auto Repair",
            "type":"Services"
        }
    ],
    "sg:phone":"+1 405 715 1968",
    "sg:postcode":"73034",
    "sg:province":"OK",
    "sg:tags":[
        "repairing",
        "automobile"
    ],
    "sg:website":"www.redearthmotorsports.com",
    "wof:name":"Redearth Motor Sports",
    "wof:placetype":"venue"
},
  "geometry": {"coordinates":[-97.41986300000001,35.724186],"type":"Point"}
}