{
  "type": "Feature",
  "properties": {
    "iso:country":"US",
    "sg:address":"2605 NE Lake Ave",
    "sg:city":"Lawton",
    "sg:classifiers":[
        {
            "category":"Personal",
            "subcategory":"Beauty Salon",
            "type":"Services"
        }
    ],
    "sg:phone":"+1 580 357 5290",
    "sg:postcode":"73507",
    "sg:province":"OK",
    "sg:tags":[
        "shop"
    ],
    "wof:name":"Dees House of Charm",
    "wof:placetype":"venue"
},
  "geometry": {"coordinates":[-98.354313,34.610775],"type":"Point"}
}