{
  "type": "Feature",
  "properties": {
    "iso:country":"US",
    "sg:address":"26 E 33rd St",
    "sg:city":"Edmond",
    "sg:classifiers":[
        {
            "category":"Restaurant",
            "type":"Food & Drink"
        }
    ],
    "sg:menulink":"http://www.allmenus.com/ok/oklahoma-city/214000-taco-bell/menu/",
    "sg:phone":"+1 405 330 4640",
    "sg:postcode":"73013",
    "sg:province":"OK",
    "sg:tags":[
        "mexican"
    ],
    "wof:name":"Taco Bell",
    "wof:placetype":"venue"
},
  "geometry": {"coordinates":[-97.484054,35.623158],"type":"Point"}
}