{
  "type": "Feature",
  "properties": {
    "addr:full":"1414 S Santa Fe Ave Edmond OK 73003",
    "addr:housenumber":"1414",
    "addr:postcode":"73003",
    "addr:street":"S Santa Fe Ave",
    "iso:country":"US",
    "sg:address":"1414 S Santa Fe Ave",
    "sg:city":"Edmond",
    "sg:classifiers":[
        {
            "category":"Food & Beverages",
            "subcategory":"Groceries & Convenience Stores",
            "type":"Retail Goods"
        }
    ],
    "sg:phone":"+1 405 844 4547",
    "sg:postcode":"73003",
    "sg:province":"OK",
    "wof:name":"Flash Mart 1",
    "wof:placetype":"venue"
},
  "geometry": {"coordinates":[-97.513847,35.638359],"type":"Point"}
}