{
  "type": "Feature",
  "properties": {
    "iso:country":"US",
    "sg:address":"2 Cll Laventa",
    "sg:city":"Shawnee",
    "sg:classifiers":[
        {
            "category":"Wholesale",
            "subcategory":"Chemicals & Plastics",
            "type":"Manufacturing & Wholesale Goods"
        }
    ],
    "sg:phone":"+1 405 395 0017",
    "sg:postcode":"74801",
    "sg:province":"OK",
    "wof:name":"Dairy Partners",
    "wof:placetype":"venue"
},
  "geometry": {"coordinates":[-96.992474,35.393842],"type":"Point"}
}