{
  "type": "Feature",
  "properties": {
    "iso:country":"US",
    "sg:address":"1405 N 4th Ave",
    "sg:city":"Durant",
    "sg:classifiers":[
        {
            "category":"Organizations",
            "subcategory":"Non-profit Organization",
            "type":"Services"
        }
    ],
    "sg:phone":"+1 580 920 1061",
    "sg:postcode":"74701",
    "sg:province":"OK",
    "sg:tags":[
        "social"
    ],
    "wof:name":"South Eastrn Eldrcre/Bryan CNT",
    "wof:placetype":"venue"
},
  "geometry": {"coordinates":[-96.376423,34.0042],"type":"Point"}
}