{
  "type": "Feature",
  "properties": {
    "addr:full":"15 Ridgecrest Dr Chickasha OK 73018",
    "addr:housenumber":"15",
    "addr:postcode":"73018",
    "addr:street":"Ridgecrest Dr",
    "iso:country":"US",
    "sg:address":"15 Ridgecrest Dr",
    "sg:city":"Chickasha",
    "sg:classifiers":[
        {
            "category":"Freight",
            "type":"Transportation"
        }
    ],
    "sg:phone":"+1 405 222 1846",
    "sg:postcode":"73018",
    "sg:province":"OK",
    "sg:tags":[
        "operator",
        "local",
        "trucking"
    ],
    "wof:name":"Wagner Trucking",
    "wof:placetype":"venue"
},
  "geometry": {"coordinates":[-97.960414,35.02493],"type":"Point"}
}