{
  "type": "Feature",
  "properties": {
    "iso:country":"US",
    "sg:address":"219 N Main St",
    "sg:city":"Quapaw",
    "sg:classifiers":[
        {
            "category":"Food & Beverages",
            "subcategory":"Groceries & Convenience Stores",
            "type":"Retail Goods"
        }
    ],
    "sg:phone":"+1 918 674 2397",
    "sg:postcode":"74363",
    "sg:province":"OK",
    "wof:name":"Quapaw Express",
    "wof:placetype":"venue"
},
  "geometry": {"coordinates":[-94.787924,36.957193],"type":"Point"}
}