{
  "type": "Feature",
  "properties": {
    "iso:country":"US",
    "sg:address":"105 N Hudson Ave",
    "sg:city":"Oklahoma City",
    "sg:classifiers":[
        {
            "category":"Mining & Drilling",
            "type":"Manufacturing & Wholesale Goods"
        }
    ],
    "sg:phone":"+1 405 232 9541",
    "sg:postcode":"73102",
    "sg:province":"OK",
    "sg:tags":[
        "field"
    ],
    "wof:name":"ME Oil Co",
    "wof:placetype":"venue"
},
  "geometry": {"coordinates":[-97.519593,35.468408],"type":"Point"}
}