{
  "type": "Feature",
  "properties": {
    "iso:country":"US",
    "sg:address":"341 S 33rd St",
    "sg:city":"Muskogee",
    "sg:classifiers":[
        {
            "category":"Health Services",
            "subcategory":"Doctor",
            "type":"Services"
        }
    ],
    "sg:phone":"+1 918 682 1122",
    "sg:postcode":"74401",
    "sg:province":"OK",
    "sg:tags":[
        "physician",
        "surgeon",
        "medical"
    ],
    "wof:name":"Oklahoma Oncology Inc",
    "wof:placetype":"venue"
},
  "geometry": {"coordinates":[-95.403584,35.751756],"type":"Point"}
}