{
  "type": "Feature",
  "properties": {
    "iso:country":"US",
    "sg:address":"225 US Hwy 54",
    "sg:city":"Guymon",
    "sg:classifiers":[
        {
            "category":"Organizations",
            "subcategory":"Non-profit Organization",
            "type":"Services"
        }
    ],
    "sg:phone":"+1 580 338 1005",
    "sg:postcode":"73942",
    "sg:province":"OK",
    "wof:name":"ORO Development Corp",
    "wof:placetype":"venue"
},
  "geometry": {"coordinates":[-101.483104,36.677442],"type":"Point"}
}