{
  "type": "Feature",
  "properties": {
    "iso:country":"US",
    "sg:address":"216 N 7th St",
    "sg:city":"Duncan",
    "sg:classifiers":[
        {
            "category":"Retail",
            "subcategory":"Repair Shop",
            "type":"Services"
        }
    ],
    "sg:phone":"+1 580 255 2620",
    "sg:postcode":"73533",
    "sg:province":"OK",
    "sg:tags":[
        "television",
        "radio"
    ],
    "wof:name":"Karl's Trading Post",
    "wof:placetype":"venue"
},
  "geometry": {"coordinates":[-97.955102,34.503793],"type":"Point"}
}