{
  "type": "Feature",
  "properties": {
    "iso:country":"US",
    "sg:address":"900 N Fretz Ave",
    "sg:city":"Edmond",
    "sg:classifiers":[
        {
            "category":"Professional",
            "subcategory":"Advertising",
            "type":"Services"
        }
    ],
    "sg:phone":"+1 405 359 5818",
    "sg:postcode":"73003",
    "sg:province":"OK",
    "sg:tags":[
        "distribution"
    ],
    "wof:name":"Hayes Distributing",
    "wof:placetype":"venue"
},
  "geometry": {"coordinates":[-97.487026,35.663207],"type":"Point"}
}