{
  "type": "Feature",
  "properties": {
    "iso:country":"US",
    "sg:address":"10017 S Allen Dr",
    "sg:city":"Oklahoma City",
    "sg:classifiers":[
        {
            "category":"Building & Trades",
            "subcategory":"Construction",
            "type":"Services"
        }
    ],
    "sg:phone":"+1 405 692 4464",
    "sg:postcode":"73139",
    "sg:province":"OK",
    "sg:tags":[
        "contractor"
    ],
    "wof:name":"Cupps Drywall",
    "wof:placetype":"venue"
},
  "geometry": {"coordinates":[-97.521955,35.367579],"type":"Point"}
}