{
  "type": "Feature",
  "properties": {
    "addr:full":"135 N Mustang Rd Mustang OK 73064",
    "addr:housenumber":"135",
    "addr:postcode":"73064",
    "addr:street":"N Mustang Rd",
    "iso:country":"US",
    "sg:address":"135 N Mustang Rd",
    "sg:city":"Mustang",
    "sg:classifiers":[
        {
            "category":"Building & Trades",
            "subcategory":"Construction",
            "type":"Services"
        }
    ],
    "sg:phone":"+1 405 376 4474",
    "sg:postcode":"73064",
    "sg:province":"OK",
    "sg:tags":[
        "marking",
        "maintenance",
        "parking"
    ],
    "wof:name":"Mustang Public Works",
    "wof:placetype":"venue"
},
  "geometry": {"coordinates":[-97.72465699999999,35.391939],"type":"Point"}
}