{
  "type": "Feature",
  "properties": {
    "addr:full":"212 Rosedale Rd Ada OK 74820",
    "addr:housenumber":"212",
    "addr:postcode":"74820",
    "addr:street":"Rosedale Rd",
    "iso:country":"US",
    "sg:address":"212 Rosedale Rd",
    "sg:city":"Ada",
    "sg:classifiers":[
        {
            "category":"Manufacturing",
            "subcategory":"Building Materials",
            "type":"Manufacturing & Wholesale Goods"
        }
    ],
    "sg:phone":"+1 580 332 1988",
    "sg:postcode":"74820",
    "sg:province":"OK",
    "wof:name":"Sooner Millwork",
    "wof:placetype":"venue"
},
  "geometry": {"coordinates":[-96.681059,34.796302],"type":"Point"}
}