{
  "type": "Feature",
  "properties": {
    "iso:country":"US",
    "sg:address":"1805 S Air Depot Blvd",
    "sg:city":"Midwest City",
    "sg:classifiers":[
        {
            "category":"Shopping",
            "subcategory":"Tobacco",
            "type":"Retail Goods"
        }
    ],
    "sg:phone":"+1 405 736 1188",
    "sg:postcode":"73110",
    "sg:province":"OK",
    "sg:tags":[
        "cigarette",
        "cigar",
        "dealer"
    ],
    "wof:name":"Cigarette Express",
    "wof:placetype":"venue"
},
  "geometry": {"coordinates":[-97.40611,35.445598],"type":"Point"}
}