{
  "type": "Feature",
  "properties": {
    "iso:country":"US",
    "sg:address":"701 NE 28th St",
    "sg:city":"Oklahoma City",
    "sg:classifiers":[
        {
            "category":"Organizations",
            "subcategory":"Religious Organization",
            "type":"Services"
        }
    ],
    "sg:phone":"+1 405 525 5568",
    "sg:postcode":"73105",
    "sg:province":"OK",
    "sg:tags":[
        "church"
    ],
    "wof:name":"Good Shepherd Missionary Bapt",
    "wof:placetype":"venue"
},
  "geometry": {"coordinates":[-97.498894,35.498668],"type":"Point"}
}