{
  "type": "Feature",
  "properties": {
    "iso:country":"US",
    "sg:address":"946 N Flood Ave",
    "sg:city":"Norman",
    "sg:classifiers":[
        {
            "category":"Arts & Performance",
            "subcategory":"Theater",
            "type":"Entertainment"
        }
    ],
    "sg:phone":"+1 405 292 7464",
    "sg:postcode":"73069",
    "sg:province":"OK",
    "sg:tags":[
        "group"
    ],
    "wof:name":"Blues Too Karaoke Bar",
    "wof:placetype":"venue"
},
  "geometry": {"coordinates":[-97.453036,35.226245],"type":"Point"}
}