{
  "type": "Feature",
  "properties": {
    "addr:full":"1505 S Sheridan Rd Tulsa OK 74112",
    "addr:housenumber":"1505",
    "addr:postcode":"74112",
    "addr:street":"S Sheridan Rd",
    "iso:country":"US",
    "sg:address":"1505 S Sheridan Rd",
    "sg:city":"Tulsa",
    "sg:classifiers":[
        {
            "category":"Banks & Credit Unions",
            "subcategory":"Bank",
            "type":"Services"
        }
    ],
    "sg:phone":"+1 918 832 7188",
    "sg:postcode":"74112",
    "sg:province":"OK",
    "sg:tags":[
        "loan"
    ],
    "wof:name":"Cash In A Flash",
    "wof:placetype":"venue"
},
  "geometry": {"coordinates":[-95.904482,36.138413],"type":"Point"}
}