{
  "type": "Feature",
  "properties": {
    "iso:country":"US",
    "sg:address":"815 Centennial Blvd",
    "sg:city":"Edmond",
    "sg:classifiers":[
        {
            "category":"Wholesale",
            "subcategory":"Machinery & Supplies",
            "type":"Manufacturing & Wholesale Goods"
        },
        {
            "category":"Building & Trades",
            "subcategory":"Landscaping Services",
            "type":"Services"
        }
    ],
    "sg:phone":"+1 405 330 0066",
    "sg:postcode":"73013",
    "sg:province":"OK",
    "sg:tags":[
        "equipment",
        "irrigation"
    ],
    "wof:name":"Sprinkler Store Inc",
    "wof:placetype":"venue"
},
  "geometry": {"coordinates":[-97.494665,35.628387],"type":"Point"}
}