{
  "type": "Feature",
  "properties": {
    "iso:country":"US",
    "sg:address":"614 NE 16th St",
    "sg:city":"Guymon",
    "sg:classifiers":[
        {
            "category":"Building & Trades",
            "subcategory":"Cleaning & Sanitation",
            "type":"Services"
        }
    ],
    "sg:phone":"+1 580 338 7897",
    "sg:postcode":"73942",
    "sg:province":"OK",
    "sg:tags":[
        "janitor"
    ],
    "wof:name":"David Welch Tax Svc",
    "wof:placetype":"venue"
},
  "geometry": {"coordinates":[-101.473177,36.69398],"type":"Point"}
}