{
  "type": "Feature",
  "properties": {
    "addr:full":"108 24th Ave SW Norman OK 73069",
    "addr:housenumber":"108",
    "addr:postcode":"73069",
    "addr:street":"24Th Ave Sw",
    "iso:country":"US",
    "sg:address":"108 24th Ave SW",
    "sg:city":"Norman",
    "sg:classifiers":[
        {
            "category":"Home & Garden",
            "subcategory":"Building Materials",
            "type":"Retail Goods"
        }
    ],
    "sg:phone":"+1 405 321 0167",
    "sg:postcode":"73069",
    "sg:province":"OK",
    "sg:tags":[
        "paint"
    ],
    "wof:name":"Kelley-Moore Paint Co",
    "wof:placetype":"venue"
},
  "geometry": {"coordinates":[-97.47672799999999,35.217859],"type":"Point"}
}