{
  "type": "Feature",
  "properties": {
    "iso:country":"US",
    "sg:address":"1330 N Classen Blvd",
    "sg:city":"Oklahoma City",
    "sg:classifiers":[
        {
            "category":"Organizations",
            "subcategory":"Non-profit Organization",
            "type":"Services"
        }
    ],
    "sg:phone":"+1 405 604 9092",
    "sg:postcode":"73106",
    "sg:province":"OK",
    "sg:tags":[
        "information",
        "alcoholism",
        "treatment"
    ],
    "wof:name":"Peace Of Mind Counseling Svc",
    "wof:placetype":"venue"
},
  "geometry": {"coordinates":[-97.529349,35.482077],"type":"Point"}
}