{
  "type": "Feature",
  "properties": {
    "iso:country":"US",
    "sg:address":"2750 Browne Ave",
    "sg:city":"Guthrie",
    "sg:classifiers":[
        {
            "category":"Retail",
            "subcategory":"Repair Shop",
            "type":"Services"
        }
    ],
    "sg:phone":"+1 405 282 3218",
    "sg:postcode":"73044",
    "sg:province":"OK",
    "sg:tags":[
        "welding"
    ],
    "wof:name":"Ray's Portable Welding Svc",
    "wof:placetype":"venue"
},
  "geometry": {"coordinates":[-97.390818,35.863519],"type":"Point"}
}