{
  "type": "Feature",
  "properties": {
    "iso:country":"US",
    "sg:address":"1500 E Downing St",
    "sg:city":"Tahlequah",
    "sg:classifiers":[
        {
            "category":"Shopping",
            "subcategory":"Pharmacy",
            "type":"Retail Goods"
        }
    ],
    "sg:phone":"+1 918 456 8811",
    "sg:postcode":"74464",
    "sg:province":"OK",
    "wof:name":"Birds TMC Pharmacy",
    "wof:placetype":"venue"
},
  "geometry": {"coordinates":[-94.947756,35.915417],"type":"Point"}
}