{
  "type": "Feature",
  "properties": {
    "addr:full":"501 W Elm Ave Stillwater OK 74074",
    "addr:housenumber":"501",
    "addr:postcode":"74074",
    "addr:street":"W Elm Ave",
    "iso:country":"US",
    "sg:address":"501 W Elm Ave",
    "sg:city":"Stillwater",
    "sg:classifiers":[
        {
            "category":"Restaurant",
            "type":"Food & Drink"
        }
    ],
    "sg:menulink":"http://www.allmenus.com/ok/stillwater/224744-eskimo-joes-kitchen/menu/",
    "sg:phone":"+1 405 372 8896",
    "sg:postcode":"74074",
    "sg:province":"OK",
    "sg:tags":[
        "american"
    ],
    "wof:name":"Eskimo Joe's Kitchen",
    "wof:placetype":"venue"
},
  "geometry": {"coordinates":[-97.063895,36.122198],"type":"Point"}
}