{
  "type": "Feature",
  "properties": {
    "addr:full":"321 N Main St Cement OK 73017",
    "addr:housenumber":"321",
    "addr:postcode":"73017",
    "addr:street":"N Main St",
    "iso:country":"US",
    "sg:address":"321 N Main St",
    "sg:city":"Cement",
    "sg:classifiers":[
        {
            "category":"Personal",
            "subcategory":"Beauty Salon",
            "type":"Services"
        }
    ],
    "sg:phone":"+1 405 489 7166",
    "sg:postcode":"73017",
    "sg:province":"OK",
    "wof:name":"Head To Toe",
    "wof:placetype":"venue"
},
  "geometry": {"coordinates":[-98.140156,34.934584],"type":"Point"}
}