{
  "type": "Feature",
  "properties": {
    "iso:country":"US",
    "sg:address":"1326 NW 12th St",
    "sg:city":"Oklahoma City",
    "sg:classifiers":[
        {
            "category":"Banks & Credit Unions",
            "subcategory":"Bank",
            "type":"Services"
        }
    ],
    "sg:phone":"+1 405 895 6677",
    "sg:postcode":"73106",
    "sg:province":"OK",
    "sg:tags":[
        "loan",
        "real estate"
    ],
    "wof:name":"Mortgage Pros",
    "wof:placetype":"venue"
},
  "geometry": {"coordinates":[-97.534151,35.481641],"type":"Point"}
}