{
  "type": "Feature",
  "properties": {
    "addr:full":"426 S Main St Lindsay OK 73052",
    "addr:housenumber":"426",
    "addr:postcode":"73052",
    "addr:street":"S Main St",
    "iso:country":"US",
    "sg:address":"426 S Main St",
    "sg:city":"Lindsay",
    "sg:classifiers":[
        {
            "category":"Government",
            "subcategory":"Post Office",
            "type":"Public Place"
        }
    ],
    "sg:phone":"+1 405 000 1111",
    "sg:postcode":"73052",
    "sg:province":"OK",
    "wof:name":"US Post Office",
    "wof:placetype":"venue"
},
  "geometry": {"coordinates":[-97.60279,34.83323],"type":"Point"}
}