{
  "type": "Feature",
  "properties": {
    "addr:full":"1725 Lakewood Dr Norman OK 73026",
    "addr:housenumber":"1725",
    "addr:postcode":"73026",
    "addr:street":"Lakewood Dr",
    "iso:country":"US",
    "sg:address":"1725 Lakewood Dr",
    "sg:city":"Norman",
    "sg:classifiers":[
        {
            "category":"Building & Trades",
            "subcategory":"Electrical",
            "type":"Services"
        }
    ],
    "sg:phone":"+1 405 329 4210",
    "sg:postcode":"73026",
    "sg:province":"OK",
    "sg:tags":[
        "electrical",
        "contractor"
    ],
    "wof:name":"Breakers Electric",
    "wof:placetype":"venue"
},
  "geometry": {"coordinates":[-97.16836499999999,35.239874],"type":"Point"}
}