{
  "type": "Feature",
  "properties": {
    "iso:country":"US",
    "sg:address":"3148 E 11th St",
    "sg:city":"Tulsa",
    "sg:classifiers":[
        {
            "category":"Bars & Pubs",
            "type":"Food & Drink"
        }
    ],
    "sg:phone":"+1 918 583 9663",
    "sg:postcode":"74104",
    "sg:province":"OK",
    "sg:tags":[
        "drinking"
    ],
    "wof:name":"Hardwood",
    "wof:placetype":"venue"
},
  "geometry": {"coordinates":[-95.94288299999999,36.147734],"type":"Point"}
}