{
  "type": "Feature",
  "properties": {
    "iso:country":"US",
    "sg:address":"5206 S Harvard Ave Unit 1",
    "sg:city":"Tulsa",
    "sg:classifiers":[
        {
            "category":"Health Services",
            "subcategory":"Health Practitioner",
            "type":"Services"
        },
        {
            "category":"Communications",
            "type":"Services"
        }
    ],
    "sg:phone":"+1 918 743 3036",
    "sg:postcode":"74135",
    "sg:province":"OK",
    "sg:tags":[
        "pathologist",
        "speech-language",
        "myofunctional",
        "therapy"
    ],
    "wof:name":"Patricia L Deisenroth",
    "wof:placetype":"venue"
},
  "geometry": {"coordinates":[-95.94015,36.08795],"type":"Point"}
}