{
  "type": "Feature",
  "properties": {
    "iso:country":"US",
    "sg:address":"809 W Maine St",
    "sg:city":"Enid",
    "sg:classifiers":[
        {
            "category":"Home & Garden",
            "subcategory":"Household Appliances",
            "type":"Retail Goods"
        }
    ],
    "sg:phone":"+1 580 237 1908",
    "sg:postcode":"73701",
    "sg:province":"OK",
    "sg:tags":[
        "repair"
    ],
    "wof:name":"Southwestern Sewing Supply",
    "wof:placetype":"venue"
},
  "geometry": {"coordinates":[-97.888909,36.395503],"type":"Point"}
}