{
  "type": "Feature",
  "properties": {
    "iso:country":"US",
    "sg:address":"3121 SW 95th St",
    "sg:city":"Oklahoma City",
    "sg:classifiers":[
        {
            "category":"Building & Trades",
            "subcategory":"Plumbing",
            "type":"Services"
        }
    ],
    "sg:phone":"+1 405 692 0890",
    "sg:postcode":"73159",
    "sg:province":"OK",
    "sg:tags":[
        "plumbing",
        "contractor"
    ],
    "wof:name":"Huffman Plumbing Heat & Air",
    "wof:placetype":"venue"
},
  "geometry": {"coordinates":[-97.568388,35.371863],"type":"Point"}
}