{
  "type": "Feature",
  "properties": {
    "iso:country":"US",
    "sg:address":"6929 S Memorial Dr",
    "sg:city":"Tulsa",
    "sg:classifiers":[
        {
            "category":"Manufacturing",
            "subcategory":"Tools & Machinery",
            "type":"Manufacturing & Wholesale Goods"
        }
    ],
    "sg:phone":"+1 918 250 5742",
    "sg:postcode":"74133",
    "sg:province":"OK",
    "sg:tags":[
        "equipment",
        "mfg"
    ],
    "wof:name":"Sears Roebuck",
    "wof:placetype":"venue"
},
  "geometry": {"coordinates":[-95.88624,36.065453],"type":"Point"}
}