{
  "type": "Feature",
  "properties": {
    "iso:country":"US",
    "sg:address":"807 S Lowry St",
    "sg:city":"Stillwater",
    "sg:classifiers":[
        {
            "category":"Government",
            "subcategory":"Office",
            "type":"Public Place"
        }
    ],
    "sg:phone":"+1 405 372 4906",
    "sg:postcode":"74074",
    "sg:province":"OK",
    "sg:tags":[
        "housing",
        "program"
    ],
    "wof:name":"Stillwater Housing Authority",
    "wof:placetype":"venue"
},
  "geometry": {"coordinates":[-97.055862,36.113409],"type":"Point"}
}