{
  "type": "Feature",
  "properties": {
    "addr:full":"3729 E 87th Pl Tulsa OK 74137",
    "addr:housenumber":"3729",
    "addr:postcode":"74137",
    "addr:street":"E 87Th Pl",
    "iso:country":"US",
    "sg:address":"3729 E 87th Pl",
    "sg:city":"Tulsa",
    "sg:classifiers":[
        {
            "category":"Professional",
            "subcategory":"Business Services",
            "type":"Services"
        }
    ],
    "sg:phone":"+1 918 481 3625",
    "sg:postcode":"74137",
    "sg:province":"OK",
    "wof:name":"Interiors By Mary Jane Friend",
    "wof:placetype":"venue"
},
  "geometry": {"coordinates":[-95.93503800000001,36.036693],"type":"Point"}
}