{
  "type": "Feature",
  "properties": {
    "iso:country":"US",
    "sg:address":"125 N Woodrow Ave",
    "sg:city":"Bartlesville",
    "sg:classifiers":[
        {
            "category":"Building & Trades",
            "subcategory":"Construction",
            "type":"Services"
        }
    ],
    "sg:phone":"+1 918 336 9241",
    "sg:postcode":"74003",
    "sg:province":"OK",
    "sg:tags":[
        "concrete",
        "contractor"
    ],
    "wof:name":"Dave Scott Concrete Contractor",
    "wof:placetype":"venue"
},
  "geometry": {"coordinates":[-95.983793,36.75481],"type":"Point"}
}