{
  "type": "Feature",
  "properties": {
    "iso:country":"US",
    "sg:address":"200 E 121st St",
    "sg:city":"Jenks",
    "sg:classifiers":[
        {
            "category":"Recreation",
            "type":"Entertainment"
        }
    ],
    "sg:phone":"+1 918 298 0711",
    "sg:postcode":"74037",
    "sg:province":"OK",
    "sg:tags":[
        "parks"
    ],
    "wof:name":"Morris Park",
    "wof:placetype":"venue"
},
  "geometry": {"coordinates":[-95.966217,35.988354],"type":"Point"}
}