{
  "type": "Feature",
  "properties": {
    "iso:country":"US",
    "sg:address":"821 Callahan St",
    "sg:city":"Muskogee",
    "sg:classifiers":[
        {
            "category":"Wholesale",
            "subcategory":"Plants",
            "type":"Manufacturing & Wholesale Goods"
        }
    ],
    "sg:phone":"+1 918 682 1870",
    "sg:postcode":"74403",
    "sg:province":"OK",
    "sg:tags":[
        "florist"
    ],
    "wof:name":"Green Flowers",
    "wof:placetype":"venue"
},
  "geometry": {"coordinates":[-95.35703100000001,35.7462],"type":"Point"}
}