{
  "type": "Feature",
  "properties": {
    "iso:country":"US",
    "sg:address":"1629 Edgewood Dr",
    "sg:city":"Edmond",
    "sg:classifiers":[
        {
            "category":"Building & Trades",
            "subcategory":"Construction",
            "type":"Services"
        }
    ],
    "sg:phone":"+1 405 359 7900",
    "sg:postcode":"73013",
    "sg:province":"OK",
    "sg:tags":[
        "home",
        "improvement"
    ],
    "wof:name":"One Call Home Improvements",
    "wof:placetype":"venue"
},
  "geometry": {"coordinates":[-97.471777,35.635741],"type":"Point"}
}