{
  "type": "Feature",
  "properties": {
    "addr:full":"2902 Mount Washington Rd Ardmore OK 73401",
    "addr:housenumber":"2902",
    "addr:postcode":"73401",
    "addr:street":"Mount Washington Rd",
    "iso:country":"US",
    "sg:address":"2902 Mount Washington Rd",
    "sg:city":"Ardmore",
    "sg:classifiers":[
        {
            "category":"Building & Trades",
            "subcategory":"Cleaning & Sanitation",
            "type":"Services"
        }
    ],
    "sg:phone":"+1 580 223 0471",
    "sg:postcode":"73401",
    "sg:province":"OK",
    "sg:tags":[
        "maintenance"
    ],
    "wof:name":"Howery Company Inc",
    "wof:placetype":"venue"
},
  "geometry": {"coordinates":[-97.12545299999999,34.204881],"type":"Point"}
}