{
  "type": "Feature",
  "properties": {
    "iso:country":"US",
    "sg:address":"701 N Harrison Ave",
    "sg:city":"Shawnee",
    "sg:classifiers":[
        {
            "category":"Sports & Exercise",
            "subcategory":"Bowling",
            "type":"Entertainment"
        }
    ],
    "sg:phone":"+1 405 275 4064",
    "sg:postcode":"74801",
    "sg:province":"OK",
    "sg:tags":[
        "center"
    ],
    "wof:name":"Shawnee Bowl",
    "wof:placetype":"venue"
},
  "geometry": {"coordinates":[-96.912124,35.335781],"type":"Point"}
}