{
  "type": "Feature",
  "properties": {
    "addr:full":"303 SW 2nd St Tuttle OK 73089",
    "addr:housenumber":"303",
    "addr:postcode":"73089",
    "addr:street":"Sw 2Nd St",
    "iso:country":"US",
    "sg:address":"303 SW 2nd St",
    "sg:city":"Tuttle",
    "sg:classifiers":[
        {
            "category":"Education",
            "subcategory":"School",
            "type":"Public Place"
        }
    ],
    "sg:phone":"+1 405 381 2605",
    "sg:postcode":"73089",
    "sg:province":"OK",
    "wof:name":"Tuttle School District",
    "wof:placetype":"venue"
},
  "geometry": {"coordinates":[-97.814727,35.287732],"type":"Point"}
}