{
  "type": "Feature",
  "properties": {
    "iso:country":"US",
    "sg:address":"300 SE 5th Ave",
    "sg:city":"Marietta",
    "sg:classifiers":[
        {
            "category":"Professional",
            "type":"Services"
        }
    ],
    "sg:phone":"+1 580 276 4488",
    "sg:postcode":"73448",
    "sg:province":"OK",
    "wof:name":"Restoration Service",
    "wof:placetype":"venue"
},
  "geometry": {"coordinates":[-97.110987,33.934521],"type":"Point"}
}