{
  "type": "Feature",
  "properties": {
    "iso:country":"US",
    "sg:address":"222 E Commercial St",
    "sg:city":"Inola",
    "sg:classifiers":[
        {
            "category":"Food & Beverages",
            "subcategory":"Liquor & Beverages",
            "type":"Retail Goods"
        }
    ],
    "sg:phone":"+1 918 543 7720",
    "sg:postcode":"74036",
    "sg:province":"OK",
    "wof:name":"Inola Spirits",
    "wof:placetype":"venue"
},
  "geometry": {"coordinates":[-95.50539499999999,36.153182],"type":"Point"}
}