{
  "type": "Feature",
  "properties": {
    "iso:country":"US",
    "sg:address":"1606 Deskin Pl",
    "sg:city":"Norman",
    "sg:classifiers":[
        {
            "category":"Wholesale",
            "subcategory":"Machinery & Supplies",
            "type":"Manufacturing & Wholesale Goods"
        }
    ],
    "sg:phone":"+1 405 447 3200",
    "sg:postcode":"73069",
    "sg:province":"OK",
    "sg:tags":[
        "cleaners",
        "vacuum"
    ],
    "wof:name":"Keystone Enterprises",
    "wof:placetype":"venue"
},
  "geometry": {"coordinates":[-97.465023,35.259842],"type":"Point"}
}