{
  "type": "Feature",
  "properties": {
    "iso:country":"US",
    "sg:address":"6308 NW Taylor Ave",
    "sg:city":"Lawton",
    "sg:classifiers":[
        {
            "category":"Shopping",
            "subcategory":"Gifts & Souvenirs",
            "type":"Retail Goods"
        }
    ],
    "sg:phone":"+1 580 536 6264",
    "sg:postcode":"73505",
    "sg:province":"OK",
    "wof:name":"Zs Gurmet Shop Gifts",
    "wof:placetype":"venue"
},
  "geometry": {"coordinates":[-98.474441,34.627514],"type":"Point"}
}