{
  "type": "Feature",
  "properties": {
    "iso:country":"US",
    "sg:address":"811 E Pecan St S",
    "sg:city":"Sand Springs",
    "sg:classifiers":[
        {
            "category":"Real Estate",
            "subcategory":"Real Estate Operator",
            "type":"Services"
        }
    ],
    "sg:phone":"+1 918 241 3704",
    "sg:postcode":"74063",
    "sg:province":"OK",
    "sg:tags":[
        "apartment"
    ],
    "wof:name":"Eight Hundred Eleven Apartment",
    "wof:placetype":"venue"
},
  "geometry": {"coordinates":[-96.096698,36.136308],"type":"Point"}
}