{
  "type": "Feature",
  "properties": {
    "iso:country":"US",
    "sg:address":"400 S Vermont Ave",
    "sg:city":"Oklahoma City",
    "sg:classifiers":[
        {
            "category":"Shopping",
            "subcategory":"Optical Goods",
            "type":"Retail Goods"
        }
    ],
    "sg:phone":"+1 405 947 3937",
    "sg:postcode":"73108",
    "sg:province":"OK",
    "sg:tags":[
        "lense",
        "contact",
        "eye",
        "glasses"
    ],
    "wof:name":"Eye Care Discount Optical",
    "wof:placetype":"venue"
},
  "geometry": {"coordinates":[-97.597044,35.461148],"type":"Point"}
}