{
  "type": "Feature",
  "properties": {
    "addr:full":"205 E Main St Sayre OK 73662",
    "addr:housenumber":"205",
    "addr:postcode":"73662",
    "addr:street":"E Main St",
    "iso:country":"US",
    "sg:address":"205 E Main St",
    "sg:city":"Sayre",
    "sg:classifiers":[
        {
            "category":"Shopping",
            "subcategory":"Florist",
            "type":"Retail Goods"
        }
    ],
    "sg:phone":"+1 580 928 3355",
    "sg:postcode":"73662",
    "sg:province":"OK",
    "wof:name":"Sayre Floral Jewelry & Gifts",
    "wof:placetype":"venue"
},
  "geometry": {"coordinates":[-99.63723400000001,35.291364],"type":"Point"}
}