{
  "type": "Feature",
  "properties": {
    "iso:country":"US",
    "sg:address":"9724 E 55th Pl",
    "sg:city":"Tulsa",
    "sg:classifiers":[
        {
            "category":"Building & Trades",
            "subcategory":"Construction",
            "type":"Services"
        }
    ],
    "sg:phone":"+1 918 270 2575",
    "sg:postcode":"74146",
    "sg:province":"OK",
    "sg:tags":[
        "material",
        "carpentry"
    ],
    "wof:name":"Stormco Window Products",
    "wof:placetype":"venue"
},
  "geometry": {"coordinates":[-95.866487,36.083529],"type":"Point"}
}