{
  "type": "Feature",
  "properties": {
    "addr:full":"9724 E 55th Pl Tulsa OK 74146",
    "addr:housenumber":"9724",
    "addr:postcode":"74146",
    "addr:street":"E 55Th Pl",
    "iso:country":"US",
    "sg:address":"9724 E 55th Pl",
    "sg:city":"Tulsa",
    "sg:classifiers":[
        {
            "category":"Building & Trades",
            "subcategory":"Construction",
            "type":"Services"
        }
    ],
    "sg:phone":"+1 918 270 2575",
    "sg:postcode":"74146",
    "sg:province":"OK",
    "sg:tags":[
        "material",
        "carpentry"
    ],
    "wof:name":"Stormco Window Products",
    "wof:placetype":"venue"
},
  "geometry": {"coordinates":[-95.86648700000001,36.083529],"type":"Point"}
}