{
  "type": "Feature",
  "properties": {
    "iso:country":"US",
    "sg:address":"2424 E 21st St",
    "sg:city":"Tulsa",
    "sg:classifiers":[
        {
            "category":"Professional",
            "subcategory":"Accounting & Tax Preparation",
            "type":"Services"
        }
    ],
    "sg:phone":"+1 918 745 2333",
    "sg:postcode":"74114",
    "sg:province":"OK",
    "sg:tags":[
        "accountant"
    ],
    "sg:website":"www.ttsscpa.com",
    "wof:name":"Tullius Taylor Sartain Sartain",
    "wof:placetype":"venue"
},
  "geometry": {"coordinates":[-95.956685,36.133167],"type":"Point"}
}