{
  "type": "Feature",
  "properties": {
    "addr:full":"224 S Main St Bristow OK 74010",
    "addr:housenumber":"224",
    "addr:postcode":"74010",
    "addr:street":"S Main St",
    "iso:country":"US",
    "sg:address":"224 S Main St",
    "sg:city":"Bristow",
    "sg:classifiers":[
        {
            "category":"Restaurant",
            "type":"Food & Drink"
        }
    ],
    "sg:menulink":"http://www.allmenus.com/ok/bristow/144436-subway/menu/",
    "sg:phone":"+1 918 367 2024",
    "sg:postcode":"74010",
    "sg:province":"OK",
    "sg:tags":[
        "american",
        "sandwich"
    ],
    "wof:name":"Subway",
    "wof:placetype":"venue"
},
  "geometry": {"coordinates":[-96.39102800000001,35.831563],"type":"Point"}
}