{
  "type": "Feature",
  "properties": {
    "iso:country":"US",
    "sg:address":"200 N Harvey Ave",
    "sg:city":"Oklahoma City",
    "sg:classifiers":[
        {
            "category":"Mining & Drilling",
            "type":"Manufacturing & Wholesale Goods"
        }
    ],
    "sg:phone":"+1 405 232 3044",
    "sg:postcode":"73102",
    "sg:province":"OK",
    "sg:tags":[
        "exploration"
    ],
    "wof:name":"Steve Delmas Inc",
    "wof:placetype":"venue"
},
  "geometry": {"coordinates":[-97.517949,35.469084],"type":"Point"}
}