{
  "type": "Feature",
  "properties": {
    "iso:country":"US",
    "sg:address":"8316 NW 19th St",
    "sg:city":"Oklahoma City",
    "sg:classifiers":[
        {
            "category":"Professional",
            "subcategory":"Computer Services",
            "type":"Services"
        }
    ],
    "sg:phone":"+1 405 789 6777",
    "sg:postcode":"73127",
    "sg:province":"OK",
    "sg:tags":[
        "consultant",
        "designer"
    ],
    "wof:name":"Darden Consultants",
    "wof:placetype":"venue"
},
  "geometry": {"coordinates":[-97.662879,35.488221],"type":"Point"}
}