{
  "type": "Feature",
  "properties": {
    "iso:country":"US",
    "sg:address":"58500 E 155 Rd",
    "sg:city":"Fairland",
    "sg:classifiers":[
        {
            "category":"Farming",
            "subcategory":"Livestock Farm",
            "type":"Manufacturing & Wholesale Goods"
        }
    ],
    "sg:phone":"+1 918 676 3886",
    "sg:postcode":"74343",
    "sg:province":"OK",
    "sg:tags":[
        "beef",
        "feedlot",
        "cattle"
    ],
    "wof:name":"Charles Wyrick",
    "wof:placetype":"venue"
},
  "geometry": {"coordinates":[-94.83153900000001,36.793659],"type":"Point"}
}