{
  "type": "Feature",
  "properties": {
    "iso:country":"US",
    "sg:address":"3501 Lakeside Dr",
    "sg:city":"Oklahoma City",
    "sg:classifiers":[
        {
            "category":"Mining & Drilling",
            "type":"Manufacturing & Wholesale Goods"
        }
    ],
    "sg:phone":"+1 405 681 9400",
    "sg:postcode":"73179",
    "sg:province":"OK",
    "sg:tags":[
        "development",
        "gas",
        "oil",
        "exploration"
    ],
    "wof:name":"Citation Oil & Gas Corp",
    "wof:placetype":"venue"
},
  "geometry": {"coordinates":[-97.602881,35.429017],"type":"Point"}
}