{
  "type": "Feature",
  "properties": {
    "addr:full":"3344 S Santa Fe Ave Tulsa OK 74107",
    "addr:housenumber":"3344",
    "addr:postcode":"74107",
    "addr:street":"S Santa Fe Ave",
    "iso:country":"US",
    "sg:address":"3344 S Santa Fe Ave",
    "sg:city":"Tulsa",
    "sg:classifiers":[
        {
            "category":"Retail",
            "subcategory":"Auto Repair",
            "type":"Services"
        }
    ],
    "sg:phone":"+1 918 447 8006",
    "sg:postcode":"74107",
    "sg:province":"OK",
    "sg:tags":[
        "trailer"
    ],
    "wof:name":"Reese Trailer Repair Inc",
    "wof:placetype":"venue"
},
  "geometry": {"coordinates":[-96.009545,36.115085],"type":"Point"}
}