{
  "type": "Feature",
  "properties": {
    "addr:full":"5416 S Harvard Ave Tulsa OK 74135",
    "addr:housenumber":"5416",
    "addr:postcode":"74135",
    "addr:street":"S Harvard Ave",
    "iso:country":"US",
    "sg:address":"5416 S Harvard Ave",
    "sg:city":"Tulsa",
    "sg:classifiers":[
        {
            "category":"Autos & Motor Vehicles",
            "subcategory":"Automobile Sales",
            "type":"Retail Goods"
        },
        {
            "category":"Retail",
            "subcategory":"Auto Rental",
            "type":"Services"
        }
    ],
    "sg:phone":"+1 918 743 3220",
    "sg:postcode":"74135",
    "sg:province":"OK",
    "sg:tags":[
        "truck",
        "leasing",
        "car"
    ],
    "sg:website":"http://www.enterprise.com/car_rental/deeplinkmap.do?gpbr=5157&bid=004&cnty=US&arc=YPTRL01&cm_mmc=Yellowpages.com-_-IYP-_-Tradelisting-_-branch",
    "wof:name":"Enterprise Rent-A-Car",
    "wof:placetype":"venue"
},
  "geometry": {"coordinates":[-95.940147,36.085424],"type":"Point"}
}