{
  "type": "Feature",
  "properties": {
    "iso:country":"US",
    "sg:address":"203 S Fenway Ave",
    "sg:city":"Bartlesville",
    "sg:classifiers":[
        {
            "category":"Communications",
            "type":"Services"
        }
    ],
    "sg:phone":"+1 918 333 6066",
    "sg:postcode":"74006",
    "sg:province":"OK",
    "sg:tags":[
        "communication"
    ],
    "wof:name":"Fielder Services",
    "wof:placetype":"venue"
},
  "geometry": {"coordinates":[-95.924198,36.754819],"type":"Point"}
}