{
  "type": "Feature",
  "properties": {
    "addr:full":"1116 S George Nigh Expy Mcalester OK 74501",
    "addr:housenumber":"1116",
    "addr:postcode":"74501",
    "addr:street":"S George Nigh Expy",
    "iso:country":"US",
    "sg:address":"1116 S George Nigh Expy",
    "sg:city":"Mcalester",
    "sg:classifiers":[
        {
            "category":"Cinema",
            "subcategory":"Movie Theater",
            "type":"Entertainment"
        }
    ],
    "sg:phone":"+1 918 423 4353",
    "sg:postcode":"74501",
    "sg:province":"OK",
    "wof:name":"Cinema 69 Theatres",
    "wof:placetype":"venue"
},
  "geometry": {"coordinates":[-95.755089,34.899194],"type":"Point"}
}