{
  "type": "Feature",
  "properties": {
    "addr:full":"8247 E 71st St Tulsa OK 74133",
    "addr:housenumber":"8247",
    "addr:postcode":"74133",
    "addr:street":"E 71St St",
    "iso:country":"US",
    "sg:address":"8247 E 71st St",
    "sg:city":"Tulsa",
    "sg:classifiers":[
        {
            "category":"Restaurant",
            "type":"Food & Drink"
        }
    ],
    "sg:menulink":"http://www.allmenus.com/ok/tulsa/10023-famous-daves/menu/",
    "sg:phone":"+1 918 249 2140",
    "sg:postcode":"74133",
    "sg:province":"OK",
    "sg:tags":[
        "barbecue",
        "american"
    ],
    "wof:name":"Famous Dave's",
    "wof:placetype":"venue"
},
  "geometry": {"coordinates":[-95.884344,36.06094],"type":"Point"}
}