{
  "type": "Feature",
  "properties": {
    "iso:country":"US",
    "sg:address":"301 E 5th Ave",
    "sg:city":"Owasso",
    "sg:classifiers":[
        {
            "category":"Wholesale",
            "subcategory":"Meat",
            "type":"Manufacturing & Wholesale Goods"
        }
    ],
    "sg:phone":"+1 918 274 8787",
    "sg:postcode":"74055",
    "sg:province":"OK",
    "sg:tags":[
        "poultry",
        "processor",
        "beef"
    ],
    "sg:website":"www.nationalsteak.com",
    "wof:name":"National Steak & Poultry",
    "wof:placetype":"venue"
},
  "geometry": {"coordinates":[-95.85061399999999,36.259012],"type":"Point"}
}