{
  "type": "Feature",
  "properties": {
    "iso:country":"US",
    "sg:address":"1606 W Orlando St",
    "sg:city":"Broken Arrow",
    "sg:classifiers":[
        {
            "category":"Freight",
            "type":"Transportation"
        }
    ],
    "sg:phone":"+1 918 836 3761",
    "sg:postcode":"74011",
    "sg:province":"OK",
    "sg:tags":[
        "transport"
    ],
    "wof:name":"Artina E Silas",
    "wof:placetype":"venue"
},
  "geometry": {"coordinates":[-95.810823,36.016807],"type":"Point"}
}