{
  "type": "Feature",
  "properties": {
    "iso:country":"US",
    "sg:address":"5000 N Portland Ave",
    "sg:city":"Oklahoma City",
    "sg:classifiers":[
        {
            "category":"Food & Beverages",
            "subcategory":"Groceries & Convenience Stores",
            "type":"Retail Goods"
        }
    ],
    "sg:phone":"+1 405 943 1459",
    "sg:postcode":"73112",
    "sg:province":"OK",
    "wof:name":"7-Eleven",
    "wof:placetype":"venue"
},
  "geometry": {"coordinates":[-97.583359,35.520919],"type":"Point"}
}