{
  "type": "Feature",
  "properties": {
    "addr:full":"106 N Main St Mcloud OK 74851",
    "addr:housenumber":"106",
    "addr:postcode":"74851",
    "addr:street":"N Main St",
    "iso:country":"US",
    "sg:address":"106 N Main St",
    "sg:city":"Mcloud",
    "sg:classifiers":[
        {
            "category":"Retail",
            "subcategory":"Repair Shop",
            "type":"Services"
        }
    ],
    "sg:phone":"+1 405 964 3600",
    "sg:postcode":"74851",
    "sg:province":"OK",
    "sg:tags":[
        "upholsterer"
    ],
    "wof:name":"Vicks Upholstery & Hair Ctr",
    "wof:placetype":"venue"
},
  "geometry": {"coordinates":[-97.091787,35.43643],"type":"Point"}
}