{
  "type": "Feature",
  "properties": {
    "iso:country":"US",
    "sg:address":"2633 SW 59th St",
    "sg:city":"Oklahoma City",
    "sg:classifiers":[
        {
            "category":"Real Estate",
            "subcategory":"Real Estate Agent",
            "type":"Services"
        }
    ],
    "sg:phone":"+1 405 681 0611",
    "sg:postcode":"73119",
    "sg:province":"OK",
    "wof:name":"International Real Estate",
    "wof:placetype":"venue"
},
  "geometry": {"coordinates":[-97.561207,35.406172],"type":"Point"}
}