{
  "type": "Feature",
  "properties": {
    "addr:full":"3600 Beaver Cir Edmond OK 73034",
    "addr:housenumber":"3600",
    "addr:postcode":"73034",
    "addr:street":"Beaver Cir",
    "iso:country":"US",
    "sg:address":"3600 Beaver Cir",
    "sg:city":"Edmond",
    "sg:classifiers":[
        {
            "category":"Professional",
            "subcategory":"Management & Consulting",
            "type":"Services"
        }
    ],
    "sg:phone":"+1 405 844 2820",
    "sg:postcode":"73034",
    "sg:province":"OK",
    "sg:tags":[
        "consultant",
        "business"
    ],
    "wof:name":"Strategic Insights",
    "wof:placetype":"venue"
},
  "geometry": {"coordinates":[-97.45469,35.696205],"type":"Point"}
}