{
  "type": "Feature",
  "properties": {
    "iso:country":"US",
    "sg:address":"11132 Lakeridge Run",
    "sg:city":"Oklahoma City",
    "sg:classifiers":[
        {
            "category":"Health Services",
            "subcategory":"Medical Lab",
            "type":"Services"
        }
    ],
    "sg:phone":"+1 405 691 1981",
    "sg:postcode":"73170",
    "sg:province":"OK",
    "sg:tags":[
        "laboratory",
        "testing"
    ],
    "wof:name":"Par - Met Prtble Atmic X - Ray",
    "wof:placetype":"venue"
},
  "geometry": {"coordinates":[-97.55816,35.357342],"type":"Point"}
}