{
  "type": "Feature",
  "properties": {
    "iso:country":"US",
    "sg:address":"1530 S Agnew Ave",
    "sg:city":"Oklahoma City",
    "sg:classifiers":[
        {
            "category":"Banks & Credit Unions",
            "subcategory":"Bank",
            "type":"Services"
        }
    ],
    "sg:phone":"+1 405 272 0655",
    "sg:postcode":"73108",
    "sg:province":"OK",
    "sg:tags":[
        "cashing",
        "check"
    ],
    "wof:name":"Quikcash",
    "wof:placetype":"venue"
},
  "geometry": {"coordinates":[-97.55457199999999,35.449996],"type":"Point"}
}