{
  "type": "Feature",
  "properties": {
    "addr:full":"6 Windemere Cir Lawton OK 73505",
    "addr:housenumber":"6",
    "addr:postcode":"73505",
    "addr:street":"Windemere Cir",
    "iso:country":"US",
    "sg:address":"6 Windemere Cir",
    "sg:city":"Lawton",
    "sg:classifiers":[
        {
            "category":"Building & Trades",
            "subcategory":"Landscaping Services",
            "type":"Services"
        }
    ],
    "sg:phone":"+1 580 536 5172",
    "sg:postcode":"73505",
    "sg:province":"OK",
    "sg:tags":[
        "nursery"
    ],
    "wof:name":"Naturescape Nursery & Ldscpg",
    "wof:placetype":"venue"
},
  "geometry": {"coordinates":[-98.525513,34.628495],"type":"Point"}
}