{
  "type": "Feature",
  "properties": {
    "addr:full":"2800 E Danforth Rd Edmond OK 73034",
    "addr:housenumber":"2800",
    "addr:postcode":"73034",
    "addr:street":"E Danforth Rd",
    "iso:country":"US",
    "sg:address":"2800 E Danforth Rd",
    "sg:city":"Edmond",
    "sg:classifiers":[
        {
            "category":"Organizations",
            "subcategory":"Religious Organization",
            "type":"Services"
        }
    ],
    "sg:phone":"+1 405 348 1252",
    "sg:postcode":"73034",
    "sg:province":"OK",
    "sg:tags":[
        "church"
    ],
    "sg:website":"www.edmondcc.org",
    "wof:name":"Edmond Christian Church Inc",
    "wof:placetype":"venue"
},
  "geometry": {"coordinates":[-97.443388,35.667125],"type":"Point"}
}