{
  "type": "Feature",
  "properties": {
    "iso:country":"US",
    "sg:address":"223 N 3rd Ave",
    "sg:city":"Durant",
    "sg:classifiers":[
        {
            "category":"Retail",
            "subcategory":"Funeral Services",
            "type":"Services"
        }
    ],
    "sg:phone":"+1 580 924 0224",
    "sg:postcode":"74701",
    "sg:province":"OK",
    "sg:tags":[
        "home"
    ],
    "wof:name":"Dalton-Holmes Funeral Home",
    "wof:placetype":"venue"
},
  "geometry": {"coordinates":[-96.378022,33.993277],"type":"Point"}
}