{
  "type": "Feature",
  "properties": {
    "addr:full":"361 N Main St Fairfax OK 74637",
    "addr:housenumber":"361",
    "addr:postcode":"74637",
    "addr:street":"N Main St",
    "iso:country":"US",
    "sg:address":"361 N Main St",
    "sg:city":"Fairfax",
    "sg:classifiers":[
        {
            "category":"Food & Beverages",
            "subcategory":"Groceries & Convenience Stores",
            "type":"Retail Goods"
        }
    ],
    "sg:phone":"+1 918 642 5273",
    "sg:postcode":"74637",
    "sg:province":"OK",
    "wof:name":"Formby Foods",
    "wof:placetype":"venue"
},
  "geometry": {"coordinates":[-96.70437699999999,36.573947],"type":"Point"}
}