{
  "type": "Feature",
  "properties": {
    "iso:country":"US",
    "sg:address":"5138 S 94th East Ave",
    "sg:city":"Tulsa",
    "sg:classifiers":[
        {
            "category":"Shopping",
            "subcategory":"Computers & Home Electronics",
            "type":"Retail Goods"
        }
    ],
    "sg:phone":"+1 918 234 9700",
    "sg:postcode":"74145",
    "sg:province":"OK",
    "wof:name":"American Laser Inc",
    "wof:placetype":"venue"
},
  "geometry": {"coordinates":[-95.872394,36.088884],"type":"Point"}
}