{
  "type": "Feature",
  "properties": {
    "addr:full":"401 E A St Jenks OK 74037",
    "addr:housenumber":"401",
    "addr:postcode":"74037",
    "addr:street":"E A St",
    "iso:country":"US",
    "sg:address":"401 E A St",
    "sg:city":"Jenks",
    "sg:classifiers":[
        {
            "category":"Personal",
            "subcategory":"Beauty Salon",
            "type":"Services"
        },
        {
            "category":"Personal",
            "subcategory":"Nail Salon",
            "type":"Services"
        }
    ],
    "sg:phone":"+1 918 995 2500",
    "sg:postcode":"74037",
    "sg:province":"OK",
    "sg:tags":[
        "hair",
        "cosmetologist",
        "stylist"
    ],
    "wof:name":"Salon Senoj Hair & Nail Salon",
    "wof:placetype":"venue"
},
  "geometry": {"coordinates":[-95.965919,36.02359],"type":"Point"}
}