{
  "type": "Feature",
  "properties": {
    "addr:full":"1213 W Oxford Ave Enid OK 73701",
    "addr:housenumber":"1213",
    "addr:postcode":"73701",
    "addr:street":"W Oxford Ave",
    "iso:country":"US",
    "sg:address":"1213 W Oxford Ave",
    "sg:city":"Enid",
    "sg:classifiers":[
        {
            "category":"Farming",
            "subcategory":"Nursery",
            "type":"Manufacturing & Wholesale Goods"
        }
    ],
    "sg:phone":"+1 580 234 6452",
    "sg:postcode":"73701",
    "sg:province":"OK",
    "sg:tags":[
        "ornamental"
    ],
    "wof:name":"Garden House",
    "wof:placetype":"venue"
},
  "geometry": {"coordinates":[-97.891801,36.427085],"type":"Point"}
}