{
  "type": "Feature",
  "properties": {
    "iso:country":"US",
    "sg:address":"1919 S Wheeling Ave",
    "sg:city":"Tulsa",
    "sg:classifiers":[
        {
            "category":"Health Services",
            "subcategory":"Doctor",
            "type":"Services"
        }
    ],
    "sg:phone":"+1 918 293 6200",
    "sg:postcode":"74104",
    "sg:province":"OK",
    "sg:tags":[
        "medical"
    ],
    "wof:name":"Deaton Rebecca E",
    "wof:placetype":"venue"
},
  "geometry": {"coordinates":[-95.964545,36.13345],"type":"Point"}
}