{
  "type": "Feature",
  "properties": {
    "iso:country":"US",
    "sg:address":"102 E Central Blvd",
    "sg:city":"Anadarko",
    "sg:classifiers":[
        {
            "category":"Home & Garden",
            "subcategory":"Household Appliances",
            "type":"Retail Goods"
        }
    ],
    "sg:phone":"+1 405 247 7575",
    "sg:postcode":"73005",
    "sg:province":"OK",
    "wof:name":"Central Appliance & Radioshack",
    "wof:placetype":"venue"
},
  "geometry": {"coordinates":[-98.242059,35.072351],"type":"Point"}
}