{
  "type": "Feature",
  "properties": {
    "iso:country":"US",
    "sg:address":"9925 SE 15th St",
    "sg:city":"Midwest City",
    "sg:classifiers":[
        {
            "category":"Food & Beverages",
            "subcategory":"Groceries & Convenience Stores",
            "type":"Retail Goods"
        }
    ],
    "sg:phone":"+1 405 737 7729",
    "sg:postcode":"73130",
    "sg:province":"OK",
    "wof:name":"7-Eleven",
    "wof:placetype":"venue"
},
  "geometry": {"coordinates":[-97.354191,35.449632],"type":"Point"}
}