{
  "type": "Feature",
  "properties": {
    "addr:full":"701 S Westminster Rd Oklahoma City OK 73130",
    "addr:housenumber":"701",
    "addr:postcode":"73130",
    "addr:street":"S Westminster Rd",
    "iso:country":"US",
    "sg:address":"701 S Westminster Rd",
    "sg:city":"Oklahoma City",
    "sg:classifiers":[
        {
            "category":"Organizations",
            "subcategory":"Religious Organization",
            "type":"Services"
        }
    ],
    "sg:phone":"+1 405 769 4530",
    "sg:postcode":"73130",
    "sg:province":"OK",
    "sg:tags":[
        "church"
    ],
    "wof:name":"Westminster Rd Baptist Church",
    "wof:placetype":"venue"
},
  "geometry": {"coordinates":[-97.335708,35.457225],"type":"Point"}
}