{
  "type": "Feature",
  "properties": {
    "iso:country":"US",
    "sg:address":"2205 Regis Ct",
    "sg:city":"Norman",
    "sg:classifiers":[
        {
            "category":"Real Estate",
            "subcategory":"Real Estate Agent",
            "type":"Services"
        }
    ],
    "sg:phone":"+1 405 364 2454",
    "sg:postcode":"73071",
    "sg:province":"OK",
    "wof:name":"White Investments LLC",
    "wof:placetype":"venue"
},
  "geometry": {"coordinates":[-97.407206,35.24115],"type":"Point"}
}