{
  "type": "Feature",
  "properties": {
    "addr:full":"200 S Connell Ave Picher OK 74360",
    "addr:housenumber":"200",
    "addr:postcode":"74360",
    "addr:street":"S Connell Ave",
    "iso:country":"US",
    "sg:address":"200 S Connell Ave",
    "sg:city":"Picher",
    "sg:classifiers":[
        {
            "category":"Restaurant",
            "type":"Food & Drink"
        }
    ],
    "sg:phone":"+1 918 673 2175",
    "sg:postcode":"74360",
    "sg:province":"OK",
    "sg:tags":[
        "eating"
    ],
    "wof:name":"Country Girls Cafe",
    "wof:placetype":"venue"
},
  "geometry": {"coordinates":[-94.83089,36.984329],"type":"Point"}
}