{
  "type": "Feature",
  "properties": {
    "addr:full":"2333 E Britton Rd Oklahoma City OK 73131",
    "addr:housenumber":"2333",
    "addr:postcode":"73131",
    "addr:street":"E Britton Rd",
    "iso:country":"US",
    "sg:address":"2333 E Britton Rd",
    "sg:city":"Oklahoma City",
    "sg:classifiers":[
        {
            "category":"Professional",
            "subcategory":"Advertising",
            "type":"Services"
        }
    ],
    "sg:phone":"+1 405 478 4755",
    "sg:postcode":"73131",
    "sg:province":"OK",
    "sg:website":"www.admotions.com",
    "wof:name":"Admotions",
    "wof:placetype":"venue"
},
  "geometry": {"coordinates":[-97.476744,35.565681],"type":"Point"}
}