{
  "type": "Feature",
  "properties": {
    "iso:country":"US",
    "sg:address":"7602 N Western Ave",
    "sg:city":"Oklahoma City",
    "sg:classifiers":[
        {
            "category":"Sports & Exercise",
            "subcategory":"Gym",
            "type":"Entertainment"
        }
    ],
    "sg:phone":"+1 405 810 8877",
    "sg:postcode":"73116",
    "sg:province":"OK",
    "sg:tags":[
        "fitness",
        "physical",
        "facility"
    ],
    "wof:name":"Yoga Studio",
    "wof:placetype":"venue"
},
  "geometry": {"coordinates":[-97.531159,35.550005],"type":"Point"}
}