{
  "type": "Feature",
  "properties": {
    "iso:country":"US",
    "sg:address":"2605 SW 52nd St",
    "sg:city":"Oklahoma City",
    "sg:classifiers":[
        {
            "category":"Building & Trades",
            "subcategory":"Cleaning & Sanitation",
            "type":"Services"
        }
    ],
    "sg:phone":"+1 405 685 6106",
    "sg:postcode":"73119",
    "sg:province":"OK",
    "sg:tags":[
        "maintenance"
    ],
    "wof:name":"Stephanie R Brakebill",
    "wof:placetype":"venue"
},
  "geometry": {"coordinates":[-97.559235,35.413132],"type":"Point"}
}