{
  "type": "Feature",
  "properties": {
    "iso:country":"US",
    "sg:address":"416 W Treat Rd",
    "sg:city":"Muldrow",
    "sg:classifiers":[
        {
            "category":"Parking",
            "subcategory":"Garage",
            "type":"Transportation"
        },
        {
            "category":"Building & Trades",
            "subcategory":"Construction",
            "type":"Services"
        },
        {
            "category":"Retail",
            "subcategory":"Storage",
            "type":"Services"
        },
        {
            "category":"Insurance",
            "subcategory":"Life Insurance",
            "type":"Services"
        },
        {
            "category":"Manufacturing",
            "subcategory":"Buildings",
            "type":"Manufacturing & Wholesale Goods"
        },
        {
            "category":"Manufacturing",
            "subcategory":"Building Materials",
            "type":"Manufacturing & Wholesale Goods"
        }
    ],
    "sg:phone":"+1 918 427 6005",
    "sg:postcode":"74948",
    "sg:province":"OK",
    "sg:tags":[
        "carport",
        "portable",
        "materials-wholesale",
        "metal",
        "covers-protective",
        "buildings-portable",
        "unit",
        "manufacturer"
    ],
    "wof:name":"Affordable Buildings",
    "wof:placetype":"venue"
},
  "geometry": {"coordinates":[-94.607663,35.390951],"type":"Point"}
}