{
  "type": "Feature",
  "properties": {
    "addr:full":"1701 N Lynn Riggs Blvd Claremore OK 74019",
    "addr:housenumber":"1701",
    "addr:postcode":"74019",
    "addr:street":"N Lynn Riggs Blvd",
    "iso:country":"US",
    "sg:address":"1701 N Lynn Riggs Blvd",
    "sg:city":"Claremore",
    "sg:classifiers":[
        {
            "category":"Home & Garden",
            "subcategory":"Carpets & Floor Coverings",
            "type":"Retail Goods"
        }
    ],
    "sg:phone":"+1 918 637 4533",
    "sg:postcode":"74019",
    "sg:province":"OK",
    "sg:tags":[
        "dealer",
        "rug"
    ],
    "wof:name":"A & H Discount Carpets",
    "wof:placetype":"venue"
},
  "geometry": {"coordinates":[-95.60924,36.32316],"type":"Point"}
}