{
  "type": "Feature",
  "properties": {
    "iso:country":"US",
    "sg:address":"1814 NW Fort Sill Blvd",
    "sg:city":"Lawton",
    "sg:classifiers":[
        {
            "category":"Retail",
            "subcategory":"Laundry & Dry Cleaning",
            "type":"Services"
        }
    ],
    "sg:phone":"+1 580 357 7500",
    "sg:postcode":"73507",
    "sg:province":"OK",
    "sg:tags":[
        "cleaners",
        "plant",
        "drycleaning"
    ],
    "wof:name":"Kim's Cleaners",
    "wof:placetype":"venue"
},
  "geometry": {"coordinates":[-98.40476,34.627762],"type":"Point"}
}