{
  "type": "Feature",
  "properties": {
    "addr:full":"624 S Javine Ave Skiatook OK 74070",
    "addr:housenumber":"624",
    "addr:postcode":"74070",
    "addr:street":"S Javine Ave",
    "iso:country":"US",
    "sg:address":"624 S Javine Ave",
    "sg:city":"Skiatook",
    "sg:classifiers":[
        {
            "category":"Organizations",
            "subcategory":"Religious Organization",
            "type":"Services"
        }
    ],
    "sg:phone":"+1 918 396 2180",
    "sg:postcode":"74070",
    "sg:province":"OK",
    "wof:name":"Church Of God",
    "wof:placetype":"venue"
},
  "geometry": {"coordinates":[-96.00254200000001,36.364223],"type":"Point"}
}