{
  "type": "Feature",
  "properties": {
    "iso:country":"US",
    "sg:address":"58821 E 102 Rd",
    "sg:city":"Miami",
    "sg:classifiers":[
        {
            "category":"Banks & Credit Unions",
            "subcategory":"Financial Services",
            "type":"Services"
        }
    ],
    "sg:phone":"+1 918 542 4748",
    "sg:postcode":"74354",
    "sg:province":"OK",
    "sg:tags":[
        "trust",
        "management"
    ],
    "wof:name":"Hawley Family Trust",
    "wof:placetype":"venue"
},
  "geometry": {"coordinates":[-94.823894,36.867516],"type":"Point"}
}