{
  "type": "Feature",
  "properties": {
    "iso:country":"US",
    "sg:address":"2201 N Douglas Blvd",
    "sg:city":"Oklahoma City",
    "sg:classifiers":[
        {
            "category":"Professional",
            "subcategory":"Accounting & Tax Preparation",
            "type":"Services"
        }
    ],
    "sg:phone":"+1 405 769 7002",
    "sg:postcode":"73141",
    "sg:province":"OK",
    "sg:tags":[
        "return",
        "filing"
    ],
    "wof:name":"A-1 Accounting & Tax Svc",
    "wof:placetype":"venue"
},
  "geometry": {"coordinates":[-97.37088900000001,35.491423],"type":"Point"}
}