{
  "type": "Feature",
  "properties": {
    "iso:country":"US",
    "sg:address":"2241 SW 44th St",
    "sg:city":"Oklahoma City",
    "sg:classifiers":[
        {
            "category":"Sports & Exercise",
            "subcategory":"Bowling",
            "type":"Entertainment"
        }
    ],
    "sg:phone":"+1 405 685 7731",
    "sg:postcode":"73119",
    "sg:province":"OK",
    "sg:tags":[
        "center"
    ],
    "wof:name":"Penn 44 Lanes",
    "wof:placetype":"venue"
},
  "geometry": {"coordinates":[-97.551635,35.420785],"type":"Point"}
}