{
  "type": "Feature",
  "properties": {
    "addr:full":"2100 Westside Pkwy Mcalester OK 74525",
    "addr:housenumber":"2100",
    "addr:postcode":"74525",
    "addr:street":"Westside Pkwy",
    "iso:country":"US",
    "sg:address":"2100 Westside Pkwy",
    "sg:city":"Mcalester",
    "sg:classifiers":[
        {
            "category":"Bars & Pubs",
            "type":"Food & Drink"
        }
    ],
    "sg:phone":"+1 918 423 1550",
    "sg:postcode":"74525",
    "sg:province":"OK",
    "sg:tags":[
        "club",
        "night"
    ],
    "wof:name":"Westside Club",
    "wof:placetype":"venue"
},
  "geometry": {"coordinates":[-96.147271,34.37491],"type":"Point"}
}