{
  "type": "Feature",
  "properties": {
    "addr:full":"4901 NW 18th Ter Oklahoma City OK 73127",
    "addr:housenumber":"4901",
    "addr:postcode":"73127",
    "addr:street":"Nw 18Th Ter",
    "iso:country":"US",
    "sg:address":"4901 NW 18th Ter",
    "sg:city":"Oklahoma City",
    "sg:classifiers":[
        {
            "category":"Wholesale",
            "subcategory":"Electrical",
            "type":"Manufacturing & Wholesale Goods"
        }
    ],
    "sg:phone":"+1 405 946 0511",
    "sg:postcode":"73127",
    "sg:province":"OK",
    "sg:tags":[
        "alarm",
        "burglar",
        "system"
    ],
    "wof:name":"A-One Security",
    "wof:placetype":"venue"
},
  "geometry": {"coordinates":[-97.61362099999999,35.488748],"type":"Point"}
}