{
  "type": "Feature",
  "properties": {
    "addr:full":"814 Manvel Ave Chandler OK 74834",
    "addr:housenumber":"814",
    "addr:postcode":"74834",
    "addr:street":"Manvel Ave",
    "iso:country":"US",
    "sg:address":"814 Manvel Ave",
    "sg:city":"Chandler",
    "sg:classifiers":[
        {
            "category":"Professional",
            "subcategory":"Lawyer & Legal Services",
            "type":"Services"
        }
    ],
    "sg:phone":"+1 405 258 0097",
    "sg:postcode":"74834",
    "sg:province":"OK",
    "sg:tags":[
        "attorney"
    ],
    "wof:name":"Cynthia J Ferrell",
    "wof:placetype":"venue"
},
  "geometry": {"coordinates":[-96.880644,35.702444],"type":"Point"}
}