{
  "type": "Feature",
  "properties": {
    "iso:country":"US",
    "sg:address":"14014 N Western Ave",
    "sg:city":"Edmond",
    "sg:classifiers":[
        {
            "category":"Health Services",
            "subcategory":"Chiropractor",
            "type":"Services"
        }
    ],
    "sg:phone":"+1 405 751 8880",
    "sg:postcode":"73013",
    "sg:province":"OK",
    "wof:name":"Daniel Rowe Chiropractic Clnc",
    "wof:placetype":"venue"
},
  "geometry": {"coordinates":[-97.531553,35.609356],"type":"Point"}
}