{
  "type": "Feature",
  "properties": {
    "addr:full":"4 W Martin Luther King St Muskogee OK 74401",
    "addr:housenumber":"4",
    "addr:postcode":"74401",
    "addr:street":"W Martin Luther King St",
    "iso:country":"US",
    "sg:address":"4 W Martin Luther King St",
    "sg:city":"Muskogee",
    "sg:classifiers":[
        {
            "category":"Professional",
            "type":"Services"
        }
    ],
    "sg:phone":"+1 918 682 8651",
    "sg:postcode":"74401",
    "sg:province":"OK",
    "sg:tags":[
        "establishment"
    ],
    "wof:name":"Northeastern Automated Syst",
    "wof:placetype":"venue"
},
  "geometry": {"coordinates":[-95.365871,35.7541],"type":"Point"}
}