{
  "type": "Feature",
  "properties": {
    "addr:full":"5700 SE 3rd St Oklahoma City OK 73110",
    "addr:housenumber":"5700",
    "addr:postcode":"73110",
    "addr:street":"Se 3Rd St",
    "iso:country":"US",
    "sg:address":"5700 SE 3rd St",
    "sg:city":"Oklahoma City",
    "sg:classifiers":[
        {
            "category":"Home & Garden",
            "subcategory":"Furniture",
            "type":"Retail Goods"
        }
    ],
    "sg:phone":"+1 405 833 9997",
    "sg:postcode":"73110",
    "sg:province":"OK",
    "wof:name":"Carl R Holland",
    "wof:placetype":"venue"
},
  "geometry": {"coordinates":[-97.423683,35.46098],"type":"Point"}
}