{
  "type": "Feature",
  "properties": {
    "iso:country":"US",
    "sg:address":"13905 N May Ave",
    "sg:city":"Oklahoma City",
    "sg:classifiers":[
        {
            "category":"Restaurant",
            "type":"Food & Drink"
        }
    ],
    "sg:phone":"+1 405 755 4267",
    "sg:postcode":"73134",
    "sg:province":"OK",
    "sg:tags":[
        "eating"
    ],
    "wof:name":"Heavenly Ham",
    "wof:placetype":"venue"
},
  "geometry": {"coordinates":[-97.567162,35.613611],"type":"Point"}
}