{
  "type": "Feature",
  "properties": {
    "iso:country":"US",
    "sg:address":"2741 SW 29th St",
    "sg:city":"Oklahoma City",
    "sg:classifiers":[
        {
            "category":"Restaurant",
            "type":"Food & Drink"
        }
    ],
    "sg:menulink":"http://www.allmenus.com/ok/oklahoma-city/151743-aw-restaurant/menu/",
    "sg:phone":"+1 405 632 6102",
    "sg:postcode":"73119",
    "sg:province":"OK",
    "sg:tags":[
        "burger",
        "american",
        "dog",
        "pub",
        "hot"
    ],
    "wof:name":"A&W Restaurant",
    "wof:placetype":"venue"
},
  "geometry": {"coordinates":[-97.562437,35.435125],"type":"Point"}
}