{
  "type": "Feature",
  "properties": {
    "iso:country":"US",
    "sg:address":"2516 Stamford Ct",
    "sg:city":"Edmond",
    "sg:classifiers":[
        {
            "category":"Real Estate",
            "subcategory":"Real Estate Operator",
            "type":"Services"
        }
    ],
    "sg:phone":"+1 405 341 7138",
    "sg:postcode":"73034",
    "sg:province":"OK",
    "sg:tags":[
        "property",
        "lessor"
    ],
    "wof:name":"Dacrn Inc",
    "wof:placetype":"venue"
},
  "geometry": {"coordinates":[-97.447819,35.644134],"type":"Point"}
}