{
  "type": "Feature",
  "properties": {
    "iso:country":"US",
    "sg:address":"807 W Main St",
    "sg:city":"Duncan",
    "sg:classifiers":[
        {
            "category":"Manufacturing",
            "subcategory":"Printing",
            "type":"Manufacturing & Wholesale Goods"
        }
    ],
    "sg:phone":"+1 580 252 5021",
    "sg:postcode":"73533",
    "sg:province":"OK",
    "sg:tags":[
        "screen"
    ],
    "wof:name":"Screenplay T-Shirts Etc",
    "wof:placetype":"venue"
},
  "geometry": {"coordinates":[-97.958173,34.501996],"type":"Point"}
}