{
  "type": "Feature",
  "properties": {
    "iso:country":"US",
    "sg:address":"118 Dean A McGee Ave",
    "sg:city":"Oklahoma City",
    "sg:classifiers":[
        {
            "category":"Professional",
            "subcategory":"Management & Consulting",
            "type":"Services"
        }
    ],
    "sg:phone":"+1 405 232 5777",
    "sg:postcode":"73102",
    "sg:province":"OK",
    "sg:tags":[
        "consultant",
        "business"
    ],
    "wof:name":"Inroads Oklahoma Inc",
    "wof:placetype":"venue"
},
  "geometry": {"coordinates":[-97.515308,35.470794],"type":"Point"}
}