{
  "type": "Feature",
  "properties": {
    "iso:country":"US",
    "sg:address":"7485 E 46th Pl",
    "sg:city":"Tulsa",
    "sg:classifiers":[
        {
            "category":"Wholesale",
            "subcategory":"Office Equipment",
            "type":"Manufacturing & Wholesale Goods"
        }
    ],
    "sg:phone":"+1 918 663 3062",
    "sg:postcode":"74145",
    "sg:province":"OK",
    "wof:name":"C W Cook Inc",
    "wof:placetype":"venue"
},
  "geometry": {"coordinates":[-95.887415,36.096557],"type":"Point"}
}