{
  "type": "Feature",
  "properties": {
    "iso:country":"US",
    "sg:address":"2722 E 15th St",
    "sg:city":"Tulsa",
    "sg:classifiers":[
        {
            "category":"Shopping",
            "type":"Retail Goods"
        }
    ],
    "sg:phone":"+1 918 747 2787",
    "sg:postcode":"74104",
    "sg:province":"OK",
    "sg:tags":[
        "art",
        "gallery",
        "dealer"
    ],
    "wof:name":"Art & Soul School Of Art",
    "wof:placetype":"venue"
},
  "geometry": {"coordinates":[-95.951239,36.140467],"type":"Point"}
}