{
  "type": "Feature",
  "properties": {
    "addr:full":"9300 Jennifer Dr Oklahoma City OK 73165",
    "addr:housenumber":"9300",
    "addr:postcode":"73165",
    "addr:street":"Jennifer Dr",
    "iso:country":"US",
    "sg:address":"9300 Jennifer Dr",
    "sg:city":"Oklahoma City",
    "sg:classifiers":[
        {
            "category":"Professional",
            "subcategory":"Engineering",
            "type":"Services"
        }
    ],
    "sg:phone":"+1 405 732 6553",
    "sg:postcode":"73165",
    "sg:province":"OK",
    "sg:tags":[
        "surveying"
    ],
    "wof:name":"Surveying Cahill Land",
    "wof:placetype":"venue"
},
  "geometry": {"coordinates":[-97.31241,35.374179],"type":"Point"}
}