{
  "type": "Feature",
  "properties": {
    "iso:country":"US",
    "sg:address":"4802 N Keystone Ave",
    "sg:city":"Sand Springs",
    "sg:classifiers":[
        {
            "category":"Building & Trades",
            "subcategory":"Plumbing",
            "type":"Services"
        }
    ],
    "sg:phone":"+1 918 241 3850",
    "sg:postcode":"74063",
    "sg:province":"OK",
    "sg:tags":[
        "plumbing",
        "contractor"
    ],
    "wof:name":"R & R Plumbing",
    "wof:placetype":"venue"
},
  "geometry": {"coordinates":[-96.22149400000001,36.224562],"type":"Point"}
}