{
  "type": "Feature",
  "properties": {
    "addr:full":"103 E Central Ave Miami OK 74354",
    "addr:housenumber":"103",
    "addr:postcode":"74354",
    "addr:street":"E Central Ave",
    "iso:country":"US",
    "sg:address":"103 E Central Ave",
    "sg:city":"Miami",
    "sg:classifiers":[
        {
            "category":"Professional",
            "subcategory":"Lawyer & Legal Services",
            "type":"Services"
        }
    ],
    "sg:phone":"+1 918 542 9191",
    "sg:postcode":"74354",
    "sg:province":"OK",
    "sg:tags":[
        "attorney"
    ],
    "wof:name":"J Wayne Kennon Law Office",
    "wof:placetype":"venue"
},
  "geometry": {"coordinates":[-94.876373,36.874745],"type":"Point"}
}