{
  "type": "Feature",
  "properties": {
    "iso:country":"US",
    "sg:address":"223 S Main St",
    "sg:city":"Bristow",
    "sg:classifiers":[
        {
            "category":"Shopping",
            "type":"Retail Goods"
        }
    ],
    "sg:phone":"+1 918 367 5656",
    "sg:postcode":"74010",
    "sg:province":"OK",
    "sg:tags":[
        "art",
        "gallery",
        "dealer"
    ],
    "wof:name":"Russ Ribs",
    "wof:placetype":"venue"
},
  "geometry": {"coordinates":[-96.390907,35.831568],"type":"Point"}
}