{
  "type": "Feature",
  "properties": {
    "addr:full":"9816 S 239th East Ave Broken Arrow OK 74014",
    "addr:housenumber":"9816",
    "addr:postcode":"74014",
    "addr:street":"S 239Th East Ave",
    "iso:country":"US",
    "sg:address":"9816 S 239th East Ave",
    "sg:city":"Broken Arrow",
    "sg:classifiers":[
        {
            "category":"Government",
            "subcategory":"Office",
            "type":"Public Place"
        }
    ],
    "sg:phone":"+1 918 251 9836",
    "sg:postcode":"74014",
    "sg:province":"OK",
    "sg:tags":[
        "management"
    ],
    "wof:name":"Warner Company",
    "wof:placetype":"venue"
},
  "geometry": {"coordinates":[-95.710818,36.023438],"type":"Point"}
}