{
  "type": "Feature",
  "properties": {
    "iso:country":"US",
    "sg:address":"1222 Manvel Ave",
    "sg:city":"Chandler",
    "sg:classifiers":[
        {
            "category":"Retail",
            "subcategory":"Veterinary Services",
            "type":"Services"
        }
    ],
    "sg:phone":"+1 405 258 3003",
    "sg:postcode":"74834",
    "sg:province":"OK",
    "wof:name":"Vet Mart",
    "wof:placetype":"venue"
},
  "geometry": {"coordinates":[-96.88061999999999,35.698191],"type":"Point"}
}