{
  "type": "Feature",
  "properties": {
    "iso:country":"US",
    "sg:address":"4129 S 72nd East Ave",
    "sg:city":"Tulsa",
    "sg:classifiers":[
        {
            "category":"Shopping",
            "subcategory":"Crafts & Fabrics",
            "type":"Retail Goods"
        }
    ],
    "sg:phone":"+1 918 641 0633",
    "sg:postcode":"74145",
    "sg:province":"OK",
    "sg:tags":[
        "fiber",
        "cotton"
    ],
    "sg:website":"www.ssi.com",
    "wof:name":"Sustainable Solutions Inc",
    "wof:placetype":"venue"
},
  "geometry": {"coordinates":[-95.896837,36.10049],"type":"Point"}
}