{
  "type": "Feature",
  "properties": {
    "iso:country":"US",
    "sg:address":"2701 S Shields Blvd",
    "sg:city":"Oklahoma City",
    "sg:classifiers":[
        {
            "category":"Food & Beverages",
            "subcategory":"Groceries & Convenience Stores",
            "type":"Retail Goods"
        }
    ],
    "sg:phone":"+1 405 231 0059",
    "sg:postcode":"73129",
    "sg:province":"OK",
    "sg:tags":[
        "product"
    ],
    "wof:name":"Basic Foods",
    "wof:placetype":"venue"
},
  "geometry": {"coordinates":[-97.510919,35.438319],"type":"Point"}
}