{
  "type": "Feature",
  "properties": {
    "iso:country":"US",
    "sg:address":"7739 E 38th St",
    "sg:city":"Tulsa",
    "sg:classifiers":[
        {
            "category":"Professional",
            "subcategory":"Computer Services",
            "type":"Services"
        }
    ],
    "sg:phone":"+1 918 664 1965",
    "sg:postcode":"74145",
    "sg:province":"OK",
    "sg:tags":[
        "wiring"
    ],
    "wof:name":"Parasol Computer Cabling",
    "wof:placetype":"venue"
},
  "geometry": {"coordinates":[-95.892976,36.10812],"type":"Point"}
}