{
  "type": "Feature",
  "properties": {
    "iso:country":"US",
    "sg:address":"7002 S Mingo Rd",
    "sg:city":"Tulsa",
    "sg:classifiers":[
        {
            "category":"Food & Beverages",
            "subcategory":"Liquor & Beverages",
            "type":"Retail Goods"
        }
    ],
    "sg:phone":"+1 918 254 4688",
    "sg:postcode":"74133",
    "sg:province":"OK",
    "sg:tags":[
        "alcoholic"
    ],
    "wof:name":"B & B Liquor Warehouse",
    "wof:placetype":"venue"
},
  "geometry": {"coordinates":[-95.868593,36.066812],"type":"Point"}
}