{
  "type": "Feature",
  "properties": {
    "iso:country":"US",
    "sg:address":"10198 S 77th Ave E",
    "sg:city":"Tulsa",
    "sg:classifiers":[
        {
            "category":"Mining & Drilling",
            "type":"Manufacturing & Wholesale Goods"
        }
    ],
    "sg:phone":"+1 918 299 9955",
    "sg:postcode":"74133",
    "sg:province":"OK",
    "sg:tags":[
        "oil",
        "gas",
        "producer"
    ],
    "wof:name":"Carter Energy Co",
    "wof:placetype":"venue"
},
  "geometry": {"coordinates":[-95.891588,36.016113],"type":"Point"}
}