{
  "type": "Feature",
  "properties": {
    "addr:full":"1737 E 71st St Tulsa OK 74136",
    "addr:housenumber":"1737",
    "addr:postcode":"74136",
    "addr:street":"E 71St St",
    "iso:country":"US",
    "sg:address":"1737 E 71st St",
    "sg:city":"Tulsa",
    "sg:classifiers":[
        {
            "category":"Insurance",
            "subcategory":"Insurance Agent",
            "type":"Services"
        }
    ],
    "sg:phone":"+1 918 492 0285",
    "sg:postcode":"74136",
    "sg:province":"OK",
    "sg:tags":[
        "agency"
    ],
    "wof:name":"Blevins Rich Coml Insur Agenc",
    "wof:placetype":"venue"
},
  "geometry": {"coordinates":[-95.966311,36.060838],"type":"Point"}
}