{
  "type": "Feature",
  "properties": {
    "addr:full":"1963 W Lindsey St Norman OK 73069",
    "addr:housenumber":"1963",
    "addr:postcode":"73069",
    "addr:street":"W Lindsey St",
    "iso:country":"US",
    "sg:address":"1963 W Lindsey St",
    "sg:city":"Norman",
    "sg:classifiers":[
        {
            "category":"Personal",
            "subcategory":"Beauty Salon",
            "type":"Services"
        }
    ],
    "sg:phone":"+1 405 321 1408",
    "sg:postcode":"73069",
    "sg:province":"OK",
    "sg:tags":[
        "shop"
    ],
    "wof:name":"Jazz Salon",
    "wof:placetype":"venue"
},
  "geometry": {"coordinates":[-97.46978,35.203989],"type":"Point"}
}