{
  "type": "Feature",
  "properties": {
    "addr:full":"506 US Hwy 271 Wister OK 74959",
    "addr:housenumber":"506",
    "addr:postcode":"74959",
    "addr:street":"Us Hwy 271",
    "iso:country":"US",
    "sg:address":"506 US Hwy 271",
    "sg:city":"Wister",
    "sg:classifiers":[
        {
            "category":"Restaurant",
            "type":"Food & Drink"
        }
    ],
    "sg:phone":"+1 918 655 6924",
    "sg:postcode":"74959",
    "sg:province":"OK",
    "wof:name":"Rubys Cafe",
    "wof:placetype":"venue"
},
  "geometry": {"coordinates":[-94.63291,35.240221],"type":"Point"}
}