{
  "type": "Feature",
  "properties": {
    "iso:country":"US",
    "sg:address":"13426 240th St",
    "sg:city":"Blanchard",
    "sg:classifiers":[
        {
            "category":"Building & Trades",
            "subcategory":"Electrical",
            "type":"Services"
        }
    ],
    "sg:phone":"+1 405 590 0023",
    "sg:postcode":"73010",
    "sg:province":"OK",
    "sg:tags":[
        "electrical",
        "contractor"
    ],
    "wof:name":"Infinity Electric",
    "wof:placetype":"venue"
},
  "geometry": {"coordinates":[-97.610321,35.05874],"type":"Point"}
}