{
  "type": "Feature",
  "properties": {
    "iso:country":"US",
    "sg:address":"27696 E 126th St",
    "sg:city":"Coweta",
    "sg:classifiers":[
        {
            "category":"Mining & Drilling",
            "type":"Manufacturing & Wholesale Goods"
        }
    ],
    "sg:phone":"+1 918 486 5074",
    "sg:postcode":"74429",
    "sg:province":"OK",
    "sg:tags":[
        "exploration"
    ],
    "wof:name":"Bailey Drilling Co",
    "wof:placetype":"venue"
},
  "geometry": {"coordinates":[-95.66904,35.980006],"type":"Point"}
}