{
  "type": "Feature",
  "properties": {
    "iso:country":"US",
    "sg:address":"2176 S Sheridan Rd",
    "sg:city":"Tulsa",
    "sg:classifiers":[
        {
            "category":"Shopping",
            "subcategory":"Clothing, Apparel, & Fashions",
            "type":"Retail Goods"
        }
    ],
    "sg:phone":"+1 918 835 6989",
    "sg:postcode":"74129",
    "sg:province":"OK",
    "wof:name":"Pennington's Garment Station",
    "wof:placetype":"venue"
},
  "geometry": {"coordinates":[-95.904683,36.133025],"type":"Point"}
}