{
  "type": "Feature",
  "properties": {
    "iso:country":"US",
    "sg:address":"10317 Greenbriar Pl",
    "sg:city":"Oklahoma City",
    "sg:classifiers":[
        {
            "category":"Professional",
            "subcategory":"Management & Consulting",
            "type":"Services"
        }
    ],
    "sg:phone":"+1 405 691 3348",
    "sg:postcode":"73159",
    "sg:province":"OK",
    "sg:tags":[
        "business"
    ],
    "wof:name":"Edit",
    "wof:placetype":"venue"
},
  "geometry": {"coordinates":[-97.54613500000001,35.363353],"type":"Point"}
}