{
  "type": "Feature",
  "properties": {
    "iso:country":"US",
    "sg:address":"19 E 34th St",
    "sg:city":"Sand Springs",
    "sg:classifiers":[
        {
            "category":"Cinema",
            "subcategory":"Movie Rental",
            "type":"Entertainment"
        }
    ],
    "sg:phone":"+1 918 245 4902",
    "sg:postcode":"74063",
    "sg:province":"OK",
    "sg:tags":[
        "leasing",
        "video",
        "disc",
        "tape"
    ],
    "wof:name":"Battlefield",
    "wof:placetype":"venue"
},
  "geometry": {"coordinates":[-96.116667,36.113701],"type":"Point"}
}