{
  "type": "Feature",
  "properties": {
    "iso:country":"US",
    "sg:address":"1832 NW 52nd St",
    "sg:city":"Lawton",
    "sg:classifiers":[
        {
            "category":"Shopping",
            "subcategory":"Used Merchandise",
            "type":"Retail Goods"
        }
    ],
    "sg:phone":"+1 580 248 3111",
    "sg:postcode":"73505",
    "sg:province":"OK",
    "sg:tags":[
        "book",
        "rare",
        "dealer"
    ],
    "wof:name":"Lawton Book Stall",
    "wof:placetype":"venue"
},
  "geometry": {"coordinates":[-98.45723599999999,34.631771],"type":"Point"}
}