{
  "type": "Feature",
  "properties": {
    "iso:country":"US",
    "sg:address":"3333 E 30th Pl N",
    "sg:city":"Tulsa",
    "sg:classifiers":[
        {
            "category":"Organizations",
            "subcategory":"Religious Organization",
            "type":"Services"
        }
    ],
    "sg:phone":"+1 918 834 0391",
    "sg:postcode":"74115",
    "sg:province":"OK",
    "sg:tags":[
        "church"
    ],
    "wof:name":"First Baptist Mohawk Church",
    "wof:placetype":"venue"
},
  "geometry": {"coordinates":[-95.93820599999999,36.198007],"type":"Point"}
}