{
  "type": "Feature",
  "properties": {
    "iso:country":"US",
    "sg:address":"501 S Main St",
    "sg:city":"Guymon",
    "sg:classifiers":[
        {
            "category":"Government",
            "subcategory":"Police Station",
            "type":"Public Place"
        }
    ],
    "sg:phone":"+1 580 338 5821",
    "sg:postcode":"73942",
    "sg:province":"OK",
    "sg:tags":[
        "state"
    ],
    "wof:name":"Bureau Of Investigation",
    "wof:placetype":"venue"
},
  "geometry": {"coordinates":[-101.481527,36.673928],"type":"Point"}
}