{
  "type": "Feature",
  "properties": {
    "iso:country":"US",
    "sg:address":"2400 Augusta Ave",
    "sg:city":"Edmond",
    "sg:classifiers":[
        {
            "category":"Professional",
            "subcategory":"Research",
            "type":"Services"
        }
    ],
    "sg:phone":"+1 405 330 0226",
    "sg:postcode":"73034",
    "sg:province":"OK",
    "sg:tags":[
        "organization",
        "noncommercial"
    ],
    "wof:name":"Shockley & Assoc",
    "wof:placetype":"venue"
},
  "geometry": {"coordinates":[-97.448836,35.662833],"type":"Point"}
}