{
  "type": "Feature",
  "properties": {
    "iso:country":"US",
    "sg:address":"1819 W 3rd St",
    "sg:city":"Elk City",
    "sg:classifiers":[
        {
            "category":"Health Services",
            "subcategory":"Hospital",
            "type":"Services"
        }
    ],
    "sg:phone":"+1 580 225 8200",
    "sg:postcode":"73644",
    "sg:province":"OK",
    "sg:tags":[
        "treatment",
        "cancer",
        "center"
    ],
    "wof:name":"Western Oklahoma Cancer Trtmnt",
    "wof:placetype":"venue"
},
  "geometry": {"coordinates":[-99.425548,35.411771],"type":"Point"}
}