{
  "type": "Feature",
  "properties": {
    "addr:full":"113 W Oklahoma Ave Enid OK 73701",
    "addr:housenumber":"113",
    "addr:postcode":"73701",
    "addr:street":"W Oklahoma Ave",
    "iso:country":"US",
    "sg:address":"113 W Oklahoma Ave",
    "sg:city":"Enid",
    "sg:classifiers":[
        {
            "category":"Retail",
            "subcategory":"Repair Shop",
            "type":"Services"
        }
    ],
    "sg:phone":"+1 580 233 3414",
    "sg:postcode":"73701",
    "sg:province":"OK",
    "wof:name":"Darrells Upholstery & Furn RPS",
    "wof:placetype":"venue"
},
  "geometry": {"coordinates":[-97.87975299999999,36.393055],"type":"Point"}
}