{
  "type": "Feature",
  "properties": {
    "iso:country":"US",
    "sg:address":"2200 SW 15th St",
    "sg:city":"Oklahoma City",
    "sg:classifiers":[
        {
            "category":"Real Estate",
            "subcategory":"Real Estate Agent",
            "type":"Services"
        }
    ],
    "sg:phone":"+1 405 232 8578",
    "sg:postcode":"73108",
    "sg:province":"OK",
    "wof:name":"K W Sales & Leasing",
    "wof:placetype":"venue"
},
  "geometry": {"coordinates":[-97.55465,35.449684],"type":"Point"}
}