{
  "type": "Feature",
  "properties": {
    "addr:full":"7 American Way Shawnee OK 74804",
    "addr:housenumber":"7",
    "addr:postcode":"74804",
    "addr:street":"American Way",
    "iso:country":"US",
    "sg:address":"7 American Way",
    "sg:city":"Shawnee",
    "sg:classifiers":[
        {
            "category":"Wholesale",
            "subcategory":"Machinery & Supplies",
            "type":"Manufacturing & Wholesale Goods"
        }
    ],
    "sg:phone":"+1 405 395 0500",
    "sg:postcode":"74804",
    "sg:province":"OK",
    "sg:tags":[
        "field",
        "oil"
    ],
    "wof:name":"G T Engineering",
    "wof:placetype":"venue"
},
  "geometry": {"coordinates":[-96.963956,35.360181],"type":"Point"}
}