{
  "type": "Feature",
  "properties": {
    "iso:country":"US",
    "sg:address":"14712 E Pine St",
    "sg:city":"Tulsa",
    "sg:classifiers":[
        {
            "category":"Organizations",
            "subcategory":"Labor Organization",
            "type":"Services"
        }
    ],
    "sg:phone":"+1 918 234 4980",
    "sg:postcode":"74116",
    "sg:province":"OK",
    "wof:name":"Ironworkers Apprenticeship",
    "wof:placetype":"venue"
},
  "geometry": {"coordinates":[-95.808471,36.176995],"type":"Point"}
}