{
  "type": "Feature",
  "properties": {
    "addr:full":"19836 Linda Ln Harrah OK 73045",
    "addr:housenumber":"19836",
    "addr:postcode":"73045",
    "addr:street":"Linda Ln",
    "iso:country":"US",
    "sg:address":"19836 Linda Ln",
    "sg:city":"Harrah",
    "sg:classifiers":[
        {
            "category":"Professional",
            "subcategory":"Management & Consulting",
            "type":"Services"
        }
    ],
    "sg:phone":"+1 405 454 3233",
    "sg:postcode":"73045",
    "sg:province":"OK",
    "sg:tags":[
        "consultant",
        "educational"
    ],
    "wof:name":"Cargill Consulting",
    "wof:placetype":"venue"
},
  "geometry": {"coordinates":[-97.17816000000001,35.485706],"type":"Point"}
}