{
  "type": "Feature",
  "properties": {
    "iso:country":"US",
    "sg:address":"1040 N Yale Ave",
    "sg:city":"Tulsa",
    "sg:classifiers":[
        {
            "category":"Organizations",
            "subcategory":"Religious Organization",
            "type":"Services"
        }
    ],
    "sg:phone":"+1 918 835 3422",
    "sg:postcode":"74115",
    "sg:province":"OK",
    "wof:name":"Belview Baptist Church",
    "wof:placetype":"venue"
},
  "geometry": {"coordinates":[-95.922558,36.169318],"type":"Point"}
}