{
  "type": "Feature",
  "properties": {
    "addr:full":"2103 S Main St Elk City OK 73644",
    "addr:housenumber":"2103",
    "addr:postcode":"73644",
    "addr:street":"S Main St",
    "iso:country":"US",
    "sg:address":"2103 S Main St",
    "sg:city":"Elk City",
    "sg:classifiers":[
        {
            "category":"Restaurant",
            "type":"Food & Drink"
        }
    ],
    "sg:menulink":"http://www.allmenus.com/ok/elk-city/122466-quiznos-sub/menu/",
    "sg:phone":"+1 580 225 7849",
    "sg:postcode":"73644",
    "sg:province":"OK",
    "sg:tags":[
        "wrap",
        "american",
        "sandwich"
    ],
    "wof:name":"Quiznos Sub",
    "wof:placetype":"venue"
},
  "geometry": {"coordinates":[-99.399958,35.385427],"type":"Point"}
}