{
  "type": "Feature",
  "properties": {
    "iso:country":"US",
    "sg:address":"7122 S Sheridan Rd",
    "sg:city":"Tulsa",
    "sg:classifiers":[
        {
            "category":"Real Estate",
            "subcategory":"Real Estate Agent",
            "type":"Services"
        }
    ],
    "sg:phone":"+1 918 461 2288",
    "sg:postcode":"74133",
    "sg:province":"OK",
    "wof:name":"Landlord Store Inc",
    "wof:placetype":"venue"
},
  "geometry": {"coordinates":[-95.904285,36.060549],"type":"Point"}
}