{
  "type": "Feature",
  "properties": {
    "iso:country":"US",
    "sg:address":"5508 S Lewis Ct",
    "sg:city":"Tulsa",
    "sg:classifiers":[
        {
            "category":"Professional",
            "subcategory":"Lawyer & Legal Services",
            "type":"Services"
        }
    ],
    "sg:phone":"+1 918 742 3939",
    "sg:postcode":"74105",
    "sg:province":"OK",
    "sg:tags":[
        "attorney"
    ],
    "wof:name":"Wilson White Attorney At Law",
    "wof:placetype":"venue"
},
  "geometry": {"coordinates":[-95.957272,36.082407],"type":"Point"}
}