{
  "type": "Feature",
  "properties": {
    "iso:country":"US",
    "sg:address":"2019 N 14th St",
    "sg:city":"Bache",
    "sg:classifiers":[
        {
            "category":"Building & Trades",
            "subcategory":"Cleaning & Sanitation",
            "type":"Services"
        }
    ],
    "sg:phone":"+1 918 423 3706",
    "sg:postcode":"74501",
    "sg:province":"OK",
    "sg:tags":[
        "maintenance"
    ],
    "wof:name":"Farris Janitorial",
    "wof:placetype":"venue"
},
  "geometry": {"coordinates":[-95.743512,34.948632],"type":"Point"}
}