{
  "type": "Feature",
  "properties": {
    "addr:full":"240 State Hwy 152 Mustang OK 73064",
    "addr:housenumber":"240",
    "addr:postcode":"73064",
    "addr:street":"State Hwy 152",
    "iso:country":"US",
    "sg:address":"240 State Hwy 152",
    "sg:city":"Mustang",
    "sg:classifiers":[
        {
            "category":"Home & Garden",
            "subcategory":"Garden Supply",
            "type":"Retail Goods"
        }
    ],
    "sg:phone":"+1 405 376 9550",
    "sg:postcode":"73064",
    "sg:province":"OK",
    "sg:tags":[
        "automobile",
        "used"
    ],
    "wof:name":"Country Equipment",
    "wof:placetype":"venue"
},
  "geometry": {"coordinates":[-97.726044,35.391609],"type":"Point"}
}