{
  "type": "Feature",
  "properties": {
    "iso:country":"US",
    "sg:address":"1331 E 6th St",
    "sg:city":"Tulsa",
    "sg:classifiers":[
        {
            "category":"Professional",
            "subcategory":"Art Services",
            "type":"Services"
        }
    ],
    "sg:phone":"+1 918 582 2775",
    "sg:postcode":"74120",
    "sg:province":"OK",
    "sg:tags":[
        "graphic"
    ],
    "wof:name":"Pre-Press Graphics",
    "wof:placetype":"venue"
},
  "geometry": {"coordinates":[-95.973402,36.152219],"type":"Point"}
}