{
  "type": "Feature",
  "properties": {
    "addr:full":"309 SE 6th St Moore OK 73160",
    "addr:housenumber":"309",
    "addr:postcode":"73160",
    "addr:street":"Se 6Th St",
    "iso:country":"US",
    "sg:address":"309 SE 6th St",
    "sg:city":"Moore",
    "sg:classifiers":[
        {
            "category":"Professional",
            "subcategory":"Business Services",
            "type":"Services"
        }
    ],
    "sg:phone":"+1 405 912 1781",
    "sg:postcode":"73160",
    "sg:province":"OK",
    "sg:tags":[
        "interior",
        "consultant",
        "design",
        "decorator"
    ],
    "wof:name":"Ripples Gifts & Imports",
    "wof:placetype":"venue"
},
  "geometry": {"coordinates":[-97.47976199999999,35.33218],"type":"Point"}
}