{
  "type": "Feature",
  "properties": {
    "addr:full":"11630 E Skelly Dr Tulsa OK 74128",
    "addr:housenumber":"11630",
    "addr:postcode":"74128",
    "addr:street":"E Skelly Dr",
    "iso:country":"US",
    "sg:address":"11630 E Skelly Dr",
    "sg:city":"Tulsa",
    "sg:classifiers":[
        {
            "category":"Restaurant",
            "type":"Food & Drink"
        }
    ],
    "sg:phone":"+1 918 438 8878",
    "sg:postcode":"74128",
    "sg:province":"OK",
    "wof:name":"Hong Kong Bbq & Dimsum",
    "wof:placetype":"venue"
},
  "geometry": {"coordinates":[-95.847281,36.147315],"type":"Point"}
}