{
  "type": "Feature",
  "properties": {
    "iso:country":"US",
    "sg:address":"7500 W Reno Ave",
    "sg:city":"Oklahoma City",
    "sg:classifiers":[
        {
            "category":"Home & Garden",
            "subcategory":"Building Materials",
            "type":"Retail Goods"
        },
        {
            "category":"Arts & Performance",
            "subcategory":"Theater",
            "type":"Entertainment"
        }
    ],
    "sg:phone":"+1 405 495 0292",
    "sg:postcode":"73127",
    "sg:province":"OK",
    "sg:tags":[
        "theatrical",
        "trade",
        "door",
        "contractor"
    ],
    "wof:name":"ABS Wood Specialties Inc",
    "wof:placetype":"venue"
},
  "geometry": {"coordinates":[-97.64317699999999,35.464091],"type":"Point"}
}