{
  "type": "Feature",
  "properties": {
    "addr:full":"113 Shannon St Wayne OK 73080",
    "addr:housenumber":"113",
    "addr:postcode":"73080",
    "addr:street":"Shannon St",
    "iso:country":"US",
    "sg:address":"113 Shannon St",
    "sg:city":"Wayne",
    "sg:classifiers":[
        {
            "category":"Shopping",
            "subcategory":"Used Merchandise",
            "type":"Retail Goods"
        }
    ],
    "sg:phone":"+1 405 449 3455",
    "sg:postcode":"73080",
    "sg:province":"OK",
    "sg:tags":[
        "antique"
    ],
    "wof:name":"Baker's Antiques",
    "wof:placetype":"venue"
},
  "geometry": {"coordinates":[-97.314592,34.918164],"type":"Point"}
}