{
  "type": "Feature",
  "properties": {
    "iso:country":"US",
    "sg:address":"36 NE 50th St",
    "sg:city":"Oklahoma City",
    "sg:classifiers":[
        {
            "category":"Autos & Motor Vehicles",
            "subcategory":"Auto Supplies",
            "type":"Retail Goods"
        }
    ],
    "sg:phone":"+1 405 524 5438",
    "sg:postcode":"73105",
    "sg:province":"OK",
    "sg:tags":[
        "automobile",
        "parts"
    ],
    "sg:website":"www.cableautomotive.com",
    "wof:name":"Cable Automotive Equipment",
    "wof:placetype":"venue"
},
  "geometry": {"coordinates":[-97.510629,35.52225],"type":"Point"}
}