{
  "type": "Feature",
  "properties": {
    "iso:country":"US",
    "sg:address":"7390 S Walker Ave",
    "sg:city":"Oklahoma City",
    "sg:classifiers":[
        {
            "category":"Shopping",
            "subcategory":"Tobacco",
            "type":"Retail Goods"
        }
    ],
    "sg:phone":"+1 405 632 2262",
    "sg:postcode":"73139",
    "sg:province":"OK",
    "sg:tags":[
        "product"
    ],
    "wof:name":"Payless Cigarettes 3",
    "wof:placetype":"venue"
},
  "geometry": {"coordinates":[-97.521181,35.394158],"type":"Point"}
}