{
  "type": "Feature",
  "properties": {
    "iso:country":"US",
    "sg:address":"1804 NW 52nd St",
    "sg:city":"Lawton",
    "sg:classifiers":[
        {
            "category":"Social Services",
            "subcategory":"Child Care",
            "type":"Services"
        }
    ],
    "sg:phone":"+1 580 353 6161",
    "sg:postcode":"73505",
    "sg:province":"OK",
    "sg:tags":[
        "day"
    ],
    "wof:name":"Wonder Years",
    "wof:placetype":"venue"
},
  "geometry": {"coordinates":[-98.457235,34.632432],"type":"Point"}
}