{
  "type": "Feature",
  "properties": {
    "addr:full":"8117 NW 28th Ter Bethany OK 73008",
    "addr:housenumber":"8117",
    "addr:postcode":"73008",
    "addr:street":"Nw 28Th Ter Bethany",
    "iso:country":"US",
    "sg:address":"8117 NW 28th Ter",
    "sg:city":"Bethany",
    "sg:classifiers":[
        {
            "category":"Organizations",
            "subcategory":"Membership Organization",
            "type":"Services"
        }
    ],
    "sg:phone":"+1 405 787 9412",
    "sg:postcode":"73008",
    "sg:province":"OK",
    "wof:name":"Marine Corps League",
    "wof:placetype":"venue"
},
  "geometry": {"coordinates":[-97.660785,35.498912],"type":"Point"}
}