{
  "type": "Feature",
  "properties": {
    "iso:country":"US",
    "sg:address":"1009 Montreal Dr",
    "sg:city":"Yukon",
    "sg:classifiers":[
        {
            "category":"Building & Trades",
            "subcategory":"Construction",
            "type":"Services"
        }
    ],
    "sg:phone":"+1 405 354 0055",
    "sg:postcode":"73099",
    "sg:province":"OK",
    "sg:tags":[
        "general",
        "contractor"
    ],
    "wof:name":"Michael Mc Kinney",
    "wof:placetype":"venue"
},
  "geometry": {"coordinates":[-97.757012,35.488127],"type":"Point"}
}