{
  "type": "Feature",
  "properties": {
    "addr:full":"3200 E Shawnee Rd Muskogee OK 74403",
    "addr:housenumber":"3200",
    "addr:postcode":"74403",
    "addr:street":"E Shawnee Rd",
    "iso:country":"US",
    "sg:address":"3200 E Shawnee Rd",
    "sg:city":"Muskogee",
    "sg:classifiers":[
        {
            "category":"Education",
            "subcategory":"School",
            "type":"Public Place"
        }
    ],
    "sg:phone":"+1 918 684 3750",
    "sg:postcode":"74403",
    "sg:province":"OK",
    "sg:website":"www.mpsi20.org",
    "wof:name":"Muskogee High School",
    "wof:placetype":"venue"
},
  "geometry": {"coordinates":[-95.32340499999999,35.770275],"type":"Point"}
}