{
  "type": "Feature",
  "properties": {
    "iso:country":"US",
    "sg:address":"101 N Main St",
    "sg:city":"Muldrow",
    "sg:classifiers":[
        {
            "category":"Food & Beverages",
            "subcategory":"Groceries & Convenience Stores",
            "type":"Retail Goods"
        }
    ],
    "sg:phone":"+1 918 427 3541",
    "sg:postcode":"74948",
    "sg:province":"OK",
    "wof:name":"Super Stop Gas & Grocery",
    "wof:placetype":"venue"
},
  "geometry": {"coordinates":[-94.59969100000001,35.412225],"type":"Point"}
}