{
  "type": "Feature",
  "properties": {
    "addr:full":"1006 E Main St Antlers OK 74523",
    "addr:housenumber":"1006",
    "addr:postcode":"74523",
    "addr:street":"E Main St",
    "iso:country":"US",
    "sg:address":"1006 E Main St",
    "sg:city":"Antlers",
    "sg:classifiers":[
        {
            "category":"Professional",
            "subcategory":"Advertising",
            "type":"Services"
        }
    ],
    "sg:phone":"+1 580 298 5518",
    "sg:postcode":"74523",
    "sg:province":"OK",
    "wof:name":"4c Net",
    "wof:placetype":"venue"
},
  "geometry": {"coordinates":[-95.608732,34.232156],"type":"Point"}
}