{
  "type": "Feature",
  "properties": {
    "iso:country":"US",
    "sg:address":"220 E Broadway Ave",
    "sg:city":"Thomas",
    "sg:classifiers":[
        {
            "category":"Professional",
            "subcategory":"Business Services",
            "type":"Services"
        }
    ],
    "sg:phone":"+1 580 661 3663",
    "sg:postcode":"73669",
    "sg:province":"OK",
    "wof:name":"Terrier Express Inc",
    "wof:placetype":"venue"
},
  "geometry": {"coordinates":[-98.746071,35.743979],"type":"Point"}
}