{
  "type": "Feature",
  "properties": {
    "iso:country":"US",
    "sg:address":"207 W Main St",
    "sg:city":"Norman",
    "sg:classifiers":[
        {
            "category":"Professional",
            "subcategory":"Lawyer & Legal Services",
            "type":"Services"
        }
    ],
    "sg:phone":"+1 405 364 0564",
    "sg:postcode":"73069",
    "sg:province":"OK",
    "sg:tags":[
        "attorney"
    ],
    "wof:name":"William F Pain",
    "wof:placetype":"venue"
},
  "geometry": {"coordinates":[-97.446693,35.219597],"type":"Point"}
}