{
  "type": "Feature",
  "properties": {
    "iso:country":"US",
    "sg:address":"1645 W Main St",
    "sg:city":"Oklahoma City",
    "sg:classifiers":[
        {
            "category":"Shopping",
            "subcategory":"Computers & Home Electronics",
            "type":"Retail Goods"
        }
    ],
    "sg:phone":"+1 405 319 1846",
    "sg:postcode":"73106",
    "sg:province":"OK",
    "sg:tags":[
        "equipment",
        "dealer"
    ],
    "wof:name":"Computers N Stuff",
    "wof:placetype":"venue"
},
  "geometry": {"coordinates":[-97.542508,35.467934],"type":"Point"}
}