{
  "type": "Feature",
  "properties": {
    "iso:country":"US",
    "sg:address":"1102 N 6th St",
    "sg:city":"Perry",
    "sg:classifiers":[
        {
            "category":"Wholesale",
            "subcategory":"Groceries",
            "type":"Manufacturing & Wholesale Goods"
        }
    ],
    "sg:phone":"+1 580 336 5636",
    "sg:postcode":"73077",
    "sg:province":"OK",
    "wof:name":"Lifestyle Marketing",
    "wof:placetype":"venue"
},
  "geometry": {"coordinates":[-97.285732,36.296901],"type":"Point"}
}