{
  "type": "Feature",
  "properties": {
    "iso:country":"US",
    "sg:address":"8156 S Memorial Dr",
    "sg:city":"Tulsa",
    "sg:classifiers":[
        {
            "category":"Personal",
            "type":"Services"
        }
    ],
    "sg:phone":"+1 918 461 0067",
    "sg:postcode":"74133",
    "sg:province":"OK",
    "wof:name":"Tan Your Moon",
    "wof:placetype":"venue"
},
  "geometry": {"coordinates":[-95.886313,36.041572],"type":"Point"}
}