{
  "type": "Feature",
  "properties": {
    "iso:country":"US",
    "sg:address":"1622 Pinewood Dr",
    "sg:city":"Norman",
    "sg:classifiers":[
        {
            "category":"Retail",
            "subcategory":"Laundry & Dry Cleaning",
            "type":"Services"
        }
    ],
    "sg:phone":"+1 405 366 1869",
    "sg:postcode":"73071",
    "sg:province":"OK",
    "sg:tags":[
        "repairing",
        "rug",
        "carpet"
    ],
    "wof:name":"Scott's Carpet Cleaning Svc",
    "wof:placetype":"venue"
},
  "geometry": {"coordinates":[-97.41783,35.250617],"type":"Point"}
}