{
  "type": "Feature",
  "properties": {
    "addr:full":"8613 S College Ave Tulsa OK 74137",
    "addr:housenumber":"8613",
    "addr:postcode":"74137",
    "addr:street":"S College Ave",
    "iso:country":"US",
    "sg:address":"8613 S College Ave",
    "sg:city":"Tulsa",
    "sg:classifiers":[
        {
            "category":"Building & Trades",
            "subcategory":"Construction",
            "type":"Services"
        }
    ],
    "sg:phone":"+1 918 299 3390",
    "sg:postcode":"74137",
    "sg:province":"OK",
    "sg:tags":[
        "house"
    ],
    "wof:name":"Ashton Homes Inc",
    "wof:placetype":"venue"
},
  "geometry": {"coordinates":[-95.946156,36.036065],"type":"Point"}
}