{
  "type": "Feature",
  "properties": {
    "iso:country":"US",
    "sg:address":"10880 E 45th St",
    "sg:city":"Tulsa",
    "sg:classifiers":[
        {
            "category":"Organizations",
            "subcategory":"Religious Organization",
            "type":"Services"
        }
    ],
    "sg:phone":"+1 918 270 4422",
    "sg:postcode":"74146",
    "sg:province":"OK",
    "wof:name":"Liberated Living Ministries",
    "wof:placetype":"venue"
},
  "geometry": {"coordinates":[-95.855936,36.099826],"type":"Point"}
}