{
  "type": "Feature",
  "properties": {
    "iso:country":"US",
    "sg:address":"711 Evergreen St",
    "sg:city":"Edmond",
    "sg:classifiers":[
        {
            "category":"Professional",
            "subcategory":"Management & Consulting",
            "type":"Services"
        }
    ],
    "sg:phone":"+1 405 314 1452",
    "sg:postcode":"73003",
    "sg:province":"OK",
    "sg:tags":[
        "consultant",
        "educational"
    ],
    "wof:name":"Education Partners For Child",
    "wof:placetype":"venue"
},
  "geometry": {"coordinates":[-97.494079,35.644213],"type":"Point"}
}