{
  "type": "Feature",
  "properties": {
    "iso:country":"US",
    "sg:address":"335 N Smith St",
    "sg:city":"Vinita",
    "sg:classifiers":[
        {
            "category":"Organizations",
            "subcategory":"Religious Organization",
            "type":"Services"
        }
    ],
    "sg:phone":"+1 918 256 6702",
    "sg:postcode":"74301",
    "sg:province":"OK",
    "wof:name":"Trinity Baptist Church",
    "wof:placetype":"venue"
},
  "geometry": {"coordinates":[-95.15637,36.64325],"type":"Point"}
}