{
  "type": "Feature",
  "properties": {
    "addr:full":"209 W Caddo St Cleveland OK 74020",
    "addr:housenumber":"209",
    "addr:postcode":"74020",
    "addr:street":"W Caddo St",
    "iso:country":"US",
    "sg:address":"209 W Caddo St",
    "sg:city":"Cleveland",
    "sg:classifiers":[
        {
            "category":"Restaurant",
            "type":"Food & Drink"
        }
    ],
    "sg:menulink":"http://www.allmenus.com/ok/cleveland/199390-sonic/menu/",
    "sg:phone":"+1 918 358 5233",
    "sg:postcode":"74020",
    "sg:province":"OK",
    "sg:tags":[
        "burger",
        "american"
    ],
    "wof:name":"Sonic",
    "wof:placetype":"venue"
},
  "geometry": {"coordinates":[-96.465587,36.305685],"type":"Point"}
}