{
  "type": "Feature",
  "properties": {
    "iso:country":"US",
    "sg:address":"817 S Elm Pl",
    "sg:city":"Broken Arrow",
    "sg:classifiers":[
        {
            "category":"Health Services",
            "subcategory":"Doctor",
            "type":"Services"
        }
    ],
    "sg:phone":"+1 918 251 9698",
    "sg:postcode":"74012",
    "sg:province":"OK",
    "sg:tags":[
        "medical",
        "osteopathic"
    ],
    "wof:name":"Anklesaria G M",
    "wof:placetype":"venue"
},
  "geometry": {"coordinates":[-95.797371,36.044672],"type":"Point"}
}