{
  "type": "Feature",
  "properties": {
    "iso:country":"US",
    "sg:address":"703 N Saltwell St",
    "sg:city":"Salina",
    "sg:classifiers":[
        {
            "category":"Social Services",
            "subcategory":"Child Care",
            "type":"Services"
        }
    ],
    "sg:phone":"+1 918 434 5605",
    "sg:postcode":"74365",
    "sg:province":"OK",
    "sg:tags":[
        "day"
    ],
    "wof:name":"Tot Spot Day Care",
    "wof:placetype":"venue"
},
  "geometry": {"coordinates":[-95.148639,36.29874],"type":"Point"}
}