{
  "type": "Feature",
  "properties": {
    "addr:full":"208 E Graham Ave Pryor OK 74361",
    "addr:housenumber":"208",
    "addr:postcode":"74361",
    "addr:street":"E Graham Ave",
    "iso:country":"US",
    "sg:address":"208 E Graham Ave",
    "sg:city":"Pryor",
    "sg:classifiers":[
        {
            "category":"Professional",
            "type":"Services"
        }
    ],
    "sg:phone":"+1 918 825 2265",
    "sg:postcode":"74361",
    "sg:province":"OK",
    "sg:tags":[
        "establishment"
    ],
    "wof:name":"Okie Dokie Logos & Promos",
    "wof:placetype":"venue"
},
  "geometry": {"coordinates":[-95.316968,36.307662],"type":"Point"}
}