{
  "type": "Feature",
  "properties": {
    "iso:country":"US",
    "sg:address":"220 N Boston Ave",
    "sg:city":"Tulsa",
    "sg:classifiers":[
        {
            "category":"Manufacturing",
            "subcategory":"Tools & Machinery",
            "type":"Manufacturing & Wholesale Goods"
        }
    ],
    "sg:phone":"+1 918 584 3475",
    "sg:postcode":"74103",
    "sg:province":"OK",
    "sg:tags":[
        "field",
        "oil",
        "equipment"
    ],
    "wof:name":"Larkin Products Inc",
    "wof:placetype":"venue"
},
  "geometry": {"coordinates":[-95.99302900000001,36.159604],"type":"Point"}
}