{
  "type": "Feature",
  "properties": {
    "addr:full":"507 NW Sheridan Rd Lawton OK 73505",
    "addr:housenumber":"507",
    "addr:postcode":"73505",
    "addr:street":"Nw Sheridan Rd",
    "iso:country":"US",
    "sg:address":"507 NW Sheridan Rd",
    "sg:city":"Lawton",
    "sg:classifiers":[
        {
            "category":"Real Estate",
            "subcategory":"Real Estate Agent",
            "type":"Services"
        }
    ],
    "sg:phone":"+1 580 351 2226",
    "sg:postcode":"73505",
    "sg:province":"OK",
    "wof:name":"Buy From Owner Co",
    "wof:placetype":"venue"
},
  "geometry": {"coordinates":[-98.422118,34.615993],"type":"Point"}
}