{
  "type": "Feature",
  "properties": {
    "addr:full":"3131 NW 63rd St Oklahoma City OK 73116",
    "addr:housenumber":"3131",
    "addr:postcode":"73116",
    "addr:street":"Nw 63Rd St",
    "iso:country":"US",
    "sg:address":"3131 NW 63rd St",
    "sg:city":"Oklahoma City",
    "sg:classifiers":[
        {
            "category":"Professional",
            "subcategory":"Lawyer & Legal Services",
            "type":"Services"
        }
    ],
    "sg:phone":"+1 405 842 3381",
    "sg:postcode":"73116",
    "sg:province":"OK",
    "sg:tags":[
        "attorney"
    ],
    "wof:name":"Smith & Warren",
    "wof:placetype":"venue"
},
  "geometry": {"coordinates":[-97.57417100000001,35.53674],"type":"Point"}
}