{
  "type": "Feature",
  "properties": {
    "iso:country":"US",
    "sg:address":"302 W Kansas Ave",
    "sg:city":"Chickasha",
    "sg:classifiers":[
        {
            "category":"Shopping",
            "subcategory":"Discount & Variety Stores",
            "type":"Retail Goods"
        }
    ],
    "sg:phone":"+1 405 818 5189",
    "sg:postcode":"73018",
    "sg:province":"OK",
    "sg:tags":[
        "merchandise",
        "general"
    ],
    "wof:name":"B & BS Emporium",
    "wof:placetype":"venue"
},
  "geometry": {"coordinates":[-97.936858,35.050023],"type":"Point"}
}