{
  "type": "Feature",
  "properties": {
    "iso:country":"US",
    "sg:address":"17211 S 4170 Rd",
    "sg:city":"Claremore",
    "sg:classifiers":[
        {
            "category":"Building & Trades",
            "subcategory":"Construction",
            "type":"Services"
        }
    ],
    "sg:phone":"+1 918 342 0840",
    "sg:postcode":"74017",
    "sg:province":"OK",
    "sg:tags":[
        "excavating",
        "contractor"
    ],
    "wof:name":"Ira M Green Construction",
    "wof:placetype":"venue"
},
  "geometry": {"coordinates":[-95.578842,36.362316],"type":"Point"}
}