{
  "type": "Feature",
  "properties": {
    "iso:country":"US",
    "sg:address":"8521 S Council Rd",
    "sg:city":"Oklahoma City",
    "sg:classifiers":[
        {
            "category":"Building & Trades",
            "subcategory":"Construction",
            "type":"Services"
        }
    ],
    "sg:phone":"+1 405 745 2077",
    "sg:postcode":"73169",
    "sg:province":"OK",
    "sg:tags":[
        "concrete",
        "cutting",
        "breaking",
        "sawing"
    ],
    "wof:name":"A M Concrete Cutting Inc",
    "wof:placetype":"venue"
},
  "geometry": {"coordinates":[-97.653836,35.381341],"type":"Point"}
}