{
  "type": "Feature",
  "properties": {
    "addr:full":"2823 S Agnew Ave Oklahoma City OK 73108",
    "addr:housenumber":"2823",
    "addr:postcode":"73108",
    "addr:street":"S Agnew Ave",
    "iso:country":"US",
    "sg:address":"2823 S Agnew Ave",
    "sg:city":"Oklahoma City",
    "sg:classifiers":[
        {
            "category":"Restaurant",
            "type":"Food & Drink"
        }
    ],
    "sg:phone":"+1 405 631 2888",
    "sg:postcode":"73108",
    "sg:province":"OK",
    "sg:tags":[
        "cafe"
    ],
    "wof:name":"Hog House",
    "wof:placetype":"venue"
},
  "geometry": {"coordinates":[-97.554692,35.436454],"type":"Point"}
}