{
  "type": "Feature",
  "properties": {
    "iso:country":"US",
    "sg:address":"4815 S Sheridan Rd",
    "sg:city":"Tulsa",
    "sg:classifiers":[
        {
            "category":"Social Services",
            "type":"Services"
        }
    ],
    "sg:phone":"+1 918 384 0980",
    "sg:postcode":"74145",
    "sg:province":"OK",
    "sg:tags":[
        "senior",
        "citizen"
    ],
    "wof:name":"Home Instead Senior Care",
    "wof:placetype":"venue"
},
  "geometry": {"coordinates":[-95.904331,36.094091],"type":"Point"}
}