{
  "type": "Feature",
  "properties": {
    "iso:country":"US",
    "sg:address":"121 W 3rd St",
    "sg:city":"Tulsa",
    "sg:classifiers":[
        {
            "category":"Banks & Credit Unions",
            "subcategory":"Investment Brokerage",
            "type":"Services"
        },
        {
            "category":"Banks & Credit Unions",
            "subcategory":"Bank",
            "type":"Services"
        },
        {
            "category":"Banks & Credit Unions",
            "subcategory":"Financial Services",
            "type":"Services"
        }
    ],
    "sg:phone":"+1 918 582 4344",
    "sg:postcode":"74103",
    "sg:province":"OK",
    "sg:tags":[
        "mutual",
        "retirement",
        "broker",
        "fund",
        "planning",
        "security",
        "bond",
        "stock"
    ],
    "sg:website":"http://www.edwardjones.com/en_US/fa/index.html&CIRN=409512",
    "wof:name":"Edward Jones - Financial Advisor: CHUCK GRAHAM",
    "wof:placetype":"venue"
},
  "geometry": {"coordinates":[-95.992534,36.152911],"type":"Point"}
}