{
  "type": "Feature",
  "properties": {
    "iso:country":"US",
    "sg:address":"3134 NW 23rd St",
    "sg:city":"Oklahoma City",
    "sg:classifiers":[
        {
            "category":"Professional",
            "subcategory":"Lawyer & Legal Services",
            "type":"Services"
        }
    ],
    "sg:phone":"+1 405 943 9894",
    "sg:postcode":"73107",
    "sg:province":"OK",
    "wof:name":"Johanning Paul & Byron Law Off",
    "wof:placetype":"venue"
},
  "geometry": {"coordinates":[-97.571516,35.493101],"type":"Point"}
}