{
  "type": "Feature",
  "properties": {
    "addr:full":"20911 W 8th St Sand Springs OK 74063",
    "addr:housenumber":"20911",
    "addr:postcode":"74063",
    "addr:street":"W 8Th St",
    "iso:country":"US",
    "sg:address":"20911 W 8th St",
    "sg:city":"Sand Springs",
    "sg:classifiers":[
        {
            "category":"Food & Beverages",
            "subcategory":"Groceries & Convenience Stores",
            "type":"Retail Goods"
        }
    ],
    "sg:phone":"+1 918 245 0616",
    "sg:postcode":"74063",
    "sg:province":"OK",
    "wof:name":"Lakeside Food Mart",
    "wof:placetype":"venue"
},
  "geometry": {"coordinates":[-96.226219,36.152672],"type":"Point"}
}