{
  "type": "Feature",
  "properties": {
    "iso:country":"US",
    "sg:address":"7800 NW 36th St",
    "sg:city":"Bethany",
    "sg:classifiers":[
        {
            "category":"Organizations",
            "subcategory":"Religious Organization",
            "type":"Services"
        }
    ],
    "sg:phone":"+1 405 495 1104",
    "sg:postcode":"73008",
    "sg:province":"OK",
    "sg:website":"www.versebyverse.org",
    "wof:name":"Maranatha Church",
    "wof:placetype":"venue"
},
  "geometry": {"coordinates":[-97.654261,35.507796],"type":"Point"}
}