{
  "type": "Feature",
  "properties": {
    "iso:country":"US",
    "sg:address":"2605 W Main St",
    "sg:city":"Jenks",
    "sg:classifiers":[
        {
            "category":"Health Services",
            "subcategory":"Doctor",
            "type":"Services"
        }
    ],
    "sg:phone":"+1 918 298 2336",
    "sg:postcode":"74037",
    "sg:province":"OK",
    "sg:tags":[
        "osteopathic"
    ],
    "wof:name":"Vineyard Kyra",
    "wof:placetype":"venue"
},
  "geometry": {"coordinates":[-96.008752,36.024667],"type":"Point"}
}