{
  "type": "Feature",
  "properties": {
    "iso:country":"US",
    "sg:address":"400 W Locust St",
    "sg:city":"Stilwell",
    "sg:classifiers":[
        {
            "category":"Shopping",
            "subcategory":"Pharmacy",
            "type":"Retail Goods"
        }
    ],
    "sg:phone":"+1 918 696 3186",
    "sg:postcode":"74960",
    "sg:province":"OK",
    "wof:name":"Pharmacy",
    "wof:placetype":"venue"
},
  "geometry": {"coordinates":[-94.631892,35.808549],"type":"Point"}
}