{
  "type": "Feature",
  "properties": {
    "iso:country":"US",
    "sg:address":"2715 N 1st Ave",
    "sg:city":"Durant",
    "sg:classifiers":[
        {
            "category":"Utilities",
            "subcategory":"Fuel Oil & Lpg",
            "type":"Services"
        }
    ],
    "sg:phone":"+1 580 924 0430",
    "sg:postcode":"74701",
    "sg:province":"OK",
    "sg:tags":[
        "liquefied",
        "gas",
        "petroleum"
    ],
    "wof:name":"Franks Grocery",
    "wof:placetype":"venue"
},
  "geometry": {"coordinates":[-96.372995,34.018162],"type":"Point"}
}