{
  "type": "Feature",
  "properties": {
    "iso:country":"US",
    "sg:address":"2801 Coltrane Pl",
    "sg:city":"Edmond",
    "sg:classifiers":[
        {
            "category":"Professional",
            "subcategory":"Advertising",
            "type":"Services"
        }
    ],
    "sg:phone":"+1 405 348 1764",
    "sg:postcode":"73034",
    "sg:province":"OK",
    "sg:tags":[
        "mail",
        "direct"
    ],
    "wof:name":"Accumailing Service LLC",
    "wof:placetype":"venue"
},
  "geometry": {"coordinates":[-97.443108,35.649567],"type":"Point"}
}