{
  "type": "Feature",
  "properties": {
    "addr:full":"8222 E 71st St Tulsa OK 74133",
    "addr:housenumber":"8222",
    "addr:postcode":"74133",
    "addr:street":"E 71St St",
    "iso:country":"US",
    "sg:address":"8222 E 71st St",
    "sg:city":"Tulsa",
    "sg:classifiers":[
        {
            "category":"Personal",
            "subcategory":"Beauty Salon",
            "type":"Services"
        }
    ],
    "sg:phone":"+1 918 254 5570",
    "sg:postcode":"74133",
    "sg:province":"OK",
    "sg:tags":[
        "manicuring"
    ],
    "wof:name":"California Nails",
    "wof:placetype":"venue"
},
  "geometry": {"coordinates":[-95.885229,36.060818],"type":"Point"}
}