{
  "type": "Feature",
  "properties": {
    "iso:country":"US",
    "sg:address":"7130 Terminal Dr",
    "sg:city":"Oklahoma City",
    "sg:classifiers":[
        {
            "category":"Airport",
            "type":"Transportation"
        }
    ],
    "sg:phone":"+1 405 681 0937",
    "sg:postcode":"73159",
    "sg:province":"OK",
    "sg:tags":[
        "aircraft",
        "support",
        "ground"
    ],
    "wof:name":"Evergreen International Eagle",
    "wof:placetype":"venue"
},
  "geometry": {"coordinates":[-97.598364,35.404192],"type":"Point"}
}