{
  "type": "Feature",
  "properties": {
    "iso:country":"US",
    "sg:address":"8741 S Lewis Ave",
    "sg:city":"Tulsa",
    "sg:classifiers":[
        {
            "category":"Restaurant",
            "type":"Food & Drink"
        }
    ],
    "sg:phone":"+1 918 299 5243",
    "sg:postcode":"74137",
    "sg:province":"OK",
    "wof:name":"Hunan Delivery",
    "wof:placetype":"venue"
},
  "geometry": {"coordinates":[-95.954484,36.036112],"type":"Point"}
}