{
  "type": "Feature",
  "properties": {
    "iso:country":"US",
    "sg:address":"120 N Robinson Ave",
    "sg:city":"Oklahoma City",
    "sg:classifiers":[
        {
            "category":"Real Estate",
            "subcategory":"Real Estate Operator",
            "type":"Services"
        }
    ],
    "sg:phone":"+1 405 235 2500",
    "sg:postcode":"73102",
    "sg:province":"OK",
    "sg:tags":[
        "building",
        "parks"
    ],
    "wof:name":"First National Ctr",
    "wof:placetype":"venue"
},
  "geometry": {"coordinates":[-97.516346,35.468589],"type":"Point"}
}