{
  "type": "Feature",
  "properties": {
    "iso:country":"US",
    "sg:address":"13650 W Highland Ave",
    "sg:city":"Tonkawa",
    "sg:classifiers":[
        {
            "category":"Professional",
            "subcategory":"Business Services",
            "type":"Services"
        }
    ],
    "sg:phone":"+1 580 763 7100",
    "sg:postcode":"74653",
    "sg:province":"OK",
    "sg:tags":[
        "design"
    ],
    "wof:name":"Technical Design Solutions",
    "wof:placetype":"venue"
},
  "geometry": {"coordinates":[-97.29809,36.709977],"type":"Point"}
}