{
  "type": "Feature",
  "properties": {
    "addr:full":"130 W Main St Ada OK 74820",
    "addr:housenumber":"130",
    "addr:postcode":"74820",
    "addr:street":"W Main St",
    "iso:country":"US",
    "sg:address":"130 W Main St",
    "sg:city":"Ada",
    "sg:classifiers":[
        {
            "category":"Arts & Performance",
            "subcategory":"Theater",
            "type":"Entertainment"
        }
    ],
    "sg:phone":"+1 580 332 8108",
    "sg:postcode":"74820",
    "sg:province":"OK",
    "wof:name":"Mcswain Musical Theatre",
    "wof:placetype":"venue"
},
  "geometry": {"coordinates":[-96.679894,34.774569],"type":"Point"}
}