{
  "type": "Feature",
  "properties": {
    "addr:full":"5583 NW Expy Warr Acres OK 73132",
    "addr:housenumber":"5583",
    "addr:postcode":"73132",
    "addr:street":"Nw Expy",
    "iso:country":"US",
    "sg:address":"5583 NW Expy",
    "sg:city":"Warr Acres",
    "sg:classifiers":[
        {
            "category":"Health Services",
            "subcategory":"Chiropractor",
            "type":"Services"
        }
    ],
    "sg:phone":"+1 405 773 3131",
    "sg:postcode":"73132",
    "sg:province":"OK",
    "wof:name":"Seyoung Kim DC",
    "wof:placetype":"venue"
},
  "geometry": {"coordinates":[-97.610978,35.545986],"type":"Point"}
}