{
  "type": "Feature",
  "properties": {
    "addr:full":"17808 State Hwy 102 Shawnee OK 74801",
    "addr:housenumber":"17808",
    "addr:postcode":"74801",
    "addr:street":"State Hwy 102",
    "iso:country":"US",
    "sg:address":"17808 State Hwy 102",
    "sg:city":"Shawnee",
    "sg:classifiers":[
        {
            "category":"Personal",
            "subcategory":"Beauty Salon",
            "type":"Services"
        }
    ],
    "sg:phone":"+1 405 273 9485",
    "sg:postcode":"74801",
    "sg:province":"OK",
    "wof:name":"Pampering U Salon",
    "wof:placetype":"venue"
},
  "geometry": {"coordinates":[-97.05395900000001,35.306903],"type":"Point"}
}