{
  "type": "Feature",
  "properties": {
    "iso:country":"US",
    "sg:address":"4000 SE 29th St",
    "sg:city":"Oklahoma City",
    "sg:classifiers":[
        {
            "category":"Retail",
            "subcategory":"Funeral Services",
            "type":"Services"
        }
    ],
    "sg:phone":"+1 405 677 8384",
    "sg:postcode":"73115",
    "sg:province":"OK",
    "wof:name":"SCI",
    "wof:placetype":"venue"
},
  "geometry": {"coordinates":[-97.443637,35.435303],"type":"Point"}
}