{
  "type": "Feature",
  "properties": {
    "iso:country":"US",
    "sg:address":"7446 E 46th Pl",
    "sg:city":"Tulsa",
    "sg:classifiers":[
        {
            "category":"Professional",
            "subcategory":"Computer Services",
            "type":"Services"
        }
    ],
    "sg:phone":"+1 918 627 6611",
    "sg:postcode":"74145",
    "sg:province":"OK",
    "sg:tags":[
        "repair"
    ],
    "sg:website":"www.onyximaging.com",
    "wof:name":"Onyx Corp",
    "wof:placetype":"venue"
},
  "geometry": {"coordinates":[-95.887028,36.096404],"type":"Point"}
}