{
  "type": "Feature",
  "properties": {
    "iso:country":"US",
    "sg:address":"3121 N Pennsylvania Ave",
    "sg:city":"Oklahoma City",
    "sg:classifiers":[
        {
            "category":"Manufacturing",
            "subcategory":"Apparel",
            "type":"Manufacturing & Wholesale Goods"
        }
    ],
    "sg:phone":"+1 405 524 9552",
    "sg:postcode":"73112",
    "sg:province":"OK",
    "sg:tags":[
        "drapery",
        "contractor"
    ],
    "wof:name":"Capitol Stage Equipment Co",
    "wof:placetype":"venue"
},
  "geometry": {"coordinates":[-97.547766,35.501627],"type":"Point"}
}