{
  "type": "Feature",
  "properties": {
    "iso:country":"US",
    "sg:address":"1402 E Sunrise Ave",
    "sg:city":"Stillwater",
    "sg:classifiers":[
        {
            "category":"Education",
            "subcategory":"School",
            "type":"Public Place"
        }
    ],
    "sg:phone":"+1 405 533 6390",
    "sg:postcode":"74075",
    "sg:province":"OK",
    "wof:name":"Skyline Elementary School",
    "wof:placetype":"venue"
},
  "geometry": {"coordinates":[-97.04200299999999,36.137825],"type":"Point"}
}