{
  "type": "Feature",
  "properties": {
    "addr:full":"3000 N Veterans Dr Altus OK 73521",
    "addr:housenumber":"3000",
    "addr:postcode":"73521",
    "addr:street":"N Veterans Dr",
    "iso:country":"US",
    "sg:address":"3000 N Veterans Dr",
    "sg:city":"Altus",
    "sg:classifiers":[
        {
            "category":"Education",
            "subcategory":"School",
            "type":"Public Place"
        }
    ],
    "sg:phone":"+1 580 481 2198",
    "sg:postcode":"73521",
    "sg:province":"OK",
    "wof:name":"Rivers School",
    "wof:placetype":"venue"
},
  "geometry": {"coordinates":[-99.298817,34.667644],"type":"Point"}
}