{
  "type": "Feature",
  "properties": {
    "iso:country":"US",
    "sg:address":"10300 E 81st St",
    "sg:city":"Tulsa",
    "sg:classifiers":[
        {
            "category":"Building & Trades",
            "subcategory":"Construction",
            "type":"Services"
        }
    ],
    "sg:phone":"+1 918 252 9534",
    "sg:postcode":"74133",
    "sg:province":"OK",
    "sg:tags":[
        "general",
        "contractor"
    ],
    "wof:name":"Flintco Inc",
    "wof:placetype":"venue"
},
  "geometry": {"coordinates":[-95.86032,36.046444],"type":"Point"}
}