{
  "type": "Feature",
  "properties": {
    "iso:country":"US",
    "sg:address":"3300 Williams Ave",
    "sg:city":"Woodward",
    "sg:classifiers":[
        {
            "category":"Bars & Pubs",
            "type":"Food & Drink"
        }
    ],
    "sg:phone":"+1 580 256 3315",
    "sg:postcode":"73801",
    "sg:province":"OK",
    "wof:name":"Greens Sports Bar",
    "wof:placetype":"venue"
},
  "geometry": {"coordinates":[-99.380658,36.413686],"type":"Point"}
}