{
  "type": "Feature",
  "properties": {
    "iso:country":"US",
    "sg:address":"5506 N Rockwell Ave",
    "sg:city":"Bethany",
    "sg:classifiers":[
        {
            "category":"Farming",
            "subcategory":"Livestock Farm",
            "type":"Manufacturing & Wholesale Goods"
        }
    ],
    "sg:phone":"+1 405 348 1035",
    "sg:postcode":"73008",
    "sg:province":"OK",
    "sg:tags":[
        "horse",
        "other",
        "equine"
    ],
    "wof:name":"Oklahoma Quarter Horse Assn",
    "wof:placetype":"venue"
},
  "geometry": {"coordinates":[-97.636612,35.526102],"type":"Point"}
}