{
  "type": "Feature",
  "properties": {
    "iso:country":"US",
    "sg:address":"12817 SE 54th St",
    "sg:city":"Choctaw",
    "sg:classifiers":[
        {
            "category":"Manufacturing",
            "subcategory":"Metals",
            "type":"Manufacturing & Wholesale Goods"
        }
    ],
    "sg:phone":"+1 405 733 0307",
    "sg:postcode":"73020",
    "sg:province":"OK",
    "sg:tags":[
        "building",
        "prefabricated",
        "mfg"
    ],
    "wof:name":"W & W Welding",
    "wof:placetype":"venue"
},
  "geometry": {"coordinates":[-97.30648100000001,35.411904],"type":"Point"}
}