{
  "type": "Feature",
  "properties": {
    "addr:full":"15 N Elm St Sapulpa OK 74066",
    "addr:housenumber":"15",
    "addr:postcode":"74066",
    "addr:street":"N Elm St",
    "iso:country":"US",
    "sg:address":"15 N Elm St",
    "sg:city":"Sapulpa",
    "sg:classifiers":[
        {
            "category":"Professional",
            "subcategory":"Accounting & Tax Preparation",
            "type":"Services"
        },
        {
            "category":"Banks & Credit Unions",
            "subcategory":"Financial Services",
            "type":"Services"
        }
    ],
    "sg:phone":"+1 918 227 1400",
    "sg:postcode":"74066",
    "sg:province":"OK",
    "sg:tags":[
        "return",
        "preparation-business",
        "billing",
        "accountants-certified",
        "bookkeeping",
        "public"
    ],
    "wof:name":"Mayberry Accounting Services",
    "wof:placetype":"venue"
},
  "geometry": {"coordinates":[-96.11023400000001,35.998855],"type":"Point"}
}