{
  "type": "Feature",
  "properties": {
    "iso:country":"US",
    "sg:address":"501 N 1st St",
    "sg:city":"Okarche",
    "sg:phone":"+1 405 263 7662",
    "sg:postcode":"73762",
    "sg:province":"OK",
    "sg:tags":[
        "farm",
        "wheat",
        "beef",
        "feedlot",
        "cattle"
    ],
    "wof:name":"Paul Knecht",
    "wof:placetype":"venue"
},
  "geometry": {"coordinates":[-97.97157,35.731486],"type":"Point"}
}