{
  "type": "Feature",
  "properties": {
    "addr:full":"319 Novak Cir Yukon OK 73099",
    "addr:housenumber":"319",
    "addr:postcode":"73099",
    "addr:street":"Novak Cir",
    "iso:country":"US",
    "sg:address":"319 Novak Cir",
    "sg:city":"Yukon",
    "sg:classifiers":[
        {
            "category":"Building & Trades",
            "subcategory":"Construction",
            "type":"Services"
        }
    ],
    "sg:phone":"+1 405 354 0334",
    "sg:postcode":"73099",
    "sg:province":"OK",
    "sg:tags":[
        "carpentry",
        "contractor"
    ],
    "wof:name":"Chapman Custom Cabinet LLC",
    "wof:placetype":"venue"
},
  "geometry": {"coordinates":[-97.747651,35.498626],"type":"Point"}
}