{
  "type": "Feature",
  "properties": {
    "iso:country":"US",
    "sg:address":"1827 N Morton Ave",
    "sg:city":"Okmulgee",
    "sg:classifiers":[
        {
            "category":"Social Services",
            "subcategory":"Child Care",
            "type":"Services"
        }
    ],
    "sg:phone":"+1 918 759 2303",
    "sg:postcode":"74447",
    "sg:province":"OK",
    "sg:tags":[
        "day"
    ],
    "wof:name":"Joyces Daycare",
    "wof:placetype":"venue"
},
  "geometry": {"coordinates":[-95.97307499999999,35.644524],"type":"Point"}
}