{
  "type": "Feature",
  "properties": {
    "addr:full":"1220 W Will Rogers Blvd Claremore OK 74017",
    "addr:housenumber":"1220",
    "addr:postcode":"74017",
    "addr:street":"W Will Rogers Blvd",
    "iso:country":"US",
    "sg:address":"1220 W Will Rogers Blvd",
    "sg:city":"Claremore",
    "sg:classifiers":[
        {
            "category":"Restaurant",
            "type":"Food & Drink"
        }
    ],
    "sg:menulink":"http://www.allmenus.com/ok/claremore/196614-mcdonalds/menu/",
    "sg:postcode":"74017",
    "sg:province":"OK",
    "sg:tags":[
        "burger",
        "american"
    ],
    "wof:name":"McDonald's",
    "wof:placetype":"venue"
},
  "geometry": {"coordinates":[-95.62397799999999,36.315866],"type":"Point"}
}