{
  "type": "Feature",
  "properties": {
    "iso:country":"US",
    "sg:address":"517 E Rogers Dr",
    "sg:city":"Stillwater",
    "sg:classifiers":[
        {
            "category":"Retail",
            "subcategory":"Portrait Studio",
            "type":"Services"
        }
    ],
    "sg:phone":"+1 405 377 1284",
    "sg:postcode":"74075",
    "sg:province":"OK",
    "sg:tags":[
        "photo"
    ],
    "wof:name":"Photography By Jalene",
    "wof:placetype":"venue"
},
  "geometry": {"coordinates":[-97.052674,36.168605],"type":"Point"}
}