{
  "type": "Feature",
  "properties": {
    "iso:country":"US",
    "sg:address":"214 E Broadway Ave",
    "sg:city":"Enid",
    "sg:classifiers":[
        {
            "category":"Freight",
            "type":"Transportation"
        }
    ],
    "sg:phone":"+1 580 233 0929",
    "sg:postcode":"73701",
    "sg:province":"OK",
    "sg:tags":[
        "special"
    ],
    "wof:name":"Superior Storage",
    "wof:placetype":"venue"
},
  "geometry": {"coordinates":[-97.87537,36.396695],"type":"Point"}
}