{
  "type": "Feature",
  "properties": {
    "addr:full":"421 Timber Ridge Rd Edmond OK 73034",
    "addr:housenumber":"421",
    "addr:postcode":"73034",
    "addr:street":"Timber Ridge Rd",
    "iso:country":"US",
    "sg:address":"421 Timber Ridge Rd",
    "sg:city":"Edmond",
    "sg:classifiers":[
        {
            "category":"Professional",
            "subcategory":"Art Services",
            "type":"Services"
        }
    ],
    "sg:phone":"+1 405 348 5942",
    "sg:postcode":"73034",
    "sg:province":"OK",
    "sg:tags":[
        "commercial",
        "design"
    ],
    "wof:name":"Studio B",
    "wof:placetype":"venue"
},
  "geometry": {"coordinates":[-97.47483099999999,35.674143],"type":"Point"}
}