{
  "type": "Feature",
  "properties": {
    "addr:full":"700 N Greenwood Ave Tulsa OK 74106",
    "addr:housenumber":"700",
    "addr:postcode":"74106",
    "addr:street":"N Greenwood Ave",
    "iso:country":"US",
    "sg:address":"700 N Greenwood Ave",
    "sg:city":"Tulsa",
    "sg:classifiers":[
        {
            "category":"Education",
            "subcategory":"College",
            "type":"Public Place"
        }
    ],
    "sg:phone":"+1 918 594 8270",
    "sg:postcode":"74106",
    "sg:province":"OK",
    "sg:tags":[
        "state",
        "university"
    ],
    "wof:name":"Student Services",
    "wof:placetype":"venue"
},
  "geometry": {"coordinates":[-95.986786,36.165223],"type":"Point"}
}