{
  "type": "Feature",
  "properties": {
    "iso:country":"US",
    "sg:address":"2520 W Cameron St",
    "sg:city":"Tulsa",
    "sg:classifiers":[
        {
            "category":"Personal",
            "subcategory":"Beauty Salon",
            "type":"Services"
        }
    ],
    "sg:phone":"+1 918 583 7497",
    "sg:postcode":"74127",
    "sg:province":"OK",
    "sg:tags":[
        "shop"
    ],
    "wof:name":"C&J Beauty and Skincare",
    "wof:placetype":"venue"
},
  "geometry": {"coordinates":[-96.023805,36.157903],"type":"Point"}
}