{
  "type": "Feature",
  "properties": {
    "iso:country":"US",
    "sg:address":"100 N Fir Ave",
    "sg:city":"Broken Arrow",
    "sg:classifiers":[
        {
            "category":"Recreation",
            "type":"Entertainment"
        }
    ],
    "sg:phone":"+1 918 259 8696",
    "sg:postcode":"74012",
    "sg:province":"OK",
    "sg:tags":[
        "pool",
        "swimming"
    ],
    "wof:name":"Broken Arrow Country Aire Pool",
    "wof:placetype":"venue"
},
  "geometry": {"coordinates":[-95.821947,36.054086],"type":"Point"}
}