{
  "type": "Feature",
  "properties": {
    "iso:country":"US",
    "sg:address":"304 W Cherokee St",
    "sg:city":"Wagoner",
    "sg:classifiers":[
        {
            "category":"Home & Garden",
            "subcategory":"Garden Supply",
            "type":"Retail Goods"
        }
    ],
    "sg:phone":"+1 918 485 8815",
    "sg:postcode":"74467",
    "sg:province":"OK",
    "sg:tags":[
        "supp",
        "repair"
    ],
    "wof:name":"Wagoner Small Engine",
    "wof:placetype":"venue"
},
  "geometry": {"coordinates":[-95.380509,35.959519],"type":"Point"}
}