{
  "type": "Feature",
  "properties": {
    "iso:country":"US",
    "sg:address":"19701 E 91st St",
    "sg:city":"Broken Arrow",
    "sg:classifiers":[
        {
            "category":"Manufacturing",
            "subcategory":"Tools & Machinery",
            "type":"Manufacturing & Wholesale Goods"
        }
    ],
    "sg:phone":"+1 918 455 7141",
    "sg:postcode":"74014",
    "sg:province":"OK",
    "sg:tags":[
        "machine",
        "shop"
    ],
    "wof:name":"G & N Mfg Co",
    "wof:placetype":"venue"
},
  "geometry": {"coordinates":[-95.757805,36.031986],"type":"Point"}
}