{
  "type": "Feature",
  "properties": {
    "iso:country":"US",
    "sg:address":"2502 S 4th St",
    "sg:city":"Chickasha",
    "sg:classifiers":[
        {
            "category":"Mining & Drilling",
            "type":"Manufacturing & Wholesale Goods"
        }
    ],
    "sg:phone":"+1 405 222 5040",
    "sg:postcode":"73018",
    "sg:province":"OK",
    "sg:tags":[
        "gas",
        "oil",
        "exploration"
    ],
    "wof:name":"Apache Corporation",
    "wof:placetype":"venue"
},
  "geometry": {"coordinates":[-97.935164,35.025515],"type":"Point"}
}