{
  "type": "Feature",
  "properties": {
    "iso:country":"US",
    "sg:address":"223 6th St",
    "sg:city":"Medford",
    "sg:phone":"+1 580 395 2004",
    "sg:postcode":"73759",
    "sg:province":"OK",
    "sg:tags":[
        "farm",
        "wheat"
    ],
    "wof:name":"Cris R Wirtz",
    "wof:placetype":"venue"
},
  "geometry": {"coordinates":[-97.74135200000001,36.808061],"type":"Point"}
}