{
  "type": "Feature",
  "properties": {
    "iso:country":"US",
    "sg:address":"114 S Berry Rd",
    "sg:city":"Norman",
    "sg:classifiers":[
        {
            "category":"Health Services",
            "subcategory":"Doctor",
            "type":"Services"
        }
    ],
    "sg:phone":"+1 405 321 2735",
    "sg:postcode":"73069",
    "sg:province":"OK",
    "sg:tags":[
        "dentist"
    ],
    "wof:name":"Shannon Timothy M",
    "wof:placetype":"venue"
},
  "geometry": {"coordinates":[-97.459045,35.217537],"type":"Point"}
}