{
  "type": "Feature",
  "properties": {
    "iso:country":"US",
    "sg:address":"5350 S Western Ave",
    "sg:city":"Oklahoma City",
    "sg:classifiers":[
        {
            "category":"Organizations",
            "subcategory":"Labor Organization",
            "type":"Services"
        }
    ],
    "sg:phone":"+1 405 616 0141",
    "sg:postcode":"73109",
    "sg:province":"OK",
    "wof:name":"Western Oklahoma Bldg & Cnstr",
    "wof:placetype":"venue"
},
  "geometry": {"coordinates":[-97.530125,35.413012],"type":"Point"}
}