{
  "type": "Feature",
  "properties": {
    "iso:country":"US",
    "sg:address":"18646 Alameda St",
    "sg:city":"Norman",
    "sg:classifiers":[
        {
            "category":"Building & Trades",
            "subcategory":"Construction",
            "type":"Services"
        }
    ],
    "sg:phone":"+1 405 360 1370",
    "sg:postcode":"73026",
    "sg:province":"OK",
    "sg:tags":[
        "contractor"
    ],
    "wof:name":"Bayliss Roofing Company",
    "wof:placetype":"venue"
},
  "geometry": {"coordinates":[-97.16940099999999,35.217485],"type":"Point"}
}