{
  "type": "Feature",
  "properties": {
    "addr:full":"1727 S Agnew Ave Oklahoma City OK 73108",
    "addr:housenumber":"1727",
    "addr:postcode":"73108",
    "addr:street":"S Agnew Ave",
    "iso:country":"US",
    "sg:address":"1727 S Agnew Ave",
    "sg:city":"Oklahoma City",
    "sg:classifiers":[
        {
            "category":"Home & Garden",
            "subcategory":"Furniture",
            "type":"Retail Goods"
        }
    ],
    "sg:phone":"+1 405 616 2000",
    "sg:postcode":"73108",
    "sg:province":"OK",
    "wof:name":"Shylo Bedding",
    "wof:placetype":"venue"
},
  "geometry": {"coordinates":[-97.554697,35.448447],"type":"Point"}
}