{
  "type": "Feature",
  "properties": {
    "iso:country":"US",
    "sg:address":"209 N Eastern Ave",
    "sg:city":"Moore",
    "sg:classifiers":[
        {
            "category":"Retail",
            "subcategory":"Auto Repair",
            "type":"Services"
        }
    ],
    "sg:phone":"+1 405 799 1258",
    "sg:postcode":"73160",
    "sg:province":"OK",
    "sg:tags":[
        "repairing",
        "automobile",
        "general"
    ],
    "wof:name":"R W Automotive",
    "wof:placetype":"venue"
},
  "geometry": {"coordinates":[-97.476927,35.340328],"type":"Point"}
}