{
  "type": "Feature",
  "properties": {
    "addr:full":"404 Garland Ct Norman OK 73072",
    "addr:housenumber":"404",
    "addr:postcode":"73072",
    "addr:street":"Garland Ct",
    "iso:country":"US",
    "sg:address":"404 Garland Ct",
    "sg:city":"Norman",
    "sg:classifiers":[
        {
            "category":"Manufacturing",
            "subcategory":"Chemicals & Compounds",
            "type":"Manufacturing & Wholesale Goods"
        }
    ],
    "sg:phone":"+1 405 329 5513",
    "sg:postcode":"73072",
    "sg:province":"OK",
    "sg:tags":[
        "pharmaceutical",
        "drug",
        "manufacturer"
    ],
    "wof:name":"Abbott Laboratories",
    "wof:placetype":"venue"
},
  "geometry": {"coordinates":[-97.497218,35.214277],"type":"Point"}
}