{
  "type": "Feature",
  "properties": {
    "iso:country":"US",
    "sg:address":"13450 S 640 Rd",
    "sg:city":"Miami",
    "sg:classifiers":[
        {
            "category":"Building & Trades",
            "subcategory":"Landscaping Services",
            "type":"Services"
        }
    ],
    "sg:phone":"+1 918 533 0333",
    "sg:postcode":"74354",
    "sg:province":"OK",
    "sg:tags":[
        "lawn",
        "landscape",
        "contractor"
    ],
    "wof:name":"Custom Design Landscaping",
    "wof:placetype":"venue"
},
  "geometry": {"coordinates":[-94.734155,36.814961],"type":"Point"}
}