{
  "type": "Feature",
  "properties": {
    "iso:country":"US",
    "sg:address":"1348 E 11th St",
    "sg:city":"Tulsa",
    "sg:classifiers":[
        {
            "category":"Retail",
            "subcategory":"Repair Shop",
            "type":"Services"
        }
    ],
    "sg:phone":"+1 918 599 0037",
    "sg:postcode":"74120",
    "sg:province":"OK",
    "sg:tags":[
        "upholsterer"
    ],
    "wof:name":"Modern Upholstery By Don",
    "wof:placetype":"venue"
},
  "geometry": {"coordinates":[-95.973603,36.147817],"type":"Point"}
}