{
  "type": "Feature",
  "properties": {
    "iso:country":"US",
    "sg:address":"2130 S 130th East Ave",
    "sg:city":"Tulsa",
    "sg:classifiers":[
        {
            "category":"Building & Trades",
            "subcategory":"Electrical",
            "type":"Services"
        }
    ],
    "sg:phone":"+1 918 437 0684",
    "sg:postcode":"74134",
    "sg:province":"OK",
    "sg:tags":[
        "industrial",
        "electrician",
        "electric",
        "contractors-commercial"
    ],
    "wof:name":"Rci Electric Inc",
    "wof:placetype":"venue"
},
  "geometry": {"coordinates":[-95.830978,36.131883],"type":"Point"}
}