{
  "type": "Feature",
  "properties": {
    "addr:full":"1300 N Moore Ave Oklahoma City OK 73160",
    "addr:housenumber":"1300",
    "addr:postcode":"73160",
    "addr:street":"N Moore Ave",
    "iso:country":"US",
    "sg:address":"1300 N Moore Ave",
    "sg:city":"Oklahoma City",
    "sg:classifiers":[
        {
            "category":"Restaurant",
            "type":"Food & Drink"
        }
    ],
    "sg:menulink":"http://www.allmenus.com/ok/north-cleveland/164456-wendys/menu/",
    "sg:phone":"+1 405 794 4563",
    "sg:postcode":"73160",
    "sg:province":"OK",
    "sg:tags":[
        "burger",
        "american",
        "soup"
    ],
    "wof:name":"Wendy's",
    "wof:placetype":"venue"
},
  "geometry": {"coordinates":[-97.49607399999999,35.348791],"type":"Point"}
}