{
  "type": "Feature",
  "properties": {
    "iso:country":"US",
    "sg:address":"314 W 12th St",
    "sg:city":"Ada",
    "sg:classifiers":[
        {
            "category":"Food & Beverages",
            "subcategory":"Groceries & Convenience Stores",
            "type":"Retail Goods"
        }
    ],
    "sg:phone":"+1 580 332 6496",
    "sg:postcode":"74820",
    "sg:province":"OK",
    "sg:tags":[
        "grocer"
    ],
    "wof:name":"Save-A-Lot",
    "wof:placetype":"venue"
},
  "geometry": {"coordinates":[-96.68204,34.773486],"type":"Point"}
}