{
  "type": "Feature",
  "properties": {
    "iso:country":"US",
    "sg:address":"2801 N Lincoln Blvd",
    "sg:city":"Oklahoma City",
    "sg:classifiers":[
        {
            "category":"Professional",
            "subcategory":"Lawyer & Legal Services",
            "type":"Services"
        }
    ],
    "sg:phone":"+1 405 521 0202",
    "sg:postcode":"73105",
    "sg:province":"OK",
    "sg:tags":[
        "attorney"
    ],
    "wof:name":"Rosenstein Fist & Ringold",
    "wof:placetype":"venue"
},
  "geometry": {"coordinates":[-97.50318799999999,35.498641],"type":"Point"}
}