{
  "type": "Feature",
  "properties": {
    "iso:country":"US",
    "sg:address":"222 S Mission St",
    "sg:city":"Sapulpa",
    "sg:classifiers":[
        {
            "category":"Retail",
            "subcategory":"Car Wash",
            "type":"Services"
        }
    ],
    "sg:phone":"+1 918 227 0477",
    "sg:postcode":"74066",
    "sg:province":"OK",
    "sg:tags":[
        "polishing",
        "washing"
    ],
    "wof:name":"Hydro Spray Of Sapulpa",
    "wof:placetype":"venue"
},
  "geometry": {"coordinates":[-96.098864,35.996581],"type":"Point"}
}