{
  "type": "Feature",
  "properties": {
    "addr:full":"2954 S Sandwood Ave Choctaw OK 73020",
    "addr:housenumber":"2954",
    "addr:postcode":"73020",
    "addr:street":"S Sandwood Ave",
    "iso:country":"US",
    "sg:address":"2954 S Sandwood Ave",
    "sg:city":"Choctaw",
    "sg:classifiers":[
        {
            "category":"Wholesale",
            "subcategory":"Plants",
            "type":"Manufacturing & Wholesale Goods"
        }
    ],
    "sg:phone":"+1 405 390 2233",
    "sg:postcode":"73020",
    "sg:province":"OK",
    "sg:tags":[
        "r",
        "supply"
    ],
    "wof:name":"Holders Herbsgifts",
    "wof:placetype":"venue"
},
  "geometry": {"coordinates":[-97.24276,35.435986],"type":"Point"}
}