{
  "type": "Feature",
  "properties": {
    "iso:country":"US",
    "sg:address":"3601 Tuxedo Blvd",
    "sg:city":"Bartlesville",
    "sg:classifiers":[
        {
            "category":"Wholesale",
            "subcategory":"Auto Parts",
            "type":"Manufacturing & Wholesale Goods"
        }
    ],
    "sg:phone":"+1 918 333 2213",
    "sg:postcode":"74006",
    "sg:province":"OK",
    "sg:tags":[
        "automotive"
    ],
    "wof:name":"B & C Auto Parts",
    "wof:placetype":"venue"
},
  "geometry": {"coordinates":[-95.937744,36.757016],"type":"Point"}
}