{
  "type": "Feature",
  "properties": {
    "iso:country":"US",
    "sg:address":"7302 S Evanston Ave",
    "sg:city":"Tulsa",
    "sg:classifiers":[
        {
            "category":"Food & Beverages",
            "subcategory":"Liquor & Beverages",
            "type":"Retail Goods"
        }
    ],
    "sg:phone":"+1 918 492 1220",
    "sg:postcode":"74136",
    "sg:province":"OK",
    "sg:tags":[
        "store"
    ],
    "wof:name":"Wine Rack",
    "wof:placetype":"venue"
},
  "geometry": {"coordinates":[-95.948442,36.055912],"type":"Point"}
}