{
  "type": "Feature",
  "properties": {
    "addr:full":"311 E Sheridan Ave Oklahoma City OK 73104",
    "addr:housenumber":"311",
    "addr:postcode":"73104",
    "addr:street":"E Sheridan Ave",
    "iso:country":"US",
    "sg:address":"311 E Sheridan Ave",
    "sg:city":"Oklahoma City",
    "sg:classifiers":[
        {
            "category":"Organizations",
            "subcategory":"Community Association",
            "type":"Services"
        }
    ],
    "sg:phone":"+1 405 601 6276",
    "sg:postcode":"73104",
    "sg:province":"OK",
    "sg:tags":[
        "club"
    ],
    "wof:name":"Wormy Dog Saloon",
    "wof:placetype":"venue"
},
  "geometry": {"coordinates":[-97.506154,35.466509],"type":"Point"}
}