{
  "type": "Feature",
  "properties": {
    "iso:country":"US",
    "sg:address":"110 N Independence Ave",
    "sg:city":"Enid",
    "sg:classifiers":[
        {
            "category":"Banks & Credit Unions",
            "subcategory":"Investment Brokerage",
            "type":"Services"
        }
    ],
    "sg:phone":"+1 580 237 0060",
    "sg:postcode":"73701",
    "sg:province":"OK",
    "sg:tags":[
        "consultant",
        "planning",
        "financial"
    ],
    "wof:name":"Wymer Brownlee & Assoc",
    "wof:placetype":"venue"
},
  "geometry": {"coordinates":[-97.879891,36.39768],"type":"Point"}
}