{
  "type": "Feature",
  "properties": {
    "iso:country":"US",
    "sg:address":"1120 E 34th St",
    "sg:city":"Tulsa",
    "sg:classifiers":[
        {
            "category":"Organizations",
            "subcategory":"Religious Organization",
            "type":"Services"
        }
    ],
    "sg:phone":"+1 918 582 2364",
    "sg:postcode":"74105",
    "sg:province":"OK",
    "sg:tags":[
        "church"
    ],
    "wof:name":"Westminster Presbyterian Ch",
    "wof:placetype":"venue"
},
  "geometry": {"coordinates":[-95.979512,36.113796],"type":"Point"}
}