{
  "type": "Feature",
  "properties": {
    "iso:country":"US",
    "sg:address":"6409 Avondale Dr",
    "sg:city":"Nichols Hills",
    "sg:classifiers":[
        {
            "category":"Restaurant",
            "type":"Food & Drink"
        }
    ],
    "sg:phone":"+1 405 842 5006",
    "sg:postcode":"73116",
    "sg:province":"OK",
    "sg:tags":[
        "caterer"
    ],
    "wof:name":"Uncle John's Smokestack",
    "wof:placetype":"venue"
},
  "geometry": {"coordinates":[-97.531026,35.538018],"type":"Point"}
}