{
  "type": "Feature",
  "properties": {
    "iso:country":"US",
    "sg:address":"249 P St SE",
    "sg:city":"Ardmore",
    "sg:classifiers":[
        {
            "category":"Retail",
            "subcategory":"Auto Repair",
            "type":"Services"
        }
    ],
    "sg:phone":"+1 580 226 0234",
    "sg:postcode":"73401",
    "sg:province":"OK",
    "sg:tags":[
        "general"
    ],
    "wof:name":"Page Automotive",
    "wof:placetype":"venue"
},
  "geometry": {"coordinates":[-97.108136,34.168387],"type":"Point"}
}