{
  "type": "Feature",
  "properties": {
    "addr:full":"6480 Avondale Dr Oklahoma City OK 73116",
    "addr:housenumber":"6480",
    "addr:postcode":"73116",
    "addr:street":"Avondale Dr",
    "iso:country":"US",
    "sg:address":"6480 Avondale Dr",
    "sg:city":"Oklahoma City",
    "sg:classifiers":[
        {
            "category":"Shopping",
            "subcategory":"Gifts & Souvenirs",
            "type":"Retail Goods"
        }
    ],
    "sg:phone":"+1 405 843 8431",
    "sg:postcode":"73116",
    "sg:province":"OK",
    "wof:name":"Fanny Interiors",
    "wof:placetype":"venue"
},
  "geometry": {"coordinates":[-97.53219799999999,35.539535],"type":"Point"}
}