{
  "type": "Feature",
  "properties": {
    "iso:country":"US",
    "sg:address":"15420 N 247 Rd",
    "sg:city":"Okmulgee",
    "sg:classifiers":[
        {
            "category":"Freight",
            "type":"Transportation"
        }
    ],
    "sg:phone":"+1 918 756 5548",
    "sg:postcode":"74447",
    "sg:province":"OK",
    "sg:tags":[
        "commercial",
        "storage"
    ],
    "wof:name":"Bowen's Prairie Rose Mini-Stge",
    "wof:placetype":"venue"
},
  "geometry": {"coordinates":[-95.932944,35.634538],"type":"Point"}
}