{
  "type": "Feature",
  "properties": {
    "addr:full":"1408 S Fretz Ave Edmond OK 73003",
    "addr:housenumber":"1408",
    "addr:postcode":"73003",
    "addr:street":"S Fretz Ave",
    "iso:country":"US",
    "sg:address":"1408 S Fretz Ave",
    "sg:city":"Edmond",
    "sg:classifiers":[
        {
            "category":"Mining & Drilling",
            "type":"Manufacturing & Wholesale Goods"
        }
    ],
    "sg:phone":"+1 405 340 5240",
    "sg:postcode":"73003",
    "sg:province":"OK",
    "sg:tags":[
        "development",
        "gas",
        "oil",
        "exploration"
    ],
    "wof:name":"Little Bear Resources",
    "wof:placetype":"venue"
},
  "geometry": {"coordinates":[-97.487059,35.63977],"type":"Point"}
}