{
  "type": "Feature",
  "properties": {
    "iso:country":"US",
    "sg:address":"5937 E Marshall St",
    "sg:city":"Tulsa",
    "sg:classifiers":[
        {
            "category":"Shopping",
            "subcategory":"Computers & Home Electronics",
            "type":"Retail Goods"
        }
    ],
    "sg:phone":"+1 918 836 9864",
    "sg:postcode":"74115",
    "sg:province":"OK",
    "wof:name":"Compu-Tana",
    "wof:placetype":"venue"
},
  "geometry": {"coordinates":[-95.908734,36.171451],"type":"Point"}
}