{
  "type": "Feature",
  "properties": {
    "addr:full":"2681 N Florence Ave Tulsa OK 74110",
    "addr:housenumber":"2681",
    "addr:postcode":"74110",
    "addr:street":"N Florence Ave",
    "iso:country":"US",
    "sg:address":"2681 N Florence Ave",
    "sg:city":"Tulsa",
    "sg:classifiers":[
        {
            "category":"Travel",
            "subcategory":"Travel Agent",
            "type":"Entertainment"
        }
    ],
    "sg:phone":"+1 918 838 8082",
    "sg:postcode":"74110",
    "sg:province":"OK",
    "sg:tags":[
        "agency",
        "bureau"
    ],
    "sg:website":"www.redcarpet.com",
    "wof:name":"Red Carpet Charters Inc",
    "wof:placetype":"venue"
},
  "geometry": {"coordinates":[-95.943225,36.194612],"type":"Point"}
}