{
  "type": "Feature",
  "properties": {
    "iso:country":"US",
    "sg:address":"3386 W Robinson St",
    "sg:city":"Norman",
    "sg:classifiers":[
        {
            "category":"Real Estate",
            "subcategory":"Real Estate Operator",
            "type":"Services"
        }
    ],
    "sg:phone":"+1 405 366 1155",
    "sg:postcode":"73072",
    "sg:province":"OK",
    "sg:tags":[
        "apartment"
    ],
    "wof:name":"Patio Apartments",
    "wof:placetype":"venue"
},
  "geometry": {"coordinates":[-97.492741,35.232767],"type":"Point"}
}