{
  "type": "Feature",
  "properties": {
    "iso:country":"US",
    "sg:address":"501 US Hwy 77",
    "sg:city":"Marietta",
    "sg:classifiers":[
        {
            "category":"Professional",
            "subcategory":"Accounting & Tax Preparation",
            "type":"Services"
        }
    ],
    "sg:phone":"+1 580 276 9258",
    "sg:postcode":"73448",
    "sg:province":"OK",
    "wof:name":"Dobbs Bookkeeping",
    "wof:placetype":"venue"
},
  "geometry": {"coordinates":[-97.126263,33.933785],"type":"Point"}
}