{
  "type": "Feature",
  "properties": {
    "iso:country":"US",
    "sg:address":"2612 S Dogwood Ave",
    "sg:city":"Broken Arrow",
    "sg:classifiers":[
        {
            "category":"Professional",
            "subcategory":"Computer Services",
            "type":"Services"
        }
    ],
    "sg:phone":"+1 918 451 4411",
    "sg:postcode":"74012",
    "sg:province":"OK",
    "sg:tags":[
        "programing",
        "custom"
    ],
    "wof:name":"AA Den Engineering LLC",
    "wof:placetype":"venue"
},
  "geometry": {"coordinates":[-95.820173,36.027343],"type":"Point"}
}