{
  "type": "Feature",
  "properties": {
    "iso:country":"US",
    "sg:address":"312 Oklahoma Blvd",
    "sg:city":"Alva",
    "sg:classifiers":[
        {
            "category":"Autos & Motor Vehicles",
            "subcategory":"Auto Supplies",
            "type":"Retail Goods"
        }
    ],
    "sg:phone":"+1 580 327 0224",
    "sg:postcode":"73717",
    "sg:province":"OK",
    "sg:tags":[
        "automotive",
        "parts",
        "automobile"
    ],
    "wof:name":"O'Reilly Auto Parts",
    "wof:placetype":"venue"
},
  "geometry": {"coordinates":[-98.66264,36.797732],"type":"Point"}
}