{
  "type": "Feature",
  "properties": {
    "iso:country":"US",
    "sg:address":"446 State Hwy 32",
    "sg:city":"Lebanon",
    "sg:classifiers":[
        {
            "category":"Building & Trades",
            "subcategory":"Construction",
            "type":"Services"
        }
    ],
    "sg:phone":"+1 580 795 7068",
    "sg:postcode":"73440",
    "sg:province":"OK",
    "sg:tags":[
        "general",
        "contractor"
    ],
    "wof:name":"SRC Construction Inc",
    "wof:placetype":"venue"
},
  "geometry": {"coordinates":[-96.908784,33.983595],"type":"Point"}
}