{
  "type": "Feature",
  "properties": {
    "iso:country":"US",
    "sg:address":"1216 W Willow Rd",
    "sg:city":"Enid",
    "sg:classifiers":[
        {
            "category":"Government",
            "subcategory":"Office",
            "type":"Public Place"
        }
    ],
    "sg:phone":"+1 580 237 4323",
    "sg:postcode":"73703",
    "sg:province":"OK",
    "sg:tags":[
        "development",
        "grant",
        "loan",
        "delivery",
        "program",
        "rural"
    ],
    "wof:name":"Rural Development",
    "wof:placetype":"venue"
},
  "geometry": {"coordinates":[-97.891016,36.419929],"type":"Point"}
}