{
  "type": "Feature",
  "properties": {
    "iso:country":"US",
    "sg:address":"4403 NW 50th St",
    "sg:city":"Oklahoma City",
    "sg:classifiers":[
        {
            "category":"Retail",
            "subcategory":"Laundry & Dry Cleaning",
            "type":"Services"
        }
    ],
    "sg:phone":"+1 405 942 3221",
    "sg:postcode":"73112",
    "sg:province":"OK",
    "sg:tags":[
        "cleaners"
    ],
    "wof:name":"Whirlwind Cleaners",
    "wof:placetype":"venue"
},
  "geometry": {"coordinates":[-97.599166,35.522396],"type":"Point"}
}