{
  "type": "Feature",
  "properties": {
    "iso:country":"US",
    "sg:address":"405 N Eufaula Ave",
    "sg:city":"Coweta",
    "sg:classifiers":[
        {
            "category":"Personal",
            "type":"Services"
        }
    ],
    "sg:phone":"+1 918 486 3366",
    "sg:postcode":"74429",
    "sg:province":"OK",
    "sg:tags":[
        "shop",
        "beauty"
    ],
    "wof:name":"Modern Images & Co LLC",
    "wof:placetype":"venue"
},
  "geometry": {"coordinates":[-95.648155,35.954147],"type":"Point"}
}