{
  "type": "Feature",
  "properties": {
    "iso:country":"US",
    "sg:address":"915 W Plato Rd",
    "sg:city":"Duncan",
    "sg:classifiers":[
        {
            "category":"Social Services",
            "subcategory":"Adult Care",
            "type":"Services"
        }
    ],
    "sg:phone":"+1 580 252 8300",
    "sg:postcode":"73533",
    "sg:province":"OK",
    "sg:tags":[
        "home",
        "residential"
    ],
    "wof:name":"Sterling House",
    "wof:placetype":"venue"
},
  "geometry": {"coordinates":[-97.95761,34.53623],"type":"Point"}
}