{
  "type": "Feature",
  "properties": {
    "addr:full":"1532 E Apache St Tulsa OK 74106",
    "addr:housenumber":"1532",
    "addr:postcode":"74106",
    "addr:street":"E Apache St",
    "iso:country":"US",
    "sg:address":"1532 E Apache St",
    "sg:city":"Tulsa",
    "sg:classifiers":[
        {
            "category":"Food & Beverages",
            "subcategory":"Groceries & Convenience Stores",
            "type":"Retail Goods"
        }
    ],
    "sg:phone":"+1 918 425 4957",
    "sg:postcode":"74106",
    "sg:province":"OK",
    "wof:name":"Dash Inn",
    "wof:placetype":"venue"
},
  "geometry": {"coordinates":[-95.970045,36.191439],"type":"Point"}
}