{
  "type": "Feature",
  "properties": {
    "iso:country":"US",
    "sg:address":"6058 S Yale Ave",
    "sg:city":"Tulsa",
    "sg:classifiers":[
        {
            "category":"Restaurant",
            "type":"Food & Drink"
        }
    ],
    "sg:menulink":"http://www.allmenus.com/ok/tulsa/12622-mcgills-south/menu/",
    "sg:phone":"+1 918 388 8080",
    "sg:postcode":"74135",
    "sg:province":"OK",
    "sg:tags":[
        "american"
    ],
    "wof:name":"McGill's South",
    "wof:placetype":"venue"
},
  "geometry": {"coordinates":[-95.92231700000001,36.075978],"type":"Point"}
}