{
  "type": "Feature",
  "properties": {
    "iso:country":"US",
    "sg:address":"500 S Grand Ave",
    "sg:city":"Enid",
    "sg:classifiers":[
        {
            "category":"Retail",
            "subcategory":"Repair Shop",
            "type":"Services"
        }
    ],
    "sg:phone":"+1 580 234 5019",
    "sg:postcode":"73701",
    "sg:province":"OK",
    "wof:name":"Cornforth Key Shop Inc",
    "wof:placetype":"venue"
},
  "geometry": {"coordinates":[-97.87829600000001,36.391411],"type":"Point"}
}