{
  "type": "Feature",
  "properties": {
    "iso:country":"US",
    "sg:address":"2014 W Gore Blvd",
    "sg:city":"Lawton",
    "sg:classifiers":[
        {
            "category":"Shopping",
            "type":"Retail Goods"
        }
    ],
    "sg:phone":"+1 580 353 5942",
    "sg:postcode":"73501",
    "sg:province":"OK",
    "sg:tags":[
        "merchandise",
        "animal"
    ],
    "wof:name":"Fins & Critters Pet Shop",
    "wof:placetype":"venue"
},
  "geometry": {"coordinates":[-98.419176,34.60876],"type":"Point"}
}