{
  "type": "Feature",
  "properties": {
    "addr:full":"1530 N Elm Pl Broken Arrow OK 74012",
    "addr:housenumber":"1530",
    "addr:postcode":"74012",
    "addr:street":"N Elm Pl",
    "iso:country":"US",
    "sg:address":"1530 N Elm Pl",
    "sg:city":"Broken Arrow",
    "sg:classifiers":[
        {
            "category":"Restaurant",
            "type":"Food & Drink"
        }
    ],
    "sg:menulink":"http://www.allmenus.com/ok/tulsa/11687-dennys/menu/",
    "sg:phone":"+1 918 251 0955",
    "sg:postcode":"74012",
    "sg:province":"OK",
    "sg:tags":[
        "american",
        "diner"
    ],
    "wof:name":"Denny's",
    "wof:placetype":"venue"
},
  "geometry": {"coordinates":[-95.797432,36.068398],"type":"Point"}
}