{
  "type": "Feature",
  "properties": {
    "iso:country":"US",
    "sg:address":"223 S Knoblock St",
    "sg:city":"Stillwater",
    "sg:classifiers":[
        {
            "category":"Utilities",
            "subcategory":"Mobile Phone",
            "type":"Services"
        }
    ],
    "sg:phone":"+1 405 533 1111",
    "sg:postcode":"74074",
    "sg:province":"OK",
    "sg:tags":[
        "telephone",
        "cellular"
    ],
    "wof:name":"Sprocket Wireless",
    "wof:placetype":"venue"
},
  "geometry": {"coordinates":[-97.064974,36.1202],"type":"Point"}
}