{
  "type": "Feature",
  "properties": {
    "iso:country":"US",
    "sg:address":"1947 E Coleman Rd",
    "sg:city":"Ponca City",
    "sg:classifiers":[
        {
            "category":"Retail",
            "subcategory":"Repair Shop",
            "type":"Services"
        }
    ],
    "sg:phone":"+1 580 767 1019",
    "sg:postcode":"74604",
    "sg:province":"OK",
    "sg:tags":[
        "welding"
    ],
    "wof:name":"Hasselbring Welding Serv",
    "wof:placetype":"venue"
},
  "geometry": {"coordinates":[-97.05724499999999,36.76726],"type":"Point"}
}