{
  "type": "Feature",
  "properties": {
    "addr:full":"7221 E Admiral Pl Tulsa OK 74115",
    "addr:housenumber":"7221",
    "addr:postcode":"74115",
    "addr:street":"E Admiral Pl",
    "iso:country":"US",
    "sg:address":"7221 E Admiral Pl",
    "sg:city":"Tulsa",
    "sg:classifiers":[
        {
            "category":"Restaurant",
            "type":"Food & Drink"
        }
    ],
    "sg:menulink":"http://www.allmenus.com/ok/tulsa/164461-wendys/menu/",
    "sg:phone":"+1 918 835 0701",
    "sg:postcode":"74115",
    "sg:province":"OK",
    "sg:tags":[
        "burger",
        "american",
        "soup"
    ],
    "wof:name":"Wendy's",
    "wof:placetype":"venue"
},
  "geometry": {"coordinates":[-95.896029,36.161239],"type":"Point"}
}