{
  "type": "Feature",
  "properties": {
    "iso:country":"US",
    "sg:address":"311 E Marie Dr",
    "sg:city":"Stillwater",
    "sg:classifiers":[
        {
            "category":"Building & Trades",
            "subcategory":"Construction",
            "type":"Services"
        }
    ],
    "sg:phone":"+1 405 533 7705",
    "sg:postcode":"74075",
    "sg:province":"OK",
    "sg:tags":[
        "handyman"
    ],
    "wof:name":"Hawk's Helping Hand",
    "wof:placetype":"venue"
},
  "geometry": {"coordinates":[-97.055829,36.169987],"type":"Point"}
}