{
  "type": "Feature",
  "properties": {
    "addr:full":"8181 S Harvard Ave Tulsa OK 74137",
    "addr:housenumber":"8181",
    "addr:postcode":"74137",
    "addr:street":"S Harvard Ave",
    "iso:country":"US",
    "sg:address":"8181 S Harvard Ave",
    "sg:city":"Tulsa",
    "sg:classifiers":[
        {
            "category":"Personal",
            "subcategory":"Beauty Salon",
            "type":"Services"
        }
    ],
    "sg:phone":"+1 918 491 9977",
    "sg:postcode":"74137",
    "sg:province":"OK",
    "sg:tags":[
        "manicuring"
    ],
    "wof:name":"California Nails",
    "wof:placetype":"venue"
},
  "geometry": {"coordinates":[-95.939891,36.044732],"type":"Point"}
}