{
  "type": "Feature",
  "properties": {
    "addr:full":"2715 N 53rd W Ave Tulsa OK 74127",
    "addr:housenumber":"2715",
    "addr:postcode":"74127",
    "addr:street":"N 53Rd W Ave",
    "iso:country":"US",
    "sg:address":"2715 N 53rd W Ave",
    "sg:city":"Tulsa",
    "sg:classifiers":[
        {
            "category":"Professional",
            "type":"Services"
        }
    ],
    "sg:phone":"+1 918 382 5730",
    "sg:postcode":"74127",
    "sg:province":"OK",
    "sg:tags":[
        "establishment"
    ],
    "wof:name":"Amvest Osage",
    "wof:placetype":"venue"
},
  "geometry": {"coordinates":[-96.050723,36.190731],"type":"Point"}
}