{
  "type": "Feature",
  "properties": {
    "iso:country":"US",
    "sg:address":"424 W Grand Ave",
    "sg:city":"Ponca City",
    "sg:classifiers":[
        {
            "category":"Banks & Credit Unions",
            "subcategory":"Bank",
            "type":"Services"
        }
    ],
    "sg:phone":"+1 580 762 8833",
    "sg:postcode":"74601",
    "sg:province":"OK",
    "sg:tags":[
        "personal",
        "institution"
    ],
    "wof:name":"Western Shamrock Corporation",
    "wof:placetype":"venue"
},
  "geometry": {"coordinates":[-97.088951,36.703752],"type":"Point"}
}