{
  "type": "Feature",
  "properties": {
    "addr:full":"4905 S Memorial Dr Tulsa OK 74145",
    "addr:housenumber":"4905",
    "addr:postcode":"74145",
    "addr:street":"S Memorial Dr",
    "iso:country":"US",
    "sg:address":"4905 S Memorial Dr",
    "sg:city":"Tulsa",
    "sg:classifiers":[
        {
            "category":"Autos & Motor Vehicles",
            "subcategory":"Automobile Sales",
            "type":"Retail Goods"
        }
    ],
    "sg:phone":"+1 918 627 2666",
    "sg:postcode":"74145",
    "sg:province":"OK",
    "sg:tags":[
        "car",
        "dealer"
    ],
    "wof:name":"Acura Of Tulsa",
    "wof:placetype":"venue"
},
  "geometry": {"coordinates":[-95.88648000000001,36.091567],"type":"Point"}
}