{
  "type": "Feature",
  "properties": {
    "iso:country":"US",
    "sg:address":"8204 S Harvard Ave",
    "sg:city":"Tulsa",
    "sg:classifiers":[
        {
            "category":"Restaurant",
            "type":"Food & Drink"
        }
    ],
    "sg:phone":"+1 918 492 4777",
    "sg:postcode":"74137",
    "sg:province":"OK",
    "sg:tags":[
        "pizza"
    ],
    "wof:name":"Hideaway Pizza",
    "wof:placetype":"venue"
},
  "geometry": {"coordinates":[-95.940049,36.045071],"type":"Point"}
}