{
  "type": "Feature",
  "properties": {
    "addr:full":"108 Selmon Rd Eufaula OK 74432",
    "addr:housenumber":"108",
    "addr:postcode":"74432",
    "addr:street":"Selmon Rd",
    "iso:country":"US",
    "sg:address":"108 Selmon Rd",
    "sg:city":"Eufaula",
    "sg:classifiers":[
        {
            "category":"Autos & Motor Vehicles",
            "subcategory":"Automobile Sales",
            "type":"Retail Goods"
        }
    ],
    "sg:phone":"+1 918 689 9718",
    "sg:postcode":"74432",
    "sg:province":"OK",
    "sg:tags":[
        "car",
        "dealer"
    ],
    "wof:name":"Ford Eufaula",
    "wof:placetype":"venue"
},
  "geometry": {"coordinates":[-95.583248,35.287463],"type":"Point"}
}