{
  "type": "Feature",
  "properties": {
    "iso:country":"US",
    "sg:address":"8186 S Memorial Dr",
    "sg:city":"Tulsa",
    "sg:classifiers":[
        {
            "category":"Professional",
            "type":"Services"
        }
    ],
    "sg:phone":"+1 918 249 1003",
    "sg:postcode":"74133",
    "sg:province":"OK",
    "sg:tags":[
        "establishment"
    ],
    "wof:name":"8160 South Memorial LLC",
    "wof:placetype":"venue"
},
  "geometry": {"coordinates":[-95.88631,36.041954],"type":"Point"}
}