{
  "type": "Feature",
  "properties": {
    "addr:full":"4107 SE 29th St Oklahoma City OK 73115",
    "addr:housenumber":"4107",
    "addr:postcode":"73115",
    "addr:street":"Se 29Th St",
    "iso:country":"US",
    "sg:address":"4107 SE 29th St",
    "sg:city":"Oklahoma City",
    "sg:classifiers":[
        {
            "category":"Bars & Pubs",
            "type":"Food & Drink"
        }
    ],
    "sg:phone":"+1 405 677 4962",
    "sg:postcode":"73115",
    "sg:province":"OK",
    "sg:tags":[
        "drinking"
    ],
    "wof:name":"Sportsmans Bar & Grill",
    "wof:placetype":"venue"
},
  "geometry": {"coordinates":[-97.441416,35.435296],"type":"Point"}
}