{
  "type": "Feature",
  "properties": {
    "iso:country":"US",
    "sg:address":"400 S 1st St",
    "sg:city":"Eufaula",
    "sg:classifiers":[
        {
            "category":"Real Estate",
            "subcategory":"Real Estate Agent",
            "type":"Services"
        }
    ],
    "sg:phone":"+1 918 689 4800",
    "sg:postcode":"74432",
    "sg:province":"OK",
    "wof:name":"Paradise Realty",
    "wof:placetype":"venue"
},
  "geometry": {"coordinates":[-95.584064,35.283501],"type":"Point"}
}