{
  "type": "Feature",
  "properties": {
    "iso:country":"US",
    "sg:address":"2241 NW 29th St",
    "sg:city":"Oklahoma City",
    "sg:classifiers":[
        {
            "category":"Shopping",
            "subcategory":"Bicycles & Sporting Goods",
            "type":"Retail Goods"
        }
    ],
    "sg:phone":"+1 405 528 3172",
    "sg:postcode":"73107",
    "sg:province":"OK",
    "wof:name":"Eurocycle",
    "wof:placetype":"venue"
},
  "geometry": {"coordinates":[-97.55131900000001,35.499548],"type":"Point"}
}