{
  "type": "Feature",
  "properties": {
    "iso:country":"US",
    "sg:address":"3800 S Broadway",
    "sg:city":"Edmond",
    "sg:classifiers":[
        {
            "category":"Autos & Motor Vehicles",
            "subcategory":"Auto Supplies",
            "type":"Retail Goods"
        }
    ],
    "sg:phone":"+1 405 844 4112",
    "sg:postcode":"73013",
    "sg:province":"OK",
    "sg:tags":[
        "tire"
    ],
    "wof:name":"Hibdon Tire Ctr",
    "wof:placetype":"venue"
},
  "geometry": {"coordinates":[-97.49056,35.617493],"type":"Point"}
}