{
  "type": "Feature",
  "properties": {
    "addr:full":"6564 E 51st St Tulsa OK 74145",
    "addr:housenumber":"6564",
    "addr:postcode":"74145",
    "addr:street":"E 51St St",
    "iso:country":"US",
    "sg:address":"6564 E 51st St",
    "sg:city":"Tulsa",
    "sg:classifiers":[
        {
            "category":"Shopping",
            "subcategory":"Bicycles & Sporting Goods",
            "type":"Retail Goods"
        }
    ],
    "sg:phone":"+1 918 627 4611",
    "sg:postcode":"74145",
    "sg:province":"OK",
    "sg:tags":[
        "equipment",
        "exercise"
    ],
    "sg:website":"www.homefit.com",
    "wof:name":"Home Fitness Exercise Equip Co",
    "wof:placetype":"venue"
},
  "geometry": {"coordinates":[-95.90302200000001,36.089832],"type":"Point"}
}