{
  "type": "Feature",
  "properties": {
    "addr:full":"830 E 8th St Ada OK 74820",
    "addr:housenumber":"830",
    "addr:postcode":"74820",
    "addr:street":"E 8Th St",
    "iso:country":"US",
    "sg:address":"830 E 8th St",
    "sg:city":"Ada",
    "sg:classifiers":[
        {
            "category":"Personal",
            "subcategory":"Beauty Salon",
            "type":"Services"
        }
    ],
    "sg:phone":"+1 580 436 3964",
    "sg:postcode":"74820",
    "sg:province":"OK",
    "sg:tags":[
        "shop"
    ],
    "wof:name":"Hair Designs By Doyce",
    "wof:placetype":"venue"
},
  "geometry": {"coordinates":[-96.667436,34.777746],"type":"Point"}
}