{
  "type": "Feature",
  "properties": {
    "addr:full":"1400 N Louis Tittle Ave Mangum OK 73554",
    "addr:housenumber":"1400",
    "addr:postcode":"73554",
    "addr:street":"N Louis Tittle Ave",
    "iso:country":"US",
    "sg:address":"1400 N Louis Tittle Ave",
    "sg:city":"Mangum",
    "sg:classifiers":[
        {
            "category":"Banks & Credit Unions",
            "subcategory":"Bank",
            "type":"Services"
        }
    ],
    "sg:phone":"+1 580 782 2222",
    "sg:postcode":"73554",
    "sg:province":"OK",
    "sg:website":"www.stockmansbankok.com",
    "wof:name":"Stockman's Bank",
    "wof:placetype":"venue"
},
  "geometry": {"coordinates":[-99.50242900000001,34.885004],"type":"Point"}
}