{
  "type": "Feature",
  "properties": {
    "iso:country":"US",
    "sg:address":"1141 E Main St",
    "sg:city":"Norman",
    "sg:classifiers":[
        {
            "category":"Social Services",
            "subcategory":"Job Training",
            "type":"Services"
        }
    ],
    "sg:phone":"+1 405 701 2000",
    "sg:postcode":"73071",
    "sg:province":"OK",
    "wof:name":"Workforce Oklahoma",
    "wof:placetype":"venue"
},
  "geometry": {"coordinates":[-97.427025,35.225618],"type":"Point"}
}