{
  "type": "Feature",
  "properties": {
    "iso:country":"US",
    "sg:address":"1436 SW 44th St",
    "sg:city":"Oklahoma City",
    "sg:classifiers":[
        {
            "category":"Professional",
            "subcategory":"Lawyer & Legal Services",
            "type":"Services"
        }
    ],
    "sg:phone":"+1 405 685 2223",
    "sg:postcode":"73119",
    "sg:province":"OK",
    "sg:tags":[
        "attorney"
    ],
    "wof:name":"Wakely & Wakely",
    "wof:placetype":"venue"
},
  "geometry": {"coordinates":[-97.541488,35.420654],"type":"Point"}
}