{
  "type": "Feature",
  "properties": {
    "iso:country":"US",
    "sg:address":"4550 Odom Dr",
    "sg:city":"Duncan",
    "sg:classifiers":[
        {
            "category":"Mining & Drilling",
            "type":"Manufacturing & Wholesale Goods"
        }
    ],
    "sg:phone":"+1 580 255 1674",
    "sg:postcode":"73533",
    "sg:province":"OK",
    "sg:tags":[
        "development",
        "gas",
        "oil",
        "exploration"
    ],
    "wof:name":"Latigo Drilling Corp",
    "wof:placetype":"venue"
},
  "geometry": {"coordinates":[-97.945231,34.554608],"type":"Point"}
}