{
  "type": "Feature",
  "properties": {
    "iso:country":"US",
    "sg:address":"202 Beck Dr",
    "sg:city":"Pawnee",
    "sg:phone":"+1 918 762 3313",
    "sg:postcode":"74058",
    "sg:province":"OK",
    "sg:tags":[
        "farm",
        "soybean"
    ],
    "wof:name":"Billy Kelley",
    "wof:placetype":"venue"
},
  "geometry": {"coordinates":[-96.794366,36.347898],"type":"Point"}
}