{
  "type": "Feature",
  "properties": {
    "iso:country":"US",
    "sg:address":"107 S Central Ave",
    "sg:city":"Idabel",
    "sg:classifiers":[
        {
            "category":"Manufacturing",
            "subcategory":"Printing",
            "type":"Manufacturing & Wholesale Goods"
        }
    ],
    "sg:phone":"+1 580 584 6210",
    "sg:postcode":"74745",
    "sg:province":"OK",
    "sg:tags":[
        "newspaper"
    ],
    "wof:name":"Mc Curtain County News",
    "wof:placetype":"venue"
},
  "geometry": {"coordinates":[-94.826845,33.893137],"type":"Point"}
}