{
  "type": "Feature",
  "properties": {
    "iso:country":"US",
    "sg:address":"5536 N Western Ave",
    "sg:city":"Oklahoma City",
    "sg:classifiers":[
        {
            "category":"Health Services",
            "subcategory":"Doctor",
            "type":"Services"
        }
    ],
    "sg:phone":"+1 405 767 0333",
    "sg:postcode":"73118",
    "sg:province":"OK",
    "sg:tags":[
        "dentist"
    ],
    "wof:name":"Barbara Chappell DDS",
    "wof:placetype":"venue"
},
  "geometry": {"coordinates":[-97.529749,35.527433],"type":"Point"}
}