{
  "type": "Feature",
  "properties": {
    "addr:full":"3919 NW 10th St Oklahoma City OK 73107",
    "addr:housenumber":"3919",
    "addr:postcode":"73107",
    "addr:street":"Nw 10Th St",
    "iso:country":"US",
    "sg:address":"3919 NW 10th St",
    "sg:city":"Oklahoma City",
    "sg:classifiers":[
        {
            "category":"Professional",
            "subcategory":"Engineering",
            "type":"Services"
        }
    ],
    "sg:phone":"+1 405 943 2078",
    "sg:postcode":"73107",
    "sg:province":"OK",
    "sg:tags":[
        "engineer"
    ],
    "wof:name":"BKI Construction Estimating",
    "wof:placetype":"venue"
},
  "geometry": {"coordinates":[-97.589758,35.478824],"type":"Point"}
}