{
  "type": "Feature",
  "properties": {
    "iso:country":"US",
    "sg:address":"805 E 13th St",
    "sg:city":"Bartlesville",
    "sg:classifiers":[
        {
            "category":"Education",
            "subcategory":"School",
            "type":"Public Place"
        }
    ],
    "sg:phone":"+1 918 336 1733",
    "sg:postcode":"74003",
    "sg:province":"OK",
    "wof:name":"Transportation Department",
    "wof:placetype":"venue"
},
  "geometry": {"coordinates":[-95.967764,36.740728],"type":"Point"}
}