{
  "type": "Feature",
  "properties": {
    "iso:country":"US",
    "sg:address":"12 S 8th St",
    "sg:city":"Duncan",
    "sg:classifiers":[
        {
            "category":"Professional",
            "subcategory":"Accounting & Tax Preparation",
            "type":"Services"
        }
    ],
    "sg:phone":"+1 580 255 2738",
    "sg:postcode":"73533",
    "sg:province":"OK",
    "sg:tags":[
        "accountant"
    ],
    "wof:name":"Tracy L Morgan CPA",
    "wof:placetype":"venue"
},
  "geometry": {"coordinates":[-97.956676,34.501667],"type":"Point"}
}