{
  "type": "Feature",
  "properties": {
    "iso:country":"US",
    "sg:address":"116 S Broadway",
    "sg:city":"Edmond",
    "sg:classifiers":[
        {
            "category":"Government",
            "subcategory":"Office",
            "type":"Public Place"
        }
    ],
    "sg:phone":"+1 405 359 4500",
    "sg:postcode":"73034",
    "sg:province":"OK",
    "sg:tags":[
        "city"
    ],
    "wof:name":"Edmond City Mayor",
    "wof:placetype":"venue"
},
  "geometry": {"coordinates":[-97.481383,35.653694],"type":"Point"}
}