{
  "type": "Feature",
  "properties": {
    "addr:full":"9402 E 55th Pl Tulsa OK 74145",
    "addr:housenumber":"9402",
    "addr:postcode":"74145",
    "addr:street":"E 55Th Pl",
    "iso:country":"US",
    "sg:address":"9402 E 55th Pl",
    "sg:city":"Tulsa",
    "sg:classifiers":[
        {
            "category":"Local Transit",
            "type":"Transportation"
        }
    ],
    "sg:phone":"+1 918 298 5466",
    "sg:postcode":"74145",
    "sg:province":"OK",
    "sg:tags":[
        "limousine"
    ],
    "wof:name":"Red Carpet Limo",
    "wof:placetype":"venue"
},
  "geometry": {"coordinates":[-95.868635,36.083529],"type":"Point"}
}