{
  "type": "Feature",
  "properties": {
    "addr:full":"1419 Westbrooke Ter Norman OK 73072",
    "addr:housenumber":"1419",
    "addr:postcode":"73072",
    "addr:street":"Westbrooke Ter",
    "iso:country":"US",
    "sg:address":"1419 Westbrooke Ter",
    "sg:city":"Norman",
    "sg:classifiers":[
        {
            "category":"Professional",
            "subcategory":"Business Services",
            "type":"Services"
        }
    ],
    "sg:phone":"+1 405 321 5199",
    "sg:postcode":"73072",
    "sg:province":"OK",
    "wof:name":"China Lady",
    "wof:placetype":"venue"
},
  "geometry": {"coordinates":[-97.464179,35.197166],"type":"Point"}
}