{
  "type": "Feature",
  "properties": {
    "addr:full":"1205 W Edgewater St Broken Arrow OK 74012",
    "addr:housenumber":"1205",
    "addr:postcode":"74012",
    "addr:street":"W Edgewater St",
    "iso:country":"US",
    "sg:address":"1205 W Edgewater St",
    "sg:city":"Broken Arrow",
    "sg:classifiers":[
        {
            "category":"Real Estate",
            "subcategory":"Real Estate Operator",
            "type":"Services"
        }
    ],
    "sg:phone":"+1 918 455 7713",
    "sg:postcode":"74012",
    "sg:province":"OK",
    "sg:tags":[
        "building",
        "nonresidential"
    ],
    "wof:name":"Property Development Inc",
    "wof:placetype":"venue"
},
  "geometry": {"coordinates":[-95.802306,36.023453],"type":"Point"}
}