{
  "type": "Feature",
  "properties": {
    "addr:full":"1501 SW 29th St Oklahoma City OK 73119",
    "addr:housenumber":"1501",
    "addr:postcode":"73119",
    "addr:street":"Sw 29Th St",
    "iso:country":"US",
    "sg:address":"1501 SW 29th St",
    "sg:city":"Oklahoma City",
    "sg:classifiers":[
        {
            "category":"Autos & Motor Vehicles",
            "subcategory":"Auto Supplies",
            "type":"Retail Goods"
        }
    ],
    "sg:phone":"+1 405 632 2172",
    "sg:postcode":"73119",
    "sg:province":"OK",
    "sg:tags":[
        "tire"
    ],
    "wof:name":"Pinos Tire Shop",
    "wof:placetype":"venue"
},
  "geometry": {"coordinates":[-97.545745,35.43521],"type":"Point"}
}