{
  "type": "Feature",
  "properties": {
    "iso:country":"US",
    "sg:address":"2014 S Nogales Ave",
    "sg:city":"Tulsa",
    "sg:classifiers":[
        {
            "category":"Communications",
            "subcategory":"Newspaper",
            "type":"Services"
        }
    ],
    "sg:phone":"+1 918 592 0293",
    "sg:postcode":"74107",
    "sg:province":"OK",
    "wof:name":"Kathi Lahmeyer",
    "wof:placetype":"venue"
},
  "geometry": {"coordinates":[-96.00336,36.134456],"type":"Point"}
}