{
  "type": "Feature",
  "properties": {
    "addr:full":"1402 E 6th Ave Stillwater OK 74074",
    "addr:housenumber":"1402",
    "addr:postcode":"74074",
    "addr:street":"E 6Th Ave",
    "iso:country":"US",
    "sg:address":"1402 E 6th Ave",
    "sg:city":"Stillwater",
    "sg:classifiers":[
        {
            "category":"Organizations",
            "subcategory":"Religious Organization",
            "type":"Services"
        }
    ],
    "sg:phone":"+1 405 372 6721",
    "sg:postcode":"74074",
    "sg:province":"OK",
    "wof:name":"Highland Park Free Will Bptst",
    "wof:placetype":"venue"
},
  "geometry": {"coordinates":[-97.040779,36.116105],"type":"Point"}
}