{
  "type": "Feature",
  "properties": {
    "addr:full":"1102 W Oak Ave Duncan OK 73533",
    "addr:housenumber":"1102",
    "addr:postcode":"73533",
    "addr:street":"W Oak Ave",
    "iso:country":"US",
    "sg:address":"1102 W Oak Ave",
    "sg:city":"Duncan",
    "sg:classifiers":[
        {
            "category":"Retail",
            "subcategory":"Repair Shop",
            "type":"Services"
        }
    ],
    "sg:phone":"+1 580 252 7488",
    "sg:postcode":"73533",
    "sg:province":"OK",
    "wof:name":"Celebration Frames & Gallery",
    "wof:placetype":"venue"
},
  "geometry": {"coordinates":[-97.96231,34.504395],"type":"Point"}
}