{
  "type": "Feature",
  "properties": {
    "iso:country":"US",
    "sg:address":"722 S Western Rd",
    "sg:city":"Stillwater",
    "sg:classifiers":[
        {
            "category":"Food & Beverages",
            "subcategory":"Liquor & Beverages",
            "type":"Retail Goods"
        }
    ],
    "sg:phone":"+1 405 377 9365",
    "sg:postcode":"74074",
    "sg:province":"OK",
    "sg:tags":[
        "alcoholic"
    ],
    "wof:name":"Wicklow Wine & Spirits",
    "wof:placetype":"venue"
},
  "geometry": {"coordinates":[-97.08737000000001,36.114593],"type":"Point"}
}