{
  "type": "Feature",
  "properties": {
    "iso:country":"US",
    "sg:address":"2427 S Harvey Ave",
    "sg:city":"Oklahoma City",
    "sg:classifiers":[
        {
            "category":"Retail",
            "subcategory":"Funeral Services",
            "type":"Services"
        }
    ],
    "sg:phone":"+1 405 631 8751",
    "sg:postcode":"73109",
    "sg:province":"OK",
    "sg:tags":[
        "director"
    ],
    "wof:name":"Hunter Funeral Home",
    "wof:placetype":"venue"
},
  "geometry": {"coordinates":[-97.51817,35.440762],"type":"Point"}
}