{
  "type": "Feature",
  "properties": {
    "addr:full":"18663 E 410 Rd Claremore OK 74017",
    "addr:housenumber":"18663",
    "addr:postcode":"74017",
    "addr:street":"E 410 Rd",
    "iso:country":"US",
    "sg:address":"18663 E 410 Rd",
    "sg:city":"Claremore",
    "sg:classifiers":[
        {
            "category":"Building & Trades",
            "subcategory":"Construction",
            "type":"Services"
        }
    ],
    "sg:phone":"+1 918 341 3676",
    "sg:postcode":"74017",
    "sg:province":"OK",
    "sg:tags":[
        "general",
        "contractor"
    ],
    "wof:name":"Mallory Plumbing",
    "wof:placetype":"venue"
},
  "geometry": {"coordinates":[-95.494816,36.423335],"type":"Point"}
}