{
  "type": "Feature",
  "properties": {
    "iso:country":"US",
    "sg:address":"23087 Rockwell Ave",
    "sg:city":"Blanchard",
    "sg:classifiers":[
        {
            "category":"Recreation",
            "type":"Entertainment"
        }
    ],
    "sg:phone":"+1 405 344 6324",
    "sg:postcode":"73010",
    "sg:province":"OK",
    "sg:tags":[
        "club",
        "membership"
    ],
    "wof:name":"Dibble Little League Assn",
    "wof:placetype":"venue"
},
  "geometry": {"coordinates":[-97.63548299999999,35.045637],"type":"Point"}
}