{
  "type": "Feature",
  "properties": {
    "iso:country":"US",
    "sg:address":"3725 State Hwy 92",
    "sg:city":"Chickasha",
    "sg:classifiers":[
        {
            "category":"Wholesale",
            "subcategory":"Farm Supplies",
            "type":"Manufacturing & Wholesale Goods"
        }
    ],
    "sg:phone":"+1 405 224 2254",
    "sg:postcode":"73018",
    "sg:province":"OK",
    "sg:tags":[
        "nursery",
        "nitrogenous",
        "mfg"
    ],
    "wof:name":"Pro AG Chem Inc",
    "wof:placetype":"venue"
},
  "geometry": {"coordinates":[-97.976857,35.009463],"type":"Point"}
}