{
  "type": "Feature",
  "properties": {
    "iso:country":"US",
    "sg:address":"6922 S Mingo Rd",
    "sg:city":"Tulsa",
    "sg:classifiers":[
        {
            "category":"Shopping",
            "subcategory":"Department Store",
            "type":"Retail Goods"
        }
    ],
    "sg:phone":"+1 918 252 9503",
    "sg:postcode":"74133",
    "sg:province":"OK",
    "wof:name":"Sam's Club",
    "wof:placetype":"venue"
},
  "geometry": {"coordinates":[-95.86858700000001,36.065637],"type":"Point"}
}