{
  "type": "Feature",
  "properties": {
    "iso:country":"US",
    "sg:address":"1810 NW Ferris Ave",
    "sg:city":"Lawton",
    "sg:classifiers":[
        {
            "category":"Health Services",
            "subcategory":"Dentist",
            "type":"Services"
        }
    ],
    "sg:phone":"+1 580 355 1314",
    "sg:postcode":"73507",
    "sg:province":"OK",
    "wof:name":"Robert L Miracle",
    "wof:placetype":"venue"
},
  "geometry": {"coordinates":[-98.415266,34.616069],"type":"Point"}
}