{
  "type": "Feature",
  "properties": {
    "iso:country":"US",
    "sg:address":"2717 N Janeway Ave",
    "sg:city":"Moore",
    "sg:classifiers":[
        {
            "category":"Autos & Motor Vehicles",
            "subcategory":"Auto Supplies",
            "type":"Retail Goods"
        },
        {
            "category":"Wholesale",
            "subcategory":"Auto Parts",
            "type":"Manufacturing & Wholesale Goods"
        }
    ],
    "sg:phone":"+1 405 794 1551",
    "sg:postcode":"73160",
    "sg:province":"OK",
    "sg:tags":[
        "tire"
    ],
    "wof:name":"Rich Tire Co",
    "wof:placetype":"venue"
},
  "geometry": {"coordinates":[-97.50351000000001,35.361545],"type":"Point"}
}