{
  "type": "Feature",
  "properties": {
    "iso:country":"US",
    "sg:address":"7740 Riverside Dr",
    "sg:city":"Tulsa",
    "sg:classifiers":[
        {
            "category":"Shopping",
            "subcategory":"Computers & Home Electronics",
            "type":"Retail Goods"
        }
    ],
    "sg:phone":"+1 918 488 1344",
    "sg:postcode":"74136",
    "sg:province":"OK",
    "sg:tags":[
        "software"
    ],
    "wof:name":"Bunch Consulting Inc",
    "wof:placetype":"venue"
},
  "geometry": {"coordinates":[-95.97226999999999,36.054118],"type":"Point"}
}