{
  "type": "Feature",
  "properties": {
    "iso:country":"US",
    "sg:address":"131 S 41st St E",
    "sg:city":"Muskogee",
    "sg:classifiers":[
        {
            "category":"Retail",
            "subcategory":"Auto Rental",
            "type":"Services"
        }
    ],
    "sg:phone":"+1 918 683 5575",
    "sg:postcode":"74403",
    "sg:province":"OK",
    "sg:tags":[
        "renting",
        "truck",
        "leasing"
    ],
    "wof:name":"Penske Truck Leasing",
    "wof:placetype":"venue"
},
  "geometry": {"coordinates":[-95.310255,35.733867],"type":"Point"}
}