{
  "type": "Feature",
  "properties": {
    "iso:country":"US",
    "sg:address":"1046 SW 59th St",
    "sg:city":"Oklahoma City",
    "sg:classifiers":[
        {
            "category":"Food & Beverages",
            "subcategory":"Groceries & Convenience Stores",
            "type":"Retail Goods"
        }
    ],
    "sg:phone":"+1 405 632 0232",
    "sg:postcode":"73109",
    "sg:province":"OK",
    "wof:name":"M & D Food Store",
    "wof:placetype":"venue"
},
  "geometry": {"coordinates":[-97.533768,35.406154],"type":"Point"}
}