{
  "type": "Feature",
  "properties": {
    "iso:country":"US",
    "sg:address":"1625 N York St",
    "sg:city":"Muskogee",
    "sg:classifiers":[
        {
            "category":"Home & Garden",
            "subcategory":"Building Materials",
            "type":"Retail Goods"
        }
    ],
    "sg:phone":"+1 918 682 5195",
    "sg:postcode":"74403",
    "sg:province":"OK",
    "sg:tags":[
        "door"
    ],
    "wof:name":"Quality Overhead Doors",
    "wof:placetype":"venue"
},
  "geometry": {"coordinates":[-95.34044799999999,35.763059],"type":"Point"}
}