{
  "type": "Feature",
  "properties": {
    "addr:full":"901 I St NW Miami OK 74354",
    "addr:housenumber":"901",
    "addr:postcode":"74354",
    "addr:street":"I St Nw",
    "iso:country":"US",
    "sg:address":"901 I St NW",
    "sg:city":"Miami",
    "sg:classifiers":[
        {
            "category":"Retail",
            "subcategory":"Repair Shop",
            "type":"Services"
        }
    ],
    "sg:phone":"+1 918 542 3524",
    "sg:postcode":"74354",
    "sg:province":"OK",
    "wof:name":"Turleys Taxidermy",
    "wof:placetype":"venue"
},
  "geometry": {"coordinates":[-94.887738,36.886669],"type":"Point"}
}