{
  "type": "Feature",
  "properties": {
    "addr:full":"2624 N Saint Louis Ave Tulsa OK 74106",
    "addr:housenumber":"2624",
    "addr:postcode":"74106",
    "addr:street":"N Saint Louis Ave",
    "iso:country":"US",
    "sg:address":"2624 N Saint Louis Ave",
    "sg:city":"Tulsa",
    "sg:classifiers":[
        {
            "category":"Organizations",
            "subcategory":"Religious Organization",
            "type":"Services"
        }
    ],
    "sg:phone":"+1 918 425 4782",
    "sg:postcode":"74106",
    "sg:province":"OK",
    "wof:name":"Oil Capitol Singers Temple",
    "wof:placetype":"venue"
},
  "geometry": {"coordinates":[-95.971161,36.19288],"type":"Point"}
}