{
  "type": "Feature",
  "properties": {
    "iso:country":"US",
    "sg:address":"1030 S Broadway Ave",
    "sg:city":"Ada",
    "sg:classifiers":[
        {
            "category":"Professional",
            "subcategory":"Management & Consulting",
            "type":"Services"
        }
    ],
    "sg:phone":"+1 580 332 1269",
    "sg:postcode":"74820",
    "sg:province":"OK",
    "sg:tags":[
        "educational"
    ],
    "wof:name":"Whitehill Leora",
    "wof:placetype":"venue"
},
  "geometry": {"coordinates":[-96.67855400000001,34.76466],"type":"Point"}
}