{
  "type": "Feature",
  "properties": {
    "iso:country":"US",
    "sg:address":"6737 S 85th East Ave",
    "sg:city":"Tulsa",
    "sg:classifiers":[
        {
            "category":"Professional",
            "subcategory":"Business Services",
            "type":"Services"
        }
    ],
    "sg:phone":"+1 918 852 5646",
    "sg:postcode":"74133",
    "sg:province":"OK",
    "sg:tags":[
        "consultant",
        "coach"
    ],
    "wof:name":"Entrepreneur Authority Oklahoma",
    "wof:placetype":"venue"
},
  "geometry": {"coordinates":[-95.881731,36.067682],"type":"Point"}
}