{
  "type": "Feature",
  "properties": {
    "iso:country":"US",
    "sg:address":"1300 S York St",
    "sg:city":"Muskogee",
    "sg:classifiers":[
        {
            "category":"Food & Beverages",
            "subcategory":"Groceries & Convenience Stores",
            "type":"Retail Goods"
        }
    ],
    "sg:phone":"+1 918 683 2854",
    "sg:postcode":"74403",
    "sg:province":"OK",
    "sg:tags":[
        "grocer"
    ],
    "wof:name":"Homeland",
    "wof:placetype":"venue"
},
  "geometry": {"coordinates":[-95.340409,35.728618],"type":"Point"}
}