{
  "type": "Feature",
  "properties": {
    "addr:full":"4506 NW 11th St Oklahoma City OK 73127",
    "addr:housenumber":"4506",
    "addr:postcode":"73127",
    "addr:street":"Nw 11Th St",
    "iso:country":"US",
    "sg:address":"4506 NW 11th St",
    "sg:city":"Oklahoma City",
    "sg:classifiers":[
        {
            "category":"Personal",
            "subcategory":"Beauty Salon",
            "type":"Services"
        }
    ],
    "sg:phone":"+1 405 917 9377",
    "sg:postcode":"73127",
    "sg:province":"OK",
    "sg:tags":[
        "shop"
    ],
    "wof:name":"Nail Studio",
    "wof:placetype":"venue"
},
  "geometry": {"coordinates":[-97.6031,35.480493],"type":"Point"}
}