{
  "type": "Feature",
  "properties": {
    "iso:country":"US",
    "sg:address":"8121 N Western Ave",
    "sg:city":"Oklahoma City",
    "sg:classifiers":[
        {
            "category":"Food & Beverages",
            "subcategory":"Groceries & Convenience Stores",
            "type":"Retail Goods"
        }
    ],
    "sg:phone":"+1 405 842 2656",
    "sg:postcode":"73114",
    "sg:province":"OK",
    "wof:name":"O K Foodmart",
    "wof:placetype":"venue"
},
  "geometry": {"coordinates":[-97.531468,35.553704],"type":"Point"}
}