{
  "type": "Feature",
  "properties": {
    "iso:country":"US",
    "sg:address":"324 C St NE",
    "sg:city":"Miami",
    "sg:classifiers":[
        {
            "category":"Utilities",
            "subcategory":"Telephone",
            "type":"Services"
        }
    ],
    "sg:phone":"+1 918 542 9767",
    "sg:postcode":"74354",
    "sg:province":"OK",
    "sg:tags":[
        "communications",
        "computer",
        "related"
    ],
    "wof:name":"SF Industries",
    "wof:placetype":"venue"
},
  "geometry": {"coordinates":[-94.874162,36.879863],"type":"Point"}
}