{
  "type": "Feature",
  "properties": {
    "iso:country":"US",
    "sg:address":"55450 E 260 Rd",
    "sg:city":"Afton",
    "sg:classifiers":[
        {
            "category":"Professional",
            "subcategory":"Business Services",
            "type":"Services"
        }
    ],
    "sg:phone":"+1 918 257 8800",
    "sg:postcode":"74331",
    "sg:province":"OK",
    "sg:tags":[
        "embroidery"
    ],
    "wof:name":"Spirit Originals Inc",
    "wof:placetype":"venue"
},
  "geometry": {"coordinates":[-94.886422,36.643074],"type":"Point"}
}