{
  "type": "Feature",
  "properties": {
    "iso:country":"US",
    "sg:address":"1001 W Memorial Rd",
    "sg:city":"Oklahoma City",
    "sg:classifiers":[
        {
            "category":"Autos & Motor Vehicles",
            "subcategory":"Fuel & Gas Station",
            "type":"Retail Goods"
        }
    ],
    "sg:phone":"+1 405 755 8718",
    "sg:postcode":"73114",
    "sg:province":"OK",
    "sg:tags":[
        "station",
        "gasoline",
        "oil"
    ],
    "wof:name":"Memorial West Phillips 66",
    "wof:placetype":"venue"
},
  "geometry": {"coordinates":[-97.530631,35.609105],"type":"Point"}
}