{
  "type": "Feature",
  "properties": {
    "iso:country":"US",
    "sg:address":"2104 N Yellowood Ave",
    "sg:city":"Broken Arrow",
    "sg:classifiers":[
        {
            "category":"Building & Trades",
            "subcategory":"Construction",
            "type":"Services"
        }
    ],
    "sg:phone":"+1 918 307 0212",
    "sg:postcode":"74012",
    "sg:province":"OK",
    "sg:tags":[
        "roofing",
        "contractor"
    ],
    "wof:name":"A A Rooftops Inc",
    "wof:placetype":"venue"
},
  "geometry": {"coordinates":[-95.840458,36.071501],"type":"Point"}
}