{
  "type": "Feature",
  "properties": {
    "iso:country":"US",
    "sg:address":"2010 E 48th St N",
    "sg:city":"Tulsa",
    "sg:classifiers":[
        {
            "category":"Education",
            "subcategory":"School",
            "type":"Public Place"
        }
    ],
    "sg:phone":"+1 918 833 8900",
    "sg:postcode":"74130",
    "sg:province":"OK",
    "sg:tags":[
        "middle"
    ],
    "wof:name":"Monroe Middle School",
    "wof:placetype":"venue"
},
  "geometry": {"coordinates":[-95.96255499999999,36.224134],"type":"Point"}
}