{
  "type": "Feature",
  "properties": {
    "iso:country":"US",
    "sg:address":"207 S Kemp St",
    "sg:city":"Kingston",
    "sg:classifiers":[
        {
            "category":"Building & Trades",
            "subcategory":"Landscaping Services",
            "type":"Services"
        }
    ],
    "sg:phone":"+1 580 564 1980",
    "sg:postcode":"73439",
    "sg:province":"OK",
    "wof:name":"Jodys Cleaning & Lawn Service",
    "wof:placetype":"venue"
},
  "geometry": {"coordinates":[-96.724277,33.996923],"type":"Point"}
}