{
  "type": "Feature",
  "properties": {
    "iso:country":"US",
    "sg:address":"6317 NW 23rd St",
    "sg:city":"Bethany",
    "sg:classifiers":[
        {
            "category":"Manufacturing",
            "subcategory":"Retail Goods",
            "type":"Manufacturing & Wholesale Goods"
        }
    ],
    "sg:phone":"+1 405 789 7190",
    "sg:postcode":"73008",
    "sg:province":"OK",
    "sg:tags":[
        "manufacturer"
    ],
    "wof:name":"Uni-TIZER Ss & N Industries",
    "wof:placetype":"venue"
},
  "geometry": {"coordinates":[-97.624896,35.493292],"type":"Point"}
}