{
  "type": "Feature",
  "properties": {
    "iso:country":"US",
    "sg:address":"6044 S Western Ave",
    "sg:city":"Oklahoma City",
    "sg:classifiers":[
        {
            "category":"Professional",
            "subcategory":"Lawyer & Legal Services",
            "type":"Services"
        }
    ],
    "sg:phone":"+1 405 632 4646",
    "sg:postcode":"73139",
    "sg:province":"OK",
    "wof:name":"Gonshor Jerome D Jr",
    "wof:placetype":"venue"
},
  "geometry": {"coordinates":[-97.530108,35.405691],"type":"Point"}
}