{
  "type": "Feature",
  "properties": {
    "iso:country":"US",
    "sg:address":"304 E Rogers Blvd",
    "sg:city":"Skiatook",
    "sg:classifiers":[
        {
            "category":"Organizations",
            "subcategory":"Professional Association",
            "type":"Services"
        }
    ],
    "sg:phone":"+1 918 396 3702",
    "sg:postcode":"74070",
    "sg:province":"OK",
    "sg:tags":[
        "chambers",
        "commerce"
    ],
    "sg:website":"www.skiatookchamber.com",
    "wof:name":"Skiatook Chamber Of Commerce",
    "wof:placetype":"venue"
},
  "geometry": {"coordinates":[-95.998836,36.36847],"type":"Point"}
}