{
  "type": "Feature",
  "properties": {
    "addr:full":"2321 SW 100th St Oklahoma City OK 73159",
    "addr:housenumber":"2321",
    "addr:postcode":"73159",
    "addr:street":"Sw 100Th St",
    "iso:country":"US",
    "sg:address":"2321 SW 100th St",
    "sg:city":"Oklahoma City",
    "sg:classifiers":[
        {
            "category":"Manufacturing",
            "subcategory":"Tools & Machinery",
            "type":"Manufacturing & Wholesale Goods"
        }
    ],
    "sg:phone":"+1 405 691 5551",
    "sg:postcode":"73159",
    "sg:province":"OK",
    "sg:tags":[
        "industrial",
        "mfg"
    ],
    "wof:name":"Honing By Hardy",
    "wof:placetype":"venue"
},
  "geometry": {"coordinates":[-97.552505,35.367481],"type":"Point"}
}