{
  "type": "Feature",
  "properties": {
    "iso:country":"US",
    "sg:address":"1800 S Baltimore Ave",
    "sg:city":"Tulsa",
    "sg:classifiers":[
        {
            "category":"Professional",
            "subcategory":"Management & Consulting",
            "type":"Services"
        }
    ],
    "sg:phone":"+1 918 585 9166",
    "sg:postcode":"74119",
    "sg:province":"OK",
    "sg:tags":[
        "consultant"
    ],
    "wof:name":"Hartland Consulting LLC",
    "wof:placetype":"venue"
},
  "geometry": {"coordinates":[-95.98638,36.134861],"type":"Point"}
}