{
  "type": "Feature",
  "properties": {
    "iso:country":"US",
    "sg:address":"305 White St",
    "sg:city":"Norman",
    "sg:classifiers":[
        {
            "category":"Professional",
            "subcategory":"Lawyer & Legal Services",
            "type":"Services"
        }
    ],
    "sg:phone":"+1 405 310 2777",
    "sg:postcode":"73069",
    "sg:province":"OK",
    "sg:tags":[
        "attorney"
    ],
    "wof:name":"Pate & Weingartner LLP",
    "wof:placetype":"venue"
},
  "geometry": {"coordinates":[-97.444495,35.213077],"type":"Point"}
}