{
  "type": "Feature",
  "properties": {
    "iso:country":"US",
    "sg:address":"7743 E 38th St",
    "sg:city":"Tulsa",
    "sg:classifiers":[
        {
            "category":"Wholesale",
            "subcategory":"Chemicals & Plastics",
            "type":"Manufacturing & Wholesale Goods"
        }
    ],
    "sg:phone":"+1 918 622 8430",
    "sg:postcode":"74145",
    "sg:province":"OK",
    "wof:name":"Plastic Supply & Fabrication",
    "wof:placetype":"venue"
},
  "geometry": {"coordinates":[-95.893011,36.10812],"type":"Point"}
}