{
  "type": "Feature",
  "properties": {
    "iso:country":"US",
    "sg:address":"6501 Acorn Dr",
    "sg:city":"Oklahoma City",
    "sg:classifiers":[
        {
            "category":"Professional",
            "subcategory":"Computer Services",
            "type":"Services"
        }
    ],
    "sg:phone":"+1 405 771 5676",
    "sg:postcode":"73151",
    "sg:province":"OK",
    "sg:tags":[
        "datum"
    ],
    "wof:name":"Webportal Service LLC",
    "wof:placetype":"venue"
},
  "geometry": {"coordinates":[-97.414555,35.560323],"type":"Point"}
}