{
  "type": "Feature",
  "properties": {
    "addr:full":"6501 Acorn Dr Oklahoma City OK 73151",
    "addr:housenumber":"6501",
    "addr:postcode":"73151",
    "addr:street":"Acorn Dr",
    "iso:country":"US",
    "sg:address":"6501 Acorn Dr",
    "sg:city":"Oklahoma City",
    "sg:classifiers":[
        {
            "category":"Professional",
            "subcategory":"Computer Services",
            "type":"Services"
        }
    ],
    "sg:phone":"+1 405 771 5676",
    "sg:postcode":"73151",
    "sg:province":"OK",
    "sg:tags":[
        "datum"
    ],
    "wof:name":"Webportal Service LLC",
    "wof:placetype":"venue"
},
  "geometry": {"coordinates":[-97.41455499999999,35.560323],"type":"Point"}
}