{
  "type": "Feature",
  "properties": {
    "iso:country":"US",
    "sg:address":"5413 E 92nd St",
    "sg:city":"Tulsa",
    "sg:classifiers":[
        {
            "category":"Building & Trades",
            "subcategory":"Landscaping Services",
            "type":"Services"
        }
    ],
    "sg:phone":"+1 918 492 1408",
    "sg:postcode":"74137",
    "sg:province":"OK",
    "sg:tags":[
        "designer",
        "landscape"
    ],
    "wof:name":"D S Kauffmann & Assoc Inc",
    "wof:placetype":"venue"
},
  "geometry": {"coordinates":[-95.915539,36.029357],"type":"Point"}
}