{
  "type": "Feature",
  "properties": {
    "iso:country":"US",
    "sg:address":"1032 Cedar Hill Pl",
    "sg:city":"Midwest City",
    "sg:classifiers":[
        {
            "category":"Insurance",
            "subcategory":"Insurance Agent",
            "type":"Services"
        }
    ],
    "sg:phone":"+1 405 741 0842",
    "sg:postcode":"73110",
    "sg:province":"OK",
    "wof:name":"Davis Insurance",
    "wof:placetype":"venue"
},
  "geometry": {"coordinates":[-97.381193,35.469864],"type":"Point"}
}