{
  "type": "Feature",
  "properties": {
    "iso:country":"US",
    "sg:address":"1150 S Joplin Ave",
    "sg:city":"Tulsa",
    "sg:classifiers":[
        {
            "category":"Building & Trades",
            "subcategory":"Plumbing",
            "type":"Services"
        }
    ],
    "sg:phone":"+1 918 834 5737",
    "sg:postcode":"74112",
    "sg:province":"OK",
    "sg:tags":[
        "refrigeration",
        "contractor"
    ],
    "wof:name":"Sigler Sales & Service",
    "wof:placetype":"venue"
},
  "geometry": {"coordinates":[-95.91135300000001,36.147069],"type":"Point"}
}