{
  "type": "Feature",
  "properties": {
    "iso:country":"US",
    "sg:address":"1611 N Classen Blvd",
    "sg:city":"Oklahoma City",
    "sg:classifiers":[
        {
            "category":"Shopping",
            "type":"Retail Goods"
        }
    ],
    "sg:phone":"+1 405 528 6363",
    "sg:postcode":"73106",
    "sg:province":"OK",
    "sg:tags":[
        "miscellaneous",
        "store"
    ],
    "wof:name":"Nene Thomas Illustrations",
    "wof:placetype":"venue"
},
  "geometry": {"coordinates":[-97.530077,35.485958],"type":"Point"}
}