{
  "type": "Feature",
  "properties": {
    "addr:full":"1512 S Oak St Kingfisher OK 73750",
    "addr:housenumber":"1512",
    "addr:postcode":"73750",
    "addr:street":"S Oak St",
    "iso:country":"US",
    "sg:address":"1512 S Oak St",
    "sg:city":"Kingfisher",
    "sg:classifiers":[
        {
            "category":"Professional",
            "type":"Services"
        }
    ],
    "sg:phone":"+1 405 375 6544",
    "sg:postcode":"73750",
    "sg:province":"OK",
    "wof:name":"Tumbleweed Services",
    "wof:placetype":"venue"
},
  "geometry": {"coordinates":[-97.9372,35.844192],"type":"Point"}
}