{
  "type": "Feature",
  "properties": {
    "iso:country":"US",
    "sg:address":"2200 SW 59th St",
    "sg:city":"Oklahoma City",
    "sg:classifiers":[
        {
            "category":"Health Services",
            "subcategory":"Doctor",
            "type":"Services"
        }
    ],
    "sg:phone":"+1 405 685 4360",
    "sg:postcode":"73119",
    "sg:province":"OK",
    "sg:tags":[
        "physician",
        "surgeon"
    ],
    "wof:name":"Richard J Langerman PC",
    "wof:placetype":"venue"
},
  "geometry": {"coordinates":[-97.553613,35.406197],"type":"Point"}
}