{
  "type": "Feature",
  "properties": {
    "iso:country":"US",
    "sg:address":"11609 N Santa Fe Ave",
    "sg:city":"Oklahoma City",
    "sg:classifiers":[
        {
            "category":"Wholesale",
            "subcategory":"Machinery & Supplies",
            "type":"Manufacturing & Wholesale Goods"
        }
    ],
    "sg:phone":"+1 405 755 5318",
    "sg:postcode":"73114",
    "sg:province":"OK",
    "sg:tags":[
        "field",
        "oil"
    ],
    "wof:name":"Excalibur Oilfield Supply",
    "wof:placetype":"venue"
},
  "geometry": {"coordinates":[-97.51381000000001,35.593159],"type":"Point"}
}