{
  "type": "Feature",
  "properties": {
    "addr:full":"206 A St NW Miami OK 74354",
    "addr:housenumber":"206",
    "addr:postcode":"74354",
    "addr:street":"A St Nw",
    "iso:country":"US",
    "sg:address":"206 A St NW",
    "sg:city":"Miami",
    "sg:classifiers":[
        {
            "category":"Health Services",
            "subcategory":"Nursing And Care Facility",
            "type":"Services"
        }
    ],
    "sg:phone":"+1 918 541 9325",
    "sg:postcode":"74354",
    "sg:province":"OK",
    "sg:tags":[
        "skilled"
    ],
    "wof:name":"Heaven & Earth Hospice",
    "wof:placetype":"venue"
},
  "geometry": {"coordinates":[-94.87855500000001,36.878943],"type":"Point"}
}