{
  "type": "Feature",
  "properties": {
    "addr:full":"15309 S Hwy 69 Miami OK 74354",
    "addr:housenumber":"15309",
    "addr:postcode":"74354",
    "addr:street":"S Hwy 69",
    "iso:country":"US",
    "sg:address":"15309 S Hwy 69",
    "sg:city":"Miami",
    "sg:classifiers":[
        {
            "category":"Organizations",
            "subcategory":"Religious Organization",
            "type":"Services"
        }
    ],
    "sg:phone":"+1 918 542 1713",
    "sg:postcode":"74354",
    "sg:province":"OK",
    "sg:tags":[
        "church"
    ],
    "wof:name":"Narcissa First Baptist Church",
    "wof:placetype":"venue"
},
  "geometry": {"coordinates":[-94.927244,36.796746],"type":"Point"}
}