{
  "type": "Feature",
  "properties": {
    "addr:full":"19705 Harrison Rd Shawnee OK 74801",
    "addr:housenumber":"19705",
    "addr:postcode":"74801",
    "addr:street":"Harrison Rd",
    "iso:country":"US",
    "sg:address":"19705 Harrison Rd",
    "sg:city":"Shawnee",
    "sg:classifiers":[
        {
            "category":"Retail",
            "subcategory":"Animal Services",
            "type":"Services"
        }
    ],
    "sg:phone":"+1 405 275 0824",
    "sg:postcode":"74801",
    "sg:province":"OK",
    "sg:tags":[
        "farm",
        "breeding"
    ],
    "wof:name":"Roy Browning Ranch",
    "wof:placetype":"venue"
},
  "geometry": {"coordinates":[-96.912999,35.27871],"type":"Point"}
}