{
  "type": "Feature",
  "properties": {
    "iso:country":"US",
    "sg:address":"500 N Meridian Ave",
    "sg:city":"Oklahoma City",
    "sg:classifiers":[
        {
            "category":"Manufacturing",
            "subcategory":"Printing",
            "type":"Manufacturing & Wholesale Goods"
        }
    ],
    "sg:phone":"+1 405 917 9662",
    "sg:postcode":"73107",
    "sg:province":"OK",
    "sg:tags":[
        "publishing",
        "monthly",
        "house",
        "magazine",
        "newspaper",
        "news"
    ],
    "wof:name":"Oklahoma Woman Inc",
    "wof:placetype":"venue"
},
  "geometry": {"coordinates":[-97.601027,35.47112],"type":"Point"}
}