{
  "type": "Feature",
  "properties": {
    "iso:country":"US",
    "sg:address":"1201 SW 89th St",
    "sg:city":"Oklahoma City",
    "sg:classifiers":[
        {
            "category":"Health Services",
            "subcategory":"Doctor",
            "type":"Services"
        }
    ],
    "sg:phone":"+1 405 632 2273",
    "sg:postcode":"73139",
    "sg:province":"OK",
    "wof:name":"Associated Dental Services",
    "wof:placetype":"venue"
},
  "geometry": {"coordinates":[-97.540092,35.377138],"type":"Point"}
}