{
  "type": "Feature",
  "properties": {
    "iso:country":"US",
    "sg:address":"3606 W Randolph Ave",
    "sg:city":"Enid",
    "sg:classifiers":[
        {
            "category":"Autos & Motor Vehicles",
            "subcategory":"Automobile Sales",
            "type":"Retail Goods"
        }
    ],
    "sg:phone":"+1 580 234 4145",
    "sg:postcode":"73703",
    "sg:province":"OK",
    "sg:tags":[
        "used"
    ],
    "wof:name":"Family Car Center",
    "wof:placetype":"venue"
},
  "geometry": {"coordinates":[-97.925442,36.398135],"type":"Point"}
}