{
  "type": "Feature",
  "properties": {
    "iso:country":"US",
    "sg:address":"900 SW 2nd St",
    "sg:city":"Checotah",
    "sg:classifiers":[
        {
            "category":"Personal",
            "subcategory":"Beauty Salon",
            "type":"Services"
        }
    ],
    "sg:phone":"+1 918 689 4247",
    "sg:postcode":"74426",
    "sg:province":"OK",
    "wof:name":"Snips-N-Tips",
    "wof:placetype":"venue"
},
  "geometry": {"coordinates":[-95.527684,35.46308],"type":"Point"}
}