{
  "type": "Feature",
  "properties": {
    "addr:full":"5535 S Vancouver Pl Tulsa OK 74107",
    "addr:housenumber":"5535",
    "addr:postcode":"74107",
    "addr:street":"S Vancouver Pl",
    "iso:country":"US",
    "sg:address":"5535 S Vancouver Pl",
    "sg:city":"Tulsa",
    "sg:classifiers":[
        {
            "category":"Building & Trades",
            "subcategory":"Construction",
            "type":"Services"
        }
    ],
    "sg:phone":"+1 918 446 6454",
    "sg:postcode":"74107",
    "sg:province":"OK",
    "sg:tags":[
        "home",
        "improvement"
    ],
    "wof:name":"Martinez Professional Remodel",
    "wof:placetype":"venue"
},
  "geometry": {"coordinates":[-96.01304,36.081008],"type":"Point"}
}