{
  "type": "Feature",
  "properties": {
    "addr:full":"2525 NW Expwy Svc Rd Oklahoma City OK 73112",
    "addr:housenumber":"2525",
    "addr:postcode":"73112",
    "addr:street":"Nw Expwy;Rd",
    "iso:country":"US",
    "sg:address":"2525 NW Expwy Svc Rd",
    "sg:city":"Oklahoma City",
    "sg:classifiers":[
        {
            "category":"Professional",
            "subcategory":"Management & Consulting",
            "type":"Services"
        }
    ],
    "sg:phone":"+1 405 840 1592",
    "sg:postcode":"73112",
    "sg:province":"OK",
    "sg:tags":[
        "financial"
    ],
    "wof:name":"Dean & Payne Fincl Resource",
    "wof:placetype":"venue"
},
  "geometry": {"coordinates":[-97.558156,35.524536],"type":"Point"}
}