{
  "type": "Feature",
  "properties": {
    "addr:full":"323 S Main St Noble OK 73068",
    "addr:housenumber":"323",
    "addr:postcode":"73068",
    "addr:street":"S Main St",
    "iso:country":"US",
    "sg:address":"323 S Main St",
    "sg:city":"Noble",
    "sg:classifiers":[
        {
            "category":"Personal",
            "subcategory":"Tanning Parlor",
            "type":"Services"
        }
    ],
    "sg:phone":"+1 405 872 1303",
    "sg:postcode":"73068",
    "sg:province":"OK",
    "sg:tags":[
        "salon"
    ],
    "wof:name":"Sunkissed",
    "wof:placetype":"venue"
},
  "geometry": {"coordinates":[-97.394615,35.136244],"type":"Point"}
}