{
  "type": "Feature",
  "properties": {
    "addr:full":"617 W Trudgeon St Henryetta OK 74437",
    "addr:housenumber":"617",
    "addr:postcode":"74437",
    "addr:street":"W Trudgeon St",
    "iso:country":"US",
    "sg:address":"617 W Trudgeon St",
    "sg:city":"Henryetta",
    "sg:classifiers":[
        {
            "category":"Health Services",
            "subcategory":"Doctor",
            "type":"Services"
        }
    ],
    "sg:phone":"+1 918 652 4400",
    "sg:postcode":"74437",
    "sg:province":"OK",
    "sg:tags":[
        "clinic"
    ],
    "wof:name":"Henryetta Family Clinic",
    "wof:placetype":"venue"
},
  "geometry": {"coordinates":[-95.989422,35.440789],"type":"Point"}
}