{
  "type": "Feature",
  "properties": {
    "addr:full":"129 N Louis Tittle Ave Mangum OK 73554",
    "addr:housenumber":"129",
    "addr:postcode":"73554",
    "addr:street":"N Louis Tittle Ave",
    "iso:country":"US",
    "sg:address":"129 N Louis Tittle Ave",
    "sg:city":"Mangum",
    "sg:classifiers":[
        {
            "category":"Autos & Motor Vehicles",
            "subcategory":"Automobile Sales",
            "type":"Retail Goods"
        }
    ],
    "sg:phone":"+1 580 782 5165",
    "sg:postcode":"73554",
    "sg:province":"OK",
    "sg:tags":[
        "used"
    ],
    "wof:name":"Dons Used Cars",
    "wof:placetype":"venue"
},
  "geometry": {"coordinates":[-99.50279500000001,34.873766],"type":"Point"}
}