{
  "type": "Feature",
  "properties": {
    "iso:country":"US",
    "sg:address":"521 W Broadway St",
    "sg:city":"Muskogee",
    "sg:classifiers":[
        {
            "category":"Retail",
            "subcategory":"Portrait Studio",
            "type":"Services"
        }
    ],
    "sg:phone":"+1 918 683 2222",
    "sg:postcode":"74401",
    "sg:province":"OK",
    "sg:tags":[
        "photographer"
    ],
    "wof:name":"Jim Fowler Studio",
    "wof:placetype":"venue"
},
  "geometry": {"coordinates":[-95.37433,35.750583],"type":"Point"}
}