{
  "type": "Feature",
  "properties": {
    "addr:full":"7701 S Sandusky Ave Tulsa OK 74136",
    "addr:housenumber":"7701",
    "addr:postcode":"74136",
    "addr:street":"S Sandusky Ave",
    "iso:country":"US",
    "sg:address":"7701 S Sandusky Ave",
    "sg:city":"Tulsa",
    "sg:classifiers":[
        {
            "category":"Professional",
            "subcategory":"Management & Consulting",
            "type":"Services"
        }
    ],
    "sg:phone":"+1 918 497 7974",
    "sg:postcode":"74136",
    "sg:province":"OK",
    "sg:tags":[
        "business"
    ],
    "wof:name":"Beauty For All Ssons By Marian",
    "wof:placetype":"venue"
},
  "geometry": {"coordinates":[-95.926277,36.051713],"type":"Point"}
}