{
  "type": "Feature",
  "properties": {
    "addr:full":"1126 Crossroads Mall Dr Oklahoma City OK 73149",
    "addr:housenumber":"1126",
    "addr:postcode":"73149",
    "addr:street":"Crossroads Mall Dr",
    "iso:country":"US",
    "sg:address":"1126 Crossroads Mall Dr",
    "sg:city":"Oklahoma City",
    "sg:classifiers":[
        {
            "category":"Retail",
            "subcategory":"Portrait Studio",
            "type":"Services"
        }
    ],
    "sg:phone":"+1 405 631 3233",
    "sg:postcode":"73149",
    "sg:province":"OK",
    "sg:tags":[
        "photographer"
    ],
    "wof:name":"Glamour Shots",
    "wof:placetype":"venue"
},
  "geometry": {"coordinates":[-97.49094100000001,35.397678],"type":"Point"}
}