{
  "type": "Feature",
  "properties": {
    "iso:country":"US",
    "sg:address":"215 E Comanche St",
    "sg:city":"Norman",
    "sg:classifiers":[
        {
            "category":"Manufacturing",
            "subcategory":"Printing",
            "type":"Manufacturing & Wholesale Goods"
        }
    ],
    "sg:phone":"+1 405 366 3500",
    "sg:postcode":"73069",
    "sg:province":"OK",
    "sg:tags":[
        "newspaper"
    ],
    "sg:website":"www.normantranscript.com",
    "wof:name":"Norman Transcript",
    "wof:placetype":"venue"
},
  "geometry": {"coordinates":[-97.440121,35.221113],"type":"Point"}
}