{
  "type": "Feature",
  "properties": {
    "iso:country":"US",
    "sg:address":"2826 E 84th St",
    "sg:city":"Tulsa",
    "sg:classifiers":[
        {
            "category":"Wholesale",
            "subcategory":"Machinery & Supplies",
            "type":"Manufacturing & Wholesale Goods"
        }
    ],
    "sg:phone":"+1 918 493 2222",
    "sg:postcode":"74137",
    "sg:province":"OK",
    "sg:tags":[
        "machine",
        "tool",
        "sales"
    ],
    "wof:name":"CMS Machinery Sales Inc",
    "wof:placetype":"venue"
},
  "geometry": {"coordinates":[-95.945983,36.041882],"type":"Point"}
}