{
  "type": "Feature",
  "properties": {
    "iso:country":"US",
    "sg:address":"1512 W Columbia St",
    "sg:city":"Okemah",
    "sg:classifiers":[
        {
            "category":"Utilities",
            "subcategory":"Water",
            "type":"Services"
        }
    ],
    "sg:phone":"+1 918 623 2487",
    "sg:postcode":"74859",
    "sg:province":"OK",
    "sg:tags":[
        "company",
        "sewage"
    ],
    "wof:name":"Water District No 2",
    "wof:placetype":"venue"
},
  "geometry": {"coordinates":[-96.31844599999999,35.435176],"type":"Point"}
}