{
  "type": "Feature",
  "properties": {
    "addr:full":"371 W Weldon Ave Copan OK 74022",
    "addr:housenumber":"371",
    "addr:postcode":"74022",
    "addr:street":"W Weldon Ave",
    "iso:country":"US",
    "sg:address":"371 W Weldon Ave",
    "sg:city":"Copan",
    "sg:classifiers":[
        {
            "category":"Government",
            "subcategory":"Office",
            "type":"Public Place"
        }
    ],
    "sg:phone":"+1 918 532 4222",
    "sg:postcode":"74022",
    "sg:province":"OK",
    "sg:tags":[
        "general"
    ],
    "wof:name":"Washington County Road Dept",
    "wof:placetype":"venue"
},
  "geometry": {"coordinates":[-95.932303,36.895087],"type":"Point"}
}