{
  "type": "Feature",
  "properties": {
    "iso:country":"US",
    "sg:address":"3801 NW 122nd St",
    "sg:city":"Oklahoma City",
    "sg:classifiers":[
        {
            "category":"Banks & Credit Unions",
            "subcategory":"Bank",
            "type":"Services"
        }
    ],
    "sg:phone":"+1 405 752 5100",
    "sg:postcode":"73120",
    "sg:province":"OK",
    "sg:tags":[
        "state"
    ],
    "wof:name":"First Enterprise Bank Inc",
    "wof:placetype":"venue"
},
  "geometry": {"coordinates":[-97.587063,35.594715],"type":"Point"}
}