{
  "type": "Feature",
  "properties": {
    "addr:full":"4101 Maple Dr Sand Springs OK 74063",
    "addr:housenumber":"4101",
    "addr:postcode":"74063",
    "addr:street":"Maple Dr",
    "iso:country":"US",
    "sg:address":"4101 Maple Dr",
    "sg:city":"Sand Springs",
    "sg:classifiers":[
        {
            "category":"Social Services",
            "subcategory":"Child Care",
            "type":"Services"
        },
        {
            "category":"Education",
            "subcategory":"School",
            "type":"Public Place"
        }
    ],
    "sg:phone":"+1 918 245 6602",
    "sg:postcode":"74063",
    "sg:province":"OK",
    "sg:tags":[
        "kindergarten",
        "academic",
        "day"
    ],
    "wof:name":"Lake Country Christian School",
    "wof:placetype":"venue"
},
  "geometry": {"coordinates":[-96.13155999999999,36.104757],"type":"Point"}
}