{
  "type": "Feature",
  "properties": {
    "iso:country":"US",
    "sg:address":"116 S Dawson St",
    "sg:city":"Meeker",
    "sg:classifiers":[
        {
            "category":"Restaurant",
            "type":"Food & Drink"
        }
    ],
    "sg:menulink":"http://www.allmenus.com/ok/meeker/144346-subway/menu/",
    "sg:phone":"+1 405 279 2679",
    "sg:postcode":"74855",
    "sg:province":"OK",
    "sg:tags":[
        "american",
        "sandwich"
    ],
    "wof:name":"Subway",
    "wof:placetype":"venue"
},
  "geometry": {"coordinates":[-96.89449399999999,35.503091],"type":"Point"}
}