{
  "type": "Feature",
  "properties": {
    "iso:country":"US",
    "sg:address":"636 Reynolds Rd",
    "sg:city":"Edmond",
    "sg:phone":"+1 405 340 0699",
    "sg:postcode":"73013",
    "sg:province":"OK",
    "sg:tags":[
        "farm",
        "field",
        "crop"
    ],
    "wof:name":"Ray Elliott",
    "wof:placetype":"venue"
},
  "geometry": {"coordinates":[-97.470814,35.632029],"type":"Point"}
}