{
  "type": "Feature",
  "properties": {
    "iso:country":"US",
    "sg:address":"909 S Meridian Ave",
    "sg:city":"Oklahoma City",
    "sg:classifiers":[
        {
            "category":"Banks & Credit Unions",
            "subcategory":"Bank",
            "type":"Services"
        }
    ],
    "sg:phone":"+1 405 946 2265",
    "sg:postcode":"73108",
    "sg:province":"OK",
    "sg:tags":[
        "banking",
        "commercial"
    ],
    "wof:name":"Bank2 Funding LLC",
    "wof:placetype":"venue"
},
  "geometry": {"coordinates":[-97.601175,35.45407],"type":"Point"}
}