{
  "type": "Feature",
  "properties": {
    "iso:country":"US",
    "sg:address":"201 Oak Ave",
    "sg:city":"Yukon",
    "sg:classifiers":[
        {
            "category":"Manufacturing",
            "subcategory":"Retail Goods",
            "type":"Manufacturing & Wholesale Goods"
        }
    ],
    "sg:phone":"+1 405 354 9412",
    "sg:postcode":"73099",
    "sg:province":"OK",
    "sg:tags":[
        "manufacturer"
    ],
    "wof:name":"Har-Bar Industries",
    "wof:placetype":"venue"
},
  "geometry": {"coordinates":[-97.745894,35.504784],"type":"Point"}
}