{
  "type": "Feature",
  "properties": {
    "iso:country":"US",
    "sg:address":"11720 E 11th St",
    "sg:city":"Tulsa",
    "sg:classifiers":[
        {
            "category":"Restaurant",
            "type":"Food & Drink"
        }
    ],
    "sg:phone":"+1 918 437 3586",
    "sg:postcode":"74128",
    "sg:province":"OK",
    "sg:tags":[
        "style",
        "family",
        "lunch",
        "american",
        "brunch",
        "breakfast"
    ],
    "sg:website":"http://www.dennys.com",
    "wof:name":"Denny's",
    "wof:placetype":"venue"
},
  "geometry": {"coordinates":[-95.846508,36.147913],"type":"Point"}
}