{
  "type": "Feature",
  "properties": {
    "iso:country":"US",
    "sg:address":"204 NW 17th St",
    "sg:city":"Oklahoma City",
    "sg:classifiers":[
        {
            "category":"Insurance",
            "subcategory":"Insurance Agent",
            "type":"Services"
        }
    ],
    "sg:phone":"+1 405 793 7200",
    "sg:postcode":"73103",
    "sg:province":"OK",
    "wof:name":"Boston Mutual Life Insurance",
    "wof:placetype":"venue"
},
  "geometry": {"coordinates":[-97.515875,35.487],"type":"Point"}
}