{
  "type": "Feature",
  "properties": {
    "addr:full":"3815 Oklahoma Ave Woodward OK 73801",
    "addr:housenumber":"3815",
    "addr:postcode":"73801",
    "addr:street":"Oklahoma Ave",
    "iso:country":"US",
    "sg:address":"3815 Oklahoma Ave",
    "sg:city":"Woodward",
    "sg:classifiers":[
        {
            "category":"Building & Trades",
            "subcategory":"Construction",
            "type":"Services"
        }
    ],
    "sg:phone":"+1 580 254 5019",
    "sg:postcode":"73801",
    "sg:province":"OK",
    "sg:tags":[
        "boring",
        "drilling",
        "contractor"
    ],
    "wof:name":"KODA Drilling Inc",
    "wof:placetype":"venue"
},
  "geometry": {"coordinates":[-99.431991,36.433446],"type":"Point"}
}