{
  "type": "Feature",
  "properties": {
    "iso:country":"US",
    "sg:address":"1113 S Douglas Blvd",
    "sg:city":"Midwest City",
    "sg:classifiers":[
        {
            "category":"Wholesale",
            "subcategory":"Computers",
            "type":"Manufacturing & Wholesale Goods"
        }
    ],
    "sg:phone":"+1 405 733 5554",
    "sg:postcode":"73130",
    "sg:province":"OK",
    "sg:tags":[
        "equipment",
        "processing",
        "datum"
    ],
    "wof:name":"Storage Technology Corp",
    "wof:placetype":"venue"
},
  "geometry": {"coordinates":[-97.370918,35.456366],"type":"Point"}
}