{
  "type": "Feature",
  "properties": {
    "addr:full":"111 S 4th St Henryetta OK 74437",
    "addr:housenumber":"111",
    "addr:postcode":"74437",
    "addr:street":"S 4Th St",
    "iso:country":"US",
    "sg:address":"111 S 4th St",
    "sg:city":"Henryetta",
    "sg:classifiers":[
        {
            "category":"Professional",
            "subcategory":"Credit Reporting & Collection",
            "type":"Services"
        }
    ],
    "sg:phone":"+1 918 652 0261",
    "sg:postcode":"74437",
    "sg:province":"OK",
    "sg:tags":[
        "agency"
    ],
    "wof:name":"Premium Business Resources",
    "wof:placetype":"venue"
},
  "geometry": {"coordinates":[-95.985855,35.439683],"type":"Point"}
}