{
  "type": "Feature",
  "properties": {
    "addr:full":"2406 Bell Ave Elk City OK 73644",
    "addr:housenumber":"2406",
    "addr:postcode":"73644",
    "addr:street":"Bell Ave",
    "iso:country":"US",
    "sg:address":"2406 Bell Ave",
    "sg:city":"Elk City",
    "sg:classifiers":[
        {
            "category":"Health Services",
            "subcategory":"Doctor",
            "type":"Services"
        }
    ],
    "sg:phone":"+1 580 225 9420",
    "sg:postcode":"73644",
    "sg:province":"OK",
    "sg:tags":[
        "medical"
    ],
    "wof:name":"Gs Gill Family Clinic",
    "wof:placetype":"venue"
},
  "geometry": {"coordinates":[-99.433013,35.418786],"type":"Point"}
}