{
  "type": "Feature",
  "properties": {
    "iso:country":"US",
    "sg:address":"1611 S Utica Ave",
    "sg:city":"Tulsa",
    "sg:classifiers":[
        {
            "category":"Professional",
            "subcategory":"Management & Consulting",
            "type":"Services"
        }
    ],
    "sg:phone":"+1 918 951 2686",
    "sg:postcode":"74104",
    "sg:province":"OK",
    "sg:tags":[
        "consultant",
        "business"
    ],
    "wof:name":"Platinum Business Resources",
    "wof:placetype":"venue"
},
  "geometry": {"coordinates":[-95.967033,36.138169],"type":"Point"}
}