{
  "type": "Feature",
  "properties": {
    "iso:country":"US",
    "sg:address":"500 W Florence St",
    "sg:city":"Broken Arrow",
    "sg:classifiers":[
        {
            "category":"Retail",
            "subcategory":"Car Wash",
            "type":"Services"
        }
    ],
    "sg:phone":"+1 918 455 3322",
    "sg:postcode":"74011",
    "sg:province":"OK",
    "sg:tags":[
        "polishing",
        "washing"
    ],
    "wof:name":"Auto Pride Car Wash",
    "wof:placetype":"venue"
},
  "geometry": {"coordinates":[-95.794445,36.002899],"type":"Point"}
}