{
  "type": "Feature",
  "properties": {
    "iso:country":"US",
    "sg:address":"423 S Wilson St",
    "sg:city":"Vinita",
    "sg:classifiers":[
        {
            "category":"Autos & Motor Vehicles",
            "subcategory":"Auto Supplies",
            "type":"Retail Goods"
        }
    ],
    "sg:phone":"+1 918 256 6431",
    "sg:postcode":"74301",
    "sg:province":"OK",
    "sg:tags":[
        "automobile",
        "parts"
    ],
    "wof:name":"C-B Co 105",
    "wof:placetype":"venue"
},
  "geometry": {"coordinates":[-95.158024,36.632706],"type":"Point"}
}