{
  "type": "Feature",
  "properties": {
    "addr:full":"13850 S Meridian Ave Oklahoma City OK 73173",
    "addr:housenumber":"13850",
    "addr:postcode":"73173",
    "addr:street":"S Meridian Ave",
    "iso:country":"US",
    "sg:address":"13850 S Meridian Ave",
    "sg:city":"Oklahoma City",
    "sg:classifiers":[
        {
            "category":"Freight",
            "type":"Transportation"
        }
    ],
    "sg:phone":"+1 405 692 2815",
    "sg:postcode":"73173",
    "sg:province":"OK",
    "sg:tags":[
        "trucking"
    ],
    "wof:name":"R D Hoffman Enterprise",
    "wof:placetype":"venue"
},
  "geometry": {"coordinates":[-97.60042900000001,35.336362],"type":"Point"}
}