{
  "type": "Feature",
  "properties": {
    "iso:country":"US",
    "sg:address":"417 N Main St",
    "sg:city":"Guymon",
    "sg:classifiers":[
        {
            "category":"Home & Garden",
            "subcategory":"Carpets & Floor Coverings",
            "type":"Retail Goods"
        }
    ],
    "sg:phone":"+1 580 338 0505",
    "sg:postcode":"73942",
    "sg:province":"OK",
    "wof:name":"Hardestys House of Carpet",
    "wof:placetype":"venue"
},
  "geometry": {"coordinates":[-101.48148,36.681985],"type":"Point"}
}