{
  "type": "Feature",
  "properties": {
    "iso:country":"US",
    "sg:address":"3929 E 38th St",
    "sg:city":"Tulsa",
    "sg:classifiers":[
        {
            "category":"Building & Trades",
            "subcategory":"Cleaning & Sanitation",
            "type":"Services"
        }
    ],
    "sg:phone":"+1 918 361 6772",
    "sg:postcode":"74135",
    "sg:province":"OK",
    "sg:tags":[
        "butler",
        "maid"
    ],
    "wof:name":"Helpful Assistant",
    "wof:placetype":"venue"
},
  "geometry": {"coordinates":[-95.931544,36.108045],"type":"Point"}
}