{
  "type": "Feature",
  "properties": {
    "iso:country":"US",
    "sg:address":"6 SE Washington St",
    "sg:city":"Idabel",
    "sg:classifiers":[
        {
            "category":"Building & Trades",
            "subcategory":"Construction",
            "type":"Services"
        }
    ],
    "sg:phone":"+1 580 208 3091",
    "sg:postcode":"74745",
    "sg:province":"OK",
    "sg:tags":[
        "window",
        "replacement"
    ],
    "wof:name":"Capital Windows & Siding",
    "wof:placetype":"venue"
},
  "geometry": {"coordinates":[-94.826203,33.894456],"type":"Point"}
}