{
  "type": "Feature",
  "properties": {
    "addr:full":"512 SW Lee Blvd Lawton OK 73501",
    "addr:housenumber":"512",
    "addr:postcode":"73501",
    "addr:street":"Sw Lee Blvd",
    "iso:country":"US",
    "sg:address":"512 SW Lee Blvd",
    "sg:city":"Lawton",
    "sg:classifiers":[
        {
            "category":"Retail",
            "subcategory":"Auto Repair",
            "type":"Services"
        }
    ],
    "sg:phone":"+1 580 357 7660",
    "sg:postcode":"73501",
    "sg:province":"OK",
    "sg:tags":[
        "body"
    ],
    "wof:name":"Classic Body Shop",
    "wof:placetype":"venue"
},
  "geometry": {"coordinates":[-98.396631,34.594202],"type":"Point"}
}