{
  "type": "Feature",
  "properties": {
    "iso:country":"US",
    "sg:address":"219 S Pennsylvania Ave",
    "sg:city":"Oklahoma City",
    "sg:classifiers":[
        {
            "category":"Wholesale",
            "subcategory":"Apparel",
            "type":"Manufacturing & Wholesale Goods"
        }
    ],
    "sg:phone":"+1 405 272 9400",
    "sg:postcode":"73108",
    "sg:province":"OK",
    "sg:tags":[
        "t"
    ],
    "wof:name":"Inkspot",
    "wof:placetype":"venue"
},
  "geometry": {"coordinates":[-97.547981,35.464468],"type":"Point"}
}