{
  "type": "Feature",
  "properties": {
    "iso:country":"US",
    "sg:address":"201 E Broadway St",
    "sg:city":"Altus",
    "sg:classifiers":[
        {
            "category":"Home & Garden",
            "subcategory":"Building Materials",
            "type":"Retail Goods"
        }
    ],
    "sg:phone":"+1 580 482 0510",
    "sg:postcode":"73521",
    "sg:province":"OK",
    "wof:name":"Homezone LLC",
    "wof:placetype":"venue"
},
  "geometry": {"coordinates":[-99.332579,34.637819],"type":"Point"}
}