{
  "type": "Feature",
  "properties": {
    "addr:full":"708 US Hwy 59 Scn Heavener OK 74937",
    "addr:housenumber":"708",
    "addr:postcode":"74937",
    "addr:street":"Us Hwy 59 Scn",
    "iso:country":"US",
    "sg:address":"708 US Hwy 59 Scn",
    "sg:city":"Heavener",
    "sg:classifiers":[
        {
            "category":"Personal",
            "subcategory":"Barber",
            "type":"Services"
        }
    ],
    "sg:phone":"+1 918 653 3257",
    "sg:postcode":"74937",
    "sg:province":"OK",
    "wof:name":"Larry's Barber Shop & Family",
    "wof:placetype":"venue"
},
  "geometry": {"coordinates":[-94.603934,34.887504],"type":"Point"}
}