{
  "type": "Feature",
  "properties": {
    "addr:full":"8105 E Admiral Pl Tulsa OK 74115",
    "addr:housenumber":"8105",
    "addr:postcode":"74115",
    "addr:street":"E Admiral Pl",
    "iso:country":"US",
    "sg:address":"8105 E Admiral Pl",
    "sg:city":"Tulsa",
    "sg:classifiers":[
        {
            "category":"Restaurant",
            "type":"Food & Drink"
        }
    ],
    "sg:phone":"+1 918 838 3776",
    "sg:postcode":"74115",
    "sg:province":"OK",
    "wof:name":"Mc Donald's",
    "wof:placetype":"venue"
},
  "geometry": {"coordinates":[-95.882294,36.160798],"type":"Point"}
}