{
  "type": "Feature",
  "properties": {
    "addr:full":"22702 E 76th St Broken Arrow OK 74014",
    "addr:housenumber":"22702",
    "addr:postcode":"74014",
    "addr:street":"E 76Th St",
    "iso:country":"US",
    "sg:address":"22702 E 76th St",
    "sg:city":"Broken Arrow",
    "sg:classifiers":[
        {
            "category":"Manufacturing",
            "subcategory":"Retail Goods",
            "type":"Manufacturing & Wholesale Goods"
        }
    ],
    "sg:phone":"+1 918 357 3140",
    "sg:postcode":"74014",
    "sg:province":"OK",
    "sg:tags":[
        "product",
        "mfg"
    ],
    "wof:name":"Packer Mfg LLC",
    "wof:placetype":"venue"
},
  "geometry": {"coordinates":[-95.725089,36.055309],"type":"Point"}
}