{
  "type": "Feature",
  "properties": {
    "iso:country":"US",
    "sg:address":"5350 S Western Ave",
    "sg:city":"Oklahoma City",
    "sg:classifiers":[
        {
            "category":"Banks & Credit Unions",
            "subcategory":"Bank",
            "type":"Services"
        }
    ],
    "sg:phone":"+1 405 631 6900",
    "sg:postcode":"73109",
    "sg:province":"OK",
    "sg:tags":[
        "loan",
        "real estate"
    ],
    "wof:name":"Acceptance First Lending Corp",
    "wof:placetype":"venue"
},
  "geometry": {"coordinates":[-97.530125,35.413012],"type":"Point"}
}