{
  "type": "Feature",
  "properties": {
    "addr:full":"905 N Oakwood Rd Enid OK 73703",
    "addr:housenumber":"905",
    "addr:postcode":"73703",
    "addr:street":"N Oakwood Rd",
    "iso:country":"US",
    "sg:address":"905 N Oakwood Rd",
    "sg:city":"Enid",
    "sg:classifiers":[
        {
            "category":"Organizations",
            "subcategory":"Religious Organization",
            "type":"Services"
        }
    ],
    "sg:phone":"+1 580 233 1742",
    "sg:postcode":"73703",
    "sg:province":"OK",
    "wof:name":"First Assembly of God",
    "wof:placetype":"venue"
},
  "geometry": {"coordinates":[-97.92576200000001,36.406209],"type":"Point"}
}