{
  "type": "Feature",
  "properties": {
    "addr:full":"1109 W 14th St Ada OK 74820",
    "addr:housenumber":"1109",
    "addr:postcode":"74820",
    "addr:street":"W 14Th St",
    "iso:country":"US",
    "sg:address":"1109 W 14th St",
    "sg:city":"Ada",
    "sg:classifiers":[
        {
            "category":"Building & Trades",
            "subcategory":"Construction",
            "type":"Services"
        }
    ],
    "sg:phone":"+1 580 310 9393",
    "sg:postcode":"74820",
    "sg:province":"OK",
    "sg:tags":[
        "fence",
        "contractor"
    ],
    "wof:name":"Tim Mills Fence Co",
    "wof:placetype":"venue"
},
  "geometry": {"coordinates":[-96.698381,34.771201],"type":"Point"}
}