{
  "type": "Feature",
  "properties": {
    "iso:country":"US",
    "sg:address":"2520 S Rankin St",
    "sg:city":"Edmond",
    "sg:classifiers":[
        {
            "category":"Social Services",
            "subcategory":"Job Training",
            "type":"Services"
        }
    ],
    "sg:phone":"+1 405 359 7036",
    "sg:postcode":"73013",
    "sg:province":"OK",
    "sg:tags":[
        "rehabilitation"
    ],
    "wof:name":"Rehab Source",
    "wof:placetype":"venue"
},
  "geometry": {"coordinates":[-97.474622,35.630019],"type":"Point"}
}