{
  "type": "Feature",
  "properties": {
    "iso:country":"US",
    "sg:address":"7408 NW 104th St",
    "sg:city":"Oklahoma City",
    "sg:classifiers":[
        {
            "category":"Freight",
            "type":"Transportation"
        }
    ],
    "sg:phone":"+1 405 751 3291",
    "sg:postcode":"73162",
    "sg:province":"OK",
    "sg:tags":[
        "truck"
    ],
    "wof:name":"Professional Fleet Care",
    "wof:placetype":"venue"
},
  "geometry": {"coordinates":[-97.644126,35.57676],"type":"Point"}
}