{
  "type": "Feature",
  "properties": {
    "iso:country":"US",
    "sg:address":"9 N Indianapolis Ave",
    "sg:city":"Tulsa",
    "sg:classifiers":[
        {
            "category":"Building & Trades",
            "subcategory":"Construction",
            "type":"Services"
        }
    ],
    "sg:phone":"+1 918 835 8283",
    "sg:postcode":"74115",
    "sg:province":"OK",
    "sg:tags":[
        "mobile",
        "home"
    ],
    "wof:name":"S & D Mobile Home Utility Hook",
    "wof:placetype":"venue"
},
  "geometry": {"coordinates":[-95.9391,36.161353],"type":"Point"}
}