{
  "type": "Feature",
  "properties": {
    "iso:country":"US",
    "sg:address":"110 W 7th St",
    "sg:city":"Tulsa",
    "sg:classifiers":[
        {
            "category":"Insurance",
            "subcategory":"Insurance Agent",
            "type":"Services"
        }
    ],
    "sg:phone":"+1 918 728 6062",
    "sg:postcode":"74119",
    "sg:province":"OK",
    "wof:name":"Capital Risk LLC",
    "wof:placetype":"venue"
},
  "geometry": {"coordinates":[-95.991309,36.148705],"type":"Point"}
}