{
  "type": "Feature",
  "properties": {
    "iso:country":"US",
    "sg:address":"1502 SW D Ave",
    "sg:city":"Lawton",
    "sg:classifiers":[
        {
            "category":"Health Services",
            "subcategory":"Hospital",
            "type":"Services"
        }
    ],
    "sg:phone":"+1 580 357 8114",
    "sg:postcode":"73501",
    "sg:province":"OK",
    "sg:tags":[
        "rehabilitation",
        "abuse",
        "alcohol",
        "drug",
        "facility"
    ],
    "wof:name":"Miller/Holliday Homes",
    "wof:placetype":"venue"
},
  "geometry": {"coordinates":[-98.411935,34.603968],"type":"Point"}
}