{
  "type": "Feature",
  "properties": {
    "iso:country":"US",
    "sg:address":"1533 SE 66th St",
    "sg:city":"Oklahoma City",
    "sg:classifiers":[
        {
            "category":"Real Estate",
            "subcategory":"Real Estate Agent",
            "type":"Services"
        }
    ],
    "sg:phone":"+1 405 672 9732",
    "sg:postcode":"73149",
    "sg:province":"OK",
    "sg:tags":[
        "management"
    ],
    "wof:name":"Crossroads Business Park",
    "wof:placetype":"venue"
},
  "geometry": {"coordinates":[-97.48445,35.398297],"type":"Point"}
}