{
  "type": "Feature",
  "properties": {
    "iso:country":"US",
    "sg:address":"201 NW Arlington Ave",
    "sg:city":"Lawton",
    "sg:classifiers":[
        {
            "category":"Restaurant",
            "type":"Food & Drink"
        }
    ],
    "sg:phone":"+1 580 248 3502",
    "sg:postcode":"73507",
    "sg:province":"OK",
    "sg:tags":[
        "eating"
    ],
    "wof:name":"Hoffman Bar & Grill",
    "wof:placetype":"venue"
},
  "geometry": {"coordinates":[-98.392026,34.610279],"type":"Point"}
}