{
  "type": "Feature",
  "properties": {
    "iso:country":"US",
    "sg:address":"3623 NW 36th St",
    "sg:city":"Oklahoma City",
    "sg:classifiers":[
        {
            "category":"Wholesale",
            "subcategory":"Office Equipment",
            "type":"Manufacturing & Wholesale Goods"
        }
    ],
    "sg:phone":"+1 405 608 4467",
    "sg:postcode":"73112",
    "sg:province":"OK",
    "wof:name":"Sea Group",
    "wof:placetype":"venue"
},
  "geometry": {"coordinates":[-97.582915,35.507887],"type":"Point"}
}