{
  "type": "Feature",
  "properties": {
    "addr:full":"5515 Spring Creek Cir E Stillwater OK 74074",
    "addr:housenumber":"5515",
    "addr:postcode":"74074",
    "addr:street":"Spring Creek Cir E",
    "iso:country":"US",
    "sg:address":"5515 Spring Creek Cir E",
    "sg:city":"Stillwater",
    "sg:classifiers":[
        {
            "category":"Home & Garden",
            "subcategory":"Building Materials",
            "type":"Retail Goods"
        }
    ],
    "sg:phone":"+1 405 372 5777",
    "sg:postcode":"74074",
    "sg:province":"OK",
    "sg:tags":[
        "screen",
        "window"
    ],
    "wof:name":"Screens Of Oklahoma",
    "wof:placetype":"venue"
},
  "geometry": {"coordinates":[-97.027157,36.059087],"type":"Point"}
}