{
  "type": "Feature",
  "properties": {
    "iso:country":"US",
    "sg:address":"6825 S Delaware Ave",
    "sg:city":"Tulsa",
    "sg:classifiers":[
        {
            "category":"Manufacturing",
            "subcategory":"Tools & Machinery",
            "type":"Manufacturing & Wholesale Goods"
        }
    ],
    "sg:phone":"+1 918 523 9559",
    "sg:postcode":"74136",
    "sg:province":"OK",
    "sg:tags":[
        "mfg"
    ],
    "wof:name":"Base Scale Company",
    "wof:placetype":"venue"
},
  "geometry": {"coordinates":[-95.949125,36.065592],"type":"Point"}
}