{
  "type": "Feature",
  "properties": {
    "addr:full":"2320 W I- 44 Svc Rd Oklahoma City OK 73112",
    "addr:housenumber":"2320;44",
    "addr:postcode":"73112",
    "addr:street":"W I;Rd",
    "iso:country":"US",
    "sg:address":"2320 W I- 44 Svc Rd",
    "sg:city":"Oklahoma City",
    "sg:classifiers":[
        {
            "category":"Social Services",
            "subcategory":"Child Care",
            "type":"Services"
        }
    ],
    "sg:phone":"+1 405 525 5180",
    "sg:postcode":"73112",
    "sg:province":"OK",
    "wof:name":"Quality Care Child Dev Ctr",
    "wof:placetype":"venue"
},
  "geometry": {"coordinates":[-97.550428,35.512726],"type":"Point"}
}