{
  "type": "Feature",
  "properties": {
    "addr:full":"15251 S Hwy 66 Claremore OK 74017",
    "addr:housenumber":"15251",
    "addr:postcode":"74017",
    "addr:street":"S Hwy 66",
    "iso:country":"US",
    "sg:address":"15251 S Hwy 66",
    "sg:city":"Claremore",
    "sg:classifiers":[
        {
            "category":"Manufacturing",
            "subcategory":"Tools & Machinery",
            "type":"Manufacturing & Wholesale Goods"
        }
    ],
    "sg:phone":"+1 918 341 6615",
    "sg:postcode":"74017",
    "sg:province":"OK",
    "sg:tags":[
        "industrial",
        "trailer",
        "mfg"
    ],
    "wof:name":"Starlite Trailer Manufacturing",
    "wof:placetype":"venue"
},
  "geometry": {"coordinates":[-95.558476,36.379441],"type":"Point"}
}