{
  "type": "Feature",
  "properties": {
    "addr:full":"400 W Kenosha St Broken Arrow OK 74012",
    "addr:housenumber":"400",
    "addr:postcode":"74012",
    "addr:street":"W Kenosha St",
    "iso:country":"US",
    "sg:address":"400 W Kenosha St",
    "sg:city":"Broken Arrow",
    "sg:classifiers":[
        {
            "category":"Autos & Motor Vehicles",
            "subcategory":"Automobile Sales",
            "type":"Retail Goods"
        },
        {
            "category":"Professional",
            "subcategory":"Business Services",
            "type":"Services"
        }
    ],
    "sg:phone":"+1 918 251 8181",
    "sg:postcode":"74012",
    "sg:province":"OK",
    "sg:tags":[
        "car",
        "dealer"
    ],
    "wof:name":"Quality Value Auto Sales",
    "wof:placetype":"venue"
},
  "geometry": {"coordinates":[-95.794684,36.060912],"type":"Point"}
}