{
  "type": "Feature",
  "properties": {
    "iso:country":"US",
    "sg:address":"2212 E 5th Pl",
    "sg:city":"Tulsa",
    "sg:classifiers":[
        {
            "category":"Professional",
            "subcategory":"Advertising",
            "type":"Services"
        }
    ],
    "sg:phone":"+1 918 592 2608",
    "sg:postcode":"74104",
    "sg:province":"OK",
    "wof:name":"Cooke Advertising Inc",
    "wof:placetype":"venue"
},
  "geometry": {"coordinates":[-95.95993,36.152653],"type":"Point"}
}