{
  "type": "Feature",
  "properties": {
    "iso:country":"US",
    "sg:address":"1000 N Elm Pl",
    "sg:city":"Broken Arrow",
    "sg:classifiers":[
        {
            "category":"Shopping",
            "subcategory":"Used Merchandise",
            "type":"Retail Goods"
        }
    ],
    "sg:phone":"+1 918 251 2118",
    "sg:postcode":"74012",
    "sg:province":"OK",
    "sg:tags":[
        "shop",
        "thrift"
    ],
    "wof:name":"Gatesway Quality Resale",
    "wof:placetype":"venue"
},
  "geometry": {"coordinates":[-95.797438,36.063052],"type":"Point"}
}