{
  "type": "Feature",
  "properties": {
    "addr:full":"704 NW 143rd St Edmond OK 73013",
    "addr:housenumber":"704",
    "addr:postcode":"73013",
    "addr:street":"Nw 143Rd St",
    "iso:country":"US",
    "sg:address":"704 NW 143rd St",
    "sg:city":"Edmond",
    "sg:classifiers":[
        {
            "category":"Building & Trades",
            "subcategory":"Electrical",
            "type":"Services"
        }
    ],
    "sg:phone":"+1 405 650 5380",
    "sg:postcode":"73013",
    "sg:province":"OK",
    "sg:tags":[
        "electrical",
        "contractor"
    ],
    "wof:name":"J&D Hughes Electric LLC",
    "wof:placetype":"venue"
},
  "geometry": {"coordinates":[-97.526539,35.616218],"type":"Point"}
}