{
  "type": "Feature",
  "properties": {
    "iso:country":"US",
    "sg:address":"108 W 8th St",
    "sg:city":"Chandler",
    "sg:classifiers":[
        {
            "category":"Professional",
            "subcategory":"Business Services",
            "type":"Services"
        }
    ],
    "sg:phone":"+1 405 258 2104",
    "sg:postcode":"74834",
    "sg:province":"OK",
    "wof:name":"Tag Office",
    "wof:placetype":"venue"
},
  "geometry": {"coordinates":[-96.881963,35.702672],"type":"Point"}
}