{
  "type": "Feature",
  "properties": {
    "iso:country":"US",
    "sg:address":"9401 E Admiral Pl",
    "sg:city":"Tulsa",
    "sg:classifiers":[
        {
            "category":"Shopping",
            "subcategory":"Used Merchandise",
            "type":"Retail Goods"
        },
        {
            "category":"Professional",
            "subcategory":"Business Services",
            "type":"Services"
        }
    ],
    "sg:phone":"+1 918 834 9259",
    "sg:postcode":"74115",
    "sg:province":"OK",
    "sg:tags":[
        "flea",
        "market"
    ],
    "wof:name":"Admiral Flea Market Inc",
    "wof:placetype":"venue"
},
  "geometry": {"coordinates":[-95.871645,36.1608],"type":"Point"}
}