{
  "type": "Feature",
  "properties": {
    "iso:country":"US",
    "sg:address":"15604 S Hwy 10",
    "sg:city":"Wyandotte",
    "sg:classifiers":[
        {
            "category":"Building & Trades",
            "subcategory":"Construction",
            "type":"Services"
        }
    ],
    "sg:phone":"+1 918 678 2356",
    "sg:postcode":"74370",
    "sg:province":"OK",
    "sg:tags":[
        "maker",
        "cabinet"
    ],
    "wof:name":"Murphy Brothers Mfg",
    "wof:placetype":"venue"
},
  "geometry": {"coordinates":[-94.697885,36.79014],"type":"Point"}
}