{
  "type": "Feature",
  "properties": {
    "addr:full":"15150 W Frisco Dr Yukon OK 73099",
    "addr:housenumber":"15150",
    "addr:postcode":"73099",
    "addr:street":"W Frisco Dr",
    "iso:country":"US",
    "sg:address":"15150 W Frisco Dr",
    "sg:city":"Yukon",
    "sg:phone":"+1 405 354 8447",
    "sg:postcode":"73099",
    "sg:province":"OK",
    "sg:tags":[
        "farm",
        "wheat"
    ],
    "wof:name":"Chris Kastl",
    "wof:placetype":"venue"
},
  "geometry": {"coordinates":[-97.80376099999999,35.544032],"type":"Point"}
}