{
  "type": "Feature",
  "properties": {
    "addr:full":"2122 Oklahoma Ave Woodward OK 73801",
    "addr:housenumber":"2122",
    "addr:postcode":"73801",
    "addr:street":"Oklahoma Ave",
    "iso:country":"US",
    "sg:address":"2122 Oklahoma Ave",
    "sg:city":"Woodward",
    "sg:classifiers":[
        {
            "category":"Shopping",
            "subcategory":"Gifts & Souvenirs",
            "type":"Retail Goods"
        }
    ],
    "sg:phone":"+1 580 254 3970",
    "sg:postcode":"73801",
    "sg:province":"OK",
    "sg:tags":[
        "shop",
        "party",
        "specialty",
        "supply"
    ],
    "wof:name":"Celebrations",
    "wof:placetype":"venue"
},
  "geometry": {"coordinates":[-99.407172,36.433708],"type":"Point"}
}