{
  "type": "Feature",
  "properties": {
    "addr:full":"10601 NE 36th St Spencer OK 73084",
    "addr:housenumber":"10601",
    "addr:postcode":"73084",
    "addr:street":"Ne 36Th St",
    "iso:country":"US",
    "sg:address":"10601 NE 36th St",
    "sg:city":"Spencer",
    "sg:classifiers":[
        {
            "category":"Organizations",
            "subcategory":"Religious Organization",
            "type":"Services"
        }
    ],
    "sg:phone":"+1 405 769 4826",
    "sg:postcode":"73084",
    "sg:province":"OK",
    "sg:tags":[
        "church"
    ],
    "wof:name":"Christian Valley Msnry Bapt",
    "wof:placetype":"venue"
},
  "geometry": {"coordinates":[-97.342315,35.507512],"type":"Point"}
}