{
  "type": "Feature",
  "properties": {
    "iso:country":"US",
    "sg:address":"320 S Boston Ave",
    "sg:city":"Tulsa",
    "sg:classifiers":[
        {
            "category":"Professional",
            "subcategory":"Advertising",
            "type":"Services"
        }
    ],
    "sg:phone":"+1 918 592 3114",
    "sg:postcode":"74103",
    "sg:province":"OK",
    "sg:tags":[
        "counselor"
    ],
    "wof:name":"Goldspring Design & Marketing",
    "wof:placetype":"venue"
},
  "geometry": {"coordinates":[-95.989625,36.152967],"type":"Point"}
}