{
  "type": "Feature",
  "properties": {
    "iso:country":"US",
    "sg:address":"229 N Maple St",
    "sg:city":"Nowata",
    "sg:classifiers":[
        {
            "category":"Government",
            "subcategory":"Office",
            "type":"Public Place"
        }
    ],
    "sg:phone":"+1 918 273 0175",
    "sg:postcode":"74048",
    "sg:province":"OK",
    "wof:name":"Nowata County Commissioners",
    "wof:placetype":"venue"
},
  "geometry": {"coordinates":[-95.637995,36.702855],"type":"Point"}
}