{
  "type": "Feature",
  "properties": {
    "iso:country":"US",
    "sg:address":"6176 Boucher Dr",
    "sg:city":"Edmond",
    "sg:phone":"+1 405 330 9932",
    "sg:postcode":"73034",
    "sg:province":"OK",
    "sg:tags":[
        "equipment",
        "supply"
    ],
    "wof:name":"O K Restaurant",
    "wof:placetype":"venue"
},
  "geometry": {"coordinates":[-97.41946799999999,35.718932],"type":"Point"}
}