{
  "type": "Feature",
  "properties": {
    "addr:full":"3005 N Pennsylvania Ave Oklahoma City OK 73107",
    "addr:housenumber":"3005",
    "addr:postcode":"73107",
    "addr:street":"N Pennsylvania Ave",
    "iso:country":"US",
    "sg:address":"3005 N Pennsylvania Ave",
    "sg:city":"Oklahoma City",
    "sg:classifiers":[
        {
            "category":"Retail",
            "subcategory":"Laundry & Dry Cleaning",
            "type":"Services"
        }
    ],
    "sg:phone":"+1 405 524 3775",
    "sg:postcode":"73107",
    "sg:province":"OK",
    "wof:name":"Laura Tran",
    "wof:placetype":"venue"
},
  "geometry": {"coordinates":[-97.547787,35.500508],"type":"Point"}
}