{
  "type": "Feature",
  "properties": {
    "iso:country":"US",
    "sg:address":"1318 W Britton Rd",
    "sg:city":"Oklahoma City",
    "sg:classifiers":[
        {
            "category":"Restaurant",
            "type":"Food & Drink"
        }
    ],
    "sg:phone":"+1 405 840 5879",
    "sg:postcode":"73114",
    "sg:province":"OK",
    "sg:website":"www.tacomayo.com",
    "wof:name":"Taco Mayo",
    "wof:placetype":"venue"
},
  "geometry": {"coordinates":[-97.537058,35.565488],"type":"Point"}
}