{
  "type": "Feature",
  "properties": {
    "iso:country":"US",
    "sg:address":"14000 Quail Springs Pkwy",
    "sg:city":"Oklahoma City",
    "sg:classifiers":[
        {
            "category":"Social Services",
            "type":"Services"
        }
    ],
    "sg:phone":"+1 405 840 2891",
    "sg:postcode":"73134",
    "sg:province":"OK",
    "sg:tags":[
        "organization",
        "welfare"
    ],
    "sg:website":"www.osmq.com",
    "wof:name":"Ok Foundation-Med Quality Inc",
    "wof:placetype":"venue"
},
  "geometry": {"coordinates":[-97.57607299999999,35.610817],"type":"Point"}
}