{
  "type": "Feature",
  "properties": {
    "iso:country":"US",
    "sg:address":"5510 S Lewis Ave",
    "sg:city":"Tulsa",
    "sg:classifiers":[
        {
            "category":"Wholesale",
            "subcategory":"Chemicals & Plastics",
            "type":"Manufacturing & Wholesale Goods"
        }
    ],
    "sg:phone":"+1 918 749 9060",
    "sg:postcode":"74105",
    "sg:province":"OK",
    "sg:tags":[
        "industrial",
        "oil"
    ],
    "wof:name":"Tulstar Products Inc",
    "wof:placetype":"venue"
},
  "geometry": {"coordinates":[-95.958019,36.083574],"type":"Point"}
}