{
  "type": "Feature",
  "properties": {
    "iso:country":"US",
    "sg:address":"503 E 9th St",
    "sg:city":"Cushing",
    "sg:classifiers":[
        {
            "category":"Food & Beverages",
            "subcategory":"Groceries & Convenience Stores",
            "type":"Retail Goods"
        }
    ],
    "sg:phone":"+1 918 225 1240",
    "sg:postcode":"74023",
    "sg:province":"OK",
    "wof:name":"Maveric Mini Marts Inc Store 11",
    "wof:placetype":"venue"
},
  "geometry": {"coordinates":[-96.767599,35.97118],"type":"Point"}
}