{
  "type": "Feature",
  "properties": {
    "iso:country":"US",
    "sg:address":"310 2nd Ave SW",
    "sg:city":"Miami",
    "sg:classifiers":[
        {
            "category":"Professional",
            "type":"Services"
        }
    ],
    "sg:phone":"+1 918 540 7700",
    "sg:postcode":"74354",
    "sg:province":"OK",
    "sg:tags":[
        "establishment"
    ],
    "wof:name":"Baptist Regional Associated",
    "wof:placetype":"venue"
},
  "geometry": {"coordinates":[-94.881888,36.872233],"type":"Point"}
}