{
  "type": "Feature",
  "properties": {
    "iso:country":"US",
    "sg:address":"10601 S County Line Rd",
    "sg:city":"Oklahoma City",
    "sg:classifiers":[
        {
            "category":"Manufacturing",
            "subcategory":"Tools & Machinery",
            "type":"Manufacturing & Wholesale Goods"
        }
    ],
    "sg:phone":"+1 405 745 2682",
    "sg:postcode":"73173",
    "sg:province":"OK",
    "wof:name":"Wiedenmanns Machine Shop",
    "wof:placetype":"venue"
},
  "geometry": {"coordinates":[-97.671315,35.371169],"type":"Point"}
}