{
  "type": "Feature",
  "properties": {
    "iso:country":"US",
    "sg:address":"122 N Park Ave",
    "sg:city":"Bartlesville",
    "sg:classifiers":[
        {
            "category":"Recreation",
            "type":"Entertainment"
        }
    ],
    "sg:phone":"+1 918 336 2636",
    "sg:postcode":"74003",
    "sg:province":"OK",
    "sg:tags":[
        "skateboard",
        "parks",
        "rink"
    ],
    "wof:name":"Rock Skate Park",
    "wof:placetype":"venue"
},
  "geometry": {"coordinates":[-95.980379,36.754912],"type":"Point"}
}