{
  "type": "Feature",
  "properties": {
    "addr:full":"11101 N Rockwell Ave Oklahoma City OK 73132",
    "addr:housenumber":"11101",
    "addr:postcode":"73132",
    "addr:street":"N Rockwell Ave",
    "iso:country":"US",
    "sg:address":"11101 N Rockwell Ave",
    "sg:city":"Oklahoma City",
    "sg:classifiers":[
        {
            "category":"Shopping",
            "subcategory":"Department Store",
            "type":"Retail Goods"
        }
    ],
    "sg:phone":"+1 405 773 3555",
    "sg:postcode":"73132",
    "sg:province":"OK",
    "wof:name":"Wal-Mart Supercenter",
    "wof:placetype":"venue"
},
  "geometry": {"coordinates":[-97.638527,35.581949],"type":"Point"}
}