{
  "type": "Feature",
  "properties": {
    "iso:country":"US",
    "sg:address":"2601 Purdue Ave",
    "sg:city":"Oklahoma City",
    "sg:classifiers":[
        {
            "category":"Organizations",
            "subcategory":"Labor Organization",
            "type":"Services"
        }
    ],
    "sg:phone":"+1 405 680 9430",
    "sg:postcode":"73128",
    "sg:province":"OK",
    "wof:name":"National Post Office Mail",
    "wof:placetype":"venue"
},
  "geometry": {"coordinates":[-97.613145,35.439894],"type":"Point"}
}