{
  "type": "Feature",
  "properties": {
    "iso:country":"US",
    "sg:address":"121 E 2nd St",
    "sg:city":"Sand Springs",
    "sg:classifiers":[
        {
            "category":"Restaurant",
            "type":"Food & Drink"
        }
    ],
    "sg:phone":"+1 918 241 3060",
    "sg:postcode":"74063",
    "sg:province":"OK",
    "sg:tags":[
        "eating"
    ],
    "wof:name":"Mike's Hamburger Palace",
    "wof:placetype":"venue"
},
  "geometry": {"coordinates":[-96.107796,36.138531],"type":"Point"}
}