{
  "type": "Feature",
  "properties": {
    "addr:full":"5727d S Garnett Rd Tulsa OK 74146",
    "addr:housenumber":"5727d",
    "addr:postcode":"74146",
    "addr:street":"S Garnett Rd",
    "iso:country":"US",
    "sg:address":"5727d S Garnett Rd",
    "sg:city":"Tulsa",
    "sg:classifiers":[
        {
            "category":"Restaurant",
            "type":"Food & Drink"
        }
    ],
    "sg:menulink":"http://www.allmenus.com/ok/tulsa/144527-subway/menu/",
    "sg:phone":"+1 918 294 3293",
    "sg:postcode":"74146",
    "sg:province":"OK",
    "sg:tags":[
        "american",
        "sandwich"
    ],
    "wof:name":"Subway",
    "wof:placetype":"venue"
},
  "geometry": {"coordinates":[-95.851041,36.079578],"type":"Point"}
}