{
  "type": "Feature",
  "properties": {
    "iso:country":"US",
    "sg:address":"5859 S Garnett Rd",
    "sg:city":"Tulsa",
    "sg:classifiers":[
        {
            "category":"Wholesale",
            "subcategory":"Hardware",
            "type":"Manufacturing & Wholesale Goods"
        }
    ],
    "sg:phone":"+1 918 459 2777",
    "sg:postcode":"74146",
    "sg:province":"OK",
    "sg:tags":[
        "air",
        "parts",
        "conditioning",
        "supply"
    ],
    "wof:name":"Aces A-C Supply Inc",
    "wof:placetype":"venue"
},
  "geometry": {"coordinates":[-95.85096,36.075573],"type":"Point"}
}