{
  "type": "Feature",
  "properties": {
    "addr:full":"205 N Park Ave Shawnee OK 74801",
    "addr:housenumber":"205",
    "addr:postcode":"74801",
    "addr:street":"N Park Ave",
    "iso:country":"US",
    "sg:address":"205 N Park Ave",
    "sg:city":"Shawnee",
    "sg:classifiers":[
        {
            "category":"Social Services",
            "subcategory":"Adult Care",
            "type":"Services"
        },
        {
            "category":"Health Services",
            "subcategory":"Nursing And Care Facility",
            "type":"Services"
        }
    ],
    "sg:phone":"+1 405 275 6444",
    "sg:postcode":"74801",
    "sg:province":"OK",
    "sg:tags":[
        "retardation",
        "home",
        "dev",
        "disabled"
    ],
    "wof:name":"Angel's Acres",
    "wof:placetype":"venue"
},
  "geometry": {"coordinates":[-96.927299,35.329942],"type":"Point"}
}