{
  "type": "Feature",
  "properties": {
    "addr:full":"8508 S Western Ave Oklahoma City OK 73139",
    "addr:housenumber":"8508",
    "addr:postcode":"73139",
    "addr:street":"S Western Ave",
    "iso:country":"US",
    "sg:address":"8508 S Western Ave",
    "sg:city":"Oklahoma City",
    "sg:classifiers":[
        {
            "category":"Building & Trades",
            "subcategory":"Construction",
            "type":"Services"
        }
    ],
    "sg:phone":"+1 405 636 0157",
    "sg:postcode":"73139",
    "sg:province":"OK",
    "sg:tags":[
        "general",
        "contractor"
    ],
    "wof:name":"Pope Construction",
    "wof:placetype":"venue"
},
  "geometry": {"coordinates":[-97.530053,35.380874],"type":"Point"}
}