{
  "type": "Feature",
  "properties": {
    "iso:country":"US",
    "sg:address":"213 W Main St",
    "sg:city":"Purcell",
    "sg:classifiers":[
        {
            "category":"Social Services",
            "type":"Services"
        }
    ],
    "sg:phone":"+1 405 527 9911",
    "sg:postcode":"73080",
    "sg:province":"OK",
    "sg:tags":[
        "organization",
        "welfare"
    ],
    "wof:name":"Healthcare Innovations",
    "wof:placetype":"venue"
},
  "geometry": {"coordinates":[-97.362579,35.012354],"type":"Point"}
}