{
  "type": "Feature",
  "properties": {
    "addr:full":"1440 E 71st St Tulsa OK 74136",
    "addr:housenumber":"1440",
    "addr:postcode":"74136",
    "addr:street":"E 71St St",
    "iso:country":"US",
    "sg:address":"1440 E 71st St",
    "sg:city":"Tulsa",
    "sg:classifiers":[
        {
            "category":"Retail",
            "subcategory":"Car Wash",
            "type":"Services"
        }
    ],
    "sg:phone":"+1 918 494 0199",
    "sg:postcode":"74136",
    "sg:province":"OK",
    "sg:tags":[
        "polishing",
        "washing"
    ],
    "wof:name":"Splash Car Wash",
    "wof:placetype":"venue"
},
  "geometry": {"coordinates":[-95.971327,36.060641],"type":"Point"}
}