{
  "type": "Feature",
  "properties": {
    "iso:country":"US",
    "sg:address":"401 E 1st St",
    "sg:city":"Chandler",
    "sg:classifiers":[
        {
            "category":"Cinema",
            "subcategory":"Movie Rental",
            "type":"Entertainment"
        }
    ],
    "sg:phone":"+1 405 258 2885",
    "sg:postcode":"74834",
    "sg:province":"OK",
    "sg:tags":[
        "leasing",
        "video",
        "disc",
        "tape"
    ],
    "wof:name":"Outlaw Video",
    "wof:placetype":"venue"
},
  "geometry": {"coordinates":[-96.876941,35.709776],"type":"Point"}
}