{
  "type": "Feature",
  "properties": {
    "addr:full":"611 N 2nd St Davis OK 73030",
    "addr:housenumber":"611",
    "addr:postcode":"73030",
    "addr:street":"N 2Nd St",
    "iso:country":"US",
    "sg:address":"611 N 2nd St",
    "sg:city":"Davis",
    "sg:classifiers":[
        {
            "category":"Freight",
            "type":"Transportation"
        }
    ],
    "sg:phone":"+1 580 000 1111",
    "sg:postcode":"73030",
    "sg:province":"OK",
    "sg:tags":[
        "trucking"
    ],
    "wof:name":"Mulkey Livestock Trucking",
    "wof:placetype":"venue"
},
  "geometry": {"coordinates":[-97.123544,34.509793],"type":"Point"}
}