{
  "type": "Feature",
  "properties": {
    "addr:full":"401 W Broadway St Muskogee OK 74401",
    "addr:housenumber":"401",
    "addr:postcode":"74401",
    "addr:street":"W Broadway St",
    "iso:country":"US",
    "sg:address":"401 W Broadway St",
    "sg:city":"Muskogee",
    "sg:classifiers":[
        {
            "category":"Organizations",
            "subcategory":"Community Association",
            "type":"Services"
        }
    ],
    "sg:phone":"+1 918 687 6322",
    "sg:postcode":"74401",
    "sg:province":"OK",
    "sg:tags":[
        "educational"
    ],
    "wof:name":"Muskogee Education Assoc",
    "wof:placetype":"venue"
},
  "geometry": {"coordinates":[-95.37303,35.750198],"type":"Point"}
}