{
  "type": "Feature",
  "properties": {
    "addr:full":"328 Oklahoma Blvd Alva OK 73717",
    "addr:housenumber":"328",
    "addr:postcode":"73717",
    "addr:street":"Oklahoma Blvd",
    "iso:country":"US",
    "sg:address":"328 Oklahoma Blvd",
    "sg:city":"Alva",
    "sg:classifiers":[
        {
            "category":"Restaurant",
            "type":"Food & Drink"
        },
        {
            "category":"Ice Cream",
            "type":"Food & Drink"
        }
    ],
    "sg:menulink":"http://www.allmenus.com/ok/alva/175761-dairy-queen/menu/",
    "sg:phone":"+1 580 327 2582",
    "sg:postcode":"73717",
    "sg:province":"OK",
    "sg:tags":[
        "burger",
        "american",
        "ice",
        "cream"
    ],
    "wof:name":"Dairy Queen",
    "wof:placetype":"venue"
},
  "geometry": {"coordinates":[-98.66243299999999,36.797681],"type":"Point"}
}