{
  "type": "Feature",
  "properties": {
    "addr:full":"6855 E 40th St Tulsa OK 74145",
    "addr:housenumber":"6855",
    "addr:postcode":"74145",
    "addr:street":"E 40Th St",
    "iso:country":"US",
    "sg:address":"6855 E 40th St",
    "sg:city":"Tulsa",
    "sg:classifiers":[
        {
            "category":"Manufacturing",
            "subcategory":"Retail Goods",
            "type":"Manufacturing & Wholesale Goods"
        }
    ],
    "sg:phone":"+1 918 622 9412",
    "sg:postcode":"74145",
    "sg:province":"OK",
    "sg:tags":[
        "dental",
        "mfg"
    ],
    "wof:name":"P O H",
    "wof:placetype":"venue"
},
  "geometry": {"coordinates":[-95.900616,36.106839],"type":"Point"}
}