{
  "type": "Feature",
  "properties": {
    "addr:full":"801 S Main St Stillwater OK 74074",
    "addr:housenumber":"801",
    "addr:postcode":"74074",
    "addr:street":"S Main St",
    "iso:country":"US",
    "sg:address":"801 S Main St",
    "sg:city":"Stillwater",
    "sg:classifiers":[
        {
            "category":"Professional",
            "subcategory":"Lawyer & Legal Services",
            "type":"Services"
        }
    ],
    "sg:phone":"+1 405 377 3393",
    "sg:postcode":"74074",
    "sg:province":"OK",
    "sg:tags":[
        "attorney"
    ],
    "wof:name":"Szlichta & Ramsey",
    "wof:placetype":"venue"
},
  "geometry": {"coordinates":[-97.05858000000001,36.113473],"type":"Point"}
}