{
  "type": "Feature",
  "properties": {
    "iso:country":"US",
    "sg:address":"220 State Hwy 152",
    "sg:city":"Mustang",
    "sg:classifiers":[
        {
            "category":"Personal",
            "subcategory":"Barber",
            "type":"Services"
        }
    ],
    "sg:phone":"+1 405 376 8884",
    "sg:postcode":"73064",
    "sg:province":"OK",
    "wof:name":"Sport Cuts Barber Shop",
    "wof:placetype":"venue"
},
  "geometry": {"coordinates":[-97.724916,35.391605],"type":"Point"}
}