{
  "type": "Feature",
  "properties": {
    "iso:country":"US",
    "sg:address":"101 N Walker Ave",
    "sg:city":"Oklahoma City",
    "sg:classifiers":[
        {
            "category":"Banks & Credit Unions",
            "subcategory":"Bank",
            "type":"Services"
        }
    ],
    "sg:phone":"+1 405 297 2995",
    "sg:postcode":"73102",
    "sg:province":"OK",
    "sg:website":"www.mecuokc.org",
    "wof:name":"Municipal Employees CU",
    "wof:placetype":"venue"
},
  "geometry": {"coordinates":[-97.521272,35.468565],"type":"Point"}
}