{
  "type": "Feature",
  "properties": {
    "iso:country":"US",
    "sg:address":"10908 E 5th St",
    "sg:city":"Tulsa",
    "sg:classifiers":[
        {
            "category":"Education",
            "subcategory":"School",
            "type":"Public Place"
        }
    ],
    "sg:phone":"+1 918 746 6930",
    "sg:postcode":"74128",
    "sg:province":"OK",
    "wof:name":"Tulsa Public Schools",
    "wof:placetype":"venue"
},
  "geometry": {"coordinates":[-95.854065,36.154332],"type":"Point"}
}