{
  "type": "Feature",
  "properties": {
    "iso:country":"US",
    "sg:address":"2929 S Shields Blvd",
    "sg:city":"Oklahoma City",
    "sg:classifiers":[
        {
            "category":"Building & Trades",
            "subcategory":"Construction",
            "type":"Services"
        }
    ],
    "sg:phone":"+1 405 631 7547",
    "sg:postcode":"73129",
    "sg:province":"OK",
    "sg:tags":[
        "roofing",
        "contractor"
    ],
    "wof:name":"Standard Home & Industry Inc",
    "wof:placetype":"venue"
},
  "geometry": {"coordinates":[-97.509291,35.435499],"type":"Point"}
}