{
  "type": "Feature",
  "properties": {
    "iso:country":"US",
    "sg:address":"108 N Weigle Ave",
    "sg:city":"Watonga",
    "sg:classifiers":[
        {
            "category":"Insurance",
            "subcategory":"Hazard Insurance",
            "type":"Services"
        }
    ],
    "sg:phone":"+1 580 623 2120",
    "sg:postcode":"73772",
    "sg:province":"OK",
    "sg:tags":[
        "bond"
    ],
    "wof:name":"Marks Bail Bond",
    "wof:placetype":"venue"
},
  "geometry": {"coordinates":[-98.411775,35.844843],"type":"Point"}
}