{
  "type": "Feature",
  "properties": {
    "iso:country":"US",
    "sg:address":"1199 6th St",
    "sg:city":"Wilson",
    "sg:classifiers":[
        {
            "category":"Retail",
            "subcategory":"Auto Repair",
            "type":"Services"
        }
    ],
    "sg:phone":"+1 580 668 3180",
    "sg:postcode":"73463",
    "sg:province":"OK",
    "sg:tags":[
        "shop",
        "automotive",
        "general"
    ],
    "wof:name":"Vernons Garage",
    "wof:placetype":"venue"
},
  "geometry": {"coordinates":[-97.426518,34.152095],"type":"Point"}
}