{
  "type": "Feature",
  "properties": {
    "iso:country":"US",
    "sg:address":"1 N Mission St",
    "sg:city":"Sapulpa",
    "sg:classifiers":[
        {
            "category":"Fast Food",
            "type":"Food & Drink"
        },
        {
            "category":"Restaurant",
            "type":"Food & Drink"
        },
        {
            "category":"Professional",
            "type":"Services"
        }
    ],
    "sg:phone":"+1 918 224 4444",
    "sg:postcode":"74066",
    "sg:province":"OK",
    "sg:tags":[
        "delivery",
        "take",
        "pizza"
    ],
    "sg:website":"http://www.dominospizza.com",
    "wof:name":"Domino's Pizza",
    "wof:placetype":"venue"
},
  "geometry": {"coordinates":[-96.098831,35.999031],"type":"Point"}
}