{
  "type": "Feature",
  "properties": {
    "iso:country":"US",
    "sg:address":"2076 Crossroads Mall Dr",
    "sg:city":"Oklahoma City",
    "sg:classifiers":[
        {
            "category":"Shopping",
            "subcategory":"Clothing, Apparel, & Fashions",
            "type":"Retail Goods"
        }
    ],
    "sg:phone":"+1 405 632 3119",
    "sg:postcode":"73149",
    "sg:province":"OK",
    "wof:name":"Lane Bryant",
    "wof:placetype":"venue"
},
  "geometry": {"coordinates":[-97.48736599999999,35.395986],"type":"Point"}
}