{
  "type": "Feature",
  "properties": {
    "addr:full":"206 E Hwy 66 Arcadia OK 73007",
    "addr:housenumber":"206",
    "addr:postcode":"73007",
    "addr:street":"E Hwy 66",
    "iso:country":"US",
    "sg:address":"206 E Hwy 66",
    "sg:city":"Arcadia",
    "sg:classifiers":[
        {
            "category":"Autos & Motor Vehicles",
            "subcategory":"Fuel & Gas Station",
            "type":"Retail Goods"
        }
    ],
    "sg:phone":"+1 405 396 2623",
    "sg:postcode":"73007",
    "sg:province":"OK",
    "sg:tags":[
        "oil"
    ],
    "wof:name":"66 Lake Stop",
    "wof:placetype":"venue"
},
  "geometry": {"coordinates":[-97.33207299999999,35.659986],"type":"Point"}
}