{
  "type": "Feature",
  "properties": {
    "addr:full":"518 W Tyler Ave Bache OK 74501",
    "addr:housenumber":"518",
    "addr:postcode":"74501",
    "addr:street":"W Tyler Ave",
    "iso:country":"US",
    "sg:address":"518 W Tyler Ave",
    "sg:city":"Bache",
    "sg:classifiers":[
        {
            "category":"Education",
            "subcategory":"Dance Studio",
            "type":"Public Place"
        }
    ],
    "sg:phone":"+1 918 423 1594",
    "sg:postcode":"74501",
    "sg:province":"OK",
    "wof:name":"Tony S Deel Dance Studios",
    "wof:placetype":"venue"
},
  "geometry": {"coordinates":[-95.777278,34.943953],"type":"Point"}
}