{
  "type": "Feature",
  "properties": {
    "iso:country":"US",
    "sg:address":"115 S Cimarron Dr",
    "sg:city":"Perkins",
    "sg:classifiers":[
        {
            "category":"Manufacturing",
            "subcategory":"Lumber",
            "type":"Manufacturing & Wholesale Goods"
        }
    ],
    "sg:phone":"+1 405 547 2053",
    "sg:postcode":"74059",
    "sg:province":"OK",
    "sg:tags":[
        "forestry"
    ],
    "wof:name":"Jimmy Stecker Cedar Tree Cutng",
    "wof:placetype":"venue"
},
  "geometry": {"coordinates":[-97.02992,35.9668],"type":"Point"}
}