{
  "type": "Feature",
  "properties": {
    "iso:country":"US",
    "sg:address":"11419 E 21st St",
    "sg:city":"Tulsa",
    "sg:classifiers":[
        {
            "category":"Restaurant",
            "type":"Food & Drink"
        }
    ],
    "sg:phone":"+1 918 437 8088",
    "sg:postcode":"74129",
    "sg:province":"OK",
    "sg:tags":[
        "mexican"
    ],
    "sg:website":"www.elrefugioazteca.com",
    "wof:name":"El Refugio Azteca",
    "wof:placetype":"venue"
},
  "geometry": {"coordinates":[-95.848438,36.13355],"type":"Point"}
}