{
  "type": "Feature",
  "properties": {
    "iso:country":"US",
    "sg:address":"1000 Stanton L Young Blvd",
    "sg:city":"Oklahoma City",
    "sg:classifiers":[
        {
            "category":"Education",
            "subcategory":"Library",
            "type":"Public Place"
        }
    ],
    "sg:phone":"+1 405 271 2677",
    "sg:postcode":"73117",
    "sg:province":"OK",
    "wof:name":"Ou Health Science Ctr Bird Lib",
    "wof:placetype":"venue"
},
  "geometry": {"coordinates":[-97.495077,35.480038],"type":"Point"}
}