{
  "type": "Feature",
  "properties": {
    "addr:full":"913 N 161st East Ave Tulsa OK 74116",
    "addr:housenumber":"913",
    "addr:postcode":"74116",
    "addr:street":"N 161St;Ave",
    "iso:country":"US",
    "sg:address":"913 N 161st East Ave",
    "sg:city":"Tulsa",
    "sg:classifiers":[
        {
            "category":"Retail",
            "subcategory":"Veterinary Services",
            "type":"Services"
        }
    ],
    "sg:phone":"+1 918 234 7568",
    "sg:postcode":"74116",
    "sg:province":"OK",
    "sg:tags":[
        "veterinarian"
    ],
    "wof:name":"Stockyards Veterinary Clinic",
    "wof:placetype":"venue"
},
  "geometry": {"coordinates":[-95.797477,36.169338],"type":"Point"}
}