{
  "type": "Feature",
  "properties": {
    "iso:country":"US",
    "sg:address":"115 S Main St",
    "sg:city":"Miami",
    "sg:classifiers":[
        {
            "category":"Health Services",
            "subcategory":"Nursing And Care Facility",
            "type":"Services"
        }
    ],
    "sg:phone":"+1 918 542 1226",
    "sg:postcode":"74354",
    "sg:province":"OK",
    "sg:tags":[
        "skilled"
    ],
    "wof:name":"Integris Regency Hospice",
    "wof:placetype":"venue"
},
  "geometry": {"coordinates":[-94.877413,36.873233],"type":"Point"}
}