{
  "type": "Feature",
  "properties": {
    "addr:full":"2021 SW Washington Ave Lawton OK 73501",
    "addr:housenumber":"2021",
    "addr:postcode":"73501",
    "addr:street":"Sw Washington Ave",
    "iso:country":"US",
    "sg:address":"2021 SW Washington Ave",
    "sg:city":"Lawton",
    "sg:classifiers":[
        {
            "category":"Wholesale",
            "subcategory":"Hardware",
            "type":"Manufacturing & Wholesale Goods"
        }
    ],
    "sg:phone":"+1 580 248 2338",
    "sg:postcode":"73501",
    "sg:province":"OK",
    "sg:tags":[
        "refrigeration"
    ],
    "wof:name":"Amsco Supply Company",
    "wof:placetype":"venue"
},
  "geometry": {"coordinates":[-98.41973299999999,34.593439],"type":"Point"}
}