{
  "type": "Feature",
  "properties": {
    "iso:country":"US",
    "sg:address":"419 S 27th St",
    "sg:city":"Duncan",
    "sg:classifiers":[
        {
            "category":"Real Estate",
            "subcategory":"Real Estate Operator",
            "type":"Services"
        }
    ],
    "sg:phone":"+1 580 470 9200",
    "sg:postcode":"73533",
    "sg:province":"OK",
    "sg:tags":[
        "building",
        "apartment"
    ],
    "wof:name":"Gardens At Duncan",
    "wof:placetype":"venue"
},
  "geometry": {"coordinates":[-97.982063,34.500131],"type":"Point"}
}