{
  "type": "Feature",
  "properties": {
    "iso:country":"US",
    "sg:address":"5810 S Agnew Ave",
    "sg:city":"Oklahoma City",
    "sg:classifiers":[
        {
            "category":"Manufacturing",
            "subcategory":"Printing",
            "type":"Manufacturing & Wholesale Goods"
        }
    ],
    "sg:phone":"+1 405 681 4662",
    "sg:postcode":"73119",
    "sg:province":"OK",
    "sg:tags":[
        "commercial"
    ],
    "wof:name":"Mid-State Press Inc",
    "wof:placetype":"venue"
},
  "geometry": {"coordinates":[-97.555072,35.408153],"type":"Point"}
}