{
  "type": "Feature",
  "properties": {
    "addr:full":"1505 SE 66th St Oklahoma City OK 73149",
    "addr:housenumber":"1505",
    "addr:postcode":"73149",
    "addr:street":"Se 66Th St",
    "iso:country":"US",
    "sg:address":"1505 SE 66th St",
    "sg:city":"Oklahoma City",
    "sg:classifiers":[
        {
            "category":"Building & Trades",
            "subcategory":"Electrical",
            "type":"Services"
        }
    ],
    "sg:phone":"+1 405 733 8687",
    "sg:postcode":"73149",
    "sg:province":"OK",
    "sg:tags":[
        "electric",
        "contractor"
    ],
    "wof:name":"Home Electric Co",
    "wof:placetype":"venue"
},
  "geometry": {"coordinates":[-97.484004,35.398295],"type":"Point"}
}