{
  "type": "Feature",
  "properties": {
    "iso:country":"US",
    "sg:address":"309 N Sam Houston",
    "sg:city":"Mustang",
    "sg:classifiers":[
        {
            "category":"Professional",
            "subcategory":"Computer Services",
            "type":"Services"
        }
    ],
    "sg:phone":"+1 405 376 6535",
    "sg:postcode":"73064",
    "sg:province":"OK",
    "sg:tags":[
        "design",
        "system"
    ],
    "wof:name":"Infisage LLC",
    "wof:placetype":"venue"
},
  "geometry": {"coordinates":[-97.740855,35.394938],"type":"Point"}
}