{
  "type": "Feature",
  "properties": {
    "iso:country":"US",
    "sg:address":"13517 Railway Dr",
    "sg:city":"Oklahoma City",
    "sg:classifiers":[
        {
            "category":"Retail",
            "subcategory":"Animal Services",
            "type":"Services"
        }
    ],
    "sg:phone":"+1 405 751 1944",
    "sg:postcode":"73114",
    "sg:province":"OK",
    "wof:name":"Veterans Pet Care",
    "wof:placetype":"venue"
},
  "geometry": {"coordinates":[-97.503645,35.608105],"type":"Point"}
}