{
  "type": "Feature",
  "properties": {
    "iso:country":"US",
    "sg:address":"29240 E 121st St S",
    "sg:city":"Coweta",
    "sg:classifiers":[
        {
            "category":"Retail",
            "subcategory":"Animal Services",
            "type":"Services"
        }
    ],
    "sg:phone":"+1 918 486 2697",
    "sg:postcode":"74429",
    "sg:province":"OK",
    "sg:tags":[
        "pet",
        "grooming",
        "washing"
    ],
    "wof:name":"Bubbles To Bows",
    "wof:placetype":"venue"
},
  "geometry": {"coordinates":[-95.651188,35.988232],"type":"Point"}
}