{
  "type": "Feature",
  "properties": {
    "iso:country":"US",
    "sg:address":"911 E Taft Ave",
    "sg:city":"Sapulpa",
    "sg:classifiers":[
        {
            "category":"Banks & Credit Unions",
            "subcategory":"Bank",
            "type":"Services"
        }
    ],
    "sg:phone":"+1 918 227 0550",
    "sg:postcode":"74066",
    "sg:province":"OK",
    "sg:tags":[
        "federal",
        "savings",
        "institution"
    ],
    "wof:name":"International Bank Commerce",
    "wof:placetype":"venue"
},
  "geometry": {"coordinates":[-96.101706,35.988444],"type":"Point"}
}