{
  "type": "Feature",
  "properties": {
    "iso:country":"US",
    "sg:address":"410 4th St",
    "sg:city":"Cyril",
    "sg:classifiers":[
        {
            "category":"Health Services",
            "subcategory":"Nursing And Care Facility",
            "type":"Services"
        }
    ],
    "sg:phone":"+1 580 464 2242",
    "sg:postcode":"73029",
    "sg:province":"OK",
    "sg:tags":[
        "skilled"
    ],
    "wof:name":"Cyril Nursing Home",
    "wof:placetype":"venue"
},
  "geometry": {"coordinates":[-98.204044,34.891908],"type":"Point"}
}