{
  "type": "Feature",
  "properties": {
    "addr:full":"1300 N Highland Dr Oklahoma City OK 73111",
    "addr:housenumber":"1300",
    "addr:postcode":"73111",
    "addr:street":"N Highland Dr",
    "iso:country":"US",
    "sg:address":"1300 N Highland Dr",
    "sg:city":"Oklahoma City",
    "sg:classifiers":[
        {
            "category":"Wholesale",
            "subcategory":"Machinery & Supplies",
            "type":"Manufacturing & Wholesale Goods"
        }
    ],
    "sg:phone":"+1 405 232 8263",
    "sg:postcode":"73111",
    "sg:province":"OK",
    "sg:tags":[
        "industrial"
    ],
    "wof:name":"Alpha Industrial Products",
    "wof:placetype":"venue"
},
  "geometry": {"coordinates":[-97.472954,35.48251],"type":"Point"}
}