{
  "type": "Feature",
  "properties": {
    "addr:full":"2112 S Garnett Rd Tulsa OK 74129",
    "addr:housenumber":"2112",
    "addr:postcode":"74129",
    "addr:street":"S Garnett Rd",
    "iso:country":"US",
    "sg:address":"2112 S Garnett Rd",
    "sg:city":"Tulsa",
    "sg:classifiers":[
        {
            "category":"Food & Beverages",
            "subcategory":"Groceries & Convenience Stores",
            "type":"Retail Goods"
        }
    ],
    "sg:phone":"+1 918 234 7309",
    "sg:postcode":"74129",
    "sg:province":"OK",
    "wof:name":"Git-N-Go 26",
    "wof:placetype":"venue"
},
  "geometry": {"coordinates":[-95.851187,36.131451],"type":"Point"}
}