{
  "type": "Feature",
  "properties": {
    "iso:country":"US",
    "sg:address":"1103 Locust St",
    "sg:city":"Alva",
    "sg:classifiers":[
        {
            "category":"Arena",
            "subcategory":"Sports Club",
            "type":"Entertainment"
        }
    ],
    "sg:phone":"+1 580 327 0483",
    "sg:postcode":"73717",
    "sg:province":"OK",
    "wof:name":"Rowdy Ranger LLC",
    "wof:placetype":"venue"
},
  "geometry": {"coordinates":[-98.67657,36.800026],"type":"Point"}
}