{
  "type": "Feature",
  "properties": {
    "addr:full":"107 E Oklahoma Blvd Alva OK 73717",
    "addr:housenumber":"107",
    "addr:postcode":"73717",
    "addr:street":"E Oklahoma Blvd",
    "iso:country":"US",
    "sg:address":"107 E Oklahoma Blvd",
    "sg:city":"Alva",
    "sg:classifiers":[
        {
            "category":"Restaurant",
            "type":"Food & Drink"
        }
    ],
    "sg:menulink":"http://www.allmenus.com/ok/alva/144331-subway/menu/",
    "sg:phone":"+1 580 327 0955",
    "sg:postcode":"73717",
    "sg:province":"OK",
    "sg:tags":[
        "american",
        "sandwich"
    ],
    "wof:name":"Subway",
    "wof:placetype":"venue"
},
  "geometry": {"coordinates":[-98.65692799999999,36.797627],"type":"Point"}
}