{
  "type": "Feature",
  "properties": {
    "iso:country":"US",
    "sg:address":"236 SE 59th St",
    "sg:city":"Oklahoma City",
    "sg:classifiers":[
        {
            "category":"Retail",
            "subcategory":"Repair Shop",
            "type":"Services"
        }
    ],
    "sg:phone":"+1 405 632 0827",
    "sg:postcode":"73129",
    "sg:province":"OK",
    "sg:tags":[
        "upholsterer"
    ],
    "wof:name":"Frank Smith's Upholstery",
    "wof:placetype":"venue"
},
  "geometry": {"coordinates":[-97.506533,35.406152],"type":"Point"}
}