{
  "type": "Feature",
  "properties": {
    "iso:country":"US",
    "sg:address":"1840 N 105th East Ave",
    "sg:city":"Tulsa",
    "sg:classifiers":[
        {
            "category":"Utilities",
            "subcategory":"Refuse",
            "type":"Services"
        }
    ],
    "sg:phone":"+1 918 627 2671",
    "sg:postcode":"74116",
    "sg:province":"OK",
    "sg:tags":[
        "sanitary",
        "testing",
        "system",
        "laboratory"
    ],
    "wof:name":"Heritage Envmtl Svcs LLC",
    "wof:placetype":"venue"
},
  "geometry": {"coordinates":[-95.859995,36.180967],"type":"Point"}
}