{
  "type": "Feature",
  "properties": {
    "iso:country":"US",
    "sg:address":"516 Still Hollow Rd",
    "sg:city":"Edmond",
    "sg:classifiers":[
        {
            "category":"Professional",
            "subcategory":"Lawyer & Legal Services",
            "type":"Services"
        }
    ],
    "sg:phone":"+1 405 330 3993",
    "sg:postcode":"73034",
    "sg:province":"OK",
    "sg:tags":[
        "attorney"
    ],
    "wof:name":"David A Miley",
    "wof:placetype":"venue"
},
  "geometry": {"coordinates":[-97.47264,35.680377],"type":"Point"}
}