{
  "type": "Feature",
  "properties": {
    "iso:country":"US",
    "sg:address":"100 N Broadway Ave",
    "sg:city":"Oklahoma City",
    "sg:classifiers":[
        {
            "category":"Banks & Credit Unions",
            "subcategory":"Bank",
            "type":"Services"
        }
    ],
    "sg:phone":"+1 405 231 6000",
    "sg:postcode":"73102",
    "sg:province":"OK",
    "wof:name":"Bank One",
    "wof:placetype":"venue"
},
  "geometry": {"coordinates":[-97.514433,35.468762],"type":"Point"}
}