{
  "type": "Feature",
  "properties": {
    "iso:country":"US",
    "sg:address":"8225 S Pittsburg Ave",
    "sg:city":"Tulsa",
    "sg:classifiers":[
        {
            "category":"Professional",
            "subcategory":"Engineering",
            "type":"Services"
        }
    ],
    "sg:phone":"+1 918 492 6815",
    "sg:postcode":"74137",
    "sg:province":"OK",
    "wof:name":"Srm Technology Inc",
    "wof:placetype":"venue"
},
  "geometry": {"coordinates":[-95.931508,36.042749],"type":"Point"}
}