{
  "type": "Feature",
  "properties": {
    "addr:full":"8937 N 138th E Ave Owasso OK 74055",
    "addr:housenumber":"8937",
    "addr:postcode":"74055",
    "addr:street":"N 138Th E Ave",
    "iso:country":"US",
    "sg:address":"8937 N 138th E Ave",
    "sg:city":"Owasso",
    "sg:classifiers":[
        {
            "category":"Professional",
            "subcategory":"Computer Services",
            "type":"Services"
        }
    ],
    "sg:phone":"+1 918 272 1461",
    "sg:postcode":"74055",
    "sg:province":"OK",
    "wof:name":"Patton Computers",
    "wof:placetype":"venue"
},
  "geometry": {"coordinates":[-95.820105,36.287681],"type":"Point"}
}