{
  "type": "Feature",
  "properties": {
    "iso:country":"US",
    "sg:address":"309 N May St",
    "sg:city":"Guymon",
    "sg:classifiers":[
        {
            "category":"Social Services",
            "subcategory":"Adult Care",
            "type":"Services"
        }
    ],
    "sg:phone":"+1 580 338 8210",
    "sg:postcode":"73942",
    "sg:province":"OK",
    "sg:tags":[
        "home",
        "group"
    ],
    "wof:name":"Pasw Group Home",
    "wof:placetype":"venue"
},
  "geometry": {"coordinates":[-101.476257,36.680853],"type":"Point"}
}