{
  "type": "Feature",
  "properties": {
    "addr:full":"7712 E 11th St Tulsa OK 74112",
    "addr:housenumber":"7712",
    "addr:postcode":"74112",
    "addr:street":"E 11Th St",
    "iso:country":"US",
    "sg:address":"7712 E 11th St",
    "sg:city":"Tulsa",
    "sg:classifiers":[
        {
            "category":"Manufacturing",
            "subcategory":"Printing",
            "type":"Manufacturing & Wholesale Goods"
        }
    ],
    "sg:phone":"+1 918 838 2113",
    "sg:postcode":"74112",
    "sg:province":"OK",
    "sg:tags":[
        "lithographic",
        "b",
        "commercial",
        "typesetting"
    ],
    "wof:name":"Self Printing Inc",
    "wof:placetype":"venue"
},
  "geometry": {"coordinates":[-95.889026,36.147938],"type":"Point"}
}