{
  "type": "Feature",
  "properties": {
    "addr:full":"6416 N Sterling Dr Oklahoma City OK 73132",
    "addr:housenumber":"6416",
    "addr:postcode":"73132",
    "addr:street":"N Sterling Dr",
    "iso:country":"US",
    "sg:address":"6416 N Sterling Dr",
    "sg:city":"Oklahoma City",
    "sg:classifiers":[
        {
            "category":"Professional",
            "subcategory":"Business Services",
            "type":"Services"
        }
    ],
    "sg:phone":"+1 405 722 9591",
    "sg:postcode":"73132",
    "sg:province":"OK",
    "wof:name":"Kathy Reinke",
    "wof:placetype":"venue"
},
  "geometry": {"coordinates":[-97.607435,35.539012],"type":"Point"}
}