{
  "type": "Feature",
  "properties": {
    "iso:country":"US",
    "sg:address":"549 E 36th St N",
    "sg:city":"Tulsa",
    "sg:classifiers":[
        {
            "category":"Education",
            "subcategory":"School",
            "type":"Public Place"
        }
    ],
    "sg:phone":"+1 918 428 3352",
    "sg:postcode":"74106",
    "sg:province":"OK",
    "wof:name":"New Concept Preparatory School",
    "wof:placetype":"venue"
},
  "geometry": {"coordinates":[-95.987951,36.206058],"type":"Point"}
}