{
  "type": "Feature",
  "properties": {
    "iso:country":"US",
    "sg:address":"2404 Main St",
    "sg:city":"Choctaw",
    "sg:classifiers":[
        {
            "category":"Retail",
            "subcategory":"Animal Services",
            "type":"Services"
        }
    ],
    "sg:phone":"+1 405 390 3755",
    "sg:postcode":"73020",
    "sg:province":"OK",
    "sg:tags":[
        "pet",
        "grooming",
        "washing"
    ],
    "wof:name":"Somebody's Darlin",
    "wof:placetype":"venue"
},
  "geometry": {"coordinates":[-97.270877,35.49455],"type":"Point"}
}