{
  "type": "Feature",
  "properties": {
    "addr:full":"3401 NW Expy Oklahoma City OK 73132",
    "addr:housenumber":"3401",
    "addr:postcode":"73132",
    "addr:street":"Nw Expy",
    "iso:country":"US",
    "sg:address":"3401 NW Expy",
    "sg:city":"Oklahoma City",
    "sg:classifiers":[
        {
            "category":"Manufacturing",
            "subcategory":"Printing",
            "type":"Manufacturing & Wholesale Goods"
        }
    ],
    "sg:phone":"+1 405 842 1404",
    "sg:postcode":"73132",
    "sg:province":"OK",
    "sg:tags":[
        "printer"
    ],
    "wof:name":"Quik Print",
    "wof:placetype":"venue"
},
  "geometry": {"coordinates":[-97.57771099999999,35.531319],"type":"Point"}
}