{
  "type": "Feature",
  "properties": {
    "iso:country":"US",
    "sg:address":"7601 N May Ave",
    "sg:city":"Oklahoma City",
    "sg:classifiers":[
        {
            "category":"Autos & Motor Vehicles",
            "subcategory":"Auto Supplies",
            "type":"Retail Goods"
        }
    ],
    "sg:phone":"+1 405 840 5121",
    "sg:postcode":"73116",
    "sg:province":"OK",
    "sg:tags":[
        "automobile",
        "stereo",
        "radio"
    ],
    "wof:name":"David's Stereo",
    "wof:placetype":"venue"
},
  "geometry": {"coordinates":[-97.565737,35.548252],"type":"Point"}
}