{
  "type": "Feature",
  "properties": {
    "iso:country":"US",
    "sg:address":"1717 N Milt Phillips Ave",
    "sg:city":"Seminole",
    "sg:classifiers":[
        {
            "category":"Shopping",
            "subcategory":"Pharmacy",
            "type":"Retail Goods"
        }
    ],
    "sg:phone":"+1 405 382 5420",
    "sg:postcode":"74868",
    "sg:province":"OK",
    "wof:name":"Seminole Drug Inc",
    "wof:placetype":"venue"
},
  "geometry": {"coordinates":[-96.671005,35.240081],"type":"Point"}
}