{
  "type": "Feature",
  "properties": {
    "iso:country":"US",
    "sg:address":"3829 NW 67th St",
    "sg:city":"Oklahoma City",
    "sg:classifiers":[
        {
            "category":"Professional",
            "subcategory":"Lawyer & Legal Services",
            "type":"Services"
        }
    ],
    "sg:phone":"+1 405 842 2772",
    "sg:postcode":"73116",
    "sg:province":"OK",
    "wof:name":"Attorney At Law",
    "wof:placetype":"venue"
},
  "geometry": {"coordinates":[-97.588004,35.540587],"type":"Point"}
}