{
  "type": "Feature",
  "properties": {
    "iso:country":"US",
    "sg:address":"1102 W Macarthur St",
    "sg:city":"Shawnee",
    "sg:classifiers":[
        {
            "category":"Health Services",
            "subcategory":"Hospital",
            "type":"Services"
        }
    ],
    "sg:phone":"+1 405 273 2270",
    "sg:postcode":"74804",
    "sg:province":"OK",
    "sg:website":"www.unityhealthcenter.com",
    "wof:name":"Unity Health Ctr",
    "wof:placetype":"venue"
},
  "geometry": {"coordinates":[-96.938595,35.361809],"type":"Point"}
}