{
  "type": "Feature",
  "properties": {
    "iso:country":"US",
    "sg:address":"405 Comanche Ave",
    "sg:city":"Rush Springs",
    "sg:classifiers":[
        {
            "category":"Real Estate",
            "subcategory":"Real Estate Agent",
            "type":"Services"
        }
    ],
    "sg:phone":"+1 580 476 3900",
    "sg:postcode":"73082",
    "sg:province":"OK",
    "sg:tags":[
        "appraiser"
    ],
    "wof:name":"Pearl Real Estate Svc Inc",
    "wof:placetype":"venue"
},
  "geometry": {"coordinates":[-97.94634499999999,34.779114],"type":"Point"}
}