{
  "type": "Feature",
  "properties": {
    "iso:country":"US",
    "sg:address":"520 W 4th St",
    "sg:city":"Chelsea",
    "sg:classifiers":[
        {
            "category":"Organizations",
            "subcategory":"Religious Organization",
            "type":"Services"
        }
    ],
    "sg:phone":"+1 918 789 5253",
    "sg:postcode":"74016",
    "sg:province":"OK",
    "sg:tags":[
        "parsonage"
    ],
    "wof:name":"First Baptist Parsonage",
    "wof:placetype":"venue"
},
  "geometry": {"coordinates":[-95.435363,36.539064],"type":"Point"}
}