{
  "type": "Feature",
  "properties": {
    "iso:country":"US",
    "sg:address":"8925 E Hwy 20",
    "sg:city":"Claremore",
    "sg:classifiers":[
        {
            "category":"Real Estate",
            "subcategory":"Real Estate Operator",
            "type":"Services"
        }
    ],
    "sg:phone":"+1 918 341 4911",
    "sg:postcode":"74019",
    "sg:province":"OK",
    "sg:tags":[
        "mobile",
        "home",
        "community"
    ],
    "wof:name":"Lone Elm Mobile Home Park",
    "wof:placetype":"venue"
},
  "geometry": {"coordinates":[-95.67132,36.30741],"type":"Point"}
}