{
  "type": "Feature",
  "properties": {
    "iso:country":"US",
    "sg:address":"12928 N May Ave",
    "sg:city":"Oklahoma City",
    "sg:classifiers":[
        {
            "category":"Travel",
            "subcategory":"Hotels & Motels",
            "type":"Entertainment"
        }
    ],
    "sg:phone":"+1 405 748 6464",
    "sg:postcode":"73120",
    "sg:province":"OK",
    "sg:tags":[
        "operation"
    ],
    "wof:name":"Marriott",
    "wof:placetype":"venue"
},
  "geometry": {"coordinates":[-97.567105,35.601295],"type":"Point"}
}