{
  "type": "Feature",
  "properties": {
    "iso:country":"US",
    "sg:address":"2509 Redwood Ln",
    "sg:city":"Edmond",
    "sg:classifiers":[
        {
            "category":"Wholesale",
            "subcategory":"Medical Equipment & Supplies",
            "type":"Manufacturing & Wholesale Goods"
        }
    ],
    "sg:phone":"+1 405 330 8183",
    "sg:postcode":"73013",
    "sg:province":"OK",
    "sg:tags":[
        "physician",
        "surgeon"
    ],
    "wof:name":"Medco Medical",
    "wof:placetype":"venue"
},
  "geometry": {"coordinates":[-97.510744,35.629845],"type":"Point"}
}