{
  "type": "Feature",
  "properties": {
    "addr:full":"12655 Green Oak Dr Choctaw OK 73020",
    "addr:housenumber":"12655",
    "addr:postcode":"73020",
    "addr:street":"Green Oak Dr",
    "iso:country":"US",
    "sg:address":"12655 Green Oak Dr",
    "sg:city":"Choctaw",
    "sg:classifiers":[
        {
            "category":"Retail",
            "subcategory":"Repair Shop",
            "type":"Services"
        }
    ],
    "sg:phone":"+1 405 769 4525",
    "sg:postcode":"73020",
    "sg:province":"OK",
    "wof:name":"Equipment Repair Corp",
    "wof:placetype":"venue"
},
  "geometry": {"coordinates":[-97.30794899999999,35.469204],"type":"Point"}
}