{
  "type": "Feature",
  "properties": {
    "iso:country":"US",
    "sg:address":"12655 Green Oak Dr",
    "sg:city":"Choctaw",
    "sg:classifiers":[
        {
            "category":"Retail",
            "subcategory":"Repair Shop",
            "type":"Services"
        }
    ],
    "sg:phone":"+1 405 769 4525",
    "sg:postcode":"73020",
    "sg:province":"OK",
    "wof:name":"Equipment Repair Corp",
    "wof:placetype":"venue"
},
  "geometry": {"coordinates":[-97.307949,35.469204],"type":"Point"}
}