{
  "type": "Feature",
  "properties": {
    "iso:country":"US",
    "sg:address":"9494 Magnolia Wood Dr",
    "sg:city":"Claremore",
    "sg:phone":"+1 918 343 2355",
    "sg:postcode":"74019",
    "sg:province":"OK",
    "sg:tags":[
        "scale"
    ],
    "wof:name":"Scale Technologies",
    "wof:placetype":"venue"
},
  "geometry": {"coordinates":[-95.66237700000001,36.252307],"type":"Point"}
}