{
  "type": "Feature",
  "properties": {
    "addr:full":"3009 Candlestick Ct Bartlesville OK 74006",
    "addr:housenumber":"3009",
    "addr:postcode":"74006",
    "addr:street":"Candlestick Ct",
    "iso:country":"US",
    "sg:address":"3009 Candlestick Ct",
    "sg:city":"Bartlesville",
    "sg:classifiers":[
        {
            "category":"Building & Trades",
            "subcategory":"Construction",
            "type":"Services"
        }
    ],
    "sg:phone":"+1 918 335 0355",
    "sg:postcode":"74006",
    "sg:province":"OK",
    "sg:tags":[
        "house"
    ],
    "wof:name":"John McAnaw Homes",
    "wof:placetype":"venue"
},
  "geometry": {"coordinates":[-95.938478,36.703126],"type":"Point"}
}