{
  "type": "Feature",
  "properties": {
    "iso:country":"US",
    "sg:address":"2115 N Warren Dr",
    "sg:city":"Stillwater",
    "sg:classifiers":[
        {
            "category":"Manufacturing",
            "subcategory":"Toys & Sporting Goods",
            "type":"Manufacturing & Wholesale Goods"
        }
    ],
    "sg:phone":"+1 405 743 1010",
    "sg:postcode":"74075",
    "sg:province":"OK",
    "sg:tags":[
        "equipment",
        "gymnasium",
        "supply"
    ],
    "sg:website":"www.perfectgrace.com",
    "wof:name":"Perfect Grace LLC",
    "wof:placetype":"venue"
},
  "geometry": {"coordinates":[-97.101986,36.138754],"type":"Point"}
}