{
  "type": "Feature",
  "properties": {
    "addr:full":"103 N Roland Rd Roland OK 74954",
    "addr:housenumber":"103",
    "addr:postcode":"74954",
    "addr:street":"N Roland Rd",
    "iso:country":"US",
    "sg:address":"103 N Roland Rd",
    "sg:city":"Roland",
    "sg:classifiers":[
        {
            "category":"Banks & Credit Unions",
            "subcategory":"Bank",
            "type":"Services"
        }
    ],
    "sg:phone":"+1 918 427 1093",
    "sg:postcode":"74954",
    "sg:province":"OK",
    "sg:tags":[
        "loan"
    ],
    "wof:name":"Dixie Finance",
    "wof:placetype":"venue"
},
  "geometry": {"coordinates":[-94.513266,35.42118],"type":"Point"}
}