{
  "type": "Feature",
  "properties": {
    "iso:country":"US",
    "sg:address":"6902 S 49th Ave W",
    "sg:city":"Tulsa",
    "sg:classifiers":[
        {
            "category":"Organizations",
            "subcategory":"Non-profit Organization",
            "type":"Services"
        }
    ],
    "sg:phone":"+1 918 446 6161",
    "sg:postcode":"74131",
    "sg:province":"OK",
    "wof:name":"Oaks Country Club",
    "wof:placetype":"venue"
},
  "geometry": {"coordinates":[-96.04873000000001,36.067548],"type":"Point"}
}