{
  "type": "Feature",
  "properties": {
    "iso:country":"US",
    "sg:address":"2701 NE 4th St",
    "sg:city":"Oklahoma City",
    "sg:classifiers":[
        {
            "category":"Utilities",
            "type":"Services"
        }
    ],
    "sg:phone":"+1 405 232 5226",
    "sg:postcode":"73104",
    "sg:province":"OK",
    "sg:tags":[
        "water",
        "waste",
        "treatment"
    ],
    "wof:name":"Veolia Water North America",
    "wof:placetype":"venue"
},
  "geometry": {"coordinates":[-97.461729,35.47145],"type":"Point"}
}