{
  "type": "Feature",
  "properties": {
    "iso:country":"US",
    "sg:address":"5021 N Boston Pl",
    "sg:city":"Tulsa",
    "sg:classifiers":[
        {
            "category":"Shopping",
            "type":"Retail Goods"
        }
    ],
    "sg:phone":"+1 918 430 1830",
    "sg:postcode":"74126",
    "sg:province":"OK",
    "sg:tags":[
        "cosmetic",
        "perfume"
    ],
    "wof:name":"Mary Kay Cosmetics",
    "wof:placetype":"venue"
},
  "geometry": {"coordinates":[-95.994046,36.226534],"type":"Point"}
}