{
  "type": "Feature",
  "properties": {
    "addr:full":"1250 SE Adams Blvd Bartlesville OK 74003",
    "addr:housenumber":"1250",
    "addr:postcode":"74003",
    "addr:street":"Se Adams Blvd",
    "iso:country":"US",
    "sg:address":"1250 SE Adams Blvd",
    "sg:city":"Bartlesville",
    "sg:classifiers":[
        {
            "category":"Banks & Credit Unions",
            "subcategory":"Financial Services",
            "type":"Services"
        }
    ],
    "sg:phone":"+1 918 661 6600",
    "sg:postcode":"74003",
    "sg:province":"OK",
    "sg:tags":[
        "company",
        "investment"
    ],
    "wof:name":"Phillips Petroleum Intl Inv Co",
    "wof:placetype":"venue"
},
  "geometry": {"coordinates":[-95.96334299999999,36.746264],"type":"Point"}
}