{
  "type": "Feature",
  "properties": {
    "iso:country":"US",
    "sg:address":"801 N Broadway Ave",
    "sg:city":"Oklahoma City",
    "sg:classifiers":[
        {
            "category":"Retail",
            "subcategory":"Auto Repair",
            "type":"Services"
        }
    ],
    "sg:phone":"+1 405 235 1942",
    "sg:postcode":"73102",
    "sg:province":"OK",
    "sg:tags":[
        "body",
        "automobile",
        "painting"
    ],
    "wof:name":"Blevins Paint & Body",
    "wof:placetype":"venue"
},
  "geometry": {"coordinates":[-97.51415900000001,35.476068],"type":"Point"}
}