{
  "type": "Feature",
  "properties": {
    "iso:country":"US",
    "sg:address":"114 E Broadway Ave",
    "sg:city":"Enid",
    "sg:classifiers":[
        {
            "category":"Communications",
            "subcategory":"Film & Video Production",
            "type":"Services"
        }
    ],
    "sg:phone":"+1 580 242 7487",
    "sg:postcode":"73701",
    "sg:province":"OK",
    "sg:tags":[
        "motion",
        "picture",
        "taping"
    ],
    "wof:name":"River Rock Entertainment LLC",
    "wof:placetype":"venue"
},
  "geometry": {"coordinates":[-97.876867,36.396694],"type":"Point"}
}