{
  "type": "Feature",
  "properties": {
    "iso:country":"US",
    "sg:address":"3200 W Robinson St",
    "sg:city":"Norman",
    "sg:classifiers":[
        {
            "category":"Restaurant",
            "type":"Food & Drink"
        }
    ],
    "sg:phone":"+1 405 447 3506",
    "sg:postcode":"73072",
    "sg:province":"OK",
    "sg:tags":[
        "eating"
    ],
    "wof:name":"Arbys",
    "wof:placetype":"venue"
},
  "geometry": {"coordinates":[-97.48940899999999,35.232876],"type":"Point"}
}