{
  "type": "Feature",
  "properties": {
    "addr:full":"605 14th Ave NW Ardmore OK 73401",
    "addr:housenumber":"605",
    "addr:postcode":"73401",
    "addr:street":"14Th Ave Nw",
    "iso:country":"US",
    "sg:address":"605 14th Ave NW",
    "sg:city":"Ardmore",
    "sg:classifiers":[
        {
            "category":"Professional",
            "subcategory":"Computer Services",
            "type":"Services"
        }
    ],
    "sg:phone":"+1 580 223 7891",
    "sg:postcode":"73401",
    "sg:province":"OK",
    "sg:tags":[
        "related"
    ],
    "wof:name":"Robert Fike",
    "wof:placetype":"venue"
},
  "geometry": {"coordinates":[-97.13491500000001,34.188512],"type":"Point"}
}