{
  "type": "Feature",
  "properties": {
    "iso:country":"US",
    "sg:address":"1620 E 6th Ave",
    "sg:city":"Stillwater",
    "sg:classifiers":[
        {
            "category":"Retail",
            "subcategory":"Auto Repair",
            "type":"Services"
        }
    ],
    "sg:phone":"+1 405 780 7744",
    "sg:postcode":"74074",
    "sg:province":"OK",
    "sg:tags":[
        "body",
        "automobile",
        "painting"
    ],
    "wof:name":"6th St Auto Body",
    "wof:placetype":"venue"
},
  "geometry": {"coordinates":[-97.034522,36.116054],"type":"Point"}
}