{
  "type": "Feature",
  "properties": {
    "iso:country":"US",
    "sg:address":"205 S 14th St",
    "sg:city":"Ponca City",
    "sg:classifiers":[
        {
            "category":"Travel",
            "subcategory":"Hotels & Motels",
            "type":"Entertainment"
        }
    ],
    "sg:phone":"+1 580 762 1663",
    "sg:postcode":"74601",
    "sg:province":"OK",
    "wof:name":"Lazy K Motel",
    "wof:placetype":"venue"
},
  "geometry": {"coordinates":[-97.067229,36.702202],"type":"Point"}
}