{
  "type": "Feature",
  "properties": {
    "addr:full":"2602 NW Bell Ave Lawton OK 73505",
    "addr:housenumber":"2602",
    "addr:postcode":"73505",
    "addr:street":"Nw Bell Ave",
    "iso:country":"US",
    "sg:address":"2602 NW Bell Ave",
    "sg:city":"Lawton",
    "sg:classifiers":[
        {
            "category":"Education",
            "subcategory":"Special Training",
            "type":"Public Place"
        }
    ],
    "sg:phone":"+1 580 248 8212",
    "sg:postcode":"73505",
    "sg:province":"OK",
    "sg:tags":[
        "educational"
    ],
    "wof:name":"J M S Educational Services",
    "wof:placetype":"venue"
},
  "geometry": {"coordinates":[-98.42905399999999,34.614061],"type":"Point"}
}