{
  "type": "Feature",
  "properties": {
    "iso:country":"US",
    "sg:address":"421 E Grand Ave",
    "sg:city":"Ponca City",
    "sg:classifiers":[
        {
            "category":"Banks & Credit Unions",
            "subcategory":"Investment Brokerage",
            "type":"Services"
        }
    ],
    "sg:phone":"+1 580 762 4139",
    "sg:postcode":"74601",
    "sg:province":"OK",
    "sg:tags":[
        "stock",
        "bond"
    ],
    "wof:name":"Wachovia Securities",
    "wof:placetype":"venue"
},
  "geometry": {"coordinates":[-97.07966399999999,36.703653],"type":"Point"}
}