{
  "type": "Feature",
  "properties": {
    "iso:country":"US",
    "sg:address":"505 S McLish Ave",
    "sg:city":"Tishomingo",
    "sg:classifiers":[
        {
            "category":"Restaurant",
            "type":"Food & Drink"
        }
    ],
    "sg:phone":"+1 580 371 9722",
    "sg:postcode":"73460",
    "sg:province":"OK",
    "sg:tags":[
        "eating"
    ],
    "wof:name":"Daylight Donuts",
    "wof:placetype":"venue"
},
  "geometry": {"coordinates":[-96.676184,34.229058],"type":"Point"}
}