{
  "type": "Feature",
  "properties": {
    "addr:full":"505 S McLish Ave Tishomingo OK 73460",
    "addr:housenumber":"505",
    "addr:postcode":"73460",
    "addr:street":"S Mclish Ave",
    "iso:country":"US",
    "sg:address":"505 S McLish Ave",
    "sg:city":"Tishomingo",
    "sg:classifiers":[
        {
            "category":"Restaurant",
            "type":"Food & Drink"
        }
    ],
    "sg:phone":"+1 580 371 9722",
    "sg:postcode":"73460",
    "sg:province":"OK",
    "sg:tags":[
        "eating"
    ],
    "wof:name":"Daylight Donuts",
    "wof:placetype":"venue"
},
  "geometry": {"coordinates":[-96.67618400000001,34.229058],"type":"Point"}
}