{
  "type": "Feature",
  "properties": {
    "iso:country":"US",
    "sg:address":"10015 S Pennsylvania Ave",
    "sg:city":"Oklahoma City",
    "sg:classifiers":[
        {
            "category":"Professional",
            "subcategory":"Computer Services",
            "type":"Services"
        }
    ],
    "sg:phone":"+1 405 692 2123",
    "sg:postcode":"73159",
    "sg:province":"OK",
    "sg:tags":[
        "information",
        "technology"
    ],
    "wof:name":"Tek Search Assoc Inc",
    "wof:placetype":"venue"
},
  "geometry": {"coordinates":[-97.547782,35.367367],"type":"Point"}
}