{
  "type": "Feature",
  "properties": {
    "iso:country":"US",
    "sg:address":"515 6th St",
    "sg:city":"Snyder",
    "sg:classifiers":[
        {
            "category":"Real Estate",
            "subcategory":"Surveying",
            "type":"Services"
        }
    ],
    "sg:phone":"+1 580 569 2305",
    "sg:postcode":"73566",
    "sg:province":"OK",
    "sg:tags":[
        "surveyor"
    ],
    "wof:name":"North Fork Surveying",
    "wof:placetype":"venue"
},
  "geometry": {"coordinates":[-98.951731,34.66],"type":"Point"}
}