{
  "type": "Feature",
  "properties": {
    "iso:country":"US",
    "sg:address":"144 W 49th Pl N",
    "sg:city":"Tulsa",
    "sg:classifiers":[
        {
            "category":"Wholesale",
            "subcategory":"Electrical",
            "type":"Manufacturing & Wholesale Goods"
        }
    ],
    "sg:phone":"+1 918 428 0034",
    "sg:postcode":"74126",
    "sg:province":"OK",
    "sg:tags":[
        "control",
        "security",
        "system"
    ],
    "wof:name":"DEA Security Svc",
    "wof:placetype":"venue"
},
  "geometry": {"coordinates":[-96.000504,36.224929],"type":"Point"}
}