{
  "type": "Feature",
  "properties": {
    "iso:country":"US",
    "sg:address":"335 N 4th St",
    "sg:city":"Muskogee",
    "sg:classifiers":[
        {
            "category":"Shopping",
            "subcategory":"Musical Instruments",
            "type":"Retail Goods"
        }
    ],
    "sg:phone":"+1 918 687 1244",
    "sg:postcode":"74401",
    "sg:province":"OK",
    "sg:tags":[
        "piano",
        "clocks",
        "organs"
    ],
    "wof:name":"Ricketts Piano Sales",
    "wof:placetype":"venue"
},
  "geometry": {"coordinates":[-95.371147,35.751726],"type":"Point"}
}