{
  "type": "Feature",
  "properties": {
    "iso:country":"US",
    "sg:address":"434 Elm Ave",
    "sg:city":"Norman",
    "sg:classifiers":[
        {
            "category":"Real Estate",
            "subcategory":"Real Estate Operator",
            "type":"Services"
        }
    ],
    "sg:phone":"+1 405 321 3745",
    "sg:postcode":"73069",
    "sg:province":"OK",
    "sg:tags":[
        "building",
        "apartment"
    ],
    "wof:name":"Aiken Properties",
    "wof:placetype":"venue"
},
  "geometry": {"coordinates":[-97.447955,35.212052],"type":"Point"}
}