{
  "type": "Feature",
  "properties": {
    "addr:full":"1 W Main St Countyline OK 73401",
    "addr:housenumber":"1",
    "addr:postcode":"73401",
    "addr:street":"W Main St",
    "iso:country":"US",
    "sg:address":"1 W Main St",
    "sg:city":"Countyline",
    "sg:classifiers":[
        {
            "category":"Government",
            "subcategory":"Post Office",
            "type":"Public Place"
        }
    ],
    "sg:phone":"+1 580 856 3425",
    "sg:postcode":"73401",
    "sg:province":"OK",
    "wof:name":"US Post Office",
    "wof:placetype":"venue"
},
  "geometry": {"coordinates":[-97.12917400000001,34.172815],"type":"Point"}
}