{
  "type": "Feature",
  "properties": {
    "addr:full":"629 24th Ave SW Norman OK 73069",
    "addr:housenumber":"629",
    "addr:postcode":"73069",
    "addr:street":"24Th Ave Sw",
    "iso:country":"US",
    "sg:address":"629 24th Ave SW",
    "sg:city":"Norman",
    "sg:classifiers":[
        {
            "category":"Professional",
            "subcategory":"Lawyer & Legal Services",
            "type":"Services"
        }
    ],
    "sg:phone":"+1 405 292 3283",
    "sg:postcode":"73069",
    "sg:province":"OK",
    "wof:name":"Attorney At Law",
    "wof:placetype":"venue"
},
  "geometry": {"coordinates":[-97.47658699999999,35.212451],"type":"Point"}
}