{
  "type": "Feature",
  "properties": {
    "iso:country":"US",
    "sg:address":"7609 Dorset Dr",
    "sg:city":"Oklahoma City",
    "sg:classifiers":[
        {
            "category":"Organizations",
            "subcategory":"Membership Organization",
            "type":"Services"
        }
    ],
    "sg:phone":"+1 405 842 4988",
    "sg:postcode":"73116",
    "sg:province":"OK",
    "wof:name":"Thurman Magbee Foundation",
    "wof:placetype":"venue"
},
  "geometry": {"coordinates":[-97.556496,35.54972],"type":"Point"}
}