{
  "type": "Feature",
  "properties": {
    "iso:country":"US",
    "sg:address":"310 W Main St",
    "sg:city":"Durant",
    "sg:classifiers":[
        {
            "category":"Education",
            "subcategory":"Special Training",
            "type":"Public Place"
        }
    ],
    "sg:phone":"+1 580 745 9887",
    "sg:postcode":"74701",
    "sg:province":"OK",
    "sg:tags":[
        "tutoring"
    ],
    "wof:name":"Umbrella",
    "wof:placetype":"venue"
},
  "geometry": {"coordinates":[-96.37971,33.991622],"type":"Point"}
}