{
  "type": "Feature",
  "properties": {
    "iso:country":"US",
    "sg:address":"322 W Broadway Ave",
    "sg:city":"Broken Arrow",
    "sg:classifiers":[
        {
            "category":"Organizations",
            "subcategory":"Membership Organization",
            "type":"Services"
        }
    ],
    "sg:phone":"+1 918 259 3044",
    "sg:postcode":"74012",
    "sg:province":"OK",
    "wof:name":"Red Cross",
    "wof:placetype":"venue"
},
  "geometry": {"coordinates":[-95.793502,36.052472],"type":"Point"}
}