{
  "type": "Feature",
  "properties": {
    "iso:country":"US",
    "sg:address":"216 W Main St",
    "sg:city":"Oklahoma City",
    "sg:classifiers":[
        {
            "category":"Retail",
            "subcategory":"Repair Shop",
            "type":"Services"
        }
    ],
    "sg:phone":"+1 405 794 4337",
    "sg:postcode":"73160",
    "sg:province":"OK",
    "sg:tags":[
        "ho"
    ],
    "wof:name":"Fikes T V & Video of Moore",
    "wof:placetype":"venue"
},
  "geometry": {"coordinates":[-97.489745,35.338173],"type":"Point"}
}