{
  "type": "Feature",
  "properties": {
    "iso:country":"US",
    "sg:address":"253 S Coltrane Rd",
    "sg:city":"Edmond",
    "sg:classifiers":[
        {
            "category":"Shopping",
            "subcategory":"Bicycles & Sporting Goods",
            "type":"Retail Goods"
        }
    ],
    "sg:phone":"+1 405 359 9886",
    "sg:postcode":"73034",
    "sg:province":"OK",
    "sg:tags":[
        "tackle",
        "fishing"
    ],
    "wof:name":"Brandon's Bait & Tackle",
    "wof:placetype":"venue"
},
  "geometry": {"coordinates":[-97.442755,35.650783],"type":"Point"}
}