{
  "type": "Feature",
  "properties": {
    "addr:full":"713 W Main St Norman OK 73069",
    "addr:housenumber":"713",
    "addr:postcode":"73069",
    "addr:street":"W Main St",
    "iso:country":"US",
    "sg:address":"713 W Main St",
    "sg:city":"Norman",
    "sg:classifiers":[
        {
            "category":"Insurance",
            "subcategory":"Insurance Agent",
            "type":"Services"
        }
    ],
    "sg:phone":"+1 405 360 7656",
    "sg:postcode":"73069",
    "sg:province":"OK",
    "sg:tags":[
        "broker"
    ],
    "wof:name":"Allstate",
    "wof:placetype":"venue"
},
  "geometry": {"coordinates":[-97.453875,35.218468],"type":"Point"}
}