{
  "type": "Feature",
  "properties": {
    "iso:country":"US",
    "sg:address":"4001 S 24th St W",
    "sg:city":"Muskogee",
    "sg:classifiers":[
        {
            "category":"Shopping",
            "subcategory":"Used Merchandise",
            "type":"Retail Goods"
        }
    ],
    "sg:phone":"+1 918 687 4575",
    "sg:postcode":"74401",
    "sg:province":"OK",
    "wof:name":"Teresas Antiques",
    "wof:placetype":"venue"
},
  "geometry": {"coordinates":[-95.396259,35.7008],"type":"Point"}
}