{
  "type": "Feature",
  "properties": {
    "iso:country":"US",
    "sg:address":"2502 NW Cache Rd",
    "sg:city":"Lawton",
    "sg:classifiers":[
        {
            "category":"Banks & Credit Unions",
            "subcategory":"Bank",
            "type":"Services"
        }
    ],
    "sg:phone":"+1 580 357 2120",
    "sg:postcode":"73505",
    "sg:province":"OK",
    "sg:tags":[
        "company",
        "consumer",
        "finance"
    ],
    "wof:name":"HFC",
    "wof:placetype":"venue"
},
  "geometry": {"coordinates":[-98.426524,34.623281],"type":"Point"}
}