{
  "type": "Feature",
  "properties": {
    "iso:country":"US",
    "sg:address":"630 E 17th St",
    "sg:city":"Ada",
    "sg:classifiers":[
        {
            "category":"Professional",
            "subcategory":"Management & Consulting",
            "type":"Services"
        }
    ],
    "sg:phone":"+1 580 310 9715",
    "sg:postcode":"74820",
    "sg:province":"OK",
    "sg:tags":[
        "development",
        "economic",
        "agency"
    ],
    "wof:name":"Tricounty Indian Nations",
    "wof:placetype":"venue"
},
  "geometry": {"coordinates":[-96.670401,34.768233],"type":"Point"}
}