{
  "type": "Feature",
  "properties": {
    "iso:country":"US",
    "sg:address":"7300 N Macarthur Blvd",
    "sg:city":"Oklahoma City",
    "sg:classifiers":[
        {
            "category":"Health Services",
            "subcategory":"Doctor",
            "type":"Services"
        }
    ],
    "sg:phone":"+1 405 721 1616",
    "sg:postcode":"73132",
    "sg:province":"OK",
    "sg:tags":[
        "dentist"
    ],
    "wof:name":"Fred W Pike DDS",
    "wof:placetype":"venue"
},
  "geometry": {"coordinates":[-97.619018,35.547571],"type":"Point"}
}