{
  "type": "Feature",
  "properties": {
    "iso:country":"US",
    "sg:address":"410 E Grand Ave",
    "sg:city":"Tonkawa",
    "sg:classifiers":[
        {
            "category":"Organizations",
            "subcategory":"Religious Organization",
            "type":"Services"
        }
    ],
    "sg:phone":"+1 580 628 2309",
    "sg:postcode":"74653",
    "sg:province":"OK",
    "sg:tags":[
        "church"
    ],
    "sg:website":"www.gbgm-umc.org/tonkawaumc",
    "wof:name":"United Methodist Church",
    "wof:placetype":"venue"
},
  "geometry": {"coordinates":[-97.30623900000001,36.678458],"type":"Point"}
}