{
  "type": "Feature",
  "properties": {
    "iso:country":"US",
    "sg:address":"3317 Brookhollow Ct",
    "sg:city":"Oklahoma City",
    "sg:classifiers":[
        {
            "category":"Arts & Performance",
            "subcategory":"Theater",
            "type":"Entertainment"
        }
    ],
    "sg:phone":"+1 405 340 1166",
    "sg:postcode":"73120",
    "sg:province":"OK",
    "sg:tags":[
        "live",
        "music"
    ],
    "wof:name":"Dale Wehba's Entertainment",
    "wof:placetype":"venue"
},
  "geometry": {"coordinates":[-97.576748,35.582467],"type":"Point"}
}