{
  "type": "Feature",
  "properties": {
    "iso:country":"US",
    "sg:address":"619 Speck St",
    "sg:city":"Vici",
    "sg:classifiers":[
        {
            "category":"Health Services",
            "subcategory":"Nursing And Care Facility",
            "type":"Services"
        }
    ],
    "sg:phone":"+1 580 995 4216",
    "sg:postcode":"73859",
    "sg:province":"OK",
    "sg:tags":[
        "home",
        "convalescent"
    ],
    "wof:name":"Vici Nursing Home",
    "wof:placetype":"venue"
},
  "geometry": {"coordinates":[-99.30248,36.150501],"type":"Point"}
}