{
  "type": "Feature",
  "properties": {
    "iso:country":"US",
    "sg:address":"124 W 7th Ave",
    "sg:city":"Stillwater",
    "sg:classifiers":[
        {
            "category":"Shopping",
            "subcategory":"Gifts & Souvenirs",
            "type":"Retail Goods"
        }
    ],
    "sg:phone":"+1 405 743 8300",
    "sg:postcode":"74074",
    "sg:province":"OK",
    "sg:tags":[
        "shop"
    ],
    "wof:name":"Heavensent",
    "wof:placetype":"venue"
},
  "geometry": {"coordinates":[-97.058847,36.114635],"type":"Point"}
}