{
  "type": "Feature",
  "properties": {
    "iso:country":"US",
    "sg:address":"111 N Broadway Ave",
    "sg:city":"Shawnee",
    "sg:classifiers":[
        {
            "category":"Cinema",
            "subcategory":"Movie Rental",
            "type":"Entertainment"
        }
    ],
    "sg:phone":"+1 405 275 0500",
    "sg:postcode":"74801",
    "sg:province":"OK",
    "sg:tags":[
        "leasing",
        "video",
        "disc",
        "tape"
    ],
    "wof:name":"Downtown Video & Records",
    "wof:placetype":"venue"
},
  "geometry": {"coordinates":[-96.92344199999999,35.328555],"type":"Point"}
}