{
  "type": "Feature",
  "properties": {
    "addr:full":"120 N 4th St Sayre OK 73662",
    "addr:housenumber":"120",
    "addr:postcode":"73662",
    "addr:street":"N 4Th St",
    "iso:country":"US",
    "sg:address":"120 N 4th St",
    "sg:city":"Sayre",
    "sg:classifiers":[
        {
            "category":"Shopping",
            "subcategory":"Used Merchandise",
            "type":"Retail Goods"
        }
    ],
    "sg:phone":"+1 580 928 3538",
    "sg:postcode":"73662",
    "sg:province":"OK",
    "sg:tags":[
        "shop",
        "thrift"
    ],
    "wof:name":"Granny's Old Closet",
    "wof:placetype":"venue"
},
  "geometry": {"coordinates":[-99.639886,35.29162],"type":"Point"}
}