{
  "type": "Feature",
  "properties": {
    "iso:country":"US",
    "sg:address":"1500 Washington Pkwy",
    "sg:city":"Marietta",
    "sg:classifiers":[
        {
            "category":"Real Estate",
            "subcategory":"Real Estate Operator",
            "type":"Services"
        }
    ],
    "sg:phone":"+1 580 276 4096",
    "sg:postcode":"73448",
    "sg:province":"OK",
    "sg:tags":[
        "apartment"
    ],
    "wof:name":"Stone Briar Apartments",
    "wof:placetype":"venue"
},
  "geometry": {"coordinates":[-97.129927,33.924531],"type":"Point"}
}