{
  "type": "Feature",
  "properties": {
    "iso:country":"US",
    "sg:address":"5112 S Hickory Ave",
    "sg:city":"Broken Arrow",
    "sg:classifiers":[
        {
            "category":"Professional",
            "subcategory":"Business Services",
            "type":"Services"
        }
    ],
    "sg:phone":"+1 918 449 9372",
    "sg:postcode":"74011",
    "sg:province":"OK",
    "sg:tags":[
        "financial"
    ],
    "wof:name":"Infinite Finanical Freedom LL",
    "wof:placetype":"venue"
},
  "geometry": {"coordinates":[-95.801036,35.9997],"type":"Point"}
}