{
  "type": "Feature",
  "properties": {
    "addr:full":"2605 Charleston Rd Edmond OK 73025",
    "addr:housenumber":"2605",
    "addr:postcode":"73025",
    "addr:street":"Charleston Rd",
    "iso:country":"US",
    "sg:address":"2605 Charleston Rd",
    "sg:city":"Edmond",
    "sg:classifiers":[
        {
            "category":"Professional",
            "subcategory":"Management & Consulting",
            "type":"Services"
        }
    ],
    "sg:phone":"+1 405 348 0639",
    "sg:postcode":"73025",
    "sg:province":"OK",
    "sg:tags":[
        "business"
    ],
    "wof:name":"Microsolve",
    "wof:placetype":"venue"
},
  "geometry": {"coordinates":[-97.517388,35.735291],"type":"Point"}
}