{
  "type": "Feature",
  "properties": {
    "iso:country":"US",
    "sg:address":"7035 E Reno Ave",
    "sg:city":"Oklahoma City",
    "sg:classifiers":[
        {
            "category":"Health Services",
            "subcategory":"Chiropractor",
            "type":"Services"
        }
    ],
    "sg:phone":"+1 405 733 3388",
    "sg:postcode":"73110",
    "sg:province":"OK",
    "wof:name":"Lo Vette Chiropractic Clinic",
    "wof:placetype":"venue"
},
  "geometry": {"coordinates":[-97.406053,35.464139],"type":"Point"}
}