{
  "type": "Feature",
  "properties": {
    "iso:country":"US",
    "sg:address":"3314 E 51st St S",
    "sg:city":"Tulsa",
    "sg:classifiers":[
        {
            "category":"Professional",
            "subcategory":"Lawyer & Legal Services",
            "type":"Services"
        }
    ],
    "sg:phone":"+1 918 743 2265",
    "sg:postcode":"74135",
    "sg:province":"OK",
    "sg:tags":[
        "attorney"
    ],
    "wof:name":"Goldwyn & Goldwyn",
    "wof:placetype":"venue"
},
  "geometry": {"coordinates":[-95.934749,36.089719],"type":"Point"}
}