{
  "type": "Feature",
  "properties": {
    "iso:country":"US",
    "sg:address":"2702 W Beech Ave",
    "sg:city":"Duncan",
    "sg:classifiers":[
        {
            "category":"Real Estate",
            "subcategory":"Real Estate Agent",
            "type":"Services"
        }
    ],
    "sg:phone":"+1 580 255 3594",
    "sg:postcode":"73533",
    "sg:province":"OK",
    "wof:name":"Tamara L Binning Management Co",
    "wof:placetype":"venue"
},
  "geometry": {"coordinates":[-97.98256000000001,34.506984],"type":"Point"}
}