{
  "type": "Feature",
  "properties": {
    "addr:full":"121 W Main St Wilson OK 73463",
    "addr:housenumber":"121",
    "addr:postcode":"73463",
    "addr:street":"W Main St",
    "iso:country":"US",
    "sg:address":"121 W Main St",
    "sg:city":"Wilson",
    "sg:classifiers":[
        {
            "category":"Home & Garden",
            "subcategory":"Building Materials",
            "type":"Retail Goods"
        }
    ],
    "sg:phone":"+1 580 668 2477",
    "sg:postcode":"73463",
    "sg:province":"OK",
    "sg:tags":[
        "plumbing",
        "fixture",
        "supply"
    ],
    "wof:name":"Store Etc",
    "wof:placetype":"venue"
},
  "geometry": {"coordinates":[-97.426073,34.162076],"type":"Point"}
}