{
  "type": "Feature",
  "properties": {
    "iso:country":"US",
    "sg:address":"101 Tennessee Ave",
    "sg:city":"Cherokee",
    "sg:classifiers":[
        {
            "category":"Farming",
            "subcategory":"Livestock Farm",
            "type":"Manufacturing & Wholesale Goods"
        }
    ],
    "sg:phone":"+1 580 596 3182",
    "sg:postcode":"73728",
    "sg:province":"OK",
    "sg:tags":[
        "animal",
        "general"
    ],
    "wof:name":"Newton Ranch LLC",
    "wof:placetype":"venue"
},
  "geometry": {"coordinates":[-98.345649,36.75765],"type":"Point"}
}