{
  "type": "Feature",
  "properties": {
    "iso:country":"US",
    "sg:address":"2824 Hillcrest Dr",
    "sg:city":"Oklahoma City",
    "sg:classifiers":[
        {
            "category":"Building & Trades",
            "subcategory":"Construction",
            "type":"Services"
        }
    ],
    "sg:phone":"+1 405 794 0674",
    "sg:postcode":"73160",
    "sg:province":"OK",
    "sg:tags":[
        "hanging",
        "contractor"
    ],
    "wof:name":"Frontier Painting",
    "wof:placetype":"venue"
},
  "geometry": {"coordinates":[-97.500969,35.364209],"type":"Point"}
}