{
  "type": "Feature",
  "properties": {
    "iso:country":"US",
    "sg:address":"2401 S May Ave",
    "sg:city":"Oklahoma City",
    "sg:classifiers":[
        {
            "category":"Wholesale",
            "subcategory":"Auto Parts",
            "type":"Manufacturing & Wholesale Goods"
        }
    ],
    "sg:phone":"+1 405 686 0007",
    "sg:postcode":"73108",
    "sg:province":"OK",
    "sg:tags":[
        "used"
    ],
    "wof:name":"Square Deal Auto Salvage",
    "wof:placetype":"venue"
},
  "geometry": {"coordinates":[-97.565634,35.440508],"type":"Point"}
}