{
  "type": "Feature",
  "properties": {
    "iso:country":"US",
    "sg:address":"1200 E Carl Albert Pkwy",
    "sg:city":"Mcalester",
    "sg:classifiers":[
        {
            "category":"Restaurant",
            "type":"Food & Drink"
        }
    ],
    "sg:menulink":"http://www.allmenus.com/ok/mcalester/94335-dominos-pizza/menu/",
    "sg:phone":"+1 918 426 6410",
    "sg:postcode":"74501",
    "sg:province":"OK",
    "sg:tags":[
        "american",
        "wing",
        "pizza"
    ],
    "wof:name":"Domino's Pizza",
    "wof:placetype":"venue"
},
  "geometry": {"coordinates":[-95.752545,34.92878],"type":"Point"}
}