{
  "type": "Feature",
  "properties": {
    "addr:full":"525 E 46th St N Tulsa OK 74126",
    "addr:housenumber":"525",
    "addr:postcode":"74126",
    "addr:street":"E 46Th St N",
    "iso:country":"US",
    "sg:address":"525 E 46th St N",
    "sg:city":"Tulsa",
    "sg:classifiers":[
        {
            "category":"Education",
            "subcategory":"School",
            "type":"Public Place"
        }
    ],
    "sg:phone":"+1 918 746 9660",
    "sg:postcode":"74126",
    "sg:province":"OK",
    "sg:website":"www.tulsaschool.org",
    "wof:name":"Alcott Elementary School",
    "wof:placetype":"venue"
},
  "geometry": {"coordinates":[-95.988986,36.220467],"type":"Point"}
}