{
  "type": "Feature",
  "properties": {
    "addr:full":"1024 SW 21st St Oklahoma City OK 73108",
    "addr:housenumber":"1024",
    "addr:postcode":"73108",
    "addr:street":"Sw 21St St",
    "iso:country":"US",
    "sg:address":"1024 SW 21st St",
    "sg:city":"Oklahoma City",
    "sg:classifiers":[
        {
            "category":"Building & Trades",
            "subcategory":"Plumbing",
            "type":"Services"
        }
    ],
    "sg:phone":"+1 405 681 1253",
    "sg:postcode":"73108",
    "sg:province":"OK",
    "sg:tags":[
        "plumbing",
        "contractor"
    ],
    "wof:name":"Vet's Plumbing",
    "wof:placetype":"venue"
},
  "geometry": {"coordinates":[-97.53488900000001,35.443321],"type":"Point"}
}