{
  "type": "Feature",
  "properties": {
    "addr:full":"312 N 15th St Frederick OK 73542",
    "addr:housenumber":"312",
    "addr:postcode":"73542",
    "addr:street":"N 15Th St",
    "iso:country":"US",
    "sg:address":"312 N 15th St",
    "sg:city":"Frederick",
    "sg:classifiers":[
        {
            "category":"Education",
            "subcategory":"School",
            "type":"Public Place"
        }
    ],
    "sg:phone":"+1 580 335 5521",
    "sg:postcode":"73542",
    "sg:province":"OK",
    "sg:website":"www.frederickbombers.net",
    "wof:name":"Frederick High School",
    "wof:placetype":"venue"
},
  "geometry": {"coordinates":[-99.01079,34.392191],"type":"Point"}
}