{
  "type": "Feature",
  "properties": {
    "iso:country":"US",
    "sg:address":"502 Highland Pkwy",
    "sg:city":"Norman",
    "sg:classifiers":[
        {
            "category":"Building & Trades",
            "subcategory":"Construction",
            "type":"Services"
        }
    ],
    "sg:phone":"+1 405 329 1437",
    "sg:postcode":"73069",
    "sg:province":"OK",
    "sg:tags":[
        "carpentry",
        "contractor"
    ],
    "wof:name":"Clouses Glass and Mirror Inc",
    "wof:placetype":"venue"
},
  "geometry": {"coordinates":[-97.45177200000001,35.228423],"type":"Point"}
}