{
  "type": "Feature",
  "properties": {
    "iso:country":"US",
    "sg:address":"508 E Hall of Fame Ave",
    "sg:city":"Stillwater",
    "sg:classifiers":[
        {
            "category":"Restaurant",
            "type":"Food & Drink"
        }
    ],
    "sg:menulink":"http://www.allmenus.com/ok/stillwater/284018-goldies-patio-grill/menu/",
    "sg:phone":"+1 405 372 6700",
    "sg:postcode":"74075",
    "sg:province":"OK",
    "sg:tags":[
        "american"
    ],
    "wof:name":"Goldie's Patio Grill",
    "wof:placetype":"venue"
},
  "geometry": {"coordinates":[-97.053809,36.126927],"type":"Point"}
}