{
  "type": "Feature",
  "properties": {
    "iso:country":"US",
    "sg:address":"4601 Harold Scoggins Dr",
    "sg:city":"Muskogee",
    "sg:classifiers":[
        {
            "category":"Freight",
            "type":"Transportation"
        }
    ],
    "sg:phone":"+1 918 682 7883",
    "sg:postcode":"74403",
    "sg:province":"OK",
    "sg:tags":[
        "trucking"
    ],
    "sg:website":"www.johnstonports.com",
    "wof:name":"Johnston's Terminal-Muskogee",
    "wof:placetype":"venue"
},
  "geometry": {"coordinates":[-95.302542,35.787217],"type":"Point"}
}