{
  "type": "Feature",
  "properties": {
    "addr:full":"2300 Westwood Dr Norman OK 73069",
    "addr:housenumber":"2300",
    "addr:postcode":"73069",
    "addr:street":"Westwood Dr",
    "iso:country":"US",
    "sg:address":"2300 Westwood Dr",
    "sg:city":"Norman",
    "sg:classifiers":[
        {
            "category":"Professional",
            "subcategory":"Management & Consulting",
            "type":"Services"
        }
    ],
    "sg:phone":"+1 405 364 8751",
    "sg:postcode":"73069",
    "sg:province":"OK",
    "wof:name":"Pat Privett Management",
    "wof:placetype":"venue"
},
  "geometry": {"coordinates":[-97.47424599999999,35.227788],"type":"Point"}
}