{
  "type": "Feature",
  "properties": {
    "iso:country":"US",
    "sg:address":"114 N Main St",
    "sg:city":"Kingfisher",
    "sg:classifiers":[
        {
            "category":"Professional",
            "subcategory":"Lawyer & Legal Services",
            "type":"Services"
        }
    ],
    "sg:phone":"+1 405 375 5516",
    "sg:postcode":"73750",
    "sg:province":"OK",
    "sg:tags":[
        "attorney"
    ],
    "wof:name":"Pritchett & Snyder",
    "wof:placetype":"venue"
},
  "geometry": {"coordinates":[-97.93279,35.861844],"type":"Point"}
}