{
  "type": "Feature",
  "properties": {
    "iso:country":"US",
    "sg:address":"12211 E 52nd St S",
    "sg:city":"Tulsa",
    "sg:classifiers":[
        {
            "category":"Building & Trades",
            "subcategory":"Electrical",
            "type":"Services"
        }
    ],
    "sg:phone":"+1 918 461 1200",
    "sg:postcode":"74146",
    "sg:province":"OK",
    "sg:tags":[
        "electrical",
        "contractor"
    ],
    "wof:name":"Securenet Inc",
    "wof:placetype":"venue"
},
  "geometry": {"coordinates":[-95.836565,36.087858],"type":"Point"}
}