{
  "type": "Feature",
  "properties": {
    "iso:country":"US",
    "sg:address":"11014 E 51st St",
    "sg:city":"Tulsa",
    "sg:classifiers":[
        {
            "category":"Health Services",
            "subcategory":"Chiropractor",
            "type":"Services"
        }
    ],
    "sg:phone":"+1 918 664 2412",
    "sg:postcode":"74146",
    "sg:province":"OK",
    "wof:name":"Impact Chiropractic Clinic PC",
    "wof:placetype":"venue"
},
  "geometry": {"coordinates":[-95.851873,36.089915],"type":"Point"}
}