{
  "type": "Feature",
  "properties": {
    "iso:country":"US",
    "sg:address":"1405 SW 20th St",
    "sg:city":"Lawton",
    "sg:classifiers":[
        {
            "category":"Organizations",
            "subcategory":"Non-profit Organization",
            "type":"Services"
        }
    ],
    "sg:phone":"+1 580 353 7994",
    "sg:postcode":"73501",
    "sg:province":"OK",
    "wof:name":"Lawton Food Bank",
    "wof:placetype":"venue"
},
  "geometry": {"coordinates":[-98.418526,34.592899],"type":"Point"}
}