{
  "type": "Feature",
  "properties": {
    "addr:full":"5500 NW 39th St Warr Acres OK 73122",
    "addr:housenumber":"5500",
    "addr:postcode":"73122",
    "addr:street":"Nw 39Th St",
    "iso:country":"US",
    "sg:address":"5500 NW 39th St",
    "sg:city":"Warr Acres",
    "sg:classifiers":[
        {
            "category":"Autos & Motor Vehicles",
            "subcategory":"Fuel & Gas Station",
            "type":"Retail Goods"
        }
    ],
    "sg:phone":"+1 405 789 9684",
    "sg:postcode":"73122",
    "sg:province":"OK",
    "sg:tags":[
        "oil"
    ],
    "wof:name":"Mid-West Oil",
    "wof:placetype":"venue"
},
  "geometry": {"coordinates":[-97.614868,35.511176],"type":"Point"}
}