{
  "type": "Feature",
  "properties": {
    "addr:full":"103 E Harrison Ave Chouteau OK 74337",
    "addr:housenumber":"103",
    "addr:postcode":"74337",
    "addr:street":"E Harrison Ave",
    "iso:country":"US",
    "sg:address":"103 E Harrison Ave",
    "sg:city":"Chouteau",
    "sg:classifiers":[
        {
            "category":"Personal",
            "type":"Services"
        }
    ],
    "sg:phone":"+1 918 476 5763",
    "sg:postcode":"74337",
    "sg:province":"OK",
    "sg:tags":[
        "department",
        "motor",
        "vehicle"
    ],
    "wof:name":"Chouteau Tag Agent",
    "wof:placetype":"venue"
},
  "geometry": {"coordinates":[-95.341262,36.191535],"type":"Point"}
}