{
  "type": "Feature",
  "properties": {
    "iso:country":"US",
    "sg:address":"100 Mayer Dr",
    "sg:city":"Broken Bow",
    "sg:classifiers":[
        {
            "category":"Real Estate",
            "subcategory":"Real Estate Agent",
            "type":"Services"
        }
    ],
    "sg:phone":"+1 580 286 5395",
    "sg:postcode":"74728",
    "sg:province":"OK",
    "wof:name":"Crain Realty",
    "wof:placetype":"venue"
},
  "geometry": {"coordinates":[-94.749101,34.050022],"type":"Point"}
}