{
  "type": "Feature",
  "properties": {
    "iso:country":"US",
    "sg:address":"3550 W Main St",
    "sg:city":"Norman",
    "sg:classifiers":[
        {
            "category":"Professional",
            "subcategory":"Detective & Security Services",
            "type":"Services"
        }
    ],
    "sg:phone":"+1 405 364 9898",
    "sg:postcode":"73072",
    "sg:province":"OK",
    "sg:tags":[
        "investigator"
    ],
    "wof:name":"Winston Services",
    "wof:placetype":"venue"
},
  "geometry": {"coordinates":[-97.493872,35.218243],"type":"Point"}
}