{
  "type": "Feature",
  "properties": {
    "iso:country":"US",
    "sg:address":"100 W 5th St",
    "sg:city":"Tulsa",
    "sg:classifiers":[
        {
            "category":"Banks & Credit Unions",
            "subcategory":"Investment Brokerage",
            "type":"Services"
        }
    ],
    "sg:phone":"+1 918 582 3211",
    "sg:postcode":"74103",
    "sg:province":"OK",
    "sg:tags":[
        "stock",
        "bond"
    ],
    "wof:name":"Morgan Stanley",
    "wof:placetype":"venue"
},
  "geometry": {"coordinates":[-95.992435,36.1506],"type":"Point"}
}