{
  "type": "Feature",
  "properties": {
    "iso:country":"US",
    "sg:address":"2245 SE Washington Blvd",
    "sg:city":"Bartlesville",
    "sg:classifiers":[
        {
            "category":"Professional",
            "subcategory":"Lawyer & Legal Services",
            "type":"Services"
        }
    ],
    "sg:phone":"+1 918 766 0080",
    "sg:postcode":"74006",
    "sg:province":"OK",
    "sg:tags":[
        "attorney"
    ],
    "wof:name":"Bill Hall",
    "wof:placetype":"venue"
},
  "geometry": {"coordinates":[-95.935168,36.718022],"type":"Point"}
}