{
  "type": "Feature",
  "properties": {
    "addr:full":"5540 S Lewis Ave Tulsa OK 74105",
    "addr:housenumber":"5540",
    "addr:postcode":"74105",
    "addr:street":"S Lewis Ave",
    "iso:country":"US",
    "sg:address":"5540 S Lewis Ave",
    "sg:city":"Tulsa",
    "sg:classifiers":[
        {
            "category":"Utilities",
            "subcategory":"Natural Gas",
            "type":"Services"
        }
    ],
    "sg:phone":"+1 918 293 9933",
    "sg:postcode":"74105",
    "sg:province":"OK",
    "sg:tags":[
        "company"
    ],
    "wof:name":"Keystone Gas Corp",
    "wof:placetype":"venue"
},
  "geometry": {"coordinates":[-95.958026,36.084068],"type":"Point"}
}