{
  "type": "Feature",
  "properties": {
    "iso:country":"US",
    "sg:address":"4953 S Union Ave",
    "sg:city":"Tulsa",
    "sg:classifiers":[
        {
            "category":"Food & Beverages",
            "subcategory":"Liquor & Beverages",
            "type":"Retail Goods"
        }
    ],
    "sg:phone":"+1 918 446 3641",
    "sg:postcode":"74107",
    "sg:province":"OK",
    "sg:tags":[
        "alcoholic"
    ],
    "wof:name":"Neighborhood Liquor Store",
    "wof:placetype":"venue"
},
  "geometry": {"coordinates":[-96.011562,36.090502],"type":"Point"}
}