{
  "type": "Feature",
  "properties": {
    "iso:country":"US",
    "sg:address":"4317 W Memorial Rd",
    "sg:city":"Oklahoma City",
    "sg:classifiers":[
        {
            "category":"Health Services",
            "subcategory":"Clinic",
            "type":"Services"
        }
    ],
    "sg:phone":"+1 405 755 6240",
    "sg:postcode":"73134",
    "sg:province":"OK",
    "sg:tags":[
        "surgical",
        "center"
    ],
    "wof:name":"Oklahoma Surgicare",
    "wof:placetype":"venue"
},
  "geometry": {"coordinates":[-97.60025,35.610336],"type":"Point"}
}