{
  "type": "Feature",
  "properties": {
    "iso:country":"US",
    "sg:address":"223 Broadway Ave",
    "sg:city":"Eufaula",
    "sg:classifiers":[
        {
            "category":"Personal",
            "subcategory":"Beauty Salon",
            "type":"Services"
        }
    ],
    "sg:phone":"+1 918 689 3306",
    "sg:postcode":"74432",
    "sg:province":"OK",
    "sg:tags":[
        "shop"
    ],
    "wof:name":"Hair Affair",
    "wof:placetype":"venue"
},
  "geometry": {"coordinates":[-95.57808900000001,35.289485],"type":"Point"}
}