{
  "type": "Feature",
  "properties": {
    "iso:country":"US",
    "sg:address":"108 W Main St",
    "sg:city":"Jenks",
    "sg:classifiers":[
        {
            "category":"Professional",
            "subcategory":"Business Services",
            "type":"Services"
        }
    ],
    "sg:phone":"+1 918 299 2995",
    "sg:postcode":"74037",
    "sg:province":"OK",
    "wof:name":"Pizazz Gift Shop",
    "wof:placetype":"venue"
},
  "geometry": {"coordinates":[-95.969672,36.022519],"type":"Point"}
}