{
  "type": "Feature",
  "properties": {
    "iso:country":"US",
    "sg:address":"4500 Memorial Cir",
    "sg:city":"Oklahoma City",
    "sg:classifiers":[
        {
            "category":"Home & Garden",
            "subcategory":"Furniture",
            "type":"Retail Goods"
        }
    ],
    "sg:phone":"+1 405 748 5511",
    "sg:postcode":"73142",
    "sg:province":"OK",
    "wof:name":"Interior Images Inc",
    "wof:placetype":"venue"
},
  "geometry": {"coordinates":[-97.603421,35.607054],"type":"Point"}
}