{
  "type": "Feature",
  "properties": {
    "iso:country":"US",
    "sg:address":"3024 SW 94th St",
    "sg:city":"Oklahoma City",
    "sg:classifiers":[
        {
            "category":"Wholesale",
            "subcategory":"Non-durable Goods",
            "type":"Manufacturing & Wholesale Goods"
        }
    ],
    "sg:phone":"+1 405 691 7833",
    "sg:postcode":"73159",
    "sg:province":"OK",
    "wof:name":"Cimarron Specialties",
    "wof:placetype":"venue"
},
  "geometry": {"coordinates":[-97.57071000000001,35.372214],"type":"Point"}
}