{
  "type": "Feature",
  "properties": {
    "iso:country":"US",
    "sg:address":"106 E Washington St",
    "sg:city":"Tecumseh",
    "sg:classifiers":[
        {
            "category":"Personal",
            "subcategory":"Beauty Salon",
            "type":"Services"
        }
    ],
    "sg:phone":"+1 405 598 2003",
    "sg:postcode":"74873",
    "sg:province":"OK",
    "wof:name":"AAA Beauty Shop",
    "wof:placetype":"venue"
},
  "geometry": {"coordinates":[-96.936718,35.257594],"type":"Point"}
}