{
  "type": "Feature",
  "properties": {
    "iso:country":"US",
    "sg:address":"3100 Medical Pkwy Ste 300",
    "sg:city":"Claremore",
    "sg:classifiers":[
        {
            "category":"Health Services",
            "subcategory":"Medical Lab",
            "type":"Services"
        }
    ],
    "sg:phone":"+1 918 744 3000",
    "sg:postcode":"74017",
    "sg:province":"OK",
    "sg:tags":[
        "examination",
        "insurance"
    ],
    "wof:name":"St John Breast Center",
    "wof:placetype":"venue"
},
  "geometry": {"coordinates":[-95.59892,36.337607],"type":"Point"}
}