{
  "type": "Feature",
  "properties": {
    "iso:country":"US",
    "sg:address":"2727 W Main St",
    "sg:city":"Oklahoma City",
    "sg:classifiers":[
        {
            "category":"Home & Garden",
            "subcategory":"Building Materials",
            "type":"Retail Goods"
        }
    ],
    "sg:phone":"+1 405 235 3325",
    "sg:postcode":"73107",
    "sg:province":"OK",
    "sg:tags":[
        "lumber"
    ],
    "wof:name":"Redwood Products Of Oklahoma",
    "wof:placetype":"venue"
},
  "geometry": {"coordinates":[-97.563064,35.468264],"type":"Point"}
}