{
  "type": "Feature",
  "properties": {
    "iso:country":"US",
    "sg:address":"205 N Filmore Ave",
    "sg:city":"Wagoner",
    "sg:classifiers":[
        {
            "category":"Real Estate",
            "subcategory":"Real Estate Operator",
            "type":"Services"
        }
    ],
    "sg:phone":"+1 918 485 1441",
    "sg:postcode":"74467",
    "sg:province":"OK",
    "sg:tags":[
        "apartment"
    ],
    "wof:name":"Cross Timber One & Two",
    "wof:placetype":"venue"
},
  "geometry": {"coordinates":[-95.384583,35.961972],"type":"Point"}
}