{
  "type": "Feature",
  "properties": {
    "iso:country":"US",
    "sg:address":"1319 Main Ave",
    "sg:city":"Woodward",
    "sg:classifiers":[
        {
            "category":"Building & Trades",
            "subcategory":"Construction",
            "type":"Services"
        }
    ],
    "sg:phone":"+1 580 254 5828",
    "sg:postcode":"73801",
    "sg:province":"OK",
    "sg:tags":[
        "concrete",
        "contractor"
    ],
    "wof:name":"B-E-W Construction Co",
    "wof:placetype":"venue"
},
  "geometry": {"coordinates":[-99.39689300000001,36.435882],"type":"Point"}
}