{
  "type": "Feature",
  "properties": {
    "addr:full":"1828 W Archer St Tulsa OK 74127",
    "addr:housenumber":"1828",
    "addr:postcode":"74127",
    "addr:street":"W Archer St",
    "iso:country":"US",
    "sg:address":"1828 W Archer St",
    "sg:city":"Tulsa",
    "sg:classifiers":[
        {
            "category":"Building & Trades",
            "subcategory":"Construction",
            "type":"Services"
        }
    ],
    "sg:phone":"+1 918 584 2817",
    "sg:postcode":"74127",
    "sg:province":"OK",
    "sg:tags":[
        "designer",
        "dealer",
        "pool",
        "swimming"
    ],
    "wof:name":"B J Pool Construction",
    "wof:placetype":"venue"
},
  "geometry": {"coordinates":[-96.014978,36.154376],"type":"Point"}
}