{
  "type": "Feature",
  "properties": {
    "iso:country":"US",
    "sg:address":"2500 Chandler Rd",
    "sg:city":"Muskogee",
    "sg:classifiers":[
        {
            "category":"Building & Trades",
            "subcategory":"Construction",
            "type":"Services"
        }
    ],
    "sg:phone":"+1 918 687 0456",
    "sg:postcode":"74403",
    "sg:province":"OK",
    "sg:tags":[
        "coping",
        "plastering",
        "tiling",
        "pool",
        "swimming"
    ],
    "wof:name":"Sandy's Pools & Spas",
    "wof:placetype":"venue"
},
  "geometry": {"coordinates":[-95.339203,35.740656],"type":"Point"}
}