{
  "type": "Feature",
  "properties": {
    "iso:country":"US",
    "sg:address":"4100 Will Rogers Pkwy",
    "sg:city":"Oklahoma City",
    "sg:classifiers":[
        {
            "category":"Building & Trades",
            "subcategory":"Construction",
            "type":"Services"
        }
    ],
    "sg:phone":"+1 405 840 9806",
    "sg:postcode":"73108",
    "sg:province":"OK",
    "sg:tags":[
        "elevator"
    ],
    "wof:name":"Thyssen Krupp Elevator",
    "wof:placetype":"venue"
},
  "geometry": {"coordinates":[-97.590856,35.45186],"type":"Point"}
}