{
  "type": "Feature",
  "properties": {
    "iso:country":"US",
    "sg:address":"400 4th St",
    "sg:city":"Pawnee",
    "sg:classifiers":[
        {
            "category":"Food & Beverages",
            "subcategory":"Groceries & Convenience Stores",
            "type":"Retail Goods"
        }
    ],
    "sg:phone":"+1 918 762 3145",
    "sg:postcode":"74058",
    "sg:province":"OK",
    "wof:name":"B J's Quik Stop",
    "wof:placetype":"venue"
},
  "geometry": {"coordinates":[-96.800457,36.340306],"type":"Point"}
}