{
  "type": "Feature",
  "properties": {
    "iso:country":"US",
    "sg:address":"9904 E 123rd St S",
    "sg:city":"Bixby",
    "sg:classifiers":[
        {
            "category":"Banks & Credit Unions",
            "subcategory":"Bank",
            "type":"Services"
        }
    ],
    "sg:phone":"+1 918 369 1676",
    "sg:postcode":"74008",
    "sg:province":"OK",
    "sg:tags":[
        "loan",
        "real estate"
    ],
    "wof:name":"Bankers Financial Mortgage Grp",
    "wof:placetype":"venue"
},
  "geometry": {"coordinates":[-95.866354,35.987008],"type":"Point"}
}