{
  "type": "Feature",
  "properties": {
    "iso:country":"US",
    "sg:address":"1912 W Main St",
    "sg:city":"Durant",
    "sg:classifiers":[
        {
            "category":"Organizations",
            "subcategory":"Community Association",
            "type":"Services"
        }
    ],
    "sg:phone":"+1 580 924 2167",
    "sg:postcode":"74701",
    "sg:province":"OK",
    "wof:name":"Kappa Kappa Iota",
    "wof:placetype":"venue"
},
  "geometry": {"coordinates":[-96.398459,33.99642],"type":"Point"}
}