{
  "type": "Feature",
  "properties": {
    "iso:country":"US",
    "sg:address":"309 6th St",
    "sg:city":"Medford",
    "sg:classifiers":[
        {
            "category":"Professional",
            "subcategory":"Accounting & Tax Preparation",
            "type":"Services"
        }
    ],
    "sg:phone":"+1 580 395 2138",
    "sg:postcode":"73759",
    "sg:province":"OK",
    "sg:tags":[
        "return"
    ],
    "wof:name":"Gilliland Tax Preparation",
    "wof:placetype":"venue"
},
  "geometry": {"coordinates":[-97.741351,36.810134],"type":"Point"}
}