{
  "type": "Feature",
  "properties": {
    "addr:full":"4335 SW 44th St Oklahoma City OK 73119",
    "addr:housenumber":"4335",
    "addr:postcode":"73119",
    "addr:street":"Sw 44Th St",
    "iso:country":"US",
    "sg:address":"4335 SW 44th St",
    "sg:city":"Oklahoma City",
    "sg:classifiers":[
        {
            "category":"Organizations",
            "subcategory":"Labor Organization",
            "type":"Services"
        }
    ],
    "sg:phone":"+1 405 682 4571",
    "sg:postcode":"73119",
    "sg:province":"OK",
    "wof:name":"Plumbers & Pipe Fitters",
    "wof:placetype":"venue"
},
  "geometry": {"coordinates":[-97.597353,35.426433],"type":"Point"}
}