{
  "type": "Feature",
  "properties": {
    "iso:country":"US",
    "sg:address":"441 N Wilson St",
    "sg:city":"Vinita",
    "sg:classifiers":[
        {
            "category":"Government",
            "subcategory":"Office",
            "type":"Public Place"
        }
    ],
    "sg:phone":"+1 918 256 5275",
    "sg:postcode":"74301",
    "sg:province":"OK",
    "wof:name":"Visual Service Ofc",
    "wof:placetype":"venue"
},
  "geometry": {"coordinates":[-95.15150199999999,36.643955],"type":"Point"}
}