{
  "type": "Feature",
  "properties": {
    "iso:country":"US",
    "sg:address":"106 N 4th St",
    "sg:city":"Sayre",
    "sg:classifiers":[
        {
            "category":"Professional",
            "subcategory":"Management & Consulting",
            "type":"Services"
        }
    ],
    "sg:phone":"+1 580 928 2514",
    "sg:postcode":"73662",
    "sg:province":"OK",
    "sg:tags":[
        "development",
        "economic",
        "agency"
    ],
    "wof:name":"Sayre Main Street Inc",
    "wof:placetype":"venue"
},
  "geometry": {"coordinates":[-99.63989,35.291781],"type":"Point"}
}