{
  "type": "Feature",
  "properties": {
    "iso:country":"US",
    "sg:address":"107 W Main St",
    "sg:city":"Tishomingo",
    "sg:classifiers":[
        {
            "category":"Personal",
            "type":"Services"
        }
    ],
    "sg:phone":"+1 580 371 2161",
    "sg:postcode":"73460",
    "sg:province":"OK",
    "sg:tags":[
        "department",
        "motor",
        "vehicle"
    ],
    "wof:name":"Tishomingo Tag Agency",
    "wof:placetype":"venue"
},
  "geometry": {"coordinates":[-96.678299,34.235213],"type":"Point"}
}