{
  "type": "Feature",
  "properties": {
    "iso:country":"US",
    "sg:address":"6501 E Apache St",
    "sg:city":"Tulsa",
    "sg:classifiers":[
        {
            "category":"Professional",
            "type":"Services"
        }
    ],
    "sg:phone":"+1 918 834 9500",
    "sg:postcode":"74115",
    "sg:province":"OK",
    "sg:tags":[
        "establishment"
    ],
    "wof:name":"Mach Aero Intl Corp",
    "wof:placetype":"venue"
},
  "geometry": {"coordinates":[-95.901702,36.191198],"type":"Point"}
}