{
  "type": "Feature",
  "properties": {
    "iso:country":"US",
    "sg:address":"305 Vista Grande",
    "sg:city":"Poteau",
    "sg:classifiers":[
        {
            "category":"Shopping",
            "subcategory":"Hobbies, Toys, & Games",
            "type":"Retail Goods"
        },
        {
            "category":"Shopping",
            "subcategory":"Crafts & Fabrics",
            "type":"Retail Goods"
        }
    ],
    "sg:phone":"+1 918 647 0300",
    "sg:postcode":"74953",
    "sg:province":"OK",
    "sg:tags":[
        "shop",
        "hobby",
        "model",
        "supply"
    ],
    "wof:name":"Hair S Cherokee Crafts",
    "wof:placetype":"venue"
},
  "geometry": {"coordinates":[-94.646701,35.089775],"type":"Point"}
}