{
  "type": "Feature",
  "properties": {
    "addr:full":"101 E Main St Shawnee OK 74801",
    "addr:housenumber":"101",
    "addr:postcode":"74801",
    "addr:street":"E Main St",
    "iso:country":"US",
    "sg:address":"101 E Main St",
    "sg:city":"Shawnee",
    "sg:classifiers":[
        {
            "category":"Recreation",
            "subcategory":"Amusement Park",
            "type":"Entertainment"
        }
    ],
    "sg:phone":"+1 405 275 7200",
    "sg:postcode":"74801",
    "sg:province":"OK",
    "wof:name":"Lazer World",
    "wof:placetype":"venue"
},
  "geometry": {"coordinates":[-96.92219299999999,35.327369],"type":"Point"}
}