{
  "type": "Feature",
  "properties": {
    "addr:full":"222 1st St Lahoma OK 73754",
    "addr:housenumber":"222",
    "addr:postcode":"73754",
    "addr:street":"1St St",
    "iso:country":"US",
    "sg:address":"222 1st St",
    "sg:city":"Lahoma",
    "sg:classifiers":[
        {
            "category":"Professional",
            "subcategory":"Management & Consulting",
            "type":"Services"
        }
    ],
    "sg:phone":"+1 580 796 2772",
    "sg:postcode":"73754",
    "sg:province":"OK",
    "wof:name":"Cooper Ems Inc",
    "wof:placetype":"venue"
},
  "geometry": {"coordinates":[-98.08695,36.384471],"type":"Point"}
}