{
  "type": "Feature",
  "properties": {
    "addr:full":"509 W 4th St Stroud OK 74079",
    "addr:housenumber":"509",
    "addr:postcode":"74079",
    "addr:street":"W 4Th St",
    "iso:country":"US",
    "sg:address":"509 W 4th St",
    "sg:city":"Stroud",
    "sg:classifiers":[
        {
            "category":"Personal",
            "subcategory":"Beauty Salon",
            "type":"Services"
        }
    ],
    "sg:phone":"+1 918 968 4475",
    "sg:postcode":"74079",
    "sg:province":"OK",
    "wof:name":"A Cut Above",
    "wof:placetype":"venue"
},
  "geometry": {"coordinates":[-96.65903,35.75019],"type":"Point"}
}