{
  "type": "Feature",
  "properties": {
    "iso:country":"US",
    "sg:address":"919 SW Sheridan Rd",
    "sg:city":"Lawton",
    "sg:classifiers":[
        {
            "category":"Retail",
            "subcategory":"Repair Shop",
            "type":"Services"
        }
    ],
    "sg:phone":"+1 580 248 6655",
    "sg:postcode":"73505",
    "sg:province":"OK",
    "wof:name":"Mobile Service T V",
    "wof:placetype":"venue"
},
  "geometry": {"coordinates":[-98.422431,34.59815],"type":"Point"}
}