{
  "type": "Feature",
  "properties": {
    "iso:country":"US",
    "sg:address":"49600 E 220 Rd",
    "sg:city":"Afton",
    "sg:classifiers":[
        {
            "category":"Retail",
            "subcategory":"Auto Repair",
            "type":"Services"
        }
    ],
    "sg:phone":"+1 918 257 5238",
    "sg:postcode":"74331",
    "sg:province":"OK",
    "sg:tags":[
        "wrecker"
    ],
    "wof:name":"G J Wrecker Svc",
    "wof:placetype":"venue"
},
  "geometry": {"coordinates":[-94.994759,36.699316],"type":"Point"}
}