{
  "type": "Feature",
  "properties": {
    "addr:full":"1036 W Broadway St Ardmore OK 73401",
    "addr:housenumber":"1036",
    "addr:postcode":"73401",
    "addr:street":"W Broadway St",
    "iso:country":"US",
    "sg:address":"1036 W Broadway St",
    "sg:city":"Ardmore",
    "sg:classifiers":[
        {
            "category":"Restaurant",
            "type":"Food & Drink"
        }
    ],
    "sg:menulink":"http://www.allmenus.com/ok/ardmore/180570-jack-in-the-box/menu/",
    "sg:phone":"+1 580 223 1886",
    "sg:postcode":"73401",
    "sg:province":"OK",
    "sg:tags":[
        "burger",
        "american"
    ],
    "wof:name":"Jack in the Box",
    "wof:placetype":"venue"
},
  "geometry": {"coordinates":[-97.142059,34.174468],"type":"Point"}
}