{
  "type": "Feature",
  "properties": {
    "iso:country":"US",
    "sg:address":"405 Cherry St",
    "sg:city":"Chelsea",
    "sg:classifiers":[
        {
            "category":"Retail",
            "subcategory":"Repair Shop",
            "type":"Services"
        }
    ],
    "sg:phone":"+1 918 789 3952",
    "sg:postcode":"74016",
    "sg:province":"OK",
    "wof:name":"R & M Jewelry & Gems",
    "wof:placetype":"venue"
},
  "geometry": {"coordinates":[-95.425719,36.53483],"type":"Point"}
}