{
  "type": "Feature",
  "properties": {
    "addr:full":"10938 N May Ave Oklahoma City OK 73120",
    "addr:housenumber":"10938",
    "addr:postcode":"73120",
    "addr:street":"N May Ave",
    "iso:country":"US",
    "sg:address":"10938 N May Ave",
    "sg:city":"Oklahoma City",
    "sg:classifiers":[
        {
            "category":"Personal",
            "subcategory":"Beauty Salon",
            "type":"Services"
        }
    ],
    "sg:phone":"+1 405 755 7350",
    "sg:postcode":"73120",
    "sg:province":"OK",
    "wof:name":"Salon On The Plaza",
    "wof:placetype":"venue"
},
  "geometry": {"coordinates":[-97.56711300000001,35.58067],"type":"Point"}
}