{
  "type": "Feature",
  "properties": {
    "iso:country":"US",
    "sg:address":"1 Hospital Dr",
    "sg:city":"Madill",
    "sg:classifiers":[
        {
            "category":"Health Services",
            "subcategory":"Clinic",
            "type":"Services"
        }
    ],
    "sg:phone":"+1 580 795 7351",
    "sg:postcode":"73446",
    "sg:province":"OK",
    "sg:tags":[
        "home"
    ],
    "wof:name":"Marshall Memorial Hospital",
    "wof:placetype":"venue"
},
  "geometry": {"coordinates":[-96.778509,34.080555],"type":"Point"}
}