{
  "type": "Feature",
  "properties": {
    "iso:country":"US",
    "sg:address":"121 S Pine St",
    "sg:city":"Nowata",
    "sg:classifiers":[
        {
            "category":"Museum",
            "type":"Entertainment"
        }
    ],
    "sg:phone":"+1 918 273 1191",
    "sg:postcode":"74048",
    "sg:province":"OK",
    "wof:name":"Nowata County Historical",
    "wof:placetype":"venue"
},
  "geometry": {"coordinates":[-95.639162,36.699912],"type":"Point"}
}