{
  "type": "Feature",
  "properties": {
    "addr:full":"2335 NW 58th St Oklahoma City OK 73112",
    "addr:housenumber":"2335",
    "addr:postcode":"73112",
    "addr:street":"Nw 58Th St",
    "iso:country":"US",
    "sg:address":"2335 NW 58th St",
    "sg:city":"Oklahoma City",
    "sg:classifiers":[
        {
            "category":"Insurance",
            "subcategory":"Insurance Agent",
            "type":"Services"
        }
    ],
    "sg:phone":"+1 405 751 0254",
    "sg:postcode":"73112",
    "sg:province":"OK",
    "wof:name":"Donley Insurance Inc",
    "wof:placetype":"venue"
},
  "geometry": {"coordinates":[-97.55129599999999,35.531352],"type":"Point"}
}