{
  "type": "Feature",
  "properties": {
    "iso:country":"US",
    "sg:address":"4312 SE 29th St",
    "sg:city":"Oklahoma City",
    "sg:classifiers":[
        {
            "category":"Autos & Motor Vehicles",
            "subcategory":"Motorcycle Sales",
            "type":"Retail Goods"
        }
    ],
    "sg:phone":"+1 405 677 3600",
    "sg:postcode":"73115",
    "sg:province":"OK",
    "wof:name":"Cycle 1",
    "wof:placetype":"venue"
},
  "geometry": {"coordinates":[-97.440434,35.435149],"type":"Point"}
}