{
  "type": "Feature",
  "properties": {
    "iso:country":"US",
    "sg:address":"4902 E 121st St S",
    "sg:city":"Bixby",
    "sg:classifiers":[
        {
            "category":"Wholesale",
            "subcategory":"Machinery & Supplies",
            "type":"Manufacturing & Wholesale Goods"
        },
        {
            "category":"Wholesale",
            "subcategory":"Plants",
            "type":"Manufacturing & Wholesale Goods"
        }
    ],
    "sg:phone":"+1 918 369 2091",
    "sg:postcode":"74008",
    "sg:province":"OK",
    "sg:tags":[
        "nursery",
        "tree"
    ],
    "sg:website":"www.johndeerelandscapes.com",
    "wof:name":"John Deere Landscapes Inc",
    "wof:placetype":"venue"
},
  "geometry": {"coordinates":[-95.91869199999999,35.988261],"type":"Point"}
}