{
  "type": "Feature",
  "properties": {
    "iso:country":"US",
    "sg:address":"5243 Lakeview Dr",
    "sg:city":"Harrah",
    "sg:classifiers":[
        {
            "category":"Building & Trades",
            "subcategory":"Construction",
            "type":"Services"
        }
    ],
    "sg:phone":"+1 405 454 0482",
    "sg:postcode":"73045",
    "sg:province":"OK",
    "sg:tags":[
        "excavation",
        "contractor"
    ],
    "wof:name":"Holland Backhoe Constuction",
    "wof:placetype":"venue"
},
  "geometry": {"coordinates":[-97.187178,35.524929],"type":"Point"}
}