{
  "type": "Feature",
  "properties": {
    "addr:full":"112 Val Verde St Altus OK 73521",
    "addr:housenumber":"112",
    "addr:postcode":"73521",
    "addr:street":"Val Verde St",
    "iso:country":"US",
    "sg:address":"112 Val Verde St",
    "sg:city":"Altus",
    "sg:classifiers":[
        {
            "category":"Health Services",
            "subcategory":"Optometrist",
            "type":"Services"
        }
    ],
    "sg:phone":"+1 580 482 0051",
    "sg:postcode":"73521",
    "sg:province":"OK",
    "wof:name":"Steven A Gifford",
    "wof:placetype":"venue"
},
  "geometry": {"coordinates":[-99.33384599999999,34.661898],"type":"Point"}
}