{
  "type": "Feature",
  "properties": {
    "iso:country":"US",
    "sg:address":"9347 E 11th St S",
    "sg:city":"Tulsa",
    "sg:classifiers":[
        {
            "category":"Recreation",
            "type":"Entertainment"
        },
        {
            "category":"Bars & Pubs",
            "type":"Food & Drink"
        }
    ],
    "sg:phone":"+1 918 835 4616",
    "sg:postcode":"74112",
    "sg:province":"OK",
    "sg:tags":[
        "club",
        "membership"
    ],
    "wof:name":"Shep's Lounge",
    "wof:placetype":"venue"
},
  "geometry": {"coordinates":[-95.87233000000001,36.148079],"type":"Point"}
}