{
  "type": "Feature",
  "properties": {
    "iso:country":"US",
    "sg:address":"465 State Hwy 152",
    "sg:city":"Mustang",
    "sg:classifiers":[
        {
            "category":"Government",
            "subcategory":"Office",
            "type":"Public Place"
        }
    ],
    "sg:phone":"+1 405 376 9365",
    "sg:postcode":"73064",
    "sg:province":"OK",
    "sg:tags":[
        "village"
    ],
    "wof:name":"Rescue Dept",
    "wof:placetype":"venue"
},
  "geometry": {"coordinates":[-97.716764,35.39167],"type":"Point"}
}