{
  "type": "Feature",
  "properties": {
    "addr:full":"400 S Mission St Sapulpa OK 74066",
    "addr:housenumber":"400",
    "addr:postcode":"74066",
    "addr:street":"S;St",
    "iso:country":"US",
    "sg:address":"400 S Mission St",
    "sg:city":"Sapulpa",
    "sg:classifiers":[
        {
            "category":"Health Services",
            "subcategory":"Doctor",
            "type":"Services"
        }
    ],
    "sg:phone":"+1 918 224 1881",
    "sg:postcode":"74066",
    "sg:province":"OK",
    "sg:tags":[
        "clinic"
    ],
    "wof:name":"Metro Tulsa Foot & Ankle",
    "wof:placetype":"venue"
},
  "geometry": {"coordinates":[-96.09877899999999,35.993931],"type":"Point"}
}