{
  "type": "Feature",
  "properties": {
    "iso:country":"US",
    "sg:address":"5255 Nowata Rd",
    "sg:city":"Bartlesville",
    "sg:classifiers":[
        {
            "category":"Real Estate",
            "subcategory":"Real Estate Operator",
            "type":"Services"
        }
    ],
    "sg:phone":"+1 918 333 8900",
    "sg:postcode":"74006",
    "sg:province":"OK",
    "sg:tags":[
        "apartment"
    ],
    "wof:name":"Forest Creek Condos",
    "wof:placetype":"venue"
},
  "geometry": {"coordinates":[-95.918953,36.727994],"type":"Point"}
}