{
  "type": "Feature",
  "properties": {
    "addr:full":"318 W Springer Ave Bache OK 74501",
    "addr:housenumber":"318",
    "addr:postcode":"74501",
    "addr:street":"W Springer Ave",
    "iso:country":"US",
    "sg:address":"318 W Springer Ave",
    "sg:city":"Bache",
    "sg:classifiers":[
        {
            "category":"Building & Trades",
            "subcategory":"Construction",
            "type":"Services"
        }
    ],
    "sg:phone":"+1 918 423 4555",
    "sg:postcode":"74501",
    "sg:province":"OK",
    "sg:tags":[
        "downspouts",
        "gutter",
        "contractor"
    ],
    "wof:name":"A A Seamless Guttering",
    "wof:placetype":"venue"
},
  "geometry": {"coordinates":[-95.77056399999999,34.955358],"type":"Point"}
}