{
  "type": "Feature",
  "properties": {
    "iso:country":"US",
    "sg:address":"408 E Charles Ave",
    "sg:city":"Pauls Valley",
    "sg:classifiers":[
        {
            "category":"Social Services",
            "subcategory":"Child Care",
            "type":"Services"
        }
    ],
    "sg:phone":"+1 405 238 7520",
    "sg:postcode":"73075",
    "sg:province":"OK",
    "sg:tags":[
        "day"
    ],
    "wof:name":"Sallys Kinder Care",
    "wof:placetype":"venue"
},
  "geometry": {"coordinates":[-97.215283,34.741581],"type":"Point"}
}