{
  "type": "Feature",
  "properties": {
    "addr:full":"235 E Main St Healdton OK 73438",
    "addr:housenumber":"235",
    "addr:postcode":"73438",
    "addr:street":"E Main St",
    "iso:country":"US",
    "sg:address":"235 E Main St",
    "sg:city":"Healdton",
    "sg:classifiers":[
        {
            "category":"Food & Beverages",
            "subcategory":"Groceries & Convenience Stores",
            "type":"Retail Goods"
        }
    ],
    "sg:phone":"+1 580 229 2645",
    "sg:postcode":"73438",
    "sg:province":"OK",
    "wof:name":"Mom's Minit Mart",
    "wof:placetype":"venue"
},
  "geometry": {"coordinates":[-97.482215,34.23306],"type":"Point"}
}