{
  "type": "Feature",
  "properties": {
    "addr:full":"28267 E 127th St S Coweta OK 74429",
    "addr:housenumber":"28267",
    "addr:postcode":"74429",
    "addr:street":"E 127Th St S",
    "iso:country":"US",
    "sg:address":"28267 E 127th St S",
    "sg:city":"Coweta",
    "sg:classifiers":[
        {
            "category":"Shopping",
            "subcategory":"Hobbies, Toys, & Games",
            "type":"Retail Goods"
        },
        {
            "category":"Wholesale",
            "subcategory":"Non-durable Goods",
            "type":"Manufacturing & Wholesale Goods"
        }
    ],
    "sg:phone":"+1 918 486 8000",
    "sg:postcode":"74429",
    "sg:province":"OK",
    "sg:tags":[
        "advertising"
    ],
    "wof:name":"Chitty Chat Creations",
    "wof:placetype":"venue"
},
  "geometry": {"coordinates":[-95.660433,35.979034],"type":"Point"}
}