{
  "type": "Feature",
  "properties": {
    "iso:country":"US",
    "sg:address":"3528 W Reno Ave",
    "sg:city":"Oklahoma City",
    "sg:classifiers":[
        {
            "category":"Organizations",
            "subcategory":"Labor Organization",
            "type":"Services"
        }
    ],
    "sg:phone":"+1 405 947 2333",
    "sg:postcode":"73107",
    "sg:province":"OK",
    "wof:name":"Teamsters Local Union",
    "wof:placetype":"venue"
},
  "geometry": {"coordinates":[-97.581297,35.464099],"type":"Point"}
}