{
  "type": "Feature",
  "properties": {
    "iso:country":"US",
    "sg:address":"112 S Grand Ave",
    "sg:city":"Cherokee",
    "sg:classifiers":[
        {
            "category":"Restaurant",
            "type":"Food & Drink"
        }
    ],
    "sg:phone":"+1 580 596 3616",
    "sg:postcode":"73728",
    "sg:province":"OK",
    "sg:tags":[
        "eating"
    ],
    "wof:name":"Timber Dipper",
    "wof:placetype":"venue"
},
  "geometry": {"coordinates":[-98.357014,36.757646],"type":"Point"}
}