{
  "type": "Feature",
  "properties": {
    "iso:country":"US",
    "sg:address":"124 E Main St",
    "sg:city":"Wilburton",
    "sg:classifiers":[
        {
            "category":"Shopping",
            "subcategory":"Bicycles & Sporting Goods",
            "type":"Retail Goods"
        }
    ],
    "sg:phone":"+1 918 465 3130",
    "sg:postcode":"74578",
    "sg:province":"OK",
    "sg:tags":[
        "tack"
    ],
    "wof:name":"Wayne Lucas Saddlery",
    "wof:placetype":"venue"
},
  "geometry": {"coordinates":[-95.308101,34.918716],"type":"Point"}
}