{
  "type": "Feature",
  "properties": {
    "addr:full":"14002 N Yorktown Ave Skiatook OK 74070",
    "addr:housenumber":"14002",
    "addr:postcode":"74070",
    "addr:street":"N Yorktown Ave",
    "iso:country":"US",
    "sg:address":"14002 N Yorktown Ave",
    "sg:city":"Skiatook",
    "sg:classifiers":[
        {
            "category":"Building & Trades",
            "subcategory":"Construction",
            "type":"Services"
        }
    ],
    "sg:phone":"+1 918 396 2595",
    "sg:postcode":"74070",
    "sg:province":"OK",
    "sg:tags":[
        "general",
        "contractor"
    ],
    "wof:name":"Running Horse Construction",
    "wof:placetype":"venue"
},
  "geometry": {"coordinates":[-95.960476,36.356572],"type":"Point"}
}