{
  "type": "Feature",
  "properties": {
    "iso:country":"US",
    "sg:address":"7600 SW 15th St",
    "sg:city":"Oklahoma City",
    "sg:classifiers":[
        {
            "category":"Utilities",
            "subcategory":"Refuse",
            "type":"Services"
        }
    ],
    "sg:phone":"+1 405 745 3002",
    "sg:postcode":"73128",
    "sg:province":"OK",
    "sg:tags":[
        "solid",
        "landfill",
        "waste",
        "system"
    ],
    "wof:name":"Waste Connections Inc",
    "wof:placetype":"venue"
},
  "geometry": {"coordinates":[-97.652512,35.449664],"type":"Point"}
}