{
  "type": "Feature",
  "properties": {
    "iso:country":"US",
    "sg:address":"3340 NW 16th St",
    "sg:city":"Oklahoma City",
    "sg:classifiers":[
        {
            "category":"Organizations",
            "subcategory":"Religious Organization",
            "type":"Services"
        }
    ],
    "sg:phone":"+1 405 943 4425",
    "sg:postcode":"73107",
    "sg:province":"OK",
    "wof:name":"New Hope Community Church Inc",
    "wof:placetype":"venue"
},
  "geometry": {"coordinates":[-97.576101,35.485914],"type":"Point"}
}