{
  "type": "Feature",
  "properties": {
    "iso:country":"US",
    "sg:address":"1303 S Sheridan Rd",
    "sg:city":"Tulsa",
    "sg:classifiers":[
        {
            "category":"Freight",
            "type":"Transportation"
        }
    ],
    "sg:phone":"+1 918 834 3781",
    "sg:postcode":"74112",
    "sg:province":"OK",
    "sg:tags":[
        "special"
    ],
    "wof:name":"D M R V Storage Co",
    "wof:placetype":"venue"
},
  "geometry": {"coordinates":[-95.904484,36.143445],"type":"Point"}
}