{
  "type": "Feature",
  "properties": {
    "addr:full":"309 W Cedar Binger OK 73009",
    "addr:housenumber":"309",
    "addr:postcode":"73009",
    "addr:street":"W Cedar",
    "iso:country":"US",
    "sg:address":"309 W Cedar",
    "sg:city":"Binger",
    "sg:classifiers":[
        {
            "category":"Retail",
            "subcategory":"Auto Repair",
            "type":"Services"
        }
    ],
    "sg:phone":"+1 405 656 9011",
    "sg:postcode":"73009",
    "sg:province":"OK",
    "sg:tags":[
        "glass",
        "coating",
        "tinting"
    ],
    "wof:name":"Precision Window Tinting",
    "wof:placetype":"venue"
},
  "geometry": {"coordinates":[-98.346194,35.306734],"type":"Point"}
}