{
  "type": "Feature",
  "properties": {
    "addr:full":"1609 W Plato Rd Duncan OK 73533",
    "addr:housenumber":"1609",
    "addr:postcode":"73533",
    "addr:street":"W Plato Rd",
    "iso:country":"US",
    "sg:address":"1609 W Plato Rd",
    "sg:city":"Duncan",
    "sg:classifiers":[
        {
            "category":"Professional",
            "subcategory":"Art Services",
            "type":"Services"
        }
    ],
    "sg:phone":"+1 580 255 4717",
    "sg:postcode":"73533",
    "sg:province":"OK",
    "sg:tags":[
        "commercial",
        "design"
    ],
    "wof:name":"B Z Graphics",
    "wof:placetype":"venue"
},
  "geometry": {"coordinates":[-97.969067,34.536242],"type":"Point"}
}