{
  "type": "Feature",
  "properties": {
    "iso:country":"US",
    "sg:address":"3909 N College Ave",
    "sg:city":"Bethany",
    "sg:classifiers":[
        {
            "category":"Shopping",
            "subcategory":"Used Merchandise",
            "type":"Retail Goods"
        }
    ],
    "sg:phone":"+1 405 640 9246",
    "sg:postcode":"73008",
    "sg:province":"OK",
    "sg:tags":[
        "vintage",
        "clothing",
        "period"
    ],
    "wof:name":"Jean's Vintage Clothing/Jewlry",
    "wof:placetype":"venue"
},
  "geometry": {"coordinates":[-97.629203,35.510702],"type":"Point"}
}