{
  "type": "Feature",
  "properties": {
    "addr:full":"213 N Grand Ave Cherokee OK 73728",
    "addr:housenumber":"213",
    "addr:postcode":"73728",
    "addr:street":"N Grand Ave",
    "iso:country":"US",
    "sg:address":"213 N Grand Ave",
    "sg:city":"Cherokee",
    "sg:classifiers":[
        {
            "category":"Manufacturing",
            "subcategory":"Chemicals & Compounds",
            "type":"Manufacturing & Wholesale Goods"
        }
    ],
    "sg:phone":"+1 580 596 3440",
    "sg:postcode":"73728",
    "sg:province":"OK",
    "sg:tags":[
        "fertilizer"
    ],
    "wof:name":"Wilber Fertilizer Svc",
    "wof:placetype":"venue"
},
  "geometry": {"coordinates":[-98.35718,36.759064],"type":"Point"}
}