{
  "type": "Feature",
  "properties": {
    "addr:full":"3601 S Broadway Edmond OK 73013",
    "addr:housenumber":"3601",
    "addr:postcode":"73013",
    "addr:street":"S Broadway",
    "iso:country":"US",
    "sg:address":"3601 S Broadway",
    "sg:city":"Edmond",
    "sg:classifiers":[
        {
            "category":"Personal",
            "subcategory":"Beauty Salon",
            "type":"Services"
        }
    ],
    "sg:phone":"+1 405 478 5537",
    "sg:postcode":"73013",
    "sg:province":"OK",
    "wof:name":"Duncan Brothers Salon",
    "wof:placetype":"venue"
},
  "geometry": {"coordinates":[-97.488727,35.620355],"type":"Point"}
}