{
  "type": "Feature",
  "properties": {
    "addr:full":"101 Mid-America Blvd Midwest City OK 73110",
    "addr:housenumber":"101",
    "addr:postcode":"73110",
    "addr:street":"Mid-America Blvd",
    "iso:country":"US",
    "sg:address":"101 Mid-America Blvd",
    "sg:city":"Midwest City",
    "sg:classifiers":[
        {
            "category":"Shopping",
            "subcategory":"Pharmacy",
            "type":"Retail Goods"
        }
    ],
    "sg:phone":"+1 405 732 2229",
    "sg:postcode":"73110",
    "sg:province":"OK",
    "wof:name":"Conrad-Marr Drug Inc",
    "wof:placetype":"venue"
},
  "geometry": {"coordinates":[-97.400144,35.440954],"type":"Point"}
}