{
  "type": "Feature",
  "properties": {
    "iso:country":"US",
    "sg:address":"1908 S Florence Ave",
    "sg:city":"Tulsa",
    "sg:classifiers":[
        {
            "category":"Shopping",
            "subcategory":"Musical Instruments",
            "type":"Retail Goods"
        }
    ],
    "sg:phone":"+1 918 744 8928",
    "sg:postcode":"74104",
    "sg:province":"OK",
    "wof:name":"Dulcimer House",
    "wof:placetype":"venue"
},
  "geometry": {"coordinates":[-95.944901,36.133343],"type":"Point"}
}