{
  "type": "Feature",
  "properties": {
    "addr:full":"8143 E Reno Ave Oklahoma City OK 73110",
    "addr:housenumber":"8143",
    "addr:postcode":"73110",
    "addr:street":"E Reno Ave",
    "iso:country":"US",
    "sg:address":"8143 E Reno Ave",
    "sg:city":"Oklahoma City",
    "sg:classifiers":[
        {
            "category":"Education",
            "subcategory":"Special Training",
            "type":"Public Place"
        }
    ],
    "sg:phone":"+1 405 732 2737",
    "sg:postcode":"73110",
    "sg:province":"OK",
    "sg:tags":[
        "school",
        "educational"
    ],
    "wof:name":"Literacy Link",
    "wof:placetype":"venue"
},
  "geometry": {"coordinates":[-97.386538,35.464122],"type":"Point"}
}