{
  "type": "Feature",
  "properties": {
    "addr:full":"18 E 22nd St Tulsa OK 74114",
    "addr:housenumber":"18",
    "addr:postcode":"74114",
    "addr:street":"E 22Nd St",
    "iso:country":"US",
    "sg:address":"18 E 22nd St",
    "sg:city":"Tulsa",
    "sg:classifiers":[
        {
            "category":"Professional",
            "type":"Services"
        }
    ],
    "sg:phone":"+1 918 585 1940",
    "sg:postcode":"74114",
    "sg:province":"OK",
    "sg:tags":[
        "establishment"
    ],
    "wof:name":"Jamesblake",
    "wof:placetype":"venue"
},
  "geometry": {"coordinates":[-95.986158,36.13229],"type":"Point"}
}