{
  "type": "Feature",
  "properties": {
    "iso:country":"US",
    "sg:address":"3420 N Markwell Ave",
    "sg:city":"Bethany",
    "sg:classifiers":[
        {
            "category":"Freight",
            "type":"Transportation"
        }
    ],
    "sg:phone":"+1 405 787 9584",
    "sg:postcode":"73008",
    "sg:province":"OK",
    "sg:tags":[
        "operator",
        "local",
        "trucking"
    ],
    "wof:name":"Direct Delivery LLC",
    "wof:placetype":"venue"
},
  "geometry": {"coordinates":[-97.659132,35.507572],"type":"Point"}
}