{
  "type": "Feature",
  "properties": {
    "iso:country":"US",
    "sg:address":"1115 N 31st St",
    "sg:city":"Broken Arrow",
    "sg:classifiers":[
        {
            "category":"Building & Trades",
            "subcategory":"Construction",
            "type":"Services"
        }
    ],
    "sg:phone":"+1 918 355 2048",
    "sg:postcode":"74014",
    "sg:province":"OK",
    "sg:tags":[
        "contractor"
    ],
    "wof:name":"A & R Masonry",
    "wof:placetype":"venue"
},
  "geometry": {"coordinates":[-95.75311,36.062126],"type":"Point"}
}