{
  "type": "Feature",
  "properties": {
    "iso:country":"US",
    "sg:address":"8783 S Lewis Ave",
    "sg:city":"Tulsa",
    "sg:classifiers":[
        {
            "category":"Wholesale",
            "subcategory":"Hardware",
            "type":"Manufacturing & Wholesale Goods"
        }
    ],
    "sg:phone":"+1 918 299 0794",
    "sg:postcode":"74137",
    "sg:province":"OK",
    "sg:tags":[
        "plumbing",
        "fixture",
        "supply"
    ],
    "wof:name":"Locke Supply Co",
    "wof:placetype":"venue"
},
  "geometry": {"coordinates":[-95.954507,36.03617],"type":"Point"}
}