{
  "type": "Feature",
  "properties": {
    "addr:full":"2001 S Hwy 69 Wagoner OK 74467",
    "addr:housenumber":"2001",
    "addr:postcode":"74467",
    "addr:street":"S Hwy 69",
    "iso:country":"US",
    "sg:address":"2001 S Hwy 69",
    "sg:city":"Wagoner",
    "sg:classifiers":[
        {
            "category":"Shopping",
            "subcategory":"Used Merchandise",
            "type":"Retail Goods"
        }
    ],
    "sg:phone":"+1 918 485 7670",
    "sg:postcode":"74467",
    "sg:province":"OK",
    "sg:tags":[
        "antique"
    ],
    "wof:name":"Big Red Barn",
    "wof:placetype":"venue"
},
  "geometry": {"coordinates":[-95.39518,35.939059],"type":"Point"}
}