{
  "type": "Feature",
  "properties": {
    "iso:country":"US",
    "sg:address":"12321 E Pine St",
    "sg:city":"Tulsa",
    "sg:classifiers":[
        {
            "category":"Wholesale",
            "subcategory":"Machinery & Supplies",
            "type":"Manufacturing & Wholesale Goods"
        }
    ],
    "sg:phone":"+1 918 438 1700",
    "sg:postcode":"74116",
    "sg:province":"OK",
    "sg:tags":[
        "industrial",
        "equipment",
        "used",
        "machinery-new",
        "supplies-wholesale"
    ],
    "sg:website":"http://www.kirby-smith.com",
    "wof:name":"Kirby-Smith Machinery Inc",
    "wof:placetype":"venue"
},
  "geometry": {"coordinates":[-95.838829,36.177052],"type":"Point"}
}