{
  "type": "Feature",
  "properties": {
    "addr:full":"627 S Park Dr Broken Bow OK 74728",
    "addr:housenumber":"627",
    "addr:postcode":"74728",
    "addr:street":"S Park Dr",
    "iso:country":"US",
    "sg:address":"627 S Park Dr",
    "sg:city":"Broken Bow",
    "sg:classifiers":[
        {
            "category":"Professional",
            "type":"Services"
        }
    ],
    "sg:phone":"+1 580 584 9181",
    "sg:postcode":"74728",
    "sg:province":"OK",
    "sg:tags":[
        "establishment"
    ],
    "wof:name":"Style Trends",
    "wof:placetype":"venue"
},
  "geometry": {"coordinates":[-94.73947800000001,34.011618],"type":"Point"}
}