{
  "type": "Feature",
  "properties": {
    "iso:country":"US",
    "sg:address":"9815 E 520 Rd",
    "sg:city":"Claremore",
    "sg:classifiers":[
        {
            "category":"Shopping",
            "type":"Retail Goods"
        }
    ],
    "sg:phone":"+1 918 341 6200",
    "sg:postcode":"74019",
    "sg:province":"OK",
    "sg:tags":[
        "pet",
        "shop"
    ],
    "wof:name":"Lees Pet & Garden Supply",
    "wof:placetype":"venue"
},
  "geometry": {"coordinates":[-95.65702899999999,36.263984],"type":"Point"}
}