{
  "type": "Feature",
  "properties": {
    "iso:country":"US",
    "sg:address":"2221 S Central Ave",
    "sg:city":"Oklahoma City",
    "sg:classifiers":[
        {
            "category":"Restaurant",
            "type":"Food & Drink"
        }
    ],
    "sg:phone":"+1 405 235 4999",
    "sg:postcode":"73129",
    "sg:province":"OK",
    "sg:tags":[
        "eating"
    ],
    "wof:name":"Taco Max",
    "wof:placetype":"venue"
},
  "geometry": {"coordinates":[-97.506899,35.443063],"type":"Point"}
}