{
  "type": "Feature",
  "properties": {
    "addr:full":"224 E St SW Miami OK 74354",
    "addr:housenumber":"224",
    "addr:postcode":"74354",
    "addr:street":"E St Sw",
    "iso:country":"US",
    "sg:address":"224 E St SW",
    "sg:city":"Miami",
    "sg:classifiers":[
        {
            "category":"Shopping",
            "subcategory":"Crafts & Fabrics",
            "type":"Retail Goods"
        }
    ],
    "sg:phone":"+1 918 542 7896",
    "sg:postcode":"74354",
    "sg:province":"OK",
    "sg:tags":[
        "material",
        "quilting",
        "sewing",
        "supply"
    ],
    "wof:name":"Seay's Quilt Shop",
    "wof:placetype":"venue"
},
  "geometry": {"coordinates":[-94.883123,36.871859],"type":"Point"}
}