{
  "type": "Feature",
  "properties": {
    "iso:country":"US",
    "sg:address":"36250 S 4220 Rd",
    "sg:city":"Inola",
    "sg:classifiers":[
        {
            "category":"Building & Trades",
            "subcategory":"Construction",
            "type":"Services"
        }
    ],
    "sg:phone":"+1 918 543 8250",
    "sg:postcode":"74036",
    "sg:province":"OK",
    "sg:tags":[
        "concrete",
        "pumping"
    ],
    "wof:name":"Williams Concrete Pumping Inc",
    "wof:placetype":"venue"
},
  "geometry": {"coordinates":[-95.493771,36.08615],"type":"Point"}
}