{
  "type": "Feature",
  "properties": {
    "iso:country":"US",
    "sg:address":"12307 E 96th St N",
    "sg:city":"Owasso",
    "sg:classifiers":[
        {
            "category":"Wholesale",
            "subcategory":"Apparel",
            "type":"Manufacturing & Wholesale Goods"
        },
        {
            "category":"Shopping",
            "subcategory":"Clothing, Apparel, & Fashions",
            "type":"Retail Goods"
        }
    ],
    "sg:phone":"+1 918 272 8965",
    "sg:postcode":"74055",
    "sg:province":"OK",
    "sg:tags":[
        "infant",
        "wear"
    ],
    "wof:name":"Children's Orchard",
    "wof:placetype":"venue"
},
  "geometry": {"coordinates":[-95.83788,36.293084],"type":"Point"}
}