{
  "type": "Feature",
  "properties": {
    "iso:country":"US",
    "sg:address":"1613 Pecan Ave",
    "sg:city":"Norman",
    "sg:classifiers":[
        {
            "category":"Real Estate",
            "subcategory":"Real Estate Agent",
            "type":"Services"
        }
    ],
    "sg:phone":"+1 405 360 3541",
    "sg:postcode":"73072",
    "sg:province":"OK",
    "wof:name":"Rural Properties Inc",
    "wof:placetype":"venue"
},
  "geometry": {"coordinates":[-97.472746,35.198676],"type":"Point"}
}