{
  "type": "Feature",
  "properties": {
    "iso:country":"US",
    "sg:address":"1413 24th Ave SW",
    "sg:city":"Norman",
    "sg:classifiers":[
        {
            "category":"Taxi",
            "type":"Transportation"
        }
    ],
    "sg:phone":"+1 405 329 3335",
    "sg:postcode":"73072",
    "sg:province":"OK",
    "sg:tags":[
        "taxicab"
    ],
    "wof:name":"Norman Checker Cab",
    "wof:placetype":"venue"
},
  "geometry": {"coordinates":[-97.476576,35.201785],"type":"Point"}
}