{
  "type": "Feature",
  "properties": {
    "iso:country":"US",
    "sg:address":"113 S Bickford Ave",
    "sg:city":"El Reno",
    "sg:classifiers":[
        {
            "category":"Retail",
            "subcategory":"Portrait Studio",
            "type":"Services"
        }
    ],
    "sg:phone":"+1 405 262 3975",
    "sg:postcode":"73036",
    "sg:province":"OK",
    "sg:tags":[
        "photographer",
        "novelty",
        "gift",
        "photo"
    ],
    "wof:name":"Nance Larry Photography",
    "wof:placetype":"venue"
},
  "geometry": {"coordinates":[-97.953719,35.533072],"type":"Point"}
}