{
  "type": "Feature",
  "properties": {
    "iso:country":"US",
    "sg:address":"2700 E Simmons Rd",
    "sg:city":"Edmond",
    "sg:classifiers":[
        {
            "category":"Building & Trades",
            "subcategory":"Plumbing",
            "type":"Services"
        }
    ],
    "sg:phone":"+1 405 348 5856",
    "sg:postcode":"73034",
    "sg:province":"OK",
    "sg:tags":[
        "plumbing",
        "contractor"
    ],
    "wof:name":"Elder Plumbing Heating & Air",
    "wof:placetype":"venue"
},
  "geometry": {"coordinates":[-97.39316700000001,35.739805],"type":"Point"}
}