{
  "type": "Feature",
  "properties": {
    "addr:full":"639 NW 7th St Moore OK 73160",
    "addr:housenumber":"639",
    "addr:postcode":"73160",
    "addr:street":"Nw 7Th St",
    "iso:country":"US",
    "sg:address":"639 NW 7th St",
    "sg:city":"Moore",
    "sg:classifiers":[
        {
            "category":"Personal",
            "subcategory":"Beauty Salon",
            "type":"Services"
        }
    ],
    "sg:phone":"+1 405 799 2662",
    "sg:postcode":"73160",
    "sg:province":"OK",
    "wof:name":"Outlook Salon",
    "wof:placetype":"venue"
},
  "geometry": {"coordinates":[-97.496216,35.345441],"type":"Point"}
}