{
  "type": "Feature",
  "properties": {
    "addr:full":"3004 Williams Ave Woodward OK 73801",
    "addr:housenumber":"3004",
    "addr:postcode":"73801",
    "addr:street":"Williams Ave",
    "iso:country":"US",
    "sg:address":"3004 Williams Ave",
    "sg:city":"Woodward",
    "sg:classifiers":[
        {
            "category":"Cinema",
            "subcategory":"Movie Rental",
            "type":"Entertainment"
        }
    ],
    "sg:phone":"+1 580 256 1651",
    "sg:postcode":"73801",
    "sg:province":"OK",
    "sg:tags":[
        "leasing",
        "video",
        "disc",
        "tape"
    ],
    "wof:name":"Movie Gallery",
    "wof:placetype":"venue"
},
  "geometry": {"coordinates":[-99.383993,36.416811],"type":"Point"}
}