{
  "type": "Feature",
  "properties": {
    "iso:country":"US",
    "sg:address":"5601 NW 72nd St",
    "sg:city":"Oklahoma City",
    "sg:classifiers":[
        {
            "category":"Health Services",
            "subcategory":"Clinic",
            "type":"Services"
        }
    ],
    "sg:phone":"+1 405 603 4951",
    "sg:postcode":"73132",
    "sg:province":"OK",
    "sg:tags":[
        "home",
        "care"
    ],
    "wof:name":"Healing Touch Hm Care Svc Inc",
    "wof:placetype":"venue"
},
  "geometry": {"coordinates":[-97.61313,35.545321],"type":"Point"}
}