{
  "type": "Feature",
  "properties": {
    "addr:full":"220 Pioneer Rd Elk City OK 73644",
    "addr:housenumber":"220",
    "addr:postcode":"73644",
    "addr:street":"Pioneer Rd",
    "iso:country":"US",
    "sg:address":"220 Pioneer Rd",
    "sg:city":"Elk City",
    "sg:classifiers":[
        {
            "category":"Professional",
            "subcategory":"Advertising",
            "type":"Services"
        }
    ],
    "sg:phone":"+1 580 225 7366",
    "sg:postcode":"73644",
    "sg:province":"OK",
    "sg:tags":[
        "agency"
    ],
    "wof:name":"Penny News",
    "wof:placetype":"venue"
},
  "geometry": {"coordinates":[-99.43484599999999,35.412496],"type":"Point"}
}