{
  "type": "Feature",
  "properties": {
    "addr:full":"2310 W 3rd St Elk City OK 73644",
    "addr:housenumber":"2310",
    "addr:postcode":"73644",
    "addr:street":"W 3Rd St",
    "iso:country":"US",
    "sg:address":"2310 W 3rd St",
    "sg:city":"Elk City",
    "sg:classifiers":[
        {
            "category":"Professional",
            "subcategory":"Business Services",
            "type":"Services"
        }
    ],
    "sg:phone":"+1 580 243 3606",
    "sg:postcode":"73644",
    "sg:province":"OK",
    "wof:name":"Continental Airlines",
    "wof:placetype":"venue"
},
  "geometry": {"coordinates":[-99.433775,35.411627],"type":"Point"}
}