{
  "type": "Feature",
  "properties": {
    "iso:country":"US",
    "sg:address":"331 N Macarthur Blvd",
    "sg:city":"Oklahoma City",
    "sg:classifiers":[
        {
            "category":"Building & Trades",
            "subcategory":"Plumbing",
            "type":"Services"
        }
    ],
    "sg:phone":"+1 405 739 0197",
    "sg:postcode":"73127",
    "sg:province":"OK",
    "sg:tags":[
        "heating",
        "contractor"
    ],
    "wof:name":"Paul Shadid Heating & Air Cond",
    "wof:placetype":"venue"
},
  "geometry": {"coordinates":[-97.618985,35.470309],"type":"Point"}
}