{
  "type": "Feature",
  "properties": {
    "iso:country":"US",
    "sg:address":"21477 N Western Ave",
    "sg:city":"Edmond",
    "sg:classifiers":[
        {
            "category":"Education",
            "subcategory":"School",
            "type":"Public Place"
        }
    ],
    "sg:phone":"+1 405 359 7335",
    "sg:postcode":"73012",
    "sg:province":"OK",
    "wof:name":"Edmond Christian Academy",
    "wof:placetype":"venue"
},
  "geometry": {"coordinates":[-97.531938,35.692128],"type":"Point"}
}