{
  "type": "Feature",
  "properties": {
    "addr:full":"1004 Grand Ave NW Ardmore OK 73401",
    "addr:housenumber":"1004",
    "addr:postcode":"73401",
    "addr:street":"Grand Ave Nw",
    "iso:country":"US",
    "sg:address":"1004 Grand Ave NW",
    "sg:city":"Ardmore",
    "sg:classifiers":[
        {
            "category":"Shopping",
            "subcategory":"Tobacco",
            "type":"Retail Goods"
        }
    ],
    "sg:phone":"+1 580 226 8212",
    "sg:postcode":"73401",
    "sg:province":"OK",
    "sg:tags":[
        "product"
    ],
    "wof:name":"Ardmore Tobacco Store",
    "wof:placetype":"venue"
},
  "geometry": {"coordinates":[-97.140659,34.179565],"type":"Point"}
}