{
  "type": "Feature",
  "properties": {
    "iso:country":"US",
    "sg:address":"6329 S 115th East Pl",
    "sg:city":"Broken Arrow",
    "sg:classifiers":[
        {
            "category":"Communications",
            "subcategory":"Film & Video Production",
            "type":"Services"
        }
    ],
    "sg:phone":"+1 918 250 8786",
    "sg:postcode":"74012",
    "sg:province":"OK",
    "sg:tags":[
        "motion"
    ],
    "wof:name":"1 Shot Productions Inc",
    "wof:placetype":"venue"
},
  "geometry": {"coordinates":[-95.847815,36.073027],"type":"Point"}
}