{
  "type": "Feature",
  "properties": {
    "iso:country":"US",
    "sg:address":"2226 S 32nd St",
    "sg:city":"Muskogee",
    "sg:classifiers":[
        {
            "category":"Sports & Exercise",
            "subcategory":"Gym",
            "type":"Entertainment"
        }
    ],
    "sg:phone":"+1 918 683 3539",
    "sg:postcode":"74401",
    "sg:province":"OK",
    "sg:tags":[
        "club",
        "health",
        "studio",
        "gymnasium"
    ],
    "wof:name":"Flex Time Fitness",
    "wof:placetype":"venue"
},
  "geometry": {"coordinates":[-95.402467,35.728211],"type":"Point"}
}