{
  "type": "Feature",
  "properties": {
    "iso:country":"US",
    "sg:address":"8 NW 8th St",
    "sg:city":"Healdton",
    "sg:classifiers":[
        {
            "category":"Real Estate",
            "subcategory":"Real Estate Agent",
            "type":"Services"
        }
    ],
    "sg:phone":"+1 580 229 0353",
    "sg:postcode":"73438",
    "sg:province":"OK",
    "wof:name":"Vickrey-Mc Neill Agency",
    "wof:placetype":"venue"
},
  "geometry": {"coordinates":[-97.492102,34.234563],"type":"Point"}
}