{
  "type": "Feature",
  "properties": {
    "addr:full":"1930 N Broadway St Moore OK 73160",
    "addr:housenumber":"1930",
    "addr:postcode":"73160",
    "addr:street":"N Broadway St",
    "iso:country":"US",
    "sg:address":"1930 N Broadway St",
    "sg:city":"Moore",
    "sg:classifiers":[
        {
            "category":"Health Services",
            "subcategory":"Doctor",
            "type":"Services"
        }
    ],
    "sg:phone":"+1 405 794 2210",
    "sg:postcode":"73160",
    "sg:province":"OK",
    "sg:tags":[
        "dentist"
    ],
    "wof:name":"Thomas J Kelly Inc",
    "wof:placetype":"venue"
},
  "geometry": {"coordinates":[-97.493908,35.353523],"type":"Point"}
}