{
  "type": "Feature",
  "properties": {
    "iso:country":"US",
    "sg:address":"1302 N Elm Pl",
    "sg:city":"Broken Arrow",
    "sg:classifiers":[
        {
            "category":"Food & Beverages",
            "subcategory":"Groceries & Convenience Stores",
            "type":"Retail Goods"
        }
    ],
    "sg:phone":"+1 918 251 9585",
    "sg:postcode":"74012",
    "sg:province":"OK",
    "wof:name":"Git-N-Go Inc",
    "wof:placetype":"venue"
},
  "geometry": {"coordinates":[-95.797526,36.067144],"type":"Point"}
}