{
  "type": "Feature",
  "properties": {
    "iso:country":"US",
    "sg:address":"113 Meadow Ridge Dr",
    "sg:city":"Elk City",
    "sg:classifiers":[
        {
            "category":"Education",
            "subcategory":"Dance Studio",
            "type":"Public Place"
        }
    ],
    "sg:phone":"+1 580 243 5622",
    "sg:postcode":"73644",
    "sg:province":"OK",
    "sg:tags":[
        "instruction",
        "dancing"
    ],
    "wof:name":"Joyce's School Of Dance",
    "wof:placetype":"venue"
},
  "geometry": {"coordinates":[-99.406392,35.384858],"type":"Point"}
}