{
  "type": "Feature",
  "properties": {
    "iso:country":"US",
    "sg:address":"1021 7th St",
    "sg:city":"Lone Wolf",
    "sg:classifiers":[
        {
            "category":"Education",
            "subcategory":"School",
            "type":"Public Place"
        }
    ],
    "sg:phone":"+1 580 846 9091",
    "sg:postcode":"73655",
    "sg:province":"OK",
    "wof:name":"Lone Wolf School District",
    "wof:placetype":"venue"
},
  "geometry": {"coordinates":[-99.248992,34.987367],"type":"Point"}
}