{
  "type": "Feature",
  "properties": {
    "iso:country":"US",
    "sg:address":"5304 W Orlando Cir",
    "sg:city":"Broken Arrow",
    "sg:classifiers":[
        {
            "category":"Retail",
            "subcategory":"Auto Repair",
            "type":"Services"
        }
    ],
    "sg:phone":"+1 918 249 9505",
    "sg:postcode":"74011",
    "sg:province":"OK",
    "sg:tags":[
        "general"
    ],
    "wof:name":"Diesel Propulsion Service",
    "wof:placetype":"venue"
},
  "geometry": {"coordinates":[-95.857513,36.016833],"type":"Point"}
}