{
  "type": "Feature",
  "properties": {
    "iso:country":"US",
    "sg:address":"600 S Cherokee St",
    "sg:city":"Catoosa",
    "sg:classifiers":[
        {
            "category":"Education",
            "subcategory":"School",
            "type":"Public Place"
        }
    ],
    "sg:phone":"+1 918 266 1151",
    "sg:postcode":"74015",
    "sg:province":"OK",
    "wof:name":"Catoosa Upper Elementary Sch",
    "wof:placetype":"venue"
},
  "geometry": {"coordinates":[-95.75041899999999,36.178786],"type":"Point"}
}