{
  "type": "Feature",
  "properties": {
    "addr:full":"4506 S 29th West Ave Tulsa OK 74107",
    "addr:housenumber":"4506",
    "addr:postcode":"74107",
    "addr:street":"S 29Th West Ave",
    "iso:country":"US",
    "sg:address":"4506 S 29th West Ave",
    "sg:city":"Tulsa",
    "sg:classifiers":[
        {
            "category":"Professional",
            "type":"Services"
        }
    ],
    "sg:phone":"+1 918 446 5125",
    "sg:postcode":"74107",
    "sg:province":"OK",
    "wof:name":"Hardesty Services LLC",
    "wof:placetype":"venue"
},
  "geometry": {"coordinates":[-96.025081,36.098189],"type":"Point"}
}