{
  "type": "Feature",
  "properties": {
    "iso:country":"US",
    "sg:address":"548 E Apache St",
    "sg:city":"Tulsa",
    "sg:classifiers":[
        {
            "category":"Retail",
            "subcategory":"Auto Repair",
            "type":"Services"
        }
    ],
    "sg:phone":"+1 918 583 1281",
    "sg:postcode":"74106",
    "sg:province":"OK",
    "sg:tags":[
        "repairing",
        "automobile"
    ],
    "wof:name":"Lacy's Automotive Repair",
    "wof:placetype":"venue"
},
  "geometry": {"coordinates":[-95.985427,36.191382],"type":"Point"}
}