{
  "type": "Feature",
  "properties": {
    "iso:country":"US",
    "sg:address":"513 Meadowlark Ln",
    "sg:city":"Commerce",
    "sg:classifiers":[
        {
            "category":"Autos & Motor Vehicles",
            "subcategory":"Automobile Sales",
            "type":"Retail Goods"
        }
    ],
    "sg:phone":"+1 918 675 4775",
    "sg:postcode":"74339",
    "sg:province":"OK",
    "sg:tags":[
        "used"
    ],
    "wof:name":"Commerce Auto Sales",
    "wof:placetype":"venue"
},
  "geometry": {"coordinates":[-94.864976,36.928868],"type":"Point"}
}