{
  "type": "Feature",
  "properties": {
    "iso:country":"US",
    "sg:address":"400 E Britton Rd",
    "sg:city":"Oklahoma City",
    "sg:classifiers":[
        {
            "category":"Communications",
            "subcategory":"Radio Station",
            "type":"Services"
        }
    ],
    "sg:phone":"+1 405 478 5104",
    "sg:postcode":"73114",
    "sg:province":"OK",
    "sg:tags":[
        "company",
        "broadcasting"
    ],
    "sg:website":"www.rendabroadcasting.com",
    "wof:name":"KMGL",
    "wof:placetype":"venue"
},
  "geometry": {"coordinates":[-97.506764,35.565522],"type":"Point"}
}