{
  "type": "Feature",
  "properties": {
    "iso:country":"US",
    "sg:address":"1706 SW Lee Blvd",
    "sg:city":"Lawton",
    "sg:classifiers":[
        {
            "category":"Autos & Motor Vehicles",
            "subcategory":"Automobile Sales",
            "type":"Retail Goods"
        }
    ],
    "sg:phone":"+1 580 351 2488",
    "sg:postcode":"73501",
    "sg:province":"OK",
    "sg:tags":[
        "car",
        "dealer"
    ],
    "wof:name":"Twister Auto Sales",
    "wof:placetype":"venue"
},
  "geometry": {"coordinates":[-98.415318,34.594259],"type":"Point"}
}