{
  "type": "Feature",
  "properties": {
    "iso:country":"US",
    "sg:address":"23115 W Wekiwa Rd",
    "sg:city":"Sand Springs",
    "sg:classifiers":[
        {
            "category":"Building & Trades",
            "subcategory":"Equipment Rental",
            "type":"Services"
        }
    ],
    "sg:phone":"+1 918 865 2414",
    "sg:postcode":"74063",
    "sg:province":"OK",
    "sg:tags":[
        "contractor"
    ],
    "wof:name":"Billy Joe Wing",
    "wof:placetype":"venue"
},
  "geometry": {"coordinates":[-96.238981,36.148399],"type":"Point"}
}