{
  "type": "Feature",
  "properties": {
    "iso:country":"US",
    "sg:address":"1400 E Main St",
    "sg:city":"Tishomingo",
    "sg:classifiers":[
        {
            "category":"Utilities",
            "subcategory":"Fuel Oil & Lpg",
            "type":"Services"
        }
    ],
    "sg:phone":"+1 580 371 0484",
    "sg:postcode":"73460",
    "sg:province":"OK",
    "sg:tags":[
        "propane",
        "gas"
    ],
    "wof:name":"Pitmon Oil & Gas Co",
    "wof:placetype":"venue"
},
  "geometry": {"coordinates":[-96.662346,34.230562],"type":"Point"}
}