{
  "type": "Feature",
  "properties": {
    "iso:country":"US",
    "sg:address":"3303 S Yale Ave",
    "sg:city":"Tulsa",
    "sg:classifiers":[
        {
            "category":"Retail",
            "subcategory":"Auto Rental",
            "type":"Services"
        }
    ],
    "sg:phone":"+1 918 749 7525",
    "sg:postcode":"74135",
    "sg:province":"OK",
    "sg:tags":[
        "truck"
    ],
    "wof:name":"U-Haul",
    "wof:placetype":"venue"
},
  "geometry": {"coordinates":[-95.922327,36.115373],"type":"Point"}
}