{
  "type": "Feature",
  "properties": {
    "iso:country":"US",
    "sg:address":"521 W Main St",
    "sg:city":"Ada",
    "sg:classifiers":[
        {
            "category":"Retail",
            "subcategory":"Auto Repair",
            "type":"Services"
        }
    ],
    "sg:phone":"+1 580 436 4551",
    "sg:postcode":"74820",
    "sg:province":"OK",
    "sg:tags":[
        "repairing",
        "automobile"
    ],
    "wof:name":"Brassfield Radiator Repair",
    "wof:placetype":"venue"
},
  "geometry": {"coordinates":[-96.68633800000001,34.774413],"type":"Point"}
}