{
  "type": "Feature",
  "properties": {
    "iso:country":"US",
    "sg:address":"10301 S Santa Fe Ave",
    "sg:city":"Oklahoma City",
    "sg:classifiers":[
        {
            "category":"Restaurant",
            "type":"Food & Drink"
        }
    ],
    "sg:phone":"+1 405 691 0504",
    "sg:postcode":"73139",
    "sg:province":"OK",
    "sg:tags":[
        "eating"
    ],
    "wof:name":"Francas Pizza",
    "wof:placetype":"venue"
},
  "geometry": {"coordinates":[-97.512209,35.365677],"type":"Point"}
}