{
  "type": "Feature",
  "properties": {
    "addr:full":"327 N Main St Seminole OK 74868",
    "addr:housenumber":"327",
    "addr:postcode":"74868",
    "addr:street":"N Main St",
    "iso:country":"US",
    "sg:address":"327 N Main St",
    "sg:city":"Seminole",
    "sg:classifiers":[
        {
            "category":"Personal",
            "type":"Services"
        }
    ],
    "sg:phone":"+1 405 382 5462",
    "sg:postcode":"74868",
    "sg:province":"OK",
    "sg:tags":[
        "therapist",
        "massage"
    ],
    "wof:name":"Body Logic",
    "wof:placetype":"venue"
},
  "geometry": {"coordinates":[-96.66857400000001,35.226215],"type":"Point"}
}