{
  "type": "Feature",
  "properties": {
    "addr:full":"2812 E 15th St Tulsa OK 74104",
    "addr:housenumber":"2812",
    "addr:postcode":"74104",
    "addr:street":"E 15Th St",
    "iso:country":"US",
    "sg:address":"2812 E 15th St",
    "sg:city":"Tulsa",
    "sg:classifiers":[
        {
            "category":"Shopping",
            "subcategory":"Books",
            "type":"Retail Goods"
        }
    ],
    "sg:phone":"+1 918 745 0002",
    "sg:postcode":"74104",
    "sg:province":"OK",
    "sg:tags":[
        "used",
        "merchandise"
    ],
    "wof:name":"Oak Tree Books",
    "wof:placetype":"venue"
},
  "geometry": {"coordinates":[-95.948626,36.140483],"type":"Point"}
}