{
  "type": "Feature",
  "properties": {
    "iso:country":"US",
    "sg:address":"2025 E 71st St",
    "sg:city":"Tulsa",
    "sg:classifiers":[
        {
            "category":"Health Services",
            "subcategory":"Nursing And Care Facility",
            "type":"Services"
        }
    ],
    "sg:phone":"+1 918 496 8333",
    "sg:postcode":"74136",
    "sg:province":"OK",
    "sg:tags":[
        "home",
        "retirement",
        "community"
    ],
    "wof:name":"Tulsa Jewish Retirement",
    "wof:placetype":"venue"
},
  "geometry": {"coordinates":[-95.960943,36.060879],"type":"Point"}
}