{
  "type": "Feature",
  "properties": {
    "iso:country":"US",
    "sg:address":"2215 SW 74th St",
    "sg:city":"Oklahoma City",
    "sg:classifiers":[
        {
            "category":"Organizations",
            "subcategory":"Non-profit Organization",
            "type":"Services"
        }
    ],
    "sg:phone":"+1 405 733 0272",
    "sg:postcode":"73159",
    "sg:province":"OK",
    "sg:tags":[
        "charitable",
        "institution"
    ],
    "wof:name":"Central Oklahoma Habitat",
    "wof:placetype":"venue"
},
  "geometry": {"coordinates":[-97.547995,35.391828],"type":"Point"}
}