{
  "type": "Feature",
  "properties": {
    "iso:country":"US",
    "sg:address":"1913 W Tacoma St",
    "sg:city":"Broken Arrow",
    "sg:classifiers":[
        {
            "category":"Professional",
            "type":"Services"
        }
    ],
    "sg:phone":"+1 918 258 9888",
    "sg:postcode":"74012",
    "sg:province":"OK",
    "sg:tags":[
        "establishment"
    ],
    "wof:name":"Toll Free Dial",
    "wof:placetype":"venue"
},
  "geometry": {"coordinates":[-95.812839,36.071105],"type":"Point"}
}