{
  "type": "Feature",
  "properties": {
    "addr:full":"7440 E 46th Pl Tulsa OK 74145",
    "addr:housenumber":"7440",
    "addr:postcode":"74145",
    "addr:street":"E 46Th Pl",
    "iso:country":"US",
    "sg:address":"7440 E 46th Pl",
    "sg:city":"Tulsa",
    "sg:classifiers":[
        {
            "category":"Professional",
            "subcategory":"Engineering",
            "type":"Services"
        }
    ],
    "sg:phone":"+1 918 627 2952",
    "sg:postcode":"74145",
    "sg:province":"OK",
    "sg:tags":[
        "engineer"
    ],
    "wof:name":"Grant & Assoc",
    "wof:placetype":"venue"
},
  "geometry": {"coordinates":[-95.886967,36.096404],"type":"Point"}
}