{
  "type": "Feature",
  "properties": {
    "iso:country":"US",
    "sg:address":"16 N Meridian Ave",
    "sg:city":"Oklahoma City",
    "sg:classifiers":[
        {
            "category":"Freight",
            "type":"Transportation"
        }
    ],
    "sg:phone":"+1 405 943 5212",
    "sg:postcode":"73107",
    "sg:province":"OK",
    "sg:tags":[
        "trucking"
    ],
    "wof:name":"Transport Distribution Co",
    "wof:placetype":"venue"
},
  "geometry": {"coordinates":[-97.601034,35.468147],"type":"Point"}
}