{
  "type": "Feature",
  "properties": {
    "iso:country":"US",
    "sg:address":"24 N McCormick Ave",
    "sg:city":"Oklahoma City",
    "sg:classifiers":[
        {
            "category":"Wholesale",
            "subcategory":"Machinery & Supplies",
            "type":"Manufacturing & Wholesale Goods"
        },
        {
            "category":"Home & Garden",
            "subcategory":"Building Materials",
            "type":"Retail Goods"
        }
    ],
    "sg:phone":"+1 405 949 2278",
    "sg:postcode":"73127",
    "sg:province":"OK",
    "sg:tags":[
        "mason",
        "contractor"
    ],
    "wof:name":"Dolese Brothers Co",
    "wof:placetype":"venue"
},
  "geometry": {"coordinates":[-97.61522100000001,35.469617],"type":"Point"}
}