{
  "type": "Feature",
  "properties": {
    "addr:full":"120 E Lincoln St Mangum OK 73554",
    "addr:housenumber":"120",
    "addr:postcode":"73554",
    "addr:street":"E Lincoln St",
    "iso:country":"US",
    "sg:address":"120 E Lincoln St",
    "sg:city":"Mangum",
    "sg:classifiers":[
        {
            "category":"Personal",
            "type":"Services"
        }
    ],
    "sg:phone":"+1 580 782 3805",
    "sg:postcode":"73554",
    "sg:province":"OK",
    "wof:name":"Busy Bee",
    "wof:placetype":"venue"
},
  "geometry": {"coordinates":[-99.505796,34.872182],"type":"Point"}
}