{
  "type": "Feature",
  "properties": {
    "iso:country":"US",
    "sg:address":"5858 S 129th E Ave",
    "sg:city":"Tulsa",
    "sg:classifiers":[
        {
            "category":"Manufacturing",
            "subcategory":"Printing",
            "type":"Manufacturing & Wholesale Goods"
        }
    ],
    "sg:phone":"+1 918 250 6667",
    "sg:postcode":"74134",
    "sg:province":"OK",
    "sg:tags":[
        "publisher"
    ],
    "wof:name":"Christian Publishing Svc",
    "wof:placetype":"venue"
},
  "geometry": {"coordinates":[-95.833252,36.082568],"type":"Point"}
}