{
  "type": "Feature",
  "properties": {
    "addr:full":"12807 E 86th St N Owasso OK 74055",
    "addr:housenumber":"12807",
    "addr:postcode":"74055",
    "addr:street":"E 86Th St N",
    "iso:country":"US",
    "sg:address":"12807 E 86th St N",
    "sg:city":"Owasso",
    "sg:classifiers":[
        {
            "category":"Food & Beverages",
            "subcategory":"Groceries & Convenience Stores",
            "type":"Retail Goods"
        }
    ],
    "sg:phone":"+1 918 274 7121",
    "sg:postcode":"74055",
    "sg:province":"OK",
    "wof:name":"Git-N-Go Inc",
    "wof:placetype":"venue"
},
  "geometry": {"coordinates":[-95.83019,36.278597],"type":"Point"}
}