{
  "type": "Feature",
  "properties": {
    "iso:country":"US",
    "sg:address":"1621 E Electric Ave",
    "sg:city":"Mcalester",
    "sg:classifiers":[
        {
            "category":"Wholesale",
            "subcategory":"Farm Supplies",
            "type":"Manufacturing & Wholesale Goods"
        }
    ],
    "sg:phone":"+1 918 423 2345",
    "sg:postcode":"74501",
    "sg:province":"OK",
    "sg:tags":[
        "feed"
    ],
    "wof:name":"Big V Feeds Inc",
    "wof:placetype":"venue"
},
  "geometry": {"coordinates":[-95.742798,34.94432],"type":"Point"}
}