{
  "type": "Feature",
  "properties": {
    "iso:country":"US",
    "sg:address":"1413 S Broadway Ave",
    "sg:city":"Hobart",
    "sg:classifiers":[
        {
            "category":"Retail",
            "subcategory":"Repair Shop",
            "type":"Services"
        }
    ],
    "sg:phone":"+1 580 726 5744",
    "sg:postcode":"73651",
    "sg:province":"OK",
    "wof:name":"Garys AG Service",
    "wof:placetype":"venue"
},
  "geometry": {"coordinates":[-99.09603300000001,35.009575],"type":"Point"}
}