{
  "type": "Feature",
  "properties": {
    "iso:country":"US",
    "sg:address":"204 E Main St",
    "sg:city":"Henryetta",
    "sg:classifiers":[
        {
            "category":"Real Estate",
            "subcategory":"Real Estate Agent",
            "type":"Services"
        }
    ],
    "sg:phone":"+1 918 652 2642",
    "sg:postcode":"74437",
    "sg:province":"OK",
    "wof:name":"Hold Realty",
    "wof:placetype":"venue"
},
  "geometry": {"coordinates":[-95.980629,35.439878],"type":"Point"}
}