{
  "type": "Feature",
  "properties": {
    "iso:country":"US",
    "sg:address":"315 S 2nd St",
    "sg:city":"Bache",
    "sg:classifiers":[
        {
            "category":"Home & Garden",
            "subcategory":"Building Materials",
            "type":"Retail Goods"
        }
    ],
    "sg:phone":"+1 918 423 7557",
    "sg:postcode":"74501",
    "sg:province":"OK",
    "sg:tags":[
        "hardware",
        "paint",
        "wallpaper"
    ],
    "wof:name":"Cook Paint",
    "wof:placetype":"venue"
},
  "geometry": {"coordinates":[-95.768653,34.928601],"type":"Point"}
}