{
  "type": "Feature",
  "properties": {
    "iso:country":"US",
    "sg:address":"103 Woodcreek Dr",
    "sg:city":"Fairview",
    "sg:classifiers":[
        {
            "category":"Mining & Drilling",
            "type":"Manufacturing & Wholesale Goods"
        }
    ],
    "sg:phone":"+1 580 227 2361",
    "sg:postcode":"73737",
    "sg:province":"OK",
    "sg:tags":[
        "field",
        "oil"
    ],
    "wof:name":"Stan's Construction Co",
    "wof:placetype":"venue"
},
  "geometry": {"coordinates":[-98.46279199999999,36.286837],"type":"Point"}
}