{
  "type": "Feature",
  "properties": {
    "iso:country":"US",
    "sg:address":"2012 Sagewood Dr",
    "sg:city":"Edmond",
    "sg:classifiers":[
        {
            "category":"Professional",
            "subcategory":"Business Services",
            "type":"Services"
        }
    ],
    "sg:phone":"+1 405 749 8822",
    "sg:postcode":"73013",
    "sg:province":"OK",
    "sg:tags":[
        "inspection"
    ],
    "wof:name":"Buyers Inspector",
    "wof:placetype":"venue"
},
  "geometry": {"coordinates":[-97.509252,35.627603],"type":"Point"}
}