{
  "type": "Feature",
  "properties": {
    "iso:country":"US",
    "sg:address":"1384 S Douglas Blvd",
    "sg:city":"Oklahoma City",
    "sg:classifiers":[
        {
            "category":"Professional",
            "subcategory":"Lawyer & Legal Services",
            "type":"Services"
        }
    ],
    "sg:phone":"+1 405 733 1683",
    "sg:postcode":"73130",
    "sg:province":"OK",
    "sg:tags":[
        "consulting",
        "management"
    ],
    "wof:name":"Joe M Crosthwait Jr",
    "wof:placetype":"venue"
},
  "geometry": {"coordinates":[-97.370761,35.453139],"type":"Point"}
}