{
  "type": "Feature",
  "properties": {
    "addr:full":"1124 S George Nigh Expy Mcalester OK 74501",
    "addr:housenumber":"1124",
    "addr:postcode":"74501",
    "addr:street":"S George Nigh Expy",
    "iso:country":"US",
    "sg:address":"1124 S George Nigh Expy",
    "sg:city":"Mcalester",
    "sg:classifiers":[
        {
            "category":"Autos & Motor Vehicles",
            "subcategory":"Boat Sales",
            "type":"Retail Goods"
        }
    ],
    "sg:phone":"+1 918 423 1364",
    "sg:postcode":"74501",
    "sg:province":"OK",
    "sg:tags":[
        "dealer",
        "sales"
    ],
    "wof:name":"Jimmy Houston Marine",
    "wof:placetype":"venue"
},
  "geometry": {"coordinates":[-95.755156,34.899164],"type":"Point"}
}