{
  "type": "Feature",
  "properties": {
    "addr:full":"221 NW 22nd St Oklahoma City OK 73103",
    "addr:housenumber":"221",
    "addr:postcode":"73103",
    "addr:street":"Nw 22Nd St",
    "iso:country":"US",
    "sg:address":"221 NW 22nd St",
    "sg:city":"Oklahoma City",
    "sg:classifiers":[
        {
            "category":"Professional",
            "subcategory":"Management & Consulting",
            "type":"Services"
        }
    ],
    "sg:phone":"+1 405 528 3240",
    "sg:postcode":"73103",
    "sg:province":"OK",
    "wof:name":"Smei Academy of Achieveme",
    "wof:placetype":"venue"
},
  "geometry": {"coordinates":[-97.517115,35.492311],"type":"Point"}
}