{
  "type": "Feature",
  "properties": {
    "iso:country":"US",
    "sg:address":"1043 N Main St",
    "sg:city":"Seminole",
    "sg:classifiers":[
        {
            "category":"Home & Garden",
            "subcategory":"Home Furnishings",
            "type":"Retail Goods"
        }
    ],
    "sg:phone":"+1 405 382 2488",
    "sg:postcode":"74868",
    "sg:province":"OK",
    "sg:tags":[
        "curtain",
        "made",
        "drapery"
    ],
    "wof:name":"Drapery Shop",
    "wof:placetype":"venue"
},
  "geometry": {"coordinates":[-96.668639,35.232585],"type":"Point"}
}