{
  "type": "Feature",
  "properties": {
    "iso:country":"US",
    "sg:address":"415 N Main St",
    "sg:city":"Broken Arrow",
    "sg:classifiers":[
        {
            "category":"Shopping",
            "subcategory":"Jewelry",
            "type":"Retail Goods"
        }
    ],
    "sg:phone":"+1 918 251 1118",
    "sg:postcode":"74012",
    "sg:province":"OK",
    "sg:tags":[
        "jeweler"
    ],
    "wof:name":"Randy's Custom Jewelry",
    "wof:placetype":"venue"
},
  "geometry": {"coordinates":[-95.790708,36.055525],"type":"Point"}
}