{
  "type": "Feature",
  "properties": {
    "iso:country":"US",
    "sg:address":"130 E Colorado Ave",
    "sg:city":"Walters",
    "sg:classifiers":[
        {
            "category":"Shopping",
            "subcategory":"Beauty & Cosmetics",
            "type":"Retail Goods"
        }
    ],
    "sg:phone":"+1 580 875 3138",
    "sg:postcode":"73572",
    "sg:province":"OK",
    "sg:tags":[
        "florist",
        "merchandise"
    ],
    "wof:name":"Lady Bug Flowers & Gifts",
    "wof:placetype":"venue"
},
  "geometry": {"coordinates":[-98.308738,34.357864],"type":"Point"}
}