{
  "type": "Feature",
  "properties": {
    "addr:full":"4000 N May Ave Oklahoma City OK 73112",
    "addr:housenumber":"4000",
    "addr:postcode":"73112",
    "addr:street":"N May Ave",
    "iso:country":"US",
    "sg:address":"4000 N May Ave",
    "sg:city":"Oklahoma City",
    "sg:classifiers":[
        {
            "category":"Autos & Motor Vehicles",
            "subcategory":"Automobile Sales",
            "type":"Retail Goods"
        }
    ],
    "sg:phone":"+1 405 943 7300",
    "sg:postcode":"73112",
    "sg:province":"OK",
    "sg:tags":[
        "car",
        "dealer"
    ],
    "wof:name":"Express Credit Auto Sales",
    "wof:placetype":"venue"
},
  "geometry": {"coordinates":[-97.56560399999999,35.511455],"type":"Point"}
}