{
  "type": "Feature",
  "properties": {
    "addr:full":"503 Main St Jet OK 73749",
    "addr:housenumber":"503",
    "addr:postcode":"73749",
    "addr:street":"Main St",
    "iso:country":"US",
    "sg:address":"503 Main St",
    "sg:city":"Jet",
    "sg:phone":"+1 580 626 4514",
    "sg:postcode":"73749",
    "sg:province":"OK",
    "sg:tags":[
        "gas"
    ],
    "wof:name":"Yoder Gas Co",
    "wof:placetype":"venue"
},
  "geometry": {"coordinates":[-98.18293199999999,36.666322],"type":"Point"}
}