{
  "type": "Feature",
  "properties": {
    "iso:country":"US",
    "sg:address":"220 W Doolin Ave",
    "sg:city":"Blackwell",
    "sg:classifiers":[
        {
            "category":"Autos & Motor Vehicles",
            "subcategory":"Automobile Sales",
            "type":"Retail Goods"
        }
    ],
    "sg:phone":"+1 580 363 0322",
    "sg:postcode":"74631",
    "sg:province":"OK",
    "sg:tags":[
        "new",
        "used",
        "dealer",
        "car"
    ],
    "wof:name":"Sonny Cannon Auto Plaza Inc",
    "wof:placetype":"venue"
},
  "geometry": {"coordinates":[-97.284354,36.811605],"type":"Point"}
}