{
  "type": "Feature",
  "properties": {
    "addr:full":"8803 S 101st East Ave Tulsa OK 74133",
    "addr:housenumber":"8803",
    "addr:postcode":"74133",
    "addr:street":"S 101St;Ave",
    "iso:country":"US",
    "sg:address":"8803 S 101st East Ave",
    "sg:city":"Tulsa",
    "sg:classifiers":[
        {
            "category":"Health Services",
            "subcategory":"Optometrist",
            "type":"Services"
        }
    ],
    "sg:phone":"+1 918 250 2020",
    "sg:postcode":"74133",
    "sg:province":"OK",
    "sg:tags":[
        "correction",
        "laser",
        "vision"
    ],
    "wof:name":"Eyecare Associates Of South Tulsa",
    "wof:placetype":"venue"
},
  "geometry": {"coordinates":[-95.86474,36.035234],"type":"Point"}
}