{
  "type": "Feature",
  "properties": {
    "addr:full":"2020 S Sunnylane Rd Oklahoma City OK 73115",
    "addr:housenumber":"2020",
    "addr:postcode":"73115",
    "addr:street":"S Sunnylane Rd",
    "iso:country":"US",
    "sg:address":"2020 S Sunnylane Rd",
    "sg:city":"Oklahoma City",
    "sg:classifiers":[
        {
            "category":"Social Services",
            "subcategory":"Child Care",
            "type":"Services"
        }
    ],
    "sg:phone":"+1 405 672 6150",
    "sg:postcode":"73115",
    "sg:province":"OK",
    "sg:tags":[
        "day"
    ],
    "wof:name":"Sunnylane Day Care Ctr",
    "wof:placetype":"venue"
},
  "geometry": {"coordinates":[-97.441355,35.444328],"type":"Point"}
}