{
  "type": "Feature",
  "properties": {
    "iso:country":"US",
    "sg:address":"1200 NE 4th St",
    "sg:city":"Oklahoma City",
    "sg:classifiers":[
        {
            "category":"Education",
            "subcategory":"School",
            "type":"Public Place"
        }
    ],
    "sg:phone":"+1 405 793 3200",
    "sg:postcode":"73160",
    "sg:province":"OK",
    "sg:website":"www.moore.k12.ok.us",
    "wof:name":"Highland East Junior High Schl",
    "wof:placetype":"venue"
},
  "geometry": {"coordinates":[-97.469769,35.341809],"type":"Point"}
}