{
  "type": "Feature",
  "properties": {
    "iso:country":"US",
    "sg:address":"1208 N Main St",
    "sg:city":"Mcalester",
    "sg:classifiers":[
        {
            "category":"Personal",
            "type":"Services"
        }
    ],
    "sg:phone":"+1 918 423 5455",
    "sg:postcode":"74501",
    "sg:province":"OK",
    "sg:tags":[
        "department",
        "motor",
        "vehicle"
    ],
    "wof:name":"Tag Agent",
    "wof:placetype":"venue"
},
  "geometry": {"coordinates":[-95.765286,34.944986],"type":"Point"}
}