{
  "type": "Feature",
  "properties": {
    "addr:full":"9539 E 34th St Tulsa OK 74145",
    "addr:housenumber":"9539",
    "addr:postcode":"74145",
    "addr:street":"E 34Th St",
    "iso:country":"US",
    "sg:address":"9539 E 34th St",
    "sg:city":"Tulsa",
    "sg:classifiers":[
        {
            "category":"Banks & Credit Unions",
            "subcategory":"Financial Services",
            "type":"Services"
        }
    ],
    "sg:phone":"+1 918 451 5968",
    "sg:postcode":"74145",
    "sg:province":"OK",
    "sg:tags":[
        "selling",
        "real estate",
        "home",
        "investor",
        "buying"
    ],
    "wof:name":"D Halls Investments Inc",
    "wof:placetype":"venue"
},
  "geometry": {"coordinates":[-95.870051,36.114598],"type":"Point"}
}