{
  "type": "Feature",
  "properties": {
    "iso:country":"US",
    "sg:address":"1333 N Santa Fe Ave",
    "sg:city":"Edmond",
    "sg:classifiers":[
        {
            "category":"Restaurant",
            "type":"Food & Drink"
        }
    ],
    "sg:menulink":"http://www.allmenus.com/ok/oklahoma-city/122465-quiznos-sub/menu/",
    "sg:phone":"+1 405 471 6587",
    "sg:postcode":"73003",
    "sg:province":"OK",
    "sg:tags":[
        "wrap",
        "american",
        "sandwich"
    ],
    "wof:name":"Quiznos Sub",
    "wof:placetype":"venue"
},
  "geometry": {"coordinates":[-97.51412999999999,35.667885],"type":"Point"}
}