{
  "type": "Feature",
  "properties": {
    "iso:country":"US",
    "sg:address":"206 NE 9th St",
    "sg:city":"Antlers",
    "sg:classifiers":[
        {
            "category":"Education",
            "subcategory":"School",
            "type":"Public Place"
        }
    ],
    "sg:phone":"+1 580 298 2141",
    "sg:postcode":"74523",
    "sg:province":"OK",
    "wof:name":"Antlers High School",
    "wof:placetype":"venue"
},
  "geometry": {"coordinates":[-95.61971,34.240288],"type":"Point"}
}