{
  "type": "Feature",
  "properties": {
    "iso:country":"US",
    "sg:address":"1800 N Interstate Dr",
    "sg:city":"Norman",
    "sg:classifiers":[
        {
            "category":"Banks & Credit Unions",
            "subcategory":"Bank",
            "type":"Services"
        }
    ],
    "sg:phone":"+1 405 579 8900",
    "sg:postcode":"73072",
    "sg:province":"OK",
    "sg:tags":[
        "broker",
        "mortgage"
    ],
    "wof:name":"Resource Mortgage of Norman",
    "wof:placetype":"venue"
},
  "geometry": {"coordinates":[-97.486299,35.236564],"type":"Point"}
}