{
  "type": "Feature",
  "properties": {
    "addr:full":"1808 N Owasso Ave Tulsa OK 74106",
    "addr:housenumber":"1808",
    "addr:postcode":"74106",
    "addr:street":"N Owasso Ave",
    "iso:country":"US",
    "sg:address":"1808 N Owasso Ave",
    "sg:city":"Tulsa",
    "sg:classifiers":[
        {
            "category":"Building & Trades",
            "subcategory":"Construction",
            "type":"Services"
        }
    ],
    "sg:phone":"+1 918 582 1201",
    "sg:postcode":"74106",
    "sg:province":"OK",
    "sg:tags":[
        "fence",
        "contractor"
    ],
    "wof:name":"Northside Fence",
    "wof:placetype":"venue"
},
  "geometry": {"coordinates":[-95.976663,36.179104],"type":"Point"}
}