{
  "type": "Feature",
  "properties": {
    "iso:country":"US",
    "sg:address":"1815 S Main St",
    "sg:city":"Broken Arrow",
    "sg:classifiers":[
        {
            "category":"Professional",
            "subcategory":"Business Services",
            "type":"Services"
        }
    ],
    "sg:phone":"+1 918 258 4459",
    "sg:postcode":"74012",
    "sg:province":"OK",
    "sg:tags":[
        "sales",
        "estate"
    ],
    "wof:name":"DSC Estate Sales",
    "wof:placetype":"venue"
},
  "geometry": {"coordinates":[-95.790807,36.032219],"type":"Point"}
}