{
  "type": "Feature",
  "properties": {
    "addr:full":"1821 Victoria Dr Edmond OK 73003",
    "addr:housenumber":"1821",
    "addr:postcode":"73003",
    "addr:street":"Victoria Dr",
    "iso:country":"US",
    "sg:address":"1821 Victoria Dr",
    "sg:city":"Edmond",
    "sg:classifiers":[
        {
            "category":"Wholesale",
            "subcategory":"Durable Goods & Equipment",
            "type":"Manufacturing & Wholesale Goods"
        }
    ],
    "sg:phone":"+1 405 348 5273",
    "sg:postcode":"73003",
    "sg:province":"OK",
    "sg:tags":[
        "exporter"
    ],
    "wof:name":"Evermore International Inc",
    "wof:placetype":"venue"
},
  "geometry": {"coordinates":[-97.507988,35.668927],"type":"Point"}
}