{
  "type": "Feature",
  "properties": {
    "addr:full":"5105 Circle Glen Edmond OK 73003",
    "addr:housenumber":"5105",
    "addr:postcode":"73003",
    "addr:street":"Circle Glen",
    "iso:country":"US",
    "sg:address":"5105 Circle Glen",
    "sg:city":"Edmond",
    "sg:classifiers":[
        {
            "category":"Professional",
            "type":"Services"
        }
    ],
    "sg:phone":"+1 405 341 7006",
    "sg:postcode":"73003",
    "sg:province":"OK",
    "wof:name":"KB Administrative Services LLC",
    "wof:placetype":"venue"
},
  "geometry": {"coordinates":[-97.501357,35.709449],"type":"Point"}
}