{
  "type": "Feature",
  "properties": {
    "iso:country":"US",
    "sg:address":"23 E Brady St",
    "sg:city":"Tulsa",
    "sg:classifiers":[
        {
            "category":"Shopping",
            "type":"Retail Goods"
        }
    ],
    "sg:phone":"+1 918 585 1166",
    "sg:postcode":"74103",
    "sg:province":"OK",
    "sg:tags":[
        "art",
        "gallery",
        "dealer"
    ],
    "wof:name":"Boston Artists Gallery",
    "wof:placetype":"venue"
},
  "geometry": {"coordinates":[-95.99273700000001,36.158691],"type":"Point"}
}