{
  "type": "Feature",
  "properties": {
    "iso:country":"US",
    "sg:address":"9421 N Robinson Ave",
    "sg:city":"Oklahoma City",
    "sg:classifiers":[
        {
            "category":"Professional",
            "subcategory":"Management & Consulting",
            "type":"Services"
        }
    ],
    "sg:phone":"+1 405 607 4522",
    "sg:postcode":"73114",
    "sg:province":"OK",
    "wof:name":"Cattle Stats",
    "wof:placetype":"venue"
},
  "geometry": {"coordinates":[-97.515843,35.566406],"type":"Point"}
}