{
  "type": "Feature",
  "properties": {
    "iso:country":"US",
    "sg:address":"1200 SW Expressway Dr",
    "sg:city":"Broken Arrow",
    "sg:classifiers":[
        {
            "category":"Autos & Motor Vehicles",
            "subcategory":"Motorcycle Sales",
            "type":"Retail Goods"
        }
    ],
    "sg:phone":"+1 918 258 4774",
    "sg:postcode":"74012",
    "sg:province":"OK",
    "sg:tags":[
        "scooter"
    ],
    "sg:website":"www.gchonda.com",
    "wof:name":"Green Country Honda-Suzuki",
    "wof:placetype":"venue"
},
  "geometry": {"coordinates":[-95.80719499999999,36.073344],"type":"Point"}
}