{
  "type": "Feature",
  "properties": {
    "iso:country":"US",
    "sg:address":"3035 NW 63rd St",
    "sg:city":"Oklahoma City",
    "sg:classifiers":[
        {
            "category":"Professional",
            "subcategory":"Lawyer & Legal Services",
            "type":"Services"
        }
    ],
    "sg:phone":"+1 405 858 1666",
    "sg:postcode":"73116",
    "sg:province":"OK",
    "sg:tags":[
        "attorney"
    ],
    "wof:name":"Lundy Partin",
    "wof:placetype":"venue"
},
  "geometry": {"coordinates":[-97.568609,35.536649],"type":"Point"}
}