{
  "type": "Feature",
  "properties": {
    "iso:country":"US",
    "sg:address":"8007 S Sheridan Rd",
    "sg:city":"Tulsa",
    "sg:classifiers":[
        {
            "category":"Personal",
            "type":"Services"
        },
        {
            "category":"Sports & Exercise",
            "subcategory":"Gym",
            "type":"Entertainment"
        },
        {
            "category":"Health Services",
            "subcategory":"Health Practitioner",
            "type":"Services"
        },
        {
            "category":"Arena",
            "subcategory":"Sports Club",
            "type":"Entertainment"
        }
    ],
    "sg:phone":"+1 800 615 7352",
    "sg:postcode":"74133",
    "sg:province":"OK",
    "sg:tags":[
        "trainer",
        "control",
        "weight",
        "consultant",
        "program",
        "fitness",
        "physical"
    ],
    "sg:website":"http://tulsa.citysearch.com/profile/external/33556700/tulsa_ok/curves.html?publisher=yellowpages&reference_id=1&placement=ypwebsitemip",
    "wof:name":"Curves",
    "wof:placetype":"venue"
},
  "geometry": {"coordinates":[-95.904227,36.047283],"type":"Point"}
}