{
  "type": "Feature",
  "properties": {
    "iso:country":"US",
    "sg:address":"501 E Main St",
    "sg:city":"Ada",
    "sg:classifiers":[
        {
            "category":"Real Estate",
            "subcategory":"Real Estate Agent",
            "type":"Services"
        }
    ],
    "sg:phone":"+1 580 332 3737",
    "sg:postcode":"74820",
    "sg:province":"OK",
    "wof:name":"Mc Kee Real Estate",
    "wof:placetype":"venue"
},
  "geometry": {"coordinates":[-96.672201,34.774525],"type":"Point"}
}