{
  "type": "Feature",
  "properties": {
    "addr:full":"122 S 11th St Duncan OK 73533",
    "addr:housenumber":"122",
    "addr:postcode":"73533",
    "addr:street":"S 11Th St",
    "iso:country":"US",
    "sg:address":"122 S 11th St",
    "sg:city":"Duncan",
    "sg:classifiers":[
        {
            "category":"Professional",
            "subcategory":"Lawyer & Legal Services",
            "type":"Services"
        }
    ],
    "sg:phone":"+1 580 255 3300",
    "sg:postcode":"73533",
    "sg:province":"OK",
    "sg:tags":[
        "attorney"
    ],
    "wof:name":"William A Gossett",
    "wof:placetype":"venue"
},
  "geometry": {"coordinates":[-97.961414,34.500854],"type":"Point"}
}