{
  "type": "Feature",
  "properties": {
    "addr:full":"2401 Zion Park Yukon OK 73099",
    "addr:housenumber":"2401",
    "addr:postcode":"73099",
    "addr:street":"Zion Park",
    "iso:country":"US",
    "sg:address":"2401 Zion Park",
    "sg:city":"Yukon",
    "sg:classifiers":[
        {
            "category":"Education",
            "subcategory":"Special Training",
            "type":"Public Place"
        }
    ],
    "sg:phone":"+1 405 350 0489",
    "sg:postcode":"73099",
    "sg:province":"OK",
    "sg:tags":[
        "safety"
    ],
    "wof:name":"Pete Voogt",
    "wof:placetype":"venue"
},
  "geometry": {"coordinates":[-97.73677000000001,35.481235],"type":"Point"}
}