{
  "type": "Feature",
  "properties": {
    "iso:country":"US",
    "sg:address":"7403 S Pennsylvania Ave",
    "sg:city":"Oklahoma City",
    "sg:classifiers":[
        {
            "category":"Banks & Credit Unions",
            "subcategory":"Bank",
            "type":"Services"
        }
    ],
    "sg:phone":"+1 405 943 8002",
    "sg:postcode":"73159",
    "sg:province":"OK",
    "wof:name":"Mid First Bank",
    "wof:placetype":"venue"
},
  "geometry": {"coordinates":[-97.547943,35.392142],"type":"Point"}
}