{
  "type": "Feature",
  "properties": {
    "addr:full":"12 E Cherokee Ave Mcalester OK 74501",
    "addr:housenumber":"12",
    "addr:postcode":"74501",
    "addr:street":"E Cherokee Ave",
    "iso:country":"US",
    "sg:address":"12 E Cherokee Ave",
    "sg:city":"Mcalester",
    "sg:classifiers":[
        {
            "category":"Professional",
            "subcategory":"Lawyer & Legal Services",
            "type":"Services"
        }
    ],
    "sg:phone":"+1 918 423 2400",
    "sg:postcode":"74501",
    "sg:province":"OK",
    "sg:tags":[
        "attorney"
    ],
    "wof:name":"Harrison Law Firm",
    "wof:placetype":"venue"
},
  "geometry": {"coordinates":[-95.770377,34.92983],"type":"Point"}
}