{
  "type": "Feature",
  "properties": {
    "iso:country":"US",
    "sg:address":"1633 S Harvard Ave",
    "sg:city":"Tulsa",
    "sg:classifiers":[
        {
            "category":"Health Services",
            "subcategory":"Optometrist",
            "type":"Services"
        }
    ],
    "sg:phone":"+1 918 744 7638",
    "sg:postcode":"74112",
    "sg:province":"OK",
    "wof:name":"Harvard Vision Clinic",
    "wof:placetype":"venue"
},
  "geometry": {"coordinates":[-95.940279,36.1375],"type":"Point"}
}