{
  "type": "Feature",
  "properties": {
    "iso:country":"US",
    "sg:address":"19 W 1st St",
    "sg:city":"Edmond",
    "sg:classifiers":[
        {
            "category":"Mining & Drilling",
            "type":"Manufacturing & Wholesale Goods"
        }
    ],
    "sg:phone":"+1 405 348 8135",
    "sg:postcode":"73003",
    "sg:province":"OK",
    "sg:tags":[
        "development",
        "gas",
        "oil",
        "exploration"
    ],
    "wof:name":"Grande Oil & Gas Inc",
    "wof:placetype":"venue"
},
  "geometry": {"coordinates":[-97.48196,35.65435],"type":"Point"}
}