{
  "type": "Feature",
  "properties": {
    "iso:country":"US",
    "sg:address":"1115 W Elm Ave",
    "sg:city":"Duncan",
    "sg:classifiers":[
        {
            "category":"Organizations",
            "subcategory":"Religious Organization",
            "type":"Services"
        }
    ],
    "sg:phone":"+1 580 255 3488",
    "sg:postcode":"73533",
    "sg:province":"OK",
    "sg:tags":[
        "church"
    ],
    "wof:name":"Calvary Baptist Church",
    "wof:placetype":"venue"
},
  "geometry": {"coordinates":[-97.962896,34.499083],"type":"Point"}
}