{
  "type": "Feature",
  "properties": {
    "iso:country":"US",
    "sg:address":"14483 NE 23rd St",
    "sg:city":"Choctaw",
    "sg:classifiers":[
        {
            "category":"Banks & Credit Unions",
            "subcategory":"Bank",
            "type":"Services"
        }
    ],
    "sg:phone":"+1 405 390 6440",
    "sg:postcode":"73020",
    "sg:province":"OK",
    "sg:website":"www.bankone.com",
    "wof:name":"Bank One",
    "wof:placetype":"venue"
},
  "geometry": {"coordinates":[-97.282177,35.493212],"type":"Point"}
}