{
  "type": "Feature",
  "properties": {
    "addr:full":"213 Blakeley Ave Rush Springs OK 73082",
    "addr:housenumber":"213",
    "addr:postcode":"73082",
    "addr:street":"Blakeley Ave Rush",
    "iso:country":"US",
    "sg:address":"213 Blakeley Ave",
    "sg:city":"Rush Springs",
    "sg:classifiers":[
        {
            "category":"Restaurant",
            "type":"Food & Drink"
        }
    ],
    "sg:phone":"+1 580 476 9344",
    "sg:postcode":"73082",
    "sg:province":"OK",
    "wof:name":"Mainstreet Pizza",
    "wof:placetype":"venue"
},
  "geometry": {"coordinates":[-97.95474299999999,34.782711],"type":"Point"}
}