{
  "type": "Feature",
  "properties": {
    "addr:full":"410 S 2nd St Stilwell OK 74960",
    "addr:housenumber":"410",
    "addr:postcode":"74960",
    "addr:street":"S 2Nd St",
    "iso:country":"US",
    "sg:address":"410 S 2nd St",
    "sg:city":"Stilwell",
    "sg:classifiers":[
        {
            "category":"Retail",
            "subcategory":"Laundry & Dry Cleaning",
            "type":"Services"
        }
    ],
    "sg:phone":"+1 918 696 2828",
    "sg:postcode":"74960",
    "sg:province":"OK",
    "sg:tags":[
        "drycleaning",
        "plant"
    ],
    "wof:name":"Modern Cleaners",
    "wof:placetype":"venue"
},
  "geometry": {"coordinates":[-94.629085,35.810381],"type":"Point"}
}