{
  "type": "Feature",
  "properties": {
    "iso:country":"US",
    "sg:address":"8936 N 133rd E Ave",
    "sg:city":"Owasso",
    "sg:classifiers":[
        {
            "category":"Shopping",
            "type":"Retail Goods"
        }
    ],
    "sg:phone":"+1 918 274 0241",
    "sg:postcode":"74055",
    "sg:province":"OK",
    "sg:tags":[
        "merchandise"
    ],
    "wof:name":"Southern Charms",
    "wof:placetype":"venue"
},
  "geometry": {"coordinates":[-95.82654,36.284442],"type":"Point"}
}