{
  "type": "Feature",
  "properties": {
    "iso:country":"US",
    "sg:address":"802 N Canadian Ave",
    "sg:city":"Purcell",
    "sg:classifiers":[
        {
            "category":"Retail",
            "subcategory":"Auto Repair",
            "type":"Services"
        }
    ],
    "sg:phone":"+1 405 527 7971",
    "sg:postcode":"73080",
    "sg:province":"OK",
    "sg:tags":[
        "road"
    ],
    "wof:name":"A & A Tire Svc",
    "wof:placetype":"venue"
},
  "geometry": {"coordinates":[-97.358549,35.022624],"type":"Point"}
}