{
  "type": "Feature",
  "properties": {
    "iso:country":"US",
    "sg:address":"14363 SE 23rd St",
    "sg:city":"Choctaw",
    "sg:classifiers":[
        {
            "category":"Personal",
            "subcategory":"Beauty Salon",
            "type":"Services"
        }
    ],
    "sg:phone":"+1 405 390 4340",
    "sg:postcode":"73020",
    "sg:province":"OK",
    "sg:tags":[
        "shop"
    ],
    "wof:name":"Lovely Nails",
    "wof:placetype":"venue"
},
  "geometry": {"coordinates":[-97.277066,35.440839],"type":"Point"}
}