{
  "type": "Feature",
  "properties": {
    "addr:full":"8555 E 91st St Tulsa OK 74133",
    "addr:housenumber":"8555",
    "addr:postcode":"74133",
    "addr:street":"E 91St St",
    "iso:country":"US",
    "sg:address":"8555 E 91st St",
    "sg:city":"Tulsa",
    "sg:classifiers":[
        {
            "category":"Organizations",
            "subcategory":"Religious Organization",
            "type":"Services"
        }
    ],
    "sg:phone":"+1 918 250 7997",
    "sg:postcode":"74133",
    "sg:province":"OK",
    "sg:tags":[
        "church"
    ],
    "wof:name":"Calvary Bible Church",
    "wof:placetype":"venue"
},
  "geometry": {"coordinates":[-95.879434,36.031947],"type":"Point"}
}