{
  "type": "Feature",
  "properties": {
    "iso:country":"US",
    "sg:address":"11245 Thompson Ln",
    "sg:city":"Blanchard",
    "sg:classifiers":[
        {
            "category":"Retail",
            "subcategory":"Auto Repair",
            "type":"Services"
        }
    ],
    "sg:phone":"+1 405 485 2624",
    "sg:postcode":"73010",
    "sg:province":"OK",
    "sg:tags":[
        "general"
    ],
    "wof:name":"Cmj Trucking LLC",
    "wof:placetype":"venue"
},
  "geometry": {"coordinates":[-97.647376,35.094213],"type":"Point"}
}