{
  "type": "Feature",
  "properties": {
    "addr:full":"804 E Cherokee St Wagoner OK 74467",
    "addr:housenumber":"804",
    "addr:postcode":"74467",
    "addr:street":"E Cherokee St",
    "iso:country":"US",
    "sg:address":"804 E Cherokee St",
    "sg:city":"Wagoner",
    "sg:classifiers":[
        {
            "category":"Retail",
            "subcategory":"Repair Shop",
            "type":"Services"
        }
    ],
    "sg:phone":"+1 918 485 0171",
    "sg:postcode":"74467",
    "sg:province":"OK",
    "wof:name":"Artistry In Animals",
    "wof:placetype":"venue"
},
  "geometry": {"coordinates":[-95.36716800000001,35.959234],"type":"Point"}
}