{
  "type": "Feature",
  "properties": {
    "addr:full":"1805 W University Blvd Durant OK 74701",
    "addr:housenumber":"1805",
    "addr:postcode":"74701",
    "addr:street":"W University Blvd",
    "iso:country":"US",
    "sg:address":"1805 W University Blvd",
    "sg:city":"Durant",
    "sg:classifiers":[
        {
            "category":"Health Services",
            "subcategory":"Doctor",
            "type":"Services"
        }
    ],
    "sg:phone":"+1 580 920 0300",
    "sg:postcode":"74701",
    "sg:province":"OK",
    "sg:tags":[
        "osteopathic"
    ],
    "wof:name":"Southeastern Orthopedics",
    "wof:placetype":"venue"
},
  "geometry": {"coordinates":[-96.393562,34.004832],"type":"Point"}
}