{
  "type": "Feature",
  "properties": {
    "addr:full":"1841 Belle Isle Blvd Oklahoma City OK 73118",
    "addr:housenumber":"1841",
    "addr:postcode":"73118",
    "addr:street":"Belle Isle Blvd",
    "iso:country":"US",
    "sg:address":"1841 Belle Isle Blvd",
    "sg:city":"Oklahoma City",
    "sg:classifiers":[
        {
            "category":"Restaurant",
            "type":"Food & Drink"
        }
    ],
    "sg:menulink":"http://www.allmenus.com/ok/oklahoma-city/89655-moes-southwest-grill/menu/",
    "sg:phone":"+1 405 840 2200",
    "sg:postcode":"73118",
    "sg:province":"OK",
    "sg:tags":[
        "mexican"
    ],
    "wof:name":"Moe's Southwest Grill",
    "wof:placetype":"venue"
},
  "geometry": {"coordinates":[-97.54053999999999,35.524168],"type":"Point"}
}