{
  "type": "Feature",
  "properties": {
    "iso:country":"US",
    "sg:address":"9114 E 37th Ct",
    "sg:city":"Tulsa",
    "sg:classifiers":[
        {
            "category":"Health Services",
            "subcategory":"Doctor",
            "type":"Services"
        }
    ],
    "sg:phone":"+1 918 664 2292",
    "sg:postcode":"74145",
    "sg:province":"OK",
    "sg:tags":[
        "physician",
        "surgeon",
        "medical"
    ],
    "wof:name":"Ruth Crumley MD",
    "wof:placetype":"venue"
},
  "geometry": {"coordinates":[-95.872708,36.10946],"type":"Point"}
}