{
  "type": "Feature",
  "properties": {
    "iso:country":"US",
    "sg:address":"202 W Central Blvd",
    "sg:city":"Anadarko",
    "sg:classifiers":[
        {
            "category":"Shopping",
            "subcategory":"Gifts & Souvenirs",
            "type":"Retail Goods"
        }
    ],
    "sg:phone":"+1 405 247 2527",
    "sg:postcode":"73005",
    "sg:province":"OK",
    "sg:tags":[
        "florist"
    ],
    "wof:name":"Anadarko Floral Service",
    "wof:placetype":"venue"
},
  "geometry": {"coordinates":[-98.245347,35.072349],"type":"Point"}
}