{
  "type": "Feature",
  "properties": {
    "addr:full":"745 NW 32nd St Newcastle OK 73065",
    "addr:housenumber":"745",
    "addr:postcode":"73065",
    "addr:street":"Nw 32Nd St",
    "iso:country":"US",
    "sg:address":"745 NW 32nd St",
    "sg:city":"Newcastle",
    "sg:classifiers":[
        {
            "category":"Shopping",
            "subcategory":"Gifts & Souvenirs",
            "type":"Retail Goods"
        }
    ],
    "sg:phone":"+1 405 387 2247",
    "sg:postcode":"73065",
    "sg:province":"OK",
    "sg:tags":[
        "shop"
    ],
    "wof:name":"Enchanted Cottage",
    "wof:placetype":"venue"
},
  "geometry": {"coordinates":[-97.60549,35.291053],"type":"Point"}
}