{
  "type": "Feature",
  "properties": {
    "iso:country":"US",
    "sg:address":"125 W Main St",
    "sg:city":"Ada",
    "sg:classifiers":[
        {
            "category":"Personal",
            "type":"Services"
        }
    ],
    "sg:phone":"+1 580 310 9661",
    "sg:postcode":"74820",
    "sg:province":"OK",
    "sg:tags":[
        "consultant",
        "program",
        "health",
        "fitness"
    ],
    "sg:website":"www.chickasawlegislature.net",
    "wof:name":"Chickasaw Nation",
    "wof:placetype":"venue"
},
  "geometry": {"coordinates":[-96.679957,34.774419],"type":"Point"}
}