{
  "type": "Feature",
  "properties": {
    "iso:country":"US",
    "sg:address":"927 N Flood Ave",
    "sg:city":"Norman",
    "sg:classifiers":[
        {
            "category":"Personal",
            "subcategory":"Beauty Salon",
            "type":"Services"
        }
    ],
    "sg:phone":"+1 405 329 9086",
    "sg:postcode":"73069",
    "sg:province":"OK",
    "sg:tags":[
        "shop"
    ],
    "wof:name":"Klas Creations",
    "wof:placetype":"venue"
},
  "geometry": {"coordinates":[-97.45289200000001,35.226506],"type":"Point"}
}