{
  "type": "Feature",
  "properties": {
    "iso:country":"US",
    "sg:address":"606 SW D Ave",
    "sg:city":"Lawton",
    "sg:classifiers":[
        {
            "category":"Professional",
            "subcategory":"Accounting & Tax Preparation",
            "type":"Services"
        }
    ],
    "sg:phone":"+1 580 353 0238",
    "sg:postcode":"73501",
    "sg:province":"OK",
    "sg:tags":[
        "return"
    ],
    "wof:name":"Johnson Coleman R & Associates",
    "wof:placetype":"venue"
},
  "geometry": {"coordinates":[-98.39831700000001,34.60396],"type":"Point"}
}