{
  "type": "Feature",
  "properties": {
    "addr:full":"1518 W Elm St El Reno OK 73036",
    "addr:housenumber":"1518",
    "addr:postcode":"73036",
    "addr:street":"W Elm St",
    "iso:country":"US",
    "sg:address":"1518 W Elm St",
    "sg:city":"El Reno",
    "sg:classifiers":[
        {
            "category":"Retail",
            "subcategory":"Laundry & Dry Cleaning",
            "type":"Services"
        }
    ],
    "sg:phone":"+1 405 422 4505",
    "sg:postcode":"73036",
    "sg:province":"OK",
    "sg:tags":[
        "power"
    ],
    "wof:name":"Redlands Laundry",
    "wof:placetype":"venue"
},
  "geometry": {"coordinates":[-97.970754,35.522455],"type":"Point"}
}