{
  "type": "Feature",
  "properties": {
    "iso:country":"US",
    "sg:address":"132 NW 67th St",
    "sg:city":"Oklahoma City",
    "sg:classifiers":[
        {
            "category":"Professional",
            "subcategory":"Art Services",
            "type":"Services"
        }
    ],
    "sg:phone":"+1 405 842 3456",
    "sg:postcode":"73116",
    "sg:province":"OK",
    "sg:tags":[
        "photography",
        "aerial"
    ],
    "wof:name":"Ace Aerial Photography Inc",
    "wof:placetype":"venue"
},
  "geometry": {"coordinates":[-97.51582399999999,35.540407],"type":"Point"}
}