{
  "type": "Feature",
  "properties": {
    "iso:country":"US",
    "sg:address":"14308 US Hwy 177",
    "sg:city":"Shawnee",
    "sg:classifiers":[
        {
            "category":"Freight",
            "type":"Transportation"
        }
    ],
    "sg:phone":"+1 405 275 3666",
    "sg:postcode":"74804",
    "sg:province":"OK",
    "sg:tags":[
        "dry",
        "bulk",
        "trucking"
    ],
    "wof:name":"Flying B Transportation",
    "wof:placetype":"venue"
},
  "geometry": {"coordinates":[-96.9599,35.354349],"type":"Point"}
}