{
  "type": "Feature",
  "properties": {
    "iso:country":"US",
    "sg:address":"9916 E 43rd St",
    "sg:city":"Tulsa",
    "sg:classifiers":[
        {
            "category":"Health Services",
            "subcategory":"Nursing And Care Facility",
            "type":"Services"
        }
    ],
    "sg:phone":"+1 918 663 3234",
    "sg:postcode":"74146",
    "sg:province":"OK",
    "sg:tags":[
        "hospice"
    ],
    "wof:name":"Crossroads Hospice Of Oklahoma",
    "wof:placetype":"venue"
},
  "geometry": {"coordinates":[-95.863577,36.099309],"type":"Point"}
}