{
  "type": "Feature",
  "properties": {
    "iso:country":"US",
    "sg:address":"3625 NW 39th St",
    "sg:city":"Oklahoma City",
    "sg:classifiers":[
        {
            "category":"Organizations",
            "subcategory":"Membership Organization",
            "type":"Services"
        }
    ],
    "sg:phone":"+1 405 717 8200",
    "sg:postcode":"73112",
    "sg:province":"OK",
    "sg:tags":[
        "club",
        "automobile"
    ],
    "sg:website":"www.aaaoklahoma.com",
    "wof:name":"AAA Insurance",
    "wof:placetype":"venue"
},
  "geometry": {"coordinates":[-97.581907,35.511384],"type":"Point"}
}