{
  "type": "Feature",
  "properties": {
    "iso:country":"US",
    "sg:address":"723 W Park St",
    "sg:city":"Tecumseh",
    "sg:classifiers":[
        {
            "category":"Education",
            "subcategory":"School",
            "type":"Public Place"
        }
    ],
    "sg:phone":"+1 405 598 2967",
    "sg:postcode":"74873",
    "sg:province":"OK",
    "wof:name":"Krouch Elementary School",
    "wof:placetype":"venue"
},
  "geometry": {"coordinates":[-96.94542,35.258812],"type":"Point"}
}