{
  "type": "Feature",
  "properties": {
    "addr:full":"4201 W Memorial Rd Oklahoma City OK 73134",
    "addr:housenumber":"4201",
    "addr:postcode":"73134",
    "addr:street":"W Memorial Rd",
    "iso:country":"US",
    "sg:address":"4201 W Memorial Rd",
    "sg:city":"Oklahoma City",
    "sg:classifiers":[
        {
            "category":"Professional",
            "subcategory":"Management & Consulting",
            "type":"Services"
        }
    ],
    "sg:phone":"+1 405 466 2904",
    "sg:postcode":"73134",
    "sg:province":"OK",
    "sg:tags":[
        "education"
    ],
    "wof:name":"Hooks Mose Yvonne Dr",
    "wof:placetype":"venue"
},
  "geometry": {"coordinates":[-97.59805799999999,35.610265],"type":"Point"}
}