{
  "type": "Feature",
  "properties": {
    "iso:country":"US",
    "sg:address":"3417 Lytal Ln",
    "sg:city":"Edmond",
    "sg:classifiers":[
        {
            "category":"Professional",
            "subcategory":"Business Services",
            "type":"Services"
        }
    ],
    "sg:phone":"+1 405 348 2078",
    "sg:postcode":"73013",
    "sg:province":"OK",
    "wof:name":"Hays Group Inc",
    "wof:placetype":"venue"
},
  "geometry": {"coordinates":[-97.448097,35.620831],"type":"Point"}
}