{
  "type": "Feature",
  "properties": {
    "iso:country":"US",
    "sg:address":"1000 W Wilshire Blvd",
    "sg:city":"Oklahoma City",
    "sg:classifiers":[
        {
            "category":"Professional",
            "subcategory":"Employment Agencies",
            "type":"Services"
        }
    ],
    "sg:phone":"+1 405 840 1918",
    "sg:postcode":"73116",
    "sg:province":"OK",
    "sg:tags":[
        "help",
        "contractor"
    ],
    "wof:name":"On Assignment Lab Support",
    "wof:placetype":"venue"
},
  "geometry": {"coordinates":[-97.531459,35.551114],"type":"Point"}
}