{
  "type": "Feature",
  "properties": {
    "iso:country":"US",
    "sg:address":"4616 SE 29th St",
    "sg:city":"Oklahoma City",
    "sg:classifiers":[
        {
            "category":"Restaurant",
            "type":"Food & Drink"
        }
    ],
    "sg:phone":"+1 405 672 0534",
    "sg:postcode":"73115",
    "sg:province":"OK",
    "wof:name":"Taco Mayo",
    "wof:placetype":"venue"
},
  "geometry": {"coordinates":[-97.432939,35.435144],"type":"Point"}
}