{
  "type": "Feature",
  "properties": {
    "addr:full":"206 E Graham Ave Pryor OK 74361",
    "addr:housenumber":"206",
    "addr:postcode":"74361",
    "addr:street":"E Graham Ave",
    "iso:country":"US",
    "sg:address":"206 E Graham Ave",
    "sg:city":"Pryor",
    "sg:classifiers":[
        {
            "category":"Building & Trades",
            "subcategory":"Equipment Rental",
            "type":"Services"
        }
    ],
    "sg:phone":"+1 918 824 2222",
    "sg:postcode":"74361",
    "sg:province":"OK",
    "sg:tags":[
        "yard"
    ],
    "wof:name":"Stanley's Rent To Own",
    "wof:placetype":"venue"
},
  "geometry": {"coordinates":[-95.31698900000001,36.307668],"type":"Point"}
}