{
  "type": "Feature",
  "properties": {
    "iso:country":"US",
    "sg:address":"1107 W Main St",
    "sg:city":"Wilburton",
    "sg:classifiers":[
        {
            "category":"Health Services",
            "subcategory":"Doctor",
            "type":"Services"
        }
    ],
    "sg:phone":"+1 918 465 5681",
    "sg:postcode":"74578",
    "sg:province":"OK",
    "sg:tags":[
        "medical"
    ],
    "wof:name":"Richard Valbuena MD PC",
    "wof:placetype":"venue"
},
  "geometry": {"coordinates":[-95.32419400000001,34.913044],"type":"Point"}
}