{
  "type": "Feature",
  "properties": {
    "iso:country":"US",
    "sg:address":"1419 W London St",
    "sg:city":"El Reno",
    "sg:classifiers":[
        {
            "category":"Organizations",
            "subcategory":"Religious Organization",
            "type":"Services"
        }
    ],
    "sg:phone":"+1 405 262 3730",
    "sg:postcode":"73036",
    "sg:province":"OK",
    "wof:name":"Kingdom Hall Jhovahs Witnesses",
    "wof:placetype":"venue"
},
  "geometry": {"coordinates":[-97.970482,35.530377],"type":"Point"}
}