{
  "type": "Feature",
  "properties": {
    "iso:country":"US",
    "sg:address":"347 S Wilson St",
    "sg:city":"Vinita",
    "sg:classifiers":[
        {
            "category":"Autos & Motor Vehicles",
            "subcategory":"Automobile Sales",
            "type":"Retail Goods"
        }
    ],
    "sg:phone":"+1 918 256 5999",
    "sg:postcode":"74301",
    "sg:province":"OK",
    "sg:tags":[
        "car",
        "used",
        "dealer"
    ],
    "wof:name":"Vinita Motors",
    "wof:placetype":"venue"
},
  "geometry": {"coordinates":[-95.157116,36.634172],"type":"Point"}
}