{
  "type": "Feature",
  "properties": {
    "addr:full":"3295 Clarke St Choctaw OK 73020",
    "addr:housenumber":"3295",
    "addr:postcode":"73020",
    "addr:street":"Clarke St",
    "iso:country":"US",
    "sg:address":"3295 Clarke St",
    "sg:city":"Choctaw",
    "sg:classifiers":[
        {
            "category":"Wholesale",
            "subcategory":"Machinery & Supplies",
            "type":"Manufacturing & Wholesale Goods"
        }
    ],
    "sg:phone":"+1 405 390 1406",
    "sg:postcode":"73020",
    "sg:province":"OK",
    "sg:tags":[
        "equipment",
        "establishment"
    ],
    "wof:name":"A & H Salon Services Inc",
    "wof:placetype":"venue"
},
  "geometry": {"coordinates":[-97.26759,35.501248],"type":"Point"}
}