{
  "type": "Feature",
  "properties": {
    "iso:country":"US",
    "sg:address":"810 E 10th St",
    "sg:city":"Holdenville",
    "sg:classifiers":[
        {
            "category":"Professional",
            "subcategory":"Accounting & Tax Preparation",
            "type":"Services"
        }
    ],
    "sg:phone":"+1 405 379 9303",
    "sg:postcode":"74848",
    "sg:province":"OK",
    "sg:tags":[
        "return",
        "filing"
    ],
    "wof:name":"White White & Waldroup Svc",
    "wof:placetype":"venue"
},
  "geometry": {"coordinates":[-96.392005,35.079452],"type":"Point"}
}