{
  "type": "Feature",
  "properties": {
    "addr:full":"3017 Hemingford Ln Oklahoma City OK 73120",
    "addr:housenumber":"3017",
    "addr:postcode":"73120",
    "addr:street":"Hemingford Ln",
    "iso:country":"US",
    "sg:address":"3017 Hemingford Ln",
    "sg:city":"Oklahoma City",
    "sg:classifiers":[
        {
            "category":"Wholesale",
            "subcategory":"Computers",
            "type":"Manufacturing & Wholesale Goods"
        },
        {
            "category":"Manufacturing",
            "subcategory":"Metals",
            "type":"Manufacturing & Wholesale Goods"
        }
    ],
    "sg:phone":"+1 405 842 6548",
    "sg:postcode":"73120",
    "sg:province":"OK",
    "sg:tags":[
        "mfg",
        "tool",
        "processing",
        "datum",
        "equipment",
        "fabrication",
        "structural"
    ],
    "wof:name":"J R Lukeman & Associates Inc",
    "wof:placetype":"venue"
},
  "geometry": {"coordinates":[-97.56912800000001,35.5521],"type":"Point"}
}