{
  "type": "Feature",
  "properties": {
    "iso:country":"US",
    "sg:address":"839 N 92nd East Ave",
    "sg:city":"Tulsa",
    "sg:classifiers":[
        {
            "category":"Professional",
            "subcategory":"Business Services",
            "type":"Services"
        }
    ],
    "sg:phone":"+1 918 836 6439",
    "sg:postcode":"74115",
    "sg:province":"OK",
    "wof:name":"Charles Brixey Enterprises",
    "wof:placetype":"venue"
},
  "geometry": {"coordinates":[-95.873325,36.167605],"type":"Point"}
}