{
  "type": "Feature",
  "properties": {
    "iso:country":"US",
    "sg:address":"316 E Main St",
    "sg:city":"Pawhuska",
    "sg:classifiers":[
        {
            "category":"Food & Beverages",
            "subcategory":"Groceries & Convenience Stores",
            "type":"Retail Goods"
        }
    ],
    "sg:phone":"+1 918 287 4455",
    "sg:postcode":"74056",
    "sg:province":"OK",
    "wof:name":"Homeland 850",
    "wof:placetype":"venue"
},
  "geometry": {"coordinates":[-96.335714,36.662891],"type":"Point"}
}