{
  "type": "Feature",
  "properties": {
    "iso:country":"US",
    "sg:address":"1700 NW 16th St",
    "sg:city":"Oklahoma City",
    "sg:classifiers":[
        {
            "category":"Retail",
            "subcategory":"Auto Repair",
            "type":"Services"
        }
    ],
    "sg:phone":"+1 405 524 6677",
    "sg:postcode":"73106",
    "sg:province":"OK",
    "sg:tags":[
        "repairing",
        "automobile",
        "general"
    ],
    "wof:name":"Stanley's Garage",
    "wof:placetype":"venue"
},
  "geometry": {"coordinates":[-97.53923899999999,35.486001],"type":"Point"}
}