{
  "type": "Feature",
  "properties": {
    "addr:full":"143 W Main St Durant OK 74701",
    "addr:housenumber":"143",
    "addr:postcode":"74701",
    "addr:street":"W Main St",
    "iso:country":"US",
    "sg:address":"143 W Main St",
    "sg:city":"Durant",
    "sg:classifiers":[
        {
            "category":"Shopping",
            "subcategory":"Clothing, Apparel, & Fashions",
            "type":"Retail Goods"
        }
    ],
    "sg:phone":"+1 580 924 9569",
    "sg:postcode":"74701",
    "sg:province":"OK",
    "wof:name":"Teri's Plus Size Clothing",
    "wof:placetype":"venue"
},
  "geometry": {"coordinates":[-96.377166,33.990831],"type":"Point"}
}