{
  "type": "Feature",
  "properties": {
    "iso:country":"US",
    "sg:address":"3120 S Meridian Ave",
    "sg:city":"Oklahoma City",
    "sg:classifiers":[
        {
            "category":"Retail",
            "subcategory":"Auto Rental",
            "type":"Services"
        }
    ],
    "sg:phone":"+1 405 685 7726",
    "sg:postcode":"73119",
    "sg:province":"OK",
    "sg:tags":[
        "renting",
        "automobile"
    ],
    "sg:website":"www.national.com",
    "wof:name":"National Car Rental",
    "wof:placetype":"venue"
},
  "geometry": {"coordinates":[-97.600959,35.433061],"type":"Point"}
}