{
  "type": "Feature",
  "properties": {
    "iso:country":"US",
    "sg:address":"224 S Pine St",
    "sg:city":"Nowata",
    "sg:classifiers":[
        {
            "category":"Organizations",
            "subcategory":"Community Association",
            "type":"Services"
        }
    ],
    "sg:phone":"+1 918 273 2294",
    "sg:postcode":"74048",
    "sg:province":"OK",
    "wof:name":"Harmon Community Ctr Meeting",
    "wof:placetype":"venue"
},
  "geometry": {"coordinates":[-95.639422,36.697903],"type":"Point"}
}