{
  "type": "Feature",
  "properties": {
    "iso:country":"US",
    "sg:address":"2801 Parklawn Dr",
    "sg:city":"Oklahoma City",
    "sg:classifiers":[
        {
            "category":"Health Services",
            "subcategory":"Doctor",
            "type":"Services"
        }
    ],
    "sg:phone":"+1 405 733 8777",
    "sg:postcode":"73110",
    "sg:province":"OK",
    "sg:tags":[
        "physician",
        "surgeon"
    ],
    "wof:name":"Stanley J Dombek MD",
    "wof:placetype":"venue"
},
  "geometry": {"coordinates":[-97.393267,35.465067],"type":"Point"}
}