{
  "type": "Feature",
  "properties": {
    "iso:country":"US",
    "sg:address":"1111 S Eastern Ave",
    "sg:city":"Oklahoma City",
    "sg:classifiers":[
        {
            "category":"Shopping",
            "subcategory":"Jewelry",
            "type":"Retail Goods"
        }
    ],
    "sg:phone":"+1 405 619 1911",
    "sg:postcode":"73129",
    "sg:province":"OK",
    "sg:tags":[
        "jeweler"
    ],
    "wof:name":"Discount Jewelry & Gifts",
    "wof:placetype":"venue"
},
  "geometry": {"coordinates":[-97.476985,35.453506],"type":"Point"}
}