{
  "type": "Feature",
  "properties": {
    "addr:full":"383 Attucks Ave Afton OK 74301",
    "addr:housenumber":"383",
    "addr:postcode":"74301",
    "addr:street":"Attucks Ave",
    "iso:country":"US",
    "sg:address":"383 Attucks Ave",
    "sg:city":"Afton",
    "sg:classifiers":[
        {
            "category":"Utilities",
            "subcategory":"Water",
            "type":"Services"
        }
    ],
    "sg:phone":"+1 918 256 6865",
    "sg:postcode":"74301",
    "sg:province":"OK",
    "sg:tags":[
        "company",
        "sewage"
    ],
    "wof:name":"Gran-Tara Water Co",
    "wof:placetype":"venue"
},
  "geometry": {"coordinates":[-95.15190800000001,36.630797],"type":"Point"}
}