{
  "type": "Feature",
  "properties": {
    "addr:full":"3313 E 32nd Pl Tulsa OK 74135",
    "addr:housenumber":"3313",
    "addr:postcode":"74135",
    "addr:street":"E 32Nd Pl",
    "iso:country":"US",
    "sg:address":"3313 E 32nd Pl",
    "sg:city":"Tulsa",
    "sg:classifiers":[
        {
            "category":"Restaurant",
            "type":"Food & Drink"
        }
    ],
    "sg:phone":"+1 918 743 9669",
    "sg:postcode":"74135",
    "sg:province":"OK",
    "sg:tags":[
        "eating"
    ],
    "wof:name":"Bangkok Restaurant Inc",
    "wof:placetype":"venue"
},
  "geometry": {"coordinates":[-95.938151,36.116177],"type":"Point"}
}