{
  "type": "Feature",
  "properties": {
    "addr:full":"14351 E 445 Rd Claremore OK 74017",
    "addr:housenumber":"14351",
    "addr:postcode":"74017",
    "addr:street":"E 445 Rd",
    "iso:country":"US",
    "sg:address":"14351 E 445 Rd",
    "sg:city":"Claremore",
    "sg:classifiers":[
        {
            "category":"Building & Trades",
            "subcategory":"Construction",
            "type":"Services"
        }
    ],
    "sg:phone":"+1 918 341 7265",
    "sg:postcode":"74017",
    "sg:province":"OK",
    "wof:name":"Kirby Waterline Service",
    "wof:placetype":"venue"
},
  "geometry": {"coordinates":[-95.57469,36.372638],"type":"Point"}
}