{
  "type": "Feature",
  "properties": {
    "iso:country":"US",
    "sg:address":"7093 E 52nd St",
    "sg:city":"Tulsa",
    "sg:classifiers":[
        {
            "category":"Building & Trades",
            "subcategory":"Plumbing",
            "type":"Services"
        }
    ],
    "sg:phone":"+1 918 663 9809",
    "sg:postcode":"74145",
    "sg:province":"OK",
    "sg:tags":[
        "system",
        "contractor",
        "air conditioning"
    ],
    "wof:name":"Enochs Heating & Ac",
    "wof:placetype":"venue"
},
  "geometry": {"coordinates":[-95.895267,36.08933],"type":"Point"}
}