{
  "type": "Feature",
  "properties": {
    "iso:country":"US",
    "sg:address":"1875 N Highway 66",
    "sg:city":"Catoosa",
    "sg:classifiers":[
        {
            "category":"Health Services",
            "subcategory":"Dentist",
            "type":"Services"
        }
    ],
    "sg:phone":"+1 918 266 2906",
    "sg:postcode":"74015",
    "sg:province":"OK",
    "wof:name":"Dentures & Dental Services",
    "wof:placetype":"venue"
},
  "geometry": {"coordinates":[-95.744598,36.184601],"type":"Point"}
}