{
  "type": "Feature",
  "properties": {
    "iso:country":"US",
    "sg:address":"1401 N Main St",
    "sg:city":"Altus",
    "sg:classifiers":[
        {
            "category":"Shopping",
            "subcategory":"Computers & Home Electronics",
            "type":"Retail Goods"
        }
    ],
    "sg:phone":"+1 580 482 8712",
    "sg:postcode":"73521",
    "sg:province":"OK",
    "sg:tags":[
        "repair"
    ],
    "wof:name":"Audio Lab",
    "wof:placetype":"venue"
},
  "geometry": {"coordinates":[-99.333971,34.654745],"type":"Point"}
}