{
  "type": "Feature",
  "properties": {
    "iso:country":"US",
    "sg:address":"5051 S Lewis Ave",
    "sg:city":"Tulsa",
    "sg:classifiers":[
        {
            "category":"Banks & Credit Unions",
            "subcategory":"Financial Services",
            "type":"Services"
        }
    ],
    "sg:phone":"+1 918 747 4957",
    "sg:postcode":"74105",
    "sg:province":"OK",
    "sg:tags":[
        "investor"
    ],
    "wof:name":"First State Investors 5200 LLC",
    "wof:placetype":"venue"
},
  "geometry": {"coordinates":[-95.957967,36.090697],"type":"Point"}
}