{
  "type": "Feature",
  "properties": {
    "addr:full":"1117 SE 44th St Oklahoma City OK 73129",
    "addr:housenumber":"1117",
    "addr:postcode":"73129",
    "addr:street":"Se 44Th St",
    "iso:country":"US",
    "sg:address":"1117 SE 44th St",
    "sg:city":"Oklahoma City",
    "sg:classifiers":[
        {
            "category":"Retail",
            "subcategory":"Repair Shop",
            "type":"Services"
        }
    ],
    "sg:phone":"+1 405 631 5225",
    "sg:postcode":"73129",
    "sg:province":"OK",
    "sg:tags":[
        "lock",
        "locksmith"
    ],
    "wof:name":"Locksmith",
    "wof:placetype":"venue"
},
  "geometry": {"coordinates":[-97.491456,35.420898],"type":"Point"}
}