{
  "type": "Feature",
  "properties": {
    "iso:country":"US",
    "sg:address":"62 N Trenton Ave",
    "sg:city":"Tulsa",
    "sg:classifiers":[
        {
            "category":"Wholesale",
            "subcategory":"Fruits & Vegetables",
            "type":"Manufacturing & Wholesale Goods"
        }
    ],
    "sg:phone":"+1 918 587 8476",
    "sg:postcode":"74120",
    "sg:province":"OK",
    "wof:name":"Ridgway Abe Produce",
    "wof:placetype":"venue"
},
  "geometry": {"coordinates":[-95.969435,36.161592],"type":"Point"}
}