{
  "type": "Feature",
  "properties": {
    "iso:country":"US",
    "sg:address":"714 8th St",
    "sg:city":"Woodward",
    "sg:classifiers":[
        {
            "category":"Professional",
            "type":"Services"
        }
    ],
    "sg:phone":"+1 580 254 3328",
    "sg:postcode":"73801",
    "sg:province":"OK",
    "sg:tags":[
        "establishment"
    ],
    "wof:name":"Auto Dynamics",
    "wof:placetype":"venue"
},
  "geometry": {"coordinates":[-99.389287,36.440373],"type":"Point"}
}