{
  "type": "Feature",
  "properties": {
    "iso:country":"US",
    "sg:address":"4 Tiffany Plz",
    "sg:city":"Ardmore",
    "sg:classifiers":[
        {
            "category":"Wholesale",
            "subcategory":"Farm Supplies",
            "type":"Manufacturing & Wholesale Goods"
        }
    ],
    "sg:phone":"+1 580 223 0409",
    "sg:postcode":"73401",
    "sg:province":"OK",
    "wof:name":"Orscheln Farm & Home",
    "wof:placetype":"venue"
},
  "geometry": {"coordinates":[-97.15476,34.174076],"type":"Point"}
}