{
  "type": "Feature",
  "properties": {
    "addr:full":"419 E Oklahoma Ave Guthrie OK 73044",
    "addr:housenumber":"419",
    "addr:postcode":"73044",
    "addr:street":"E Oklahoma Ave",
    "iso:country":"US",
    "sg:address":"419 E Oklahoma Ave",
    "sg:city":"Guthrie",
    "sg:classifiers":[
        {
            "category":"Health Services",
            "subcategory":"Nursing And Care Facility",
            "type":"Services"
        }
    ],
    "sg:phone":"+1 405 282 0144",
    "sg:postcode":"73044",
    "sg:province":"OK",
    "sg:tags":[
        "home",
        "convalescent"
    ],
    "wof:name":"Golden Age Nursing Home",
    "wof:placetype":"venue"
},
  "geometry": {"coordinates":[-97.421297,35.877965],"type":"Point"}
}