{
  "type": "Feature",
  "properties": {
    "iso:country":"US",
    "sg:address":"10100 E 61st St",
    "sg:city":"Tulsa",
    "sg:classifiers":[
        {
            "category":"Education",
            "subcategory":"School",
            "type":"Public Place"
        }
    ],
    "sg:phone":"+1 918 459 2730",
    "sg:postcode":"74133",
    "sg:province":"OK",
    "sg:website":"www.unionps.org",
    "wof:name":"Union 6th & 7th Grade Ctr",
    "wof:placetype":"venue"
},
  "geometry": {"coordinates":[-95.861268,36.075328],"type":"Point"}
}