{
  "type": "Feature",
  "properties": {
    "iso:country":"US",
    "sg:address":"1511 S 14th St",
    "sg:city":"Clinton",
    "sg:classifiers":[
        {
            "category":"Building & Trades",
            "subcategory":"Construction",
            "type":"Services"
        }
    ],
    "sg:phone":"+1 580 323 0411",
    "sg:postcode":"73601",
    "sg:province":"OK",
    "sg:tags":[
        "underground",
        "trenching",
        "contractor"
    ],
    "wof:name":"Ricky Smith Ditching Svc",
    "wof:placetype":"venue"
},
  "geometry": {"coordinates":[-98.977011,35.490219],"type":"Point"}
}