{
  "type": "Feature",
  "properties": {
    "addr:full":"1200 W Grand Ave Ponca City OK 74601",
    "addr:housenumber":"1200",
    "addr:postcode":"74601",
    "addr:street":"W Grand Ave",
    "iso:country":"US",
    "sg:address":"1200 W Grand Ave",
    "sg:city":"Ponca City",
    "sg:classifiers":[
        {
            "category":"Organizations",
            "subcategory":"Community Association",
            "type":"Services"
        }
    ],
    "sg:phone":"+1 580 765 4128",
    "sg:postcode":"74601",
    "sg:province":"OK",
    "sg:tags":[
        "fraternal"
    ],
    "wof:name":"Masonic Lodge",
    "wof:placetype":"venue"
},
  "geometry": {"coordinates":[-97.098112,36.70399],"type":"Point"}
}