{
  "type": "Feature",
  "properties": {
    "addr:full":"5839 NW 50th St Oklahoma City OK 73122",
    "addr:housenumber":"5839",
    "addr:postcode":"73122",
    "addr:street":"Nw 50Th St",
    "iso:country":"US",
    "sg:address":"5839 NW 50th St",
    "sg:city":"Oklahoma City",
    "sg:classifiers":[
        {
            "category":"Banks & Credit Unions",
            "subcategory":"Bank",
            "type":"Services"
        }
    ],
    "sg:phone":"+1 405 495 8610",
    "sg:postcode":"73122",
    "sg:province":"OK",
    "sg:tags":[
        "money",
        "order"
    ],
    "wof:name":"Mexico Transfers Inc",
    "wof:placetype":"venue"
},
  "geometry": {"coordinates":[-97.616321,35.522372],"type":"Point"}
}