{
  "type": "Feature",
  "properties": {
    "iso:country":"US",
    "sg:address":"1144 N Flood Ave",
    "sg:city":"Norman",
    "sg:classifiers":[
        {
            "category":"Manufacturing",
            "subcategory":"Signs",
            "type":"Manufacturing & Wholesale Goods"
        }
    ],
    "sg:phone":"+1 405 364 1700",
    "sg:postcode":"73069",
    "sg:province":"OK",
    "sg:tags":[
        "advertising",
        "specialty"
    ],
    "wof:name":"Sublime Signs",
    "wof:placetype":"venue"
},
  "geometry": {"coordinates":[-97.453266,35.23024],"type":"Point"}
}