{
  "type": "Feature",
  "properties": {
    "iso:country":"US",
    "sg:address":"603 Elgin St",
    "sg:city":"Muskogee",
    "sg:classifiers":[
        {
            "category":"Autos & Motor Vehicles",
            "subcategory":"Motorcycle Sales",
            "type":"Retail Goods"
        }
    ],
    "sg:phone":"+1 918 682 9213",
    "sg:postcode":"74401",
    "sg:province":"OK",
    "wof:name":"Cycle Center Salvage & Repair",
    "wof:placetype":"venue"
},
  "geometry": {"coordinates":[-95.377895,35.747224],"type":"Point"}
}