{
  "type": "Feature",
  "properties": {
    "iso:country":"US",
    "sg:address":"500 N Meridian Ave",
    "sg:city":"Oklahoma City",
    "sg:classifiers":[
        {
            "category":"Professional",
            "subcategory":"Management & Consulting",
            "type":"Services"
        }
    ],
    "sg:phone":"+1 405 942 2180",
    "sg:postcode":"73107",
    "sg:province":"OK",
    "sg:tags":[
        "consultant",
        "educational"
    ],
    "wof:name":"Carl Albert State College",
    "wof:placetype":"venue"
},
  "geometry": {"coordinates":[-97.601027,35.47112],"type":"Point"}
}