{
  "type": "Feature",
  "properties": {
    "iso:country":"US",
    "sg:address":"5501 98th Ave NE",
    "sg:city":"Norman",
    "sg:classifiers":[
        {
            "category":"Building & Trades",
            "subcategory":"Construction",
            "type":"Services"
        }
    ],
    "sg:phone":"+1 405 321 1158",
    "sg:postcode":"73026",
    "sg:province":"OK",
    "sg:tags":[
        "concrete",
        "contractor",
        "nonresidential"
    ],
    "wof:name":"Chaffin Construction Co",
    "wof:placetype":"venue"
},
  "geometry": {"coordinates":[-97.298257,35.286513],"type":"Point"}
}