{
  "type": "Feature",
  "properties": {
    "addr:full":"825 NW 4th St Oklahoma City OK 73106",
    "addr:housenumber":"825",
    "addr:postcode":"73106",
    "addr:street":"Nw 4Th St",
    "iso:country":"US",
    "sg:address":"825 NW 4th St",
    "sg:city":"Oklahoma City",
    "sg:classifiers":[
        {
            "category":"Banks & Credit Unions",
            "subcategory":"Bank",
            "type":"Services"
        }
    ],
    "sg:phone":"+1 405 232 4112",
    "sg:postcode":"73106",
    "sg:province":"OK",
    "sg:tags":[
        "personal",
        "institution"
    ],
    "wof:name":"York Investments Company",
    "wof:placetype":"venue"
},
  "geometry": {"coordinates":[-97.526883,35.472228],"type":"Point"}
}