{
  "type": "Feature",
  "properties": {
    "iso:country":"US",
    "sg:address":"229 W 11th St",
    "sg:city":"Tulsa",
    "sg:classifiers":[
        {
            "category":"Retail",
            "subcategory":"Laundry & Dry Cleaning",
            "type":"Services"
        }
    ],
    "sg:phone":"+1 918 585 9733",
    "sg:postcode":"74119",
    "sg:province":"OK",
    "sg:tags":[
        "cleaners"
    ],
    "wof:name":"Eleventh Street Cleaners",
    "wof:placetype":"venue"
},
  "geometry": {"coordinates":[-95.990342,36.146061],"type":"Point"}
}