{
  "type": "Feature",
  "properties": {
    "addr:full":"5206 S Harvard Ave Tulsa OK 74135",
    "addr:housenumber":"5206",
    "addr:postcode":"74135",
    "addr:street":"S Harvard Ave",
    "iso:country":"US",
    "sg:address":"5206 S Harvard Ave",
    "sg:city":"Tulsa",
    "sg:classifiers":[
        {
            "category":"Organizations",
            "subcategory":"Community Association",
            "type":"Services"
        }
    ],
    "sg:phone":"+1 918 742 7366",
    "sg:postcode":"74135",
    "sg:province":"OK",
    "wof:name":"Harvard Pk Vlg Nghborhood Assn",
    "wof:placetype":"venue"
},
  "geometry": {"coordinates":[-95.94019,36.08567],"type":"Point"}
}