{
  "type": "Feature",
  "properties": {
    "iso:country":"US",
    "sg:address":"417 E Tamarack Rd",
    "sg:city":"Altus",
    "sg:classifiers":[
        {
            "category":"Personal",
            "subcategory":"Beauty Salon",
            "type":"Services"
        }
    ],
    "sg:phone":"+1 580 477 1450",
    "sg:postcode":"73521",
    "sg:province":"OK",
    "sg:tags":[
        "shop"
    ],
    "wof:name":"Reflections Beauty Shoppe",
    "wof:placetype":"venue"
},
  "geometry": {"coordinates":[-99.32973,34.666854],"type":"Point"}
}