{
  "type": "Feature",
  "properties": {
    "iso:country":"US",
    "sg:address":"8484 NW 39th Expy",
    "sg:city":"Bethany",
    "sg:classifiers":[
        {
            "category":"Building & Trades",
            "subcategory":"Plumbing",
            "type":"Services"
        }
    ],
    "sg:phone":"+1 405 789 5969",
    "sg:postcode":"73008",
    "sg:province":"OK",
    "sg:tags":[
        "conditioning",
        "air",
        "system",
        "contractor"
    ],
    "wof:name":"T S Heat & Air",
    "wof:placetype":"venue"
},
  "geometry": {"coordinates":[-97.65881,35.514816],"type":"Point"}
}