{
  "type": "Feature",
  "properties": {
    "addr:full":"111 E Main St Wilburton OK 74578",
    "addr:housenumber":"111",
    "addr:postcode":"74578",
    "addr:street":"E Main St",
    "iso:country":"US",
    "sg:address":"111 E Main St",
    "sg:city":"Wilburton",
    "sg:classifiers":[
        {
            "category":"Shopping",
            "subcategory":"Discount & Variety Stores",
            "type":"Retail Goods"
        }
    ],
    "sg:phone":"+1 918 465 5561",
    "sg:postcode":"74578",
    "sg:province":"OK",
    "wof:name":"Little Dixie Outlet",
    "wof:placetype":"venue"
},
  "geometry": {"coordinates":[-95.30788099999999,34.918874],"type":"Point"}
}