{
  "type": "Feature",
  "properties": {
    "iso:country":"US",
    "sg:address":"7752 E Brit Dr",
    "sg:city":"Claremore",
    "sg:classifiers":[
        {
            "category":"Professional",
            "type":"Services"
        }
    ],
    "sg:phone":"+1 918 266 7779",
    "sg:postcode":"74019",
    "sg:province":"OK",
    "sg:tags":[
        "establishment"
    ],
    "wof:name":"R D Hughes Ofc",
    "wof:placetype":"venue"
},
  "geometry": {"coordinates":[-95.69747,36.24402],"type":"Point"}
}