{
  "type": "Feature",
  "properties": {
    "iso:country":"US",
    "sg:address":"1250 E Gate Rd",
    "sg:city":"Newkirk",
    "sg:classifiers":[
        {
            "category":"Building & Trades",
            "subcategory":"Construction",
            "type":"Services"
        }
    ],
    "sg:phone":"+1 580 362 2800",
    "sg:postcode":"74647",
    "sg:province":"OK",
    "sg:tags":[
        "downspouts",
        "gutter"
    ],
    "wof:name":"Seamless Guttering Co",
    "wof:placetype":"venue"
},
  "geometry": {"coordinates":[-97.059054,36.94136],"type":"Point"}
}