{
  "type": "Feature",
  "properties": {
    "addr:full":"1730 E Carl Albert Pkwy Bache OK 74501",
    "addr:housenumber":"1730",
    "addr:postcode":"74501",
    "addr:street":"E Carl Albert Pkwy",
    "iso:country":"US",
    "sg:address":"1730 E Carl Albert Pkwy",
    "sg:city":"Bache",
    "sg:classifiers":[
        {
            "category":"Personal",
            "subcategory":"Beauty Salon",
            "type":"Services"
        }
    ],
    "sg:phone":"+1 918 423 4549",
    "sg:postcode":"74501",
    "sg:province":"OK",
    "sg:tags":[
        "shop",
        "manicuring"
    ],
    "wof:name":"Real Nails",
    "wof:placetype":"venue"
},
  "geometry": {"coordinates":[-95.74323,34.927435],"type":"Point"}
}