{
  "type": "Feature",
  "properties": {
    "addr:full":"415 S 7th St Ponca City OK 74601",
    "addr:housenumber":"415",
    "addr:postcode":"74601",
    "addr:street":"S 7Th St",
    "iso:country":"US",
    "sg:address":"415 S 7th St",
    "sg:city":"Ponca City",
    "sg:classifiers":[
        {
            "category":"Education",
            "subcategory":"School",
            "type":"Public Place"
        }
    ],
    "sg:phone":"+1 580 765 4387",
    "sg:postcode":"74601",
    "sg:province":"OK",
    "wof:name":"St Mary's School",
    "wof:placetype":"venue"
},
  "geometry": {"coordinates":[-97.076088,36.700199],"type":"Point"}
}