{
  "type": "Feature",
  "properties": {
    "iso:country":"US",
    "sg:address":"8125 E 51st St",
    "sg:city":"Tulsa",
    "sg:classifiers":[
        {
            "category":"Food & Beverages",
            "subcategory":"Groceries & Convenience Stores",
            "type":"Retail Goods"
        }
    ],
    "sg:phone":"+1 918 622 9900",
    "sg:postcode":"74145",
    "sg:province":"OK",
    "wof:name":"Luxor Mini Market",
    "wof:placetype":"venue"
},
  "geometry": {"coordinates":[-95.884497,36.090008],"type":"Point"}
}