{
  "type": "Feature",
  "properties": {
    "addr:full":"1610 N Main St Guymon OK 73942",
    "addr:housenumber":"1610",
    "addr:postcode":"73942",
    "addr:street":"N Main St",
    "iso:country":"US",
    "sg:address":"1610 N Main St",
    "sg:city":"Guymon",
    "sg:classifiers":[
        {
            "category":"Shopping",
            "subcategory":"Department Store",
            "type":"Retail Goods"
        }
    ],
    "sg:phone":"+1 580 338 4488",
    "sg:postcode":"73942",
    "sg:province":"OK",
    "sg:tags":[
        "shop"
    ],
    "sg:website":"www.familydollar.com",
    "wof:name":"Family Dollar Store",
    "wof:placetype":"venue"
},
  "geometry": {"coordinates":[-101.481461,36.697111],"type":"Point"}
}