{
  "type": "Feature",
  "properties": {
    "iso:country":"US",
    "sg:address":"35987 W 131st St S",
    "sg:city":"Bristow",
    "sg:classifiers":[
        {
            "category":"Wholesale",
            "subcategory":"Machinery & Supplies",
            "type":"Manufacturing & Wholesale Goods"
        }
    ],
    "sg:phone":"+1 918 352 9290",
    "sg:postcode":"74010",
    "sg:province":"OK",
    "sg:tags":[
        "truck"
    ],
    "wof:name":"Leon's Forklift Sales & Svc",
    "wof:placetype":"venue"
},
  "geometry": {"coordinates":[-96.39567,35.974091],"type":"Point"}
}