{
  "type": "Feature",
  "properties": {
    "iso:country":"US",
    "sg:address":"7905 Indian Meridian",
    "sg:city":"Choctaw",
    "sg:classifiers":[
        {
            "category":"Organizations",
            "subcategory":"Religious Organization",
            "type":"Services"
        }
    ],
    "sg:phone":"+1 405 390 9475",
    "sg:postcode":"73020",
    "sg:province":"OK",
    "wof:name":"Solid Rock Community Church",
    "wof:placetype":"venue"
},
  "geometry": {"coordinates":[-97.247476,35.388239],"type":"Point"}
}