{
  "type": "Feature",
  "properties": {
    "iso:country":"US",
    "sg:address":"1980 N Westminster Rd",
    "sg:city":"Oklahoma City",
    "sg:classifiers":[
        {
            "category":"Building & Trades",
            "subcategory":"Plumbing",
            "type":"Services"
        }
    ],
    "sg:phone":"+1 405 769 3195",
    "sg:postcode":"73141",
    "sg:province":"OK",
    "sg:tags":[
        "plumbing",
        "contractor"
    ],
    "wof:name":"Red Plains Plumbing",
    "wof:placetype":"venue"
},
  "geometry": {"coordinates":[-97.335566,35.488383],"type":"Point"}
}