{
  "type": "Feature",
  "properties": {
    "addr:full":"701 W Dewey Ave Sapulpa OK 74066",
    "addr:housenumber":"701",
    "addr:postcode":"74066",
    "addr:street":"W Dewey Ave",
    "iso:country":"US",
    "sg:address":"701 W Dewey Ave",
    "sg:city":"Sapulpa",
    "sg:classifiers":[
        {
            "category":"Autos & Motor Vehicles",
            "subcategory":"Auto Supplies",
            "type":"Retail Goods"
        }
    ],
    "sg:phone":"+1 918 248 5670",
    "sg:postcode":"74066",
    "sg:province":"OK",
    "wof:name":"S & J Discount Tires Sapulpa",
    "wof:placetype":"venue"
},
  "geometry": {"coordinates":[-96.121745,35.998378],"type":"Point"}
}