{
  "type": "Feature",
  "properties": {
    "iso:country":"US",
    "sg:address":"107 S 1st St",
    "sg:city":"Davis",
    "sg:classifiers":[
        {
            "category":"Freight",
            "type":"Transportation"
        }
    ],
    "sg:phone":"+1 580 369 5484",
    "sg:postcode":"73030",
    "sg:province":"OK",
    "sg:tags":[
        "trucking"
    ],
    "wof:name":"Chris Foster Trucking",
    "wof:placetype":"venue"
},
  "geometry": {"coordinates":[-97.121739,34.503209],"type":"Point"}
}