{
  "type": "Feature",
  "properties": {
    "addr:full":"4211 N Barnes Ave Oklahoma City OK 73112",
    "addr:housenumber":"4211",
    "addr:postcode":"73112",
    "addr:street":"N Barnes Ave",
    "iso:country":"US",
    "sg:address":"4211 N Barnes Ave",
    "sg:city":"Oklahoma City",
    "sg:classifiers":[
        {
            "category":"Utilities",
            "subcategory":"Telephone",
            "type":"Services"
        }
    ],
    "sg:phone":"+1 405 945 0800",
    "sg:postcode":"73112",
    "sg:province":"OK",
    "sg:tags":[
        "company"
    ],
    "wof:name":"Travis Voice & Data",
    "wof:placetype":"venue"
},
  "geometry": {"coordinates":[-97.549209,35.51448],"type":"Point"}
}