{
  "type": "Feature",
  "properties": {
    "iso:country":"US",
    "sg:address":"1113 Jet Dr",
    "sg:city":"Oklahoma City",
    "sg:classifiers":[
        {
            "category":"Building & Trades",
            "subcategory":"Pest Control",
            "type":"Services"
        }
    ],
    "sg:phone":"+1 405 733 4675",
    "sg:postcode":"73110",
    "sg:province":"OK",
    "sg:tags":[
        "residential",
        "remodeling"
    ],
    "wof:name":"Clarks At Your Service",
    "wof:placetype":"venue"
},
  "geometry": {"coordinates":[-97.40718200000001,35.446357],"type":"Point"}
}