{
  "type": "Feature",
  "properties": {
    "iso:country":"US",
    "sg:address":"410 N 30th St",
    "sg:city":"Enid",
    "sg:classifiers":[
        {
            "category":"Health Services",
            "subcategory":"Nursing And Care Facility",
            "type":"Services"
        }
    ],
    "sg:phone":"+1 580 237 1973",
    "sg:postcode":"73701",
    "sg:province":"OK",
    "sg:tags":[
        "skilled"
    ],
    "wof:name":"Blue Dolphin Health MGT LLC",
    "wof:placetype":"venue"
},
  "geometry": {"coordinates":[-97.83685800000001,36.40158],"type":"Point"}
}