{
  "type": "Feature",
  "properties": {
    "addr:full":"1400 College Ave Norman OK 73072",
    "addr:housenumber":"1400",
    "addr:postcode":"73072",
    "addr:street":"College Ave",
    "iso:country":"US",
    "sg:address":"1400 College Ave",
    "sg:city":"Norman",
    "sg:classifiers":[
        {
            "category":"Organizations",
            "subcategory":"Community Association",
            "type":"Services"
        }
    ],
    "sg:phone":"+1 405 701 8071",
    "sg:postcode":"73072",
    "sg:province":"OK",
    "sg:tags":[
        "sorority",
        "fraternity"
    ],
    "wof:name":"Phi Delta Theta",
    "wof:placetype":"venue"
},
  "geometry": {"coordinates":[-97.44900699999999,35.197589],"type":"Point"}
}