{
  "type": "Feature",
  "properties": {
    "iso:country":"US",
    "sg:address":"4327 NW 23rd St",
    "sg:city":"Oklahoma City",
    "sg:classifiers":[
        {
            "category":"Home & Garden",
            "subcategory":"Carpets & Floor Coverings",
            "type":"Retail Goods"
        }
    ],
    "sg:phone":"+1 405 943 1715",
    "sg:postcode":"73107",
    "sg:province":"OK",
    "wof:name":"Cornelson Flooring",
    "wof:placetype":"venue"
},
  "geometry": {"coordinates":[-97.598354,35.493386],"type":"Point"}
}