{
  "type": "Feature",
  "properties": {
    "iso:country":"US",
    "sg:address":"803 US Hwy 69",
    "sg:city":"Stringtown",
    "sg:classifiers":[
        {
            "category":"Autos & Motor Vehicles",
            "subcategory":"Automobile Sales",
            "type":"Retail Goods"
        }
    ],
    "sg:phone":"+1 580 346 7342",
    "sg:postcode":"74501",
    "sg:province":"OK",
    "sg:tags":[
        "car",
        "dealer"
    ],
    "wof:name":"Massey Auto Sales",
    "wof:placetype":"venue"
},
  "geometry": {"coordinates":[-95.747748,34.904563],"type":"Point"}
}