{
  "type": "Feature",
  "properties": {
    "iso:country":"US",
    "sg:address":"6151 S Yale Ave",
    "sg:city":"Tulsa",
    "sg:classifiers":[
        {
            "category":"Health Services",
            "subcategory":"Doctor",
            "type":"Services"
        }
    ],
    "sg:phone":"+1 918 494 8500",
    "sg:postcode":"74136",
    "sg:province":"OK",
    "sg:tags":[
        "physician",
        "surgeon"
    ],
    "sg:website":"www.cardiologytulsa.com",
    "wof:name":"Cardiology Of Tulsa",
    "wof:placetype":"venue"
},
  "geometry": {"coordinates":[-95.922078,36.074435],"type":"Point"}
}