{
  "type": "Feature",
  "properties": {
    "iso:country":"US",
    "sg:address":"1501 Trio Ln",
    "sg:city":"Ponca City",
    "sg:classifiers":[
        {
            "category":"Building & Trades",
            "subcategory":"Equipment Rental",
            "type":"Services"
        }
    ],
    "sg:phone":"+1 580 762 1958",
    "sg:postcode":"74604",
    "sg:province":"OK",
    "wof:name":"Neilsons Rentals",
    "wof:placetype":"venue"
},
  "geometry": {"coordinates":[-97.05047999999999,36.71955],"type":"Point"}
}