{
  "type": "Feature",
  "properties": {
    "addr:full":"1202 W Oxford Ave Enid OK 73701",
    "addr:housenumber":"1202",
    "addr:postcode":"73701",
    "addr:street":"W Oxford Ave",
    "iso:country":"US",
    "sg:address":"1202 W Oxford Ave",
    "sg:city":"Enid",
    "sg:classifiers":[
        {
            "category":"Organizations",
            "subcategory":"Religious Organization",
            "type":"Services"
        }
    ],
    "sg:phone":"+1 580 233 1818",
    "sg:postcode":"73701",
    "sg:province":"OK",
    "sg:tags":[
        "church"
    ],
    "wof:name":"Central Assembly of God",
    "wof:placetype":"venue"
},
  "geometry": {"coordinates":[-97.891882,36.427235],"type":"Point"}
}