{
  "type": "Feature",
  "properties": {
    "iso:country":"US",
    "sg:address":"2728 S Portland Ave",
    "sg:city":"Oklahoma City",
    "sg:classifiers":[
        {
            "category":"Organizations",
            "subcategory":"Religious Organization",
            "type":"Services"
        }
    ],
    "sg:phone":"+1 405 682 2780",
    "sg:postcode":"73108",
    "sg:province":"OK",
    "wof:name":"Jordan Baptist Church",
    "wof:placetype":"venue"
},
  "geometry": {"coordinates":[-97.583335,35.43886],"type":"Point"}
}