{
  "type": "Feature",
  "properties": {
    "iso:country":"US",
    "sg:address":"8007 S Sheridan Rd",
    "sg:city":"Tulsa",
    "sg:classifiers":[
        {
            "category":"Education",
            "subcategory":"Special Training",
            "type":"Public Place"
        }
    ],
    "sg:phone":"+1 918 493 1112",
    "sg:postcode":"74133",
    "sg:province":"OK",
    "sg:tags":[
        "school",
        "instruction",
        "art"
    ],
    "wof:name":"Upscale Artist",
    "wof:placetype":"venue"
},
  "geometry": {"coordinates":[-95.904168,36.047435],"type":"Point"}
}