{
  "type": "Feature",
  "properties": {
    "iso:country":"US",
    "sg:address":"901 NW 71st Pl",
    "sg:city":"Oklahoma City",
    "sg:phone":"+1 405 843 1833",
    "sg:postcode":"73116",
    "sg:province":"OK",
    "sg:tags":[
        "oil"
    ],
    "wof:name":"Fentress Oil Co Inc",
    "wof:placetype":"venue"
},
  "geometry": {"coordinates":[-97.529008,35.544669],"type":"Point"}
}