{
  "type": "Feature",
  "properties": {
    "iso:country":"US",
    "sg:address":"14300 N Western Ave",
    "sg:city":"Edmond",
    "sg:classifiers":[
        {
            "category":"Social Services",
            "subcategory":"Child Care",
            "type":"Services"
        }
    ],
    "sg:phone":"+1 405 748 4424",
    "sg:postcode":"73013",
    "sg:province":"OK",
    "sg:tags":[
        "day"
    ],
    "wof:name":"New Horizons Child Dev Ctr LLC",
    "wof:placetype":"venue"
},
  "geometry": {"coordinates":[-97.531568,35.611789],"type":"Point"}
}