{
  "type": "Feature",
  "properties": {
    "addr:full":"16 E Main St Yukon OK 73099",
    "addr:housenumber":"16",
    "addr:postcode":"73099",
    "addr:street":"E Main St",
    "iso:country":"US",
    "sg:address":"16 E Main St",
    "sg:city":"Yukon",
    "sg:classifiers":[
        {
            "category":"Home & Garden",
            "subcategory":"Furniture",
            "type":"Retail Goods"
        }
    ],
    "sg:phone":"+1 405 354 8460",
    "sg:postcode":"73099",
    "sg:province":"OK",
    "wof:name":"Pottery Outlet & More",
    "wof:placetype":"venue"
},
  "geometry": {"coordinates":[-97.742329,35.507763],"type":"Point"}
}