{
  "type": "Feature",
  "properties": {
    "iso:country":"US",
    "sg:address":"1823 S Chester St",
    "sg:city":"Stillwater",
    "sg:classifiers":[
        {
            "category":"Real Estate",
            "subcategory":"Real Estate Operator",
            "type":"Services"
        }
    ],
    "sg:phone":"+1 405 372 4873",
    "sg:postcode":"74074",
    "sg:province":"OK",
    "sg:tags":[
        "mobile",
        "home",
        "site"
    ],
    "wof:name":"Affordable Residential Communi",
    "wof:placetype":"venue"
},
  "geometry": {"coordinates":[-97.054508,36.105221],"type":"Point"}
}