{
  "type": "Feature",
  "properties": {
    "iso:country":"US",
    "sg:address":"2828 Parklawn Dr",
    "sg:city":"Midwest City",
    "sg:classifiers":[
        {
            "category":"Wholesale",
            "subcategory":"Medical Equipment & Supplies",
            "type":"Manufacturing & Wholesale Goods"
        }
    ],
    "sg:phone":"+1 405 736 0955",
    "sg:postcode":"73110",
    "sg:province":"OK",
    "sg:tags":[
        "hospital"
    ],
    "sg:website":"www.lincare.com",
    "wof:name":"Lincare",
    "wof:placetype":"venue"
},
  "geometry": {"coordinates":[-97.39321,35.464126],"type":"Point"}
}