{
  "type": "Feature",
  "properties": {
    "iso:country":"US",
    "sg:address":"9109 E Admiral Pl",
    "sg:city":"Tulsa",
    "sg:classifiers":[
        {
            "category":"Home & Garden",
            "subcategory":"Mobile Homes",
            "type":"Retail Goods"
        }
    ],
    "sg:phone":"+1 918 836 3806",
    "sg:postcode":"74115",
    "sg:province":"OK",
    "wof:name":"Solitaire Homes Of Tulsa",
    "wof:placetype":"venue"
},
  "geometry": {"coordinates":[-95.874352,36.160788],"type":"Point"}
}