{
  "type": "Feature",
  "properties": {
    "iso:country":"US",
    "sg:address":"16 Constitution Ave",
    "sg:city":"Altus",
    "sg:classifiers":[
        {
            "category":"Autos & Motor Vehicles",
            "subcategory":"Automobile Sales",
            "type":"Retail Goods"
        }
    ],
    "sg:phone":"+1 580 482 6748",
    "sg:postcode":"73521",
    "sg:province":"OK",
    "sg:tags":[
        "used"
    ],
    "wof:name":"Race Cars Unlimited",
    "wof:placetype":"venue"
},
  "geometry": {"coordinates":[-99.320055,34.679595],"type":"Point"}
}