{
  "type": "Feature",
  "properties": {
    "addr:full":"915 N 8th St Duncan OK 73533",
    "addr:housenumber":"915",
    "addr:postcode":"73533",
    "addr:street":"N 8Th St",
    "iso:country":"US",
    "sg:address":"915 N 8th St",
    "sg:city":"Duncan",
    "sg:classifiers":[
        {
            "category":"Sports & Exercise",
            "subcategory":"Gym",
            "type":"Entertainment"
        }
    ],
    "sg:phone":"+1 580 255 8215",
    "sg:postcode":"73533",
    "sg:province":"OK",
    "sg:tags":[
        "fitness",
        "physical",
        "facility"
    ],
    "wof:name":"Ancient Free & Accepted M",
    "wof:placetype":"venue"
},
  "geometry": {"coordinates":[-97.955365,34.512823],"type":"Point"}
}