{
  "type": "Feature",
  "properties": {
    "iso:country":"US",
    "sg:address":"10801 S Sunnylane Rd",
    "sg:city":"Oklahoma City",
    "sg:classifiers":[
        {
            "category":"Restaurant",
            "type":"Food & Drink"
        }
    ],
    "sg:phone":"+1 405 793 0752",
    "sg:postcode":"73160",
    "sg:province":"OK",
    "sg:tags":[
        "job",
        "eating"
    ],
    "wof:name":"Wons Taekwendo",
    "wof:placetype":"venue"
},
  "geometry": {"coordinates":[-97.441455,35.361146],"type":"Point"}
}