{
  "type": "Feature",
  "properties": {
    "addr:full":"630 S Roland St Bristow OK 74010",
    "addr:housenumber":"630",
    "addr:postcode":"74010",
    "addr:street":"S Roland St",
    "iso:country":"US",
    "sg:address":"630 S Roland St",
    "sg:city":"Bristow",
    "sg:classifiers":[
        {
            "category":"Restaurant",
            "type":"Food & Drink"
        }
    ],
    "sg:phone":"+1 918 367 9014",
    "sg:postcode":"74010",
    "sg:province":"OK",
    "sg:tags":[
        "eating"
    ],
    "wof:name":"Anchor Drive Inn",
    "wof:placetype":"venue"
},
  "geometry": {"coordinates":[-96.400087,35.827589],"type":"Point"}
}