{
  "type": "Feature",
  "properties": {
    "iso:country":"US",
    "sg:address":"4718 E 11th St",
    "sg:city":"Tulsa",
    "sg:classifiers":[
        {
            "category":"Shopping",
            "subcategory":"Musical Instruments",
            "type":"Retail Goods"
        }
    ],
    "sg:phone":"+1 918 838 9895",
    "sg:postcode":"74112",
    "sg:province":"OK",
    "wof:name":"Firey Brothers Music",
    "wof:placetype":"venue"
},
  "geometry": {"coordinates":[-95.923801,36.147721],"type":"Point"}
}