{
  "type": "Feature",
  "properties": {
    "addr:full":"618 N Delaware St Dewey OK 74029",
    "addr:housenumber":"618",
    "addr:postcode":"74029",
    "addr:street":"N Delaware St",
    "iso:country":"US",
    "sg:address":"618 N Delaware St",
    "sg:city":"Dewey",
    "sg:classifiers":[
        {
            "category":"Organizations",
            "subcategory":"Religious Organization",
            "type":"Services"
        }
    ],
    "sg:phone":"+1 918 534 2328",
    "sg:postcode":"74029",
    "sg:province":"OK",
    "sg:tags":[
        "church"
    ],
    "sg:website":"www.okcm.org",
    "wof:name":"Dewey United Methodist Church",
    "wof:placetype":"venue"
},
  "geometry": {"coordinates":[-95.93808799999999,36.797894],"type":"Point"}
}