{
  "type": "Feature",
  "properties": {
    "addr:full":"216 N 4th St Muskogee OK 74401",
    "addr:housenumber":"216",
    "addr:postcode":"74401",
    "addr:street":"N 4Th St",
    "iso:country":"US",
    "sg:address":"216 N 4th St",
    "sg:city":"Muskogee",
    "sg:classifiers":[
        {
            "category":"Insurance",
            "subcategory":"Hazard Insurance",
            "type":"Services"
        }
    ],
    "sg:phone":"+1 918 686 0020",
    "sg:postcode":"74401",
    "sg:province":"OK",
    "sg:tags":[
        "bond"
    ],
    "wof:name":"Cooper Bail Bonds",
    "wof:placetype":"venue"
},
  "geometry": {"coordinates":[-95.371863,35.750165],"type":"Point"}
}