{
  "type": "Feature",
  "properties": {
    "iso:country":"US",
    "sg:address":"8333 SW 29th St",
    "sg:city":"Oklahoma City",
    "sg:classifiers":[
        {
            "category":"Wholesale",
            "subcategory":"Construction Materials",
            "type":"Manufacturing & Wholesale Goods"
        }
    ],
    "sg:phone":"+1 405 745 4333",
    "sg:postcode":"73179",
    "sg:province":"OK",
    "sg:tags":[
        "pallet",
        "skid"
    ],
    "wof:name":"Palletworld",
    "wof:placetype":"venue"
},
  "geometry": {"coordinates":[-97.654554,35.435304],"type":"Point"}
}