{
  "type": "Feature",
  "properties": {
    "addr:full":"11025 NW 114th St Yukon OK 73099",
    "addr:housenumber":"11025",
    "addr:postcode":"73099",
    "addr:street":"Nw 114Th St",
    "iso:country":"US",
    "sg:address":"11025 NW 114th St",
    "sg:city":"Yukon",
    "sg:phone":"+1 405 373 2755",
    "sg:postcode":"73099",
    "sg:province":"OK",
    "sg:tags":[
        "farm",
        "wheat"
    ],
    "wof:name":"Reherman Farm",
    "wof:placetype":"venue"
},
  "geometry": {"coordinates":[-97.723516,35.58541],"type":"Point"}
}