{
  "type": "Feature",
  "properties": {
    "iso:country":"US",
    "sg:address":"519 W University Ave",
    "sg:city":"Stillwater",
    "sg:classifiers":[
        {
            "category":"Organizations",
            "subcategory":"Religious Organization",
            "type":"Services"
        }
    ],
    "sg:phone":"+1 405 624 0141",
    "sg:postcode":"74074",
    "sg:province":"OK",
    "wof:name":"Canterbury Center Episcopal",
    "wof:placetype":"venue"
},
  "geometry": {"coordinates":[-97.064914,36.11962],"type":"Point"}
}