{
  "type": "Feature",
  "properties": {
    "iso:country":"US",
    "sg:address":"407 W Shawnee St",
    "sg:city":"Tahlequah",
    "sg:classifiers":[
        {
            "category":"Building & Trades",
            "subcategory":"Landscaping Services",
            "type":"Services"
        }
    ],
    "sg:phone":"+1 918 456 3984",
    "sg:postcode":"74464",
    "sg:province":"OK",
    "sg:tags":[
        "landscape"
    ],
    "wof:name":"Combs Landscape & Mainten",
    "wof:placetype":"venue"
},
  "geometry": {"coordinates":[-94.975782,35.916027],"type":"Point"}
}