{
  "type": "Feature",
  "properties": {
    "iso:country":"US",
    "sg:address":"6991 N Dobbs Rd",
    "sg:city":"Harrah",
    "sg:classifiers":[
        {
            "category":"Building & Trades",
            "subcategory":"Construction",
            "type":"Services"
        }
    ],
    "sg:phone":"+1 405 454 1324",
    "sg:postcode":"73045",
    "sg:province":"OK",
    "sg:tags":[
        "house"
    ],
    "wof:name":"Grissam Construction",
    "wof:placetype":"venue"
},
  "geometry": {"coordinates":[-97.177137,35.541605],"type":"Point"}
}