{
  "type": "Feature",
  "properties": {
    "iso:country":"US",
    "sg:address":"7221 NW 39th Expy",
    "sg:city":"Bethany",
    "sg:classifiers":[
        {
            "category":"Autos & Motor Vehicles",
            "subcategory":"Automobile Sales",
            "type":"Retail Goods"
        }
    ],
    "sg:phone":"+1 405 787 1177",
    "sg:postcode":"73008",
    "sg:province":"OK",
    "sg:tags":[
        "used"
    ],
    "wof:name":"Showtime Leasing",
    "wof:placetype":"venue"
},
  "geometry": {"coordinates":[-97.639948,35.51389],"type":"Point"}
}