{
  "type": "Feature",
  "properties": {
    "iso:country":"US",
    "sg:address":"1901 S Elm Pl",
    "sg:city":"Broken Arrow",
    "sg:classifiers":[
        {
            "category":"Food & Beverages",
            "subcategory":"Groceries & Convenience Stores",
            "type":"Retail Goods"
        }
    ],
    "sg:phone":"+1 918 451 7558",
    "sg:postcode":"74012",
    "sg:province":"OK",
    "wof:name":"Yours Mart",
    "wof:placetype":"venue"
},
  "geometry": {"coordinates":[-95.797488,36.030066],"type":"Point"}
}