{
  "type": "Feature",
  "properties": {
    "addr:full":"1421 NW 39th St Oklahoma City OK 73118",
    "addr:housenumber":"1421",
    "addr:postcode":"73118",
    "addr:street":"Nw 39Th St",
    "iso:country":"US",
    "sg:address":"1421 NW 39th St",
    "sg:city":"Oklahoma City",
    "sg:classifiers":[
        {
            "category":"Health Services",
            "subcategory":"Health Practitioner",
            "type":"Services"
        }
    ],
    "sg:phone":"+1 405 528 1441",
    "sg:postcode":"73118",
    "sg:province":"OK",
    "wof:name":"Susan S Ramseyer",
    "wof:placetype":"venue"
},
  "geometry": {"coordinates":[-97.53752,35.511448],"type":"Point"}
}