{
  "type": "Feature",
  "properties": {
    "iso:country":"US",
    "sg:address":"114 E Sheridan Ave",
    "sg:city":"Oklahoma City",
    "sg:classifiers":[
        {
            "category":"Food & Beverages",
            "subcategory":"Groceries & Convenience Stores",
            "type":"Retail Goods"
        }
    ],
    "sg:phone":"+1 405 236 3535",
    "sg:postcode":"73104",
    "sg:province":"OK",
    "wof:name":"Samco Capitol Markets",
    "wof:placetype":"venue"
},
  "geometry": {"coordinates":[-97.509291,35.466397],"type":"Point"}
}