{
  "type": "Feature",
  "properties": {
    "iso:country":"US",
    "sg:address":"1701 N Cimarron Rd",
    "sg:city":"Yukon",
    "sg:classifiers":[
        {
            "category":"Airport",
            "type":"Transportation"
        }
    ],
    "sg:phone":"+1 405 354 6631",
    "sg:postcode":"73099",
    "sg:province":"OK",
    "sg:tags":[
        "aircraft",
        "maintenance"
    ],
    "wof:name":"Mid Continent Airmotive",
    "wof:placetype":"venue"
},
  "geometry": {"coordinates":[-97.813135,35.485074],"type":"Point"}
}