{
  "type": "Feature",
  "properties": {
    "iso:country":"US",
    "sg:address":"801 E Maple St",
    "sg:city":"Cushing",
    "sg:classifiers":[
        {
            "category":"Retail",
            "subcategory":"Repair Shop",
            "type":"Services"
        }
    ],
    "sg:phone":"+1 918 225 5072",
    "sg:postcode":"74023",
    "sg:province":"OK",
    "sg:tags":[
        "appliance",
        "household",
        "electrical"
    ],
    "wof:name":"Reliable Vacuum",
    "wof:placetype":"venue"
},
  "geometry": {"coordinates":[-96.763105,35.983038],"type":"Point"}
}