{
  "type": "Feature",
  "properties": {
    "iso:country":"US",
    "sg:address":"103 S 4th St",
    "sg:city":"Davis",
    "sg:classifiers":[
        {
            "category":"Social Services",
            "type":"Services"
        }
    ],
    "sg:phone":"+1 580 369 2452",
    "sg:postcode":"73030",
    "sg:province":"OK",
    "sg:tags":[
        "senior",
        "citizen"
    ],
    "wof:name":"Davis Senior Citizens Ctr",
    "wof:placetype":"venue"
},
  "geometry": {"coordinates":[-97.118483,34.504838],"type":"Point"}
}