{
  "type": "Feature",
  "properties": {
    "iso:country":"US",
    "sg:address":"2124 S Czech Hall Rd",
    "sg:city":"Yukon",
    "sg:classifiers":[
        {
            "category":"Shopping",
            "subcategory":"Crafts & Fabrics",
            "type":"Retail Goods"
        }
    ],
    "sg:phone":"+1 405 789 0304",
    "sg:postcode":"73099",
    "sg:province":"OK",
    "sg:tags":[
        "monogram"
    ],
    "wof:name":"Gregory & Co Monogramming",
    "wof:placetype":"venue"
},
  "geometry": {"coordinates":[-97.742293,35.43128],"type":"Point"}
}