{
  "type": "Feature",
  "properties": {
    "addr:full":"1441 W Broadway St Ardmore OK 73401",
    "addr:housenumber":"1441",
    "addr:postcode":"73401",
    "addr:street":"W Broadway St",
    "iso:country":"US",
    "sg:address":"1441 W Broadway St",
    "sg:city":"Ardmore",
    "sg:classifiers":[
        {
            "category":"Shopping",
            "subcategory":"Clothing, Apparel, & Fashions",
            "type":"Retail Goods"
        }
    ],
    "sg:phone":"+1 580 226 4092",
    "sg:postcode":"73401",
    "sg:province":"OK",
    "wof:name":"Beane Western Wear",
    "wof:placetype":"venue"
},
  "geometry": {"coordinates":[-97.147547,34.174514],"type":"Point"}
}