{
  "type": "Feature",
  "properties": {
    "iso:country":"US",
    "sg:address":"500 Cherokee St",
    "sg:city":"Wakita",
    "sg:classifiers":[
        {
            "category":"Health Services",
            "subcategory":"Doctor",
            "type":"Services"
        }
    ],
    "sg:phone":"+1 580 594 2344",
    "sg:postcode":"73701",
    "sg:province":"OK",
    "sg:tags":[
        "physician",
        "surgeon"
    ],
    "wof:name":"Wakita Family Clinic",
    "wof:placetype":"venue"
},
  "geometry": {"coordinates":[-97.89882900000001,36.282153],"type":"Point"}
}