{
  "type": "Feature",
  "properties": {
    "addr:full":"2606 S Sheridan Rd Tulsa OK 74129",
    "addr:housenumber":"2606",
    "addr:postcode":"74129",
    "addr:street":"S Sheridan Rd",
    "iso:country":"US",
    "sg:address":"2606 S Sheridan Rd",
    "sg:city":"Tulsa",
    "sg:classifiers":[
        {
            "category":"Banks & Credit Unions",
            "subcategory":"Bank",
            "type":"Services"
        }
    ],
    "sg:phone":"+1 918 836 1400",
    "sg:postcode":"74129",
    "sg:province":"OK",
    "sg:tags":[
        "loan"
    ],
    "wof:name":"Standard Finance Co",
    "wof:placetype":"venue"
},
  "geometry": {"coordinates":[-95.90464900000001,36.126533],"type":"Point"}
}