{
  "type": "Feature",
  "properties": {
    "addr:full":"2409 N 1st Ave Durant OK 74701",
    "addr:housenumber":"2409",
    "addr:postcode":"74701",
    "addr:street":"N 1St Ave",
    "iso:country":"US",
    "sg:address":"2409 N 1st Ave",
    "sg:city":"Durant",
    "sg:classifiers":[
        {
            "category":"Retail",
            "subcategory":"Auto Repair",
            "type":"Services"
        }
    ],
    "sg:phone":"+1 580 924 5958",
    "sg:postcode":"74701",
    "sg:province":"OK",
    "sg:tags":[
        "body",
        "automobile",
        "painting"
    ],
    "wof:name":"S & L Paint & Body Shop",
    "wof:placetype":"venue"
},
  "geometry": {"coordinates":[-96.373006,34.015293],"type":"Point"}
}