{
  "type": "Feature",
  "properties": {
    "iso:country":"US",
    "sg:address":"1508 S Rock Island Ave",
    "sg:city":"El Reno",
    "sg:classifiers":[
        {
            "category":"Home & Garden",
            "subcategory":"Building Materials",
            "type":"Retail Goods"
        }
    ],
    "sg:phone":"+1 405 262 0247",
    "sg:postcode":"73036",
    "sg:province":"OK",
    "sg:tags":[
        "company",
        "lumber"
    ],
    "wof:name":"Watts & Company LLC",
    "wof:placetype":"venue"
},
  "geometry": {"coordinates":[-97.950866,35.518805],"type":"Point"}
}