{
  "type": "Feature",
  "properties": {
    "addr:full":"1007 W Will Rogers Blvd Claremore OK 74017",
    "addr:housenumber":"1007",
    "addr:postcode":"74017",
    "addr:street":"W Will Rogers Blvd",
    "iso:country":"US",
    "sg:address":"1007 W Will Rogers Blvd",
    "sg:city":"Claremore",
    "sg:classifiers":[
        {
            "category":"Personal",
            "subcategory":"Beauty Salon",
            "type":"Services"
        }
    ],
    "sg:phone":"+1 918 342 4945",
    "sg:postcode":"74017",
    "sg:province":"OK",
    "sg:tags":[
        "shop"
    ],
    "wof:name":"California Nails",
    "wof:placetype":"venue"
},
  "geometry": {"coordinates":[-95.623679,36.315633],"type":"Point"}
}