{
  "type": "Feature",
  "properties": {
    "addr:full":"5408 S 103rd East Ave Tulsa OK 74146",
    "addr:housenumber":"5408",
    "addr:postcode":"74146",
    "addr:street":"S 103Rd;Ave",
    "iso:country":"US",
    "sg:address":"5408 S 103rd East Ave",
    "sg:city":"Tulsa",
    "sg:classifiers":[
        {
            "category":"Wholesale",
            "subcategory":"Hardware",
            "type":"Manufacturing & Wholesale Goods"
        }
    ],
    "sg:phone":"+1 918 627 3521",
    "sg:postcode":"74146",
    "sg:province":"OK",
    "sg:tags":[
        "air",
        "heating",
        "conditioning",
        "supply"
    ],
    "wof:name":"Amoco",
    "wof:placetype":"venue"
},
  "geometry": {"coordinates":[-95.86179199999999,36.083856],"type":"Point"}
}