{
  "type": "Feature",
  "properties": {
    "iso:country":"US",
    "sg:address":"123 E 9th Ave",
    "sg:city":"Stillwater",
    "sg:classifiers":[
        {
            "category":"Shopping",
            "subcategory":"Used Merchandise",
            "type":"Retail Goods"
        }
    ],
    "sg:phone":"+1 405 533 5323",
    "sg:postcode":"74074",
    "sg:province":"OK",
    "sg:tags":[
        "antique"
    ],
    "wof:name":"Uncle Mike's Mall",
    "wof:placetype":"venue"
},
  "geometry": {"coordinates":[-97.058337,36.11231],"type":"Point"}
}