{
  "type": "Feature",
  "properties": {
    "iso:country":"US",
    "sg:address":"13304 S Robinson Ave",
    "sg:city":"Oklahoma City",
    "sg:classifiers":[
        {
            "category":"Professional",
            "subcategory":"Computer Services",
            "type":"Services"
        }
    ],
    "sg:phone":"+1 405 717 0524",
    "sg:postcode":"73170",
    "sg:province":"OK",
    "sg:tags":[
        "consulting",
        "related"
    ],
    "wof:name":"Foster Consulting & Sales",
    "wof:placetype":"venue"
},
  "geometry": {"coordinates":[-97.514733,35.335686],"type":"Point"}
}