{
  "type": "Feature",
  "properties": {
    "iso:country":"US",
    "sg:address":"341 NW 94th St",
    "sg:city":"Oklahoma City",
    "sg:classifiers":[
        {
            "category":"Shopping",
            "subcategory":"Bicycles & Sporting Goods",
            "type":"Retail Goods"
        }
    ],
    "sg:phone":"+1 405 842 3277",
    "sg:postcode":"73114",
    "sg:province":"OK",
    "wof:name":"Claude Hall Show Productions",
    "wof:placetype":"venue"
},
  "geometry": {"coordinates":[-97.517489,35.566689],"type":"Point"}
}