{
  "type": "Feature",
  "properties": {
    "iso:country":"US",
    "sg:address":"4400 W Main St",
    "sg:city":"Norman",
    "sg:classifiers":[
        {
            "category":"Farming",
            "subcategory":"Nursery",
            "type":"Manufacturing & Wholesale Goods"
        }
    ],
    "sg:phone":"+1 405 360 6811",
    "sg:postcode":"73072",
    "sg:province":"OK",
    "sg:tags":[
        "turf"
    ],
    "wof:name":"QUA Turf Of Oklahoma",
    "wof:placetype":"venue"
},
  "geometry": {"coordinates":[-97.504939,35.218394],"type":"Point"}
}