{
  "type": "Feature",
  "properties": {
    "addr:full":"304 E 123rd Ct Jenks OK 74037",
    "addr:housenumber":"304",
    "addr:postcode":"74037",
    "addr:street":"E 123Rd Ct",
    "iso:country":"US",
    "sg:address":"304 E 123rd Ct",
    "sg:city":"Jenks",
    "sg:classifiers":[
        {
            "category":"Building & Trades",
            "subcategory":"Equipment Rental",
            "type":"Services"
        }
    ],
    "sg:phone":"+1 918 296 9543",
    "sg:postcode":"74037",
    "sg:province":"OK",
    "wof:name":"Maple Leaf Leasing Inc",
    "wof:placetype":"venue"
},
  "geometry": {"coordinates":[-95.966622,35.986005],"type":"Point"}
}