{
  "type": "Feature",
  "properties": {
    "iso:country":"US",
    "sg:address":"3925 SE 29th St",
    "sg:city":"Oklahoma City",
    "sg:classifiers":[
        {
            "category":"Arts & Performance",
            "subcategory":"Theater",
            "type":"Entertainment"
        }
    ],
    "sg:phone":"+1 405 677 6107",
    "sg:postcode":"73115",
    "sg:province":"OK",
    "sg:tags":[
        "musician"
    ],
    "wof:name":"Oklahoma Country Music Assn",
    "wof:placetype":"venue"
},
  "geometry": {"coordinates":[-97.444316,35.435231],"type":"Point"}
}