{
  "type": "Feature",
  "properties": {
    "iso:country":"US",
    "sg:address":"2101 N 170th East Ave",
    "sg:city":"Tulsa",
    "sg:classifiers":[
        {
            "category":"Manufacturing",
            "subcategory":"Metals",
            "type":"Manufacturing & Wholesale Goods"
        }
    ],
    "sg:phone":"+1 918 234 0081",
    "sg:postcode":"74116",
    "sg:province":"OK",
    "sg:tags":[
        "barrels",
        "drum"
    ],
    "sg:website":"www.soonercontainer.com",
    "wof:name":"Sooner Container Inc",
    "wof:placetype":"venue"
},
  "geometry": {"coordinates":[-95.78547500000001,36.181182],"type":"Point"}
}