{
  "type": "Feature",
  "properties": {
    "iso:country":"US",
    "sg:address":"218 N Hoy St",
    "sg:city":"Buffalo",
    "sg:classifiers":[
        {
            "category":"Wholesale",
            "subcategory":"Machinery & Supplies",
            "type":"Manufacturing & Wholesale Goods"
        }
    ],
    "sg:phone":"+1 580 735 2824",
    "sg:postcode":"73834",
    "sg:province":"OK",
    "sg:tags":[
        "farm",
        "equipment"
    ],
    "wof:name":"K & S Repairs Inc",
    "wof:placetype":"venue"
},
  "geometry": {"coordinates":[-99.63024,36.838135],"type":"Point"}
}