{
  "type": "Feature",
  "properties": {
    "iso:country":"US",
    "sg:address":"924 Robtrice Ct",
    "sg:city":"Edmond",
    "sg:classifiers":[
        {
            "category":"Health Services",
            "subcategory":"Doctor",
            "type":"Services"
        }
    ],
    "sg:phone":"+1 405 340 5110",
    "sg:postcode":"73034",
    "sg:province":"OK",
    "wof:name":"Lee A Eliot DDS",
    "wof:placetype":"venue"
},
  "geometry": {"coordinates":[-97.46250499999999,35.644681],"type":"Point"}
}