{
  "type": "Feature",
  "properties": {
    "addr:full":"11427 S 249th East Ave Broken Arrow OK 74014",
    "addr:housenumber":"11427",
    "addr:postcode":"74014",
    "addr:street":"S 249Th East Ave",
    "iso:country":"US",
    "sg:address":"11427 S 249th East Ave",
    "sg:city":"Broken Arrow",
    "sg:classifiers":[
        {
            "category":"Manufacturing",
            "subcategory":"Printing",
            "type":"Manufacturing & Wholesale Goods"
        }
    ],
    "sg:phone":"+1 918 663 8990",
    "sg:postcode":"74014",
    "sg:province":"OK",
    "sg:tags":[
        "printer"
    ],
    "wof:name":"Performance Printing",
    "wof:placetype":"venue"
},
  "geometry": {"coordinates":[-95.699765,35.998271],"type":"Point"}
}