{
  "type": "Feature",
  "properties": {
    "iso:country":"US",
    "sg:address":"622 N Main St",
    "sg:city":"Muskogee",
    "sg:classifiers":[
        {
            "category":"Retail",
            "subcategory":"Auto Repair",
            "type":"Services"
        }
    ],
    "sg:phone":"+1 918 687 1172",
    "sg:postcode":"74401",
    "sg:province":"OK",
    "sg:tags":[
        "body",
        "automotive",
        "painting",
        "automobile"
    ],
    "wof:name":"Port City Body Shop Inc",
    "wof:placetype":"venue"
},
  "geometry": {"coordinates":[-95.36505699999999,35.755409],"type":"Point"}
}