{
  "type": "Feature",
  "properties": {
    "addr:full":"550 NW 24th St Oklahoma City OK 73103",
    "addr:housenumber":"550",
    "addr:postcode":"73103",
    "addr:street":"Nw 24Th St",
    "iso:country":"US",
    "sg:address":"550 NW 24th St",
    "sg:city":"Oklahoma City",
    "sg:classifiers":[
        {
            "category":"Freight",
            "type":"Transportation"
        }
    ],
    "sg:phone":"+1 405 364 8218",
    "sg:postcode":"73103",
    "sg:province":"OK",
    "sg:tags":[
        "commercial",
        "storage"
    ],
    "wof:name":"Westwood Mini Storage",
    "wof:placetype":"venue"
},
  "geometry": {"coordinates":[-97.52185,35.494281],"type":"Point"}
}