{
  "type": "Feature",
  "properties": {
    "iso:country":"US",
    "sg:address":"3001 E 11th St",
    "sg:city":"Tulsa",
    "sg:classifiers":[
        {
            "category":"Restaurant",
            "type":"Food & Drink"
        }
    ],
    "sg:phone":"+1 918 592 2616",
    "sg:postcode":"74104",
    "sg:province":"OK",
    "sg:tags":[
        "personal",
        "eating"
    ],
    "wof:name":"Metro Diner",
    "wof:placetype":"venue"
},
  "geometry": {"coordinates":[-95.944902,36.147818],"type":"Point"}
}