{
  "type": "Feature",
  "properties": {
    "iso:country":"US",
    "sg:address":"401 S Boston Ave",
    "sg:city":"Tulsa",
    "sg:classifiers":[
        {
            "category":"Mining & Drilling",
            "type":"Manufacturing & Wholesale Goods"
        }
    ],
    "sg:phone":"+1 918 584 5155",
    "sg:postcode":"74103",
    "sg:province":"OK",
    "sg:tags":[
        "oil",
        "producer"
    ],
    "wof:name":"Edward C Lawson Properties",
    "wof:placetype":"venue"
},
  "geometry": {"coordinates":[-95.988942,36.151824],"type":"Point"}
}