{
  "type": "Feature",
  "properties": {
    "addr:full":"9600 N May Ave Oklahoma City OK 73120",
    "addr:housenumber":"9600",
    "addr:postcode":"73120",
    "addr:street":"N May Ave",
    "iso:country":"US",
    "sg:address":"9600 N May Ave",
    "sg:city":"Oklahoma City",
    "sg:classifiers":[
        {
            "category":"Shopping",
            "subcategory":"Gifts & Souvenirs",
            "type":"Retail Goods"
        }
    ],
    "sg:phone":"+1 405 751 5510",
    "sg:postcode":"73120",
    "sg:province":"OK",
    "sg:tags":[
        "party",
        "supply"
    ],
    "wof:name":"Party Bazaar",
    "wof:placetype":"venue"
},
  "geometry": {"coordinates":[-97.567105,35.568921],"type":"Point"}
}