{
  "type": "Feature",
  "properties": {
    "iso:country":"US",
    "sg:address":"902 N Dorothy Ave",
    "sg:city":"Claremore",
    "sg:classifiers":[
        {
            "category":"Shopping",
            "subcategory":"Tobacco",
            "type":"Retail Goods"
        }
    ],
    "sg:phone":"+1 918 341 9150",
    "sg:postcode":"74017",
    "sg:province":"OK",
    "sg:tags":[
        "product"
    ],
    "wof:name":"Ou Pon Ahlung Smoke Shop",
    "wof:placetype":"venue"
},
  "geometry": {"coordinates":[-95.599135,36.316098],"type":"Point"}
}