{
  "type": "Feature",
  "properties": {
    "addr:full":"3020 SW 40th St Oklahoma City OK 73119",
    "addr:housenumber":"3020",
    "addr:postcode":"73119",
    "addr:street":"Sw 40Th St",
    "iso:country":"US",
    "sg:address":"3020 SW 40th St",
    "sg:city":"Oklahoma City",
    "sg:classifiers":[
        {
            "category":"Shopping",
            "subcategory":"Florist",
            "type":"Retail Goods"
        }
    ],
    "sg:phone":"+1 405 681 6480",
    "sg:postcode":"73119",
    "sg:province":"OK",
    "wof:name":"Tropical Connection",
    "wof:placetype":"venue"
},
  "geometry": {"coordinates":[-97.56777700000001,35.424641],"type":"Point"}
}