{
  "type": "Feature",
  "properties": {
    "iso:country":"US",
    "sg:address":"5512 E 115th St",
    "sg:city":"Tulsa",
    "sg:classifiers":[
        {
            "category":"Autos & Motor Vehicles",
            "subcategory":"Auto Supplies",
            "type":"Retail Goods"
        },
        {
            "category":"Manufacturing",
            "subcategory":"Petroleum Products",
            "type":"Manufacturing & Wholesale Goods"
        }
    ],
    "sg:phone":"+1 918 671 1430",
    "sg:postcode":"74137",
    "sg:province":"OK",
    "sg:tags":[
        "lubricating",
        "oil",
        "lubricant"
    ],
    "wof:name":"D'onofrio Enterprises",
    "wof:placetype":"venue"
},
  "geometry": {"coordinates":[-95.914814,35.997624],"type":"Point"}
}