{
  "type": "Feature",
  "properties": {
    "addr:full":"2721 Glen Oaks Dr Norman OK 73071",
    "addr:housenumber":"2721",
    "addr:postcode":"73071",
    "addr:street":"Glen Oaks Dr",
    "iso:country":"US",
    "sg:address":"2721 Glen Oaks Dr",
    "sg:city":"Norman",
    "sg:classifiers":[
        {
            "category":"Professional",
            "subcategory":"Business Services",
            "type":"Services"
        }
    ],
    "sg:phone":"+1 405 573 0160",
    "sg:postcode":"73071",
    "sg:province":"OK",
    "wof:name":"Walde Enterprises Inc",
    "wof:placetype":"venue"
},
  "geometry": {"coordinates":[-97.401736,35.201355],"type":"Point"}
}