{
  "type": "Feature",
  "properties": {
    "iso:country":"US",
    "sg:address":"4512 SE 24th St",
    "sg:city":"Oklahoma City",
    "sg:classifiers":[
        {
            "category":"Manufacturing",
            "subcategory":"Lumber",
            "type":"Manufacturing & Wholesale Goods"
        }
    ],
    "sg:phone":"+1 405 740 4760",
    "sg:postcode":"73115",
    "sg:province":"OK",
    "sg:tags":[
        "forestry"
    ],
    "wof:name":"Kenneth Zink",
    "wof:placetype":"venue"
},
  "geometry": {"coordinates":[-97.43271799999999,35.439915],"type":"Point"}
}