{
  "type": "Feature",
  "properties": {
    "addr:full":"115 N Glenn L English St Cordell OK 73632",
    "addr:housenumber":"115",
    "addr:postcode":"73632",
    "addr:street":"N Glenn L English St",
    "iso:country":"US",
    "sg:address":"115 N Glenn L English St",
    "sg:city":"Cordell",
    "sg:classifiers":[
        {
            "category":"Restaurant",
            "type":"Food & Drink"
        }
    ],
    "sg:phone":"+1 580 832 5043",
    "sg:postcode":"73632",
    "sg:province":"OK",
    "wof:name":"Lavena's Restaurant",
    "wof:placetype":"venue"
},
  "geometry": {"coordinates":[-98.98753499999999,35.292202],"type":"Point"}
}