{
  "type": "Feature",
  "properties": {
    "addr:full":"8100 N Classen Blvd Oklahoma City OK 73114",
    "addr:housenumber":"8100",
    "addr:postcode":"73114",
    "addr:street":"N Classen Blvd",
    "iso:country":"US",
    "sg:address":"8100 N Classen Blvd",
    "sg:city":"Oklahoma City",
    "sg:classifiers":[
        {
            "category":"Professional",
            "type":"Services"
        }
    ],
    "sg:phone":"+1 405 848 3100",
    "sg:postcode":"73114",
    "sg:province":"OK",
    "sg:tags":[
        "establishment"
    ],
    "wof:name":"Nsc Marketing Inc",
    "wof:placetype":"venue"
},
  "geometry": {"coordinates":[-97.527001,35.55274],"type":"Point"}
}