{
  "type": "Feature",
  "properties": {
    "addr:full":"2615 W Toledo Ct Broken Arrow OK 74012",
    "addr:housenumber":"2615",
    "addr:postcode":"74012",
    "addr:street":"W Toledo Ct",
    "iso:country":"US",
    "sg:address":"2615 W Toledo Ct",
    "sg:city":"Broken Arrow",
    "sg:classifiers":[
        {
            "category":"Freight",
            "type":"Transportation"
        }
    ],
    "sg:phone":"+1 918 258 1729",
    "sg:postcode":"74012",
    "sg:province":"OK",
    "wof:name":"We Assoc Inc",
    "wof:placetype":"venue"
},
  "geometry": {"coordinates":[-95.82175599999999,36.034048],"type":"Point"}
}