{
  "type": "Feature",
  "properties": {
    "iso:country":"US",
    "sg:address":"1612 Fredonia St",
    "sg:city":"Muskogee",
    "sg:classifiers":[
        {
            "category":"Bars & Pubs",
            "type":"Food & Drink"
        }
    ],
    "sg:phone":"+1 918 682 4287",
    "sg:postcode":"74403",
    "sg:province":"OK",
    "sg:tags":[
        "drinking"
    ],
    "wof:name":"Nannys Pub",
    "wof:placetype":"venue"
},
  "geometry": {"coordinates":[-95.34688800000001,35.746806],"type":"Point"}
}