{
  "type": "Feature",
  "properties": {
    "iso:country":"US",
    "sg:address":"303 Dayton St",
    "sg:city":"Muskogee",
    "sg:classifiers":[
        {
            "category":"Retail",
            "subcategory":"Laundry & Dry Cleaning",
            "type":"Services"
        }
    ],
    "sg:phone":"+1 918 687 9065",
    "sg:postcode":"74403",
    "sg:province":"OK",
    "wof:name":"Sunshine Laundry",
    "wof:placetype":"venue"
},
  "geometry": {"coordinates":[-95.364274,35.749318],"type":"Point"}
}