{
  "type": "Feature",
  "properties": {
    "addr:full":"924 SE 59th St Oklahoma City OK 73129",
    "addr:housenumber":"924",
    "addr:postcode":"73129",
    "addr:street":"Se 59Th St",
    "iso:country":"US",
    "sg:address":"924 SE 59th St",
    "sg:city":"Oklahoma City",
    "sg:classifiers":[
        {
            "category":"Autos & Motor Vehicles",
            "subcategory":"Fuel & Gas Station",
            "type":"Retail Goods"
        }
    ],
    "sg:phone":"+1 405 632 1166",
    "sg:postcode":"73129",
    "sg:province":"OK",
    "sg:tags":[
        "oil"
    ],
    "wof:name":"Diamond Shamrock",
    "wof:placetype":"venue"
},
  "geometry": {"coordinates":[-97.494665,35.40619],"type":"Point"}
}