{
  "type": "Feature",
  "properties": {
    "iso:country":"US",
    "sg:address":"118 E Commercial St",
    "sg:city":"Broken Arrow",
    "sg:classifiers":[
        {
            "category":"Organizations",
            "subcategory":"Religious Organization",
            "type":"Services"
        }
    ],
    "sg:phone":"+1 918 251 8591",
    "sg:postcode":"74012",
    "sg:province":"OK",
    "sg:tags":[
        "church"
    ],
    "wof:name":"Broken Arrow Assembly of God",
    "wof:placetype":"venue"
},
  "geometry": {"coordinates":[-95.789657,36.051301],"type":"Point"}
}