{
  "type": "Feature",
  "properties": {
    "iso:country":"US",
    "sg:address":"2116 N Divis Ave",
    "sg:city":"Bethany",
    "sg:classifiers":[
        {
            "category":"Professional",
            "type":"Services"
        }
    ],
    "sg:phone":"+1 405 787 6826",
    "sg:postcode":"73008",
    "sg:province":"OK",
    "wof:name":"Unique Services Inc",
    "wof:placetype":"venue"
},
  "geometry": {"coordinates":[-97.63863000000001,35.491109],"type":"Point"}
}