{
  "type": "Feature",
  "properties": {
    "addr:full":"2915 S Douglas Blvd Oklahoma City OK 73130",
    "addr:housenumber":"2915",
    "addr:postcode":"73130",
    "addr:street":"S Douglas Blvd",
    "iso:country":"US",
    "sg:address":"2915 S Douglas Blvd",
    "sg:city":"Oklahoma City",
    "sg:classifiers":[
        {
            "category":"Restaurant",
            "type":"Food & Drink"
        }
    ],
    "sg:menulink":"http://www.allmenus.com/ok/oklahoma-city/199296-sonic/menu/",
    "sg:phone":"+1 405 732 2831",
    "sg:postcode":"73130",
    "sg:province":"OK",
    "sg:tags":[
        "burger",
        "american"
    ],
    "wof:name":"Sonic",
    "wof:placetype":"venue"
},
  "geometry": {"coordinates":[-97.37125399999999,35.436229],"type":"Point"}
}