{
  "type": "Feature",
  "properties": {
    "iso:country":"US",
    "sg:address":"9606 N May Ave",
    "sg:city":"Oklahoma City",
    "sg:classifiers":[
        {
            "category":"Shopping",
            "subcategory":"Clothing, Apparel, & Fashions",
            "type":"Retail Goods"
        }
    ],
    "sg:phone":"+1 405 748 6066",
    "sg:postcode":"73120",
    "sg:province":"OK",
    "sg:tags":[
        "uniform"
    ],
    "wof:name":"Parker School Uniforms",
    "wof:placetype":"venue"
},
  "geometry": {"coordinates":[-97.567105,35.568872],"type":"Point"}
}