{
  "type": "Feature",
  "properties": {
    "iso:country":"US",
    "sg:address":"1271 W Covell Rd",
    "sg:city":"Edmond",
    "sg:classifiers":[
        {
            "category":"Organizations",
            "subcategory":"Religious Organization",
            "type":"Services"
        }
    ],
    "sg:phone":"+1 405 359 2286",
    "sg:postcode":"73003",
    "sg:province":"OK",
    "sg:tags":[
        "church"
    ],
    "wof:name":"Acts 2 United Methodist Church",
    "wof:placetype":"venue"
},
  "geometry": {"coordinates":[-97.497405,35.682109],"type":"Point"}
}