{
  "type": "Feature",
  "properties": {
    "iso:country":"US",
    "sg:address":"1117 N 13th St",
    "sg:city":"Enid",
    "sg:classifiers":[
        {
            "category":"Building & Trades",
            "subcategory":"Construction",
            "type":"Services"
        }
    ],
    "sg:phone":"+1 580 234 1696",
    "sg:postcode":"73701",
    "sg:province":"OK",
    "sg:tags":[
        "hanging",
        "contractor"
    ],
    "wof:name":"Byers Painting",
    "wof:placetype":"venue"
},
  "geometry": {"coordinates":[-97.859156,36.407809],"type":"Point"}
}