{
  "type": "Feature",
  "properties": {
    "iso:country":"US",
    "sg:address":"1301 SW 29th St",
    "sg:city":"Oklahoma City",
    "sg:classifiers":[
        {
            "category":"Shopping",
            "subcategory":"Pharmacy",
            "type":"Retail Goods"
        }
    ],
    "sg:phone":"+1 405 634 3317",
    "sg:postcode":"73119",
    "sg:province":"OK",
    "wof:name":"Ralphs Drug Co",
    "wof:placetype":"venue"
},
  "geometry": {"coordinates":[-97.541315,35.435223],"type":"Point"}
}