{
  "type": "Feature",
  "properties": {
    "addr:full":"4702 NW Cache Rd Lawton OK 73505",
    "addr:housenumber":"4702",
    "addr:postcode":"73505",
    "addr:street":"Nw Cache Rd",
    "iso:country":"US",
    "sg:address":"4702 NW Cache Rd",
    "sg:city":"Lawton",
    "sg:classifiers":[
        {
            "category":"Restaurant",
            "type":"Food & Drink"
        }
    ],
    "sg:phone":"+1 580 355 2229",
    "sg:postcode":"73505",
    "sg:province":"OK",
    "wof:name":"KFC",
    "wof:placetype":"venue"
},
  "geometry": {"coordinates":[-98.448868,34.623299],"type":"Point"}
}