{
  "type": "Feature",
  "properties": {
    "iso:country":"US",
    "sg:address":"7018 N Lakewood Ave",
    "sg:city":"Tulsa",
    "sg:classifiers":[
        {
            "category":"Manufacturing",
            "subcategory":"Aerospace",
            "type":"Manufacturing & Wholesale Goods"
        }
    ],
    "sg:phone":"+1 918 274 2700",
    "sg:postcode":"74117",
    "sg:province":"OK",
    "sg:tags":[
        "aircraft",
        "component"
    ],
    "sg:website":"www.nordam.net",
    "wof:name":"Nordam Grp Transparency Div",
    "wof:placetype":"venue"
},
  "geometry": {"coordinates":[-95.907097,36.256117],"type":"Point"}
}