{
  "type": "Feature",
  "properties": {
    "iso:country":"US",
    "sg:address":"3213 SW 41st St",
    "sg:city":"Oklahoma City",
    "sg:classifiers":[
        {
            "category":"Professional",
            "subcategory":"Computer Services",
            "type":"Services"
        }
    ],
    "sg:phone":"+1 405 921 6776",
    "sg:postcode":"73119",
    "sg:province":"OK",
    "sg:tags":[
        "datum"
    ],
    "wof:name":"Wilhm Data Services",
    "wof:placetype":"venue"
},
  "geometry": {"coordinates":[-97.572277,35.423924],"type":"Point"}
}