{
  "type": "Feature",
  "properties": {
    "addr:full":"1602 Lakeview Dr Kingfisher OK 73750",
    "addr:housenumber":"1602",
    "addr:postcode":"73750",
    "addr:street":"Lakeview Dr",
    "iso:country":"US",
    "sg:address":"1602 Lakeview Dr",
    "sg:city":"Kingfisher",
    "sg:classifiers":[
        {
            "category":"Restaurant",
            "type":"Food & Drink"
        }
    ],
    "sg:phone":"+1 405 375 3254",
    "sg:postcode":"73750",
    "sg:province":"OK",
    "sg:tags":[
        "eating"
    ],
    "wof:name":"A&S Restaurants Inc",
    "wof:placetype":"venue"
},
  "geometry": {"coordinates":[-97.93853300000001,35.841175],"type":"Point"}
}