{
  "type": "Feature",
  "properties": {
    "iso:country":"US",
    "sg:address":"6207 S Yorktown Pl",
    "sg:city":"Tulsa",
    "sg:classifiers":[
        {
            "category":"Farming",
            "subcategory":"Livestock Farm",
            "type":"Manufacturing & Wholesale Goods"
        }
    ],
    "sg:phone":"+1 918 745 9705",
    "sg:postcode":"74136",
    "sg:province":"OK",
    "sg:tags":[
        "animal",
        "general"
    ],
    "wof:name":"Gina Rasure",
    "wof:placetype":"venue"
},
  "geometry": {"coordinates":[-95.96268999999999,36.072529],"type":"Point"}
}