{
  "type": "Feature",
  "properties": {
    "iso:country":"US",
    "sg:address":"106 W Charlotte Dr",
    "sg:city":"Oklahoma City",
    "sg:classifiers":[
        {
            "category":"Retail",
            "subcategory":"Auto Rental",
            "type":"Services"
        }
    ],
    "sg:phone":"+1 405 755 2679",
    "sg:postcode":"73139",
    "sg:province":"OK",
    "sg:tags":[
        "renting",
        "truck",
        "leasing"
    ],
    "wof:name":"U-Haul Co",
    "wof:placetype":"venue"
},
  "geometry": {"coordinates":[-97.516655,35.372854],"type":"Point"}
}