{
  "type": "Feature",
  "properties": {
    "iso:country":"US",
    "sg:address":"1401 W Boyd St",
    "sg:city":"Norman",
    "sg:classifiers":[
        {
            "category":"Organizations",
            "subcategory":"Religious Organization",
            "type":"Services"
        }
    ],
    "sg:phone":"+1 405 329 3101",
    "sg:postcode":"73069",
    "sg:province":"OK",
    "wof:name":"New Life Bible Church",
    "wof:placetype":"venue"
},
  "geometry": {"coordinates":[-97.460566,35.21123],"type":"Point"}
}