{
  "type": "Feature",
  "properties": {
    "iso:country":"US",
    "sg:address":"9509 Bartlett Dr",
    "sg:city":"Oklahoma City",
    "sg:classifiers":[
        {
            "category":"Farming",
            "subcategory":"Nursery",
            "type":"Manufacturing & Wholesale Goods"
        }
    ],
    "sg:phone":"+1 405 478 4769",
    "sg:postcode":"73131",
    "sg:province":"OK",
    "sg:tags":[
        "flor",
        "supply",
        "greenhouse",
        "ornamental"
    ],
    "wof:name":"Mc Cauley's Greenhouses",
    "wof:placetype":"venue"
},
  "geometry": {"coordinates":[-97.471507,35.567495],"type":"Point"}
}