{
  "type": "Feature",
  "properties": {
    "addr:full":"820 N 8th St Hollis OK 73550",
    "addr:housenumber":"820",
    "addr:postcode":"73550",
    "addr:street":"N 8Th St",
    "iso:country":"US",
    "sg:address":"820 N 8th St",
    "sg:city":"Hollis",
    "sg:classifiers":[
        {
            "category":"Food & Beverages",
            "subcategory":"Groceries & Convenience Stores",
            "type":"Retail Goods"
        }
    ],
    "sg:phone":"+1 580 688 9109",
    "sg:postcode":"73550",
    "sg:province":"OK",
    "sg:tags":[
        "merchandise"
    ],
    "wof:name":"Quickie Mart",
    "wof:placetype":"venue"
},
  "geometry": {"coordinates":[-99.912283,34.689573],"type":"Point"}
}