{
  "type": "Feature",
  "properties": {
    "iso:country":"US",
    "sg:address":"11 Autumn Dr",
    "sg:city":"Lawton",
    "sg:classifiers":[
        {
            "category":"Government",
            "subcategory":"Office",
            "type":"Public Place"
        }
    ],
    "sg:phone":"+1 580 529 5298",
    "sg:postcode":"73507",
    "sg:province":"OK",
    "sg:tags":[
        "village"
    ],
    "wof:name":"Medicine Park Tag Agency",
    "wof:placetype":"venue"
},
  "geometry": {"coordinates":[-98.442427,34.724823],"type":"Point"}
}