{
  "type": "Feature",
  "properties": {
    "addr:full":"1502 S Denver Ave Tulsa OK 74119",
    "addr:housenumber":"1502",
    "addr:postcode":"74119",
    "addr:street":"S Denver Ave",
    "iso:country":"US",
    "sg:address":"1502 S Denver Ave",
    "sg:city":"Tulsa",
    "sg:classifiers":[
        {
            "category":"Insurance",
            "subcategory":"Insurance Agent",
            "type":"Services"
        }
    ],
    "sg:phone":"+1 918 392 1970",
    "sg:postcode":"74119",
    "sg:province":"OK",
    "wof:name":"National Sports Insurance Inc",
    "wof:placetype":"venue"
},
  "geometry": {"coordinates":[-95.992439,36.139734],"type":"Point"}
}