{
  "type": "Feature",
  "properties": {
    "iso:country":"US",
    "sg:address":"307 N Perkins Rd",
    "sg:city":"Stillwater",
    "sg:classifiers":[
        {
            "category":"Professional",
            "subcategory":"Printing & Photocopies",
            "type":"Services"
        }
    ],
    "sg:phone":"+1 405 743 0806",
    "sg:postcode":"74075",
    "sg:province":"OK",
    "sg:tags":[
        "photocopying"
    ],
    "wof:name":"Kinkos",
    "wof:placetype":"venue"
},
  "geometry": {"coordinates":[-97.05136,36.126757],"type":"Point"}
}