{
  "type": "Feature",
  "properties": {
    "iso:country":"US",
    "sg:address":"123 N 7th St",
    "sg:city":"Henryetta",
    "sg:classifiers":[
        {
            "category":"Professional",
            "type":"Services"
        }
    ],
    "sg:phone":"+1 918 652 3473",
    "sg:postcode":"74437",
    "sg:province":"OK",
    "sg:tags":[
        "establishment"
    ],
    "wof:name":"Harvest Fire Fellowship",
    "wof:placetype":"venue"
},
  "geometry": {"coordinates":[-95.989664,35.440084],"type":"Point"}
}