{
  "type": "Feature",
  "properties": {
    "iso:country":"US",
    "sg:address":"5101 N Classen Cir",
    "sg:city":"Oklahoma City",
    "sg:classifiers":[
        {
            "category":"Wholesale",
            "subcategory":"Stationery",
            "type":"Manufacturing & Wholesale Goods"
        }
    ],
    "sg:phone":"+1 405 842 9756",
    "sg:postcode":"73118",
    "sg:province":"OK",
    "sg:tags":[
        "business",
        "form",
        "system"
    ],
    "wof:name":"Moore Wallace Inc",
    "wof:placetype":"venue"
},
  "geometry": {"coordinates":[-97.532296,35.5233],"type":"Point"}
}