{
  "type": "Feature",
  "properties": {
    "iso:country":"US",
    "sg:address":"3625 NW 56th St",
    "sg:city":"Oklahoma City",
    "sg:classifiers":[
        {
            "category":"Health Services",
            "subcategory":"Clinic",
            "type":"Services"
        }
    ],
    "sg:phone":"+1 405 942 6556",
    "sg:postcode":"73112",
    "sg:province":"OK",
    "wof:name":"Oklahoma Area Health Board",
    "wof:placetype":"venue"
},
  "geometry": {"coordinates":[-97.580674,35.528318],"type":"Point"}
}