{
  "type": "Feature",
  "properties": {
    "iso:country":"US",
    "sg:address":"800 S Pennsylvania Ave",
    "sg:city":"Cherokee",
    "sg:classifiers":[
        {
            "category":"Insurance",
            "subcategory":"Hazard Insurance",
            "type":"Services"
        }
    ],
    "sg:phone":"+1 580 596 2600",
    "sg:postcode":"73728",
    "sg:province":"OK",
    "sg:tags":[
        "carrier"
    ],
    "wof:name":"Woods Agency",
    "wof:placetype":"venue"
},
  "geometry": {"coordinates":[-98.35446399999999,36.750682],"type":"Point"}
}