{
  "type": "Feature",
  "properties": {
    "addr:full":"2302 W 7th Ave Stillwater OK 74074",
    "addr:housenumber":"2302",
    "addr:postcode":"74074",
    "addr:street":"W 7Th Ave",
    "iso:country":"US",
    "sg:address":"2302 W 7th Ave",
    "sg:city":"Stillwater",
    "sg:classifiers":[
        {
            "category":"Restaurant",
            "type":"Food & Drink"
        }
    ],
    "sg:phone":"+1 405 780 7400",
    "sg:postcode":"74074",
    "sg:province":"OK",
    "wof:name":"Mcdonald's Office",
    "wof:placetype":"venue"
},
  "geometry": {"coordinates":[-97.08937899999999,36.114723],"type":"Point"}
}