{
  "type": "Feature",
  "properties": {
    "addr:full":"45 E 15th St Edmond OK 73013",
    "addr:housenumber":"45",
    "addr:postcode":"73013",
    "addr:street":"E 15Th St",
    "iso:country":"US",
    "sg:address":"45 E 15th St",
    "sg:city":"Edmond",
    "sg:classifiers":[
        {
            "category":"Health Services",
            "subcategory":"Chiropractor",
            "type":"Services"
        }
    ],
    "sg:phone":"+1 405 340 7926",
    "sg:postcode":"73013",
    "sg:province":"OK",
    "wof:name":"Swan Chiropractic Clinic",
    "wof:placetype":"venue"
},
  "geometry": {"coordinates":[-97.483009,35.638381],"type":"Point"}
}