{
  "type": "Feature",
  "properties": {
    "addr:full":"3640 N Rockwell Ave Bethany OK 73008",
    "addr:housenumber":"3640",
    "addr:postcode":"73008",
    "addr:street":"N Rockwell Ave",
    "iso:country":"US",
    "sg:address":"3640 N Rockwell Ave",
    "sg:city":"Bethany",
    "sg:classifiers":[
        {
            "category":"Food & Beverages",
            "subcategory":"Groceries & Convenience Stores",
            "type":"Retail Goods"
        }
    ],
    "sg:phone":"+1 405 495 9613",
    "sg:postcode":"73008",
    "sg:province":"OK",
    "wof:name":"Kwik Shop 817",
    "wof:placetype":"venue"
},
  "geometry": {"coordinates":[-97.636551,35.505619],"type":"Point"}
}