{
  "type": "Feature",
  "properties": {
    "iso:country":"US",
    "sg:address":"12904 E 11th St",
    "sg:city":"Tulsa",
    "sg:classifiers":[
        {
            "category":"Wholesale",
            "subcategory":"Construction Materials",
            "type":"Manufacturing & Wholesale Goods"
        },
        {
            "category":"Building & Trades",
            "subcategory":"Construction",
            "type":"Services"
        }
    ],
    "sg:phone":"+1 918 437 8997",
    "sg:postcode":"74108",
    "sg:province":"OK",
    "wof:name":"Metro Portable Building Co Inc",
    "wof:placetype":"venue"
},
  "geometry": {"coordinates":[-95.831097,36.147905],"type":"Point"}
}