{
  "type": "Feature",
  "properties": {
    "iso:country":"US",
    "sg:address":"1915 W Beech Ave",
    "sg:city":"Duncan",
    "sg:classifiers":[
        {
            "category":"Food & Beverages",
            "subcategory":"Groceries & Convenience Stores",
            "type":"Retail Goods"
        }
    ],
    "sg:phone":"+1 580 252 2545",
    "sg:postcode":"73533",
    "sg:province":"OK",
    "wof:name":"C J's KWIK Stop",
    "wof:placetype":"venue"
},
  "geometry": {"coordinates":[-97.973377,34.507167],"type":"Point"}
}