{
  "type": "Feature",
  "properties": {
    "iso:country":"US",
    "sg:address":"925 S Yale Ave",
    "sg:city":"Tulsa",
    "sg:classifiers":[
        {
            "category":"Wholesale",
            "subcategory":"Auto Parts",
            "type":"Manufacturing & Wholesale Goods"
        }
    ],
    "sg:phone":"+1 918 627 8174",
    "sg:postcode":"74112",
    "sg:province":"OK",
    "wof:name":"Roy J & Roy L Sinor",
    "wof:placetype":"venue"
},
  "geometry": {"coordinates":[-95.92243499999999,36.147961],"type":"Point"}
}