{
  "type": "Feature",
  "properties": {
    "iso:country":"US",
    "sg:address":"4602 Alpine Pl",
    "sg:city":"Enid",
    "sg:classifiers":[
        {
            "category":"Manufacturing",
            "subcategory":"Food",
            "type":"Manufacturing & Wholesale Goods"
        }
    ],
    "sg:phone":"+1 580 234 8729",
    "sg:postcode":"73703",
    "sg:province":"OK",
    "sg:tags":[
        "mfg",
        "potato"
    ],
    "wof:name":"Frito-Lay",
    "wof:placetype":"venue"
},
  "geometry": {"coordinates":[-97.93588800000001,36.404891],"type":"Point"}
}