{
  "type": "Feature",
  "properties": {
    "iso:country":"US",
    "sg:address":"303 S Peters Ave",
    "sg:city":"Norman",
    "sg:classifiers":[
        {
            "category":"Professional",
            "subcategory":"Lawyer & Legal Services",
            "type":"Services"
        }
    ],
    "sg:phone":"+1 405 579 4480",
    "sg:postcode":"73069",
    "sg:province":"OK",
    "sg:tags":[
        "attorney"
    ],
    "wof:name":"Steve L Stice",
    "wof:placetype":"venue"
},
  "geometry": {"coordinates":[-97.440036,35.218785],"type":"Point"}
}