{
  "type": "Feature",
  "properties": {
    "iso:country":"US",
    "sg:address":"301 N Grand Ave",
    "sg:city":"Cherokee",
    "sg:classifiers":[
        {
            "category":"Home & Garden",
            "subcategory":"Building Materials",
            "type":"Retail Goods"
        }
    ],
    "sg:phone":"+1 580 596 3481",
    "sg:postcode":"73728",
    "sg:province":"OK",
    "sg:tags":[
        "lumber"
    ],
    "wof:name":"T H Rogers Lumber Co",
    "wof:placetype":"venue"
},
  "geometry": {"coordinates":[-98.357112,36.761392],"type":"Point"}
}