{
  "type": "Feature",
  "properties": {
    "iso:country":"US",
    "sg:address":"6437 N Olie Ave",
    "sg:city":"Oklahoma City",
    "sg:classifiers":[
        {
            "category":"Professional",
            "subcategory":"Art Services",
            "type":"Services"
        }
    ],
    "sg:phone":"+1 405 840 4771",
    "sg:postcode":"73116",
    "sg:province":"OK",
    "sg:tags":[
        "graphic",
        "designer"
    ],
    "wof:name":"B Creative Inc",
    "wof:placetype":"venue"
},
  "geometry": {"coordinates":[-97.528595,35.538593],"type":"Point"}
}