{
  "type": "Feature",
  "properties": {
    "iso:country":"US",
    "sg:address":"3304 S Boomer Rd",
    "sg:city":"Stillwater",
    "sg:classifiers":[
        {
            "category":"Utilities",
            "subcategory":"Electric",
            "type":"Services"
        }
    ],
    "sg:phone":"+1 405 372 2884",
    "sg:postcode":"74074",
    "sg:province":"OK",
    "sg:tags":[
        "company"
    ],
    "sg:website":"www.crec.coop",
    "wof:name":"Central Rural Electric",
    "wof:placetype":"venue"
},
  "geometry": {"coordinates":[-97.053803,36.086004],"type":"Point"}
}