{
  "type": "Feature",
  "properties": {
    "iso:country":"US",
    "sg:address":"500 N 15th St",
    "sg:city":"Frederick",
    "sg:classifiers":[
        {
            "category":"Organizations",
            "subcategory":"Religious Organization",
            "type":"Services"
        }
    ],
    "sg:phone":"+1 580 335 3521",
    "sg:postcode":"73542",
    "sg:province":"OK",
    "wof:name":"First Christian Church",
    "wof:placetype":"venue"
},
  "geometry": {"coordinates":[-99.01072499999999,34.395007],"type":"Point"}
}