{
  "type": "Feature",
  "properties": {
    "addr:full":"102 S Main St Davidson OK 73530",
    "addr:housenumber":"102",
    "addr:postcode":"73530",
    "addr:street":"S Main St",
    "iso:country":"US",
    "sg:address":"102 S Main St",
    "sg:city":"Davidson",
    "sg:classifiers":[
        {
            "category":"Banks & Credit Unions",
            "subcategory":"Bank",
            "type":"Services"
        }
    ],
    "sg:phone":"+1 580 568 2273",
    "sg:postcode":"73530",
    "sg:province":"OK",
    "wof:name":"First State Bank",
    "wof:placetype":"venue"
},
  "geometry": {"coordinates":[-99.07803699999999,34.241722],"type":"Point"}
}