{
  "type": "Feature",
  "properties": {
    "iso:country":"US",
    "sg:address":"510 S Broadway Ave",
    "sg:city":"Ada",
    "sg:classifiers":[
        {
            "category":"Shopping",
            "subcategory":"Used Merchandise",
            "type":"Retail Goods"
        }
    ],
    "sg:phone":"+1 918 482 2623",
    "sg:postcode":"74820",
    "sg:province":"OK",
    "sg:tags":[
        "antique"
    ],
    "wof:name":"Yester Daze",
    "wof:placetype":"venue"
},
  "geometry": {"coordinates":[-96.678539,34.769838],"type":"Point"}
}