{
  "type": "Feature",
  "properties": {
    "iso:country":"US",
    "sg:address":"3306 S Mingo Rd",
    "sg:city":"Tulsa",
    "sg:classifiers":[
        {
            "category":"Shopping",
            "subcategory":"Jewelry",
            "type":"Retail Goods"
        }
    ],
    "sg:phone":"+1 918 664 7710",
    "sg:postcode":"74146",
    "sg:province":"OK",
    "sg:tags":[
        "sporting",
        "used"
    ],
    "wof:name":"Once A Pawn A Time Inc",
    "wof:placetype":"venue"
},
  "geometry": {"coordinates":[-95.86865299999999,36.116223],"type":"Point"}
}