{
  "type": "Feature",
  "properties": {
    "iso:country":"US",
    "sg:address":"435 W Broadway St",
    "sg:city":"Muskogee",
    "sg:classifiers":[
        {
            "category":"Health Services",
            "subcategory":"Optometrist",
            "type":"Services"
        }
    ],
    "sg:phone":"+1 918 687 4459",
    "sg:postcode":"74401",
    "sg:province":"OK",
    "sg:tags":[
        "clinic"
    ],
    "wof:name":"Candace Stewart & Associates",
    "wof:placetype":"venue"
},
  "geometry": {"coordinates":[-95.372642,35.749938],"type":"Point"}
}