{
  "type": "Feature",
  "properties": {
    "iso:country":"US",
    "sg:address":"1838 NW 1st St",
    "sg:city":"Oklahoma City",
    "sg:classifiers":[
        {
            "category":"Personal",
            "type":"Services"
        }
    ],
    "sg:phone":"+1 405 232 3571",
    "sg:postcode":"73106",
    "sg:province":"OK",
    "sg:tags":[
        "wear",
        "formal"
    ],
    "wof:name":"Tuxedo Specialists",
    "wof:placetype":"venue"
},
  "geometry": {"coordinates":[-97.54764,35.468783],"type":"Point"}
}