{
  "type": "Feature",
  "properties": {
    "iso:country":"US",
    "sg:address":"208 S Guthrie Ave",
    "sg:city":"Tulsa",
    "sg:classifiers":[
        {
            "category":"Organizations",
            "subcategory":"Labor Organization",
            "type":"Services"
        }
    ],
    "sg:phone":"+1 918 583 5261",
    "sg:postcode":"74103",
    "sg:province":"OK",
    "wof:name":"Laborers International Un N A",
    "wof:placetype":"venue"
},
  "geometry": {"coordinates":[-95.998283,36.150999],"type":"Point"}
}