{
  "type": "Feature",
  "properties": {
    "iso:country":"US",
    "sg:address":"310 W Taft Ave",
    "sg:city":"Sapulpa",
    "sg:classifiers":[
        {
            "category":"Health Services",
            "subcategory":"Nursing And Care Facility",
            "type":"Services"
        }
    ],
    "sg:phone":"+1 918 224 6012",
    "sg:postcode":"74066",
    "sg:province":"OK",
    "sg:tags":[
        "home",
        "skilled",
        "convalescent"
    ],
    "wof:name":"Pleasant Manor Nursing Home",
    "wof:placetype":"venue"
},
  "geometry": {"coordinates":[-96.117617,35.988385],"type":"Point"}
}