{
  "type": "Feature",
  "properties": {
    "iso:country":"US",
    "sg:address":"2211 US Hwy 81",
    "sg:city":"Duncan",
    "sg:classifiers":[
        {
            "category":"Building & Trades",
            "subcategory":"Equipment Rental",
            "type":"Services"
        }
    ],
    "sg:phone":"+1 580 255 4530",
    "sg:postcode":"73533",
    "sg:province":"OK",
    "sg:tags":[
        "leasing"
    ],
    "wof:name":"Duncan Leasing Co",
    "wof:placetype":"venue"
},
  "geometry": {"coordinates":[-97.966874,34.532164],"type":"Point"}
}