{
  "type": "Feature",
  "properties": {
    "addr:full":"1255 N Washington Ave Durant OK 74701",
    "addr:housenumber":"1255",
    "addr:postcode":"74701",
    "addr:street":"N Washington Ave",
    "iso:country":"US",
    "sg:address":"1255 N Washington Ave",
    "sg:city":"Durant",
    "sg:classifiers":[
        {
            "category":"Restaurant",
            "type":"Food & Drink"
        }
    ],
    "sg:phone":"+1 580 924 5388",
    "sg:postcode":"74701",
    "sg:province":"OK",
    "sg:tags":[
        "eating"
    ],
    "wof:name":"Great Wall",
    "wof:placetype":"venue"
},
  "geometry": {"coordinates":[-96.390507,34.005628],"type":"Point"}
}