{
  "type": "Feature",
  "properties": {
    "iso:country":"US",
    "sg:address":"420 S Cleveland St",
    "sg:city":"Enid",
    "sg:classifiers":[
        {
            "category":"Food & Beverages",
            "subcategory":"Liquor & Beverages",
            "type":"Retail Goods"
        }
    ],
    "sg:phone":"+1 580 237 7117",
    "sg:postcode":"73703",
    "sg:province":"OK",
    "sg:tags":[
        "alcoholic"
    ],
    "wof:name":"JB Liquor Store",
    "wof:placetype":"venue"
},
  "geometry": {"coordinates":[-97.90796,36.391874],"type":"Point"}
}