{
  "type": "Feature",
  "properties": {
    "iso:country":"US",
    "sg:address":"7610 Sally Brown Rd",
    "sg:city":"Muskogee",
    "sg:classifiers":[
        {
            "category":"Building & Trades",
            "subcategory":"Electrical",
            "type":"Services"
        }
    ],
    "sg:phone":"+1 918 683 2345",
    "sg:postcode":"74403",
    "sg:province":"OK",
    "sg:tags":[
        "electrical",
        "contractor"
    ],
    "wof:name":"National Electric",
    "wof:placetype":"venue"
},
  "geometry": {"coordinates":[-95.24819599999999,35.711477],"type":"Point"}
}