{
  "type": "Feature",
  "properties": {
    "iso:country":"US",
    "sg:address":"619 Broadway",
    "sg:city":"Prague",
    "sg:classifiers":[
        {
            "category":"Mining & Drilling",
            "type":"Manufacturing & Wholesale Goods"
        }
    ],
    "sg:phone":"+1 405 567 4606",
    "sg:postcode":"74873",
    "sg:province":"OK",
    "sg:tags":[
        "oil",
        "gas",
        "producer"
    ],
    "wof:name":"Simek Oil Properties Inc",
    "wof:placetype":"venue"
},
  "geometry": {"coordinates":[-96.936717,35.263598],"type":"Point"}
}