{
  "type": "Feature",
  "properties": {
    "iso:country":"US",
    "sg:address":"4017 SE 29th St",
    "sg:city":"Oklahoma City",
    "sg:classifiers":[
        {
            "category":"Autos & Motor Vehicles",
            "subcategory":"Fuel & Gas Station",
            "type":"Retail Goods"
        }
    ],
    "sg:phone":"+1 405 677 8133",
    "sg:postcode":"73115",
    "sg:province":"OK",
    "sg:tags":[
        "grocery",
        "station",
        "gasoline"
    ],
    "wof:name":"Okie Mini Mart",
    "wof:placetype":"venue"
},
  "geometry": {"coordinates":[-97.443731,35.435304],"type":"Point"}
}