{
  "type": "Feature",
  "properties": {
    "iso:country":"US",
    "sg:address":"1932 Quail Run",
    "sg:city":"Newcastle",
    "sg:classifiers":[
        {
            "category":"Shopping",
            "subcategory":"Computers & Home Electronics",
            "type":"Retail Goods"
        }
    ],
    "sg:phone":"+1 405 387 3192",
    "sg:postcode":"73065",
    "sg:province":"OK",
    "sg:tags":[
        "parts",
        "supply"
    ],
    "wof:name":"C & B Form Shop",
    "wof:placetype":"venue"
},
  "geometry": {"coordinates":[-97.625039,35.233806],"type":"Point"}
}