{
  "type": "Feature",
  "properties": {
    "addr:full":"1112 E 6th Ave Stillwater OK 74074",
    "addr:housenumber":"1112",
    "addr:postcode":"74074",
    "addr:street":"E 6Th Ave",
    "iso:country":"US",
    "sg:address":"1112 E 6th Ave",
    "sg:city":"Stillwater",
    "sg:classifiers":[
        {
            "category":"Autos & Motor Vehicles",
            "subcategory":"Automobile Sales",
            "type":"Retail Goods"
        }
    ],
    "sg:phone":"+1 405 743 0000",
    "sg:postcode":"74074",
    "sg:province":"OK",
    "sg:tags":[
        "car",
        "dealer"
    ],
    "wof:name":"Cowboy Cars",
    "wof:placetype":"venue"
},
  "geometry": {"coordinates":[-97.044743,36.116086],"type":"Point"}
}