{
  "type": "Feature",
  "properties": {
    "addr:full":"17480 NE 23rd St Choctaw OK 73020",
    "addr:housenumber":"17480",
    "addr:postcode":"73020",
    "addr:street":"Ne 23Rd St",
    "iso:country":"US",
    "sg:address":"17480 NE 23rd St",
    "sg:city":"Choctaw",
    "sg:classifiers":[
        {
            "category":"Sports & Exercise",
            "subcategory":"Gym",
            "type":"Entertainment"
        }
    ],
    "sg:phone":"+1 405 390 0295",
    "sg:postcode":"73020",
    "sg:province":"OK",
    "sg:tags":[
        "fitness",
        "physical",
        "facility"
    ],
    "wof:name":"Curves For Women",
    "wof:placetype":"venue"
},
  "geometry": {"coordinates":[-97.220373,35.493263],"type":"Point"}
}