{
  "type": "Feature",
  "properties": {
    "iso:country":"US",
    "sg:address":"2701 S Council Rd",
    "sg:city":"Oklahoma City",
    "sg:classifiers":[
        {
            "category":"Autos & Motor Vehicles",
            "subcategory":"Auto Supplies",
            "type":"Retail Goods"
        }
    ],
    "sg:phone":"+1 405 745 4473",
    "sg:postcode":"73128",
    "sg:province":"OK",
    "sg:tags":[
        "tire"
    ],
    "wof:name":"Tire Centers LLC",
    "wof:placetype":"venue"
},
  "geometry": {"coordinates":[-97.654123,35.446642],"type":"Point"}
}