{
  "type": "Feature",
  "properties": {
    "iso:country":"US",
    "sg:address":"1002 S McQuarrie Ave",
    "sg:city":"Wagoner",
    "sg:classifiers":[
        {
            "category":"Insurance",
            "subcategory":"Insurance Agent",
            "type":"Services"
        }
    ],
    "sg:phone":"+1 918 485 3429",
    "sg:postcode":"74467",
    "sg:province":"OK",
    "wof:name":"Olson Insurance",
    "wof:placetype":"venue"
},
  "geometry": {"coordinates":[-95.367193,35.949906],"type":"Point"}
}