{
  "type": "Feature",
  "properties": {
    "iso:country":"US",
    "sg:address":"3939 S Harvard Ave",
    "sg:city":"Tulsa",
    "sg:classifiers":[
        {
            "category":"Building & Trades",
            "subcategory":"Electrical",
            "type":"Services"
        }
    ],
    "sg:phone":"+1 918 747 3210",
    "sg:postcode":"74135",
    "sg:province":"OK",
    "sg:tags":[
        "home",
        "system",
        "automation"
    ],
    "sg:website":"www.phonographonline.com",
    "wof:name":"Phonograph",
    "wof:placetype":"venue"
},
  "geometry": {"coordinates":[-95.940138,36.104734],"type":"Point"}
}