{
  "type": "Feature",
  "properties": {
    "addr:full":"4411 W Gore Blvd Lawton OK 73505",
    "addr:housenumber":"4411",
    "addr:postcode":"73505",
    "addr:street":"W Gore Blvd",
    "iso:country":"US",
    "sg:address":"4411 W Gore Blvd",
    "sg:city":"Lawton",
    "sg:classifiers":[
        {
            "category":"Health Services",
            "subcategory":"Doctor",
            "type":"Services"
        }
    ],
    "sg:phone":"+1 580 351 2400",
    "sg:postcode":"73505",
    "sg:province":"OK",
    "sg:tags":[
        "physician",
        "surgeon",
        "medical"
    ],
    "wof:name":"Nabila El Zind MD",
    "wof:placetype":"venue"
},
  "geometry": {"coordinates":[-98.445852,34.609003],"type":"Point"}
}