{
  "type": "Feature",
  "properties": {
    "addr:full":"1005 Jenkins Ave Norman OK 73069",
    "addr:housenumber":"1005",
    "addr:postcode":"73069",
    "addr:street":"Jenkins Ave",
    "iso:country":"US",
    "sg:address":"1005 Jenkins Ave",
    "sg:city":"Norman",
    "sg:classifiers":[
        {
            "category":"Education",
            "subcategory":"College",
            "type":"Public Place"
        }
    ],
    "sg:phone":"+1 405 325 2821",
    "sg:postcode":"73069",
    "sg:province":"OK",
    "wof:name":"Social Works",
    "wof:placetype":"venue"
},
  "geometry": {"coordinates":[-97.441199,35.207514],"type":"Point"}
}