{
  "type": "Feature",
  "properties": {
    "addr:full":"11605 Blueridge Ct Oklahoma City OK 73162",
    "addr:housenumber":"11605",
    "addr:postcode":"73162",
    "addr:street":"Blueridge Ct",
    "iso:country":"US",
    "sg:address":"11605 Blueridge Ct",
    "sg:city":"Oklahoma City",
    "sg:classifiers":[
        {
            "category":"Shopping",
            "subcategory":"Computers & Home Electronics",
            "type":"Retail Goods"
        }
    ],
    "sg:phone":"+1 405 205 4829",
    "sg:postcode":"73162",
    "sg:province":"OK",
    "sg:tags":[
        "software"
    ],
    "wof:name":"Database Application Solutions",
    "wof:placetype":"venue"
},
  "geometry": {"coordinates":[-97.67280599999999,35.591749],"type":"Point"}
}