{
  "type": "Feature",
  "properties": {
    "addr:full":"1230 N Sooner Rd Edmond OK 73034",
    "addr:housenumber":"1230",
    "addr:postcode":"73034",
    "addr:street":"N Sooner Rd",
    "iso:country":"US",
    "sg:address":"1230 N Sooner Rd",
    "sg:city":"Edmond",
    "sg:classifiers":[
        {
            "category":"Organizations",
            "subcategory":"Religious Organization",
            "type":"Services"
        }
    ],
    "sg:phone":"+1 405 348 1745",
    "sg:postcode":"73034",
    "sg:province":"OK",
    "sg:tags":[
        "church"
    ],
    "wof:name":"Fairview Baptist Church",
    "wof:placetype":"venue"
},
  "geometry": {"coordinates":[-97.42490599999999,35.663921],"type":"Point"}
}