{
  "type": "Feature",
  "properties": {
    "iso:country":"US",
    "sg:address":"501 N Main St",
    "sg:city":"Muskogee",
    "sg:classifiers":[
        {
            "category":"Shopping",
            "subcategory":"Department Store",
            "type":"Retail Goods"
        }
    ],
    "sg:phone":"+1 918 682 1000",
    "sg:postcode":"74401",
    "sg:province":"OK",
    "sg:website":"www.dillards.com",
    "wof:name":"Dillard's",
    "wof:placetype":"venue"
},
  "geometry": {"coordinates":[-95.366723,35.752663],"type":"Point"}
}