{
  "type": "Feature",
  "properties": {
    "iso:country":"US",
    "sg:address":"1410 N 155th East Ave",
    "sg:city":"Tulsa",
    "sg:classifiers":[
        {
            "category":"Building & Trades",
            "subcategory":"Cleaning & Sanitation",
            "type":"Services"
        }
    ],
    "sg:phone":"+1 918 232 0918",
    "sg:postcode":"74116",
    "sg:province":"OK",
    "sg:tags":[
        "window"
    ],
    "wof:name":"Budget Glass Cleaning",
    "wof:placetype":"venue"
},
  "geometry": {"coordinates":[-95.804258,36.175469],"type":"Point"}
}