{
  "type": "Feature",
  "properties": {
    "iso:country":"US",
    "sg:address":"510 S Allegheny Ave",
    "sg:city":"Tulsa",
    "sg:classifiers":[
        {
            "category":"Professional",
            "subcategory":"Business Services",
            "type":"Services"
        }
    ],
    "sg:phone":"+1 918 834 7585",
    "sg:postcode":"74112",
    "sg:province":"OK",
    "sg:tags":[
        "consultant",
        "coach"
    ],
    "wof:name":"Hoefling Consulting",
    "wof:placetype":"venue"
},
  "geometry": {"coordinates":[-95.919352,36.152895],"type":"Point"}
}