{
  "type": "Feature",
  "properties": {
    "addr:full":"8233 W Reno Ave Oklahoma City OK 73127",
    "addr:housenumber":"8233",
    "addr:postcode":"73127",
    "addr:street":"W Reno Ave",
    "iso:country":"US",
    "sg:address":"8233 W Reno Ave",
    "sg:city":"Oklahoma City",
    "sg:classifiers":[
        {
            "category":"Wholesale",
            "subcategory":"Machinery & Supplies",
            "type":"Manufacturing & Wholesale Goods"
        }
    ],
    "sg:phone":"+1 405 495 0606",
    "sg:postcode":"73127",
    "sg:province":"OK",
    "sg:tags":[
        "equipment",
        "industrial",
        "electrical",
        "repair"
    ],
    "wof:name":"Van Keppel Lift Truck",
    "wof:placetype":"venue"
},
  "geometry": {"coordinates":[-97.658676,35.464193],"type":"Point"}
}