{
  "type": "Feature",
  "properties": {
    "iso:country":"US",
    "sg:address":"6825 S Memorial Dr",
    "sg:city":"Tulsa",
    "sg:classifiers":[
        {
            "category":"Restaurant",
            "type":"Food & Drink"
        }
    ],
    "sg:phone":"+1 918 252 1444",
    "sg:postcode":"74133",
    "sg:province":"OK",
    "sg:tags":[
        "eating"
    ],
    "wof:name":"Taco Bueno 3031",
    "wof:placetype":"venue"
},
  "geometry": {"coordinates":[-95.886238,36.063748],"type":"Point"}
}