{
  "type": "Feature",
  "properties": {
    "addr:full":"119 E Main St Sperry OK 74073",
    "addr:housenumber":"119",
    "addr:postcode":"74073",
    "addr:street":"E Main St",
    "iso:country":"US",
    "sg:address":"119 E Main St",
    "sg:city":"Sperry",
    "sg:classifiers":[
        {
            "category":"Wholesale",
            "subcategory":"Sporting Goods",
            "type":"Manufacturing & Wholesale Goods"
        }
    ],
    "sg:phone":"+1 918 288 7335",
    "sg:postcode":"74073",
    "sg:province":"OK",
    "sg:tags":[
        "equipment",
        "pool",
        "swimming"
    ],
    "wof:name":"Main St Pool Supply",
    "wof:placetype":"venue"
},
  "geometry": {"coordinates":[-95.989313,36.296678],"type":"Point"}
}