{
  "type": "Feature",
  "properties": {
    "iso:country":"US",
    "sg:address":"16352 E Hwy 20",
    "sg:city":"Claremore",
    "sg:classifiers":[
        {
            "category":"Retail",
            "subcategory":"Veterinary Services",
            "type":"Services"
        }
    ],
    "sg:phone":"+1 918 342 4554",
    "sg:postcode":"74019",
    "sg:province":"OK",
    "sg:tags":[
        "veterinarian"
    ],
    "wof:name":"Shipman Veterinary Svc",
    "wof:placetype":"venue"
},
  "geometry": {"coordinates":[-95.537529,36.30742],"type":"Point"}
}