{
  "type": "Feature",
  "properties": {
    "iso:country":"US",
    "sg:address":"6305 E 86th Pl",
    "sg:city":"Tulsa",
    "sg:classifiers":[
        {
            "category":"Farming",
            "subcategory":"Livestock Farm",
            "type":"Manufacturing & Wholesale Goods"
        }
    ],
    "sg:phone":"+1 918 495 0856",
    "sg:postcode":"74137",
    "sg:province":"OK",
    "sg:tags":[
        "beef",
        "feedlot",
        "cattle"
    ],
    "wof:name":"Larry Edwards",
    "wof:placetype":"venue"
},
  "geometry": {"coordinates":[-95.905198,36.03742],"type":"Point"}
}