{
  "type": "Feature",
  "properties": {
    "iso:country":"US",
    "sg:address":"3105 Acme Rd",
    "sg:city":"Shawnee",
    "sg:classifiers":[
        {
            "category":"Real Estate",
            "subcategory":"Real Estate Operator",
            "type":"Services"
        }
    ],
    "sg:phone":"+1 405 214 6000",
    "sg:postcode":"74804",
    "sg:province":"OK",
    "sg:tags":[
        "building",
        "apartment"
    ],
    "wof:name":"Ashford Place Apartments",
    "wof:placetype":"venue"
},
  "geometry": {"coordinates":[-96.965151,35.366831],"type":"Point"}
}