{
  "type": "Feature",
  "properties": {
    "iso:country":"US",
    "sg:address":"2411 E Skelly Dr",
    "sg:city":"Tulsa",
    "sg:classifiers":[
        {
            "category":"Banks & Credit Unions",
            "subcategory":"Investment Brokerage",
            "type":"Services"
        }
    ],
    "sg:phone":"+1 918 747 2001",
    "sg:postcode":"74105",
    "sg:province":"OK",
    "sg:tags":[
        "advisory",
        "financial"
    ],
    "wof:name":"Harley Financial Svc",
    "wof:placetype":"venue"
},
  "geometry": {"coordinates":[-95.956042,36.09111],"type":"Point"}
}