{
  "type": "Feature",
  "properties": {
    "addr:full":"301 S 6th St Clinton OK 73601",
    "addr:housenumber":"301",
    "addr:postcode":"73601",
    "addr:street":"S 6Th St",
    "iso:country":"US",
    "sg:address":"301 S 6th St",
    "sg:city":"Clinton",
    "sg:classifiers":[
        {
            "category":"Government",
            "subcategory":"Office",
            "type":"Public Place"
        }
    ],
    "sg:phone":"+1 580 323 1527",
    "sg:postcode":"73601",
    "sg:province":"OK",
    "sg:tags":[
        "state",
        "program",
        "health"
    ],
    "wof:name":"Health Care Resources",
    "wof:placetype":"venue"
},
  "geometry": {"coordinates":[-98.96720000000001,35.51227],"type":"Point"}
}