{
  "type": "Feature",
  "properties": {
    "iso:country":"US",
    "sg:address":"5102 W Owen K Garriott Rd",
    "sg:city":"Enid",
    "sg:classifiers":[
        {
            "category":"Food & Beverages",
            "subcategory":"Bakery",
            "type":"Retail Goods"
        }
    ],
    "sg:phone":"+1 580 234 2412",
    "sg:postcode":"73703",
    "sg:province":"OK",
    "wof:name":"Wonder Bread Branch 12",
    "wof:placetype":"venue"
},
  "geometry": {"coordinates":[-97.940545,36.390937],"type":"Point"}
}