{
  "type": "Feature",
  "properties": {
    "iso:country":"US",
    "sg:address":"515 W Main St",
    "sg:city":"Jenks",
    "sg:classifiers":[
        {
            "category":"Wholesale",
            "subcategory":"Auto Parts",
            "type":"Manufacturing & Wholesale Goods"
        }
    ],
    "sg:phone":"+1 918 298 8765",
    "sg:postcode":"74037",
    "sg:province":"OK",
    "sg:tags":[
        "body",
        "automobile",
        "shop"
    ],
    "wof:name":"PBE Solutions Inc",
    "wof:placetype":"venue"
},
  "geometry": {"coordinates":[-95.977012,36.022674],"type":"Point"}
}