{
  "type": "Feature",
  "properties": {
    "iso:country":"US",
    "sg:address":"816 Royal Ave",
    "sg:city":"Oklahoma City",
    "sg:classifiers":[
        {
            "category":"Retail",
            "subcategory":"Car Wash",
            "type":"Services"
        }
    ],
    "sg:phone":"+1 405 732 8011",
    "sg:postcode":"73130",
    "sg:province":"OK",
    "sg:tags":[
        "automobile",
        "detail",
        "clean"
    ],
    "wof:name":"James Detail Shop",
    "wof:placetype":"venue"
},
  "geometry": {"coordinates":[-97.35505000000001,35.477267],"type":"Point"}
}