{
  "type": "Feature",
  "properties": {
    "iso:country":"US",
    "sg:address":"6 SW F Ave",
    "sg:city":"Lawton",
    "sg:classifiers":[
        {
            "category":"Home & Garden",
            "subcategory":"Carpets & Floor Coverings",
            "type":"Retail Goods"
        }
    ],
    "sg:phone":"+1 580 355 4653",
    "sg:postcode":"73501",
    "sg:province":"OK",
    "sg:tags":[
        "laying",
        "contractor"
    ],
    "wof:name":"Browns Carpets",
    "wof:placetype":"venue"
},
  "geometry": {"coordinates":[-98.386365,34.601608],"type":"Point"}
}