{
  "type": "Feature",
  "properties": {
    "iso:country":"US",
    "sg:address":"824 S Main St",
    "sg:city":"Stillwater",
    "sg:classifiers":[
        {
            "category":"Communications",
            "subcategory":"Television Station",
            "type":"Services"
        }
    ],
    "sg:phone":"+1 405 377 8831",
    "sg:postcode":"74074",
    "sg:province":"OK",
    "sg:tags":[
        "broadcasting",
        "co"
    ],
    "wof:name":"KWEM",
    "wof:placetype":"venue"
},
  "geometry": {"coordinates":[-97.058656,36.113207],"type":"Point"}
}