{
  "type": "Feature",
  "properties": {
    "addr:full":"8011 NW 82nd St Oklahoma City OK 73132",
    "addr:housenumber":"8011",
    "addr:postcode":"73132",
    "addr:street":"Nw 82Nd St",
    "iso:country":"US",
    "sg:address":"8011 NW 82nd St",
    "sg:city":"Oklahoma City",
    "sg:classifiers":[
        {
            "category":"Professional",
            "subcategory":"Business Services",
            "type":"Services"
        }
    ],
    "sg:phone":"+1 405 844 2573",
    "sg:postcode":"73132",
    "sg:province":"OK",
    "wof:name":"Fast Stitch",
    "wof:placetype":"venue"
},
  "geometry": {"coordinates":[-97.656567,35.55485],"type":"Point"}
}