{
  "type": "Feature",
  "properties": {
    "iso:country":"US",
    "sg:address":"305 W Caddo St",
    "sg:city":"Cleveland",
    "sg:classifiers":[
        {
            "category":"Health Services",
            "subcategory":"Doctor",
            "type":"Services"
        }
    ],
    "sg:phone":"+1 580 358 3512",
    "sg:postcode":"74020",
    "sg:province":"OK",
    "sg:tags":[
        "dentist"
    ],
    "wof:name":"Dwight Turner DDS",
    "wof:placetype":"venue"
},
  "geometry": {"coordinates":[-96.467066,36.305763],"type":"Point"}
}