{
  "type": "Feature",
  "properties": {
    "iso:country":"US",
    "sg:address":"1301 SE 17th St",
    "sg:city":"Pryor",
    "sg:classifiers":[
        {
            "category":"Freight",
            "type":"Transportation"
        }
    ],
    "sg:phone":"+1 918 825 4619",
    "sg:postcode":"74361",
    "sg:province":"OK",
    "sg:tags":[
        "special"
    ],
    "wof:name":"Erwin Mini Storage",
    "wof:placetype":"venue"
},
  "geometry": {"coordinates":[-95.29915,36.28599],"type":"Point"}
}