{
  "type": "Feature",
  "properties": {
    "addr:full":"5272 Lake Rd Ponca City OK 74604",
    "addr:housenumber":"5272",
    "addr:postcode":"74604",
    "addr:street":"Lake Rd",
    "iso:country":"US",
    "sg:address":"5272 Lake Rd",
    "sg:city":"Ponca City",
    "sg:classifiers":[
        {
            "category":"Manufacturing",
            "subcategory":"Metals",
            "type":"Manufacturing & Wholesale Goods"
        }
    ],
    "sg:phone":"+1 580 762 8684",
    "sg:postcode":"74604",
    "sg:province":"OK",
    "sg:tags":[
        "building",
        "prefabricated",
        "mfg"
    ],
    "wof:name":"Madden Steel Buildings",
    "wof:placetype":"venue"
},
  "geometry": {"coordinates":[-97.011111,36.709472],"type":"Point"}
}