{
  "type": "Feature",
  "properties": {
    "iso:country":"US",
    "sg:address":"2505 Sunnyside Rd",
    "sg:city":"Durant",
    "sg:classifiers":[
        {
            "category":"Manufacturing",
            "subcategory":"Motor Vehicles & Parts",
            "type":"Manufacturing & Wholesale Goods"
        }
    ],
    "sg:phone":"+1 580 924 7157",
    "sg:postcode":"74701",
    "sg:province":"OK",
    "sg:tags":[
        "apparel",
        "automotive",
        "trimmings"
    ],
    "wof:name":"Double R Mfg",
    "wof:placetype":"venue"
},
  "geometry": {"coordinates":[-96.40766600000001,33.983068],"type":"Point"}
}