{
  "type": "Feature",
  "properties": {
    "addr:full":"12609 Arrowhead Ter Oklahoma City OK 73120",
    "addr:housenumber":"12609",
    "addr:postcode":"73120",
    "addr:street":"Arrowhead Ter",
    "iso:country":"US",
    "sg:address":"12609 Arrowhead Ter",
    "sg:city":"Oklahoma City",
    "sg:classifiers":[
        {
            "category":"Freight",
            "type":"Transportation"
        }
    ],
    "sg:phone":"+1 405 936 9401",
    "sg:postcode":"73120",
    "sg:province":"OK",
    "sg:tags":[
        "trucking"
    ],
    "wof:name":"GST Inc",
    "wof:placetype":"venue"
},
  "geometry": {"coordinates":[-97.595883,35.598974],"type":"Point"}
}