{
  "type": "Feature",
  "properties": {
    "iso:country":"US",
    "sg:address":"1200 N Moore Ave",
    "sg:city":"Oklahoma City",
    "sg:classifiers":[
        {
            "category":"Restaurant",
            "type":"Food & Drink"
        }
    ],
    "sg:menulink":"http://www.allmenus.com/ok/north-cleveland/211091-kfc---kentucky-fried-chicken/menu/",
    "sg:phone":"+1 405 794 3982",
    "sg:postcode":"73160",
    "sg:province":"OK",
    "sg:tags":[
        "american",
        "chicken"
    ],
    "wof:name":"KFC - Kentucky Fried Chicken",
    "wof:placetype":"venue"
},
  "geometry": {"coordinates":[-97.49704300000001,35.348392],"type":"Point"}
}