{
  "type": "Feature",
  "properties": {
    "addr:full":"324 N 19th St Guthrie OK 73044",
    "addr:housenumber":"324",
    "addr:postcode":"73044",
    "addr:street":"N 19Th St",
    "iso:country":"US",
    "sg:address":"324 N 19th St",
    "sg:city":"Guthrie",
    "sg:classifiers":[
        {
            "category":"Health Services",
            "subcategory":"Doctor",
            "type":"Services"
        }
    ],
    "sg:phone":"+1 405 282 6301",
    "sg:postcode":"73044",
    "sg:province":"OK",
    "sg:tags":[
        "clinic"
    ],
    "wof:name":"Center For Internal Medicine",
    "wof:placetype":"venue"
},
  "geometry": {"coordinates":[-97.44901900000001,35.880182],"type":"Point"}
}