{
  "type": "Feature",
  "properties": {
    "iso:country":"US",
    "sg:address":"1530 E 1st St",
    "sg:city":"Tulsa",
    "sg:classifiers":[
        {
            "category":"Professional",
            "subcategory":"Employment Agencies",
            "type":"Services"
        },
        {
            "category":"Building & Trades",
            "subcategory":"Construction",
            "type":"Services"
        }
    ],
    "sg:phone":"+1 918 582 7337",
    "sg:postcode":"74120",
    "sg:province":"OK",
    "sg:tags":[
        "consultant",
        "welder",
        "temporary",
        "contractor"
    ],
    "sg:website":"http://www.standbypersonnel.com",
    "wof:name":"Standby Personnel Inc",
    "wof:placetype":"venue"
},
  "geometry": {"coordinates":[-95.970896,36.158671],"type":"Point"}
}