{
  "type": "Feature",
  "properties": {
    "iso:country":"US",
    "sg:address":"630 24th Ave SW",
    "sg:city":"Norman",
    "sg:classifiers":[
        {
            "category":"Sports & Exercise",
            "subcategory":"Gym",
            "type":"Entertainment"
        }
    ],
    "sg:phone":"+1 405 321 4401",
    "sg:postcode":"73069",
    "sg:province":"OK",
    "sg:tags":[
        "fitness",
        "physical",
        "facility"
    ],
    "wof:name":"Image Plus",
    "wof:placetype":"venue"
},
  "geometry": {"coordinates":[-97.476737,35.212478],"type":"Point"}
}