{
  "type": "Feature",
  "properties": {
    "iso:country":"US",
    "sg:address":"18 Spring Creek Rd",
    "sg:city":"Muskogee",
    "sg:classifiers":[
        {
            "category":"Airport",
            "type":"Transportation"
        }
    ],
    "sg:phone":"+1 918 681 7599",
    "sg:postcode":"74401",
    "sg:province":"OK",
    "wof:name":"Air Park Race Way",
    "wof:placetype":"venue"
},
  "geometry": {"coordinates":[-95.420207,35.762899],"type":"Point"}
}