{
  "type": "Feature",
  "properties": {
    "addr:full":"2141 E Brook Ter Mustang OK 73064",
    "addr:housenumber":"2141",
    "addr:postcode":"73064",
    "addr:street":"E Brook Ter",
    "iso:country":"US",
    "sg:address":"2141 E Brook Ter",
    "sg:city":"Mustang",
    "sg:classifiers":[
        {
            "category":"Farming",
            "subcategory":"Livestock Farm",
            "type":"Manufacturing & Wholesale Goods"
        }
    ],
    "sg:phone":"+1 405 745 9351",
    "sg:postcode":"73064",
    "sg:province":"OK",
    "sg:tags":[
        "general"
    ],
    "wof:name":"Austin Livestock",
    "wof:placetype":"venue"
},
  "geometry": {"coordinates":[-97.67840700000001,35.395381],"type":"Point"}
}