{
  "type": "Feature",
  "properties": {
    "addr:full":"2325 SW 52nd St Oklahoma City OK 73119",
    "addr:housenumber":"2325",
    "addr:postcode":"73119",
    "addr:street":"Sw 52Nd St",
    "iso:country":"US",
    "sg:address":"2325 SW 52nd St",
    "sg:city":"Oklahoma City",
    "sg:classifiers":[
        {
            "category":"Building & Trades",
            "subcategory":"Construction",
            "type":"Services"
        }
    ],
    "sg:phone":"+1 405 681 9870",
    "sg:postcode":"73119",
    "sg:province":"OK",
    "sg:tags":[
        "residential",
        "nonresidential"
    ],
    "wof:name":"Hailey Construction",
    "wof:placetype":"venue"
},
  "geometry": {"coordinates":[-97.55436,35.412958],"type":"Point"}
}