{
  "type": "Feature",
  "properties": {
    "iso:country":"US",
    "sg:address":"3117 Hickory Stick Rd",
    "sg:city":"Oklahoma City",
    "sg:classifiers":[
        {
            "category":"Health Services",
            "subcategory":"Doctor",
            "type":"Services"
        }
    ],
    "sg:phone":"+1 405 751 9274",
    "sg:postcode":"73120",
    "sg:province":"OK",
    "sg:tags":[
        "medical"
    ],
    "wof:name":"Charles J Wine",
    "wof:placetype":"venue"
},
  "geometry": {"coordinates":[-97.57154,35.594204],"type":"Point"}
}