{
  "type": "Feature",
  "properties": {
    "addr:full":"721 NW 6th St Oklahoma City OK 73102",
    "addr:housenumber":"721",
    "addr:postcode":"73102",
    "addr:street":"Nw 6Th St",
    "iso:country":"US",
    "sg:address":"721 NW 6th St",
    "sg:city":"Oklahoma City",
    "sg:classifiers":[
        {
            "category":"Health Services",
            "subcategory":"Doctor",
            "type":"Services"
        }
    ],
    "sg:phone":"+1 405 271 7000",
    "sg:postcode":"73102",
    "sg:province":"OK",
    "sg:tags":[
        "physician",
        "surgeon"
    ],
    "wof:name":"Capstone Medical Group",
    "wof:placetype":"venue"
},
  "geometry": {"coordinates":[-97.525432,35.47428],"type":"Point"}
}