{
  "type": "Feature",
  "properties": {
    "iso:country":"US",
    "sg:address":"2214 NW 23rd St",
    "sg:city":"Oklahoma City",
    "sg:classifiers":[
        {
            "category":"Personal",
            "subcategory":"Beauty Salon",
            "type":"Services"
        }
    ],
    "sg:phone":"+1 405 525 3323",
    "sg:postcode":"73107",
    "sg:province":"OK",
    "sg:tags":[
        "shop"
    ],
    "wof:name":"Le Chic Salon",
    "wof:placetype":"venue"
},
  "geometry": {"coordinates":[-97.55063699999999,35.493178],"type":"Point"}
}