{
  "type": "Feature",
  "properties": {
    "iso:country":"US",
    "sg:address":"722 N Broadway Ave",
    "sg:city":"Oklahoma City",
    "sg:classifiers":[
        {
            "category":"Professional",
            "subcategory":"Engineering",
            "type":"Services"
        }
    ],
    "sg:phone":"+1 405 236 3011",
    "sg:postcode":"73102",
    "sg:province":"OK",
    "sg:tags":[
        "engineer"
    ],
    "wof:name":"Ross Relph ASM Co",
    "wof:placetype":"venue"
},
  "geometry": {"coordinates":[-97.51423699999999,35.47398],"type":"Point"}
}