{
  "type": "Feature",
  "properties": {
    "iso:country":"US",
    "sg:address":"739 SW 29th St",
    "sg:city":"Oklahoma City",
    "sg:classifiers":[
        {
            "category":"Autos & Motor Vehicles",
            "subcategory":"Auto Supplies",
            "type":"Retail Goods"
        }
    ],
    "sg:phone":"+1 405 606 4801",
    "sg:postcode":"73109",
    "sg:province":"OK",
    "sg:tags":[
        "tire"
    ],
    "wof:name":"Lopez Tires",
    "wof:placetype":"venue"
},
  "geometry": {"coordinates":[-97.527546,35.435323],"type":"Point"}
}