{
  "type": "Feature",
  "properties": {
    "iso:country":"US",
    "sg:address":"TULSA AND SURROUNDING AREAS",
    "sg:city":"Tulsa",
    "sg:classifiers":[
        {
            "category":"Professional",
            "subcategory":"Art Services",
            "type":"Services"
        },
        {
            "category":"Building & Trades",
            "subcategory":"Construction",
            "type":"Services"
        }
    ],
    "sg:phone":"+1 918 734 6206",
    "sg:postcode":"74107",
    "sg:province":"OK",
    "sg:tags":[
        "mason",
        "spray",
        "faux",
        "finishing",
        "contractor",
        "painting"
    ],
    "wof:name":"Home Beautiful Painting",
    "wof:placetype":"venue"
},
  "geometry": {"coordinates":[-96.042793,36.0881],"type":"Point"}
}