{
  "type": "Feature",
  "properties": {
    "addr:full":"18 Cedar Ridge Rd Broken Arrow OK 74011",
    "addr:housenumber":"18",
    "addr:postcode":"74011",
    "addr:street":"Cedar Ridge Rd",
    "iso:country":"US",
    "sg:address":"18 Cedar Ridge Rd",
    "sg:city":"Broken Arrow",
    "sg:classifiers":[
        {
            "category":"Airline",
            "type":"Transportation"
        }
    ],
    "sg:phone":"+1 918 250 0400",
    "sg:postcode":"74011",
    "sg:province":"OK",
    "sg:tags":[
        "scheduled",
        "air"
    ],
    "wof:name":"Air Oklahoma Inc",
    "wof:placetype":"venue"
},
  "geometry": {"coordinates":[-95.85225199999999,36.011775],"type":"Point"}
}