{
  "type": "Feature",
  "properties": {
    "iso:country":"US",
    "sg:address":"8092 S Yale Ave",
    "sg:city":"Tulsa",
    "sg:classifiers":[
        {
            "category":"Professional",
            "subcategory":"Accounting & Tax Preparation",
            "type":"Services"
        }
    ],
    "sg:phone":"+1 918 493 2940",
    "sg:postcode":"74136",
    "sg:province":"OK",
    "sg:tags":[
        "accountant"
    ],
    "wof:name":"Younger Accounting Service",
    "wof:placetype":"venue"
},
  "geometry": {"coordinates":[-95.9222,36.046543],"type":"Point"}
}