{
  "type": "Feature",
  "properties": {
    "iso:country":"US",
    "sg:address":"1010 N Van Buren St",
    "sg:city":"Enid",
    "sg:classifiers":[
        {
            "category":"Professional",
            "subcategory":"Accounting & Tax Preparation",
            "type":"Services"
        }
    ],
    "sg:phone":"+1 580 233 2091",
    "sg:postcode":"73703",
    "sg:province":"OK",
    "sg:tags":[
        "return",
        "filing"
    ],
    "wof:name":"Schoonover Agency",
    "wof:placetype":"venue"
},
  "geometry": {"coordinates":[-97.891205,36.407251],"type":"Point"}
}