{
  "type": "Feature",
  "properties": {
    "iso:country":"US",
    "sg:address":"919 W Willow Ave",
    "sg:city":"Duncan",
    "sg:classifiers":[
        {
            "category":"Wholesale",
            "subcategory":"Medical Equipment & Supplies",
            "type":"Manufacturing & Wholesale Goods"
        }
    ],
    "sg:phone":"+1 580 252 8164",
    "sg:postcode":"73533",
    "sg:province":"OK",
    "sg:tags":[
        "physician",
        "surgeon"
    ],
    "wof:name":"Med-Tech Of Duncan",
    "wof:placetype":"venue"
},
  "geometry": {"coordinates":[-97.959701,34.501009],"type":"Point"}
}