{
  "type": "Feature",
  "properties": {
    "iso:country":"US",
    "sg:address":"1209 W Bois D Arc Ave",
    "sg:city":"Duncan",
    "sg:classifiers":[
        {
            "category":"Restaurant",
            "type":"Food & Drink"
        }
    ],
    "sg:phone":"+1 580 252 1314",
    "sg:postcode":"73533",
    "sg:province":"OK",
    "sg:tags":[
        "eating"
    ],
    "wof:name":"El Palacio Mexican Restaurant",
    "wof:placetype":"venue"
},
  "geometry": {"coordinates":[-97.965126,34.492723],"type":"Point"}
}