{
  "type": "Feature",
  "properties": {
    "iso:country":"US",
    "sg:address":"5512 S Washington St",
    "sg:city":"Stillwater",
    "sg:classifiers":[
        {
            "category":"Retail",
            "subcategory":"Auto Repair",
            "type":"Services"
        }
    ],
    "sg:phone":"+1 405 780 7735",
    "sg:postcode":"74074",
    "sg:province":"OK",
    "sg:tags":[
        "wrecker"
    ],
    "wof:name":"A A Auto & Wrecker Svc",
    "wof:placetype":"venue"
},
  "geometry": {"coordinates":[-97.069147,36.058692],"type":"Point"}
}