{
  "type": "Feature",
  "properties": {
    "iso:country":"US",
    "sg:address":"109 E Choctaw Ave",
    "sg:city":"Bache",
    "sg:classifiers":[
        {
            "category":"Shopping",
            "subcategory":"Gifts & Souvenirs",
            "type":"Retail Goods"
        }
    ],
    "sg:phone":"+1 918 423 5512",
    "sg:postcode":"74501",
    "sg:province":"OK",
    "sg:tags":[
        "shop",
        "store"
    ],
    "wof:name":"Yellow Gazebo Inc",
    "wof:placetype":"venue"
},
  "geometry": {"coordinates":[-95.768551,34.932019],"type":"Point"}
}