{
  "type": "Feature",
  "properties": {
    "iso:country":"US",
    "sg:address":"1830 NW Crosby Park Cir",
    "sg:city":"Lawton",
    "sg:classifiers":[
        {
            "category":"Shopping",
            "subcategory":"Discount & Variety Stores",
            "type":"Retail Goods"
        }
    ],
    "sg:phone":"+1 580 536 2315",
    "sg:postcode":"73505",
    "sg:province":"OK",
    "sg:tags":[
        "merchandise",
        "general"
    ],
    "sg:website":"www.pu-usa.com",
    "wof:name":"Products Unlimited",
    "wof:placetype":"venue"
},
  "geometry": {"coordinates":[-98.46927599999999,34.629785],"type":"Point"}
}