{
  "type": "Feature",
  "properties": {
    "iso:country":"US",
    "sg:address":"3264 SW 44th St",
    "sg:city":"Oklahoma City",
    "sg:classifiers":[
        {
            "category":"Social Services",
            "subcategory":"Child Care",
            "type":"Services"
        }
    ],
    "sg:phone":"+1 405 682 5625",
    "sg:postcode":"73119",
    "sg:province":"OK",
    "sg:tags":[
        "center",
        "day"
    ],
    "wof:name":"New Beginings Learning Center",
    "wof:placetype":"venue"
},
  "geometry": {"coordinates":[-97.572468,35.420624],"type":"Point"}
}