{
  "type": "Feature",
  "properties": {
    "iso:country":"US",
    "sg:address":"717 S Hoff Ave",
    "sg:city":"El Reno",
    "sg:classifiers":[
        {
            "category":"Professional",
            "type":"Services"
        }
    ],
    "sg:phone":"+1 405 422 3706",
    "sg:postcode":"73036",
    "sg:province":"OK",
    "wof:name":"Dwight Darin Miller",
    "wof:placetype":"venue"
},
  "geometry": {"coordinates":[-97.949235,35.527603],"type":"Point"}
}