{
  "type": "Feature",
  "properties": {
    "iso:country":"US",
    "sg:address":"135 W 1st St",
    "sg:city":"Arcadia",
    "sg:classifiers":[
        {
            "category":"Shopping",
            "subcategory":"Gifts & Souvenirs",
            "type":"Retail Goods"
        }
    ],
    "sg:phone":"+1 405 396 2202",
    "sg:postcode":"73007",
    "sg:province":"OK",
    "sg:tags":[
        "indian"
    ],
    "wof:name":"Southwest Collectibles",
    "wof:placetype":"venue"
},
  "geometry": {"coordinates":[-97.328054,35.663076],"type":"Point"}
}