{
  "type": "Feature",
  "properties": {
    "addr:full":"611 N Illinois St Weatherford OK 73096",
    "addr:housenumber":"611",
    "addr:postcode":"73096",
    "addr:street":"N Illinois St",
    "iso:country":"US",
    "sg:address":"611 N Illinois St",
    "sg:city":"Weatherford",
    "sg:classifiers":[
        {
            "category":"Government",
            "subcategory":"Office",
            "type":"Public Place"
        }
    ],
    "sg:phone":"+1 580 772 1974",
    "sg:postcode":"73096",
    "sg:province":"OK",
    "sg:tags":[
        "village"
    ],
    "wof:name":"Scout Hut",
    "wof:placetype":"venue"
},
  "geometry": {"coordinates":[-98.701232,35.532035],"type":"Point"}
}