{
  "type": "Feature",
  "properties": {
    "addr:full":"2703 Spencer Rd Spencer OK 73084",
    "addr:housenumber":"2703",
    "addr:postcode":"73084",
    "addr:street":"Spencer Rd",
    "iso:country":"US",
    "sg:address":"2703 Spencer Rd",
    "sg:city":"Spencer",
    "sg:classifiers":[
        {
            "category":"Social Services",
            "subcategory":"Child Care",
            "type":"Services"
        }
    ],
    "sg:phone":"+1 405 424 5500",
    "sg:postcode":"73084",
    "sg:province":"OK",
    "wof:name":"First Steps Daycare",
    "wof:placetype":"venue"
},
  "geometry": {"coordinates":[-97.379817,35.496917],"type":"Point"}
}