{
  "type": "Feature",
  "properties": {
    "iso:country":"US",
    "sg:address":"9327 W Reno Ave",
    "sg:city":"Oklahoma City",
    "sg:classifiers":[
        {
            "category":"Recreation",
            "type":"Entertainment"
        }
    ],
    "sg:phone":"+1 405 789 4400",
    "sg:postcode":"73127",
    "sg:province":"OK",
    "sg:tags":[
        "range",
        "baseball",
        "batting"
    ],
    "wof:name":"Strike Zone",
    "wof:placetype":"venue"
},
  "geometry": {"coordinates":[-97.682123,35.464433],"type":"Point"}
}