{
  "type": "Feature",
  "properties": {
    "iso:country":"US",
    "sg:address":"1266 S Memorial Dr",
    "sg:city":"Tulsa",
    "sg:classifiers":[
        {
            "category":"Freight",
            "type":"Transportation"
        }
    ],
    "sg:phone":"+1 918 835 7774",
    "sg:postcode":"74112",
    "sg:province":"OK",
    "sg:tags":[
        "operator",
        "warehouse"
    ],
    "wof:name":"U-Stor-It Warehouse",
    "wof:placetype":"venue"
},
  "geometry": {"coordinates":[-95.88670999999999,36.143161],"type":"Point"}
}