{
  "type": "Feature",
  "properties": {
    "addr:full":"20515 W 51st St Sand Springs OK 74063",
    "addr:housenumber":"20515",
    "addr:postcode":"74063",
    "addr:street":"W 51St St",
    "iso:country":"US",
    "sg:address":"20515 W 51st St",
    "sg:city":"Sand Springs",
    "sg:classifiers":[
        {
            "category":"Wholesale",
            "subcategory":"Durable Goods & Equipment",
            "type":"Manufacturing & Wholesale Goods"
        }
    ],
    "sg:phone":"+1 918 363 8246",
    "sg:postcode":"74063",
    "sg:province":"OK",
    "wof:name":"Bartley & Assoc Inc",
    "wof:placetype":"venue"
},
  "geometry": {"coordinates":[-96.218029,36.09017],"type":"Point"}
}