{
  "type": "Feature",
  "properties": {
    "iso:country":"US",
    "sg:address":"5805 NW 63rd St",
    "sg:city":"Oklahoma City",
    "sg:classifiers":[
        {
            "category":"Shopping",
            "subcategory":"Gifts & Souvenirs",
            "type":"Retail Goods"
        }
    ],
    "sg:phone":"+1 405 603 3644",
    "sg:postcode":"73132",
    "sg:province":"OK",
    "sg:tags":[
        "shop"
    ],
    "wof:name":"Greenhouse Creations",
    "wof:placetype":"venue"
},
  "geometry": {"coordinates":[-97.618848,35.5369],"type":"Point"}
}