{
  "type": "Feature",
  "properties": {
    "iso:country":"US",
    "sg:address":"1904 Washington Blvd",
    "sg:city":"Oklahoma City",
    "sg:classifiers":[
        {
            "category":"Retail",
            "subcategory":"Portrait Studio",
            "type":"Services"
        }
    ],
    "sg:phone":"+1 405 427 6790",
    "sg:postcode":"73121",
    "sg:province":"OK",
    "sg:tags":[
        "photo"
    ],
    "wof:name":"Broiles Custom Photograph",
    "wof:placetype":"venue"
},
  "geometry": {"coordinates":[-97.453713,35.487062],"type":"Point"}
}