{
  "type": "Feature",
  "properties": {
    "iso:country":"US",
    "sg:address":"10026 S Mingo Rd",
    "sg:city":"Tulsa",
    "sg:classifiers":[
        {
            "category":"Professional",
            "subcategory":"Advertising",
            "type":"Services"
        }
    ],
    "sg:phone":"+1 918 249 8773",
    "sg:postcode":"74133",
    "sg:province":"OK",
    "sg:tags":[
        "mailing",
        "shipping"
    ],
    "wof:name":"Mail Boxes Etc",
    "wof:placetype":"venue"
},
  "geometry": {"coordinates":[-95.868595,36.019417],"type":"Point"}
}