{
  "type": "Feature",
  "properties": {
    "iso:country":"US",
    "sg:address":"27 Oakwood Dr",
    "sg:city":"Oklahoma City",
    "sg:classifiers":[
        {
            "category":"Travel",
            "subcategory":"Hotels & Motels",
            "type":"Entertainment"
        }
    ],
    "sg:phone":"+1 405 427 2133",
    "sg:postcode":"73121",
    "sg:province":"OK",
    "sg:tags":[
        "operation"
    ],
    "sg:website":"www.oklabedandbreakfast.com",
    "wof:name":"Willow Way Bed & Breakfast",
    "wof:placetype":"venue"
},
  "geometry": {"coordinates":[-97.441736,35.509116],"type":"Point"}
}