{
  "type": "Feature",
  "properties": {
    "addr:full":"1408 W D Ave Elk City OK 73644",
    "addr:housenumber":"1408",
    "addr:postcode":"73644",
    "addr:street":"W D Ave",
    "iso:country":"US",
    "sg:address":"1408 W D Ave",
    "sg:city":"Elk City",
    "sg:classifiers":[
        {
            "category":"Farming",
            "subcategory":"Livestock Farm",
            "type":"Manufacturing & Wholesale Goods"
        }
    ],
    "sg:phone":"+1 580 225 3777",
    "sg:postcode":"73644",
    "sg:province":"OK",
    "sg:tags":[
        "ranch",
        "farmer"
    ],
    "wof:name":"Simmons Ranches LTD",
    "wof:placetype":"venue"
},
  "geometry": {"coordinates":[-99.420097,35.417565],"type":"Point"}
}