{
  "type": "Feature",
  "properties": {
    "addr:full":"710 E Broadway St Drumright OK 74030",
    "addr:housenumber":"710",
    "addr:postcode":"74030",
    "addr:street":"E Broadway St",
    "iso:country":"US",
    "sg:address":"710 E Broadway St",
    "sg:city":"Drumright",
    "sg:classifiers":[
        {
            "category":"Restaurant",
            "type":"Food & Drink"
        }
    ],
    "sg:menulink":"http://www.allmenus.com/ok/drumright/199394-sonic/menu/",
    "sg:phone":"+1 918 352 4300",
    "sg:postcode":"74030",
    "sg:province":"OK",
    "sg:tags":[
        "burger",
        "american"
    ],
    "wof:name":"Sonic",
    "wof:placetype":"venue"
},
  "geometry": {"coordinates":[-96.594005,35.988447],"type":"Point"}
}