{
  "type": "Feature",
  "properties": {
    "iso:country":"US",
    "sg:address":"9108 E 47th Pl",
    "sg:city":"Tulsa",
    "sg:classifiers":[
        {
            "category":"Professional",
            "subcategory":"Employment Agencies",
            "type":"Services"
        }
    ],
    "sg:phone":"+1 918 622 1618",
    "sg:postcode":"74145",
    "sg:province":"OK",
    "wof:name":"D&S Personnel Inc",
    "wof:placetype":"venue"
},
  "geometry": {"coordinates":[-95.874235,36.095047],"type":"Point"}
}