{
  "type": "Feature",
  "properties": {
    "addr:full":"2524 SW 44th St Oklahoma City OK 73119",
    "addr:housenumber":"2524",
    "addr:postcode":"73119",
    "addr:street":"Sw 44Th St",
    "iso:country":"US",
    "sg:address":"2524 SW 44th St",
    "sg:city":"Oklahoma City",
    "sg:classifiers":[
        {
            "category":"Manufacturing",
            "subcategory":"Printing",
            "type":"Manufacturing & Wholesale Goods"
        }
    ],
    "sg:phone":"+1 405 685 3822",
    "sg:postcode":"73119",
    "sg:province":"OK",
    "sg:tags":[
        "newspaper"
    ],
    "wof:name":"Nuestra Counidra",
    "wof:placetype":"venue"
},
  "geometry": {"coordinates":[-97.55780300000001,35.420625],"type":"Point"}
}