{
  "type": "Feature",
  "properties": {
    "iso:country":"US",
    "sg:address":"7918 NW 10th St",
    "sg:city":"Oklahoma City",
    "sg:classifiers":[
        {
            "category":"Manufacturing",
            "subcategory":"Metals",
            "type":"Manufacturing & Wholesale Goods"
        }
    ],
    "sg:phone":"+1 405 787 4400",
    "sg:postcode":"73127",
    "sg:province":"OK",
    "sg:tags":[
        "fabricator",
        "sheet"
    ],
    "wof:name":"Council Stainless & Sheet Mtl",
    "wof:placetype":"venue"
},
  "geometry": {"coordinates":[-97.65398399999999,35.478701],"type":"Point"}
}