{
  "type": "Feature",
  "properties": {
    "addr:full":"116 E Broadway St Ardmore OK 73401",
    "addr:housenumber":"116",
    "addr:postcode":"73401",
    "addr:street":"E Broadway St",
    "iso:country":"US",
    "sg:address":"116 E Broadway St",
    "sg:city":"Ardmore",
    "sg:classifiers":[
        {
            "category":"Food & Beverages",
            "subcategory":"Groceries & Convenience Stores",
            "type":"Retail Goods"
        }
    ],
    "sg:phone":"+1 580 223 8821",
    "sg:postcode":"73401",
    "sg:province":"OK",
    "wof:name":"Keys Uptown Grocery Downtown",
    "wof:placetype":"venue"
},
  "geometry": {"coordinates":[-97.12698899999999,34.173962],"type":"Point"}
}