{
  "type": "Feature",
  "properties": {
    "iso:country":"US",
    "sg:address":"700 N York St",
    "sg:city":"Muskogee",
    "sg:classifiers":[
        {
            "category":"Wholesale",
            "subcategory":"Office Equipment",
            "type":"Manufacturing & Wholesale Goods"
        }
    ],
    "sg:phone":"+1 918 683 5274",
    "sg:postcode":"74403",
    "sg:province":"OK",
    "sg:tags":[
        "machine",
        "duplicating",
        "copying"
    ],
    "wof:name":"Lashley Office Systems",
    "wof:placetype":"venue"
},
  "geometry": {"coordinates":[-95.340372,35.749106],"type":"Point"}
}