{
  "type": "Feature",
  "properties": {
    "iso:country":"US",
    "sg:address":"30210 Oklahoma St",
    "sg:city":"Mcloud",
    "sg:classifiers":[
        {
            "category":"Real Estate",
            "subcategory":"Real Estate Operator",
            "type":"Services"
        }
    ],
    "sg:phone":"+1 405 964 3323",
    "sg:postcode":"74851",
    "sg:province":"OK",
    "sg:tags":[
        "mobile",
        "home",
        "community"
    ],
    "wof:name":"Shady Valley Mobile Home Park",
    "wof:placetype":"venue"
},
  "geometry": {"coordinates":[-97.120335,35.434812],"type":"Point"}
}