{
  "type": "Feature",
  "properties": {
    "iso:country":"US",
    "sg:address":"110 W 2nd St",
    "sg:city":"Wewoka",
    "sg:classifiers":[
        {
            "category":"Professional",
            "subcategory":"Accounting & Tax Preparation",
            "type":"Services"
        }
    ],
    "sg:phone":"+1 405 257 2490",
    "sg:postcode":"74884",
    "sg:province":"OK",
    "sg:tags":[
        "accountant"
    ],
    "wof:name":"Benny R Aguirre CPA",
    "wof:placetype":"venue"
},
  "geometry": {"coordinates":[-96.49190400000001,35.157603],"type":"Point"}
}