{
  "type": "Feature",
  "properties": {
    "addr:full":"3900 Price Rd Bartlesville OK 74006",
    "addr:housenumber":"3900",
    "addr:postcode":"74006",
    "addr:street":"Price Rd",
    "iso:country":"US",
    "sg:address":"3900 Price Rd",
    "sg:city":"Bartlesville",
    "sg:classifiers":[
        {
            "category":"Personal",
            "subcategory":"Beauty Salon",
            "type":"Services"
        }
    ],
    "sg:phone":"+1 918 335 3530",
    "sg:postcode":"74006",
    "sg:province":"OK",
    "sg:tags":[
        "shop"
    ],
    "wof:name":"Regis Salons",
    "wof:placetype":"venue"
},
  "geometry": {"coordinates":[-95.93425999999999,36.713609],"type":"Point"}
}