{
  "type": "Feature",
  "properties": {
    "iso:country":"US",
    "sg:address":"123 S Sunset Ln",
    "sg:city":"Guymon",
    "sg:classifiers":[
        {
            "category":"Professional",
            "subcategory":"Computer Services",
            "type":"Services"
        }
    ],
    "sg:phone":"+1 580 338 8850",
    "sg:postcode":"73942",
    "sg:province":"OK",
    "sg:tags":[
        "farm",
        "datum",
        "analysis"
    ],
    "wof:name":"Clyde G Haisten",
    "wof:placetype":"venue"
},
  "geometry": {"coordinates":[-101.49213,36.67833],"type":"Point"}
}