{
  "type": "Feature",
  "properties": {
    "addr:full":"8988 S Sheridan Rd Tulsa OK 74133",
    "addr:housenumber":"8988",
    "addr:postcode":"74133",
    "addr:street":"S Sheridan Rd",
    "iso:country":"US",
    "sg:address":"8988 S Sheridan Rd",
    "sg:city":"Tulsa",
    "sg:classifiers":[
        {
            "category":"Education",
            "subcategory":"Vocational School",
            "type":"Public Place"
        }
    ],
    "sg:phone":"+1 918 477 7891",
    "sg:postcode":"74133",
    "sg:province":"OK",
    "wof:name":"Tulsa Real Estate Academy",
    "wof:placetype":"venue"
},
  "geometry": {"coordinates":[-95.90424299999999,36.033623],"type":"Point"}
}