{
  "type": "Feature",
  "properties": {
    "iso:country":"US",
    "sg:address":"714 S Dunlap St",
    "sg:city":"Hennessey",
    "sg:classifiers":[
        {
            "category":"Insurance",
            "subcategory":"Insurance Agent",
            "type":"Services"
        }
    ],
    "sg:phone":"+1 405 853 4602",
    "sg:postcode":"73742",
    "sg:province":"OK",
    "wof:name":"King Fisher County Farm Bureau",
    "wof:placetype":"venue"
},
  "geometry": {"coordinates":[-97.90039400000001,36.102682],"type":"Point"}
}