{
  "type": "Feature",
  "properties": {
    "iso:country":"US",
    "sg:address":"213 E Stadium Rd",
    "sg:city":"Bixby",
    "sg:classifiers":[
        {
            "category":"Social Services",
            "subcategory":"Child Care",
            "type":"Services"
        }
    ],
    "sg:phone":"+1 918 366 7345",
    "sg:postcode":"74008",
    "sg:province":"OK",
    "sg:tags":[
        "day"
    ],
    "wof:name":"A Childs Dream Daycare Inc",
    "wof:placetype":"venue"
},
  "geometry": {"coordinates":[-95.879654,35.936057],"type":"Point"}
}