{
  "type": "Feature",
  "properties": {
    "iso:country":"US",
    "sg:address":"9410 E 51st St",
    "sg:city":"Tulsa",
    "sg:classifiers":[
        {
            "category":"Building & Trades",
            "subcategory":"Construction",
            "type":"Services"
        }
    ],
    "sg:phone":"+1 918 622 4680",
    "sg:postcode":"74145",
    "sg:province":"OK",
    "sg:tags":[
        "general",
        "contractor"
    ],
    "sg:website":"www.premierbranding.com",
    "wof:name":"Premier Construction Svc",
    "wof:placetype":"venue"
},
  "geometry": {"coordinates":[-95.871617,36.089879],"type":"Point"}
}