{
  "type": "Feature",
  "properties": {
    "iso:country":"US",
    "sg:address":"9629 S 92nd West Ave",
    "sg:city":"Sapulpa",
    "sg:classifiers":[
        {
            "category":"Building & Trades",
            "subcategory":"Construction",
            "type":"Services"
        }
    ],
    "sg:phone":"+1 918 224 9477",
    "sg:postcode":"74066",
    "sg:province":"OK",
    "sg:tags":[
        "general",
        "contractor"
    ],
    "wof:name":"Shields Construction",
    "wof:placetype":"venue"
},
  "geometry": {"coordinates":[-96.095406,36.024633],"type":"Point"}
}