{
  "type": "Feature",
  "properties": {
    "iso:country":"US",
    "sg:address":"1321 State Hwy 152",
    "sg:city":"Mustang",
    "sg:classifiers":[
        {
            "category":"Organizations",
            "subcategory":"Religious Organization",
            "type":"Services"
        }
    ],
    "sg:phone":"+1 405 376 1554",
    "sg:postcode":"73064",
    "sg:province":"OK",
    "sg:tags":[
        "church"
    ],
    "wof:name":"United Pentecostal Church",
    "wof:placetype":"venue"
},
  "geometry": {"coordinates":[-97.75093099999999,35.391795],"type":"Point"}
}