{
  "type": "Feature",
  "properties": {
    "addr:full":"519 N Porter Ave Norman OK 73071",
    "addr:housenumber":"519",
    "addr:postcode":"73071",
    "addr:street":"N Porter Ave",
    "iso:country":"US",
    "sg:address":"519 N Porter Ave",
    "sg:city":"Norman",
    "sg:classifiers":[
        {
            "category":"Autos & Motor Vehicles",
            "subcategory":"Automobile Sales",
            "type":"Retail Goods"
        }
    ],
    "sg:phone":"+1 405 364 5620",
    "sg:postcode":"73071",
    "sg:province":"OK",
    "sg:tags":[
        "car",
        "dealer"
    ],
    "wof:name":"Preferred Auto Sales Inc",
    "wof:placetype":"venue"
},
  "geometry": {"coordinates":[-97.44100299999999,35.225988],"type":"Point"}
}