{
  "type": "Feature",
  "properties": {
    "addr:full":"1505 N Florence Pl Claremore OK 74017",
    "addr:housenumber":"1505",
    "addr:postcode":"74017",
    "addr:street":"N Florence Pl",
    "iso:country":"US",
    "sg:address":"1505 N Florence Pl",
    "sg:city":"Claremore",
    "sg:classifiers":[
        {
            "category":"Professional",
            "subcategory":"Business Services",
            "type":"Services"
        }
    ],
    "sg:phone":"+1 918 343 2827",
    "sg:postcode":"74017",
    "sg:province":"OK",
    "wof:name":"Claremorescoop Enterprises LLC",
    "wof:placetype":"venue"
},
  "geometry": {"coordinates":[-95.60315199999999,36.325024],"type":"Point"}
}