{
  "type": "Feature",
  "properties": {
    "iso:country":"US",
    "sg:address":"800 US Hwy 77",
    "sg:city":"Marietta",
    "sg:classifiers":[
        {
            "category":"Social Services",
            "subcategory":"Child Care",
            "type":"Services"
        }
    ],
    "sg:phone":"+1 580 276 2474",
    "sg:postcode":"73448",
    "sg:province":"OK",
    "wof:name":"Marietta Daycare Ctr",
    "wof:placetype":"venue"
},
  "geometry": {"coordinates":[-97.12628599999999,33.947505],"type":"Point"}
}