{
  "type": "Feature",
  "properties": {
    "iso:country":"US",
    "sg:address":"122 N 3rd St",
    "sg:city":"Ponca City",
    "sg:classifiers":[
        {
            "category":"Communications",
            "subcategory":"Radio Station",
            "type":"Services"
        }
    ],
    "sg:phone":"+1 580 762 9930",
    "sg:postcode":"74601",
    "sg:province":"OK",
    "sg:tags":[
        "company",
        "broadcasting"
    ],
    "wof:name":"KLOR-FM",
    "wof:placetype":"venue"
},
  "geometry": {"coordinates":[-97.08126,36.704461],"type":"Point"}
}