{
  "type": "Feature",
  "properties": {
    "addr:full":"5601 NW 72nd St Oklahoma City OK 73132",
    "addr:housenumber":"5601",
    "addr:postcode":"73132",
    "addr:street":"Nw 72Nd St",
    "iso:country":"US",
    "sg:address":"5601 NW 72nd St",
    "sg:city":"Oklahoma City",
    "sg:classifiers":[
        {
            "category":"Education",
            "subcategory":"Vocational School",
            "type":"Public Place"
        }
    ],
    "sg:phone":"+1 405 721 3555",
    "sg:postcode":"73132",
    "sg:province":"OK",
    "sg:tags":[
        "datum",
        "secretarial"
    ],
    "wof:name":"Andrews School",
    "wof:placetype":"venue"
},
  "geometry": {"coordinates":[-97.61313,35.545321],"type":"Point"}
}