{
  "type": "Feature",
  "properties": {
    "iso:country":"US",
    "sg:address":"6333 E Skelly Dr",
    "sg:city":"Tulsa",
    "sg:classifiers":[
        {
            "category":"Social Services",
            "subcategory":"Adult Care",
            "type":"Services"
        }
    ],
    "sg:phone":"+1 918 664 4224",
    "sg:postcode":"74135",
    "sg:province":"OK",
    "sg:tags":[
        "resident",
        "substance",
        "rehabilitation",
        "abuse",
        "center"
    ],
    "sg:website":"www.12and12.org",
    "wof:name":"12 & 12 Inc",
    "wof:placetype":"venue"
},
  "geometry": {"coordinates":[-95.90446,36.108391],"type":"Point"}
}