{
  "type": "Feature",
  "properties": {
    "iso:country":"US",
    "sg:address":"1409 W Shawnee St",
    "sg:city":"Muskogee",
    "sg:classifiers":[
        {
            "category":"Manufacturing",
            "subcategory":"Printing",
            "type":"Manufacturing & Wholesale Goods"
        }
    ],
    "sg:phone":"+1 918 682 8341",
    "sg:postcode":"74401",
    "sg:province":"OK",
    "sg:tags":[
        "printer"
    ],
    "sg:website":"www.hoffmanprinting.com",
    "wof:name":"Hoffman Printing",
    "wof:placetype":"venue"
},
  "geometry": {"coordinates":[-95.378311,35.769564],"type":"Point"}
}