{
  "type": "Feature",
  "properties": {
    "iso:country":"US",
    "sg:address":"120 N 5th St",
    "sg:city":"Muskogee",
    "sg:classifiers":[
        {
            "category":"Organizations",
            "subcategory":"Religious Organization",
            "type":"Services"
        }
    ],
    "sg:phone":"+1 918 682 2662",
    "sg:postcode":"74401",
    "sg:province":"OK",
    "sg:tags":[
        "church"
    ],
    "wof:name":"New Testament Family Worship",
    "wof:placetype":"venue"
},
  "geometry": {"coordinates":[-95.373849,35.750307],"type":"Point"}
}