{
  "type": "Feature",
  "properties": {
    "iso:country":"US",
    "sg:address":"1711 E 15th St",
    "sg:city":"Tulsa",
    "sg:classifiers":[
        {
            "category":"Health Services",
            "subcategory":"Doctor",
            "type":"Services"
        }
    ],
    "sg:phone":"+1 918 742 2237",
    "sg:postcode":"74104",
    "sg:province":"OK",
    "sg:tags":[
        "medical"
    ],
    "wof:name":"Virginia R Heller",
    "wof:placetype":"venue"
},
  "geometry": {"coordinates":[-95.96596700000001,36.140649],"type":"Point"}
}