{
  "type": "Feature",
  "properties": {
    "iso:country":"US",
    "sg:address":"301 6th St",
    "sg:city":"Dewar",
    "sg:classifiers":[
        {
            "category":"Building & Trades",
            "subcategory":"Pest Control",
            "type":"Services"
        }
    ],
    "sg:phone":"+1 918 652 7695",
    "sg:postcode":"74431",
    "sg:province":"OK",
    "wof:name":"Cantrell Pest Control",
    "wof:placetype":"venue"
},
  "geometry": {"coordinates":[-95.944076,35.458163],"type":"Point"}
}