{
  "type": "Feature",
  "properties": {
    "addr:full":"5105 S Lewis Ave Tulsa OK 74105",
    "addr:housenumber":"5105",
    "addr:postcode":"74105",
    "addr:street":"S Lewis Ave",
    "iso:country":"US",
    "sg:address":"5105 S Lewis Ave",
    "sg:city":"Tulsa",
    "sg:classifiers":[
        {
            "category":"Personal",
            "subcategory":"Shoe Repair & Shine",
            "type":"Services"
        }
    ],
    "sg:phone":"+1 918 747 7540",
    "sg:postcode":"74105",
    "sg:province":"OK",
    "sg:tags":[
        "parlor"
    ],
    "wof:name":"Bestway Shoe Hospital",
    "wof:placetype":"venue"
},
  "geometry": {"coordinates":[-95.957903,36.086968],"type":"Point"}
}