{
  "type": "Feature",
  "properties": {
    "addr:full":"113 N Broadway St Coweta OK 74429",
    "addr:housenumber":"113",
    "addr:postcode":"74429",
    "addr:street":"N Broadway St",
    "iso:country":"US",
    "sg:address":"113 N Broadway St",
    "sg:city":"Coweta",
    "sg:classifiers":[
        {
            "category":"Shopping",
            "subcategory":"Pharmacy",
            "type":"Retail Goods"
        }
    ],
    "sg:phone":"+1 918 486 2193",
    "sg:postcode":"74429",
    "sg:province":"OK",
    "wof:name":"City Drug Co",
    "wof:placetype":"venue"
},
  "geometry": {"coordinates":[-95.650599,35.951063],"type":"Point"}
}