{
  "type": "Feature",
  "properties": {
    "iso:country":"US",
    "sg:address":"240 W Wilshire Blvd",
    "sg:city":"Oklahoma City",
    "sg:classifiers":[
        {
            "category":"Government",
            "subcategory":"Office",
            "type":"Public Place"
        }
    ],
    "sg:phone":"+1 405 879 2044",
    "sg:postcode":"73116",
    "sg:province":"OK",
    "sg:tags":[
        "armed",
        "force",
        "recruiting"
    ],
    "wof:name":"Guthrie Job Corps Recruiting",
    "wof:placetype":"venue"
},
  "geometry": {"coordinates":[-97.515891,35.551052],"type":"Point"}
}