{
  "type": "Feature",
  "properties": {
    "iso:country":"US",
    "sg:address":"8513 S Airport Way",
    "sg:city":"Tulsa",
    "sg:classifiers":[
        {
            "category":"Autos & Motor Vehicles",
            "subcategory":"Automobile Sales",
            "type":"Retail Goods"
        }
    ],
    "sg:phone":"+1 918 298 6960",
    "sg:postcode":"74132",
    "sg:province":"OK",
    "sg:tags":[
        "aircraft"
    ],
    "sg:website":"www.tllsales.com",
    "wof:name":"Transportation Locators LTD",
    "wof:placetype":"venue"
},
  "geometry": {"coordinates":[-95.991785,36.03969],"type":"Point"}
}