{
  "type": "Feature",
  "properties": {
    "iso:country":"US",
    "sg:address":"212 N Main St",
    "sg:city":"Blackwell",
    "sg:classifiers":[
        {
            "category":"Personal",
            "subcategory":"Beauty Salon",
            "type":"Services"
        }
    ],
    "sg:phone":"+1 580 363 4437",
    "sg:postcode":"74631",
    "sg:province":"OK",
    "sg:tags":[
        "shop"
    ],
    "wof:name":"Vickie's Hair Affair",
    "wof:placetype":"venue"
},
  "geometry": {"coordinates":[-97.28289599999999,36.806166],"type":"Point"}
}