{
  "type": "Feature",
  "properties": {
    "addr:full":"422 E 4th St Tulsa OK 74120",
    "addr:housenumber":"422",
    "addr:postcode":"74120",
    "addr:street":"E 4Th St",
    "iso:country":"US",
    "sg:address":"422 E 4th St",
    "sg:city":"Tulsa",
    "sg:classifiers":[
        {
            "category":"Retail",
            "subcategory":"Laundry & Dry Cleaning",
            "type":"Services"
        }
    ],
    "sg:phone":"+1 918 341 0610",
    "sg:postcode":"74120",
    "sg:province":"OK",
    "sg:tags":[
        "drycleaning",
        "plant"
    ],
    "wof:name":"Archer Cleaners Inc",
    "wof:placetype":"venue"
},
  "geometry": {"coordinates":[-95.984841,36.154339],"type":"Point"}
}