{
  "type": "Feature",
  "properties": {
    "iso:country":"US",
    "sg:address":"601 NE 2nd St",
    "sg:city":"Oklahoma City",
    "sg:classifiers":[
        {
            "category":"Organizations",
            "subcategory":"Religious Organization",
            "type":"Services"
        }
    ],
    "sg:phone":"+1 405 235 4788",
    "sg:postcode":"73104",
    "sg:province":"OK",
    "sg:tags":[
        "church"
    ],
    "wof:name":"St Timothy Cogic",
    "wof:placetype":"venue"
},
  "geometry": {"coordinates":[-97.501996,35.46957],"type":"Point"}
}