{
  "type": "Feature",
  "properties": {
    "iso:country":"US",
    "sg:address":"1800 N Portland Ave",
    "sg:city":"Oklahoma City",
    "sg:classifiers":[
        {
            "category":"Food & Beverages",
            "subcategory":"Groceries & Convenience Stores",
            "type":"Retail Goods"
        }
    ],
    "sg:phone":"+1 405 947 7474",
    "sg:postcode":"73107",
    "sg:province":"OK",
    "wof:name":"L & S Quick Stop",
    "wof:placetype":"venue"
},
  "geometry": {"coordinates":[-97.583357,35.488085],"type":"Point"}
}