{
  "type": "Feature",
  "properties": {
    "addr:full":"419 E 5th St Tulsa OK 74120",
    "addr:housenumber":"419",
    "addr:postcode":"74120",
    "addr:street":"E 5Th St",
    "iso:country":"US",
    "sg:address":"419 E 5th St",
    "sg:city":"Tulsa",
    "sg:classifiers":[
        {
            "category":"Shopping",
            "type":"Retail Goods"
        }
    ],
    "sg:phone":"+1 918 583 5003",
    "sg:postcode":"74120",
    "sg:province":"OK",
    "sg:tags":[
        "awning",
        "canopy"
    ],
    "wof:name":"City Tent & Awning Co",
    "wof:placetype":"venue"
},
  "geometry": {"coordinates":[-95.984371,36.153539],"type":"Point"}
}