{
  "type": "Feature",
  "properties": {
    "iso:country":"US",
    "sg:address":"8250 E 111th St S",
    "sg:city":"Bixby",
    "sg:classifiers":[
        {
            "category":"Recreation",
            "type":"Entertainment"
        }
    ],
    "sg:phone":"+1 918 369 3938",
    "sg:postcode":"74008",
    "sg:province":"OK",
    "wof:name":"Cheers To You Inc",
    "wof:placetype":"venue"
},
  "geometry": {"coordinates":[-95.885277,36.002751],"type":"Point"}
}