{
  "type": "Feature",
  "properties": {
    "addr:full":"620 N Harvey Ave Oklahoma City OK 73102",
    "addr:housenumber":"620",
    "addr:postcode":"73102",
    "addr:street":"N Harvey Ave",
    "iso:country":"US",
    "sg:address":"620 N Harvey Ave",
    "sg:city":"Oklahoma City",
    "sg:classifiers":[
        {
            "category":"Museum",
            "type":"Entertainment"
        }
    ],
    "sg:phone":"+1 405 235 3313",
    "sg:postcode":"73102",
    "sg:province":"OK",
    "sg:website":"www.oklahomacitynationalmemorial.org",
    "wof:name":"Oklahoma City National Meml",
    "wof:placetype":"venue"
},
  "geometry": {"coordinates":[-97.51769400000001,35.473848],"type":"Point"}
}