{
  "type": "Feature",
  "properties": {
    "iso:country":"US",
    "sg:address":"207 S Broadway St",
    "sg:city":"Checotah",
    "sg:classifiers":[
        {
            "category":"Food & Beverages",
            "subcategory":"Groceries & Convenience Stores",
            "type":"Retail Goods"
        }
    ],
    "sg:phone":"+1 918 473 2369",
    "sg:postcode":"74426",
    "sg:province":"OK",
    "sg:tags":[
        "grocer"
    ],
    "sg:website":"www.glninc.com",
    "wof:name":"GLN Inc",
    "wof:placetype":"venue"
},
  "geometry": {"coordinates":[-95.52341199999999,35.469083],"type":"Point"}
}