{
  "type": "Feature",
  "properties": {
    "addr:full":"2316 N 11th St Enid OK 73701",
    "addr:housenumber":"2316",
    "addr:postcode":"73701",
    "addr:street":"N 11Th St",
    "iso:country":"US",
    "sg:address":"2316 N 11th St",
    "sg:city":"Enid",
    "sg:classifiers":[
        {
            "category":"Wholesale",
            "subcategory":"Machinery & Supplies",
            "type":"Manufacturing & Wholesale Goods"
        }
    ],
    "sg:phone":"+1 580 233 8885",
    "sg:postcode":"73701",
    "sg:province":"OK",
    "sg:tags":[
        "equipment",
        "industrial"
    ],
    "sg:website":"www.mandmsupply.com",
    "wof:name":"M & M Supply Co",
    "wof:placetype":"venue"
},
  "geometry": {"coordinates":[-97.862064,36.419921],"type":"Point"}
}