{
  "type": "Feature",
  "properties": {
    "iso:country":"US",
    "sg:address":"1624 SE 22nd St",
    "sg:city":"Oklahoma City",
    "sg:classifiers":[
        {
            "category":"Mining & Drilling",
            "type":"Manufacturing & Wholesale Goods"
        }
    ],
    "sg:phone":"+1 405 672 7550",
    "sg:postcode":"73129",
    "sg:province":"OK",
    "sg:tags":[
        "field",
        "oil"
    ],
    "wof:name":"Madden Sales & Svc Inc",
    "wof:placetype":"venue"
},
  "geometry": {"coordinates":[-97.482597,35.442512],"type":"Point"}
}