{
  "type": "Feature",
  "properties": {
    "iso:country":"US",
    "sg:address":"5424 S 103rd East Ave",
    "sg:city":"Tulsa",
    "sg:classifiers":[
        {
            "category":"Home & Garden",
            "subcategory":"Building Materials",
            "type":"Retail Goods"
        }
    ],
    "sg:phone":"+1 918 665 6223",
    "sg:postcode":"74146",
    "sg:province":"OK",
    "sg:tags":[
        "siding"
    ],
    "wof:name":"Burton Building Products Inc",
    "wof:placetype":"venue"
},
  "geometry": {"coordinates":[-95.861735,36.084333],"type":"Point"}
}