{
  "type": "Feature",
  "properties": {
    "iso:country":"US",
    "sg:address":"8120 E 63rd Pl",
    "sg:city":"Tulsa",
    "sg:classifiers":[
        {
            "category":"Real Estate",
            "subcategory":"Real Estate Operator",
            "type":"Services"
        }
    ],
    "sg:phone":"+1 918 252 5669",
    "sg:postcode":"74133",
    "sg:province":"OK",
    "sg:tags":[
        "building",
        "apartment"
    ],
    "wof:name":"Coventry Park",
    "wof:placetype":"venue"
},
  "geometry": {"coordinates":[-95.88553400000001,36.071644],"type":"Point"}
}