{
  "type": "Feature",
  "properties": {
    "iso:country":"US",
    "sg:address":"2360 Nowata Pl",
    "sg:city":"Bartlesville",
    "sg:classifiers":[
        {
            "category":"Food & Beverages",
            "subcategory":"Liquor & Beverages",
            "type":"Retail Goods"
        }
    ],
    "sg:phone":"+1 918 335 2922",
    "sg:postcode":"74006",
    "sg:province":"OK",
    "sg:tags":[
        "alcoholic"
    ],
    "wof:name":"2 Dames Liquor Store",
    "wof:placetype":"venue"
},
  "geometry": {"coordinates":[-95.95073,36.729082],"type":"Point"}
}