{
  "type": "Feature",
  "properties": {
    "iso:country":"US",
    "sg:address":"607 SW B Ave",
    "sg:city":"Lawton",
    "sg:classifiers":[
        {
            "category":"Real Estate",
            "subcategory":"Real Estate Agent",
            "type":"Services"
        }
    ],
    "sg:phone":"+1 580 355 1911",
    "sg:postcode":"73501",
    "sg:province":"OK",
    "wof:name":"Kennedy & Co Real Estate",
    "wof:placetype":"venue"
},
  "geometry": {"coordinates":[-98.398314,34.606417],"type":"Point"}
}