{
  "type": "Feature",
  "properties": {
    "addr:full":"7798 E 25th Pl Tulsa OK 74129",
    "addr:housenumber":"7798",
    "addr:postcode":"74129",
    "addr:street":"E 25Th Pl",
    "iso:country":"US",
    "sg:address":"7798 E 25th Pl",
    "sg:city":"Tulsa",
    "sg:classifiers":[
        {
            "category":"Shopping",
            "type":"Retail Goods"
        }
    ],
    "sg:phone":"+1 918 280 1783",
    "sg:postcode":"74129",
    "sg:province":"OK",
    "sg:tags":[
        "candle",
        "merchandise"
    ],
    "wof:name":"Makin' Scents",
    "wof:placetype":"venue"
},
  "geometry": {"coordinates":[-95.887541,36.127017],"type":"Point"}
}