{
  "type": "Feature",
  "properties": {
    "addr:full":"3346 E 51st St Tulsa OK 74135",
    "addr:housenumber":"3346",
    "addr:postcode":"74135",
    "addr:street":"E 51St St",
    "iso:country":"US",
    "sg:address":"3346 E 51st St",
    "sg:city":"Tulsa",
    "sg:classifiers":[
        {
            "category":"Personal",
            "subcategory":"Beauty Salon",
            "type":"Services"
        }
    ],
    "sg:phone":"+1 918 745 9240",
    "sg:postcode":"74135",
    "sg:province":"OK",
    "sg:tags":[
        "shop"
    ],
    "wof:name":"Great Lengths",
    "wof:placetype":"venue"
},
  "geometry": {"coordinates":[-95.935022,36.089719],"type":"Point"}
}