{
  "type": "Feature",
  "properties": {
    "addr:full":"2118 2nd St Woodward OK 73801",
    "addr:housenumber":"2118",
    "addr:postcode":"73801",
    "addr:street":"2Nd St",
    "iso:country":"US",
    "sg:address":"2118 2nd St",
    "sg:city":"Woodward",
    "sg:classifiers":[
        {
            "category":"Social Services",
            "type":"Services"
        }
    ],
    "sg:phone":"+1 580 254 3983",
    "sg:postcode":"73801",
    "sg:province":"OK",
    "sg:tags":[
        "organization",
        "welfare"
    ],
    "wof:name":"Woodward United Fund",
    "wof:placetype":"venue"
},
  "geometry": {"coordinates":[-99.382231,36.425241],"type":"Point"}
}