{
  "type": "Feature",
  "properties": {
    "iso:country":"US",
    "sg:address":"8 B St NW",
    "sg:city":"Ardmore",
    "sg:classifiers":[
        {
            "category":"Banks & Credit Unions",
            "subcategory":"Bank",
            "type":"Services"
        }
    ],
    "sg:phone":"+1 580 226 7740",
    "sg:postcode":"73401",
    "sg:province":"OK",
    "sg:tags":[
        "small",
        "loan",
        "company"
    ],
    "wof:name":"Cash Loan",
    "wof:placetype":"venue"
},
  "geometry": {"coordinates":[-97.12992,34.17429],"type":"Point"}
}