{
  "type": "Feature",
  "properties": {
    "addr:full":"507 E Normal St Cordell OK 73632",
    "addr:housenumber":"507",
    "addr:postcode":"73632",
    "addr:street":"E Normal St",
    "iso:country":"US",
    "sg:address":"507 E Normal St",
    "sg:city":"Cordell",
    "sg:classifiers":[
        {
            "category":"Health Services",
            "subcategory":"Clinic",
            "type":"Services"
        }
    ],
    "sg:phone":"+1 580 832 3807",
    "sg:postcode":"73632",
    "sg:province":"OK",
    "sg:tags":[
        "organization",
        "maintenance"
    ],
    "wof:name":"Bell & Assoc",
    "wof:placetype":"venue"
},
  "geometry": {"coordinates":[-98.984933,35.28521],"type":"Point"}
}