{
  "type": "Feature",
  "properties": {
    "addr:full":"5230 SW 11th St Oklahoma City OK 73128",
    "addr:housenumber":"5230",
    "addr:postcode":"73128",
    "addr:street":"Sw 11Th St",
    "iso:country":"US",
    "sg:address":"5230 SW 11th St",
    "sg:city":"Oklahoma City",
    "sg:classifiers":[
        {
            "category":"Building & Trades",
            "subcategory":"Construction",
            "type":"Services"
        }
    ],
    "sg:phone":"+1 405 942 4685",
    "sg:postcode":"73128",
    "sg:province":"OK",
    "sg:tags":[
        "contractor"
    ],
    "wof:name":"Hutchco Construction Co",
    "wof:placetype":"venue"
},
  "geometry": {"coordinates":[-97.612668,35.454185],"type":"Point"}
}