{
  "type": "Feature",
  "properties": {
    "iso:country":"US",
    "sg:address":"5649 S Mingo Rd",
    "sg:city":"Tulsa",
    "sg:classifiers":[
        {
            "category":"Education",
            "subcategory":"Special Training",
            "type":"Public Place"
        }
    ],
    "sg:phone":"+1 918 461 0881",
    "sg:postcode":"74146",
    "sg:province":"OK",
    "sg:tags":[
        "instruction",
        "driving"
    ],
    "wof:name":"Northeastern Oklahoma Driving",
    "wof:placetype":"venue"
},
  "geometry": {"coordinates":[-95.86850699999999,36.08152],"type":"Point"}
}