{
  "type": "Feature",
  "properties": {
    "addr:full":"307 W Main St Ada OK 74820",
    "addr:housenumber":"307",
    "addr:postcode":"74820",
    "addr:street":"W Main St",
    "iso:country":"US",
    "sg:address":"307 W Main St",
    "sg:city":"Ada",
    "sg:classifiers":[
        {
            "category":"Building & Trades",
            "subcategory":"Construction",
            "type":"Services"
        }
    ],
    "sg:phone":"+1 580 436 5450",
    "sg:postcode":"74820",
    "sg:province":"OK",
    "sg:tags":[
        "remodeling",
        "general"
    ],
    "wof:name":"Good-One Construction LLC",
    "wof:placetype":"venue"
},
  "geometry": {"coordinates":[-96.683348,34.774409],"type":"Point"}
}