{
  "type": "Feature",
  "properties": {
    "addr:full":"3115 NW 63rd St Oklahoma City OK 73116",
    "addr:housenumber":"3115",
    "addr:postcode":"73116",
    "addr:street":"Nw 63Rd St",
    "iso:country":"US",
    "sg:address":"3115 NW 63rd St",
    "sg:city":"Oklahoma City",
    "sg:classifiers":[
        {
            "category":"Organizations",
            "subcategory":"Community Association",
            "type":"Services"
        }
    ],
    "sg:phone":"+1 405 848 3029",
    "sg:postcode":"73116",
    "sg:province":"OK",
    "sg:tags":[
        "civic",
        "social"
    ],
    "wof:name":"Jamestown First Association",
    "wof:placetype":"venue"
},
  "geometry": {"coordinates":[-97.574471,35.536746],"type":"Point"}
}