{
  "type": "Feature",
  "properties": {
    "iso:country":"US",
    "sg:address":"312 S 10th St",
    "sg:city":"Okemah",
    "sg:classifiers":[
        {
            "category":"Personal",
            "subcategory":"Beauty Salon",
            "type":"Services"
        }
    ],
    "sg:phone":"+1 918 623 0762",
    "sg:postcode":"74859",
    "sg:province":"OK",
    "wof:name":"Classique Cuts",
    "wof:placetype":"venue"
},
  "geometry": {"coordinates":[-96.312375,35.428936],"type":"Point"}
}