{
  "type": "Feature",
  "properties": {
    "iso:country":"US",
    "sg:address":"3600 Sunvalley Dr",
    "sg:city":"Norman",
    "sg:phone":"+1 405 579 0200",
    "sg:postcode":"73026",
    "sg:province":"OK",
    "sg:tags":[
        "equipment",
        "commercial"
    ],
    "wof:name":"Universal Mill Work LLC",
    "wof:placetype":"venue"
},
  "geometry": {"coordinates":[-97.38758900000001,35.241234],"type":"Point"}
}