{
  "type": "Feature",
  "properties": {
    "iso:country":"US",
    "sg:address":"1011 W Main St",
    "sg:city":"Durant",
    "sg:classifiers":[
        {
            "category":"Building & Trades",
            "subcategory":"Equipment Rental",
            "type":"Services"
        }
    ],
    "sg:phone":"+1 580 920 0288",
    "sg:postcode":"74701",
    "sg:province":"OK",
    "sg:tags":[
        "home",
        "electronics",
        "appliance",
        "furniture"
    ],
    "wof:name":"Rent-Way",
    "wof:placetype":"venue"
},
  "geometry": {"coordinates":[-96.387822,33.99356],"type":"Point"}
}