{
  "type": "Feature",
  "properties": {
    "iso:country":"US",
    "sg:address":"1303 E Danforth Rd",
    "sg:city":"Edmond",
    "sg:classifiers":[
        {
            "category":"Shopping",
            "subcategory":"Jewelry",
            "type":"Retail Goods"
        }
    ],
    "sg:phone":"+1 405 340 9612",
    "sg:postcode":"73034",
    "sg:province":"OK",
    "wof:name":"Jewels By Gerjeans",
    "wof:placetype":"venue"
},
  "geometry": {"coordinates":[-97.461814,35.667271],"type":"Point"}
}