{
  "type": "Feature",
  "properties": {
    "iso:country":"US",
    "sg:address":"1206 N 7th St",
    "sg:city":"Tonkawa",
    "sg:classifiers":[
        {
            "category":"Manufacturing",
            "subcategory":"Electronics",
            "type":"Manufacturing & Wholesale Goods"
        }
    ],
    "sg:phone":"+1 580 628 3650",
    "sg:postcode":"74653",
    "sg:province":"OK",
    "sg:tags":[
        "measuring",
        "mfg",
        "component",
        "electrical",
        "inst",
        "electronic"
    ],
    "wof:name":"Fault Finders",
    "wof:placetype":"venue"
},
  "geometry": {"coordinates":[-97.308253,36.691447],"type":"Point"}
}