{
  "type": "Feature",
  "properties": {
    "iso:country":"US",
    "sg:address":"1526 W 8th Ave",
    "sg:city":"Stillwater",
    "sg:classifiers":[
        {
            "category":"Health Services",
            "subcategory":"Doctor",
            "type":"Services"
        }
    ],
    "sg:phone":"+1 405 372 1575",
    "sg:postcode":"74074",
    "sg:province":"OK",
    "sg:tags":[
        "dentist"
    ],
    "wof:name":"Alan T Plaxico DDS",
    "wof:placetype":"venue"
},
  "geometry": {"coordinates":[-97.07706,36.113495],"type":"Point"}
}