{
  "type": "Feature",
  "properties": {
    "addr:full":"6334 NW 39th Expy Bethany OK 73008",
    "addr:housenumber":"6334",
    "addr:postcode":"73008",
    "addr:street":"Nw 39Th Expy",
    "iso:country":"US",
    "sg:address":"6334 NW 39th Expy",
    "sg:city":"Bethany",
    "sg:classifiers":[
        {
            "category":"Autos & Motor Vehicles",
            "subcategory":"Auto Supplies",
            "type":"Retail Goods"
        }
    ],
    "sg:phone":"+1 405 789 1510",
    "sg:postcode":"73008",
    "sg:province":"OK",
    "wof:name":"All Season Tires",
    "wof:placetype":"venue"
},
  "geometry": {"coordinates":[-97.626074,35.51107],"type":"Point"}
}