{
  "type": "Feature",
  "properties": {
    "addr:full":"23373 State Hwy 39 Purcell OK 73080",
    "addr:housenumber":"23373",
    "addr:postcode":"73080",
    "addr:street":"State Hwy 39",
    "iso:country":"US",
    "sg:address":"23373 State Hwy 39",
    "sg:city":"Purcell",
    "sg:classifiers":[
        {
            "category":"Travel",
            "subcategory":"Campground",
            "type":"Entertainment"
        }
    ],
    "sg:phone":"+1 405 527 3922",
    "sg:postcode":"73080",
    "sg:province":"OK",
    "sg:tags":[
        "farm",
        "camp",
        "equine"
    ],
    "wof:name":"Todd Arvidson Quarter Horses",
    "wof:placetype":"venue"
},
  "geometry": {"coordinates":[-97.432935,35.000802],"type":"Point"}
}