{
  "type": "Feature",
  "properties": {
    "iso:country":"US",
    "sg:address":"3610 SE Huntington Cir",
    "sg:city":"Lawton",
    "sg:classifiers":[
        {
            "category":"Real Estate",
            "subcategory":"Real Estate Operator",
            "type":"Services"
        }
    ],
    "sg:phone":"+1 580 353 1190",
    "sg:postcode":"73505",
    "sg:province":"OK",
    "sg:tags":[
        "retirement",
        "community"
    ],
    "wof:name":"Ten Oaks Merill Gardens LLC",
    "wof:placetype":"venue"
},
  "geometry": {"coordinates":[-98.34505900000001,34.597197],"type":"Point"}
}