{
  "type": "Feature",
  "properties": {
    "addr:full":"4361 NW 50th St Oklahoma City OK 73112",
    "addr:housenumber":"4361",
    "addr:postcode":"73112",
    "addr:street":"Nw 50Th St",
    "iso:country":"US",
    "sg:address":"4361 NW 50th St",
    "sg:city":"Oklahoma City",
    "sg:classifiers":[
        {
            "category":"Professional",
            "subcategory":"Computer Services",
            "type":"Services"
        }
    ],
    "sg:phone":"+1 405 488 0742",
    "sg:postcode":"73112",
    "sg:province":"OK",
    "sg:tags":[
        "internet"
    ],
    "wof:name":"Telephone Internet Svc",
    "wof:placetype":"venue"
},
  "geometry": {"coordinates":[-97.599932,35.522399],"type":"Point"}
}