{
  "type": "Feature",
  "properties": {
    "iso:country":"US",
    "sg:address":"905 N Sooner Rd",
    "sg:city":"Edmond",
    "sg:classifiers":[
        {
            "category":"Real Estate",
            "subcategory":"Real Estate Operator",
            "type":"Services"
        }
    ],
    "sg:phone":"+1 405 341 1843",
    "sg:postcode":"73034",
    "sg:province":"OK",
    "sg:tags":[
        "mobile",
        "home",
        "community"
    ],
    "wof:name":"Waterloo Woods Mobile Home Pk",
    "wof:placetype":"venue"
},
  "geometry": {"coordinates":[-97.425061,35.664414],"type":"Point"}
}