{
  "type": "Feature",
  "properties": {
    "iso:country":"US",
    "sg:address":"7105 NW 39th Expy",
    "sg:city":"Bethany",
    "sg:classifiers":[
        {
            "category":"Autos & Motor Vehicles",
            "subcategory":"Automobile Sales",
            "type":"Retail Goods"
        }
    ],
    "sg:phone":"+1 405 495 3535",
    "sg:postcode":"73008",
    "sg:province":"OK",
    "sg:tags":[
        "car",
        "dealer"
    ],
    "wof:name":"National Motors Sales & Leasin",
    "wof:placetype":"venue"
},
  "geometry": {"coordinates":[-97.637656,35.513323],"type":"Point"}
}