{
  "type": "Feature",
  "properties": {
    "addr:full":"3405 S Wofford Rd Oklahoma City OK 73115",
    "addr:housenumber":"3405",
    "addr:postcode":"73115",
    "addr:street":"S Wofford Rd",
    "iso:country":"US",
    "sg:address":"3405 S Wofford Rd",
    "sg:city":"Oklahoma City",
    "sg:classifiers":[
        {
            "category":"Organizations",
            "subcategory":"Religious Organization",
            "type":"Services"
        }
    ],
    "sg:phone":"+1 405 672 8833",
    "sg:postcode":"73115",
    "sg:province":"OK",
    "sg:tags":[
        "catholic",
        "church"
    ],
    "wof:name":"Korean Catholic Community",
    "wof:placetype":"venue"
},
  "geometry": {"coordinates":[-97.439187,35.429859],"type":"Point"}
}