{
  "type": "Feature",
  "properties": {
    "addr:full":"600 W 9th St Ada OK 74820",
    "addr:housenumber":"600",
    "addr:postcode":"74820",
    "addr:street":"W 9Th St",
    "iso:country":"US",
    "sg:address":"600 W 9th St",
    "sg:city":"Ada",
    "sg:classifiers":[
        {
            "category":"Organizations",
            "subcategory":"Religious Organization",
            "type":"Services"
        }
    ],
    "sg:phone":"+1 580 436 2444",
    "sg:postcode":"74820",
    "sg:province":"OK",
    "sg:tags":[
        "church"
    ],
    "wof:name":"Christian Cornerstone Church",
    "wof:placetype":"venue"
},
  "geometry": {"coordinates":[-96.68665,34.776609],"type":"Point"}
}