{
  "type": "Feature",
  "properties": {
    "iso:country":"US",
    "sg:address":"218 W Main St",
    "sg:city":"Glencoe",
    "sg:classifiers":[
        {
            "category":"Shopping",
            "subcategory":"Computers & Home Electronics",
            "type":"Retail Goods"
        }
    ],
    "sg:phone":"+1 580 669 2439",
    "sg:postcode":"74032",
    "sg:province":"OK",
    "sg:tags":[
        "game",
        "video"
    ],
    "wof:name":"Game Busters",
    "wof:placetype":"venue"
},
  "geometry": {"coordinates":[-96.928175,36.227661],"type":"Point"}
}