{
  "type": "Feature",
  "properties": {
    "addr:full":"1005 N Country Club Rd Ada OK 74820",
    "addr:housenumber":"1005",
    "addr:postcode":"74820",
    "addr:street":"N Country Club Rd",
    "iso:country":"US",
    "sg:address":"1005 N Country Club Rd",
    "sg:city":"Ada",
    "sg:classifiers":[
        {
            "category":"Government",
            "subcategory":"Office",
            "type":"Public Place"
        }
    ],
    "sg:phone":"+1 580 436 5000",
    "sg:postcode":"74820",
    "sg:province":"OK",
    "sg:tags":[
        "federal",
        "program"
    ],
    "wof:name":"US Health & Human Svc Dept",
    "wof:placetype":"venue"
},
  "geometry": {"coordinates":[-96.652422,34.786278],"type":"Point"}
}