{
  "type": "Feature",
  "properties": {
    "iso:country":"US",
    "sg:address":"2842 NW 63rd St",
    "sg:city":"Oklahoma City",
    "sg:classifiers":[
        {
            "category":"Restaurant",
            "type":"Food & Drink"
        }
    ],
    "sg:menulink":"http://www.allmenus.com/ok/oklahoma-city/95733-furrs-buffet/menu/",
    "sg:phone":"+1 405 848 5656",
    "sg:postcode":"73116",
    "sg:province":"OK",
    "sg:tags":[
        "american"
    ],
    "wof:name":"Furrs Buffet",
    "wof:placetype":"venue"
},
  "geometry": {"coordinates":[-97.564217,35.5364],"type":"Point"}
}