{
  "type": "Feature",
  "properties": {
    "addr:full":"4500 S Western Ave Oklahoma City OK 73109",
    "addr:housenumber":"4500",
    "addr:postcode":"73109",
    "addr:street":"S Western Ave",
    "iso:country":"US",
    "sg:address":"4500 S Western Ave",
    "sg:city":"Oklahoma City",
    "sg:classifiers":[
        {
            "category":"Restaurant",
            "type":"Food & Drink"
        }
    ],
    "sg:menulink":"http://www.allmenus.com/ok/oklahoma-city/164423-wendys/menu/",
    "sg:phone":"+1 405 632 9671",
    "sg:postcode":"73109",
    "sg:province":"OK",
    "sg:tags":[
        "burger",
        "american",
        "soup"
    ],
    "wof:name":"Wendy's",
    "wof:placetype":"venue"
},
  "geometry": {"coordinates":[-97.52977,35.420437],"type":"Point"}
}