{
  "type": "Feature",
  "properties": {
    "addr:full":"113 S Perkins Rd Stillwater OK 74074",
    "addr:housenumber":"113",
    "addr:postcode":"74074",
    "addr:street":"S Perkins Rd",
    "iso:country":"US",
    "sg:address":"113 S Perkins Rd",
    "sg:city":"Stillwater",
    "sg:classifiers":[
        {
            "category":"Personal",
            "type":"Services"
        }
    ],
    "sg:phone":"+1 405 377 7990",
    "sg:postcode":"74074",
    "sg:province":"OK",
    "sg:tags":[
        "gift"
    ],
    "wof:name":"Costumes Balloons & Stuff",
    "wof:placetype":"venue"
},
  "geometry": {"coordinates":[-97.051378,36.123139],"type":"Point"}
}