{
  "type": "Feature",
  "properties": {
    "iso:country":"US",
    "sg:address":"110 E 8th St",
    "sg:city":"Okmulgee",
    "sg:classifiers":[
        {
            "category":"Professional",
            "subcategory":"Business Services",
            "type":"Services"
        }
    ],
    "sg:phone":"+1 918 758 0644",
    "sg:postcode":"74447",
    "sg:province":"OK",
    "wof:name":"Butler Bail Bonds",
    "wof:placetype":"venue"
},
  "geometry": {"coordinates":[-95.971676,35.621329],"type":"Point"}
}