{
  "type": "Feature",
  "properties": {
    "iso:country":"US",
    "sg:address":"801 N 15th St",
    "sg:city":"Broken Arrow",
    "sg:classifiers":[
        {
            "category":"Wholesale",
            "subcategory":"Electrical",
            "type":"Manufacturing & Wholesale Goods"
        }
    ],
    "sg:phone":"+1 918 251 0925",
    "sg:postcode":"74012",
    "sg:province":"OK",
    "sg:tags":[
        "communication",
        "radio",
        "system"
    ],
    "wof:name":"Commercial Electronics",
    "wof:placetype":"venue"
},
  "geometry": {"coordinates":[-95.770537,36.059052],"type":"Point"}
}