{
  "type": "Feature",
  "properties": {
    "addr:full":"3181 S 129th E Ave Tulsa OK 74134",
    "addr:housenumber":"3181",
    "addr:postcode":"74134",
    "addr:street":"S 129Th E Ave",
    "iso:country":"US",
    "sg:address":"3181 S 129th E Ave",
    "sg:city":"Tulsa",
    "sg:classifiers":[
        {
            "category":"Personal",
            "type":"Services"
        }
    ],
    "sg:phone":"+1 918 627 8811",
    "sg:postcode":"74134",
    "sg:province":"OK",
    "sg:tags":[
        "home"
    ],
    "sg:website":"www.briarglenstorage.com",
    "wof:name":"Briarglen Mini Storage",
    "wof:placetype":"venue"
},
  "geometry": {"coordinates":[-95.83320999999999,36.117924],"type":"Point"}
}