{
  "type": "Feature",
  "properties": {
    "iso:country":"US",
    "sg:address":"2617 W 6th Ave",
    "sg:city":"Stillwater",
    "sg:classifiers":[
        {
            "category":"Restaurant",
            "type":"Food & Drink"
        }
    ],
    "sg:phone":"+1 405 385 0800",
    "sg:postcode":"74074",
    "sg:province":"OK",
    "wof:name":"Oriental Garden Inc",
    "wof:placetype":"venue"
},
  "geometry": {"coordinates":[-97.093028,36.11573],"type":"Point"}
}