{
  "type": "Feature",
  "properties": {
    "iso:country":"US",
    "sg:address":"50501 E 240 Rd",
    "sg:city":"Afton",
    "sg:classifiers":[
        {
            "category":"Farming",
            "subcategory":"Farm",
            "type":"Manufacturing & Wholesale Goods"
        }
    ],
    "sg:phone":"+1 918 257 5534",
    "sg:postcode":"74331",
    "sg:province":"OK",
    "wof:name":"Johnson Brothers Farms",
    "wof:placetype":"venue"
},
  "geometry": {"coordinates":[-94.97321,36.670612],"type":"Point"}
}