{
  "type": "Feature",
  "properties": {
    "iso:country":"US",
    "sg:address":"3808 Michigan St",
    "sg:city":"Bartlesville",
    "sg:classifiers":[
        {
            "category":"Professional",
            "type":"Services"
        }
    ],
    "sg:phone":"+1 918 333 3100",
    "sg:postcode":"74006",
    "sg:province":"OK",
    "sg:tags":[
        "establishment"
    ],
    "wof:name":"Chaos Command Post",
    "wof:placetype":"venue"
},
  "geometry": {"coordinates":[-95.935389,36.7589],"type":"Point"}
}