{
  "type": "Feature",
  "properties": {
    "addr:full":"1110 E McElroy Rd Stillwater OK 74075",
    "addr:housenumber":"1110",
    "addr:postcode":"74075",
    "addr:street":"E Mcelroy Rd",
    "iso:country":"US",
    "sg:address":"1110 E McElroy Rd",
    "sg:city":"Stillwater",
    "sg:classifiers":[
        {
            "category":"Organizations",
            "subcategory":"Religious Organization",
            "type":"Services"
        }
    ],
    "sg:phone":"+1 405 533 4343",
    "sg:postcode":"74075",
    "sg:province":"OK",
    "sg:tags":[
        "church"
    ],
    "sg:website":"www.ifgfok.org",
    "wof:name":"Indonesian Full Gospel Fllwshp",
    "wof:placetype":"venue"
},
  "geometry": {"coordinates":[-97.044668,36.13057],"type":"Point"}
}