{
  "type": "Feature",
  "properties": {
    "iso:country":"US",
    "sg:address":"4336 NW 23rd St",
    "sg:city":"Oklahoma City",
    "sg:classifiers":[
        {
            "category":"Health Services",
            "subcategory":"Doctor",
            "type":"Services"
        }
    ],
    "sg:phone":"+1 405 943 0377",
    "sg:postcode":"73107",
    "sg:province":"OK",
    "sg:tags":[
        "dentist"
    ],
    "wof:name":"Lori Anderson DDS",
    "wof:placetype":"venue"
},
  "geometry": {"coordinates":[-97.599259,35.493236],"type":"Point"}
}