{
  "type": "Feature",
  "properties": {
    "iso:country":"US",
    "sg:address":"13419 N Pennsylvania Ave",
    "sg:city":"Oklahoma City",
    "sg:classifiers":[
        {
            "category":"Personal",
            "type":"Services"
        }
    ],
    "sg:phone":"+1 405 748 4300",
    "sg:postcode":"73120",
    "sg:province":"OK",
    "sg:tags":[
        "wear",
        "formal"
    ],
    "wof:name":"Al's Formal Wear",
    "wof:placetype":"venue"
},
  "geometry": {"coordinates":[-97.549558,35.609061],"type":"Point"}
}