{
  "type": "Feature",
  "properties": {
    "addr:full":"4853 S Sheridan Rd Tulsa OK 74145",
    "addr:housenumber":"4853",
    "addr:postcode":"74145",
    "addr:street":"S Sheridan Rd",
    "iso:country":"US",
    "sg:address":"4853 S Sheridan Rd",
    "sg:city":"Tulsa",
    "sg:classifiers":[
        {
            "category":"Banks & Credit Unions",
            "subcategory":"Bank",
            "type":"Services"
        }
    ],
    "sg:phone":"+1 918 743 1914",
    "sg:postcode":"74145",
    "sg:province":"OK",
    "sg:tags":[
        "mortgage",
        "loan",
        "broker",
        "real estate"
    ],
    "wof:name":"Frabur Mortgage Group LLC",
    "wof:placetype":"venue"
},
  "geometry": {"coordinates":[-95.904319,36.091767],"type":"Point"}
}