{
  "type": "Feature",
  "properties": {
    "iso:country":"US",
    "sg:address":"2702 N Sheridan Rd",
    "sg:city":"Tulsa",
    "sg:classifiers":[
        {
            "category":"Autos & Motor Vehicles",
            "subcategory":"Automobile Sales",
            "type":"Retail Goods"
        }
    ],
    "sg:phone":"+1 918 835 3660",
    "sg:postcode":"74115",
    "sg:province":"OK",
    "sg:tags":[
        "equipment",
        "aircraft",
        "parts",
        "supply"
    ],
    "sg:website":"www.aircrafthose.com",
    "wof:name":"Precision Hose Technology",
    "wof:placetype":"venue"
},
  "geometry": {"coordinates":[-95.904647,36.196612],"type":"Point"}
}