{
  "type": "Feature",
  "properties": {
    "iso:country":"US",
    "sg:address":"1619 S 108th East Ave",
    "sg:city":"Tulsa",
    "sg:classifiers":[
        {
            "category":"Professional",
            "subcategory":"Management & Consulting",
            "type":"Services"
        }
    ],
    "sg:phone":"+1 918 438 6555",
    "sg:postcode":"74128",
    "sg:province":"OK",
    "sg:tags":[
        "marketing",
        "consultant"
    ],
    "wof:name":"Commercial Waffle Program",
    "wof:placetype":"venue"
},
  "geometry": {"coordinates":[-95.856473,36.138019],"type":"Point"}
}