{
  "type": "Feature",
  "properties": {
    "iso:country":"US",
    "sg:address":"6702 US Hwy 62",
    "sg:city":"Lawton",
    "sg:classifiers":[
        {
            "category":"Banks & Credit Unions",
            "subcategory":"Bank",
            "type":"Services"
        }
    ],
    "sg:phone":"+1 580 536 3591",
    "sg:postcode":"73505",
    "sg:province":"OK",
    "sg:website":"www.gsbbank.com",
    "wof:name":"Guarantee State Bank-Lawton",
    "wof:placetype":"venue"
},
  "geometry": {"coordinates":[-98.477316,34.630829],"type":"Point"}
}