{
  "type": "Feature",
  "properties": {
    "iso:country":"US",
    "sg:address":"303 Dewey Ave",
    "sg:city":"Poteau",
    "sg:classifiers":[
        {
            "category":"Government",
            "subcategory":"Office",
            "type":"Public Place"
        }
    ],
    "sg:phone":"+1 918 647 8231",
    "sg:postcode":"74953",
    "sg:province":"OK",
    "wof:name":"Le Flore County Agricultural",
    "wof:placetype":"venue"
},
  "geometry": {"coordinates":[-94.620769,35.051565],"type":"Point"}
}