{
  "type": "Feature",
  "properties": {
    "addr:full":"1519 S Baltimore Ave Tulsa OK 74119",
    "addr:housenumber":"1519",
    "addr:postcode":"74119",
    "addr:street":"S Baltimore Ave",
    "iso:country":"US",
    "sg:address":"1519 S Baltimore Ave",
    "sg:city":"Tulsa",
    "sg:classifiers":[
        {
            "category":"Mining & Drilling",
            "type":"Manufacturing & Wholesale Goods"
        }
    ],
    "sg:phone":"+1 918 587 2497",
    "sg:postcode":"74119",
    "sg:province":"OK",
    "sg:tags":[
        "development",
        "gas",
        "oil",
        "exploration"
    ],
    "wof:name":"Lyons & Lyons",
    "wof:placetype":"venue"
},
  "geometry": {"coordinates":[-95.98616699999999,36.139891],"type":"Point"}
}