{
  "type": "Feature",
  "properties": {
    "iso:country":"US",
    "sg:address":"502 W A St",
    "sg:city":"Jenks",
    "sg:classifiers":[
        {
            "category":"Personal",
            "type":"Services"
        }
    ],
    "sg:phone":"+1 918 299 2120",
    "sg:postcode":"74037",
    "sg:province":"OK",
    "sg:tags":[
        "department",
        "motor",
        "vehicle"
    ],
    "wof:name":"Jenks Tag",
    "wof:placetype":"venue"
},
  "geometry": {"coordinates":[-95.974414,36.023556],"type":"Point"}
}