{
  "type": "Feature",
  "properties": {
    "iso:country":"US",
    "sg:address":"3801 N Lincoln Blvd",
    "sg:city":"Oklahoma City",
    "sg:classifiers":[
        {
            "category":"Restaurant",
            "type":"Food & Drink"
        }
    ],
    "sg:phone":"+1 405 521 9824",
    "sg:postcode":"73105",
    "sg:province":"OK",
    "wof:name":"Arby's",
    "wof:placetype":"venue"
},
  "geometry": {"coordinates":[-97.50313800000001,35.509601],"type":"Point"}
}