{
  "type": "Feature",
  "properties": {
    "iso:country":"US",
    "sg:address":"901 SE Washington St",
    "sg:city":"Idabel",
    "sg:classifiers":[
        {
            "category":"Shopping",
            "subcategory":"Clothing, Apparel, & Fashions",
            "type":"Retail Goods"
        }
    ],
    "sg:phone":"+1 580 286 7442",
    "sg:postcode":"74745",
    "sg:province":"OK",
    "sg:tags":[
        "family"
    ],
    "sg:website":"www.catofashions.com",
    "wof:name":"Cato",
    "wof:placetype":"venue"
},
  "geometry": {"coordinates":[-94.81778799999999,33.89555],"type":"Point"}
}