{
  "type": "Feature",
  "properties": {
    "iso:country":"US",
    "sg:address":"317 W Kenosha St",
    "sg:city":"Broken Arrow",
    "sg:classifiers":[
        {
            "category":"Autos & Motor Vehicles",
            "subcategory":"Automobile Sales",
            "type":"Retail Goods"
        }
    ],
    "sg:phone":"+1 918 258 4545",
    "sg:postcode":"74012",
    "sg:province":"OK",
    "sg:tags":[
        "car",
        "dealer"
    ],
    "wof:name":"Beason Motor Sports",
    "wof:placetype":"venue"
},
  "geometry": {"coordinates":[-95.793521,36.06106],"type":"Point"}
}