{
  "type": "Feature",
  "properties": {
    "iso:country":"US",
    "sg:address":"221 S Perkins Rd",
    "sg:city":"Stillwater",
    "sg:classifiers":[
        {
            "category":"Shopping",
            "subcategory":"Books",
            "type":"Retail Goods"
        }
    ],
    "sg:phone":"+1 405 743 9100",
    "sg:postcode":"74074",
    "sg:province":"OK",
    "wof:name":"Legendary Comics",
    "wof:placetype":"venue"
},
  "geometry": {"coordinates":[-97.051351,36.121585],"type":"Point"}
}