{
  "type": "Feature",
  "properties": {
    "iso:country":"US",
    "sg:address":"1716 S Phoenix Ave",
    "sg:city":"Tulsa",
    "sg:classifiers":[
        {
            "category":"Real Estate",
            "subcategory":"Architect",
            "type":"Services"
        }
    ],
    "sg:phone":"+1 918 587 3274",
    "sg:postcode":"74107",
    "sg:province":"OK",
    "sg:tags":[
        "architectural"
    ],
    "wof:name":"JKL Architecture",
    "wof:placetype":"venue"
},
  "geometry": {"coordinates":[-96.00587,36.137036],"type":"Point"}
}