{
  "type": "Feature",
  "properties": {
    "iso:country":"US",
    "sg:address":"510 N Main St",
    "sg:city":"Altus",
    "sg:classifiers":[
        {
            "category":"Shopping",
            "subcategory":"Computers & Home Electronics",
            "type":"Retail Goods"
        }
    ],
    "sg:phone":"+1 580 480 1422",
    "sg:postcode":"73521",
    "sg:province":"OK",
    "wof:name":"A Plus Computer Guy",
    "wof:placetype":"venue"
},
  "geometry": {"coordinates":[-99.333832,34.643199],"type":"Point"}
}