{
  "type": "Feature",
  "properties": {
    "addr:full":"800 Brett Dr Edmond OK 73013",
    "addr:housenumber":"800",
    "addr:postcode":"73013",
    "addr:street":"Brett Dr",
    "iso:country":"US",
    "sg:address":"800 Brett Dr",
    "sg:city":"Edmond",
    "sg:classifiers":[
        {
            "category":"Professional",
            "type":"Services"
        }
    ],
    "sg:phone":"+1 405 844 8755",
    "sg:postcode":"73013",
    "sg:province":"OK",
    "wof:name":"Fletchers Foundation",
    "wof:placetype":"venue"
},
  "geometry": {"coordinates":[-97.46692299999999,35.632137],"type":"Point"}
}