{
  "type": "Feature",
  "properties": {
    "iso:country":"US",
    "sg:address":"3320 S Frisco Rd",
    "sg:city":"Yukon",
    "sg:classifiers":[
        {
            "category":"Wholesale",
            "subcategory":"Machinery & Supplies",
            "type":"Manufacturing & Wholesale Goods"
        }
    ],
    "sg:phone":"+1 405 577 2656",
    "sg:postcode":"73099",
    "sg:province":"OK",
    "sg:tags":[
        "equipment",
        "irrigation",
        "system"
    ],
    "wof:name":"Midwest Irrigation Inc",
    "wof:placetype":"venue"
},
  "geometry": {"coordinates":[-97.777551,35.438234],"type":"Point"}
}