{
  "type": "Feature",
  "properties": {
    "iso:country":"US",
    "sg:address":"1005 S Lewis Ave",
    "sg:city":"Tulsa",
    "sg:classifiers":[
        {
            "category":"Manufacturing",
            "subcategory":"Food",
            "type":"Manufacturing & Wholesale Goods"
        },
        {
            "category":"Food & Beverages",
            "subcategory":"Groceries & Convenience Stores",
            "type":"Retail Goods"
        },
        {
            "category":"Food & Beverages",
            "subcategory":"Supermarket",
            "type":"Retail Goods"
        },
        {
            "category":"Food & Beverages",
            "subcategory":"Meat & Fish",
            "type":"Retail Goods"
        }
    ],
    "sg:phone":"+1 918 583 2000",
    "sg:postcode":"74104",
    "sg:province":"OK",
    "sg:tags":[
        "product",
        "super",
        "market"
    ],
    "wof:name":"Perry Food Store Meat Dept",
    "wof:placetype":"venue"
},
  "geometry": {"coordinates":[-95.9582,36.14873],"type":"Point"}
}