{
  "type": "Feature",
  "properties": {
    "addr:full":"115 W Stonewall Ave Mcalester OK 74501",
    "addr:housenumber":"115",
    "addr:postcode":"74501",
    "addr:street":"W Stonewall Ave",
    "iso:country":"US",
    "sg:address":"115 W Stonewall Ave",
    "sg:city":"Mcalester",
    "sg:classifiers":[
        {
            "category":"Building & Trades",
            "subcategory":"Plumbing",
            "type":"Services"
        }
    ],
    "sg:phone":"+1 918 423 4113",
    "sg:postcode":"74501",
    "sg:province":"OK",
    "sg:tags":[
        "plumbing",
        "contractor"
    ],
    "wof:name":"AAA Plumbing & Heating",
    "wof:placetype":"venue"
},
  "geometry": {"coordinates":[-95.766955,34.954746],"type":"Point"}
}