{
  "type": "Feature",
  "properties": {
    "iso:country":"US",
    "sg:address":"1876 N 105th East Ave",
    "sg:city":"Tulsa",
    "sg:classifiers":[
        {
            "category":"Wholesale",
            "subcategory":"Machinery & Supplies",
            "type":"Manufacturing & Wholesale Goods"
        }
    ],
    "sg:phone":"+1 918 836 8851",
    "sg:postcode":"74116",
    "sg:province":"OK",
    "sg:tags":[
        "equipment",
        "contractor"
    ],
    "sg:website":"www.vankeppel.com",
    "wof:name":"Van Keppel Lift Truck",
    "wof:placetype":"venue"
},
  "geometry": {"coordinates":[-95.860008,36.180686],"type":"Point"}
}