{
  "type": "Feature",
  "properties": {
    "addr:full":"1876 N 105th East Ave Tulsa OK 74116",
    "addr:housenumber":"1876",
    "addr:postcode":"74116",
    "addr:street":"N 105Th;Ave",
    "iso:country":"US",
    "sg:address":"1876 N 105th East Ave",
    "sg:city":"Tulsa",
    "sg:classifiers":[
        {
            "category":"Wholesale",
            "subcategory":"Machinery & Supplies",
            "type":"Manufacturing & Wholesale Goods"
        }
    ],
    "sg:phone":"+1 918 836 8851",
    "sg:postcode":"74116",
    "sg:province":"OK",
    "sg:tags":[
        "equipment",
        "contractor"
    ],
    "sg:website":"www.vankeppel.com",
    "wof:name":"Van Keppel Lift Truck",
    "wof:placetype":"venue"
},
  "geometry": {"coordinates":[-95.86000799999999,36.180686],"type":"Point"}
}