{
  "type": "Feature",
  "properties": {
    "iso:country":"US",
    "sg:address":"300 SW 7th St",
    "sg:city":"Oklahoma City",
    "sg:classifiers":[
        {
            "category":"Government",
            "subcategory":"Office",
            "type":"Public Place"
        }
    ],
    "sg:phone":"+1 405 297 3571",
    "sg:postcode":"73109",
    "sg:province":"OK",
    "sg:tags":[
        "general"
    ],
    "wof:name":"Public Works Dept",
    "wof:placetype":"venue"
},
  "geometry": {"coordinates":[-97.51947800000001,35.457961],"type":"Point"}
}