{
  "type": "Feature",
  "properties": {
    "iso:country":"US",
    "sg:address":"103 E 8th St",
    "sg:city":"Pawhuska",
    "sg:classifiers":[
        {
            "category":"Banks & Credit Unions",
            "subcategory":"Bank",
            "type":"Services"
        }
    ],
    "sg:phone":"+1 918 287 4111",
    "sg:postcode":"74056",
    "sg:province":"OK",
    "wof:name":"NBC Bank",
    "wof:placetype":"venue"
},
  "geometry": {"coordinates":[-96.338605,36.666294],"type":"Point"}
}