{
  "type": "Feature",
  "properties": {
    "iso:country":"US",
    "sg:address":"5000 NW 4th St",
    "sg:city":"Oklahoma City",
    "sg:classifiers":[
        {
            "category":"Wholesale",
            "subcategory":"Machinery & Supplies",
            "type":"Manufacturing & Wholesale Goods"
        }
    ],
    "sg:phone":"+1 405 949 1798",
    "sg:postcode":"73127",
    "sg:province":"OK",
    "sg:tags":[
        "industrial"
    ],
    "wof:name":"Industrial Sup Unlimited LLC",
    "wof:placetype":"venue"
},
  "geometry": {"coordinates":[-97.611277,35.470006],"type":"Point"}
}