{
  "type": "Feature",
  "properties": {
    "addr:full":"7180 S Memorial Dr Tulsa OK 74133",
    "addr:housenumber":"7180",
    "addr:postcode":"74133",
    "addr:street":"S Memorial Dr",
    "iso:country":"US",
    "sg:address":"7180 S Memorial Dr",
    "sg:city":"Tulsa",
    "sg:classifiers":[
        {
            "category":"Restaurant",
            "type":"Food & Drink"
        }
    ],
    "sg:menulink":"http://www.allmenus.com/ok/tulsa/211155-kfc---kentucky-fried-chicken/menu/",
    "sg:phone":"+1 918 252 1476",
    "sg:postcode":"74133",
    "sg:province":"OK",
    "sg:tags":[
        "american",
        "chicken"
    ],
    "wof:name":"KFC - Kentucky Fried Chicken",
    "wof:placetype":"venue"
},
  "geometry": {"coordinates":[-95.886426,36.058424],"type":"Point"}
}