{
  "type": "Feature",
  "properties": {
    "addr:full":"320 N Quapah Ave Oklahoma City OK 73107",
    "addr:housenumber":"320",
    "addr:postcode":"73107",
    "addr:street":"N Quapah Ave",
    "iso:country":"US",
    "sg:address":"320 N Quapah Ave",
    "sg:city":"Oklahoma City",
    "sg:classifiers":[
        {
            "category":"Wholesale",
            "subcategory":"Groceries",
            "type":"Manufacturing & Wholesale Goods"
        }
    ],
    "sg:phone":"+1 405 945 0033",
    "sg:postcode":"73107",
    "sg:province":"OK",
    "sg:tags":[
        "grocer"
    ],
    "wof:name":"Ben's Warehouse",
    "wof:placetype":"venue"
},
  "geometry": {"coordinates":[-97.585589,35.465238],"type":"Point"}
}