{
  "type": "Feature",
  "properties": {
    "addr:full":"3215 S Harvard Ave Tulsa OK 74135",
    "addr:housenumber":"3215",
    "addr:postcode":"74135",
    "addr:street":"S Harvard Ave",
    "iso:country":"US",
    "sg:address":"3215 S Harvard Ave",
    "sg:city":"Tulsa",
    "sg:classifiers":[
        {
            "category":"Utilities",
            "subcategory":"Mobile Phone",
            "type":"Services"
        }
    ],
    "sg:phone":"+1 918 749 6977",
    "sg:postcode":"74135",
    "sg:province":"OK",
    "sg:tags":[
        "telephone",
        "cellular"
    ],
    "wof:name":"U S Cellular",
    "wof:placetype":"venue"
},
  "geometry": {"coordinates":[-95.94018800000001,36.116624],"type":"Point"}
}