{
  "type": "Feature",
  "properties": {
    "iso:country":"US",
    "sg:address":"324 S Main St",
    "sg:city":"Fairfax",
    "sg:classifiers":[
        {
            "category":"Sports & Exercise",
            "subcategory":"Gym",
            "type":"Entertainment"
        }
    ],
    "sg:phone":"+1 918 642 3030",
    "sg:postcode":"74637",
    "sg:province":"OK",
    "sg:tags":[
        "club",
        "health",
        "studio",
        "gymnasium"
    ],
    "wof:name":"PLS Toning",
    "wof:placetype":"venue"
},
  "geometry": {"coordinates":[-96.704285,36.568283],"type":"Point"}
}