{
  "type": "Feature",
  "properties": {
    "iso:country":"US",
    "sg:address":"500 N Falcon Way",
    "sg:city":"Mustang",
    "sg:classifiers":[
        {
            "category":"Real Estate",
            "subcategory":"Real Estate Services",
            "type":"Services"
        }
    ],
    "sg:phone":"+1 405 376 1966",
    "sg:postcode":"73064",
    "sg:province":"OK",
    "sg:tags":[
        "abstract",
        "title"
    ],
    "wof:name":"American Guaranty Title",
    "wof:placetype":"venue"
},
  "geometry": {"coordinates":[-97.756557,35.398619],"type":"Point"}
}