{
  "type": "Feature",
  "properties": {
    "addr:full":"912 NW 57th St Oklahoma City OK 73118",
    "addr:housenumber":"912",
    "addr:postcode":"73118",
    "addr:street":"Nw 57Th St",
    "iso:country":"US",
    "sg:address":"912 NW 57th St",
    "sg:city":"Oklahoma City",
    "sg:classifiers":[
        {
            "category":"Real Estate",
            "subcategory":"Developer",
            "type":"Services"
        }
    ],
    "sg:phone":"+1 405 842 0456",
    "sg:postcode":"73118",
    "sg:province":"OK",
    "wof:name":"Penn Crossing /Ennten",
    "wof:placetype":"venue"
},
  "geometry": {"coordinates":[-97.525189,35.530982],"type":"Point"}
}