{
  "type": "Feature",
  "properties": {
    "iso:country":"US",
    "sg:address":"1600 N Martin Luther King Ave",
    "sg:city":"Oklahoma City",
    "sg:classifiers":[
        {
            "category":"Restaurant",
            "type":"Food & Drink"
        }
    ],
    "sg:phone":"+1 405 427 2551",
    "sg:postcode":"73111",
    "sg:province":"OK",
    "sg:tags":[
        "delicatessen"
    ],
    "wof:name":"Circle J Ice Cream Parlor",
    "wof:placetype":"venue"
},
  "geometry": {"coordinates":[-97.476726,35.485856],"type":"Point"}
}