{
  "type": "Feature",
  "properties": {
    "iso:country":"US",
    "sg:address":"502 Ridley Rd",
    "sg:city":"Duncan",
    "sg:classifiers":[
        {
            "category":"Building & Trades",
            "subcategory":"Construction",
            "type":"Services"
        }
    ],
    "sg:phone":"+1 580 470 9669",
    "sg:postcode":"73533",
    "sg:province":"OK",
    "sg:tags":[
        "home",
        "improvement"
    ],
    "wof:name":"Home Etc",
    "wof:placetype":"venue"
},
  "geometry": {"coordinates":[-97.938216,34.498182],"type":"Point"}
}