{
  "type": "Feature",
  "properties": {
    "iso:country":"US",
    "sg:address":"5814 S Victor Ave",
    "sg:city":"Tulsa",
    "sg:classifiers":[
        {
            "category":"Professional",
            "subcategory":"Management & Consulting",
            "type":"Services"
        }
    ],
    "sg:phone":"+1 918 645 6017",
    "sg:postcode":"74105",
    "sg:province":"OK",
    "sg:tags":[
        "business"
    ],
    "wof:name":"Knight Performance MGT LLC",
    "wof:placetype":"venue"
},
  "geometry": {"coordinates":[-95.965994,36.078773],"type":"Point"}
}