{
  "type": "Feature",
  "properties": {
    "iso:country":"US",
    "sg:address":"1024 S Lewis St",
    "sg:city":"Stillwater",
    "sg:classifiers":[
        {
            "category":"Organizations",
            "subcategory":"Religious Organization",
            "type":"Services"
        }
    ],
    "sg:phone":"+1 405 372 7344",
    "sg:postcode":"74074",
    "sg:province":"OK",
    "sg:tags":[
        "church"
    ],
    "wof:name":"First Assembly Of God",
    "wof:placetype":"venue"
},
  "geometry": {"coordinates":[-97.057295,36.110997],"type":"Point"}
}