{
  "type": "Feature",
  "properties": {
    "addr:full":"3700 Highway 66 Catoosa OK 74015",
    "addr:housenumber":"3700",
    "addr:postcode":"74015",
    "addr:street":"Highway 66",
    "iso:country":"US",
    "sg:address":"3700 Highway 66",
    "sg:city":"Catoosa",
    "sg:classifiers":[
        {
            "category":"Restaurant",
            "type":"Food & Drink"
        }
    ],
    "sg:phone":"+1 918 266 7853",
    "sg:postcode":"74015",
    "sg:province":"OK",
    "wof:name":"Molly's Steak House",
    "wof:placetype":"venue"
},
  "geometry": {"coordinates":[-95.744598,36.184601],"type":"Point"}
}