{
  "type": "Feature",
  "properties": {
    "addr:full":"2127 N Main St Miami OK 74354",
    "addr:housenumber":"2127",
    "addr:postcode":"74354",
    "addr:street":"N Main St",
    "iso:country":"US",
    "sg:address":"2127 N Main St",
    "sg:city":"Miami",
    "sg:classifiers":[
        {
            "category":"Organizations",
            "subcategory":"Religious Organization",
            "type":"Services"
        }
    ],
    "sg:phone":"+1 918 542 5549",
    "sg:postcode":"74354",
    "sg:province":"OK",
    "wof:name":"Bethany Christian Church",
    "wof:placetype":"venue"
},
  "geometry": {"coordinates":[-94.877582,36.898778],"type":"Point"}
}