{
  "type": "Feature",
  "properties": {
    "iso:country":"US",
    "sg:address":"217 E Grand Ave",
    "sg:city":"Ponca City",
    "sg:classifiers":[
        {
            "category":"Shopping",
            "subcategory":"Gifts & Souvenirs",
            "type":"Retail Goods"
        }
    ],
    "sg:phone":"+1 580 762 3726",
    "sg:postcode":"74601",
    "sg:province":"OK",
    "sg:tags":[
        "novelty"
    ],
    "wof:name":"Victorias Garden & Interiors",
    "wof:placetype":"venue"
},
  "geometry": {"coordinates":[-97.082333,36.703724],"type":"Point"}
}