{
  "type": "Feature",
  "properties": {
    "addr:full":"4717 S Mingo Rd Tulsa OK 74146",
    "addr:housenumber":"4717",
    "addr:postcode":"74146",
    "addr:street":"S Mingo Rd",
    "iso:country":"US",
    "sg:address":"4717 S Mingo Rd",
    "sg:city":"Tulsa",
    "sg:classifiers":[
        {
            "category":"Wholesale",
            "subcategory":"Groceries",
            "type":"Manufacturing & Wholesale Goods"
        }
    ],
    "sg:phone":"+1 918 665 3737",
    "sg:postcode":"74146",
    "sg:province":"OK",
    "sg:tags":[
        "grocer"
    ],
    "sg:website":"www.usfoodservice.com",
    "wof:name":"U S Foodservice-Oklahoma Div",
    "wof:placetype":"venue"
},
  "geometry": {"coordinates":[-95.86857000000001,36.093003],"type":"Point"}
}