{
  "type": "Feature",
  "properties": {
    "addr:full":"2677 Terwilleger Blvd Tulsa OK 74114",
    "addr:housenumber":"2677",
    "addr:postcode":"74114",
    "addr:street":"Terwilleger Blvd",
    "iso:country":"US",
    "sg:address":"2677 Terwilleger Blvd",
    "sg:city":"Tulsa",
    "sg:classifiers":[
        {
            "category":"Structure",
            "subcategory":"Office Building",
            "type":"Public Place"
        }
    ],
    "sg:phone":"+1 918 743 9362",
    "sg:postcode":"74114",
    "sg:province":"OK",
    "sg:tags":[
        "park"
    ],
    "wof:name":"Ramey Properties",
    "wof:placetype":"venue"
},
  "geometry": {"coordinates":[-95.96736199999999,36.125188],"type":"Point"}
}