{
  "type": "Feature",
  "properties": {
    "addr:full":"9520 Hillcrest Dr Broken Arrow OK 74014",
    "addr:housenumber":"9520",
    "addr:postcode":"74014",
    "addr:street":"Hillcrest Dr",
    "iso:country":"US",
    "sg:address":"9520 Hillcrest Dr",
    "sg:city":"Broken Arrow",
    "sg:classifiers":[
        {
            "category":"Organizations",
            "subcategory":"Religious Organization",
            "type":"Services"
        }
    ],
    "sg:phone":"+1 918 258 7137",
    "sg:postcode":"74014",
    "sg:province":"OK",
    "sg:tags":[
        "church"
    ],
    "wof:name":"Faith An'Joy Fellowship",
    "wof:placetype":"venue"
},
  "geometry": {"coordinates":[-95.722719,36.027359],"type":"Point"}
}