{
  "type": "Feature",
  "properties": {
    "iso:country":"US",
    "sg:address":"4919 S Columbia Ave",
    "sg:city":"Tulsa",
    "sg:classifiers":[
        {
            "category":"Building & Trades",
            "subcategory":"Construction",
            "type":"Services"
        }
    ],
    "sg:phone":"+1 918 743 9991",
    "sg:postcode":"74105",
    "sg:province":"OK",
    "sg:tags":[
        "builder",
        "patio",
        "deck"
    ],
    "wof:name":"Tulsa Patios",
    "wof:placetype":"venue"
},
  "geometry": {"coordinates":[-95.952308,36.090907],"type":"Point"}
}