{
  "type": "Feature",
  "properties": {
    "addr:full":"809 E 6th St Tishomingo OK 73460",
    "addr:housenumber":"809",
    "addr:postcode":"73460",
    "addr:street":"E 6Th St",
    "iso:country":"US",
    "sg:address":"809 E 6th St",
    "sg:city":"Tishomingo",
    "sg:classifiers":[
        {
            "category":"Social Services",
            "subcategory":"Child Care",
            "type":"Services"
        }
    ],
    "sg:phone":"+1 580 371 3680",
    "sg:postcode":"73460",
    "sg:province":"OK",
    "sg:tags":[
        "day"
    ],
    "wof:name":"Tishomingo Head Start",
    "wof:placetype":"venue"
},
  "geometry": {"coordinates":[-96.66689700000001,34.234389],"type":"Point"}
}