{
  "type": "Feature",
  "properties": {
    "iso:country":"US",
    "sg:address":"2520 E 71st St",
    "sg:city":"Tulsa",
    "sg:classifiers":[
        {
            "category":"Professional",
            "subcategory":"Accounting & Tax Preparation",
            "type":"Services"
        }
    ],
    "sg:phone":"+1 918 494 2888",
    "sg:postcode":"74136",
    "sg:province":"OK",
    "sg:tags":[
        "return",
        "filing"
    ],
    "wof:name":"Tax Depot LLC",
    "wof:placetype":"venue"
},
  "geometry": {"coordinates":[-95.95297100000001,36.060754],"type":"Point"}
}