{
  "type": "Feature",
  "properties": {
    "iso:country":"US",
    "sg:address":"6937 S Sheridan Rd",
    "sg:city":"Tulsa",
    "sg:classifiers":[
        {
            "category":"Insurance",
            "subcategory":"Insurance Agent",
            "type":"Services"
        }
    ],
    "sg:phone":"+1 918 492 4900",
    "sg:postcode":"74133",
    "sg:province":"OK",
    "sg:website":"www.statefarm.com",
    "wof:name":"State Farm Insurance",
    "wof:placetype":"venue"
},
  "geometry": {"coordinates":[-95.904152,36.061312],"type":"Point"}
}