{
  "type": "Feature",
  "properties": {
    "addr:full":"6219 E 11th St Tulsa OK 74112",
    "addr:housenumber":"6219",
    "addr:postcode":"74112",
    "addr:street":"E 11Th St",
    "iso:country":"US",
    "sg:address":"6219 E 11th St",
    "sg:city":"Tulsa",
    "sg:classifiers":[
        {
            "category":"Building & Trades",
            "subcategory":"Construction",
            "type":"Services"
        }
    ],
    "sg:phone":"+1 918 838 7670",
    "sg:postcode":"74112",
    "sg:province":"OK",
    "sg:tags":[
        "designer",
        "dealer",
        "pool",
        "swimming"
    ],
    "wof:name":"Dolphin Pools",
    "wof:placetype":"venue"
},
  "geometry": {"coordinates":[-95.907011,36.148001],"type":"Point"}
}