{
  "type": "Feature",
  "properties": {
    "iso:country":"US",
    "sg:address":"707 S Husband St",
    "sg:city":"Stillwater",
    "sg:classifiers":[
        {
            "category":"Shopping",
            "type":"Retail Goods"
        }
    ],
    "sg:phone":"+1 405 372 2657",
    "sg:postcode":"74074",
    "sg:province":"OK",
    "sg:tags":[
        "hearing",
        "equipment",
        "supply",
        "impaired"
    ],
    "wof:name":"Integrity Hearing Aid Ctr",
    "wof:placetype":"venue"
},
  "geometry": {"coordinates":[-97.05987,36.1145],"type":"Point"}
}