{
  "type": "Feature",
  "properties": {
    "iso:country":"US",
    "sg:address":"2400 S 13th St",
    "sg:city":"Clinton",
    "sg:classifiers":[
        {
            "category":"Wholesale",
            "subcategory":"Beer",
            "type":"Manufacturing & Wholesale Goods"
        }
    ],
    "sg:phone":"+1 580 323 1333",
    "sg:postcode":"73601",
    "sg:province":"OK",
    "wof:name":"Jett Distributing Co",
    "wof:placetype":"venue"
},
  "geometry": {"coordinates":[-98.975878,35.483278],"type":"Point"}
}