{
  "type": "Feature",
  "properties": {
    "iso:country":"US",
    "sg:address":"6859 S Canton Ave",
    "sg:city":"Tulsa",
    "sg:classifiers":[
        {
            "category":"Real Estate",
            "subcategory":"Real Estate Agent",
            "type":"Services"
        }
    ],
    "sg:phone":"+1 918 488 8485",
    "sg:postcode":"74136",
    "sg:province":"OK",
    "wof:name":"Lynco Inc",
    "wof:placetype":"venue"
},
  "geometry": {"coordinates":[-95.918745,36.063424],"type":"Point"}
}