{
  "type": "Feature",
  "properties": {
    "iso:country":"US",
    "sg:address":"923 E Highland Ave",
    "sg:city":"Ponca City",
    "sg:classifiers":[
        {
            "category":"Insurance",
            "subcategory":"Insurance Agent",
            "type":"Services"
        }
    ],
    "sg:phone":"+1 580 762 1362",
    "sg:postcode":"74601",
    "sg:province":"OK",
    "wof:name":"Bill Leming",
    "wof:placetype":"venue"
},
  "geometry": {"coordinates":[-97.072678,36.709698],"type":"Point"}
}