{
  "type": "Feature",
  "properties": {
    "addr:full":"315 S Silver Dr Mustang OK 73064",
    "addr:housenumber":"315",
    "addr:postcode":"73064",
    "addr:street":"S Silver Dr",
    "iso:country":"US",
    "sg:address":"315 S Silver Dr",
    "sg:city":"Mustang",
    "sg:classifiers":[
        {
            "category":"Retail",
            "subcategory":"Repair Shop",
            "type":"Services"
        }
    ],
    "sg:phone":"+1 405 376 2252",
    "sg:postcode":"73064",
    "sg:province":"OK",
    "sg:tags":[
        "refrigeration"
    ],
    "wof:name":"Ferguson Heat & Air",
    "wof:placetype":"venue"
},
  "geometry": {"coordinates":[-97.73746800000001,35.387779],"type":"Point"}
}