{
  "type": "Feature",
  "properties": {
    "iso:country":"US",
    "sg:address":"2121 N Harvard Ave",
    "sg:city":"Tulsa",
    "sg:classifiers":[
        {
            "category":"Organizations",
            "subcategory":"Religious Organization",
            "type":"Services"
        }
    ],
    "sg:phone":"+1 918 834 1979",
    "sg:postcode":"74115",
    "sg:province":"OK",
    "sg:tags":[
        "church"
    ],
    "wof:name":"Parkland Baptist Church Inc",
    "wof:placetype":"venue"
},
  "geometry": {"coordinates":[-95.940247,36.184046],"type":"Point"}
}