{
  "type": "Feature",
  "properties": {
    "iso:country":"US",
    "sg:address":"31188 State Hwy 48",
    "sg:city":"Bristow",
    "sg:classifiers":[
        {
            "category":"Building & Trades",
            "subcategory":"Construction",
            "type":"Services"
        }
    ],
    "sg:phone":"+1 918 367 1700",
    "sg:postcode":"74010",
    "sg:province":"OK",
    "sg:tags":[
        "contractor"
    ],
    "wof:name":"Timco Sandblasting & Painting",
    "wof:placetype":"venue"
},
  "geometry": {"coordinates":[-96.387253,35.710545],"type":"Point"}
}