{
  "type": "Feature",
  "properties": {
    "iso:country":"US",
    "sg:address":"12115 N I- 35 Svc Rd",
    "sg:city":"Oklahoma City",
    "sg:phone":"+1 405 475 2978",
    "sg:postcode":"73131",
    "sg:province":"OK",
    "sg:tags":[
        "agricultural",
        "product"
    ],
    "wof:name":"Osu Division Of Agriculture",
    "wof:placetype":"venue"
},
  "geometry": {"coordinates":[-97.437877,35.587522],"type":"Point"}
}