{
  "type": "Feature",
  "properties": {
    "iso:country":"US",
    "sg:address":"1220 N Main St",
    "sg:city":"Newcastle",
    "sg:classifiers":[
        {
            "category":"Restaurant",
            "type":"Food & Drink"
        }
    ],
    "sg:phone":"+1 405 387 2828",
    "sg:postcode":"73065",
    "sg:province":"OK",
    "wof:name":"Pit Stop Grill",
    "wof:placetype":"venue"
},
  "geometry": {"coordinates":[-97.600058,35.256145],"type":"Point"}
}