{
  "type": "Feature",
  "properties": {
    "addr:full":"205 S Main St Sapulpa OK 74066",
    "addr:housenumber":"205",
    "addr:postcode":"74066",
    "addr:street":"S Main St",
    "iso:country":"US",
    "sg:address":"205 S Main St",
    "sg:city":"Sapulpa",
    "sg:classifiers":[
        {
            "category":"Retail",
            "subcategory":"Auto Repair",
            "type":"Services"
        }
    ],
    "sg:phone":"+1 918 224 0374",
    "sg:postcode":"74066",
    "sg:province":"OK",
    "sg:tags":[
        "body"
    ],
    "wof:name":"I-Care Auto Parts",
    "wof:placetype":"venue"
},
  "geometry": {"coordinates":[-96.113947,35.995284],"type":"Point"}
}