{
  "type": "Feature",
  "properties": {
    "addr:full":"1707 E 6th Ave Stillwater OK 74074",
    "addr:housenumber":"1707",
    "addr:postcode":"74074",
    "addr:street":"E 6Th Ave",
    "iso:country":"US",
    "sg:address":"1707 E 6th Ave",
    "sg:city":"Stillwater",
    "sg:classifiers":[
        {
            "category":"Restaurant",
            "type":"Food & Drink"
        }
    ],
    "sg:phone":"+1 405 377 8777",
    "sg:postcode":"74074",
    "sg:province":"OK",
    "sg:website":"www.freddiepauls.com",
    "wof:name":"Freddie Paul's Steakhouse",
    "wof:placetype":"venue"
},
  "geometry": {"coordinates":[-97.034992,36.11591],"type":"Point"}
}