{
  "type": "Feature",
  "properties": {
    "iso:country":"US",
    "sg:address":"4921 S Yorktown Ave",
    "sg:city":"Tulsa",
    "sg:classifiers":[
        {
            "category":"Building & Trades",
            "subcategory":"Electrical",
            "type":"Services"
        }
    ],
    "sg:phone":"+1 918 742 9868",
    "sg:postcode":"74105",
    "sg:province":"OK",
    "sg:tags":[
        "electric",
        "contractor"
    ],
    "wof:name":"ASC Electric Svc Co",
    "wof:placetype":"venue"
},
  "geometry": {"coordinates":[-95.962898,36.092161],"type":"Point"}
}