{
  "type": "Feature",
  "properties": {
    "addr:full":"3019 S Sheridan Rd Tulsa OK 74129",
    "addr:housenumber":"3019",
    "addr:postcode":"74129",
    "addr:street":"S Sheridan Rd",
    "iso:country":"US",
    "sg:address":"3019 S Sheridan Rd",
    "sg:city":"Tulsa",
    "sg:classifiers":[
        {
            "category":"Shopping",
            "subcategory":"Discount & Variety Stores",
            "type":"Retail Goods"
        }
    ],
    "sg:phone":"+1 918 641 1000",
    "sg:postcode":"74129",
    "sg:province":"OK",
    "sg:tags":[
        "merchandise",
        "general"
    ],
    "wof:name":"Family Dollar Store",
    "wof:placetype":"venue"
},
  "geometry": {"coordinates":[-95.90446900000001,36.119313],"type":"Point"}
}