{
  "type": "Feature",
  "properties": {
    "addr:full":"315 Franklin St Healdton OK 73438",
    "addr:housenumber":"315",
    "addr:postcode":"73438",
    "addr:street":"Franklin St",
    "iso:country":"US",
    "sg:address":"315 Franklin St",
    "sg:city":"Healdton",
    "sg:classifiers":[
        {
            "category":"Government",
            "subcategory":"Post Office",
            "type":"Public Place"
        }
    ],
    "sg:phone":"+1 580 229 0450",
    "sg:postcode":"73438",
    "sg:province":"OK",
    "wof:name":"US Post Office",
    "wof:placetype":"venue"
},
  "geometry": {"coordinates":[-97.48765400000001,34.234131],"type":"Point"}
}