{
  "type": "Feature",
  "properties": {
    "iso:country":"US",
    "sg:address":"121 N 2nd Ave",
    "sg:city":"Purcell",
    "sg:classifiers":[
        {
            "category":"Government",
            "subcategory":"Police Station",
            "type":"Public Place"
        }
    ],
    "sg:phone":"+1 405 527 2141",
    "sg:postcode":"73080",
    "sg:province":"OK",
    "sg:tags":[
        "sheriff"
    ],
    "wof:name":"Mc Clain County Sheriff",
    "wof:placetype":"venue"
},
  "geometry": {"coordinates":[-97.36108,35.013329],"type":"Point"}
}