{
  "type": "Feature",
  "properties": {
    "iso:country":"US",
    "sg:address":"8324 W Reno Ave",
    "sg:city":"Oklahoma City",
    "sg:classifiers":[
        {
            "category":"Manufacturing",
            "subcategory":"Tools & Machinery",
            "type":"Manufacturing & Wholesale Goods"
        }
    ],
    "sg:phone":"+1 405 440 1015",
    "sg:postcode":"73127",
    "sg:province":"OK",
    "sg:tags":[
        "field",
        "oil",
        "equipment"
    ],
    "wof:name":"Production Control Svc Inc",
    "wof:placetype":"venue"
},
  "geometry": {"coordinates":[-97.660102,35.464123],"type":"Point"}
}