{
  "type": "Feature",
  "properties": {
    "addr:full":"114 S Broadway St Tecumseh OK 74873",
    "addr:housenumber":"114",
    "addr:postcode":"74873",
    "addr:street":"S Broadway St",
    "iso:country":"US",
    "sg:address":"114 S Broadway St",
    "sg:city":"Tecumseh",
    "sg:classifiers":[
        {
            "category":"Organizations",
            "subcategory":"Professional Association",
            "type":"Services"
        }
    ],
    "sg:phone":"+1 405 598 8666",
    "sg:postcode":"74873",
    "sg:province":"OK",
    "sg:tags":[
        "business"
    ],
    "wof:name":"Tecumseh Chamber of Commerce",
    "wof:placetype":"venue"
},
  "geometry": {"coordinates":[-96.936852,35.257513],"type":"Point"}
}