{
  "type": "Feature",
  "properties": {
    "iso:country":"US",
    "sg:address":"11 NW 44th St",
    "sg:city":"Lawton",
    "sg:classifiers":[
        {
            "category":"Banks & Credit Unions",
            "subcategory":"Investment Brokerage",
            "type":"Services"
        }
    ],
    "sg:phone":"+1 580 353 7704",
    "sg:postcode":"73505",
    "sg:province":"OK",
    "sg:tags":[
        "security"
    ],
    "wof:name":"Edward Jones 07324",
    "wof:placetype":"venue"
},
  "geometry": {"coordinates":[-98.445829,34.610089],"type":"Point"}
}