{
  "type": "Feature",
  "properties": {
    "iso:country":"US",
    "sg:address":"3301 SW 17th St",
    "sg:city":"Oklahoma City",
    "sg:classifiers":[
        {
            "category":"Social Services",
            "subcategory":"Child Care",
            "type":"Services"
        }
    ],
    "sg:phone":"+1 405 685 2277",
    "sg:postcode":"73108",
    "sg:province":"OK",
    "sg:tags":[
        "day"
    ],
    "wof:name":"Oak Grove Head Start",
    "wof:placetype":"venue"
},
  "geometry": {"coordinates":[-97.578331,35.446336],"type":"Point"}
}