{
  "type": "Feature",
  "properties": {
    "addr:full":"518 E Main St Ada OK 74820",
    "addr:housenumber":"518",
    "addr:postcode":"74820",
    "addr:street":"E Main St",
    "iso:country":"US",
    "sg:address":"518 E Main St",
    "sg:city":"Ada",
    "sg:classifiers":[
        {
            "category":"Retail",
            "subcategory":"Auto Repair",
            "type":"Services"
        }
    ],
    "sg:phone":"+1 580 332 6687",
    "sg:postcode":"74820",
    "sg:province":"OK",
    "sg:tags":[
        "repairing",
        "automobile"
    ],
    "wof:name":"Wiley's Automotive",
    "wof:placetype":"venue"
},
  "geometry": {"coordinates":[-96.671958,34.7746],"type":"Point"}
}