{
  "type": "Feature",
  "properties": {
    "addr:full":"3209 Broce Dr Norman OK 73072",
    "addr:housenumber":"3209",
    "addr:postcode":"73072",
    "addr:street":"Broce Dr",
    "iso:country":"US",
    "sg:address":"3209 Broce Dr",
    "sg:city":"Norman",
    "sg:classifiers":[
        {
            "category":"Manufacturing",
            "subcategory":"Apparel",
            "type":"Manufacturing & Wholesale Goods"
        }
    ],
    "sg:phone":"+1 405 360 4598",
    "sg:postcode":"73072",
    "sg:province":"OK",
    "sg:tags":[
        "shirt",
        "mfg"
    ],
    "wof:name":"University Athletic Society",
    "wof:placetype":"venue"
},
  "geometry": {"coordinates":[-97.487117,35.253696],"type":"Point"}
}