{
  "type": "Feature",
  "properties": {
    "addr:full":"3724 E Harris Rd Muskogee OK 74403",
    "addr:housenumber":"3724",
    "addr:postcode":"74403",
    "addr:street":"E Harris Rd",
    "iso:country":"US",
    "sg:address":"3724 E Harris Rd",
    "sg:city":"Muskogee",
    "sg:classifiers":[
        {
            "category":"Building & Trades",
            "subcategory":"Construction",
            "type":"Services"
        }
    ],
    "sg:phone":"+1 918 683 4915",
    "sg:postcode":"74403",
    "sg:province":"OK",
    "sg:tags":[
        "contractor"
    ],
    "wof:name":"Beck Construction",
    "wof:placetype":"venue"
},
  "geometry": {"coordinates":[-95.316485,35.784318],"type":"Point"}
}