{
  "type": "Feature",
  "properties": {
    "iso:country":"US",
    "sg:address":"3329 S Elm Pl",
    "sg:city":"Broken Arrow",
    "sg:classifiers":[
        {
            "category":"Social Services",
            "subcategory":"Child Care",
            "type":"Services"
        }
    ],
    "sg:phone":"+1 918 451 9336",
    "sg:postcode":"74012",
    "sg:province":"OK",
    "sg:tags":[
        "day"
    ],
    "wof:name":"Playtime (+) Inc",
    "wof:placetype":"venue"
},
  "geometry": {"coordinates":[-95.79738500000001,36.017909],"type":"Point"}
}