{
  "type": "Feature",
  "properties": {
    "addr:full":"101 W Benton Ave Davis OK 73030",
    "addr:housenumber":"101",
    "addr:postcode":"73030",
    "addr:street":"W Benton Ave",
    "iso:country":"US",
    "sg:address":"101 W Benton Ave",
    "sg:city":"Davis",
    "sg:classifiers":[
        {
            "category":"Sports & Exercise",
            "subcategory":"Gym",
            "type":"Entertainment"
        }
    ],
    "sg:phone":"+1 580 369 3500",
    "sg:postcode":"73030",
    "sg:province":"OK",
    "sg:tags":[
        "club",
        "health",
        "studio",
        "gymnasium"
    ],
    "wof:name":"Extreme Fitness",
    "wof:placetype":"venue"
},
  "geometry": {"coordinates":[-97.122928,34.50456],"type":"Point"}
}