{
  "type": "Feature",
  "properties": {
    "addr:full":"2321 W Okmulgee Ave Muskogee OK 74401",
    "addr:housenumber":"2321",
    "addr:postcode":"74401",
    "addr:street":"W Okmulgee Ave",
    "iso:country":"US",
    "sg:address":"2321 W Okmulgee Ave",
    "sg:city":"Muskogee",
    "sg:classifiers":[
        {
            "category":"Insurance",
            "subcategory":"Insurance Agent",
            "type":"Services"
        }
    ],
    "sg:phone":"+1 918 682 2081",
    "sg:postcode":"74401",
    "sg:province":"OK",
    "wof:name":"James Dause Ins Agency",
    "wof:placetype":"venue"
},
  "geometry": {"coordinates":[-95.393545,35.75497],"type":"Point"}
}