{
  "type": "Feature",
  "properties": {
    "iso:country":"US",
    "sg:address":"701 E Barnes Ave",
    "sg:city":"Alva",
    "sg:classifiers":[
        {
            "category":"Education",
            "subcategory":"School",
            "type":"Public Place"
        }
    ],
    "sg:phone":"+1 580 327 3518",
    "sg:postcode":"73717",
    "sg:province":"OK",
    "sg:website":"www.alvaschools.com",
    "wof:name":"Washington Elementary School",
    "wof:placetype":"venue"
},
  "geometry": {"coordinates":[-98.649285,36.80354],"type":"Point"}
}