{
  "type": "Feature",
  "properties": {
    "iso:country":"US",
    "sg:address":"7000 NW 32nd St",
    "sg:city":"Bethany",
    "sg:classifiers":[
        {
            "category":"Education",
            "subcategory":"College",
            "type":"Public Place"
        }
    ],
    "sg:phone":"+1 405 491 9871",
    "sg:postcode":"73008",
    "sg:province":"OK",
    "sg:tags":[
        "academic",
        "school"
    ],
    "wof:name":"Grace College",
    "wof:placetype":"venue"
},
  "geometry": {"coordinates":[-97.636618,35.504273],"type":"Point"}
}