{
  "type": "Feature",
  "properties": {
    "iso:country":"US",
    "sg:address":"7127 E 91st Ct",
    "sg:city":"Tulsa",
    "sg:classifiers":[
        {
            "category":"Professional",
            "type":"Services"
        },
        {
            "category":"Personal",
            "type":"Services"
        },
        {
            "category":"Freight",
            "type":"Transportation"
        }
    ],
    "sg:phone":"+1 918 477 2121",
    "sg:postcode":"74133",
    "sg:province":"OK",
    "sg:tags":[
        "full",
        "material",
        "storage",
        "trucking",
        "moving",
        "services-labor",
        "mover",
        "local"
    ],
    "wof:name":"International Facility Mg",
    "wof:placetype":"venue"
},
  "geometry": {"coordinates":[-95.894402,36.030899],"type":"Point"}
}