{
  "type": "Feature",
  "properties": {
    "iso:country":"US",
    "sg:address":"6702 S Lewis Ave",
    "sg:city":"Tulsa",
    "sg:classifiers":[
        {
            "category":"Retail",
            "subcategory":"Veterinary Services",
            "type":"Services"
        }
    ],
    "sg:phone":"+1 918 493 5757",
    "sg:postcode":"74136",
    "sg:province":"OK",
    "sg:tags":[
        "hospital",
        "animal"
    ],
    "wof:name":"Horizon Animal Hospital",
    "wof:placetype":"venue"
},
  "geometry": {"coordinates":[-95.95796799999999,36.065728],"type":"Point"}
}