{
  "type": "Feature",
  "properties": {
    "iso:country":"US",
    "sg:address":"1816 Gray Fox Dr",
    "sg:city":"Edmond",
    "sg:classifiers":[
        {
            "category":"Insurance",
            "subcategory":"Insurance Agent",
            "type":"Services"
        }
    ],
    "sg:phone":"+1 405 341 0369",
    "sg:postcode":"73003",
    "sg:province":"OK",
    "wof:name":"Mid America Full Claims Servic",
    "wof:placetype":"venue"
},
  "geometry": {"coordinates":[-97.507776,35.647387],"type":"Point"}
}