{
  "type": "Feature",
  "properties": {
    "addr:full":"1107 Sampson St Seminole OK 74868",
    "addr:housenumber":"1107",
    "addr:postcode":"74868",
    "addr:street":"Sampson St",
    "iso:country":"US",
    "sg:address":"1107 Sampson St",
    "sg:city":"Seminole",
    "sg:classifiers":[
        {
            "category":"Organizations",
            "subcategory":"Religious Organization",
            "type":"Services"
        }
    ],
    "sg:phone":"+1 405 303 2333",
    "sg:postcode":"74868",
    "sg:province":"OK",
    "sg:tags":[
        "church"
    ],
    "wof:name":"First United Pentecostal Ch",
    "wof:placetype":"venue"
},
  "geometry": {"coordinates":[-96.691868,35.235216],"type":"Point"}
}