{
  "type": "Feature",
  "properties": {
    "iso:country":"US",
    "sg:address":"1665 N Airport Rd",
    "sg:city":"Healdton",
    "sg:classifiers":[
        {
            "category":"Mining & Drilling",
            "type":"Manufacturing & Wholesale Goods"
        }
    ],
    "sg:phone":"+1 580 229 0044",
    "sg:postcode":"73438",
    "sg:province":"OK",
    "sg:tags":[
        "field"
    ],
    "wof:name":"Oasis Plugging Co",
    "wof:placetype":"venue"
},
  "geometry": {"coordinates":[-97.474662,34.240238],"type":"Point"}
}