{
  "type": "Feature",
  "properties": {
    "iso:country":"US",
    "sg:address":"124 N Broadway Ave",
    "sg:city":"Shawnee",
    "sg:classifiers":[
        {
            "category":"Banks & Credit Unions",
            "subcategory":"Bank",
            "type":"Services"
        }
    ],
    "sg:phone":"+1 405 275 6630",
    "sg:postcode":"74801",
    "sg:province":"OK",
    "sg:tags":[
        "loan"
    ],
    "wof:name":"World Acceptance Corp",
    "wof:placetype":"venue"
},
  "geometry": {"coordinates":[-96.923595,35.328366],"type":"Point"}
}