{
  "type": "Feature",
  "properties": {
    "addr:full":"124 N Broadway Ave Shawnee OK 74801",
    "addr:housenumber":"124",
    "addr:postcode":"74801",
    "addr:street":"N Broadway Ave",
    "iso:country":"US",
    "sg:address":"124 N Broadway Ave",
    "sg:city":"Shawnee",
    "sg:classifiers":[
        {
            "category":"Banks & Credit Unions",
            "subcategory":"Bank",
            "type":"Services"
        }
    ],
    "sg:phone":"+1 405 275 6630",
    "sg:postcode":"74801",
    "sg:province":"OK",
    "sg:tags":[
        "loan"
    ],
    "wof:name":"World Acceptance Corp",
    "wof:placetype":"venue"
},
  "geometry": {"coordinates":[-96.92359500000001,35.328366],"type":"Point"}
}