{
  "type": "Feature",
  "properties": {
    "iso:country":"US",
    "sg:address":"1140 NW 63rd St",
    "sg:city":"Oklahoma City",
    "sg:classifiers":[
        {
            "category":"Health Services",
            "subcategory":"Health Practitioner",
            "type":"Services"
        }
    ],
    "sg:phone":"+1 405 843 1998",
    "sg:postcode":"73116",
    "sg:province":"OK",
    "wof:name":"Kay Goebel PHD",
    "wof:placetype":"venue"
},
  "geometry": {"coordinates":[-97.532231,35.536786],"type":"Point"}
}