{
  "type": "Feature",
  "properties": {
    "iso:country":"US",
    "sg:address":"3030 NW 23rd St",
    "sg:city":"Oklahoma City",
    "sg:classifiers":[
        {
            "category":"Organizations",
            "subcategory":"Religious Organization",
            "type":"Services"
        }
    ],
    "sg:phone":"+1 405 942 5557",
    "sg:postcode":"73107",
    "sg:province":"OK",
    "sg:tags":[
        "church"
    ],
    "sg:website":"www.northwestbaptist.org",
    "wof:name":"Northwest Baptist Church",
    "wof:placetype":"venue"
},
  "geometry": {"coordinates":[-97.569507,35.493085],"type":"Point"}
}