{
  "type": "Feature",
  "properties": {
    "iso:country":"US",
    "sg:address":"7325 E Reno Ave",
    "sg:city":"Oklahoma City",
    "sg:classifiers":[
        {
            "category":"Health Services",
            "subcategory":"Medical Lab",
            "type":"Services"
        }
    ],
    "sg:phone":"+1 405 737 4111",
    "sg:postcode":"73110",
    "sg:province":"OK",
    "wof:name":"Oklahoma Diagnostic Imaging",
    "wof:placetype":"venue"
},
  "geometry": {"coordinates":[-97.394373,35.464131],"type":"Point"}
}