{
  "type": "Feature",
  "properties": {
    "iso:country":"US",
    "sg:address":"1746 Neptune Dr",
    "sg:city":"Clinton",
    "sg:classifiers":[
        {
            "category":"Restaurant",
            "type":"Food & Drink"
        }
    ],
    "sg:phone":"+1 580 323 9843",
    "sg:postcode":"73601",
    "sg:province":"OK",
    "sg:tags":[
        "eating"
    ],
    "wof:name":"Dairy Best",
    "wof:placetype":"venue"
},
  "geometry": {"coordinates":[-98.979803,35.48397],"type":"Point"}
}