{
  "type": "Feature",
  "properties": {
    "iso:country":"US",
    "sg:address":"2238 N Yorktown Ave",
    "sg:city":"Tulsa",
    "sg:classifiers":[
        {
            "category":"Arts & Performance",
            "subcategory":"Theater",
            "type":"Entertainment"
        }
    ],
    "sg:phone":"+1 918 583 7711",
    "sg:postcode":"74110",
    "sg:province":"OK",
    "sg:tags":[
        "band",
        "orchestra"
    ],
    "wof:name":"Legend",
    "wof:placetype":"venue"
},
  "geometry": {"coordinates":[-95.961046,36.187464],"type":"Point"}
}