{
  "type": "Feature",
  "properties": {
    "iso:country":"US",
    "sg:address":"700 SW 29th St",
    "sg:city":"Oklahoma City",
    "sg:classifiers":[
        {
            "category":"Banks & Credit Unions",
            "subcategory":"Bank",
            "type":"Services"
        }
    ],
    "sg:phone":"+1 405 416 2222",
    "sg:postcode":"73109",
    "sg:province":"OK",
    "wof:name":"First Fidelity Bank",
    "wof:placetype":"venue"
},
  "geometry": {"coordinates":[-97.52837,35.43525],"type":"Point"}
}