{
  "type": "Feature",
  "properties": {
    "addr:full":"512 S 28th Ct Broken Arrow OK 74014",
    "addr:housenumber":"512",
    "addr:postcode":"74014",
    "addr:street":"S 28Th Ct",
    "iso:country":"US",
    "sg:address":"512 S 28th Ct",
    "sg:city":"Broken Arrow",
    "sg:classifiers":[
        {
            "category":"Professional",
            "subcategory":"Business Services",
            "type":"Services"
        }
    ],
    "sg:phone":"+1 918 258 2136",
    "sg:postcode":"74014",
    "sg:province":"OK",
    "wof:name":"Dwayne Green",
    "wof:placetype":"venue"
},
  "geometry": {"coordinates":[-95.756325,36.047036],"type":"Point"}
}