{
  "type": "Feature",
  "properties": {
    "addr:full":"6027 S Sheridan Rd Tulsa OK 74145",
    "addr:housenumber":"6027",
    "addr:postcode":"74145",
    "addr:street":"S Sheridan Rd",
    "iso:country":"US",
    "sg:address":"6027 S Sheridan Rd",
    "sg:city":"Tulsa",
    "sg:classifiers":[
        {
            "category":"Restaurant",
            "type":"Food & Drink"
        }
    ],
    "sg:phone":"+1 918 491 6436",
    "sg:postcode":"74145",
    "sg:province":"OK",
    "sg:tags":[
        "eating"
    ],
    "wof:name":"Laroma Pizza",
    "wof:placetype":"venue"
},
  "geometry": {"coordinates":[-95.904247,36.075978],"type":"Point"}
}