{
  "type": "Feature",
  "properties": {
    "iso:country":"US",
    "sg:address":"200 E Central Ave",
    "sg:city":"Miami",
    "sg:classifiers":[
        {
            "category":"Banks & Credit Unions",
            "subcategory":"Bank",
            "type":"Services"
        }
    ],
    "sg:phone":"+1 918 542 6287",
    "sg:postcode":"74354",
    "sg:province":"OK",
    "sg:tags":[
        "business",
        "used",
        "institution",
        "merchandise"
    ],
    "wof:name":"East Central Pawn",
    "wof:placetype":"venue"
},
  "geometry": {"coordinates":[-94.87532,36.87467],"type":"Point"}
}