{
  "type": "Feature",
  "properties": {
    "iso:country":"US",
    "sg:address":"3600 E I- 240 Svc Rd",
    "sg:city":"Oklahoma City",
    "sg:classifiers":[
        {
            "category":"Building & Trades",
            "subcategory":"Construction",
            "type":"Services"
        }
    ],
    "sg:phone":"+1 405 670 2827",
    "sg:postcode":"73135",
    "sg:province":"OK",
    "sg:tags":[
        "designer",
        "dealer",
        "pool",
        "swimming"
    ],
    "wof:name":"J Trimble Pools & Spas",
    "wof:placetype":"venue"
},
  "geometry": {"coordinates":[-97.45763599999999,35.39233],"type":"Point"}
}