{
  "type": "Feature",
  "properties": {
    "addr:full":"2204 Cherry Ave Woodward OK 73801",
    "addr:housenumber":"2204",
    "addr:postcode":"73801",
    "addr:street":"Cherry Ave",
    "iso:country":"US",
    "sg:address":"2204 Cherry Ave",
    "sg:city":"Woodward",
    "sg:classifiers":[
        {
            "category":"Building & Trades",
            "subcategory":"Construction",
            "type":"Services"
        }
    ],
    "sg:phone":"+1 580 256 4848",
    "sg:postcode":"73801",
    "sg:province":"OK",
    "wof:name":"Alvies Backhoe Service",
    "wof:placetype":"venue"
},
  "geometry": {"coordinates":[-99.40976999999999,36.430426],"type":"Point"}
}