{
  "type": "Feature",
  "properties": {
    "addr:full":"5800 E Skelly Dr Tulsa OK 74135",
    "addr:housenumber":"5800",
    "addr:postcode":"74135",
    "addr:street":"E Skelly Dr",
    "iso:country":"US",
    "sg:address":"5800 E Skelly Dr",
    "sg:city":"Tulsa",
    "sg:classifiers":[
        {
            "category":"Banks & Credit Unions",
            "subcategory":"Bank",
            "type":"Services"
        }
    ],
    "sg:phone":"+1 918 295 6455",
    "sg:postcode":"74135",
    "sg:province":"OK",
    "sg:tags":[
        "cashing",
        "check"
    ],
    "wof:name":"ACE Cash Express",
    "wof:placetype":"venue"
},
  "geometry": {"coordinates":[-95.911756,36.102024],"type":"Point"}
}