{
  "type": "Feature",
  "properties": {
    "iso:country":"US",
    "sg:address":"300 S Ranchwood Blvd",
    "sg:city":"Yukon",
    "sg:classifiers":[
        {
            "category":"Personal",
            "subcategory":"Beauty Salon",
            "type":"Services"
        }
    ],
    "sg:phone":"+1 405 350 3331",
    "sg:postcode":"73099",
    "sg:province":"OK",
    "wof:name":"Robert James Salon",
    "wof:placetype":"venue"
},
  "geometry": {"coordinates":[-97.737718,35.506067],"type":"Point"}
}