{
  "type": "Feature",
  "properties": {
    "iso:country":"US",
    "sg:address":"231 E Choctaw Ave",
    "sg:city":"Bache",
    "sg:classifiers":[
        {
            "category":"Professional",
            "subcategory":"Accounting & Tax Preparation",
            "type":"Services"
        }
    ],
    "sg:phone":"+1 918 423 1881",
    "sg:postcode":"74501",
    "sg:province":"OK",
    "wof:name":"Walter L Bethune CPA",
    "wof:placetype":"venue"
},
  "geometry": {"coordinates":[-95.76704,34.931611],"type":"Point"}
}