{
  "type": "Feature",
  "properties": {
    "iso:country":"US",
    "sg:address":"716 Wall St",
    "sg:city":"Norman",
    "sg:classifiers":[
        {
            "category":"Health Services",
            "subcategory":"Medical Lab",
            "type":"Services"
        }
    ],
    "sg:phone":"+1 405 364 2211",
    "sg:postcode":"73069",
    "sg:province":"OK",
    "sg:tags":[
        "laboratory",
        "dental"
    ],
    "wof:name":"Tyler Weeks Dental Studio Inc",
    "wof:placetype":"venue"
},
  "geometry": {"coordinates":[-97.481718,35.226384],"type":"Point"}
}