{
  "type": "Feature",
  "properties": {
    "iso:country":"US",
    "sg:address":"4834 S 83rd East Ave",
    "sg:city":"Tulsa",
    "sg:classifiers":[
        {
            "category":"Professional",
            "subcategory":"Accounting & Tax Preparation",
            "type":"Services"
        }
    ],
    "sg:phone":"+1 918 520 3689",
    "sg:postcode":"74145",
    "sg:province":"OK",
    "sg:tags":[
        "return",
        "filing"
    ],
    "wof:name":"Tax Solution",
    "wof:placetype":"venue"
},
  "geometry": {"coordinates":[-95.88436,36.09329],"type":"Point"}
}