{
  "type": "Feature",
  "properties": {
    "iso:country":"US",
    "sg:address":"311 S 6th St",
    "sg:city":"Minco",
    "sg:classifiers":[
        {
            "category":"Education",
            "subcategory":"School",
            "type":"Public Place"
        }
    ],
    "sg:phone":"+1 405 352 4867",
    "sg:postcode":"73059",
    "sg:province":"OK",
    "wof:name":"Minco Superintendent's Office",
    "wof:placetype":"venue"
},
  "geometry": {"coordinates":[-97.949448,35.312976],"type":"Point"}
}