{
  "type": "Feature",
  "properties": {
    "iso:country":"US",
    "sg:address":"111 Park Pl",
    "sg:city":"Midwest City",
    "sg:classifiers":[
        {
            "category":"Building & Trades",
            "subcategory":"Plumbing",
            "type":"Services"
        }
    ],
    "sg:phone":"+1 405 732 6886",
    "sg:postcode":"73110",
    "sg:province":"OK",
    "sg:tags":[
        "plumbing",
        "contractor"
    ],
    "wof:name":"Chester's Plumbing Heating",
    "wof:placetype":"venue"
},
  "geometry": {"coordinates":[-97.377048,35.465397],"type":"Point"}
}