{
  "type": "Feature",
  "properties": {
    "addr:full":"1200 SE Frank Phillips Blvd Bartlesville OK 74003",
    "addr:housenumber":"1200",
    "addr:postcode":"74003",
    "addr:street":"Se Frank Phillips Blvd",
    "iso:country":"US",
    "sg:address":"1200 SE Frank Phillips Blvd",
    "sg:city":"Bartlesville",
    "sg:classifiers":[
        {
            "category":"Communications",
            "subcategory":"Radio Station",
            "type":"Services"
        }
    ],
    "sg:phone":"+1 918 336 1004",
    "sg:postcode":"74003",
    "sg:province":"OK",
    "sg:tags":[
        "company",
        "broadcasting"
    ],
    "wof:name":"KRIG",
    "wof:placetype":"venue"
},
  "geometry": {"coordinates":[-95.963882,36.750721],"type":"Point"}
}