{
  "type": "Feature",
  "properties": {
    "iso:country":"US",
    "sg:address":"311 N 1st St",
    "sg:city":"Ponca City",
    "sg:classifiers":[
        {
            "category":"Retail",
            "subcategory":"Auto Repair",
            "type":"Services"
        }
    ],
    "sg:phone":"+1 580 765 9323",
    "sg:postcode":"74601",
    "sg:province":"OK",
    "sg:tags":[
        "body"
    ],
    "wof:name":"Upholstery Shop The",
    "wof:placetype":"venue"
},
  "geometry": {"coordinates":[-97.08360500000001,36.706743],"type":"Point"}
}