{
  "type": "Feature",
  "properties": {
    "iso:country":"US",
    "sg:address":"424 Larkspur Ln",
    "sg:city":"Edmond",
    "sg:classifiers":[
        {
            "category":"Wholesale",
            "subcategory":"Machinery & Supplies",
            "type":"Manufacturing & Wholesale Goods"
        }
    ],
    "sg:phone":"+1 405 341 1462",
    "sg:postcode":"73003",
    "sg:province":"OK",
    "sg:tags":[
        "product",
        "health",
        "care"
    ],
    "wof:name":"CJ Products Intl Inc",
    "wof:placetype":"venue"
},
  "geometry": {"coordinates":[-97.490713,35.664226],"type":"Point"}
}