{
  "type": "Feature",
  "properties": {
    "addr:full":"1605 N Elm St Miami OK 74354",
    "addr:housenumber":"1605",
    "addr:postcode":"74354",
    "addr:street":"N Elm St",
    "iso:country":"US",
    "sg:address":"1605 N Elm St",
    "sg:city":"Miami",
    "sg:classifiers":[
        {
            "category":"Wholesale",
            "subcategory":"Medical Equipment & Supplies",
            "type":"Manufacturing & Wholesale Goods"
        }
    ],
    "sg:phone":"+1 918 542 7396",
    "sg:postcode":"74354",
    "sg:province":"OK",
    "sg:tags":[
        "hospital"
    ],
    "wof:name":"Brady's Home Health",
    "wof:placetype":"venue"
},
  "geometry": {"coordinates":[-94.859864,36.893713],"type":"Point"}
}