{
  "type": "Feature",
  "properties": {
    "iso:country":"US",
    "sg:address":"2316 W 3rd St",
    "sg:city":"Elk City",
    "sg:classifiers":[
        {
            "category":"Shopping",
            "subcategory":"Beauty & Cosmetics",
            "type":"Retail Goods"
        }
    ],
    "sg:phone":"+1 580 225 8710",
    "sg:postcode":"73644",
    "sg:province":"OK",
    "sg:tags":[
        "salon"
    ],
    "wof:name":"Beautyco Beauty Supply",
    "wof:placetype":"venue"
},
  "geometry": {"coordinates":[-99.433685,35.411627],"type":"Point"}
}