{
  "type": "Feature",
  "properties": {
    "iso:country":"US",
    "sg:address":"2720 N Sheridan Rd",
    "sg:city":"Tulsa",
    "sg:classifiers":[
        {
            "category":"Autos & Motor Vehicles",
            "subcategory":"Automobile Sales",
            "type":"Retail Goods"
        }
    ],
    "sg:phone":"+1 918 835 2525",
    "sg:postcode":"74115",
    "sg:province":"OK",
    "sg:tags":[
        "equipment",
        "aircraft",
        "parts",
        "supply"
    ],
    "wof:name":"Global Air Space Coatings Inc",
    "wof:placetype":"venue"
},
  "geometry": {"coordinates":[-95.90464799999999,36.196381],"type":"Point"}
}