{
  "type": "Feature",
  "properties": {
    "iso:country":"US",
    "sg:address":"6161 S Yale Ave",
    "sg:city":"Tulsa",
    "sg:classifiers":[
        {
            "category":"Organizations",
            "subcategory":"Religious Organization",
            "type":"Services"
        }
    ],
    "sg:phone":"+1 918 494 1215",
    "sg:postcode":"74136",
    "sg:province":"OK",
    "wof:name":"Religious Sisters of Mercy",
    "wof:placetype":"venue"
},
  "geometry": {"coordinates":[-95.92207399999999,36.07488],"type":"Point"}
}