{
  "type": "Feature",
  "properties": {
    "addr:full":"4406 S Memorial Dr Tulsa OK 74145",
    "addr:housenumber":"4406",
    "addr:postcode":"74145",
    "addr:street":"S Memorial Dr",
    "iso:country":"US",
    "sg:address":"4406 S Memorial Dr",
    "sg:city":"Tulsa",
    "sg:classifiers":[
        {
            "category":"Retail",
            "subcategory":"Auto Rental",
            "type":"Services"
        }
    ],
    "sg:phone":"+1 918 627 5516",
    "sg:postcode":"74145",
    "sg:province":"OK",
    "sg:tags":[
        "car",
        "truck"
    ],
    "sg:website":"http://clickserve.dartsearch.net/link/click?lid=43000000357776038",
    "wof:name":"Hertz Rent-A-Car",
    "wof:placetype":"venue"
},
  "geometry": {"coordinates":[-95.886619,36.099392],"type":"Point"}
}