{
  "type": "Feature",
  "properties": {
    "iso:country":"US",
    "sg:address":"110 E Main St",
    "sg:city":"Ada",
    "sg:classifiers":[
        {
            "category":"Banks & Credit Unions",
            "subcategory":"Bank",
            "type":"Services"
        }
    ],
    "sg:phone":"+1 580 235 0002",
    "sg:postcode":"74820",
    "sg:province":"OK",
    "sg:tags":[
        "loan"
    ],
    "wof:name":"Capital Advance",
    "wof:placetype":"venue"
},
  "geometry": {"coordinates":[-96.678759,34.774572],"type":"Point"}
}