{
  "type": "Feature",
  "properties": {
    "addr:full":"638 N 6th St Clinton OK 73601",
    "addr:housenumber":"638",
    "addr:postcode":"73601",
    "addr:street":"N 6Th St",
    "iso:country":"US",
    "sg:address":"638 N 6th St",
    "sg:city":"Clinton",
    "sg:classifiers":[
        {
            "category":"Manufacturing",
            "subcategory":"Glass & Minerals",
            "type":"Manufacturing & Wholesale Goods"
        }
    ],
    "sg:phone":"+1 580 323 7513",
    "sg:postcode":"73601",
    "sg:province":"OK",
    "sg:tags":[
        "cut",
        "merchandise",
        "mfg"
    ],
    "wof:name":"Nicholson Monument Co",
    "wof:placetype":"venue"
},
  "geometry": {"coordinates":[-98.96726700000001,35.520419],"type":"Point"}
}