{
  "type": "Feature",
  "properties": {
    "iso:country":"US",
    "sg:address":"1506 N Harrison Ave",
    "sg:city":"Shawnee",
    "sg:classifiers":[
        {
            "category":"Autos & Motor Vehicles",
            "subcategory":"Automobile Sales",
            "type":"Retail Goods"
        }
    ],
    "sg:phone":"+1 405 273 5678",
    "sg:postcode":"74804",
    "sg:province":"OK",
    "sg:tags":[
        "boat"
    ],
    "wof:name":"Boaties",
    "wof:placetype":"venue"
},
  "geometry": {"coordinates":[-96.912146,35.348104],"type":"Point"}
}