{
  "type": "Feature",
  "properties": {
    "iso:country":"US",
    "sg:address":"3515 Dawson Rd",
    "sg:city":"Tulsa",
    "sg:classifiers":[
        {
            "category":"Manufacturing",
            "subcategory":"Metals",
            "type":"Manufacturing & Wholesale Goods"
        }
    ],
    "sg:phone":"+1 918 834 2200",
    "sg:postcode":"74115",
    "sg:province":"OK",
    "sg:tags":[
        "steel"
    ],
    "sg:website":"www.hemphillbts.com",
    "wof:name":"Hemphill Corp",
    "wof:placetype":"venue"
},
  "geometry": {"coordinates":[-95.938979,36.175293],"type":"Point"}
}