{
  "type": "Feature",
  "properties": {
    "iso:country":"US",
    "sg:address":"13204 N Macarthur Blvd",
    "sg:city":"Oklahoma City",
    "sg:classifiers":[
        {
            "category":"Professional",
            "subcategory":"Accounting & Tax Preparation",
            "type":"Services"
        }
    ],
    "sg:phone":"+1 405 720 3115",
    "sg:postcode":"73142",
    "sg:province":"OK",
    "wof:name":"Compusource Business Svcs Corp",
    "wof:placetype":"venue"
},
  "geometry": {"coordinates":[-97.620672,35.604509],"type":"Point"}
}