{
  "type": "Feature",
  "properties": {
    "addr:full":"1200 Hwy 9 E Seminole OK 74868",
    "addr:housenumber":"1200",
    "addr:postcode":"74868",
    "addr:street":"Hwy 9 E",
    "iso:country":"US",
    "sg:address":"1200 Hwy 9 E",
    "sg:city":"Seminole",
    "sg:classifiers":[
        {
            "category":"Real Estate",
            "subcategory":"Real Estate Operator",
            "type":"Services"
        }
    ],
    "sg:phone":"+1 405 382 1127",
    "sg:postcode":"74868",
    "sg:province":"OK",
    "sg:tags":[
        "building",
        "apartment"
    ],
    "wof:name":"Seminole Estates Apts",
    "wof:placetype":"venue"
},
  "geometry": {"coordinates":[-96.65817800000001,35.246662],"type":"Point"}
}