{
  "type": "Feature",
  "properties": {
    "iso:country":"US",
    "sg:address":"8838 E 77th Pl",
    "sg:city":"Tulsa",
    "sg:classifiers":[
        {
            "category":"Building & Trades",
            "subcategory":"Cleaning & Sanitation",
            "type":"Services"
        }
    ],
    "sg:phone":"+1 918 307 0330",
    "sg:postcode":"74133",
    "sg:province":"OK",
    "sg:tags":[
        "ceiling",
        "commercial"
    ],
    "wof:name":"D & D Interiors Inc",
    "wof:placetype":"venue"
},
  "geometry": {"coordinates":[-95.876701,36.051939],"type":"Point"}
}