{
  "type": "Feature",
  "properties": {
    "iso:country":"US",
    "sg:address":"4444 N Classen Blvd",
    "sg:city":"Oklahoma City",
    "sg:classifiers":[
        {
            "category":"Professional",
            "subcategory":"Accounting & Tax Preparation",
            "type":"Services"
        }
    ],
    "sg:phone":"+1 405 842 1120",
    "sg:postcode":"73118",
    "sg:province":"OK",
    "wof:name":"Buxton & Cloud PC",
    "wof:placetype":"venue"
},
  "geometry": {"coordinates":[-97.534159,35.516504],"type":"Point"}
}