{
  "type": "Feature",
  "properties": {
    "iso:country":"US",
    "sg:address":"11333 E 21st St",
    "sg:city":"Tulsa",
    "sg:classifiers":[
        {
            "category":"Banks & Credit Unions",
            "subcategory":"Bank",
            "type":"Services"
        }
    ],
    "sg:phone":"+1 918 437 4900",
    "sg:postcode":"74129",
    "sg:province":"OK",
    "sg:tags":[
        "loan"
    ],
    "wof:name":"Money Time Check Cashers",
    "wof:placetype":"venue"
},
  "geometry": {"coordinates":[-95.849889,36.133531],"type":"Point"}
}