{
  "type": "Feature",
  "properties": {
    "iso:country":"US",
    "sg:address":"412 Spencer St",
    "sg:city":"Chouteau",
    "sg:classifiers":[
        {
            "category":"Freight",
            "type":"Transportation"
        }
    ],
    "sg:phone":"+1 918 476 6279",
    "sg:postcode":"74337",
    "sg:province":"OK",
    "sg:tags":[
        "trucking"
    ],
    "wof:name":"Burrow Trucking Inc",
    "wof:placetype":"venue"
},
  "geometry": {"coordinates":[-95.352935,36.191182],"type":"Point"}
}