{
  "type": "Feature",
  "properties": {
    "iso:country":"US",
    "sg:address":"2917 E Waterloo Rd",
    "sg:city":"Edmond",
    "sg:classifiers":[
        {
            "category":"Building & Trades",
            "subcategory":"Electrical",
            "type":"Services"
        }
    ],
    "sg:phone":"+1 405 341 6908",
    "sg:postcode":"73034",
    "sg:province":"OK",
    "sg:tags":[
        "electric",
        "contractor"
    ],
    "wof:name":"Bill Mc Gee Electric",
    "wof:placetype":"venue"
},
  "geometry": {"coordinates":[-97.387956,35.725343],"type":"Point"}
}