{
  "type": "Feature",
  "properties": {
    "iso:country":"US",
    "sg:address":"615 Marietta Ave",
    "sg:city":"Muskogee",
    "sg:classifiers":[
        {
            "category":"Building & Trades",
            "subcategory":"Construction",
            "type":"Services"
        }
    ],
    "sg:phone":"+1 918 683 9282",
    "sg:postcode":"74401",
    "sg:province":"OK",
    "sg:tags":[
        "concrete",
        "contractor"
    ],
    "wof:name":"A-Plus Concrete",
    "wof:placetype":"venue"
},
  "geometry": {"coordinates":[-95.38556199999999,35.734408],"type":"Point"}
}