{
  "type": "Feature",
  "properties": {
    "addr:full":"115 E Broadway St Drumright OK 74030",
    "addr:housenumber":"115",
    "addr:postcode":"74030",
    "addr:street":"E Broadway St",
    "iso:country":"US",
    "sg:address":"115 E Broadway St",
    "sg:city":"Drumright",
    "sg:classifiers":[
        {
            "category":"Health Services",
            "subcategory":"Health Practitioner",
            "type":"Services"
        }
    ],
    "sg:phone":"+1 918 352 3838",
    "sg:postcode":"74030",
    "sg:province":"OK",
    "wof:name":"Green Country Physical Therapy",
    "wof:placetype":"venue"
},
  "geometry": {"coordinates":[-96.601421,35.988546],"type":"Point"}
}