{
  "type": "Feature",
  "properties": {
    "iso:country":"US",
    "sg:address":"615 Lake Murray Dr E",
    "sg:city":"Ardmore",
    "sg:classifiers":[
        {
            "category":"Building & Trades",
            "subcategory":"Construction",
            "type":"Services"
        }
    ],
    "sg:phone":"+1 580 223 8580",
    "sg:postcode":"73401",
    "sg:province":"OK",
    "sg:tags":[
        "concrete",
        "contractor"
    ],
    "wof:name":"Collins Rocky Concrete Cnstr",
    "wof:placetype":"venue"
},
  "geometry": {"coordinates":[-97.12303300000001,34.163107],"type":"Point"}
}