{
  "type": "Feature",
  "properties": {
    "iso:country":"US",
    "sg:address":"1424 S Harvard Ave",
    "sg:city":"Tulsa",
    "sg:classifiers":[
        {
            "category":"Building & Trades",
            "subcategory":"Construction",
            "type":"Services"
        }
    ],
    "sg:phone":"+1 918 749 7904",
    "sg:postcode":"74112",
    "sg:province":"OK",
    "sg:tags":[
        "residential",
        "general",
        "commercial",
        "contractor"
    ],
    "wof:name":"Barron & Mc Clary Gen Contrs",
    "wof:placetype":"venue"
},
  "geometry": {"coordinates":[-95.940398,36.140999],"type":"Point"}
}