{
  "type": "Feature",
  "properties": {
    "addr:full":"424 E Warner Ave Guthrie OK 73044",
    "addr:housenumber":"424",
    "addr:postcode":"73044",
    "addr:street":"E Warner Ave",
    "iso:country":"US",
    "sg:address":"424 E Warner Ave",
    "sg:city":"Guthrie",
    "sg:classifiers":[
        {
            "category":"Organizations",
            "subcategory":"Religious Organization",
            "type":"Services"
        }
    ],
    "sg:phone":"+1 405 282 3914",
    "sg:postcode":"73044",
    "sg:province":"OK",
    "sg:tags":[
        "church"
    ],
    "wof:name":"Zion Lutheran Church",
    "wof:placetype":"venue"
},
  "geometry": {"coordinates":[-97.421201,35.881242],"type":"Point"}
}