{
  "type": "Feature",
  "properties": {
    "iso:country":"US",
    "sg:address":"3256 Delmar Rd",
    "sg:city":"Oklahoma City",
    "sg:classifiers":[
        {
            "category":"Retail",
            "subcategory":"Auto Repair",
            "type":"Services"
        }
    ],
    "sg:phone":"+1 405 672 4549",
    "sg:postcode":"73115",
    "sg:province":"OK",
    "sg:tags":[
        "repairing",
        "automobile",
        "general"
    ],
    "wof:name":"Romo's Auto Repair",
    "wof:placetype":"venue"
},
  "geometry": {"coordinates":[-97.453746,35.456466],"type":"Point"}
}