{
  "type": "Feature",
  "properties": {
    "addr:full":"13160 S Memorial Dr Bixby OK 74008",
    "addr:housenumber":"13160",
    "addr:postcode":"74008",
    "addr:street":"S Memorial Dr",
    "iso:country":"US",
    "sg:address":"13160 S Memorial Dr",
    "sg:city":"Bixby",
    "sg:classifiers":[
        {
            "category":"Manufacturing",
            "subcategory":"Signs",
            "type":"Manufacturing & Wholesale Goods"
        }
    ],
    "sg:phone":"+1 918 369 8778",
    "sg:postcode":"74008",
    "sg:province":"OK",
    "sg:tags":[
        "advertising",
        "specialty"
    ],
    "wof:name":"Signs & Graphix Inc South",
    "wof:placetype":"venue"
},
  "geometry": {"coordinates":[-95.88666499999999,35.972956],"type":"Point"}
}