{
  "type": "Feature",
  "properties": {
    "addr:full":"116 S Broadway Edmond OK 73034",
    "addr:housenumber":"116",
    "addr:postcode":"73034",
    "addr:street":"S Broadway",
    "iso:country":"US",
    "sg:address":"116 S Broadway",
    "sg:city":"Edmond",
    "sg:classifiers":[
        {
            "category":"Banks & Credit Unions",
            "subcategory":"Investment Brokerage",
            "type":"Services"
        }
    ],
    "sg:phone":"+1 405 330 3930",
    "sg:postcode":"73034",
    "sg:province":"OK",
    "sg:tags":[
        "security"
    ],
    "wof:name":"Edward Jones Co",
    "wof:placetype":"venue"
},
  "geometry": {"coordinates":[-97.48138299999999,35.653694],"type":"Point"}
}