{
  "type": "Feature",
  "properties": {
    "addr:full":"7420 Nichols Rd Oklahoma City OK 73120",
    "addr:housenumber":"7420",
    "addr:postcode":"73120",
    "addr:street":"Nichols Rd",
    "iso:country":"US",
    "sg:address":"7420 Nichols Rd",
    "sg:city":"Oklahoma City",
    "sg:classifiers":[
        {
            "category":"Shopping",
            "subcategory":"Florist",
            "type":"Retail Goods"
        }
    ],
    "sg:phone":"+1 405 842 5461",
    "sg:postcode":"73120",
    "sg:province":"OK",
    "wof:name":"Abacus Enterprizes",
    "wof:placetype":"venue"
},
  "geometry": {"coordinates":[-97.54487399999999,35.558914],"type":"Point"}
}