{
  "type": "Feature",
  "properties": {
    "iso:country":"US",
    "sg:address":"124 W Cleveland Ave",
    "sg:city":"Guthrie",
    "sg:classifiers":[
        {
            "category":"Shopping",
            "subcategory":"Gifts & Souvenirs",
            "type":"Retail Goods"
        }
    ],
    "sg:phone":"+1 405 282 7117",
    "sg:postcode":"73044",
    "sg:province":"OK",
    "sg:tags":[
        "shop"
    ],
    "wof:name":"Blessings Made In Ok",
    "wof:placetype":"venue"
},
  "geometry": {"coordinates":[-97.426271,35.879148],"type":"Point"}
}