{
  "type": "Feature",
  "properties": {
    "iso:country":"US",
    "sg:address":"12424 N Macarthur Blvd",
    "sg:city":"Oklahoma City",
    "sg:classifiers":[
        {
            "category":"Professional",
            "subcategory":"Accounting & Tax Preparation",
            "type":"Services"
        }
    ],
    "sg:phone":"+1 405 728 1040",
    "sg:postcode":"73142",
    "sg:province":"OK",
    "sg:tags":[
        "return"
    ],
    "wof:name":"Tax Guy",
    "wof:placetype":"venue"
},
  "geometry": {"coordinates":[-97.62062400000001,35.596277],"type":"Point"}
}