{
  "type": "Feature",
  "properties": {
    "addr:full":"2211 Westpark Dr Norman OK 73069",
    "addr:housenumber":"2211",
    "addr:postcode":"73069",
    "addr:street":"Westpark Dr",
    "iso:country":"US",
    "sg:address":"2211 Westpark Dr",
    "sg:city":"Norman",
    "sg:classifiers":[
        {
            "category":"Farming",
            "subcategory":"Nursery",
            "type":"Manufacturing & Wholesale Goods"
        }
    ],
    "sg:phone":"+1 405 364 7511",
    "sg:postcode":"73069",
    "sg:province":"OK",
    "sg:tags":[
        "farm",
        "sod"
    ],
    "wof:name":"Bentley Turf Farms Inc",
    "wof:placetype":"venue"
},
  "geometry": {"coordinates":[-97.475066,35.20934],"type":"Point"}
}