{
  "type": "Feature",
  "properties": {
    "addr:full":"7136 S Yale Ave Tulsa OK 74136",
    "addr:housenumber":"7136",
    "addr:postcode":"74136",
    "addr:street":"S Yale Ave",
    "iso:country":"US",
    "sg:address":"7136 S Yale Ave",
    "sg:city":"Tulsa",
    "sg:classifiers":[
        {
            "category":"Wholesale",
            "subcategory":"Office Equipment",
            "type":"Manufacturing & Wholesale Goods"
        },
        {
            "category":"Shopping",
            "subcategory":"Computers & Home Electronics",
            "type":"Retail Goods"
        },
        {
            "category":"Home & Garden",
            "subcategory":"Furniture",
            "type":"Retail Goods"
        }
    ],
    "sg:phone":"+1 918 497 1731",
    "sg:postcode":"74136",
    "sg:province":"OK",
    "sg:tags":[
        "store",
        "typewriter"
    ],
    "wof:name":"Core Office Furniture",
    "wof:placetype":"venue"
},
  "geometry": {"coordinates":[-95.92221499999999,36.060256],"type":"Point"}
}