{
  "type": "Feature",
  "properties": {
    "iso:country":"US",
    "sg:address":"802 W Rogers Blvd",
    "sg:city":"Skiatook",
    "sg:classifiers":[
        {
            "category":"Shopping",
            "subcategory":"Used Merchandise",
            "type":"Retail Goods"
        }
    ],
    "sg:phone":"+1 918 396 3838",
    "sg:postcode":"74070",
    "sg:province":"OK",
    "sg:tags":[
        "shop",
        "consignment"
    ],
    "wof:name":"Top Rack",
    "wof:placetype":"venue"
},
  "geometry": {"coordinates":[-96.010871,36.368504],"type":"Point"}
}