{
  "type": "Feature",
  "properties": {
    "iso:country":"US",
    "sg:address":"7666 E 61st St",
    "sg:city":"Tulsa",
    "sg:classifiers":[
        {
            "category":"Professional",
            "subcategory":"Lawyer & Legal Services",
            "type":"Services"
        }
    ],
    "sg:phone":"+1 918 254 1521",
    "sg:postcode":"74133",
    "sg:province":"OK",
    "sg:tags":[
        "attorney"
    ],
    "wof:name":"Hogue & Ross Inc Attys",
    "wof:placetype":"venue"
},
  "geometry": {"coordinates":[-95.889979,36.075313],"type":"Point"}
}