{
  "type": "Feature",
  "properties": {
    "iso:country":"US",
    "sg:address":"7819 E Admiral Pl",
    "sg:city":"Tulsa",
    "sg:classifiers":[
        {
            "category":"Restaurant",
            "type":"Food & Drink"
        }
    ],
    "sg:phone":"+1 918 834 6635",
    "sg:postcode":"74115",
    "sg:province":"OK",
    "sg:tags":[
        "eating"
    ],
    "sg:website":"www.panchosmexicanbuffet.com",
    "wof:name":"Pancho's Mexican Buffet Inc",
    "wof:placetype":"venue"
},
  "geometry": {"coordinates":[-95.888276,36.160777],"type":"Point"}
}