{
  "type": "Feature",
  "properties": {
    "iso:country":"US",
    "sg:address":"1203 SE Quincy St",
    "sg:city":"Idabel",
    "sg:classifiers":[
        {
            "category":"Education",
            "subcategory":"School",
            "type":"Public Place"
        }
    ],
    "sg:phone":"+1 580 286 3056",
    "sg:postcode":"74745",
    "sg:province":"OK",
    "wof:name":"Idabel Even Start",
    "wof:placetype":"venue"
},
  "geometry": {"coordinates":[-94.81445,33.890034],"type":"Point"}
}