{
  "type": "Feature",
  "properties": {
    "iso:country":"US",
    "sg:address":"12201 N Rockwell Ave",
    "sg:city":"Oklahoma City",
    "sg:classifiers":[
        {
            "category":"Restaurant",
            "type":"Food & Drink"
        }
    ],
    "sg:phone":"+1 405 722 5001",
    "sg:postcode":"73162",
    "sg:province":"OK",
    "sg:tags":[
        "eating"
    ],
    "wof:name":"Burger King",
    "wof:placetype":"venue"
},
  "geometry": {"coordinates":[-97.638535,35.592959],"type":"Point"}
}