{
  "type": "Feature",
  "properties": {
    "iso:country":"US",
    "sg:address":"509 NW 4th St",
    "sg:city":"Checotah",
    "sg:classifiers":[
        {
            "category":"Building & Trades",
            "subcategory":"Construction",
            "type":"Services"
        }
    ],
    "sg:phone":"+1 918 473 4826",
    "sg:postcode":"74426",
    "sg:province":"OK",
    "sg:tags":[
        "layer",
        "contractor",
        "laying",
        "floor",
        "carpet"
    ],
    "wof:name":"Carl Hornbeak Carpet Installat",
    "wof:placetype":"venue"
},
  "geometry": {"coordinates":[-95.526035,35.476474],"type":"Point"}
}