{
  "type": "Feature",
  "properties": {
    "addr:full":"6853 S Canton Ave Tulsa OK 74136",
    "addr:housenumber":"6853",
    "addr:postcode":"74136",
    "addr:street":"S Canton Ave",
    "iso:country":"US",
    "sg:address":"6853 S Canton Ave",
    "sg:city":"Tulsa",
    "sg:classifiers":[
        {
            "category":"Social Services",
            "type":"Services"
        }
    ],
    "sg:phone":"+1 918 496 8050",
    "sg:postcode":"74136",
    "sg:province":"OK",
    "sg:tags":[
        "health"
    ],
    "wof:name":"Fritz Jeri",
    "wof:placetype":"venue"
},
  "geometry": {"coordinates":[-95.918757,36.063842],"type":"Point"}
}