{
  "type": "Feature",
  "properties": {
    "iso:country":"US",
    "sg:address":"12036 N Pennsylvania Ave",
    "sg:city":"Oklahoma City",
    "sg:classifiers":[
        {
            "category":"Utilities",
            "subcategory":"Mobile Phone",
            "type":"Services"
        }
    ],
    "sg:phone":"+1 405 748 7100",
    "sg:postcode":"73120",
    "sg:province":"OK",
    "sg:tags":[
        "communication",
        "radio",
        "telephone"
    ],
    "wof:name":"Nextel",
    "wof:placetype":"venue"
},
  "geometry": {"coordinates":[-97.549285,35.591204],"type":"Point"}
}