{
  "type": "Feature",
  "properties": {
    "addr:full":"6827 S Peoria Ave Tulsa OK 74136",
    "addr:housenumber":"6827",
    "addr:postcode":"74136",
    "addr:street":"S Peoria Ave",
    "iso:country":"US",
    "sg:address":"6827 S Peoria Ave",
    "sg:city":"Tulsa",
    "sg:classifiers":[
        {
            "category":"Shopping",
            "type":"Retail Goods"
        },
        {
            "category":"Manufacturing",
            "subcategory":"Food",
            "type":"Manufacturing & Wholesale Goods"
        }
    ],
    "sg:phone":"+1 918 492 1138",
    "sg:postcode":"74136",
    "sg:province":"OK",
    "sg:tags":[
        "canned",
        "mexican",
        "specialty",
        "mfg"
    ],
    "wof:name":"El Mojado",
    "wof:placetype":"venue"
},
  "geometry": {"coordinates":[-95.976208,36.062728],"type":"Point"}
}