{
  "type": "Feature",
  "properties": {
    "iso:country":"US",
    "sg:address":"3542 E 51st St",
    "sg:city":"Tulsa",
    "sg:classifiers":[
        {
            "category":"Shopping",
            "subcategory":"Pharmacy",
            "type":"Retail Goods"
        }
    ],
    "sg:phone":"+1 918 610 8285",
    "sg:postcode":"74135",
    "sg:province":"OK",
    "sg:tags":[
        "aid",
        "first",
        "supply"
    ],
    "wof:name":"Zee Medical",
    "wof:placetype":"venue"
},
  "geometry": {"coordinates":[-95.935803,36.112325],"type":"Point"}
}