{
  "type": "Feature",
  "properties": {
    "iso:country":"US",
    "sg:address":"704 Chateau Ave",
    "sg:city":"Yukon",
    "sg:classifiers":[
        {
            "category":"Professional",
            "subcategory":"Management & Consulting",
            "type":"Services"
        }
    ],
    "sg:phone":"+1 405 354 4609",
    "sg:postcode":"73099",
    "sg:province":"OK",
    "sg:tags":[
        "business"
    ],
    "wof:name":"Eb Consulting Inc",
    "wof:placetype":"venue"
},
  "geometry": {"coordinates":[-97.770347,35.4975],"type":"Point"}
}