{
  "type": "Feature",
  "properties": {
    "iso:country":"US",
    "sg:address":"702 E Trudgeon St",
    "sg:city":"Henryetta",
    "sg:classifiers":[
        {
            "category":"Restaurant",
            "type":"Food & Drink"
        }
    ],
    "sg:phone":"+1 918 652 8000",
    "sg:postcode":"74437",
    "sg:province":"OK",
    "wof:name":"New China Restaurant",
    "wof:placetype":"venue"
},
  "geometry": {"coordinates":[-95.973285,35.440979],"type":"Point"}
}