{
  "type": "Feature",
  "properties": {
    "iso:country":"US",
    "sg:address":"2224 US Hwy 64",
    "sg:city":"Guymon",
    "sg:classifiers":[
        {
            "category":"Utilities",
            "subcategory":"Telephone",
            "type":"Services"
        }
    ],
    "sg:phone":"+1 580 338 7525",
    "sg:postcode":"73942",
    "sg:province":"OK",
    "sg:tags":[
        "company"
    ],
    "wof:name":"PTSI Answering Svc",
    "wof:placetype":"venue"
},
  "geometry": {"coordinates":[-101.484613,36.702615],"type":"Point"}
}