{
  "type": "Feature",
  "properties": {
    "iso:country":"US",
    "sg:address":"1501 Apollo Rd",
    "sg:city":"Edmond",
    "sg:classifiers":[
        {
            "category":"Organizations",
            "subcategory":"Community Association",
            "type":"Services"
        }
    ],
    "sg:phone":"+1 405 340 8246",
    "sg:postcode":"73003",
    "sg:province":"OK",
    "wof:name":"Delta Kappa Gamma Society",
    "wof:placetype":"venue"
},
  "geometry": {"coordinates":[-97.50486600000001,35.645103],"type":"Point"}
}