{
  "type": "Feature",
  "properties": {
    "addr:full":"351 N Air Depot Blvd Oklahoma City OK 73110",
    "addr:housenumber":"351",
    "addr:postcode":"73110",
    "addr:street":"N Air Depot Blvd",
    "iso:country":"US",
    "sg:address":"351 N Air Depot Blvd",
    "sg:city":"Oklahoma City",
    "sg:classifiers":[
        {
            "category":"Banks & Credit Unions",
            "subcategory":"Bank",
            "type":"Services"
        }
    ],
    "sg:phone":"+1 405 741 1495",
    "sg:postcode":"73110",
    "sg:province":"OK",
    "sg:tags":[
        "loan",
        "real estate"
    ],
    "wof:name":"Wells Fargo Financial Accptnce",
    "wof:placetype":"venue"
},
  "geometry": {"coordinates":[-97.40630400000001,35.467793],"type":"Point"}
}