{
  "type": "Feature",
  "properties": {
    "iso:country":"US",
    "sg:address":"1836 NE 54th St",
    "sg:city":"Oklahoma City",
    "sg:classifiers":[
        {
            "category":"Building & Trades",
            "subcategory":"Cleaning & Sanitation",
            "type":"Services"
        }
    ],
    "sg:phone":"+1 405 427 2146",
    "sg:postcode":"73111",
    "sg:province":"OK",
    "sg:tags":[
        "janitor"
    ],
    "wof:name":"Mike Turner's Janitorial Svc",
    "wof:placetype":"venue"
},
  "geometry": {"coordinates":[-97.479582,35.525519],"type":"Point"}
}