{
  "type": "Feature",
  "properties": {
    "addr:full":"3608 N Ridgewood Dr Oklahoma City OK 73110",
    "addr:housenumber":"3608",
    "addr:postcode":"73110",
    "addr:street":"N Ridgewood Dr",
    "iso:country":"US",
    "sg:address":"3608 N Ridgewood Dr",
    "sg:city":"Oklahoma City",
    "sg:classifiers":[
        {
            "category":"Banks & Credit Unions",
            "subcategory":"Bank",
            "type":"Services"
        }
    ],
    "sg:phone":"+1 405 732 2791",
    "sg:postcode":"73110",
    "sg:province":"OK",
    "sg:tags":[
        "broker",
        "mortgage"
    ],
    "wof:name":"JMB Mortgage Company",
    "wof:placetype":"venue"
},
  "geometry": {"coordinates":[-97.403947,35.478456],"type":"Point"}
}