{
  "type": "Feature",
  "properties": {
    "addr:full":"307 SW Lee Blvd Lawton OK 73501",
    "addr:housenumber":"307",
    "addr:postcode":"73501",
    "addr:street":"Sw Lee Blvd",
    "iso:country":"US",
    "sg:address":"307 SW Lee Blvd",
    "sg:city":"Lawton",
    "sg:classifiers":[
        {
            "category":"Restaurant",
            "type":"Food & Drink"
        }
    ],
    "sg:menulink":"http://www.allmenus.com/ok/lawton/199348-sonic/menu/",
    "sg:phone":"+1 580 357 4906",
    "sg:postcode":"73501",
    "sg:province":"OK",
    "sg:tags":[
        "burger",
        "american"
    ],
    "wof:name":"Sonic",
    "wof:placetype":"venue"
},
  "geometry": {"coordinates":[-98.392124,34.59436],"type":"Point"}
}