{
  "type": "Feature",
  "properties": {
    "iso:country":"US",
    "sg:address":"2109 S Sheridan Rd",
    "sg:city":"Tulsa",
    "sg:classifiers":[
        {
            "category":"Autos & Motor Vehicles",
            "subcategory":"Fuel & Gas Station",
            "type":"Retail Goods"
        }
    ],
    "sg:phone":"+1 918 834 9709",
    "sg:postcode":"74129",
    "sg:province":"OK",
    "sg:tags":[
        "oil"
    ],
    "wof:name":"Texaco Self Svc",
    "wof:placetype":"venue"
},
  "geometry": {"coordinates":[-95.904523,36.131784],"type":"Point"}
}