{
  "type": "Feature",
  "properties": {
    "iso:country":"US",
    "sg:address":"519 E Wyandotte Ave",
    "sg:city":"Bache",
    "sg:classifiers":[
        {
            "category":"Restaurant",
            "type":"Food & Drink"
        }
    ],
    "sg:phone":"+1 918 426 9600",
    "sg:postcode":"74501",
    "sg:province":"OK",
    "sg:tags":[
        "eating"
    ],
    "wof:name":"Harbor Mountain Coffe House",
    "wof:placetype":"venue"
},
  "geometry": {"coordinates":[-95.7642,34.927725],"type":"Point"}
}