{
  "type": "Feature",
  "properties": {
    "addr:full":"1404 S Lewis Ave Unit Hm Tulsa OK 74104",
    "addr:housenumber":"1404",
    "addr:postcode":"74104",
    "addr:street":"S Lewis Ave Unit",
    "iso:country":"US",
    "sg:address":"1404 S Lewis Ave Unit Hm",
    "sg:city":"Tulsa",
    "sg:classifiers":[
        {
            "category":"Structure",
            "subcategory":"Office Building",
            "type":"Public Place"
        }
    ],
    "sg:phone":"+1 918 747 2972",
    "sg:postcode":"74104",
    "sg:province":"OK",
    "sg:tags":[
        "park"
    ],
    "wof:name":"University Properties",
    "wof:placetype":"venue"
},
  "geometry": {"coordinates":[-95.95829000000001,36.142021],"type":"Point"}
}