{
  "type": "Feature",
  "properties": {
    "iso:country":"US",
    "sg:address":"1310 Key Rd",
    "sg:city":"Mcalester",
    "sg:classifiers":[
        {
            "category":"Building & Trades",
            "subcategory":"Construction",
            "type":"Services"
        }
    ],
    "sg:phone":"+1 918 423 2205",
    "sg:postcode":"74501",
    "sg:province":"OK",
    "sg:tags":[
        "siding",
        "contractor"
    ],
    "wof:name":"Clagg Siding & Windows",
    "wof:placetype":"venue"
},
  "geometry": {"coordinates":[-95.749803,35.036116],"type":"Point"}
}