{
  "type": "Feature",
  "properties": {
    "addr:full":"3034 NW 160th St Edmond OK 73013",
    "addr:housenumber":"3034",
    "addr:postcode":"73013",
    "addr:street":"Nw 160Th St",
    "iso:country":"US",
    "sg:address":"3034 NW 160th St",
    "sg:city":"Edmond",
    "sg:classifiers":[
        {
            "category":"Wholesale",
            "subcategory":"Non-durable Goods",
            "type":"Manufacturing & Wholesale Goods"
        }
    ],
    "sg:phone":"+1 405 348 8819",
    "sg:postcode":"73013",
    "sg:province":"OK",
    "wof:name":"Bailey & 39 S Trading Co",
    "wof:placetype":"venue"
},
  "geometry": {"coordinates":[-97.568139,35.631985],"type":"Point"}
}