{
  "type": "Feature",
  "properties": {
    "iso:country":"US",
    "sg:address":"1016 W Cherokee Ave",
    "sg:city":"Sallisaw",
    "sg:classifiers":[
        {
            "category":"Banks & Credit Unions",
            "subcategory":"Bank",
            "type":"Services"
        }
    ],
    "sg:phone":"+1 918 775 6271",
    "sg:postcode":"74955",
    "sg:province":"OK",
    "sg:tags":[
        "personal",
        "loan",
        "institution"
    ],
    "wof:name":"Convenient Loan Co",
    "wof:placetype":"venue"
},
  "geometry": {"coordinates":[-94.802442,35.459845],"type":"Point"}
}