{
  "type": "Feature",
  "properties": {
    "iso:country":"US",
    "sg:address":"301 E Kings Rd",
    "sg:city":"Ada",
    "sg:classifiers":[
        {
            "category":"Organizations",
            "subcategory":"Religious Organization",
            "type":"Services"
        }
    ],
    "sg:phone":"+1 580 332 3073",
    "sg:postcode":"74820",
    "sg:province":"OK",
    "sg:tags":[
        "church"
    ],
    "wof:name":"First Presbyterian Church",
    "wof:placetype":"venue"
},
  "geometry": {"coordinates":[-96.676716,34.759862],"type":"Point"}
}