{
  "type": "Feature",
  "properties": {
    "addr:full":"241 E 46th St N Tulsa OK 74126",
    "addr:housenumber":"241",
    "addr:postcode":"74126",
    "addr:street":"E 46Th St N",
    "iso:country":"US",
    "sg:address":"241 E 46th St N",
    "sg:city":"Tulsa",
    "sg:classifiers":[
        {
            "category":"Personal",
            "subcategory":"Beauty Salon",
            "type":"Services"
        }
    ],
    "sg:phone":"+1 918 425 4600",
    "sg:postcode":"74126",
    "sg:province":"OK",
    "wof:name":"Ultimate Experience Salon",
    "wof:placetype":"venue"
},
  "geometry": {"coordinates":[-95.991874,36.220569],"type":"Point"}
}