{
  "type": "Feature",
  "properties": {
    "iso:country":"US",
    "sg:address":"1400 Bryan Dr",
    "sg:city":"Durant",
    "sg:classifiers":[
        {
            "category":"Building & Trades",
            "subcategory":"Equipment Rental",
            "type":"Services"
        }
    ],
    "sg:phone":"+1 580 924 0290",
    "sg:postcode":"74701",
    "sg:province":"OK",
    "sg:tags":[
        "medical",
        "lease"
    ],
    "wof:name":"Durant Medical Supply Inc",
    "wof:placetype":"venue"
},
  "geometry": {"coordinates":[-96.398382,34.005673],"type":"Point"}
}