{
  "type": "Feature",
  "properties": {
    "addr:full":"7940 E 41st St Tulsa OK 74145",
    "addr:housenumber":"7940",
    "addr:postcode":"74145",
    "addr:street":"E 41St St",
    "iso:country":"US",
    "sg:address":"7940 E 41st St",
    "sg:city":"Tulsa",
    "sg:classifiers":[
        {
            "category":"Personal",
            "subcategory":"Beauty Salon",
            "type":"Services"
        }
    ],
    "sg:phone":"+1 918 828 9822",
    "sg:postcode":"74145",
    "sg:province":"OK",
    "sg:tags":[
        "shop"
    ],
    "wof:name":"All About Nails",
    "wof:placetype":"venue"
},
  "geometry": {"coordinates":[-95.886968,36.104347],"type":"Point"}
}