{
  "type": "Feature",
  "properties": {
    "iso:country":"US",
    "sg:address":"5909 Chestnut Ct",
    "sg:city":"Edmond",
    "sg:classifiers":[
        {
            "category":"Organizations",
            "subcategory":"Professional Association",
            "type":"Services"
        }
    ],
    "sg:phone":"+1 405 340 4966",
    "sg:postcode":"73025",
    "sg:province":"OK",
    "wof:name":"Association Of Owners-Oaks Inc",
    "wof:placetype":"venue"
},
  "geometry": {"coordinates":[-97.504428,35.716448],"type":"Point"}
}