{
  "type": "Feature",
  "properties": {
    "iso:country":"US",
    "sg:address":"1757 SW Frank Phillips Blvd",
    "sg:city":"Bartlesville",
    "sg:classifiers":[
        {
            "category":"Restaurant",
            "type":"Food & Drink"
        }
    ],
    "sg:phone":"+1 918 336 2828",
    "sg:postcode":"74003",
    "sg:province":"OK",
    "sg:tags":[
        "eating"
    ],
    "wof:name":"Wing's Country Cafe",
    "wof:placetype":"venue"
},
  "geometry": {"coordinates":[-95.997213,36.751496],"type":"Point"}
}