{
  "type": "Feature",
  "properties": {
    "addr:full":"627 Roosevelt Ave Stuart OK 74570",
    "addr:housenumber":"627",
    "addr:postcode":"74570",
    "addr:street":"Roosevelt Ave",
    "iso:country":"US",
    "sg:address":"627 Roosevelt Ave",
    "sg:city":"Stuart",
    "sg:classifiers":[
        {
            "category":"Utilities",
            "subcategory":"Water",
            "type":"Services"
        }
    ],
    "sg:phone":"+1 918 546 2611",
    "sg:postcode":"74570",
    "sg:province":"OK",
    "sg:tags":[
        "company",
        "sewage"
    ],
    "wof:name":"Rural Water Dist",
    "wof:placetype":"venue"
},
  "geometry": {"coordinates":[-96.099329,34.901166],"type":"Point"}
}