{
  "type": "Feature",
  "properties": {
    "addr:full":"5619 N Western Ave Oklahoma City OK 73118",
    "addr:housenumber":"5619",
    "addr:postcode":"73118",
    "addr:street":"N Western Ave",
    "iso:country":"US",
    "sg:address":"5619 N Western Ave",
    "sg:city":"Oklahoma City",
    "sg:classifiers":[
        {
            "category":"Shopping",
            "type":"Retail Goods"
        }
    ],
    "sg:phone":"+1 405 848 4106",
    "sg:postcode":"73118",
    "sg:province":"OK",
    "sg:tags":[
        "florist",
        "merchandise"
    ],
    "wof:name":"Aquarium Interiors",
    "wof:placetype":"venue"
},
  "geometry": {"coordinates":[-97.52989100000001,35.528371],"type":"Point"}
}