{
  "type": "Feature",
  "properties": {
    "iso:country":"US",
    "sg:address":"623 N Broadway St",
    "sg:city":"Moore",
    "sg:classifiers":[
        {
            "category":"Shopping",
            "subcategory":"Books",
            "type":"Retail Goods"
        }
    ],
    "sg:phone":"+1 405 912 4700",
    "sg:postcode":"73160",
    "sg:province":"OK",
    "sg:tags":[
        "comic"
    ],
    "wof:name":"Movies Music & Heroes",
    "wof:placetype":"venue"
},
  "geometry": {"coordinates":[-97.48726,35.343654],"type":"Point"}
}