{
  "type": "Feature",
  "properties": {
    "iso:country":"US",
    "sg:address":"3004 S 135th East Ave A",
    "sg:city":"Tulsa",
    "sg:classifiers":[
        {
            "category":"Manufacturing",
            "subcategory":"Food",
            "type":"Manufacturing & Wholesale Goods"
        },
        {
            "category":"Food & Beverages",
            "subcategory":"Groceries & Convenience Stores",
            "type":"Retail Goods"
        }
    ],
    "sg:phone":"+1 918 622 8412",
    "sg:postcode":"74134",
    "sg:province":"OK",
    "sg:tags":[
        "product"
    ],
    "wof:name":"Mary K Gleason Retailer",
    "wof:placetype":"venue"
},
  "geometry": {"coordinates":[-95.826023,36.120267],"type":"Point"}
}