{
  "type": "Feature",
  "properties": {
    "iso:country":"US",
    "sg:address":"1101 S McKenna St",
    "sg:city":"Poteau",
    "sg:classifiers":[
        {
            "category":"Shopping",
            "subcategory":"Discount & Variety Stores",
            "type":"Retail Goods"
        }
    ],
    "sg:phone":"+1 918 647 8012",
    "sg:postcode":"74953",
    "sg:province":"OK",
    "wof:name":"Jacks Bargains",
    "wof:placetype":"venue"
},
  "geometry": {"coordinates":[-94.630535,35.045565],"type":"Point"}
}