{
  "type": "Feature",
  "properties": {
    "iso:country":"US",
    "sg:address":"203 W Bond St",
    "sg:city":"Langston",
    "sg:classifiers":[
        {
            "category":"Social Services",
            "type":"Services"
        }
    ],
    "sg:phone":"+1 405 466 3761",
    "sg:postcode":"73050",
    "sg:province":"OK",
    "sg:tags":[
        "counseling",
        "senior",
        "citizen"
    ],
    "wof:name":"Logan County Aging",
    "wof:placetype":"venue"
},
  "geometry": {"coordinates":[-97.25433200000001,35.940924],"type":"Point"}
}