{
  "type": "Feature",
  "properties": {
    "addr:full":"1208 N Eastern Ave Moore OK 73160",
    "addr:housenumber":"1208",
    "addr:postcode":"73160",
    "addr:street":"N Eastern Ave",
    "iso:country":"US",
    "sg:address":"1208 N Eastern Ave",
    "sg:city":"Moore",
    "sg:classifiers":[
        {
            "category":"Restaurant",
            "type":"Food & Drink"
        }
    ],
    "sg:phone":"+1 405 799 1440",
    "sg:postcode":"73160",
    "sg:province":"OK",
    "sg:tags":[
        "eating"
    ],
    "wof:name":"Monty's Gyros & Subs",
    "wof:placetype":"venue"
},
  "geometry": {"coordinates":[-97.476832,35.348149],"type":"Point"}
}