{
  "type": "Feature",
  "properties": {
    "addr:full":"401 N Harrah Rd Harrah OK 73045",
    "addr:housenumber":"401",
    "addr:postcode":"73045",
    "addr:street":"N Harrah Rd",
    "iso:country":"US",
    "sg:address":"401 N Harrah Rd",
    "sg:city":"Harrah",
    "sg:classifiers":[
        {
            "category":"Restaurant",
            "type":"Food & Drink"
        }
    ],
    "sg:phone":"+1 405 454 2362",
    "sg:postcode":"73045",
    "sg:province":"OK",
    "wof:name":"Lori's Checkerboard Deli",
    "wof:placetype":"venue"
},
  "geometry": {"coordinates":[-97.159245,35.468732],"type":"Point"}
}