{
  "type": "Feature",
  "properties": {
    "addr:full":"334 E 15th St Claremore OK 74017",
    "addr:housenumber":"334",
    "addr:postcode":"74017",
    "addr:street":"E 15Th St",
    "iso:country":"US",
    "sg:address":"334 E 15th St",
    "sg:city":"Claremore",
    "sg:classifiers":[
        {
            "category":"Building & Trades",
            "subcategory":"Construction",
            "type":"Services"
        }
    ],
    "sg:phone":"+1 918 343 6023",
    "sg:postcode":"74017",
    "sg:province":"OK",
    "sg:tags":[
        "contractor"
    ],
    "wof:name":"Sandeckis Vinyl Siding",
    "wof:placetype":"venue"
},
  "geometry": {"coordinates":[-95.599109,36.323584],"type":"Point"}
}