{
  "type": "Feature",
  "properties": {
    "iso:country":"US",
    "sg:address":"205 S Chickasaw St",
    "sg:city":"Pauls Valley",
    "sg:classifiers":[
        {
            "category":"Insurance",
            "subcategory":"Insurance Agent",
            "type":"Services"
        }
    ],
    "sg:phone":"+1 405 238 7523",
    "sg:postcode":"73075",
    "sg:province":"OK",
    "wof:name":"Lucille Ensey Insurance",
    "wof:placetype":"venue"
},
  "geometry": {"coordinates":[-97.219147,34.740043],"type":"Point"}
}