{
  "type": "Feature",
  "properties": {
    "iso:country":"US",
    "sg:address":"1005 NE 28th St",
    "sg:city":"Oklahoma City",
    "sg:classifiers":[
        {
            "category":"Organizations",
            "subcategory":"Religious Organization",
            "type":"Services"
        }
    ],
    "sg:phone":"+1 405 424 6131",
    "sg:postcode":"73111",
    "sg:province":"OK",
    "sg:tags":[
        "baptist",
        "church"
    ],
    "wof:name":"Greater New Zion Bapt Church",
    "wof:placetype":"venue"
},
  "geometry": {"coordinates":[-97.492559,35.498962],"type":"Point"}
}