{
  "type": "Feature",
  "properties": {
    "iso:country":"US",
    "sg:address":"518 W Cherokee St",
    "sg:city":"Wagoner",
    "sg:classifiers":[
        {
            "category":"Manufacturing",
            "subcategory":"Printing",
            "type":"Manufacturing & Wholesale Goods"
        }
    ],
    "sg:phone":"+1 918 485 8107",
    "sg:postcode":"74467",
    "sg:province":"OK",
    "sg:tags":[
        "printer"
    ],
    "wof:name":"Arrow Printing",
    "wof:placetype":"venue"
},
  "geometry": {"coordinates":[-95.383327,35.959793],"type":"Point"}
}