{
  "type": "Feature",
  "properties": {
    "iso:country":"US",
    "sg:address":"116 E Lincoln St",
    "sg:city":"Mangum",
    "sg:classifiers":[
        {
            "category":"Government",
            "subcategory":"Office",
            "type":"Public Place"
        }
    ],
    "sg:phone":"+1 580 782 3004",
    "sg:postcode":"73554",
    "sg:province":"OK",
    "sg:tags":[
        "transportation"
    ],
    "wof:name":"Tag Agency",
    "wof:placetype":"venue"
},
  "geometry": {"coordinates":[-99.505853,34.872182],"type":"Point"}
}