{
  "type": "Feature",
  "properties": {
    "addr:full":"511 N Main St Guymon OK 73942",
    "addr:housenumber":"511",
    "addr:postcode":"73942",
    "addr:street":"N Main St",
    "iso:country":"US",
    "sg:address":"511 N Main St",
    "sg:city":"Guymon",
    "sg:classifiers":[
        {
            "category":"Food & Beverages",
            "subcategory":"Bakery",
            "type":"Retail Goods"
        }
    ],
    "sg:phone":"+1 580 338 2692",
    "sg:postcode":"73942",
    "sg:province":"OK",
    "wof:name":"Daylight Donuts",
    "wof:placetype":"venue"
},
  "geometry": {"coordinates":[-101.481492,36.682954],"type":"Point"}
}