{
  "type": "Feature",
  "properties": {
    "addr:full":"200 W 46th St N Tulsa OK 74126",
    "addr:housenumber":"200",
    "addr:postcode":"74126",
    "addr:street":"W 46Th St N",
    "iso:country":"US",
    "sg:address":"200 W 46th St N",
    "sg:city":"Tulsa",
    "sg:classifiers":[
        {
            "category":"Organizations",
            "subcategory":"Religious Organization",
            "type":"Services"
        },
        {
            "category":"Recreation",
            "type":"Entertainment"
        }
    ],
    "sg:phone":"+1 918 430 9984",
    "sg:postcode":"74126",
    "sg:province":"OK",
    "sg:tags":[
        "center"
    ],
    "wof:name":"Tulsa Dream Center",
    "wof:placetype":"venue"
},
  "geometry": {"coordinates":[-96.000553,36.220431],"type":"Point"}
}