{
  "type": "Feature",
  "properties": {
    "iso:country":"US",
    "sg:address":"124 S Scraper St",
    "sg:city":"Vinita",
    "sg:classifiers":[
        {
            "category":"Personal",
            "type":"Services"
        }
    ],
    "sg:phone":"+1 918 256 5787",
    "sg:postcode":"74301",
    "sg:province":"OK",
    "wof:name":"Suns Up Tanning Salon",
    "wof:placetype":"venue"
},
  "geometry": {"coordinates":[-95.155855,36.638742],"type":"Point"}
}