{
  "type": "Feature",
  "properties": {
    "addr:full":"215 S 4th St Chouteau OK 74337",
    "addr:housenumber":"215",
    "addr:postcode":"74337",
    "addr:street":"S 4Th St",
    "iso:country":"US",
    "sg:address":"215 S 4th St",
    "sg:city":"Chouteau",
    "sg:classifiers":[
        {
            "category":"Manufacturing",
            "subcategory":"Metals",
            "type":"Manufacturing & Wholesale Goods"
        }
    ],
    "sg:phone":"+1 918 476 6708",
    "sg:postcode":"74337",
    "sg:province":"OK",
    "sg:tags":[
        "fence"
    ],
    "wof:name":"Mayes County Fence Co",
    "wof:placetype":"venue"
},
  "geometry": {"coordinates":[-95.33734699999999,36.185173],"type":"Point"}
}