{
  "type": "Feature",
  "properties": {
    "addr:full":"301 E Greeley St Broken Arrow OK 74012",
    "addr:housenumber":"301",
    "addr:postcode":"74012",
    "addr:street":"E Greeley St",
    "iso:country":"US",
    "sg:address":"301 E Greeley St",
    "sg:city":"Broken Arrow",
    "sg:classifiers":[
        {
            "category":"Building & Trades",
            "subcategory":"Plumbing",
            "type":"Services"
        }
    ],
    "sg:phone":"+1 918 830 8589",
    "sg:postcode":"74012",
    "sg:province":"OK",
    "sg:tags":[
        "plumbing",
        "contractor"
    ],
    "wof:name":"A-Ok Plumbing",
    "wof:placetype":"venue"
},
  "geometry": {"coordinates":[-95.78643700000001,36.05727],"type":"Point"}
}