{
  "type": "Feature",
  "properties": {
    "iso:country":"US",
    "sg:address":"2012 NW 122nd St",
    "sg:city":"Oklahoma City",
    "sg:classifiers":[
        {
            "category":"Autos & Motor Vehicles",
            "subcategory":"Auto Supplies",
            "type":"Retail Goods"
        }
    ],
    "sg:phone":"+1 405 752 1646",
    "sg:postcode":"73114",
    "sg:province":"OK",
    "sg:tags":[
        "automobile",
        "accessory"
    ],
    "wof:name":"Specialty Auto Designs",
    "wof:placetype":"venue"
},
  "geometry": {"coordinates":[-97.549193,35.594556],"type":"Point"}
}