{
  "type": "Feature",
  "properties": {
    "iso:country":"US",
    "sg:address":"2504 E 6th Ave",
    "sg:city":"Stillwater",
    "sg:classifiers":[
        {
            "category":"Building & Trades",
            "subcategory":"Construction",
            "type":"Services"
        }
    ],
    "sg:phone":"+1 405 372 6543",
    "sg:postcode":"74074",
    "sg:province":"OK",
    "wof:name":"Oakley Portable Buildings",
    "wof:placetype":"venue"
},
  "geometry": {"coordinates":[-97.026974,36.116145],"type":"Point"}
}