{
  "type": "Feature",
  "properties": {
    "iso:country":"US",
    "sg:address":"400 S 24th St",
    "sg:city":"Clinton",
    "sg:classifiers":[
        {
            "category":"Professional",
            "subcategory":"Management & Consulting",
            "type":"Services"
        }
    ],
    "sg:phone":"+1 580 323 2811",
    "sg:postcode":"73601",
    "sg:province":"OK",
    "sg:tags":[
        "retail",
        "direct",
        "sales"
    ],
    "wof:name":"Avon Cosmetics",
    "wof:placetype":"venue"
},
  "geometry": {"coordinates":[-98.989742,35.510345],"type":"Point"}
}