{
  "type": "Feature",
  "properties": {
    "iso:country":"US",
    "sg:address":"9032 W 151st St S",
    "sg:city":"Sapulpa",
    "sg:classifiers":[
        {
            "category":"Manufacturing",
            "subcategory":"Metals",
            "type":"Manufacturing & Wholesale Goods"
        }
    ],
    "sg:phone":"+1 918 321 3562",
    "sg:postcode":"74066",
    "sg:province":"OK",
    "sg:tags":[
        "metalwork",
        "architectural",
        "mfg"
    ],
    "wof:name":"Carroll Boyd",
    "wof:placetype":"venue"
},
  "geometry": {"coordinates":[-96.085022,35.944727],"type":"Point"}
}