{
  "type": "Feature",
  "properties": {
    "addr:full":"2929 S 129th East Pl Tulsa OK 74134",
    "addr:housenumber":"2929",
    "addr:postcode":"74134",
    "addr:street":"S 129Th East Pl",
    "iso:country":"US",
    "sg:address":"2929 S 129th East Pl",
    "sg:city":"Tulsa",
    "sg:classifiers":[
        {
            "category":"Real Estate",
            "subcategory":"Real Estate Operator",
            "type":"Services"
        }
    ],
    "sg:phone":"+1 918 664 4420",
    "sg:postcode":"74134",
    "sg:province":"OK",
    "sg:tags":[
        "building",
        "apartment"
    ],
    "wof:name":"Ashwood Apartments",
    "wof:placetype":"venue"
},
  "geometry": {"coordinates":[-95.83245599999999,36.115186],"type":"Point"}
}