{
  "type": "Feature",
  "properties": {
    "iso:country":"US",
    "sg:address":"18 N Adair St",
    "sg:city":"Pryor",
    "sg:classifiers":[
        {
            "category":"Professional",
            "subcategory":"Accounting & Tax Preparation",
            "type":"Services"
        }
    ],
    "sg:phone":"+1 918 825 7322",
    "sg:postcode":"74361",
    "sg:province":"OK",
    "wof:name":"Kolker & Kolker Inc",
    "wof:placetype":"venue"
},
  "geometry": {"coordinates":[-95.31678599999999,36.308598],"type":"Point"}
}