{
  "type": "Feature",
  "properties": {
    "iso:country":"US",
    "sg:address":"712 Research Park Blvd",
    "sg:city":"Norman",
    "sg:classifiers":[
        {
            "category":"Retail",
            "subcategory":"Auto Repair",
            "type":"Services"
        }
    ],
    "sg:phone":"+1 405 364 7824",
    "sg:postcode":"73069",
    "sg:province":"OK",
    "sg:tags":[
        "general"
    ],
    "wof:name":"Jerrys Auto Service",
    "wof:placetype":"venue"
},
  "geometry": {"coordinates":[-97.450413,35.242728],"type":"Point"}
}