{
  "type": "Feature",
  "properties": {
    "iso:country":"US",
    "sg:address":"4823 S 83rd East Ave",
    "sg:city":"Tulsa",
    "sg:classifiers":[
        {
            "category":"Organizations",
            "subcategory":"Labor Organization",
            "type":"Services"
        }
    ],
    "sg:phone":"+1 918 622 1900",
    "sg:postcode":"74145",
    "sg:province":"OK",
    "sg:website":"www.local798.org",
    "wof:name":"Pipeliners Local Union",
    "wof:placetype":"venue"
},
  "geometry": {"coordinates":[-95.883707,36.09764],"type":"Point"}
}