{
  "type": "Feature",
  "properties": {
    "addr:full":"1801 W Locust St Stilwell OK 74960",
    "addr:housenumber":"1801",
    "addr:postcode":"74960",
    "addr:street":"W Locust St",
    "iso:country":"US",
    "sg:address":"1801 W Locust St",
    "sg:city":"Stilwell",
    "sg:classifiers":[
        {
            "category":"Education",
            "subcategory":"School",
            "type":"Public Place"
        }
    ],
    "sg:phone":"+1 918 696 7001",
    "sg:postcode":"74960",
    "sg:province":"OK",
    "wof:name":"Stilwell School District",
    "wof:placetype":"venue"
},
  "geometry": {"coordinates":[-94.638255,35.808455],"type":"Point"}
}