{
  "type": "Feature",
  "properties": {
    "iso:country":"US",
    "sg:address":"101 S Sooner Rd",
    "sg:city":"Oklahoma City",
    "sg:classifiers":[
        {
            "category":"Autos & Motor Vehicles",
            "subcategory":"Fuel & Gas Station",
            "type":"Retail Goods"
        }
    ],
    "sg:phone":"+1 405 670 1402",
    "sg:postcode":"73110",
    "sg:province":"OK",
    "sg:tags":[
        "station",
        "gasoline"
    ],
    "wof:name":"Four Seasons Gas",
    "wof:placetype":"venue"
},
  "geometry": {"coordinates":[-97.423931,35.462727],"type":"Point"}
}