{
  "type": "Feature",
  "properties": {
    "addr:full":"5527 E 41st St Tulsa OK 74135",
    "addr:housenumber":"5527",
    "addr:postcode":"74135",
    "addr:street":"E 41St St",
    "iso:country":"US",
    "sg:address":"5527 E 41st St",
    "sg:city":"Tulsa",
    "sg:classifiers":[
        {
            "category":"Building & Trades",
            "subcategory":"Equipment Rental",
            "type":"Services"
        }
    ],
    "sg:phone":"+1 918 622 7895",
    "sg:postcode":"74135",
    "sg:province":"OK",
    "sg:tags":[
        "medical",
        "chem",
        "merchandise"
    ],
    "wof:name":"Lincare Homecare Med Systems",
    "wof:placetype":"venue"
},
  "geometry": {"coordinates":[-95.913303,36.104448],"type":"Point"}
}