{
  "type": "Feature",
  "properties": {
    "iso:country":"US",
    "sg:address":"5600 W Skelly Dr",
    "sg:city":"Tulsa",
    "sg:classifiers":[
        {
            "category":"Travel",
            "subcategory":"Hotels & Motels",
            "type":"Entertainment"
        }
    ],
    "sg:phone":"+1 918 446 6611",
    "sg:postcode":"74107",
    "sg:province":"OK",
    "sg:tags":[
        "operation"
    ],
    "wof:name":"Gateway Motor Inn",
    "wof:placetype":"venue"
},
  "geometry": {"coordinates":[-96.045846,36.082192],"type":"Point"}
}