{
  "type": "Feature",
  "properties": {
    "iso:country":"US",
    "sg:address":"3705 W Broadway St",
    "sg:city":"Muskogee",
    "sg:classifiers":[
        {
            "category":"Health Services",
            "subcategory":"Optometrist",
            "type":"Services"
        }
    ],
    "sg:phone":"+1 918 687 7539",
    "sg:postcode":"74401",
    "sg:province":"OK",
    "wof:name":"Creed & Miller",
    "wof:placetype":"venue"
},
  "geometry": {"coordinates":[-95.409193,35.755933],"type":"Point"}
}