{
  "type": "Feature",
  "properties": {
    "iso:country":"US",
    "sg:address":"2248 N Harvard Ave",
    "sg:city":"Tulsa",
    "sg:classifiers":[
        {
            "category":"Restaurant",
            "type":"Food & Drink"
        }
    ],
    "sg:phone":"+1 918 835 6827",
    "sg:postcode":"74115",
    "sg:province":"OK",
    "wof:name":"Rubicon Restaurant",
    "wof:placetype":"venue"
},
  "geometry": {"coordinates":[-95.940376,36.186312],"type":"Point"}
}