{
  "type": "Feature",
  "properties": {
    "addr:full":"4707 Coyote Pass Ct Muskogee OK 74403",
    "addr:housenumber":"4707",
    "addr:postcode":"74403",
    "addr:street":"Coyote Pass Ct",
    "iso:country":"US",
    "sg:address":"4707 Coyote Pass Ct",
    "sg:city":"Muskogee",
    "sg:classifiers":[
        {
            "category":"Freight",
            "type":"Transportation"
        }
    ],
    "sg:phone":"+1 918 684 3242",
    "sg:postcode":"74403",
    "sg:province":"OK",
    "sg:tags":[
        "trucking"
    ],
    "wof:name":"Dozier Trucking",
    "wof:placetype":"venue"
},
  "geometry": {"coordinates":[-95.344309,35.692885],"type":"Point"}
}