{
  "type": "Feature",
  "properties": {
    "iso:country":"US",
    "sg:address":"2200 Heatherstone Rd",
    "sg:city":"Edmond",
    "sg:classifiers":[
        {
            "category":"Building & Trades",
            "subcategory":"Plumbing",
            "type":"Services"
        }
    ],
    "sg:phone":"+1 405 359 8913",
    "sg:postcode":"73034",
    "sg:province":"OK",
    "sg:tags":[
        "contractor"
    ],
    "wof:name":"Suntech Mechanical",
    "wof:placetype":"venue"
},
  "geometry": {"coordinates":[-97.473297,35.677357],"type":"Point"}
}