{
  "type": "Feature",
  "properties": {
    "addr:full":"1322 Quail Hollow Dr Norman OK 73072",
    "addr:housenumber":"1322",
    "addr:postcode":"73072",
    "addr:street":"Quail Hollow Dr",
    "iso:country":"US",
    "sg:address":"1322 Quail Hollow Dr",
    "sg:city":"Norman",
    "sg:classifiers":[
        {
            "category":"Professional",
            "subcategory":"Business Services",
            "type":"Services"
        }
    ],
    "sg:phone":"+1 405 329 6798",
    "sg:postcode":"73072",
    "sg:province":"OK",
    "wof:name":"Shipman Family Partnership",
    "wof:placetype":"venue"
},
  "geometry": {"coordinates":[-97.492931,35.235673],"type":"Point"}
}