{
  "type": "Feature",
  "properties": {
    "iso:country":"US",
    "sg:address":"4972 Frisco Rd NW",
    "sg:city":"Piedmont",
    "sg:classifiers":[
        {
            "category":"Building & Trades",
            "subcategory":"Construction",
            "type":"Services"
        }
    ],
    "sg:phone":"+1 405 373 0157",
    "sg:postcode":"73078",
    "sg:province":"OK",
    "sg:tags":[
        "house"
    ],
    "wof:name":"Westrup Construction",
    "wof:placetype":"venue"
},
  "geometry": {"coordinates":[-97.780535,35.683443],"type":"Point"}
}