{
  "type": "Feature",
  "properties": {
    "iso:country":"US",
    "sg:address":"1309 N James St",
    "sg:city":"Guymon",
    "sg:classifiers":[
        {
            "category":"Shopping",
            "subcategory":"Stationery & Office Supplies",
            "type":"Retail Goods"
        }
    ],
    "sg:phone":"+1 580 338 2122",
    "sg:postcode":"73942",
    "sg:province":"OK",
    "wof:name":"Collins Supply",
    "wof:placetype":"venue"
},
  "geometry": {"coordinates":[-101.486677,36.69077],"type":"Point"}
}