{
  "type": "Feature",
  "properties": {
    "iso:country":"US",
    "sg:address":"2950 S Hickory St",
    "sg:city":"Sapulpa",
    "sg:classifiers":[
        {
            "category":"Social Services",
            "type":"Services"
        }
    ],
    "sg:phone":"+1 918 224 6863",
    "sg:postcode":"74066",
    "sg:province":"OK",
    "wof:name":"Hickory Ridge Apartments",
    "wof:placetype":"venue"
},
  "geometry": {"coordinates":[-96.118808,35.967924],"type":"Point"}
}