{
  "type": "Feature",
  "properties": {
    "iso:country":"US",
    "sg:address":"439 SW 89th St",
    "sg:city":"Oklahoma City",
    "sg:classifiers":[
        {
            "category":"Professional",
            "subcategory":"Business Services",
            "type":"Services"
        }
    ],
    "sg:phone":"+1 405 631 9558",
    "sg:postcode":"73139",
    "sg:province":"OK",
    "sg:tags":[
        "interior",
        "designer"
    ],
    "wof:name":"CBS Designs Inc",
    "wof:placetype":"venue"
},
  "geometry": {"coordinates":[-97.518399,35.377267],"type":"Point"}
}