{
  "type": "Feature",
  "properties": {
    "iso:country":"US",
    "sg:address":"316 W 39th St",
    "sg:city":"Sand Springs",
    "sg:classifiers":[
        {
            "category":"Shopping",
            "type":"Retail Goods"
        }
    ],
    "sg:phone":"+1 918 245 4714",
    "sg:postcode":"74063",
    "sg:province":"OK",
    "sg:tags":[
        "miscellaneous",
        "store"
    ],
    "wof:name":"Johnson Family Medical",
    "wof:placetype":"venue"
},
  "geometry": {"coordinates":[-96.12597,36.107295],"type":"Point"}
}