{
  "type": "Feature",
  "properties": {
    "addr:full":"11110 NE 23rd St Choctaw OK 73020",
    "addr:housenumber":"11110",
    "addr:postcode":"73020",
    "addr:street":"Ne 23Rd St",
    "iso:country":"US",
    "sg:address":"11110 NE 23rd St",
    "sg:city":"Choctaw",
    "sg:classifiers":[
        {
            "category":"Manufacturing",
            "subcategory":"Watercraft",
            "type":"Manufacturing & Wholesale Goods"
        }
    ],
    "sg:phone":"+1 405 769 9710",
    "sg:postcode":"73020",
    "sg:province":"OK",
    "sg:tags":[
        "boat"
    ],
    "wof:name":"Fulton Marine",
    "wof:placetype":"venue"
},
  "geometry": {"coordinates":[-97.33339700000001,35.492976],"type":"Point"}
}