{
  "type": "Feature",
  "properties": {
    "iso:country":"US",
    "sg:address":"2500 S Riverside Rd",
    "sg:city":"Sand Springs",
    "sg:classifiers":[
        {
            "category":"Professional",
            "type":"Services"
        }
    ],
    "sg:phone":"+1 918 245 5269",
    "sg:postcode":"74085",
    "sg:province":"OK",
    "sg:tags":[
        "establishment"
    ],
    "wof:name":"T-TOWNE Bmx Inc",
    "wof:placetype":"venue"
},
  "geometry": {"coordinates":[-96.749419,36.094927],"type":"Point"}
}