{
  "type": "Feature",
  "properties": {
    "iso:country":"US",
    "sg:address":"9501 Mohawk Blvd",
    "sg:city":"Tulsa",
    "sg:classifiers":[
        {
            "category":"Manufacturing",
            "subcategory":"Glass & Minerals",
            "type":"Manufacturing & Wholesale Goods"
        }
    ],
    "sg:phone":"+1 918 272 4240",
    "sg:postcode":"74117",
    "sg:province":"OK",
    "sg:tags":[
        "ready"
    ],
    "wof:name":"Mid Continent Concrete",
    "wof:placetype":"venue"
},
  "geometry": {"coordinates":[-95.869107,36.232971],"type":"Point"}
}