{
  "type": "Feature",
  "properties": {
    "iso:country":"US",
    "sg:address":"2812 S Walker Ave",
    "sg:city":"Oklahoma City",
    "sg:classifiers":[
        {
            "category":"Retail",
            "subcategory":"Auto Repair",
            "type":"Services"
        }
    ],
    "sg:phone":"+1 405 634 9665",
    "sg:postcode":"73109",
    "sg:province":"OK",
    "sg:tags":[
        "body",
        "automobile",
        "painting"
    ],
    "wof:name":"Eskridge Collision Ctr South",
    "wof:placetype":"venue"
},
  "geometry": {"coordinates":[-97.521359,35.436389],"type":"Point"}
}