{
  "type": "Feature",
  "properties": {
    "iso:country":"US",
    "sg:address":"7902 E 50th St",
    "sg:city":"Tulsa",
    "sg:classifiers":[
        {
            "category":"Professional",
            "type":"Services"
        }
    ],
    "sg:phone":"+1 918 446 0691",
    "sg:postcode":"74145",
    "sg:province":"OK",
    "sg:tags":[
        "establishment"
    ],
    "wof:name":"Mr Victor",
    "wof:placetype":"venue"
},
  "geometry": {"coordinates":[-95.886594,36.091431],"type":"Point"}
}