{
  "type": "Feature",
  "properties": {
    "iso:country":"US",
    "sg:address":"2340 W Memorial Rd",
    "sg:city":"Oklahoma City",
    "sg:classifiers":[
        {
            "category":"Shopping",
            "type":"Retail Goods"
        }
    ],
    "sg:phone":"+1 405 302 4900",
    "sg:postcode":"73134",
    "sg:province":"OK",
    "sg:tags":[
        "cosmetic",
        "perfume"
    ],
    "wof:name":"Ulta 3 Cosmetics",
    "wof:placetype":"venue"
},
  "geometry": {"coordinates":[-97.556891,35.608482],"type":"Point"}
}