{
  "type": "Feature",
  "properties": {
    "addr:full":"4321 E Hayes St Muskogee OK 74403",
    "addr:housenumber":"4321",
    "addr:postcode":"74403",
    "addr:street":"E Hayes St",
    "iso:country":"US",
    "sg:address":"4321 E Hayes St",
    "sg:city":"Muskogee",
    "sg:classifiers":[
        {
            "category":"Organizations",
            "subcategory":"Membership Organization",
            "type":"Services"
        }
    ],
    "sg:phone":"+1 918 686 7297",
    "sg:postcode":"74403",
    "sg:province":"OK",
    "sg:tags":[
        "society",
        "humane"
    ],
    "wof:name":"Promoting Animal Welfare Scty",
    "wof:placetype":"venue"
},
  "geometry": {"coordinates":[-95.309256,35.749546],"type":"Point"}
}