{
  "type": "Feature",
  "properties": {
    "iso:country":"US",
    "sg:address":"201 E Jefferson St",
    "sg:city":"Mangum",
    "sg:classifiers":[
        {
            "category":"Organizations",
            "subcategory":"Community Association",
            "type":"Services"
        }
    ],
    "sg:phone":"+1 580 782 5152",
    "sg:postcode":"73554",
    "sg:province":"OK",
    "wof:name":"Masonic Lodge Hall",
    "wof:placetype":"venue"
},
  "geometry": {"coordinates":[-99.50367,34.873597],"type":"Point"}
}