{
  "type": "Feature",
  "properties": {
    "iso:country":"US",
    "sg:address":"114 W Main St",
    "sg:city":"Hominy",
    "sg:classifiers":[
        {
            "category":"Professional",
            "type":"Services"
        }
    ],
    "sg:phone":"+1 918 885 2522",
    "sg:postcode":"74035",
    "sg:province":"OK",
    "sg:tags":[
        "establishment"
    ],
    "wof:name":"Hamilton KANE & KANE",
    "wof:placetype":"venue"
},
  "geometry": {"coordinates":[-96.395275,36.415479],"type":"Point"}
}