{
  "type": "Feature",
  "properties": {
    "iso:country":"US",
    "sg:address":"2320 N Park Ln",
    "sg:city":"Altus",
    "sg:classifiers":[
        {
            "category":"Retail",
            "subcategory":"Repair Shop",
            "type":"Services"
        },
        {
            "category":"Home & Garden",
            "subcategory":"Garden Supply",
            "type":"Retail Goods"
        }
    ],
    "sg:phone":"+1 580 482 0909",
    "sg:postcode":"73521",
    "sg:province":"OK",
    "sg:tags":[
        "equipment",
        "lawn",
        "outdoor",
        "mower"
    ],
    "wof:name":"Precision Lawnmower Repair Inc",
    "wof:placetype":"venue"
},
  "geometry": {"coordinates":[-99.316302,34.66152],"type":"Point"}
}