{
  "type": "Feature",
  "properties": {
    "addr:full":"16719 N Briggs Flat Rd Tahlequah OK 74464",
    "addr:housenumber":"16719",
    "addr:postcode":"74464",
    "addr:street":"N Briggs Flat Rd",
    "iso:country":"US",
    "sg:address":"16719 N Briggs Flat Rd",
    "sg:city":"Tahlequah",
    "sg:classifiers":[
        {
            "category":"Food & Beverages",
            "subcategory":"Specialty",
            "type":"Retail Goods"
        }
    ],
    "sg:phone":"+1 918 458 6417",
    "sg:postcode":"74464",
    "sg:province":"OK",
    "sg:tags":[
        "herb"
    ],
    "wof:name":"Herbal Solution",
    "wof:placetype":"venue"
},
  "geometry": {"coordinates":[-94.873637,35.932866],"type":"Point"}
}