{
  "type": "Feature",
  "properties": {
    "addr:full":"2316 Bradford Pl Edmond OK 73012",
    "addr:housenumber":"2316",
    "addr:postcode":"73012",
    "addr:street":"Bradford Pl",
    "iso:country":"US",
    "sg:address":"2316 Bradford Pl",
    "sg:city":"Edmond",
    "sg:classifiers":[
        {
            "category":"Professional",
            "subcategory":"Engineering",
            "type":"Services"
        }
    ],
    "sg:phone":"+1 405 285 2440",
    "sg:postcode":"73012",
    "sg:province":"OK",
    "sg:tags":[
        "engineer"
    ],
    "wof:name":"FBS Engineering",
    "wof:placetype":"venue"
},
  "geometry": {"coordinates":[-97.514009,35.663401],"type":"Point"}
}