{
  "type": "Feature",
  "properties": {
    "addr:full":"10604 E 100th Pl Tulsa OK 74133",
    "addr:housenumber":"10604",
    "addr:postcode":"74133",
    "addr:street":"E 100Th Pl",
    "iso:country":"US",
    "sg:address":"10604 E 100th Pl",
    "sg:city":"Tulsa",
    "sg:classifiers":[
        {
            "category":"Professional",
            "type":"Services"
        }
    ],
    "sg:phone":"+1 918 249 8955",
    "sg:postcode":"74133",
    "sg:province":"OK",
    "sg:tags":[
        "establishment"
    ],
    "wof:name":"Advanced Composites",
    "wof:placetype":"venue"
},
  "geometry": {"coordinates":[-95.857907,36.017939],"type":"Point"}
}