{
  "type": "Feature",
  "properties": {
    "iso:country":"US",
    "sg:address":"8012 NW 129th Cir",
    "sg:city":"Oklahoma City",
    "sg:classifiers":[
        {
            "category":"Shopping",
            "subcategory":"Crafts & Fabrics",
            "type":"Retail Goods"
        }
    ],
    "sg:phone":"+1 405 722 3656",
    "sg:postcode":"73142",
    "sg:province":"OK",
    "sg:tags":[
        "sewing"
    ],
    "wof:name":"Sew Special",
    "wof:placetype":"venue"
},
  "geometry": {"coordinates":[-97.657932,35.60262],"type":"Point"}
}