{
  "type": "Feature",
  "properties": {
    "iso:country":"US",
    "sg:address":"122 S Broadway St",
    "sg:city":"Coweta",
    "sg:classifiers":[
        {
            "category":"Shopping",
            "subcategory":"Gifts & Souvenirs",
            "type":"Retail Goods"
        }
    ],
    "sg:phone":"+1 918 486 5044",
    "sg:postcode":"74429",
    "sg:province":"OK",
    "sg:tags":[
        "shop",
        "novelty"
    ],
    "wof:name":"Robins Flower Garden",
    "wof:placetype":"venue"
},
  "geometry": {"coordinates":[-95.650596,35.95015],"type":"Point"}
}