{
  "type": "Feature",
  "properties": {
    "addr:full":"7030 S Yale Ave Tulsa OK 74136",
    "addr:housenumber":"7030",
    "addr:postcode":"74136",
    "addr:street":"S Yale Ave",
    "iso:country":"US",
    "sg:address":"7030 S Yale Ave",
    "sg:city":"Tulsa",
    "sg:classifiers":[
        {
            "category":"Professional",
            "subcategory":"Lawyer & Legal Services",
            "type":"Services"
        }
    ],
    "sg:phone":"+1 918 493 2584",
    "sg:postcode":"74136",
    "sg:province":"OK",
    "wof:name":"Family Wealth Council PLC",
    "wof:placetype":"venue"
},
  "geometry": {"coordinates":[-95.92214199999999,36.061462],"type":"Point"}
}