{
  "type": "Feature",
  "properties": {
    "iso:country":"US",
    "sg:address":"9406 N 133rd E Ave",
    "sg:city":"Owasso",
    "sg:classifiers":[
        {
            "category":"Retail",
            "subcategory":"Repair Shop",
            "type":"Services"
        }
    ],
    "sg:phone":"+1 918 272 5820",
    "sg:postcode":"74055",
    "sg:province":"OK",
    "wof:name":"Copper Mill",
    "wof:placetype":"venue"
},
  "geometry": {"coordinates":[-95.826612,36.291349],"type":"Point"}
}