{
  "type": "Feature",
  "properties": {
    "iso:country":"US",
    "sg:address":"1600 Linwood Blvd",
    "sg:city":"Oklahoma City",
    "sg:classifiers":[
        {
            "category":"Building & Trades",
            "subcategory":"Construction",
            "type":"Services"
        }
    ],
    "sg:phone":"+1 405 236 5444",
    "sg:postcode":"73106",
    "sg:province":"OK",
    "sg:tags":[
        "contracting",
        "general"
    ],
    "wof:name":"Vjc Contracting Inc",
    "wof:placetype":"venue"
},
  "geometry": {"coordinates":[-97.538904,35.474756],"type":"Point"}
}