{
  "type": "Feature",
  "properties": {
    "addr:full":"3131 E Waterloo Rd Edmond OK 73034",
    "addr:housenumber":"3131",
    "addr:postcode":"73034",
    "addr:street":"E Waterloo Rd",
    "iso:country":"US",
    "sg:address":"3131 E Waterloo Rd",
    "sg:city":"Edmond",
    "sg:classifiers":[
        {
            "category":"Professional",
            "subcategory":"Accounting & Tax Preparation",
            "type":"Services"
        }
    ],
    "sg:phone":"+1 405 330 2907",
    "sg:postcode":"73034",
    "sg:province":"OK",
    "sg:tags":[
        "return",
        "filing"
    ],
    "wof:name":"Ratliff Tax Svc",
    "wof:placetype":"venue"
},
  "geometry": {"coordinates":[-97.382473,35.725347],"type":"Point"}
}