{
  "type": "Feature",
  "properties": {
    "iso:country":"US",
    "sg:address":"4917 SE 55th St",
    "sg:city":"Oklahoma City",
    "sg:classifiers":[
        {
            "category":"Real Estate",
            "subcategory":"Real Estate Agent",
            "type":"Services"
        },
        {
            "category":"Professional",
            "subcategory":"Business Services",
            "type":"Services"
        }
    ],
    "sg:phone":"+1 405 677 4542",
    "sg:postcode":"73135",
    "sg:province":"OK",
    "sg:tags":[
        "appraiser"
    ],
    "wof:name":"Burk Appraisals & Home Inspctn",
    "wof:placetype":"venue"
},
  "geometry": {"coordinates":[-97.433277,35.40966],"type":"Point"}
}