{
  "type": "Feature",
  "properties": {
    "iso:country":"US",
    "sg:address":"721 Evergreen St",
    "sg:city":"Edmond",
    "sg:classifiers":[
        {
            "category":"Building & Trades",
            "subcategory":"Construction",
            "type":"Services"
        }
    ],
    "sg:phone":"+1 405 348 4333",
    "sg:postcode":"73003",
    "sg:province":"OK",
    "sg:tags":[
        "designer",
        "dealer",
        "pool",
        "swimming"
    ],
    "wof:name":"Darren's Pool Plastering",
    "wof:placetype":"venue"
},
  "geometry": {"coordinates":[-97.494157,35.644214],"type":"Point"}
}