{
  "type": "Feature",
  "properties": {
    "iso:country":"US",
    "sg:address":"1001 E 17th Ave",
    "sg:city":"Stillwater",
    "sg:classifiers":[
        {
            "category":"Shopping",
            "subcategory":"Gifts & Souvenirs",
            "type":"Retail Goods"
        }
    ],
    "sg:phone":"+1 405 624 0903",
    "sg:postcode":"74074",
    "sg:province":"OK",
    "wof:name":"Rock Barn Relics",
    "wof:placetype":"venue"
},
  "geometry": {"coordinates":[-97.044629,36.104141],"type":"Point"}
}