{
  "type": "Feature",
  "properties": {
    "addr:full":"14340 Celia Berryhill Rd Okmulgee OK 74447",
    "addr:housenumber":"14340",
    "addr:postcode":"74447",
    "addr:street":"Celia Berryhill Rd",
    "iso:country":"US",
    "sg:address":"14340 Celia Berryhill Rd",
    "sg:city":"Okmulgee",
    "sg:classifiers":[
        {
            "category":"Personal",
            "subcategory":"Beauty Salon",
            "type":"Services"
        }
    ],
    "sg:phone":"+1 918 758 0424",
    "sg:postcode":"74447",
    "sg:province":"OK",
    "sg:tags":[
        "shop"
    ],
    "wof:name":"Karen S Beauty Works Etc",
    "wof:placetype":"venue"
},
  "geometry": {"coordinates":[-95.943262,35.682437],"type":"Point"}
}