{
  "type": "Feature",
  "properties": {
    "addr:full":"503 W Country Club Blvd Elk City OK 73644",
    "addr:housenumber":"503",
    "addr:postcode":"73644",
    "addr:street":"W Country Club Blvd",
    "iso:country":"US",
    "sg:address":"503 W Country Club Blvd",
    "sg:city":"Elk City",
    "sg:classifiers":[
        {
            "category":"Health Services",
            "subcategory":"Doctor",
            "type":"Services"
        }
    ],
    "sg:phone":"+1 580 225 4466",
    "sg:postcode":"73644",
    "sg:province":"OK",
    "sg:tags":[
        "physician",
        "surgeon"
    ],
    "wof:name":"Paul Firth MD",
    "wof:placetype":"venue"
},
  "geometry": {"coordinates":[-99.409429,35.421985],"type":"Point"}
}