{
  "type": "Feature",
  "properties": {
    "addr:full":"6609 S Blackwelder Ave Oklahoma City OK 73159",
    "addr:housenumber":"6609",
    "addr:postcode":"73159",
    "addr:street":"S Blackwelder Ave",
    "iso:country":"US",
    "sg:address":"6609 S Blackwelder Ave",
    "sg:city":"Oklahoma City",
    "sg:classifiers":[
        {
            "category":"Education",
            "subcategory":"School",
            "type":"Public Place"
        }
    ],
    "sg:phone":"+1 405 681 2944",
    "sg:postcode":"73159",
    "sg:province":"OK",
    "wof:name":"Prairie Queen Elementary Schl",
    "wof:placetype":"venue"
},
  "geometry": {"coordinates":[-97.539107,35.399617],"type":"Point"}
}