{
  "type": "Feature",
  "properties": {
    "iso:country":"US",
    "sg:address":"2148 W Britton Rd",
    "sg:city":"Oklahoma City",
    "sg:classifiers":[
        {
            "category":"Personal",
            "subcategory":"Shoe Repair & Shine",
            "type":"Services"
        }
    ],
    "sg:phone":"+1 405 848 0247",
    "sg:postcode":"73120",
    "sg:province":"OK",
    "sg:tags":[
        "repairing",
        "boot"
    ],
    "wof:name":"Zeigler's Shoe Repair",
    "wof:placetype":"venue"
},
  "geometry": {"coordinates":[-97.551801,35.565553],"type":"Point"}
}