{
  "type": "Feature",
  "properties": {
    "iso:country":"US",
    "sg:address":"6530 E 21st Pl",
    "sg:city":"Tulsa",
    "sg:classifiers":[
        {
            "category":"Real Estate",
            "subcategory":"Real Estate Operator",
            "type":"Services"
        }
    ],
    "sg:phone":"+1 918 835 0105",
    "sg:postcode":"74129",
    "sg:province":"OK",
    "sg:tags":[
        "building",
        "apartment"
    ],
    "wof:name":"2200 Sheridan Apartments",
    "wof:placetype":"venue"
},
  "geometry": {"coordinates":[-95.900636,36.131556],"type":"Point"}
}