{
  "type": "Feature",
  "properties": {
    "iso:country":"US",
    "sg:address":"1439 E 71st St",
    "sg:city":"Tulsa",
    "sg:classifiers":[
        {
            "category":"Organizations",
            "subcategory":"Religious Organization",
            "type":"Services"
        }
    ],
    "sg:phone":"+1 918 492 5511",
    "sg:postcode":"74136",
    "sg:province":"OK",
    "sg:website":"www.obftulsa.org",
    "wof:name":"Open Bible Fellowship",
    "wof:placetype":"venue"
},
  "geometry": {"coordinates":[-95.97414,36.060757],"type":"Point"}
}