{
  "type": "Feature",
  "properties": {
    "iso:country":"US",
    "sg:address":"2913 W Chestnut Ave",
    "sg:city":"Enid",
    "sg:classifiers":[
        {
            "category":"Building & Trades",
            "subcategory":"Construction",
            "type":"Services"
        }
    ],
    "sg:phone":"+1 580 234 4960",
    "sg:postcode":"73703",
    "sg:province":"OK",
    "sg:tags":[
        "house"
    ],
    "wof:name":"Otto Hildebrand Construction",
    "wof:placetype":"venue"
},
  "geometry": {"coordinates":[-97.913605,36.405168],"type":"Point"}
}