{
  "type": "Feature",
  "properties": {
    "iso:country":"US",
    "sg:address":"12775 E 41st St",
    "sg:city":"Tulsa",
    "sg:classifiers":[
        {
            "category":"Shopping",
            "subcategory":"Hobbies, Toys, & Games",
            "type":"Retail Goods"
        }
    ],
    "sg:phone":"+1 918 664 1800",
    "sg:postcode":"74146",
    "sg:province":"OK",
    "sg:tags":[
        "model",
        "supply"
    ],
    "wof:name":"Model Works Inc",
    "wof:placetype":"venue"
},
  "geometry": {"coordinates":[-95.833915,36.104589],"type":"Point"}
}