{
  "type": "Feature",
  "properties": {
    "iso:country":"US",
    "sg:address":"129 N Lewis Ave",
    "sg:city":"Tulsa",
    "sg:classifiers":[
        {
            "category":"Autos & Motor Vehicles",
            "subcategory":"Auto Supplies",
            "type":"Retail Goods"
        }
    ],
    "sg:phone":"+1 918 834 3601",
    "sg:postcode":"74110",
    "sg:province":"OK",
    "sg:tags":[
        "transmission",
        "automobile",
        "accessory",
        "part",
        "supplies-used",
        "clutch",
        "rebuilt"
    ],
    "sg:website":"http://www.lestersgear.com",
    "wof:name":"Lester's Gear",
    "wof:placetype":"venue"
},
  "geometry": {"coordinates":[-95.95816499999999,36.163613],"type":"Point"}
}