{
  "type": "Feature",
  "properties": {
    "addr:full":"20208 NE 23rd St Harrah OK 73045",
    "addr:housenumber":"20208",
    "addr:postcode":"73045",
    "addr:street":"Ne 23Rd St",
    "iso:country":"US",
    "sg:address":"20208 NE 23rd St",
    "sg:city":"Harrah",
    "sg:classifiers":[
        {
            "category":"Shopping",
            "subcategory":"Discount & Variety Stores",
            "type":"Retail Goods"
        },
        {
            "category":"Shopping",
            "subcategory":"Department Store",
            "type":"Retail Goods"
        }
    ],
    "sg:phone":"+1 405 454 3838",
    "sg:postcode":"73045",
    "sg:province":"OK",
    "sg:tags":[
        "shop"
    ],
    "wof:name":"Family Dollar Stores",
    "wof:placetype":"venue"
},
  "geometry": {"coordinates":[-97.175292,35.492956],"type":"Point"}
}