{
  "type": "Feature",
  "properties": {
    "iso:country":"US",
    "sg:address":"1125 E Main St",
    "sg:city":"Shawnee",
    "sg:classifiers":[
        {
            "category":"Organizations",
            "subcategory":"Religious Organization",
            "type":"Services"
        }
    ],
    "sg:phone":"+1 405 273 2248",
    "sg:postcode":"74801",
    "sg:province":"OK",
    "wof:name":"Singles Ministry",
    "wof:placetype":"venue"
},
  "geometry": {"coordinates":[-96.909015,35.327322],"type":"Point"}
}