{
  "type": "Feature",
  "properties": {
    "iso:country":"US",
    "sg:address":"410 SW 5th St",
    "sg:city":"Guymon",
    "sg:classifiers":[
        {
            "category":"Building & Trades",
            "subcategory":"Construction",
            "type":"Services"
        }
    ],
    "sg:phone":"+1 580 338 2084",
    "sg:postcode":"73942",
    "sg:province":"OK",
    "sg:tags":[
        "home",
        "improvement"
    ],
    "wof:name":"House Siding Inc",
    "wof:placetype":"venue"
},
  "geometry": {"coordinates":[-101.486599,36.675028],"type":"Point"}
}