{
  "type": "Feature",
  "properties": {
    "addr:full":"205 S 3rd Ave Stroud OK 74079",
    "addr:housenumber":"205",
    "addr:postcode":"74079",
    "addr:street":"S 3Rd Ave",
    "iso:country":"US",
    "sg:address":"205 S 3rd Ave",
    "sg:city":"Stroud",
    "sg:classifiers":[
        {
            "category":"Organizations",
            "subcategory":"Religious Organization",
            "type":"Services"
        }
    ],
    "sg:phone":"+1 918 968 2782",
    "sg:postcode":"74079",
    "sg:province":"OK",
    "sg:tags":[
        "church"
    ],
    "wof:name":"First Free Will Baptist Church",
    "wof:placetype":"venue"
},
  "geometry": {"coordinates":[-96.65637,35.745879],"type":"Point"}
}