{
  "type": "Feature",
  "properties": {
    "iso:country":"US",
    "sg:address":"430 Bartles Rd",
    "sg:city":"Dewey",
    "sg:classifiers":[
        {
            "category":"Social Services",
            "subcategory":"Job Training",
            "type":"Services"
        }
    ],
    "sg:phone":"+1 918 534 1862",
    "sg:postcode":"74006",
    "sg:province":"OK",
    "sg:tags":[
        "rehabilitation"
    ],
    "wof:name":"Key Rehabilitation Inc",
    "wof:placetype":"venue"
},
  "geometry": {"coordinates":[-95.95417399999999,36.774543],"type":"Point"}
}