{
  "type": "Feature",
  "properties": {
    "addr:full":"2205 N Willow Ave Broken Arrow OK 74012",
    "addr:housenumber":"2205",
    "addr:postcode":"74012",
    "addr:street":"N Willow Ave",
    "iso:country":"US",
    "sg:address":"2205 N Willow Ave",
    "sg:city":"Broken Arrow",
    "sg:classifiers":[
        {
            "category":"Professional",
            "subcategory":"Business Services",
            "type":"Services"
        }
    ],
    "sg:phone":"+1 918 622 8558",
    "sg:postcode":"74012",
    "sg:province":"OK",
    "sg:tags":[
        "packaging"
    ],
    "wof:name":"Omni Packaging",
    "wof:placetype":"venue"
},
  "geometry": {"coordinates":[-95.838613,36.073814],"type":"Point"}
}