{
  "type": "Feature",
  "properties": {
    "iso:country":"US",
    "sg:address":"2828 W Skelly Dr",
    "sg:city":"Tulsa",
    "sg:classifiers":[
        {
            "category":"Retail",
            "subcategory":"Auto Repair",
            "type":"Services"
        }
    ],
    "sg:phone":"+1 918 446 7677",
    "sg:postcode":"74107",
    "sg:province":"OK",
    "sg:tags":[
        "repairing",
        "automobile",
        "general"
    ],
    "wof:name":"Claver's Garage",
    "wof:placetype":"venue"
},
  "geometry": {"coordinates":[-96.019473,36.088579],"type":"Point"}
}