{
  "type": "Feature",
  "properties": {
    "iso:country":"US",
    "sg:address":"7101 S Perkins Rd",
    "sg:city":"Stillwater",
    "sg:classifiers":[
        {
            "category":"Home & Garden",
            "subcategory":"Mobile Homes",
            "type":"Retail Goods"
        }
    ],
    "sg:phone":"+1 405 372 3161",
    "sg:postcode":"74074",
    "sg:province":"OK",
    "wof:name":"Affordable Manufactured Homes",
    "wof:placetype":"venue"
},
  "geometry": {"coordinates":[-97.051147,36.040566],"type":"Point"}
}