{
  "type": "Feature",
  "properties": {
    "iso:country":"US",
    "sg:address":"11104 E 41st St",
    "sg:city":"Tulsa",
    "sg:classifiers":[
        {
            "category":"Restaurant",
            "type":"Food & Drink"
        }
    ],
    "sg:menulink":"http://www.allmenus.com/ok/tulsa/82214-applebees/menu/",
    "sg:phone":"+1 918 664 1400",
    "sg:postcode":"74146",
    "sg:province":"OK",
    "sg:tags":[
        "burger",
        "american",
        "sandwich",
        "soup"
    ],
    "wof:name":"Applebee's",
    "wof:placetype":"venue"
},
  "geometry": {"coordinates":[-95.85324300000001,36.103977],"type":"Point"}
}