{
  "type": "Feature",
  "properties": {
    "addr:full":"2503 E 88th St Tulsa OK 74137",
    "addr:housenumber":"2503",
    "addr:postcode":"74137",
    "addr:street":"E 88Th St",
    "iso:country":"US",
    "sg:address":"2503 E 88th St",
    "sg:city":"Tulsa",
    "sg:classifiers":[
        {
            "category":"Education",
            "subcategory":"Special Training",
            "type":"Public Place"
        }
    ],
    "sg:phone":"+1 918 296 9883",
    "sg:postcode":"74137",
    "sg:province":"OK",
    "sg:tags":[
        "center"
    ],
    "wof:name":"A-1 Early Educational Ctr",
    "wof:placetype":"venue"
},
  "geometry": {"coordinates":[-95.95423700000001,36.036011],"type":"Point"}
}