{
  "type": "Feature",
  "properties": {
    "addr:full":"116 E 15th St Edmond OK 73013",
    "addr:housenumber":"116",
    "addr:postcode":"73013",
    "addr:street":"E 15Th St",
    "iso:country":"US",
    "sg:address":"116 E 15th St",
    "sg:city":"Edmond",
    "sg:classifiers":[
        {
            "category":"Shopping",
            "subcategory":"Gifts & Souvenirs",
            "type":"Retail Goods"
        }
    ],
    "sg:phone":"+1 405 348 7583",
    "sg:postcode":"73013",
    "sg:province":"OK",
    "sg:tags":[
        "business"
    ],
    "wof:name":"Als Sports Cards",
    "wof:placetype":"venue"
},
  "geometry": {"coordinates":[-97.479782,35.638221],"type":"Point"}
}