{
  "type": "Feature",
  "properties": {
    "iso:country":"US",
    "sg:address":"1706 College Blvd",
    "sg:city":"Alva",
    "sg:classifiers":[
        {
            "category":"Shopping",
            "subcategory":"Bicycles & Sporting Goods",
            "type":"Retail Goods"
        }
    ],
    "sg:phone":"+1 580 327 3463",
    "sg:postcode":"73717",
    "sg:province":"OK",
    "sg:tags":[
        "horse",
        "furnishing"
    ],
    "wof:name":"Sports & Stress Marketing",
    "wof:placetype":"venue"
},
  "geometry": {"coordinates":[-98.665941,36.789926],"type":"Point"}
}