{
  "type": "Feature",
  "properties": {
    "addr:full":"1124 W Mansur Ave Guthrie OK 73044",
    "addr:housenumber":"1124",
    "addr:postcode":"73044",
    "addr:street":"W Mansur Ave",
    "iso:country":"US",
    "sg:address":"1124 W Mansur Ave",
    "sg:city":"Guthrie",
    "sg:classifiers":[
        {
            "category":"Organizations",
            "subcategory":"Religious Organization",
            "type":"Services"
        }
    ],
    "sg:phone":"+1 405 282 4244",
    "sg:postcode":"73044",
    "sg:province":"OK",
    "sg:tags":[
        "church"
    ],
    "wof:name":"Free Methodist Church",
    "wof:placetype":"venue"
},
  "geometry": {"coordinates":[-97.438278,35.882238],"type":"Point"}
}