{
  "type": "Feature",
  "properties": {
    "addr:full":"16203 Lola Rd Norman OK 73026",
    "addr:housenumber":"16203",
    "addr:postcode":"73026",
    "addr:street":"Lola Rd",
    "iso:country":"US",
    "sg:address":"16203 Lola Rd",
    "sg:city":"Norman",
    "sg:classifiers":[
        {
            "category":"Food & Beverages",
            "subcategory":"Groceries & Convenience Stores",
            "type":"Retail Goods"
        }
    ],
    "sg:phone":"+1 405 573 1814",
    "sg:postcode":"73026",
    "sg:province":"OK",
    "wof:name":"Grebs Convenience Store",
    "wof:placetype":"venue"
},
  "geometry": {"coordinates":[-97.203541,35.259375],"type":"Point"}
}