{
  "type": "Feature",
  "properties": {
    "iso:country":"US",
    "sg:address":"8125 E Skelly Dr",
    "sg:city":"Tulsa",
    "sg:classifiers":[
        {
            "category":"Retail",
            "subcategory":"Repair Shop",
            "type":"Services"
        }
    ],
    "sg:phone":"+1 918 627 8705",
    "sg:postcode":"74129",
    "sg:province":"OK",
    "wof:name":"Roto-Rooter",
    "wof:placetype":"venue"
},
  "geometry": {"coordinates":[-95.885493,36.121977],"type":"Point"}
}