{
  "type": "Feature",
  "properties": {
    "iso:country":"US",
    "sg:address":"1181 S Aspen Ave",
    "sg:city":"Broken Arrow",
    "sg:classifiers":[
        {
            "category":"Personal",
            "type":"Services"
        }
    ],
    "sg:phone":"+1 918 258 8344",
    "sg:postcode":"74012",
    "sg:province":"OK",
    "sg:tags":[
        "program",
        "physical",
        "exercise",
        "fitness"
    ],
    "wof:name":"Jazzercise",
    "wof:placetype":"venue"
},
  "geometry": {"coordinates":[-95.81527800000001,36.040952],"type":"Point"}
}