{
  "type": "Feature",
  "properties": {
    "addr:full":"505 NW Sheridan Rd Lawton OK 73505",
    "addr:housenumber":"505",
    "addr:postcode":"73505",
    "addr:street":"Nw Sheridan Rd",
    "iso:country":"US",
    "sg:address":"505 NW Sheridan Rd",
    "sg:city":"Lawton",
    "sg:classifiers":[
        {
            "category":"Personal",
            "type":"Services"
        }
    ],
    "sg:phone":"+1 580 355 2818",
    "sg:postcode":"73505",
    "sg:province":"OK",
    "wof:name":"Docs Weight Loss Clinic",
    "wof:placetype":"venue"
},
  "geometry": {"coordinates":[-98.422118,34.616014],"type":"Point"}
}