{
  "type": "Feature",
  "properties": {
    "iso:country":"US",
    "sg:address":"304 S Osage Ave",
    "sg:city":"Dewey",
    "sg:classifiers":[
        {
            "category":"Restaurant",
            "type":"Food & Drink"
        }
    ],
    "sg:menulink":"http://www.allmenus.com/ok/bartlesville/199393-sonic/menu/",
    "sg:phone":"+1 918 534 1028",
    "sg:postcode":"74029",
    "sg:province":"OK",
    "sg:tags":[
        "burger",
        "american"
    ],
    "wof:name":"Sonic",
    "wof:placetype":"venue"
},
  "geometry": {"coordinates":[-95.935107,36.787806],"type":"Point"}
}