{
  "type": "Feature",
  "properties": {
    "iso:country":"US",
    "sg:address":"319 N 2nd St",
    "sg:city":"Stilwell",
    "sg:classifiers":[
        {
            "category":"Health Services",
            "subcategory":"Doctor",
            "type":"Services"
        }
    ],
    "sg:phone":"+1 918 696 2072",
    "sg:postcode":"74960",
    "sg:province":"OK",
    "sg:tags":[
        "clinic",
        "dialysis"
    ],
    "sg:website":"http://www.davita.com/",
    "wof:name":"Stillwell Dialysis Ctr",
    "wof:placetype":"venue"
},
  "geometry": {"coordinates":[-94.627802,35.817679],"type":"Point"}
}