{
  "type": "Feature",
  "properties": {
    "iso:country":"US",
    "sg:address":"1405 S George Nigh Expy",
    "sg:city":"Mcalester",
    "sg:classifiers":[
        {
            "category":"Real Estate",
            "subcategory":"Real Estate Agent",
            "type":"Services"
        }
    ],
    "sg:phone":"+1 918 426 6010",
    "sg:postcode":"74501",
    "sg:province":"OK",
    "wof:name":"Realty World-Service Pros",
    "wof:placetype":"venue"
},
  "geometry": {"coordinates":[-95.75811899999999,34.898376],"type":"Point"}
}