{
  "type": "Feature",
  "properties": {
    "iso:country":"US",
    "sg:address":"2713 W Owen K Garriott Rd",
    "sg:city":"Enid",
    "sg:classifiers":[
        {
            "category":"Travel",
            "subcategory":"Hotels & Motels",
            "type":"Entertainment"
        }
    ],
    "sg:phone":"+1 580 242 6100",
    "sg:postcode":"73703",
    "sg:province":"OK",
    "wof:name":"Stratford House Inn",
    "wof:placetype":"venue"
},
  "geometry": {"coordinates":[-97.91273,36.390676],"type":"Point"}
}