{
  "type": "Feature",
  "properties": {
    "addr:full":"3735 S Harvard Ave Tulsa OK 74135",
    "addr:housenumber":"3735",
    "addr:postcode":"74135",
    "addr:street":"S Harvard Ave",
    "iso:country":"US",
    "sg:address":"3735 S Harvard Ave",
    "sg:city":"Tulsa",
    "sg:classifiers":[
        {
            "category":"Personal",
            "subcategory":"Beauty Salon",
            "type":"Services"
        }
    ],
    "sg:phone":"+1 918 747 2887",
    "sg:postcode":"74135",
    "sg:province":"OK",
    "wof:name":"Devine Inspiration",
    "wof:placetype":"venue"
},
  "geometry": {"coordinates":[-95.940158,36.109344],"type":"Point"}
}