{
  "type": "Feature",
  "properties": {
    "addr:full":"5625 Vernon Dr Newalla OK 74857",
    "addr:housenumber":"5625",
    "addr:postcode":"74857",
    "addr:street":"Vernon Dr",
    "iso:country":"US",
    "sg:address":"5625 Vernon Dr",
    "sg:city":"Newalla",
    "sg:classifiers":[
        {
            "category":"Social Services",
            "subcategory":"Child Care",
            "type":"Services"
        }
    ],
    "sg:phone":"+1 405 391 9056",
    "sg:postcode":"74857",
    "sg:province":"OK",
    "wof:name":"Newalla Child Development Ctr",
    "wof:placetype":"venue"
},
  "geometry": {"coordinates":[-97.148601,35.406309],"type":"Point"}
}