{
  "type": "Feature",
  "properties": {
    "iso:country":"US",
    "sg:address":"810 Santa Fe Ave",
    "sg:city":"Woodward",
    "sg:classifiers":[
        {
            "category":"Wholesale",
            "subcategory":"Beer",
            "type":"Manufacturing & Wholesale Goods"
        }
    ],
    "sg:phone":"+1 580 256 6074",
    "sg:postcode":"73801",
    "sg:province":"OK",
    "sg:tags":[
        "ale"
    ],
    "wof:name":"Pope Distributing Co",
    "wof:placetype":"venue"
},
  "geometry": {"coordinates":[-99.390506,36.438378],"type":"Point"}
}