{
  "type": "Feature",
  "properties": {
    "iso:country":"US",
    "sg:address":"5800 S Sunnylane Rd",
    "sg:city":"Oklahoma City",
    "sg:classifiers":[
        {
            "category":"Social Services",
            "subcategory":"Child Care",
            "type":"Services"
        }
    ],
    "sg:phone":"+1 405 677 8232",
    "sg:postcode":"73135",
    "sg:province":"OK",
    "wof:name":"Everlasting Gospel Lighthouse",
    "wof:placetype":"venue"
},
  "geometry": {"coordinates":[-97.441293,35.408121],"type":"Point"}
}