{
  "type": "Feature",
  "properties": {
    "iso:country":"US",
    "sg:address":"2200 W Memorial Rd",
    "sg:city":"Oklahoma City",
    "sg:classifiers":[
        {
            "category":"Shopping",
            "subcategory":"Hobbies, Toys, & Games",
            "type":"Retail Goods"
        }
    ],
    "sg:phone":"+1 405 755 4242",
    "sg:postcode":"73134",
    "sg:province":"OK",
    "sg:tags":[
        "craft",
        "supply"
    ],
    "sg:website":"www.michaels.com",
    "wof:name":"Michaels Arts & Crafts Store",
    "wof:placetype":"venue"
},
  "geometry": {"coordinates":[-97.550348,35.608437],"type":"Point"}
}