{
  "type": "Feature",
  "properties": {
    "addr:full":"150 W Foley St Eufaula OK 74432",
    "addr:housenumber":"150",
    "addr:postcode":"74432",
    "addr:street":"W Foley St",
    "iso:country":"US",
    "sg:address":"150 W Foley St",
    "sg:city":"Eufaula",
    "sg:classifiers":[
        {
            "category":"Professional",
            "subcategory":"Lawyer & Legal Services",
            "type":"Services"
        }
    ],
    "sg:phone":"+1 918 689 2528",
    "sg:postcode":"74432",
    "sg:province":"OK",
    "sg:tags":[
        "attorney"
    ],
    "wof:name":"W R Burnham Law Office",
    "wof:placetype":"venue"
},
  "geometry": {"coordinates":[-95.583046,35.286645],"type":"Point"}
}