{
  "type": "Feature",
  "properties": {
    "addr:full":"301 W 6th Ave Stillwater OK 74074",
    "addr:housenumber":"301",
    "addr:postcode":"74074",
    "addr:street":"W 6Th Ave",
    "iso:country":"US",
    "sg:address":"301 W 6th Ave",
    "sg:city":"Stillwater",
    "sg:classifiers":[
        {
            "category":"Autos & Motor Vehicles",
            "subcategory":"Automobile Sales",
            "type":"Retail Goods"
        }
    ],
    "sg:phone":"+1 405 377 8306",
    "sg:postcode":"74074",
    "sg:province":"OK",
    "sg:tags":[
        "car",
        "dealer"
    ],
    "wof:name":"Mitchell Motors",
    "wof:placetype":"venue"
},
  "geometry": {"coordinates":[-97.061312,36.115685],"type":"Point"}
}