{
  "type": "Feature",
  "properties": {
    "addr:full":"2359 County Rd Chickasha OK 73045",
    "addr:housenumber":"2359",
    "addr:postcode":"73045",
    "addr:street":"County Rd",
    "iso:country":"US",
    "sg:address":"2359 County Rd",
    "sg:city":"Chickasha",
    "sg:classifiers":[
        {
            "category":"Local Transit",
            "type":"Transportation"
        }
    ],
    "sg:phone":"+1 405 222 5221",
    "sg:postcode":"73045",
    "sg:province":"OK",
    "sg:tags":[
        "passenger"
    ],
    "wof:name":"Ace Limousine Inc",
    "wof:placetype":"venue"
},
  "geometry": {"coordinates":[-97.16085699999999,35.492824],"type":"Point"}
}