{
  "type": "Feature",
  "properties": {
    "addr:full":"1009 N Farra Dr Oklahoma City OK 73107",
    "addr:housenumber":"1009",
    "addr:postcode":"73107",
    "addr:street":"N Farra Dr",
    "iso:country":"US",
    "sg:address":"1009 N Farra Dr",
    "sg:city":"Oklahoma City",
    "sg:classifiers":[
        {
            "category":"Retail",
            "subcategory":"Portrait Studio",
            "type":"Services"
        }
    ],
    "sg:phone":"+1 405 601 3808",
    "sg:postcode":"73107",
    "sg:province":"OK",
    "sg:tags":[
        "photographer"
    ],
    "wof:name":"Bellyssimo Photography",
    "wof:placetype":"venue"
},
  "geometry": {"coordinates":[-97.590616,35.478611],"type":"Point"}
}