{
  "type": "Feature",
  "properties": {
    "addr:full":"210 N Roland Rd Roland OK 74954",
    "addr:housenumber":"210",
    "addr:postcode":"74954",
    "addr:street":"N Roland Rd",
    "iso:country":"US",
    "sg:address":"210 N Roland Rd",
    "sg:city":"Roland",
    "sg:classifiers":[
        {
            "category":"Food & Beverages",
            "subcategory":"Bakery",
            "type":"Retail Goods"
        }
    ],
    "sg:phone":"+1 918 427 8007",
    "sg:postcode":"74954",
    "sg:province":"OK",
    "wof:name":"Grannys Sweet Shop",
    "wof:placetype":"venue"
},
  "geometry": {"coordinates":[-94.513295,35.419751],"type":"Point"}
}