{
  "type": "Feature",
  "properties": {
    "iso:country":"US",
    "sg:address":"810 12th Ave NW",
    "sg:city":"Ardmore",
    "sg:classifiers":[
        {
            "category":"Home & Garden",
            "subcategory":"Building Materials",
            "type":"Retail Goods"
        }
    ],
    "sg:phone":"+1 580 223 5504",
    "sg:postcode":"73401",
    "sg:province":"OK",
    "sg:tags":[
        "energy",
        "conservation",
        "prod"
    ],
    "wof:name":"Spenjen Energy Consulting",
    "wof:placetype":"venue"
},
  "geometry": {"coordinates":[-97.141257,34.187073],"type":"Point"}
}