{
  "type": "Feature",
  "properties": {
    "iso:country":"US",
    "sg:address":"14205 Broadway Exn",
    "sg:city":"Edmond",
    "sg:classifiers":[
        {
            "category":"Autos & Motor Vehicles",
            "subcategory":"Boat Sales",
            "type":"Retail Goods"
        }
    ],
    "sg:phone":"+1 405 478 5668",
    "sg:postcode":"73013",
    "sg:province":"OK",
    "sg:tags":[
        "dealer",
        "sales"
    ],
    "sg:website":"www.boatworldokc.com",
    "wof:name":"Boat World",
    "wof:placetype":"venue"
},
  "geometry": {"coordinates":[-97.493089,35.614554],"type":"Point"}
}