{
  "type": "Feature",
  "properties": {
    "iso:country":"US",
    "sg:address":"121 S Broadway St",
    "sg:city":"Coweta",
    "sg:classifiers":[
        {
            "category":"Building & Trades",
            "subcategory":"Construction",
            "type":"Services"
        }
    ],
    "sg:phone":"+1 918 486 4673",
    "sg:postcode":"74429",
    "sg:province":"OK",
    "sg:tags":[
        "contractor"
    ],
    "wof:name":"Kraco Construction Co",
    "wof:placetype":"venue"
},
  "geometry": {"coordinates":[-95.650446,35.95013],"type":"Point"}
}