{
  "type": "Feature",
  "properties": {
    "iso:country":"US",
    "sg:address":"2930 E 51st St",
    "sg:city":"Tulsa",
    "sg:classifiers":[
        {
            "category":"Real Estate",
            "subcategory":"Real Estate Agent",
            "type":"Services"
        }
    ],
    "sg:phone":"+1 918 749 7781",
    "sg:postcode":"74105",
    "sg:province":"OK",
    "wof:name":"Tom Wenrick Development Co",
    "wof:placetype":"venue"
},
  "geometry": {"coordinates":[-95.943915,36.089726],"type":"Point"}
}