{
  "type": "Feature",
  "properties": {
    "iso:country":"US",
    "sg:address":"402 S Willow St",
    "sg:city":"Pauls Valley",
    "sg:classifiers":[
        {
            "category":"Real Estate",
            "subcategory":"Surveying",
            "type":"Services"
        }
    ],
    "sg:phone":"+1 405 238 3445",
    "sg:postcode":"73075",
    "sg:province":"OK",
    "wof:name":"Casey Land Survey",
    "wof:placetype":"venue"
},
  "geometry": {"coordinates":[-97.218726,34.738352],"type":"Point"}
}