{
  "type": "Feature",
  "properties": {
    "iso:country":"US",
    "sg:address":"1057 N Service Rd",
    "sg:city":"Calera",
    "sg:classifiers":[
        {
            "category":"Travel",
            "subcategory":"Hotels & Motels",
            "type":"Entertainment"
        },
        {
            "category":"Travel",
            "subcategory":"Bed & Breakfast",
            "type":"Entertainment"
        }
    ],
    "sg:phone":"+1 580 434 6200",
    "sg:postcode":"74730",
    "sg:province":"OK",
    "sg:tags":[
        "inn"
    ],
    "wof:name":"Best Express Inn & Suite",
    "wof:placetype":"venue"
},
  "geometry": {"coordinates":[-96.420587,33.94083],"type":"Point"}
}