{
  "type": "Feature",
  "properties": {
    "iso:country":"US",
    "sg:address":"401 Columbia Ave",
    "sg:city":"Sayre",
    "sg:classifiers":[
        {
            "category":"Real Estate",
            "subcategory":"Real Estate Operator",
            "type":"Services"
        }
    ],
    "sg:phone":"+1 580 928 3225",
    "sg:postcode":"73662",
    "sg:province":"OK",
    "sg:tags":[
        "apartment"
    ],
    "wof:name":"Northside Apartments",
    "wof:placetype":"venue"
},
  "geometry": {"coordinates":[-99.635396,35.307787],"type":"Point"}
}