{
  "type": "Feature",
  "properties": {
    "iso:country":"US",
    "sg:address":"2015 E Virginia Ave",
    "sg:city":"Stillwater",
    "sg:classifiers":[
        {
            "category":"Organizations",
            "subcategory":"Religious Organization",
            "type":"Services"
        }
    ],
    "sg:phone":"+1 405 624 1610",
    "sg:postcode":"74075",
    "sg:province":"OK",
    "wof:name":"Korean Baptist Church",
    "wof:placetype":"venue"
},
  "geometry": {"coordinates":[-97.03528,36.123144],"type":"Point"}
}