{
  "type": "Feature",
  "properties": {
    "iso:country":"US",
    "sg:address":"611 N Lynn Riggs Blvd",
    "sg:city":"Claremore",
    "sg:classifiers":[
        {
            "category":"Banks & Credit Unions",
            "subcategory":"Bank",
            "type":"Services"
        }
    ],
    "sg:phone":"+1 918 341 6881",
    "sg:postcode":"74017",
    "sg:province":"OK",
    "sg:tags":[
        "cashing",
        "check"
    ],
    "wof:name":"Money Mart",
    "wof:placetype":"venue"
},
  "geometry": {"coordinates":[-95.61298600000001,36.317494],"type":"Point"}
}