{
  "type": "Feature",
  "properties": {
    "addr:full":"1800 S Cherokee St Catoosa OK 74015",
    "addr:housenumber":"1800",
    "addr:postcode":"74015",
    "addr:street":"S Cherokee St",
    "iso:country":"US",
    "sg:address":"1800 S Cherokee St",
    "sg:city":"Catoosa",
    "sg:classifiers":[
        {
            "category":"Building & Trades",
            "subcategory":"Electrical",
            "type":"Services"
        }
    ],
    "sg:phone":"+1 918 379 0497",
    "sg:postcode":"74015",
    "sg:province":"OK",
    "sg:tags":[
        "electrician"
    ],
    "wof:name":"Pike Electric Inc",
    "wof:placetype":"venue"
},
  "geometry": {"coordinates":[-95.755348,36.173161],"type":"Point"}
}