{
  "type": "Feature",
  "properties": {
    "iso:country":"US",
    "sg:address":"1312 S Garnett Rd",
    "sg:city":"Tulsa",
    "sg:classifiers":[
        {
            "category":"Professional",
            "subcategory":"Lawyer & Legal Services",
            "type":"Services"
        }
    ],
    "sg:phone":"+1 918 437 4592",
    "sg:postcode":"74128",
    "sg:province":"OK",
    "sg:tags":[
        "plan"
    ],
    "wof:name":"ACFB Wells",
    "wof:placetype":"venue"
},
  "geometry": {"coordinates":[-95.851167,36.142829],"type":"Point"}
}