{
  "type": "Feature",
  "properties": {
    "iso:country":"US",
    "sg:address":"1500 NE 4th St",
    "sg:city":"Oklahoma City",
    "sg:classifiers":[
        {
            "category":"Professional",
            "type":"Services"
        }
    ],
    "sg:phone":"+1 405 319 0646",
    "sg:postcode":"73117",
    "sg:province":"OK",
    "sg:tags":[
        "establishment"
    ],
    "wof:name":"Henna Internationale LTD",
    "wof:placetype":"venue"
},
  "geometry": {"coordinates":[-97.484882,35.471464],"type":"Point"}
}