{
  "type": "Feature",
  "properties": {
    "addr:full":"608 Julie's Trl Edmond OK 73003",
    "addr:housenumber":"608",
    "addr:postcode":"73003",
    "addr:street":"Julie'S Trl",
    "iso:country":"US",
    "sg:address":"608 Julie's Trl",
    "sg:city":"Edmond",
    "sg:classifiers":[
        {
            "category":"Banks & Credit Unions",
            "subcategory":"Investment Brokerage",
            "type":"Services"
        },
        {
            "category":"Professional",
            "subcategory":"Management & Consulting",
            "type":"Services"
        }
    ],
    "sg:phone":"+1 405 340 1571",
    "sg:postcode":"73003",
    "sg:province":"OK",
    "wof:name":"M J L Investments Inc",
    "wof:placetype":"venue"
},
  "geometry": {"coordinates":[-97.516864,35.662324],"type":"Point"}
}