{
  "type": "Feature",
  "properties": {
    "iso:country":"US",
    "sg:address":"2310 S Urbana Ave",
    "sg:city":"Tulsa",
    "sg:classifiers":[
        {
            "category":"Social Services",
            "type":"Services"
        }
    ],
    "sg:phone":"+1 918 744 9446",
    "sg:postcode":"74114",
    "sg:province":"OK",
    "wof:name":"American Assn Retired People",
    "wof:placetype":"venue"
},
  "geometry": {"coordinates":[-95.925453,36.129726],"type":"Point"}
}