{
  "type": "Feature",
  "properties": {
    "iso:country":"US",
    "sg:address":"1900 N Wilburn Ave",
    "sg:city":"Bethany",
    "sg:classifiers":[
        {
            "category":"Building & Trades",
            "subcategory":"Construction",
            "type":"Services"
        }
    ],
    "sg:phone":"+1 405 326 1770",
    "sg:postcode":"73008",
    "sg:province":"OK",
    "sg:tags":[
        "painter"
    ],
    "wof:name":"Metro Painting & Remodeling",
    "wof:placetype":"venue"
},
  "geometry": {"coordinates":[-97.640417,35.488856],"type":"Point"}
}