{
  "type": "Feature",
  "properties": {
    "iso:country":"US",
    "sg:address":"201 E Ayers St",
    "sg:city":"Edmond",
    "sg:classifiers":[
        {
            "category":"Personal",
            "type":"Services"
        }
    ],
    "sg:phone":"+1 405 348 3511",
    "sg:postcode":"73034",
    "sg:province":"OK",
    "sg:tags":[
        "monogram",
        "embroidery"
    ],
    "wof:name":"Personal Touch Monograms",
    "wof:placetype":"venue"
},
  "geometry": {"coordinates":[-97.476569,35.659015],"type":"Point"}
}