{
  "type": "Feature",
  "properties": {
    "addr:full":"1520 SW 38th St Oklahoma City OK 73160",
    "addr:housenumber":"1520",
    "addr:postcode":"73160",
    "addr:street":"Sw 38Th St",
    "iso:country":"US",
    "sg:address":"1520 SW 38th St",
    "sg:city":"Oklahoma City",
    "sg:classifiers":[
        {
            "category":"Wholesale",
            "subcategory":"Groceries",
            "type":"Manufacturing & Wholesale Goods"
        }
    ],
    "sg:phone":"+1 405 794 0484",
    "sg:postcode":"73160",
    "sg:province":"OK",
    "sg:tags":[
        "confectionery"
    ],
    "wof:name":"Glasgow Distributing",
    "wof:placetype":"venue"
},
  "geometry": {"coordinates":[-97.495966,35.302491],"type":"Point"}
}