{
  "type": "Feature",
  "properties": {
    "addr:full":"522 N 14th St Ponca City OK 74601",
    "addr:housenumber":"522",
    "addr:postcode":"74601",
    "addr:street":"N 14Th St",
    "iso:country":"US",
    "sg:address":"522 N 14th St",
    "sg:city":"Ponca City",
    "sg:classifiers":[
        {
            "category":"Professional",
            "subcategory":"Business Services",
            "type":"Services"
        }
    ],
    "sg:phone":"+1 580 762 6225",
    "sg:postcode":"74601",
    "sg:province":"OK",
    "sg:tags":[
        "rental",
        "mailbox"
    ],
    "wof:name":"UPS Stores The",
    "wof:placetype":"venue"
},
  "geometry": {"coordinates":[-97.067367,36.708078],"type":"Point"}
}