{
  "type": "Feature",
  "properties": {
    "addr:full":"100 Dolomite Clinton OK 73601",
    "addr:housenumber":"100",
    "addr:postcode":"73601",
    "addr:street":"Dolomite",
    "iso:country":"US",
    "sg:address":"100 Dolomite",
    "sg:city":"Clinton",
    "sg:classifiers":[
        {
            "category":"Autos & Motor Vehicles",
            "subcategory":"Auto Supplies",
            "type":"Retail Goods"
        }
    ],
    "sg:phone":"+1 580 323 1251",
    "sg:postcode":"73601",
    "sg:province":"OK",
    "sg:tags":[
        "automotive",
        "parts"
    ],
    "wof:name":"Terrys Auto Parts",
    "wof:placetype":"venue"
},
  "geometry": {"coordinates":[-98.990742,35.515341],"type":"Point"}
}