{
  "type": "Feature",
  "properties": {
    "iso:country":"US",
    "sg:address":"1200 N 16th St",
    "sg:city":"Chickasha",
    "sg:classifiers":[
        {
            "category":"Wholesale",
            "subcategory":"Hardware",
            "type":"Manufacturing & Wholesale Goods"
        }
    ],
    "sg:phone":"+1 405 677 3305",
    "sg:postcode":"73018",
    "sg:province":"OK",
    "sg:tags":[
        "fastener"
    ],
    "wof:name":"Purchased Parts Group",
    "wof:placetype":"venue"
},
  "geometry": {"coordinates":[-97.95262,35.067595],"type":"Point"}
}