{
  "type": "Feature",
  "properties": {
    "iso:country":"US",
    "sg:address":"115 N Crumley St",
    "sg:city":"Guymon",
    "sg:classifiers":[
        {
            "category":"Retail",
            "subcategory":"Auto Repair",
            "type":"Services"
        }
    ],
    "sg:phone":"+1 580 338 3528",
    "sg:postcode":"73942",
    "sg:province":"OK",
    "sg:tags":[
        "body"
    ],
    "wof:name":"Ep Paint & Body",
    "wof:placetype":"venue"
},
  "geometry": {"coordinates":[-101.478878,36.678781],"type":"Point"}
}