{
  "type": "Feature",
  "properties": {
    "addr:full":"1402 N Main St Bache OK 74501",
    "addr:housenumber":"1402",
    "addr:postcode":"74501",
    "addr:street":"N Main St",
    "iso:country":"US",
    "sg:address":"1402 N Main St",
    "sg:city":"Bache",
    "sg:classifiers":[
        {
            "category":"Autos & Motor Vehicles",
            "subcategory":"Auto Supplies",
            "type":"Retail Goods"
        },
        {
            "category":"Wholesale",
            "subcategory":"Auto Parts",
            "type":"Manufacturing & Wholesale Goods"
        }
    ],
    "sg:phone":"+1 918 423 3030",
    "sg:postcode":"74501",
    "sg:province":"OK",
    "sg:tags":[
        "automobile"
    ],
    "wof:name":"Kiamichi Automotive Warehouse",
    "wof:placetype":"venue"
},
  "geometry": {"coordinates":[-95.76449100000001,34.946632],"type":"Point"}
}