{
  "type": "Feature",
  "properties": {
    "addr:full":"1611 S Utica Ave Tulsa OK 74104",
    "addr:housenumber":"1611",
    "addr:postcode":"74104",
    "addr:street":"S Utica Ave",
    "iso:country":"US",
    "sg:address":"1611 S Utica Ave",
    "sg:city":"Tulsa",
    "sg:classifiers":[
        {
            "category":"Shopping",
            "type":"Retail Goods"
        }
    ],
    "sg:phone":"+1 918 809 6095",
    "sg:postcode":"74104",
    "sg:province":"OK",
    "sg:tags":[
        "merchandise"
    ],
    "wof:name":"Delta Course",
    "wof:placetype":"venue"
},
  "geometry": {"coordinates":[-95.967033,36.138169],"type":"Point"}
}