{
  "type": "Feature",
  "properties": {
    "addr:full":"6733 S Yale Ave Tulsa OK 74136",
    "addr:housenumber":"6733",
    "addr:postcode":"74136",
    "addr:street":"S Yale Ave",
    "iso:country":"US",
    "sg:address":"6733 S Yale Ave",
    "sg:city":"Tulsa",
    "sg:classifiers":[
        {
            "category":"Mining & Drilling",
            "type":"Manufacturing & Wholesale Goods"
        }
    ],
    "sg:phone":"+1 918 491 0989",
    "sg:postcode":"74136",
    "sg:province":"OK",
    "sg:tags":[
        "development",
        "gas",
        "oil",
        "exploration"
    ],
    "wof:name":"Kaiser Francis Oil Co",
    "wof:placetype":"venue"
},
  "geometry": {"coordinates":[-95.922003,36.062997],"type":"Point"}
}