{
  "type": "Feature",
  "properties": {
    "iso:country":"US",
    "sg:address":"4631 Harold Scoggins Dr",
    "sg:city":"Muskogee",
    "sg:classifiers":[
        {
            "category":"Manufacturing",
            "subcategory":"Metals",
            "type":"Manufacturing & Wholesale Goods"
        },
        {
            "category":"Wholesale",
            "subcategory":"Metals & Minerals",
            "type":"Manufacturing & Wholesale Goods"
        }
    ],
    "sg:phone":"+1 918 781 1430",
    "sg:postcode":"74403",
    "sg:province":"OK",
    "sg:tags":[
        "pipe",
        "plant",
        "processing"
    ],
    "wof:name":"Paragon Industries Inc",
    "wof:placetype":"venue"
},
  "geometry": {"coordinates":[-95.302019,35.787162],"type":"Point"}
}