{
  "type": "Feature",
  "properties": {
    "iso:country":"US",
    "sg:address":"1215 SW 44th St",
    "sg:city":"Oklahoma City",
    "sg:classifiers":[
        {
            "category":"Insurance",
            "subcategory":"Insurance Agent",
            "type":"Services"
        }
    ],
    "sg:phone":"+1 405 682 8477",
    "sg:postcode":"73109",
    "sg:province":"OK",
    "wof:name":"Solutions Insurance & Invstmnt",
    "wof:placetype":"venue"
},
  "geometry": {"coordinates":[-97.538831,35.420808],"type":"Point"}
}