{
  "type": "Feature",
  "properties": {
    "iso:country":"US",
    "sg:address":"6717 NW 23rd St",
    "sg:city":"Bethany",
    "sg:classifiers":[
        {
            "category":"Restaurant",
            "type":"Food & Drink"
        }
    ],
    "sg:phone":"+1 405 495 8388",
    "sg:postcode":"73008",
    "sg:province":"OK",
    "sg:tags":[
        "chinese"
    ],
    "wof:name":"Mandarin Express",
    "wof:placetype":"venue"
},
  "geometry": {"coordinates":[-97.630221,35.493423],"type":"Point"}
}