{
  "type": "Feature",
  "properties": {
    "iso:country":"US",
    "sg:address":"1729 College Blvd",
    "sg:city":"Alva",
    "sg:classifiers":[
        {
            "category":"Banks & Credit Unions",
            "subcategory":"Bank",
            "type":"Services"
        }
    ],
    "sg:phone":"+1 580 327 5500",
    "sg:postcode":"73717",
    "sg:province":"OK",
    "wof:name":"Community National Bank",
    "wof:placetype":"venue"
},
  "geometry": {"coordinates":[-98.666093,36.789618],"type":"Point"}
}