{
  "type": "Feature",
  "properties": {
    "iso:country":"US",
    "sg:address":"4733 S Union Ave",
    "sg:city":"Tulsa",
    "sg:classifiers":[
        {
            "category":"Social Services",
            "type":"Services"
        }
    ],
    "sg:phone":"+1 918 446 8447",
    "sg:postcode":"74107",
    "sg:province":"OK",
    "sg:tags":[
        "information",
        "planning",
        "center",
        "family"
    ],
    "sg:website":"www.ppaeo.org",
    "wof:name":"Planned Parenthood",
    "wof:placetype":"venue"
},
  "geometry": {"coordinates":[-96.011572,36.092393],"type":"Point"}
}