{
  "type": "Feature",
  "properties": {
    "iso:country":"US",
    "sg:address":"306 W 92nd St",
    "sg:city":"Perkins",
    "sg:classifiers":[
        {
            "category":"Recreation",
            "type":"Entertainment"
        }
    ],
    "sg:phone":"+1 405 377 9186",
    "sg:postcode":"74059",
    "sg:province":"OK",
    "sg:tags":[
        "stable"
    ],
    "wof:name":"Circle F Stables LLC",
    "wof:placetype":"venue"
},
  "geometry": {"coordinates":[-97.062506,36.014511],"type":"Point"}
}