{
  "type": "Feature",
  "properties": {
    "addr:full":"6400 Industrial Blvd Edmond OK 73034",
    "addr:housenumber":"6400",
    "addr:postcode":"73034",
    "addr:street":"Industrial Blvd",
    "iso:country":"US",
    "sg:address":"6400 Industrial Blvd",
    "sg:city":"Edmond",
    "sg:classifiers":[
        {
            "category":"Education",
            "subcategory":"School",
            "type":"Public Place"
        }
    ],
    "sg:phone":"+1 405 341 4923",
    "sg:postcode":"73034",
    "sg:province":"OK",
    "wof:name":"Faith Christian School",
    "wof:placetype":"venue"
},
  "geometry": {"coordinates":[-97.415724,35.720347],"type":"Point"}
}