{
  "type": "Feature",
  "properties": {
    "iso:country":"US",
    "sg:address":"7998 E 41st St",
    "sg:city":"Tulsa",
    "sg:classifiers":[
        {
            "category":"Food & Beverages",
            "subcategory":"Groceries & Convenience Stores",
            "type":"Retail Goods"
        }
    ],
    "sg:phone":"+1 918 622 6631",
    "sg:postcode":"74145",
    "sg:province":"OK",
    "wof:name":"Fastrip",
    "wof:placetype":"venue"
},
  "geometry": {"coordinates":[-95.887485,36.104344],"type":"Point"}
}