{
  "type": "Feature",
  "properties": {
    "addr:full":"10601 Laramie Rd Yukon OK 73099",
    "addr:housenumber":"10601",
    "addr:postcode":"73099",
    "addr:street":"Laramie Rd",
    "iso:country":"US",
    "sg:address":"10601 Laramie Rd",
    "sg:city":"Yukon",
    "sg:classifiers":[
        {
            "category":"Manufacturing",
            "subcategory":"Metals",
            "type":"Manufacturing & Wholesale Goods"
        }
    ],
    "sg:phone":"+1 405 722 7447",
    "sg:postcode":"73099",
    "sg:province":"OK",
    "sg:tags":[
        "tower"
    ],
    "wof:name":"Rocky Mtn Erection Co",
    "wof:placetype":"venue"
},
  "geometry": {"coordinates":[-97.69834,35.577876],"type":"Point"}
}