{
  "type": "Feature",
  "properties": {
    "iso:country":"US",
    "sg:address":"3300 S Aspen Ave",
    "sg:city":"Broken Arrow",
    "sg:classifiers":[
        {
            "category":"Health Services",
            "subcategory":"Doctor",
            "type":"Services"
        }
    ],
    "sg:phone":"+1 918 455 2416",
    "sg:postcode":"74012",
    "sg:province":"OK",
    "sg:tags":[
        "medical"
    ],
    "wof:name":"Family Practice & Health",
    "wof:placetype":"venue"
},
  "geometry": {"coordinates":[-95.815329,36.01838],"type":"Point"}
}