{
  "type": "Feature",
  "properties": {
    "addr:full":"1411 W Chestnut Ave Enid OK 73703",
    "addr:housenumber":"1411",
    "addr:postcode":"73703",
    "addr:street":"W Chestnut Ave",
    "iso:country":"US",
    "sg:address":"1411 W Chestnut Ave",
    "sg:city":"Enid",
    "sg:classifiers":[
        {
            "category":"Manufacturing",
            "subcategory":"Glass & Minerals",
            "type":"Manufacturing & Wholesale Goods"
        }
    ],
    "sg:phone":"+1 580 234 2052",
    "sg:postcode":"73703",
    "sg:province":"OK",
    "sg:tags":[
        "concrete",
        "block",
        "mfg"
    ],
    "wof:name":"Dolese Bros Co",
    "wof:placetype":"venue"
},
  "geometry": {"coordinates":[-97.895365,36.405266],"type":"Point"}
}