{
  "type": "Feature",
  "properties": {
    "iso:country":"US",
    "sg:address":"116 N 4th St",
    "sg:city":"Ponca City",
    "sg:classifiers":[
        {
            "category":"Restaurant",
            "type":"Food & Drink"
        }
    ],
    "sg:phone":"+1 580 718 0909",
    "sg:postcode":"74601",
    "sg:province":"OK",
    "wof:name":"Ponca Townsite Co",
    "wof:placetype":"venue"
},
  "geometry": {"coordinates":[-97.079953,36.704494],"type":"Point"}
}