{
  "type": "Feature",
  "properties": {
    "iso:country":"US",
    "sg:address":"701 W 27th St",
    "sg:city":"Sand Springs",
    "sg:classifiers":[
        {
            "category":"Professional",
            "subcategory":"Business Services",
            "type":"Services"
        }
    ],
    "sg:phone":"+1 918 382 9171",
    "sg:postcode":"74063",
    "sg:province":"OK",
    "wof:name":"Jones Enterprises",
    "wof:placetype":"venue"
},
  "geometry": {"coordinates":[-96.134777,36.123408],"type":"Point"}
}