{
  "type": "Feature",
  "properties": {
    "addr:full":"925 N Main St Muskogee OK 74401",
    "addr:housenumber":"925",
    "addr:postcode":"74401",
    "addr:street":"N Main St",
    "iso:country":"US",
    "sg:address":"925 N Main St",
    "sg:city":"Muskogee",
    "sg:classifiers":[
        {
            "category":"Autos & Motor Vehicles",
            "subcategory":"Automobile Sales",
            "type":"Retail Goods"
        }
    ],
    "sg:phone":"+1 918 683 5422",
    "sg:postcode":"74401",
    "sg:province":"OK",
    "sg:tags":[
        "car",
        "dealer"
    ],
    "wof:name":"Dandie Auto Sales",
    "wof:placetype":"venue"
},
  "geometry": {"coordinates":[-95.363168,35.758937],"type":"Point"}
}