{
  "type": "Feature",
  "properties": {
    "addr:full":"1701 S Midwest Blvd Oklahoma City OK 73110",
    "addr:housenumber":"1701",
    "addr:postcode":"73110",
    "addr:street":"S Midwest Blvd",
    "iso:country":"US",
    "sg:address":"1701 S Midwest Blvd",
    "sg:city":"Oklahoma City",
    "sg:classifiers":[
        {
            "category":"Personal",
            "subcategory":"Barber",
            "type":"Services"
        }
    ],
    "sg:phone":"+1 405 733 7748",
    "sg:postcode":"73110",
    "sg:province":"OK",
    "wof:name":"Cheree's Barber & Style Shop",
    "wof:placetype":"venue"
},
  "geometry": {"coordinates":[-97.38845499999999,35.447815],"type":"Point"}
}