{
  "type": "Feature",
  "properties": {
    "iso:country":"US",
    "sg:address":"2824 W Country Club Dr",
    "sg:city":"Oklahoma City",
    "sg:classifiers":[
        {
            "category":"Restaurant",
            "type":"Food & Drink"
        }
    ],
    "sg:menulink":"http://www.allmenus.com/ok/oklahoma-city/219333-michaels-grill/menu/",
    "sg:phone":"+1 405 810 9000",
    "sg:postcode":"73116",
    "sg:province":"OK",
    "sg:tags":[
        "american"
    ],
    "wof:name":"Michael's Grill",
    "wof:placetype":"venue"
},
  "geometry": {"coordinates":[-97.564211,35.547266],"type":"Point"}
}