{
  "type": "Feature",
  "properties": {
    "iso:country":"US",
    "sg:address":"2205 E 51st St S",
    "sg:city":"Tulsa",
    "sg:classifiers":[
        {
            "category":"Professional",
            "subcategory":"Business Services",
            "type":"Services"
        }
    ],
    "sg:phone":"+1 918 743 7877",
    "sg:postcode":"74105",
    "sg:province":"OK",
    "sg:tags":[
        "appraiser"
    ],
    "wof:name":"Property Damage Appraisers Inc",
    "wof:placetype":"venue"
},
  "geometry": {"coordinates":[-95.95817,36.089835],"type":"Point"}
}