{
  "type": "Feature",
  "properties": {
    "addr:full":"7943 E 50th St Tulsa OK 74145",
    "addr:housenumber":"7943",
    "addr:postcode":"74145",
    "addr:street":"E 50Th St",
    "iso:country":"US",
    "sg:address":"7943 E 50th St",
    "sg:city":"Tulsa",
    "sg:classifiers":[
        {
            "category":"Home & Garden",
            "subcategory":"Carpets & Floor Coverings",
            "type":"Retail Goods"
        }
    ],
    "sg:phone":"+1 918 607 1386",
    "sg:postcode":"74145",
    "sg:province":"OK",
    "sg:tags":[
        "material"
    ],
    "wof:name":"Natural Stone Source",
    "wof:placetype":"venue"
},
  "geometry": {"coordinates":[-95.887304,36.091599],"type":"Point"}
}