{
  "type": "Feature",
  "properties": {
    "iso:country":"US",
    "sg:address":"2830 Charles Page Blvd",
    "sg:city":"Tulsa",
    "sg:classifiers":[
        {
            "category":"Wholesale",
            "subcategory":"Electrical",
            "type":"Manufacturing & Wholesale Goods"
        }
    ],
    "sg:phone":"+1 918 576 0000",
    "sg:postcode":"74127",
    "sg:province":"OK",
    "sg:tags":[
        "manufacture",
        "communication",
        "tower",
        "permanent",
        "portable"
    ],
    "sg:website":"www.goalltech.com",
    "wof:name":"Alltech Communications",
    "wof:placetype":"venue"
},
  "geometry": {"coordinates":[-96.025861,36.151123],"type":"Point"}
}