{
  "type": "Feature",
  "properties": {
    "addr:full":"1131 Enterprise Ave Oklahoma City OK 73128",
    "addr:housenumber":"1131",
    "addr:postcode":"73128",
    "addr:street":"Enterprise Ave",
    "iso:country":"US",
    "sg:address":"1131 Enterprise Ave",
    "sg:city":"Oklahoma City",
    "sg:classifiers":[
        {
            "category":"Home & Garden",
            "subcategory":"Building Materials",
            "type":"Retail Goods"
        }
    ],
    "sg:phone":"+1 405 947 8116",
    "sg:postcode":"73128",
    "sg:province":"OK",
    "sg:tags":[
        "roofing"
    ],
    "wof:name":"ABC Supply Co",
    "wof:placetype":"venue"
},
  "geometry": {"coordinates":[-97.60331499999999,35.456282],"type":"Point"}
}