{
  "type": "Feature",
  "properties": {
    "iso:country":"US",
    "sg:address":"200 S Wewoka Ave",
    "sg:city":"Wewoka",
    "sg:classifiers":[
        {
            "category":"Real Estate",
            "subcategory":"Real Estate Agent",
            "type":"Services"
        }
    ],
    "sg:phone":"+1 405 257 3335",
    "sg:postcode":"74884",
    "sg:province":"OK",
    "wof:name":"National Real Estate Agency",
    "wof:placetype":"venue"
},
  "geometry": {"coordinates":[-96.491434,35.15768],"type":"Point"}
}