{
  "type": "Feature",
  "properties": {
    "iso:country":"US",
    "sg:address":"1223 W 14th St",
    "sg:city":"Sulphur",
    "sg:classifiers":[
        {
            "category":"Personal",
            "subcategory":"Beauty Salon",
            "type":"Services"
        }
    ],
    "sg:phone":"+1 580 622 4454",
    "sg:postcode":"73086",
    "sg:province":"OK",
    "wof:name":"Sue's Hair Shop",
    "wof:placetype":"venue"
},
  "geometry": {"coordinates":[-96.984786,34.510113],"type":"Point"}
}