{
  "type": "Feature",
  "properties": {
    "addr:full":"10900 Hefner Pointe Dr Oklahoma City OK 73120",
    "addr:postcode":"10900;73120",
    "addr:street":"Hefner Pointe Dr",
    "iso:country":"US",
    "sg:address":"10900 Hefner Pointe Dr",
    "sg:city":"Oklahoma City",
    "sg:classifiers":[
        {
            "category":"Banks & Credit Unions",
            "subcategory":"Bank",
            "type":"Services"
        }
    ],
    "sg:phone":"+1 405 749 6880",
    "sg:postcode":"73120",
    "sg:province":"OK",
    "sg:tags":[
        "escrow"
    ],
    "wof:name":"Lawyers Title",
    "wof:placetype":"venue"
},
  "geometry": {"coordinates":[-97.58503399999999,35.583271],"type":"Point"}
}