{
  "type": "Feature",
  "properties": {
    "addr:full":"908 E St Snyder OK 73566",
    "addr:housenumber":"908",
    "addr:postcode":"73566",
    "addr:street":"E St",
    "iso:country":"US",
    "sg:address":"908 E St",
    "sg:city":"Snyder",
    "sg:classifiers":[
        {
            "category":"Organizations",
            "subcategory":"Religious Organization",
            "type":"Services"
        }
    ],
    "sg:phone":"+1 580 569 4308",
    "sg:postcode":"73566",
    "sg:province":"OK",
    "wof:name":"Methodist Parsonage",
    "wof:placetype":"venue"
},
  "geometry": {"coordinates":[-98.951784,34.656668],"type":"Point"}
}