{
  "type": "Feature",
  "properties": {
    "addr:full":"828 W Danforth Rd Edmond OK 73003",
    "addr:housenumber":"828",
    "addr:postcode":"73003",
    "addr:street":"W Danforth Rd",
    "iso:country":"US",
    "sg:address":"828 W Danforth Rd",
    "sg:city":"Edmond",
    "sg:classifiers":[
        {
            "category":"Retail",
            "subcategory":"Portrait Studio",
            "type":"Services"
        }
    ],
    "sg:phone":"+1 405 340 3676",
    "sg:postcode":"73003",
    "sg:province":"OK",
    "sg:tags":[
        "photographer"
    ],
    "wof:name":"Photo Loft",
    "wof:placetype":"venue"
},
  "geometry": {"coordinates":[-97.492676,35.667368],"type":"Point"}
}