{
  "type": "Feature",
  "properties": {
    "iso:country":"US",
    "sg:address":"3808 E 51st St S",
    "sg:city":"Tulsa",
    "sg:classifiers":[
        {
            "category":"Health Services",
            "subcategory":"Doctor",
            "type":"Services"
        }
    ],
    "sg:phone":"+1 918 749 5033",
    "sg:postcode":"74135",
    "sg:province":"OK",
    "wof:name":"Firey Kimberley A",
    "wof:placetype":"venue"
},
  "geometry": {"coordinates":[-95.932545,36.089763],"type":"Point"}
}