{
  "type": "Feature",
  "properties": {
    "iso:country":"US",
    "sg:address":"2956 SW 59th St",
    "sg:city":"Oklahoma City",
    "sg:classifiers":[
        {
            "category":"Cinema",
            "subcategory":"Movie Theater",
            "type":"Entertainment"
        }
    ],
    "sg:phone":"+1 405 682 5419",
    "sg:postcode":"73119",
    "sg:province":"OK",
    "wof:name":"Almonte Cinema Six",
    "wof:placetype":"venue"
},
  "geometry": {"coordinates":[-97.568451,35.406092],"type":"Point"}
}