{
  "type": "Feature",
  "properties": {
    "addr:full":"9600 Broadway Exn Oklahoma City OK 73114",
    "addr:housenumber":"9600",
    "addr:postcode":"73114",
    "addr:street":"Broadway",
    "iso:country":"US",
    "sg:address":"9600 Broadway Exn",
    "sg:city":"Oklahoma City",
    "sg:classifiers":[
        {
            "category":"Professional",
            "subcategory":"Management & Consulting",
            "type":"Services"
        }
    ],
    "sg:phone":"+1 405 600 0711",
    "sg:postcode":"73114",
    "sg:province":"OK",
    "sg:tags":[
        "consultant",
        "energy",
        "conservation"
    ],
    "wof:name":"GMX Resources Inc",
    "wof:placetype":"venue"
},
  "geometry": {"coordinates":[-97.51374199999999,35.568192],"type":"Point"}
}