{
  "type": "Feature",
  "properties": {
    "addr:full":"3345 S Ann Arbor Ave Oklahoma City OK 73179",
    "addr:housenumber":"3345",
    "addr:postcode":"73179",
    "addr:street":"S Ann Arbor Ave",
    "iso:country":"US",
    "sg:address":"3345 S Ann Arbor Ave",
    "sg:city":"Oklahoma City",
    "sg:classifiers":[
        {
            "category":"Manufacturing",
            "subcategory":"Tools & Machinery",
            "type":"Manufacturing & Wholesale Goods"
        }
    ],
    "sg:phone":"+1 405 682 3003",
    "sg:postcode":"73179",
    "sg:province":"OK",
    "sg:tags":[
        "shop",
        "sheet",
        "metal",
        "machine",
        "gasket",
        "fabrication"
    ],
    "sg:website":"www.necoind.com",
    "wof:name":"Neco Industries Inc",
    "wof:placetype":"venue"
},
  "geometry": {"coordinates":[-97.61100999999999,35.432146],"type":"Point"}
}