{
  "type": "Feature",
  "properties": {
    "iso:country":"US",
    "sg:address":"2205 Industrial Rd",
    "sg:city":"Broken Arrow",
    "sg:classifiers":[
        {
            "category":"Building & Trades",
            "subcategory":"Cleaning & Sanitation",
            "type":"Services"
        }
    ],
    "sg:phone":"+1 918 251 9077",
    "sg:postcode":"74066",
    "sg:province":"OK",
    "sg:tags":[
        "janitor"
    ],
    "sg:website":"www.cleanovation.net",
    "wof:name":"Cleanovation",
    "wof:placetype":"venue"
},
  "geometry": {"coordinates":[-96.10234,36.026764],"type":"Point"}
}