{
  "type": "Feature",
  "properties": {
    "iso:country":"US",
    "sg:address":"12402 NW 15th St",
    "sg:city":"Oklahoma City",
    "sg:classifiers":[
        {
            "category":"Utilities",
            "subcategory":"Telephone",
            "type":"Services"
        }
    ],
    "sg:phone":"+1 405 769 5133",
    "sg:postcode":"73127",
    "sg:province":"OK",
    "sg:tags":[
        "communications",
        "voice",
        "datum",
        "microwave"
    ],
    "wof:name":"Brcom Inc",
    "wof:placetype":"venue"
},
  "geometry": {"coordinates":[-97.706026,35.483656],"type":"Point"}
}