{
  "type": "Feature",
  "properties": {
    "addr:full":"6705 N Midwest Blvd Edmond OK 73034",
    "addr:housenumber":"6705",
    "addr:postcode":"73034",
    "addr:street":"N Midwest Blvd",
    "iso:country":"US",
    "sg:address":"6705 N Midwest Blvd",
    "sg:city":"Edmond",
    "sg:classifiers":[
        {
            "category":"Real Estate",
            "subcategory":"Real Estate Agent",
            "type":"Services"
        }
    ],
    "sg:phone":"+1 405 359 1985",
    "sg:postcode":"73034",
    "sg:province":"OK",
    "wof:name":"Jungroth Appraisal Inc",
    "wof:placetype":"venue"
},
  "geometry": {"coordinates":[-97.389555,35.724334],"type":"Point"}
}