{
  "type": "Feature",
  "properties": {
    "addr:full":"2547 E 21st St Tulsa OK 74114",
    "addr:housenumber":"2547",
    "addr:postcode":"74114",
    "addr:street":"E 21St St",
    "iso:country":"US",
    "sg:address":"2547 E 21st St",
    "sg:city":"Tulsa",
    "sg:classifiers":[
        {
            "category":"Banks & Credit Unions",
            "subcategory":"Bank",
            "type":"Services"
        }
    ],
    "sg:phone":"+1 918 747 6671",
    "sg:postcode":"74114",
    "sg:province":"OK",
    "wof:name":"Midfirst Bank",
    "wof:placetype":"venue"
},
  "geometry": {"coordinates":[-95.954182,36.13332],"type":"Point"}
}