{
  "type": "Feature",
  "properties": {
    "iso:country":"US",
    "sg:address":"110 Commerce St",
    "sg:city":"Commerce",
    "sg:classifiers":[
        {
            "category":"Organizations",
            "subcategory":"Community Association",
            "type":"Services"
        }
    ],
    "sg:phone":"+1 918 675 5375",
    "sg:postcode":"74339",
    "sg:province":"OK",
    "sg:tags":[
        "military"
    ],
    "wof:name":"Disabled American Veterans",
    "wof:placetype":"venue"
},
  "geometry": {"coordinates":[-94.87627999999999,36.933305],"type":"Point"}
}