{
  "type": "Feature",
  "properties": {
    "iso:country":"US",
    "sg:address":"8700 NW Expy",
    "sg:city":"Oklahoma City",
    "sg:classifiers":[
        {
            "category":"Autos & Motor Vehicles",
            "subcategory":"Automobile Sales",
            "type":"Retail Goods"
        }
    ],
    "sg:phone":"+1 405 621 6000",
    "sg:postcode":"73162",
    "sg:province":"OK",
    "sg:tags":[
        "car",
        "dealer"
    ],
    "wof:name":"Steve Bailey Honda Used Cars",
    "wof:placetype":"venue"
},
  "geometry": {"coordinates":[-97.668014,35.570606],"type":"Point"}
}