{
  "type": "Feature",
  "properties": {
    "addr:full":"8020 SW 3rd St Oklahoma City OK 73128",
    "addr:housenumber":"8020",
    "addr:postcode":"73128",
    "addr:street":"Sw 3Rd St",
    "iso:country":"US",
    "sg:address":"8020 SW 3rd St",
    "sg:city":"Oklahoma City",
    "sg:classifiers":[
        {
            "category":"Restaurant",
            "type":"Food & Drink"
        }
    ],
    "sg:phone":"+1 405 495 4367",
    "sg:postcode":"73128",
    "sg:province":"OK",
    "sg:tags":[
        "eating"
    ],
    "wof:name":"Waffle House",
    "wof:placetype":"venue"
},
  "geometry": {"coordinates":[-97.65550500000001,35.462409],"type":"Point"}
}