{
  "type": "Feature",
  "properties": {
    "iso:country":"US",
    "sg:address":"1298 S Muskogee Ave",
    "sg:city":"Tahlequah",
    "sg:classifiers":[
        {
            "category":"Autos & Motor Vehicles",
            "subcategory":"Automobile Sales",
            "type":"Retail Goods"
        }
    ],
    "sg:phone":"+1 918 456 6321",
    "sg:postcode":"74464",
    "sg:province":"OK",
    "sg:tags":[
        "car",
        "dealer"
    ],
    "wof:name":"Hensley's Auto Sales",
    "wof:placetype":"venue"
},
  "geometry": {"coordinates":[-94.97521399999999,35.899552],"type":"Point"}
}