{
  "type": "Feature",
  "properties": {
    "iso:country":"US",
    "sg:address":"8101 S Walker Ave",
    "sg:city":"Oklahoma City",
    "sg:classifiers":[
        {
            "category":"Health Services",
            "subcategory":"Doctor",
            "type":"Services"
        }
    ],
    "sg:phone":"+1 405 616 7770",
    "sg:postcode":"73139",
    "sg:province":"OK",
    "sg:tags":[
        "dentist"
    ],
    "wof:name":"Stephen W Herren DDS PC",
    "wof:placetype":"venue"
},
  "geometry": {"coordinates":[-97.521351,35.387943],"type":"Point"}
}