{
  "type": "Feature",
  "properties": {
    "iso:country":"US",
    "sg:address":"1245 S Eastern Ave",
    "sg:city":"Moore",
    "sg:classifiers":[
        {
            "category":"Building & Trades",
            "subcategory":"Construction",
            "type":"Services"
        }
    ],
    "sg:phone":"+1 405 790 0653",
    "sg:postcode":"73160",
    "sg:province":"OK",
    "sg:tags":[
        "home",
        "builder"
    ],
    "wof:name":"Vesta Homes",
    "wof:placetype":"venue"
},
  "geometry": {"coordinates":[-97.476877,35.328334],"type":"Point"}
}