{
  "type": "Feature",
  "properties": {
    "iso:country":"US",
    "sg:address":"429 E Downs Ave",
    "sg:city":"Woodward",
    "sg:classifiers":[
        {
            "category":"Health Services",
            "subcategory":"Clinic",
            "type":"Services"
        }
    ],
    "sg:phone":"+1 580 256 2560",
    "sg:postcode":"73801",
    "sg:province":"OK",
    "sg:tags":[
        "specialty",
        "outpatient"
    ],
    "wof:name":"Rehabsource L L C",
    "wof:placetype":"venue"
},
  "geometry": {"coordinates":[-99.37457000000001,36.418958],"type":"Point"}
}