{
  "type": "Feature",
  "properties": {
    "addr:full":"404 N Main St Jay OK 74346",
    "addr:housenumber":"404",
    "addr:postcode":"74346",
    "addr:street":"N Main St",
    "iso:country":"US",
    "sg:address":"404 N Main St",
    "sg:city":"Jay",
    "sg:classifiers":[
        {
            "category":"Restaurant",
            "type":"Food & Drink"
        }
    ],
    "sg:menulink":"http://www.allmenus.com/ok/jay/196725-mcdonalds/menu/",
    "sg:postcode":"74346",
    "sg:province":"OK",
    "sg:tags":[
        "burger",
        "american"
    ],
    "wof:name":"McDonald's",
    "wof:placetype":"venue"
},
  "geometry": {"coordinates":[-94.786158,36.42626],"type":"Point"}
}