{
  "type": "Feature",
  "properties": {
    "iso:country":"US",
    "sg:address":"7133 S Yale Ave",
    "sg:city":"Tulsa",
    "sg:classifiers":[
        {
            "category":"Professional",
            "type":"Services"
        }
    ],
    "sg:phone":"+1 918 495 3947",
    "sg:postcode":"74136",
    "sg:province":"OK",
    "sg:tags":[
        "establishment"
    ],
    "wof:name":"Allstateinsurance Companies",
    "wof:placetype":"venue"
},
  "geometry": {"coordinates":[-95.922007,36.06048],"type":"Point"}
}