{
  "type": "Feature",
  "properties": {
    "iso:country":"US",
    "sg:address":"3076 SW 67th St",
    "sg:city":"Oklahoma City",
    "sg:classifiers":[
        {
            "category":"Manufacturing",
            "subcategory":"Toys & Sporting Goods",
            "type":"Manufacturing & Wholesale Goods"
        }
    ],
    "sg:phone":"+1 405 570 7155",
    "sg:postcode":"73159",
    "sg:province":"OK",
    "sg:tags":[
        "mfg"
    ],
    "wof:name":"Dgraph Sports Apparel",
    "wof:placetype":"venue"
},
  "geometry": {"coordinates":[-97.570037,35.397369],"type":"Point"}
}