{
  "type": "Feature",
  "properties": {
    "addr:full":"6670 S Lewis Ave Tulsa OK 74136",
    "addr:housenumber":"6670",
    "addr:postcode":"74136",
    "addr:street":"S Lewis Ave",
    "iso:country":"US",
    "sg:address":"6670 S Lewis Ave",
    "sg:city":"Tulsa",
    "sg:classifiers":[
        {
            "category":"Restaurant",
            "type":"Food & Drink"
        }
    ],
    "sg:phone":"+1 918 524 4241",
    "sg:postcode":"74136",
    "sg:province":"OK",
    "wof:name":"Webers Root Beer & Burgers",
    "wof:placetype":"venue"
},
  "geometry": {"coordinates":[-95.957972,36.065452],"type":"Point"}
}