{
  "type": "Feature",
  "properties": {
    "iso:country":"US",
    "sg:address":"4 Santa Fe Plz",
    "sg:city":"Oklahoma City",
    "sg:classifiers":[
        {
            "category":"Restaurant",
            "type":"Food & Drink"
        }
    ],
    "sg:phone":"+1 405 270 0888",
    "sg:postcode":"73102",
    "sg:province":"OK",
    "wof:name":"Pad Thai Downtown",
    "wof:placetype":"venue"
},
  "geometry": {"coordinates":[-97.51372499999999,35.4688],"type":"Point"}
}