{
  "type": "Feature",
  "properties": {
    "iso:country":"US",
    "sg:address":"1014 NE 2nd St",
    "sg:city":"Pryor",
    "sg:classifiers":[
        {
            "category":"Building & Trades",
            "subcategory":"Equipment Rental",
            "type":"Services"
        }
    ],
    "sg:phone":"+1 918 825 9289",
    "sg:postcode":"74361",
    "sg:province":"OK",
    "sg:tags":[
        "yard"
    ],
    "wof:name":"Mid America Rental Ctr",
    "wof:placetype":"venue"
},
  "geometry": {"coordinates":[-95.306159,36.309074],"type":"Point"}
}