{
  "type": "Feature",
  "properties": {
    "addr:full":"227 W Main St Norman OK 73069",
    "addr:housenumber":"227",
    "addr:postcode":"73069",
    "addr:street":"W Main St",
    "iso:country":"US",
    "sg:address":"227 W Main St",
    "sg:city":"Norman",
    "sg:classifiers":[
        {
            "category":"Organizations",
            "subcategory":"Non-profit Organization",
            "type":"Services"
        }
    ],
    "sg:phone":"+1 405 360 4822",
    "sg:postcode":"73069",
    "sg:province":"OK",
    "sg:tags":[
        "information",
        "alcoholism",
        "treatment"
    ],
    "wof:name":"Phoenix Group",
    "wof:placetype":"venue"
},
  "geometry": {"coordinates":[-97.446462,35.219717],"type":"Point"}
}