{
  "type": "Feature",
  "properties": {
    "iso:country":"US",
    "sg:address":"5537 S Sunnylane Rd",
    "sg:city":"Oklahoma City",
    "sg:classifiers":[
        {
            "category":"Real Estate",
            "subcategory":"Real Estate Operator",
            "type":"Services"
        }
    ],
    "sg:phone":"+1 405 672 2852",
    "sg:postcode":"73135",
    "sg:province":"OK",
    "sg:tags":[
        "apartment"
    ],
    "wof:name":"Aspen Walk Apartments",
    "wof:placetype":"venue"
},
  "geometry": {"coordinates":[-97.44137,35.410148],"type":"Point"}
}