{
  "type": "Feature",
  "properties": {
    "iso:country":"US",
    "sg:address":"1926 N Gary Ave",
    "sg:city":"Tulsa",
    "sg:classifiers":[
        {
            "category":"Real Estate",
            "subcategory":"Real Estate Operator",
            "type":"Services"
        }
    ],
    "sg:phone":"+1 918 838 2935",
    "sg:postcode":"74110",
    "sg:province":"OK",
    "sg:tags":[
        "building",
        "apartment"
    ],
    "wof:name":"Gardenwood Apartments",
    "wof:placetype":"venue"
},
  "geometry": {"coordinates":[-95.942325,36.18409],"type":"Point"}
}