{
  "type": "Feature",
  "properties": {
    "addr:full":"58251 E 170 Rd Fairland OK 74343",
    "addr:housenumber":"58251",
    "addr:postcode":"74343",
    "addr:street":"E 170 Rd",
    "iso:country":"US",
    "sg:address":"58251 E 170 Rd",
    "sg:city":"Fairland",
    "sg:classifiers":[
        {
            "category":"Manufacturing",
            "subcategory":"Metals",
            "type":"Manufacturing & Wholesale Goods"
        }
    ],
    "sg:phone":"+1 918 676 5158",
    "sg:postcode":"74343",
    "sg:province":"OK",
    "sg:tags":[
        "product",
        "wire",
        "fabricated",
        "mfg"
    ],
    "wof:name":"Heartland Belt Service Inc",
    "wof:placetype":"venue"
},
  "geometry": {"coordinates":[-94.832949,36.771804],"type":"Point"}
}