{
  "type": "Feature",
  "properties": {
    "iso:country":"US",
    "sg:address":"4912 E 22nd Pl",
    "sg:city":"Tulsa",
    "sg:classifiers":[
        {
            "category":"Building & Trades",
            "subcategory":"Plumbing",
            "type":"Services"
        }
    ],
    "sg:phone":"+1 918 749 8043",
    "sg:postcode":"74114",
    "sg:province":"OK",
    "sg:tags":[
        "plumbing",
        "contractor"
    ],
    "wof:name":"Gould Plumbing",
    "wof:placetype":"venue"
},
  "geometry": {"coordinates":[-95.920374,36.130545],"type":"Point"}
}