{
  "type": "Feature",
  "properties": {
    "iso:country":"US",
    "sg:address":"2 W Preston Ln",
    "sg:city":"Stillwater",
    "sg:classifiers":[
        {
            "category":"Farming",
            "subcategory":"Livestock Farm",
            "type":"Manufacturing & Wholesale Goods"
        }
    ],
    "sg:phone":"+1 405 372 4593",
    "sg:postcode":"74075",
    "sg:province":"OK",
    "sg:tags":[
        "beef",
        "feedlot",
        "cattle"
    ],
    "wof:name":"Darryl Kletke",
    "wof:placetype":"venue"
},
  "geometry": {"coordinates":[-97.08043499999999,36.146495],"type":"Point"}
}