{
  "type": "Feature",
  "properties": {
    "addr:full":"6600 E 390 Rd Oologah OK 74053",
    "addr:housenumber":"6600",
    "addr:postcode":"74053",
    "addr:street":"E 390 Rd",
    "iso:country":"US",
    "sg:address":"6600 E 390 Rd",
    "sg:city":"Oologah",
    "sg:classifiers":[
        {
            "category":"Building & Trades",
            "subcategory":"Landscaping Services",
            "type":"Services"
        }
    ],
    "sg:phone":"+1 918 443 6539",
    "sg:postcode":"74053",
    "sg:province":"OK",
    "sg:tags":[
        "irrigation",
        "system",
        "landscape",
        "contractor"
    ],
    "wof:name":"Clayton's Irrigation & Repair",
    "wof:placetype":"venue"
},
  "geometry": {"coordinates":[-95.710829,36.452294],"type":"Point"}
}