{
  "type": "Feature",
  "properties": {
    "iso:country":"US",
    "sg:address":"2530 E 71st St",
    "sg:city":"Tulsa",
    "sg:classifiers":[
        {
            "category":"Building & Trades",
            "subcategory":"Equipment Rental",
            "type":"Services"
        }
    ],
    "sg:phone":"+1 918 629 1111",
    "sg:postcode":"74136",
    "sg:province":"OK",
    "wof:name":"Metro Party Rental & Supply",
    "wof:placetype":"venue"
},
  "geometry": {"coordinates":[-95.953395,36.060755],"type":"Point"}
}