{
  "type": "Feature",
  "properties": {
    "iso:country":"US",
    "sg:address":"3045 S Harvard Ave",
    "sg:city":"Tulsa",
    "sg:classifiers":[
        {
            "category":"Banks & Credit Unions",
            "subcategory":"Bank",
            "type":"Services"
        }
    ],
    "sg:phone":"+1 918 743 6471",
    "sg:postcode":"74114",
    "sg:province":"OK",
    "sg:tags":[
        "state",
        "commercial"
    ],
    "wof:name":"Bank of Oklahoma NA",
    "wof:placetype":"venue"
},
  "geometry": {"coordinates":[-95.9402,36.119004],"type":"Point"}
}