{
  "type": "Feature",
  "properties": {
    "iso:country":"US",
    "sg:address":"906 N Ann Arbor Ave",
    "sg:city":"Oklahoma City",
    "sg:classifiers":[
        {
            "category":"Arts & Performance",
            "subcategory":"Theater",
            "type":"Entertainment"
        }
    ],
    "sg:phone":"+1 405 204 7319",
    "sg:postcode":"73127",
    "sg:province":"OK",
    "sg:tags":[
        "magician"
    ],
    "wof:name":"Joe Beene Dewey Jr",
    "wof:placetype":"venue"
},
  "geometry": {"coordinates":[-97.609983,35.4785],"type":"Point"}
}