{
  "type": "Feature",
  "properties": {
    "iso:country":"US",
    "sg:address":"19181 E 430 Rd",
    "sg:city":"Claremore",
    "sg:classifiers":[
        {
            "category":"Wholesale",
            "subcategory":"Meat",
            "type":"Manufacturing & Wholesale Goods"
        }
    ],
    "sg:phone":"+1 918 343 4868",
    "sg:postcode":"74017",
    "sg:province":"OK",
    "sg:tags":[
        "product"
    ],
    "wof:name":"Classic Taxidermy &Meat Proces",
    "wof:placetype":"venue"
},
  "geometry": {"coordinates":[-95.487032,36.394444],"type":"Point"}
}