{
  "type": "Feature",
  "properties": {
    "iso:country":"US",
    "sg:address":"2265 N Denver Pl",
    "sg:city":"Tulsa",
    "sg:classifiers":[
        {
            "category":"Communications",
            "subcategory":"Film & Video Production",
            "type":"Services"
        },
        {
            "category":"Professional",
            "type":"Services"
        }
    ],
    "sg:phone":"+1 918 584 5111",
    "sg:postcode":"74106",
    "sg:province":"OK",
    "wof:name":"Bulldog Production Services",
    "wof:placetype":"venue"
},
  "geometry": {"coordinates":[-95.998758,36.185341],"type":"Point"}
}