{
  "type": "Feature",
  "properties": {
    "iso:country":"US",
    "sg:address":"1111 W Main St",
    "sg:city":"Oklahoma City",
    "sg:classifiers":[
        {
            "category":"Retail",
            "subcategory":"Auto Repair",
            "type":"Services"
        }
    ],
    "sg:phone":"+1 405 235 5385",
    "sg:postcode":"73106",
    "sg:province":"OK",
    "sg:tags":[
        "automotive"
    ],
    "wof:name":"Modern Wheel Alignment Service",
    "wof:placetype":"venue"
},
  "geometry": {"coordinates":[-97.53107199999999,35.467959],"type":"Point"}
}