{
  "type": "Feature",
  "properties": {
    "addr:full":"7400 E Reno Ave Oklahoma City OK 73110",
    "addr:housenumber":"7400",
    "addr:postcode":"73110",
    "addr:street":"E Reno Ave",
    "iso:country":"US",
    "sg:address":"7400 E Reno Ave",
    "sg:city":"Oklahoma City",
    "sg:classifiers":[
        {
            "category":"Education",
            "subcategory":"School",
            "type":"Public Place"
        }
    ],
    "sg:phone":"+1 405 739 1786",
    "sg:postcode":"73110",
    "sg:province":"OK",
    "sg:tags":[
        "combined"
    ],
    "wof:name":"Monroney Jr H S",
    "wof:placetype":"venue"
},
  "geometry": {"coordinates":[-97.394218,35.464057],"type":"Point"}
}