{
  "type": "Feature",
  "properties": {
    "iso:country":"US",
    "sg:address":"1825 N Airport Dr",
    "sg:city":"Shawnee",
    "sg:classifiers":[
        {
            "category":"Organizations",
            "subcategory":"Non-profit Organization",
            "type":"Services"
        }
    ],
    "sg:phone":"+1 405 273 9457",
    "sg:postcode":"74804",
    "sg:province":"OK",
    "sg:tags":[
        "information",
        "alcoholism",
        "treatment"
    ],
    "wof:name":"Alcoholics Anonymous-Shawnee",
    "wof:placetype":"venue"
},
  "geometry": {"coordinates":[-96.934429,35.351281],"type":"Point"}
}