{
  "type": "Feature",
  "properties": {
    "iso:country":"US",
    "sg:address":"4904 S 79th East Ave",
    "sg:city":"Tulsa",
    "sg:classifiers":[
        {
            "category":"Recreation",
            "type":"Entertainment"
        }
    ],
    "sg:phone":"+1 918 607 6845",
    "sg:postcode":"74145",
    "sg:province":"OK",
    "sg:tags":[
        "martial",
        "arts",
        "instruction"
    ],
    "wof:name":"Luohan Wushu Kungfu Ctr",
    "wof:placetype":"venue"
},
  "geometry": {"coordinates":[-95.888837,36.092956],"type":"Point"}
}