{
  "type": "Feature",
  "properties": {
    "iso:country":"US",
    "sg:address":"3223 E 31st St S",
    "sg:city":"Tulsa",
    "sg:classifiers":[
        {
            "category":"Social Services",
            "type":"Services"
        }
    ],
    "sg:phone":"+1 918 744 8771",
    "sg:postcode":"74105",
    "sg:province":"OK",
    "wof:name":"George Mark Lmft",
    "wof:placetype":"venue"
},
  "geometry": {"coordinates":[-95.942111,36.118861],"type":"Point"}
}