{
  "type": "Feature",
  "properties": {
    "iso:country":"US",
    "sg:address":"320 S Walnut St",
    "sg:city":"Bristow",
    "sg:classifiers":[
        {
            "category":"Organizations",
            "subcategory":"Religious Organization",
            "type":"Services"
        }
    ],
    "sg:phone":"+1 918 367 2664",
    "sg:postcode":"74010",
    "sg:province":"OK",
    "wof:name":"First Church of God",
    "wof:placetype":"venue"
},
  "geometry": {"coordinates":[-96.388882,35.830624],"type":"Point"}
}