{
  "type": "Feature",
  "properties": {
    "iso:country":"US",
    "sg:address":"4500 NE 4th St",
    "sg:city":"Oklahoma City",
    "sg:classifiers":[
        {
            "category":"Building & Trades",
            "subcategory":"Construction",
            "type":"Services"
        }
    ],
    "sg:phone":"+1 405 671 2872",
    "sg:postcode":"73117",
    "sg:province":"OK",
    "sg:tags":[
        "marking",
        "maintenance",
        "parking"
    ],
    "wof:name":"Del City Public Works Dept",
    "wof:placetype":"venue"
},
  "geometry": {"coordinates":[-97.433573,35.471305],"type":"Point"}
}