{
  "type": "Feature",
  "properties": {
    "iso:country":"US",
    "sg:address":"3128 S Madole Blvd",
    "sg:city":"Oklahoma City",
    "sg:classifiers":[
        {
            "category":"Manufacturing",
            "subcategory":"Apparel",
            "type":"Manufacturing & Wholesale Goods"
        }
    ],
    "sg:phone":"+1 405 602 5903",
    "sg:postcode":"73159",
    "sg:province":"OK",
    "sg:tags":[
        "printing",
        "commercial"
    ],
    "wof:name":"Heck Graphics",
    "wof:placetype":"venue"
},
  "geometry": {"coordinates":[-97.571984,35.396002],"type":"Point"}
}