{
  "type": "Feature",
  "properties": {
    "addr:full":"306 S Main St Tonkawa OK 74653",
    "addr:housenumber":"306",
    "addr:postcode":"74653",
    "addr:street":"S Main St",
    "iso:country":"US",
    "sg:address":"306 S Main St",
    "sg:city":"Tonkawa",
    "sg:classifiers":[
        {
            "category":"Personal",
            "type":"Services"
        }
    ],
    "sg:phone":"+1 580 628 4120",
    "sg:postcode":"74653",
    "sg:province":"OK",
    "wof:name":"Fantastic Tan",
    "wof:placetype":"venue"
},
  "geometry": {"coordinates":[-97.309704,36.67573],"type":"Point"}
}