{
  "type": "Feature",
  "properties": {
    "iso:country":"US",
    "sg:address":"12251 Timberline Dr",
    "sg:city":"Guthrie",
    "sg:classifiers":[
        {
            "category":"Building & Trades",
            "subcategory":"Construction",
            "type":"Services"
        }
    ],
    "sg:phone":"+1 405 282 4695",
    "sg:postcode":"73044",
    "sg:province":"OK",
    "sg:tags":[
        "woodworker"
    ],
    "wof:name":"Woody II Woodworks",
    "wof:placetype":"venue"
},
  "geometry": {"coordinates":[-97.470617,35.778164],"type":"Point"}
}