{
  "type": "Feature",
  "properties": {
    "iso:country":"US",
    "sg:address":"4002 S Yale Ave",
    "sg:city":"Tulsa",
    "sg:classifiers":[
        {
            "category":"Shopping",
            "subcategory":"Optical Goods",
            "type":"Retail Goods"
        }
    ],
    "sg:phone":"+1 918 664 1500",
    "sg:postcode":"74135",
    "sg:province":"OK",
    "wof:name":"Eyemart Express",
    "wof:placetype":"venue"
},
  "geometry": {"coordinates":[-95.922405,36.104381],"type":"Point"}
}