{
  "type": "Feature",
  "properties": {
    "iso:country":"US",
    "sg:address":"329 B St SW",
    "sg:city":"Miami",
    "sg:classifiers":[
        {
            "category":"Social Services",
            "subcategory":"Child Care",
            "type":"Services"
        }
    ],
    "sg:phone":"+1 918 541 9101",
    "sg:postcode":"74354",
    "sg:province":"OK",
    "wof:name":"Critter Care",
    "wof:placetype":"venue"
},
  "geometry": {"coordinates":[-94.87970199999999,36.870495],"type":"Point"}
}