{
  "type": "Feature",
  "properties": {
    "iso:country":"US",
    "sg:address":"7101 Kings Rd",
    "sg:city":"Shawnee",
    "sg:classifiers":[
        {
            "category":"Organizations",
            "subcategory":"Religious Organization",
            "type":"Services"
        }
    ],
    "sg:phone":"+1 405 275 5809",
    "sg:postcode":"74804",
    "sg:province":"OK",
    "sg:tags":[
        "church"
    ],
    "wof:name":"Mt Pleasant Baptist Church",
    "wof:placetype":"venue"
},
  "geometry": {"coordinates":[-96.84174899999999,35.410031],"type":"Point"}
}