{
  "type": "Feature",
  "properties": {
    "iso:country":"US",
    "sg:address":"4819 N May Ave",
    "sg:city":"Oklahoma City",
    "sg:classifiers":[
        {
            "category":"Personal",
            "subcategory":"Tanning Parlor",
            "type":"Services"
        },
        {
            "category":"Personal",
            "subcategory":"Beauty Salon",
            "type":"Services"
        }
    ],
    "sg:phone":"+1 405 942 1110",
    "sg:postcode":"73112",
    "sg:province":"OK",
    "sg:tags":[
        "shop"
    ],
    "wof:name":"Paradise Tan & Salon Inc",
    "wof:placetype":"venue"
},
  "geometry": {"coordinates":[-97.565753,35.520261],"type":"Point"}
}