{
  "type": "Feature",
  "properties": {
    "iso:country":"US",
    "sg:address":"7739 E 38th St",
    "sg:city":"Tulsa",
    "sg:classifiers":[
        {
            "category":"Building & Trades",
            "subcategory":"Construction",
            "type":"Services"
        }
    ],
    "sg:phone":"+1 918 622 0009",
    "sg:postcode":"74145",
    "sg:province":"OK",
    "sg:tags":[
        "insulation",
        "heat",
        "contractor"
    ],
    "wof:name":"Northwest Insulation Co Inc",
    "wof:placetype":"venue"
},
  "geometry": {"coordinates":[-95.892976,36.10812],"type":"Point"}
}