{
  "type": "Feature",
  "properties": {
    "iso:country":"US",
    "sg:address":"3012 NW 41st St",
    "sg:city":"Oklahoma City",
    "sg:classifiers":[
        {
            "category":"Manufacturing",
            "subcategory":"Jewelry",
            "type":"Manufacturing & Wholesale Goods"
        }
    ],
    "sg:phone":"+1 405 787 7707",
    "sg:postcode":"73112",
    "sg:province":"OK",
    "sg:tags":[
        "precious",
        "metal",
        "mfg"
    ],
    "wof:name":"Kerr Jewelry Manufacturers",
    "wof:placetype":"venue"
},
  "geometry": {"coordinates":[-97.568334,35.513613],"type":"Point"}
}