{
  "type": "Feature",
  "properties": {
    "addr:full":"14501 Lamplight Ln Edmond OK 73013",
    "addr:housenumber":"14501",
    "addr:postcode":"73013",
    "addr:street":"Lamplight Ln",
    "iso:country":"US",
    "sg:address":"14501 Lamplight Ln",
    "sg:city":"Edmond",
    "sg:classifiers":[
        {
            "category":"Professional",
            "subcategory":"Business Services",
            "type":"Services"
        }
    ],
    "sg:phone":"+1 405 615 0446",
    "sg:postcode":"73013",
    "sg:province":"OK",
    "sg:tags":[
        "specializing",
        "training"
    ],
    "wof:name":"Guiding Light Enterprises LLC",
    "wof:placetype":"venue"
},
  "geometry": {"coordinates":[-97.54063499999999,35.618446],"type":"Point"}
}