{
  "type": "Feature",
  "properties": {
    "iso:country":"US",
    "sg:address":"10956 N May Ave",
    "sg:city":"Oklahoma City",
    "sg:classifiers":[
        {
            "category":"Sports & Exercise",
            "subcategory":"Gym",
            "type":"Entertainment"
        }
    ],
    "sg:phone":"+1 405 755 6200",
    "sg:postcode":"73120",
    "sg:province":"OK",
    "sg:tags":[
        "club",
        "health",
        "studio",
        "gymnasium"
    ],
    "wof:name":"Tan & Tone America",
    "wof:placetype":"venue"
},
  "geometry": {"coordinates":[-97.56711300000001,35.580549],"type":"Point"}
}