{
  "type": "Feature",
  "properties": {
    "addr:full":"2502 N Hemlock Cir Broken Arrow OK 74012",
    "addr:housenumber":"2502",
    "addr:postcode":"74012",
    "addr:street":"N Hemlock Cir",
    "iso:country":"US",
    "sg:address":"2502 N Hemlock Cir",
    "sg:city":"Broken Arrow",
    "sg:classifiers":[
        {
            "category":"Wholesale",
            "subcategory":"Machinery & Supplies",
            "type":"Manufacturing & Wholesale Goods"
        }
    ],
    "sg:phone":"+1 918 258 9533",
    "sg:postcode":"74012",
    "sg:province":"OK",
    "sg:tags":[
        "valve"
    ],
    "wof:name":"Zidell Valve Corp",
    "wof:placetype":"venue"
},
  "geometry": {"coordinates":[-95.82189,36.078423],"type":"Point"}
}