{
  "type": "Feature",
  "properties": {
    "iso:country":"US",
    "sg:address":"7178 S Memorial Dr",
    "sg:city":"Tulsa",
    "sg:classifiers":[
        {
            "category":"Home & Garden",
            "subcategory":"Furniture",
            "type":"Retail Goods"
        }
    ],
    "sg:phone":"+1 918 250 7880",
    "sg:postcode":"74133",
    "sg:province":"OK",
    "sg:tags":[
        "store"
    ],
    "wof:name":"Sunshine Furniture",
    "wof:placetype":"venue"
},
  "geometry": {"coordinates":[-95.886414,36.05827],"type":"Point"}
}