{
  "type": "Feature",
  "properties": {
    "iso:country":"US",
    "sg:address":"6755 S 4060 Rd",
    "sg:city":"Talala",
    "sg:classifiers":[
        {
            "category":"Professional",
            "subcategory":"Engineering",
            "type":"Services"
        }
    ],
    "sg:phone":"+1 918 275 4080",
    "sg:postcode":"74080",
    "sg:province":"OK",
    "wof:name":"Kellogg Engineering",
    "wof:placetype":"venue"
},
  "geometry": {"coordinates":[-95.776335,36.514001],"type":"Point"}
}