{
  "type": "Feature",
  "properties": {
    "addr:full":"1225 Val Genes Rd Edmond OK 73003",
    "addr:housenumber":"1225",
    "addr:postcode":"73003",
    "addr:street":"Val Genes Rd",
    "iso:country":"US",
    "sg:address":"1225 Val Genes Rd",
    "sg:city":"Edmond",
    "sg:classifiers":[
        {
            "category":"Building & Trades",
            "subcategory":"Electrical",
            "type":"Services"
        }
    ],
    "sg:phone":"+1 405 359 6333",
    "sg:postcode":"73003",
    "sg:province":"OK",
    "sg:tags":[
        "electrical",
        "contractor"
    ],
    "wof:name":"Trinity Electrical Contg Co",
    "wof:placetype":"venue"
},
  "geometry": {"coordinates":[-97.503029,35.644861],"type":"Point"}
}