{
  "type": "Feature",
  "properties": {
    "addr:full":"108 W Ohio Ave Coalgate OK 74538",
    "addr:housenumber":"108",
    "addr:postcode":"74538",
    "addr:street":"W Ohio Ave Coalgate",
    "iso:country":"US",
    "sg:address":"108 W Ohio Ave",
    "sg:city":"Coalgate",
    "sg:classifiers":[
        {
            "category":"Health Services",
            "subcategory":"Doctor",
            "type":"Services"
        }
    ],
    "sg:phone":"+1 580 927 2334",
    "sg:postcode":"74538",
    "sg:province":"OK",
    "sg:tags":[
        "physician",
        "surgeon"
    ],
    "wof:name":"Helton Rural Health Clinic",
    "wof:placetype":"venue"
},
  "geometry": {"coordinates":[-96.218901,34.53967],"type":"Point"}
}