{
  "type": "Feature",
  "properties": {
    "iso:country":"US",
    "sg:address":"2817 Wild Oaks Dr",
    "sg:city":"Duncan",
    "sg:classifiers":[
        {
            "category":"Freight",
            "type":"Transportation"
        }
    ],
    "sg:phone":"+1 580 470 8926",
    "sg:postcode":"73533",
    "sg:province":"OK",
    "sg:tags":[
        "trucking"
    ],
    "wof:name":"Sooner Trucking",
    "wof:placetype":"venue"
},
  "geometry": {"coordinates":[-97.962441,34.53939],"type":"Point"}
}