{
  "type": "Feature",
  "properties": {
    "iso:country":"US",
    "sg:address":"3230 N Rockwell Ave",
    "sg:city":"Bethany",
    "sg:classifiers":[
        {
            "category":"Personal",
            "type":"Services"
        }
    ],
    "sg:phone":"+1 405 789 2227",
    "sg:postcode":"73008",
    "sg:province":"OK",
    "sg:tags":[
        "credit",
        "debt",
        "counseling"
    ],
    "wof:name":"Consumer Credit Counseling Svc",
    "wof:placetype":"venue"
},
  "geometry": {"coordinates":[-97.63655199999999,35.503678],"type":"Point"}
}