{
  "type": "Feature",
  "properties": {
    "addr:full":"104 W Main St Jenks OK 74037",
    "addr:housenumber":"104",
    "addr:postcode":"74037",
    "addr:street":"W Main St",
    "iso:country":"US",
    "sg:address":"104 W Main St",
    "sg:city":"Jenks",
    "sg:classifiers":[
        {
            "category":"Building & Trades",
            "subcategory":"Landscaping Services",
            "type":"Services"
        }
    ],
    "sg:phone":"+1 918 786 2174",
    "sg:postcode":"74037",
    "sg:province":"OK",
    "sg:tags":[
        "landscape",
        "contractor"
    ],
    "wof:name":"Greenery",
    "wof:placetype":"venue"
},
  "geometry": {"coordinates":[-95.969612,36.022517],"type":"Point"}
}