{
  "type": "Feature",
  "properties": {
    "iso:country":"US",
    "sg:address":"944 SW 4th Pl",
    "sg:city":"Oklahoma City",
    "sg:classifiers":[
        {
            "category":"Professional",
            "type":"Services"
        }
    ],
    "sg:phone":"+1 405 759 3554",
    "sg:postcode":"73160",
    "sg:province":"OK",
    "wof:name":"Amazing Leaps LLC",
    "wof:placetype":"venue"
},
  "geometry": {"coordinates":[-97.506731,35.33481],"type":"Point"}
}