{
  "type": "Feature",
  "properties": {
    "addr:full":"231 E Chickasaw Ave Mcalester OK 74501",
    "addr:housenumber":"231",
    "addr:postcode":"74501",
    "addr:street":"E Chickasaw Ave",
    "iso:country":"US",
    "sg:address":"231 E Chickasaw Ave",
    "sg:city":"Mcalester",
    "sg:classifiers":[
        {
            "category":"Personal",
            "subcategory":"Beauty Salon",
            "type":"Services"
        }
    ],
    "sg:phone":"+1 918 423 4247",
    "sg:postcode":"74501",
    "sg:province":"OK",
    "wof:name":"Sheer Designs",
    "wof:placetype":"venue"
},
  "geometry": {"coordinates":[-95.767478,34.930526],"type":"Point"}
}