{
  "type": "Feature",
  "properties": {
    "addr:full":"131 W Main St Roff OK 74865",
    "addr:housenumber":"131",
    "addr:postcode":"74865",
    "addr:street":"W Main St",
    "iso:country":"US",
    "sg:address":"131 W Main St",
    "sg:city":"Roff",
    "sg:classifiers":[
        {
            "category":"Banks & Credit Unions",
            "subcategory":"Bank",
            "type":"Services"
        }
    ],
    "sg:phone":"+1 580 436 2026",
    "sg:postcode":"74865",
    "sg:province":"OK",
    "wof:name":"Pontotoc County Bank",
    "wof:placetype":"venue"
},
  "geometry": {"coordinates":[-96.841212,34.627268],"type":"Point"}
}