{
  "type": "Feature",
  "properties": {
    "iso:country":"US",
    "sg:address":"5220 W 21st St",
    "sg:city":"Tulsa",
    "sg:classifiers":[
        {
            "category":"Manufacturing",
            "subcategory":"Metals",
            "type":"Manufacturing & Wholesale Goods"
        }
    ],
    "sg:phone":"+1 918 599 7229",
    "sg:postcode":"74107",
    "sg:province":"OK",
    "sg:tags":[
        "steel",
        "structural",
        "forging",
        "fabrication",
        "mfg"
    ],
    "wof:name":"H & H Steel Fabricators",
    "wof:placetype":"venue"
},
  "geometry": {"coordinates":[-96.051348,36.133413],"type":"Point"}
}