{
  "type": "Feature",
  "properties": {
    "iso:country":"US",
    "sg:address":"25 N Lakewood Ave",
    "sg:city":"Tulsa",
    "sg:classifiers":[
        {
            "category":"Social Services",
            "subcategory":"Child Care",
            "type":"Services"
        }
    ],
    "sg:phone":"+1 918 836 7556",
    "sg:postcode":"74115",
    "sg:province":"OK",
    "wof:name":"Peggy's Daycare",
    "wof:placetype":"venue"
},
  "geometry": {"coordinates":[-95.908833,36.161152],"type":"Point"}
}