{
  "type": "Feature",
  "properties": {
    "iso:country":"US",
    "sg:address":"109 S 3rd St",
    "sg:city":"Chickasha",
    "sg:classifiers":[
        {
            "category":"Real Estate",
            "subcategory":"Real Estate Agent",
            "type":"Services"
        }
    ],
    "sg:phone":"+1 405 224 7053",
    "sg:postcode":"73018",
    "sg:province":"OK",
    "wof:name":"Crider Assoc Rlty & Accounting",
    "wof:placetype":"venue"
},
  "geometry": {"coordinates":[-97.935339,35.051052],"type":"Point"}
}