{
  "type": "Feature",
  "properties": {
    "iso:country":"US",
    "sg:address":"1378 E 42nd Pl",
    "sg:city":"Tulsa",
    "sg:classifiers":[
        {
            "category":"Professional",
            "subcategory":"Business Services",
            "type":"Services"
        }
    ],
    "sg:phone":"+1 918 742 8473",
    "sg:postcode":"74105",
    "sg:province":"OK",
    "wof:name":"M O & A G Enterprise",
    "wof:placetype":"venue"
},
  "geometry": {"coordinates":[-95.97264199999999,36.101711],"type":"Point"}
}