{
  "type": "Feature",
  "properties": {
    "iso:country":"US",
    "sg:address":"2418 N Wheeling Ave",
    "sg:city":"Tulsa",
    "sg:classifiers":[
        {
            "category":"Organizations",
            "subcategory":"Religious Organization",
            "type":"Services"
        }
    ],
    "sg:phone":"+1 918 430 1797",
    "sg:postcode":"74110",
    "sg:province":"OK",
    "wof:name":"Tri Love Ministries Inc",
    "wof:placetype":"venue"
},
  "geometry": {"coordinates":[-95.966679,36.188887],"type":"Point"}
}