{
  "type": "Feature",
  "properties": {
    "addr:full":"315 Trevyn St Holdenville OK 74848",
    "addr:housenumber":"315",
    "addr:postcode":"74848",
    "addr:street":"Trevyn St",
    "iso:country":"US",
    "sg:address":"315 Trevyn St",
    "sg:city":"Holdenville",
    "sg:classifiers":[
        {
            "category":"Manufacturing",
            "subcategory":"Tools & Machinery",
            "type":"Manufacturing & Wholesale Goods"
        }
    ],
    "sg:phone":"+1 405 379 6811",
    "sg:postcode":"74848",
    "sg:province":"OK",
    "sg:tags":[
        "mfg",
        "repair",
        "industrial",
        "welding"
    ],
    "wof:name":"Jeffs Machine",
    "wof:placetype":"venue"
},
  "geometry": {"coordinates":[-96.383538,35.089433],"type":"Point"}
}