{
  "type": "Feature",
  "properties": {
    "iso:country":"US",
    "sg:address":"1021 NE 26th St",
    "sg:city":"Oklahoma City",
    "sg:classifiers":[
        {
            "category":"Personal",
            "subcategory":"Beauty Salon",
            "type":"Services"
        }
    ],
    "sg:phone":"+1 405 424 6195",
    "sg:postcode":"73111",
    "sg:province":"OK",
    "wof:name":"Sandee's Beauty Salon",
    "wof:placetype":"venue"
},
  "geometry": {"coordinates":[-97.492787,35.496969],"type":"Point"}
}