{
  "type": "Feature",
  "properties": {
    "iso:country":"US",
    "sg:address":"1301 State Hwy 3",
    "sg:city":"Guymon",
    "sg:classifiers":[
        {
            "category":"Real Estate",
            "subcategory":"Real Estate Operator",
            "type":"Services"
        }
    ],
    "sg:phone":"+1 580 338 4800",
    "sg:postcode":"73942",
    "sg:province":"OK",
    "sg:tags":[
        "apartment"
    ],
    "wof:name":"Apache Trace Apartments",
    "wof:placetype":"venue"
},
  "geometry": {"coordinates":[-101.481569,36.690684],"type":"Point"}
}