{
  "type": "Feature",
  "properties": {
    "iso:country":"US",
    "sg:address":"303 NW 15th St",
    "sg:city":"Idabel",
    "sg:classifiers":[
        {
            "category":"Utilities",
            "subcategory":"Mobile Phone",
            "type":"Services"
        }
    ],
    "sg:phone":"+1 580 208 3777",
    "sg:postcode":"74745",
    "sg:province":"OK",
    "sg:tags":[
        "telephone",
        "cellular"
    ],
    "wof:name":"OCTM Wireless",
    "wof:placetype":"venue"
},
  "geometry": {"coordinates":[-94.834794,33.908919],"type":"Point"}
}