{
  "type": "Feature",
  "properties": {
    "iso:country":"US",
    "sg:address":"19266 Town Ln",
    "sg:city":"Catoosa",
    "sg:classifiers":[
        {
            "category":"Wholesale",
            "subcategory":"Hardware",
            "type":"Manufacturing & Wholesale Goods"
        }
    ],
    "sg:phone":"+1 918 266 6410",
    "sg:postcode":"74015",
    "sg:province":"OK",
    "sg:tags":[
        "purifying",
        "cleaning",
        "air"
    ],
    "wof:name":"A Breath Of Fresh Air",
    "wof:placetype":"venue"
},
  "geometry": {"coordinates":[-95.76158,36.171134],"type":"Point"}
}