{
  "type": "Feature",
  "properties": {
    "addr:full":"3380 W Washington St Broken Arrow OK 74012",
    "addr:housenumber":"3380",
    "addr:postcode":"74012",
    "addr:street":"W Washington St",
    "iso:country":"US",
    "sg:address":"3380 W Washington St",
    "sg:city":"Broken Arrow",
    "sg:classifiers":[
        {
            "category":"Recreation",
            "type":"Entertainment"
        }
    ],
    "sg:phone":"+1 918 294 9786",
    "sg:postcode":"74012",
    "sg:province":"OK",
    "wof:name":"Dean Adkisson Golf",
    "wof:placetype":"venue"
},
  "geometry": {"coordinates":[-95.83096500000001,36.031884],"type":"Point"}
}