{
  "type": "Feature",
  "properties": {
    "addr:full":"2104 Crossroads Mall Dr Oklahoma City OK 73149",
    "addr:housenumber":"2104",
    "addr:postcode":"73149",
    "addr:street":"Crossroads Mall Dr",
    "iso:country":"US",
    "sg:address":"2104 Crossroads Mall Dr",
    "sg:city":"Oklahoma City",
    "sg:classifiers":[
        {
            "category":"Shopping",
            "subcategory":"Gifts & Souvenirs",
            "type":"Retail Goods"
        }
    ],
    "sg:phone":"+1 405 632 5363",
    "sg:postcode":"73149",
    "sg:province":"OK",
    "wof:name":"Spencer Gifts LLC",
    "wof:placetype":"venue"
},
  "geometry": {"coordinates":[-97.487329,35.396069],"type":"Point"}
}