{
  "type": "Feature",
  "properties": {
    "iso:country":"US",
    "sg:address":"2823 S Husband St",
    "sg:city":"Stillwater",
    "sg:classifiers":[
        {
            "category":"Organizations",
            "subcategory":"Religious Organization",
            "type":"Services"
        }
    ],
    "sg:phone":"+1 405 372 3280",
    "sg:postcode":"74074",
    "sg:province":"OK",
    "wof:name":"Southern Hts Untd Mthdst Chrch",
    "wof:placetype":"venue"
},
  "geometry": {"coordinates":[-97.06020700000001,36.091096],"type":"Point"}
}