{
  "type": "Feature",
  "properties": {
    "addr:full":"202 S 2nd St Jenks OK 74037",
    "addr:housenumber":"202",
    "addr:postcode":"74037",
    "addr:street":"S 2Nd St",
    "iso:country":"US",
    "sg:address":"202 S 2nd St",
    "sg:city":"Jenks",
    "sg:classifiers":[
        {
            "category":"Health Services",
            "subcategory":"Doctor",
            "type":"Services"
        }
    ],
    "sg:phone":"+1 918 299 2182",
    "sg:postcode":"74037",
    "sg:province":"OK",
    "wof:name":"Kevin C Ray DDS",
    "wof:placetype":"venue"
},
  "geometry": {"coordinates":[-95.968356,36.020613],"type":"Point"}
}