{
  "type": "Feature",
  "properties": {
    "addr:full":"1415 Main Ave Woodward OK 73801",
    "addr:housenumber":"1415",
    "addr:postcode":"73801",
    "addr:street":"Main Ave",
    "iso:country":"US",
    "sg:address":"1415 Main Ave",
    "sg:city":"Woodward",
    "sg:classifiers":[
        {
            "category":"Retail",
            "subcategory":"Animal Services",
            "type":"Services"
        }
    ],
    "sg:phone":"+1 580 254 3823",
    "sg:postcode":"73801",
    "sg:province":"OK",
    "sg:tags":[
        "pet",
        "grooming",
        "washing"
    ],
    "wof:name":"Tammy's Grooming Shop",
    "wof:placetype":"venue"
},
  "geometry": {"coordinates":[-99.398218,36.435893],"type":"Point"}
}