{
  "type": "Feature",
  "properties": {
    "iso:country":"US",
    "sg:address":"811 N Mill St",
    "sg:city":"Muskogee",
    "sg:classifiers":[
        {
            "category":"Building & Trades",
            "subcategory":"Landscaping Services",
            "type":"Services"
        }
    ],
    "sg:phone":"+1 918 683 5094",
    "sg:postcode":"74401",
    "sg:province":"OK",
    "wof:name":"Home Turf",
    "wof:placetype":"venue"
},
  "geometry": {"coordinates":[-95.36309,35.756425],"type":"Point"}
}