{
  "type": "Feature",
  "properties": {
    "iso:country":"US",
    "sg:address":"11212 N Memorial Dr",
    "sg:city":"Owasso",
    "sg:classifiers":[
        {
            "category":"Building & Trades",
            "subcategory":"Electrical",
            "type":"Services"
        }
    ],
    "sg:phone":"+1 918 371 6537",
    "sg:postcode":"74055",
    "sg:province":"OK",
    "sg:tags":[
        "electric",
        "contractor"
    ],
    "wof:name":"David's Electrical Svc",
    "wof:placetype":"venue"
},
  "geometry": {"coordinates":[-95.88423400000001,36.312699],"type":"Point"}
}