{
  "type": "Feature",
  "properties": {
    "iso:country":"US",
    "sg:address":"131 N Oklahoma Ave",
    "sg:city":"Mangum",
    "sg:classifiers":[
        {
            "category":"Government",
            "subcategory":"Office",
            "type":"Public Place"
        }
    ],
    "sg:phone":"+1 580 782 2341",
    "sg:postcode":"73554",
    "sg:province":"OK",
    "sg:tags":[
        "govt",
        "city"
    ],
    "wof:name":"Mangum Gas & Water-Mntnc",
    "wof:placetype":"venue"
},
  "geometry": {"coordinates":[-99.50613300000001,34.873838],"type":"Point"}
}