{
  "type": "Feature",
  "properties": {
    "addr:full":"717 N Perkins Rd Stillwater OK 74075",
    "addr:housenumber":"717",
    "addr:postcode":"74075",
    "addr:street":"N Perkins Rd",
    "iso:country":"US",
    "sg:address":"717 N Perkins Rd",
    "sg:city":"Stillwater",
    "sg:classifiers":[
        {
            "category":"Utilities",
            "subcategory":"Mobile Phone",
            "type":"Services"
        }
    ],
    "sg:phone":"+1 405 372 4033",
    "sg:postcode":"74075",
    "sg:province":"OK",
    "sg:tags":[
        "telephone",
        "cellular"
    ],
    "wof:name":"T-Mobile",
    "wof:placetype":"venue"
},
  "geometry": {"coordinates":[-97.051401,36.130405],"type":"Point"}
}