{
  "type": "Feature",
  "properties": {
    "iso:country":"US",
    "sg:address":"1401 Linwood Blvd",
    "sg:city":"Oklahoma City",
    "sg:classifiers":[
        {
            "category":"Food & Beverages",
            "subcategory":"Groceries & Convenience Stores",
            "type":"Retail Goods"
        }
    ],
    "sg:phone":"+1 405 236 2485",
    "sg:postcode":"73106",
    "sg:province":"OK",
    "sg:tags":[
        "grocer"
    ],
    "wof:name":"Linwood Food Store",
    "wof:placetype":"venue"
},
  "geometry": {"coordinates":[-97.534843,35.474801],"type":"Point"}
}