{
  "type": "Feature",
  "properties": {
    "iso:country":"US",
    "sg:address":"1650 W Tecumseh Rd",
    "sg:city":"Norman",
    "sg:classifiers":[
        {
            "category":"Government",
            "subcategory":"Office",
            "type":"Public Place"
        }
    ],
    "sg:phone":"+1 405 360 9393",
    "sg:postcode":"73069",
    "sg:province":"OK",
    "wof:name":"Honorable Janet A Foss",
    "wof:placetype":"venue"
},
  "geometry": {"coordinates":[-97.466894,35.261842],"type":"Point"}
}