{
  "type": "Feature",
  "properties": {
    "iso:country":"US",
    "sg:address":"828 Apache St",
    "sg:city":"Garber",
    "sg:classifiers":[
        {
            "category":"Personal",
            "subcategory":"Beauty Salon",
            "type":"Services"
        }
    ],
    "sg:phone":"+1 580 863 2893",
    "sg:postcode":"73738",
    "sg:province":"OK",
    "wof:name":"Lori's Hair Studio",
    "wof:placetype":"venue"
},
  "geometry": {"coordinates":[-97.578049,36.433538],"type":"Point"}
}