{
  "type": "Feature",
  "properties": {
    "addr:full":"8955 S Memorial Dr Tulsa OK 74133",
    "addr:housenumber":"8955",
    "addr:postcode":"74133",
    "addr:street":"S Memorial Dr",
    "iso:country":"US",
    "sg:address":"8955 S Memorial Dr",
    "sg:city":"Tulsa",
    "sg:classifiers":[
        {
            "category":"Restaurant",
            "type":"Food & Drink"
        }
    ],
    "sg:phone":"+1 918 392 0770",
    "sg:postcode":"74133",
    "sg:province":"OK",
    "sg:tags":[
        "delicatessen"
    ],
    "wof:name":"Mc Alister's Deli",
    "wof:placetype":"venue"
},
  "geometry": {"coordinates":[-95.88623800000001,36.036297],"type":"Point"}
}