{
  "type": "Feature",
  "properties": {
    "iso:country":"US",
    "sg:address":"8200 S Shields Blvd",
    "sg:city":"Oklahoma City",
    "sg:classifiers":[
        {
            "category":"Home & Garden",
            "subcategory":"Mobile Homes",
            "type":"Retail Goods"
        }
    ],
    "sg:phone":"+1 405 631 6601",
    "sg:postcode":"73149",
    "sg:province":"OK",
    "sg:tags":[
        "sales"
    ],
    "wof:name":"A1 Homes Group LP",
    "wof:placetype":"venue"
},
  "geometry": {"coordinates":[-97.503717,35.38464],"type":"Point"}
}