{
  "type": "Feature",
  "properties": {
    "iso:country":"US",
    "sg:address":"902 E Main St",
    "sg:city":"Weatherford",
    "sg:classifiers":[
        {
            "category":"Restaurant",
            "type":"Food & Drink"
        }
    ],
    "sg:menulink":"http://www.allmenus.com/ok/weatherford/144582-subway/menu/",
    "sg:phone":"+1 580 772 0125",
    "sg:postcode":"73096",
    "sg:province":"OK",
    "sg:tags":[
        "american",
        "sandwich"
    ],
    "wof:name":"Subway",
    "wof:placetype":"venue"
},
  "geometry": {"coordinates":[-98.69835399999999,35.526035],"type":"Point"}
}