{
  "type": "Feature",
  "properties": {
    "addr:full":"8125 NW 11th St Oklahoma City OK 73127",
    "addr:housenumber":"8125",
    "addr:postcode":"73127",
    "addr:street":"Nw 11Th St",
    "iso:country":"US",
    "sg:address":"8125 NW 11th St",
    "sg:city":"Oklahoma City",
    "sg:classifiers":[
        {
            "category":"Manufacturing",
            "subcategory":"Leather Goods",
            "type":"Manufacturing & Wholesale Goods"
        }
    ],
    "sg:phone":"+1 405 789 6620",
    "sg:postcode":"73127",
    "sg:province":"OK",
    "sg:tags":[
        "saddle"
    ],
    "wof:name":"Hay Babies",
    "wof:placetype":"venue"
},
  "geometry": {"coordinates":[-97.65821699999999,35.480654],"type":"Point"}
}