{
  "type": "Feature",
  "properties": {
    "iso:country":"US",
    "sg:address":"1121 W Willow Rd",
    "sg:city":"Enid",
    "sg:classifiers":[
        {
            "category":"Food & Beverages",
            "subcategory":"Dairy",
            "type":"Retail Goods"
        }
    ],
    "sg:phone":"+1 580 242 6152",
    "sg:postcode":"73703",
    "sg:province":"OK",
    "sg:tags":[
        "product"
    ],
    "wof:name":"Braums Ice Cream & Dar Stores",
    "wof:placetype":"venue"
},
  "geometry": {"coordinates":[-97.892096,36.41978],"type":"Point"}
}