{
  "type": "Feature",
  "properties": {
    "iso:country":"US",
    "sg:address":"437 W Wilshire Blvd",
    "sg:city":"Oklahoma City",
    "sg:classifiers":[
        {
            "category":"Professional",
            "subcategory":"Employment Agencies",
            "type":"Services"
        }
    ],
    "sg:phone":"+1 405 306 6818",
    "sg:postcode":"73116",
    "sg:province":"OK",
    "sg:tags":[
        "help",
        "contractor"
    ],
    "wof:name":"Drivers & Temps Unlimited Temp",
    "wof:placetype":"venue"
},
  "geometry": {"coordinates":[-97.522066,35.551195],"type":"Point"}
}