{
  "type": "Feature",
  "properties": {
    "addr:full":"2727 W 111th Pl Jenks OK 74037",
    "addr:housenumber":"2727",
    "addr:postcode":"74037",
    "addr:street":"W 111Th Pl",
    "iso:country":"US",
    "sg:address":"2727 W 111th Pl",
    "sg:city":"Jenks",
    "sg:classifiers":[
        {
            "category":"Building & Trades",
            "subcategory":"Plumbing",
            "type":"Services"
        }
    ],
    "sg:phone":"+1 918 298 1800",
    "sg:postcode":"74037",
    "sg:province":"OK",
    "sg:tags":[
        "conditioning",
        "air",
        "system",
        "contractor"
    ],
    "wof:name":"Design Air Systems Inc",
    "wof:placetype":"venue"
},
  "geometry": {"coordinates":[-96.00792199999999,36.002427],"type":"Point"}
}