{
  "type": "Feature",
  "properties": {
    "iso:country":"US",
    "sg:address":"400 W 3rd St",
    "sg:city":"Heavener",
    "sg:classifiers":[
        {
            "category":"Organizations",
            "subcategory":"Religious Organization",
            "type":"Services"
        }
    ],
    "sg:phone":"+1 918 653 4486",
    "sg:postcode":"74937",
    "sg:province":"OK",
    "sg:tags":[
        "church"
    ],
    "wof:name":"First Christian Church",
    "wof:placetype":"venue"
},
  "geometry": {"coordinates":[-94.60541499999999,34.89062],"type":"Point"}
}