{
  "type": "Feature",
  "properties": {
    "iso:country":"US",
    "sg:address":"609 W Main St",
    "sg:city":"Ardmore",
    "sg:classifiers":[
        {
            "category":"Banks & Credit Unions",
            "subcategory":"Investment Brokerage",
            "type":"Services"
        }
    ],
    "sg:phone":"+1 580 226 6866",
    "sg:postcode":"73401",
    "sg:province":"OK",
    "sg:tags":[
        "security"
    ],
    "wof:name":"Edward Jones 03583",
    "wof:placetype":"venue"
},
  "geometry": {"coordinates":[-97.136257,34.174601],"type":"Point"}
}