{
  "type": "Feature",
  "properties": {
    "iso:country":"US",
    "sg:address":"504 NW 7th St",
    "sg:city":"Stigler",
    "sg:classifiers":[
        {
            "category":"Organizations",
            "subcategory":"Religious Organization",
            "type":"Services"
        }
    ],
    "sg:phone":"+1 918 967 4818",
    "sg:postcode":"74462",
    "sg:province":"OK",
    "sg:tags":[
        "church"
    ],
    "wof:name":"Pentecostal Holiness Church",
    "wof:placetype":"venue"
},
  "geometry": {"coordinates":[-95.132456,35.257939],"type":"Point"}
}