{
  "type": "Feature",
  "properties": {
    "iso:country":"US",
    "sg:address":"3621 N Everest Ave",
    "sg:city":"Oklahoma City",
    "sg:classifiers":[
        {
            "category":"Autos & Motor Vehicles",
            "subcategory":"Motorcycle Sales",
            "type":"Retail Goods"
        }
    ],
    "sg:phone":"+1 405 424 7433",
    "sg:postcode":"73111",
    "sg:province":"OK",
    "sg:tags":[
        "scooter"
    ],
    "wof:name":"Oklahoma Rider Edu Program",
    "wof:placetype":"venue"
},
  "geometry": {"coordinates":[-97.491674,35.507469],"type":"Point"}
}