{
  "type": "Feature",
  "properties": {
    "iso:country":"US",
    "sg:address":"115 N Broadway St",
    "sg:city":"Weatherford",
    "sg:classifiers":[
        {
            "category":"Banks & Credit Unions",
            "subcategory":"Bank",
            "type":"Services"
        }
    ],
    "sg:phone":"+1 580 772 5051",
    "sg:postcode":"73096",
    "sg:province":"OK",
    "sg:tags":[
        "personal",
        "institution"
    ],
    "wof:name":"Quick Loans",
    "wof:placetype":"venue"
},
  "geometry": {"coordinates":[-98.709216,35.526422],"type":"Point"}
}