{
  "type": "Feature",
  "properties": {
    "addr:full":"6108 NW 63rd St Oklahoma City OK 73132",
    "addr:housenumber":"6108",
    "addr:postcode":"73132",
    "addr:street":"Nw 63Rd St",
    "iso:country":"US",
    "sg:address":"6108 NW 63rd St",
    "sg:city":"Oklahoma City",
    "sg:classifiers":[
        {
            "category":"Building & Trades",
            "subcategory":"Construction",
            "type":"Services"
        }
    ],
    "sg:phone":"+1 405 720 7780",
    "sg:postcode":"73132",
    "sg:province":"OK",
    "sg:tags":[
        "window",
        "replacement"
    ],
    "sg:website":"www.fairwayhomeimprovement.com",
    "wof:name":"Fairway Home Improvement Inc",
    "wof:placetype":"venue"
},
  "geometry": {"coordinates":[-97.62455799999999,35.536796],"type":"Point"}
}