{
  "type": "Feature",
  "properties": {
    "iso:country":"US",
    "sg:address":"1417 N Moore Ave",
    "sg:city":"Oklahoma City",
    "sg:classifiers":[
        {
            "category":"Travel",
            "subcategory":"Hotels & Motels",
            "type":"Entertainment"
        }
    ],
    "sg:phone":"+1 405 799 6616",
    "sg:postcode":"73160",
    "sg:province":"OK",
    "sg:tags":[
        "operation"
    ],
    "wof:name":"Motel 6",
    "wof:placetype":"venue"
},
  "geometry": {"coordinates":[-97.49526400000001,35.352065],"type":"Point"}
}