{
  "type": "Feature",
  "properties": {
    "addr:full":"219 N Bickford Ave El Reno OK 73036",
    "addr:housenumber":"219",
    "addr:postcode":"73036",
    "addr:street":"N Bickford Ave",
    "iso:country":"US",
    "sg:address":"219 N Bickford Ave",
    "sg:city":"El Reno",
    "sg:classifiers":[
        {
            "category":"Professional",
            "subcategory":"Lawyer & Legal Services",
            "type":"Services"
        }
    ],
    "sg:phone":"+1 405 262 7100",
    "sg:postcode":"73036",
    "sg:province":"OK",
    "sg:tags":[
        "attorney"
    ],
    "wof:name":"Haley Law Office",
    "wof:placetype":"venue"
},
  "geometry": {"coordinates":[-97.953855,35.53484],"type":"Point"}
}