{
  "type": "Feature",
  "properties": {
    "iso:country":"US",
    "sg:address":"6700 Sears Ter",
    "sg:city":"Oklahoma City",
    "sg:classifiers":[
        {
            "category":"Manufacturing",
            "subcategory":"Textiles",
            "type":"Manufacturing & Wholesale Goods"
        },
        {
            "category":"Manufacturing",
            "subcategory":"Apparel",
            "type":"Manufacturing & Wholesale Goods"
        }
    ],
    "sg:phone":"+1 405 631 6128",
    "sg:postcode":"73149",
    "sg:province":"OK",
    "sg:tags":[
        "curtain",
        "mfg"
    ],
    "wof:name":"San-Dee's Custom Draperies",
    "wof:placetype":"venue"
},
  "geometry": {"coordinates":[-97.501114,35.395996],"type":"Point"}
}