{
  "type": "Feature",
  "properties": {
    "iso:country":"US",
    "sg:address":"124 E Main St",
    "sg:city":"Ada",
    "sg:classifiers":[
        {
            "category":"Communications",
            "subcategory":"Television Station",
            "type":"Services"
        }
    ],
    "sg:phone":"+1 580 436 5836",
    "sg:postcode":"74820",
    "sg:province":"OK",
    "sg:tags":[
        "broadcasting",
        "co"
    ],
    "wof:name":"KTEN Television",
    "wof:placetype":"venue"
},
  "geometry": {"coordinates":[-96.678517,34.774573],"type":"Point"}
}