{
  "type": "Feature",
  "properties": {
    "iso:country":"US",
    "sg:address":"753 NW Fort Sill Blvd",
    "sg:city":"Lawton",
    "sg:classifiers":[
        {
            "category":"Education",
            "subcategory":"School",
            "type":"Public Place"
        }
    ],
    "sg:phone":"+1 580 357 6900",
    "sg:postcode":"73507",
    "sg:province":"OK",
    "wof:name":"John Shoemaker Education Ctr",
    "wof:placetype":"venue"
},
  "geometry": {"coordinates":[-98.404605,34.61711],"type":"Point"}
}