{
  "type": "Feature",
  "properties": {
    "iso:country":"US",
    "sg:address":"507 E 1st St",
    "sg:city":"Heavener",
    "sg:classifiers":[
        {
            "category":"Professional",
            "subcategory":"Computer Services",
            "type":"Services"
        }
    ],
    "sg:phone":"+1 918 653 4488",
    "sg:postcode":"74937",
    "sg:province":"OK",
    "sg:tags":[
        "consultant"
    ],
    "wof:name":"Soletec",
    "wof:placetype":"venue"
},
  "geometry": {"coordinates":[-94.600889,34.889165],"type":"Point"}
}