{
  "type": "Feature",
  "properties": {
    "iso:country":"US",
    "sg:address":"808 N Porter Ave",
    "sg:city":"Norman",
    "sg:classifiers":[
        {
            "category":"Shopping",
            "subcategory":"Pharmacy",
            "type":"Retail Goods"
        }
    ],
    "sg:phone":"+1 405 321 1445",
    "sg:postcode":"73071",
    "sg:province":"OK",
    "sg:tags":[
        "st"
    ],
    "wof:name":"Ken's Discount Pharmacy",
    "wof:placetype":"venue"
},
  "geometry": {"coordinates":[-97.441169,35.229551],"type":"Point"}
}