{
  "type": "Feature",
  "properties": {
    "iso:country":"US",
    "sg:address":"10415 Greenbriar Pl",
    "sg:city":"Oklahoma City",
    "sg:classifiers":[
        {
            "category":"Real Estate",
            "subcategory":"Real Estate Services",
            "type":"Services"
        }
    ],
    "sg:phone":"+1 405 691 7070",
    "sg:postcode":"73159",
    "sg:province":"OK",
    "sg:tags":[
        "company",
        "title"
    ],
    "wof:name":"Capitol Abstract",
    "wof:placetype":"venue"
},
  "geometry": {"coordinates":[-97.546134,35.363321],"type":"Point"}
}