{
  "type": "Feature",
  "properties": {
    "addr:full":"902 N 30th St Enid OK 73701",
    "addr:housenumber":"902",
    "addr:postcode":"73701",
    "addr:street":"N 30Th St",
    "iso:country":"US",
    "sg:address":"902 N 30th St",
    "sg:city":"Enid",
    "sg:classifiers":[
        {
            "category":"Building & Trades",
            "subcategory":"Construction",
            "type":"Services"
        }
    ],
    "sg:phone":"+1 580 237 4288",
    "sg:postcode":"73701",
    "sg:province":"OK",
    "sg:tags":[
        "general",
        "contractor"
    ],
    "wof:name":"Watkins Construction",
    "wof:placetype":"venue"
},
  "geometry": {"coordinates":[-97.83682,36.406195],"type":"Point"}
}