{
  "type": "Feature",
  "properties": {
    "addr:full":"118 N 2nd St Stilwell OK 74960",
    "addr:housenumber":"118",
    "addr:postcode":"74960",
    "addr:street":"N 2Nd St",
    "iso:country":"US",
    "sg:address":"118 N 2nd St",
    "sg:city":"Stilwell",
    "sg:classifiers":[
        {
            "category":"Communications",
            "subcategory":"Newspaper",
            "type":"Services"
        },
        {
            "category":"Wholesale",
            "subcategory":"Books, Periodicals, & Newspapers",
            "type":"Manufacturing & Wholesale Goods"
        }
    ],
    "sg:phone":"+1 918 696 2228",
    "sg:postcode":"74960",
    "sg:province":"OK",
    "sg:tags":[
        "dealers-wholesale",
        "news"
    ],
    "sg:website":"http://www.democratjournal.com",
    "wof:name":"Democrat Journal",
    "wof:placetype":"venue"
},
  "geometry": {"coordinates":[-94.628192,35.815724],"type":"Point"}
}