{
  "type": "Feature",
  "properties": {
    "iso:country":"US",
    "sg:address":"16 W 9th St",
    "sg:city":"Shawnee",
    "sg:classifiers":[
        {
            "category":"Government",
            "subcategory":"Office",
            "type":"Public Place"
        },
        {
            "category":"Government",
            "subcategory":"Court House",
            "type":"Public Place"
        }
    ],
    "sg:phone":"+1 405 878 1604",
    "sg:postcode":"74801",
    "sg:province":"OK",
    "sg:tags":[
        "city"
    ],
    "wof:name":"Shawnee City Court Clerk",
    "wof:placetype":"venue"
},
  "geometry": {"coordinates":[-96.924656,35.328765],"type":"Point"}
}