{
  "type": "Feature",
  "properties": {
    "addr:full":"3616 E 11th St Tulsa OK 74112",
    "addr:housenumber":"3616",
    "addr:postcode":"74112",
    "addr:street":"E 11Th St",
    "iso:country":"US",
    "sg:address":"3616 E 11th St",
    "sg:city":"Tulsa",
    "sg:classifiers":[
        {
            "category":"Restaurant",
            "type":"Food & Drink"
        }
    ],
    "sg:phone":"+1 918 258 8302",
    "sg:postcode":"74112",
    "sg:province":"OK",
    "sg:tags":[
        "eating"
    ],
    "wof:name":"A&W Restaurant",
    "wof:placetype":"venue"
},
  "geometry": {"coordinates":[-95.936409,36.147742],"type":"Point"}
}