{
  "type": "Feature",
  "properties": {
    "iso:country":"US",
    "sg:address":"1010 S Central Ave",
    "sg:city":"Idabel",
    "sg:phone":"+1 580 286 5693",
    "sg:postcode":"74745",
    "sg:province":"OK",
    "sg:tags":[
        "distributor",
        "oil",
        "marketer"
    ],
    "wof:name":"Young Oil Co",
    "wof:placetype":"venue"
},
  "geometry": {"coordinates":[-94.826379,33.885569],"type":"Point"}
}