{
  "type": "Feature",
  "properties": {
    "iso:country":"US",
    "sg:address":"103 S 109th East Pl",
    "sg:city":"Tulsa",
    "sg:classifiers":[
        {
            "category":"Building & Trades",
            "subcategory":"Construction",
            "type":"Services"
        }
    ],
    "sg:phone":"+1 918 234 7675",
    "sg:postcode":"74128",
    "sg:province":"OK",
    "sg:tags":[
        "nonresidential"
    ],
    "wof:name":"Ross Group Construction Corp",
    "wof:placetype":"venue"
},
  "geometry": {"coordinates":[-95.854766,36.157916],"type":"Point"}
}