{
  "type": "Feature",
  "properties": {
    "iso:country":"US",
    "sg:address":"607 E Main St",
    "sg:city":"Antlers",
    "sg:classifiers":[
        {
            "category":"Restaurant",
            "type":"Food & Drink"
        }
    ],
    "sg:menulink":"http://www.allmenus.com/ok/antlers/199454-sonic/menu/",
    "sg:phone":"+1 580 298 5596",
    "sg:postcode":"74523",
    "sg:province":"OK",
    "sg:tags":[
        "burger",
        "american"
    ],
    "wof:name":"Sonic",
    "wof:placetype":"venue"
},
  "geometry": {"coordinates":[-95.61408,34.23187],"type":"Point"}
}