{
  "type": "Feature",
  "properties": {
    "addr:full":"9022 S Pennsylvania Ave Oklahoma City OK 73159",
    "addr:housenumber":"9022",
    "addr:postcode":"73159",
    "addr:street":"S Pennsylvania Ave",
    "iso:country":"US",
    "sg:address":"9022 S Pennsylvania Ave",
    "sg:city":"Oklahoma City",
    "sg:classifiers":[
        {
            "category":"Restaurant",
            "type":"Food & Drink"
        }
    ],
    "sg:phone":"+1 405 691 9989",
    "sg:postcode":"73159",
    "sg:province":"OK",
    "wof:name":"Padthai",
    "wof:placetype":"venue"
},
  "geometry": {"coordinates":[-97.54774500000001,35.374502],"type":"Point"}
}