{
  "type": "Feature",
  "properties": {
    "iso:country":"US",
    "sg:address":"9022 S Pennsylvania Ave",
    "sg:city":"Oklahoma City",
    "sg:classifiers":[
        {
            "category":"Restaurant",
            "type":"Food & Drink"
        }
    ],
    "sg:phone":"+1 405 691 9989",
    "sg:postcode":"73159",
    "sg:province":"OK",
    "wof:name":"Padthai",
    "wof:placetype":"venue"
},
  "geometry": {"coordinates":[-97.547745,35.374502],"type":"Point"}
}