{
  "type": "Feature",
  "properties": {
    "iso:country":"US",
    "sg:address":"1101 Ash St",
    "sg:city":"Chelsea",
    "sg:classifiers":[
        {
            "category":"Social Services",
            "subcategory":"Child Care",
            "type":"Services"
        }
    ],
    "sg:phone":"+1 918 789 3094",
    "sg:postcode":"74016",
    "sg:province":"OK",
    "sg:tags":[
        "day"
    ],
    "wof:name":"Card Head Start-Chelsea",
    "wof:placetype":"venue"
},
  "geometry": {"coordinates":[-95.441407,36.53189],"type":"Point"}
}