{
  "type": "Feature",
  "properties": {
    "iso:country":"US",
    "sg:address":"4409 N 4th St",
    "sg:city":"Enid",
    "sg:classifiers":[
        {
            "category":"Home & Garden",
            "subcategory":"Garden Supply",
            "type":"Retail Goods"
        }
    ],
    "sg:phone":"+1 580 234 1653",
    "sg:postcode":"73701",
    "sg:province":"OK",
    "sg:tags":[
        "lawn"
    ],
    "wof:name":"North Enid Repair",
    "wof:placetype":"venue"
},
  "geometry": {"coordinates":[-97.872729,36.437936],"type":"Point"}
}