{
  "type": "Feature",
  "properties": {
    "iso:country":"US",
    "sg:address":"644 Woodland Way",
    "sg:city":"Oklahoma City",
    "sg:classifiers":[
        {
            "category":"Professional",
            "subcategory":"Management & Consulting",
            "type":"Services"
        }
    ],
    "sg:phone":"+1 405 789 3922",
    "sg:postcode":"73127",
    "sg:province":"OK",
    "wof:name":"Hopper Management Inc",
    "wof:placetype":"venue"
},
  "geometry": {"coordinates":[-97.639727,35.473956],"type":"Point"}
}