{
  "type": "Feature",
  "properties": {
    "addr:full":"100 W 5th St Tulsa OK 74103",
    "addr:housenumber":"100",
    "addr:postcode":"74103",
    "addr:street":"W 5Th St",
    "iso:country":"US",
    "sg:address":"100 W 5th St",
    "sg:city":"Tulsa",
    "sg:classifiers":[
        {
            "category":"Professional",
            "subcategory":"Lawyer & Legal Services",
            "type":"Services"
        }
    ],
    "sg:phone":"+1 918 583 5791",
    "sg:postcode":"74103",
    "sg:province":"OK",
    "sg:tags":[
        "attorney"
    ],
    "wof:name":"R Thomas Seymour Attorneys",
    "wof:placetype":"venue"
},
  "geometry": {"coordinates":[-95.992435,36.1506],"type":"Point"}
}