{
  "type": "Feature",
  "properties": {
    "addr:full":"9501 N Macarthur Blvd Oklahoma City OK 73162",
    "addr:housenumber":"9501",
    "addr:postcode":"73162",
    "addr:street":"N Macarthur Blvd",
    "iso:country":"US",
    "sg:address":"9501 N Macarthur Blvd",
    "sg:city":"Oklahoma City",
    "sg:classifiers":[
        {
            "category":"Building & Trades",
            "subcategory":"Construction",
            "type":"Services"
        }
    ],
    "sg:phone":"+1 405 812 4563",
    "sg:postcode":"73162",
    "sg:province":"OK",
    "sg:tags":[
        "tile",
        "dealer"
    ],
    "wof:name":"Home Dynamics",
    "wof:placetype":"venue"
},
  "geometry": {"coordinates":[-97.620774,35.569485],"type":"Point"}
}