{
  "type": "Feature",
  "properties": {
    "addr:full":"2908 W Okmulgee Ave Muskogee OK 74401",
    "addr:housenumber":"2908",
    "addr:postcode":"74401",
    "addr:street":"W Okmulgee Ave",
    "iso:country":"US",
    "sg:address":"2908 W Okmulgee Ave",
    "sg:city":"Muskogee",
    "sg:classifiers":[
        {
            "category":"Personal",
            "subcategory":"Beauty Salon",
            "type":"Services"
        },
        {
            "category":"Personal",
            "subcategory":"Barber",
            "type":"Services"
        }
    ],
    "sg:phone":"+1 918 687 9170",
    "sg:postcode":"74401",
    "sg:province":"OK",
    "sg:tags":[
        "shop"
    ],
    "wof:name":"Roffler of Muskogee",
    "wof:placetype":"venue"
},
  "geometry": {"coordinates":[-95.40037700000001,35.755076],"type":"Point"}
}