{
  "type": "Feature",
  "properties": {
    "iso:country":"US",
    "sg:address":"131 W Oklahoma Ave",
    "sg:city":"Anadarko",
    "sg:classifiers":[
        {
            "category":"Ice Cream",
            "type":"Food & Drink"
        }
    ],
    "sg:menulink":"http://www.allmenus.com/ok/anadarko/175758-dairy-queen/menu/",
    "sg:phone":"+1 405 247 5496",
    "sg:postcode":"73005",
    "sg:province":"OK",
    "sg:tags":[
        "burger",
        "american"
    ],
    "wof:name":"Dairy Queen",
    "wof:placetype":"venue"
},
  "geometry": {"coordinates":[-98.244191,35.07375],"type":"Point"}
}