{
  "type": "Feature",
  "properties": {
    "iso:country":"US",
    "sg:address":"2015 W Danforth Rd",
    "sg:city":"Edmond",
    "sg:classifiers":[
        {
            "category":"Coffee & Tea",
            "type":"Food & Drink"
        }
    ],
    "sg:menulink":"http://www.allmenus.com/ok/oklahoma-city/119172-starbucks-coffee/menu/",
    "sg:phone":"+1 405 341 1032",
    "sg:postcode":"73003",
    "sg:province":"OK",
    "sg:tags":[
        "american"
    ],
    "wof:name":"Starbucks Coffee",
    "wof:placetype":"venue"
},
  "geometry": {"coordinates":[-97.51049,35.667541],"type":"Point"}
}