{
  "type": "Feature",
  "properties": {
    "addr:full":"709 Oklahoma Blvd Alva OK 73717",
    "addr:housenumber":"709",
    "addr:postcode":"73717",
    "addr:street":"Oklahoma Blvd",
    "iso:country":"US",
    "sg:address":"709 Oklahoma Blvd",
    "sg:city":"Alva",
    "sg:classifiers":[
        {
            "category":"Manufacturing",
            "subcategory":"Toys & Sporting Goods",
            "type":"Manufacturing & Wholesale Goods"
        }
    ],
    "sg:phone":"+1 580 327 8162",
    "sg:postcode":"73717",
    "sg:province":"OK",
    "sg:tags":[
        "construction",
        "mfg"
    ],
    "wof:name":"American Iron Sports LLC",
    "wof:placetype":"venue"
},
  "geometry": {"coordinates":[-98.669083,36.79761],"type":"Point"}
}