{
  "type": "Feature",
  "properties": {
    "iso:country":"US",
    "sg:address":"1221 N Pioneer Rd",
    "sg:city":"Elk City",
    "sg:classifiers":[
        {
            "category":"Education",
            "subcategory":"School",
            "type":"Public Place"
        }
    ],
    "sg:phone":"+1 580 225 0105",
    "sg:postcode":"73644",
    "sg:province":"OK",
    "wof:name":"Elk City Senior High School",
    "wof:placetype":"venue"
},
  "geometry": {"coordinates":[-99.434884,35.420231],"type":"Point"}
}