{
  "type": "Feature",
  "properties": {
    "iso:country":"US",
    "sg:address":"221 NE 1st St",
    "sg:city":"Oklahoma City",
    "sg:classifiers":[
        {
            "category":"Wholesale",
            "subcategory":"Furniture",
            "type":"Manufacturing & Wholesale Goods"
        }
    ],
    "sg:phone":"+1 405 843 6709",
    "sg:postcode":"73104",
    "sg:province":"OK",
    "wof:name":"Wright Line",
    "wof:placetype":"venue"
},
  "geometry": {"coordinates":[-97.507679,35.468654],"type":"Point"}
}