{
  "type": "Feature",
  "properties": {
    "addr:full":"1240 SW 65th St Oklahoma City OK 73139",
    "addr:housenumber":"1240",
    "addr:postcode":"73139",
    "addr:street":"Sw 65Th St",
    "iso:country":"US",
    "sg:address":"1240 SW 65th St",
    "sg:city":"Oklahoma City",
    "sg:classifiers":[
        {
            "category":"Social Services",
            "subcategory":"Child Care",
            "type":"Services"
        }
    ],
    "sg:phone":"+1 405 632 7019",
    "sg:postcode":"73139",
    "sg:province":"OK",
    "sg:tags":[
        "day"
    ],
    "wof:name":"Mc Anally Day Nursery",
    "wof:placetype":"venue"
},
  "geometry": {"coordinates":[-97.53827699999999,35.400346],"type":"Point"}
}