{
  "type": "Feature",
  "properties": {
    "addr:full":"1701 Alameda St Norman OK 73071",
    "addr:housenumber":"1701",
    "addr:postcode":"73071",
    "addr:street":"Alameda St",
    "iso:country":"US",
    "sg:address":"1701 Alameda St",
    "sg:city":"Norman",
    "sg:classifiers":[
        {
            "category":"Social Services",
            "subcategory":"Adult Care",
            "type":"Services"
        }
    ],
    "sg:phone":"+1 405 573 9200",
    "sg:postcode":"73071",
    "sg:province":"OK",
    "sg:tags":[
        "home",
        "residential"
    ],
    "wof:name":"Sterling House",
    "wof:placetype":"venue"
},
  "geometry": {"coordinates":[-97.41595599999999,35.218357],"type":"Point"}
}