{
  "type": "Feature",
  "properties": {
    "addr:full":"508 N Walnut Ave Oklahoma City OK 73104",
    "addr:housenumber":"508",
    "addr:postcode":"73104",
    "addr:street":"N Walnut Ave",
    "iso:country":"US",
    "sg:address":"508 N Walnut Ave",
    "sg:city":"Oklahoma City",
    "sg:classifiers":[
        {
            "category":"Building & Trades",
            "subcategory":"Electrical",
            "type":"Services"
        },
        {
            "category":"Wholesale",
            "subcategory":"Electrical",
            "type":"Manufacturing & Wholesale Goods"
        }
    ],
    "sg:phone":"+1 405 235 5647",
    "sg:postcode":"73104",
    "sg:province":"OK",
    "sg:tags":[
        "sound",
        "equipment",
        "system",
        "contractor"
    ],
    "wof:name":"Fentriss Sound Company",
    "wof:placetype":"venue"
},
  "geometry": {"coordinates":[-97.50884000000001,35.472746],"type":"Point"}
}