{
  "type": "Feature",
  "properties": {
    "addr:full":"1325 NE 55th St Oklahoma City OK 73111",
    "addr:housenumber":"1325",
    "addr:postcode":"73111",
    "addr:street":"Ne 55Th St",
    "iso:country":"US",
    "sg:address":"1325 NE 55th St",
    "sg:city":"Oklahoma City",
    "sg:classifiers":[
        {
            "category":"Health Services",
            "subcategory":"Health Practitioner",
            "type":"Services"
        }
    ],
    "sg:phone":"+1 405 424 3240",
    "sg:postcode":"73111",
    "sg:province":"OK",
    "wof:name":"Gloria Carpenter",
    "wof:placetype":"venue"
},
  "geometry": {"coordinates":[-97.48710800000001,35.526813],"type":"Point"}
}