{
  "type": "Feature",
  "properties": {
    "iso:country":"US",
    "sg:address":"221 W Broadway St",
    "sg:city":"Muskogee",
    "sg:classifiers":[
        {
            "category":"Shopping",
            "type":"Retail Goods"
        }
    ],
    "sg:phone":"+1 918 683 6041",
    "sg:postcode":"74401",
    "sg:province":"OK",
    "sg:tags":[
        "art",
        "gallery",
        "dealer"
    ],
    "wof:name":"Art Market",
    "wof:placetype":"venue"
},
  "geometry": {"coordinates":[-95.37085,35.749285],"type":"Point"}
}