{
  "type": "Feature",
  "properties": {
    "iso:country":"US",
    "sg:address":"2001 W Houston St",
    "sg:city":"Broken Arrow",
    "sg:classifiers":[
        {
            "category":"Restaurant",
            "type":"Food & Drink"
        }
    ],
    "sg:phone":"+1 918 258 4141",
    "sg:postcode":"74012",
    "sg:province":"OK",
    "sg:tags":[
        "barbecue"
    ],
    "wof:name":"Mr Barbeque",
    "wof:placetype":"venue"
},
  "geometry": {"coordinates":[-95.81664499999999,36.046324],"type":"Point"}
}