{
  "type": "Feature",
  "properties": {
    "iso:country":"US",
    "sg:address":"1608 Cimarron Dr",
    "sg:city":"Stillwater",
    "sg:classifiers":[
        {
            "category":"Shopping",
            "subcategory":"Discount & Variety Stores",
            "type":"Retail Goods"
        }
    ],
    "sg:phone":"+1 405 377 6525",
    "sg:postcode":"74075",
    "sg:province":"OK",
    "wof:name":"Dollar General",
    "wof:placetype":"venue"
},
  "geometry": {"coordinates":[-97.038361,36.133735],"type":"Point"}
}