{
  "type": "Feature",
  "properties": {
    "iso:country":"US",
    "sg:address":"405 W Kenosha St",
    "sg:city":"Broken Arrow",
    "sg:classifiers":[
        {
            "category":"Shopping",
            "type":"Retail Goods"
        }
    ],
    "sg:phone":"+1 918 258 0750",
    "sg:postcode":"74012",
    "sg:province":"OK",
    "sg:tags":[
        "picture",
        "frame"
    ],
    "wof:name":"Broken Arrow Frame & Gallery",
    "wof:placetype":"venue"
},
  "geometry": {"coordinates":[-95.79472,36.061063],"type":"Point"}
}