{
  "type": "Feature",
  "properties": {
    "addr:full":"1708 Cedar Creek Ter Oklahoma City OK 73131",
    "addr:housenumber":"1708",
    "addr:postcode":"73131",
    "addr:street":"Cedar Creek Ter",
    "iso:country":"US",
    "sg:address":"1708 Cedar Creek Ter",
    "sg:city":"Oklahoma City",
    "sg:classifiers":[
        {
            "category":"Health Services",
            "subcategory":"Doctor",
            "type":"Services"
        }
    ],
    "sg:phone":"+1 405 478 7600",
    "sg:postcode":"73131",
    "sg:province":"OK",
    "wof:name":"Brackett Susan Elizabeth Dd S",
    "wof:placetype":"venue"
},
  "geometry": {"coordinates":[-97.483104,35.603008],"type":"Point"}
}