{
  "type": "Feature",
  "properties": {
    "iso:country":"US",
    "sg:address":"23115 W Wekiwa Rd",
    "sg:city":"Sand Springs",
    "sg:classifiers":[
        {
            "category":"Government",
            "subcategory":"Office",
            "type":"Public Place"
        }
    ],
    "sg:phone":"+1 918 865 2621",
    "sg:postcode":"74063",
    "sg:province":"OK",
    "sg:tags":[
        "federal"
    ],
    "wof:name":"US Army Corps Of Engineers",
    "wof:placetype":"venue"
},
  "geometry": {"coordinates":[-96.238981,36.148399],"type":"Point"}
}