{
  "type": "Feature",
  "properties": {
    "addr:full":"324 W Columbia St Okemah OK 74859",
    "addr:housenumber":"324",
    "addr:postcode":"74859",
    "addr:street":"W Columbia St",
    "iso:country":"US",
    "sg:address":"324 W Columbia St",
    "sg:city":"Okemah",
    "sg:classifiers":[
        {
            "category":"Personal",
            "subcategory":"Beauty Salon",
            "type":"Services"
        }
    ],
    "sg:phone":"+1 918 623 9398",
    "sg:postcode":"74859",
    "sg:province":"OK",
    "sg:tags":[
        "manicuring"
    ],
    "wof:name":"A-Tone-Able You",
    "wof:placetype":"venue"
},
  "geometry": {"coordinates":[-96.304485,35.435223],"type":"Point"}
}