{
  "type": "Feature",
  "properties": {
    "iso:country":"US",
    "sg:address":"1111 S Main St",
    "sg:city":"Muskogee",
    "sg:classifiers":[
        {
            "category":"Local Transit",
            "type":"Transportation"
        }
    ],
    "sg:phone":"+1 918 682 1371",
    "sg:postcode":"74401",
    "sg:province":"OK",
    "sg:tags":[
        "bus",
        "line"
    ],
    "wof:name":"Greyhound Bus Lines",
    "wof:placetype":"venue"
},
  "geometry": {"coordinates":[-95.37478900000001,35.738295],"type":"Point"}
}