{
  "type": "Feature",
  "properties": {
    "addr:full":"2328 NW 55th St Oklahoma City OK 73112",
    "addr:housenumber":"2328",
    "addr:postcode":"73112",
    "addr:street":"Nw 55Th St",
    "iso:country":"US",
    "sg:address":"2328 NW 55th St",
    "sg:city":"Oklahoma City",
    "sg:classifiers":[
        {
            "category":"Banks & Credit Unions",
            "subcategory":"Financial Services",
            "type":"Services"
        }
    ],
    "sg:phone":"+1 405 232 5732",
    "sg:postcode":"73112",
    "sg:province":"OK",
    "sg:tags":[
        "royalty",
        "interest",
        "oil"
    ],
    "wof:name":"Talco Exploration Inc",
    "wof:placetype":"venue"
},
  "geometry": {"coordinates":[-97.556093,35.526024],"type":"Point"}
}