{
  "type": "Feature",
  "properties": {
    "addr:full":"3525 E 51st St Tulsa OK 74135",
    "addr:housenumber":"3525",
    "addr:postcode":"74135",
    "addr:street":"E 51St St",
    "iso:country":"US",
    "sg:address":"3525 E 51st St",
    "sg:city":"Tulsa",
    "sg:classifiers":[
        {
            "category":"Coffee & Tea",
            "type":"Food & Drink"
        },
        {
            "category":"Restaurant",
            "type":"Food & Drink"
        },
        {
            "category":"Bakery",
            "type":"Food & Drink"
        },
        {
            "category":"Donuts",
            "type":"Food & Drink"
        }
    ],
    "sg:menulink":"http://www.allmenus.com/ok/tulsa/231065-daylight-donuts/menu/",
    "sg:phone":"+1 918 712 2212",
    "sg:postcode":"74135",
    "sg:province":"OK",
    "sg:tags":[
        "tea",
        "coffee",
        "bakery",
        "american",
        "pastry"
    ],
    "wof:name":"Daylight Donuts",
    "wof:placetype":"venue"
},
  "geometry": {"coordinates":[-95.93683900000001,36.090225],"type":"Point"}
}