{
  "type": "Feature",
  "properties": {
    "addr:full":"423 S Pine St Ponca City OK 74601",
    "addr:housenumber":"423",
    "addr:postcode":"74601",
    "addr:street":"S Pine St",
    "iso:country":"US",
    "sg:address":"423 S Pine St",
    "sg:city":"Ponca City",
    "sg:classifiers":[
        {
            "category":"Retail",
            "subcategory":"Auto Repair",
            "type":"Services"
        }
    ],
    "sg:phone":"+1 580 762 6222",
    "sg:postcode":"74601",
    "sg:province":"OK",
    "sg:tags":[
        "general"
    ],
    "wof:name":"Transmission Center",
    "wof:placetype":"venue"
},
  "geometry": {"coordinates":[-97.08664899999999,36.700283],"type":"Point"}
}