{
  "type": "Feature",
  "properties": {
    "iso:country":"US",
    "sg:address":"1024 N Lansing Ave",
    "sg:city":"Tulsa",
    "sg:classifiers":[
        {
            "category":"Manufacturing",
            "subcategory":"Chemicals & Compounds",
            "type":"Manufacturing & Wholesale Goods"
        }
    ],
    "sg:phone":"+1 918 584 2810",
    "sg:postcode":"74106",
    "sg:province":"OK",
    "sg:tags":[
        "protective",
        "coating",
        "applicator",
        "mfg"
    ],
    "sg:website":"www.ravenlining.com",
    "wof:name":"Raven Lining Systems Inc",
    "wof:placetype":"venue"
},
  "geometry": {"coordinates":[-95.980655,36.168281],"type":"Point"}
}