{
  "type": "Feature",
  "properties": {
    "iso:country":"US",
    "sg:address":"115 N 2nd Ave",
    "sg:city":"Purcell",
    "sg:classifiers":[
        {
            "category":"Shopping",
            "subcategory":"Shoes",
            "type":"Retail Goods"
        }
    ],
    "sg:phone":"+1 405 527 2331",
    "sg:postcode":"73080",
    "sg:province":"OK",
    "wof:name":"Lindy's Shoes",
    "wof:placetype":"venue"
},
  "geometry": {"coordinates":[-97.361074,35.013414],"type":"Point"}
}