{
  "type": "Feature",
  "properties": {
    "iso:country":"US",
    "sg:address":"208 W Rogers St",
    "sg:city":"El Reno",
    "sg:classifiers":[
        {
            "category":"Government",
            "subcategory":"Police Station",
            "type":"Public Place"
        }
    ],
    "sg:phone":"+1 405 422 3187",
    "sg:postcode":"73036",
    "sg:province":"OK",
    "sg:tags":[
        "protection"
    ],
    "wof:name":"Canadian Cnty Sheriffs Ofc Inc",
    "wof:placetype":"venue"
},
  "geometry": {"coordinates":[-97.955956,35.53508],"type":"Point"}
}