{
  "type": "Feature",
  "properties": {
    "iso:country":"US",
    "sg:address":"324 E Main St",
    "sg:city":"Ada",
    "sg:classifiers":[
        {
            "category":"Retail",
            "subcategory":"Repair Shop",
            "type":"Services"
        }
    ],
    "sg:phone":"+1 580 332 4490",
    "sg:postcode":"74820",
    "sg:province":"OK",
    "sg:tags":[
        "lock",
        "locksmith"
    ],
    "wof:name":"Crowell Lock & Safe",
    "wof:placetype":"venue"
},
  "geometry": {"coordinates":[-96.675075,34.774596],"type":"Point"}
}