{
  "type": "Feature",
  "properties": {
    "addr:full":"1203 W Broadway St Ardmore OK 73401",
    "addr:housenumber":"1203",
    "addr:postcode":"73401",
    "addr:street":"W Broadway St",
    "iso:country":"US",
    "sg:address":"1203 W Broadway St",
    "sg:city":"Ardmore",
    "sg:classifiers":[
        {
            "category":"Banks & Credit Unions",
            "subcategory":"Investment Brokerage",
            "type":"Services"
        }
    ],
    "sg:phone":"+1 580 224 9977",
    "sg:postcode":"73401",
    "sg:province":"OK",
    "sg:tags":[
        "security"
    ],
    "wof:name":"Ryan Hobbs Investment Service",
    "wof:placetype":"venue"
},
  "geometry": {"coordinates":[-97.14357200000001,34.174583],"type":"Point"}
}