{
  "type": "Feature",
  "properties": {
    "iso:country":"US",
    "sg:address":"624 E Archer St",
    "sg:city":"Tulsa",
    "sg:classifiers":[
        {
            "category":"Professional",
            "subcategory":"Lawyer & Legal Services",
            "type":"Services"
        }
    ],
    "sg:phone":"+1 918 582 9181",
    "sg:postcode":"74120",
    "sg:province":"OK",
    "sg:tags":[
        "attorney"
    ],
    "wof:name":"Goodwin & Goodwin",
    "wof:placetype":"venue"
},
  "geometry": {"coordinates":[-95.986141,36.159682],"type":"Point"}
}