{
  "type": "Feature",
  "properties": {
    "iso:country":"US",
    "sg:address":"1012 Falcon Rd",
    "sg:city":"Altus",
    "sg:classifiers":[
        {
            "category":"Organizations",
            "subcategory":"Religious Organization",
            "type":"Services"
        }
    ],
    "sg:phone":"+1 580 482 4778",
    "sg:postcode":"73521",
    "sg:province":"OK",
    "wof:name":"Anointed Word Bible Church",
    "wof:placetype":"venue"
},
  "geometry": {"coordinates":[-99.321774,34.652217],"type":"Point"}
}