{
  "type": "Feature",
  "properties": {
    "iso:country":"US",
    "sg:address":"11720 S Hudson Pl",
    "sg:city":"Tulsa",
    "sg:classifiers":[
        {
            "category":"Food & Beverages",
            "subcategory":"Farmers Market",
            "type":"Retail Goods"
        }
    ],
    "sg:phone":"+1 918 299 7500",
    "sg:postcode":"74137",
    "sg:province":"OK",
    "sg:tags":[
        "operator",
        "oil"
    ],
    "wof:name":"Shiloh Energy",
    "wof:placetype":"venue"
},
  "geometry": {"coordinates":[-95.912794,35.994578],"type":"Point"}
}