{
  "type": "Feature",
  "properties": {
    "iso:country":"US",
    "sg:address":"9332 E Broken Arrow Expy",
    "sg:city":"Tulsa",
    "sg:classifiers":[
        {
            "category":"Wholesale",
            "subcategory":"Machinery & Supplies",
            "type":"Manufacturing & Wholesale Goods"
        },
        {
            "category":"Manufacturing",
            "subcategory":"Metals",
            "type":"Manufacturing & Wholesale Goods"
        }
    ],
    "sg:phone":"+1 918 627 9333",
    "sg:postcode":"74145",
    "sg:province":"OK",
    "sg:tags":[
        "corrosion",
        "installation",
        "lining",
        "coating",
        "contract",
        "pipe",
        "cathodic"
    ],
    "wof:name":"Corrosion Control Products Co",
    "wof:placetype":"venue"
},
  "geometry": {"coordinates":[-95.869096,36.10109],"type":"Point"}
}