{
  "type": "Feature",
  "properties": {
    "addr:full":"2707 E Marshall St Tulsa OK 74110",
    "addr:housenumber":"2707",
    "addr:postcode":"74110",
    "addr:street":"E Marshall St",
    "iso:country":"US",
    "sg:address":"2707 E Marshall St",
    "sg:city":"Tulsa",
    "sg:classifiers":[
        {
            "category":"Professional",
            "subcategory":"Art Services",
            "type":"Services"
        }
    ],
    "sg:phone":"+1 918 832 8838",
    "sg:postcode":"74110",
    "sg:province":"OK",
    "sg:tags":[
        "commercial",
        "design"
    ],
    "wof:name":"Hudson Graphics",
    "wof:placetype":"venue"
},
  "geometry": {"coordinates":[-95.950806,36.17259],"type":"Point"}
}