{
  "type": "Feature",
  "properties": {
    "addr:full":"1120 W Gary Blvd Clinton OK 73601",
    "addr:housenumber":"1120",
    "addr:postcode":"73601",
    "addr:street":"W Gary Blvd",
    "iso:country":"US",
    "sg:address":"1120 W Gary Blvd",
    "sg:city":"Clinton",
    "sg:classifiers":[
        {
            "category":"Local Transit",
            "type":"Transportation"
        }
    ],
    "sg:phone":"+1 580 323 2244",
    "sg:postcode":"73601",
    "sg:province":"OK",
    "sg:tags":[
        "bus",
        "line"
    ],
    "wof:name":"Greyhound Bus Lines",
    "wof:placetype":"venue"
},
  "geometry": {"coordinates":[-98.973433,35.515327],"type":"Point"}
}