{
  "type": "Feature",
  "properties": {
    "iso:country":"US",
    "sg:address":"5110 E 104th Pl",
    "sg:city":"Tulsa",
    "sg:classifiers":[
        {
            "category":"Building & Trades",
            "subcategory":"Construction",
            "type":"Services"
        }
    ],
    "sg:phone":"+1 918 299 8858",
    "sg:postcode":"74137",
    "sg:province":"OK",
    "sg:tags":[
        "carpentry",
        "contractor"
    ],
    "wof:name":"S R O Contracting",
    "wof:placetype":"venue"
},
  "geometry": {"coordinates":[-95.918764,36.012282],"type":"Point"}
}