{
  "type": "Feature",
  "properties": {
    "addr:full":"1017 E Huber Ave Weatherford OK 73096",
    "addr:housenumber":"1017",
    "addr:postcode":"73096",
    "addr:street":"E Huber Ave",
    "iso:country":"US",
    "sg:address":"1017 E Huber Ave",
    "sg:city":"Weatherford",
    "sg:classifiers":[
        {
            "category":"Manufacturing",
            "subcategory":"Printing",
            "type":"Manufacturing & Wholesale Goods"
        }
    ],
    "sg:phone":"+1 580 772 2266",
    "sg:postcode":"73096",
    "sg:province":"OK",
    "sg:tags":[
        "newspaper"
    ],
    "wof:name":"Weatherford Shopper",
    "wof:placetype":"venue"
},
  "geometry": {"coordinates":[-98.696018,35.531431],"type":"Point"}
}