{
  "type": "Feature",
  "properties": {
    "addr:full":"1140 N 129th East Ave Tulsa OK 74116",
    "addr:housenumber":"1140",
    "addr:postcode":"74116",
    "addr:street":"N 129Th;Ave",
    "iso:country":"US",
    "sg:address":"1140 N 129th East Ave",
    "sg:city":"Tulsa",
    "sg:classifiers":[
        {
            "category":"Building & Trades",
            "subcategory":"Construction",
            "type":"Services"
        }
    ],
    "sg:phone":"+1 918 234 7675",
    "sg:postcode":"74116",
    "sg:province":"OK",
    "sg:tags":[
        "contractor"
    ],
    "sg:website":"www.trgcc.com",
    "wof:name":"The Ross Group Construction Corp",
    "wof:placetype":"venue"
},
  "geometry": {"coordinates":[-95.833483,36.170637],"type":"Point"}
}