{
  "type": "Feature",
  "properties": {
    "iso:country":"US",
    "sg:address":"1866 E 15th St",
    "sg:city":"Tulsa",
    "sg:classifiers":[
        {
            "category":"Professional",
            "subcategory":"Management & Consulting",
            "type":"Services"
        }
    ],
    "sg:phone":"+1 918 744 5914",
    "sg:postcode":"74104",
    "sg:province":"OK",
    "sg:tags":[
        "consultant",
        "medical",
        "legal"
    ],
    "wof:name":"B C Group",
    "wof:placetype":"venue"
},
  "geometry": {"coordinates":[-95.965901,36.140574],"type":"Point"}
}