{
  "type": "Feature",
  "properties": {
    "addr:full":"6800 Camille Ave Oklahoma City OK 73149",
    "addr:housenumber":"6800",
    "addr:postcode":"73149",
    "addr:street":"Camille Ave",
    "iso:country":"US",
    "sg:address":"6800 Camille Ave",
    "sg:city":"Oklahoma City",
    "sg:classifiers":[
        {
            "category":"Professional",
            "subcategory":"Accounting & Tax Preparation",
            "type":"Services"
        }
    ],
    "sg:phone":"+1 405 677 8299",
    "sg:postcode":"73149",
    "sg:province":"OK",
    "wof:name":"Cathy H Polzien",
    "wof:placetype":"venue"
},
  "geometry": {"coordinates":[-97.482811,35.395317],"type":"Point"}
}