{
  "type": "Feature",
  "properties": {
    "addr:full":"117 E California Ave Oklahoma City OK 73104",
    "addr:housenumber":"117",
    "addr:postcode":"73104",
    "addr:street":"E California Ave",
    "iso:country":"US",
    "sg:address":"117 E California Ave",
    "sg:city":"Oklahoma City",
    "sg:classifiers":[
        {
            "category":"Restaurant",
            "type":"Food & Drink"
        }
    ],
    "sg:phone":"+1 405 602 1494",
    "sg:postcode":"73104",
    "sg:province":"OK",
    "wof:name":"Bricktown Keys On The Canal",
    "wof:placetype":"venue"
},
  "geometry": {"coordinates":[-97.50933999999999,35.465487],"type":"Point"}
}