{
  "type": "Feature",
  "properties": {
    "iso:country":"US",
    "sg:address":"1503 S Memorial Dr",
    "sg:city":"Tulsa",
    "sg:classifiers":[
        {
            "category":"Organizations",
            "subcategory":"Labor Organization",
            "type":"Services"
        }
    ],
    "sg:phone":"+1 918 587 6798",
    "sg:postcode":"74112",
    "sg:province":"OK",
    "wof:name":"Communications Workers-America",
    "wof:placetype":"venue"
},
  "geometry": {"coordinates":[-95.886537,36.138947],"type":"Point"}
}