{
  "type": "Feature",
  "properties": {
    "iso:country":"US",
    "sg:address":"123 Cleason Ave",
    "sg:city":"Davenport",
    "sg:classifiers":[
        {
            "category":"Organizations",
            "subcategory":"Religious Organization",
            "type":"Services"
        }
    ],
    "sg:phone":"+1 918 377 2720",
    "sg:postcode":"74026",
    "sg:province":"OK",
    "sg:tags":[
        "church"
    ],
    "wof:name":"Baptist Church",
    "wof:placetype":"venue"
},
  "geometry": {"coordinates":[-96.763806,35.704525],"type":"Point"}
}