{
  "type": "Feature",
  "properties": {
    "iso:country":"US",
    "sg:address":"2121 E 51st St",
    "sg:city":"Tulsa",
    "sg:classifiers":[
        {
            "category":"Building & Trades",
            "subcategory":"Construction",
            "type":"Services"
        }
    ],
    "sg:phone":"+1 918 493 3900",
    "sg:postcode":"74105",
    "sg:province":"OK",
    "sg:tags":[
        "asbestos",
        "removal"
    ],
    "wof:name":"Quality Asbestos Removal",
    "wof:placetype":"venue"
},
  "geometry": {"coordinates":[-95.961794,36.089838],"type":"Point"}
}