{
  "type": "Feature",
  "properties": {
    "iso:country":"US",
    "sg:address":"8528 SW 2nd St",
    "sg:city":"Oklahoma City",
    "sg:classifiers":[
        {
            "category":"Wholesale",
            "subcategory":"Machinery & Supplies",
            "type":"Manufacturing & Wholesale Goods"
        },
        {
            "category":"Manufacturing",
            "subcategory":"Tools & Machinery",
            "type":"Manufacturing & Wholesale Goods"
        }
    ],
    "sg:phone":"+1 405 789 8182",
    "sg:postcode":"73128",
    "sg:province":"OK",
    "sg:tags":[
        "repair",
        "oil",
        "field",
        "mfg",
        "equipment",
        "industrial",
        "mach"
    ],
    "sg:website":"www.downingwell.com",
    "wof:name":"Downing Wellhead Equipment Inc",
    "wof:placetype":"venue"
},
  "geometry": {"coordinates":[-97.664,35.462372],"type":"Point"}
}