{
  "type": "Feature",
  "properties": {
    "addr:full":"1415 W Main St Duncan OK 73533",
    "addr:housenumber":"1415",
    "addr:postcode":"73533",
    "addr:street":"W Main St",
    "iso:country":"US",
    "sg:address":"1415 W Main St",
    "sg:city":"Duncan",
    "sg:classifiers":[
        {
            "category":"Health Services",
            "subcategory":"Doctor",
            "type":"Services"
        }
    ],
    "sg:phone":"+1 580 255 2773",
    "sg:postcode":"73533",
    "sg:province":"OK",
    "wof:name":"Dillard Jo Ann",
    "wof:placetype":"venue"
},
  "geometry": {"coordinates":[-97.966802,34.502779],"type":"Point"}
}