{
  "type": "Feature",
  "properties": {
    "iso:country":"US",
    "sg:address":"504 N Wolfley St",
    "sg:city":"Elk City",
    "sg:classifiers":[
        {
            "category":"Building & Trades",
            "subcategory":"Construction",
            "type":"Services"
        }
    ],
    "sg:phone":"+1 580 225 1300",
    "sg:postcode":"73644",
    "sg:province":"OK",
    "sg:tags":[
        "downspouts",
        "gutter"
    ],
    "wof:name":"Rain-Away Seamless Gutter",
    "wof:placetype":"venue"
},
  "geometry": {"coordinates":[-99.395808,35.41595],"type":"Point"}
}