{
  "type": "Feature",
  "properties": {
    "iso:country":"US",
    "sg:address":"1615 N Main St",
    "sg:city":"Guymon",
    "sg:classifiers":[
        {
            "category":"Personal",
            "subcategory":"Beauty Salon",
            "type":"Services"
        }
    ],
    "sg:phone":"+1 580 338 2631",
    "sg:postcode":"73942",
    "sg:province":"OK",
    "wof:name":"Three's Co Beauty Shop",
    "wof:placetype":"venue"
},
  "geometry": {"coordinates":[-101.481321,36.697057],"type":"Point"}
}