{
  "type": "Feature",
  "properties": {
    "iso:country":"US",
    "sg:address":"3100 Thorn Ridge Rd",
    "sg:city":"Oklahoma City",
    "sg:classifiers":[
        {
            "category":"Real Estate",
            "subcategory":"Real Estate Agent",
            "type":"Services"
        }
    ],
    "sg:phone":"+1 405 751 2917",
    "sg:postcode":"73120",
    "sg:province":"OK",
    "wof:name":"Eldridge Realty Company Inc",
    "wof:placetype":"venue"
},
  "geometry": {"coordinates":[-97.57141300000001,35.59613],"type":"Point"}
}