{
  "type": "Feature",
  "properties": {
    "iso:country":"US",
    "sg:address":"2704 Warwick Ct",
    "sg:city":"Bartlesville",
    "sg:classifiers":[
        {
            "category":"Building & Trades",
            "subcategory":"Equipment Rental",
            "type":"Services"
        }
    ],
    "sg:phone":"+1 918 333 7464",
    "sg:postcode":"74006",
    "sg:province":"OK",
    "wof:name":"Manufactures Leasing Services",
    "wof:placetype":"venue"
},
  "geometry": {"coordinates":[-95.955932,36.708957],"type":"Point"}
}