{
  "type": "Feature",
  "properties": {
    "addr:full":"5800 NW Expressway St Warr Acres OK 73132",
    "addr:housenumber":"5800",
    "addr:postcode":"73132",
    "addr:street":"Nw Expressway St",
    "iso:country":"US",
    "sg:address":"5800 NW Expressway St",
    "sg:city":"Warr Acres",
    "sg:classifiers":[
        {
            "category":"Restaurant",
            "type":"Food & Drink"
        }
    ],
    "sg:menulink":"http://www.allmenus.com/ok/oklahoma-city/200122-long-john-silvers/menu/",
    "sg:phone":"+1 405 721 8255",
    "sg:postcode":"73132",
    "sg:province":"OK",
    "sg:tags":[
        "seafood",
        "american"
    ],
    "wof:name":"Long John Silver's",
    "wof:placetype":"venue"
},
  "geometry": {"coordinates":[-97.615989,35.547939],"type":"Point"}
}