{
  "type": "Feature",
  "properties": {
    "iso:country":"US",
    "sg:address":"2013 S Air Depot Blvd",
    "sg:city":"Oklahoma City",
    "sg:classifiers":[
        {
            "category":"Health Services",
            "subcategory":"Chiropractor",
            "type":"Services"
        }
    ],
    "sg:phone":"+1 405 737 5653",
    "sg:postcode":"73110",
    "sg:province":"OK",
    "sg:tags":[
        "clinic",
        "chiropractic"
    ],
    "wof:name":"Wiersig Chiropractic Clinic",
    "wof:placetype":"venue"
},
  "geometry": {"coordinates":[-97.40612299999999,35.445092],"type":"Point"}
}