{
  "type": "Feature",
  "properties": {
    "addr:full":"1019 N Broadway Ave Ada OK 74820",
    "addr:housenumber":"1019",
    "addr:postcode":"74820",
    "addr:street":"N Broadway Ave",
    "iso:country":"US",
    "sg:address":"1019 N Broadway Ave",
    "sg:city":"Ada",
    "sg:classifiers":[
        {
            "category":"Professional",
            "subcategory":"Advertising",
            "type":"Services"
        }
    ],
    "sg:phone":"+1 580 332 1212",
    "sg:postcode":"74820",
    "sg:province":"OK",
    "wof:name":"KADA",
    "wof:placetype":"venue"
},
  "geometry": {"coordinates":[-96.678828,34.784704],"type":"Point"}
}