{
  "type": "Feature",
  "properties": {
    "iso:country":"US",
    "sg:address":"201 E 45th St",
    "sg:city":"Shawnee",
    "sg:classifiers":[
        {
            "category":"Retail",
            "subcategory":"Funeral Services",
            "type":"Services"
        }
    ],
    "sg:phone":"+1 405 273 4700",
    "sg:postcode":"74804",
    "sg:province":"OK",
    "sg:tags":[
        "director"
    ],
    "wof:name":"Walker Funeral Svc",
    "wof:placetype":"venue"
},
  "geometry": {"coordinates":[-96.921898,35.376226],"type":"Point"}
}