{
  "type": "Feature",
  "properties": {
    "iso:country":"US",
    "sg:address":"13730 N Pennsylvania Ave",
    "sg:city":"Oklahoma City",
    "sg:classifiers":[
        {
            "category":"Shopping",
            "subcategory":"Computers & Home Electronics",
            "type":"Retail Goods"
        }
    ],
    "sg:phone":"+1 405 752 2161",
    "sg:postcode":"73134",
    "sg:province":"OK",
    "sg:tags":[
        "equipment",
        "electronic",
        "supply"
    ],
    "wof:name":"Circuit City",
    "wof:placetype":"venue"
},
  "geometry": {"coordinates":[-97.549412,35.610407],"type":"Point"}
}