{
  "type": "Feature",
  "properties": {
    "iso:country":"US",
    "sg:address":"2809 W Atlanta St",
    "sg:city":"Broken Arrow",
    "sg:classifiers":[
        {
            "category":"Building & Trades",
            "subcategory":"Construction",
            "type":"Services"
        }
    ],
    "sg:phone":"+1 918 254 1360",
    "sg:postcode":"74012",
    "sg:province":"OK",
    "sg:tags":[
        "contractor"
    ],
    "wof:name":"Concrete Prsrvtion Systems Inc",
    "wof:placetype":"venue"
},
  "geometry": {"coordinates":[-95.825654,36.030601],"type":"Point"}
}