{
  "type": "Feature",
  "properties": {
    "addr:full":"2001 N Perkins Rd Stillwater OK 74075",
    "addr:housenumber":"2001",
    "addr:postcode":"74075",
    "addr:street":"N Perkins Rd",
    "iso:country":"US",
    "sg:address":"2001 N Perkins Rd",
    "sg:city":"Stillwater",
    "sg:classifiers":[
        {
            "category":"Real Estate",
            "subcategory":"Real Estate Operator",
            "type":"Services"
        }
    ],
    "sg:phone":"+1 405 372 3616",
    "sg:postcode":"74075",
    "sg:province":"OK",
    "sg:tags":[
        "apartment"
    ],
    "wof:name":"Lift Apartments",
    "wof:placetype":"venue"
},
  "geometry": {"coordinates":[-97.051466,36.140962],"type":"Point"}
}