{
  "type": "Feature",
  "properties": {
    "iso:country":"US",
    "sg:address":"1004 S Okfusakee Ave",
    "sg:city":"Wewoka",
    "sg:classifiers":[
        {
            "category":"Social Services",
            "subcategory":"Child Care",
            "type":"Services"
        }
    ],
    "sg:phone":"+1 405 257 6114",
    "sg:postcode":"74884",
    "sg:province":"OK",
    "wof:name":"Keiki Lani",
    "wof:placetype":"venue"
},
  "geometry": {"coordinates":[-96.495295,35.148887],"type":"Point"}
}