{
  "type": "Feature",
  "properties": {
    "iso:country":"US",
    "sg:address":"705 E Prospect Ave",
    "sg:city":"Ponca City",
    "sg:classifiers":[
        {
            "category":"Home & Garden",
            "subcategory":"Building Materials",
            "type":"Retail Goods"
        }
    ],
    "sg:phone":"+1 580 762 8301",
    "sg:postcode":"74601",
    "sg:province":"OK",
    "sg:tags":[
        "lumber"
    ],
    "wof:name":"Hughes Lumber 05",
    "wof:placetype":"venue"
},
  "geometry": {"coordinates":[-97.076365,36.7387],"type":"Point"}
}