{
  "type": "Feature",
  "properties": {
    "iso:country":"US",
    "sg:address":"12546 E 18th St",
    "sg:city":"Tulsa",
    "sg:classifiers":[
        {
            "category":"Manufacturing",
            "subcategory":"Metals",
            "type":"Manufacturing & Wholesale Goods"
        }
    ],
    "sg:phone":"+1 918 437 9028",
    "sg:postcode":"74128",
    "sg:province":"OK",
    "sg:tags":[
        "frame",
        "door"
    ],
    "wof:name":"Hamilton Metal Doors",
    "wof:placetype":"venue"
},
  "geometry": {"coordinates":[-95.836955,36.1369],"type":"Point"}
}