{
  "type": "Feature",
  "properties": {
    "addr:full":"210 Oak St Poteau OK 74953",
    "addr:housenumber":"210",
    "addr:postcode":"74953",
    "addr:street":"Oak St",
    "iso:country":"US",
    "sg:address":"210 Oak St",
    "sg:city":"Poteau",
    "sg:classifiers":[
        {
            "category":"Utilities",
            "subcategory":"Cable",
            "type":"Services"
        }
    ],
    "sg:phone":"+1 918 649 1069",
    "sg:postcode":"74953",
    "sg:province":"OK",
    "sg:tags":[
        "satellite",
        "carrier"
    ],
    "wof:name":"Gene's Satellite Svc",
    "wof:placetype":"venue"
},
  "geometry": {"coordinates":[-94.621438,35.065159],"type":"Point"}
}