{
  "type": "Feature",
  "properties": {
    "iso:country":"US",
    "sg:address":"3101 N Toledo Ave",
    "sg:city":"Tulsa",
    "sg:classifiers":[
        {
            "category":"Manufacturing",
            "subcategory":"Tools & Machinery",
            "type":"Manufacturing & Wholesale Goods"
        },
        {
            "category":"Transit Center",
            "subcategory":"Freight",
            "type":"Transportation"
        },
        {
            "category":"Building & Trades",
            "subcategory":"Equipment Rental",
            "type":"Services"
        },
        {
            "category":"Building & Trades",
            "subcategory":"Construction",
            "type":"Services"
        },
        {
            "category":"Manufacturing",
            "subcategory":"Building Materials",
            "type":"Manufacturing & Wholesale Goods"
        }
    ],
    "sg:phone":"+1 918 835 4500",
    "sg:postcode":"74115",
    "sg:province":"OK",
    "sg:tags":[
        "leasing",
        "cranes-mobile",
        "erectors",
        "hoist",
        "crane",
        "cranes-renting",
        "mover"
    ],
    "sg:website":"http://www.midwestcraneservices.com",
    "wof:name":"Midwest Crane Services",
    "wof:placetype":"venue"
},
  "geometry": {"coordinates":[-95.92736499999999,36.201676],"type":"Point"}
}