{
  "type": "Feature",
  "properties": {
    "iso:country":"US",
    "sg:address":"1409 NW Sheridan Rd",
    "sg:city":"Lawton",
    "sg:classifiers":[
        {
            "category":"Restaurant",
            "type":"Food & Drink"
        }
    ],
    "sg:phone":"+1 580 353 0883",
    "sg:postcode":"73505",
    "sg:province":"OK",
    "sg:tags":[
        "eating"
    ],
    "wof:name":"China Wok Express",
    "wof:placetype":"venue"
},
  "geometry": {"coordinates":[-98.422184,34.624271],"type":"Point"}
}