{
  "type": "Feature",
  "properties": {
    "addr:full":"1313 E Main St Cushing OK 74023",
    "addr:housenumber":"1313",
    "addr:postcode":"74023",
    "addr:street":"E Main St",
    "iso:country":"US",
    "sg:address":"1313 E Main St",
    "sg:city":"Cushing",
    "sg:classifiers":[
        {
            "category":"Restaurant",
            "type":"Food & Drink"
        },
        {
            "category":"Ice Cream",
            "type":"Food & Drink"
        }
    ],
    "sg:menulink":"http://www.allmenus.com/ok/cushing/218823-braums-ice-cream--dairy-stores/menu/",
    "sg:phone":"+1 918 225 3290",
    "sg:postcode":"74023",
    "sg:province":"OK",
    "sg:tags":[
        "american",
        "ice",
        "cream"
    ],
    "wof:name":"Braum's Ice Cream & Dairy Stores",
    "wof:placetype":"venue"
},
  "geometry": {"coordinates":[-96.75181000000001,35.985048],"type":"Point"}
}