{
  "type": "Feature",
  "properties": {
    "iso:country":"US",
    "sg:address":"10100 NE 10th St",
    "sg:city":"Midwest City",
    "sg:classifiers":[
        {
            "category":"Home & Garden",
            "subcategory":"Building Materials",
            "type":"Retail Goods"
        },
        {
            "category":"Manufacturing",
            "subcategory":"Glass & Minerals",
            "type":"Manufacturing & Wholesale Goods"
        }
    ],
    "sg:phone":"+1 405 424 4383",
    "sg:postcode":"73130",
    "sg:province":"OK",
    "sg:tags":[
        "ready",
        "mixed",
        "mfg",
        "concrete"
    ],
    "wof:name":"Goddard Ready Mix Concrete Co",
    "wof:placetype":"venue"
},
  "geometry": {"coordinates":[-97.350065,35.478533],"type":"Point"}
}