{
  "type": "Feature",
  "properties": {
    "addr:full":"203 East Hwy Holdenville OK 74848",
    "addr:housenumber":"203",
    "addr:postcode":"74848",
    "addr:street":"East Hwy",
    "iso:country":"US",
    "sg:address":"203 East Hwy",
    "sg:city":"Holdenville",
    "sg:classifiers":[
        {
            "category":"Shopping",
            "subcategory":"Pharmacy",
            "type":"Retail Goods"
        }
    ],
    "sg:phone":"+1 405 379 3381",
    "sg:postcode":"74848",
    "sg:province":"OK",
    "wof:name":"Nichol's Dollar Saver Pharmacy",
    "wof:placetype":"venue"
},
  "geometry": {"coordinates":[-96.38686300000001,35.086697],"type":"Point"}
}