{
  "type": "Feature",
  "properties": {
    "iso:country":"US",
    "sg:address":"2816 Parklawn Dr",
    "sg:city":"Oklahoma City",
    "sg:classifiers":[
        {
            "category":"Health Services",
            "subcategory":"Doctor",
            "type":"Services"
        }
    ],
    "sg:phone":"+1 405 869 0340",
    "sg:postcode":"73110",
    "sg:province":"OK",
    "sg:tags":[
        "clinic"
    ],
    "wof:name":"Sunshine Medical Clinic",
    "wof:placetype":"venue"
},
  "geometry": {"coordinates":[-97.393196,35.464528],"type":"Point"}
}