{
  "type": "Feature",
  "properties": {
    "iso:country":"US",
    "sg:address":"6012 S Western Ave",
    "sg:city":"Oklahoma City",
    "sg:classifiers":[
        {
            "category":"Shopping",
            "subcategory":"Clothing, Apparel, & Fashions",
            "type":"Retail Goods"
        }
    ],
    "sg:phone":"+1 405 631 2229",
    "sg:postcode":"73139",
    "sg:province":"OK",
    "sg:tags":[
        "used",
        "wear",
        "merchandise"
    ],
    "wof:name":"Babys Bargains Resale Inc",
    "wof:placetype":"venue"
},
  "geometry": {"coordinates":[-97.530107,35.405369],"type":"Point"}
}