{
  "type": "Feature",
  "properties": {
    "iso:country":"US",
    "sg:address":"1001 Stanton L Young Blvd",
    "sg:city":"Oklahoma City",
    "sg:classifiers":[
        {
            "category":"Health Services",
            "subcategory":"Doctor",
            "type":"Services"
        }
    ],
    "sg:phone":"+1 405 271 2209",
    "sg:postcode":"73117",
    "sg:province":"OK",
    "sg:tags":[
        "dentist"
    ],
    "wof:name":"Univ Of Oklahoma Dental School",
    "wof:placetype":"venue"
},
  "geometry": {"coordinates":[-97.495081,35.480187],"type":"Point"}
}