{
  "type": "Feature",
  "properties": {
    "iso:country":"US",
    "sg:address":"6313 Connaught Ct",
    "sg:city":"Oklahoma City",
    "sg:classifiers":[
        {
            "category":"Real Estate",
            "subcategory":"Architect",
            "type":"Services"
        }
    ],
    "sg:phone":"+1 405 943 2352",
    "sg:postcode":"73132",
    "sg:province":"OK",
    "sg:tags":[
        "architectural"
    ],
    "wof:name":"Sprague & Associates Inc",
    "wof:placetype":"venue"
},
  "geometry": {"coordinates":[-97.627219,35.560433],"type":"Point"}
}