{
  "type": "Feature",
  "properties": {
    "addr:full":"3801 W Gore Blvd Lawton OK 73505",
    "addr:housenumber":"3801",
    "addr:postcode":"73505",
    "addr:street":"W Gore Blvd",
    "iso:country":"US",
    "sg:address":"3801 W Gore Blvd",
    "sg:city":"Lawton",
    "sg:classifiers":[
        {
            "category":"Food & Beverages",
            "subcategory":"Groceries & Convenience Stores",
            "type":"Retail Goods"
        }
    ],
    "sg:phone":"+1 580 248 3801",
    "sg:postcode":"73505",
    "sg:province":"OK",
    "wof:name":"Circle K Store",
    "wof:placetype":"venue"
},
  "geometry": {"coordinates":[-98.440693,34.608919],"type":"Point"}
}