{
  "type": "Feature",
  "properties": {
    "iso:country":"US",
    "sg:address":"2000 W Detroit St",
    "sg:city":"Broken Arrow",
    "sg:classifiers":[
        {
            "category":"Professional",
            "type":"Services"
        },
        {
            "category":"Building & Trades",
            "subcategory":"Plumbing",
            "type":"Services"
        }
    ],
    "sg:phone":"+1 918 258 9666",
    "sg:postcode":"74012",
    "sg:province":"OK",
    "sg:tags":[
        "installation",
        "fire",
        "system",
        "hazard",
        "contractor",
        "establishment"
    ],
    "wof:name":"Automatic Protection Systems",
    "wof:placetype":"venue"
},
  "geometry": {"coordinates":[-95.811927,36.05424],"type":"Point"}
}