{
  "type": "Feature",
  "properties": {
    "iso:country":"US",
    "sg:address":"2600 Highland Ave",
    "sg:city":"Woodward",
    "sg:classifiers":[
        {
            "category":"Communications",
            "subcategory":"Film & Video Production",
            "type":"Services"
        }
    ],
    "sg:phone":"+1 580 256 1892",
    "sg:postcode":"73801",
    "sg:province":"OK",
    "sg:tags":[
        "taping"
    ],
    "wof:name":"Still N Motion",
    "wof:placetype":"venue"
},
  "geometry": {"coordinates":[-99.41484199999999,36.439707],"type":"Point"}
}