{
  "type": "Feature",
  "properties": {
    "iso:country":"US",
    "sg:address":"6967 S Lewis Ave",
    "sg:city":"Tulsa",
    "sg:classifiers":[
        {
            "category":"Wholesale",
            "subcategory":"Jewelry",
            "type":"Manufacturing & Wholesale Goods"
        },
        {
            "category":"Shopping",
            "subcategory":"Gifts & Souvenirs",
            "type":"Retail Goods"
        }
    ],
    "sg:phone":"+1 918 524 4300",
    "sg:postcode":"74136",
    "sg:province":"OK",
    "sg:tags":[
        "jeweler",
        "supply"
    ],
    "wof:name":"Beaded Sisters Inc",
    "wof:placetype":"venue"
},
  "geometry": {"coordinates":[-95.957855,36.063145],"type":"Point"}
}