{
  "type": "Feature",
  "properties": {
    "iso:country":"US",
    "sg:address":"2324 W 7th Ave",
    "sg:city":"Stillwater",
    "sg:classifiers":[
        {
            "category":"Professional",
            "subcategory":"Accounting & Tax Preparation",
            "type":"Services"
        }
    ],
    "sg:phone":"+1 405 533 2800",
    "sg:postcode":"74074",
    "sg:province":"OK",
    "sg:tags":[
        "accountant"
    ],
    "wof:name":"Jerry Parsons CPA",
    "wof:placetype":"venue"
},
  "geometry": {"coordinates":[-97.088994,36.114716],"type":"Point"}
}