{
  "type": "Feature",
  "properties": {
    "iso:country":"US",
    "sg:address":"904 N Hemlock Ave",
    "sg:city":"Broken Arrow",
    "sg:classifiers":[
        {
            "category":"Home & Garden",
            "subcategory":"Building Materials",
            "type":"Retail Goods"
        }
    ],
    "sg:phone":"+1 918 250 8681",
    "sg:postcode":"74012",
    "sg:province":"OK",
    "wof:name":"Mike Fretz Inc",
    "wof:placetype":"venue"
},
  "geometry": {"coordinates":[-95.825074,36.059926],"type":"Point"}
}