{
  "type": "Feature",
  "properties": {
    "iso:country":"US",
    "sg:address":"15645 State Hwy 66",
    "sg:city":"Yukon",
    "sg:classifiers":[
        {
            "category":"Building & Trades",
            "subcategory":"Construction",
            "type":"Services"
        }
    ],
    "sg:phone":"+1 405 350 2133",
    "sg:postcode":"73099",
    "sg:province":"OK",
    "sg:tags":[
        "masonry",
        "contractor"
    ],
    "wof:name":"Masonry Service",
    "wof:placetype":"venue"
},
  "geometry": {"coordinates":[-97.818744,35.507956],"type":"Point"}
}