{
  "type": "Feature",
  "properties": {
    "addr:full":"820 E Detroit St Broken Arrow OK 74012",
    "addr:housenumber":"820",
    "addr:postcode":"74012",
    "addr:street":"E Detroit St",
    "iso:country":"US",
    "sg:address":"820 E Detroit St",
    "sg:city":"Broken Arrow",
    "sg:classifiers":[
        {
            "category":"Shopping",
            "type":"Retail Goods"
        }
    ],
    "sg:phone":"+1 918 251 5973",
    "sg:postcode":"74012",
    "sg:province":"OK",
    "sg:tags":[
        "merchandise"
    ],
    "wof:name":"Oneta Warehouse LLC",
    "wof:placetype":"venue"
},
  "geometry": {"coordinates":[-95.78040799999999,36.054505],"type":"Point"}
}