{
  "type": "Feature",
  "properties": {
    "iso:country":"US",
    "sg:address":"3701 N Meridian Ave",
    "sg:city":"Oklahoma City",
    "sg:classifiers":[
        {
            "category":"Professional",
            "subcategory":"Accounting & Tax Preparation",
            "type":"Services"
        }
    ],
    "sg:phone":"+1 405 495 5595",
    "sg:postcode":"73112",
    "sg:province":"OK",
    "sg:tags":[
        "accountant"
    ],
    "wof:name":"David Green CPA",
    "wof:placetype":"venue"
},
  "geometry": {"coordinates":[-97.60118300000001,35.508976],"type":"Point"}
}