{
  "type": "Feature",
  "properties": {
    "iso:country":"US",
    "sg:address":"25373 S Concord Dr",
    "sg:city":"Catoosa",
    "sg:classifiers":[
        {
            "category":"Wholesale",
            "subcategory":"Medical Equipment & Supplies",
            "type":"Manufacturing & Wholesale Goods"
        }
    ],
    "sg:phone":"+1 918 835 4357",
    "sg:postcode":"74019",
    "sg:province":"OK",
    "sg:tags":[
        "physician",
        "surgeon"
    ],
    "wof:name":"Raley's Lifeline",
    "wof:placetype":"venue"
},
  "geometry": {"coordinates":[-95.666505,36.245064],"type":"Point"}
}