{
  "type": "Feature",
  "properties": {
    "iso:country":"US",
    "sg:address":"1401 E 138th Pl",
    "sg:city":"Glenpool",
    "sg:classifiers":[
        {
            "category":"Building & Trades",
            "subcategory":"Construction",
            "type":"Services"
        }
    ],
    "sg:phone":"+1 918 291 0430",
    "sg:postcode":"74033",
    "sg:province":"OK",
    "sg:tags":[
        "hanging",
        "contractor"
    ],
    "wof:name":"Craig Adams",
    "wof:placetype":"venue"
},
  "geometry": {"coordinates":[-95.986645,35.962744],"type":"Point"}
}