{
  "type": "Feature",
  "properties": {
    "iso:country":"US",
    "sg:address":"608 Wellington St",
    "sg:city":"Glencoe",
    "sg:classifiers":[
        {
            "category":"Building & Trades",
            "subcategory":"Construction",
            "type":"Services"
        }
    ],
    "sg:phone":"+1 405 612 4169",
    "sg:postcode":"74032",
    "sg:province":"OK",
    "sg:tags":[
        "downspouts",
        "gutter"
    ],
    "wof:name":"Pioneer Gutter",
    "wof:placetype":"venue"
},
  "geometry": {"coordinates":[-96.932206,36.220943],"type":"Point"}
}