{
  "type": "Feature",
  "properties": {
    "iso:country":"US",
    "sg:address":"5303 N Santa Fe Ave",
    "sg:city":"Oklahoma City",
    "sg:classifiers":[
        {
            "category":"Building & Trades",
            "subcategory":"Construction",
            "type":"Services"
        }
    ],
    "sg:phone":"+1 405 842 9801",
    "sg:postcode":"73118",
    "sg:province":"OK",
    "wof:name":"Muskogee Bridge Co Inc",
    "wof:placetype":"venue"
},
  "geometry": {"coordinates":[-97.512199,35.525032],"type":"Point"}
}