{
  "type": "Feature",
  "properties": {
    "iso:country":"US",
    "sg:address":"424 N Washington St",
    "sg:city":"Stillwater",
    "sg:classifiers":[
        {
            "category":"Organizations",
            "subcategory":"Community Association",
            "type":"Services"
        }
    ],
    "sg:phone":"+1 405 372 7264",
    "sg:postcode":"74075",
    "sg:province":"OK",
    "sg:tags":[
        "membership",
        "lodging"
    ],
    "wof:name":"Farmhouse Fraternity",
    "wof:placetype":"venue"
},
  "geometry": {"coordinates":[-97.06948300000001,36.127825],"type":"Point"}
}