{
  "type": "Feature",
  "properties": {
    "iso:country":"US",
    "sg:address":"100 W Reno Ave",
    "sg:city":"Oklahoma City",
    "sg:classifiers":[
        {
            "category":"Arena",
            "subcategory":"Sports Club",
            "type":"Entertainment"
        }
    ],
    "sg:phone":"+1 405 602 8700",
    "sg:postcode":"73102",
    "sg:province":"OK",
    "sg:tags":[
        "athletic",
        "fields",
        "stadium"
    ],
    "wof:name":"Ford Center",
    "wof:placetype":"venue"
},
  "geometry": {"coordinates":[-97.516247,35.464272],"type":"Point"}
}