{
  "type": "Feature",
  "properties": {
    "addr:full":"3069 E Interstate Dr Norman OK 73069",
    "addr:housenumber":"3069",
    "addr:postcode":"73069",
    "addr:street":"E Interstate Dr",
    "iso:country":"US",
    "sg:address":"3069 E Interstate Dr",
    "sg:city":"Norman",
    "sg:classifiers":[
        {
            "category":"Wholesale",
            "subcategory":"Medical Equipment & Supplies",
            "type":"Manufacturing & Wholesale Goods"
        }
    ],
    "sg:phone":"+1 405 321 5593",
    "sg:postcode":"73069",
    "sg:province":"OK",
    "sg:tags":[
        "physician",
        "surgeon"
    ],
    "wof:name":"Red River Industries Inc",
    "wof:placetype":"venue"
},
  "geometry": {"coordinates":[-97.48666900000001,35.258521],"type":"Point"}
}