{
  "type": "Feature",
  "properties": {
    "addr:full":"809 S 12th St Broken Arrow OK 74012",
    "addr:housenumber":"809",
    "addr:postcode":"74012",
    "addr:street":"S 12Th St",
    "iso:country":"US",
    "sg:address":"809 S 12th St",
    "sg:city":"Broken Arrow",
    "sg:classifiers":[
        {
            "category":"Manufacturing",
            "subcategory":"Tools & Machinery",
            "type":"Manufacturing & Wholesale Goods"
        }
    ],
    "sg:phone":"+1 918 251 1164",
    "sg:postcode":"74012",
    "sg:province":"OK",
    "sg:tags":[
        "shop",
        "repair",
        "industrial",
        "mfg",
        "machine",
        "welding"
    ],
    "wof:name":"Hill Manufacturing Inc",
    "wof:placetype":"venue"
},
  "geometry": {"coordinates":[-95.775807,36.045419],"type":"Point"}
}