{
  "type": "Feature",
  "properties": {
    "iso:country":"US",
    "sg:address":"505 NW A St",
    "sg:city":"Stigler",
    "sg:classifiers":[
        {
            "category":"Professional",
            "subcategory":"Management & Consulting",
            "type":"Services"
        }
    ],
    "sg:phone":"+1 918 967 2317",
    "sg:postcode":"74462",
    "sg:province":"OK",
    "sg:tags":[
        "selling",
        "establishment",
        "direct"
    ],
    "wof:name":"Shaklee Distributor",
    "wof:placetype":"venue"
},
  "geometry": {"coordinates":[-95.130976,35.256634],"type":"Point"}
}