{
  "type": "Feature",
  "properties": {
    "iso:country":"US",
    "sg:address":"1717 W Xyler St",
    "sg:city":"Tulsa",
    "sg:classifiers":[
        {
            "category":"Local Transit",
            "type":"Transportation"
        }
    ],
    "sg:phone":"+1 918 587 4300",
    "sg:postcode":"74127",
    "sg:province":"OK",
    "sg:tags":[
        "passenger"
    ],
    "wof:name":"Tanyas Classic Limousines",
    "wof:placetype":"venue"
},
  "geometry": {"coordinates":[-96.01378,36.186583],"type":"Point"}
}