{
  "type": "Feature",
  "properties": {
    "addr:full":"12584 E 111th St N Owasso OK 74055",
    "addr:housenumber":"12584",
    "addr:postcode":"74055",
    "addr:street":"E 111Th St N",
    "iso:country":"US",
    "sg:address":"12584 E 111th St N",
    "sg:city":"Owasso",
    "sg:classifiers":[
        {
            "category":"Building & Trades",
            "subcategory":"Construction",
            "type":"Services"
        }
    ],
    "sg:phone":"+1 918 371 3715",
    "sg:postcode":"74055",
    "sg:province":"OK",
    "sg:tags":[
        "concrete",
        "contractor"
    ],
    "wof:name":"Prw Construction",
    "wof:placetype":"venue"
},
  "geometry": {"coordinates":[-95.83386299999999,36.315672],"type":"Point"}
}