{
  "type": "Feature",
  "properties": {
    "iso:country":"US",
    "sg:address":"1150 S Sheridan Rd",
    "sg:city":"Tulsa",
    "sg:classifiers":[
        {
            "category":"Recreation",
            "type":"Entertainment"
        }
    ],
    "sg:phone":"+1 918 836 3344",
    "sg:postcode":"74112",
    "sg:province":"OK",
    "wof:name":"Skateland Inc",
    "wof:placetype":"venue"
},
  "geometry": {"coordinates":[-95.90466,36.14706],"type":"Point"}
}