{
  "type": "Feature",
  "properties": {
    "iso:country":"US",
    "sg:address":"5228 N Peoria Ave",
    "sg:city":"Tulsa",
    "sg:classifiers":[
        {
            "category":"Shopping",
            "subcategory":"Department Store",
            "type":"Retail Goods"
        }
    ],
    "sg:phone":"+1 918 428 2451",
    "sg:postcode":"74126",
    "sg:province":"OK",
    "sg:tags":[
        "shop"
    ],
    "wof:name":"Family Dollar Store",
    "wof:placetype":"venue"
},
  "geometry": {"coordinates":[-95.975635,36.230364],"type":"Point"}
}