{
  "type": "Feature",
  "properties": {
    "iso:country":"US",
    "sg:address":"9972 Old US Hwy 75",
    "sg:city":"Beggs",
    "sg:classifiers":[
        {
            "category":"Social Services",
            "type":"Services"
        }
    ],
    "sg:phone":"+1 918 458 9827",
    "sg:postcode":"74421",
    "sg:province":"OK",
    "sg:tags":[
        "individual",
        "family"
    ],
    "wof:name":"Greater Works",
    "wof:placetype":"venue"
},
  "geometry": {"coordinates":[-96.016721,35.711559],"type":"Point"}
}