{
  "type": "Feature",
  "properties": {
    "addr:full":"9500 NE 150th St Arcadia OK 73007",
    "addr:housenumber":"9500",
    "addr:postcode":"73007",
    "addr:street":"Ne 150Th St",
    "iso:country":"US",
    "sg:address":"9500 NE 150th St",
    "sg:city":"Arcadia",
    "sg:classifiers":[
        {
            "category":"Organizations",
            "subcategory":"Non-profit Organization",
            "type":"Services"
        }
    ],
    "sg:phone":"+1 405 396 2942",
    "sg:postcode":"73007",
    "sg:province":"OK",
    "sg:tags":[
        "information",
        "abuse",
        "treatment",
        "child"
    ],
    "wof:name":"Genesis Project",
    "wof:placetype":"venue"
},
  "geometry": {"coordinates":[-97.370318,35.623694],"type":"Point"}
}