{
  "type": "Feature",
  "properties": {
    "iso:country":"US",
    "sg:address":"1423 Wrangler Blvd",
    "sg:city":"Seminole",
    "sg:classifiers":[
        {
            "category":"Personal",
            "type":"Services"
        }
    ],
    "sg:phone":"+1 405 382 5462",
    "sg:postcode":"74868",
    "sg:province":"OK",
    "sg:tags":[
        "therapist",
        "massage"
    ],
    "wof:name":"Kim Chaffin Massage & Nails",
    "wof:placetype":"venue"
},
  "geometry": {"coordinates":[-96.68706400000001,35.246503],"type":"Point"}
}