{
  "type": "Feature",
  "properties": {
    "iso:country":"US",
    "sg:address":"213 N Bickford Ave",
    "sg:city":"El Reno",
    "sg:classifiers":[
        {
            "category":"Banks & Credit Unions",
            "subcategory":"Bank",
            "type":"Services"
        }
    ],
    "sg:phone":"+1 405 422 3102",
    "sg:postcode":"73036",
    "sg:province":"OK",
    "sg:tags":[
        "loan"
    ],
    "wof:name":"Tower Loan",
    "wof:placetype":"venue"
},
  "geometry": {"coordinates":[-97.953855,35.534896],"type":"Point"}
}