{
  "type": "Feature",
  "properties": {
    "addr:full":"8125 E 112th St S Bixby OK 74008",
    "addr:housenumber":"8125",
    "addr:postcode":"74008",
    "addr:street":"E 112Th St S",
    "iso:country":"US",
    "sg:address":"8125 E 112th St S",
    "sg:city":"Bixby",
    "sg:classifiers":[
        {
            "category":"Building & Trades",
            "subcategory":"Construction",
            "type":"Services"
        }
    ],
    "sg:phone":"+1 918 369 6448",
    "sg:postcode":"74008",
    "sg:province":"OK",
    "sg:tags":[
        "downspouts",
        "gutter"
    ],
    "wof:name":"Aqua Flo Guttering Co",
    "wof:placetype":"venue"
},
  "geometry": {"coordinates":[-95.883217,36.000798],"type":"Point"}
}