{
  "type": "Feature",
  "properties": {
    "iso:country":"US",
    "sg:address":"1002 N Main St",
    "sg:city":"Guymon",
    "sg:classifiers":[
        {
            "category":"Building & Trades",
            "subcategory":"Landscaping Services",
            "type":"Services"
        }
    ],
    "sg:phone":"+1 580 338 6144",
    "sg:postcode":"73942",
    "sg:province":"OK",
    "sg:tags":[
        "grass"
    ],
    "wof:name":"Dino Partnership LTD",
    "wof:placetype":"venue"
},
  "geometry": {"coordinates":[-101.481646,36.68791],"type":"Point"}
}