{
  "type": "Feature",
  "properties": {
    "addr:full":"790 Oak Hill Rd Choctaw OK 73020",
    "addr:housenumber":"790",
    "addr:postcode":"73020",
    "addr:street":"Oak Hill Rd",
    "iso:country":"US",
    "sg:address":"790 Oak Hill Rd",
    "sg:city":"Choctaw",
    "sg:classifiers":[
        {
            "category":"Retail",
            "subcategory":"Repair Shop",
            "type":"Services"
        }
    ],
    "sg:phone":"+1 405 390 1910",
    "sg:postcode":"73020",
    "sg:province":"OK",
    "sg:tags":[
        "related"
    ],
    "wof:name":"Control Center",
    "wof:placetype":"venue"
},
  "geometry": {"coordinates":[-97.272189,35.476213],"type":"Point"}
}