{
  "type": "Feature",
  "properties": {
    "addr:full":"9198 W Shady Grove Rd Hulbert OK 74441",
    "addr:housenumber":"9198",
    "addr:postcode":"74441",
    "addr:street":"W Shady Grove Rd",
    "iso:country":"US",
    "sg:address":"9198 W Shady Grove Rd",
    "sg:city":"Hulbert",
    "sg:classifiers":[
        {
            "category":"Personal",
            "subcategory":"Beauty Salon",
            "type":"Services"
        }
    ],
    "sg:phone":"+1 918 772 3134",
    "sg:postcode":"74441",
    "sg:province":"OK",
    "sg:tags":[
        "shop"
    ],
    "wof:name":"Joy's Beauty Shop",
    "wof:placetype":"venue"
},
  "geometry": {"coordinates":[-95.132543,35.944233],"type":"Point"}
}