{
  "type": "Feature",
  "properties": {
    "iso:country":"US",
    "sg:address":"8400 S Hwy 137",
    "sg:city":"Miami",
    "sg:classifiers":[
        {
            "category":"Communications",
            "subcategory":"Radio Station",
            "type":"Services"
        }
    ],
    "sg:phone":"+1 918 542 1818",
    "sg:postcode":"74354",
    "sg:province":"OK",
    "sg:tags":[
        "company",
        "broadcasting"
    ],
    "wof:name":"KGLC",
    "wof:placetype":"venue"
},
  "geometry": {"coordinates":[-94.787603,36.894337],"type":"Point"}
}