{
  "type": "Feature",
  "properties": {
    "iso:country":"US",
    "sg:address":"6425 N Rockford Ave",
    "sg:city":"Tulsa",
    "sg:classifiers":[
        {
            "category":"Retail",
            "subcategory":"Auto Repair",
            "type":"Services"
        }
    ],
    "sg:phone":"+1 918 425 0070",
    "sg:postcode":"74126",
    "sg:province":"OK",
    "sg:tags":[
        "repairing",
        "automobile"
    ],
    "wof:name":"Masters Mobile Auto Repair",
    "wof:placetype":"venue"
},
  "geometry": {"coordinates":[-95.971757,36.246095],"type":"Point"}
}