{
  "type": "Feature",
  "properties": {
    "addr:full":"14543 E Hwy 20 Claremore OK 74019",
    "addr:housenumber":"14543",
    "addr:postcode":"74019",
    "addr:street":"E Hwy 20",
    "iso:country":"US",
    "sg:address":"14543 E Hwy 20",
    "sg:city":"Claremore",
    "sg:classifiers":[
        {
            "category":"Home & Garden",
            "subcategory":"Garden Supply",
            "type":"Retail Goods"
        }
    ],
    "sg:phone":"+1 918 342 2312",
    "sg:postcode":"74019",
    "sg:province":"OK",
    "sg:tags":[
        "lawn",
        "mower"
    ],
    "wof:name":"C & D Rental & Sales",
    "wof:placetype":"venue"
},
  "geometry": {"coordinates":[-95.56326900000001,36.30728],"type":"Point"}
}