{
  "type": "Feature",
  "properties": {
    "iso:country":"US",
    "sg:address":"419 N Massingale Dr",
    "sg:city":"Cordell",
    "sg:classifiers":[
        {
            "category":"Education",
            "subcategory":"School",
            "type":"Public Place"
        }
    ],
    "sg:phone":"+1 580 832 3220",
    "sg:postcode":"73632",
    "sg:province":"OK",
    "sg:website":"www.cordell.k12.ok.us",
    "wof:name":"Cordell Elementary School",
    "wof:placetype":"venue"
},
  "geometry": {"coordinates":[-98.97995299999999,35.294562],"type":"Point"}
}