{
  "type": "Feature",
  "properties": {
    "addr:city":"Tulsa",
    "addr:full":"2435 S Peoria Ave Tulsa, Ok 74114-1326",
    "addr:house_number":"2435",
    "addr:housenumber":"2435",
    "addr:phone":"+1 918-746-5125",
    "addr:postcode":"74114-1326",
    "addr:road":"S Peoria Ave",
    "addr:state":"OK",
    "addr:street":"S Peoria Ave",
    "iso:country":"US",
    "sg:address":"2435 S Peoria Ave",
    "sg:city":"Tulsa",
    "sg:classifiers":[
        {
            "category":"Organizations",
            "subcategory":"Non-profit Organization",
            "type":"Services"
        }
    ],
    "sg:phone":"+1 918 746 5125",
    "sg:postcode":"74114",
    "sg:province":"OK",
    "sg:website":"www.tulsagardencenter.com",
    "wof:airports":[
        102528139,
        102527781
    ],
    "wof:name":"Tulsa Garden Center",
    "wof:placetype":"venue"
},
  "geometry": {"coordinates":[-95.97557,36.13072],"type":"Point"}
}