{
  "type": "Feature",
  "properties": {
    "iso:country":"US",
    "sg:address":"2435 S Peoria Ave",
    "sg:city":"Tulsa",
    "sg:classifiers":[
        {
            "category":"Organizations",
            "subcategory":"Non-profit Organization",
            "type":"Services"
        }
    ],
    "sg:phone":"+1 918 746 5125",
    "sg:postcode":"74114",
    "sg:province":"OK",
    "sg:website":"www.tulsagardencenter.com",
    "wof:name":"Tulsa Garden Ctr",
    "wof:placetype":"venue"
},
  "geometry": {"coordinates":[-95.97567,36.131518],"type":"Point"}
}