{
  "type": "Feature",
  "properties": {
    "addr:full":"232 S Air Depot Blvd Midwest City OK 73110",
    "addr:housenumber":"232",
    "addr:postcode":"73110",
    "addr:street":"S Air Depot Blvd",
    "iso:country":"US",
    "sg:address":"232 S Air Depot Blvd",
    "sg:city":"Midwest City",
    "sg:classifiers":[
        {
            "category":"Shopping",
            "subcategory":"Discount & Variety Stores",
            "type":"Retail Goods"
        }
    ],
    "sg:phone":"+1 405 737 3471",
    "sg:postcode":"73110",
    "sg:province":"OK",
    "sg:tags":[
        "merchandise",
        "general"
    ],
    "wof:name":"Aarons Sales & Lease Ownership",
    "wof:placetype":"venue"
},
  "geometry": {"coordinates":[-97.406133,35.460132],"type":"Point"}
}