{
  "type": "Feature",
  "properties": {
    "iso:country":"US",
    "sg:address":"399998 W 2900 Rd",
    "sg:city":"Ramona",
    "sg:classifiers":[
        {
            "category":"Recreation",
            "type":"Entertainment"
        }
    ],
    "sg:phone":"+1 918 535 2400",
    "sg:postcode":"74061",
    "sg:province":"OK",
    "sg:tags":[
        "guide"
    ],
    "wof:name":"Cross JR Ranch",
    "wof:placetype":"venue"
},
  "geometry": {"coordinates":[-95.884413,36.597502],"type":"Point"}
}