{
  "type": "Feature",
  "properties": {
    "iso:country":"US",
    "sg:address":"1805 E Main St",
    "sg:city":"Weatherford",
    "sg:classifiers":[
        {
            "category":"Recreation",
            "type":"Entertainment"
        }
    ],
    "sg:phone":"+1 580 772 3897",
    "sg:postcode":"73096",
    "sg:province":"OK",
    "wof:name":"Karate Academy Chris Pollman",
    "wof:placetype":"venue"
},
  "geometry": {"coordinates":[-98.689892,35.528345],"type":"Point"}
}