{
  "type": "Feature",
  "properties": {
    "iso:country":"US",
    "sg:address":"307 State Hwy 44",
    "sg:city":"Burns Flat",
    "sg:classifiers":[
        {
            "category":"Retail",
            "subcategory":"Repair Shop",
            "type":"Services"
        }
    ],
    "sg:phone":"+1 580 562 4322",
    "sg:postcode":"73624",
    "sg:province":"OK",
    "sg:tags":[
        "refrigerator",
        "freezer"
    ],
    "wof:name":"L & S Equipment Co",
    "wof:placetype":"venue"
},
  "geometry": {"coordinates":[-99.170216,35.34938],"type":"Point"}
}