{
  "type": "Feature",
  "properties": {
    "addr:full":"17501 State Hwy 102 Shawnee OK 74801",
    "addr:housenumber":"17501",
    "addr:postcode":"74801",
    "addr:street":"State Hwy 102",
    "iso:country":"US",
    "sg:address":"17501 State Hwy 102",
    "sg:city":"Shawnee",
    "sg:classifiers":[
        {
            "category":"Manufacturing",
            "subcategory":"Glass & Minerals",
            "type":"Manufacturing & Wholesale Goods"
        }
    ],
    "sg:phone":"+1 405 214 1900",
    "sg:postcode":"74801",
    "sg:province":"OK",
    "sg:tags":[
        "concrete",
        "product",
        "mfg"
    ],
    "wof:name":"Precision Stone",
    "wof:placetype":"venue"
},
  "geometry": {"coordinates":[-97.053911,35.311456],"type":"Point"}
}