{
  "type": "Feature",
  "properties": {
    "iso:country":"US",
    "sg:address":"24704 S Hwy 66 Ste 29",
    "sg:city":"Claremore",
    "sg:classifiers":[
        {
            "category":"Retail",
            "subcategory":"Auto Repair",
            "type":"Services"
        }
    ],
    "sg:phone":"+1 918 341 8703",
    "sg:postcode":"74019",
    "sg:province":"OK",
    "wof:name":"Country Side Automotive",
    "wof:placetype":"venue"
},
  "geometry": {"coordinates":[-95.661922,36.255916],"type":"Point"}
}