{
  "type": "Feature",
  "properties": {
    "iso:country":"US",
    "sg:address":"802 S Jackson Ave",
    "sg:city":"Tulsa",
    "sg:classifiers":[
        {
            "category":"Health Services",
            "subcategory":"Doctor",
            "type":"Services"
        }
    ],
    "sg:phone":"+1 918 582 3154",
    "sg:postcode":"74127",
    "sg:province":"OK",
    "sg:tags":[
        "physician",
        "surgeon"
    ],
    "wof:name":"Osteopathic Physicians-Tulsa",
    "wof:placetype":"venue"
},
  "geometry": {"coordinates":[-95.99940100000001,36.145949],"type":"Point"}
}