{
  "type": "Feature",
  "properties": {
    "iso:country":"US",
    "sg:address":"29405 E 62nd St",
    "sg:city":"Broken Arrow",
    "sg:classifiers":[
        {
            "category":"Professional",
            "subcategory":"Management & Consulting",
            "type":"Services"
        }
    ],
    "sg:phone":"+1 918 357 9999",
    "sg:postcode":"74014",
    "sg:province":"OK",
    "sg:tags":[
        "business"
    ],
    "wof:name":"7x Corp",
    "wof:placetype":"venue"
},
  "geometry": {"coordinates":[-95.648819,36.074446],"type":"Point"}
}