{
  "type": "Feature",
  "properties": {
    "iso:country":"US",
    "sg:address":"741 W I- 240 Svc Rd",
    "sg:city":"Oklahoma City",
    "sg:classifiers":[
        {
            "category":"Autos & Motor Vehicles",
            "subcategory":"Automobile Sales",
            "type":"Retail Goods"
        }
    ],
    "sg:phone":"+1 405 632 3660",
    "sg:postcode":"73139",
    "sg:province":"OK",
    "sg:tags":[
        "used"
    ],
    "wof:name":"David Stanley Supercenter",
    "wof:placetype":"venue"
},
  "geometry": {"coordinates":[-97.52829,35.391785],"type":"Point"}
}