{
  "type": "Feature",
  "properties": {
    "addr:full":"1930 NW Ferris Ave Lawton OK 73507",
    "addr:housenumber":"1930",
    "addr:postcode":"73507",
    "addr:street":"Nw Ferris Ave",
    "iso:country":"US",
    "sg:address":"1930 NW Ferris Ave",
    "sg:city":"Lawton",
    "sg:classifiers":[
        {
            "category":"Insurance",
            "subcategory":"Life Insurance",
            "type":"Services"
        }
    ],
    "sg:phone":"+1 580 355 6231",
    "sg:postcode":"73507",
    "sg:province":"OK",
    "sg:tags":[
        "carrier"
    ],
    "wof:name":"MetLife",
    "wof:placetype":"venue"
},
  "geometry": {"coordinates":[-98.41820199999999,34.615984],"type":"Point"}
}