{
  "type": "Feature",
  "properties": {
    "addr:full":"510 S 1st St Madill OK 73446",
    "addr:housenumber":"510",
    "addr:postcode":"73446",
    "addr:street":"S 1St St",
    "iso:country":"US",
    "sg:address":"510 S 1st St",
    "sg:city":"Madill",
    "sg:classifiers":[
        {
            "category":"Food & Beverages",
            "subcategory":"Liquor & Beverages",
            "type":"Retail Goods"
        }
    ],
    "sg:phone":"+1 580 795 2626",
    "sg:postcode":"73446",
    "sg:province":"OK",
    "wof:name":"Red Arrow Liquor",
    "wof:placetype":"venue"
},
  "geometry": {"coordinates":[-96.770161,34.086233],"type":"Point"}
}