{
  "type": "Feature",
  "properties": {
    "iso:country":"US",
    "sg:address":"236 NW 62nd St",
    "sg:city":"Oklahoma City",
    "sg:classifiers":[
        {
            "category":"Manufacturing",
            "subcategory":"Tools & Machinery",
            "type":"Manufacturing & Wholesale Goods"
        }
    ],
    "sg:phone":"+1 405 775 4200",
    "sg:postcode":"73118",
    "sg:province":"OK",
    "sg:tags":[
        "physician",
        "surgeon"
    ],
    "wof:name":"Integrated Medical Delivery",
    "wof:placetype":"venue"
},
  "geometry": {"coordinates":[-97.517591,35.535861],"type":"Point"}
}