{
  "type": "Feature",
  "properties": {
    "addr:full":"1009 E 2nd St Edmond OK 73034",
    "addr:housenumber":"1009",
    "addr:postcode":"73034",
    "addr:street":"E 2Nd St",
    "iso:country":"US",
    "sg:address":"1009 E 2nd St",
    "sg:city":"Edmond",
    "sg:classifiers":[
        {
            "category":"Utilities",
            "subcategory":"Mobile Phone",
            "type":"Services"
        }
    ],
    "sg:phone":"+1 405 359 1222",
    "sg:postcode":"73034",
    "sg:province":"OK",
    "sg:tags":[
        "telephone",
        "cellular"
    ],
    "wof:name":"U S Cellular",
    "wof:placetype":"venue"
},
  "geometry": {"coordinates":[-97.465744,35.652855],"type":"Point"}
}