{
  "type": "Feature",
  "properties": {
    "addr:full":"307 US Hwy 77 Marietta OK 73448",
    "addr:housenumber":"307",
    "addr:postcode":"73448",
    "addr:street":"Us Hwy 77",
    "iso:country":"US",
    "sg:address":"307 US Hwy 77",
    "sg:city":"Marietta",
    "sg:classifiers":[
        {
            "category":"Cinema",
            "subcategory":"Movie Rental",
            "type":"Entertainment"
        }
    ],
    "sg:phone":"+1 580 276 3277",
    "sg:postcode":"73448",
    "sg:province":"OK",
    "sg:tags":[
        "leasing",
        "video",
        "disc",
        "tape"
    ],
    "wof:name":"Video Magic",
    "wof:placetype":"venue"
},
  "geometry": {"coordinates":[-97.126339,33.932678],"type":"Point"}
}