{
  "type": "Feature",
  "properties": {
    "addr:full":"731 N Oakwood Rd Enid OK 73703",
    "addr:housenumber":"731",
    "addr:postcode":"73703",
    "addr:street":"N Oakwood Rd",
    "iso:country":"US",
    "sg:address":"731 N Oakwood Rd",
    "sg:city":"Enid",
    "sg:classifiers":[
        {
            "category":"Shopping",
            "subcategory":"Pharmacy",
            "type":"Retail Goods"
        }
    ],
    "sg:phone":"+1 580 233 1455",
    "sg:postcode":"73703",
    "sg:province":"OK",
    "sg:tags":[
        "product",
        "health",
        "care"
    ],
    "wof:name":"Neese Enterprises Shaklee",
    "wof:placetype":"venue"
},
  "geometry": {"coordinates":[-97.925749,36.404019],"type":"Point"}
}