{
  "type": "Feature",
  "properties": {
    "addr:full":"117 S Main St Perkins OK 74059",
    "addr:housenumber":"117",
    "addr:postcode":"74059",
    "addr:street":"S Main St",
    "iso:country":"US",
    "sg:address":"117 S Main St",
    "sg:city":"Perkins",
    "sg:classifiers":[
        {
            "category":"Health Services",
            "subcategory":"Doctor",
            "type":"Services"
        }
    ],
    "sg:phone":"+1 405 547 4020",
    "sg:postcode":"74059",
    "sg:province":"OK",
    "sg:tags":[
        "clinic"
    ],
    "wof:name":"Perkins Family Care Clinic",
    "wof:placetype":"venue"
},
  "geometry": {"coordinates":[-97.033721,35.973891],"type":"Point"}
}