{
  "type": "Feature",
  "properties": {
    "iso:country":"US",
    "sg:address":"1310 S Main St",
    "sg:city":"Kingfisher",
    "sg:classifiers":[
        {
            "category":"Banks & Credit Unions",
            "subcategory":"Investment Brokerage",
            "type":"Services"
        }
    ],
    "sg:phone":"+1 405 375 6360",
    "sg:postcode":"73750",
    "sg:province":"OK",
    "sg:tags":[
        "security"
    ],
    "wof:name":"Edward Jones 05917",
    "wof:placetype":"venue"
},
  "geometry": {"coordinates":[-97.932676,35.847524],"type":"Point"}
}