{
  "type": "Feature",
  "properties": {
    "iso:country":"US",
    "sg:address":"225 W Mc Clure Ave",
    "sg:city":"Pauls Valley",
    "sg:classifiers":[
        {
            "category":"Shopping",
            "subcategory":"Bicycles & Sporting Goods",
            "type":"Retail Goods"
        }
    ],
    "sg:phone":"+1 405 238 3870",
    "sg:postcode":"73075",
    "sg:province":"OK",
    "sg:tags":[
        "business",
        "association"
    ],
    "wof:name":"Big 5 Community Service",
    "wof:placetype":"venue"
},
  "geometry": {"coordinates":[-97.220273,34.739286],"type":"Point"}
}