{
  "type": "Feature",
  "properties": {
    "addr:full":"1501 S Main St Kingfisher OK 73750",
    "addr:housenumber":"1501",
    "addr:postcode":"73750",
    "addr:street":"S Main St",
    "iso:country":"US",
    "sg:address":"1501 S Main St",
    "sg:city":"Kingfisher",
    "sg:classifiers":[
        {
            "category":"Retail",
            "subcategory":"Veterinary Services",
            "type":"Services"
        }
    ],
    "sg:phone":"+1 405 375 3434",
    "sg:postcode":"73750",
    "sg:province":"OK",
    "wof:name":"Kingfisher Animal Hospital",
    "wof:placetype":"venue"
},
  "geometry": {"coordinates":[-97.93251100000001,35.844474],"type":"Point"}
}