{
  "type": "Feature",
  "properties": {
    "addr:full":"8609 N Council Rd Oklahoma City OK 73132",
    "addr:housenumber":"8609",
    "addr:postcode":"73132",
    "addr:street":"N Council Rd",
    "iso:country":"US",
    "sg:address":"8609 N Council Rd",
    "sg:city":"Oklahoma City",
    "sg:classifiers":[
        {
            "category":"Retail",
            "subcategory":"Laundry & Dry Cleaning",
            "type":"Services"
        }
    ],
    "sg:phone":"+1 405 621 5991",
    "sg:postcode":"73132",
    "sg:province":"OK",
    "sg:tags":[
        "cleaners"
    ],
    "wof:name":"Uptown Cleaners",
    "wof:placetype":"venue"
},
  "geometry": {"coordinates":[-97.65627600000001,35.560841],"type":"Point"}
}