{
  "type": "Feature",
  "properties": {
    "iso:country":"US",
    "sg:address":"9020 N May Ave",
    "sg:city":"Oklahoma City",
    "sg:classifiers":[
        {
            "category":"Real Estate",
            "subcategory":"Real Estate Agent",
            "type":"Services"
        }
    ],
    "sg:phone":"+1 405 879 1050",
    "sg:postcode":"73120",
    "sg:province":"OK",
    "sg:tags":[
        "development",
        "company"
    ],
    "wof:name":"Legacy Communities",
    "wof:placetype":"venue"
},
  "geometry": {"coordinates":[-97.567122,35.562297],"type":"Point"}
}