{
  "type": "Feature",
  "properties": {
    "addr:full":"120 NE 4th St Moore OK 73160",
    "addr:housenumber":"120",
    "addr:postcode":"73160",
    "addr:street":"Ne 4Th St",
    "iso:country":"US",
    "sg:address":"120 NE 4th St",
    "sg:city":"Moore",
    "sg:classifiers":[
        {
            "category":"Communications",
            "subcategory":"Radio Station",
            "type":"Services"
        }
    ],
    "sg:phone":"+1 405 794 5674",
    "sg:postcode":"73160",
    "sg:province":"OK",
    "sg:tags":[
        "company",
        "broadcasting"
    ],
    "wof:name":"KMSI",
    "wof:placetype":"venue"
},
  "geometry": {"coordinates":[-97.486124,35.342212],"type":"Point"}
}