{
  "type": "Feature",
  "properties": {
    "iso:country":"US",
    "sg:address":"700 S Penn Ave",
    "sg:city":"Bartlesville",
    "sg:classifiers":[
        {
            "category":"Government",
            "subcategory":"Office",
            "type":"Public Place"
        }
    ],
    "sg:phone":"+1 918 338 5706",
    "sg:postcode":"74003",
    "sg:province":"OK",
    "sg:tags":[
        "state",
        "resource"
    ],
    "wof:name":"Developmental Disabilities",
    "wof:placetype":"venue"
},
  "geometry": {"coordinates":[-95.990555,36.747288],"type":"Point"}
}