{
  "type": "Feature",
  "properties": {
    "iso:country":"US",
    "sg:address":"1416 N Lewis Pl",
    "sg:city":"Tulsa",
    "sg:classifiers":[
        {
            "category":"Personal",
            "type":"Services"
        },
        {
            "category":"Building & Trades",
            "subcategory":"Cleaning & Sanitation",
            "type":"Services"
        }
    ],
    "sg:phone":"+1 918 836 4918",
    "sg:postcode":"74110",
    "sg:province":"OK",
    "sg:tags":[
        "house",
        "butlers'",
        "maids'"
    ],
    "wof:name":"Trudy's Cleaning Service",
    "wof:placetype":"venue"
},
  "geometry": {"coordinates":[-95.957141,36.175563],"type":"Point"}
}