{
  "type": "Feature",
  "properties": {
    "addr:full":"1207 W London St El Reno OK 73036",
    "addr:housenumber":"1207",
    "addr:postcode":"73036",
    "addr:street":"W London St",
    "iso:country":"US",
    "sg:address":"1207 W London St",
    "sg:city":"El Reno",
    "sg:classifiers":[
        {
            "category":"Home & Garden",
            "subcategory":"Building Materials",
            "type":"Retail Goods"
        }
    ],
    "sg:phone":"+1 405 262 6258",
    "sg:postcode":"73036",
    "sg:province":"OK",
    "wof:name":"Buckles Paint",
    "wof:placetype":"venue"
},
  "geometry": {"coordinates":[-97.96805999999999,35.530371],"type":"Point"}
}