{
  "type": "Feature",
  "properties": {
    "addr:full":"14518 Gomez Dr Sand Springs OK 74063",
    "addr:housenumber":"14518",
    "addr:postcode":"74063",
    "addr:street":"Gomez Dr",
    "iso:country":"US",
    "sg:address":"14518 Gomez Dr",
    "sg:city":"Sand Springs",
    "sg:classifiers":[
        {
            "category":"Building & Trades",
            "subcategory":"Plumbing",
            "type":"Services"
        }
    ],
    "sg:phone":"+1 918 446 4274",
    "sg:postcode":"74063",
    "sg:province":"OK",
    "sg:tags":[
        "contractor"
    ],
    "wof:name":"Tim Robbins Mechanical",
    "wof:placetype":"venue"
},
  "geometry": {"coordinates":[-96.155554,36.135817],"type":"Point"}
}