{
  "type": "Feature",
  "properties": {
    "addr:full":"2005 N 14th St Ponca City OK 74601",
    "addr:housenumber":"2005",
    "addr:postcode":"74601",
    "addr:street":"N 14Th St",
    "iso:country":"US",
    "sg:address":"2005 N 14th St",
    "sg:city":"Ponca City",
    "sg:classifiers":[
        {
            "category":"Restaurant",
            "type":"Food & Drink"
        }
    ],
    "sg:menulink":"http://www.allmenus.com/ok/ponca-city/106951-soup-man/menu/",
    "sg:phone":"+1 580 762 9537",
    "sg:postcode":"74601",
    "sg:province":"OK",
    "sg:tags":[
        "soup",
        "american",
        "salad"
    ],
    "wof:name":"Soup Man",
    "wof:placetype":"venue"
},
  "geometry": {"coordinates":[-97.067187,36.726065],"type":"Point"}
}