{
  "type": "Feature",
  "properties": {
    "iso:country":"US",
    "sg:address":"2604 N Pecan Rd",
    "sg:city":"Ponca City",
    "sg:classifiers":[
        {
            "category":"Building & Trades",
            "subcategory":"Construction",
            "type":"Services"
        }
    ],
    "sg:phone":"+1 580 762 4839",
    "sg:postcode":"74604",
    "sg:province":"OK",
    "sg:tags":[
        "paint",
        "dry wall",
        "contractor"
    ],
    "wof:name":"Avery Painting & Drywall Co",
    "wof:placetype":"venue"
},
  "geometry": {"coordinates":[-97.049435,36.736133],"type":"Point"}
}