{
  "type": "Feature",
  "properties": {
    "iso:country":"US",
    "sg:address":"3500 W Robinson St",
    "sg:city":"Norman",
    "sg:classifiers":[
        {
            "category":"Banks & Credit Unions",
            "subcategory":"Investment Brokerage",
            "type":"Services"
        }
    ],
    "sg:phone":"+1 405 329 9232",
    "sg:postcode":"73072",
    "sg:province":"OK",
    "sg:tags":[
        "land",
        "oil",
        "lease"
    ],
    "wof:name":"Warren Land Svc",
    "wof:placetype":"venue"
},
  "geometry": {"coordinates":[-97.493008,35.232767],"type":"Point"}
}