{
  "type": "Feature",
  "properties": {
    "iso:country":"US",
    "sg:address":"2200 SE 44th St",
    "sg:city":"Oklahoma City",
    "sg:classifiers":[
        {
            "category":"Shopping",
            "subcategory":"Used Merchandise",
            "type":"Retail Goods"
        }
    ],
    "sg:phone":"+1 405 670 2882",
    "sg:postcode":"73129",
    "sg:province":"OK",
    "sg:tags":[
        "furniture"
    ],
    "wof:name":"Almost Anything Store",
    "wof:placetype":"venue"
},
  "geometry": {"coordinates":[-97.468603,35.420826],"type":"Point"}
}