{
  "type": "Feature",
  "properties": {
    "iso:country":"US",
    "sg:address":"806 Belmont Rd",
    "sg:city":"Bartlesville",
    "sg:classifiers":[
        {
            "category":"Retail",
            "subcategory":"Repair Shop",
            "type":"Services"
        }
    ],
    "sg:phone":"+1 918 333 6479",
    "sg:postcode":"74006",
    "sg:province":"OK",
    "sg:tags":[
        "welding"
    ],
    "wof:name":"J B Welding",
    "wof:placetype":"venue"
},
  "geometry": {"coordinates":[-95.904505,36.744505],"type":"Point"}
}