{
  "type": "Feature",
  "properties": {
    "addr:full":"5901 W Reno Ave Oklahoma City OK 73127",
    "addr:housenumber":"5901",
    "addr:postcode":"73127",
    "addr:street":"W Reno Ave",
    "iso:country":"US",
    "sg:address":"5901 W Reno Ave",
    "sg:city":"Oklahoma City",
    "sg:classifiers":[
        {
            "category":"Restaurant",
            "type":"Food & Drink"
        }
    ],
    "sg:menulink":"http://www.allmenus.com/ok/oklahoma-city/199314-sonic/menu/",
    "sg:phone":"+1 405 787 7774",
    "sg:postcode":"73127",
    "sg:province":"OK",
    "sg:tags":[
        "burger",
        "american"
    ],
    "wof:name":"Sonic",
    "wof:placetype":"venue"
},
  "geometry": {"coordinates":[-97.617847,35.464458],"type":"Point"}
}