{
  "type": "Feature",
  "properties": {
    "addr:full":"1437 E 41st St Tulsa OK 74105",
    "addr:housenumber":"1437",
    "addr:postcode":"74105",
    "addr:street":"E 41St St",
    "iso:country":"US",
    "sg:address":"1437 E 41st St",
    "sg:city":"Tulsa",
    "sg:classifiers":[
        {
            "category":"Professional",
            "subcategory":"Business Services",
            "type":"Services"
        }
    ],
    "sg:phone":"+1 918 743 6099",
    "sg:postcode":"74105",
    "sg:province":"OK",
    "sg:tags":[
        "interior",
        "consultant",
        "design",
        "decorator"
    ],
    "wof:name":"Jan Johnson Interiors",
    "wof:placetype":"venue"
},
  "geometry": {"coordinates":[-95.971385,36.104368],"type":"Point"}
}