{
  "type": "Feature",
  "properties": {
    "addr:full":"1029 E Steve Owens Blvd Miami OK 74354",
    "addr:housenumber":"1029",
    "addr:postcode":"74354",
    "addr:street":"E Steve Owens Blvd",
    "iso:country":"US",
    "sg:address":"1029 E Steve Owens Blvd",
    "sg:city":"Miami",
    "sg:classifiers":[
        {
            "category":"Banks & Credit Unions",
            "subcategory":"Bank",
            "type":"Services"
        }
    ],
    "sg:phone":"+1 918 540 1161",
    "sg:postcode":"74354",
    "sg:province":"OK",
    "sg:tags":[
        "institution",
        "business"
    ],
    "wof:name":"Afc Loans",
    "wof:placetype":"venue"
},
  "geometry": {"coordinates":[-94.866338,36.871126],"type":"Point"}
}