{
  "type": "Feature",
  "properties": {
    "iso:country":"US",
    "sg:address":"1221 Harrison St",
    "sg:city":"Pawnee",
    "sg:classifiers":[
        {
            "category":"Farming",
            "subcategory":"Livestock Farm",
            "type":"Manufacturing & Wholesale Goods"
        }
    ],
    "sg:phone":"+1 918 762 3432",
    "sg:postcode":"74058",
    "sg:province":"OK",
    "sg:tags":[
        "wheat",
        "beef",
        "feedlot",
        "cattle"
    ],
    "wof:name":"Melvin Gillialand",
    "wof:placetype":"venue"
},
  "geometry": {"coordinates":[-96.81146699999999,36.337804],"type":"Point"}
}