{
  "type": "Feature",
  "properties": {
    "addr:full":"17444 E Coffee Creek Rd Luther OK 73083",
    "addr:housenumber":"17444 e",
    "addr:postcode":"73083",
    "addr:street":"Coffee Creek Rd",
    "iso:country":"US",
    "sg:address":"17444 E Coffee Creek Rd",
    "sg:city":"Luther",
    "sg:classifiers":[
        {
            "category":"Retail",
            "subcategory":"Laundry & Dry Cleaning",
            "type":"Services"
        }
    ],
    "sg:phone":"+1 405 277 7098",
    "sg:postcode":"73083",
    "sg:province":"OK",
    "sg:tags":[
        "cleaners",
        "rug",
        "carpet"
    ],
    "wof:name":"Savory's Carpet Cleaning",
    "wof:placetype":"venue"
},
  "geometry": {"coordinates":[-97.229867,35.695999],"type":"Point"}
}