{
  "type": "Feature",
  "properties": {
    "iso:country":"US",
    "sg:address":"7030 S Lewis Ave",
    "sg:city":"Tulsa",
    "sg:classifiers":[
        {
            "category":"Mining & Drilling",
            "type":"Manufacturing & Wholesale Goods"
        }
    ],
    "sg:phone":"+1 918 291 3200",
    "sg:postcode":"74136",
    "sg:province":"OK",
    "sg:tags":[
        "development",
        "gas",
        "oil",
        "exploration"
    ],
    "wof:name":"Concorde Resources",
    "wof:placetype":"venue"
},
  "geometry": {"coordinates":[-95.95796799999999,36.060888],"type":"Point"}
}