{
  "type": "Feature",
  "properties": {
    "iso:country":"US",
    "sg:address":"4750 SE 29th St",
    "sg:city":"Oklahoma City",
    "sg:classifiers":[
        {
            "category":"Personal",
            "subcategory":"Barber",
            "type":"Services"
        }
    ],
    "sg:phone":"+1 405 604 6897",
    "sg:postcode":"73115",
    "sg:province":"OK",
    "wof:name":"Off Base Barber Shop",
    "wof:placetype":"venue"
},
  "geometry": {"coordinates":[-97.429237,35.43516],"type":"Point"}
}