{
  "type": "Feature",
  "properties": {
    "addr:full":"1013 S Air Depot Blvd Oklahoma City OK 73110",
    "addr:housenumber":"1013",
    "addr:postcode":"73110",
    "addr:street":"S Air Depot Blvd",
    "iso:country":"US",
    "sg:address":"1013 S Air Depot Blvd",
    "sg:city":"Oklahoma City",
    "sg:classifiers":[
        {
            "category":"Food & Beverages",
            "subcategory":"Groceries & Convenience Stores",
            "type":"Retail Goods"
        }
    ],
    "sg:phone":"+1 405 741 3368",
    "sg:postcode":"73110",
    "sg:province":"OK",
    "wof:name":"Q-Mart",
    "wof:placetype":"venue"
},
  "geometry": {"coordinates":[-97.40620199999999,35.454655],"type":"Point"}
}