{
  "type": "Feature",
  "properties": {
    "iso:country":"US",
    "sg:address":"206 N 12th St",
    "sg:city":"Hugo",
    "sg:classifiers":[
        {
            "category":"Personal",
            "type":"Services"
        }
    ],
    "sg:phone":"+1 580 326 8247",
    "sg:postcode":"74743",
    "sg:province":"OK",
    "sg:tags":[
        "paper",
        "product",
        "converted",
        "mfg"
    ],
    "wof:name":"Tag Agent",
    "wof:placetype":"venue"
},
  "geometry": {"coordinates":[-95.499574,34.011563],"type":"Point"}
}