{
  "type": "Feature",
  "properties": {
    "iso:country":"US",
    "sg:address":"109 Deer Dr",
    "sg:city":"Cache",
    "sg:classifiers":[
        {
            "category":"Real Estate",
            "subcategory":"Real Estate Operator",
            "type":"Services"
        }
    ],
    "sg:phone":"+1 580 429 8390",
    "sg:postcode":"73527",
    "sg:province":"OK",
    "sg:tags":[
        "building",
        "apartment"
    ],
    "wof:name":"Wichita Village Apts",
    "wof:placetype":"venue"
},
  "geometry": {"coordinates":[-98.62111899999999,34.624476],"type":"Point"}
}