{
  "type": "Feature",
  "properties": {
    "iso:country":"US",
    "sg:address":"201 S Osage Ave",
    "sg:city":"Dewey",
    "sg:classifiers":[
        {
            "category":"Wholesale",
            "subcategory":"Auto Parts",
            "type":"Manufacturing & Wholesale Goods"
        }
    ],
    "sg:phone":"+1 918 534 1441",
    "sg:postcode":"74029",
    "sg:province":"OK",
    "sg:tags":[
        "automobile",
        "rebuilt"
    ],
    "wof:name":"Performance Ignition Systems",
    "wof:placetype":"venue"
},
  "geometry": {"coordinates":[-95.935198,36.789677],"type":"Point"}
}