{
  "type": "Feature",
  "properties": {
    "addr:full":"2332 W Shawnee St Muskogee OK 74401",
    "addr:housenumber":"2332",
    "addr:postcode":"74401",
    "addr:street":"W Shawnee St",
    "iso:country":"US",
    "sg:address":"2332 W Shawnee St",
    "sg:city":"Muskogee",
    "sg:classifiers":[
        {
            "category":"Home & Garden",
            "subcategory":"Furniture",
            "type":"Retail Goods"
        }
    ],
    "sg:phone":"+1 918 682 0033",
    "sg:postcode":"74401",
    "sg:province":"OK",
    "wof:name":"Allen Furniture Mart",
    "wof:placetype":"venue"
},
  "geometry": {"coordinates":[-95.392849,35.76989],"type":"Point"}
}