{
  "type": "Feature",
  "properties": {
    "iso:country":"US",
    "sg:address":"427 W 149th Pl",
    "sg:city":"Glenpool",
    "sg:classifiers":[
        {
            "category":"Professional",
            "subcategory":"Business Services",
            "type":"Services"
        }
    ],
    "sg:phone":"+1 918 227 0444",
    "sg:postcode":"74033",
    "sg:province":"OK",
    "sg:tags":[
        "embroidery"
    ],
    "wof:name":"Monograms By Brenda",
    "wof:placetype":"venue"
},
  "geometry": {"coordinates":[-96.012888,35.946394],"type":"Point"}
}