{
  "type": "Feature",
  "properties": {
    "iso:country":"US",
    "sg:address":"419 S Kentucky St",
    "sg:city":"Quapaw",
    "sg:classifiers":[
        {
            "category":"Organizations",
            "subcategory":"Religious Organization",
            "type":"Services"
        }
    ],
    "sg:phone":"+1 918 674 2788",
    "sg:postcode":"74363",
    "sg:province":"OK",
    "sg:tags":[
        "church"
    ],
    "wof:name":"First Baptist Church",
    "wof:placetype":"venue"
},
  "geometry": {"coordinates":[-94.789082,36.954182],"type":"Point"}
}