{
  "type": "Feature",
  "properties": {
    "iso:country":"US",
    "sg:address":"1356 E 27th St",
    "sg:city":"Tulsa",
    "sg:classifiers":[
        {
            "category":"Home & Garden",
            "subcategory":"Furniture",
            "type":"Retail Goods"
        }
    ],
    "sg:phone":"+1 918 749 5464",
    "sg:postcode":"74114",
    "sg:province":"OK",
    "wof:name":"Furniture For Business",
    "wof:placetype":"venue"
},
  "geometry": {"coordinates":[-95.97229299999999,36.125538],"type":"Point"}
}