{
  "type": "Feature",
  "properties": {
    "addr:full":"116 W 8th Ave Stillwater OK 74074",
    "addr:housenumber":"116",
    "addr:postcode":"74074",
    "addr:street":"W 8Th Ave",
    "iso:country":"US",
    "sg:address":"116 W 8th Ave",
    "sg:city":"Stillwater",
    "sg:classifiers":[
        {
            "category":"Shopping",
            "type":"Retail Goods"
        },
        {
            "category":"Health Services",
            "subcategory":"Health Practitioner",
            "type":"Services"
        }
    ],
    "sg:phone":"+1 405 624 8605",
    "sg:postcode":"74074",
    "sg:province":"OK",
    "sg:tags":[
        "audiologists",
        "merchandise"
    ],
    "wof:name":"Stillwater Hearing Clinic Inc",
    "wof:placetype":"venue"
},
  "geometry": {"coordinates":[-97.059039,36.113552],"type":"Point"}
}