{
  "type": "Feature",
  "properties": {
    "iso:country":"US",
    "sg:address":"2415 SW 122nd St",
    "sg:city":"Oklahoma City",
    "sg:classifiers":[
        {
            "category":"Professional",
            "subcategory":"Business Services",
            "type":"Services"
        }
    ],
    "sg:phone":"+1 405 691 1218",
    "sg:postcode":"73170",
    "sg:province":"OK",
    "sg:tags":[
        "interior",
        "consultant",
        "design",
        "decorator"
    ],
    "wof:name":"Rosemary Mc Kinney Designer",
    "wof:placetype":"venue"
},
  "geometry": {"coordinates":[-97.552229,35.344617],"type":"Point"}
}