{
  "type": "Feature",
  "properties": {
    "iso:country":"US",
    "sg:address":"500 W Main St",
    "sg:city":"Oklahoma City",
    "sg:classifiers":[
        {
            "category":"Government",
            "subcategory":"Office",
            "type":"Public Place"
        }
    ],
    "sg:phone":"+1 405 553 7401",
    "sg:postcode":"73102",
    "sg:province":"OK",
    "sg:tags":[
        "federal",
        "program"
    ],
    "wof:name":"Us Housing & Urban Dev",
    "wof:placetype":"venue"
},
  "geometry": {"coordinates":[-97.522695,35.46787],"type":"Point"}
}