{
  "type": "Feature",
  "properties": {
    "addr:full":"2022 NW 33rd St Oklahoma City OK 73118",
    "addr:housenumber":"2022",
    "addr:postcode":"73118",
    "addr:street":"Nw 33Rd St",
    "iso:country":"US",
    "sg:address":"2022 NW 33rd St",
    "sg:city":"Oklahoma City",
    "sg:classifiers":[
        {
            "category":"Building & Trades",
            "subcategory":"Construction",
            "type":"Services"
        }
    ],
    "sg:phone":"+1 405 524 7634",
    "sg:postcode":"73118",
    "sg:province":"OK",
    "sg:tags":[
        "house"
    ],
    "wof:name":"Remodel By Dan Slate Inc",
    "wof:placetype":"venue"
},
  "geometry": {"coordinates":[-97.54600499999999,35.504174],"type":"Point"}
}