{
  "type": "Feature",
  "properties": {
    "addr:full":"2103 W Greeley St Broken Arrow OK 74012",
    "addr:housenumber":"2103",
    "addr:postcode":"74012",
    "addr:street":"W Greeley St",
    "iso:country":"US",
    "sg:address":"2103 W Greeley St",
    "sg:city":"Broken Arrow",
    "sg:classifiers":[
        {
            "category":"Organizations",
            "subcategory":"Religious Organization",
            "type":"Services"
        }
    ],
    "sg:phone":"+1 918 251 5035",
    "sg:postcode":"74012",
    "sg:province":"OK",
    "wof:name":"Morris Joseph Ministries",
    "wof:placetype":"venue"
},
  "geometry": {"coordinates":[-95.81371300000001,36.057596],"type":"Point"}
}