{
  "type": "Feature",
  "properties": {
    "iso:country":"US",
    "sg:address":"2314 N Rhode Island Ave",
    "sg:city":"Oklahoma City",
    "sg:classifiers":[
        {
            "category":"Retail",
            "subcategory":"Auto Repair",
            "type":"Services"
        }
    ],
    "sg:phone":"+1 405 424 0606",
    "sg:postcode":"73111",
    "sg:province":"OK",
    "sg:tags":[
        "repairing",
        "automobile",
        "radiator"
    ],
    "wof:name":"Northside Radiator",
    "wof:placetype":"venue"
},
  "geometry": {"coordinates":[-97.481089,35.492102],"type":"Point"}
}