{
  "type": "Feature",
  "properties": {
    "iso:country":"US",
    "sg:address":"4909 S Yale Ave",
    "sg:city":"Tulsa",
    "sg:classifiers":[
        {
            "category":"Restaurant",
            "type":"Food & Drink"
        }
    ],
    "sg:phone":"+1 918 622 1413",
    "sg:postcode":"74135",
    "sg:province":"OK",
    "sg:website":"www.arbys.com",
    "wof:name":"Arby's",
    "wof:placetype":"venue"
},
  "geometry": {"coordinates":[-95.92218800000001,36.09355],"type":"Point"}
}