{
  "type": "Feature",
  "properties": {
    "iso:country":"US",
    "sg:address":"4600 E 2nd St",
    "sg:city":"Edmond",
    "sg:classifiers":[
        {
            "category":"Organizations",
            "subcategory":"Religious Organization",
            "type":"Services"
        }
    ],
    "sg:phone":"+1 405 680 5433",
    "sg:postcode":"73034",
    "sg:province":"OK",
    "sg:tags":[
        "church"
    ],
    "wof:name":"Life Church",
    "wof:placetype":"venue"
},
  "geometry": {"coordinates":[-97.419852,35.652715],"type":"Point"}
}