{
  "type": "Feature",
  "properties": {
    "iso:country":"US",
    "sg:address":"400 W Washington Ave",
    "sg:city":"Mcalester",
    "sg:classifiers":[
        {
            "category":"Education",
            "subcategory":"School",
            "type":"Public Place"
        }
    ],
    "sg:phone":"+1 918 426 4700",
    "sg:postcode":"74501",
    "sg:province":"OK",
    "wof:name":"Krebs School District",
    "wof:placetype":"venue"
},
  "geometry": {"coordinates":[-95.77654800000001,34.936102],"type":"Point"}
}