{
  "type": "Feature",
  "properties": {
    "addr:full":"2500 W Modelle Ave Clinton OK 73601",
    "addr:housenumber":"2500",
    "addr:postcode":"73601",
    "addr:street":"W Modelle Ave",
    "iso:country":"US",
    "sg:address":"2500 W Modelle Ave",
    "sg:city":"Clinton",
    "sg:classifiers":[
        {
            "category":"Retail",
            "subcategory":"Funeral Services",
            "type":"Services"
        }
    ],
    "sg:phone":"+1 580 323 1212",
    "sg:postcode":"73601",
    "sg:province":"OK",
    "sg:tags":[
        "director"
    ],
    "wof:name":"Kiesau Marler Funeral Home",
    "wof:placetype":"venue"
},
  "geometry": {"coordinates":[-98.991035,35.508559],"type":"Point"}
}