{
  "type": "Feature",
  "properties": {
    "iso:country":"US",
    "sg:address":"709 E McElroy Rd",
    "sg:city":"Stillwater",
    "sg:classifiers":[
        {
            "category":"Banks & Credit Unions",
            "subcategory":"Bank",
            "type":"Services"
        }
    ],
    "sg:phone":"+1 405 372 0276",
    "sg:postcode":"74075",
    "sg:province":"OK",
    "sg:tags":[
        "loan",
        "real estate"
    ],
    "wof:name":"Beneficial Oklahoma Inc",
    "wof:placetype":"venue"
},
  "geometry": {"coordinates":[-97.050839,36.130442],"type":"Point"}
}