{
  "type": "Feature",
  "properties": {
    "iso:country":"US",
    "sg:address":"14 Oak Pond Dr",
    "sg:city":"Shawnee",
    "sg:classifiers":[
        {
            "category":"Building & Trades",
            "subcategory":"Landscaping Services",
            "type":"Services"
        }
    ],
    "sg:phone":"+1 405 878 6844",
    "sg:postcode":"74804",
    "sg:province":"OK",
    "sg:tags":[
        "landscape",
        "contractor"
    ],
    "wof:name":"Complete Landscape",
    "wof:placetype":"venue"
},
  "geometry": {"coordinates":[-96.860168,35.414446],"type":"Point"}
}