{
  "type": "Feature",
  "properties": {
    "iso:country":"US",
    "sg:address":"6510 E 71st St",
    "sg:city":"Tulsa",
    "sg:classifiers":[
        {
            "category":"Retail",
            "subcategory":"Car Wash",
            "type":"Services"
        }
    ],
    "sg:phone":"+1 918 494 6091",
    "sg:postcode":"74133",
    "sg:province":"OK",
    "wof:name":"Short Car Wash",
    "wof:placetype":"venue"
},
  "geometry": {"coordinates":[-95.900522,36.060811],"type":"Point"}
}