{
  "type": "Feature",
  "properties": {
    "addr:full":"2420 Westport Dr Norman OK 73069",
    "addr:housenumber":"2420",
    "addr:postcode":"73069",
    "addr:street":"Westport Dr",
    "iso:country":"US",
    "sg:address":"2420 Westport Dr",
    "sg:city":"Norman",
    "sg:classifiers":[
        {
            "category":"Recreation",
            "type":"Entertainment"
        }
    ],
    "sg:phone":"+1 405 366 8859",
    "sg:postcode":"73069",
    "sg:province":"OK",
    "sg:tags":[
        "tennis",
        "court"
    ],
    "wof:name":"Westwood Tennis Ctr",
    "wof:placetype":"venue"
},
  "geometry": {"coordinates":[-97.480181,35.231681],"type":"Point"}
}