{
  "type": "Feature",
  "properties": {
    "addr:full":"1300 S Muskogee Ave Tahlequah OK 74464",
    "addr:housenumber":"1300",
    "addr:postcode":"74464",
    "addr:street":"S Muskogee Ave",
    "iso:country":"US",
    "sg:address":"1300 S Muskogee Ave",
    "sg:city":"Tahlequah",
    "sg:classifiers":[
        {
            "category":"Shopping",
            "subcategory":"Bicycles & Sporting Goods",
            "type":"Retail Goods"
        }
    ],
    "sg:phone":"+1 918 456 6528",
    "sg:postcode":"74464",
    "sg:province":"OK",
    "sg:tags":[
        "shop"
    ],
    "wof:name":"Tahlequah Vending",
    "wof:placetype":"venue"
},
  "geometry": {"coordinates":[-94.975222,35.899527],"type":"Point"}
}