{
  "type": "Feature",
  "properties": {
    "iso:country":"US",
    "sg:address":"7556 SE 15th St",
    "sg:city":"Oklahoma City",
    "sg:classifiers":[
        {
            "category":"Restaurant",
            "type":"Food & Drink"
        }
    ],
    "sg:phone":"+1 405 691 3443",
    "sg:postcode":"73110",
    "sg:province":"OK",
    "sg:tags":[
        "caterer"
    ],
    "wof:name":"Receptions Remembered",
    "wof:placetype":"venue"
},
  "geometry": {"coordinates":[-97.388637,35.449575],"type":"Point"}
}