{
  "type": "Feature",
  "properties": {
    "iso:country":"US",
    "sg:address":"37 NW 122nd St",
    "sg:city":"Oklahoma City",
    "sg:classifiers":[
        {
            "category":"Wholesale",
            "subcategory":"Groceries",
            "type":"Manufacturing & Wholesale Goods"
        }
    ],
    "sg:phone":"+1 405 775 7100",
    "sg:postcode":"73114",
    "sg:province":"OK",
    "sg:tags":[
        "food",
        "broker"
    ],
    "wof:name":"Us Foods Svc OCD",
    "wof:placetype":"venue"
},
  "geometry": {"coordinates":[-97.517556,35.5947],"type":"Point"}
}