{
  "type": "Feature",
  "properties": {
    "iso:country":"US",
    "sg:address":"2170 S Garnett Rd",
    "sg:city":"Tulsa",
    "sg:classifiers":[
        {
            "category":"Restaurant",
            "type":"Food & Drink"
        }
    ],
    "sg:phone":"+1 918 437 1718",
    "sg:postcode":"74129",
    "sg:province":"OK",
    "sg:tags":[
        "eating"
    ],
    "wof:name":"Casa San Marcos",
    "wof:placetype":"venue"
},
  "geometry": {"coordinates":[-95.851161,36.132805],"type":"Point"}
}