{
  "type": "Feature",
  "properties": {
    "addr:full":"916 Manvel Ave Chandler OK 74834",
    "addr:housenumber":"916",
    "addr:postcode":"74834",
    "addr:street":"Manvel Ave",
    "iso:country":"US",
    "sg:address":"916 Manvel Ave",
    "sg:city":"Chandler",
    "sg:classifiers":[
        {
            "category":"Restaurant",
            "type":"Food & Drink"
        }
    ],
    "sg:menulink":"http://www.allmenus.com/ok/chandler/144589-subway/menu/",
    "sg:phone":"+1 405 258 9966",
    "sg:postcode":"74834",
    "sg:province":"OK",
    "sg:tags":[
        "american",
        "sandwich"
    ],
    "wof:name":"Subway",
    "wof:placetype":"venue"
},
  "geometry": {"coordinates":[-96.880775,35.701459],"type":"Point"}
}