{
  "type": "Feature",
  "properties": {
    "iso:country":"US",
    "sg:address":"1826 A St NW",
    "sg:city":"Miami",
    "sg:classifiers":[
        {
            "category":"Shopping",
            "subcategory":"Florist",
            "type":"Retail Goods"
        }
    ],
    "sg:phone":"+1 918 542 6273",
    "sg:postcode":"74354",
    "sg:province":"OK",
    "sg:tags":[
        "plant"
    ],
    "wof:name":"Plant Place",
    "wof:placetype":"venue"
},
  "geometry": {"coordinates":[-94.878623,36.896938],"type":"Point"}
}