{
  "type": "Feature",
  "properties": {
    "iso:country":"US",
    "sg:address":"1924 S Coltrane Rd",
    "sg:city":"Edmond",
    "sg:classifiers":[
        {
            "category":"Professional",
            "subcategory":"Business Services",
            "type":"Services"
        }
    ],
    "sg:phone":"+1 405 359 6591",
    "sg:postcode":"73013",
    "sg:province":"OK",
    "wof:name":"Stonehill Enterprises LLC",
    "wof:placetype":"venue"
},
  "geometry": {"coordinates":[-97.442649,35.6358],"type":"Point"}
}