{
  "type": "Feature",
  "properties": {
    "addr:full":"1829 Linwood Blvd Oklahoma City OK 73106",
    "addr:housenumber":"1829",
    "addr:postcode":"73106",
    "addr:street":"Linwood Blvd",
    "iso:country":"US",
    "sg:address":"1829 Linwood Blvd",
    "sg:city":"Oklahoma City",
    "sg:classifiers":[
        {
            "category":"Retail",
            "subcategory":"Repair Shop",
            "type":"Services"
        }
    ],
    "sg:phone":"+1 405 232 2158",
    "sg:postcode":"73106",
    "sg:province":"OK",
    "sg:tags":[
        "tool",
        "parts"
    ],
    "wof:name":"Commercial Tool",
    "wof:placetype":"venue"
},
  "geometry": {"coordinates":[-97.54277399999999,35.474834],"type":"Point"}
}