{
  "type": "Feature",
  "properties": {
    "addr:full":"408 Broadway St Cheyenne OK 73654",
    "addr:housenumber":"408",
    "addr:postcode":"73654",
    "addr:street":"Broadway St",
    "iso:country":"US",
    "sg:address":"408 Broadway St",
    "sg:city":"Cheyenne",
    "sg:classifiers":[
        {
            "category":"Insurance",
            "subcategory":"Insurance Agent",
            "type":"Services"
        }
    ],
    "sg:phone":"+1 580 497 2481",
    "sg:postcode":"73654",
    "sg:province":"OK",
    "wof:name":"Pyatt Agency Office",
    "wof:placetype":"venue"
},
  "geometry": {"coordinates":[-99.342602,35.868929],"type":"Point"}
}