{
  "type": "Feature",
  "properties": {
    "addr:full":"2725 N Moore Ave Oklahoma City OK 73160",
    "addr:housenumber":"2725",
    "addr:postcode":"73160",
    "addr:street":"N Moore Ave",
    "iso:country":"US",
    "sg:address":"2725 N Moore Ave",
    "sg:city":"Oklahoma City",
    "sg:classifiers":[
        {
            "category":"Autos & Motor Vehicles",
            "subcategory":"Recreational Vehicle Sales",
            "type":"Retail Goods"
        }
    ],
    "sg:phone":"+1 405 912 5363",
    "sg:postcode":"73160",
    "sg:province":"OK",
    "wof:name":"Lee's Rv City South",
    "wof:placetype":"venue"
},
  "geometry": {"coordinates":[-97.49782399999999,35.361083],"type":"Point"}
}