{
  "type": "Feature",
  "properties": {
    "addr:full":"1900 W Harrison Ave Guthrie OK 73044",
    "addr:housenumber":"1900",
    "addr:postcode":"73044",
    "addr:street":"W Harrison Ave",
    "iso:country":"US",
    "sg:address":"1900 W Harrison Ave",
    "sg:city":"Guthrie",
    "sg:classifiers":[
        {
            "category":"Education",
            "subcategory":"School",
            "type":"Public Place"
        }
    ],
    "sg:phone":"+1 405 282 5794",
    "sg:postcode":"73044",
    "sg:province":"OK",
    "sg:tags":[
        "retarded"
    ],
    "wof:name":"Westview Vocational Ctr",
    "wof:placetype":"venue"
},
  "geometry": {"coordinates":[-97.448211,35.876863],"type":"Point"}
}