{
  "type": "Feature",
  "properties": {
    "addr:full":"2805 del Arbole Dr Oklahoma City OK 73110",
    "addr:housenumber":"2805",
    "addr:postcode":"73110",
    "addr:street":"Del Arbole Dr",
    "iso:country":"US",
    "sg:address":"2805 del Arbole Dr",
    "sg:city":"Oklahoma City",
    "sg:classifiers":[
        {
            "category":"Home & Garden",
            "subcategory":"Carpets & Floor Coverings",
            "type":"Retail Goods"
        }
    ],
    "sg:phone":"+1 405 521 5101",
    "sg:postcode":"73110",
    "sg:province":"OK",
    "wof:name":"Carpets By Walkers Ent",
    "wof:placetype":"venue"
},
  "geometry": {"coordinates":[-97.37882999999999,35.467659],"type":"Point"}
}