{
  "type": "Feature",
  "properties": {
    "iso:country":"US",
    "sg:address":"205 N Price Ave",
    "sg:city":"Hominy",
    "sg:classifiers":[
        {
            "category":"Organizations",
            "subcategory":"Religious Organization",
            "type":"Services"
        }
    ],
    "sg:phone":"+1 918 885 4920",
    "sg:postcode":"74035",
    "sg:province":"OK",
    "sg:tags":[
        "church"
    ],
    "wof:name":"First Presbyterian Church",
    "wof:placetype":"venue"
},
  "geometry": {"coordinates":[-96.394125,36.417714],"type":"Point"}
}