{
  "type": "Feature",
  "properties": {
    "iso:country":"US",
    "sg:address":"220 E Cleveland Ave",
    "sg:city":"Guthrie",
    "sg:classifiers":[
        {
            "category":"Food & Beverages",
            "subcategory":"Groceries & Convenience Stores",
            "type":"Retail Goods"
        }
    ],
    "sg:phone":"+1 405 282 0530",
    "sg:postcode":"73044",
    "sg:province":"OK",
    "wof:name":"Homeland 188",
    "wof:placetype":"venue"
},
  "geometry": {"coordinates":[-97.42379,35.879155],"type":"Point"}
}