{
  "type": "Feature",
  "properties": {
    "iso:country":"US",
    "sg:address":"2722 E Pine Ave",
    "sg:city":"Enid",
    "sg:classifiers":[
        {
            "category":"Shopping",
            "subcategory":"Hobbies, Toys, & Games",
            "type":"Retail Goods"
        }
    ],
    "sg:phone":"+1 580 237 2731",
    "sg:postcode":"73701",
    "sg:province":"OK",
    "sg:tags":[
        "craft"
    ],
    "wof:name":"Sylvia's Crafts",
    "wof:placetype":"venue"
},
  "geometry": {"coordinates":[-97.839409,36.401747],"type":"Point"}
}