{
  "type": "Feature",
  "properties": {
    "iso:country":"US",
    "sg:address":"300 N Iowa Ave",
    "sg:city":"Chandler",
    "sg:classifiers":[
        {
            "category":"Wholesale",
            "subcategory":"Farm Supplies",
            "type":"Manufacturing & Wholesale Goods"
        }
    ],
    "sg:phone":"+1 405 258 0300",
    "sg:postcode":"74834",
    "sg:province":"OK",
    "sg:tags":[
        "commission",
        "livestock"
    ],
    "wof:name":"Chandler Livestock Sales",
    "wof:placetype":"venue"
},
  "geometry": {"coordinates":[-96.875589,35.710522],"type":"Point"}
}