{
  "type": "Feature",
  "properties": {
    "iso:country":"US",
    "sg:address":"1219 S Quebec Ave",
    "sg:city":"Tulsa",
    "sg:classifiers":[
        {
            "category":"Building & Trades",
            "subcategory":"Construction",
            "type":"Services"
        }
    ],
    "sg:phone":"+1 918 832 5544",
    "sg:postcode":"74112",
    "sg:province":"OK",
    "sg:tags":[
        "drainage",
        "contractor"
    ],
    "wof:name":"Jonesplan Drainage Svc",
    "wof:placetype":"venue"
},
  "geometry": {"coordinates":[-95.930245,36.144519],"type":"Point"}
}