{
  "type": "Feature",
  "properties": {
    "iso:country":"US",
    "sg:address":"306 W Highland St",
    "sg:city":"Shawnee",
    "sg:classifiers":[
        {
            "category":"Real Estate",
            "subcategory":"Real Estate Agent",
            "type":"Services"
        }
    ],
    "sg:phone":"+1 405 273 4061",
    "sg:postcode":"74801",
    "sg:province":"OK",
    "sg:tags":[
        "management"
    ],
    "wof:name":"A Property Managament",
    "wof:placetype":"venue"
},
  "geometry": {"coordinates":[-96.92746099999999,35.332733],"type":"Point"}
}