{
  "type": "Feature",
  "properties": {
    "addr:full":"2020 Castle Rock Edmond OK 73003",
    "addr:housenumber":"2020",
    "addr:postcode":"73003",
    "addr:street":"Castle",
    "iso:country":"US",
    "sg:address":"2020 Castle Rock",
    "sg:city":"Edmond",
    "sg:classifiers":[
        {
            "category":"Organizations",
            "subcategory":"Religious Organization",
            "type":"Services"
        }
    ],
    "sg:phone":"+1 405 340 5267",
    "sg:postcode":"73003",
    "sg:province":"OK",
    "sg:website":"www.totallifenow.org",
    "wof:name":"Wayne Bristow Evangelistic",
    "wof:placetype":"venue"
},
  "geometry": {"coordinates":[-97.510181,35.659791],"type":"Point"}
}