{
  "type": "Feature",
  "properties": {
    "iso:country":"US",
    "sg:address":"2939 N Birch St",
    "sg:city":"Bache",
    "sg:classifiers":[
        {
            "category":"Building & Trades",
            "subcategory":"Electrical",
            "type":"Services"
        }
    ],
    "sg:phone":"+1 918 423 5883",
    "sg:postcode":"74501",
    "sg:province":"OK",
    "sg:tags":[
        "electrical",
        "contractor"
    ],
    "wof:name":"Tonys Refrigeration Elec Contg",
    "wof:placetype":"venue"
},
  "geometry": {"coordinates":[-95.765843,34.959079],"type":"Point"}
}