{
  "type": "Feature",
  "properties": {
    "iso:country":"US",
    "sg:address":"420 E Main St",
    "sg:city":"Yukon",
    "sg:classifiers":[
        {
            "category":"Restaurant",
            "type":"Food & Drink"
        }
    ],
    "sg:phone":"+1 405 354 6665",
    "sg:postcode":"73099",
    "sg:province":"OK",
    "sg:tags":[
        "rest",
        "pizza"
    ],
    "wof:name":"Pizza Hut",
    "wof:placetype":"venue"
},
  "geometry": {"coordinates":[-97.73490700000001,35.507687],"type":"Point"}
}