{
  "type": "Feature",
  "properties": {
    "addr:full":"3317 SW 74th St Oklahoma City OK 73159",
    "addr:housenumber":"3317",
    "addr:postcode":"73159",
    "addr:street":"Sw 74Th St",
    "iso:country":"US",
    "sg:address":"3317 SW 74th St",
    "sg:city":"Oklahoma City",
    "sg:classifiers":[
        {
            "category":"Real Estate",
            "subcategory":"Real Estate Operator",
            "type":"Services"
        }
    ],
    "sg:phone":"+1 405 682 2622",
    "sg:postcode":"73159",
    "sg:province":"OK",
    "sg:tags":[
        "apartment"
    ],
    "wof:name":"Hillcrest Green Apartments",
    "wof:placetype":"venue"
},
  "geometry": {"coordinates":[-97.573813,35.391725],"type":"Point"}
}