{
  "type": "Feature",
  "properties": {
    "iso:country":"US",
    "sg:address":"510 W Elk Ave",
    "sg:city":"Duncan",
    "sg:classifiers":[
        {
            "category":"Home & Garden",
            "subcategory":"Building Materials",
            "type":"Retail Goods"
        }
    ],
    "sg:phone":"+1 580 252 1159",
    "sg:postcode":"73533",
    "sg:province":"OK",
    "sg:tags":[
        "type",
        "door"
    ],
    "wof:name":"Duncan Door Co",
    "wof:placetype":"venue"
},
  "geometry": {"coordinates":[-97.950659,34.521559],"type":"Point"}
}