{
  "type": "Feature",
  "properties": {
    "addr:full":"107 N Dean A McGee Ave Wynnewood OK 73098",
    "addr:housenumber":"107",
    "addr:postcode":"73098",
    "addr:street":"N Dean A Mcgee Ave",
    "iso:country":"US",
    "sg:address":"107 N Dean A McGee Ave",
    "sg:city":"Wynnewood",
    "sg:classifiers":[
        {
            "category":"Manufacturing",
            "subcategory":"Paper Products",
            "type":"Manufacturing & Wholesale Goods"
        }
    ],
    "sg:phone":"+1 405 665 2211",
    "sg:postcode":"73098",
    "sg:province":"OK",
    "sg:tags":[
        "tag"
    ],
    "wof:name":"Underwood Tag Agency",
    "wof:placetype":"venue"
},
  "geometry": {"coordinates":[-97.17029599999999,34.642776],"type":"Point"}
}