{
  "type": "Feature",
  "properties": {
    "iso:country":"US",
    "sg:address":"2530 Port Pl",
    "sg:city":"Muskogee",
    "sg:classifiers":[
        {
            "category":"Manufacturing",
            "subcategory":"Pet Food",
            "type":"Manufacturing & Wholesale Goods"
        }
    ],
    "sg:phone":"+1 918 683 7215",
    "sg:postcode":"74403",
    "sg:province":"OK",
    "sg:tags":[
        "feed",
        "mfg",
        "prepared"
    ],
    "wof:name":"Southern Qlf",
    "wof:placetype":"venue"
},
  "geometry": {"coordinates":[-95.302954,35.781549],"type":"Point"}
}