{
  "type": "Feature",
  "properties": {
    "iso:country":"US",
    "sg:address":"710 S 1st St",
    "sg:city":"Ponca City",
    "sg:classifiers":[
        {
            "category":"Manufacturing",
            "subcategory":"Metals",
            "type":"Manufacturing & Wholesale Goods"
        }
    ],
    "sg:phone":"+1 580 762 4000",
    "sg:postcode":"74601",
    "sg:province":"OK",
    "sg:tags":[
        "trim",
        "frame",
        "door",
        "sash"
    ],
    "wof:name":"Johndrow Termite & Pest",
    "wof:placetype":"venue"
},
  "geometry": {"coordinates":[-97.08417,36.696486],"type":"Point"}
}