{
  "type": "Feature",
  "properties": {
    "iso:country":"US",
    "sg:address":"7240 E 46th St",
    "sg:city":"Tulsa",
    "sg:classifiers":[
        {
            "category":"Home & Garden",
            "subcategory":"Home Furnishings",
            "type":"Retail Goods"
        },
        {
            "category":"Manufacturing",
            "subcategory":"Glass & Minerals",
            "type":"Manufacturing & Wholesale Goods"
        },
        {
            "category":"Manufacturing",
            "subcategory":"Building Materials",
            "type":"Manufacturing & Wholesale Goods"
        },
        {
            "category":"Shopping",
            "subcategory":"Computers & Home Electronics",
            "type":"Retail Goods"
        }
    ],
    "sg:phone":"+1 918 664 7904",
    "sg:postcode":"74145",
    "sg:province":"OK",
    "sg:tags":[
        "ornamental",
        "door",
        "etc-manufacturers",
        "shower",
        "plate",
        "glass-auto",
        "glass-wholesale",
        "window",
        "carved",
        "glass-automobile",
        "mirror",
        "glass-beveled",
        "etched",
        "enclosure",
        "manufacturer"
    ],
    "sg:website":"http://www.robinsonglass.com",
    "wof:name":"Robinson Glass",
    "wof:placetype":"venue"
},
  "geometry": {"coordinates":[-95.896044,36.097252],"type":"Point"}
}