{
  "type": "Feature",
  "properties": {
    "iso:country":"US",
    "sg:address":"5450 N May Ave",
    "sg:city":"Oklahoma City",
    "sg:classifiers":[
        {
            "category":"Shopping",
            "subcategory":"Stationery & Office Supplies",
            "type":"Retail Goods"
        }
    ],
    "sg:phone":"+1 405 946 4644",
    "sg:postcode":"73112",
    "sg:province":"OK",
    "sg:website":"www.officedepot.com",
    "wof:name":"Office Depot",
    "wof:placetype":"venue"
},
  "geometry": {"coordinates":[-97.565551,35.524432],"type":"Point"}
}