{
  "type": "Feature",
  "properties": {
    "addr:full":"8118 E 15th St Tulsa OK 74112",
    "addr:housenumber":"8118",
    "addr:postcode":"74112",
    "addr:street":"E 15Th St",
    "iso:country":"US",
    "sg:address":"8118 E 15th St",
    "sg:city":"Tulsa",
    "sg:classifiers":[
        {
            "category":"Autos & Motor Vehicles",
            "subcategory":"Auto Supplies",
            "type":"Retail Goods"
        }
    ],
    "sg:phone":"+1 918 622 3939",
    "sg:postcode":"74112",
    "sg:province":"OK",
    "sg:tags":[
        "tire"
    ],
    "wof:name":"Tire Barn Inc",
    "wof:placetype":"venue"
},
  "geometry": {"coordinates":[-95.88508,36.140676],"type":"Point"}
}