{
  "type": "Feature",
  "properties": {
    "iso:country":"US",
    "sg:address":"7900 120th St",
    "sg:city":"Noble",
    "sg:classifiers":[
        {
            "category":"Retail",
            "subcategory":"Auto Repair",
            "type":"Services"
        }
    ],
    "sg:phone":"+1 405 872 7002",
    "sg:postcode":"73068",
    "sg:province":"OK",
    "sg:tags":[
        "repairing",
        "automobile"
    ],
    "wof:name":"Gustin's Automotive",
    "wof:placetype":"venue"
},
  "geometry": {"coordinates":[-97.265295,35.122503],"type":"Point"}
}