{
  "type": "Feature",
  "properties": {
    "addr:full":"511 NE 31st St Oklahoma City OK 73105",
    "addr:housenumber":"511",
    "addr:postcode":"73105",
    "addr:street":"Ne 31St St",
    "iso:country":"US",
    "sg:address":"511 NE 31st St",
    "sg:city":"Oklahoma City",
    "sg:classifiers":[
        {
            "category":"Government",
            "subcategory":"Office",
            "type":"Public Place"
        }
    ],
    "sg:phone":"+1 405 521 3165",
    "sg:postcode":"73105",
    "sg:province":"OK",
    "wof:name":"Taxes Print Shop",
    "wof:placetype":"venue"
},
  "geometry": {"coordinates":[-97.50548000000001,35.50165],"type":"Point"}
}