{
  "type": "Feature",
  "properties": {
    "addr:full":"2616 S Interstate 35 St Oklahoma City OK 73160",
    "addr:housenumber":"2616",
    "addr:postcode":"73160",
    "addr:street":"S Interstate 35 St",
    "iso:country":"US",
    "sg:address":"2616 S Interstate 35 St",
    "sg:city":"Oklahoma City",
    "sg:classifiers":[
        {
            "category":"Travel",
            "subcategory":"Hotels & Motels",
            "type":"Entertainment"
        }
    ],
    "sg:phone":"+1 405 677 0521",
    "sg:postcode":"73160",
    "sg:province":"OK",
    "wof:name":"Days Inn",
    "wof:placetype":"venue"
},
  "geometry": {"coordinates":[-97.48944899999999,35.314245],"type":"Point"}
}