{
  "type": "Feature",
  "properties": {
    "addr:full":"511 SE Washington Blvd Bartlesville OK 74006",
    "addr:housenumber":"511",
    "addr:postcode":"74006",
    "addr:street":"Se Washington Blvd",
    "iso:country":"US",
    "sg:address":"511 SE Washington Blvd",
    "sg:city":"Bartlesville",
    "sg:classifiers":[
        {
            "category":"Restaurant",
            "type":"Food & Drink"
        }
    ],
    "sg:menulink":"http://www.allmenus.com/ok/bartlesville/68491-mazzios-pizza/menu/",
    "sg:phone":"+1 918 335 5555",
    "sg:postcode":"74006",
    "sg:province":"OK",
    "sg:tags":[
        "american",
        "pizza"
    ],
    "wof:name":"Mazzio's Pizza",
    "wof:placetype":"venue"
},
  "geometry": {"coordinates":[-95.935558,36.749304],"type":"Point"}
}