{
  "type": "Feature",
  "properties": {
    "iso:country":"US",
    "sg:address":"1300 E Tuxedo Blvd",
    "sg:city":"Bartlesville",
    "sg:classifiers":[
        {
            "category":"Autos & Motor Vehicles",
            "subcategory":"Auto Supplies",
            "type":"Retail Goods"
        }
    ],
    "sg:phone":"+1 918 336 8522",
    "sg:postcode":"74003",
    "sg:province":"OK",
    "sg:tags":[
        "automobile",
        "parts"
    ],
    "wof:name":"NAPA Auto Parts",
    "wof:placetype":"venue"
},
  "geometry": {"coordinates":[-95.963443,36.754671],"type":"Point"}
}