{
  "type": "Feature",
  "properties": {
    "addr:full":"3530 N Martin Luther King Ave Oklahoma City OK 73111",
    "addr:housenumber":"3530",
    "addr:postcode":"73111",
    "addr:street":"N Martin Luther King Ave",
    "iso:country":"US",
    "sg:address":"3530 N Martin Luther King Ave",
    "sg:city":"Oklahoma City",
    "sg:classifiers":[
        {
            "category":"Government",
            "subcategory":"Police Station",
            "type":"Public Place"
        }
    ],
    "sg:phone":"+1 405 425 2750",
    "sg:postcode":"73111",
    "sg:province":"OK",
    "sg:tags":[
        "state"
    ],
    "sg:website":"www.cleet.state.ok.us",
    "wof:name":"Council On Law Enforcement",
    "wof:placetype":"venue"
},
  "geometry": {"coordinates":[-97.476626,35.506341],"type":"Point"}
}