{
  "type": "Feature",
  "properties": {
    "addr:full":"1840 N 105th East Ave Tulsa OK 74116",
    "addr:housenumber":"1840",
    "addr:postcode":"74116",
    "addr:street":"N 105Th;Ave",
    "iso:country":"US",
    "sg:address":"1840 N 105th East Ave",
    "sg:city":"Tulsa",
    "sg:classifiers":[
        {
            "category":"Manufacturing",
            "subcategory":"Metals",
            "type":"Manufacturing & Wholesale Goods"
        }
    ],
    "sg:phone":"+1 918 838 0021",
    "sg:postcode":"74116",
    "sg:province":"OK",
    "sg:tags":[
        "fabricator",
        "sheet"
    ],
    "wof:name":"Aero-Fab Corp",
    "wof:placetype":"venue"
},
  "geometry": {"coordinates":[-95.859995,36.180967],"type":"Point"}
}