{
  "type": "Feature",
  "properties": {
    "addr:full":"1603 S Park Dr Broken Bow OK 74728",
    "addr:housenumber":"1603",
    "addr:postcode":"74728",
    "addr:street":"S Park Dr",
    "iso:country":"US",
    "sg:address":"1603 S Park Dr",
    "sg:city":"Broken Bow",
    "sg:classifiers":[
        {
            "category":"Autos & Motor Vehicles",
            "subcategory":"Automobile Sales",
            "type":"Retail Goods"
        }
    ],
    "sg:phone":"+1 580 584 7696",
    "sg:postcode":"74728",
    "sg:province":"OK",
    "sg:tags":[
        "used"
    ],
    "wof:name":"Broken Bow Auto Sales",
    "wof:placetype":"venue"
},
  "geometry": {"coordinates":[-94.739492,34.008098],"type":"Point"}
}