{
  "type": "Feature",
  "properties": {
    "addr:full":"311 S Elm St Bristow OK 74010",
    "addr:housenumber":"311",
    "addr:postcode":"74010",
    "addr:street":"S Elm St",
    "iso:country":"US",
    "sg:address":"311 S Elm St",
    "sg:city":"Bristow",
    "sg:classifiers":[
        {
            "category":"Autos & Motor Vehicles",
            "subcategory":"Automobile Sales",
            "type":"Retail Goods"
        }
    ],
    "sg:phone":"+1 918 367 8844",
    "sg:postcode":"74010",
    "sg:province":"OK",
    "sg:tags":[
        "car",
        "dealer"
    ],
    "wof:name":"Michael Motors",
    "wof:placetype":"venue"
},
  "geometry": {"coordinates":[-96.393203,35.830709],"type":"Point"}
}