{
  "type": "Feature",
  "properties": {
    "iso:country":"US",
    "sg:address":"2406 13th St",
    "sg:city":"Woodward",
    "sg:classifiers":[
        {
            "category":"Communications",
            "subcategory":"Radio Station",
            "type":"Services"
        }
    ],
    "sg:phone":"+1 580 256 5407",
    "sg:postcode":"73801",
    "sg:province":"OK",
    "sg:tags":[
        "company",
        "broadcasting"
    ],
    "wof:name":"F M 92",
    "wof:placetype":"venue"
},
  "geometry": {"coordinates":[-99.395721,36.422031],"type":"Point"}
}