{
  "type": "Feature",
  "properties": {
    "iso:country":"US",
    "sg:address":"1550 S Harvard Ave",
    "sg:city":"Tulsa",
    "sg:classifiers":[
        {
            "category":"Insurance",
            "subcategory":"Insurance Agent",
            "type":"Services"
        }
    ],
    "sg:phone":"+1 918 743 5991",
    "sg:postcode":"74112",
    "sg:province":"OK",
    "wof:name":"Allstate Insurance",
    "wof:placetype":"venue"
},
  "geometry": {"coordinates":[-95.940442,36.139658],"type":"Point"}
}