{
  "type": "Feature",
  "properties": {
    "addr:full":"104 Woolsey Ave Morrison OK 73061",
    "addr:housenumber":"104",
    "addr:postcode":"73061",
    "addr:street":"Woolsey Ave",
    "iso:country":"US",
    "sg:address":"104 Woolsey Ave",
    "sg:city":"Morrison",
    "sg:classifiers":[
        {
            "category":"Organizations",
            "subcategory":"Religious Organization",
            "type":"Services"
        }
    ],
    "sg:phone":"+1 580 724 3262",
    "sg:postcode":"73061",
    "sg:province":"OK",
    "sg:tags":[
        "church"
    ],
    "wof:name":"Assembly Of God",
    "wof:placetype":"venue"
},
  "geometry": {"coordinates":[-97.006314,36.296252],"type":"Point"}
}