{
  "type": "Feature",
  "properties": {
    "iso:country":"US",
    "sg:address":"1409 W Detroit St",
    "sg:city":"Broken Arrow",
    "sg:classifiers":[
        {
            "category":"Manufacturing",
            "subcategory":"Retail Goods",
            "type":"Manufacturing & Wholesale Goods"
        }
    ],
    "sg:phone":"+1 918 258 3988",
    "sg:postcode":"74012",
    "sg:province":"OK",
    "sg:tags":[
        "assembly",
        "fabricating"
    ],
    "wof:name":"Metro Sales Assembly",
    "wof:placetype":"venue"
},
  "geometry": {"coordinates":[-95.804149,36.054386],"type":"Point"}
}