{
  "type": "Feature",
  "properties": {
    "addr:full":"217 N 12th St Muskogee OK 74401",
    "addr:housenumber":"217",
    "addr:postcode":"74401",
    "addr:street":"N 12Th St",
    "iso:country":"US",
    "sg:address":"217 N 12th St",
    "sg:city":"Muskogee",
    "sg:classifiers":[
        {
            "category":"Social Services",
            "subcategory":"Child Care",
            "type":"Services"
        }
    ],
    "sg:phone":"+1 918 687 5575",
    "sg:postcode":"74401",
    "sg:province":"OK",
    "wof:name":"Henry's Purple Play House II",
    "wof:placetype":"venue"
},
  "geometry": {"coordinates":[-95.381838,35.75478],"type":"Point"}
}