{
  "type": "Feature",
  "properties": {
    "iso:country":"US",
    "sg:address":"110 S B Ave",
    "sg:city":"Cleveland",
    "sg:classifiers":[
        {
            "category":"Insurance",
            "subcategory":"Insurance Agent",
            "type":"Services"
        }
    ],
    "sg:phone":"+1 918 358 2099",
    "sg:postcode":"74020",
    "sg:province":"OK",
    "wof:name":"AFLAC",
    "wof:placetype":"venue"
},
  "geometry": {"coordinates":[-96.466572,36.308844],"type":"Point"}
}