{
  "type": "Feature",
  "properties": {
    "iso:country":"US",
    "sg:address":"203 S Mickey Mantle Blvd",
    "sg:city":"Commerce",
    "sg:classifiers":[
        {
            "category":"Autos & Motor Vehicles",
            "subcategory":"Fuel & Gas Station",
            "type":"Retail Goods"
        }
    ],
    "sg:phone":"+1 918 675 4524",
    "sg:postcode":"74339",
    "sg:province":"OK",
    "sg:tags":[
        "station",
        "gasoline"
    ],
    "wof:name":"Mullen Service Station",
    "wof:placetype":"venue"
},
  "geometry": {"coordinates":[-94.86726400000001,36.932598],"type":"Point"}
}