{
  "type": "Feature",
  "properties": {
    "iso:country":"US",
    "sg:address":"2204 NW Pollard Ave",
    "sg:city":"Lawton",
    "sg:classifiers":[
        {
            "category":"Organizations",
            "subcategory":"Religious Organization",
            "type":"Services"
        }
    ],
    "sg:phone":"+1 580 355 4347",
    "sg:postcode":"73505",
    "sg:province":"OK",
    "sg:tags":[
        "church"
    ],
    "wof:name":"Pollar Ave Baptist Church",
    "wof:placetype":"venue"
},
  "geometry": {"coordinates":[-98.428843,34.634644],"type":"Point"}
}