{
  "type": "Feature",
  "properties": {
    "iso:country":"US",
    "sg:address":"7404 E 55th Pl",
    "sg:city":"Tulsa",
    "sg:classifiers":[
        {
            "category":"Building & Trades",
            "subcategory":"Pest Control",
            "type":"Services"
        }
    ],
    "sg:phone":"+1 918 622 1874",
    "sg:postcode":"74145",
    "sg:province":"OK",
    "wof:name":"Rips Exterminators",
    "wof:placetype":"venue"
},
  "geometry": {"coordinates":[-95.892686,36.084268],"type":"Point"}
}