{
  "type": "Feature",
  "properties": {
    "iso:country":"US",
    "sg:address":"921 NW 72nd St",
    "sg:city":"Oklahoma City",
    "sg:classifiers":[
        {
            "category":"Manufacturing",
            "subcategory":"Food",
            "type":"Manufacturing & Wholesale Goods"
        },
        {
            "category":"Wholesale",
            "subcategory":"Groceries",
            "type":"Manufacturing & Wholesale Goods"
        }
    ],
    "sg:phone":"+1 405 840 5633",
    "sg:postcode":"73116",
    "sg:province":"OK",
    "sg:tags":[
        "product",
        "manufacturer"
    ],
    "wof:name":"Food Concentrate Corporation",
    "wof:placetype":"venue"
},
  "geometry": {"coordinates":[-97.529536,35.545739],"type":"Point"}
}