{
  "type": "Feature",
  "properties": {
    "addr:full":"630 US Hwy 70 Waurika OK 73573",
    "addr:housenumber":"630",
    "addr:postcode":"73573",
    "addr:street":"Us Hwy 70",
    "iso:country":"US",
    "sg:address":"630 US Hwy 70",
    "sg:city":"Waurika",
    "sg:classifiers":[
        {
            "category":"Autos & Motor Vehicles",
            "subcategory":"Automobile Sales",
            "type":"Retail Goods"
        }
    ],
    "sg:phone":"+1 580 228 3543",
    "sg:postcode":"73573",
    "sg:province":"OK",
    "sg:tags":[
        "car",
        "dealer"
    ],
    "wof:name":"Waurika Used Auto Sales",
    "wof:placetype":"venue"
},
  "geometry": {"coordinates":[-98.009124,34.158789],"type":"Point"}
}