{
  "type": "Feature",
  "properties": {
    "addr:full":"215 N Clarence Nash Blvd Watonga OK 73772",
    "addr:housenumber":"215",
    "addr:postcode":"73772",
    "addr:street":"N;Nash Blvd",
    "iso:country":"US",
    "sg:address":"215 N Clarence Nash Blvd",
    "sg:city":"Watonga",
    "sg:classifiers":[
        {
            "category":"Health Services",
            "subcategory":"Optometrist",
            "type":"Services"
        }
    ],
    "sg:phone":"+1 580 623 2300",
    "sg:postcode":"73772",
    "sg:province":"OK",
    "wof:name":"Susan N Lee OD",
    "wof:placetype":"venue"
},
  "geometry": {"coordinates":[-98.419336,35.845865],"type":"Point"}
}