{
  "type": "Feature",
  "properties": {
    "iso:country":"US",
    "sg:address":"3101 N Hemlock Cir",
    "sg:city":"Broken Arrow",
    "sg:phone":"+1 918 258 0291",
    "sg:postcode":"74012",
    "sg:province":"OK",
    "sg:tags":[
        "equipment",
        "supply"
    ],
    "wof:name":"Captive Aire Systs",
    "wof:placetype":"venue"
},
  "geometry": {"coordinates":[-95.819954,36.079749],"type":"Point"}
}