{
  "type": "Feature",
  "properties": {
    "iso:country":"US",
    "sg:address":"11931 N Pennsylvania Ave",
    "sg:city":"Oklahoma City",
    "sg:classifiers":[
        {
            "category":"Shopping",
            "subcategory":"Pharmacy",
            "type":"Retail Goods"
        }
    ],
    "sg:phone":"+1 405 755 5182",
    "sg:postcode":"73120",
    "sg:province":"OK",
    "wof:name":"Eckerd",
    "wof:placetype":"venue"
},
  "geometry": {"coordinates":[-97.54943799999999,35.591938],"type":"Point"}
}