{
  "type": "Feature",
  "properties": {
    "addr:full":"714 Steele Ave Chandler OK 74834",
    "addr:housenumber":"714",
    "addr:postcode":"74834",
    "addr:street":"Steele Ave",
    "iso:country":"US",
    "sg:address":"714 Steele Ave",
    "sg:city":"Chandler",
    "sg:classifiers":[
        {
            "category":"Real Estate",
            "subcategory":"Real Estate Services",
            "type":"Services"
        }
    ],
    "sg:phone":"+1 405 258 0066",
    "sg:postcode":"74834",
    "sg:province":"OK",
    "wof:name":"Abstract Guaranty Co",
    "wof:placetype":"venue"
},
  "geometry": {"coordinates":[-96.881985,35.703491],"type":"Point"}
}