{
  "type": "Feature",
  "properties": {
    "iso:country":"US",
    "sg:address":"1130 N Oklahoma Ave",
    "sg:city":"Oklahoma City",
    "sg:classifiers":[
        {
            "category":"Professional",
            "subcategory":"Lawyer & Legal Services",
            "type":"Services"
        }
    ],
    "sg:phone":"+1 405 236 8000",
    "sg:postcode":"73104",
    "sg:province":"OK",
    "wof:name":"J Drew Houghton PC",
    "wof:placetype":"venue"
},
  "geometry": {"coordinates":[-97.510373,35.478529],"type":"Point"}
}