{
  "type": "Feature",
  "properties": {
    "addr:full":"908 N Elm St Mooreland OK 73852",
    "addr:housenumber":"908",
    "addr:postcode":"73852",
    "addr:street":"N Elm St",
    "iso:country":"US",
    "sg:address":"908 N Elm St",
    "sg:city":"Mooreland",
    "sg:classifiers":[
        {
            "category":"Retail",
            "subcategory":"Repair Shop",
            "type":"Services"
        }
    ],
    "sg:phone":"+1 580 334 6673",
    "sg:postcode":"73852",
    "sg:province":"OK",
    "sg:tags":[
        "welding"
    ],
    "wof:name":"JM Welding Inc",
    "wof:placetype":"venue"
},
  "geometry": {"coordinates":[-99.205832,36.447372],"type":"Point"}
}