{
  "type": "Feature",
  "properties": {
    "iso:country":"US",
    "sg:address":"15196 E 495 Rd",
    "sg:city":"Claremore",
    "sg:classifiers":[
        {
            "category":"Wholesale",
            "subcategory":"Metals & Minerals",
            "type":"Manufacturing & Wholesale Goods"
        }
    ],
    "sg:phone":"+1 918 342 5111",
    "sg:postcode":"74019",
    "sg:province":"OK",
    "sg:tags":[
        "steel",
        "warehouse"
    ],
    "wof:name":"Flatrolled Steel Inc",
    "wof:placetype":"venue"
},
  "geometry": {"coordinates":[-95.55027,36.299025],"type":"Point"}
}