{
  "type": "Feature",
  "properties": {
    "iso:country":"US",
    "sg:address":"9320 Haskell Dr",
    "sg:city":"Broken Arrow",
    "sg:classifiers":[
        {
            "category":"Building & Trades",
            "subcategory":"Construction",
            "type":"Services"
        }
    ],
    "sg:phone":"+1 918 251 9771",
    "sg:postcode":"74014",
    "sg:province":"OK",
    "sg:tags":[
        "hanging",
        "painter",
        "contractor"
    ],
    "wof:name":"Perfection Painting Co",
    "wof:placetype":"venue"
},
  "geometry": {"coordinates":[-95.718397,36.028634],"type":"Point"}
}