{
  "type": "Feature",
  "properties": {
    "addr:full":"7980 E 11th St Tulsa OK 74112",
    "addr:housenumber":"7980",
    "addr:postcode":"74112",
    "addr:street":"E 11Th St",
    "iso:country":"US",
    "sg:address":"7980 E 11th St",
    "sg:city":"Tulsa",
    "sg:classifiers":[
        {
            "category":"Home & Garden",
            "subcategory":"Garden Supply",
            "type":"Retail Goods"
        }
    ],
    "sg:phone":"+1 918 836 6843",
    "sg:postcode":"74112",
    "sg:province":"OK",
    "sg:tags":[
        "hardware",
        "farm",
        "supp"
    ],
    "wof:name":"Farm & Ranch Supply",
    "wof:placetype":"venue"
},
  "geometry": {"coordinates":[-95.8874,36.147924],"type":"Point"}
}