{
  "type": "Feature",
  "properties": {
    "iso:country":"US",
    "sg:address":"2506 N Harrison Ave",
    "sg:city":"Shawnee",
    "sg:classifiers":[
        {
            "category":"Shopping",
            "type":"Retail Goods"
        }
    ],
    "sg:phone":"+1 405 878 0515",
    "sg:postcode":"74804",
    "sg:province":"OK",
    "sg:tags":[
        "pet",
        "shop"
    ],
    "wof:name":"Petopia",
    "wof:placetype":"venue"
},
  "geometry": {"coordinates":[-96.91215200000001,35.359832],"type":"Point"}
}