{
  "type": "Feature",
  "properties": {
    "iso:country":"US",
    "sg:address":"2 S Coo Y Yah St",
    "sg:city":"Pryor",
    "sg:classifiers":[
        {
            "category":"Health Services",
            "subcategory":"Doctor",
            "type":"Services"
        }
    ],
    "sg:phone":"+1 918 825 7444",
    "sg:postcode":"74361",
    "sg:province":"OK",
    "wof:name":"Douglas A Orthdnst Kirkpatrick",
    "wof:placetype":"venue"
},
  "geometry": {"coordinates":[-95.31318,36.30682],"type":"Point"}
}