{
  "type": "Feature",
  "properties": {
    "iso:country":"US",
    "sg:address":"2102 Union Ave",
    "sg:city":"Seminole",
    "sg:classifiers":[
        {
            "category":"Freight",
            "type":"Transportation"
        }
    ],
    "sg:phone":"+1 405 382 2400",
    "sg:postcode":"74868",
    "sg:province":"OK",
    "sg:tags":[
        "delivery"
    ],
    "wof:name":"Jennifer's Delivery Svc",
    "wof:placetype":"venue"
},
  "geometry": {"coordinates":[-96.694871,35.237338],"type":"Point"}
}