{
  "type": "Feature",
  "properties": {
    "addr:full":"5818 S Peoria Ave Tulsa OK 74105",
    "addr:housenumber":"5818",
    "addr:postcode":"74105",
    "addr:street":"S Peoria Ave",
    "iso:country":"US",
    "sg:address":"5818 S Peoria Ave",
    "sg:city":"Tulsa",
    "sg:classifiers":[
        {
            "category":"Manufacturing",
            "subcategory":"Printing",
            "type":"Manufacturing & Wholesale Goods"
        }
    ],
    "sg:phone":"+1 918 743 4317",
    "sg:postcode":"74105",
    "sg:province":"OK",
    "sg:tags":[
        "quick",
        "copy",
        "offset"
    ],
    "wof:name":"KWIK KOPY Printing",
    "wof:placetype":"venue"
},
  "geometry": {"coordinates":[-95.97576599999999,36.077044],"type":"Point"}
}