{
  "type": "Feature",
  "properties": {
    "addr:full":"8178 S Lewis Ave Tulsa OK 74137",
    "addr:housenumber":"8178",
    "addr:postcode":"74137",
    "addr:street":"S Lewis Ave",
    "iso:country":"US",
    "sg:address":"8178 S Lewis Ave",
    "sg:city":"Tulsa",
    "sg:classifiers":[
        {
            "category":"Professional",
            "type":"Services"
        }
    ],
    "sg:phone":"+1 918 296 5150",
    "sg:postcode":"74137",
    "sg:province":"OK",
    "sg:tags":[
        "establishment"
    ],
    "wof:name":"Bon Appetit",
    "wof:placetype":"venue"
},
  "geometry": {"coordinates":[-95.95783299999999,36.046412],"type":"Point"}
}