{
  "type": "Feature",
  "properties": {
    "iso:country":"US",
    "sg:address":"1915 SE 29th St",
    "sg:city":"Oklahoma City",
    "sg:classifiers":[
        {
            "category":"Retail",
            "subcategory":"Repair Shop",
            "type":"Services"
        }
    ],
    "sg:phone":"+1 405 670 9616",
    "sg:postcode":"73129",
    "sg:province":"OK",
    "sg:tags":[
        "welding"
    ],
    "wof:name":"Fabricating Specialists",
    "wof:placetype":"venue"
},
  "geometry": {"coordinates":[-97.477149,35.435375],"type":"Point"}
}