{
  "type": "Feature",
  "properties": {
    "iso:country":"US",
    "sg:address":"1006 N 7th St",
    "sg:city":"Duncan",
    "sg:classifiers":[
        {
            "category":"Social Services",
            "type":"Services"
        }
    ],
    "sg:phone":"+1 580 255 3733",
    "sg:postcode":"73533",
    "sg:province":"OK",
    "sg:tags":[
        "youth",
        "organization",
        "center"
    ],
    "wof:name":"Duncan Jaycess",
    "wof:placetype":"venue"
},
  "geometry": {"coordinates":[-97.953148,34.514079],"type":"Point"}
}