{
  "type": "Feature",
  "properties": {
    "iso:country":"US",
    "sg:address":"101 S Smith St",
    "sg:city":"Vinita",
    "sg:classifiers":[
        {
            "category":"Education",
            "subcategory":"School",
            "type":"Public Place"
        }
    ],
    "sg:phone":"+1 918 256 5350",
    "sg:postcode":"74301",
    "sg:province":"OK",
    "wof:name":"Will Rogers Elementary Sch",
    "wof:placetype":"venue"
},
  "geometry": {"coordinates":[-95.15813900000001,36.64016],"type":"Point"}
}