{
  "type": "Feature",
  "properties": {
    "iso:country":"US",
    "sg:address":"4403 S Walker Ave",
    "sg:city":"Oklahoma City",
    "sg:classifiers":[
        {
            "category":"Shopping",
            "subcategory":"Used Merchandise",
            "type":"Retail Goods"
        }
    ],
    "sg:phone":"+1 405 631 0902",
    "sg:postcode":"73109",
    "sg:province":"OK",
    "sg:tags":[
        "shop",
        "thrift"
    ],
    "wof:name":"LA Donna's Nifty Thrify",
    "wof:placetype":"venue"
},
  "geometry": {"coordinates":[-97.521449,35.420764],"type":"Point"}
}