{
  "type": "Feature",
  "properties": {
    "iso:country":"US",
    "sg:address":"1238 Forrest Ln",
    "sg:city":"Catoosa",
    "sg:classifiers":[
        {
            "category":"Food & Beverages",
            "subcategory":"Specialty",
            "type":"Retail Goods"
        }
    ],
    "sg:phone":"+1 918 266 2239",
    "sg:postcode":"74015",
    "sg:province":"OK",
    "wof:name":"Xtreme Freedom",
    "wof:placetype":"venue"
},
  "geometry": {"coordinates":[-95.770276,36.173774],"type":"Point"}
}