{
  "type": "Feature",
  "properties": {
    "addr:full":"213 N Broadway Marlow OK 73055",
    "addr:housenumber":"213",
    "addr:postcode":"73055",
    "addr:street":"N Broadway",
    "iso:country":"US",
    "sg:address":"213 N Broadway",
    "sg:city":"Marlow",
    "sg:classifiers":[
        {
            "category":"Organizations",
            "subcategory":"Religious Organization",
            "type":"Services"
        }
    ],
    "sg:phone":"+1 580 658 5413",
    "sg:postcode":"73055",
    "sg:province":"OK",
    "sg:tags":[
        "church"
    ],
    "sg:website":"www.fbcmarlow.org",
    "wof:name":"First Baptist Church Of Marlow",
    "wof:placetype":"venue"
},
  "geometry": {"coordinates":[-97.957888,34.649873],"type":"Point"}
}