{
  "type": "Feature",
  "properties": {
    "iso:country":"US",
    "sg:address":"305 N 2nd St",
    "sg:city":"Guthrie",
    "sg:classifiers":[
        {
            "category":"Building & Trades",
            "subcategory":"Construction",
            "type":"Services"
        }
    ],
    "sg:phone":"+1 405 282 3582",
    "sg:postcode":"73044",
    "sg:province":"OK",
    "sg:tags":[
        "residential"
    ],
    "wof:name":"Mike Savory Construction",
    "wof:placetype":"venue"
},
  "geometry": {"coordinates":[-97.427629,35.880194],"type":"Point"}
}