{
  "type": "Feature",
  "properties": {
    "iso:country":"US",
    "sg:address":"6520 E Skelly Dr",
    "sg:city":"Tulsa",
    "sg:classifiers":[
        {
            "category":"Building & Trades",
            "subcategory":"Equipment Rental",
            "type":"Services"
        }
    ],
    "sg:phone":"+1 918 663 7997",
    "sg:postcode":"74145",
    "sg:province":"OK",
    "sg:tags":[
        "party",
        "supply"
    ],
    "wof:name":"Class Act Party & Wedding Rntl",
    "wof:placetype":"venue"
},
  "geometry": {"coordinates":[-95.90513300000001,36.107726],"type":"Point"}
}