{
  "type": "Feature",
  "properties": {
    "iso:country":"US",
    "sg:address":"6214 Masons Dr",
    "sg:city":"Oklahoma City",
    "sg:classifiers":[
        {
            "category":"Professional",
            "subcategory":"Computer Services",
            "type":"Services"
        }
    ],
    "sg:phone":"+1 405 603 7655",
    "sg:postcode":"73142",
    "sg:province":"OK",
    "sg:tags":[
        "engine",
        "search",
        "internet"
    ],
    "wof:name":"Top Rank Position",
    "wof:placetype":"venue"
},
  "geometry": {"coordinates":[-97.627194,35.601185],"type":"Point"}
}