{
  "type": "Feature",
  "properties": {
    "iso:country":"US",
    "sg:address":"920 N Main St",
    "sg:city":"Thomas",
    "sg:classifiers":[
        {
            "category":"Education",
            "subcategory":"School",
            "type":"Public Place"
        }
    ],
    "sg:phone":"+1 580 661 3522",
    "sg:postcode":"73669",
    "sg:province":"OK",
    "wof:name":"Thomas High School",
    "wof:placetype":"venue"
},
  "geometry": {"coordinates":[-99.404781,35.418162],"type":"Point"}
}