{
  "type": "Feature",
  "properties": {
    "iso:country":"US",
    "sg:address":"3412 W University Blvd",
    "sg:city":"Durant",
    "sg:classifiers":[
        {
            "category":"Education",
            "subcategory":"School",
            "type":"Public Place"
        }
    ],
    "sg:phone":"+1 580 920 0850",
    "sg:postcode":"74701",
    "sg:province":"OK",
    "sg:website":"www.duanesheriffministries.org",
    "wof:name":"Victory Life Academy",
    "wof:placetype":"venue"
},
  "geometry": {"coordinates":[-96.412118,34.005011],"type":"Point"}
}