{
  "type": "Feature",
  "properties": {
    "addr:full":"1110 Hargrove St Ardmore OK 73401",
    "addr:housenumber":"1110",
    "addr:postcode":"73401",
    "addr:street":"Hargrove St",
    "iso:country":"US",
    "sg:address":"1110 Hargrove St",
    "sg:city":"Ardmore",
    "sg:classifiers":[
        {
            "category":"Real Estate",
            "subcategory":"Architect",
            "type":"Services"
        }
    ],
    "sg:phone":"+1 580 223 5060",
    "sg:postcode":"73401",
    "sg:province":"OK",
    "wof:name":"Lumpkin & Assoc",
    "wof:placetype":"venue"
},
  "geometry": {"coordinates":[-97.13311,34.186046],"type":"Point"}
}