{
  "type": "Feature",
  "properties": {
    "iso:country":"US",
    "sg:address":"1410 NW 15th St",
    "sg:city":"Lawton",
    "sg:classifiers":[
        {
            "category":"Wholesale",
            "subcategory":"Auto Parts",
            "type":"Manufacturing & Wholesale Goods"
        }
    ],
    "sg:phone":"+1 580 354 9036",
    "sg:postcode":"73507",
    "sg:province":"OK",
    "sg:tags":[
        "new",
        "provider",
        "automotive"
    ],
    "wof:name":"USA 6x6",
    "wof:placetype":"venue"
},
  "geometry": {"coordinates":[-98.411826,34.624181],"type":"Point"}
}