{
  "type": "Feature",
  "properties": {
    "addr:full":"2025 W Broadway St Muskogee OK 74401",
    "addr:housenumber":"2025",
    "addr:postcode":"74401",
    "addr:street":"W Broadway St",
    "iso:country":"US",
    "sg:address":"2025 W Broadway St",
    "sg:city":"Muskogee",
    "sg:classifiers":[
        {
            "category":"Real Estate",
            "subcategory":"Real Estate Agent",
            "type":"Services"
        },
        {
            "category":"Organizations",
            "subcategory":"Professional Association",
            "type":"Services"
        }
    ],
    "sg:phone":"+1 918 683 6422",
    "sg:postcode":"74401",
    "sg:province":"OK",
    "sg:tags":[
        "builder"
    ],
    "wof:name":"Muskogee Board Of Realtors Inc",
    "wof:placetype":"venue"
},
  "geometry": {"coordinates":[-95.39069499999999,35.755999],"type":"Point"}
}