{
  "type": "Feature",
  "properties": {
    "iso:country":"US",
    "sg:address":"264 Main St",
    "sg:city":"Big Cabin",
    "sg:classifiers":[
        {
            "category":"Local Transit",
            "type":"Transportation"
        }
    ],
    "sg:phone":"+1 918 783 5141",
    "sg:postcode":"74332",
    "sg:province":"OK",
    "sg:tags":[
        "ambulance"
    ],
    "wof:name":"Remo Ambulance",
    "wof:placetype":"venue"
},
  "geometry": {"coordinates":[-95.219183,36.536942],"type":"Point"}
}