{
  "type": "Feature",
  "properties": {
    "addr:full":"14357 180th St Lindsay OK 73052",
    "addr:housenumber":"14357",
    "addr:postcode":"73052",
    "addr:street":"180Th St",
    "iso:country":"US",
    "sg:address":"14357 180th St",
    "sg:city":"Lindsay",
    "sg:classifiers":[
        {
            "category":"Autos & Motor Vehicles",
            "subcategory":"Auto Supplies",
            "type":"Retail Goods"
        }
    ],
    "sg:phone":"+1 405 756 4436",
    "sg:postcode":"73052",
    "sg:province":"OK",
    "wof:name":"Tapco Auto Parts",
    "wof:placetype":"venue"
},
  "geometry": {"coordinates":[-97.592259,34.97165],"type":"Point"}
}