{
  "type": "Feature",
  "properties": {
    "iso:country":"US",
    "sg:address":"201 W Oak Ave",
    "sg:city":"Seminole",
    "sg:classifiers":[
        {
            "category":"Health Services",
            "subcategory":"Clinic",
            "type":"Services"
        },
        {
            "category":"Social Services",
            "subcategory":"Job Training",
            "type":"Services"
        }
    ],
    "sg:phone":"+1 405 382 2330",
    "sg:postcode":"74868",
    "sg:province":"OK",
    "sg:tags":[
        "rehabilitation",
        "outpatient",
        "specialty"
    ],
    "wof:name":"Rehabilitation Services Dept",
    "wof:placetype":"venue"
},
  "geometry": {"coordinates":[-96.672878,35.225481],"type":"Point"}
}