{
  "type": "Feature",
  "properties": {
    "addr:full":"711 Peaceable Acres Rd Stillwater OK 74075",
    "addr:housenumber":"711",
    "addr:postcode":"74075",
    "addr:street":"Peaceable Acres Rd",
    "iso:country":"US",
    "sg:address":"711 Peaceable Acres Rd",
    "sg:city":"Stillwater",
    "sg:classifiers":[
        {
            "category":"Professional",
            "subcategory":"Management & Consulting",
            "type":"Services"
        }
    ],
    "sg:phone":"+1 405 624 2222",
    "sg:postcode":"74075",
    "sg:province":"OK",
    "wof:name":"World Export Services Inc",
    "wof:placetype":"venue"
},
  "geometry": {"coordinates":[-97.06968500000001,36.182477],"type":"Point"}
}