{
  "type": "Feature",
  "properties": {
    "iso:country":"US",
    "sg:address":"416 W Washington Ave",
    "sg:city":"Chickasha",
    "sg:classifiers":[
        {
            "category":"Building & Trades",
            "subcategory":"Construction",
            "type":"Services"
        }
    ],
    "sg:phone":"+1 405 222 7120",
    "sg:postcode":"73018",
    "sg:province":"OK",
    "sg:tags":[
        "concrete"
    ],
    "wof:name":"Concrete Coring",
    "wof:placetype":"venue"
},
  "geometry": {"coordinates":[-97.93736199999999,35.041126],"type":"Point"}
}