{
  "type": "Feature",
  "properties": {
    "addr:full":"7300 Southwest Blvd Tulsa OK 74050",
    "addr:housenumber":"7300",
    "addr:postcode":"74050",
    "addr:street":"Southwest Blvd",
    "iso:country":"US",
    "sg:address":"7300 Southwest Blvd",
    "sg:city":"Tulsa",
    "sg:classifiers":[
        {
            "category":"Retail",
            "subcategory":"Auto Repair",
            "type":"Services"
        }
    ],
    "sg:phone":"+1 918 447 0808",
    "sg:postcode":"74050",
    "sg:province":"OK",
    "sg:tags":[
        "towing"
    ],
    "wof:name":"Kellyville Towing",
    "wof:placetype":"venue"
},
  "geometry": {"coordinates":[-96.0741,36.07689],"type":"Point"}
}