{
  "type": "Feature",
  "properties": {
    "addr:full":"3400 NE 36th St Oklahoma City OK 73121",
    "addr:housenumber":"3400",
    "addr:postcode":"73121",
    "addr:street":"Ne 36Th St",
    "iso:country":"US",
    "sg:address":"3400 NE 36th St",
    "sg:city":"Oklahoma City",
    "sg:classifiers":[
        {
            "category":"Professional",
            "subcategory":"Business Services",
            "type":"Services"
        }
    ],
    "sg:phone":"+1 405 427 1668",
    "sg:postcode":"73121",
    "sg:province":"OK",
    "sg:tags":[
        "real estate"
    ],
    "wof:name":"Mid America Appraisal Inc",
    "wof:placetype":"venue"
},
  "geometry": {"coordinates":[-97.45183,35.507737],"type":"Point"}
}