{
  "type": "Feature",
  "properties": {
    "iso:country":"US",
    "sg:address":"521 E Gladstone Ave",
    "sg:city":"Frederick",
    "sg:classifiers":[
        {
            "category":"Home & Garden",
            "subcategory":"Carpets & Floor Coverings",
            "type":"Retail Goods"
        }
    ],
    "sg:phone":"+1 580 335 7299",
    "sg:postcode":"73542",
    "sg:province":"OK",
    "sg:tags":[
        "dealer",
        "rug"
    ],
    "wof:name":"Carpet Shop",
    "wof:placetype":"venue"
},
  "geometry": {"coordinates":[-99.01166499999999,34.392124],"type":"Point"}
}