{
  "type": "Feature",
  "properties": {
    "iso:country":"US",
    "sg:address":"1000 W Wilshire Blvd",
    "sg:city":"Oklahoma City",
    "sg:classifiers":[
        {
            "category":"Health Services",
            "subcategory":"Doctor",
            "type":"Services"
        }
    ],
    "sg:phone":"+1 405 737 3491",
    "sg:postcode":"73116",
    "sg:province":"OK",
    "sg:tags":[
        "physician",
        "surgeon"
    ],
    "wof:name":"Midwest Orthopedics",
    "wof:placetype":"venue"
},
  "geometry": {"coordinates":[-97.531459,35.551114],"type":"Point"}
}