{
  "type": "Feature",
  "properties": {
    "iso:country":"US",
    "sg:address":"817 Jim Thorpe Blvd",
    "sg:city":"Prague",
    "sg:classifiers":[
        {
            "category":"Restaurant",
            "type":"Food & Drink"
        }
    ],
    "sg:phone":"+1 405 567 3663",
    "sg:postcode":"74864",
    "sg:province":"OK",
    "sg:tags":[
        "eating"
    ],
    "wof:name":"Downtown Cafe",
    "wof:placetype":"venue"
},
  "geometry": {"coordinates":[-96.685948,35.485181],"type":"Point"}
}