{
  "type": "Feature",
  "properties": {
    "addr:full":"1216 S Detroit Ave Tulsa OK 74120",
    "addr:housenumber":"1216",
    "addr:postcode":"74120",
    "addr:street":"S Detroit Ave",
    "iso:country":"US",
    "sg:address":"1216 S Detroit Ave",
    "sg:city":"Tulsa",
    "sg:classifiers":[
        {
            "category":"Retail",
            "subcategory":"Auto Repair",
            "type":"Services"
        }
    ],
    "sg:phone":"+1 918 587 4356",
    "sg:postcode":"74120",
    "sg:province":"OK",
    "sg:tags":[
        "body",
        "automotive",
        "shop"
    ],
    "sg:website":"www.carstar.com",
    "wof:name":"Carstar",
    "wof:placetype":"venue"
},
  "geometry": {"coordinates":[-95.982512,36.144476],"type":"Point"}
}