{
  "type": "Feature",
  "properties": {
    "addr:full":"305 W Craig Rd Broken Bow OK 74728",
    "addr:housenumber":"305",
    "addr:postcode":"74728",
    "addr:street":"W Craig Rd",
    "iso:country":"US",
    "sg:address":"305 W Craig Rd",
    "sg:city":"Broken Bow",
    "sg:classifiers":[
        {
            "category":"Food & Beverages",
            "subcategory":"Groceries & Convenience Stores",
            "type":"Retail Goods"
        }
    ],
    "sg:phone":"+1 580 584 9612",
    "sg:postcode":"74728",
    "sg:province":"OK",
    "wof:name":"E-Z Mart",
    "wof:placetype":"venue"
},
  "geometry": {"coordinates":[-94.740054,34.026458],"type":"Point"}
}