{
  "type": "Feature",
  "properties": {
    "addr:full":"1751 Garth Brooks Blvd Yukon OK 73099",
    "addr:housenumber":"1751",
    "addr:postcode":"73099",
    "addr:street":"Garth Brooks Blvd",
    "iso:country":"US",
    "sg:address":"1751 Garth Brooks Blvd",
    "sg:city":"Yukon",
    "sg:classifiers":[
        {
            "category":"Utilities",
            "subcategory":"Mobile Phone",
            "type":"Services"
        }
    ],
    "sg:phone":"+1 405 354 1661",
    "sg:postcode":"73099",
    "sg:province":"OK",
    "sg:tags":[
        "telephone",
        "cellular"
    ],
    "wof:name":"Totally Wireless",
    "wof:placetype":"venue"
},
  "geometry": {"coordinates":[-97.760148,35.491573],"type":"Point"}
}