{
  "type": "Feature",
  "properties": {
    "iso:country":"US",
    "sg:address":"3023 S Harvard Ave",
    "sg:city":"Tulsa",
    "sg:classifiers":[
        {
            "category":"Restaurant",
            "type":"Food & Drink"
        }
    ],
    "sg:phone":"+1 918 743 5252",
    "sg:postcode":"74114",
    "sg:province":"OK",
    "wof:name":"Alfred's Restaurante Mexicano",
    "wof:placetype":"venue"
},
  "geometry": {"coordinates":[-95.94020399999999,36.120494],"type":"Point"}
}