{
  "type": "Feature",
  "properties": {
    "addr:full":"4600 N Martin Luther King Ave Oklahoma City OK 73111",
    "addr:housenumber":"4600",
    "addr:postcode":"73111",
    "addr:street":"N Martin Luther King Ave",
    "iso:country":"US",
    "sg:address":"4600 N Martin Luther King Ave",
    "sg:city":"Oklahoma City",
    "sg:classifiers":[
        {
            "category":"Retail",
            "subcategory":"Animal Services",
            "type":"Services"
        }
    ],
    "sg:phone":"+1 405 000 1111",
    "sg:postcode":"73111",
    "sg:province":"OK",
    "sg:tags":[
        "shelter"
    ],
    "wof:name":"Okc Animal Control",
    "wof:placetype":"venue"
},
  "geometry": {"coordinates":[-97.476589,35.517984],"type":"Point"}
}