{
  "type": "Feature",
  "properties": {
    "iso:country":"US",
    "sg:address":"2725 N Moore Ave",
    "sg:city":"Oklahoma City",
    "sg:classifiers":[
        {
            "category":"Autos & Motor Vehicles",
            "subcategory":"Boat Sales",
            "type":"Retail Goods"
        }
    ],
    "sg:phone":"+1 405 793 7894",
    "sg:postcode":"73160",
    "sg:province":"OK",
    "wof:name":"M & P Boats",
    "wof:placetype":"venue"
},
  "geometry": {"coordinates":[-97.49782399999999,35.361083],"type":"Point"}
}