{
  "type": "Feature",
  "properties": {
    "iso:country":"US",
    "sg:address":"3220 Charles Page Blvd",
    "sg:city":"Tulsa",
    "sg:classifiers":[
        {
            "category":"Travel",
            "subcategory":"Hotels & Motels",
            "type":"Entertainment"
        }
    ],
    "sg:phone":"+1 918 599 0975",
    "sg:postcode":"74127",
    "sg:province":"OK",
    "sg:tags":[
        "operation"
    ],
    "wof:name":"Holiday Inn",
    "wof:placetype":"venue"
},
  "geometry": {"coordinates":[-96.034761,36.147939],"type":"Point"}
}