{
  "type": "Feature",
  "properties": {
    "addr:full":"575 E 36th St N Tulsa OK 74106",
    "addr:housenumber":"575",
    "addr:postcode":"74106",
    "addr:street":"E 36Th St N",
    "iso:country":"US",
    "sg:address":"575 E 36th St N",
    "sg:city":"Tulsa",
    "sg:classifiers":[
        {
            "category":"Government",
            "subcategory":"Office",
            "type":"Public Place"
        }
    ],
    "sg:phone":"+1 918 428 4030",
    "sg:postcode":"74106",
    "sg:province":"OK",
    "sg:tags":[
        "state",
        "program"
    ],
    "wof:name":"Drivers License Testing",
    "wof:placetype":"venue"
},
  "geometry": {"coordinates":[-95.988353,36.206062],"type":"Point"}
}