{
  "type": "Feature",
  "properties": {
    "iso:country":"US",
    "sg:address":"510 S Rockford Ave",
    "sg:city":"Tulsa",
    "sg:classifiers":[
        {
            "category":"Government",
            "subcategory":"Office",
            "type":"Public Place"
        }
    ],
    "sg:phone":"+1 918 582 2100",
    "sg:postcode":"74120",
    "sg:province":"OK",
    "sg:tags":[
        "village"
    ],
    "wof:name":"Bus Service Information",
    "wof:placetype":"venue"
},
  "geometry": {"coordinates":[-95.97169,36.15343],"type":"Point"}
}