{
  "type": "Feature",
  "properties": {
    "iso:country":"US",
    "sg:address":"501 E Broadway St",
    "sg:city":"Altus",
    "sg:classifiers":[
        {
            "category":"Restaurant",
            "type":"Food & Drink"
        }
    ],
    "sg:menulink":"http://www.allmenus.com/ok/altus/144510-subway/menu/",
    "sg:phone":"+1 580 482 8899",
    "sg:postcode":"73521",
    "sg:province":"OK",
    "sg:tags":[
        "american",
        "sandwich"
    ],
    "wof:name":"Subway",
    "wof:placetype":"venue"
},
  "geometry": {"coordinates":[-99.329162,34.637876],"type":"Point"}
}