{
  "type": "Feature",
  "properties": {
    "iso:country":"US",
    "sg:address":"120 S College St",
    "sg:city":"Cordell",
    "sg:classifiers":[
        {
            "category":"Utilities",
            "subcategory":"Cable",
            "type":"Services"
        }
    ],
    "sg:phone":"+1 580 832 5311",
    "sg:postcode":"73632",
    "sg:province":"OK",
    "sg:tags":[
        "television"
    ],
    "wof:name":"Cable One Inc",
    "wof:placetype":"venue"
},
  "geometry": {"coordinates":[-98.99034,35.291062],"type":"Point"}
}