{
  "type": "Feature",
  "properties": {
    "iso:country":"US",
    "sg:address":"3499 N Wood Dr",
    "sg:city":"Okmulgee",
    "sg:classifiers":[
        {
            "category":"Travel",
            "subcategory":"Hotels & Motels",
            "type":"Entertainment"
        }
    ],
    "sg:phone":"+1 877 574 2464",
    "sg:postcode":"74447",
    "sg:province":"OK",
    "sg:tags":[
        "lodging"
    ],
    "sg:website":"http://book.bestwestern.com/bestwestern/priceAvail.do?propertyCode=37081&cm_mmc=IYP-_-YP-_-property-_-37081",
    "wof:name":"Best Western Okmulgee",
    "wof:placetype":"venue"
},
  "geometry": {"coordinates":[-95.96189099999999,35.65358],"type":"Point"}
}