{
  "type": "Feature",
  "properties": {
    "iso:country":"US",
    "sg:address":"1935 N Moore Ave",
    "sg:city":"Oklahoma City",
    "sg:classifiers":[
        {
            "category":"Organizations",
            "subcategory":"Community Association",
            "type":"Services"
        }
    ],
    "sg:phone":"+1 405 799 1732",
    "sg:postcode":"73141",
    "sg:province":"OK",
    "sg:tags":[
        "educational"
    ],
    "wof:name":"Early Childhood Assn Of Ok",
    "wof:placetype":"venue"
},
  "geometry": {"coordinates":[-97.345652,35.487681],"type":"Point"}
}