{
  "type": "Feature",
  "properties": {
    "iso:country":"US",
    "sg:address":"7720 N Robinson Ave",
    "sg:city":"Oklahoma City",
    "sg:classifiers":[
        {
            "category":"Building & Trades",
            "subcategory":"Construction",
            "type":"Services"
        }
    ],
    "sg:phone":"+1 405 840 9806",
    "sg:postcode":"73116",
    "sg:province":"OK",
    "sg:tags":[
        "installation",
        "elevator"
    ],
    "wof:name":"Thyssenkrupp Elevator Corp",
    "wof:placetype":"venue"
},
  "geometry": {"coordinates":[-97.515694,35.548701],"type":"Point"}
}