{
  "type": "Feature",
  "properties": {
    "addr:full":"505 W Main St Jenks OK 74037",
    "addr:housenumber":"505",
    "addr:postcode":"74037",
    "addr:street":"W Main St",
    "iso:country":"US",
    "sg:address":"505 W Main St",
    "sg:city":"Jenks",
    "sg:classifiers":[
        {
            "category":"Restaurant",
            "type":"Food & Drink"
        }
    ],
    "sg:phone":"+1 918 296 4328",
    "sg:postcode":"74037",
    "sg:province":"OK",
    "wof:name":"Ron's Hamburger & Chili",
    "wof:placetype":"venue"
},
  "geometry": {"coordinates":[-95.976906,36.022673],"type":"Point"}
}