{
  "type": "Feature",
  "properties": {
    "iso:country":"US",
    "sg:address":"2106 SW 44th St",
    "sg:city":"Oklahoma City",
    "sg:classifiers":[
        {
            "category":"Bars & Pubs",
            "type":"Food & Drink"
        }
    ],
    "sg:phone":"+1 405 682 4011",
    "sg:postcode":"73119",
    "sg:province":"OK",
    "wof:name":"Sugar's Mai-Kai Bar",
    "wof:placetype":"venue"
},
  "geometry": {"coordinates":[-97.549895,35.420638],"type":"Point"}
}