{
  "type": "Feature",
  "properties": {
    "iso:country":"US",
    "sg:address":"3414 S Yale Ave",
    "sg:city":"Tulsa",
    "sg:classifiers":[
        {
            "category":"Health Services",
            "subcategory":"Health Practitioner",
            "type":"Services"
        }
    ],
    "sg:phone":"+1 918 747 1600",
    "sg:postcode":"74135",
    "sg:province":"OK",
    "sg:tags":[
        "psychologist"
    ],
    "wof:name":"Riverparks Developmental Ctr",
    "wof:placetype":"venue"
},
  "geometry": {"coordinates":[-95.922535,36.113991],"type":"Point"}
}