{
  "type": "Feature",
  "properties": {
    "addr:full":"1150 Alameda St Norman OK 73071",
    "addr:housenumber":"1150",
    "addr:postcode":"73071",
    "addr:street":"Alameda St",
    "iso:country":"US",
    "sg:address":"1150 Alameda St",
    "sg:city":"Norman",
    "sg:classifiers":[
        {
            "category":"Restaurant",
            "type":"Food & Drink"
        }
    ],
    "sg:menulink":"http://www.allmenus.com/ok/norman/196606-mcdonalds/menu/",
    "sg:phone":"+1 405 321 1228",
    "sg:postcode":"73071",
    "sg:province":"OK",
    "sg:tags":[
        "burger",
        "american"
    ],
    "wof:name":"McDonald's",
    "wof:placetype":"venue"
},
  "geometry": {"coordinates":[-97.42451199999999,35.218235],"type":"Point"}
}