{
  "type": "Feature",
  "properties": {
    "iso:country":"US",
    "sg:address":"711 Kenwood Blvd",
    "sg:city":"Enid",
    "sg:classifiers":[
        {
            "category":"Railroad",
            "type":"Transportation"
        }
    ],
    "sg:phone":"+1 580 237 0543",
    "sg:postcode":"73701",
    "sg:province":"OK",
    "wof:name":"Burlington Northern",
    "wof:placetype":"venue"
},
  "geometry": {"coordinates":[-97.887936,36.403466],"type":"Point"}
}