{
  "type": "Feature",
  "properties": {
    "iso:country":"US",
    "sg:address":"822 N 6th St",
    "sg:city":"Blackwell",
    "sg:classifiers":[
        {
            "category":"Manufacturing",
            "subcategory":"Building Materials",
            "type":"Manufacturing & Wholesale Goods"
        }
    ],
    "sg:phone":"+1 580 363 2882",
    "sg:postcode":"74631",
    "sg:province":"OK",
    "sg:tags":[
        "mfg",
        "wood",
        "kitchen",
        "cabinet"
    ],
    "wof:name":"Daves Cabinets",
    "wof:placetype":"venue"
},
  "geometry": {"coordinates":[-97.291856,36.813354],"type":"Point"}
}