{
  "type": "Feature",
  "properties": {
    "iso:country":"US",
    "sg:address":"1425 E 71st St",
    "sg:city":"Tulsa",
    "sg:classifiers":[
        {
            "category":"Real Estate",
            "subcategory":"Developer",
            "type":"Services"
        }
    ],
    "sg:phone":"+1 918 492 7811",
    "sg:postcode":"74136",
    "sg:province":"OK",
    "wof:name":"Burton Co",
    "wof:placetype":"venue"
},
  "geometry": {"coordinates":[-95.974025,36.060765],"type":"Point"}
}