{
  "type": "Feature",
  "properties": {
    "iso:country":"US",
    "sg:address":"8916 S Pennsylvania Ave",
    "sg:city":"Oklahoma City",
    "sg:classifiers":[
        {
            "category":"Restaurant",
            "type":"Food & Drink"
        }
    ],
    "sg:menulink":"http://www.allmenus.com/ok/oklahoma-city/236042-pickermans-soup--sandwiches/menu/",
    "sg:phone":"+1 405 685 0000",
    "sg:postcode":"73159",
    "sg:province":"OK",
    "sg:tags":[
        "wrap",
        "soup",
        "american",
        "sandwich",
        "salad"
    ],
    "wof:name":"Pickerman's Soup & Sandwiches",
    "wof:placetype":"venue"
},
  "geometry": {"coordinates":[-97.547861,35.37797],"type":"Point"}
}