{
  "type": "Feature",
  "properties": {
    "iso:country":"US",
    "sg:address":"637 SW 6th St",
    "sg:city":"Oklahoma City",
    "sg:classifiers":[
        {
            "category":"Home & Garden",
            "subcategory":"Carpets & Floor Coverings",
            "type":"Retail Goods"
        }
    ],
    "sg:phone":"+1 405 314 9889",
    "sg:postcode":"73160",
    "sg:province":"OK",
    "wof:name":"Woodcock Zac",
    "wof:placetype":"venue"
},
  "geometry": {"coordinates":[-97.496498,35.332301],"type":"Point"}
}