{
  "type": "Feature",
  "properties": {
    "iso:country":"US",
    "sg:address":"2015 E Steve Owens Blvd",
    "sg:city":"Miami",
    "sg:classifiers":[
        {
            "category":"Travel",
            "subcategory":"Hotels & Motels",
            "type":"Entertainment"
        }
    ],
    "sg:phone":"+1 918 540 3333",
    "sg:postcode":"74354",
    "sg:province":"OK",
    "wof:name":"Microtel Inns & Suites",
    "wof:placetype":"venue"
},
  "geometry": {"coordinates":[-94.855175,36.871175],"type":"Point"}
}