{
  "type": "Feature",
  "properties": {
    "iso:country":"US",
    "sg:address":"204 S Mayes St",
    "sg:city":"Adair",
    "sg:classifiers":[
        {
            "category":"Professional",
            "subcategory":"Business Services",
            "type":"Services"
        }
    ],
    "sg:phone":"+1 918 785 2126",
    "sg:postcode":"74361",
    "sg:province":"OK",
    "sg:tags":[
        "embroidery"
    ],
    "wof:name":"Sandy's Embroidery Work",
    "wof:placetype":"venue"
},
  "geometry": {"coordinates":[-95.324115,36.305315],"type":"Point"}
}