{
  "type": "Feature",
  "properties": {
    "addr:full":"512 NW 9th St Oklahoma City OK 73102",
    "addr:housenumber":"512",
    "addr:postcode":"73102",
    "addr:street":"Nw 9Th St",
    "iso:country":"US",
    "sg:address":"512 NW 9th St",
    "sg:city":"Oklahoma City",
    "sg:classifiers":[
        {
            "category":"Travel",
            "subcategory":"Hotels & Motels",
            "type":"Entertainment"
        }
    ],
    "sg:phone":"+1 405 232 5624",
    "sg:postcode":"73102",
    "sg:province":"OK",
    "wof:name":"Century Hotel",
    "wof:placetype":"venue"
},
  "geometry": {"coordinates":[-97.52257,35.477167],"type":"Point"}
}