{
  "type": "Feature",
  "properties": {
    "iso:country":"US",
    "sg:address":"306 W 1st St",
    "sg:city":"Heavener",
    "sg:classifiers":[
        {
            "category":"Autos & Motor Vehicles",
            "subcategory":"Auto Supplies",
            "type":"Retail Goods"
        }
    ],
    "sg:phone":"+1 918 653 4544",
    "sg:postcode":"74937",
    "sg:province":"OK",
    "sg:tags":[
        "automobile",
        "parts"
    ],
    "wof:name":"Ok Auto Supply",
    "wof:placetype":"venue"
},
  "geometry": {"coordinates":[-94.603092,34.891537],"type":"Point"}
}