{
  "type": "Feature",
  "properties": {
    "iso:country":"US",
    "sg:address":"7906 E 55th St",
    "sg:city":"Tulsa",
    "sg:classifiers":[
        {
            "category":"Mining & Drilling",
            "type":"Manufacturing & Wholesale Goods"
        }
    ],
    "sg:phone":"+1 918 392 0123",
    "sg:postcode":"74145",
    "sg:province":"OK",
    "sg:tags":[
        "development",
        "gas",
        "oil",
        "exploration"
    ],
    "wof:name":"Crown Exploration",
    "wof:placetype":"venue"
},
  "geometry": {"coordinates":[-95.886623,36.085012],"type":"Point"}
}