{
  "type": "Feature",
  "properties": {
    "addr:full":"802 N Boomer Rd Stillwater OK 74075",
    "addr:housenumber":"802",
    "addr:postcode":"74075",
    "addr:street":"N Boomer Rd",
    "iso:country":"US",
    "sg:address":"802 N Boomer Rd",
    "sg:city":"Stillwater",
    "sg:classifiers":[
        {
            "category":"Retail",
            "subcategory":"Auto Repair",
            "type":"Services"
        }
    ],
    "sg:phone":"+1 405 743 0661",
    "sg:postcode":"74075",
    "sg:province":"OK",
    "sg:tags":[
        "glass",
        "replacement"
    ],
    "wof:name":"City Glass Co",
    "wof:placetype":"venue"
},
  "geometry": {"coordinates":[-97.060429,36.13219],"type":"Point"}
}