{
  "type": "Feature",
  "properties": {
    "iso:country":"US",
    "sg:address":"1912 W C St",
    "sg:city":"Jenks",
    "sg:classifiers":[
        {
            "category":"Professional",
            "subcategory":"Lawyer & Legal Services",
            "type":"Services"
        }
    ],
    "sg:phone":"+1 918 299 4300",
    "sg:postcode":"74037",
    "sg:province":"OK",
    "sg:tags":[
        "attorney",
        "family",
        "divorce",
        "practice",
        "child",
        "law",
        "probate",
        "custody"
    ],
    "sg:website":"http://www.kupermanlawok.com",
    "wof:name":"Steven Oren Kuperman",
    "wof:placetype":"venue"
},
  "geometry": {"coordinates":[-95.999037,36.025219],"type":"Point"}
}