{
  "type": "Feature",
  "properties": {
    "iso:country":"US",
    "sg:address":"1710 E Carl Albert Pkwy",
    "sg:city":"Bache",
    "sg:classifiers":[
        {
            "category":"Restaurant",
            "type":"Food & Drink"
        }
    ],
    "sg:phone":"+1 918 423 8408",
    "sg:postcode":"74501",
    "sg:province":"OK",
    "sg:tags":[
        "eating"
    ],
    "wof:name":"Golden China",
    "wof:placetype":"venue"
},
  "geometry": {"coordinates":[-95.74358599999999,34.927432],"type":"Point"}
}