{
  "type": "Feature",
  "properties": {
    "iso:country":"US",
    "sg:address":"508 US Hwy 271",
    "sg:city":"Antlers",
    "sg:classifiers":[
        {
            "category":"Government",
            "subcategory":"Office",
            "type":"Public Place"
        }
    ],
    "sg:phone":"+1 580 298 3339",
    "sg:postcode":"74523",
    "sg:province":"OK",
    "sg:tags":[
        "federal",
        "planning",
        "dev"
    ],
    "wof:name":"USDA Rural Development",
    "wof:placetype":"venue"
},
  "geometry": {"coordinates":[-95.61422399999999,34.231937],"type":"Point"}
}