{
  "type": "Feature",
  "properties": {
    "addr:full":"5941 E Admiral Pl Tulsa OK 74115",
    "addr:housenumber":"5941",
    "addr:postcode":"74115",
    "addr:street":"E Admiral Pl",
    "iso:country":"US",
    "sg:address":"5941 E Admiral Pl",
    "sg:city":"Tulsa",
    "sg:classifiers":[
        {
            "category":"Restaurant",
            "type":"Food & Drink"
        }
    ],
    "sg:phone":"+1 918 838 9410",
    "sg:postcode":"74115",
    "sg:province":"OK",
    "wof:name":"Ike's Catering",
    "wof:placetype":"venue"
},
  "geometry": {"coordinates":[-95.909295,36.160835],"type":"Point"}
}