{
  "type": "Feature",
  "properties": {
    "iso:country":"US",
    "sg:address":"755 Harrison St",
    "sg:city":"Harrah",
    "sg:classifiers":[
        {
            "category":"Education",
            "subcategory":"School",
            "type":"Public Place"
        }
    ],
    "sg:phone":"+1 405 454 6201",
    "sg:postcode":"73045",
    "sg:province":"OK",
    "wof:name":"Clara Reynolds Elem School",
    "wof:placetype":"venue"
},
  "geometry": {"coordinates":[-97.16814100000001,35.475333],"type":"Point"}
}