{
  "type": "Feature",
  "properties": {
    "iso:country":"US",
    "sg:address":"402 Telstar St",
    "sg:city":"Norman",
    "sg:classifiers":[
        {
            "category":"Building & Trades",
            "subcategory":"Plumbing",
            "type":"Services"
        }
    ],
    "sg:phone":"+1 405 672 9535",
    "sg:postcode":"73069",
    "sg:province":"OK",
    "sg:tags":[
        "conditioning",
        "air",
        "system",
        "contractor"
    ],
    "wof:name":"Prism Heating & Air",
    "wof:placetype":"venue"
},
  "geometry": {"coordinates":[-97.448132,35.238702],"type":"Point"}
}