{
  "type": "Feature",
  "properties": {
    "iso:country":"US",
    "sg:address":"3038 E 49th St",
    "sg:city":"Tulsa",
    "sg:classifiers":[
        {
            "category":"Building & Trades",
            "subcategory":"Landscaping Services",
            "type":"Services"
        }
    ],
    "sg:phone":"+1 918 742 8196",
    "sg:postcode":"74105",
    "sg:province":"OK",
    "sg:tags":[
        "designer",
        "landscape"
    ],
    "wof:name":"Sundown Corp",
    "wof:placetype":"venue"
},
  "geometry": {"coordinates":[-95.943824,36.092426],"type":"Point"}
}