{
  "type": "Feature",
  "properties": {
    "iso:country":"US",
    "sg:address":"2700 N Main St",
    "sg:city":"Mcalester",
    "sg:classifiers":[
        {
            "category":"Shopping",
            "subcategory":"Used Merchandise",
            "type":"Retail Goods"
        }
    ],
    "sg:phone":"+1 918 423 8620",
    "sg:postcode":"74501",
    "sg:province":"OK",
    "sg:tags":[
        "antique"
    ],
    "wof:name":"Old Town Antique Mall",
    "wof:placetype":"venue"
},
  "geometry": {"coordinates":[-95.760566,34.956461],"type":"Point"}
}