{
  "type": "Feature",
  "properties": {
    "iso:country":"US",
    "sg:address":"215 N McKinley Ave",
    "sg:city":"Oklahoma City",
    "sg:classifiers":[
        {
            "category":"Organizations",
            "subcategory":"Religious Organization",
            "type":"Services"
        }
    ],
    "sg:phone":"+1 405 232 7291",
    "sg:postcode":"73106",
    "sg:province":"OK",
    "wof:name":"Second United Methodist",
    "wof:placetype":"venue"
},
  "geometry": {"coordinates":[-97.536827,35.469784],"type":"Point"}
}