{
  "type": "Feature",
  "properties": {
    "addr:full":"1701 NW Sheridan Rd Lawton OK 73505",
    "addr:housenumber":"1701",
    "addr:postcode":"73505",
    "addr:street":"Nw Sheridan Rd",
    "iso:country":"US",
    "sg:address":"1701 NW Sheridan Rd",
    "sg:city":"Lawton",
    "sg:classifiers":[
        {
            "category":"Social Services",
            "subcategory":"Child Care",
            "type":"Services"
        }
    ],
    "sg:phone":"+1 580 354 1266",
    "sg:postcode":"73505",
    "sg:province":"OK",
    "wof:name":"Y 2 Kids",
    "wof:placetype":"venue"
},
  "geometry": {"coordinates":[-98.42218699999999,34.6266],"type":"Point"}
}