{
  "type": "Feature",
  "properties": {
    "iso:country":"US",
    "sg:address":"3316 N May Ave",
    "sg:city":"Oklahoma City",
    "sg:classifiers":[
        {
            "category":"Wholesale",
            "subcategory":"Auto Parts",
            "type":"Manufacturing & Wholesale Goods"
        }
    ],
    "sg:phone":"+1 405 948 3111",
    "sg:postcode":"73112",
    "sg:province":"OK",
    "sg:tags":[
        "truck",
        "accessory"
    ],
    "wof:name":"Wholesale Accessories",
    "wof:placetype":"venue"
},
  "geometry": {"coordinates":[-97.565592,35.503849],"type":"Point"}
}