{
  "type": "Feature",
  "properties": {
    "addr:full":"123 W 7th Ave Stillwater OK 74074",
    "addr:housenumber":"123",
    "addr:postcode":"74074",
    "addr:street":"W 7Th Ave",
    "iso:country":"US",
    "sg:address":"123 W 7th Ave",
    "sg:city":"Stillwater",
    "sg:classifiers":[
        {
            "category":"Professional",
            "subcategory":"Lawyer & Legal Services",
            "type":"Services"
        }
    ],
    "sg:phone":"+1 405 377 8185",
    "sg:postcode":"74074",
    "sg:province":"OK",
    "sg:tags":[
        "attorney"
    ],
    "wof:name":"Bob Brown & Assoc",
    "wof:placetype":"venue"
},
  "geometry": {"coordinates":[-97.058825,36.114485],"type":"Point"}
}