{
  "type": "Feature",
  "properties": {
    "iso:country":"US",
    "sg:address":"1702 Lancaster Cir",
    "sg:city":"Norman",
    "sg:classifiers":[
        {
            "category":"Retail",
            "subcategory":"Repair Shop",
            "type":"Services"
        }
    ],
    "sg:phone":"+1 405 292 6701",
    "sg:postcode":"73069",
    "sg:province":"OK",
    "sg:tags":[
        "repairing",
        "equipment",
        "electric"
    ],
    "wof:name":"Mc Murphy Electric Motor Repr",
    "wof:placetype":"venue"
},
  "geometry": {"coordinates":[-97.467035,35.205361],"type":"Point"}
}