{
  "type": "Feature",
  "properties": {
    "addr:full":"1912 S Elm Pl Broken Arrow OK 74012",
    "addr:housenumber":"1912",
    "addr:postcode":"74012",
    "addr:street":"S Elm Pl",
    "iso:country":"US",
    "sg:address":"1912 S Elm Pl",
    "sg:city":"Broken Arrow",
    "sg:classifiers":[
        {
            "category":"Restaurant",
            "type":"Food & Drink"
        }
    ],
    "sg:phone":"+1 918 254 8100",
    "sg:postcode":"74012",
    "sg:province":"OK",
    "wof:name":"Goldie's Patio Grill",
    "wof:placetype":"venue"
},
  "geometry": {"coordinates":[-95.79756,36.030298],"type":"Point"}
}