{
  "type": "Feature",
  "properties": {
    "iso:country":"US",
    "sg:address":"9955 S Sandusky Ave",
    "sg:city":"Tulsa",
    "sg:classifiers":[
        {
            "category":"Wholesale",
            "subcategory":"Machinery & Supplies",
            "type":"Manufacturing & Wholesale Goods"
        }
    ],
    "sg:phone":"+1 918 299 2552",
    "sg:postcode":"74137",
    "sg:province":"OK",
    "sg:tags":[
        "work",
        "plate",
        "industrial",
        "fabricated",
        "mfg"
    ],
    "wof:name":"Jbco Inc",
    "wof:placetype":"venue"
},
  "geometry": {"coordinates":[-95.927288,36.018405],"type":"Point"}
}