{
  "type": "Feature",
  "properties": {
    "iso:country":"US",
    "sg:address":"8501 Mantle Ave",
    "sg:city":"Oklahoma City",
    "sg:classifiers":[
        {
            "category":"Building & Trades",
            "subcategory":"Construction",
            "type":"Services"
        }
    ],
    "sg:phone":"+1 405 720 3107",
    "sg:postcode":"73132",
    "sg:province":"OK",
    "sg:tags":[
        "house"
    ],
    "wof:name":"Life Style Pool LLC",
    "wof:placetype":"venue"
},
  "geometry": {"coordinates":[-97.646741,35.556833],"type":"Point"}
}