{
  "type": "Feature",
  "properties": {
    "addr:full":"1920 Collins Blvd Ada OK 74820",
    "addr:housenumber":"1920",
    "addr:postcode":"74820",
    "addr:street":"Collins Blvd",
    "iso:country":"US",
    "sg:address":"1920 Collins Blvd",
    "sg:city":"Ada",
    "sg:classifiers":[
        {
            "category":"Building & Trades",
            "subcategory":"Plumbing",
            "type":"Services"
        }
    ],
    "sg:phone":"+1 580 332 4160",
    "sg:postcode":"74820",
    "sg:province":"OK",
    "sg:tags":[
        "conditioning",
        "air",
        "system",
        "contractor"
    ],
    "wof:name":"Bob Whiteley Svc",
    "wof:placetype":"venue"
},
  "geometry": {"coordinates":[-96.65058399999999,34.77304],"type":"Point"}
}