{
  "type": "Feature",
  "properties": {
    "iso:country":"US",
    "sg:address":"10603 N I 35 Service Rd",
    "sg:city":"Oklahoma City",
    "sg:classifiers":[
        {
            "category":"Restaurant",
            "type":"Food & Drink"
        }
    ],
    "sg:menulink":"http://www.allmenus.com/ok/oklahoma-city/4573-papas-lil-italy/menu/",
    "sg:phone":"+1 405 478 4400",
    "sg:postcode":"73131",
    "sg:province":"OK",
    "sg:tags":[
        "italian"
    ],
    "wof:name":"Papa's Lil Italy",
    "wof:placetype":"venue"
},
  "geometry": {"coordinates":[-97.444514,35.577928],"type":"Point"}
}