{
  "type": "Feature",
  "properties": {
    "addr:full":"40210 Hardesty Rd Shawnee OK 74801",
    "addr:postcode":"40210;74801",
    "addr:street":"Hardesty Rd",
    "iso:country":"US",
    "sg:address":"40210 Hardesty Rd",
    "sg:city":"Shawnee",
    "sg:classifiers":[
        {
            "category":"Restaurant",
            "type":"Food & Drink"
        }
    ],
    "sg:menulink":"http://www.allmenus.com/ok/shawnee/199473-sonic/menu/",
    "sg:phone":"+1 405 878 8804",
    "sg:postcode":"74801",
    "sg:province":"OK",
    "sg:tags":[
        "burger",
        "american"
    ],
    "wof:name":"Sonic",
    "wof:placetype":"venue"
},
  "geometry": {"coordinates":[-96.944168,35.304248],"type":"Point"}
}