{
  "type": "Feature",
  "properties": {
    "addr:full":"2520 S Rankin St Edmond OK 73013",
    "addr:housenumber":"2520",
    "addr:postcode":"73013",
    "addr:street":"S Rankin St",
    "iso:country":"US",
    "sg:address":"2520 S Rankin St",
    "sg:city":"Edmond",
    "sg:classifiers":[
        {
            "category":"Health Services",
            "subcategory":"Nursing And Care Facility",
            "type":"Services"
        }
    ],
    "sg:phone":"+1 405 341 1433",
    "sg:postcode":"73013",
    "sg:province":"OK",
    "sg:tags":[
        "intermediate",
        "hospital",
        "skilled",
        "specialty"
    ],
    "wof:name":"Amity Care  LLC",
    "wof:placetype":"venue"
},
  "geometry": {"coordinates":[-97.474622,35.630019],"type":"Point"}
}