{
  "type": "Feature",
  "properties": {
    "iso:country":"US",
    "sg:address":"16619 S Memorial Dr",
    "sg:city":"Bixby",
    "sg:classifiers":[
        {
            "category":"Real Estate",
            "subcategory":"Real Estate Operator",
            "type":"Services"
        }
    ],
    "sg:phone":"+1 918 369 5120",
    "sg:postcode":"74008",
    "sg:province":"OK",
    "sg:tags":[
        "mobile",
        "home",
        "site",
        "community"
    ],
    "wof:name":"Southside Mobile Village",
    "wof:placetype":"venue"
},
  "geometry": {"coordinates":[-95.886521,35.923247],"type":"Point"}
}