{
  "type": "Feature",
  "properties": {
    "iso:country":"US",
    "sg:address":"1314 S Division St",
    "sg:city":"Guthrie",
    "sg:classifiers":[
        {
            "category":"Restaurant",
            "type":"Food & Drink"
        }
    ],
    "sg:menulink":"http://www.allmenus.com/ok/guthrie/94359-dominos-pizza/menu/",
    "sg:phone":"+1 405 282 1014",
    "sg:postcode":"73044",
    "sg:province":"OK",
    "sg:tags":[
        "american",
        "wing",
        "pizza"
    ],
    "wof:name":"Domino's Pizza",
    "wof:placetype":"venue"
},
  "geometry": {"coordinates":[-97.42536200000001,35.865443],"type":"Point"}
}