{
  "type": "Feature",
  "properties": {
    "iso:country":"US",
    "sg:address":"3103 Turner St",
    "sg:city":"Ponca City",
    "sg:classifiers":[
        {
            "category":"Health Services",
            "subcategory":"Clinic",
            "type":"Services"
        }
    ],
    "sg:phone":"+1 580 762 9027",
    "sg:postcode":"74604",
    "sg:province":"OK",
    "sg:tags":[
        "specialty",
        "outpatient"
    ],
    "wof:name":"Bodyworks By Lilly Freeman Chp",
    "wof:placetype":"venue"
},
  "geometry": {"coordinates":[-97.057751,36.742837],"type":"Point"}
}