{
  "type": "Feature",
  "properties": {
    "iso:country":"US",
    "sg:address":"1233 S Main St",
    "sg:city":"Blackwell",
    "sg:phone":"+1 580 363 4163",
    "sg:postcode":"74631",
    "sg:province":"OK",
    "sg:tags":[
        "farm",
        "wheat"
    ],
    "wof:name":"Claybaker Farms",
    "wof:placetype":"venue"
},
  "geometry": {"coordinates":[-97.283084,36.792323],"type":"Point"}
}