{
  "type": "Feature",
  "properties": {
    "iso:country":"US",
    "sg:address":"5505 E 51st St",
    "sg:city":"Tulsa",
    "sg:classifiers":[
        {
            "category":"Health Services",
            "subcategory":"Health Practitioner",
            "type":"Services"
        }
    ],
    "sg:phone":"+1 918 270 4770",
    "sg:postcode":"74135",
    "sg:province":"OK",
    "wof:name":"Phillip White",
    "wof:placetype":"venue"
},
  "geometry": {"coordinates":[-95.913786,36.089935],"type":"Point"}
}