{
  "type": "Feature",
  "properties": {
    "addr:full":"412 Norvell Rd S Heavener OK 74937",
    "addr:housenumber":"412",
    "addr:postcode":"74937",
    "addr:street":"Norvell Rd",
    "iso:country":"US",
    "sg:address":"412 Norvell Rd S",
    "sg:city":"Heavener",
    "sg:classifiers":[
        {
            "category":"Animal Shelter",
            "type":"Public Place"
        },
        {
            "category":"Retail",
            "subcategory":"Pet Boarding",
            "type":"Services"
        }
    ],
    "sg:phone":"+1 918 653 2814",
    "sg:postcode":"74937",
    "sg:province":"OK",
    "sg:tags":[
        "kennel"
    ],
    "wof:name":"J And K Kennels",
    "wof:placetype":"venue"
},
  "geometry": {"coordinates":[-94.60833700000001,34.867952],"type":"Point"}
}