{
  "type": "Feature",
  "properties": {
    "iso:country":"US",
    "sg:address":"3200 NE 30th St",
    "sg:city":"Oklahoma City",
    "sg:classifiers":[
        {
            "category":"Professional",
            "subcategory":"Business Services",
            "type":"Services"
        }
    ],
    "sg:phone":"+1 405 424 4591",
    "sg:postcode":"73121",
    "sg:province":"OK",
    "sg:tags":[
        "distribution",
        "manufacturing",
        "merchandising",
        "educational"
    ],
    "wof:name":"W C A E M USA",
    "wof:placetype":"venue"
},
  "geometry": {"coordinates":[-97.455571,35.500381],"type":"Point"}
}