{
  "type": "Feature",
  "properties": {
    "addr:full":"3700 N Rockwell Ave Bethany OK 73008",
    "addr:housenumber":"3700",
    "addr:postcode":"73008",
    "addr:street":"N Rockwell Ave",
    "iso:country":"US",
    "sg:address":"3700 N Rockwell Ave",
    "sg:city":"Bethany",
    "sg:classifiers":[
        {
            "category":"Retail",
            "subcategory":"Auto Repair",
            "type":"Services"
        }
    ],
    "sg:phone":"+1 405 787 6798",
    "sg:postcode":"73008",
    "sg:province":"OK",
    "sg:tags":[
        "automotive",
        "replacement",
        "coating",
        "tinting",
        "glass"
    ],
    "wof:name":"Adams Auto Tinting Inc",
    "wof:placetype":"venue"
},
  "geometry": {"coordinates":[-97.636628,35.509287],"type":"Point"}
}