{
  "type": "Feature",
  "properties": {
    "iso:country":"US",
    "sg:address":"1645 S 101st East Ave",
    "sg:city":"Tulsa",
    "sg:classifiers":[
        {
            "category":"Recreation",
            "type":"Entertainment"
        }
    ],
    "sg:phone":"+1 918 669 7280",
    "sg:postcode":"74128",
    "sg:province":"OK",
    "sg:tags":[
        "gate",
        "attendant"
    ],
    "wof:name":"Shirley White",
    "wof:placetype":"venue"
},
  "geometry": {"coordinates":[-95.864484,36.137933],"type":"Point"}
}