{
  "type": "Feature",
  "properties": {
    "iso:country":"US",
    "sg:address":"9207 N Pennsylvania Ave",
    "sg:city":"Oklahoma City",
    "sg:classifiers":[
        {
            "category":"Real Estate",
            "subcategory":"Real Estate Operator",
            "type":"Services"
        }
    ],
    "sg:phone":"+1 405 843 7474",
    "sg:postcode":"73120",
    "sg:province":"OK",
    "sg:tags":[
        "mall",
        "shopping",
        "center"
    ],
    "wof:name":"Casady Square Shopping Ctr",
    "wof:placetype":"venue"
},
  "geometry": {"coordinates":[-97.54925799999999,35.563818],"type":"Point"}
}