{
  "type": "Feature",
  "properties": {
    "addr:full":"630 McLish Ave SW Ardmore OK 73401",
    "addr:housenumber":"630",
    "addr:postcode":"73401",
    "addr:street":"Mclish Ave Sw",
    "iso:country":"US",
    "sg:address":"630 McLish Ave SW",
    "sg:city":"Ardmore",
    "sg:classifiers":[
        {
            "category":"Recreation",
            "type":"Entertainment"
        }
    ],
    "sg:phone":"+1 580 223 2832",
    "sg:postcode":"73401",
    "sg:province":"OK",
    "wof:name":"A K S",
    "wof:placetype":"venue"
},
  "geometry": {"coordinates":[-97.136323,34.173029],"type":"Point"}
}