{
  "type": "Feature",
  "properties": {
    "iso:country":"US",
    "sg:address":"4415 S Harvard Ave",
    "sg:city":"Tulsa",
    "sg:classifiers":[
        {
            "category":"Health Services",
            "subcategory":"Health Practitioner",
            "type":"Services"
        }
    ],
    "sg:phone":"+1 918 743 1133",
    "sg:postcode":"74135",
    "sg:province":"OK",
    "sg:tags":[
        "therapist",
        "physical"
    ],
    "wof:name":"Spinal Therapeutic Svc Inc",
    "wof:placetype":"venue"
},
  "geometry": {"coordinates":[-95.940131,36.100711],"type":"Point"}
}