{
  "type": "Feature",
  "properties": {
    "iso:country":"US",
    "sg:address":"3900 NW 12th St",
    "sg:city":"Oklahoma City",
    "sg:classifiers":[
        {
            "category":"Professional",
            "subcategory":"Business Services",
            "type":"Services"
        }
    ],
    "sg:phone":"+1 405 946 4534",
    "sg:postcode":"73107",
    "sg:province":"OK",
    "wof:name":"Music Row Recording LLC",
    "wof:placetype":"venue"
},
  "geometry": {"coordinates":[-97.590013,35.482396],"type":"Point"}
}