{
  "type": "Feature",
  "properties": {
    "addr:full":"649 W Claremore St Claremore OK 74017",
    "addr:housenumber":"649",
    "addr:postcode":"74017",
    "addr:street":"W Claremore St",
    "iso:country":"US",
    "sg:address":"649 W Claremore St",
    "sg:city":"Claremore",
    "sg:classifiers":[
        {
            "category":"Building & Trades",
            "subcategory":"Construction",
            "type":"Services"
        }
    ],
    "sg:phone":"+1 918 341 5602",
    "sg:postcode":"74017",
    "sg:province":"OK",
    "sg:tags":[
        "house"
    ],
    "wof:name":"Griggs Construction Co",
    "wof:placetype":"venue"
},
  "geometry": {"coordinates":[-95.618072,36.309673],"type":"Point"}
}