{
  "type": "Feature",
  "properties": {
    "iso:country":"US",
    "sg:address":"7021 S Memorial Dr",
    "sg:city":"Tulsa",
    "sg:classifiers":[
        {
            "category":"Professional",
            "type":"Services"
        }
    ],
    "sg:phone":"+1 918 459 5091",
    "sg:postcode":"74133",
    "sg:province":"OK",
    "sg:tags":[
        "establishment"
    ],
    "wof:name":"Sky International Inc",
    "wof:placetype":"venue"
},
  "geometry": {"coordinates":[-95.88627,36.062097],"type":"Point"}
}