{
  "type": "Feature",
  "properties": {
    "iso:country":"US",
    "sg:address":"607 SW 11th St",
    "sg:city":"Lawton",
    "sg:classifiers":[
        {
            "category":"Banks & Credit Unions",
            "subcategory":"Bank",
            "type":"Services"
        }
    ],
    "sg:phone":"+1 580 353 8151",
    "sg:postcode":"73501",
    "sg:province":"OK",
    "sg:tags":[
        "personal",
        "institution"
    ],
    "wof:name":"American General Finance",
    "wof:placetype":"venue"
},
  "geometry": {"coordinates":[-98.40481800000001,34.601161],"type":"Point"}
}