{
  "type": "Feature",
  "properties": {
    "iso:country":"US",
    "sg:address":"11220 NW 113th St",
    "sg:city":"Yukon",
    "sg:classifiers":[
        {
            "category":"Professional",
            "subcategory":"Management & Consulting",
            "type":"Services"
        }
    ],
    "sg:phone":"+1 405 373 9038",
    "sg:postcode":"73099",
    "sg:province":"OK",
    "wof:name":"Perdue Marketing",
    "wof:placetype":"venue"
},
  "geometry": {"coordinates":[-97.72418399999999,35.584524],"type":"Point"}
}