{
  "type": "Feature",
  "properties": {
    "addr:full":"826 W 12th St Sulphur OK 73086",
    "addr:housenumber":"826",
    "addr:postcode":"73086",
    "addr:street":"W 12Th St",
    "iso:country":"US",
    "sg:address":"826 W 12th St",
    "sg:city":"Sulphur",
    "sg:classifiers":[
        {
            "category":"Personal",
            "subcategory":"Beauty Salon",
            "type":"Services"
        }
    ],
    "sg:phone":"+1 580 622 4247",
    "sg:postcode":"73086",
    "sg:province":"OK",
    "wof:name":"Shear Excellence",
    "wof:placetype":"venue"
},
  "geometry": {"coordinates":[-96.982088,34.505537],"type":"Point"}
}