{
  "type": "Feature",
  "properties": {
    "addr:full":"701 N Council Rd Oklahoma City OK 73127",
    "addr:housenumber":"701",
    "addr:postcode":"73127",
    "addr:street":"N Council Rd",
    "iso:country":"US",
    "sg:address":"701 N Council Rd",
    "sg:city":"Oklahoma City",
    "sg:classifiers":[
        {
            "category":"Social Services",
            "subcategory":"Adult Care",
            "type":"Services"
        }
    ],
    "sg:phone":"+1 405 787 4466",
    "sg:postcode":"73127",
    "sg:province":"OK",
    "sg:tags":[
        "home",
        "residential"
    ],
    "sg:website":"www.emerald-square.com",
    "wof:name":"Emerald Square",
    "wof:placetype":"venue"
},
  "geometry": {"coordinates":[-97.654298,35.474775],"type":"Point"}
}