{
  "type": "Feature",
  "properties": {
    "iso:country":"US",
    "sg:address":"725 E Taft St",
    "sg:city":"Sapulpa",
    "sg:classifiers":[
        {
            "category":"Restaurant",
            "type":"Food & Drink"
        }
    ],
    "sg:menulink":"http://www.allmenus.com/ok/sapulpa/214038-taco-bell/menu/",
    "sg:phone":"+1 918 227 2004",
    "sg:postcode":"74066",
    "sg:province":"OK",
    "sg:tags":[
        "mexican"
    ],
    "wof:name":"Taco Bell",
    "wof:placetype":"venue"
},
  "geometry": {"coordinates":[-96.104249,35.988425],"type":"Point"}
}