{
  "type": "Feature",
  "properties": {
    "iso:country":"US",
    "sg:address":"4717 S Mingo Rd",
    "sg:city":"Tulsa",
    "sg:classifiers":[
        {
            "category":"Professional",
            "subcategory":"Accounting & Tax Preparation",
            "type":"Services"
        }
    ],
    "sg:phone":"+1 918 622 3646",
    "sg:postcode":"74146",
    "sg:province":"OK",
    "sg:tags":[
        "return",
        "filing"
    ],
    "wof:name":"KDO Professional Svc",
    "wof:placetype":"venue"
},
  "geometry": {"coordinates":[-95.86857,36.093003],"type":"Point"}
}