{
  "type": "Feature",
  "properties": {
    "iso:country":"US",
    "sg:address":"9785 State Hwy 82A",
    "sg:city":"Tahlequah",
    "sg:classifiers":[
        {
            "category":"Professional",
            "subcategory":"Accounting & Tax Preparation",
            "type":"Services"
        }
    ],
    "sg:phone":"+1 918 458 0564",
    "sg:postcode":"74464",
    "sg:province":"OK",
    "sg:tags":[
        "accountant"
    ],
    "wof:name":"Tkdintellex",
    "wof:placetype":"venue"
},
  "geometry": {"coordinates":[-94.957947,36.031328],"type":"Point"}
}