{
  "type": "Feature",
  "properties": {
    "iso:country":"US",
    "sg:address":"310 E 1st St",
    "sg:city":"Tulsa",
    "sg:classifiers":[
        {
            "category":"Bars & Pubs",
            "type":"Food & Drink"
        }
    ],
    "sg:phone":"+1 918 587 2789",
    "sg:postcode":"74120",
    "sg:province":"OK",
    "sg:tags":[
        "club",
        "night"
    ],
    "wof:name":"Studio 54",
    "wof:placetype":"venue"
},
  "geometry": {"coordinates":[-95.987436,36.156894],"type":"Point"}
}