{
  "type": "Feature",
  "properties": {
    "iso:country":"US",
    "sg:address":"3234 E 15th St",
    "sg:city":"Tulsa",
    "sg:classifiers":[
        {
            "category":"Real Estate",
            "subcategory":"Real Estate Agent",
            "type":"Services"
        }
    ],
    "sg:phone":"+1 918 749 7748",
    "sg:postcode":"74104",
    "sg:province":"OK",
    "wof:name":"Perry Properties",
    "wof:placetype":"venue"
},
  "geometry": {"coordinates":[-95.940403,36.140483],"type":"Point"}
}