{
  "type": "Feature",
  "properties": {
    "iso:country":"US",
    "sg:address":"410 S Main St",
    "sg:city":"Tulsa",
    "sg:classifiers":[
        {
            "category":"Personal",
            "subcategory":"Barber",
            "type":"Services"
        }
    ],
    "sg:phone":"+1 918 583 5510",
    "sg:postcode":"74103",
    "sg:province":"OK",
    "wof:name":"Ruby's Barber Shop",
    "wof:placetype":"venue"
},
  "geometry": {"coordinates":[-95.990258,36.1515],"type":"Point"}
}