{
  "type": "Feature",
  "properties": {
    "addr:full":"415 E Commercial St Inola OK 74036",
    "addr:housenumber":"415",
    "addr:postcode":"74036",
    "addr:street":"E Commercial St",
    "iso:country":"US",
    "sg:address":"415 E Commercial St",
    "sg:city":"Inola",
    "sg:classifiers":[
        {
            "category":"Coffee & Tea",
            "type":"Food & Drink"
        },
        {
            "category":"Bakery",
            "type":"Food & Drink"
        },
        {
            "category":"Donuts",
            "type":"Food & Drink"
        }
    ],
    "sg:menulink":"http://www.allmenus.com/ok/inola/231090-daylight-donuts/menu/",
    "sg:phone":"+1 918 543 4500",
    "sg:postcode":"74036",
    "sg:province":"OK",
    "sg:tags":[
        "american",
        "pastry"
    ],
    "wof:name":"Daylight Donuts",
    "wof:placetype":"venue"
},
  "geometry": {"coordinates":[-95.505026,36.153459],"type":"Point"}
}