{
  "type": "Feature",
  "properties": {
    "iso:country":"US",
    "sg:address":"1602 W Muskogee Ave",
    "sg:city":"Sulphur",
    "sg:classifiers":[
        {
            "category":"Freight",
            "type":"Transportation"
        }
    ],
    "sg:phone":"+1 580 622 6568",
    "sg:postcode":"73086",
    "sg:province":"OK",
    "sg:tags":[
        "courier"
    ],
    "wof:name":"Shipping Depot",
    "wof:placetype":"venue"
},
  "geometry": {"coordinates":[-96.989197,34.507718],"type":"Point"}
}