{
  "type": "Feature",
  "properties": {
    "addr:full":"3205 N Macarthur Blvd Oklahoma City OK 73122",
    "addr:housenumber":"3205",
    "addr:postcode":"73122",
    "addr:street":"N Macarthur Blvd",
    "iso:country":"US",
    "sg:address":"3205 N Macarthur Blvd",
    "sg:city":"Oklahoma City",
    "sg:classifiers":[
        {
            "category":"Personal",
            "subcategory":"Beauty Salon",
            "type":"Services"
        }
    ],
    "sg:phone":"+1 405 789 3666",
    "sg:postcode":"73122",
    "sg:province":"OK",
    "sg:tags":[
        "shop"
    ],
    "wof:name":"Exquisite Nails",
    "wof:placetype":"venue"
},
  "geometry": {"coordinates":[-97.61905400000001,35.502437],"type":"Point"}
}