{
  "type": "Feature",
  "properties": {
    "iso:country":"US",
    "sg:address":"603 SW 62nd St",
    "sg:city":"Lawton",
    "sg:classifiers":[
        {
            "category":"Manufacturing",
            "subcategory":"Signs",
            "type":"Manufacturing & Wholesale Goods"
        }
    ],
    "sg:phone":"+1 580 536 1434",
    "sg:postcode":"73505",
    "sg:province":"OK",
    "sg:tags":[
        "specialty",
        "mfg"
    ],
    "wof:name":"New Dimension Sign Works",
    "wof:placetype":"venue"
},
  "geometry": {"coordinates":[-98.468473,34.600525],"type":"Point"}
}