{
  "type": "Feature",
  "properties": {
    "iso:country":"US",
    "sg:address":"2029 S Harvard Ave",
    "sg:city":"Oklahoma City",
    "sg:classifiers":[
        {
            "category":"Manufacturing",
            "subcategory":"Textiles",
            "type":"Manufacturing & Wholesale Goods"
        }
    ],
    "sg:phone":"+1 405 680 8988",
    "sg:postcode":"73128",
    "sg:province":"OK",
    "sg:tags":[
        "imprinted"
    ],
    "wof:name":"American Promotions Inc",
    "wof:placetype":"venue"
},
  "geometry": {"coordinates":[-97.60292800000001,35.445573],"type":"Point"}
}