{
  "type": "Feature",
  "properties": {
    "addr:full":"123 E Okmulgee St Muskogee OK 74403",
    "addr:housenumber":"123",
    "addr:postcode":"74403",
    "addr:street":"E Okmulgee St",
    "iso:country":"US",
    "sg:address":"123 E Okmulgee St",
    "sg:city":"Muskogee",
    "sg:classifiers":[
        {
            "category":"Shopping",
            "subcategory":"Computers & Home Electronics",
            "type":"Retail Goods"
        }
    ],
    "sg:phone":"+1 918 683 4901",
    "sg:postcode":"74403",
    "sg:province":"OK",
    "sg:tags":[
        "tape",
        "video",
        "rental"
    ],
    "wof:name":"Sound World",
    "wof:placetype":"venue"
},
  "geometry": {"coordinates":[-95.366972,35.746862],"type":"Point"}
}