{
  "type": "Feature",
  "properties": {
    "addr:full":"3505 E Frank Phillips Blvd Bartlesville OK 74006",
    "addr:housenumber":"3505",
    "addr:postcode":"74006",
    "addr:street":"E Frank Phillips Blvd",
    "iso:country":"US",
    "sg:address":"3505 E Frank Phillips Blvd",
    "sg:city":"Bartlesville",
    "sg:classifiers":[
        {
            "category":"Restaurant",
            "type":"Food & Drink"
        }
    ],
    "sg:menulink":"http://www.allmenus.com/ok/bartlesville/236322-taco-mayo/menu/",
    "sg:phone":"+1 405 691 8226",
    "sg:postcode":"74006",
    "sg:province":"OK",
    "sg:tags":[
        "mexican"
    ],
    "wof:name":"Taco Mayo",
    "wof:placetype":"venue"
},
  "geometry": {"coordinates":[-95.93964099999999,36.750675],"type":"Point"}
}