{
  "type": "Feature",
  "properties": {
    "addr:full":"1901 NW Expy Oklahoma City OK 73118",
    "addr:housenumber":"1901",
    "addr:postcode":"73118",
    "addr:street":"Nw Expy",
    "iso:country":"US",
    "sg:address":"1901 NW Expy",
    "sg:city":"Oklahoma City",
    "sg:classifiers":[
        {
            "category":"Shopping",
            "subcategory":"Clothing, Apparel, & Fashions",
            "type":"Retail Goods"
        }
    ],
    "sg:phone":"+1 405 842 5449",
    "sg:postcode":"73118",
    "sg:province":"OK",
    "wof:name":"Hot Topic",
    "wof:placetype":"venue"
},
  "geometry": {"coordinates":[-97.54491,35.52257],"type":"Point"}
}