{
  "type": "Feature",
  "properties": {
    "iso:country":"US",
    "sg:address":"500 Frisco Ave",
    "sg:city":"Clinton",
    "sg:classifiers":[
        {
            "category":"Shopping",
            "subcategory":"Gifts & Souvenirs",
            "type":"Retail Goods"
        }
    ],
    "sg:phone":"+1 580 323 2289",
    "sg:postcode":"73601",
    "sg:province":"OK",
    "wof:name":"Gift Gallery",
    "wof:placetype":"venue"
},
  "geometry": {"coordinates":[-98.96597,35.514368],"type":"Point"}
}