{
  "type": "Feature",
  "properties": {
    "addr:full":"8121 S Western Ave Oklahoma City OK 73139",
    "addr:housenumber":"8121",
    "addr:postcode":"73139",
    "addr:street":"S Western Ave",
    "iso:country":"US",
    "sg:address":"8121 S Western Ave",
    "sg:city":"Oklahoma City",
    "sg:classifiers":[
        {
            "category":"Insurance",
            "subcategory":"Insurance Agent",
            "type":"Services"
        }
    ],
    "sg:phone":"+1 405 636 1536",
    "sg:postcode":"73139",
    "sg:province":"OK",
    "sg:tags":[
        "broker"
    ],
    "wof:name":"Farmers Insurance",
    "wof:placetype":"venue"
},
  "geometry": {"coordinates":[-97.530192,35.385734],"type":"Point"}
}