{
  "type": "Feature",
  "properties": {
    "addr:full":"1125 N Maitlen Dr Cushing OK 74023",
    "addr:housenumber":"1125",
    "addr:postcode":"74023",
    "addr:street":"N Maitlen Dr",
    "iso:country":"US",
    "sg:address":"1125 N Maitlen Dr",
    "sg:city":"Cushing",
    "sg:classifiers":[
        {
            "category":"Manufacturing",
            "subcategory":"Tools & Machinery",
            "type":"Manufacturing & Wholesale Goods"
        }
    ],
    "sg:phone":"+1 918 225 7000",
    "sg:postcode":"74023",
    "sg:province":"OK",
    "sg:tags":[
        "manufacture",
        "for",
        "dredge",
        "sale",
        "rent",
        "or",
        "lease"
    ],
    "wof:name":"V M I Inc",
    "wof:placetype":"venue"
},
  "geometry": {"coordinates":[-96.745195,35.9897],"type":"Point"}
}