{
  "type": "Feature",
  "properties": {
    "addr:full":"1339 N Lansing Ave Tulsa OK 74106",
    "addr:housenumber":"1339",
    "addr:postcode":"74106",
    "addr:street":"N Lansing Ave",
    "iso:country":"US",
    "sg:address":"1339 N Lansing Ave",
    "sg:city":"Tulsa",
    "sg:classifiers":[
        {
            "category":"Building & Trades",
            "subcategory":"Construction",
            "type":"Services"
        }
    ],
    "sg:phone":"+1 918 582 2033",
    "sg:postcode":"74106",
    "sg:province":"OK",
    "sg:tags":[
        "development",
        "real estate"
    ],
    "wof:name":"Next American Development LLC",
    "wof:placetype":"venue"
},
  "geometry": {"coordinates":[-95.980554,36.174504],"type":"Point"}
}