{
  "type": "Feature",
  "properties": {
    "iso:country":"US",
    "sg:address":"4404 S Gary Ave",
    "sg:city":"Tulsa",
    "sg:classifiers":[
        {
            "category":"Shopping",
            "subcategory":"Beauty & Cosmetics",
            "type":"Retail Goods"
        }
    ],
    "sg:phone":"+1 918 743 1731",
    "sg:postcode":"74105",
    "sg:province":"OK",
    "sg:tags":[
        "equipment",
        "perfume",
        "supply"
    ],
    "wof:name":"Mary Kay Cosmetics",
    "wof:placetype":"venue"
},
  "geometry": {"coordinates":[-95.94178100000001,36.101061],"type":"Point"}
}