{
  "type": "Feature",
  "properties": {
    "iso:country":"US",
    "sg:address":"1123 NW Cherry Ave",
    "sg:city":"Lawton",
    "sg:classifiers":[
        {
            "category":"Health Services",
            "subcategory":"Dentist",
            "type":"Services"
        }
    ],
    "sg:phone":"+1 580 353 5277",
    "sg:postcode":"73507",
    "sg:province":"OK",
    "wof:name":"Frank S Wamsley",
    "wof:placetype":"venue"
},
  "geometry": {"coordinates":[-98.406688,34.619341],"type":"Point"}
}