{
  "type": "Feature",
  "properties": {
    "iso:country":"US",
    "sg:address":"1634 SW 29th St",
    "sg:city":"Oklahoma City",
    "sg:classifiers":[
        {
            "category":"Autos & Motor Vehicles",
            "subcategory":"Automobile Sales",
            "type":"Retail Goods"
        }
    ],
    "sg:phone":"+1 405 616 0084",
    "sg:postcode":"73119",
    "sg:province":"OK",
    "sg:tags":[
        "truck"
    ],
    "wof:name":"Fiesta Auto Plaza",
    "wof:placetype":"venue"
},
  "geometry": {"coordinates":[-97.546863,35.435132],"type":"Point"}
}