{
  "type": "Feature",
  "properties": {
    "iso:country":"US",
    "sg:address":"7 E Choctaw Ave",
    "sg:city":"Mcalester",
    "sg:classifiers":[
        {
            "category":"Professional",
            "subcategory":"Management & Consulting",
            "type":"Services"
        }
    ],
    "sg:phone":"+1 918 423 2479",
    "sg:postcode":"74501",
    "sg:province":"OK",
    "sg:tags":[
        "development",
        "economic",
        "agency"
    ],
    "wof:name":"Ouachita Mountains Resource",
    "wof:placetype":"venue"
},
  "geometry": {"coordinates":[-95.769606,34.932304],"type":"Point"}
}