{
  "type": "Feature",
  "properties": {
    "iso:country":"US",
    "sg:address":"8539 N Rockwell Ave",
    "sg:city":"Oklahoma City",
    "sg:classifiers":[
        {
            "category":"Shopping",
            "subcategory":"Clothing, Apparel, & Fashions",
            "type":"Retail Goods"
        }
    ],
    "sg:phone":"+1 405 728 9401",
    "sg:postcode":"73132",
    "sg:province":"OK",
    "wof:name":"Cato",
    "wof:placetype":"venue"
},
  "geometry": {"coordinates":[-97.63847699999999,35.555212],"type":"Point"}
}