{
  "type": "Feature",
  "properties": {
    "iso:country":"US",
    "sg:address":"108 NE 11th St",
    "sg:city":"Guymon",
    "sg:classifiers":[
        {
            "category":"Personal",
            "subcategory":"Beauty Salon",
            "type":"Services"
        }
    ],
    "sg:phone":"+1 580 338 5222",
    "sg:postcode":"73942",
    "sg:province":"OK",
    "wof:name":"Hair Benders",
    "wof:placetype":"venue"
},
  "geometry": {"coordinates":[-101.48148500000001,36.68901],"type":"Point"}
}