{
  "type": "Feature",
  "properties": {
    "iso:country":"US",
    "sg:address":"7 E 2nd St",
    "sg:city":"Tulsa",
    "sg:classifiers":[
        {
            "category":"Health Services",
            "subcategory":"Doctor",
            "type":"Services"
        }
    ],
    "sg:phone":"+1 918 573 8990",
    "sg:postcode":"74103",
    "sg:province":"OK",
    "sg:tags":[
        "physician",
        "surgeon"
    ],
    "wof:name":"Warren Clinic",
    "wof:placetype":"venue"
},
  "geometry": {"coordinates":[-95.98924,36.155231],"type":"Point"}
}