{
  "type": "Feature",
  "properties": {
    "addr:full":"422 W Madison St Mangum OK 73554",
    "addr:housenumber":"422",
    "addr:postcode":"73554",
    "addr:street":"W Madison St",
    "iso:country":"US",
    "sg:address":"422 W Madison St",
    "sg:city":"Mangum",
    "sg:classifiers":[
        {
            "category":"Farming",
            "subcategory":"Farm & Veterinary Services",
            "type":"Manufacturing & Wholesale Goods"
        }
    ],
    "sg:phone":"+1 580 782 2570",
    "sg:postcode":"73554",
    "sg:province":"OK",
    "sg:tags":[
        "crop",
        "harvesting"
    ],
    "wof:name":"Kenneth Paul Slaton",
    "wof:placetype":"venue"
},
  "geometry": {"coordinates":[-99.510965,34.882093],"type":"Point"}
}