{
  "type": "Feature",
  "properties": {
    "iso:country":"US",
    "sg:address":"7944 E 41st St",
    "sg:city":"Tulsa",
    "sg:classifiers":[
        {
            "category":"Wholesale",
            "subcategory":"Painting Supplies",
            "type":"Manufacturing & Wholesale Goods"
        }
    ],
    "sg:phone":"+1 918 664 6044",
    "sg:postcode":"74145",
    "sg:province":"OK",
    "wof:name":"Keagys Paint Supply Inc",
    "wof:placetype":"venue"
},
  "geometry": {"coordinates":[-95.887004,36.104347],"type":"Point"}
}