{
  "type": "Feature",
  "properties": {
    "iso:country":"US",
    "sg:address":"1077 N Harrah Rd",
    "sg:city":"Harrah",
    "sg:classifiers":[
        {
            "category":"Restaurant",
            "type":"Food & Drink"
        }
    ],
    "sg:phone":"+1 405 454 6545",
    "sg:postcode":"73045",
    "sg:province":"OK",
    "sg:tags":[
        "eating"
    ],
    "wof:name":"Harrah Steakhouse",
    "wof:placetype":"venue"
},
  "geometry": {"coordinates":[-97.159196,35.478205],"type":"Point"}
}