{
  "type": "Feature",
  "properties": {
    "addr:full":"3413 N Flamingo Ave Bethany OK 73008",
    "addr:housenumber":"3413",
    "addr:postcode":"73008",
    "addr:street":"N Flamingo Ave",
    "iso:country":"US",
    "sg:address":"3413 N Flamingo Ave",
    "sg:city":"Bethany",
    "sg:classifiers":[
        {
            "category":"Freight",
            "type":"Transportation"
        }
    ],
    "sg:phone":"+1 405 789 0450",
    "sg:postcode":"73008",
    "sg:province":"OK",
    "sg:tags":[
        "dry",
        "bulk",
        "trucking"
    ],
    "wof:name":"Petro-Chemical Transport Inc",
    "wof:placetype":"venue"
},
  "geometry": {"coordinates":[-97.64606000000001,35.506824],"type":"Point"}
}