{
  "type": "Feature",
  "properties": {
    "iso:country":"US",
    "sg:address":"1009 E 13th St",
    "sg:city":"Okmulgee",
    "sg:classifiers":[
        {
            "category":"Retail",
            "subcategory":"Auto Repair",
            "type":"Services"
        }
    ],
    "sg:phone":"+1 918 756 0930",
    "sg:postcode":"74447",
    "sg:province":"OK",
    "sg:tags":[
        "repairing",
        "automobile"
    ],
    "wof:name":"Ledbetter Automotive",
    "wof:placetype":"venue"
},
  "geometry": {"coordinates":[-95.96009599999999,35.615896],"type":"Point"}
}