{
  "type": "Feature",
  "properties": {
    "addr:full":"1326 N 7th St Duncan OK 73533",
    "addr:housenumber":"1326",
    "addr:postcode":"73533",
    "addr:street":"N 7Th St",
    "iso:country":"US",
    "sg:address":"1326 N 7th St",
    "sg:city":"Duncan",
    "sg:classifiers":[
        {
            "category":"Shopping",
            "subcategory":"Beauty & Cosmetics",
            "type":"Retail Goods"
        }
    ],
    "sg:phone":"+1 580 252 4140",
    "sg:postcode":"73533",
    "sg:province":"OK",
    "sg:tags":[
        "merchandise"
    ],
    "wof:name":"Mary Kay Cos",
    "wof:placetype":"venue"
},
  "geometry": {"coordinates":[-97.953153,34.518186],"type":"Point"}
}