{
  "type": "Feature",
  "properties": {
    "iso:country":"US",
    "sg:address":"2308 E 6th Ave",
    "sg:city":"Stillwater",
    "sg:classifiers":[
        {
            "category":"Retail",
            "subcategory":"Auto Repair",
            "type":"Services"
        }
    ],
    "sg:phone":"+1 405 372 6666",
    "sg:postcode":"74074",
    "sg:province":"OK",
    "sg:tags":[
        "automotive",
        "gasoline",
        "general"
    ],
    "wof:name":"AAA Towing",
    "wof:placetype":"venue"
},
  "geometry": {"coordinates":[-97.027994,36.116118],"type":"Point"}
}