{
  "type": "Feature",
  "properties": {
    "iso:country":"US",
    "sg:address":"406 Davis St",
    "sg:city":"Paoli",
    "sg:classifiers":[
        {
            "category":"Government",
            "subcategory":"Police Station",
            "type":"Public Place"
        }
    ],
    "sg:phone":"+1 405 000 1111",
    "sg:postcode":"73074",
    "sg:province":"OK",
    "sg:tags":[
        "department"
    ],
    "wof:name":"Lone Grove Police Dept",
    "wof:placetype":"venue"
},
  "geometry": {"coordinates":[-97.263281,34.826224],"type":"Point"}
}