{
  "type": "Feature",
  "properties": {
    "addr:full":"302 N Independence Ave Enid OK 73701",
    "addr:housenumber":"302",
    "addr:postcode":"73701",
    "addr:street":"N Independence Ave",
    "iso:country":"US",
    "sg:address":"302 N Independence Ave",
    "sg:city":"Enid",
    "sg:classifiers":[
        {
            "category":"Restaurant",
            "type":"Food & Drink"
        }
    ],
    "sg:phone":"+1 580 233 5051",
    "sg:postcode":"73701",
    "sg:province":"OK",
    "wof:name":"Marilyn K's",
    "wof:placetype":"venue"
},
  "geometry": {"coordinates":[-97.87997900000001,36.40012],"type":"Point"}
}