{
  "type": "Feature",
  "properties": {
    "iso:country":"US",
    "sg:address":"621 SW D Ave",
    "sg:city":"Lawton",
    "sg:classifiers":[
        {
            "category":"Professional",
            "subcategory":"Lawyer & Legal Services",
            "type":"Services"
        }
    ],
    "sg:phone":"+1 580 248 4675",
    "sg:postcode":"73501",
    "sg:province":"OK",
    "sg:tags":[
        "attorney"
    ],
    "wof:name":"Legal Aid Of Western Ok Inc",
    "wof:placetype":"venue"
},
  "geometry": {"coordinates":[-98.398128,34.604107],"type":"Point"}
}