{
  "type": "Feature",
  "properties": {
    "addr:full":"116 N 9th St Clinton OK 73601",
    "addr:housenumber":"116",
    "addr:postcode":"73601",
    "addr:street":"N 9Th St",
    "iso:country":"US",
    "sg:address":"116 N 9th St",
    "sg:city":"Clinton",
    "sg:classifiers":[
        {
            "category":"Insurance",
            "subcategory":"Insurance Agent",
            "type":"Services"
        }
    ],
    "sg:phone":"+1 580 323 3216",
    "sg:postcode":"73601",
    "sg:province":"OK",
    "sg:tags":[
        "adjuster"
    ],
    "wof:name":"Southwest Adjustment Co",
    "wof:placetype":"venue"
},
  "geometry": {"coordinates":[-98.970877,35.514728],"type":"Point"}
}