{
  "type": "Feature",
  "properties": {
    "iso:country":"US",
    "sg:address":"903 Willow St",
    "sg:city":"S Coffeyville",
    "sg:classifiers":[
        {
            "category":"Wholesale",
            "subcategory":"Farm Supplies",
            "type":"Manufacturing & Wholesale Goods"
        }
    ],
    "sg:phone":"+1 918 255 6200",
    "sg:postcode":"74072",
    "sg:province":"OK",
    "sg:tags":[
        "auction",
        "livestock",
        "market"
    ],
    "wof:name":"South Coffeyville Stockyard",
    "wof:placetype":"venue"
},
  "geometry": {"coordinates":[-95.620364,36.989279],"type":"Point"}
}