{
  "type": "Feature",
  "properties": {
    "iso:country":"US",
    "sg:address":"2025 S Santa Fe Ave",
    "sg:city":"Oklahoma City",
    "sg:classifiers":[
        {
            "category":"Autos & Motor Vehicles",
            "subcategory":"Automobile Sales",
            "type":"Retail Goods"
        }
    ],
    "sg:phone":"+1 405 760 4000",
    "sg:postcode":"73109",
    "sg:province":"OK",
    "sg:tags":[
        "car",
        "dealer"
    ],
    "wof:name":"Auto Group Of Okc",
    "wof:placetype":"venue"
},
  "geometry": {"coordinates":[-97.512536,35.446877],"type":"Point"}
}