{
  "type": "Feature",
  "properties": {
    "addr:full":"1820 W Lindsey St Norman OK 73069",
    "addr:housenumber":"1820",
    "addr:postcode":"73069",
    "addr:street":"W Lindsey St",
    "iso:country":"US",
    "sg:address":"1820 W Lindsey St",
    "sg:city":"Norman",
    "sg:classifiers":[
        {
            "category":"Restaurant",
            "type":"Food & Drink"
        }
    ],
    "sg:phone":"+1 405 366 7579",
    "sg:postcode":"73069",
    "sg:province":"OK",
    "wof:name":"Taco Bueno",
    "wof:placetype":"venue"
},
  "geometry": {"coordinates":[-97.468588,35.203835],"type":"Point"}
}