{
  "type": "Feature",
  "properties": {
    "addr:full":"808 E Taft Ave Sapulpa OK 74066",
    "addr:housenumber":"808",
    "addr:postcode":"74066",
    "addr:street":"E Taft Ave",
    "iso:country":"US",
    "sg:address":"808 E Taft Ave",
    "sg:city":"Sapulpa",
    "sg:classifiers":[
        {
            "category":"Shopping",
            "subcategory":"Used Merchandise",
            "type":"Retail Goods"
        }
    ],
    "sg:phone":"+1 918 248 4565",
    "sg:postcode":"74066",
    "sg:province":"OK",
    "sg:tags":[
        "clothing"
    ],
    "wof:name":"Magic Hanger",
    "wof:placetype":"venue"
},
  "geometry": {"coordinates":[-96.102316,35.988293],"type":"Point"}
}