{
  "type": "Feature",
  "properties": {
    "iso:country":"US",
    "sg:address":"300 E Hill St",
    "sg:city":"Oklahoma City",
    "sg:classifiers":[
        {
            "category":"Wholesale",
            "subcategory":"Machinery & Supplies",
            "type":"Manufacturing & Wholesale Goods"
        }
    ],
    "sg:phone":"+1 405 525 6205",
    "sg:postcode":"73105",
    "sg:province":"OK",
    "sg:tags":[
        "casket"
    ],
    "wof:name":"Newmark of Oklahoma",
    "wof:placetype":"venue"
},
  "geometry": {"coordinates":[-97.50371,35.503085],"type":"Point"}
}