{
  "type": "Feature",
  "properties": {
    "iso:country":"US",
    "sg:address":"7613 N Classen Blvd",
    "sg:city":"Oklahoma City",
    "sg:classifiers":[
        {
            "category":"Building & Trades",
            "subcategory":"Construction",
            "type":"Services"
        }
    ],
    "sg:phone":"+1 405 840 2521",
    "sg:postcode":"73116",
    "sg:province":"OK",
    "sg:tags":[
        "general",
        "contractor"
    ],
    "sg:website":"www.timberlakeconstruction.com",
    "wof:name":"Timberlake Construction Co",
    "wof:placetype":"venue"
},
  "geometry": {"coordinates":[-97.527626,35.551114],"type":"Point"}
}