{
  "type": "Feature",
  "properties": {
    "addr:full":"1219 8th St Woodward OK 73801",
    "addr:housenumber":"1219",
    "addr:postcode":"73801",
    "addr:street":"8Th St",
    "iso:country":"US",
    "sg:address":"1219 8th St",
    "sg:city":"Woodward",
    "sg:classifiers":[
        {
            "category":"Recreation",
            "type":"Entertainment"
        }
    ],
    "sg:phone":"+1 580 254 8548",
    "sg:postcode":"73801",
    "sg:province":"OK",
    "sg:tags":[
        "pool",
        "swimming"
    ],
    "wof:name":"Woodward Swimming Pool",
    "wof:placetype":"venue"
},
  "geometry": {"coordinates":[-99.389455,36.434592],"type":"Point"}
}