{
  "type": "Feature",
  "properties": {
    "iso:country":"US",
    "sg:address":"2530 S Robinson Ave",
    "sg:city":"Oklahoma City",
    "sg:classifiers":[
        {
            "category":"Shopping",
            "subcategory":"Used Merchandise",
            "type":"Retail Goods"
        }
    ],
    "sg:phone":"+1 405 232 1513",
    "sg:postcode":"73109",
    "sg:province":"OK",
    "wof:name":"El Ranchito",
    "wof:placetype":"venue"
},
  "geometry": {"coordinates":[-97.516034,35.439738],"type":"Point"}
}