{
  "type": "Feature",
  "properties": {
    "iso:country":"US",
    "sg:address":"1115 N Utica Ave",
    "sg:city":"Tulsa",
    "sg:classifiers":[
        {
            "category":"Wholesale",
            "subcategory":"Machinery & Supplies",
            "type":"Manufacturing & Wholesale Goods"
        },
        {
            "category":"Manufacturing",
            "subcategory":"Metals",
            "type":"Manufacturing & Wholesale Goods"
        }
    ],
    "sg:phone":"+1 918 583 0171",
    "sg:postcode":"74110",
    "sg:province":"OK",
    "sg:tags":[
        "steel",
        "industrial",
        "mfg",
        "spring",
        "wire",
        "fab"
    ],
    "sg:website":"www.gardnerspring.com",
    "wof:name":"Gardner Spring Inc",
    "wof:placetype":"venue"
},
  "geometry": {"coordinates":[-95.967142,36.169879],"type":"Point"}
}