{
  "type": "Feature",
  "properties": {
    "iso:country":"US",
    "sg:address":"3930 S Granite Ave",
    "sg:city":"Tulsa",
    "sg:classifiers":[
        {
            "category":"Travel",
            "subcategory":"Travel Agent",
            "type":"Entertainment"
        }
    ],
    "sg:phone":"+1 918 622 7824",
    "sg:postcode":"74135",
    "sg:province":"OK",
    "sg:tags":[
        "agency"
    ],
    "wof:name":"Active Associate Independant",
    "wof:placetype":"venue"
},
  "geometry": {"coordinates":[-95.913788,36.10744],"type":"Point"}
}