{
  "type": "Feature",
  "properties": {
    "addr:full":"12330 SE 29th St Choctaw OK 73020",
    "addr:postcode":"12330;73020",
    "addr:street":"Se 29Th St",
    "iso:country":"US",
    "sg:address":"12330 SE 29th St",
    "sg:city":"Choctaw",
    "sg:classifiers":[
        {
            "category":"Real Estate",
            "subcategory":"Real Estate Agent",
            "type":"Services"
        }
    ],
    "sg:phone":"+1 405 733 7667",
    "sg:postcode":"73020",
    "sg:province":"OK",
    "wof:name":"Ronald Carlton Barton",
    "wof:placetype":"venue"
},
  "geometry": {"coordinates":[-97.30191600000001,35.435433],"type":"Point"}
}