{
  "type": "Feature",
  "properties": {
    "addr:full":"4908 W 51st St Tulsa OK 74107",
    "addr:housenumber":"4908",
    "addr:postcode":"74107",
    "addr:street":"W 51St St",
    "iso:country":"US",
    "sg:address":"4908 W 51st St",
    "sg:city":"Tulsa",
    "sg:classifiers":[
        {
            "category":"Restaurant",
            "type":"Food & Drink"
        }
    ],
    "sg:phone":"+1 918 447 1015",
    "sg:postcode":"74107",
    "sg:province":"OK",
    "wof:name":"Taquito House",
    "wof:placetype":"venue"
},
  "geometry": {"coordinates":[-96.05040200000001,36.089846],"type":"Point"}
}