{
  "type": "Feature",
  "properties": {
    "iso:country":"US",
    "sg:address":"9208 E Admiral Ct",
    "sg:city":"Tulsa",
    "sg:classifiers":[
        {
            "category":"Manufacturing",
            "subcategory":"Metals",
            "type":"Manufacturing & Wholesale Goods"
        }
    ],
    "sg:phone":"+1 918 835 1482",
    "sg:postcode":"74115",
    "sg:province":"OK",
    "wof:name":"Century Plating Inc",
    "wof:placetype":"venue"
},
  "geometry": {"coordinates":[-95.8733,36.161709],"type":"Point"}
}