{
  "type": "Feature",
  "properties": {
    "iso:country":"US",
    "sg:address":"7302 S Shelby Ln",
    "sg:city":"Broken Arrow",
    "sg:phone":"+1 918 357 3181",
    "sg:postcode":"74014",
    "sg:province":"OK",
    "sg:tags":[
        "distributor",
        "oil",
        "marketer"
    ],
    "wof:name":"Mustang Oil Inc",
    "wof:placetype":"venue"
},
  "geometry": {"coordinates":[-95.71373800000001,36.056963],"type":"Point"}
}