{
  "type": "Feature",
  "properties": {
    "iso:country":"US",
    "sg:address":"10840 N Pennsylvania Ave",
    "sg:city":"Oklahoma City",
    "sg:classifiers":[
        {
            "category":"Food & Beverages",
            "subcategory":"Groceries & Convenience Stores",
            "type":"Retail Goods"
        }
    ],
    "sg:phone":"+1 405 751 6660",
    "sg:postcode":"73120",
    "sg:province":"OK",
    "wof:name":"Village Quality Food Inc",
    "wof:placetype":"venue"
},
  "geometry": {"coordinates":[-97.549224,35.578855],"type":"Point"}
}