{
  "type": "Feature",
  "properties": {
    "iso:country":"US",
    "sg:address":"1123 SW 59th St",
    "sg:city":"Oklahoma City",
    "sg:classifiers":[
        {
            "category":"Professional",
            "subcategory":"Employment Agencies",
            "type":"Services"
        }
    ],
    "sg:phone":"+1 405 634 9885",
    "sg:postcode":"73109",
    "sg:province":"OK",
    "sg:tags":[
        "help",
        "contractor"
    ],
    "wof:name":"Alternative Labor Resources",
    "wof:placetype":"venue"
},
  "geometry": {"coordinates":[-97.536507,35.406301],"type":"Point"}
}