{
  "type": "Feature",
  "properties": {
    "addr:full":"291 SE 3rd St Lindsay OK 73052",
    "addr:housenumber":"291",
    "addr:postcode":"73052",
    "addr:street":"Se 3Rd St",
    "iso:country":"US",
    "sg:address":"291 SE 3rd St",
    "sg:city":"Lindsay",
    "sg:classifiers":[
        {
            "category":"Mining & Drilling",
            "type":"Manufacturing & Wholesale Goods"
        }
    ],
    "sg:phone":"+1 405 756 4440",
    "sg:postcode":"73052",
    "sg:province":"OK",
    "sg:tags":[
        "field",
        "oil"
    ],
    "wof:name":"Test Tanks LLC",
    "wof:placetype":"venue"
},
  "geometry": {"coordinates":[-97.599867,34.8347],"type":"Point"}
}