{
  "type": "Feature",
  "properties": {
    "addr:full":"1011 S 30th St Enid OK 73701",
    "addr:housenumber":"1011",
    "addr:postcode":"73701",
    "addr:street":"S 30Th St",
    "iso:country":"US",
    "sg:address":"1011 S 30th St",
    "sg:city":"Enid",
    "sg:classifiers":[
        {
            "category":"Real Estate",
            "subcategory":"Real Estate Operator",
            "type":"Services"
        }
    ],
    "sg:phone":"+1 580 233 5336",
    "sg:postcode":"73701",
    "sg:province":"OK",
    "sg:tags":[
        "apartment"
    ],
    "wof:name":"Pine Manor Apartments",
    "wof:placetype":"venue"
},
  "geometry": {"coordinates":[-97.836862,36.376251],"type":"Point"}
}