{
  "type": "Feature",
  "properties": {
    "iso:country":"US",
    "sg:address":"8500 E 106th St N",
    "sg:city":"Owasso",
    "sg:classifiers":[
        {
            "category":"Farming",
            "subcategory":"Livestock Farm",
            "type":"Manufacturing & Wholesale Goods"
        }
    ],
    "sg:phone":"+1 918 272 1844",
    "sg:postcode":"74055",
    "sg:province":"OK",
    "sg:tags":[
        "beef",
        "feedlot",
        "cattle"
    ],
    "wof:name":"Carl Worley",
    "wof:placetype":"venue"
},
  "geometry": {"coordinates":[-95.884125,36.307408],"type":"Point"}
}