{
  "type": "Feature",
  "properties": {
    "iso:country":"US",
    "sg:address":"3633 NW 39th St",
    "sg:city":"Oklahoma City",
    "sg:classifiers":[
        {
            "category":"Shopping",
            "subcategory":"Bicycles & Sporting Goods",
            "type":"Retail Goods"
        }
    ],
    "sg:phone":"+1 405 943 9997",
    "sg:postcode":"73112",
    "sg:province":"OK",
    "sg:website":"www.outdoor-outfitters.com",
    "wof:name":"Outdoor Outfitters",
    "wof:placetype":"venue"
},
  "geometry": {"coordinates":[-97.581585,35.511384],"type":"Point"}
}