{
  "type": "Feature",
  "properties": {
    "addr:full":"2331 SE 15th St Oklahoma City OK 73129",
    "addr:housenumber":"2331",
    "addr:postcode":"73129",
    "addr:street":"Se 15Th St",
    "iso:country":"US",
    "sg:address":"2331 SE 15th St",
    "sg:city":"Oklahoma City",
    "sg:classifiers":[
        {
            "category":"Food & Beverages",
            "subcategory":"Groceries & Convenience Stores",
            "type":"Retail Goods"
        }
    ],
    "sg:phone":"+1 405 619 1833",
    "sg:postcode":"73129",
    "sg:province":"OK",
    "wof:name":"Speedy Food Mart",
    "wof:placetype":"venue"
},
  "geometry": {"coordinates":[-97.470395,35.449873],"type":"Point"}
}