{
  "type": "Feature",
  "properties": {
    "addr:full":"8321 E 41st St Tulsa OK 74145",
    "addr:housenumber":"8321",
    "addr:postcode":"74145",
    "addr:street":"E 41St St",
    "iso:country":"US",
    "sg:address":"8321 E 41st St",
    "sg:city":"Tulsa",
    "sg:classifiers":[
        {
            "category":"Banks & Credit Unions",
            "subcategory":"Bank",
            "type":"Services"
        },
        {
            "category":"Banks & Credit Unions",
            "subcategory":"Financial Services",
            "type":"Services"
        }
    ],
    "sg:phone":"+1 918 280 7959",
    "sg:postcode":"74145",
    "sg:province":"OK",
    "sg:tags":[
        "saving",
        "loan",
        "commercial"
    ],
    "wof:name":"Chase",
    "wof:placetype":"venue"
},
  "geometry": {"coordinates":[-95.88217,36.104431],"type":"Point"}
}