{
  "type": "Feature",
  "properties": {
    "iso:country":"US",
    "sg:address":"240 E Apache St",
    "sg:city":"Tulsa",
    "sg:classifiers":[
        {
            "category":"Social Services",
            "type":"Services"
        }
    ],
    "sg:phone":"+1 918 584 1117",
    "sg:postcode":"74106",
    "sg:province":"OK",
    "sg:tags":[
        "organization",
        "welfare"
    ],
    "wof:name":"Save Our Babies Outreach",
    "wof:placetype":"venue"
},
  "geometry": {"coordinates":[-95.989699,36.191366],"type":"Point"}
}