{
  "type": "Feature",
  "properties": {
    "addr:full":"20 N Urbana Ave Tulsa OK 74115",
    "addr:housenumber":"20",
    "addr:postcode":"74115",
    "addr:street":"N Urbana Ave",
    "iso:country":"US",
    "sg:address":"20 N Urbana Ave",
    "sg:city":"Tulsa",
    "sg:classifiers":[
        {
            "category":"Building & Trades",
            "subcategory":"Construction",
            "type":"Services"
        }
    ],
    "sg:phone":"+1 918 836 1274",
    "sg:postcode":"74115",
    "sg:province":"OK",
    "sg:tags":[
        "floor",
        "laying",
        "contractor"
    ],
    "wof:name":"Woodfloor Specials",
    "wof:placetype":"venue"
},
  "geometry": {"coordinates":[-95.925642,36.160512],"type":"Point"}
}