{
  "type": "Feature",
  "properties": {
    "addr:full":"1211 N Shartel Ave Oklahoma City OK 73103",
    "addr:housenumber":"1211",
    "addr:postcode":"73103",
    "addr:street":"N Shartel Ave",
    "iso:country":"US",
    "sg:address":"1211 N Shartel Ave",
    "sg:city":"Oklahoma City",
    "sg:classifiers":[
        {
            "category":"Health Services",
            "subcategory":"Doctor",
            "type":"Services"
        }
    ],
    "sg:phone":"+1 405 232 4211",
    "sg:postcode":"73103",
    "sg:province":"OK",
    "sg:tags":[
        "physician",
        "surgeon"
    ],
    "wof:name":"General Surgeons Of Ok",
    "wof:placetype":"venue"
},
  "geometry": {"coordinates":[-97.525654,35.481119],"type":"Point"}
}