{
  "type": "Feature",
  "properties": {
    "addr:full":"8445 S Florence Ave Tulsa OK 74137",
    "addr:housenumber":"8445",
    "addr:postcode":"74137",
    "addr:street":"S Florence Ave",
    "iso:country":"US",
    "sg:address":"8445 S Florence Ave",
    "sg:city":"Tulsa",
    "sg:classifiers":[
        {
            "category":"Personal",
            "type":"Services"
        }
    ],
    "sg:phone":"+1 918 495 3623",
    "sg:postcode":"74137",
    "sg:province":"OK",
    "wof:name":"Body Therapy",
    "wof:placetype":"venue"
},
  "geometry": {"coordinates":[-95.943866,36.041152],"type":"Point"}
}