{
  "type": "Feature",
  "properties": {
    "addr:full":"517 E Broadway Allen OK 74825",
    "addr:housenumber":"517",
    "addr:postcode":"74825",
    "addr:street":"E Broadway",
    "iso:country":"US",
    "sg:address":"517 E Broadway",
    "sg:city":"Allen",
    "sg:classifiers":[
        {
            "category":"Organizations",
            "subcategory":"Religious Organization",
            "type":"Services"
        }
    ],
    "sg:phone":"+1 580 857 2791",
    "sg:postcode":"74825",
    "sg:province":"OK",
    "sg:tags":[
        "church"
    ],
    "wof:name":"Allen Assembly Of God",
    "wof:placetype":"venue"
},
  "geometry": {"coordinates":[-96.411126,34.878434],"type":"Point"}
}