{
  "type": "Feature",
  "properties": {
    "addr:full":"15900 Vintage Dr Edmond OK 73013",
    "addr:housenumber":"15900",
    "addr:postcode":"73013",
    "addr:street":"Vintage Dr",
    "iso:country":"US",
    "sg:address":"15900 Vintage Dr",
    "sg:city":"Edmond",
    "sg:classifiers":[
        {
            "category":"Insurance",
            "subcategory":"Insurance Agent",
            "type":"Services"
        }
    ],
    "sg:phone":"+1 405 720 1540",
    "sg:postcode":"73013",
    "sg:province":"OK",
    "wof:name":"Rineharts Insurance Agency",
    "wof:placetype":"venue"
},
  "geometry": {"coordinates":[-97.548844,35.63301],"type":"Point"}
}