{
  "type": "Feature",
  "properties": {
    "iso:country":"US",
    "sg:address":"927 Arlington St",
    "sg:city":"Ada",
    "sg:classifiers":[
        {
            "category":"Shopping",
            "subcategory":"Computers & Home Electronics",
            "type":"Retail Goods"
        }
    ],
    "sg:phone":"+1 580 436 3080",
    "sg:postcode":"74820",
    "sg:province":"OK",
    "sg:tags":[
        "prep"
    ],
    "wof:name":"Computer Options",
    "wof:placetype":"venue"
},
  "geometry": {"coordinates":[-96.664672,34.78158],"type":"Point"}
}