{
  "type": "Feature",
  "properties": {
    "addr:full":"1709 Southwest Blvd Tulsa OK 74107",
    "addr:housenumber":"1709",
    "addr:postcode":"74107",
    "addr:street":"Southwest Blvd",
    "iso:country":"US",
    "sg:address":"1709 Southwest Blvd",
    "sg:city":"Tulsa",
    "sg:classifiers":[
        {
            "category":"Restaurant",
            "type":"Food & Drink"
        }
    ],
    "sg:phone":"+1 918 587 0808",
    "sg:postcode":"74107",
    "sg:province":"OK",
    "sg:tags":[
        "eating"
    ],
    "wof:name":"Fortune Star Chinese Rest",
    "wof:placetype":"venue"
},
  "geometry": {"coordinates":[-96.006865,36.137052],"type":"Point"}
}