{
  "type": "Feature",
  "properties": {
    "addr:full":"3606 E 103rd St Tulsa OK 74137",
    "addr:housenumber":"3606",
    "addr:postcode":"74137",
    "addr:street":"E 103Rd St",
    "iso:country":"US",
    "sg:address":"3606 E 103rd St",
    "sg:city":"Tulsa",
    "sg:classifiers":[
        {
            "category":"Real Estate",
            "subcategory":"Real Estate Agent",
            "type":"Services"
        }
    ],
    "sg:phone":"+1 918 492 8777",
    "sg:postcode":"74137",
    "sg:province":"OK",
    "sg:website":"www.vaneaton.org",
    "wof:name":"Van Eaton Enterprises Inc",
    "wof:placetype":"venue"
},
  "geometry": {"coordinates":[-95.93577500000001,36.014303],"type":"Point"}
}