{
  "type": "Feature",
  "properties": {
    "iso:country":"US",
    "sg:address":"225 S Brady St",
    "sg:city":"Claremore",
    "sg:classifiers":[
        {
            "category":"Retail",
            "subcategory":"Car Wash",
            "type":"Services"
        }
    ],
    "sg:phone":"+1 918 341 9222",
    "sg:postcode":"74017",
    "sg:province":"OK",
    "sg:tags":[
        "polishing",
        "washing"
    ],
    "wof:name":"Quick & Clean",
    "wof:placetype":"venue"
},
  "geometry": {"coordinates":[-95.631079,36.317393],"type":"Point"}
}