{
  "type": "Feature",
  "properties": {
    "iso:country":"US",
    "sg:address":"525 NW 13th St",
    "sg:city":"Oklahoma City",
    "sg:classifiers":[
        {
            "category":"Professional",
            "subcategory":"Lawyer & Legal Services",
            "type":"Services"
        }
    ],
    "sg:phone":"+1 405 235 4000",
    "sg:postcode":"73103",
    "sg:province":"OK",
    "sg:tags":[
        "attorney"
    ],
    "sg:website":"www.dandavislaw.com",
    "wof:name":"Daniel M Davis Law Offices",
    "wof:placetype":"venue"
},
  "geometry": {"coordinates":[-97.52230299999999,35.482454],"type":"Point"}
}