{
  "type": "Feature",
  "properties": {
    "addr:full":"2201 SE Washington Blvd Bartlesville OK 74006",
    "addr:housenumber":"2201",
    "addr:postcode":"74006",
    "addr:street":"Se Washington Blvd",
    "iso:country":"US",
    "sg:address":"2201 SE Washington Blvd",
    "sg:city":"Bartlesville",
    "sg:classifiers":[
        {
            "category":"Professional",
            "subcategory":"Business Services",
            "type":"Services"
        }
    ],
    "sg:phone":"+1 918 331 9700",
    "sg:postcode":"74006",
    "sg:province":"OK",
    "sg:tags":[
        "embroidery"
    ],
    "wof:name":"Sew N Sew",
    "wof:placetype":"venue"
},
  "geometry": {"coordinates":[-95.93518299999999,36.718828],"type":"Point"}
}