{
  "type": "Feature",
  "properties": {
    "iso:country":"US",
    "sg:address":"112 NE 5th St",
    "sg:city":"Guymon",
    "sg:classifiers":[
        {
            "category":"Professional",
            "subcategory":"Advertising",
            "type":"Services"
        }
    ],
    "sg:phone":"+1 580 338 8494",
    "sg:postcode":"73942",
    "sg:province":"OK",
    "sg:tags":[
        "counselor"
    ],
    "wof:name":"Crane-Freeman Concepts",
    "wof:placetype":"venue"
},
  "geometry": {"coordinates":[-101.481433,36.682921],"type":"Point"}
}