{
  "type": "Feature",
  "properties": {
    "addr:full":"12922 E 76 St N Tulsa OK 74103",
    "addr:housenumber":"12922;76",
    "addr:postcode":"74103",
    "addr:street":"E;St N",
    "iso:country":"US",
    "sg:address":"12922 E 76 St N",
    "sg:city":"Tulsa",
    "sg:classifiers":[
        {
            "category":"Social Services",
            "subcategory":"Child Care",
            "type":"Services"
        }
    ],
    "sg:phone":"+1 918 948 7738",
    "sg:postcode":"74103",
    "sg:province":"OK",
    "sg:tags":[
        "day"
    ],
    "sg:website":"www.kindercare.com",
    "wof:name":"Kindercare Learning Centers",
    "wof:placetype":"venue"
},
  "geometry": {"coordinates":[-95.826522,36.263975],"type":"Point"}
}