{
  "type": "Feature",
  "properties": {
    "iso:country":"US",
    "sg:address":"316 E Lee Ave",
    "sg:city":"Sapulpa",
    "sg:classifiers":[
        {
            "category":"Organizations",
            "subcategory":"Professional Association",
            "type":"Services"
        }
    ],
    "sg:phone":"+1 918 224 1313",
    "sg:postcode":"74066",
    "sg:province":"OK",
    "wof:name":"Sapulpa Burial Assn",
    "wof:placetype":"venue"
},
  "geometry": {"coordinates":[-96.109593,35.997565],"type":"Point"}
}