{
  "type": "Feature",
  "properties": {
    "iso:country":"US",
    "sg:address":"3900 SW 29th St",
    "sg:city":"Oklahoma City",
    "sg:classifiers":[
        {
            "category":"Retail",
            "subcategory":"Auto Repair",
            "type":"Services"
        }
    ],
    "sg:phone":"+1 405 686 1580",
    "sg:postcode":"73119",
    "sg:province":"OK",
    "sg:tags":[
        "repairing",
        "automobile",
        "general"
    ],
    "wof:name":"Mc Ree Automotive Repair",
    "wof:placetype":"venue"
},
  "geometry": {"coordinates":[-97.590018,35.435219],"type":"Point"}
}