{
  "type": "Feature",
  "properties": {
    "addr:full":"1925 N Ann Arbor Pl Oklahoma City OK 73127",
    "addr:housenumber":"1925",
    "addr:postcode":"73127",
    "addr:street":"N Ann;Pl",
    "iso:country":"US",
    "sg:address":"1925 N Ann Arbor Pl",
    "sg:city":"Oklahoma City",
    "sg:classifiers":[
        {
            "category":"Professional",
            "type":"Services"
        }
    ],
    "sg:phone":"+1 405 231 0092",
    "sg:postcode":"73127",
    "sg:province":"OK",
    "sg:tags":[
        "establishment"
    ],
    "wof:name":"Aaron's Shelters",
    "wof:placetype":"venue"
},
  "geometry": {"coordinates":[-97.610955,35.489458],"type":"Point"}
}