{
  "type": "Feature",
  "properties": {
    "iso:country":"US",
    "sg:address":"5327 E 36th St",
    "sg:city":"Tulsa",
    "sg:classifiers":[
        {
            "category":"Recreation",
            "subcategory":"Boat Charter",
            "type":"Entertainment"
        }
    ],
    "sg:phone":"+1 918 745 0938",
    "sg:postcode":"74135",
    "sg:province":"OK",
    "sg:tags":[
        "boat-rental"
    ],
    "wof:name":"Tara Sailing Inc",
    "wof:placetype":"venue"
},
  "geometry": {"coordinates":[-95.918536,36.11158],"type":"Point"}
}