{
  "type": "Feature",
  "properties": {
    "iso:country":"US",
    "sg:address":"1620 NE 32nd St",
    "sg:city":"Oklahoma City",
    "sg:classifiers":[
        {
            "category":"Social Services",
            "type":"Services"
        }
    ],
    "sg:phone":"+1 405 424 4177",
    "sg:postcode":"73111",
    "sg:province":"OK",
    "sg:tags":[
        "profit"
    ],
    "wof:name":"Building A Better Tomorrow",
    "wof:placetype":"venue"
},
  "geometry": {"coordinates":[-97.481575,35.502148],"type":"Point"}
}