{
  "type": "Feature",
  "properties": {
    "iso:country":"US",
    "sg:address":"7407 S Oak Pl",
    "sg:city":"Broken Arrow",
    "sg:classifiers":[
        {
            "category":"Building & Trades",
            "subcategory":"Landscaping Services",
            "type":"Services"
        }
    ],
    "sg:phone":"+1 918 451 0073",
    "sg:postcode":"74011",
    "sg:province":"OK",
    "sg:tags":[
        "lawn",
        "maintenance",
        "grounds"
    ],
    "wof:name":"Grass Kickers",
    "wof:placetype":"venue"
},
  "geometry": {"coordinates":[-95.80672199999999,35.980722],"type":"Point"}
}