{
  "type": "Feature",
  "properties": {
    "addr:full":"1502 N Rockwell Ave Oklahoma City OK 73127",
    "addr:housenumber":"1502",
    "addr:postcode":"73127",
    "addr:street":"N Rockwell Ave",
    "iso:country":"US",
    "sg:address":"1502 N Rockwell Ave",
    "sg:city":"Oklahoma City",
    "sg:classifiers":[
        {
            "category":"Bars & Pubs",
            "type":"Food & Drink"
        }
    ],
    "sg:phone":"+1 405 495 8730",
    "sg:postcode":"73127",
    "sg:province":"OK",
    "wof:name":"Well",
    "wof:placetype":"venue"
},
  "geometry": {"coordinates":[-97.636596,35.485691],"type":"Point"}
}