{
  "type": "Feature",
  "properties": {
    "iso:country":"US",
    "sg:address":"3711 S Harvard Ave",
    "sg:city":"Tulsa",
    "sg:classifiers":[
        {
            "category":"Shopping",
            "subcategory":"Clothing, Apparel, & Fashions",
            "type":"Retail Goods"
        }
    ],
    "sg:phone":"+1 918 746 4006",
    "sg:postcode":"74135",
    "sg:province":"OK",
    "wof:name":"African Creations",
    "wof:placetype":"venue"
},
  "geometry": {"coordinates":[-95.940161,36.108658],"type":"Point"}
}