{
  "type": "Feature",
  "properties": {
    "iso:country":"US",
    "sg:address":"1950 S Shepard Ave",
    "sg:city":"El Reno",
    "sg:classifiers":[
        {
            "category":"Shopping",
            "subcategory":"Books",
            "type":"Retail Goods"
        }
    ],
    "sg:phone":"+1 405 262 6826",
    "sg:postcode":"73036",
    "sg:province":"OK",
    "sg:tags":[
        "bible"
    ],
    "sg:website":"www.rainbowstudies.com",
    "wof:name":"Rainbow Studies Intl",
    "wof:placetype":"venue"
},
  "geometry": {"coordinates":[-97.93716999999999,35.516614],"type":"Point"}
}