{
  "type": "Feature",
  "properties": {
    "addr:full":"1101 N Michigan Ave Mangum OK 73554",
    "addr:housenumber":"1101",
    "addr:postcode":"73554",
    "addr:street":"N Michigan Ave",
    "iso:country":"US",
    "sg:address":"1101 N Michigan Ave",
    "sg:city":"Mangum",
    "sg:phone":"+1 580 782 2278",
    "sg:postcode":"73554",
    "sg:province":"OK",
    "sg:tags":[
        "farm",
        "wheat",
        "beef",
        "feedlot",
        "cattle"
    ],
    "wof:name":"J H Heatly",
    "wof:placetype":"venue"
},
  "geometry": {"coordinates":[-99.509773,34.883618],"type":"Point"}
}