{
  "type": "Feature",
  "properties": {
    "iso:country":"US",
    "sg:address":"14907 S Hwy 69",
    "sg:city":"Miami",
    "sg:classifiers":[
        {
            "category":"Retail",
            "subcategory":"Repair Shop",
            "type":"Services"
        },
        {
            "category":"Home & Garden",
            "subcategory":"Garden Supply",
            "type":"Retail Goods"
        }
    ],
    "sg:phone":"+1 918 542 8086",
    "sg:postcode":"74354",
    "sg:province":"OK",
    "sg:tags":[
        "equipment",
        "lawn",
        "tractor"
    ],
    "wof:name":"Schulte Equipment Co",
    "wof:placetype":"venue"
},
  "geometry": {"coordinates":[-94.927215,36.802589],"type":"Point"}
}