{
  "type": "Feature",
  "properties": {
    "addr:full":"5201 N Washington St Stillwater OK 74075",
    "addr:housenumber":"5201",
    "addr:postcode":"74075",
    "addr:street":"N Washington St",
    "iso:country":"US",
    "sg:address":"5201 N Washington St",
    "sg:city":"Stillwater",
    "sg:classifiers":[
        {
            "category":"Sports & Exercise",
            "subcategory":"Golf",
            "type":"Entertainment"
        },
        {
            "category":"Recreation",
            "type":"Entertainment"
        }
    ],
    "sg:phone":"+1 405 372 3399",
    "sg:postcode":"74075",
    "sg:province":"OK",
    "sg:tags":[
        "club",
        "course",
        "membership",
        "public"
    ],
    "wof:name":"Lakeside Memorial Golf Club",
    "wof:placetype":"venue"
},
  "geometry": {"coordinates":[-97.069686,36.176522],"type":"Point"}
}