{
  "type": "Feature",
  "properties": {
    "addr:full":"6303 E 9th St Cushing OK 74023",
    "addr:housenumber":"6303",
    "addr:postcode":"74023",
    "addr:street":"E 9Th St",
    "iso:country":"US",
    "sg:address":"6303 E 9th St",
    "sg:city":"Cushing",
    "sg:classifiers":[
        {
            "category":"Real Estate",
            "subcategory":"Real Estate Operator",
            "type":"Services"
        }
    ],
    "sg:phone":"+1 918 372 4452",
    "sg:postcode":"74023",
    "sg:province":"OK",
    "sg:tags":[
        "mobile",
        "home",
        "community"
    ],
    "wof:name":"Timberline Mobile Home & Rv",
    "wof:placetype":"venue"
},
  "geometry": {"coordinates":[-96.67377399999999,35.971163],"type":"Point"}
}