{
  "type": "Feature",
  "properties": {
    "iso:country":"US",
    "sg:address":"6006 E 79th St",
    "sg:city":"Tulsa",
    "sg:classifiers":[
        {
            "category":"Social Services",
            "type":"Services"
        }
    ],
    "sg:phone":"+1 918 488 0004",
    "sg:postcode":"74136",
    "sg:province":"OK",
    "sg:tags":[
        "senior",
        "citizen"
    ],
    "wof:name":"Transitions",
    "wof:placetype":"venue"
},
  "geometry": {"coordinates":[-95.907925,36.04949],"type":"Point"}
}