{
  "type": "Feature",
  "properties": {
    "iso:country":"US",
    "sg:address":"25713 State Hwy 82",
    "sg:city":"Park Hill",
    "sg:classifiers":[
        {
            "category":"Freight",
            "type":"Transportation"
        }
    ],
    "sg:phone":"+1 918 456 3344",
    "sg:postcode":"74451",
    "sg:province":"OK",
    "sg:tags":[
        "commercial",
        "storage"
    ],
    "wof:name":"Storage Solutions",
    "wof:placetype":"venue"
},
  "geometry": {"coordinates":[-94.967577,35.802562],"type":"Point"}
}