{
  "type": "Feature",
  "properties": {
    "iso:country":"US",
    "sg:address":"211 W Ridge Rd",
    "sg:city":"Norman",
    "sg:classifiers":[
        {
            "category":"Building & Trades",
            "subcategory":"Construction",
            "type":"Services"
        }
    ],
    "sg:phone":"+1 405 366 1084",
    "sg:postcode":"73069",
    "sg:province":"OK",
    "sg:tags":[
        "hanging",
        "contractor"
    ],
    "wof:name":"Numillennia Painting",
    "wof:placetype":"venue"
},
  "geometry": {"coordinates":[-97.44977900000001,35.236285],"type":"Point"}
}