{
  "type": "Feature",
  "properties": {
    "addr:full":"2701 W Eseco Rd Cushing OK 74023",
    "addr:housenumber":"2701",
    "addr:postcode":"74023",
    "addr:street":"W Eseco Rd",
    "iso:country":"US",
    "sg:address":"2701 W Eseco Rd",
    "sg:city":"Cushing",
    "sg:classifiers":[
        {
            "category":"Government",
            "subcategory":"Office",
            "type":"Public Place"
        }
    ],
    "sg:phone":"+1 918 225 4634",
    "sg:postcode":"74023",
    "sg:province":"OK",
    "sg:tags":[
        "village"
    ],
    "wof:name":"Sewage Treatment Plant",
    "wof:placetype":"venue"
},
  "geometry": {"coordinates":[-96.80493199999999,35.956708],"type":"Point"}
}