{
  "type": "Feature",
  "properties": {
    "addr:full":"4853 S Sheridan Rd Tulsa OK 74145",
    "addr:housenumber":"4853",
    "addr:postcode":"74145",
    "addr:street":"S Sheridan Rd",
    "iso:country":"US",
    "sg:address":"4853 S Sheridan Rd",
    "sg:city":"Tulsa",
    "sg:classifiers":[
        {
            "category":"Professional",
            "subcategory":"Accounting & Tax Preparation",
            "type":"Services"
        }
    ],
    "sg:phone":"+1 918 664 9106",
    "sg:postcode":"74145",
    "sg:province":"OK",
    "sg:tags":[
        "accountant"
    ],
    "wof:name":"Phil Nelson CPA",
    "wof:placetype":"venue"
},
  "geometry": {"coordinates":[-95.904319,36.091767],"type":"Point"}
}