{
  "type": "Feature",
  "properties": {
    "iso:country":"US",
    "sg:address":"1215 E Carol Dr",
    "sg:city":"Shawnee",
    "sg:classifiers":[
        {
            "category":"Professional",
            "subcategory":"Art Services",
            "type":"Services"
        }
    ],
    "sg:phone":"+1 405 395 9982",
    "sg:postcode":"74804",
    "sg:province":"OK",
    "sg:tags":[
        "commercial",
        "design"
    ],
    "wof:name":"Dazzle Sticks",
    "wof:placetype":"venue"
},
  "geometry": {"coordinates":[-96.90718,35.350551],"type":"Point"}
}