{
  "type": "Feature",
  "properties": {
    "iso:country":"US",
    "sg:address":"6909 S Perkins Rd",
    "sg:city":"Stillwater",
    "sg:classifiers":[
        {
            "category":"Retail",
            "subcategory":"Auto Repair",
            "type":"Services"
        }
    ],
    "sg:phone":"+1 405 372 0756",
    "sg:postcode":"74074",
    "sg:province":"OK",
    "sg:tags":[
        "general"
    ],
    "wof:name":"Transmissions Plus",
    "wof:placetype":"venue"
},
  "geometry": {"coordinates":[-97.051083,36.04282],"type":"Point"}
}