{
  "type": "Feature",
  "properties": {
    "iso:country":"US",
    "sg:address":"2601 N Cottonwood Rd",
    "sg:city":"Stillwater",
    "sg:classifiers":[
        {
            "category":"Professional",
            "subcategory":"Business Services",
            "type":"Services"
        }
    ],
    "sg:phone":"+1 405 372 0563",
    "sg:postcode":"74075",
    "sg:province":"OK",
    "sg:tags":[
        "auctioneer"
    ],
    "wof:name":"Ernie Pickens Real Estate",
    "wof:placetype":"venue"
},
  "geometry": {"coordinates":[-97.15843,36.152406],"type":"Point"}
}