{
  "type": "Feature",
  "properties": {
    "addr:full":"4300 NW 23rd St Oklahoma City OK 73107",
    "addr:housenumber":"4300",
    "addr:postcode":"73107",
    "addr:street":"Nw 23Rd St",
    "iso:country":"US",
    "sg:address":"4300 NW 23rd St",
    "sg:city":"Oklahoma City",
    "sg:classifiers":[
        {
            "category":"Shopping",
            "subcategory":"Department Store",
            "type":"Retail Goods"
        }
    ],
    "sg:phone":"+1 405 752 7794",
    "sg:postcode":"73107",
    "sg:province":"OK",
    "wof:name":"Sears Roebuck & Co",
    "wof:placetype":"venue"
},
  "geometry": {"coordinates":[-97.597489,35.493239],"type":"Point"}
}