{
  "type": "Feature",
  "properties": {
    "iso:country":"US",
    "sg:address":"618 Main Ave",
    "sg:city":"Woodward",
    "sg:classifiers":[
        {
            "category":"Building & Trades",
            "subcategory":"Plumbing",
            "type":"Services"
        }
    ],
    "sg:phone":"+1 580 256 2242",
    "sg:postcode":"73801",
    "sg:province":"OK",
    "sg:tags":[
        "conditioning",
        "contractor",
        "system",
        "air"
    ],
    "wof:name":"Gilreath Service Company",
    "wof:placetype":"venue"
},
  "geometry": {"coordinates":[-99.388206,36.435974],"type":"Point"}
}