{
  "type": "Feature",
  "properties": {
    "iso:country":"US",
    "sg:address":"328 S Eagle Ln",
    "sg:city":"Oklahoma City",
    "sg:classifiers":[
        {
            "category":"Manufacturing",
            "subcategory":"Metals",
            "type":"Manufacturing & Wholesale Goods"
        }
    ],
    "sg:phone":"+1 405 495 1269",
    "sg:postcode":"73128",
    "sg:province":"OK",
    "sg:tags":[
        "coating"
    ],
    "sg:website":"www.profireindustries.com",
    "wof:name":"Pro-Fire INDUSTRIES LLC",
    "wof:placetype":"venue"
},
  "geometry": {"coordinates":[-97.662297,35.461818],"type":"Point"}
}