{
  "type": "Feature",
  "properties": {
    "addr:full":"3970 I- 240 Oklahoma City OK 73135",
    "addr:housenumber":"3970;240",
    "addr:postcode":"73135",
    "addr:street":"I",
    "iso:country":"US",
    "sg:address":"3970 I- 240",
    "sg:city":"Oklahoma City",
    "sg:classifiers":[
        {
            "category":"Building & Trades",
            "subcategory":"Pest Control",
            "type":"Services"
        }
    ],
    "sg:phone":"+1 405 670 9919",
    "sg:postcode":"73135",
    "sg:province":"OK",
    "wof:name":"Terminix",
    "wof:placetype":"venue"
},
  "geometry": {"coordinates":[-97.450108,35.391463],"type":"Point"}
}