{
  "type": "Feature",
  "properties": {
    "iso:country":"US",
    "sg:address":"105 N Hudson Ave",
    "sg:city":"Oklahoma City",
    "sg:classifiers":[
        {
            "category":"Shopping",
            "subcategory":"Computers & Home Electronics",
            "type":"Retail Goods"
        }
    ],
    "sg:phone":"+1 405 239 0119",
    "sg:postcode":"73102",
    "sg:province":"OK",
    "sg:tags":[
        "software"
    ],
    "wof:name":"Enertia Software",
    "wof:placetype":"venue"
},
  "geometry": {"coordinates":[-97.519593,35.468408],"type":"Point"}
}