{
  "type": "Feature",
  "properties": {
    "iso:country":"US",
    "sg:address":"1124 N Douglas Blvd",
    "sg:city":"Midwest City",
    "sg:classifiers":[
        {
            "category":"Government",
            "subcategory":"Fire Station",
            "type":"Public Place"
        }
    ],
    "sg:phone":"+1 405 732 4663",
    "sg:postcode":"73130",
    "sg:province":"OK",
    "sg:tags":[
        "department"
    ],
    "wof:name":"Midwest City Fire Dept",
    "wof:placetype":"venue"
},
  "geometry": {"coordinates":[-97.37074800000001,35.480817],"type":"Point"}
}