{
  "type": "Feature",
  "properties": {
    "addr:full":"5121 E 85th St Tulsa OK 74137",
    "addr:housenumber":"5121",
    "addr:postcode":"74137",
    "addr:street":"E 85Th St",
    "iso:country":"US",
    "sg:address":"5121 E 85th St",
    "sg:city":"Tulsa",
    "sg:classifiers":[
        {
            "category":"Health Services",
            "subcategory":"Doctor",
            "type":"Services"
        }
    ],
    "sg:phone":"+1 918 481 1138",
    "sg:postcode":"74137",
    "sg:province":"OK",
    "sg:tags":[
        "medical"
    ],
    "wof:name":"Accutech Laborators",
    "wof:placetype":"venue"
},
  "geometry": {"coordinates":[-95.91914199999999,36.039467],"type":"Point"}
}