{
  "type": "Feature",
  "properties": {
    "iso:country":"US",
    "sg:address":"324 S Main St",
    "sg:city":"Tulsa",
    "sg:classifiers":[
        {
            "category":"Professional",
            "subcategory":"Management & Consulting",
            "type":"Services"
        }
    ],
    "sg:phone":"+1 918 583 5816",
    "sg:postcode":"74103",
    "sg:province":"OK",
    "sg:tags":[
        "counselor",
        "public",
        "relations"
    ],
    "wof:name":"Public Relations Intl LTD",
    "wof:placetype":"venue"
},
  "geometry": {"coordinates":[-95.990829,36.152588],"type":"Point"}
}