{
  "type": "Feature",
  "properties": {
    "addr:full":"3101 Country Aire Ests Bache OK 74501",
    "addr:housenumber":"3101",
    "addr:postcode":"74501",
    "addr:street":"Country Aire Ests Bache",
    "iso:country":"US",
    "sg:address":"3101 Country Aire Ests",
    "sg:city":"Bache",
    "sg:classifiers":[
        {
            "category":"Restaurant",
            "type":"Food & Drink"
        }
    ],
    "sg:phone":"+1 918 423 4253",
    "sg:postcode":"74501",
    "sg:province":"OK",
    "sg:tags":[
        "eating"
    ],
    "wof:name":"Toms Porky Inc",
    "wof:placetype":"venue"
},
  "geometry": {"coordinates":[-95.726333,34.95793],"type":"Point"}
}