{
  "type": "Feature",
  "properties": {
    "addr:full":"427 S Boston Ave Tulsa OK 74103",
    "addr:housenumber":"427",
    "addr:postcode":"74103",
    "addr:street":"S Boston Ave",
    "iso:country":"US",
    "sg:address":"427 S Boston Ave",
    "sg:city":"Tulsa",
    "sg:classifiers":[
        {
            "category":"Mining & Drilling",
            "type":"Manufacturing & Wholesale Goods"
        }
    ],
    "sg:phone":"+1 918 585 6777",
    "sg:postcode":"74103",
    "sg:province":"OK",
    "sg:tags":[
        "development",
        "gas",
        "oil",
        "exploration"
    ],
    "wof:name":"Aspire Energy LLC",
    "wof:placetype":"venue"
},
  "geometry": {"coordinates":[-95.988989,36.152112],"type":"Point"}
}