{
  "type": "Feature",
  "properties": {
    "iso:country":"US",
    "sg:address":"2816 NW 58th St",
    "sg:city":"Oklahoma City",
    "sg:classifiers":[
        {
            "category":"Insurance",
            "subcategory":"Hazard Insurance",
            "type":"Services"
        }
    ],
    "sg:phone":"+1 405 631 5511",
    "sg:postcode":"73112",
    "sg:province":"OK",
    "sg:tags":[
        "fidelity",
        "bond"
    ],
    "wof:name":"Snipes Insurance",
    "wof:placetype":"venue"
},
  "geometry": {"coordinates":[-97.56531200000001,35.530698],"type":"Point"}
}