{
  "type": "Feature",
  "properties": {
    "addr:full":"314 W Rogers St El Reno OK 73036",
    "addr:housenumber":"314",
    "addr:postcode":"73036",
    "addr:street":"W Rogers St",
    "iso:country":"US",
    "sg:address":"314 W Rogers St",
    "sg:city":"El Reno",
    "sg:classifiers":[
        {
            "category":"Government",
            "subcategory":"Office",
            "type":"Public Place"
        },
        {
            "category":"Social Services",
            "type":"Services"
        }
    ],
    "sg:phone":"+1 405 262 2030",
    "sg:postcode":"73036",
    "sg:province":"OK",
    "sg:tags":[
        "department",
        "state",
        "resource",
        "human"
    ],
    "sg:website":"www.okdhs.org",
    "wof:name":"Human Services Oklahoma Dept",
    "wof:placetype":"venue"
},
  "geometry": {"coordinates":[-97.95643,35.53508],"type":"Point"}
}