{
  "type": "Feature",
  "properties": {
    "addr:full":"123 Circle Dr Poteau OK 74953",
    "addr:housenumber":"123",
    "addr:postcode":"74953",
    "addr:street":"Circle Dr",
    "iso:country":"US",
    "sg:address":"123 Circle Dr",
    "sg:city":"Poteau",
    "sg:classifiers":[
        {
            "category":"Building & Trades",
            "subcategory":"Construction",
            "type":"Services"
        }
    ],
    "sg:phone":"+1 918 647 4062",
    "sg:postcode":"74953",
    "sg:province":"OK",
    "sg:tags":[
        "contractor"
    ],
    "wof:name":"Quality Masonry",
    "wof:placetype":"venue"
},
  "geometry": {"coordinates":[-94.628704,35.06928],"type":"Point"}
}