{
  "type": "Feature",
  "properties": {
    "iso:country":"US",
    "sg:address":"11611 S Western Ave",
    "sg:city":"Oklahoma City",
    "sg:classifiers":[
        {
            "category":"Professional",
            "subcategory":"Business Services",
            "type":"Services"
        }
    ],
    "sg:phone":"+1 405 692 4215",
    "sg:postcode":"73170",
    "sg:province":"OK",
    "wof:name":"Richard Self & Associates Proc",
    "wof:placetype":"venue"
},
  "geometry": {"coordinates":[-97.530052,35.350841],"type":"Point"}
}