{
  "type": "Feature",
  "properties": {
    "iso:country":"US",
    "sg:address":"408 N 7th St",
    "sg:city":"Henryetta",
    "sg:classifiers":[
        {
            "category":"Organizations",
            "subcategory":"Religious Organization",
            "type":"Services"
        }
    ],
    "sg:phone":"+1 918 652 8825",
    "sg:postcode":"74437",
    "sg:province":"OK",
    "sg:tags":[
        "church"
    ],
    "wof:name":"Word Of Life Holiness Church",
    "wof:placetype":"venue"
},
  "geometry": {"coordinates":[-95.989538,35.443379],"type":"Point"}
}