{
  "type": "Feature",
  "properties": {
    "addr:full":"1348 N Yale Ave Tulsa OK 74115",
    "addr:housenumber":"1348",
    "addr:postcode":"74115",
    "addr:street":"N Yale Ave",
    "iso:country":"US",
    "sg:address":"1348 N Yale Ave",
    "sg:city":"Tulsa",
    "sg:classifiers":[
        {
            "category":"Food & Beverages",
            "subcategory":"Bakery",
            "type":"Retail Goods"
        }
    ],
    "sg:phone":"+1 918 836 7828",
    "sg:postcode":"74115",
    "sg:province":"OK",
    "sg:tags":[
        "doughnut"
    ],
    "wof:name":"Browns Donut Shop",
    "wof:placetype":"venue"
},
  "geometry": {"coordinates":[-95.92256999999999,36.174389],"type":"Point"}
}