{
  "type": "Feature",
  "properties": {
    "addr:full":"10801 White Oak Canyon Rd Oklahoma City OK 73162",
    "addr:housenumber":"10801",
    "addr:postcode":"73162",
    "addr:street":"White Oak Canyon Rd",
    "iso:country":"US",
    "sg:address":"10801 White Oak Canyon Rd",
    "sg:city":"Oklahoma City",
    "sg:classifiers":[
        {
            "category":"Professional",
            "subcategory":"Detective & Security Services",
            "type":"Services"
        }
    ],
    "sg:phone":"+1 405 621 9366",
    "sg:postcode":"73162",
    "sg:province":"OK",
    "sg:tags":[
        "guard"
    ],
    "wof:name":"King Lucinda",
    "wof:placetype":"venue"
},
  "geometry": {"coordinates":[-97.636534,35.580069],"type":"Point"}
}