{
  "type": "Feature",
  "properties": {
    "iso:country":"US",
    "sg:address":"129 S Oklahoma Ave",
    "sg:city":"Mangum",
    "sg:classifiers":[
        {
            "category":"Professional",
            "subcategory":"Accounting & Tax Preparation",
            "type":"Services"
        }
    ],
    "sg:phone":"+1 580 782 3403",
    "sg:postcode":"73554",
    "sg:province":"OK",
    "wof:name":"Parker Bookkeeping & Tax Svc",
    "wof:placetype":"venue"
},
  "geometry": {"coordinates":[-99.506134,34.873262],"type":"Point"}
}