{
  "type": "Feature",
  "properties": {
    "iso:country":"US",
    "sg:address":"2000 S Meridian Ave",
    "sg:city":"Oklahoma City",
    "sg:classifiers":[
        {
            "category":"Restaurant",
            "type":"Food & Drink"
        }
    ],
    "sg:menulink":"http://www.allmenus.com/ok/oklahoma-city/5005-charlestons/menu/",
    "sg:phone":"+1 405 681 6686",
    "sg:postcode":"73108",
    "sg:province":"OK",
    "sg:tags":[
        "american"
    ],
    "wof:name":"Charleston's",
    "wof:placetype":"venue"
},
  "geometry": {"coordinates":[-97.60106500000001,35.444217],"type":"Point"}
}