{
  "type": "Feature",
  "properties": {
    "iso:country":"US",
    "sg:address":"300 N Telephone Rd",
    "sg:city":"Oklahoma City",
    "sg:classifiers":[
        {
            "category":"Shopping",
            "subcategory":"Florist",
            "type":"Retail Goods"
        }
    ],
    "sg:phone":"+1 405 912 8724",
    "sg:postcode":"73160",
    "sg:province":"OK",
    "sg:website":"www.pamtrotter.com",
    "wof:name":"Pam Trotter Designs",
    "wof:placetype":"venue"
},
  "geometry": {"coordinates":[-97.494486,35.340292],"type":"Point"}
}