{
  "type": "Feature",
  "properties": {
    "iso:country":"US",
    "sg:address":"9500 Sleepy Hollow Dr",
    "sg:city":"Newalla",
    "sg:classifiers":[
        {
            "category":"Professional",
            "subcategory":"Accounting & Tax Preparation",
            "type":"Services"
        }
    ],
    "sg:phone":"+1 405 677 1655",
    "sg:postcode":"74857",
    "sg:province":"OK",
    "wof:name":"Affordable Solutions",
    "wof:placetype":"venue"
},
  "geometry": {"coordinates":[-97.17218,35.373506],"type":"Point"}
}