{
  "type": "Feature",
  "properties": {
    "iso:country":"US",
    "sg:address":"4901 W Owen K Garriott Rd",
    "sg:city":"Enid",
    "sg:classifiers":[
        {
            "category":"Restaurant",
            "type":"Food & Drink"
        }
    ],
    "sg:menulink":"http://www.allmenus.com/ok/enid/105106-rib-crib/menu/",
    "sg:phone":"+1 580 237 7333",
    "sg:postcode":"73703",
    "sg:province":"OK",
    "sg:tags":[
        "barbecue",
        "american"
    ],
    "wof:name":"Rib Crib",
    "wof:placetype":"venue"
},
  "geometry": {"coordinates":[-97.938154,36.39067],"type":"Point"}
}