{
  "type": "Feature",
  "properties": {
    "iso:country":"US",
    "sg:address":"1212 N Broadway Ave",
    "sg:city":"Ada",
    "sg:classifiers":[
        {
            "category":"Restaurant",
            "type":"Food & Drink"
        }
    ],
    "sg:phone":"+1 580 622 3125",
    "sg:postcode":"74820",
    "sg:province":"OK",
    "wof:name":"Bricks Restaurant & Catering",
    "wof:placetype":"venue"
},
  "geometry": {"coordinates":[-96.678679,34.786755],"type":"Point"}
}