{
  "type": "Feature",
  "properties": {
    "iso:country":"US",
    "sg:address":"1231 36th Ave NW",
    "sg:city":"Norman",
    "sg:classifiers":[
        {
            "category":"Retail",
            "subcategory":"Car Wash",
            "type":"Services"
        }
    ],
    "sg:phone":"+1 405 321 4505",
    "sg:postcode":"73072",
    "sg:province":"OK",
    "sg:tags":[
        "carwash"
    ],
    "wof:name":"Hodges Car Wash",
    "wof:placetype":"venue"
},
  "geometry": {"coordinates":[-97.494462,35.232952],"type":"Point"}
}