{
  "type": "Feature",
  "properties": {
    "iso:country":"US",
    "sg:address":"1200 State Hwy 152",
    "sg:city":"Mustang",
    "sg:classifiers":[
        {
            "category":"Autos & Motor Vehicles",
            "subcategory":"Automobile Sales",
            "type":"Retail Goods"
        }
    ],
    "sg:phone":"+1 405 376 0800",
    "sg:postcode":"73064",
    "sg:province":"OK",
    "sg:tags":[
        "car",
        "dealer"
    ],
    "wof:name":"Mike Hale Auto Sales Inc",
    "wof:placetype":"venue"
},
  "geometry": {"coordinates":[-97.749199,35.391647],"type":"Point"}
}