{
  "type": "Feature",
  "properties": {
    "iso:country":"US",
    "sg:address":"4200 N Western Ave",
    "sg:city":"Oklahoma City",
    "sg:classifiers":[
        {
            "category":"Professional",
            "subcategory":"Business Services",
            "type":"Services"
        }
    ],
    "sg:phone":"+1 405 521 9393",
    "sg:postcode":"73118",
    "sg:province":"OK",
    "sg:tags":[
        "interior",
        "consultant",
        "design",
        "decorator"
    ],
    "wof:name":"Interior Vignettes",
    "wof:placetype":"venue"
},
  "geometry": {"coordinates":[-97.529831,35.51459],"type":"Point"}
}