{
  "type": "Feature",
  "properties": {
    "iso:country":"US",
    "sg:address":"224 W McArthur Dr",
    "sg:city":"Midwest City",
    "sg:classifiers":[
        {
            "category":"Retail",
            "subcategory":"Car Wash",
            "type":"Services"
        }
    ],
    "sg:phone":"+1 405 741 3900",
    "sg:postcode":"73110",
    "sg:province":"OK",
    "sg:tags":[
        "automobile",
        "detail",
        "clean",
        "automotive"
    ],
    "wof:name":"Splish Splash Mobile Detailer",
    "wof:placetype":"venue"
},
  "geometry": {"coordinates":[-97.40533499999999,35.440985],"type":"Point"}
}