{
  "type": "Feature",
  "properties": {
    "iso:country":"US",
    "sg:address":"825 SW 134th St",
    "sg:city":"Oklahoma City",
    "sg:classifiers":[
        {
            "category":"Autos & Motor Vehicles",
            "subcategory":"Fuel & Gas Station",
            "type":"Retail Goods"
        }
    ],
    "sg:phone":"+1 405 691 6141",
    "sg:postcode":"73170",
    "sg:province":"OK",
    "sg:tags":[
        "oil"
    ],
    "wof:name":"Phillips 66",
    "wof:placetype":"venue"
},
  "geometry": {"coordinates":[-97.529809,35.334363],"type":"Point"}
}