{
  "type": "Feature",
  "properties": {
    "iso:country":"US",
    "sg:address":"3604 N Cincinnati Ave",
    "sg:city":"Tulsa",
    "sg:classifiers":[
        {
            "category":"Health Services",
            "subcategory":"Hospital",
            "type":"Services"
        }
    ],
    "sg:phone":"+1 918 425 4200",
    "sg:postcode":"74106",
    "sg:province":"OK",
    "sg:tags":[
        "mental"
    ],
    "sg:website":"www.fcsok.org",
    "wof:name":"Family & Children Svc",
    "wof:placetype":"venue"
},
  "geometry": {"coordinates":[-95.993584,36.206049],"type":"Point"}
}