{
  "type": "Feature",
  "properties": {
    "iso:country":"US",
    "sg:address":"601 State Hwy 9",
    "sg:city":"Wetumka",
    "sg:classifiers":[
        {
            "category":"Autos & Motor Vehicles",
            "subcategory":"Auto Supplies",
            "type":"Retail Goods"
        }
    ],
    "sg:phone":"+1 405 452 3372",
    "sg:postcode":"74883",
    "sg:province":"OK",
    "sg:tags":[
        "automotive",
        "parts"
    ],
    "wof:name":"Goodsons Auto & Tractor Supply",
    "wof:placetype":"venue"
},
  "geometry": {"coordinates":[-96.233241,35.232031],"type":"Point"}
}