{
  "type": "Feature",
  "properties": {
    "iso:country":"US",
    "sg:address":"400 N 14th St",
    "sg:city":"Ponca City",
    "sg:classifiers":[
        {
            "category":"Organizations",
            "subcategory":"Religious Organization",
            "type":"Services"
        }
    ],
    "sg:phone":"+1 580 765 5229",
    "sg:postcode":"74601",
    "sg:province":"OK",
    "wof:name":"St Johns Baptist Church",
    "wof:placetype":"venue"
},
  "geometry": {"coordinates":[-97.067303,36.707505],"type":"Point"}
}