{
  "type": "Feature",
  "properties": {
    "iso:country":"US",
    "sg:address":"800 Country Club Dr",
    "sg:city":"Holdenville",
    "sg:classifiers":[
        {
            "category":"Wholesale",
            "subcategory":"Auto Parts",
            "type":"Manufacturing & Wholesale Goods"
        }
    ],
    "sg:phone":"+1 405 379 5630",
    "sg:postcode":"74848",
    "sg:province":"OK",
    "sg:tags":[
        "magneto"
    ],
    "wof:name":"Mag Shop",
    "wof:placetype":"venue"
},
  "geometry": {"coordinates":[-96.38045700000001,35.084695],"type":"Point"}
}