{
  "type": "Feature",
  "properties": {
    "iso:country":"US",
    "sg:address":"10701 N Pennsylvania Ave",
    "sg:city":"Oklahoma City",
    "sg:classifiers":[
        {
            "category":"Restaurant",
            "type":"Food & Drink"
        }
    ],
    "sg:phone":"+1 405 752 5151",
    "sg:postcode":"73120",
    "sg:province":"OK",
    "sg:website":"www.burgerking.com",
    "wof:name":"Burger King",
    "wof:placetype":"venue"
},
  "geometry": {"coordinates":[-97.54937099999999,35.577935],"type":"Point"}
}