{
  "type": "Feature",
  "properties": {
    "addr:full":"5203 S 193rd E Ave Broken Arrow OK 74014",
    "addr:housenumber":"5203",
    "addr:postcode":"74014",
    "addr:street":"S 193Rd E Ave",
    "iso:country":"US",
    "sg:address":"5203 S 193rd E Ave",
    "sg:city":"Broken Arrow",
    "sg:classifiers":[
        {
            "category":"Retail",
            "subcategory":"Auto Rental",
            "type":"Services"
        }
    ],
    "sg:phone":"+1 918 355 9372",
    "sg:postcode":"74014",
    "sg:province":"OK",
    "sg:tags":[
        "renting",
        "truck",
        "leasing"
    ],
    "wof:name":"U-Haul Co",
    "wof:placetype":"venue"
},
  "geometry": {"coordinates":[-95.761588,36.08876],"type":"Point"}
}