{
  "type": "Feature",
  "properties": {
    "iso:country":"US",
    "sg:address":"1414 E 71st St S",
    "sg:city":"Tulsa",
    "sg:classifiers":[
        {
            "category":"Health Services",
            "subcategory":"Clinic",
            "type":"Services"
        }
    ],
    "sg:phone":"+1 918 599 5431",
    "sg:postcode":"74136",
    "sg:province":"OK",
    "sg:tags":[
        "rehabilitation"
    ],
    "wof:name":"Tulsa Regional Medical Center",
    "wof:placetype":"venue"
},
  "geometry": {"coordinates":[-95.974378,36.060592],"type":"Point"}
}