{
  "type": "Feature",
  "properties": {
    "iso:country":"US",
    "sg:address":"9312 N Western Ave",
    "sg:city":"Oklahoma City",
    "sg:classifiers":[
        {
            "category":"Retail",
            "subcategory":"Auto Repair",
            "type":"Services"
        }
    ],
    "sg:phone":"+1 405 841 3371",
    "sg:postcode":"73114",
    "sg:province":"OK",
    "sg:tags":[
        "repairing",
        "automobile"
    ],
    "wof:name":"Big Brothers Allstar Svc & Col",
    "wof:placetype":"venue"
},
  "geometry": {"coordinates":[-97.531222,35.565412],"type":"Point"}
}