{
  "type": "Feature",
  "properties": {
    "addr:full":"222 S Quapaw Ave Bartlesville OK 74003",
    "addr:housenumber":"222",
    "addr:postcode":"74003",
    "addr:street":"S Quapaw Ave",
    "iso:country":"US",
    "sg:address":"222 S Quapaw Ave",
    "sg:city":"Bartlesville",
    "sg:classifiers":[
        {
            "category":"Freight",
            "type":"Transportation"
        }
    ],
    "sg:phone":"+1 918 336 1055",
    "sg:postcode":"74003",
    "sg:province":"OK",
    "sg:tags":[
        "local",
        "without",
        "storage",
        "trucking"
    ],
    "wof:name":"Bartlesville Moving Systems",
    "wof:placetype":"venue"
},
  "geometry": {"coordinates":[-95.963814,36.750506],"type":"Point"}
}