{
  "type": "Feature",
  "properties": {
    "iso:country":"US",
    "sg:address":"800 W Rock Creek Rd",
    "sg:city":"Norman",
    "sg:classifiers":[
        {
            "category":"Health Services",
            "subcategory":"Medical Lab",
            "type":"Services"
        }
    ],
    "sg:phone":"+1 405 360 5557",
    "sg:postcode":"73069",
    "sg:province":"OK",
    "sg:tags":[
        "laboratory"
    ],
    "wof:name":"One Dental Ceramics",
    "wof:placetype":"venue"
},
  "geometry": {"coordinates":[-97.451512,35.247357],"type":"Point"}
}