{
  "type": "Feature",
  "properties": {
    "iso:country":"US",
    "sg:address":"5600 N May Ave",
    "sg:city":"Oklahoma City",
    "sg:classifiers":[
        {
            "category":"Manufacturing",
            "subcategory":"Printing",
            "type":"Manufacturing & Wholesale Goods"
        }
    ],
    "sg:phone":"+1 405 286 9500",
    "sg:postcode":"73112",
    "sg:province":"OK",
    "sg:tags":[
        "multimedia"
    ],
    "wof:name":"Christensen Media Group",
    "wof:placetype":"venue"
},
  "geometry": {"coordinates":[-97.565552,35.526921],"type":"Point"}
}