{
  "type": "Feature",
  "properties": {
    "iso:country":"US",
    "sg:address":"808 W Gary Blvd",
    "sg:city":"Clinton",
    "sg:classifiers":[
        {
            "category":"Real Estate",
            "subcategory":"Real Estate Agent",
            "type":"Services"
        }
    ],
    "sg:phone":"+1 580 323 3092",
    "sg:postcode":"73601",
    "sg:province":"OK",
    "wof:name":"Mike Perkins Realty",
    "wof:placetype":"venue"
},
  "geometry": {"coordinates":[-98.970738,35.515326],"type":"Point"}
}