{
  "type": "Feature",
  "properties": {
    "iso:country":"US",
    "sg:address":"3016 Castle Rock Rd",
    "sg:city":"Oklahoma City",
    "sg:classifiers":[
        {
            "category":"Building & Trades",
            "subcategory":"Electrical",
            "type":"Services"
        }
    ],
    "sg:phone":"+1 405 748 3330",
    "sg:postcode":"73120",
    "sg:province":"OK",
    "sg:tags":[
        "electric",
        "contractor"
    ],
    "wof:name":"Pro Tech Electrical",
    "wof:placetype":"venue"
},
  "geometry": {"coordinates":[-97.569654,35.605917],"type":"Point"}
}