{
  "type": "Feature",
  "properties": {
    "addr:full":"422 W Locust St Stilwell OK 74960",
    "addr:housenumber":"422",
    "addr:postcode":"74960",
    "addr:street":"W Locust St",
    "iso:country":"US",
    "sg:address":"422 W Locust St",
    "sg:city":"Stilwell",
    "sg:classifiers":[
        {
            "category":"Health Services",
            "subcategory":"Nursing And Care Facility",
            "type":"Services"
        }
    ],
    "sg:phone":"+1 918 696 7715",
    "sg:postcode":"74960",
    "sg:province":"OK",
    "sg:tags":[
        "home",
        "convalescent"
    ],
    "wof:name":"Stilwell Nursing Home",
    "wof:placetype":"venue"
},
  "geometry": {"coordinates":[-94.63265800000001,35.808476],"type":"Point"}
}