{
  "type": "Feature",
  "properties": {
    "iso:country":"US",
    "sg:address":"1347 W Lindsey St",
    "sg:city":"Norman",
    "sg:classifiers":[
        {
            "category":"Restaurant",
            "type":"Food & Drink"
        }
    ],
    "sg:phone":"+1 405 329 9790",
    "sg:postcode":"73069",
    "sg:province":"OK",
    "wof:name":"Thai Kumkoon Restaurant",
    "wof:placetype":"venue"
},
  "geometry": {"coordinates":[-97.465373,35.20382],"type":"Point"}
}