{
  "type": "Feature",
  "properties": {
    "iso:country":"US",
    "sg:address":"111 W 12th St",
    "sg:city":"Snyder",
    "sg:classifiers":[
        {
            "category":"Farming",
            "subcategory":"Farm & Veterinary Services",
            "type":"Manufacturing & Wholesale Goods"
        }
    ],
    "sg:phone":"+1 580 569 2153",
    "sg:postcode":"73566",
    "sg:province":"OK",
    "sg:tags":[
        "control",
        "weed"
    ],
    "wof:name":"Snyder Spraying Svc",
    "wof:placetype":"venue"
},
  "geometry": {"coordinates":[-98.957097,34.653833],"type":"Point"}
}