{
  "type": "Feature",
  "properties": {
    "iso:country":"US",
    "sg:address":"2624 Broadway Ct",
    "sg:city":"Edmond",
    "sg:classifiers":[
        {
            "category":"Shopping",
            "subcategory":"Bicycles & Sporting Goods",
            "type":"Retail Goods"
        }
    ],
    "sg:phone":"+1 405 341 4331",
    "sg:postcode":"73013",
    "sg:province":"OK",
    "sg:tags":[
        "shop"
    ],
    "wof:name":"Al's Bicycles",
    "wof:placetype":"venue"
},
  "geometry": {"coordinates":[-97.48556000000001,35.625772],"type":"Point"}
}