{
  "type": "Feature",
  "properties": {
    "iso:country":"US",
    "sg:address":"3313 S Byers Ave",
    "sg:city":"Oklahoma City",
    "sg:classifiers":[
        {
            "category":"Wholesale",
            "subcategory":"Construction Materials",
            "type":"Manufacturing & Wholesale Goods"
        }
    ],
    "sg:phone":"+1 405 616 9203",
    "sg:postcode":"73129",
    "sg:province":"OK",
    "sg:tags":[
        "fence"
    ],
    "wof:name":"Superior Fence Construction",
    "wof:placetype":"venue"
},
  "geometry": {"coordinates":[-97.50371,35.431455],"type":"Point"}
}