{
  "type": "Feature",
  "properties": {
    "iso:country":"US",
    "sg:address":"1217 Circle Dr",
    "sg:city":"Sapulpa",
    "sg:classifiers":[
        {
            "category":"Building & Trades",
            "subcategory":"Construction",
            "type":"Services"
        }
    ],
    "sg:phone":"+1 918 224 2602",
    "sg:postcode":"74066",
    "sg:province":"OK",
    "sg:tags":[
        "house"
    ],
    "wof:name":"Kp Construction",
    "wof:placetype":"venue"
},
  "geometry": {"coordinates":[-96.093235,35.987381],"type":"Point"}
}