{
  "type": "Feature",
  "properties": {
    "addr:full":"6068 S Western Ave Oklahoma City OK 73139",
    "addr:housenumber":"6068",
    "addr:postcode":"73139",
    "addr:street":"S Western Ave",
    "iso:country":"US",
    "sg:address":"6068 S Western Ave",
    "sg:city":"Oklahoma City",
    "sg:classifiers":[
        {
            "category":"Shopping",
            "subcategory":"Florist",
            "type":"Retail Goods"
        }
    ],
    "sg:phone":"+1 405 636 1161",
    "sg:postcode":"73139",
    "sg:province":"OK",
    "wof:name":"Array of Flowers & Gifts Inc",
    "wof:placetype":"venue"
},
  "geometry": {"coordinates":[-97.530108,35.405932],"type":"Point"}
}