{
  "type": "Feature",
  "properties": {
    "iso:country":"US",
    "sg:address":"1100 Classen Dr",
    "sg:city":"Oklahoma City",
    "sg:classifiers":[
        {
            "category":"Professional",
            "subcategory":"Lawyer & Legal Services",
            "type":"Services"
        }
    ],
    "sg:phone":"+1 405 232 1106",
    "sg:postcode":"73103",
    "sg:province":"OK",
    "sg:tags":[
        "attorney"
    ],
    "wof:name":"John P Caporal",
    "wof:placetype":"venue"
},
  "geometry": {"coordinates":[-97.522643,35.480004],"type":"Point"}
}