{
  "type": "Feature",
  "properties": {
    "iso:country":"US",
    "sg:address":"1044 SW 44th St",
    "sg:city":"Oklahoma City",
    "sg:classifiers":[
        {
            "category":"Health Services",
            "subcategory":"Hospital",
            "type":"Services"
        }
    ],
    "sg:phone":"+1 405 631 3085",
    "sg:postcode":"73109",
    "sg:province":"OK",
    "wof:name":"Orthopedic Hospital",
    "wof:placetype":"venue"
},
  "geometry": {"coordinates":[-97.533807,35.420668],"type":"Point"}
}