{
  "type": "Feature",
  "properties": {
    "iso:country":"US",
    "sg:address":"4316 Northridge Rd",
    "sg:city":"Norman",
    "sg:classifiers":[
        {
            "category":"Banks & Credit Unions",
            "subcategory":"Investment Brokerage",
            "type":"Services"
        }
    ],
    "sg:phone":"+1 405 364 6920",
    "sg:postcode":"73072",
    "sg:province":"OK",
    "sg:tags":[
        "oil",
        "gas",
        "lease"
    ],
    "wof:name":"Rose Sam B Oil & Gas Prpts",
    "wof:placetype":"venue"
},
  "geometry": {"coordinates":[-97.505257,35.239116],"type":"Point"}
}