{
  "type": "Feature",
  "properties": {
    "addr:full":"1517 Cimarron Dr Stillwater OK 74075",
    "addr:housenumber":"1517",
    "addr:postcode":"74075",
    "addr:street":"Cimarron Dr",
    "iso:country":"US",
    "sg:address":"1517 Cimarron Dr",
    "sg:city":"Stillwater",
    "sg:classifiers":[
        {
            "category":"Retail",
            "subcategory":"Auto Repair",
            "type":"Services"
        }
    ],
    "sg:phone":"+1 405 372 0033",
    "sg:postcode":"74075",
    "sg:province":"OK",
    "sg:tags":[
        "repairing",
        "automobile"
    ],
    "wof:name":"Mike's Automotive",
    "wof:placetype":"venue"
},
  "geometry": {"coordinates":[-97.039086,36.133608],"type":"Point"}
}