{
  "type": "Feature",
  "properties": {
    "addr:full":"9822 S 233rd East Ave Broken Arrow OK 74014",
    "addr:housenumber":"9822",
    "addr:postcode":"74014",
    "addr:street":"S 233Rd East Ave",
    "iso:country":"US",
    "sg:address":"9822 S 233rd East Ave",
    "sg:city":"Broken Arrow",
    "sg:classifiers":[
        {
            "category":"Building & Trades",
            "subcategory":"Plumbing",
            "type":"Services"
        }
    ],
    "sg:phone":"+1 918 455 3463",
    "sg:postcode":"74014",
    "sg:province":"OK",
    "sg:tags":[
        "conditioning",
        "air",
        "system",
        "contractor"
    ],
    "wof:name":"County Line Heating & Air Cond",
    "wof:placetype":"venue"
},
  "geometry": {"coordinates":[-95.717967,36.018746],"type":"Point"}
}