{
  "type": "Feature",
  "properties": {
    "iso:country":"US",
    "sg:address":"1015 N Shartel Ave",
    "sg:city":"Oklahoma City",
    "sg:classifiers":[
        {
            "category":"Health Services",
            "subcategory":"Nursing And Care Facility",
            "type":"Services"
        },
        {
            "category":"Health Services",
            "subcategory":"Clinic",
            "type":"Services"
        }
    ],
    "sg:phone":"+1 405 602 6473",
    "sg:postcode":"73102",
    "sg:province":"OK",
    "sg:tags":[
        "hospice",
        "home",
        "patient"
    ],
    "wof:name":"Preferred Hospice Care",
    "wof:placetype":"venue"
},
  "geometry": {"coordinates":[-97.525691,35.478572],"type":"Point"}
}