{
  "type": "Feature",
  "properties": {
    "addr:full":"519 Rimrock Rd Edmond OK 73034",
    "addr:housenumber":"519",
    "addr:postcode":"73034",
    "addr:street":"Rimrock Rd",
    "iso:country":"US",
    "sg:address":"519 Rimrock Rd",
    "sg:city":"Edmond",
    "sg:classifiers":[
        {
            "category":"Home & Garden",
            "subcategory":"Home Furnishings",
            "type":"Retail Goods"
        }
    ],
    "sg:phone":"+1 405 340 1247",
    "sg:postcode":"73034",
    "sg:province":"OK",
    "wof:name":"Pamperd Chf Indpndt Ktchn Cnst",
    "wof:placetype":"venue"
},
  "geometry": {"coordinates":[-97.43907299999999,35.648556],"type":"Point"}
}