{
  "type": "Feature",
  "properties": {
    "iso:country":"US",
    "sg:address":"8800 S Pennsylvania Ave",
    "sg:city":"Oklahoma City",
    "sg:classifiers":[
        {
            "category":"Real Estate",
            "subcategory":"Real Estate Agent",
            "type":"Services"
        }
    ],
    "sg:phone":"+1 405 688 4061",
    "sg:postcode":"73159",
    "sg:province":"OK",
    "sg:tags":[
        "appraiser"
    ],
    "wof:name":"A Better Appraisal Co",
    "wof:placetype":"venue"
},
  "geometry": {"coordinates":[-97.547997,35.377131],"type":"Point"}
}