{
  "type": "Feature",
  "properties": {
    "iso:country":"US",
    "sg:address":"7420 NW 85th St",
    "sg:city":"Oklahoma City",
    "sg:classifiers":[
        {
            "category":"Professional",
            "subcategory":"Research",
            "type":"Services"
        }
    ],
    "sg:phone":"+1 405 773 0046",
    "sg:postcode":"73132",
    "sg:province":"OK",
    "sg:tags":[
        "environmental",
        "ecological"
    ],
    "wof:name":"Environmental Water Solutions",
    "wof:placetype":"venue"
},
  "geometry": {"coordinates":[-97.646004,35.557635],"type":"Point"}
}