{
  "type": "Feature",
  "properties": {
    "addr:full":"1200 N 9th Ave Purcell OK 73080",
    "addr:housenumber":"1200",
    "addr:postcode":"73080",
    "addr:street":"N 9Th Ave",
    "iso:country":"US",
    "sg:address":"1200 N 9th Ave",
    "sg:city":"Purcell",
    "sg:classifiers":[
        {
            "category":"Real Estate",
            "subcategory":"Real Estate Operator",
            "type":"Services"
        }
    ],
    "sg:phone":"+1 405 527 4966",
    "sg:postcode":"73080",
    "sg:province":"OK",
    "sg:tags":[
        "apartment"
    ],
    "wof:name":"Purcell Village Apartments",
    "wof:placetype":"venue"
},
  "geometry": {"coordinates":[-97.370993,35.02715],"type":"Point"}
}