{
  "type": "Feature",
  "properties": {
    "addr:full":"322 S Eastern Ave Hominy OK 74035",
    "addr:housenumber":"322",
    "addr:postcode":"74035",
    "addr:street":"S Eastern Ave",
    "iso:country":"US",
    "sg:address":"322 S Eastern Ave",
    "sg:city":"Hominy",
    "sg:classifiers":[
        {
            "category":"Retail",
            "subcategory":"Auto Repair",
            "type":"Services"
        }
    ],
    "sg:phone":"+1 918 885 6414",
    "sg:postcode":"74035",
    "sg:province":"OK",
    "sg:tags":[
        "repairing",
        "automobile"
    ],
    "wof:name":"John's Automotive Repair",
    "wof:placetype":"venue"
},
  "geometry": {"coordinates":[-96.38951400000001,36.413022],"type":"Point"}
}