{
  "type": "Feature",
  "properties": {
    "iso:country":"US",
    "sg:address":"210 Park Ave",
    "sg:city":"Oklahoma City",
    "sg:classifiers":[
        {
            "category":"Utilities",
            "subcategory":"Natural Gas",
            "type":"Services"
        }
    ],
    "sg:phone":"+1 405 605 3803",
    "sg:postcode":"73102",
    "sg:province":"OK",
    "wof:name":"Duke Energy Field Svc",
    "wof:placetype":"venue"
},
  "geometry": {"coordinates":[-97.517831,35.468767],"type":"Point"}
}