{
  "type": "Feature",
  "properties": {
    "iso:country":"US",
    "sg:address":"6601 Broadway Exd",
    "sg:city":"Oklahoma City",
    "sg:classifiers":[
        {
            "category":"Banks & Credit Unions",
            "subcategory":"Bank",
            "type":"Services"
        }
    ],
    "sg:phone":"+1 405 842 0743",
    "sg:postcode":"73116",
    "sg:province":"OK",
    "sg:tags":[
        "mortgage",
        "loan",
        "broker",
        "real estate"
    ],
    "wof:name":"Millennium Financial Group Inc",
    "wof:placetype":"venue"
},
  "geometry": {"coordinates":[-97.51389399999999,35.547105],"type":"Point"}
}