{
  "type": "Feature",
  "properties": {
    "addr:full":"1450 Cradduck Rd Ada OK 74820",
    "addr:housenumber":"1450",
    "addr:postcode":"74820",
    "addr:street":"Cradduck Rd",
    "iso:country":"US",
    "sg:address":"1450 Cradduck Rd",
    "sg:city":"Ada",
    "sg:classifiers":[
        {
            "category":"Arts & Performance",
            "subcategory":"Theater",
            "type":"Entertainment"
        }
    ],
    "sg:phone":"+1 580 436 2282",
    "sg:postcode":"74820",
    "sg:province":"OK",
    "wof:name":"Act II Inc",
    "wof:placetype":"venue"
},
  "geometry": {"coordinates":[-96.662423,34.760045],"type":"Point"}
}