{
  "type": "Feature",
  "properties": {
    "iso:country":"US",
    "sg:address":"5512 NE 2nd St",
    "sg:city":"Oklahoma City",
    "sg:classifiers":[
        {
            "category":"Real Estate",
            "subcategory":"Real Estate Agent",
            "type":"Services"
        }
    ],
    "sg:phone":"+1 405 670 2644",
    "sg:postcode":"73117",
    "sg:province":"OK",
    "wof:name":"One North Sooner Road Indus Pk",
    "wof:placetype":"venue"
},
  "geometry": {"coordinates":[-97.424077,35.466999],"type":"Point"}
}