{
  "type": "Feature",
  "properties": {
    "addr:full":"2205 N Portland Ave Oklahoma City OK 73107",
    "addr:housenumber":"2205",
    "addr:postcode":"73107",
    "addr:street":"N Portland Ave",
    "iso:country":"US",
    "sg:address":"2205 N Portland Ave",
    "sg:city":"Oklahoma City",
    "sg:classifiers":[
        {
            "category":"Organizations",
            "subcategory":"Community Association",
            "type":"Services"
        }
    ],
    "sg:phone":"+1 405 948 7789",
    "sg:postcode":"73107",
    "sg:province":"OK",
    "sg:tags":[
        "fraternal"
    ],
    "wof:name":"IOOF",
    "wof:placetype":"venue"
},
  "geometry": {"coordinates":[-97.58344200000001,35.492246],"type":"Point"}
}