{
  "type": "Feature",
  "properties": {
    "iso:country":"US",
    "sg:address":"8494 NW Expy",
    "sg:city":"Oklahoma City",
    "sg:classifiers":[
        {
            "category":"Personal",
            "subcategory":"Beauty Salon",
            "type":"Services"
        }
    ],
    "sg:phone":"+1 405 722 4499",
    "sg:postcode":"73162",
    "sg:province":"OK",
    "sg:tags":[
        "school"
    ],
    "wof:name":"Central State Beauty Academy",
    "wof:placetype":"venue"
},
  "geometry": {"coordinates":[-97.671096,35.572044],"type":"Point"}
}