{
  "type": "Feature",
  "properties": {
    "iso:country":"US",
    "sg:address":"315 E Gray St",
    "sg:city":"Norman",
    "sg:classifiers":[
        {
            "category":"Retail",
            "subcategory":"Auto Repair",
            "type":"Services"
        }
    ],
    "sg:phone":"+1 405 364 6477",
    "sg:postcode":"73069",
    "sg:province":"OK",
    "sg:tags":[
        "body"
    ],
    "wof:name":"Norman Body Works Inc",
    "wof:placetype":"venue"
},
  "geometry": {"coordinates":[-97.43994000000001,35.223639],"type":"Point"}
}