{
  "type": "Feature",
  "properties": {
    "iso:country":"US",
    "sg:address":"120 W Central St",
    "sg:city":"Fairview",
    "sg:phone":"+1 580 227 3729",
    "sg:postcode":"73737",
    "sg:province":"OK",
    "sg:tags":[
        "distributor",
        "oil",
        "marketer"
    ],
    "wof:name":"Frontier Trucking Inc",
    "wof:placetype":"venue"
},
  "geometry": {"coordinates":[-98.48027399999999,36.267999],"type":"Point"}
}