{
  "type": "Feature",
  "properties": {
    "iso:country":"US",
    "sg:address":"3749 E 46th Pl",
    "sg:city":"Tulsa",
    "sg:classifiers":[
        {
            "category":"Professional",
            "type":"Services"
        }
    ],
    "sg:phone":"+1 918 742 9757",
    "sg:postcode":"74135",
    "sg:province":"OK",
    "sg:tags":[
        "geophysicist"
    ],
    "wof:name":"Rasmussen & Associates",
    "wof:placetype":"venue"
},
  "geometry": {"coordinates":[-95.931695,36.097295],"type":"Point"}
}