{
  "type": "Feature",
  "properties": {
    "iso:country":"US",
    "sg:address":"4300 Brookfield Dr",
    "sg:city":"Norman",
    "sg:classifiers":[
        {
            "category":"Banks & Credit Unions",
            "subcategory":"Financial Services",
            "type":"Services"
        }
    ],
    "sg:phone":"+1 405 364 0446",
    "sg:postcode":"73072",
    "sg:province":"OK",
    "sg:tags":[
        "company",
        "holding"
    ],
    "wof:name":"Chm Holdings LLC",
    "wof:placetype":"venue"
},
  "geometry": {"coordinates":[-97.503653,35.243236],"type":"Point"}
}