{
  "type": "Feature",
  "properties": {
    "addr:full":"4415 N Western Ave Oklahoma City OK 73118",
    "addr:housenumber":"4415",
    "addr:postcode":"73118",
    "addr:street":"N Western Ave",
    "iso:country":"US",
    "sg:address":"4415 N Western Ave",
    "sg:city":"Oklahoma City",
    "sg:classifiers":[
        {
            "category":"Autos & Motor Vehicles",
            "subcategory":"Motorcycle Sales",
            "type":"Retail Goods"
        }
    ],
    "sg:phone":"+1 405 605 3789",
    "sg:postcode":"73118",
    "sg:province":"OK",
    "sg:tags":[
        "scooter"
    ],
    "wof:name":"Atomic Brown Scooter Shop",
    "wof:placetype":"venue"
},
  "geometry": {"coordinates":[-97.529832,35.516024],"type":"Point"}
}