{
  "type": "Feature",
  "properties": {
    "addr:full":"10962 N May Ave Oklahoma City OK 73120",
    "addr:housenumber":"10962",
    "addr:postcode":"73120",
    "addr:street":"N May Ave",
    "iso:country":"US",
    "sg:address":"10962 N May Ave",
    "sg:city":"Oklahoma City",
    "sg:classifiers":[
        {
            "category":"Food & Beverages",
            "subcategory":"Specialty",
            "type":"Retail Goods"
        }
    ],
    "sg:phone":"+1 405 842 2770",
    "sg:postcode":"73120",
    "sg:province":"OK",
    "sg:tags":[
        "health",
        "diet"
    ],
    "wof:name":"General Nutrition Ctr",
    "wof:placetype":"venue"
},
  "geometry": {"coordinates":[-97.56711300000001,35.580508],"type":"Point"}
}