{
  "type": "Feature",
  "properties": {
    "iso:country":"US",
    "sg:address":"618 S Air Depot Blvd",
    "sg:city":"Oklahoma City",
    "sg:classifiers":[
        {
            "category":"Restaurant",
            "type":"Food & Drink"
        }
    ],
    "sg:menulink":"http://www.allmenus.com/ok/oklahoma-city/230846-cocina-de-mino-mexican-restaurant/menu/",
    "sg:phone":"+1 405 741 6735",
    "sg:postcode":"73110",
    "sg:province":"OK",
    "sg:tags":[
        "mexican"
    ],
    "wof:name":"Cocina De Mino Mexican Restaurant",
    "wof:placetype":"venue"
},
  "geometry": {"coordinates":[-97.405489,35.458278],"type":"Point"}
}