{
  "type": "Feature",
  "properties": {
    "addr:full":"415 E Main St Shawnee OK 74801",
    "addr:housenumber":"415",
    "addr:postcode":"74801",
    "addr:street":"E Main St",
    "iso:country":"US",
    "sg:address":"415 E Main St",
    "sg:city":"Shawnee",
    "sg:classifiers":[
        {
            "category":"Local Transit",
            "type":"Transportation"
        }
    ],
    "sg:phone":"+1 405 275 6988",
    "sg:postcode":"74801",
    "sg:province":"OK",
    "sg:tags":[
        "shuttle"
    ],
    "wof:name":"Sahwnee Veterans Shuttle Inc",
    "wof:placetype":"venue"
},
  "geometry": {"coordinates":[-96.91825300000001,35.327294],"type":"Point"}
}