{
  "type": "Feature",
  "properties": {
    "iso:country":"US",
    "sg:address":"3406 S Boulevard St",
    "sg:city":"Edmond",
    "sg:classifiers":[
        {
            "category":"Shopping",
            "subcategory":"Computers & Home Electronics",
            "type":"Retail Goods"
        }
    ],
    "sg:phone":"+1 405 348 8463",
    "sg:postcode":"73013",
    "sg:province":"OK",
    "wof:name":"Radio Shack",
    "wof:placetype":"venue"
},
  "geometry": {"coordinates":[-97.478165,35.619572],"type":"Point"}
}