{
  "type": "Feature",
  "properties": {
    "addr:full":"1489 E 15th St Edmond OK 73013",
    "addr:housenumber":"1489",
    "addr:postcode":"73013",
    "addr:street":"E 15Th St",
    "iso:country":"US",
    "sg:address":"1489 E 15th St",
    "sg:city":"Edmond",
    "sg:classifiers":[
        {
            "category":"Coffee & Tea",
            "type":"Food & Drink"
        }
    ],
    "sg:menulink":"http://www.allmenus.com/ok/oklahoma-city/119170-starbucks-coffee/menu/",
    "sg:phone":"+1 405 340 6854",
    "sg:postcode":"73013",
    "sg:province":"OK",
    "sg:tags":[
        "american"
    ],
    "wof:name":"Starbucks Coffee",
    "wof:placetype":"venue"
},
  "geometry": {"coordinates":[-97.459721,35.638282],"type":"Point"}
}