{
  "type": "Feature",
  "properties": {
    "iso:country":"US",
    "sg:address":"1635 E 37th St",
    "sg:city":"Tulsa",
    "sg:classifiers":[
        {
            "category":"Building & Trades",
            "subcategory":"Equipment Rental",
            "type":"Services"
        }
    ],
    "sg:phone":"+1 918 293 9239",
    "sg:postcode":"74105",
    "sg:province":"OK",
    "sg:tags":[
        "yard",
        "leasing",
        "store"
    ],
    "wof:name":"Jfc Leasing",
    "wof:placetype":"venue"
},
  "geometry": {"coordinates":[-95.967891,36.109217],"type":"Point"}
}