{
  "type": "Feature",
  "properties": {
    "addr:full":"4721 W 6th Ave Stillwater OK 74074",
    "addr:housenumber":"4721",
    "addr:postcode":"74074",
    "addr:street":"W 6Th Ave",
    "iso:country":"US",
    "sg:address":"4721 W 6th Ave",
    "sg:city":"Stillwater",
    "sg:classifiers":[
        {
            "category":"Banks & Credit Unions",
            "subcategory":"Investment Brokerage",
            "type":"Services"
        }
    ],
    "sg:phone":"+1 405 372 8472",
    "sg:postcode":"74074",
    "sg:province":"OK",
    "sg:tags":[
        "security"
    ],
    "wof:name":"Edward Jones Co",
    "wof:placetype":"venue"
},
  "geometry": {"coordinates":[-97.121042,36.115744],"type":"Point"}
}