{
  "type": "Feature",
  "properties": {
    "iso:country":"US",
    "sg:address":"1320 N Grand Blvd",
    "sg:city":"Duncan",
    "sg:classifiers":[
        {
            "category":"Home & Garden",
            "subcategory":"Building Materials",
            "type":"Retail Goods"
        }
    ],
    "sg:phone":"+1 405 364 1180",
    "sg:postcode":"73533",
    "sg:province":"OK",
    "sg:tags":[
        "door"
    ],
    "wof:name":"Windsor Door Siding & Window",
    "wof:placetype":"venue"
},
  "geometry": {"coordinates":[-97.961635,34.519531],"type":"Point"}
}