{
  "type": "Feature",
  "properties": {
    "iso:country":"US",
    "sg:address":"213 Park Ave",
    "sg:city":"Oklahoma City",
    "sg:classifiers":[
        {
            "category":"Restaurant",
            "type":"Food & Drink"
        }
    ],
    "sg:phone":"+1 405 235 8877",
    "sg:postcode":"73102",
    "sg:province":"OK",
    "sg:tags":[
        "eating"
    ],
    "wof:name":"Chick-Fil-A",
    "wof:placetype":"venue"
},
  "geometry": {"coordinates":[-97.51779999999999,35.468916],"type":"Point"}
}