{
  "type": "Feature",
  "properties": {
    "iso:country":"US",
    "sg:address":"4117 NW 122nd St",
    "sg:city":"Oklahoma City",
    "sg:classifiers":[
        {
            "category":"Banks & Credit Unions",
            "subcategory":"Bank",
            "type":"Services"
        }
    ],
    "sg:phone":"+1 405 752 8808",
    "sg:postcode":"73120",
    "sg:province":"OK",
    "sg:tags":[
        "loan",
        "mortgage",
        "real estate"
    ],
    "wof:name":"Crest Mortgage Company",
    "wof:placetype":"venue"
},
  "geometry": {"coordinates":[-97.596549,35.594722],"type":"Point"}
}