{
  "type": "Feature",
  "properties": {
    "iso:country":"US",
    "sg:address":"2915 W Britton Rd",
    "sg:city":"Oklahoma City",
    "sg:classifiers":[
        {
            "category":"Home & Garden",
            "subcategory":"Furniture",
            "type":"Retail Goods"
        }
    ],
    "sg:phone":"+1 405 751 9051",
    "sg:postcode":"73120",
    "sg:province":"OK",
    "wof:name":"Cunningham Interiors",
    "wof:placetype":"venue"
},
  "geometry": {"coordinates":[-97.569971,35.565759],"type":"Point"}
}