{
  "type": "Feature",
  "properties": {
    "iso:country":"US",
    "sg:address":"7227 S Memorial Dr",
    "sg:city":"Tulsa",
    "sg:classifiers":[
        {
            "category":"Restaurant",
            "type":"Food & Drink"
        }
    ],
    "sg:menulink":"http://www.allmenus.com/ok/tulsa/254589-lanna-thai/menu/",
    "sg:phone":"+1 918 249 5262",
    "sg:postcode":"74133",
    "sg:province":"OK",
    "sg:tags":[
        "thai",
        "asian"
    ],
    "wof:name":"Lanna Thai",
    "wof:placetype":"venue"
},
  "geometry": {"coordinates":[-95.885704,36.058846],"type":"Point"}
}