{
  "type": "Feature",
  "properties": {
    "iso:country":"US",
    "sg:address":"102 N Main St",
    "sg:city":"Guymon",
    "sg:classifiers":[
        {
            "category":"Wholesale",
            "subcategory":"Electrical",
            "type":"Manufacturing & Wholesale Goods"
        }
    ],
    "sg:phone":"+1 580 338 7763",
    "sg:postcode":"73942",
    "sg:province":"OK",
    "sg:tags":[
        "communication",
        "radio",
        "system"
    ],
    "sg:website":"www.gandgelectronics.com",
    "wof:name":"G & G Electronics",
    "wof:placetype":"venue"
},
  "geometry": {"coordinates":[-101.481595,36.678608],"type":"Point"}
}