{
  "type": "Feature",
  "properties": {
    "addr:full":"617 W 14th Pl Tulsa OK 74127",
    "addr:housenumber":"617",
    "addr:postcode":"74127",
    "addr:street":"W 14Th Pl",
    "iso:country":"US",
    "sg:address":"617 W 14th Pl",
    "sg:city":"Tulsa",
    "sg:classifiers":[
        {
            "category":"Wholesale",
            "subcategory":"Machinery & Supplies",
            "type":"Manufacturing & Wholesale Goods"
        }
    ],
    "sg:phone":"+1 918 585 5045",
    "sg:postcode":"74127",
    "sg:province":"OK",
    "sg:tags":[
        "equipment",
        "material",
        "handling"
    ],
    "wof:name":"Positech",
    "wof:placetype":"venue"
},
  "geometry": {"coordinates":[-95.99703700000001,36.141603],"type":"Point"}
}