{
  "type": "Feature",
  "properties": {
    "addr:full":"1108 SW Tennessee Ave Lawton OK 73501",
    "addr:housenumber":"1108",
    "addr:postcode":"73501",
    "addr:street":"Sw Tennessee Ave",
    "iso:country":"US",
    "sg:address":"1108 SW Tennessee Ave",
    "sg:city":"Lawton",
    "sg:classifiers":[
        {
            "category":"Organizations",
            "subcategory":"Religious Organization",
            "type":"Services"
        }
    ],
    "sg:phone":"+1 580 357 5288",
    "sg:postcode":"73501",
    "sg:province":"OK",
    "sg:tags":[
        "school",
        "bible",
        "study"
    ],
    "wof:name":"Zoe Christian Ctr Church",
    "wof:placetype":"venue"
},
  "geometry": {"coordinates":[-98.406126,34.582711],"type":"Point"}
}