{
  "type": "Feature",
  "properties": {
    "iso:country":"US",
    "sg:address":"100 N Cheyenne Ave",
    "sg:city":"Bartlesville",
    "sg:classifiers":[
        {
            "category":"Utilities",
            "subcategory":"Refuse",
            "type":"Services"
        }
    ],
    "sg:phone":"+1 918 336 5828",
    "sg:postcode":"74003",
    "sg:province":"OK",
    "sg:tags":[
        "system"
    ],
    "wof:name":"A B C Recycling",
    "wof:placetype":"venue"
},
  "geometry": {"coordinates":[-95.985959,36.755331],"type":"Point"}
}