{
  "type": "Feature",
  "properties": {
    "addr:full":"10520 E Charter Oak Rd Meridian OK 73058",
    "addr:housenumber":"10520 e",
    "addr:postcode":"73058",
    "addr:street":"Charter Oak Rd",
    "iso:country":"US",
    "sg:address":"10520 E Charter Oak Rd",
    "sg:city":"Meridian",
    "sg:classifiers":[
        {
            "category":"Building & Trades",
            "subcategory":"Landscaping Services",
            "type":"Services"
        }
    ],
    "sg:phone":"+1 405 834 3201",
    "sg:postcode":"73058",
    "sg:province":"OK",
    "sg:tags":[
        "designer",
        "landscape"
    ],
    "wof:name":"Aspen Gardens Landscaping",
    "wof:placetype":"venue"
},
  "geometry": {"coordinates":[-97.294539,35.7541],"type":"Point"}
}