{
  "type": "Feature",
  "properties": {
    "iso:country":"US",
    "sg:address":"2505 N Little Ave",
    "sg:city":"Cushing",
    "sg:classifiers":[
        {
            "category":"Building & Trades",
            "subcategory":"Construction",
            "type":"Services"
        }
    ],
    "sg:phone":"+1 918 225 1833",
    "sg:postcode":"74023",
    "sg:province":"OK",
    "sg:tags":[
        "pipe",
        "line",
        "contractor"
    ],
    "wof:name":"Mills Construction & Welding",
    "wof:placetype":"venue"
},
  "geometry": {"coordinates":[-96.767673,36.001656],"type":"Point"}
}