{
  "type": "Feature",
  "properties": {
    "iso:country":"US",
    "sg:address":"5801 NW Grand Blvd",
    "sg:city":"Oklahoma City",
    "sg:phone":"+1 405 415 0090",
    "sg:postcode":"73118",
    "sg:province":"OK",
    "sg:tags":[
        "oil"
    ],
    "wof:name":"Fuel Man",
    "wof:placetype":"venue"
},
  "geometry": {"coordinates":[-97.53013900000001,35.531514],"type":"Point"}
}