{
  "type": "Feature",
  "properties": {
    "iso:country":"US",
    "sg:address":"511 S Broadway",
    "sg:city":"Edmond",
    "sg:classifiers":[
        {
            "category":"Restaurant",
            "type":"Food & Drink"
        }
    ],
    "sg:phone":"+1 405 341 8337",
    "sg:postcode":"73034",
    "sg:province":"OK",
    "sg:tags":[
        "eating"
    ],
    "wof:name":"Mandarin Express",
    "wof:placetype":"venue"
},
  "geometry": {"coordinates":[-97.481995,35.649483],"type":"Point"}
}