{
  "type": "Feature",
  "properties": {
    "iso:country":"US",
    "sg:address":"411 Foster Pl",
    "sg:city":"Oklahoma City",
    "sg:classifiers":[
        {
            "category":"Retail",
            "subcategory":"Auto Repair",
            "type":"Services"
        }
    ],
    "sg:phone":"+1 405 741 1155",
    "sg:postcode":"73110",
    "sg:province":"OK",
    "sg:tags":[
        "shop",
        "automotive"
    ],
    "wof:name":"Mid-Del Auto Repair",
    "wof:placetype":"venue"
},
  "geometry": {"coordinates":[-97.406229,35.443425],"type":"Point"}
}