{
  "type": "Feature",
  "properties": {
    "addr:full":"404 NW 2nd St Buffalo OK 73834",
    "addr:housenumber":"404",
    "addr:postcode":"73834",
    "addr:street":"Nw 2Nd St",
    "iso:country":"US",
    "sg:address":"404 NW 2nd St",
    "sg:city":"Buffalo",
    "sg:classifiers":[
        {
            "category":"Personal",
            "subcategory":"Beauty Salon",
            "type":"Services"
        }
    ],
    "sg:phone":"+1 580 735 2996",
    "sg:postcode":"73834",
    "sg:province":"OK",
    "sg:tags":[
        "shop"
    ],
    "wof:name":"Headquarters",
    "wof:placetype":"venue"
},
  "geometry": {"coordinates":[-99.632316,36.839098],"type":"Point"}
}