{
  "type": "Feature",
  "properties": {
    "iso:country":"US",
    "sg:address":"12 NE 3rd St",
    "sg:city":"Oklahoma City",
    "sg:classifiers":[
        {
            "category":"Retail",
            "subcategory":"Auto Repair",
            "type":"Services"
        }
    ],
    "sg:phone":"+1 405 232 4248",
    "sg:postcode":"73104",
    "sg:province":"OK",
    "sg:tags":[
        "repairing",
        "automobile",
        "body",
        "general"
    ],
    "wof:name":"Ruedy's Auto Shop Inc",
    "wof:placetype":"venue"
},
  "geometry": {"coordinates":[-97.510657,35.470667],"type":"Point"}
}