{
  "type": "Feature",
  "properties": {
    "iso:country":"US",
    "sg:address":"6100 SE 61st St",
    "sg:city":"Oklahoma City",
    "sg:classifiers":[
        {
            "category":"Professional",
            "type":"Services"
        }
    ],
    "sg:phone":"+1 405 737 3061",
    "sg:postcode":"73135",
    "sg:province":"OK",
    "wof:name":"Hilbert Mail Service",
    "wof:placetype":"venue"
},
  "geometry": {"coordinates":[-97.415709,35.404355],"type":"Point"}
}