{
  "type": "Feature",
  "properties": {
    "addr:full":"5075 S Yale Ave Tulsa OK 74135",
    "addr:housenumber":"5075",
    "addr:postcode":"74135",
    "addr:street":"S Yale Ave",
    "iso:country":"US",
    "sg:address":"5075 S Yale Ave",
    "sg:city":"Tulsa",
    "sg:classifiers":[
        {
            "category":"Restaurant",
            "type":"Food & Drink"
        }
    ],
    "sg:menulink":"http://www.allmenus.com/ok/tulsa/136754-smoothie-king/menu/",
    "sg:phone":"+1 918 622 2224",
    "sg:postcode":"74135",
    "sg:province":"OK",
    "sg:tags":[
        "smoothy",
        "juice",
        "american"
    ],
    "wof:name":"Smoothie King",
    "wof:placetype":"venue"
},
  "geometry": {"coordinates":[-95.922164,36.090032],"type":"Point"}
}