{
  "type": "Feature",
  "properties": {
    "iso:country":"US",
    "sg:address":"608 E Charles Page Blvd",
    "sg:city":"Sand Springs",
    "sg:classifiers":[
        {
            "category":"Banks & Credit Unions",
            "subcategory":"Bank",
            "type":"Services"
        }
    ],
    "sg:phone":"+1 918 245 0777",
    "sg:postcode":"74063",
    "sg:province":"OK",
    "sg:tags":[
        "cashing",
        "check"
    ],
    "wof:name":"National Quik Cash",
    "wof:placetype":"venue"
},
  "geometry": {"coordinates":[-96.100658,36.13673],"type":"Point"}
}