{
  "type": "Feature",
  "properties": {
    "iso:country":"US",
    "sg:address":"941 SW 22nd St",
    "sg:city":"Oklahoma City",
    "sg:classifiers":[
        {
            "category":"Building & Trades",
            "subcategory":"Equipment Rental",
            "type":"Services"
        }
    ],
    "sg:phone":"+1 405 632 5683",
    "sg:postcode":"73109",
    "sg:province":"OK",
    "sg:tags":[
        "aircraft",
        "leasing",
        "charter"
    ],
    "sg:website":"www.interstatehelicopters.com",
    "wof:name":"Interstate Helicopters",
    "wof:placetype":"venue"
},
  "geometry": {"coordinates":[-97.536113,35.442534],"type":"Point"}
}