{
  "type": "Feature",
  "properties": {
    "iso:country":"US",
    "sg:address":"6612 NW 38th St",
    "sg:city":"Bethany",
    "sg:classifiers":[
        {
            "category":"Government",
            "subcategory":"Post Office",
            "type":"Public Place"
        }
    ],
    "sg:phone":"+1 405 000 1111",
    "sg:postcode":"73008",
    "sg:province":"OK",
    "wof:name":"US Post Office",
    "wof:placetype":"venue"
},
  "geometry": {"coordinates":[-97.628995,35.510133],"type":"Point"}
}