{
  "type": "Feature",
  "properties": {
    "iso:country":"US",
    "sg:address":"12319 N Rockwell Ave",
    "sg:city":"Oklahoma City",
    "sg:classifiers":[
        {
            "category":"Personal",
            "subcategory":"Beauty Salon",
            "type":"Services"
        }
    ],
    "sg:phone":"+1 405 720 1087",
    "sg:postcode":"73142",
    "sg:province":"OK",
    "sg:tags":[
        "manicuring"
    ],
    "wof:name":"Sugar Shack",
    "wof:placetype":"venue"
},
  "geometry": {"coordinates":[-97.638551,35.597368],"type":"Point"}
}