{
  "type": "Feature",
  "properties": {
    "addr:full":"12319 N Rockwell Ave Oklahoma City OK 73142",
    "addr:housenumber":"12319",
    "addr:postcode":"73142",
    "addr:street":"N Rockwell Ave",
    "iso:country":"US",
    "sg:address":"12319 N Rockwell Ave",
    "sg:city":"Oklahoma City",
    "sg:classifiers":[
        {
            "category":"Personal",
            "subcategory":"Beauty Salon",
            "type":"Services"
        }
    ],
    "sg:phone":"+1 405 720 1087",
    "sg:postcode":"73142",
    "sg:province":"OK",
    "sg:tags":[
        "manicuring"
    ],
    "wof:name":"Sugar Shack",
    "wof:placetype":"venue"
},
  "geometry": {"coordinates":[-97.63855100000001,35.597368],"type":"Point"}
}