{
  "type": "Feature",
  "properties": {
    "addr:full":"3705 NW 52nd St Oklahoma City OK 73112",
    "addr:housenumber":"3705",
    "addr:postcode":"73112",
    "addr:street":"Nw 52Nd St",
    "iso:country":"US",
    "sg:address":"3705 NW 52nd St",
    "sg:city":"Oklahoma City",
    "sg:classifiers":[
        {
            "category":"Building & Trades",
            "subcategory":"Plumbing",
            "type":"Services"
        }
    ],
    "sg:phone":"+1 405 942 3426",
    "sg:postcode":"73112",
    "sg:province":"OK",
    "sg:tags":[
        "contractor"
    ],
    "wof:name":"Dewey Osburn Heating & AC",
    "wof:placetype":"venue"
},
  "geometry": {"coordinates":[-97.58626,35.524922],"type":"Point"}
}