{
  "type": "Feature",
  "properties": {
    "iso:country":"US",
    "sg:address":"2917 N Glade Ave",
    "sg:city":"Bethany",
    "sg:classifiers":[
        {
            "category":"Food & Beverages",
            "subcategory":"Specialty",
            "type":"Retail Goods"
        }
    ],
    "sg:phone":"+1 405 787 6697",
    "sg:postcode":"73008",
    "sg:province":"OK",
    "sg:tags":[
        "grocery"
    ],
    "wof:name":"Hamilton Sellers Enterprises",
    "wof:placetype":"venue"
},
  "geometry": {"coordinates":[-97.645512,35.499684],"type":"Point"}
}