{
  "type": "Feature",
  "properties": {
    "iso:country":"US",
    "sg:address":"300 N Mississippi Ave",
    "sg:city":"Atoka",
    "sg:classifiers":[
        {
            "category":"Manufacturing",
            "subcategory":"Signs",
            "type":"Manufacturing & Wholesale Goods"
        }
    ],
    "sg:phone":"+1 580 889 3837",
    "sg:postcode":"74525",
    "sg:province":"OK",
    "wof:name":"Signs Unlimited",
    "wof:placetype":"venue"
},
  "geometry": {"coordinates":[-96.126692,34.389717],"type":"Point"}
}