{
  "type": "Feature",
  "properties": {
    "iso:country":"US",
    "sg:address":"1862 Rolling Hills St",
    "sg:city":"Norman",
    "sg:classifiers":[
        {
            "category":"Arts & Performance",
            "subcategory":"Theater",
            "type":"Entertainment"
        }
    ],
    "sg:phone":"+1 405 321 4216",
    "sg:postcode":"73072",
    "sg:province":"OK",
    "sg:tags":[
        "group"
    ],
    "wof:name":"Talk of The Town Orchestra",
    "wof:placetype":"venue"
},
  "geometry": {"coordinates":[-97.469003,35.196088],"type":"Point"}
}