{
  "type": "Feature",
  "properties": {
    "iso:country":"US",
    "sg:address":"611 W Wabash Ave",
    "sg:city":"Enid",
    "sg:classifiers":[
        {
            "category":"Education",
            "subcategory":"School",
            "type":"Public Place"
        }
    ],
    "sg:phone":"+1 580 234 2404",
    "sg:postcode":"73701",
    "sg:province":"OK",
    "wof:name":"Enid High School",
    "wof:placetype":"venue"
},
  "geometry": {"coordinates":[-97.886396,36.388688],"type":"Point"}
}