{
  "type": "Feature",
  "properties": {
    "addr:full":"11103 Murray Dr Guthrie OK 73044",
    "addr:housenumber":"11103",
    "addr:postcode":"73044",
    "addr:street":"Murray Dr",
    "iso:country":"US",
    "sg:address":"11103 Murray Dr",
    "sg:city":"Guthrie",
    "sg:classifiers":[
        {
            "category":"Professional",
            "type":"Services"
        }
    ],
    "sg:phone":"+1 405 282 8003",
    "sg:postcode":"73044",
    "sg:province":"OK",
    "wof:name":"Tropical Pool Service Inc",
    "wof:placetype":"venue"
},
  "geometry": {"coordinates":[-97.479392,35.768969],"type":"Point"}
}