{
  "type": "Feature",
  "properties": {
    "addr:full":"6410 N May Ave Oklahoma City OK 73116",
    "addr:housenumber":"6410",
    "addr:postcode":"73116",
    "addr:street":"N May Ave",
    "iso:country":"US",
    "sg:address":"6410 N May Ave",
    "sg:city":"Oklahoma City",
    "sg:classifiers":[
        {
            "category":"Shopping",
            "subcategory":"Computers & Home Electronics",
            "type":"Retail Goods"
        }
    ],
    "sg:phone":"+1 405 879 2300",
    "sg:postcode":"73116",
    "sg:province":"OK",
    "sg:tags":[
        "equipment",
        "dealer"
    ],
    "wof:name":"Compusa",
    "wof:placetype":"venue"
},
  "geometry": {"coordinates":[-97.565619,35.536573],"type":"Point"}
}