{
  "type": "Feature",
  "properties": {
    "iso:country":"US",
    "sg:address":"7172 Melrose Ln",
    "sg:city":"Oklahoma City",
    "sg:classifiers":[
        {
            "category":"Manufacturing",
            "subcategory":"Printing",
            "type":"Manufacturing & Wholesale Goods"
        }
    ],
    "sg:phone":"+1 405 495 0050",
    "sg:postcode":"73127",
    "sg:province":"OK",
    "sg:tags":[
        "label"
    ],
    "wof:name":"High Quality Labels Inc",
    "wof:placetype":"venue"
},
  "geometry": {"coordinates":[-97.642039,35.471521],"type":"Point"}
}