{
  "type": "Feature",
  "properties": {
    "iso:country":"US",
    "sg:address":"114 E 5th St",
    "sg:city":"Tulsa",
    "sg:classifiers":[
        {
            "category":"Food & Beverages",
            "subcategory":"Groceries & Convenience Stores",
            "type":"Retail Goods"
        }
    ],
    "sg:phone":"+1 918 584 5291",
    "sg:postcode":"74103",
    "sg:province":"OK",
    "sg:tags":[
        "petroleum",
        "refiner"
    ],
    "wof:name":"Anchor Gasoline Corporation",
    "wof:placetype":"venue"
},
  "geometry": {"coordinates":[-95.987831,36.152159],"type":"Point"}
}