{
  "type": "Feature",
  "properties": {
    "iso:country":"US",
    "sg:address":"28 NW 10th St",
    "sg:city":"Oklahoma City",
    "sg:classifiers":[
        {
            "category":"Wholesale",
            "subcategory":"Machinery & Supplies",
            "type":"Manufacturing & Wholesale Goods"
        }
    ],
    "sg:phone":"+1 405 236 3438",
    "sg:postcode":"73103",
    "sg:province":"OK",
    "sg:tags":[
        "cleaners",
        "janitorial",
        "vacuum"
    ],
    "wof:name":"Non-Mar Co The",
    "wof:placetype":"venue"
},
  "geometry": {"coordinates":[-97.513561,35.478063],"type":"Point"}
}