{
  "type": "Feature",
  "properties": {
    "addr:full":"2900 Chautauqua Ave Norman OK 73072",
    "addr:housenumber":"2900",
    "addr:postcode":"73072",
    "addr:street":"Chautauqua Ave",
    "iso:country":"US",
    "sg:address":"2900 Chautauqua Ave",
    "sg:city":"Norman",
    "sg:classifiers":[
        {
            "category":"Insurance",
            "subcategory":"Insurance Agent",
            "type":"Services"
        }
    ],
    "sg:phone":"+1 405 408 7647",
    "sg:postcode":"73072",
    "sg:province":"OK",
    "wof:name":"Kevin Rolla Insurance",
    "wof:placetype":"venue"
},
  "geometry": {"coordinates":[-97.450277,35.188633],"type":"Point"}
}