{
  "type": "Feature",
  "properties": {
    "iso:country":"US",
    "sg:address":"5525 W Skelly Dr",
    "sg:city":"Tulsa",
    "sg:classifiers":[
        {
            "category":"Travel",
            "subcategory":"Hotels & Motels",
            "type":"Entertainment"
        }
    ],
    "sg:phone":"+1 918 445 4766",
    "sg:postcode":"74107",
    "sg:province":"OK",
    "sg:tags":[
        "operation"
    ],
    "wof:name":"Mptd Enterprises Inc",
    "wof:placetype":"venue"
},
  "geometry": {"coordinates":[-96.046424,36.081086],"type":"Point"}
}