{
  "type": "Feature",
  "properties": {
    "addr:full":"6205 E Tecumseh St Tulsa OK 74115",
    "addr:housenumber":"6205",
    "addr:postcode":"74115",
    "addr:street":"E Tecumseh",
    "iso:country":"US",
    "sg:address":"6205 E Tecumseh St",
    "sg:city":"Tulsa",
    "sg:classifiers":[
        {
            "category":"Professional",
            "subcategory":"Advertising",
            "type":"Services"
        }
    ],
    "sg:phone":"+1 918 832 9930",
    "sg:postcode":"74115",
    "sg:province":"OK",
    "sg:website":"www.creativesculptures.com",
    "wof:name":"Tower Awards",
    "wof:placetype":"venue"
},
  "geometry": {"coordinates":[-95.90745099999999,36.18201],"type":"Point"}
}