{
  "type": "Feature",
  "properties": {
    "iso:country":"US",
    "sg:address":"1420 Pleasant View Ln",
    "sg:city":"Choctaw",
    "sg:classifiers":[
        {
            "category":"Retail",
            "subcategory":"Self-service Laundry",
            "type":"Services"
        }
    ],
    "sg:phone":"+1 405 390 3116",
    "sg:postcode":"73020",
    "sg:province":"OK",
    "sg:tags":[
        "coin"
    ],
    "wof:name":"Quick Kleen Laundries",
    "wof:placetype":"venue"
},
  "geometry": {"coordinates":[-97.235427,35.483976],"type":"Point"}
}