{
  "type": "Feature",
  "properties": {
    "addr:full":"202 S 117th East Ave Tulsa OK 74128",
    "addr:housenumber":"202",
    "addr:postcode":"74128",
    "addr:street":"S 117Th;Ave",
    "iso:country":"US",
    "sg:address":"202 S 117th East Ave",
    "sg:city":"Tulsa",
    "sg:classifiers":[
        {
            "category":"Education",
            "subcategory":"School",
            "type":"Public Place"
        }
    ],
    "sg:phone":"+1 918 746 9580",
    "sg:postcode":"74128",
    "sg:province":"OK",
    "sg:website":"www.tulsaschools.org",
    "wof:name":"Kerr Elementary School",
    "wof:placetype":"venue"
},
  "geometry": {"coordinates":[-95.847397,36.157398],"type":"Point"}
}