{
  "type": "Feature",
  "properties": {
    "iso:country":"US",
    "sg:address":"1216 W 9th St",
    "sg:city":"Sulphur",
    "sg:classifiers":[
        {
            "category":"Government",
            "subcategory":"Office",
            "type":"Public Place"
        }
    ],
    "sg:phone":"+1 580 622 5700",
    "sg:postcode":"73086",
    "sg:province":"OK",
    "wof:name":"INCA Community Svc",
    "wof:placetype":"venue"
},
  "geometry": {"coordinates":[-96.978269,34.510024],"type":"Point"}
}