{
  "type": "Feature",
  "properties": {
    "addr:full":"3009 Paseo Oklahoma City OK 73103",
    "addr:housenumber":"3009",
    "addr:postcode":"73103",
    "addr:street":"Paseo",
    "iso:country":"US",
    "sg:address":"3009 Paseo",
    "sg:city":"Oklahoma City",
    "sg:classifiers":[
        {
            "category":"Bars & Pubs",
            "type":"Food & Drink"
        }
    ],
    "sg:menulink":"http://www.allmenus.com/ok/oklahoma-city/4555-galileo-bar/menu/",
    "sg:phone":"+1 405 415 7827",
    "sg:postcode":"73103",
    "sg:province":"OK",
    "sg:tags":[
        "american"
    ],
    "wof:name":"Galileo Bar",
    "wof:placetype":"venue"
},
  "geometry": {"coordinates":[-97.52294999999999,35.499605],"type":"Point"}
}