{
  "type": "Feature",
  "properties": {
    "iso:country":"US",
    "sg:address":"1336 E 45th St",
    "sg:city":"Tulsa",
    "sg:classifiers":[
        {
            "category":"Home & Garden",
            "subcategory":"Home Furnishings",
            "type":"Retail Goods"
        }
    ],
    "sg:phone":"+1 918 742 9494",
    "sg:postcode":"74105",
    "sg:province":"OK",
    "sg:tags":[
        "venetian",
        "blind"
    ],
    "wof:name":"Budget Blinds",
    "wof:placetype":"venue"
},
  "geometry": {"coordinates":[-95.971863,36.098335],"type":"Point"}
}