{
  "type": "Feature",
  "properties": {
    "iso:country":"US",
    "sg:address":"1527 S Norfolk Ave",
    "sg:city":"Tulsa",
    "sg:classifiers":[
        {
            "category":"Professional",
            "subcategory":"Business Services",
            "type":"Services"
        }
    ],
    "sg:phone":"+1 918 583 2212",
    "sg:postcode":"74120",
    "sg:province":"OK",
    "sg:tags":[
        "interior",
        "residential",
        "designing"
    ],
    "wof:name":"Williams Sheri Meyer Interiors",
    "wof:placetype":"venue"
},
  "geometry": {"coordinates":[-95.979036,36.139441],"type":"Point"}
}