{
  "type": "Feature",
  "properties": {
    "iso:country":"US",
    "sg:address":"2431 E 51st St",
    "sg:city":"Tulsa",
    "sg:classifiers":[
        {
            "category":"Professional",
            "subcategory":"Business Services",
            "type":"Services"
        }
    ],
    "sg:phone":"+1 918 743 1130",
    "sg:postcode":"74105",
    "sg:province":"OK",
    "sg:tags":[
        "broker"
    ],
    "wof:name":"Corporate Finance Assoc",
    "wof:placetype":"venue"
},
  "geometry": {"coordinates":[-95.95586400000001,36.089832],"type":"Point"}
}