{
  "type": "Feature",
  "properties": {
    "iso:country":"US",
    "sg:address":"8000 N Harrison Ave",
    "sg:city":"Shawnee",
    "sg:classifiers":[
        {
            "category":"Utilities",
            "subcategory":"Natural Gas",
            "type":"Services"
        }
    ],
    "sg:phone":"+1 405 275 7134",
    "sg:postcode":"74804",
    "sg:province":"OK",
    "sg:tags":[
        "distribution"
    ],
    "wof:name":"Oklahoma Natural Gas Co",
    "wof:placetype":"venue"
},
  "geometry": {"coordinates":[-96.91216,35.414033],"type":"Point"}
}