{
  "type": "Feature",
  "properties": {
    "addr:full":"500 E Trice St Hugo OK 74743",
    "addr:housenumber":"500",
    "addr:postcode":"74743",
    "addr:street":"E Trice St",
    "iso:country":"US",
    "sg:address":"500 E Trice St",
    "sg:city":"Hugo",
    "sg:classifiers":[
        {
            "category":"Organizations",
            "subcategory":"Religious Organization",
            "type":"Services"
        }
    ],
    "sg:phone":"+1 580 326 7337",
    "sg:postcode":"74743",
    "sg:province":"OK",
    "sg:tags":[
        "church"
    ],
    "wof:name":"Southside Baptist Church",
    "wof:placetype":"venue"
},
  "geometry": {"coordinates":[-95.507729,33.998913],"type":"Point"}
}