{
  "type": "Feature",
  "properties": {
    "iso:country":"US",
    "sg:address":"1701 S Western Ave",
    "sg:city":"Oklahoma City",
    "sg:classifiers":[
        {
            "category":"Government",
            "subcategory":"Office",
            "type":"Public Place"
        }
    ],
    "sg:phone":"+1 405 631 8820",
    "sg:postcode":"73109",
    "sg:province":"OK",
    "sg:tags":[
        "management"
    ],
    "wof:name":"Oklahoma City Riverfront Redev",
    "wof:placetype":"venue"
},
  "geometry": {"coordinates":[-97.530216,35.449091],"type":"Point"}
}