{
  "type": "Feature",
  "properties": {
    "addr:full":"1330 Oklahoma Blvd Alva OK 73717",
    "addr:housenumber":"1330",
    "addr:postcode":"73717",
    "addr:street":"Oklahoma Blvd",
    "iso:country":"US",
    "sg:address":"1330 Oklahoma Blvd",
    "sg:city":"Alva",
    "sg:classifiers":[
        {
            "category":"Social Services",
            "type":"Services"
        }
    ],
    "sg:phone":"+1 580 327 6648",
    "sg:postcode":"73717",
    "sg:province":"OK",
    "sg:tags":[
        "crisis",
        "intervention"
    ],
    "wof:name":"Northwest Domestic Crisis Svc",
    "wof:placetype":"venue"
},
  "geometry": {"coordinates":[-98.678894,36.797793],"type":"Point"}
}