{
  "type": "Feature",
  "properties": {
    "iso:country":"US",
    "sg:address":"2100 SW 59th St",
    "sg:city":"Oklahoma City",
    "sg:classifiers":[
        {
            "category":"Autos & Motor Vehicles",
            "subcategory":"Auto Supplies",
            "type":"Retail Goods"
        }
    ],
    "sg:phone":"+1 405 682 2824",
    "sg:postcode":"73119",
    "sg:province":"OK",
    "sg:tags":[
        "wheel",
        "cover"
    ],
    "wof:name":"Erick Wheels & Tires",
    "wof:placetype":"venue"
},
  "geometry": {"coordinates":[-97.551047,35.406203],"type":"Point"}
}