{
  "type": "Feature",
  "properties": {
    "iso:country":"US",
    "sg:address":"1712 NW Cache Rd",
    "sg:city":"Lawton",
    "sg:classifiers":[
        {
            "category":"Personal",
            "subcategory":"Beauty Salon",
            "type":"Services"
        }
    ],
    "sg:phone":"+1 580 581 1090",
    "sg:postcode":"73507",
    "sg:province":"OK",
    "sg:tags":[
        "shop"
    ],
    "wof:name":"Shades Hair Salon",
    "wof:placetype":"venue"
},
  "geometry": {"coordinates":[-98.415304,34.623098],"type":"Point"}
}