{
  "type": "Feature",
  "properties": {
    "iso:country":"US",
    "sg:address":"504 S 1st St",
    "sg:city":"Madill",
    "sg:classifiers":[
        {
            "category":"Restaurant",
            "type":"Food & Drink"
        }
    ],
    "sg:phone":"+1 580 795 7518",
    "sg:postcode":"73446",
    "sg:province":"OK",
    "wof:name":"Grill Restaurant The",
    "wof:placetype":"venue"
},
  "geometry": {"coordinates":[-96.770174,34.086268],"type":"Point"}
}