{
  "type": "Feature",
  "properties": {
    "iso:country":"US",
    "sg:address":"3231 N Meridian Ave",
    "sg:city":"Newcastle",
    "sg:classifiers":[
        {
            "category":"Building & Trades",
            "subcategory":"Equipment Rental",
            "type":"Services"
        }
    ],
    "sg:phone":"+1 405 387 2226",
    "sg:postcode":"73065",
    "sg:province":"OK",
    "sg:tags":[
        "heavy",
        "construction"
    ],
    "wof:name":"Rent X",
    "wof:placetype":"venue"
},
  "geometry": {"coordinates":[-97.600221,35.27223],"type":"Point"}
}