{
  "type": "Feature",
  "properties": {
    "iso:country":"US",
    "sg:address":"3910 S 24th Pl W",
    "sg:city":"Muskogee",
    "sg:classifiers":[
        {
            "category":"Retail",
            "subcategory":"Repair Shop",
            "type":"Services"
        }
    ],
    "sg:phone":"+1 918 683 4161",
    "sg:postcode":"74401",
    "sg:province":"OK",
    "sg:tags":[
        "television",
        "radio"
    ],
    "wof:name":"Jerry James Svc Co",
    "wof:placetype":"venue"
},
  "geometry": {"coordinates":[-95.393642,35.698547],"type":"Point"}
}