{
  "type": "Feature",
  "properties": {
    "addr:full":"1620 S 13th St Clinton OK 73601",
    "addr:housenumber":"1620",
    "addr:postcode":"73601",
    "addr:street":"S 13Th St",
    "iso:country":"US",
    "sg:address":"1620 S 13th St",
    "sg:city":"Clinton",
    "sg:classifiers":[
        {
            "category":"Retail",
            "subcategory":"Repair Shop",
            "type":"Services"
        }
    ],
    "sg:phone":"+1 580 323 2422",
    "sg:postcode":"73601",
    "sg:province":"OK",
    "sg:tags":[
        "sales",
        "motor",
        "rewinding"
    ],
    "wof:name":"Capitol Electric Motor Repair",
    "wof:placetype":"venue"
},
  "geometry": {"coordinates":[-98.976023,35.488471],"type":"Point"}
}