{
  "type": "Feature",
  "properties": {
    "iso:country":"US",
    "sg:address":"6327 SW 3rd St",
    "sg:city":"Oklahoma City",
    "sg:classifiers":[
        {
            "category":"Retail",
            "subcategory":"Veterinary Services",
            "type":"Services"
        }
    ],
    "sg:phone":"+1 405 787 8000",
    "sg:postcode":"73128",
    "sg:province":"OK",
    "sg:tags":[
        "veterinarian"
    ],
    "wof:name":"Banfield The Pet Hospital",
    "wof:placetype":"venue"
},
  "geometry": {"coordinates":[-97.623282,35.461467],"type":"Point"}
}