{
  "type": "Feature",
  "properties": {
    "iso:country":"US",
    "sg:address":"28 NE 50th St",
    "sg:city":"Oklahoma City",
    "sg:classifiers":[
        {
            "category":"Shopping",
            "subcategory":"Used Merchandise",
            "type":"Retail Goods"
        }
    ],
    "sg:phone":"+1 405 521 1691",
    "sg:postcode":"73105",
    "sg:province":"OK",
    "wof:name":"Santa Fe Pawn Shop",
    "wof:placetype":"venue"
},
  "geometry": {"coordinates":[-97.510477,35.52225],"type":"Point"}
}