{
  "type": "Feature",
  "properties": {
    "iso:country":"US",
    "sg:address":"6200 Academy Ln",
    "sg:city":"Harrah",
    "sg:classifiers":[
        {
            "category":"Shopping",
            "subcategory":"Catalog Store",
            "type":"Retail Goods"
        },
        {
            "category":"Wholesale",
            "subcategory":"Durable Goods & Equipment",
            "type":"Manufacturing & Wholesale Goods"
        }
    ],
    "sg:phone":"+1 405 454 6267",
    "sg:postcode":"73045",
    "sg:province":"OK",
    "sg:tags":[
        "publication",
        "representative",
        "mail",
        "religious",
        "order",
        "manufacturer"
    ],
    "wof:name":"Mission Publishing Inc",
    "wof:placetype":"venue"
},
  "geometry": {"coordinates":[-97.20222,35.53525],"type":"Point"}
}