{
  "type": "Feature",
  "properties": {
    "iso:country":"US",
    "sg:address":"2002 W A Ave",
    "sg:city":"Elk City",
    "sg:classifiers":[
        {
            "category":"School Buses",
            "type":"Transportation"
        }
    ],
    "sg:phone":"+1 580 225 1711",
    "sg:postcode":"73644",
    "sg:province":"OK",
    "wof:name":"Elk City School Bus Barn",
    "wof:placetype":"venue"
},
  "geometry": {"coordinates":[-99.428342,35.414567],"type":"Point"}
}