{
  "type": "Feature",
  "properties": {
    "iso:country":"US",
    "sg:address":"124 E Bridge Ave",
    "sg:city":"Blackwell",
    "sg:classifiers":[
        {
            "category":"Home & Garden",
            "subcategory":"Building Materials",
            "type":"Retail Goods"
        }
    ],
    "sg:phone":"+1 580 363 0333",
    "sg:postcode":"74631",
    "sg:province":"OK",
    "sg:tags":[
        "lumber"
    ],
    "wof:name":"W W Starr Lumber Co",
    "wof:placetype":"venue"
},
  "geometry": {"coordinates":[-97.282676,36.803345],"type":"Point"}
}