{
  "type": "Feature",
  "properties": {
    "addr:full":"101 N Douglas Blvd Oklahoma City OK 73130",
    "addr:housenumber":"101",
    "addr:postcode":"73130",
    "addr:street":"N Douglas Blvd",
    "iso:country":"US",
    "sg:address":"101 N Douglas Blvd",
    "sg:city":"Oklahoma City",
    "sg:classifiers":[
        {
            "category":"Insurance",
            "subcategory":"Insurance Agent",
            "type":"Services"
        }
    ],
    "sg:phone":"+1 405 736 1010",
    "sg:postcode":"73130",
    "sg:province":"OK",
    "wof:name":"Allstate",
    "wof:placetype":"venue"
},
  "geometry": {"coordinates":[-97.370921,35.465254],"type":"Point"}
}