{
  "type": "Feature",
  "properties": {
    "addr:full":"3722 N Shartel Ave Oklahoma City OK 73118",
    "addr:housenumber":"3722",
    "addr:postcode":"73118",
    "addr:street":"N Shartel Ave",
    "iso:country":"US",
    "sg:address":"3722 N Shartel Ave",
    "sg:city":"Oklahoma City",
    "sg:classifiers":[
        {
            "category":"Arts & Performance",
            "subcategory":"Theater",
            "type":"Entertainment"
        }
    ],
    "sg:phone":"+1 405 751 0610",
    "sg:postcode":"73118",
    "sg:province":"OK",
    "sg:tags":[
        "theatrical"
    ],
    "wof:name":"Captive Audience Marketing",
    "wof:placetype":"venue"
},
  "geometry": {"coordinates":[-97.52542699999999,35.508452],"type":"Point"}
}