{
  "type": "Feature",
  "properties": {
    "iso:country":"US",
    "sg:address":"154 N Garnett Rd",
    "sg:city":"Tulsa",
    "sg:classifiers":[
        {
            "category":"Restaurant",
            "type":"Food & Drink"
        }
    ],
    "sg:phone":"+1 918 437 2902",
    "sg:postcode":"74116",
    "sg:province":"OK",
    "sg:tags":[
        "eating"
    ],
    "wof:name":"Brady's Grill",
    "wof:placetype":"venue"
},
  "geometry": {"coordinates":[-95.851113,36.163581],"type":"Point"}
}