{
  "type": "Feature",
  "properties": {
    "iso:country":"US",
    "sg:address":"1811 S Main St",
    "sg:city":"Broken Arrow",
    "sg:classifiers":[
        {
            "category":"Professional",
            "type":"Services"
        }
    ],
    "sg:phone":"+1 918 258 6276",
    "sg:postcode":"74012",
    "sg:province":"OK",
    "sg:tags":[
        "establishment"
    ],
    "wof:name":"Children's Exchange",
    "wof:placetype":"venue"
},
  "geometry": {"coordinates":[-95.790807,36.032219],"type":"Point"}
}