{
  "type": "Feature",
  "properties": {
    "iso:country":"US",
    "sg:address":"118 S Broadway St",
    "sg:city":"Weatherford",
    "sg:classifiers":[
        {
            "category":"Manufacturing",
            "subcategory":"Printing",
            "type":"Manufacturing & Wholesale Goods"
        }
    ],
    "sg:phone":"+1 580 772 3301",
    "sg:postcode":"73096",
    "sg:province":"OK",
    "sg:tags":[
        "newspaper"
    ],
    "sg:website":"www.wdnonline.com",
    "wof:name":"Weatherford Daily News",
    "wof:placetype":"venue"
},
  "geometry": {"coordinates":[-98.709064,35.525811],"type":"Point"}
}