{
  "type": "Feature",
  "properties": {
    "addr:full":"1011 Main Ave Woodward OK 73801",
    "addr:housenumber":"1011",
    "addr:postcode":"73801",
    "addr:street":"Main Ave",
    "iso:country":"US",
    "sg:address":"1011 Main Ave",
    "sg:city":"Woodward",
    "sg:classifiers":[
        {
            "category":"Insurance",
            "subcategory":"Insurance Agent",
            "type":"Services"
        }
    ],
    "sg:phone":"+1 580 256 4255",
    "sg:postcode":"73801",
    "sg:province":"OK",
    "wof:name":"New York Life Insurance Co",
    "wof:placetype":"venue"
},
  "geometry": {"coordinates":[-99.393085,36.435878],"type":"Point"}
}