{
  "type": "Feature",
  "properties": {
    "iso:country":"US",
    "sg:address":"4001 Price Rd",
    "sg:city":"Bartlesville",
    "sg:classifiers":[
        {
            "category":"Manufacturing",
            "subcategory":"Glass & Minerals",
            "type":"Manufacturing & Wholesale Goods"
        }
    ],
    "sg:phone":"+1 918 335 9775",
    "sg:postcode":"74006",
    "sg:province":"OK",
    "sg:website":"www.glassworks.com",
    "wof:name":"Glass Works",
    "wof:placetype":"venue"
},
  "geometry": {"coordinates":[-95.933373,36.713458],"type":"Point"}
}