{
  "type": "Feature",
  "properties": {
    "iso:country":"US",
    "sg:address":"5015 S Pennsylvania Ave",
    "sg:city":"Oklahoma City",
    "sg:classifiers":[
        {
            "category":"Home & Garden",
            "subcategory":"Garden Supply",
            "type":"Retail Goods"
        }
    ],
    "sg:phone":"+1 405 685 0414",
    "sg:postcode":"73119",
    "sg:province":"OK",
    "sg:tags":[
        "lawn",
        "mower"
    ],
    "wof:name":"Southside Lawn & Garden Inc",
    "wof:placetype":"venue"
},
  "geometry": {"coordinates":[-97.548011,35.415077],"type":"Point"}
}