{
  "type": "Feature",
  "properties": {
    "iso:country":"US",
    "sg:address":"2114 SW 74th St",
    "sg:city":"Oklahoma City",
    "sg:classifiers":[
        {
            "category":"Personal",
            "subcategory":"Beauty Salon",
            "type":"Services"
        }
    ],
    "sg:phone":"+1 405 686 1376",
    "sg:postcode":"73159",
    "sg:province":"OK",
    "sg:tags":[
        "shop"
    ],
    "wof:name":"Styles Unlimited",
    "wof:placetype":"venue"
},
  "geometry": {"coordinates":[-97.548945,35.390975],"type":"Point"}
}