{
  "type": "Feature",
  "properties": {
    "iso:country":"US",
    "sg:address":"6580 E 40th St",
    "sg:city":"Tulsa",
    "sg:classifiers":[
        {
            "category":"Autos & Motor Vehicles",
            "subcategory":"Motorcycle Sales",
            "type":"Retail Goods"
        }
    ],
    "sg:phone":"+1 918 641 1192",
    "sg:postcode":"74145",
    "sg:province":"OK",
    "wof:name":"Conans Classics",
    "wof:placetype":"venue"
},
  "geometry": {"coordinates":[-95.89789,36.105443],"type":"Point"}
}