{
  "type": "Feature",
  "properties": {
    "addr:full":"5620 S Pennsylvania Ave Oklahoma City OK 73119",
    "addr:housenumber":"5620",
    "addr:postcode":"73119",
    "addr:street":"S Pennsylvania Ave",
    "iso:country":"US",
    "sg:address":"5620 S Pennsylvania Ave",
    "sg:city":"Oklahoma City",
    "sg:classifiers":[
        {
            "category":"Shopping",
            "subcategory":"Florist",
            "type":"Retail Goods"
        }
    ],
    "sg:phone":"+1 405 680 9090",
    "sg:postcode":"73119",
    "sg:province":"OK",
    "wof:name":"Fran's Flowers & Gifts",
    "wof:placetype":"venue"
},
  "geometry": {"coordinates":[-97.54786300000001,35.409269],"type":"Point"}
}