{
  "type": "Feature",
  "properties": {
    "iso:country":"US",
    "sg:address":"27 NE 26th St",
    "sg:city":"Oklahoma City",
    "sg:classifiers":[
        {
            "category":"Building & Trades",
            "subcategory":"Construction",
            "type":"Services"
        }
    ],
    "sg:phone":"+1 405 528 7495",
    "sg:postcode":"73105",
    "sg:province":"OK",
    "sg:tags":[
        "fabricator",
        "metal"
    ],
    "sg:website":"www.yorkmetal.com",
    "wof:name":"York Metal Fabricators Inc",
    "wof:placetype":"venue"
},
  "geometry": {"coordinates":[-97.510535,35.496984],"type":"Point"}
}