{
  "type": "Feature",
  "properties": {
    "addr:full":"997 N Douglas Blvd Oklahoma City OK 73130",
    "addr:housenumber":"997",
    "addr:postcode":"73130",
    "addr:street":"N Douglas Blvd",
    "iso:country":"US",
    "sg:address":"997 N Douglas Blvd",
    "sg:city":"Oklahoma City",
    "sg:classifiers":[
        {
            "category":"Organizations",
            "subcategory":"Religious Organization",
            "type":"Services"
        }
    ],
    "sg:phone":"+1 405 732 4537",
    "sg:postcode":"73130",
    "sg:province":"OK",
    "sg:tags":[
        "a",
        "as",
        "miss",
        "operates"
    ],
    "wof:name":"Neighbrhd Missonary Baptist Ch",
    "wof:placetype":"venue"
},
  "geometry": {"coordinates":[-97.370896,35.474924],"type":"Point"}
}