{
  "type": "Feature",
  "properties": {
    "iso:country":"US",
    "sg:address":"1120 N Duck St",
    "sg:city":"Stillwater",
    "sg:classifiers":[
        {
            "category":"Food & Beverages",
            "subcategory":"Specialty",
            "type":"Retail Goods"
        }
    ],
    "sg:phone":"+1 405 377 1688",
    "sg:postcode":"74075",
    "sg:province":"OK",
    "wof:name":"Karen Breedlove",
    "wof:placetype":"venue"
},
  "geometry": {"coordinates":[-97.062799,36.132975],"type":"Point"}
}