{
  "type": "Feature",
  "properties": {
    "iso:country":"US",
    "sg:address":"913 Denise St",
    "sg:city":"Altus",
    "sg:classifiers":[
        {
            "category":"Retail",
            "subcategory":"Repair Shop",
            "type":"Services"
        }
    ],
    "sg:phone":"+1 580 482 6629",
    "sg:postcode":"73521",
    "sg:province":"OK",
    "sg:tags":[
        "machine",
        "sewing"
    ],
    "wof:name":"X Pert Sewing Machine Repair",
    "wof:placetype":"venue"
},
  "geometry": {"coordinates":[-99.323825,34.626181],"type":"Point"}
}