{
  "type": "Feature",
  "properties": {
    "iso:country":"US",
    "sg:address":"820 SE 2nd St",
    "sg:city":"Lawton",
    "sg:classifiers":[
        {
            "category":"Building & Trades",
            "subcategory":"Construction",
            "type":"Services"
        }
    ],
    "sg:phone":"+1 580 353 1550",
    "sg:postcode":"73501",
    "sg:province":"OK",
    "sg:tags":[
        "resurfacing",
        "laying",
        "refinishing",
        "floor"
    ],
    "wof:name":"Universal Cleaning Inc",
    "wof:placetype":"venue"
},
  "geometry": {"coordinates":[-98.382945,34.597825],"type":"Point"}
}