{
  "type": "Feature",
  "properties": {
    "addr:full":"332 N Scraper St Vinita OK 74301",
    "addr:housenumber":"332",
    "addr:postcode":"74301",
    "addr:street":"N Scraper St",
    "iso:country":"US",
    "sg:address":"332 N Scraper St",
    "sg:city":"Vinita",
    "sg:classifiers":[
        {
            "category":"Retail",
            "subcategory":"Funeral Services",
            "type":"Services"
        }
    ],
    "sg:phone":"+1 918 256 5555",
    "sg:postcode":"74301",
    "sg:province":"OK",
    "sg:tags":[
        "director"
    ],
    "wof:name":"Luginbuel Funeral Home",
    "wof:placetype":"venue"
},
  "geometry": {"coordinates":[-95.153074,36.643537],"type":"Point"}
}