{
  "type": "Feature",
  "properties": {
    "iso:country":"US",
    "sg:address":"8725 E 43rd St",
    "sg:city":"Tulsa",
    "sg:classifiers":[
        {
            "category":"Retail",
            "subcategory":"Auto Repair",
            "type":"Services"
        }
    ],
    "sg:phone":"+1 918 665 8110",
    "sg:postcode":"74145",
    "sg:province":"OK",
    "sg:tags":[
        "repairing",
        "automobile"
    ],
    "wof:name":"John Baskin Auto Svc",
    "wof:placetype":"venue"
},
  "geometry": {"coordinates":[-95.878643,36.102052],"type":"Point"}
}