{
  "type": "Feature",
  "properties": {
    "addr:full":"1724 N Sheridan Rd Tulsa OK 74115",
    "addr:housenumber":"1724",
    "addr:postcode":"74115",
    "addr:street":"N Sheridan Rd",
    "iso:country":"US",
    "sg:address":"1724 N Sheridan Rd",
    "sg:city":"Tulsa",
    "sg:classifiers":[
        {
            "category":"Personal",
            "subcategory":"Beauty Salon",
            "type":"Services"
        }
    ],
    "sg:phone":"+1 918 838 7086",
    "sg:postcode":"74115",
    "sg:province":"OK",
    "sg:tags":[
        "shop"
    ],
    "wof:name":"Sheridan Square Beauty Shop",
    "wof:placetype":"venue"
},
  "geometry": {"coordinates":[-95.904662,36.180935],"type":"Point"}
}