{
  "type": "Feature",
  "properties": {
    "addr:full":"104 W Ohio Ave Coalgate OK 74538",
    "addr:housenumber":"104",
    "addr:postcode":"74538",
    "addr:street":"W Ohio Ave Coalgate",
    "iso:country":"US",
    "sg:address":"104 W Ohio Ave",
    "sg:city":"Coalgate",
    "sg:classifiers":[
        {
            "category":"Shopping",
            "subcategory":"Pharmacy",
            "type":"Retail Goods"
        }
    ],
    "sg:phone":"+1 580 927 2064",
    "sg:postcode":"74538",
    "sg:province":"OK",
    "wof:name":"Palace Drug Store",
    "wof:placetype":"venue"
},
  "geometry": {"coordinates":[-96.218863,34.539662],"type":"Point"}
}