{
  "type": "Feature",
  "properties": {
    "iso:country":"US",
    "sg:address":"4509 N Redmond Ave",
    "sg:city":"Bethany",
    "sg:classifiers":[
        {
            "category":"Freight",
            "type":"Transportation"
        }
    ],
    "sg:phone":"+1 405 787 4030",
    "sg:postcode":"73008",
    "sg:province":"OK",
    "sg:tags":[
        "commercial",
        "storage",
        "general"
    ],
    "wof:name":"Mc S Mini Storage",
    "wof:placetype":"venue"
},
  "geometry": {"coordinates":[-97.625662,35.517731],"type":"Point"}
}