{
  "type": "Feature",
  "properties": {
    "addr:full":"1301 NW 67th St Lawton OK 73505",
    "addr:housenumber":"1301",
    "addr:postcode":"73505",
    "addr:street":"Nw 67Th St",
    "iso:country":"US",
    "sg:address":"1301 NW 67th St",
    "sg:city":"Lawton",
    "sg:classifiers":[
        {
            "category":"Building & Trades",
            "subcategory":"Construction",
            "type":"Services"
        }
    ],
    "sg:phone":"+1 580 536 7063",
    "sg:postcode":"73505",
    "sg:province":"OK",
    "sg:tags":[
        "general",
        "contractor"
    ],
    "wof:name":"St K Construction",
    "wof:placetype":"venue"
},
  "geometry": {"coordinates":[-98.474756,34.622695],"type":"Point"}
}