{
  "type": "Feature",
  "properties": {
    "iso:country":"US",
    "sg:address":"306 Hickory Bend St",
    "sg:city":"Bache",
    "sg:classifiers":[
        {
            "category":"Shopping",
            "subcategory":"Beauty & Cosmetics",
            "type":"Retail Goods"
        }
    ],
    "sg:phone":"+1 918 429 0035",
    "sg:postcode":"74501",
    "sg:province":"OK",
    "sg:tags":[
        "merchandise"
    ],
    "wof:name":"Lyn Salyers",
    "wof:placetype":"venue"
},
  "geometry": {"coordinates":[-95.77019300000001,34.912535],"type":"Point"}
}