{
  "type": "Feature",
  "properties": {
    "iso:country":"US",
    "sg:address":"7504 E 11th St",
    "sg:city":"Tulsa",
    "sg:classifiers":[
        {
            "category":"Autos & Motor Vehicles",
            "subcategory":"Automobile Sales",
            "type":"Retail Goods"
        }
    ],
    "sg:phone":"+1 918 832 9411",
    "sg:postcode":"74112",
    "sg:province":"OK",
    "sg:tags":[
        "car",
        "dealer"
    ],
    "wof:name":"Frank Johnson Auto Sales",
    "wof:placetype":"venue"
},
  "geometry": {"coordinates":[-95.892291,36.147959],"type":"Point"}
}