{
  "type": "Feature",
  "properties": {
    "iso:country":"US",
    "sg:address":"10909 Maple Grove",
    "sg:city":"Oklahoma City",
    "sg:classifiers":[
        {
            "category":"Building & Trades",
            "subcategory":"Construction",
            "type":"Services"
        }
    ],
    "sg:phone":"+1 405 748 5647",
    "sg:postcode":"73120",
    "sg:province":"OK",
    "sg:tags":[
        "home",
        "builder"
    ],
    "wof:name":"Mighty Oak Log Homes",
    "wof:placetype":"venue"
},
  "geometry": {"coordinates":[-97.57423,35.582817],"type":"Point"}
}