{
  "type": "Feature",
  "properties": {
    "iso:country":"US",
    "sg:address":"9905 S Allen Dr",
    "sg:city":"Oklahoma City",
    "sg:classifiers":[
        {
            "category":"Building & Trades",
            "subcategory":"Construction",
            "type":"Services"
        }
    ],
    "sg:phone":"+1 405 691 2969",
    "sg:postcode":"73139",
    "sg:province":"OK",
    "sg:tags":[
        "home",
        "speculative",
        "family"
    ],
    "wof:name":"Helm Plumbing & Heating",
    "wof:placetype":"venue"
},
  "geometry": {"coordinates":[-97.52196499999999,35.368437],"type":"Point"}
}