{
  "type": "Feature",
  "properties": {
    "iso:country":"US",
    "sg:address":"2605 N Main St",
    "sg:city":"Bache",
    "sg:classifiers":[
        {
            "category":"Autos & Motor Vehicles",
            "subcategory":"Auto Supplies",
            "type":"Retail Goods"
        }
    ],
    "sg:phone":"+1 918 423 7444",
    "sg:postcode":"74501",
    "sg:province":"OK",
    "sg:tags":[
        "automotive",
        "tire"
    ],
    "wof:name":"Jet Tire Service Inc",
    "wof:placetype":"venue"
},
  "geometry": {"coordinates":[-95.760456,34.957174],"type":"Point"}
}