{
  "type": "Feature",
  "properties": {
    "addr:full":"422 Avant Ave Clinton OK 73601",
    "addr:housenumber":"422",
    "addr:postcode":"73601",
    "addr:street":"Avant Ave",
    "iso:country":"US",
    "sg:address":"422 Avant Ave",
    "sg:city":"Clinton",
    "sg:classifiers":[
        {
            "category":"Government",
            "subcategory":"Jail",
            "type":"Public Place"
        }
    ],
    "sg:phone":"+1 580 323 4331",
    "sg:postcode":"73601",
    "sg:province":"OK",
    "sg:tags":[
        "govt",
        "state",
        "institution"
    ],
    "wof:name":"Office Of Juvenile Affairs",
    "wof:placetype":"venue"
},
  "geometry": {"coordinates":[-98.96575300000001,35.513276],"type":"Point"}
}