{
  "type": "Feature",
  "properties": {
    "addr:full":"4710 Copperwood St Duncan OK 73533",
    "addr:housenumber":"4710",
    "addr:postcode":"73533",
    "addr:street":"Copperwood St",
    "iso:country":"US",
    "sg:address":"4710 Copperwood St",
    "sg:city":"Duncan",
    "sg:classifiers":[
        {
            "category":"Professional",
            "type":"Services"
        }
    ],
    "sg:phone":"+1 580 255 8323",
    "sg:postcode":"73533",
    "sg:province":"OK",
    "wof:name":"Mitchell Svc Inc",
    "wof:placetype":"venue"
},
  "geometry": {"coordinates":[-97.97634600000001,34.556819],"type":"Point"}
}