{
  "type": "Feature",
  "properties": {
    "iso:country":"US",
    "sg:address":"801 24th Ave NW",
    "sg:city":"Norman",
    "sg:classifiers":[
        {
            "category":"Health Services",
            "subcategory":"Doctor",
            "type":"Services"
        }
    ],
    "sg:phone":"+1 405 360 9117",
    "sg:postcode":"73069",
    "sg:province":"OK",
    "sg:tags":[
        "clinic"
    ],
    "wof:name":"Robert Y Takano Inc",
    "wof:placetype":"venue"
},
  "geometry": {"coordinates":[-97.47793900000001,35.226938],"type":"Point"}
}