{
  "type": "Feature",
  "properties": {
    "addr:full":"3836 NW 10th St Oklahoma City OK 73107",
    "addr:housenumber":"3836",
    "addr:postcode":"73107",
    "addr:street":"Nw 10Th St",
    "iso:country":"US",
    "sg:address":"3836 NW 10th St",
    "sg:city":"Oklahoma City",
    "sg:classifiers":[
        {
            "category":"Retail",
            "subcategory":"Repair Shop",
            "type":"Services"
        }
    ],
    "sg:phone":"+1 405 947 3077",
    "sg:postcode":"73107",
    "sg:province":"OK",
    "wof:name":"Professional TV Analysts",
    "wof:placetype":"venue"
},
  "geometry": {"coordinates":[-97.587754,35.47882],"type":"Point"}
}