{
  "type": "Feature",
  "properties": {
    "iso:country":"US",
    "sg:address":"3054 S Madison Ave",
    "sg:city":"Tulsa",
    "sg:classifiers":[
        {
            "category":"Health Services",
            "subcategory":"Health Practitioner",
            "type":"Services"
        }
    ],
    "sg:phone":"+1 918 712 7021",
    "sg:postcode":"74114",
    "sg:province":"OK",
    "sg:tags":[
        "therapist",
        "physical"
    ],
    "wof:name":"Comprehensive Physical Therapy",
    "wof:placetype":"venue"
},
  "geometry": {"coordinates":[-95.978798,36.120496],"type":"Point"}
}