{
  "type": "Feature",
  "properties": {
    "iso:country":"US",
    "sg:address":"4125 W Owen K Garriott Rd",
    "sg:city":"Enid",
    "sg:classifiers":[
        {
            "category":"Recreation",
            "type":"Entertainment"
        }
    ],
    "sg:phone":"+1 580 234 4334",
    "sg:postcode":"73703",
    "sg:province":"OK",
    "sg:tags":[
        "amusement"
    ],
    "wof:name":"Oklahoma Storm Basketball",
    "wof:placetype":"venue"
},
  "geometry": {"coordinates":[-97.928956,36.390776],"type":"Point"}
}