{
  "type": "Feature",
  "properties": {
    "iso:country":"US",
    "sg:address":"1404 S Muskogee Ave",
    "sg:city":"Tahlequah",
    "sg:classifiers":[
        {
            "category":"Utilities",
            "subcategory":"Mobile Phone",
            "type":"Services"
        }
    ],
    "sg:phone":"+1 918 431 0201",
    "sg:postcode":"74464",
    "sg:province":"OK",
    "sg:tags":[
        "telephone",
        "cellular"
    ],
    "wof:name":"Reasor's Cingular",
    "wof:placetype":"venue"
},
  "geometry": {"coordinates":[-94.974957,35.900594],"type":"Point"}
}