{
  "type": "Feature",
  "properties": {
    "iso:country":"US",
    "sg:address":"5635 NW 37th St",
    "sg:city":"Oklahoma City",
    "sg:classifiers":[
        {
            "category":"Autos & Motor Vehicles",
            "subcategory":"Automobile Sales",
            "type":"Retail Goods"
        }
    ],
    "sg:phone":"+1 405 787 8663",
    "sg:postcode":"73122",
    "sg:province":"OK",
    "sg:tags":[
        "used"
    ],
    "wof:name":"Nicholas Motors",
    "wof:placetype":"venue"
},
  "geometry": {"coordinates":[-97.612037,35.508838],"type":"Point"}
}