{
  "type": "Feature",
  "properties": {
    "iso:country":"US",
    "sg:address":"725 W Freeport St",
    "sg:city":"Broken Arrow",
    "sg:classifiers":[
        {
            "category":"Shopping",
            "subcategory":"Clothing, Apparel, & Fashions",
            "type":"Retail Goods"
        }
    ],
    "sg:phone":"+1 918 251 2758",
    "sg:postcode":"74012",
    "sg:province":"OK",
    "wof:name":"LEggs Products",
    "wof:placetype":"venue"
},
  "geometry": {"coordinates":[-95.798387,36.056519],"type":"Point"}
}