{
  "type": "Feature",
  "properties": {
    "iso:country":"US",
    "sg:address":"1307 SW 20th St",
    "sg:city":"Lawton",
    "sg:classifiers":[
        {
            "category":"Professional",
            "subcategory":"Management & Consulting",
            "type":"Services"
        }
    ],
    "sg:phone":"+1 580 353 0128",
    "sg:postcode":"73501",
    "sg:province":"OK",
    "sg:tags":[
        "business"
    ],
    "wof:name":"Northrop Grmman Technical Svcs",
    "wof:placetype":"venue"
},
  "geometry": {"coordinates":[-98.418504,34.593909],"type":"Point"}
}