{
  "type": "Feature",
  "properties": {
    "addr:full":"821 S McFarland St Stillwater OK 74074",
    "addr:housenumber":"821",
    "addr:postcode":"74074",
    "addr:street":"S Mcfarland St",
    "iso:country":"US",
    "sg:address":"821 S McFarland St",
    "sg:city":"Stillwater",
    "sg:classifiers":[
        {
            "category":"Retail",
            "subcategory":"Portrait Studio",
            "type":"Services"
        }
    ],
    "sg:phone":"+1 405 743 0567",
    "sg:postcode":"74074",
    "sg:province":"OK",
    "sg:tags":[
        "photo"
    ],
    "wof:name":"Willis Photography",
    "wof:placetype":"venue"
},
  "geometry": {"coordinates":[-97.08268700000001,36.113161],"type":"Point"}
}