{
  "type": "Feature",
  "properties": {
    "addr:full":"710 N 8th St Hollis OK 73550",
    "addr:housenumber":"710",
    "addr:postcode":"73550",
    "addr:street":"N 8Th St",
    "iso:country":"US",
    "sg:address":"710 N 8th St",
    "sg:city":"Hollis",
    "sg:classifiers":[
        {
            "category":"Retail",
            "subcategory":"Auto Repair",
            "type":"Services"
        }
    ],
    "sg:phone":"+1 580 688 3553",
    "sg:postcode":"73550",
    "sg:province":"OK",
    "sg:tags":[
        "body",
        "painting",
        "repairing",
        "automobile"
    ],
    "wof:name":"R&R Body Work Gym",
    "wof:placetype":"venue"
},
  "geometry": {"coordinates":[-99.912235,34.67955],"type":"Point"}
}