{
  "type": "Feature",
  "properties": {
    "iso:country":"US",
    "sg:address":"11120 NE 5th St",
    "sg:city":"Choctaw",
    "sg:classifiers":[
        {
            "category":"Building & Trades",
            "subcategory":"Landscaping Services",
            "type":"Services"
        }
    ],
    "sg:phone":"+1 405 769 7500",
    "sg:postcode":"73020",
    "sg:province":"OK",
    "sg:tags":[
        "lawn",
        "maintenance",
        "grounds"
    ],
    "wof:name":"Buckaloo's Lawn & Weed Control",
    "wof:placetype":"venue"
},
  "geometry": {"coordinates":[-97.33132,35.471337],"type":"Point"}
}