{
  "type": "Feature",
  "properties": {
    "addr:full":"1316 SE Quincy St Idabel OK 74745",
    "addr:housenumber":"1316",
    "addr:postcode":"74745",
    "addr:street":"Se Quincy St",
    "iso:country":"US",
    "sg:address":"1316 SE Quincy St",
    "sg:city":"Idabel",
    "sg:classifiers":[
        {
            "category":"Retail",
            "subcategory":"Repair Shop",
            "type":"Services"
        }
    ],
    "sg:phone":"+1 580 286 3238",
    "sg:postcode":"74745",
    "sg:province":"OK",
    "sg:tags":[
        "appliance"
    ],
    "wof:name":"Canant Appliance Repair",
    "wof:placetype":"venue"
},
  "geometry": {"coordinates":[-94.81139,33.890301],"type":"Point"}
}