{
  "type": "Feature",
  "properties": {
    "iso:country":"US",
    "sg:address":"11200 E Pine St",
    "sg:city":"Tulsa",
    "sg:classifiers":[
        {
            "category":"Manufacturing",
            "subcategory":"Aerospace",
            "type":"Manufacturing & Wholesale Goods"
        }
    ],
    "sg:phone":"+1 918 234 5155",
    "sg:postcode":"74116",
    "sg:province":"OK",
    "sg:tags":[
        "aircraft",
        "component"
    ],
    "sg:website":"www.nordam.com",
    "wof:name":"Nordam Group",
    "wof:placetype":"venue"
},
  "geometry": {"coordinates":[-95.856144,36.177047],"type":"Point"}
}