{
  "type": "Feature",
  "properties": {
    "addr:full":"3812 SW 113th St Oklahoma City OK 73173",
    "addr:housenumber":"3812",
    "addr:postcode":"73173",
    "addr:street":"Sw 113Th St",
    "iso:country":"US",
    "sg:address":"3812 SW 113th St",
    "sg:city":"Oklahoma City",
    "sg:classifiers":[
        {
            "category":"Building & Trades",
            "subcategory":"Electrical",
            "type":"Services"
        }
    ],
    "sg:phone":"+1 405 378 0285",
    "sg:postcode":"73173",
    "sg:province":"OK",
    "sg:tags":[
        "electric",
        "contractor"
    ],
    "wof:name":"Youngblood Electric Inc",
    "wof:placetype":"venue"
},
  "geometry": {"coordinates":[-97.58864699999999,35.35463],"type":"Point"}
}