{
  "type": "Feature",
  "properties": {
    "addr:full":"2035 W Elk Ave Duncan OK 73533",
    "addr:housenumber":"2035",
    "addr:postcode":"73533",
    "addr:street":"W Elk Ave",
    "iso:country":"US",
    "sg:address":"2035 W Elk Ave",
    "sg:city":"Duncan",
    "sg:classifiers":[
        {
            "category":"Health Services",
            "subcategory":"Doctor",
            "type":"Services"
        }
    ],
    "sg:phone":"+1 580 255 4880",
    "sg:postcode":"73533",
    "sg:province":"OK",
    "sg:tags":[
        "dentist"
    ],
    "wof:name":"Schreiner & Schreiner",
    "wof:placetype":"venue"
},
  "geometry": {"coordinates":[-97.97260799999999,34.521741],"type":"Point"}
}