{
  "type": "Feature",
  "properties": {
    "iso:country":"US",
    "sg:address":"2035 W Elk Ave",
    "sg:city":"Duncan",
    "sg:classifiers":[
        {
            "category":"Health Services",
            "subcategory":"Doctor",
            "type":"Services"
        }
    ],
    "sg:phone":"+1 580 255 4880",
    "sg:postcode":"73533",
    "sg:province":"OK",
    "sg:tags":[
        "dentist"
    ],
    "wof:name":"Schreiner & Schreiner",
    "wof:placetype":"venue"
},
  "geometry": {"coordinates":[-97.972608,34.521741],"type":"Point"}
}