{
  "type": "Feature",
  "properties": {
    "iso:country":"US",
    "sg:address":"6310 Antler Ridge Rd",
    "sg:city":"Sand Springs",
    "sg:classifiers":[
        {
            "category":"Building & Trades",
            "subcategory":"Plumbing",
            "type":"Services"
        }
    ],
    "sg:phone":"+1 918 246 0006",
    "sg:postcode":"74063",
    "sg:province":"OK",
    "sg:tags":[
        "air",
        "heating",
        "conditioning",
        "contractor"
    ],
    "wof:name":"Actionaire",
    "wof:placetype":"venue"
},
  "geometry": {"coordinates":[-96.111323,36.226306],"type":"Point"}
}