{
  "type": "Feature",
  "properties": {
    "iso:country":"US",
    "sg:address":"2509 S Oklahoma Ave",
    "sg:city":"Oklahoma City",
    "sg:classifiers":[
        {
            "category":"Organizations",
            "subcategory":"Religious Organization",
            "type":"Services"
        }
    ],
    "sg:phone":"+1 405 319 0804",
    "sg:postcode":"73129",
    "sg:province":"OK",
    "sg:tags":[
        "church"
    ],
    "wof:name":"Street People Ministries",
    "wof:placetype":"venue"
},
  "geometry": {"coordinates":[-97.51058500000001,35.439473],"type":"Point"}
}