{
  "type": "Feature",
  "properties": {
    "iso:country":"US",
    "sg:address":"500 S Meridian Ave",
    "sg:city":"Oklahoma City",
    "sg:classifiers":[
        {
            "category":"Restaurant",
            "type":"Food & Drink"
        }
    ],
    "sg:phone":"+1 405 948 8168",
    "sg:postcode":"73108",
    "sg:province":"OK",
    "wof:name":"Jin Wei Restaurant",
    "wof:placetype":"venue"
},
  "geometry": {"coordinates":[-97.601038,35.461713],"type":"Point"}
}