{
  "type": "Feature",
  "properties": {
    "addr:full":"1309 S Agnew Ave Oklahoma City OK 73108",
    "addr:housenumber":"1309",
    "addr:postcode":"73108",
    "addr:street":"S Agnew Ave",
    "iso:country":"US",
    "sg:address":"1309 S Agnew Ave",
    "sg:city":"Oklahoma City",
    "sg:classifiers":[
        {
            "category":"Restaurant",
            "type":"Food & Drink"
        }
    ],
    "sg:phone":"+1 405 947 1484",
    "sg:postcode":"73108",
    "sg:province":"OK",
    "sg:tags":[
        "eating"
    ],
    "wof:name":"Applewoods Restaurant",
    "wof:placetype":"venue"
},
  "geometry": {"coordinates":[-97.55471,35.451833],"type":"Point"}
}