{
  "type": "Feature",
  "properties": {
    "iso:country":"US",
    "sg:address":"8101 N Norfolk Rd",
    "sg:city":"Cushing",
    "sg:classifiers":[
        {
            "category":"Manufacturing",
            "subcategory":"Apparel",
            "type":"Manufacturing & Wholesale Goods"
        }
    ],
    "sg:phone":"+1 405 372 0421",
    "sg:postcode":"74023",
    "sg:province":"OK",
    "sg:tags":[
        "drapery",
        "contractor"
    ],
    "wof:name":"Hancock's Upholstery",
    "wof:placetype":"venue"
},
  "geometry": {"coordinates":[-96.713921,36.065268],"type":"Point"}
}