{
  "type": "Feature",
  "properties": {
    "iso:country":"US",
    "sg:address":"13901 N Cincinnati Ave",
    "sg:city":"Skiatook",
    "sg:classifiers":[
        {
            "category":"Retail",
            "subcategory":"Auto Repair",
            "type":"Services"
        }
    ],
    "sg:phone":"+1 918 396 2878",
    "sg:postcode":"74070",
    "sg:province":"OK",
    "sg:tags":[
        "body"
    ],
    "wof:name":"Skalnik Automotive",
    "wof:placetype":"venue"
},
  "geometry": {"coordinates":[-95.99132400000001,36.353559],"type":"Point"}
}