{
  "type": "Feature",
  "properties": {
    "iso:country":"US",
    "sg:address":"4510 US Hwy 70",
    "sg:city":"Durant",
    "sg:classifiers":[
        {
            "category":"Home & Garden",
            "subcategory":"Garden Supply",
            "type":"Retail Goods"
        }
    ],
    "sg:phone":"+1 580 931 3722",
    "sg:postcode":"74701",
    "sg:province":"OK",
    "sg:tags":[
        "lawn",
        "mower"
    ],
    "wof:name":"Stacy's Small Engine Repair",
    "wof:placetype":"venue"
},
  "geometry": {"coordinates":[-96.422601,33.997845],"type":"Point"}
}