{
  "type": "Feature",
  "properties": {
    "addr:full":"301 W Boyd St Norman OK 73069",
    "addr:housenumber":"301",
    "addr:postcode":"73069",
    "addr:street":"W Boyd St",
    "iso:country":"US",
    "sg:address":"301 W Boyd St",
    "sg:city":"Norman",
    "sg:classifiers":[
        {
            "category":"Mining & Drilling",
            "type":"Manufacturing & Wholesale Goods"
        }
    ],
    "sg:phone":"+1 405 701 0676",
    "sg:postcode":"73069",
    "sg:province":"OK",
    "sg:tags":[
        "oil",
        "gas",
        "producer"
    ],
    "wof:name":"Keith Walker Oil & Gas",
    "wof:placetype":"venue"
},
  "geometry": {"coordinates":[-97.44464499999999,35.211127],"type":"Point"}
}