{
  "type": "Feature",
  "properties": {
    "iso:country":"US",
    "sg:address":"1240 Exchange Ave",
    "sg:city":"Oklahoma City",
    "sg:classifiers":[
        {
            "category":"Building & Trades",
            "subcategory":"Construction",
            "type":"Services"
        }
    ],
    "sg:phone":"+1 405 235 4013",
    "sg:postcode":"73108",
    "sg:province":"OK",
    "sg:tags":[
        "mfg",
        "contractor",
        "sandblasting",
        "hanging",
        "sig",
        "special"
    ],
    "wof:name":"Clean It Co Inc",
    "wof:placetype":"venue"
},
  "geometry": {"coordinates":[-97.534615,35.460753],"type":"Point"}
}