{
  "type": "Feature",
  "properties": {
    "addr:full":"733 Arlington St Ada OK 74820",
    "addr:housenumber":"733",
    "addr:postcode":"74820",
    "addr:street":"Arlington St",
    "iso:country":"US",
    "sg:address":"733 Arlington St",
    "sg:city":"Ada",
    "sg:classifiers":[
        {
            "category":"Health Services",
            "subcategory":"Chiropractor",
            "type":"Services"
        }
    ],
    "sg:phone":"+1 580 332 2688",
    "sg:postcode":"74820",
    "sg:province":"OK",
    "wof:name":"W Frank Starns Jr DC",
    "wof:placetype":"venue"
},
  "geometry": {"coordinates":[-96.66922,34.781631],"type":"Point"}
}