{
  "type": "Feature",
  "properties": {
    "iso:country":"US",
    "sg:address":"12225 I- 35",
    "sg:city":"Oklahoma City",
    "sg:classifiers":[
        {
            "category":"Restaurant",
            "type":"Food & Drink"
        }
    ],
    "sg:phone":"+1 405 478 2143",
    "sg:postcode":"73131",
    "sg:province":"OK",
    "wof:name":"Godfather's Pizza",
    "wof:placetype":"venue"
},
  "geometry": {"coordinates":[-97.433038,35.594235],"type":"Point"}
}