{
  "type": "Feature",
  "properties": {
    "addr:full":"7500 New Sapulpa Rd Tulsa OK 74131",
    "addr:housenumber":"7500",
    "addr:postcode":"74131",
    "addr:street":"New Sapulpa Rd",
    "iso:country":"US",
    "sg:address":"7500 New Sapulpa Rd",
    "sg:city":"Tulsa",
    "sg:classifiers":[
        {
            "category":"Recreation",
            "subcategory":"Marina",
            "type":"Entertainment"
        }
    ],
    "sg:phone":"+1 918 224 6530",
    "sg:postcode":"74131",
    "sg:province":"OK",
    "sg:tags":[
        "operation"
    ],
    "wof:name":"Windmill Run Marina",
    "wof:placetype":"venue"
},
  "geometry": {"coordinates":[-96.07255600000001,36.056428],"type":"Point"}
}