{
  "type": "Feature",
  "properties": {
    "iso:country":"US",
    "sg:address":"6600 N Meridian Ave",
    "sg:city":"Oklahoma City",
    "sg:classifiers":[
        {
            "category":"Professional",
            "subcategory":"Employment Agencies",
            "type":"Services"
        }
    ],
    "sg:phone":"+1 405 810 9355",
    "sg:postcode":"73116",
    "sg:province":"OK",
    "sg:tags":[
        "leasing"
    ],
    "sg:website":"www.freedomservices.net",
    "wof:name":"Freedom Services Inc",
    "wof:placetype":"venue"
},
  "geometry": {"coordinates":[-97.601119,35.541655],"type":"Point"}
}