{
  "type": "Feature",
  "properties": {
    "addr:full":"57100 E Hwy 59 Fairland OK 74343",
    "addr:housenumber":"57100",
    "addr:postcode":"74343",
    "addr:street":"E Hwy 59",
    "iso:country":"US",
    "sg:address":"57100 E Hwy 59",
    "sg:city":"Fairland",
    "sg:classifiers":[
        {
            "category":"Professional",
            "subcategory":"Business Services",
            "type":"Services"
        }
    ],
    "sg:phone":"+1 918 257 8142",
    "sg:postcode":"74343",
    "sg:province":"OK",
    "wof:name":"Time After Time",
    "wof:placetype":"venue"
},
  "geometry": {"coordinates":[-94.85385599999999,36.678553],"type":"Point"}
}