{
  "type": "Feature",
  "properties": {
    "iso:country":"US",
    "sg:address":"116 N 3rd St",
    "sg:city":"Madill",
    "sg:classifiers":[
        {
            "category":"Home & Garden",
            "subcategory":"Building Materials",
            "type":"Retail Goods"
        }
    ],
    "sg:phone":"+1 580 795 2339",
    "sg:postcode":"73446",
    "sg:province":"OK",
    "wof:name":"Homecenter 18",
    "wof:placetype":"venue"
},
  "geometry": {"coordinates":[-96.769425,34.091398],"type":"Point"}
}