{
  "type": "Feature",
  "properties": {
    "addr:full":"27502 S 4380 Rd Vinita OK 74301",
    "addr:housenumber":"27502",
    "addr:postcode":"74301",
    "addr:street":"S 4380 Rd",
    "iso:country":"US",
    "sg:address":"27502 S 4380 Rd",
    "sg:city":"Vinita",
    "sg:classifiers":[
        {
            "category":"Organizations",
            "subcategory":"Religious Organization",
            "type":"Services"
        }
    ],
    "sg:phone":"+1 918 256 4180",
    "sg:postcode":"74301",
    "sg:province":"OK",
    "wof:name":"Cowboy Junction Bookstore",
    "wof:placetype":"venue"
},
  "geometry": {"coordinates":[-95.19756,36.620799],"type":"Point"}
}