{
  "type": "Feature",
  "properties": {
    "iso:country":"US",
    "sg:address":"227 S 67th East Ave",
    "sg:city":"Tulsa",
    "sg:classifiers":[
        {
            "category":"Home & Garden",
            "subcategory":"Carpets & Floor Coverings",
            "type":"Retail Goods"
        }
    ],
    "sg:phone":"+1 918 610 5150",
    "sg:postcode":"74112",
    "sg:province":"OK",
    "sg:tags":[
        "dealer",
        "rug"
    ],
    "wof:name":"Specialized Beveling",
    "wof:placetype":"venue"
},
  "geometry": {"coordinates":[-95.902187,36.157407],"type":"Point"}
}