{
  "type": "Feature",
  "properties": {
    "iso:country":"US",
    "sg:address":"325 N Littler Ave",
    "sg:city":"Edmond",
    "sg:classifiers":[
        {
            "category":"Recreation",
            "type":"Entertainment"
        }
    ],
    "sg:phone":"+1 405 330 0373",
    "sg:postcode":"73034",
    "sg:province":"OK",
    "sg:tags":[
        "instruction",
        "golf"
    ],
    "wof:name":"Sport Golf Training Facility",
    "wof:placetype":"venue"
},
  "geometry": {"coordinates":[-97.479222,35.658567],"type":"Point"}
}