{
  "type": "Feature",
  "properties": {
    "iso:country":"US",
    "sg:address":"629 NW 113th St",
    "sg:city":"Oklahoma City",
    "sg:classifiers":[
        {
            "category":"Building & Trades",
            "subcategory":"Construction",
            "type":"Services"
        }
    ],
    "sg:phone":"+1 405 751 1385",
    "sg:postcode":"73114",
    "sg:province":"OK",
    "sg:tags":[
        "janitorial"
    ],
    "wof:name":"H&D Janitorial",
    "wof:placetype":"venue"
},
  "geometry": {"coordinates":[-97.52351899999999,35.585345],"type":"Point"}
}