{
  "type": "Feature",
  "properties": {
    "iso:country":"US",
    "sg:address":"8131 S Lakewood Pl",
    "sg:city":"Tulsa",
    "sg:classifiers":[
        {
            "category":"Mining & Drilling",
            "type":"Manufacturing & Wholesale Goods"
        }
    ],
    "sg:phone":"+1 918 488 0107",
    "sg:postcode":"74137",
    "sg:province":"OK",
    "sg:tags":[
        "crude",
        "production",
        "gas"
    ],
    "wof:name":"Robert P Jackman Inc",
    "wof:placetype":"venue"
},
  "geometry": {"coordinates":[-95.90556599999999,36.04431],"type":"Point"}
}