{
  "type": "Feature",
  "properties": {
    "addr:full":"1303 SW Lee Blvd Lawton OK 73501",
    "addr:housenumber":"1303",
    "addr:postcode":"73501",
    "addr:street":"Sw Lee Blvd",
    "iso:country":"US",
    "sg:address":"1303 SW Lee Blvd",
    "sg:city":"Lawton",
    "sg:classifiers":[
        {
            "category":"Restaurant",
            "type":"Food & Drink"
        }
    ],
    "sg:phone":"+1 580 355 7888",
    "sg:postcode":"73501",
    "sg:province":"OK",
    "wof:name":"Hot Wok Chinese Restaurant",
    "wof:placetype":"venue"
},
  "geometry": {"coordinates":[-98.40756500000001,34.594314],"type":"Point"}
}