{
  "type": "Feature",
  "properties": {
    "iso:country":"US",
    "sg:address":"6565 S Yale Ave",
    "sg:city":"Tulsa",
    "sg:classifiers":[
        {
            "category":"Professional",
            "type":"Services"
        }
    ],
    "sg:phone":"+1 918 481 7880",
    "sg:postcode":"74136",
    "sg:province":"OK",
    "sg:tags":[
        "establishment"
    ],
    "wof:name":"Ron Smith Transplant Coordntr",
    "wof:placetype":"venue"
},
  "geometry": {"coordinates":[-95.922046,36.069389],"type":"Point"}
}