{
  "type": "Feature",
  "properties": {
    "iso:country":"US",
    "sg:address":"317 E Main St",
    "sg:city":"Watonga",
    "sg:classifiers":[
        {
            "category":"Building & Trades",
            "subcategory":"Construction",
            "type":"Services"
        }
    ],
    "sg:phone":"+1 580 623 5046",
    "sg:postcode":"73772",
    "sg:province":"OK",
    "sg:tags":[
        "repairing",
        "remodeling",
        "contractor"
    ],
    "wof:name":"Home Remodeling & Repair",
    "wof:placetype":"venue"
},
  "geometry": {"coordinates":[-98.410516,35.844479],"type":"Point"}
}