{
  "type": "Feature",
  "properties": {
    "iso:country":"US",
    "sg:address":"1004 E Main St",
    "sg:city":"Cordell",
    "sg:classifiers":[
        {
            "category":"Retail",
            "subcategory":"Auto Repair",
            "type":"Services"
        }
    ],
    "sg:phone":"+1 580 832 2615",
    "sg:postcode":"73632",
    "sg:province":"OK",
    "sg:tags":[
        "muffler",
        "exhaust",
        "system",
        "automotive"
    ],
    "wof:name":"Dee Hines Welding & Mufflers",
    "wof:placetype":"venue"
},
  "geometry": {"coordinates":[-98.979985,35.291185],"type":"Point"}
}