{
  "type": "Feature",
  "properties": {
    "iso:country":"US",
    "sg:address":"1701 Belle Isle Blvd",
    "sg:city":"Oklahoma City",
    "sg:classifiers":[
        {
            "category":"Shopping",
            "subcategory":"Shoes",
            "type":"Retail Goods"
        }
    ],
    "sg:phone":"+1 405 810 9080",
    "sg:postcode":"73118",
    "sg:province":"OK",
    "sg:website":"www.shoecarnival.com",
    "wof:name":"Shoe Carnival",
    "wof:placetype":"venue"
},
  "geometry": {"coordinates":[-97.542536,35.522389],"type":"Point"}
}