{
  "type": "Feature",
  "properties": {
    "iso:country":"US",
    "sg:address":"1621 N Harrison Ave",
    "sg:city":"Shawnee",
    "sg:classifiers":[
        {
            "category":"Government",
            "subcategory":"Office",
            "type":"Public Place"
        }
    ],
    "sg:phone":"+1 405 275 0142",
    "sg:postcode":"74804",
    "sg:province":"OK",
    "sg:tags":[
        "armed",
        "force",
        "recruiting"
    ],
    "wof:name":"US Air Force Recruiting",
    "wof:placetype":"venue"
},
  "geometry": {"coordinates":[-96.912015,35.34929],"type":"Point"}
}