{
  "type": "Feature",
  "properties": {
    "iso:country":"US",
    "sg:address":"109 E North St",
    "sg:city":"Coweta",
    "sg:classifiers":[
        {
            "category":"Retail",
            "subcategory":"Self-service Laundry",
            "type":"Services"
        }
    ],
    "sg:phone":"+1 918 486 2262",
    "sg:postcode":"74429",
    "sg:province":"OK",
    "sg:tags":[
        "coin"
    ],
    "wof:name":"Coweta Laundromat",
    "wof:placetype":"venue"
},
  "geometry": {"coordinates":[-95.650824,35.959193],"type":"Point"}
}