{
  "type": "Feature",
  "properties": {
    "iso:country":"US",
    "sg:address":"1925 S Elm Pl",
    "sg:city":"Broken Arrow",
    "sg:classifiers":[
        {
            "category":"Retail",
            "subcategory":"Laundry & Dry Cleaning",
            "type":"Services"
        },
        {
            "category":"Shopping",
            "subcategory":"Clothing, Apparel, & Fashions",
            "type":"Retail Goods"
        }
    ],
    "sg:phone":"+1 918 455 1913",
    "sg:postcode":"74012",
    "sg:province":"OK",
    "sg:tags":[
        "drycleaning",
        "plant",
        "uniform"
    ],
    "wof:name":"Yale Cleaners Inc",
    "wof:placetype":"venue"
},
  "geometry": {"coordinates":[-95.79740700000001,36.030527],"type":"Point"}
}