{
  "type": "Feature",
  "properties": {
    "iso:country":"US",
    "sg:address":"907 S Detroit Ave",
    "sg:city":"Tulsa",
    "sg:classifiers":[
        {
            "category":"Insurance",
            "subcategory":"Insurance Agent",
            "type":"Services"
        }
    ],
    "sg:phone":"+1 918 749 1641",
    "sg:postcode":"74120",
    "sg:province":"OK",
    "wof:name":"Insurers Loss Management",
    "wof:placetype":"venue"
},
  "geometry": {"coordinates":[-95.983893,36.148],"type":"Point"}
}