{
  "type": "Feature",
  "properties": {
    "addr:full":"6700 N Classen Blvd Oklahoma City OK 73116",
    "addr:housenumber":"6700",
    "addr:postcode":"73116",
    "addr:street":"N Classen Blvd",
    "iso:country":"US",
    "sg:address":"6700 N Classen Blvd",
    "sg:city":"Oklahoma City",
    "sg:classifiers":[
        {
            "category":"Insurance",
            "subcategory":"Insurance Agent",
            "type":"Services"
        }
    ],
    "sg:phone":"+1 405 848 8960",
    "sg:postcode":"73116",
    "sg:province":"OK",
    "sg:website":"www.ailife.com",
    "wof:name":"American Income Life Ins Co",
    "wof:placetype":"venue"
},
  "geometry": {"coordinates":[-97.526861,35.540483],"type":"Point"}
}