{
  "type": "Feature",
  "properties": {
    "iso:country":"US",
    "sg:address":"1412 Wendell Dr",
    "sg:city":"Durant",
    "sg:classifiers":[
        {
            "category":"Building & Trades",
            "subcategory":"Plumbing",
            "type":"Services"
        }
    ],
    "sg:phone":"+1 580 924 3323",
    "sg:postcode":"74701",
    "sg:province":"OK",
    "sg:tags":[
        "plumbing",
        "contractor"
    ],
    "wof:name":"Sanitary Plumbing Co",
    "wof:placetype":"venue"
},
  "geometry": {"coordinates":[-96.390531,34.004441],"type":"Point"}
}