{
  "type": "Feature",
  "properties": {
    "iso:country":"US",
    "sg:address":"2019 Cedar St",
    "sg:city":"Ponca City",
    "sg:classifiers":[
        {
            "category":"Building & Trades",
            "subcategory":"Landscaping Services",
            "type":"Services"
        }
    ],
    "sg:phone":"+1 580 767 1233",
    "sg:postcode":"74604",
    "sg:province":"OK",
    "wof:name":"A Plus Tree Service",
    "wof:placetype":"venue"
},
  "geometry": {"coordinates":[-97.06088,36.72667],"type":"Point"}
}