{
  "type": "Feature",
  "properties": {
    "iso:country":"US",
    "sg:address":"5808 E 6th Ave",
    "sg:city":"Stillwater",
    "sg:classifiers":[
        {
            "category":"Food & Beverages",
            "subcategory":"Groceries & Convenience Stores",
            "type":"Retail Goods"
        }
    ],
    "sg:phone":"+1 405 377 6662",
    "sg:postcode":"74074",
    "sg:province":"OK",
    "wof:name":"Country Convenience",
    "wof:placetype":"venue"
},
  "geometry": {"coordinates":[-96.97931,36.116464],"type":"Point"}
}