{
  "type": "Feature",
  "properties": {
    "iso:country":"US",
    "sg:address":"1515 N Florence Ave",
    "sg:city":"Claremore",
    "sg:classifiers":[
        {
            "category":"Education",
            "subcategory":"Library",
            "type":"Public Place"
        }
    ],
    "sg:phone":"+1 918 341 1564",
    "sg:postcode":"74017",
    "sg:province":"OK",
    "wof:name":"Will Rogers Library",
    "wof:placetype":"venue"
},
  "geometry": {"coordinates":[-95.60375500000001,36.324941],"type":"Point"}
}