{
  "type": "Feature",
  "properties": {
    "iso:country":"US",
    "sg:address":"1504 Howard Dr",
    "sg:city":"Oklahoma City",
    "sg:classifiers":[
        {
            "category":"Professional",
            "subcategory":"Business Services",
            "type":"Services"
        }
    ],
    "sg:phone":"+1 405 590 8059",
    "sg:postcode":"73115",
    "sg:province":"OK",
    "sg:tags":[
        "inspection"
    ],
    "wof:name":"A 1 Inspection Svc",
    "wof:placetype":"venue"
},
  "geometry": {"coordinates":[-97.428122,35.449645],"type":"Point"}
}