{
  "type": "Feature",
  "properties": {
    "addr:full":"6505 Avondale Dr Oklahoma City OK 73116",
    "addr:housenumber":"6505",
    "addr:postcode":"73116",
    "addr:street":"Avondale Dr",
    "iso:country":"US",
    "sg:address":"6505 Avondale Dr",
    "sg:city":"Oklahoma City",
    "sg:classifiers":[
        {
            "category":"Professional",
            "subcategory":"Business Services",
            "type":"Services"
        }
    ],
    "sg:phone":"+1 405 706 1948",
    "sg:postcode":"73116",
    "sg:province":"OK",
    "sg:tags":[
        "interior",
        "residential",
        "designer",
        "commercial"
    ],
    "wof:name":"D Design",
    "wof:placetype":"venue"
},
  "geometry": {"coordinates":[-97.532203,35.539106],"type":"Point"}
}