{
  "type": "Feature",
  "properties": {
    "iso:country":"US",
    "sg:address":"111 W 119th St S",
    "sg:city":"Jenks",
    "sg:classifiers":[
        {
            "category":"Restaurant",
            "type":"Food & Drink"
        }
    ],
    "sg:phone":"+1 918 299 5267",
    "sg:postcode":"74037",
    "sg:province":"OK",
    "sg:tags":[
        "eating"
    ],
    "wof:name":"Hughes Restaurant Systems",
    "wof:placetype":"venue"
},
  "geometry": {"coordinates":[-95.968575,35.991381],"type":"Point"}
}