{
  "type": "Feature",
  "properties": {
    "iso:country":"US",
    "sg:address":"315 W Lafayette Ave",
    "sg:city":"Checotah",
    "sg:classifiers":[
        {
            "category":"Professional",
            "subcategory":"Accounting & Tax Preparation",
            "type":"Services"
        }
    ],
    "sg:phone":"+1 918 473 1040",
    "sg:postcode":"74426",
    "sg:province":"OK",
    "sg:tags":[
        "return",
        "filing"
    ],
    "wof:name":"Jackson Hewitt Tax Svc",
    "wof:placetype":"venue"
},
  "geometry": {"coordinates":[-95.523746,35.469292],"type":"Point"}
}