{
  "type": "Feature",
  "properties": {
    "addr:full":"8605 N Norfolk Rd Cushing OK 74023",
    "addr:housenumber":"8605",
    "addr:postcode":"74023",
    "addr:street":"N Norfolk Rd",
    "iso:country":"US",
    "sg:address":"8605 N Norfolk Rd",
    "sg:city":"Cushing",
    "sg:classifiers":[
        {
            "category":"Retail",
            "subcategory":"Animal Services",
            "type":"Services"
        }
    ],
    "sg:phone":"+1 918 387 2200",
    "sg:postcode":"74023",
    "sg:province":"OK",
    "sg:tags":[
        "training",
        "dog"
    ],
    "wof:name":"Happy Tails Dog Training",
    "wof:placetype":"venue"
},
  "geometry": {"coordinates":[-96.71386,36.081621],"type":"Point"}
}