{
  "type": "Feature",
  "properties": {
    "addr:full":"108 W Main St Ada OK 74820",
    "addr:housenumber":"108",
    "addr:postcode":"74820",
    "addr:street":"W Main St",
    "iso:country":"US",
    "sg:address":"108 W Main St",
    "sg:city":"Ada",
    "sg:classifiers":[
        {
            "category":"Professional",
            "subcategory":"Business Services",
            "type":"Services"
        }
    ],
    "sg:phone":"+1 580 265 9626",
    "sg:postcode":"74820",
    "sg:province":"OK",
    "sg:tags":[
        "auctioneer"
    ],
    "wof:name":"Ok Auction 28",
    "wof:placetype":"venue"
},
  "geometry": {"coordinates":[-96.680172,34.774569],"type":"Point"}
}