{
  "type": "Feature",
  "properties": {
    "iso:country":"US",
    "sg:address":"2404 N Westminster Rd",
    "sg:city":"Spencer",
    "sg:classifiers":[
        {
            "category":"Retail",
            "subcategory":"Repair Shop",
            "type":"Services"
        }
    ],
    "sg:phone":"+1 405 427 9419",
    "sg:postcode":"73084",
    "sg:province":"OK",
    "sg:tags":[
        "pump"
    ],
    "wof:name":"Boulware Pump & Supply",
    "wof:placetype":"venue"
},
  "geometry": {"coordinates":[-97.335587,35.493931],"type":"Point"}
}