{
  "type": "Feature",
  "properties": {
    "addr:full":"1447 SE Washington St Idabel OK 74745",
    "addr:housenumber":"1447",
    "addr:postcode":"74745",
    "addr:street":"Se Washington St",
    "iso:country":"US",
    "sg:address":"1447 SE Washington St",
    "sg:city":"Idabel",
    "sg:classifiers":[
        {
            "category":"Shopping",
            "subcategory":"Clothing, Apparel, & Fashions",
            "type":"Retail Goods"
        }
    ],
    "sg:phone":"+1 580 286 9200",
    "sg:postcode":"74745",
    "sg:province":"OK",
    "sg:tags":[
        "shop",
        "bridal",
        "rental",
        "wear",
        "formal"
    ],
    "wof:name":"Chandras Boutique & Formal",
    "wof:placetype":"venue"
},
  "geometry": {"coordinates":[-94.81030199999999,33.895607],"type":"Point"}
}