{
  "type": "Feature",
  "properties": {
    "addr:full":"109 S Blair St Stillwater OK 74074",
    "addr:housenumber":"109",
    "addr:postcode":"74074",
    "addr:street":"S Blair St",
    "iso:country":"US",
    "sg:address":"109 S Blair St",
    "sg:city":"Stillwater",
    "sg:classifiers":[
        {
            "category":"Professional",
            "subcategory":"Computer Services",
            "type":"Services"
        }
    ],
    "sg:phone":"+1 405 614 0654",
    "sg:postcode":"74074",
    "sg:province":"OK",
    "sg:tags":[
        "repair"
    ],
    "wof:name":"Helpdesk",
    "wof:placetype":"venue"
},
  "geometry": {"coordinates":[-97.037502,36.122733],"type":"Point"}
}