{
  "type": "Feature",
  "properties": {
    "iso:country":"US",
    "sg:address":"4628 SE 19th St",
    "sg:city":"Oklahoma City",
    "sg:classifiers":[
        {
            "category":"Autos & Motor Vehicles",
            "subcategory":"Recreational Vehicle Sales",
            "type":"Retail Goods"
        }
    ],
    "sg:phone":"+1 405 619 1889",
    "sg:postcode":"73115",
    "sg:province":"OK",
    "wof:name":"G & G Camper Supply",
    "wof:placetype":"venue"
},
  "geometry": {"coordinates":[-97.435226,35.44465],"type":"Point"}
}