{
  "type": "Feature",
  "properties": {
    "addr:full":"8105 Glade Ave Oklahoma City OK 73132",
    "addr:housenumber":"8105",
    "addr:postcode":"73132",
    "addr:street":"Glade Ave",
    "iso:country":"US",
    "sg:address":"8105 Glade Ave",
    "sg:city":"Oklahoma City",
    "sg:classifiers":[
        {
            "category":"Professional",
            "subcategory":"Detective & Security Services",
            "type":"Services"
        }
    ],
    "sg:phone":"+1 405 773 3188",
    "sg:postcode":"73132",
    "sg:province":"OK",
    "sg:tags":[
        "system"
    ],
    "sg:website":"www.ealeselectronics.com",
    "wof:name":"Eales Electronics Corp",
    "wof:placetype":"venue"
},
  "geometry": {"coordinates":[-97.645669,35.553205],"type":"Point"}
}