{
  "type": "Feature",
  "properties": {
    "iso:country":"US",
    "sg:address":"1928 N Broadway St",
    "sg:city":"Poteau",
    "sg:classifiers":[
        {
            "category":"Personal",
            "subcategory":"Beauty Salon",
            "type":"Services"
        }
    ],
    "sg:phone":"+1 918 647 9775",
    "sg:postcode":"74953",
    "sg:province":"OK",
    "wof:name":"The Clip Joint",
    "wof:placetype":"venue"
},
  "geometry": {"coordinates":[-94.625949,35.067447],"type":"Point"}
}