{
  "type": "Feature",
  "properties": {
    "addr:full":"124 E Choctaw St Tahlequah OK 74464",
    "addr:housenumber":"124",
    "addr:postcode":"74464",
    "addr:street":"E Choctaw St",
    "iso:country":"US",
    "sg:address":"124 E Choctaw St",
    "sg:city":"Tahlequah",
    "sg:classifiers":[
        {
            "category":"Education",
            "subcategory":"Library",
            "type":"Public Place"
        }
    ],
    "sg:phone":"+1 918 458 0577",
    "sg:postcode":"74464",
    "sg:province":"OK",
    "wof:name":"Tsa LA Gi Library",
    "wof:placetype":"venue"
},
  "geometry": {"coordinates":[-94.97169599999999,35.910935],"type":"Point"}
}