{
  "type": "Feature",
  "properties": {
    "iso:country":"US",
    "sg:address":"411 W 11th St",
    "sg:city":"Shawnee",
    "sg:classifiers":[
        {
            "category":"Retail",
            "subcategory":"Laundry & Dry Cleaning",
            "type":"Services"
        }
    ],
    "sg:phone":"+1 405 273 5797",
    "sg:postcode":"74801",
    "sg:province":"OK",
    "sg:tags":[
        "cleaners",
        "rug",
        "carpet"
    ],
    "wof:name":"Maston Carpet Cleaners",
    "wof:placetype":"venue"
},
  "geometry": {"coordinates":[-96.929808,35.331253],"type":"Point"}
}