{
  "type": "Feature",
  "properties": {
    "addr:full":"8208 S Indiana Ave Oklahoma City OK 73159",
    "addr:housenumber":"8208",
    "addr:postcode":"73159",
    "addr:street":"S Indiana Ave",
    "iso:country":"US",
    "sg:address":"8208 S Indiana Ave",
    "sg:city":"Oklahoma City",
    "sg:classifiers":[
        {
            "category":"Retail",
            "subcategory":"Repair Shop",
            "type":"Services"
        }
    ],
    "sg:phone":"+1 405 602 3933",
    "sg:postcode":"73159",
    "sg:province":"OK",
    "sg:tags":[
        "bathtub",
        "sink",
        "refinishing"
    ],
    "wof:name":"Nu-Look Finish",
    "wof:placetype":"venue"
},
  "geometry": {"coordinates":[-97.542694,35.384371],"type":"Point"}
}