{
  "type": "Feature",
  "properties": {
    "iso:country":"US",
    "sg:address":"7101 NW 39th Expy",
    "sg:city":"Bethany",
    "sg:classifiers":[
        {
            "category":"Restaurant",
            "type":"Food & Drink"
        }
    ],
    "sg:phone":"+1 405 722 7827",
    "sg:postcode":"73008",
    "sg:province":"OK",
    "sg:tags":[
        "eating"
    ],
    "wof:name":"Subway",
    "wof:placetype":"venue"
},
  "geometry": {"coordinates":[-97.637737,35.513267],"type":"Point"}
}