{
  "type": "Feature",
  "properties": {
    "iso:country":"US",
    "sg:address":"13439 Broadway Exn",
    "sg:city":"Oklahoma City",
    "sg:classifiers":[
        {
            "category":"Utilities",
            "subcategory":"Mobile Phone",
            "type":"Services"
        }
    ],
    "sg:phone":"+1 405 529 8500",
    "sg:postcode":"73114",
    "sg:province":"OK",
    "sg:tags":[
        "cellular",
        "fiber",
        "tel",
        "telephone",
        "optic"
    ],
    "wof:name":"Dobson CC LP",
    "wof:placetype":"venue"
},
  "geometry": {"coordinates":[-97.500632,35.603804],"type":"Point"}
}