{
  "type": "Feature",
  "properties": {
    "addr:full":"1605 E 1st St Chandler OK 74834",
    "addr:housenumber":"1605",
    "addr:postcode":"74834",
    "addr:street":"E 1St St",
    "iso:country":"US",
    "sg:address":"1605 E 1st St",
    "sg:city":"Chandler",
    "sg:classifiers":[
        {
            "category":"Social Services",
            "subcategory":"Child Care",
            "type":"Services"
        }
    ],
    "sg:phone":"+1 405 258 5571",
    "sg:postcode":"74834",
    "sg:province":"OK",
    "wof:name":"Toddler Town Playland",
    "wof:placetype":"venue"
},
  "geometry": {"coordinates":[-96.862362,35.709726],"type":"Point"}
}