{
  "type": "Feature",
  "properties": {
    "iso:country":"US",
    "sg:address":"8310 N Western Ave",
    "sg:city":"Oklahoma City",
    "sg:classifiers":[
        {
            "category":"Organizations",
            "subcategory":"Community Association",
            "type":"Services"
        }
    ],
    "sg:phone":"+1 405 810 8440",
    "sg:postcode":"73114",
    "sg:province":"OK",
    "sg:tags":[
        "club"
    ],
    "wof:name":"Classics Bar & Grill",
    "wof:placetype":"venue"
},
  "geometry": {"coordinates":[-97.531273,35.555449],"type":"Point"}
}