{
  "type": "Feature",
  "properties": {
    "iso:country":"US",
    "sg:address":"7 NW 7th St",
    "sg:city":"Piedmont",
    "sg:classifiers":[
        {
            "category":"Retail",
            "subcategory":"Auto Repair",
            "type":"Services"
        }
    ],
    "sg:phone":"+1 405 373 0118",
    "sg:postcode":"73078",
    "sg:province":"OK",
    "sg:tags":[
        "automotive"
    ],
    "wof:name":"Performance Parts Machine",
    "wof:placetype":"venue"
},
  "geometry": {"coordinates":[-97.75393200000001,35.63836],"type":"Point"}
}