{
  "type": "Feature",
  "properties": {
    "addr:full":"1039 NW 63rd St Nichols Hills OK 73116",
    "addr:housenumber":"1039",
    "addr:postcode":"73116",
    "addr:street":"Nw 63Rd St",
    "iso:country":"US",
    "sg:address":"1039 NW 63rd St",
    "sg:city":"Nichols Hills",
    "sg:classifiers":[
        {
            "category":"Banks & Credit Unions",
            "subcategory":"Bank",
            "type":"Services"
        }
    ],
    "sg:phone":"+1 405 810 8600",
    "sg:postcode":"73116",
    "sg:province":"OK",
    "sg:tags":[
        "state"
    ],
    "wof:name":"Guarantee State Bank",
    "wof:placetype":"venue"
},
  "geometry": {"coordinates":[-97.527603,35.537319],"type":"Point"}
}