{
  "type": "Feature",
  "properties": {
    "iso:country":"US",
    "sg:address":"2803 S Bryant Ave",
    "sg:city":"Edmond",
    "sg:classifiers":[
        {
            "category":"Wholesale",
            "subcategory":"Medical Equipment & Supplies",
            "type":"Manufacturing & Wholesale Goods"
        }
    ],
    "sg:phone":"+1 405 285 4674",
    "sg:postcode":"73013",
    "sg:province":"OK",
    "sg:tags":[
        "physician",
        "surgeon"
    ],
    "wof:name":"Taylor Medical",
    "wof:placetype":"venue"
},
  "geometry": {"coordinates":[-97.460505,35.628684],"type":"Point"}
}