{
  "type": "Feature",
  "properties": {
    "iso:country":"US",
    "sg:address":"1912 S Park Dr",
    "sg:city":"Broken Bow",
    "sg:classifiers":[
        {
            "category":"Travel",
            "subcategory":"Hotels & Motels",
            "type":"Entertainment"
        }
    ],
    "sg:phone":"+1 580 584 9103",
    "sg:postcode":"74728",
    "sg:province":"OK",
    "wof:name":"Broken Bow Inn",
    "wof:placetype":"venue"
},
  "geometry": {"coordinates":[-94.739492,34.007915],"type":"Point"}
}