{
  "type": "Feature",
  "properties": {
    "iso:country":"US",
    "sg:address":"5529 SE 15th St",
    "sg:city":"Oklahoma City",
    "sg:classifiers":[
        {
            "category":"Banks & Credit Unions",
            "subcategory":"Bank",
            "type":"Services"
        }
    ],
    "sg:phone":"+1 405 677 8737",
    "sg:postcode":"73115",
    "sg:province":"OK",
    "sg:tags":[
        "financing"
    ],
    "wof:name":"American General Finance Inc",
    "wof:placetype":"venue"
},
  "geometry": {"coordinates":[-97.424645,35.449697],"type":"Point"}
}