{
  "type": "Feature",
  "properties": {
    "iso:country":"US",
    "sg:address":"1408 W Detroit St",
    "sg:city":"Broken Arrow",
    "sg:classifiers":[
        {
            "category":"Health Services",
            "subcategory":"Clinic",
            "type":"Services"
        }
    ],
    "sg:phone":"+1 918 258 1122",
    "sg:postcode":"74012",
    "sg:province":"OK",
    "sg:tags":[
        "allied"
    ],
    "wof:name":"Emergency Medical Services Plu",
    "wof:placetype":"venue"
},
  "geometry": {"coordinates":[-95.804153,36.054237],"type":"Point"}
}