{
  "type": "Feature",
  "properties": {
    "iso:country":"US",
    "sg:address":"528 State Hwy 152",
    "sg:city":"Mustang",
    "sg:classifiers":[
        {
            "category":"Autos & Motor Vehicles",
            "subcategory":"Automobile Sales",
            "type":"Retail Goods"
        }
    ],
    "sg:phone":"+1 405 376 1400",
    "sg:postcode":"73064",
    "sg:province":"OK",
    "sg:tags":[
        "car",
        "dealer"
    ],
    "wof:name":"Showcase Motorsports & Classic",
    "wof:placetype":"venue"
},
  "geometry": {"coordinates":[-97.73274600000001,35.391623],"type":"Point"}
}