{
  "type": "Feature",
  "properties": {
    "iso:country":"US",
    "sg:address":"711 W Main St",
    "sg:city":"Duncan",
    "sg:classifiers":[
        {
            "category":"Arts & Performance",
            "subcategory":"Theater",
            "type":"Entertainment"
        }
    ],
    "sg:phone":"+1 580 252 3291",
    "sg:postcode":"73533",
    "sg:province":"OK",
    "sg:tags":[
        "karaoke"
    ],
    "wof:name":"Karaoke King",
    "wof:placetype":"venue"
},
  "geometry": {"coordinates":[-97.956619,34.501853],"type":"Point"}
}