{
  "type": "Feature",
  "properties": {
    "iso:country":"US",
    "sg:address":"1000 W Wilshire Blvd",
    "sg:city":"Oklahoma City",
    "sg:classifiers":[
        {
            "category":"Real Estate",
            "subcategory":"Real Estate Agent",
            "type":"Services"
        }
    ],
    "sg:phone":"+1 405 848 6746",
    "sg:postcode":"73116",
    "sg:province":"OK",
    "wof:name":"Wyndham Properties Inc",
    "wof:placetype":"venue"
},
  "geometry": {"coordinates":[-97.531459,35.551114],"type":"Point"}
}