{
  "type": "Feature",
  "properties": {
    "iso:country":"US",
    "sg:address":"8205 E 22nd St",
    "sg:city":"Tulsa",
    "sg:classifiers":[
        {
            "category":"Real Estate",
            "subcategory":"Real Estate Operator",
            "type":"Services"
        }
    ],
    "sg:phone":"+1 918 622 2151",
    "sg:postcode":"74129",
    "sg:province":"OK",
    "sg:tags":[
        "dwelling"
    ],
    "wof:name":"Gold Medalian Properties",
    "wof:placetype":"venue"
},
  "geometry": {"coordinates":[-95.885856,36.131796],"type":"Point"}
}