{
  "type": "Feature",
  "properties": {
    "addr:full":"1117 NW 24th St Oklahoma City OK 73106",
    "addr:housenumber":"1117",
    "addr:postcode":"73106",
    "addr:street":"Nw 24Th St",
    "iso:country":"US",
    "sg:address":"1117 NW 24th St",
    "sg:city":"Oklahoma City",
    "sg:classifiers":[
        {
            "category":"Government",
            "subcategory":"Post Office",
            "type":"Public Place"
        }
    ],
    "sg:phone":"+1 405 528 8758",
    "sg:postcode":"73106",
    "sg:province":"OK",
    "sg:tags":[
        "postal",
        "us"
    ],
    "wof:name":"Northwest Station",
    "wof:placetype":"venue"
},
  "geometry": {"coordinates":[-97.531831,35.494402],"type":"Point"}
}