{
  "type": "Feature",
  "properties": {
    "iso:country":"US",
    "sg:address":"5229 S Peoria Ave",
    "sg:city":"Tulsa",
    "sg:classifiers":[
        {
            "category":"Retail",
            "subcategory":"Auto Repair",
            "type":"Services"
        }
    ],
    "sg:phone":"+1 918 743 2197",
    "sg:postcode":"74105",
    "sg:province":"OK",
    "sg:tags":[
        "station",
        "gasoline",
        "general"
    ],
    "wof:name":"Brookside Radiator",
    "wof:placetype":"venue"
},
  "geometry": {"coordinates":[-95.97566,36.089101],"type":"Point"}
}