{
  "type": "Feature",
  "properties": {
    "iso:country":"US",
    "sg:address":"317 N 1st Ave",
    "sg:city":"Durant",
    "sg:classifiers":[
        {
            "category":"Autos & Motor Vehicles",
            "subcategory":"Fuel & Gas Station",
            "type":"Retail Goods"
        }
    ],
    "sg:phone":"+1 580 924 5551",
    "sg:postcode":"74701",
    "sg:province":"OK",
    "sg:tags":[
        "station",
        "gasoline"
    ],
    "wof:name":"Texaco",
    "wof:placetype":"venue"
},
  "geometry": {"coordinates":[-96.375366,33.993739],"type":"Point"}
}