{
  "type": "Feature",
  "properties": {
    "addr:full":"123 W Commerce St Altus OK 73521",
    "addr:housenumber":"123",
    "addr:postcode":"73521",
    "addr:street":"W Commerce St",
    "iso:country":"US",
    "sg:address":"123 W Commerce St",
    "sg:city":"Altus",
    "sg:classifiers":[
        {
            "category":"Banks & Credit Unions",
            "subcategory":"Bank",
            "type":"Services"
        }
    ],
    "sg:phone":"+1 580 477 1100",
    "sg:postcode":"73521",
    "sg:province":"OK",
    "sg:website":"www.nbcok.com",
    "wof:name":"NBC Bank",
    "wof:placetype":"venue"
},
  "geometry": {"coordinates":[-99.33502,34.638967],"type":"Point"}
}