{
  "type": "Feature",
  "properties": {
    "addr:full":"7603 S Sheridan Rd Tulsa OK 74133",
    "addr:housenumber":"7603",
    "addr:postcode":"74133",
    "addr:street":"S Sheridan Rd",
    "iso:country":"US",
    "sg:address":"7603 S Sheridan Rd",
    "sg:city":"Tulsa",
    "sg:classifiers":[
        {
            "category":"Personal",
            "subcategory":"Beauty Salon",
            "type":"Services"
        }
    ],
    "sg:phone":"+1 918 492 5678",
    "sg:postcode":"74133",
    "sg:province":"OK",
    "sg:tags":[
        "shop"
    ],
    "wof:name":"Vi's Beauty Shop",
    "wof:placetype":"venue"
},
  "geometry": {"coordinates":[-95.90425500000001,36.051311],"type":"Point"}
}