{
  "type": "Feature",
  "properties": {
    "iso:country":"US",
    "sg:address":"626 Tinker Ave",
    "sg:city":"Pawhuska",
    "sg:classifiers":[
        {
            "category":"Building & Trades",
            "subcategory":"Construction",
            "type":"Services"
        }
    ],
    "sg:phone":"+1 918 287 2216",
    "sg:postcode":"74056",
    "sg:province":"OK",
    "sg:tags":[
        "contractor"
    ],
    "wof:name":"Bond Welding",
    "wof:placetype":"venue"
},
  "geometry": {"coordinates":[-96.345295,36.666531],"type":"Point"}
}