{
  "type": "Feature",
  "properties": {
    "addr:full":"119 N Walnut St Edmond OK 73003",
    "addr:housenumber":"119",
    "addr:postcode":"73003",
    "addr:street":"N Walnut St",
    "iso:country":"US",
    "sg:address":"119 N Walnut St",
    "sg:city":"Edmond",
    "sg:classifiers":[
        {
            "category":"Banks & Credit Unions",
            "subcategory":"Investment Brokerage",
            "type":"Services"
        }
    ],
    "sg:phone":"+1 405 330 6833",
    "sg:postcode":"73003",
    "sg:province":"OK",
    "sg:tags":[
        "advisory"
    ],
    "wof:name":"D & A Leasing",
    "wof:placetype":"venue"
},
  "geometry": {"coordinates":[-97.488603,35.657086],"type":"Point"}
}