{
  "type": "Feature",
  "properties": {
    "iso:country":"US",
    "sg:address":"136 N Falcon Dr",
    "sg:city":"Oklahoma City",
    "sg:classifiers":[
        {
            "category":"Wholesale",
            "subcategory":"Plants",
            "type":"Manufacturing & Wholesale Goods"
        }
    ],
    "sg:phone":"+1 405 495 9115",
    "sg:postcode":"73127",
    "sg:province":"OK",
    "sg:tags":[
        "flower",
        "artificial"
    ],
    "wof:name":"T & B Mfg",
    "wof:placetype":"venue"
},
  "geometry": {"coordinates":[-97.660832,35.465309],"type":"Point"}
}