{
  "type": "Feature",
  "properties": {
    "iso:country":"US",
    "sg:address":"700 Asp Ave",
    "sg:city":"Norman",
    "sg:classifiers":[
        {
            "category":"Health Services",
            "subcategory":"Doctor",
            "type":"Services"
        }
    ],
    "sg:phone":"+1 405 329 4141",
    "sg:postcode":"73069",
    "sg:province":"OK",
    "wof:name":"H Grant Ritchey DDS",
    "wof:placetype":"venue"
},
  "geometry": {"coordinates":[-97.44369500000001,35.212982],"type":"Point"}
}