{
  "type": "Feature",
  "properties": {
    "addr:full":"8509 N Rockwell Ave Oklahoma City OK 73132",
    "addr:housenumber":"8509",
    "addr:postcode":"73132",
    "addr:street":"N Rockwell Ave",
    "iso:country":"US",
    "sg:address":"8509 N Rockwell Ave",
    "sg:city":"Oklahoma City",
    "sg:classifiers":[
        {
            "category":"Education",
            "subcategory":"Special Training",
            "type":"Public Place"
        }
    ],
    "sg:phone":"+1 405 720 6284",
    "sg:postcode":"73132",
    "sg:province":"OK",
    "sg:tags":[
        "tutoring"
    ],
    "wof:name":"Kumon Math & Reading Ctr",
    "wof:placetype":"venue"
},
  "geometry": {"coordinates":[-97.63847699999999,35.55545],"type":"Point"}
}