{
  "type": "Feature",
  "properties": {
    "iso:country":"US",
    "sg:address":"105 48th St",
    "sg:city":"Woodward",
    "sg:classifiers":[
        {
            "category":"Mining & Drilling",
            "type":"Manufacturing & Wholesale Goods"
        }
    ],
    "sg:phone":"+1 580 254 3036",
    "sg:postcode":"73801",
    "sg:province":"OK",
    "sg:tags":[
        "field",
        "oil"
    ],
    "wof:name":"Case Wireline Svc Inc",
    "wof:placetype":"venue"
},
  "geometry": {"coordinates":[-99.44365999999999,36.447899],"type":"Point"}
}