{
  "type": "Feature",
  "properties": {
    "iso:country":"US",
    "sg:address":"126 W Jackson St",
    "sg:city":"Hugo",
    "sg:classifiers":[
        {
            "category":"Shopping",
            "subcategory":"Beauty & Cosmetics",
            "type":"Retail Goods"
        }
    ],
    "sg:phone":"+1 580 326 3633",
    "sg:postcode":"74743",
    "sg:province":"OK",
    "sg:tags":[
        "merchandise"
    ],
    "wof:name":"Merle Norman Cosmetics",
    "wof:placetype":"venue"
},
  "geometry": {"coordinates":[-95.513763,34.010986],"type":"Point"}
}