{
  "type": "Feature",
  "properties": {
    "iso:country":"US",
    "sg:address":"2308 E Broadway St",
    "sg:city":"Altus",
    "sg:classifiers":[
        {
            "category":"Recreation",
            "type":"Entertainment"
        },
        {
            "category":"Organizations",
            "subcategory":"Community Association",
            "type":"Services"
        }
    ],
    "sg:phone":"+1 580 477 2373",
    "sg:postcode":"73521",
    "sg:province":"OK",
    "sg:tags":[
        "club",
        "membership"
    ],
    "wof:name":"Trader Tom's Tavern",
    "wof:placetype":"venue"
},
  "geometry": {"coordinates":[-99.30317599999999,34.637635],"type":"Point"}
}