{
  "type": "Feature",
  "properties": {
    "iso:country":"US",
    "sg:address":"300 S Ranchwood Blvd",
    "sg:city":"Yukon",
    "sg:classifiers":[
        {
            "category":"Professional",
            "subcategory":"Business Services",
            "type":"Services"
        },
        {
            "category":"Manufacturing",
            "subcategory":"Apparel",
            "type":"Manufacturing & Wholesale Goods"
        }
    ],
    "sg:phone":"+1 405 350 0126",
    "sg:postcode":"73099",
    "sg:province":"OK",
    "sg:tags":[
        "embroidery"
    ],
    "wof:name":"Stitch Designs",
    "wof:placetype":"venue"
},
  "geometry": {"coordinates":[-97.737718,35.506067],"type":"Point"}
}