{
  "type": "Feature",
  "properties": {
    "addr:full":"56 S Western Ave Oklahoma City OK 73106",
    "addr:housenumber":"56",
    "addr:postcode":"73106",
    "addr:street":"S Western Ave",
    "iso:country":"US",
    "sg:address":"56 S Western Ave",
    "sg:city":"Oklahoma City",
    "sg:classifiers":[
        {
            "category":"Restaurant",
            "type":"Food & Drink"
        }
    ],
    "sg:phone":"+1 405 635 0909",
    "sg:postcode":"73106",
    "sg:province":"OK",
    "wof:name":"Cardena's Restaurant",
    "wof:placetype":"venue"
},
  "geometry": {"coordinates":[-97.530041,35.46602],"type":"Point"}
}