{
  "type": "Feature",
  "properties": {
    "iso:country":"US",
    "sg:address":"22146 W 877 Rd",
    "sg:city":"Cookson",
    "sg:classifiers":[
        {
            "category":"Manufacturing",
            "subcategory":"Tools & Machinery",
            "type":"Manufacturing & Wholesale Goods"
        }
    ],
    "sg:phone":"+1 918 457 5457",
    "sg:postcode":"74427",
    "sg:province":"OK",
    "sg:tags":[
        "shop",
        "job"
    ],
    "wof:name":"Ziese Products Inc",
    "wof:placetype":"venue"
},
  "geometry": {"coordinates":[-94.910526,35.744505],"type":"Point"}
}