{
  "type": "Feature",
  "properties": {
    "iso:country":"US",
    "sg:address":"103 N Central Ave",
    "sg:city":"Idabel",
    "sg:classifiers":[
        {
            "category":"Professional",
            "subcategory":"Lawyer & Legal Services",
            "type":"Services"
        }
    ],
    "sg:phone":"+1 580 286 7472",
    "sg:postcode":"74745",
    "sg:province":"OK",
    "sg:tags":[
        "attorney"
    ],
    "wof:name":"Haley Law Office",
    "wof:placetype":"venue"
},
  "geometry": {"coordinates":[-94.828542,33.895879],"type":"Point"}
}