{
  "type": "Feature",
  "properties": {
    "iso:country":"US",
    "sg:address":"719 Sunny Brook Dr",
    "sg:city":"Edmond",
    "sg:classifiers":[
        {
            "category":"Professional",
            "subcategory":"Management & Consulting",
            "type":"Services"
        }
    ],
    "sg:phone":"+1 405 341 7125",
    "sg:postcode":"73034",
    "sg:province":"OK",
    "sg:tags":[
        "consultant",
        "business"
    ],
    "wof:name":"Bates Consulting Inc",
    "wof:placetype":"venue"
},
  "geometry": {"coordinates":[-97.471262,35.675191],"type":"Point"}
}