{
  "type": "Feature",
  "properties": {
    "iso:country":"US",
    "sg:address":"1716 N County Line Rd E",
    "sg:city":"Fort Gibson",
    "sg:classifiers":[
        {
            "category":"Shopping",
            "subcategory":"Bicycles & Sporting Goods",
            "type":"Retail Goods"
        }
    ],
    "sg:phone":"+1 918 478 3225",
    "sg:postcode":"74434",
    "sg:province":"OK",
    "sg:tags":[
        "bait",
        "fishing"
    ],
    "wof:name":"Grand River Bait & Tackle",
    "wof:placetype":"venue"
},
  "geometry": {"coordinates":[-95.127224,35.807277],"type":"Point"}
}