{
  "type": "Feature",
  "properties": {
    "iso:country":"US",
    "sg:address":"3965 State Hwy 97",
    "sg:city":"Sand Springs",
    "sg:classifiers":[
        {
            "category":"Banks & Credit Unions",
            "subcategory":"Investment Brokerage",
            "type":"Services"
        }
    ],
    "sg:phone":"+1 918 245 4280",
    "sg:postcode":"74063",
    "sg:province":"OK",
    "sg:tags":[
        "stock",
        "bond"
    ],
    "wof:name":"Edward Jones Co",
    "wof:placetype":"venue"
},
  "geometry": {"coordinates":[-96.11706599999999,36.106066],"type":"Point"}
}