{
  "type": "Feature",
  "properties": {
    "iso:country":"US",
    "sg:address":"6291 Wooster St",
    "sg:city":"Norman",
    "sg:classifiers":[
        {
            "category":"Manufacturing",
            "subcategory":"Metals",
            "type":"Manufacturing & Wholesale Goods"
        }
    ],
    "sg:phone":"+1 405 364 9489",
    "sg:postcode":"73071",
    "sg:province":"OK",
    "sg:tags":[
        "tower"
    ],
    "wof:name":"Top Hand Tower Co",
    "wof:placetype":"venue"
},
  "geometry": {"coordinates":[-97.418072,35.293724],"type":"Point"}
}