{
  "type": "Feature",
  "properties": {
    "iso:country":"US",
    "sg:address":"18409 S 27th West Ave",
    "sg:city":"Mounds",
    "sg:classifiers":[
        {
            "category":"Building & Trades",
            "subcategory":"Construction",
            "type":"Services"
        }
    ],
    "sg:phone":"+1 918 827 5214",
    "sg:postcode":"74047",
    "sg:province":"OK",
    "sg:tags":[
        "house"
    ],
    "wof:name":"Saam Construction",
    "wof:placetype":"venue"
},
  "geometry": {"coordinates":[-96.024474,35.89978],"type":"Point"}
}