{
  "type": "Feature",
  "properties": {
    "iso:country":"US",
    "sg:address":"400 W Foley St",
    "sg:city":"Eufaula",
    "sg:classifiers":[
        {
            "category":"Education",
            "subcategory":"School",
            "type":"Public Place"
        }
    ],
    "sg:phone":"+1 918 689 9010",
    "sg:postcode":"74432",
    "sg:province":"OK",
    "wof:name":"Joyful Day Preschool",
    "wof:placetype":"venue"
},
  "geometry": {"coordinates":[-95.587561,35.286722],"type":"Point"}
}