{
  "type": "Feature",
  "properties": {
    "iso:country":"US",
    "sg:address":"6828 Melrose Ln",
    "sg:city":"Oklahoma City",
    "sg:classifiers":[
        {
            "category":"Manufacturing",
            "subcategory":"Furniture",
            "type":"Manufacturing & Wholesale Goods"
        }
    ],
    "sg:phone":"+1 405 787 1212",
    "sg:postcode":"73127",
    "sg:province":"OK",
    "sg:tags":[
        "mfg"
    ],
    "wof:name":"Leggett & Platt Incorporated",
    "wof:placetype":"venue"
},
  "geometry": {"coordinates":[-97.634159,35.471533],"type":"Point"}
}