{
  "type": "Feature",
  "properties": {
    "iso:country":"US",
    "sg:address":"8125 N Classen Blvd",
    "sg:city":"Oklahoma City",
    "sg:classifiers":[
        {
            "category":"Professional",
            "subcategory":"Business Services",
            "type":"Services"
        }
    ],
    "sg:phone":"+1 405 810 9733",
    "sg:postcode":"73114",
    "sg:province":"OK",
    "sg:tags":[
        "recording",
        "studio"
    ],
    "wof:name":"Systems Records",
    "wof:placetype":"venue"
},
  "geometry": {"coordinates":[-97.527225,35.55251],"type":"Point"}
}