{
  "type": "Feature",
  "properties": {
    "iso:country":"US",
    "sg:address":"9726 E 42nd St",
    "sg:city":"Tulsa",
    "sg:classifiers":[
        {
            "category":"Health Services",
            "subcategory":"Doctor",
            "type":"Services"
        },
        {
            "category":"Health Services",
            "subcategory":"Health Practitioner",
            "type":"Services"
        }
    ],
    "sg:phone":"+1 918 664 4483",
    "sg:postcode":"74146",
    "sg:province":"OK",
    "sg:tags":[
        "control",
        "physician",
        "management",
        "weight",
        "loss",
        "dietitian",
        "surgeons",
        "nutritionist"
    ],
    "sg:website":"http://www.lifedesignnutrition.com",
    "wof:name":"Life Design Nutrition",
    "wof:placetype":"venue"
},
  "geometry": {"coordinates":[-95.867651,36.102341],"type":"Point"}
}