{
  "type": "Feature",
  "properties": {
    "iso:country":"US",
    "sg:address":"3300 E Noble Dr",
    "sg:city":"Edmond",
    "sg:classifiers":[
        {
            "category":"Building & Trades",
            "subcategory":"Construction",
            "type":"Services"
        }
    ],
    "sg:phone":"+1 405 388 5157",
    "sg:postcode":"73034",
    "sg:province":"OK",
    "sg:tags":[
        "house"
    ],
    "wof:name":"Morgan Vinci LLC",
    "wof:placetype":"venue"
},
  "geometry": {"coordinates":[-97.43546499999999,35.735051],"type":"Point"}
}