{
  "type": "Feature",
  "properties": {
    "iso:country":"US",
    "sg:address":"2830 US Hwy 81",
    "sg:city":"El Reno",
    "sg:classifiers":[
        {
            "category":"Autos & Motor Vehicles",
            "subcategory":"Automobile Sales",
            "type":"Retail Goods"
        }
    ],
    "sg:phone":"+1 405 262 2466",
    "sg:postcode":"73036",
    "sg:province":"OK",
    "sg:tags":[
        "car",
        "dealer"
    ],
    "sg:website":"www.rickjonesautos.com",
    "wof:name":"Rick Jones Pontiac Buick GMC",
    "wof:placetype":"venue"
},
  "geometry": {"coordinates":[-97.937136,35.507274],"type":"Point"}
}