{
  "type": "Feature",
  "properties": {
    "iso:country":"US",
    "sg:address":"3408 Jim Robison Dr",
    "sg:city":"Edmond",
    "sg:classifiers":[
        {
            "category":"Manufacturing",
            "subcategory":"Building Materials",
            "type":"Manufacturing & Wholesale Goods"
        }
    ],
    "sg:phone":"+1 405 216 9975",
    "sg:postcode":"73013",
    "sg:province":"OK",
    "sg:tags":[
        "mfg",
        "wood",
        "kitchen",
        "cabinet"
    ],
    "wof:name":"Kellys Kabinets",
    "wof:placetype":"venue"
},
  "geometry": {"coordinates":[-97.466819,35.622079],"type":"Point"}
}