{
  "type": "Feature",
  "properties": {
    "iso:country":"US",
    "sg:address":"1137 S Aspen Ave",
    "sg:city":"Broken Arrow",
    "sg:classifiers":[
        {
            "category":"Recreation",
            "type":"Entertainment"
        }
    ],
    "sg:phone":"+1 918 695 8885",
    "sg:postcode":"74012",
    "sg:province":"OK",
    "sg:tags":[
        "martial",
        "arts",
        "instruction"
    ],
    "sg:website":"www.apollos.com",
    "wof:name":"Apollo's Martial Arts Ctr",
    "wof:placetype":"venue"
},
  "geometry": {"coordinates":[-95.81527699999999,36.040425],"type":"Point"}
}