{
  "type": "Feature",
  "properties": {
    "iso:country":"US",
    "sg:address":"11313 Broadway Exn",
    "sg:city":"Oklahoma City",
    "sg:classifiers":[
        {
            "category":"Professional",
            "type":"Services"
        }
    ],
    "sg:phone":"+1 405 753 9644",
    "sg:postcode":"73114",
    "sg:province":"OK",
    "sg:tags":[
        "establishment"
    ],
    "wof:name":"Atkinson Colonel G",
    "wof:placetype":"venue"
},
  "geometry": {"coordinates":[-97.51180100000001,35.588673],"type":"Point"}
}