{
  "type": "Feature",
  "properties": {
    "iso:country":"US",
    "sg:address":"1114 E Lincoln Ave",
    "sg:city":"Sapulpa",
    "sg:classifiers":[
        {
            "category":"Retail",
            "subcategory":"Repair Shop",
            "type":"Services"
        }
    ],
    "sg:phone":"+1 918 224 2183",
    "sg:postcode":"74066",
    "sg:province":"OK",
    "wof:name":"Clairmont Repair Co",
    "wof:placetype":"venue"
},
  "geometry": {"coordinates":[-96.098434,35.995628],"type":"Point"}
}