{
  "type": "Feature",
  "properties": {
    "addr:full":"13720 N Bryant Ave Edmond OK 73013",
    "addr:housenumber":"13720",
    "addr:postcode":"73013",
    "addr:street":"N Bryant Ave",
    "iso:country":"US",
    "sg:address":"13720 N Bryant Ave",
    "sg:city":"Edmond",
    "sg:classifiers":[
        {
            "category":"Professional",
            "type":"Services"
        }
    ],
    "sg:phone":"+1 405 478 4173",
    "sg:postcode":"73013",
    "sg:province":"OK",
    "sg:tags":[
        "establishment"
    ],
    "wof:name":"Aneet International",
    "wof:placetype":"venue"
},
  "geometry": {"coordinates":[-97.460336,35.611643],"type":"Point"}
}