{
  "type": "Feature",
  "properties": {
    "iso:country":"US",
    "sg:address":"1708 Topeka St",
    "sg:city":"Norman",
    "sg:classifiers":[
        {
            "category":"Wholesale",
            "subcategory":"Machinery & Supplies",
            "type":"Manufacturing & Wholesale Goods"
        }
    ],
    "sg:phone":"+1 405 364 1950",
    "sg:postcode":"73069",
    "sg:province":"OK",
    "sg:tags":[
        "field",
        "oil",
        "equipment"
    ],
    "wof:name":"Arvine Pipe & Supply Co Inc",
    "wof:placetype":"venue"
},
  "geometry": {"coordinates":[-97.469523,35.256633],"type":"Point"}
}