{
  "type": "Feature",
  "properties": {
    "addr:full":"1105 Moonshine Ct Noble OK 73068",
    "addr:housenumber":"1105",
    "addr:postcode":"73068",
    "addr:street":"Moonshine Ct",
    "iso:country":"US",
    "sg:address":"1105 Moonshine Ct",
    "sg:city":"Noble",
    "sg:classifiers":[
        {
            "category":"Building & Trades",
            "subcategory":"Landscaping Services",
            "type":"Services"
        }
    ],
    "sg:phone":"+1 405 872 5185",
    "sg:postcode":"73068",
    "sg:province":"OK",
    "sg:tags":[
        "landscape",
        "contractor"
    ],
    "wof:name":"Pro-Mow Lawn Care",
    "wof:placetype":"venue"
},
  "geometry": {"coordinates":[-97.3841,35.149822],"type":"Point"}
}