{
  "type": "Feature",
  "properties": {
    "iso:country":"US",
    "sg:address":"720 Oklahoma Blvd",
    "sg:city":"Alva",
    "sg:classifiers":[
        {
            "category":"Shopping",
            "subcategory":"Florist",
            "type":"Retail Goods"
        }
    ],
    "sg:phone":"+1 580 327 2618",
    "sg:postcode":"73717",
    "sg:province":"OK",
    "wof:name":"Tuxhorn's Flowers & Gifts",
    "wof:placetype":"venue"
},
  "geometry": {"coordinates":[-98.668885,36.797759],"type":"Point"}
}