{
  "type": "Feature",
  "properties": {
    "addr:full":"811 S Elm Pl Broken Arrow OK 74012",
    "addr:housenumber":"811",
    "addr:postcode":"74012",
    "addr:street":"S Elm Pl",
    "iso:country":"US",
    "sg:address":"811 S Elm Pl",
    "sg:city":"Broken Arrow",
    "sg:classifiers":[
        {
            "category":"Autos & Motor Vehicles",
            "subcategory":"Auto Supplies",
            "type":"Retail Goods"
        }
    ],
    "sg:phone":"+1 918 258 4330",
    "sg:postcode":"74012",
    "sg:province":"OK",
    "sg:tags":[
        "automobile",
        "parts"
    ],
    "sg:website":"www.autozone.com",
    "wof:name":"Autozone",
    "wof:placetype":"venue"
},
  "geometry": {"coordinates":[-95.797371,36.044613],"type":"Point"}
}