{
  "type": "Feature",
  "properties": {
    "iso:country":"US",
    "sg:address":"521 E Broadway St",
    "sg:city":"Drumright",
    "sg:classifiers":[
        {
            "category":"Organizations",
            "subcategory":"Religious Organization",
            "type":"Services"
        }
    ],
    "sg:phone":"+1 918 352 2735",
    "sg:postcode":"74030",
    "sg:province":"OK",
    "wof:name":"Church of God of Apstlic Faith",
    "wof:placetype":"venue"
},
  "geometry": {"coordinates":[-96.594373,35.988521],"type":"Point"}
}