{
  "type": "Feature",
  "properties": {
    "iso:country":"US",
    "sg:address":"10101 N May Ave",
    "sg:city":"Oklahoma City",
    "sg:classifiers":[
        {
            "category":"Shopping",
            "subcategory":"Bicycles & Sporting Goods",
            "type":"Retail Goods"
        }
    ],
    "sg:phone":"+1 405 755 1954",
    "sg:postcode":"73120",
    "sg:province":"OK",
    "wof:name":"International Golf Discount",
    "wof:placetype":"venue"
},
  "geometry": {"coordinates":[-97.567258,35.57364],"type":"Point"}
}