{
  "type": "Feature",
  "properties": {
    "iso:country":"US",
    "sg:address":"4433 SE 28th St",
    "sg:city":"Oklahoma City",
    "sg:classifiers":[
        {
            "category":"Professional",
            "subcategory":"Business Services",
            "type":"Services"
        }
    ],
    "sg:phone":"+1 405 619 7009",
    "sg:postcode":"73115",
    "sg:province":"OK",
    "wof:name":"Copy Service",
    "wof:placetype":"venue"
},
  "geometry": {"coordinates":[-97.438853,35.436336],"type":"Point"}
}