{
  "type": "Feature",
  "properties": {
    "addr:full":"10012 E 47th St Tulsa OK 74146",
    "addr:housenumber":"10012",
    "addr:postcode":"74146",
    "addr:street":"E 47Th St",
    "iso:country":"US",
    "sg:address":"10012 E 47th St",
    "sg:city":"Tulsa",
    "sg:classifiers":[
        {
            "category":"Manufacturing",
            "subcategory":"Tools & Machinery",
            "type":"Manufacturing & Wholesale Goods"
        }
    ],
    "sg:phone":"+1 918 663 7601",
    "sg:postcode":"74146",
    "sg:province":"OK",
    "sg:tags":[
        "equipment",
        "infrared"
    ],
    "wof:name":"I R Rents",
    "wof:placetype":"venue"
},
  "geometry": {"coordinates":[-95.86395899999999,36.095708],"type":"Point"}
}