{
  "type": "Feature",
  "properties": {
    "iso:country":"US",
    "sg:address":"2715 E Waterloo Rd",
    "sg:city":"Edmond",
    "sg:classifiers":[
        {
            "category":"Food & Beverages",
            "subcategory":"Groceries & Convenience Stores",
            "type":"Retail Goods"
        }
    ],
    "sg:phone":"+1 405 340 3721",
    "sg:postcode":"73034",
    "sg:province":"OK",
    "sg:tags":[
        "eating"
    ],
    "wof:name":"Waterloo Corner Store",
    "wof:placetype":"venue"
},
  "geometry": {"coordinates":[-97.391694,35.72528],"type":"Point"}
}