{
  "type": "Feature",
  "properties": {
    "iso:country":"US",
    "sg:address":"13262 S 49th West Ave",
    "sg:city":"Sapulpa",
    "sg:classifiers":[
        {
            "category":"Building & Trades",
            "subcategory":"Plumbing",
            "type":"Services"
        }
    ],
    "sg:phone":"+1 918 321 5106",
    "sg:postcode":"74066",
    "sg:province":"OK",
    "sg:tags":[
        "contractor"
    ],
    "wof:name":"Air Kiefer",
    "wof:placetype":"venue"
},
  "geometry": {"coordinates":[-96.04909,35.970635],"type":"Point"}
}