{
  "type": "Feature",
  "properties": {
    "addr:full":"12864 Council Ave Lindsay OK 73052",
    "addr:housenumber":"12864",
    "addr:postcode":"73052",
    "addr:street":"Council Ave",
    "iso:country":"US",
    "sg:address":"12864 Council Ave",
    "sg:city":"Lindsay",
    "sg:classifiers":[
        {
            "category":"Freight",
            "type":"Transportation"
        }
    ],
    "sg:phone":"+1 405 756 2713",
    "sg:postcode":"73052",
    "sg:province":"OK",
    "sg:tags":[
        "operator",
        "local",
        "trucking"
    ],
    "wof:name":"Rocking O Trucking",
    "wof:placetype":"venue"
},
  "geometry": {"coordinates":[-97.652974,34.896263],"type":"Point"}
}