{
  "type": "Feature",
  "properties": {
    "iso:country":"US",
    "sg:address":"4701 NW 10th St",
    "sg:city":"Oklahoma City",
    "sg:classifiers":[
        {
            "category":"Wholesale",
            "subcategory":"Hardware",
            "type":"Manufacturing & Wholesale Goods"
        }
    ],
    "sg:phone":"+1 405 947 6695",
    "sg:postcode":"73127",
    "sg:province":"OK",
    "sg:tags":[
        "fastener"
    ],
    "sg:website":"www.am-supply.com",
    "wof:name":"A M Supply",
    "wof:placetype":"venue"
},
  "geometry": {"coordinates":[-97.60790299999999,35.478778],"type":"Point"}
}