{
  "type": "Feature",
  "properties": {
    "addr:full":"121 NE 40th St Oklahoma City OK 73105",
    "addr:housenumber":"121",
    "addr:postcode":"73105",
    "addr:street":"Ne 40Th St",
    "iso:country":"US",
    "sg:address":"121 NE 40th St",
    "sg:city":"Oklahoma City",
    "sg:classifiers":[
        {
            "category":"Wholesale",
            "subcategory":"Chemicals & Plastics",
            "type":"Manufacturing & Wholesale Goods"
        }
    ],
    "sg:phone":"+1 405 525 2426",
    "sg:postcode":"73105",
    "sg:province":"OK",
    "sg:tags":[
        "concrete",
        "additive"
    ],
    "sg:website":"www.thestampstore.com",
    "wof:name":"Stamp Store",
    "wof:placetype":"venue"
},
  "geometry": {"coordinates":[-97.508169,35.512871],"type":"Point"}
}