{
  "type": "Feature",
  "properties": {
    "iso:country":"US",
    "sg:address":"8013 NW 23rd St",
    "sg:city":"Bethany",
    "sg:classifiers":[
        {
            "category":"Personal",
            "subcategory":"Barber",
            "type":"Services"
        }
    ],
    "sg:phone":"+1 405 789 0341",
    "sg:postcode":"73008",
    "sg:province":"OK",
    "wof:name":"Oak Center Barber Shop",
    "wof:placetype":"venue"
},
  "geometry": {"coordinates":[-97.656547,35.493349],"type":"Point"}
}