{
  "type": "Feature",
  "properties": {
    "iso:country":"US",
    "sg:address":"3225 S Norwood Ave",
    "sg:city":"Tulsa",
    "sg:classifiers":[
        {
            "category":"Banks & Credit Unions",
            "subcategory":"Investment Brokerage",
            "type":"Services"
        }
    ],
    "sg:phone":"+1 918 747 3331",
    "sg:postcode":"74135",
    "sg:province":"OK",
    "sg:tags":[
        "advisory",
        "financial"
    ],
    "wof:name":"All Fund Financial Svc",
    "wof:placetype":"venue"
},
  "geometry": {"coordinates":[-95.906448,36.117012],"type":"Point"}
}