{
  "type": "Feature",
  "properties": {
    "iso:country":"US",
    "sg:address":"2431 E 61st St",
    "sg:city":"Tulsa",
    "sg:classifiers":[
        {
            "category":"Insurance",
            "subcategory":"Insurance Agent",
            "type":"Services"
        }
    ],
    "sg:phone":"+1 918 581 8819",
    "sg:postcode":"74136",
    "sg:province":"OK",
    "wof:name":"New York Life",
    "wof:placetype":"venue"
},
  "geometry": {"coordinates":[-95.95686499999999,36.075359],"type":"Point"}
}