{
  "type": "Feature",
  "properties": {
    "addr:full":"211 S Choctaw Ave Okmulgee OK 74447",
    "addr:housenumber":"211",
    "addr:postcode":"74447",
    "addr:street":"S Choctaw Ave",
    "iso:country":"US",
    "sg:address":"211 S Choctaw Ave",
    "sg:city":"Okmulgee",
    "sg:classifiers":[
        {
            "category":"Manufacturing",
            "subcategory":"Printing",
            "type":"Manufacturing & Wholesale Goods"
        }
    ],
    "sg:phone":"+1 918 756 6360",
    "sg:postcode":"74447",
    "sg:province":"OK",
    "sg:tags":[
        "publisher",
        "software"
    ],
    "wof:name":"Hacker Environmental Corp",
    "wof:placetype":"venue"
},
  "geometry": {"coordinates":[-95.961697,35.622271],"type":"Point"}
}