{
  "type": "Feature",
  "properties": {
    "iso:country":"US",
    "sg:address":"104 S Cedar St",
    "sg:city":"Luther",
    "sg:classifiers":[
        {
            "category":"Organizations",
            "subcategory":"Religious Organization",
            "type":"Services"
        }
    ],
    "sg:phone":"+1 405 277 3282",
    "sg:postcode":"73054",
    "sg:province":"OK",
    "sg:tags":[
        "church"
    ],
    "wof:name":"First Baptist Church",
    "wof:placetype":"venue"
},
  "geometry": {"coordinates":[-97.19218100000001,35.661335],"type":"Point"}
}