{
  "type": "Feature",
  "properties": {
    "iso:country":"US",
    "sg:address":"501 E 10th St",
    "sg:city":"Ada",
    "sg:classifiers":[
        {
            "category":"Professional",
            "subcategory":"Accounting & Tax Preparation",
            "type":"Services"
        }
    ],
    "sg:phone":"+1 580 436 3676",
    "sg:postcode":"74820",
    "sg:province":"OK",
    "sg:tags":[
        "accountant"
    ],
    "wof:name":"Jackie R Whomble Inc",
    "wof:placetype":"venue"
},
  "geometry": {"coordinates":[-96.672198,34.775581],"type":"Point"}
}