{
  "type": "Feature",
  "properties": {
    "addr:full":"802 N 5th St Sayre OK 73662",
    "addr:housenumber":"802",
    "addr:postcode":"73662",
    "addr:street":"N 5Th St",
    "iso:country":"US",
    "sg:address":"802 N 5th St",
    "sg:city":"Sayre",
    "sg:classifiers":[
        {
            "category":"Autos & Motor Vehicles",
            "subcategory":"Auto Supplies",
            "type":"Retail Goods"
        }
    ],
    "sg:phone":"+1 580 928 2051",
    "sg:postcode":"73662",
    "sg:province":"OK",
    "wof:name":"Coast To Coast",
    "wof:placetype":"venue"
},
  "geometry": {"coordinates":[-99.64134300000001,35.300107],"type":"Point"}
}