{
  "type": "Feature",
  "properties": {
    "iso:country":"US",
    "sg:address":"521 N Central Ave",
    "sg:city":"Okmulgee",
    "sg:classifiers":[
        {
            "category":"Organizations",
            "subcategory":"Religious Organization",
            "type":"Services"
        }
    ],
    "sg:phone":"+1 918 756 0578",
    "sg:postcode":"74447",
    "sg:province":"OK",
    "sg:tags":[
        "church"
    ],
    "wof:name":"First Baptist Church N Central",
    "wof:placetype":"venue"
},
  "geometry": {"coordinates":[-95.97036,35.627808],"type":"Point"}
}