{
  "type": "Feature",
  "properties": {
    "addr:full":"6465 S Yale Ave Tulsa OK 74136",
    "addr:housenumber":"6465",
    "addr:postcode":"74136",
    "addr:street":"S Yale Ave",
    "iso:country":"US",
    "sg:address":"6465 S Yale Ave",
    "sg:city":"Tulsa",
    "sg:classifiers":[
        {
            "category":"Health Services",
            "subcategory":"Doctor",
            "type":"Services"
        }
    ],
    "sg:phone":"+1 918 481 4880",
    "sg:postcode":"74136",
    "sg:province":"OK",
    "sg:tags":[
        "physician",
        "surgeon",
        "medical"
    ],
    "wof:name":"Franz Moncada Inc",
    "wof:placetype":"venue"
},
  "geometry": {"coordinates":[-95.92204599999999,36.06908],"type":"Point"}
}