{
  "type": "Feature",
  "properties": {
    "iso:country":"US",
    "sg:address":"510 E Virginia Ave",
    "sg:city":"Anadarko",
    "sg:classifiers":[
        {
            "category":"Social Services",
            "subcategory":"Adult Care",
            "type":"Services"
        }
    ],
    "sg:phone":"+1 405 247 6727",
    "sg:postcode":"73005",
    "sg:province":"OK",
    "sg:tags":[
        "retardation",
        "home",
        "dev",
        "disabled"
    ],
    "wof:name":"Neil J Dikeman Group Home",
    "wof:placetype":"venue"
},
  "geometry": {"coordinates":[-98.235609,35.070354],"type":"Point"}
}