{
  "type": "Feature",
  "properties": {
    "iso:country":"US",
    "sg:address":"3707 US Hwy 81",
    "sg:city":"Duncan",
    "sg:classifiers":[
        {
            "category":"Home & Garden",
            "subcategory":"Building Materials",
            "type":"Retail Goods"
        }
    ],
    "sg:phone":"+1 580 252 4222",
    "sg:postcode":"73533",
    "sg:province":"OK",
    "sg:website":"www.mccoys.com",
    "wof:name":"Mc Coy's Building Supply Ctr",
    "wof:placetype":"venue"
},
  "geometry": {"coordinates":[-97.96669900000001,34.545617],"type":"Point"}
}