{
  "type": "Feature",
  "properties": {
    "iso:country":"US",
    "sg:address":"1215 Crossroads Blvd",
    "sg:city":"Norman",
    "sg:classifiers":[
        {
            "category":"Professional",
            "subcategory":"Computer Services",
            "type":"Services"
        }
    ],
    "sg:phone":"+1 405 307 8145",
    "sg:postcode":"73072",
    "sg:province":"OK",
    "sg:tags":[
        "credit",
        "card"
    ],
    "wof:name":"Merchants Choice LLC",
    "wof:placetype":"venue"
},
  "geometry": {"coordinates":[-97.48916800000001,35.233286],"type":"Point"}
}