{
  "type": "Feature",
  "properties": {
    "addr:full":"11012 E 74th St Ripley OK 74062",
    "addr:housenumber":"11012",
    "addr:postcode":"74062",
    "addr:street":"E 74Th St",
    "iso:country":"US",
    "sg:address":"11012 E 74th St",
    "sg:city":"Ripley",
    "sg:classifiers":[
        {
            "category":"Freight",
            "type":"Transportation"
        }
    ],
    "sg:phone":"+1 918 372 4262",
    "sg:postcode":"74062",
    "sg:province":"OK",
    "sg:tags":[
        "mobile",
        "home"
    ],
    "wof:name":"CER Mobile Home Enterprises",
    "wof:placetype":"venue"
},
  "geometry": {"coordinates":[-96.907011,36.036918],"type":"Point"}
}