{
  "type": "Feature",
  "properties": {
    "iso:country":"US",
    "sg:address":"1545 SW 29th St",
    "sg:city":"Oklahoma City",
    "sg:classifiers":[
        {
            "category":"Wholesale",
            "subcategory":"Motor Vehicles",
            "type":"Manufacturing & Wholesale Goods"
        }
    ],
    "sg:phone":"+1 405 631 0510",
    "sg:postcode":"73119",
    "sg:province":"OK",
    "wof:name":"Carnero Auto Sales",
    "wof:placetype":"venue"
},
  "geometry": {"coordinates":[-97.54485200000001,35.435287],"type":"Point"}
}