{
  "type": "Feature",
  "properties": {
    "addr:full":"1700 N Main St Altus OK 73521",
    "addr:housenumber":"1700",
    "addr:postcode":"73521",
    "addr:street":"N Main St",
    "iso:country":"US",
    "sg:address":"1700 N Main St",
    "sg:city":"Altus",
    "sg:classifiers":[
        {
            "category":"Wholesale",
            "subcategory":"Electrical",
            "type":"Manufacturing & Wholesale Goods"
        }
    ],
    "sg:phone":"+1 580 482 9358",
    "sg:postcode":"73521",
    "sg:province":"OK",
    "sg:tags":[
        "fixture",
        "lighting",
        "electronic"
    ],
    "wof:name":"Locke Wholesale Electric Supl",
    "wof:placetype":"venue"
},
  "geometry": {"coordinates":[-99.33394199999999,34.656127],"type":"Point"}
}