{
  "type": "Feature",
  "properties": {
    "iso:country":"US",
    "sg:address":"101 E Choctaw Ave",
    "sg:city":"Bache",
    "sg:classifiers":[
        {
            "category":"Social Services",
            "subcategory":"Job Training",
            "type":"Services"
        }
    ],
    "sg:phone":"+1 918 429 4227",
    "sg:postcode":"74501",
    "sg:province":"OK",
    "sg:tags":[
        "organization",
        "religious"
    ],
    "wof:name":"Life Church Inc",
    "wof:placetype":"venue"
},
  "geometry": {"coordinates":[-95.768637,34.931968],"type":"Point"}
}