{
  "type": "Feature",
  "properties": {
    "addr:full":"11605 E 31st St Tulsa OK 74146",
    "addr:housenumber":"11605",
    "addr:postcode":"74146",
    "addr:street":"E 31St St",
    "iso:country":"US",
    "sg:address":"11605 E 31st St",
    "sg:city":"Tulsa",
    "sg:classifiers":[
        {
            "category":"Building & Trades",
            "subcategory":"Locksmith",
            "type":"Services"
        }
    ],
    "sg:phone":"+1 918 948 7063",
    "sg:postcode":"74146",
    "sg:province":"OK",
    "sg:tags":[
        "key"
    ],
    "wof:name":"Aalways Available Locksmith",
    "wof:placetype":"venue"
},
  "geometry": {"coordinates":[-95.847419,36.119107],"type":"Point"}
}