{
  "type": "Feature",
  "properties": {
    "addr:full":"300 Black Jack Fort Gibson OK 74434",
    "addr:housenumber":"300",
    "addr:postcode":"74434",
    "addr:street":"Black Jack",
    "iso:country":"US",
    "sg:address":"300 Black Jack",
    "sg:city":"Fort Gibson",
    "sg:classifiers":[
        {
            "category":"Organizations",
            "subcategory":"Religious Organization",
            "type":"Services"
        }
    ],
    "sg:phone":"+1 918 478 3811",
    "sg:postcode":"74434",
    "sg:province":"OK",
    "sg:tags":[
        "church"
    ],
    "wof:name":"First United Methodist Church",
    "wof:placetype":"venue"
},
  "geometry": {"coordinates":[-95.24975499999999,35.801226],"type":"Point"}
}