{
  "type": "Feature",
  "properties": {
    "addr:full":"410 NE 6th St Stigler OK 74462",
    "addr:housenumber":"410",
    "addr:postcode":"74462",
    "addr:street":"Ne 6Th St",
    "iso:country":"US",
    "sg:address":"410 NE 6th St",
    "sg:city":"Stigler",
    "sg:classifiers":[
        {
            "category":"Recreation",
            "type":"Entertainment"
        }
    ],
    "sg:phone":"+1 918 967 2626",
    "sg:postcode":"74462",
    "sg:province":"OK",
    "sg:tags":[
        "pool",
        "swimming"
    ],
    "wof:name":"Stigler City Pool",
    "wof:placetype":"venue"
},
  "geometry": {"coordinates":[-95.118262,35.256372],"type":"Point"}
}