{
  "type": "Feature",
  "properties": {
    "iso:country":"US",
    "sg:address":"2109 NW 62nd St",
    "sg:city":"Oklahoma City",
    "sg:classifiers":[
        {
            "category":"Building & Trades",
            "subcategory":"Landscaping Services",
            "type":"Services"
        }
    ],
    "sg:phone":"+1 405 843 6425",
    "sg:postcode":"73112",
    "sg:province":"OK",
    "sg:tags":[
        "retail",
        "tree",
        "transplant"
    ],
    "wof:name":"Big Tree Transplanting Inc",
    "wof:placetype":"venue"
},
  "geometry": {"coordinates":[-97.549088,35.535953],"type":"Point"}
}