{
  "type": "Feature",
  "properties": {
    "iso:country":"US",
    "sg:address":"1315 E Taft Ave",
    "sg:city":"Sapulpa",
    "sg:classifiers":[
        {
            "category":"Banks & Credit Unions",
            "subcategory":"Bank",
            "type":"Services"
        }
    ],
    "sg:phone":"+1 918 227 3000",
    "sg:postcode":"74066",
    "sg:province":"OK",
    "wof:name":"Spirit Bank",
    "wof:placetype":"venue"
},
  "geometry": {"coordinates":[-96.096725,35.988471],"type":"Point"}
}