{
  "type": "Feature",
  "properties": {
    "iso:country":"US",
    "sg:address":"5312 State Hwy 37",
    "sg:city":"Tuttle",
    "sg:classifiers":[
        {
            "category":"Wholesale",
            "subcategory":"Machinery & Supplies",
            "type":"Manufacturing & Wholesale Goods"
        },
        {
            "category":"Home & Garden",
            "subcategory":"Garden Supply",
            "type":"Retail Goods"
        }
    ],
    "sg:phone":"+1 405 381 2555",
    "sg:postcode":"73089",
    "sg:province":"OK",
    "sg:tags":[
        "farm",
        "equipment"
    ],
    "wof:name":"Mc Carthey Farm Equipment",
    "wof:placetype":"venue"
},
  "geometry": {"coordinates":[-97.71693,35.290872],"type":"Point"}
}