{
  "type": "Feature",
  "properties": {
    "iso:country":"US",
    "sg:address":"1003 Annakay Dr",
    "sg:city":"Chandler",
    "sg:classifiers":[
        {
            "category":"Professional",
            "subcategory":"Business Services",
            "type":"Services"
        }
    ],
    "sg:phone":"+1 405 258 5616",
    "sg:postcode":"74834",
    "sg:province":"OK",
    "wof:name":"Imperial Enterprises Inc",
    "wof:placetype":"venue"
},
  "geometry": {"coordinates":[-96.868306,35.711073],"type":"Point"}
}