{
  "type": "Feature",
  "properties": {
    "addr:full":"3305 Sheridan Rd Bartlesville OK 74006",
    "addr:housenumber":"3305",
    "addr:postcode":"74006",
    "addr:street":"Sheridan Rd",
    "iso:country":"US",
    "sg:address":"3305 Sheridan Rd",
    "sg:city":"Bartlesville",
    "sg:classifiers":[
        {
            "category":"Building & Trades",
            "subcategory":"Construction",
            "type":"Services"
        }
    ],
    "sg:phone":"+1 918 914 3443",
    "sg:postcode":"74006",
    "sg:province":"OK",
    "sg:tags":[
        "painting",
        "business"
    ],
    "wof:name":"Custom Home Maintenance",
    "wof:placetype":"venue"
},
  "geometry": {"coordinates":[-95.940687,36.729038],"type":"Point"}
}