{
  "type": "Feature",
  "properties": {
    "iso:country":"US",
    "sg:address":"1107 E Moman Ave",
    "sg:city":"Sapulpa",
    "sg:classifiers":[
        {
            "category":"Retail",
            "subcategory":"Auto Repair",
            "type":"Services"
        }
    ],
    "sg:phone":"+1 918 224 3726",
    "sg:postcode":"74066",
    "sg:province":"OK",
    "sg:tags":[
        "automotive"
    ],
    "wof:name":"Toms Algnmt & Total Car Repr",
    "wof:placetype":"venue"
},
  "geometry": {"coordinates":[-96.098801,36.009382],"type":"Point"}
}