{
  "type": "Feature",
  "properties": {
    "addr:full":"4130 Arlington St Ada OK 74820",
    "addr:housenumber":"4130",
    "addr:postcode":"74820",
    "addr:street":"Arlington St",
    "iso:country":"US",
    "sg:address":"4130 Arlington St",
    "sg:city":"Ada",
    "sg:classifiers":[
        {
            "category":"Food & Beverages",
            "subcategory":"Groceries & Convenience Stores",
            "type":"Retail Goods"
        }
    ],
    "sg:phone":"+1 580 332 2522",
    "sg:postcode":"74820",
    "sg:province":"OK",
    "wof:name":"Homer Stop-N-Go",
    "wof:placetype":"venue"
},
  "geometry": {"coordinates":[-96.618853,34.781613],"type":"Point"}
}