{
  "type": "Feature",
  "properties": {
    "iso:country":"US",
    "sg:address":"320 S Boston Ave",
    "sg:city":"Tulsa",
    "sg:classifiers":[
        {
            "category":"Banks & Credit Unions",
            "subcategory":"Bank",
            "type":"Services"
        }
    ],
    "sg:phone":"+1 918 588 6435",
    "sg:postcode":"74103",
    "sg:province":"OK",
    "wof:name":"Bank Of Oklahoma",
    "wof:placetype":"venue"
},
  "geometry": {"coordinates":[-95.989625,36.152967],"type":"Point"}
}