{
  "type": "Feature",
  "properties": {
    "addr:full":"10313 Oxlow Rd Oklahoma City OK 73159",
    "addr:housenumber":"10313",
    "addr:postcode":"73159",
    "addr:street":"Oxlow Rd",
    "iso:country":"US",
    "sg:address":"10313 Oxlow Rd",
    "sg:city":"Oklahoma City",
    "sg:classifiers":[
        {
            "category":"Professional",
            "subcategory":"Management & Consulting",
            "type":"Services"
        }
    ],
    "sg:phone":"+1 405 691 5529",
    "sg:postcode":"73159",
    "sg:province":"OK",
    "sg:tags":[
        "building",
        "environmental"
    ],
    "wof:name":"American Building & Envmtl S",
    "wof:placetype":"venue"
},
  "geometry": {"coordinates":[-97.543088,35.365391],"type":"Point"}
}