{
  "type": "Feature",
  "properties": {
    "iso:country":"US",
    "sg:address":"211 N Robinson Ave",
    "sg:city":"Oklahoma City",
    "sg:classifiers":[
        {
            "category":"Arena",
            "subcategory":"Sports Club",
            "type":"Entertainment"
        }
    ],
    "sg:phone":"+1 405 236 5000",
    "sg:postcode":"73102",
    "sg:province":"OK",
    "sg:tags":[
        "manager",
        "recruiter",
        "promoter"
    ],
    "sg:website":"www.okcallsports.org",
    "wof:name":"Oklahoma City All Sports Assn",
    "wof:placetype":"venue"
},
  "geometry": {"coordinates":[-97.51647699999999,35.469091],"type":"Point"}
}