{
  "type": "Feature",
  "properties": {
    "addr:full":"6807 E Reno Ave Midwest City OK 73110",
    "addr:housenumber":"6807",
    "addr:postcode":"73110",
    "addr:street":"E Reno Ave",
    "iso:country":"US",
    "sg:address":"6807 E Reno Ave",
    "sg:city":"Midwest City",
    "sg:classifiers":[
        {
            "category":"Shopping",
            "type":"Retail Goods"
        }
    ],
    "sg:phone":"+1 405 732 5602",
    "sg:postcode":"73110",
    "sg:province":"OK",
    "sg:tags":[
        "telephone",
        "cellular"
    ],
    "wof:name":"Millennium Wireless Inc",
    "wof:placetype":"venue"
},
  "geometry": {"coordinates":[-97.40893800000001,35.464123],"type":"Point"}
}