{
  "type": "Feature",
  "properties": {
    "addr:full":"103 S Willow St Pauls Valley OK 73075",
    "addr:housenumber":"103",
    "addr:postcode":"73075",
    "addr:street":"S Willow St",
    "iso:country":"US",
    "sg:address":"103 S Willow St",
    "sg:city":"Pauls Valley",
    "sg:classifiers":[
        {
            "category":"Professional",
            "type":"Services"
        }
    ],
    "sg:phone":"+1 405 238 5375",
    "sg:postcode":"73075",
    "sg:province":"OK",
    "sg:tags":[
        "establishment"
    ],
    "wof:name":"Wacker Ewert Interests LLC",
    "wof:placetype":"venue"
},
  "geometry": {"coordinates":[-97.22074600000001,34.739919],"type":"Point"}
}