{
  "type": "Feature",
  "properties": {
    "iso:country":"US",
    "sg:address":"15800 Napa Ridge",
    "sg:city":"Edmond",
    "sg:phone":"+1 405 340 6060",
    "sg:postcode":"73013",
    "sg:province":"OK",
    "sg:tags":[
        "farm",
        "wheat"
    ],
    "wof:name":"Edna L Hodges",
    "wof:placetype":"venue"
},
  "geometry": {"coordinates":[-97.54770499999999,35.632062],"type":"Point"}
}