{
  "type": "Feature",
  "properties": {
    "iso:country":"US",
    "sg:address":"1901 NW Expy",
    "sg:city":"Oklahoma City",
    "sg:classifiers":[
        {
            "category":"Shopping",
            "subcategory":"Jewelry",
            "type":"Retail Goods"
        }
    ],
    "sg:phone":"+1 405 848 4653",
    "sg:postcode":"73118",
    "sg:province":"OK",
    "sg:tags":[
        "jeweler"
    ],
    "wof:name":"Treasures",
    "wof:placetype":"venue"
},
  "geometry": {"coordinates":[-97.54491,35.52257],"type":"Point"}
}