{
  "type": "Feature",
  "properties": {
    "addr:full":"4800 NW 39th St Oklahoma City OK 73122",
    "addr:housenumber":"4800",
    "addr:postcode":"73122",
    "addr:street":"Nw 39Th St",
    "iso:country":"US",
    "sg:address":"4800 NW 39th St",
    "sg:city":"Oklahoma City",
    "sg:classifiers":[
        {
            "category":"Autos & Motor Vehicles",
            "subcategory":"Automobile Sales",
            "type":"Retail Goods"
        }
    ],
    "sg:phone":"+1 405 495 4700",
    "sg:postcode":"73122",
    "sg:province":"OK",
    "sg:tags":[
        "car",
        "dealer"
    ],
    "sg:website":"www.automaxok.com",
    "wof:name":"Automax Nissan",
    "wof:placetype":"venue"
},
  "geometry": {"coordinates":[-97.606448,35.511138],"type":"Point"}
}