{
  "type": "Feature",
  "properties": {
    "iso:country":"US",
    "sg:address":"5810 N Pennsylvania Ave",
    "sg:city":"Oklahoma City",
    "sg:classifiers":[
        {
            "category":"Professional",
            "subcategory":"Business Services",
            "type":"Services"
        }
    ],
    "sg:phone":"+1 405 755 3929",
    "sg:postcode":"73112",
    "sg:province":"OK",
    "wof:name":"Internatnl Insur Reinsur Cnsu",
    "wof:placetype":"venue"
},
  "geometry": {"coordinates":[-97.547291,35.529444],"type":"Point"}
}