{
  "type": "Feature",
  "properties": {
    "iso:country":"US",
    "sg:address":"102 S 109th East Pl",
    "sg:city":"Tulsa",
    "sg:classifiers":[
        {
            "category":"Professional",
            "subcategory":"Testing Lab",
            "type":"Services"
        }
    ],
    "sg:phone":"+1 918 592 6560",
    "sg:postcode":"74128",
    "sg:province":"OK",
    "sg:tags":[
        "inspection",
        "infrared"
    ],
    "wof:name":"Industrial Electric & Testing",
    "wof:placetype":"venue"
},
  "geometry": {"coordinates":[-95.85491500000001,36.157883],"type":"Point"}
}