{
  "type": "Feature",
  "properties": {
    "addr:full":"1430 N Evanston Pl Tulsa OK 74110",
    "addr:housenumber":"1430",
    "addr:postcode":"74110",
    "addr:street":"N;Pl",
    "iso:country":"US",
    "sg:address":"1430 N Evanston Pl",
    "sg:city":"Tulsa",
    "sg:classifiers":[
        {
            "category":"Real Estate",
            "subcategory":"Real Estate Agent",
            "type":"Services"
        }
    ],
    "sg:phone":"+1 918 836 8930",
    "sg:postcode":"74110",
    "sg:province":"OK",
    "wof:name":"N & N Real Estate Investors",
    "wof:placetype":"venue"
},
  "geometry": {"coordinates":[-95.946541,36.176575],"type":"Point"}
}