{
  "type": "Feature",
  "properties": {
    "iso:country":"US",
    "sg:address":"1224 S Main St",
    "sg:city":"Mcalester",
    "sg:classifiers":[
        {
            "category":"Wholesale",
            "subcategory":"Electrical",
            "type":"Manufacturing & Wholesale Goods"
        }
    ],
    "sg:phone":"+1 918 426 0972",
    "sg:postcode":"74501",
    "sg:province":"OK",
    "sg:tags":[
        "communication",
        "radio",
        "system"
    ],
    "wof:name":"State Wide Communications",
    "wof:placetype":"venue"
},
  "geometry": {"coordinates":[-95.769587,34.931584],"type":"Point"}
}