{
  "type": "Feature",
  "properties": {
    "addr:full":"8223 E 118th St S Bixby OK 74008",
    "addr:housenumber":"8223",
    "addr:postcode":"74008",
    "addr:street":"E 118Th St S",
    "iso:country":"US",
    "sg:address":"8223 E 118th St S",
    "sg:city":"Bixby",
    "sg:classifiers":[
        {
            "category":"Building & Trades",
            "subcategory":"Landscaping Services",
            "type":"Services"
        }
    ],
    "sg:phone":"+1 918 369 5835",
    "sg:postcode":"74008",
    "sg:province":"OK",
    "sg:tags":[
        "lawn",
        "maintenance",
        "grounds"
    ],
    "wof:name":"Lawn Care & Lot Cleaning",
    "wof:placetype":"venue"
},
  "geometry": {"coordinates":[-95.884725,35.992541],"type":"Point"}
}