{
  "type": "Feature",
  "properties": {
    "addr:full":"1802 E 3rd Ave Stillwater OK 74074",
    "addr:housenumber":"1802",
    "addr:postcode":"74074",
    "addr:street":"E 3Rd Ave",
    "iso:country":"US",
    "sg:address":"1802 E 3rd Ave",
    "sg:city":"Stillwater",
    "sg:classifiers":[
        {
            "category":"Farming",
            "subcategory":"Livestock Farm",
            "type":"Manufacturing & Wholesale Goods"
        }
    ],
    "sg:phone":"+1 405 377 7206",
    "sg:postcode":"74074",
    "sg:province":"OK",
    "sg:tags":[
        "feedlot",
        "grain",
        "cash",
        "beef",
        "cattle"
    ],
    "wof:name":"Kastl Farms",
    "wof:placetype":"venue"
},
  "geometry": {"coordinates":[-97.036891,36.119661],"type":"Point"}
}