{
  "type": "Feature",
  "properties": {
    "iso:country":"US",
    "sg:address":"4222 N Harrison Ave",
    "sg:city":"Shawnee",
    "sg:classifiers":[
        {
            "category":"Building & Trades",
            "subcategory":"Construction",
            "type":"Services"
        }
    ],
    "sg:phone":"+1 405 273 1415",
    "sg:postcode":"74804",
    "sg:province":"OK",
    "sg:tags":[
        "home",
        "builder"
    ],
    "wof:name":"Apex Homes",
    "wof:placetype":"venue"
},
  "geometry": {"coordinates":[-96.91213500000001,35.374013],"type":"Point"}
}