{
  "type": "Feature",
  "properties": {
    "addr:full":"6028 S Western Ave Oklahoma City OK 73139",
    "addr:housenumber":"6028",
    "addr:postcode":"73139",
    "addr:street":"S Western Ave",
    "iso:country":"US",
    "sg:address":"6028 S Western Ave",
    "sg:city":"Oklahoma City",
    "sg:classifiers":[
        {
            "category":"Shopping",
            "type":"Retail Goods"
        }
    ],
    "sg:phone":"+1 405 632 0513",
    "sg:postcode":"73139",
    "sg:province":"OK",
    "sg:tags":[
        "telephone",
        "cellular"
    ],
    "wof:name":"Radio Shack",
    "wof:placetype":"venue"
},
  "geometry": {"coordinates":[-97.530107,35.40553],"type":"Point"}
}