{
  "type": "Feature",
  "properties": {
    "addr:full":"119 N 2nd St Noble OK 73068",
    "addr:housenumber":"119",
    "addr:postcode":"73068",
    "addr:street":"N 2Nd St",
    "iso:country":"US",
    "sg:address":"119 N 2nd St",
    "sg:city":"Noble",
    "sg:classifiers":[
        {
            "category":"Government",
            "subcategory":"Fire Station",
            "type":"Public Place"
        }
    ],
    "sg:phone":"+1 405 872 3030",
    "sg:postcode":"73068",
    "sg:province":"OK",
    "sg:tags":[
        "department"
    ],
    "wof:name":"Noble City Fire Dept",
    "wof:placetype":"venue"
},
  "geometry": {"coordinates":[-97.395923,35.140438],"type":"Point"}
}