{
  "type": "Feature",
  "properties": {
    "addr:full":"6402 E Pine St Tulsa OK 74115",
    "addr:housenumber":"6402",
    "addr:postcode":"74115",
    "addr:street":"E Pine St",
    "iso:country":"US",
    "sg:address":"6402 E Pine St",
    "sg:city":"Tulsa",
    "sg:classifiers":[
        {
            "category":"Wholesale",
            "subcategory":"Furniture",
            "type":"Manufacturing & Wholesale Goods"
        }
    ],
    "sg:phone":"+1 918 582 5959",
    "sg:postcode":"74115",
    "sg:province":"OK",
    "wof:name":"Stow's Office Furniture",
    "wof:placetype":"venue"
},
  "geometry": {"coordinates":[-95.905047,36.177019],"type":"Point"}
}