{
  "type": "Feature",
  "properties": {
    "iso:country":"US",
    "sg:address":"1414 S Sangre Rd",
    "sg:city":"Stillwater",
    "sg:classifiers":[
        {
            "category":"Professional",
            "type":"Services"
        }
    ],
    "sg:phone":"+1 405 743 3062",
    "sg:postcode":"74074",
    "sg:province":"OK",
    "wof:name":"DVP Media",
    "wof:placetype":"venue"
},
  "geometry": {"coordinates":[-97.105082,36.10673],"type":"Point"}
}