{
  "type": "Feature",
  "properties": {
    "addr:full":"1405 N Main St Miami OK 74354",
    "addr:housenumber":"1405",
    "addr:postcode":"74354",
    "addr:street":"N Main St",
    "iso:country":"US",
    "sg:address":"1405 N Main St",
    "sg:city":"Miami",
    "sg:classifiers":[
        {
            "category":"Banks & Credit Unions",
            "subcategory":"Bank",
            "type":"Services"
        }
    ],
    "sg:phone":"+1 918 540 2414",
    "sg:postcode":"74354",
    "sg:province":"OK",
    "sg:tags":[
        "federal",
        "savings",
        "institution"
    ],
    "wof:name":"Arvest Bank",
    "wof:placetype":"venue"
},
  "geometry": {"coordinates":[-94.877605,36.89227],"type":"Point"}
}