{
  "type": "Feature",
  "properties": {
    "addr:full":"17330 168th St Lexington OK 73051",
    "addr:housenumber":"17330",
    "addr:postcode":"73051",
    "addr:street":"168Th St",
    "iso:country":"US",
    "sg:address":"17330 168th St",
    "sg:city":"Lexington",
    "sg:classifiers":[
        {
            "category":"Farming",
            "subcategory":"Farm & Veterinary Services",
            "type":"Manufacturing & Wholesale Goods"
        }
    ],
    "sg:phone":"+1 405 527 1513",
    "sg:postcode":"73051",
    "sg:province":"OK",
    "sg:tags":[
        "livestock"
    ],
    "wof:name":"Mc Whirter John L B",
    "wof:placetype":"venue"
},
  "geometry": {"coordinates":[-97.19494400000001,35.010437],"type":"Point"}
}