{
  "type": "Feature",
  "properties": {
    "addr:full":"5705 NW 58th St Oklahoma City OK 73122",
    "addr:housenumber":"5705",
    "addr:postcode":"73122",
    "addr:street":"Nw 58Th St",
    "iso:country":"US",
    "sg:address":"5705 NW 58th St",
    "sg:city":"Oklahoma City",
    "sg:classifiers":[
        {
            "category":"Building & Trades",
            "subcategory":"Construction",
            "type":"Services"
        }
    ],
    "sg:phone":"+1 405 721 5748",
    "sg:postcode":"73122",
    "sg:province":"OK",
    "sg:tags":[
        "hanging",
        "home",
        "paper",
        "painting",
        "improvement"
    ],
    "wof:name":"Hooks H Jack Painting",
    "wof:placetype":"venue"
},
  "geometry": {"coordinates":[-97.617553,35.529649],"type":"Point"}
}