{
  "type": "Feature",
  "properties": {
    "addr:full":"1405 W Baton Rouge Cir Broken Arrow OK 74011",
    "addr:housenumber":"1405",
    "addr:postcode":"74011",
    "addr:street":"W Baton Rouge Cir",
    "iso:country":"US",
    "sg:address":"1405 W Baton Rouge Cir",
    "sg:city":"Broken Arrow",
    "sg:classifiers":[
        {
            "category":"Professional",
            "subcategory":"Computer Services",
            "type":"Services"
        }
    ],
    "sg:phone":"+1 918 451 2967",
    "sg:postcode":"74011",
    "sg:province":"OK",
    "sg:tags":[
        "internet"
    ],
    "sg:website":"www.padirtkart.com",
    "wof:name":"Bob's 4 Cycle Karting",
    "wof:placetype":"venue"
},
  "geometry": {"coordinates":[-95.806865,35.983536],"type":"Point"}
}