{
  "type": "Feature",
  "properties": {
    "addr:full":"1001 N Porter Ave Okmulgee OK 74447",
    "addr:housenumber":"1001",
    "addr:postcode":"74447",
    "addr:street":"N Porter Ave",
    "iso:country":"US",
    "sg:address":"1001 N Porter Ave",
    "sg:city":"Okmulgee",
    "sg:classifiers":[
        {
            "category":"Professional",
            "type":"Services"
        }
    ],
    "sg:phone":"+1 918 756 8466",
    "sg:postcode":"74447",
    "sg:province":"OK",
    "sg:tags":[
        "establishment"
    ],
    "wof:name":"URS Inc",
    "wof:placetype":"venue"
},
  "geometry": {"coordinates":[-95.969132,35.632872],"type":"Point"}
}