{
  "type": "Feature",
  "properties": {
    "iso:country":"US",
    "sg:address":"5151 E 51st St S",
    "sg:city":"Tulsa",
    "sg:classifiers":[
        {
            "category":"Health Services",
            "subcategory":"Doctor",
            "type":"Services"
        }
    ],
    "sg:phone":"+1 918 663 4666",
    "sg:postcode":"74135",
    "sg:province":"OK",
    "sg:tags":[
        "dentist"
    ],
    "wof:name":"Tulsa Dental Implant Center PC",
    "wof:placetype":"venue"
},
  "geometry": {"coordinates":[-95.918229,36.089951],"type":"Point"}
}