{
  "type": "Feature",
  "properties": {
    "iso:country":"US",
    "sg:address":"312 SE 45th St",
    "sg:city":"Lawton",
    "sg:classifiers":[
        {
            "category":"Government",
            "subcategory":"Fire Station",
            "type":"Public Place"
        }
    ],
    "sg:phone":"+1 580 581 3296",
    "sg:postcode":"73501",
    "sg:province":"OK",
    "sg:tags":[
        "department"
    ],
    "wof:name":"Lawton Fire Dept #6",
    "wof:placetype":"venue"
},
  "geometry": {"coordinates":[-98.33467899999999,34.605105],"type":"Point"}
}