{
  "type": "Feature",
  "properties": {
    "addr:full":"2800 Purdue Ave Oklahoma City OK 73128",
    "addr:housenumber":"2800",
    "addr:postcode":"73128",
    "addr:street":"Purdue Ave",
    "iso:country":"US",
    "sg:address":"2800 Purdue Ave",
    "sg:city":"Oklahoma City",
    "sg:classifiers":[
        {
            "category":"Manufacturing",
            "subcategory":"Tools & Machinery",
            "type":"Manufacturing & Wholesale Goods"
        }
    ],
    "sg:phone":"+1 405 680 0100",
    "sg:postcode":"73128",
    "sg:province":"OK",
    "sg:tags":[
        "electronic",
        "assembly"
    ],
    "wof:name":"Maverick Technologies LLC",
    "wof:placetype":"venue"
},
  "geometry": {"coordinates":[-97.613086,35.437601],"type":"Point"}
}