{
  "type": "Feature",
  "properties": {
    "iso:country":"US",
    "sg:address":"921 E 11th St",
    "sg:city":"Edmond",
    "sg:classifiers":[
        {
            "category":"Building & Trades",
            "subcategory":"Equipment Rental",
            "type":"Services"
        }
    ],
    "sg:phone":"+1 405 359 8823",
    "sg:postcode":"73034",
    "sg:province":"OK",
    "wof:name":"D & L Leasing LLC",
    "wof:placetype":"venue"
},
  "geometry": {"coordinates":[-97.46608,35.642839],"type":"Point"}
}