{
  "type": "Feature",
  "properties": {
    "iso:country":"US",
    "sg:address":"309 Norman Center Ct",
    "sg:city":"Norman",
    "sg:classifiers":[
        {
            "category":"Travel",
            "subcategory":"Hotels & Motels",
            "type":"Entertainment"
        }
    ],
    "sg:phone":"+1 405 366 2100",
    "sg:postcode":"73072",
    "sg:province":"OK",
    "sg:tags":[
        "operation"
    ],
    "sg:website":"www.hamptoninn.com",
    "wof:name":"Hampton Inn",
    "wof:placetype":"venue"
},
  "geometry": {"coordinates":[-97.489339,35.215069],"type":"Point"}
}