{
  "type": "Feature",
  "properties": {
    "addr:full":"1301 N York St Muskogee OK 74403",
    "addr:housenumber":"1301",
    "addr:postcode":"74403",
    "addr:street":"N York St",
    "iso:country":"US",
    "sg:address":"1301 N York St",
    "sg:city":"Muskogee",
    "sg:classifiers":[
        {
            "category":"Retail",
            "subcategory":"Animal Services",
            "type":"Services"
        }
    ],
    "sg:phone":"+1 918 683 9354",
    "sg:postcode":"74403",
    "sg:province":"OK",
    "wof:name":"Pet Parlor",
    "wof:placetype":"venue"
},
  "geometry": {"coordinates":[-95.340442,35.758778],"type":"Point"}
}