{
  "type": "Feature",
  "properties": {
    "iso:country":"US",
    "sg:address":"112 Vine St",
    "sg:city":"Chelsea",
    "sg:classifiers":[
        {
            "category":"Retail",
            "subcategory":"Auto Repair",
            "type":"Services"
        }
    ],
    "sg:phone":"+1 918 789 3218",
    "sg:postcode":"74016",
    "sg:province":"OK",
    "sg:tags":[
        "general"
    ],
    "wof:name":"T&R Auto Repair",
    "wof:placetype":"venue"
},
  "geometry": {"coordinates":[-95.431344,36.540823],"type":"Point"}
}