{
  "type": "Feature",
  "properties": {
    "iso:country":"US",
    "sg:address":"117 N Rennie Ave",
    "sg:city":"Shawnee",
    "sg:classifiers":[
        {
            "category":"Real Estate",
            "subcategory":"Real Estate Operator",
            "type":"Services"
        }
    ],
    "sg:phone":"+1 405 275 1034",
    "sg:postcode":"74820",
    "sg:province":"OK",
    "sg:tags":[
        "building",
        "nonresidential"
    ],
    "wof:name":"Winsett Properties LLC",
    "wof:placetype":"venue"
},
  "geometry": {"coordinates":[-96.677069,34.774684],"type":"Point"}
}