{
  "type": "Feature",
  "properties": {
    "iso:country":"US",
    "sg:address":"102 S East St",
    "sg:city":"Guymon",
    "sg:classifiers":[
        {
            "category":"Mining & Drilling",
            "type":"Manufacturing & Wholesale Goods"
        }
    ],
    "sg:phone":"+1 580 338 3830",
    "sg:postcode":"73942",
    "sg:province":"OK",
    "sg:tags":[
        "mud",
        "oil",
        "well",
        "additive"
    ],
    "wof:name":"Winter Mud Co",
    "wof:placetype":"venue"
},
  "geometry": {"coordinates":[-101.474742,36.677917],"type":"Point"}
}