{
  "type": "Feature",
  "properties": {
    "addr:full":"3620 E 40th St Tulsa OK 74135",
    "addr:housenumber":"3620",
    "addr:postcode":"74135",
    "addr:street":"E 40Th St",
    "iso:country":"US",
    "sg:address":"3620 E 40th St",
    "sg:city":"Tulsa",
    "sg:classifiers":[
        {
            "category":"Shopping",
            "type":"Retail Goods"
        }
    ],
    "sg:phone":"+1 918 749 7228",
    "sg:postcode":"74135",
    "sg:province":"OK",
    "sg:tags":[
        "picture",
        "frame",
        "merchandise"
    ],
    "wof:name":"I'Ve Been Framed",
    "wof:placetype":"venue"
},
  "geometry": {"coordinates":[-95.935971,36.105542],"type":"Point"}
}