{
  "type": "Feature",
  "properties": {
    "iso:country":"US",
    "sg:address":"1302 W Bois D Arc Ave",
    "sg:city":"Duncan",
    "sg:classifiers":[
        {
            "category":"Food & Beverages",
            "subcategory":"Specialty",
            "type":"Retail Goods"
        }
    ],
    "sg:phone":"+1 580 252 9699",
    "sg:postcode":"73533",
    "sg:province":"OK",
    "sg:tags":[
        "health",
        "diet"
    ],
    "wof:name":"Natures Health Food Ctr",
    "wof:placetype":"venue"
},
  "geometry": {"coordinates":[-97.966406,34.492555],"type":"Point"}
}