{
  "type": "Feature",
  "properties": {
    "iso:country":"US",
    "sg:address":"201 E Watova St",
    "sg:city":"Talala",
    "sg:classifiers":[
        {
            "category":"Building & Trades",
            "subcategory":"Construction",
            "type":"Services"
        }
    ],
    "sg:phone":"+1 918 275 4307",
    "sg:postcode":"74080",
    "sg:province":"OK",
    "sg:tags":[
        "concrete",
        "contractor"
    ],
    "wof:name":"Henderson Concrete Co",
    "wof:placetype":"venue"
},
  "geometry": {"coordinates":[-95.698775,36.530799],"type":"Point"}
}