{
  "type": "Feature",
  "properties": {
    "iso:country":"US",
    "sg:address":"204 E Highland St",
    "sg:city":"Shawnee",
    "sg:classifiers":[
        {
            "category":"Insurance",
            "subcategory":"Hazard Insurance",
            "type":"Services"
        }
    ],
    "sg:phone":"+1 405 275 3130",
    "sg:postcode":"74801",
    "sg:province":"OK",
    "sg:tags":[
        "bond"
    ],
    "wof:name":"First Advantage Bail Bonds",
    "wof:placetype":"venue"
},
  "geometry": {"coordinates":[-96.921002,35.332805],"type":"Point"}
}