{
  "type": "Feature",
  "properties": {
    "addr:full":"207 N Main St Sand Springs OK 74063",
    "addr:housenumber":"207",
    "addr:postcode":"74063",
    "addr:street":"N Main St",
    "iso:country":"US",
    "sg:address":"207 N Main St",
    "sg:city":"Sand Springs",
    "sg:classifiers":[
        {
            "category":"Professional",
            "subcategory":"Lawyer & Legal Services",
            "type":"Services"
        }
    ],
    "sg:phone":"+1 918 245 2022",
    "sg:postcode":"74063",
    "sg:province":"OK",
    "sg:tags":[
        "attorney"
    ],
    "wof:name":"Erwin D Phillips",
    "wof:placetype":"venue"
},
  "geometry": {"coordinates":[-96.110136,36.138507],"type":"Point"}
}