{
  "type": "Feature",
  "properties": {
    "iso:country":"US",
    "sg:address":"12602 E 31st St",
    "sg:city":"Tulsa",
    "sg:classifiers":[
        {
            "category":"Food & Beverages",
            "subcategory":"Groceries & Convenience Stores",
            "type":"Retail Goods"
        }
    ],
    "sg:phone":"+1 918 610 0866",
    "sg:postcode":"74146",
    "sg:province":"OK",
    "sg:website":"p66conoco76.conocophillips.com",
    "wof:name":"Phillips 66 Food Plaza",
    "wof:placetype":"venue"
},
  "geometry": {"coordinates":[-95.837097,36.1189],"type":"Point"}
}