{
  "type": "Feature",
  "properties": {
    "iso:country":"US",
    "sg:address":"708 W Main St",
    "sg:city":"Duncan",
    "sg:classifiers":[
        {
            "category":"Home & Garden",
            "subcategory":"Furniture",
            "type":"Retail Goods"
        }
    ],
    "sg:phone":"+1 580 255 7477",
    "sg:postcode":"73533",
    "sg:province":"OK",
    "wof:name":"Henderson Furniture Co",
    "wof:placetype":"venue"
},
  "geometry": {"coordinates":[-97.956657,34.501706],"type":"Point"}
}