{
  "type": "Feature",
  "properties": {
    "iso:country":"US",
    "sg:address":"8300 NE 36th St",
    "sg:city":"Spencer",
    "sg:classifiers":[
        {
            "category":"Government",
            "subcategory":"Police Station",
            "type":"Public Place"
        }
    ],
    "sg:phone":"+1 405 771 3798",
    "sg:postcode":"73084",
    "sg:province":"OK",
    "sg:tags":[
        "department"
    ],
    "wof:name":"Spencer Police Dept",
    "wof:placetype":"venue"
},
  "geometry": {"coordinates":[-97.382643,35.507623],"type":"Point"}
}