{
  "type": "Feature",
  "properties": {
    "addr:full":"213 Main St Ringwood OK 73768",
    "addr:housenumber":"213",
    "addr:postcode":"73768",
    "addr:street":"Main St",
    "iso:country":"US",
    "sg:address":"213 Main St",
    "sg:city":"Ringwood",
    "sg:classifiers":[
        {
            "category":"Building & Trades",
            "subcategory":"Plumbing",
            "type":"Services"
        }
    ],
    "sg:phone":"+1 580 883 4966",
    "sg:postcode":"73768",
    "sg:province":"OK",
    "sg:tags":[
        "conditioning",
        "air",
        "system",
        "contractor"
    ],
    "wof:name":"Craig Shockley Co",
    "wof:placetype":"venue"
},
  "geometry": {"coordinates":[-98.245897,36.376115],"type":"Point"}
}