{
  "type": "Feature",
  "properties": {
    "addr:full":"3901 Beacon Dr Oklahoma City OK 73179",
    "addr:housenumber":"3901",
    "addr:postcode":"73179",
    "addr:street":"Beacon Dr",
    "iso:country":"US",
    "sg:address":"3901 Beacon Dr",
    "sg:city":"Oklahoma City",
    "sg:classifiers":[
        {
            "category":"Autos & Motor Vehicles",
            "subcategory":"Automobile Sales",
            "type":"Retail Goods"
        }
    ],
    "sg:phone":"+1 405 745 4991",
    "sg:postcode":"73179",
    "sg:province":"OK",
    "sg:tags":[
        "car",
        "dealer"
    ],
    "wof:name":"Frasher Wholesale Inc",
    "wof:placetype":"venue"
},
  "geometry": {"coordinates":[-97.63191,35.425513],"type":"Point"}
}