{
  "type": "Feature",
  "properties": {
    "addr:full":"2425 NW 111th St Oklahoma City OK 73120",
    "addr:housenumber":"2425",
    "addr:postcode":"73120",
    "addr:street":"Nw 111Th St",
    "iso:country":"US",
    "sg:address":"2425 NW 111th St",
    "sg:city":"Oklahoma City",
    "sg:classifiers":[
        {
            "category":"Professional",
            "subcategory":"Advertising",
            "type":"Services"
        }
    ],
    "sg:phone":"+1 405 751 9008",
    "sg:postcode":"73120",
    "sg:province":"OK",
    "wof:name":"Vernon Co",
    "wof:placetype":"venue"
},
  "geometry": {"coordinates":[-97.554725,35.582115],"type":"Point"}
}