{
  "type": "Feature",
  "properties": {
    "iso:country":"US",
    "sg:address":"13998 US Hwy 177",
    "sg:city":"Braman",
    "sg:classifiers":[
        {
            "category":"Bars & Pubs",
            "type":"Food & Drink"
        }
    ],
    "sg:phone":"+1 580 894 5748",
    "sg:postcode":"74632",
    "sg:province":"OK",
    "wof:name":"State Line Tavern",
    "wof:placetype":"venue"
},
  "geometry": {"coordinates":[-97.39906999999999,36.98482],"type":"Point"}
}