{
  "type": "Feature",
  "properties": {
    "addr:full":"2 N Main St Miami OK 74354",
    "addr:housenumber":"2",
    "addr:postcode":"74354",
    "addr:street":"N Main St",
    "iso:country":"US",
    "sg:address":"2 N Main St",
    "sg:city":"Miami",
    "sg:classifiers":[
        {
            "category":"Professional",
            "subcategory":"Lawyer & Legal Services",
            "type":"Services"
        }
    ],
    "sg:phone":"+1 918 542 1517",
    "sg:postcode":"74354",
    "sg:province":"OK",
    "sg:tags":[
        "attorney"
    ],
    "wof:name":"William R Sharp",
    "wof:placetype":"venue"
},
  "geometry": {"coordinates":[-94.87751,36.87622],"type":"Point"}
}