{
  "type": "Feature",
  "properties": {
    "iso:country":"US",
    "sg:address":"3404 SE 15th St",
    "sg:city":"Oklahoma City",
    "sg:classifiers":[
        {
            "category":"Retail",
            "subcategory":"Repair Shop",
            "type":"Services"
        },
        {
            "category":"Home & Garden",
            "subcategory":"Household Appliances",
            "type":"Retail Goods"
        }
    ],
    "sg:phone":"+1 405 677 4332",
    "sg:postcode":"73115",
    "sg:province":"OK",
    "sg:tags":[
        "cleaners",
        "electrical",
        "vacuum"
    ],
    "wof:name":"Frank's Vacuum Sales & Repair",
    "wof:placetype":"venue"
},
  "geometry": {"coordinates":[-97.45137800000001,35.449668],"type":"Point"}
}