{
  "type": "Feature",
  "properties": {
    "addr:full":"112 W Memphis St Broken Arrow OK 74012",
    "addr:housenumber":"112",
    "addr:postcode":"74012",
    "addr:street":"W Memphis St",
    "iso:country":"US",
    "sg:address":"112 W Memphis St",
    "sg:city":"Broken Arrow",
    "sg:classifiers":[
        {
            "category":"Health Services",
            "subcategory":"Nursing And Care Facility",
            "type":"Services"
        }
    ],
    "sg:phone":"+1 918 258 1782",
    "sg:postcode":"74012",
    "sg:province":"OK",
    "sg:tags":[
        "intermediate"
    ],
    "wof:name":"Touch of Love Inc",
    "wof:placetype":"venue"
},
  "geometry": {"coordinates":[-95.790969,36.042347],"type":"Point"}
}