{
  "type": "Feature",
  "properties": {
    "iso:country":"US",
    "sg:address":"12713 E 89th St N",
    "sg:city":"Owasso",
    "sg:classifiers":[
        {
            "category":"Organizations",
            "subcategory":"Religious Organization",
            "type":"Services"
        }
    ],
    "sg:phone":"+1 918 272 0494",
    "sg:postcode":"74055",
    "sg:province":"OK",
    "wof:name":"Standing In Gap Inc",
    "wof:placetype":"venue"
},
  "geometry": {"coordinates":[-95.833003,36.284935],"type":"Point"}
}