{
  "type": "Feature",
  "properties": {
    "iso:country":"US",
    "sg:address":"5301 S Hattie Ave",
    "sg:city":"Oklahoma City",
    "sg:classifiers":[
        {
            "category":"Shopping",
            "subcategory":"Computers & Home Electronics",
            "type":"Retail Goods"
        }
    ],
    "sg:phone":"+1 405 672 2021",
    "sg:postcode":"73129",
    "sg:province":"OK",
    "sg:tags":[
        "equipment",
        "satellite",
        "system"
    ],
    "sg:website":"www.fibra.com",
    "wof:name":"Fibra Com",
    "wof:placetype":"venue"
},
  "geometry": {"coordinates":[-97.487749,35.407244],"type":"Point"}
}