{
  "type": "Feature",
  "properties": {
    "iso:country":"US",
    "sg:address":"6201 N Santa Fe Ave",
    "sg:city":"Oklahoma City",
    "sg:classifiers":[
        {
            "category":"Health Services",
            "subcategory":"Doctor",
            "type":"Services"
        }
    ],
    "sg:phone":"+1 405 419 5477",
    "sg:postcode":"73118",
    "sg:province":"OK",
    "sg:tags":[
        "physician",
        "surgeon"
    ],
    "wof:name":"Gary Dickinson MD",
    "wof:placetype":"venue"
},
  "geometry": {"coordinates":[-97.512041,35.535959],"type":"Point"}
}