{
  "type": "Feature",
  "properties": {
    "addr:full":"316 NW Hwy 270 Woodward OK 73801",
    "addr:housenumber":"316",
    "addr:postcode":"73801",
    "addr:street":"Nw Hwy 270",
    "iso:country":"US",
    "sg:address":"316 NW Hwy 270",
    "sg:city":"Woodward",
    "sg:classifiers":[
        {
            "category":"Retail",
            "subcategory":"Car Wash",
            "type":"Services"
        }
    ],
    "sg:phone":"+1 580 254 3667",
    "sg:postcode":"73801",
    "sg:province":"OK",
    "sg:tags":[
        "carwash"
    ],
    "wof:name":"Super Star Wash of Woodward",
    "wof:placetype":"venue"
},
  "geometry": {"coordinates":[-99.434046,36.443992],"type":"Point"}
}