{
  "type": "Feature",
  "properties": {
    "iso:country":"US",
    "sg:address":"3201 E Memorial Rd",
    "sg:city":"Edmond",
    "sg:classifiers":[
        {
            "category":"Mining & Drilling",
            "type":"Manufacturing & Wholesale Goods"
        }
    ],
    "sg:phone":"+1 405 478 0404",
    "sg:postcode":"73013",
    "sg:province":"OK",
    "sg:tags":[
        "development",
        "gas",
        "oil",
        "exploration"
    ],
    "wof:name":"Blackgold Trading LLC",
    "wof:placetype":"venue"
},
  "geometry": {"coordinates":[-97.457104,35.609222],"type":"Point"}
}