{
  "type": "Feature",
  "properties": {
    "addr:full":"6801 Broadway Exd Oklahoma City OK 73116",
    "addr:housenumber":"6801",
    "addr:postcode":"73116",
    "addr:street":"Broadway Exd",
    "iso:country":"US",
    "sg:address":"6801 Broadway Exd",
    "sg:city":"Oklahoma City",
    "sg:classifiers":[
        {
            "category":"Professional",
            "subcategory":"Management & Consulting",
            "type":"Services"
        }
    ],
    "sg:phone":"+1 405 843 5650",
    "sg:postcode":"73116",
    "sg:province":"OK",
    "sg:tags":[
        "consultant",
        "energy",
        "conservation"
    ],
    "wof:name":"Sentinel Resources LLC",
    "wof:placetype":"venue"
},
  "geometry": {"coordinates":[-97.513914,35.545641],"type":"Point"}
}