{
  "type": "Feature",
  "properties": {
    "addr:full":"1521 Plains Ave Weatherford OK 73096",
    "addr:housenumber":"1521",
    "addr:postcode":"73096",
    "addr:street":"Plains Ave",
    "iso:country":"US",
    "sg:address":"1521 Plains Ave",
    "sg:city":"Weatherford",
    "sg:phone":"+1 580 772 3501",
    "sg:postcode":"73096",
    "sg:province":"OK",
    "sg:tags":[
        "farm",
        "wheat"
    ],
    "wof:name":"Amen Noble Farm",
    "wof:placetype":"venue"
},
  "geometry": {"coordinates":[-98.686813,35.542895],"type":"Point"}
}