{
  "type": "Feature",
  "properties": {
    "iso:country":"US",
    "sg:address":"1555 N 105th East Ave",
    "sg:city":"Tulsa",
    "sg:classifiers":[
        {
            "category":"Building & Trades",
            "subcategory":"Plumbing",
            "type":"Services"
        }
    ],
    "sg:phone":"+1 918 835 2611",
    "sg:postcode":"74116",
    "sg:province":"OK",
    "sg:tags":[
        "conditioning",
        "air",
        "system",
        "contractor"
    ],
    "wof:name":"Darrough Heating & Cooling",
    "wof:placetype":"venue"
},
  "geometry": {"coordinates":[-95.860471,36.178246],"type":"Point"}
}