{
  "type": "Feature",
  "properties": {
    "addr:full":"700 S Oklahoma Ave Okmulgee OK 74447",
    "addr:housenumber":"700",
    "addr:postcode":"74447",
    "addr:street":"S Oklahoma Ave",
    "iso:country":"US",
    "sg:address":"700 S Oklahoma Ave",
    "sg:city":"Okmulgee",
    "sg:classifiers":[
        {
            "category":"Retail",
            "subcategory":"Auto Repair",
            "type":"Services"
        }
    ],
    "sg:phone":"+1 918 758 0204",
    "sg:postcode":"74447",
    "sg:province":"OK",
    "sg:tags":[
        "body"
    ],
    "wof:name":"Bagbys Body Shop",
    "wof:placetype":"venue"
},
  "geometry": {"coordinates":[-95.979789,35.616504],"type":"Point"}
}