{
  "type": "Feature",
  "properties": {
    "iso:country":"US",
    "sg:address":"1141 NW 34th St",
    "sg:city":"Oklahoma City",
    "sg:classifiers":[
        {
            "category":"Professional",
            "subcategory":"Business Services",
            "type":"Services"
        }
    ],
    "sg:phone":"+1 405 232 7373",
    "sg:postcode":"73118",
    "sg:province":"OK",
    "wof:name":"Best Bail Bonds",
    "wof:placetype":"venue"
},
  "geometry": {"coordinates":[-97.531893,35.505333],"type":"Point"}
}