{
  "type": "Feature",
  "properties": {
    "addr:full":"1316 George Ave Norman OK 73072",
    "addr:housenumber":"1316",
    "addr:postcode":"73072",
    "addr:street":"George Ave",
    "iso:country":"US",
    "sg:address":"1316 George Ave",
    "sg:city":"Norman",
    "sg:classifiers":[
        {
            "category":"Taxi",
            "type":"Transportation"
        }
    ],
    "sg:phone":"+1 405 366 8999",
    "sg:postcode":"73072",
    "sg:province":"OK",
    "sg:tags":[
        "taxicab"
    ],
    "wof:name":"Town Taxi",
    "wof:placetype":"venue"
},
  "geometry": {"coordinates":[-97.43692,35.203341],"type":"Point"}
}