{
  "type": "Feature",
  "properties": {
    "iso:country":"US",
    "sg:address":"4100 E 51st St #111",
    "sg:city":"Tulsa",
    "sg:phone":"+1 918 742 6700",
    "sg:postcode":"74135",
    "sg:province":"OK",
    "wof:name":"Crestwood Clinic, PC",
    "wof:placetype":"venue"
},
  "geometry": {"coordinates":[-95.930344,36.089834],"type":"Point"}
}