{
  "type": "Feature",
  "properties": {
    "iso:country":"US",
    "sg:address":"1905 W Broadway Ave",
    "sg:city":"Sulphur",
    "sg:classifiers":[
        {
            "category":"Real Estate",
            "subcategory":"Real Estate Operator",
            "type":"Services"
        }
    ],
    "sg:phone":"+1 580 622 6704",
    "sg:postcode":"73086",
    "sg:province":"OK",
    "sg:tags":[
        "apartment"
    ],
    "wof:name":"Lancaster Home Rentals",
    "wof:placetype":"venue"
},
  "geometry": {"coordinates":[-96.993728,34.506235],"type":"Point"}
}