{
  "type": "Feature",
  "properties": {
    "addr:full":"15151 180th St Lexington OK 73051",
    "addr:housenumber":"15151",
    "addr:postcode":"73051",
    "addr:street":"180Th St",
    "iso:country":"US",
    "sg:address":"15151 180th St",
    "sg:city":"Lexington",
    "sg:classifiers":[
        {
            "category":"Farming",
            "subcategory":"Livestock Farm",
            "type":"Manufacturing & Wholesale Goods"
        }
    ],
    "sg:phone":"+1 405 527 2155",
    "sg:postcode":"73051",
    "sg:province":"OK",
    "sg:tags":[
        "beef",
        "feedlot",
        "cattle"
    ],
    "wof:name":"Daryl Covey",
    "wof:placetype":"venue"
},
  "geometry": {"coordinates":[-97.177223,35.034797],"type":"Point"}
}