{
  "type": "Feature",
  "properties": {
    "iso:country":"US",
    "sg:address":"109 N Main St",
    "sg:city":"Blackwell",
    "sg:classifiers":[
        {
            "category":"Professional",
            "subcategory":"Accounting & Tax Preparation",
            "type":"Services"
        }
    ],
    "sg:phone":"+1 580 363 4829",
    "sg:postcode":"74631",
    "sg:province":"OK",
    "sg:tags":[
        "return"
    ],
    "wof:name":"Jackson Hewitt Tax Service",
    "wof:placetype":"venue"
},
  "geometry": {"coordinates":[-97.283055,36.804726],"type":"Point"}
}