{
  "type": "Feature",
  "properties": {
    "iso:country":"US",
    "sg:address":"806 SE 4th St",
    "sg:city":"Lindsay",
    "sg:classifiers":[
        {
            "category":"Retail",
            "subcategory":"Veterinary Services",
            "type":"Services"
        }
    ],
    "sg:phone":"+1 405 756 2929",
    "sg:postcode":"73052",
    "sg:province":"OK",
    "sg:tags":[
        "veterinarian"
    ],
    "wof:name":"Lindsay Veterinary Hospital",
    "wof:placetype":"venue"
},
  "geometry": {"coordinates":[-97.598482,34.828976],"type":"Point"}
}