{
  "type": "Feature",
  "properties": {
    "iso:country":"US",
    "sg:address":"3534 S Louisville Ave",
    "sg:city":"Tulsa",
    "sg:classifiers":[
        {
            "category":"Banks & Credit Unions",
            "subcategory":"Investment Brokerage",
            "type":"Services"
        }
    ],
    "sg:phone":"+1 918 493 7635",
    "sg:postcode":"74135",
    "sg:province":"OK",
    "sg:tags":[
        "brokerage",
        "oil",
        "gas",
        "for"
    ],
    "wof:name":"Waterstone Environmental Inc",
    "wof:placetype":"venue"
},
  "geometry": {"coordinates":[-95.93579699999999,36.112181],"type":"Point"}
}