{
  "type": "Feature",
  "properties": {
    "addr:full":"3324 French Park Dr Edmond OK 73034",
    "addr:housenumber":"3324",
    "addr:postcode":"73034",
    "addr:street":"French Park Dr",
    "iso:country":"US",
    "sg:address":"3324 French Park Dr",
    "sg:city":"Edmond",
    "sg:classifiers":[
        {
            "category":"Professional",
            "subcategory":"Management & Consulting",
            "type":"Services"
        }
    ],
    "sg:phone":"+1 405 341 0033",
    "sg:postcode":"73034",
    "sg:province":"OK",
    "sg:tags":[
        "communications",
        "consultant"
    ],
    "wof:name":"Cmc",
    "wof:placetype":"venue"
},
  "geometry": {"coordinates":[-97.43572899999999,35.651904],"type":"Point"}
}