{
  "type": "Feature",
  "properties": {
    "iso:country":"US",
    "sg:address":"101 E Broadway",
    "sg:city":"Allen",
    "sg:classifiers":[
        {
            "category":"Banks & Credit Unions",
            "subcategory":"Bank",
            "type":"Services"
        }
    ],
    "sg:phone":"+1 580 857 2402",
    "sg:postcode":"74825",
    "sg:province":"OK",
    "wof:name":"Farmers State Bank",
    "wof:placetype":"venue"
},
  "geometry": {"coordinates":[-96.41453799999999,34.879134],"type":"Point"}
}