{
  "type": "Feature",
  "properties": {
    "addr:full":"618 W Main St Henryetta OK 74437",
    "addr:housenumber":"618",
    "addr:postcode":"74437",
    "addr:street":"W Main St",
    "iso:country":"US",
    "sg:address":"618 W Main St",
    "sg:city":"Henryetta",
    "sg:classifiers":[
        {
            "category":"Professional",
            "subcategory":"Business Services",
            "type":"Services"
        }
    ],
    "sg:phone":"+1 918 652 8095",
    "sg:postcode":"74437",
    "sg:province":"OK",
    "sg:tags":[
        "appraiser"
    ],
    "wof:name":"Davidson Appraisers",
    "wof:placetype":"venue"
},
  "geometry": {"coordinates":[-95.98940399999999,35.439861],"type":"Point"}
}