{
  "type": "Feature",
  "properties": {
    "addr:full":"3806 Charles Page Blvd Tulsa OK 74127",
    "addr:housenumber":"3806",
    "addr:postcode":"74127",
    "addr:street":"Charles Page Blvd",
    "iso:country":"US",
    "sg:address":"3806 Charles Page Blvd",
    "sg:city":"Tulsa",
    "sg:classifiers":[
        {
            "category":"Wholesale",
            "subcategory":"Metals & Minerals",
            "type":"Manufacturing & Wholesale Goods"
        }
    ],
    "sg:phone":"+1 918 582 3466",
    "sg:postcode":"74127",
    "sg:province":"OK",
    "sg:tags":[
        "foundry",
        "center",
        "aluminum"
    ],
    "wof:name":"Accucast",
    "wof:placetype":"venue"
},
  "geometry": {"coordinates":[-96.035877,36.147904],"type":"Point"}
}