{
  "type": "Feature",
  "properties": {
    "iso:country":"US",
    "sg:address":"525 E Creek Ave",
    "sg:city":"Bache",
    "sg:classifiers":[
        {
            "category":"Freight",
            "type":"Transportation"
        }
    ],
    "sg:phone":"+1 918 423 3838",
    "sg:postcode":"74501",
    "sg:province":"OK",
    "sg:tags":[
        "operator",
        "local",
        "trucking"
    ],
    "wof:name":"Wills Delivery",
    "wof:placetype":"venue"
},
  "geometry": {"coordinates":[-95.767608,34.919194],"type":"Point"}
}