{
  "type": "Feature",
  "properties": {
    "addr:full":"10830 E 45th St Tulsa OK 74146",
    "addr:housenumber":"10830",
    "addr:postcode":"74146",
    "addr:street":"E 45Th St",
    "iso:country":"US",
    "sg:address":"10830 E 45th St",
    "sg:city":"Tulsa",
    "sg:classifiers":[
        {
            "category":"Wholesale",
            "subcategory":"Hardware",
            "type":"Manufacturing & Wholesale Goods"
        }
    ],
    "sg:phone":"+1 918 627 7100",
    "sg:postcode":"74146",
    "sg:province":"OK",
    "sg:tags":[
        "dust",
        "collecting",
        "system"
    ],
    "wof:name":"Donaldson-Torit",
    "wof:placetype":"venue"
},
  "geometry": {"coordinates":[-95.855794,36.099748],"type":"Point"}
}