{
  "type": "Feature",
  "properties": {
    "iso:country":"US",
    "sg:address":"118 W H St",
    "sg:city":"Ringling",
    "sg:classifiers":[
        {
            "category":"Organizations",
            "subcategory":"Religious Organization",
            "type":"Services"
        }
    ],
    "sg:phone":"+1 580 662 2119",
    "sg:postcode":"73456",
    "sg:province":"OK",
    "sg:tags":[
        "church"
    ],
    "wof:name":"Marvin Acree Meml Unite",
    "wof:placetype":"venue"
},
  "geometry": {"coordinates":[-97.593831,34.175387],"type":"Point"}
}