{
  "type": "Feature",
  "properties": {
    "iso:country":"US",
    "sg:address":"1545 S Harvard Ave",
    "sg:city":"Tulsa",
    "sg:classifiers":[
        {
            "category":"Shopping",
            "subcategory":"Used Merchandise",
            "type":"Retail Goods"
        }
    ],
    "sg:phone":"+1 918 749 3240",
    "sg:postcode":"74112",
    "sg:province":"OK",
    "sg:tags":[
        "antique"
    ],
    "wof:name":"Side Door Antiques LTD",
    "wof:placetype":"venue"
},
  "geometry": {"coordinates":[-95.94029500000001,36.13954],"type":"Point"}
}