{
  "type": "Feature",
  "properties": {
    "addr:full":"6020 Newcastle Rd Oklahoma City OK 73179",
    "addr:housenumber":"6020",
    "addr:postcode":"73179",
    "addr:street":"Newcastle Rd",
    "iso:country":"US",
    "sg:address":"6020 Newcastle Rd",
    "sg:city":"Oklahoma City",
    "sg:classifiers":[
        {
            "category":"Wholesale",
            "subcategory":"Machinery & Supplies",
            "type":"Manufacturing & Wholesale Goods"
        }
    ],
    "sg:phone":"+1 405 745 2769",
    "sg:postcode":"73179",
    "sg:province":"OK",
    "sg:tags":[
        "field",
        "oil",
        "equipment"
    ],
    "sg:website":"www.sivalls.com",
    "wof:name":"Sivalls Inc",
    "wof:placetype":"venue"
},
  "geometry": {"coordinates":[-97.620839,35.415837],"type":"Point"}
}