{
  "type": "Feature",
  "properties": {
    "iso:country":"US",
    "sg:address":"19418 Patterson Rd",
    "sg:city":"Tecumseh",
    "sg:classifiers":[
        {
            "category":"Freight",
            "type":"Transportation"
        }
    ],
    "sg:phone":"+1 405 202 2664",
    "sg:postcode":"74873",
    "sg:province":"OK",
    "sg:tags":[
        "mover"
    ],
    "wof:name":"AAA Moving",
    "wof:placetype":"venue"
},
  "geometry": {"coordinates":[-97.089181,35.28157],"type":"Point"}
}