{
  "type": "Feature",
  "properties": {
    "iso:country":"US",
    "sg:address":"5800 S 68th St",
    "sg:city":"Tulsa",
    "sg:classifiers":[
        {
            "category":"Freight",
            "type":"Transportation"
        }
    ],
    "sg:phone":"+1 918 446 4700",
    "sg:postcode":"74131",
    "sg:province":"OK",
    "sg:tags":[
        "hauling",
        "trucking"
    ],
    "wof:name":"Wesley Messenger",
    "wof:placetype":"venue"
},
  "geometry": {"coordinates":[-96.058084,36.064616],"type":"Point"}
}