{
  "type": "Feature",
  "properties": {
    "iso:country":"US",
    "sg:address":"742 Willow St",
    "sg:city":"Sand Springs",
    "sg:classifiers":[
        {
            "category":"Building & Trades",
            "subcategory":"Electrical",
            "type":"Services"
        }
    ],
    "sg:phone":"+1 918 245 4005",
    "sg:postcode":"74063",
    "sg:province":"OK",
    "sg:tags":[
        "electric",
        "contractor"
    ],
    "wof:name":"Wood Electric",
    "wof:placetype":"venue"
},
  "geometry": {"coordinates":[-96.141453,36.143589],"type":"Point"}
}