{
  "type": "Feature",
  "properties": {
    "iso:country":"US",
    "sg:address":"500 Cameron St",
    "sg:city":"Ardmore",
    "sg:classifiers":[
        {
            "category":"Wholesale",
            "subcategory":"Petroleum",
            "type":"Manufacturing & Wholesale Goods"
        }
    ],
    "sg:phone":"+1 580 226 1638",
    "sg:postcode":"73401",
    "sg:province":"OK",
    "sg:tags":[
        "pipe",
        "line",
        "company"
    ],
    "wof:name":"Valero Logistics Operations LP",
    "wof:placetype":"venue"
},
  "geometry": {"coordinates":[-97.104909,34.205783],"type":"Point"}
}