{
  "type": "Feature",
  "properties": {
    "iso:country":"US",
    "sg:address":"3452 SW 29th St",
    "sg:city":"Oklahoma City",
    "sg:classifiers":[
        {
            "category":"Food & Beverages",
            "subcategory":"Groceries & Convenience Stores",
            "type":"Retail Goods"
        }
    ],
    "sg:phone":"+1 405 681 9442",
    "sg:postcode":"73119",
    "sg:province":"OK",
    "sg:tags":[
        "grocer"
    ],
    "wof:name":"Speed Mart Grocery",
    "wof:placetype":"venue"
},
  "geometry": {"coordinates":[-97.57787399999999,35.435103],"type":"Point"}
}