{
  "type": "Feature",
  "properties": {
    "iso:country":"US",
    "sg:address":"812 SW 26th St",
    "sg:city":"El Reno",
    "sg:classifiers":[
        {
            "category":"Shopping",
            "type":"Retail Goods"
        }
    ],
    "sg:phone":"+1 405 262 8204",
    "sg:postcode":"73036",
    "sg:province":"OK",
    "sg:tags":[
        "cosmetic",
        "perfume"
    ],
    "wof:name":"Mary Kay Cosmetics",
    "wof:placetype":"venue"
},
  "geometry": {"coordinates":[-97.965976,35.509391],"type":"Point"}
}