{
  "type": "Feature",
  "properties": {
    "addr:full":"323 W Broadway St Muskogee OK 74401",
    "addr:housenumber":"323",
    "addr:postcode":"74401",
    "addr:street":"W Broadway St",
    "iso:country":"US",
    "sg:address":"323 W Broadway St",
    "sg:city":"Muskogee",
    "sg:classifiers":[
        {
            "category":"Social Services",
            "type":"Services"
        }
    ],
    "sg:phone":"+1 918 682 1364",
    "sg:postcode":"74401",
    "sg:province":"OK",
    "sg:tags":[
        "organization",
        "welfare"
    ],
    "wof:name":"United Way",
    "wof:placetype":"venue"
},
  "geometry": {"coordinates":[-95.37197999999999,35.74971],"type":"Point"}
}