{
  "type": "Feature",
  "properties": {
    "iso:country":"US",
    "sg:address":"1301 E Main St",
    "sg:city":"Wilburton",
    "sg:classifiers":[
        {
            "category":"Mining & Drilling",
            "type":"Manufacturing & Wholesale Goods"
        }
    ],
    "sg:phone":"+1 918 465 4742",
    "sg:postcode":"74578",
    "sg:province":"OK",
    "sg:tags":[
        "oil",
        "gas",
        "producer"
    ],
    "wof:name":"Oil Tools Inc",
    "wof:placetype":"venue"
},
  "geometry": {"coordinates":[-95.289465,34.919726],"type":"Point"}
}