{
  "type": "Feature",
  "properties": {
    "addr:full":"910 W Main St Norman OK 73069",
    "addr:housenumber":"910",
    "addr:postcode":"73069",
    "addr:street":"W Main St",
    "iso:country":"US",
    "sg:address":"910 W Main St",
    "sg:city":"Norman",
    "sg:classifiers":[
        {
            "category":"Personal",
            "subcategory":"Beauty Salon",
            "type":"Services"
        }
    ],
    "sg:phone":"+1 405 360 8893",
    "sg:postcode":"73069",
    "sg:province":"OK",
    "sg:tags":[
        "manicuring"
    ],
    "wof:name":"Top Nail",
    "wof:placetype":"venue"
},
  "geometry": {"coordinates":[-97.45576,35.218333],"type":"Point"}
}