{
  "type": "Feature",
  "properties": {
    "iso:country":"US",
    "sg:address":"402 Main St",
    "sg:city":"Shattuck",
    "sg:classifiers":[
        {
            "category":"Retail",
            "subcategory":"Auto Repair",
            "type":"Services"
        }
    ],
    "sg:phone":"+1 580 938 2569",
    "sg:postcode":"73858",
    "sg:province":"OK",
    "sg:tags":[
        "engine"
    ],
    "wof:name":"Schoenhals Diesel Svc",
    "wof:placetype":"venue"
},
  "geometry": {"coordinates":[-99.881429,36.269683],"type":"Point"}
}