{
  "type": "Feature",
  "properties": {
    "iso:country":"US",
    "sg:address":"121 W College St",
    "sg:city":"Broken Arrow",
    "sg:classifiers":[
        {
            "category":"Organizations",
            "subcategory":"Religious Organization",
            "type":"Services"
        }
    ],
    "sg:phone":"+1 918 251 5174",
    "sg:postcode":"74012",
    "sg:province":"OK",
    "sg:tags":[
        "church"
    ],
    "wof:name":"First Presbyterian Church",
    "wof:placetype":"venue"
},
  "geometry": {"coordinates":[-95.790992,36.053506],"type":"Point"}
}