{
  "type": "Feature",
  "properties": {
    "iso:country":"US",
    "sg:address":"8000 N Western Ave",
    "sg:city":"Oklahoma City",
    "sg:classifiers":[
        {
            "category":"Personal",
            "subcategory":"Beauty Salon",
            "type":"Services"
        }
    ],
    "sg:phone":"+1 405 767 9322",
    "sg:postcode":"73114",
    "sg:province":"OK",
    "sg:tags":[
        "shop"
    ],
    "wof:name":"Joe Garrison's Hair Studio",
    "wof:placetype":"venue"
},
  "geometry": {"coordinates":[-97.531411,35.552952],"type":"Point"}
}