{
  "type": "Feature",
  "properties": {
    "iso:country":"US",
    "sg:address":"1901 W Wyandotte Ave",
    "sg:city":"Sulphur",
    "sg:classifiers":[
        {
            "category":"Sports & Exercise",
            "subcategory":"Bowling",
            "type":"Entertainment"
        }
    ],
    "sg:phone":"+1 580 622 3313",
    "sg:postcode":"73086",
    "sg:province":"OK",
    "sg:tags":[
        "alley",
        "arcade"
    ],
    "wof:name":"Dawg Bowl",
    "wof:placetype":"venue"
},
  "geometry": {"coordinates":[-96.991687,34.505234],"type":"Point"}
}