{
  "type": "Feature",
  "properties": {
    "addr:full":"3126 S Garnett Rd Tulsa OK 74146",
    "addr:housenumber":"3126",
    "addr:postcode":"74146",
    "addr:street":"S Garnett Rd",
    "iso:country":"US",
    "sg:address":"3126 S Garnett Rd",
    "sg:city":"Tulsa",
    "sg:classifiers":[
        {
            "category":"Health Services",
            "subcategory":"Chiropractor",
            "type":"Services"
        }
    ],
    "sg:phone":"+1 918 665 0036",
    "sg:postcode":"74146",
    "sg:province":"OK",
    "wof:name":"Bruce Frye A-Dr",
    "wof:placetype":"venue"
},
  "geometry": {"coordinates":[-95.85120499999999,36.117835],"type":"Point"}
}