{
  "type": "Feature",
  "properties": {
    "iso:country":"US",
    "sg:address":"7633 NW 28th St",
    "sg:city":"Bethany",
    "sg:classifiers":[
        {
            "category":"Building & Trades",
            "subcategory":"Construction",
            "type":"Services"
        }
    ],
    "sg:phone":"+1 405 863 3791",
    "sg:postcode":"73008",
    "sg:province":"OK",
    "sg:tags":[
        "framing",
        "contractor"
    ],
    "wof:name":"B & L Framing",
    "wof:placetype":"venue"
},
  "geometry": {"coordinates":[-97.645882,35.498341],"type":"Point"}
}