{
  "type": "Feature",
  "properties": {
    "addr:full":"5308 Nowata Rd Bartlesville OK 74006",
    "addr:postcode":"5308;74006",
    "addr:street":"Nowata Rd",
    "iso:country":"US",
    "sg:address":"5308 Nowata Rd",
    "sg:city":"Bartlesville",
    "sg:classifiers":[
        {
            "category":"Autos & Motor Vehicles",
            "subcategory":"Automobile Sales",
            "type":"Retail Goods"
        }
    ],
    "sg:phone":"+1 918 333 3868",
    "sg:postcode":"74006",
    "sg:province":"OK",
    "sg:tags":[
        "car",
        "dealer"
    ],
    "wof:name":"Cheap Cars R Us",
    "wof:placetype":"venue"
},
  "geometry": {"coordinates":[-95.918454,36.728065],"type":"Point"}
}