{
  "type": "Feature",
  "properties": {
    "iso:country":"US",
    "sg:address":"834 W 139th Pl",
    "sg:city":"Glenpool",
    "sg:classifiers":[
        {
            "category":"Building & Trades",
            "subcategory":"Construction",
            "type":"Services"
        }
    ],
    "sg:phone":"+1 918 322 5319",
    "sg:postcode":"74033",
    "sg:province":"OK",
    "sg:tags":[
        "steel",
        "erection",
        "structural"
    ],
    "wof:name":"Creative Concrete",
    "wof:placetype":"venue"
},
  "geometry": {"coordinates":[-96.01752999999999,35.960265],"type":"Point"}
}