{
  "type": "Feature",
  "properties": {
    "addr:full":"7123 E 92nd Ct Tulsa OK 74133",
    "addr:housenumber":"7123",
    "addr:postcode":"74133",
    "addr:street":"E 92Nd Ct",
    "iso:country":"US",
    "sg:address":"7123 E 92nd Ct",
    "sg:city":"Tulsa",
    "sg:classifiers":[
        {
            "category":"Professional",
            "subcategory":"Business Services",
            "type":"Services"
        }
    ],
    "sg:phone":"+1 918 249 8876",
    "sg:postcode":"74133",
    "sg:province":"OK",
    "wof:name":"Basement Technologies Inc",
    "wof:placetype":"venue"
},
  "geometry": {"coordinates":[-95.896176,36.030676],"type":"Point"}
}