{
  "type": "Feature",
  "properties": {
    "iso:country":"US",
    "sg:address":"1304 SW Jefferson Ave",
    "sg:city":"Lawton",
    "sg:classifiers":[
        {
            "category":"Wholesale",
            "subcategory":"Home Furnishings",
            "type":"Manufacturing & Wholesale Goods"
        }
    ],
    "sg:phone":"+1 580 353 3590",
    "sg:postcode":"73501",
    "sg:province":"OK",
    "wof:name":"Fan Store & Fireplace Shop",
    "wof:placetype":"venue"
},
  "geometry": {"coordinates":[-98.409244,34.592269],"type":"Point"}
}