{
  "type": "Feature",
  "properties": {
    "iso:country":"US",
    "sg:address":"432 N Broadway Ave",
    "sg:city":"Shawnee",
    "sg:classifiers":[
        {
            "category":"Restaurant",
            "type":"Food & Drink"
        }
    ],
    "sg:phone":"+1 405 273 9177",
    "sg:postcode":"74801",
    "sg:province":"OK",
    "sg:tags":[
        "eating"
    ],
    "wof:name":"Sunny Side Up Inc",
    "wof:placetype":"venue"
},
  "geometry": {"coordinates":[-96.923625,35.332256],"type":"Point"}
}