{
  "type": "Feature",
  "properties": {
    "iso:country":"US",
    "sg:address":"5451 S Mingo Rd",
    "sg:city":"Tulsa",
    "sg:classifiers":[
        {
            "category":"Manufacturing",
            "subcategory":"Printing",
            "type":"Manufacturing & Wholesale Goods"
        }
    ],
    "sg:phone":"+1 918 660 2868",
    "sg:postcode":"74146",
    "sg:province":"OK",
    "sg:tags":[
        "screen"
    ],
    "wof:name":"Panda Enterprises LLC",
    "wof:placetype":"venue"
},
  "geometry": {"coordinates":[-95.868541,36.08447],"type":"Point"}
}