{
  "type": "Feature",
  "properties": {
    "iso:country":"US",
    "sg:address":"1521 S Cincinnati Ave",
    "sg:city":"Tulsa",
    "sg:classifiers":[
        {
            "category":"Shopping",
            "subcategory":"Stationery & Office Supplies",
            "type":"Retail Goods"
        }
    ],
    "sg:phone":"+1 918 582 1143",
    "sg:postcode":"74119",
    "sg:province":"OK",
    "wof:name":"Duke's Office Supplies",
    "wof:placetype":"venue"
},
  "geometry": {"coordinates":[-95.983937,36.13991],"type":"Point"}
}