{
  "type": "Feature",
  "properties": {
    "addr:full":"10702 N May Ave Oklahoma City OK 73120",
    "addr:housenumber":"10702",
    "addr:postcode":"73120",
    "addr:street":"N May Ave",
    "iso:country":"US",
    "sg:address":"10702 N May Ave",
    "sg:city":"Oklahoma City",
    "sg:classifiers":[
        {
            "category":"Insurance",
            "subcategory":"Insurance Agent",
            "type":"Services"
        }
    ],
    "sg:phone":"+1 405 751 0440",
    "sg:postcode":"73120",
    "sg:province":"OK",
    "wof:name":"State Farm Insurance",
    "wof:placetype":"venue"
},
  "geometry": {"coordinates":[-97.56711,35.57775],"type":"Point"}
}