{
  "type": "Feature",
  "properties": {
    "iso:country":"US",
    "sg:address":"4100 E 51st Pl",
    "sg:city":"Tulsa",
    "sg:classifiers":[
        {
            "category":"Health Services",
            "subcategory":"Chiropractor",
            "type":"Services"
        }
    ],
    "sg:phone":"+1 918 749 3950",
    "sg:postcode":"74135",
    "sg:province":"OK",
    "wof:name":"Neeman Chiropractic",
    "wof:placetype":"venue"
},
  "geometry": {"coordinates":[-95.930702,36.088795],"type":"Point"}
}