{
  "type": "Feature",
  "properties": {
    "addr:full":"3105 Belaire Dr Oklahoma City OK 73110",
    "addr:housenumber":"3105",
    "addr:postcode":"73110",
    "addr:street":"Belaire Dr",
    "iso:country":"US",
    "sg:address":"3105 Belaire Dr",
    "sg:city":"Oklahoma City",
    "sg:classifiers":[
        {
            "category":"Building & Trades",
            "subcategory":"Construction",
            "type":"Services"
        }
    ],
    "sg:phone":"+1 405 733 0544",
    "sg:postcode":"73110",
    "sg:province":"OK",
    "sg:tags":[
        "home",
        "builder"
    ],
    "wof:name":"Red Oak Construction Inc",
    "wof:placetype":"venue"
},
  "geometry": {"coordinates":[-97.39210300000001,35.471424],"type":"Point"}
}