{
  "type": "Feature",
  "properties": {
    "iso:country":"US",
    "sg:address":"1031 NE 36th St",
    "sg:city":"Oklahoma City",
    "sg:classifiers":[
        {
            "category":"Real Estate",
            "subcategory":"Real Estate Agent",
            "type":"Services"
        }
    ],
    "sg:phone":"+1 405 427 8311",
    "sg:postcode":"73111",
    "sg:province":"OK",
    "wof:name":"Carbin Realty",
    "wof:placetype":"venue"
},
  "geometry": {"coordinates":[-97.492332,35.507806],"type":"Point"}
}