{
  "type": "Feature",
  "properties": {
    "addr:full":"3400 Pendleton Ct Norman OK 73072",
    "addr:housenumber":"3400",
    "addr:postcode":"73072",
    "addr:street":"Pendleton Ct",
    "iso:country":"US",
    "sg:address":"3400 Pendleton Ct",
    "sg:city":"Norman",
    "sg:classifiers":[
        {
            "category":"Real Estate",
            "subcategory":"Real Estate Agent",
            "type":"Services"
        }
    ],
    "sg:phone":"+1 405 366 2141",
    "sg:postcode":"73072",
    "sg:province":"OK",
    "wof:name":"Robertson Real Estate Inc",
    "wof:placetype":"venue"
},
  "geometry": {"coordinates":[-97.49086200000001,35.241208],"type":"Point"}
}