{
  "type": "Feature",
  "properties": {
    "iso:country":"US",
    "sg:address":"401 E Court St",
    "sg:city":"Atoka",
    "sg:classifiers":[
        {
            "category":"Government",
            "subcategory":"Post Office",
            "type":"Public Place"
        }
    ],
    "sg:phone":"+1 580 889 3589",
    "sg:postcode":"74525",
    "sg:province":"OK",
    "sg:tags":[
        "postal",
        "us"
    ],
    "wof:name":"Atoka Main Office",
    "wof:placetype":"venue"
},
  "geometry": {"coordinates":[-96.124596,34.385062],"type":"Point"}
}