{
  "type": "Feature",
  "properties": {
    "addr:full":"408 W G Ave Cache OK 73527",
    "addr:housenumber":"408",
    "addr:postcode":"73527",
    "addr:street":"W G Ave",
    "iso:country":"US",
    "sg:address":"408 W G Ave",
    "sg:city":"Cache",
    "sg:classifiers":[
        {
            "category":"Banks & Credit Unions",
            "subcategory":"Bank",
            "type":"Services"
        }
    ],
    "sg:phone":"+1 580 429 9222",
    "sg:postcode":"73527",
    "sg:province":"OK",
    "sg:tags":[
        "loan"
    ],
    "wof:name":"J & J Finance Co",
    "wof:placetype":"venue"
},
  "geometry": {"coordinates":[-98.628957,34.624588],"type":"Point"}
}