{
  "type": "Feature",
  "properties": {
    "addr:full":"11500 E 80th St N Owasso OK 74055",
    "addr:housenumber":"11500",
    "addr:postcode":"74055",
    "addr:street":"E 80Th St N",
    "iso:country":"US",
    "sg:address":"11500 E 80th St N",
    "sg:city":"Owasso",
    "sg:classifiers":[
        {
            "category":"Freight",
            "type":"Transportation"
        }
    ],
    "sg:phone":"+1 918 272 7705",
    "sg:postcode":"74055",
    "sg:province":"OK",
    "sg:tags":[
        "special"
    ],
    "wof:name":"Three Lakes Mini Storage Inc",
    "wof:placetype":"venue"
},
  "geometry": {"coordinates":[-95.84385899999999,36.267835],"type":"Point"}
}