{
  "type": "Feature",
  "properties": {
    "addr:full":"5815 S Mingo Rd Tulsa OK 74146",
    "addr:housenumber":"5815",
    "addr:postcode":"74146",
    "addr:street":"S Mingo Rd",
    "iso:country":"US",
    "sg:address":"5815 S Mingo Rd",
    "sg:city":"Tulsa",
    "sg:classifiers":[
        {
            "category":"Freight",
            "type":"Transportation"
        }
    ],
    "sg:phone":"+1 918 250 8288",
    "sg:postcode":"74146",
    "sg:province":"OK",
    "sg:tags":[
        "commercial",
        "storage"
    ],
    "wof:name":"South Mingo Mini Storage",
    "wof:placetype":"venue"
},
  "geometry": {"coordinates":[-95.868487,36.079695],"type":"Point"}
}