{
  "type": "Feature",
  "properties": {
    "iso:country":"US",
    "sg:address":"2104 Denver Harner Dr",
    "sg:city":"Miami",
    "sg:classifiers":[
        {
            "category":"Social Services",
            "type":"Services"
        }
    ],
    "sg:phone":"+1 918 542 1575",
    "sg:postcode":"74354",
    "sg:province":"OK",
    "sg:tags":[
        "senior",
        "citizen"
    ],
    "wof:name":"Central Kitchen",
    "wof:placetype":"venue"
},
  "geometry": {"coordinates":[-94.857735,36.899772],"type":"Point"}
}