{
  "type": "Feature",
  "properties": {
    "addr:full":"8421 E 61st St Tulsa OK 74133",
    "addr:housenumber":"8421",
    "addr:postcode":"74133",
    "addr:street":"E 61St St",
    "iso:country":"US",
    "sg:address":"8421 E 61st St",
    "sg:city":"Tulsa",
    "sg:classifiers":[
        {
            "category":"Personal",
            "type":"Services"
        },
        {
            "category":"Arena",
            "subcategory":"Sports Club",
            "type":"Entertainment"
        }
    ],
    "sg:phone":"+1 918 294 0999",
    "sg:postcode":"74133",
    "sg:province":"OK",
    "sg:tags":[
        "trainer",
        "consultant",
        "physical",
        "health",
        "fitness"
    ],
    "wof:name":"Aspen Athletic Clubs",
    "wof:placetype":"venue"
},
  "geometry": {"coordinates":[-95.88288900000001,36.075407],"type":"Point"}
}