{
  "type": "Feature",
  "properties": {
    "addr:full":"13829 S Casper St Glenpool OK 74033",
    "addr:housenumber":"13829",
    "addr:postcode":"74033",
    "addr:street":"S Casper St",
    "iso:country":"US",
    "sg:address":"13829 S Casper St",
    "sg:city":"Glenpool",
    "sg:classifiers":[
        {
            "category":"Health Services",
            "subcategory":"Doctor",
            "type":"Services"
        }
    ],
    "sg:phone":"+1 918 291 0004",
    "sg:postcode":"74033",
    "sg:province":"OK",
    "sg:tags":[
        "clinic"
    ],
    "wof:name":"Faith Women's Clinic",
    "wof:placetype":"venue"
},
  "geometry": {"coordinates":[-96.011302,35.963375],"type":"Point"}
}