{
  "type": "Feature",
  "properties": {
    "iso:country":"US",
    "sg:address":"609 Woody Ln",
    "sg:city":"Chandler",
    "sg:classifiers":[
        {
            "category":"Building & Trades",
            "subcategory":"Cleaning & Sanitation",
            "type":"Services"
        }
    ],
    "sg:phone":"+1 405 258 5869",
    "sg:postcode":"74834",
    "sg:province":"OK",
    "sg:tags":[
        "maintenance"
    ],
    "wof:name":"Mitchells Cleaning Service",
    "wof:placetype":"venue"
},
  "geometry": {"coordinates":[-96.87377,35.67879],"type":"Point"}
}