{
  "type": "Feature",
  "properties": {
    "iso:country":"US",
    "sg:address":"5526 S 48th West Ave",
    "sg:city":"Tulsa",
    "sg:classifiers":[
        {
            "category":"Autos & Motor Vehicles",
            "subcategory":"Auto Supplies",
            "type":"Retail Goods"
        },
        {
            "category":"Wholesale",
            "subcategory":"Auto Parts",
            "type":"Manufacturing & Wholesale Goods"
        }
    ],
    "sg:phone":"+1 918 584 4618",
    "sg:postcode":"74107",
    "sg:province":"OK",
    "sg:tags":[
        "equipment",
        "truck"
    ],
    "wof:name":"Oklahoma Truck Supply Inc",
    "wof:placetype":"venue"
},
  "geometry": {"coordinates":[-96.04606200000001,36.083605],"type":"Point"}
}