{
  "type": "Feature",
  "properties": {
    "addr:full":"1206 S McQuarrie Ave Wagoner OK 74467",
    "addr:housenumber":"1206",
    "addr:postcode":"74467",
    "addr:street":"S Mcquarrie Ave",
    "iso:country":"US",
    "sg:address":"1206 S McQuarrie Ave",
    "sg:city":"Wagoner",
    "sg:classifiers":[
        {
            "category":"Retail",
            "subcategory":"Car Wash",
            "type":"Services"
        }
    ],
    "sg:phone":"+1 918 485 2368",
    "sg:postcode":"74467",
    "sg:province":"OK",
    "sg:tags":[
        "polishing",
        "washing"
    ],
    "wof:name":"East Side Car Wash",
    "wof:placetype":"venue"
},
  "geometry": {"coordinates":[-95.367375,35.947779],"type":"Point"}
}