{
  "type": "Feature",
  "properties": {
    "iso:country":"US",
    "sg:address":"100 S Broadway St",
    "sg:city":"Hugo",
    "sg:classifiers":[
        {
            "category":"Banks & Credit Unions",
            "subcategory":"Bank",
            "type":"Services"
        }
    ],
    "sg:phone":"+1 580 326 9641",
    "sg:postcode":"74743",
    "sg:province":"OK",
    "wof:name":"Hugo Bankshares Inc",
    "wof:placetype":"venue"
},
  "geometry": {"coordinates":[-95.512768,33.996515],"type":"Point"}
}