{
  "type": "Feature",
  "properties": {
    "iso:country":"US",
    "sg:address":"1215 W 10th Ave",
    "sg:city":"Stillwater",
    "sg:classifiers":[
        {
            "category":"Health Services",
            "subcategory":"Nursing And Care Facility",
            "type":"Services"
        }
    ],
    "sg:phone":"+1 405 372 1000",
    "sg:postcode":"74074",
    "sg:province":"OK",
    "sg:tags":[
        "home",
        "convalescent"
    ],
    "wof:name":"Grace Living Ctr Stillwater",
    "wof:placetype":"venue"
},
  "geometry": {"coordinates":[-97.072627,36.111216],"type":"Point"}
}