{
  "type": "Feature",
  "properties": {
    "addr:full":"8545 E 41st St Tulsa OK 74145",
    "addr:housenumber":"8545",
    "addr:postcode":"74145",
    "addr:street":"E 41St St",
    "iso:country":"US",
    "sg:address":"8545 E 41st St",
    "sg:city":"Tulsa",
    "sg:phone":"+1 918 583 9151",
    "sg:postcode":"74145",
    "sg:province":"OK",
    "sg:website":"http://www.ckwsupply.com",
    "wof:name":"C-K & W Supply, Inc.",
    "wof:placetype":"venue"
},
  "geometry": {"coordinates":[-95.87952199999999,36.104421],"type":"Point"}
}