{
  "type": "Feature",
  "properties": {
    "addr:full":"22274 Valley Rd Red Rock OK 74651",
    "addr:housenumber":"22274",
    "addr:postcode":"74651",
    "addr:street":"Valley Rd",
    "iso:country":"US",
    "sg:address":"22274 Valley Rd",
    "sg:city":"Red Rock",
    "sg:classifiers":[
        {
            "category":"Government",
            "subcategory":"Fire Station",
            "type":"Public Place"
        }
    ],
    "sg:phone":"+1 405 747 4442",
    "sg:postcode":"74651",
    "sg:province":"OK",
    "sg:tags":[
        "protection"
    ],
    "wof:name":"Red Rock Fire Department",
    "wof:placetype":"venue"
},
  "geometry": {"coordinates":[-97.06851899999999,36.463595],"type":"Point"}
}