{
  "type": "Feature",
  "properties": {
    "iso:country":"US",
    "sg:address":"1219 SW Frank Phillips Blvd",
    "sg:city":"Bartlesville",
    "sg:classifiers":[
        {
            "category":"Health Services",
            "subcategory":"Medical Lab",
            "type":"Services"
        }
    ],
    "sg:phone":"+1 918 336 5161",
    "sg:postcode":"74003",
    "sg:province":"OK",
    "sg:tags":[
        "laboratory"
    ],
    "wof:name":"Aesthetics Unlimited",
    "wof:placetype":"venue"
},
  "geometry": {"coordinates":[-95.99150899999999,36.751521],"type":"Point"}
}