{
  "type": "Feature",
  "properties": {
    "iso:country":"US",
    "sg:address":"1420 S Air Depot Blvd",
    "sg:city":"Oklahoma City",
    "sg:classifiers":[
        {
            "category":"Restaurant",
            "type":"Food & Drink"
        }
    ],
    "sg:menulink":"http://www.allmenus.com/ok/oklahoma-city/211103-kfc---kentucky-fried-chicken/menu/",
    "sg:phone":"+1 405 737 3016",
    "sg:postcode":"73110",
    "sg:province":"OK",
    "sg:tags":[
        "american",
        "chicken"
    ],
    "wof:name":"KFC - Kentucky Fried Chicken",
    "wof:placetype":"venue"
},
  "geometry": {"coordinates":[-97.40563,35.450408],"type":"Point"}
}