{
  "type": "Feature",
  "properties": {
    "iso:country":"US",
    "sg:address":"7201 S Santa Fe Ave",
    "sg:city":"Oklahoma City",
    "sg:classifiers":[
        {
            "category":"Organizations",
            "subcategory":"Religious Organization",
            "type":"Services"
        }
    ],
    "sg:phone":"+1 405 634 2474",
    "sg:postcode":"73139",
    "sg:province":"OK",
    "sg:tags":[
        "church"
    ],
    "wof:name":"Southern Oaks Free Will Church",
    "wof:placetype":"venue"
},
  "geometry": {"coordinates":[-97.512463,35.392328],"type":"Point"}
}