{
  "type": "Feature",
  "properties": {
    "iso:country":"US",
    "sg:address":"2504 S Hwy 66",
    "sg:city":"Claremore",
    "sg:classifiers":[
        {
            "category":"Government",
            "subcategory":"Office",
            "type":"Public Place"
        }
    ],
    "sg:phone":"+1 918 341 2380",
    "sg:postcode":"74017",
    "sg:province":"OK",
    "sg:website":"www.rogerscounty.org",
    "wof:name":"Rogers County Warehouse",
    "wof:placetype":"venue"
},
  "geometry": {"coordinates":[-95.603481,36.333986],"type":"Point"}
}