{
  "type": "Feature",
  "properties": {
    "addr:full":"10207 E 42nd St Tulsa OK 74146",
    "addr:housenumber":"10207",
    "addr:postcode":"74146",
    "addr:street":"E 42Nd St",
    "iso:country":"US",
    "sg:address":"10207 E 42nd St",
    "sg:city":"Tulsa",
    "sg:classifiers":[
        {
            "category":"Professional",
            "subcategory":"Accounting & Tax Preparation",
            "type":"Services"
        }
    ],
    "sg:phone":"+1 918 627 0250",
    "sg:postcode":"74146",
    "sg:province":"OK",
    "wof:name":"Ajs Accounting Service",
    "wof:placetype":"venue"
},
  "geometry": {"coordinates":[-95.862882,36.102968],"type":"Point"}
}