{
  "type": "Feature",
  "properties": {
    "iso:country":"US",
    "sg:address":"2600 Tealwood Dr",
    "sg:city":"Oklahoma City",
    "sg:classifiers":[
        {
            "category":"Real Estate",
            "subcategory":"Real Estate Operator",
            "type":"Services"
        }
    ],
    "sg:phone":"+1 405 752 1401",
    "sg:postcode":"73120",
    "sg:province":"OK",
    "sg:tags":[
        "apartment"
    ],
    "wof:name":"Walker's Station Apartments",
    "wof:placetype":"venue"
},
  "geometry": {"coordinates":[-97.56045399999999,35.598185],"type":"Point"}
}