{
  "type": "Feature",
  "properties": {
    "iso:country":"US",
    "sg:address":"9140 S 61st St E",
    "sg:city":"Muskogee",
    "sg:classifiers":[
        {
            "category":"Building & Trades",
            "subcategory":"Plumbing",
            "type":"Services"
        }
    ],
    "sg:phone":"+1 918 686 6543",
    "sg:postcode":"74403",
    "sg:province":"OK",
    "sg:tags":[
        "conditioning",
        "air",
        "system",
        "contractor"
    ],
    "wof:name":"Hamby Heating & Air Cond",
    "wof:placetype":"venue"
},
  "geometry": {"coordinates":[-95.27604100000001,35.624392],"type":"Point"}
}