{
  "type": "Feature",
  "properties": {
    "iso:country":"US",
    "sg:address":"2100 E Grand Blvd",
    "sg:city":"Oklahoma City",
    "sg:classifiers":[
        {
            "category":"Manufacturing",
            "subcategory":"Tools & Machinery",
            "type":"Manufacturing & Wholesale Goods"
        }
    ],
    "sg:phone":"+1 405 672 6793",
    "sg:postcode":"73129",
    "sg:province":"OK",
    "sg:tags":[
        "mfg",
        "equipment",
        "oil",
        "field"
    ],
    "wof:name":"J M Huber Corporation",
    "wof:placetype":"venue"
},
  "geometry": {"coordinates":[-97.46146,35.445479],"type":"Point"}
}