{
  "type": "Feature",
  "properties": {
    "iso:country":"US",
    "sg:address":"630 NW 17th St",
    "sg:city":"Oklahoma City",
    "sg:classifiers":[
        {
            "category":"Real Estate",
            "subcategory":"Real Estate Agent",
            "type":"Services"
        }
    ],
    "sg:phone":"+1 405 521 1710",
    "sg:postcode":"73103",
    "sg:province":"OK",
    "wof:name":"Splash Poolgardenhome",
    "wof:placetype":"venue"
},
  "geometry": {"coordinates":[-97.52376700000001,35.486936],"type":"Point"}
}