{
  "type": "Feature",
  "properties": {
    "iso:country":"US",
    "sg:address":"131 NE 4th St",
    "sg:city":"Moore",
    "sg:classifiers":[
        {
            "category":"Building & Trades",
            "subcategory":"Plumbing",
            "type":"Services"
        }
    ],
    "sg:phone":"+1 405 799 5841",
    "sg:postcode":"73160",
    "sg:province":"OK",
    "sg:tags":[
        "conditioning",
        "air",
        "system",
        "contractor"
    ],
    "wof:name":"Randall's Temperature Control",
    "wof:placetype":"venue"
},
  "geometry": {"coordinates":[-97.486183,35.342362],"type":"Point"}
}