{
  "type": "Feature",
  "properties": {
    "iso:country":"US",
    "sg:address":"10134 E 24th Pl",
    "sg:city":"Tulsa",
    "sg:classifiers":[
        {
            "category":"Communications",
            "subcategory":"Film & Video Production",
            "type":"Services"
        }
    ],
    "sg:phone":"+1 918 481 8464",
    "sg:postcode":"74129",
    "sg:province":"OK",
    "sg:tags":[
        "visual",
        "audio"
    ],
    "wof:name":"Paystyle Productions Inc",
    "wof:placetype":"venue"
},
  "geometry": {"coordinates":[-95.861333,36.126468],"type":"Point"}
}