{
  "type": "Feature",
  "properties": {
    "addr:full":"109 E Washington Ave Mcalester OK 74501",
    "addr:housenumber":"109",
    "addr:postcode":"74501",
    "addr:street":"E Washington Ave",
    "iso:country":"US",
    "sg:address":"109 E Washington Ave",
    "sg:city":"Mcalester",
    "sg:classifiers":[
        {
            "category":"Real Estate",
            "subcategory":"Real Estate Agent",
            "type":"Services"
        }
    ],
    "sg:phone":"+1 918 423 2245",
    "sg:postcode":"74501",
    "sg:province":"OK",
    "wof:name":"Allen Nixon Real Estate",
    "wof:placetype":"venue"
},
  "geometry": {"coordinates":[-95.768778,34.934396],"type":"Point"}
}