{
  "type": "Feature",
  "properties": {
    "iso:country":"US",
    "sg:address":"421 S Van Buren St",
    "sg:city":"Enid",
    "sg:classifiers":[
        {
            "category":"Organizations",
            "subcategory":"Community Association",
            "type":"Services"
        }
    ],
    "sg:phone":"+1 580 237 7345",
    "sg:postcode":"73703",
    "sg:province":"OK",
    "sg:tags":[
        "club"
    ],
    "wof:name":"Rendezvous Club & Cafe",
    "wof:placetype":"venue"
},
  "geometry": {"coordinates":[-97.890051,36.393311],"type":"Point"}
}