{
  "type": "Feature",
  "properties": {
    "iso:country":"US",
    "sg:address":"437 NW 5th St",
    "sg:city":"Oklahoma City",
    "sg:classifiers":[
        {
            "category":"Professional",
            "subcategory":"Lawyer & Legal Services",
            "type":"Services"
        }
    ],
    "sg:phone":"+1 405 848 5044",
    "sg:postcode":"73102",
    "sg:province":"OK",
    "sg:tags":[
        "attorney"
    ],
    "wof:name":"David M Dunlap",
    "wof:placetype":"venue"
},
  "geometry": {"coordinates":[-97.520641,35.47315],"type":"Point"}
}