{
  "type": "Feature",
  "properties": {
    "iso:country":"US",
    "sg:address":"4 E Main St",
    "sg:city":"Ardmore",
    "sg:classifiers":[
        {
            "category":"Wholesale",
            "subcategory":"Home Furnishings",
            "type":"Manufacturing & Wholesale Goods"
        }
    ],
    "sg:phone":"+1 580 223 6641",
    "sg:postcode":"73401",
    "sg:province":"OK",
    "wof:name":"Cook Paint Ardmore",
    "wof:placetype":"venue"
},
  "geometry": {"coordinates":[-97.12835699999999,34.172512],"type":"Point"}
}