{
  "type": "Feature",
  "properties": {
    "addr:full":"121 N Rangeline St Tecumseh OK 74873",
    "addr:housenumber":"121",
    "addr:postcode":"74873",
    "addr:street":"N Rangeline St",
    "iso:country":"US",
    "sg:address":"121 N Rangeline St",
    "sg:city":"Tecumseh",
    "sg:classifiers":[
        {
            "category":"Organizations",
            "subcategory":"Religious Organization",
            "type":"Services"
        }
    ],
    "sg:phone":"+1 405 598 2233",
    "sg:postcode":"74873",
    "sg:province":"OK",
    "wof:name":"First Free Will Baptist Church",
    "wof:placetype":"venue"
},
  "geometry": {"coordinates":[-96.93035500000001,35.258463],"type":"Point"}
}