{
  "type": "Feature",
  "properties": {
    "iso:country":"US",
    "sg:address":"1200 W Main St",
    "sg:city":"Hugo",
    "sg:classifiers":[
        {
            "category":"Social Services",
            "type":"Services"
        }
    ],
    "sg:phone":"+1 580 326 2161",
    "sg:postcode":"74743",
    "sg:province":"OK",
    "sg:tags":[
        "organization",
        "welfare"
    ],
    "wof:name":"Horace Mann Headstart Ctr",
    "wof:placetype":"venue"
},
  "geometry": {"coordinates":[-95.52757,34.008946],"type":"Point"}
}