{
  "type": "Feature",
  "properties": {
    "addr:full":"1509 US Hwy 81 Duncan OK 73533",
    "addr:housenumber":"1509",
    "addr:postcode":"73533",
    "addr:street":"Us Hwy 81",
    "iso:country":"US",
    "sg:address":"1509 US Hwy 81",
    "sg:city":"Duncan",
    "sg:classifiers":[
        {
            "category":"Shopping",
            "subcategory":"Department Store",
            "type":"Retail Goods"
        }
    ],
    "sg:phone":"+1 580 255 3695",
    "sg:postcode":"73533",
    "sg:province":"OK",
    "sg:website":"www.stagestores.com",
    "wof:name":"Stage",
    "wof:placetype":"venue"
},
  "geometry": {"coordinates":[-97.96682699999999,34.522971],"type":"Point"}
}