{
  "type": "Feature",
  "properties": {
    "iso:country":"US",
    "sg:address":"900 N Eastern Ave",
    "sg:city":"Moore",
    "sg:classifiers":[
        {
            "category":"Building & Trades",
            "subcategory":"Plumbing",
            "type":"Services"
        }
    ],
    "sg:phone":"+1 405 793 8363",
    "sg:postcode":"73160",
    "sg:province":"OK",
    "sg:tags":[
        "plumbing",
        "contractor"
    ],
    "wof:name":"Water Heater Man",
    "wof:placetype":"venue"
},
  "geometry": {"coordinates":[-97.476895,35.347441],"type":"Point"}
}