{
  "type": "Feature",
  "properties": {
    "addr:full":"3024 W 9th St Cushing OK 74023",
    "addr:housenumber":"3024",
    "addr:postcode":"74023",
    "addr:street":"W 9Th St",
    "iso:country":"US",
    "sg:address":"3024 W 9th St",
    "sg:city":"Cushing",
    "sg:classifiers":[
        {
            "category":"Building & Trades",
            "subcategory":"Construction",
            "type":"Services"
        }
    ],
    "sg:phone":"+1 918 225 2202",
    "sg:postcode":"74023",
    "sg:province":"OK",
    "sg:tags":[
        "excavating",
        "contractor"
    ],
    "wof:name":"LBJ Construction",
    "wof:placetype":"venue"
},
  "geometry": {"coordinates":[-96.81059999999999,35.971277],"type":"Point"}
}