{
  "type": "Feature",
  "properties": {
    "iso:country":"US",
    "sg:address":"2208 W South Ave",
    "sg:city":"Ponca City",
    "sg:classifiers":[
        {
            "category":"Retail",
            "subcategory":"Auto Repair",
            "type":"Services"
        }
    ],
    "sg:phone":"+1 580 765 4686",
    "sg:postcode":"74601",
    "sg:province":"OK",
    "sg:tags":[
        "general"
    ],
    "wof:name":"Pioneer Hydraulics",
    "wof:placetype":"venue"
},
  "geometry": {"coordinates":[-97.109856,36.695249],"type":"Point"}
}