{
  "type": "Feature",
  "properties": {
    "iso:country":"US",
    "sg:address":"105 Sutton Cir",
    "sg:city":"Oklahoma City",
    "sg:classifiers":[
        {
            "category":"Professional",
            "subcategory":"Business Services",
            "type":"Services"
        }
    ],
    "sg:phone":"+1 405 793 1843",
    "sg:postcode":"73160",
    "sg:province":"OK",
    "sg:tags":[
        "fund",
        "raising"
    ],
    "wof:name":"Therdale Farms",
    "wof:placetype":"venue"
},
  "geometry": {"coordinates":[-97.49201100000001,35.349909],"type":"Point"}
}