{
  "type": "Feature",
  "properties": {
    "addr:full":"409 S Central Ave Idabel OK 74745",
    "addr:housenumber":"409",
    "addr:postcode":"74745",
    "addr:street":"S Central Ave",
    "iso:country":"US",
    "sg:address":"409 S Central Ave",
    "sg:city":"Idabel",
    "sg:classifiers":[
        {
            "category":"Shopping",
            "subcategory":"Musical Instruments",
            "type":"Retail Goods"
        }
    ],
    "sg:phone":"+1 580 286 5420",
    "sg:postcode":"74745",
    "sg:province":"OK",
    "wof:name":"Unk's Strings & Things",
    "wof:placetype":"venue"
},
  "geometry": {"coordinates":[-94.82606699999999,33.891909],"type":"Point"}
}