{
  "type": "Feature",
  "properties": {
    "iso:country":"US",
    "sg:address":"4201 N Midwest Blvd",
    "sg:city":"Oklahoma City",
    "sg:classifiers":[
        {
            "category":"Building & Trades",
            "subcategory":"Construction",
            "type":"Services"
        }
    ],
    "sg:phone":"+1 405 771 8236",
    "sg:postcode":"73141",
    "sg:province":"OK",
    "sg:tags":[
        "roofing",
        "contractor"
    ],
    "wof:name":"Northeast Roofing",
    "wof:placetype":"venue"
},
  "geometry": {"coordinates":[-97.388743,35.512106],"type":"Point"}
}