{
  "type": "Feature",
  "properties": {
    "iso:country":"US",
    "sg:address":"3124 SW 41st St",
    "sg:city":"Oklahoma City",
    "sg:classifiers":[
        {
            "category":"Building & Trades",
            "subcategory":"Construction",
            "type":"Services"
        }
    ],
    "sg:phone":"+1 405 550 1492",
    "sg:postcode":"73119",
    "sg:province":"OK",
    "sg:tags":[
        "handyman"
    ],
    "wof:name":"Tony's Handyman Svc",
    "wof:placetype":"venue"
},
  "geometry": {"coordinates":[-97.574017,35.423774],"type":"Point"}
}