{
  "type": "Feature",
  "properties": {
    "addr:full":"4100 Nicole Pl Norman OK 73072",
    "addr:housenumber":"4100",
    "addr:postcode":"73072",
    "addr:street":"Nicole Pl",
    "iso:country":"US",
    "sg:address":"4100 Nicole Pl",
    "sg:city":"Norman",
    "sg:classifiers":[
        {
            "category":"Professional",
            "subcategory":"Engineering",
            "type":"Services"
        }
    ],
    "sg:phone":"+1 405 364 1209",
    "sg:postcode":"73072",
    "sg:province":"OK",
    "sg:tags":[
        "consultant",
        "industrial",
        "ergonomics"
    ],
    "wof:name":"Kimberly G Wolfinbarger",
    "wof:placetype":"venue"
},
  "geometry": {"coordinates":[-97.501712,35.268457],"type":"Point"}
}