{
  "type": "Feature",
  "properties": {
    "iso:country":"US",
    "sg:address":"1421 N Main St",
    "sg:city":"Guymon",
    "sg:classifiers":[
        {
            "category":"Autos & Motor Vehicles",
            "subcategory":"Automobile Sales",
            "type":"Retail Goods"
        }
    ],
    "sg:phone":"+1 580 338 2471",
    "sg:postcode":"73942",
    "sg:province":"OK",
    "sg:tags":[
        "car",
        "dealer"
    ],
    "wof:name":"Sierra Motor Co",
    "wof:placetype":"venue"
},
  "geometry": {"coordinates":[-101.48151,36.69214],"type":"Point"}
}