{
  "type": "Feature",
  "properties": {
    "iso:country":"US",
    "sg:address":"128 S Main St",
    "sg:city":"Newkirk",
    "sg:classifiers":[
        {
            "category":"Professional",
            "subcategory":"Lawyer & Legal Services",
            "type":"Services"
        }
    ],
    "sg:phone":"+1 580 362 9996",
    "sg:postcode":"74647",
    "sg:province":"OK",
    "sg:tags":[
        "attorney"
    ],
    "wof:name":"Salisbury Law Office",
    "wof:placetype":"venue"
},
  "geometry": {"coordinates":[-97.053545,36.882026],"type":"Point"}
}