{
  "type": "Feature",
  "properties": {
    "addr:full":"4921 E 3rd St Tulsa OK 74112",
    "addr:housenumber":"4921",
    "addr:postcode":"74112",
    "addr:street":"E 3Rd St",
    "iso:country":"US",
    "sg:address":"4921 E 3rd St",
    "sg:city":"Tulsa",
    "sg:classifiers":[
        {
            "category":"Building & Trades",
            "subcategory":"Landscaping Services",
            "type":"Services"
        }
    ],
    "sg:phone":"+1 918 834 2785",
    "sg:postcode":"74112",
    "sg:province":"OK",
    "sg:tags":[
        "landscape",
        "contractor"
    ],
    "wof:name":"Campbell Landscape Co",
    "wof:placetype":"venue"
},
  "geometry": {"coordinates":[-95.92065599999999,36.157455],"type":"Point"}
}