{
  "type": "Feature",
  "properties": {
    "iso:country":"US",
    "sg:address":"4921 E 3rd St",
    "sg:city":"Tulsa",
    "sg:classifiers":[
        {
            "category":"Building & Trades",
            "subcategory":"Landscaping Services",
            "type":"Services"
        }
    ],
    "sg:phone":"+1 918 834 2785",
    "sg:postcode":"74112",
    "sg:province":"OK",
    "sg:tags":[
        "landscape",
        "contractor"
    ],
    "wof:name":"Campbell Landscape Co",
    "wof:placetype":"venue"
},
  "geometry": {"coordinates":[-95.920656,36.157455],"type":"Point"}
}