{
  "type": "Feature",
  "properties": {
    "iso:country":"US",
    "sg:address":"301 W Main St",
    "sg:city":"Norman",
    "sg:classifiers":[
        {
            "category":"Wholesale",
            "subcategory":"Durable Goods & Equipment",
            "type":"Manufacturing & Wholesale Goods"
        }
    ],
    "sg:phone":"+1 405 447 1515",
    "sg:postcode":"73069",
    "sg:province":"OK",
    "sg:tags":[
        "importer"
    ],
    "wof:name":"Mexico City Imports",
    "wof:placetype":"venue"
},
  "geometry": {"coordinates":[-97.448088,35.218931],"type":"Point"}
}