{
  "type": "Feature",
  "properties": {
    "iso:country":"US",
    "sg:address":"8189 E 44th St",
    "sg:city":"Tulsa",
    "sg:classifiers":[
        {
            "category":"Building & Trades",
            "subcategory":"Construction",
            "type":"Services"
        }
    ],
    "sg:phone":"+1 918 664 4707",
    "sg:postcode":"74145",
    "sg:province":"OK",
    "sg:tags":[
        "contractor"
    ],
    "wof:name":"Lassiter Richey Co",
    "wof:placetype":"venue"
},
  "geometry": {"coordinates":[-95.881675,36.099511],"type":"Point"}
}