{
  "type": "Feature",
  "properties": {
    "iso:country":"US",
    "sg:address":"711 W 9th St",
    "sg:city":"Hobart",
    "sg:classifiers":[
        {
            "category":"Manufacturing",
            "subcategory":"Tools & Machinery",
            "type":"Manufacturing & Wholesale Goods"
        }
    ],
    "sg:phone":"+1 580 726 5601",
    "sg:postcode":"73651",
    "sg:province":"OK",
    "sg:tags":[
        "bearing",
        "mfg",
        "anti",
        "friction",
        "seal"
    ],
    "wof:name":"SKF USA Inc",
    "wof:placetype":"venue"
},
  "geometry": {"coordinates":[-99.099198,35.017952],"type":"Point"}
}