{
  "type": "Feature",
  "properties": {
    "iso:country":"US",
    "sg:address":"6519 E Pine Pl",
    "sg:city":"Tulsa",
    "sg:classifiers":[
        {
            "category":"Restaurant",
            "type":"Food & Drink"
        }
    ],
    "sg:phone":"+1 918 834 7507",
    "sg:postcode":"74115",
    "sg:province":"OK",
    "sg:tags":[
        "eating"
    ],
    "wof:name":"Jody and Walts Place",
    "wof:placetype":"venue"
},
  "geometry": {"coordinates":[-95.90325900000001,36.178055],"type":"Point"}
}