{
  "type": "Feature",
  "properties": {
    "iso:country":"US",
    "sg:address":"504 E Elm Ave",
    "sg:city":"Eufaula",
    "sg:classifiers":[
        {
            "category":"Retail",
            "subcategory":"Laundry & Dry Cleaning",
            "type":"Services"
        }
    ],
    "sg:phone":"+1 918 689 5491",
    "sg:postcode":"74432",
    "sg:province":"OK",
    "wof:name":"Bubs Carpet Service",
    "wof:placetype":"venue"
},
  "geometry": {"coordinates":[-95.572273,35.290147],"type":"Point"}
}