{
  "type": "Feature",
  "properties": {
    "addr:full":"601 E Kenosha St Broken Arrow OK 74012",
    "addr:housenumber":"601",
    "addr:postcode":"74012",
    "addr:street":"E Kenosha St",
    "iso:country":"US",
    "sg:address":"601 E Kenosha St",
    "sg:city":"Broken Arrow",
    "sg:classifiers":[
        {
            "category":"Banks & Credit Unions",
            "subcategory":"Bank",
            "type":"Services"
        }
    ],
    "sg:phone":"+1 918 251 8596",
    "sg:postcode":"74012",
    "sg:province":"OK",
    "sg:tags":[
        "loan",
        "real estate"
    ],
    "wof:name":"Farm Credit Svc",
    "wof:placetype":"venue"
},
  "geometry": {"coordinates":[-95.78465199999999,36.061093],"type":"Point"}
}