{
  "type": "Feature",
  "properties": {
    "iso:country":"US",
    "sg:address":"1 W 3rd St",
    "sg:city":"Tulsa",
    "sg:classifiers":[
        {
            "category":"Real Estate",
            "subcategory":"Architect",
            "type":"Services"
        }
    ],
    "sg:phone":"+1 918 582 8771",
    "sg:postcode":"74103",
    "sg:province":"OK",
    "sg:tags":[
        "development",
        "specializing"
    ],
    "wof:name":"Bsw",
    "wof:placetype":"venue"
},
  "geometry": {"coordinates":[-95.991171,36.153331],"type":"Point"}
}