{
  "type": "Feature",
  "properties": {
    "addr:full":"2825 S Broadway Edmond OK 73013",
    "addr:housenumber":"2825",
    "addr:postcode":"73013",
    "addr:street":"S Broadway",
    "iso:country":"US",
    "sg:address":"2825 S Broadway",
    "sg:city":"Edmond",
    "sg:classifiers":[
        {
            "category":"Retail",
            "subcategory":"Veterinary Services",
            "type":"Services"
        }
    ],
    "sg:phone":"+1 405 341 0000",
    "sg:postcode":"73013",
    "sg:province":"OK",
    "sg:tags":[
        "veterinarian"
    ],
    "wof:name":"All Care Pet Hospital",
    "wof:placetype":"venue"
},
  "geometry": {"coordinates":[-97.48483299999999,35.626973],"type":"Point"}
}