{
  "type": "Feature",
  "properties": {
    "iso:country":"US",
    "sg:address":"3211 S Lakewood Ave",
    "sg:city":"Tulsa",
    "sg:classifiers":[
        {
            "category":"Professional",
            "subcategory":"Business Services",
            "type":"Services"
        }
    ],
    "sg:phone":"+1 918 492 1273",
    "sg:postcode":"74135",
    "sg:province":"OK",
    "sg:tags":[
        "sales",
        "estate"
    ],
    "wof:name":"Connie Fletcher",
    "wof:placetype":"venue"
},
  "geometry": {"coordinates":[-95.908289,36.117742],"type":"Point"}
}