{
  "type": "Feature",
  "properties": {
    "iso:country":"US",
    "sg:address":"5079 E 51st St",
    "sg:city":"Tulsa",
    "sg:classifiers":[
        {
            "category":"Banks & Credit Unions",
            "subcategory":"Bank",
            "type":"Services"
        }
    ],
    "sg:phone":"+1 918 270 4050",
    "sg:postcode":"74135",
    "sg:province":"OK",
    "sg:tags":[
        "loan"
    ],
    "wof:name":"Triple A Blazer Loan Co",
    "wof:placetype":"venue"
},
  "geometry": {"coordinates":[-95.921629,36.089905],"type":"Point"}
}