{
  "type": "Feature",
  "properties": {
    "addr:full":"2311 Red Wheat Dr Clinton OK 73601",
    "addr:housenumber":"2311",
    "addr:postcode":"73601",
    "addr:street":"Red Wheat Dr",
    "iso:country":"US",
    "sg:address":"2311 Red Wheat Dr",
    "sg:city":"Clinton",
    "sg:classifiers":[
        {
            "category":"Restaurant",
            "type":"Food & Drink"
        }
    ],
    "sg:menulink":"http://www.allmenus.com/ok/clinton/200140-long-john-silvers/menu/",
    "sg:phone":"+1 580 323 6499",
    "sg:postcode":"73601",
    "sg:province":"OK",
    "sg:tags":[
        "seafood",
        "american"
    ],
    "wof:name":"Long John Silver's",
    "wof:placetype":"venue"
},
  "geometry": {"coordinates":[-98.987579,35.501124],"type":"Point"}
}