{
  "type": "Feature",
  "properties": {
    "iso:country":"US",
    "sg:address":"2902 N Broadway St",
    "sg:city":"Poteau",
    "sg:classifiers":[
        {
            "category":"Travel",
            "subcategory":"Hotels & Motels",
            "type":"Entertainment"
        }
    ],
    "sg:phone":"+1 918 647 3995",
    "sg:postcode":"74953",
    "sg:province":"OK",
    "wof:name":"Green Country Motor Inn",
    "wof:placetype":"venue"
},
  "geometry": {"coordinates":[-94.630409,35.086925],"type":"Point"}
}