{
  "type": "Feature",
  "properties": {
    "iso:country":"US",
    "sg:address":"10505 Lakeside Dr",
    "sg:city":"Oklahoma City",
    "sg:classifiers":[
        {
            "category":"Building & Trades",
            "subcategory":"Plumbing",
            "type":"Services"
        }
    ],
    "sg:phone":"+1 405 752 1837",
    "sg:postcode":"73120",
    "sg:province":"OK",
    "sg:tags":[
        "repair",
        "heating",
        "maintenance",
        "system"
    ],
    "wof:name":"Ellingworth Heating & AC",
    "wof:placetype":"venue"
},
  "geometry": {"coordinates":[-97.57049000000001,35.573682],"type":"Point"}
}