{
  "type": "Feature",
  "properties": {
    "iso:country":"US",
    "sg:address":"1107 Quail Creek Dr",
    "sg:city":"Enid",
    "sg:classifiers":[
        {
            "category":"Professional",
            "subcategory":"Computer Services",
            "type":"Services"
        }
    ],
    "sg:phone":"+1 580 237 3699",
    "sg:postcode":"73703",
    "sg:province":"OK",
    "sg:tags":[
        "development",
        "software"
    ],
    "wof:name":"Jcclorg",
    "wof:placetype":"venue"
},
  "geometry": {"coordinates":[-97.927557,36.40861],"type":"Point"}
}