{
  "type": "Feature",
  "properties": {
    "addr:full":"2101 N Yellowood Ave Broken Arrow OK 74012",
    "addr:housenumber":"2101",
    "addr:postcode":"74012",
    "addr:street":"N Yellowood Ave",
    "iso:country":"US",
    "sg:address":"2101 N Yellowood Ave",
    "sg:city":"Broken Arrow",
    "sg:classifiers":[
        {
            "category":"Wholesale",
            "subcategory":"Machinery & Supplies",
            "type":"Manufacturing & Wholesale Goods"
        }
    ],
    "sg:phone":"+1 918 252 0241",
    "sg:postcode":"74012",
    "sg:province":"OK",
    "sg:tags":[
        "equipment",
        "safety",
        "clothing"
    ],
    "wof:name":"Industrial & Safety Eyewear",
    "wof:placetype":"venue"
},
  "geometry": {"coordinates":[-95.84036999999999,36.071534],"type":"Point"}
}