{
  "type": "Feature",
  "properties": {
    "addr:full":"1301 S Rock Island Ave El Reno OK 73036",
    "addr:housenumber":"1301",
    "addr:postcode":"73036",
    "addr:street":"S Rock Island Ave",
    "iso:country":"US",
    "sg:address":"1301 S Rock Island Ave",
    "sg:city":"El Reno",
    "sg:classifiers":[
        {
            "category":"Shopping",
            "subcategory":"Used Merchandise",
            "type":"Retail Goods"
        }
    ],
    "sg:phone":"+1 405 262 2226",
    "sg:postcode":"73036",
    "sg:province":"OK",
    "sg:tags":[
        "appliance"
    ],
    "wof:name":"Pioneer Painting",
    "wof:placetype":"venue"
},
  "geometry": {"coordinates":[-97.95258699999999,35.522301],"type":"Point"}
}