{
  "type": "Feature",
  "properties": {
    "iso:country":"US",
    "sg:address":"3963 State Hwy 97",
    "sg:city":"Sand Springs",
    "sg:classifiers":[
        {
            "category":"Professional",
            "subcategory":"Engineering",
            "type":"Services"
        }
    ],
    "sg:phone":"+1 918 688 2299",
    "sg:postcode":"74063",
    "sg:province":"OK",
    "sg:tags":[
        "development",
        "research"
    ],
    "wof:name":"Schuermann Enterprises Inc",
    "wof:placetype":"venue"
},
  "geometry": {"coordinates":[-96.117066,36.106093],"type":"Point"}
}