{
  "type": "Feature",
  "properties": {
    "iso:country":"US",
    "sg:address":"408 E Washington St",
    "sg:city":"Broken Arrow",
    "sg:classifiers":[
        {
            "category":"Freight",
            "type":"Transportation"
        }
    ],
    "sg:phone":"+1 918 251 4358",
    "sg:postcode":"74012",
    "sg:province":"OK",
    "sg:tags":[
        "operator",
        "local",
        "trucking"
    ],
    "wof:name":"David D Irvin Trucking",
    "wof:placetype":"venue"
},
  "geometry": {"coordinates":[-95.782358,36.031996],"type":"Point"}
}