{
  "type": "Feature",
  "properties": {
    "iso:country":"US",
    "sg:address":"501 N Rockwell Ave",
    "sg:city":"Oklahoma City",
    "sg:classifiers":[
        {
            "category":"Restaurant",
            "type":"Food & Drink"
        }
    ],
    "sg:phone":"+1 405 787 2776",
    "sg:postcode":"73127",
    "sg:province":"OK",
    "wof:name":"Mai Noodle House",
    "wof:placetype":"venue"
},
  "geometry": {"coordinates":[-97.63664,35.472688],"type":"Point"}
}