{
  "type": "Feature",
  "properties": {
    "iso:country":"US",
    "sg:address":"2331 N Main St",
    "sg:city":"Miami",
    "sg:classifiers":[
        {
            "category":"Building & Trades",
            "subcategory":"Equipment Rental",
            "type":"Services"
        }
    ],
    "sg:phone":"+1 918 540 2433",
    "sg:postcode":"74354",
    "sg:province":"OK",
    "sg:tags":[
        "yard"
    ],
    "wof:name":"Color Tyme",
    "wof:placetype":"venue"
},
  "geometry": {"coordinates":[-94.877593,36.902136],"type":"Point"}
}