{
  "type": "Feature",
  "properties": {
    "iso:country":"US",
    "sg:address":"4143 E 31st St",
    "sg:city":"Tulsa",
    "sg:classifiers":[
        {
            "category":"Professional",
            "subcategory":"Lawyer & Legal Services",
            "type":"Services"
        }
    ],
    "sg:phone":"+1 918 743 4400",
    "sg:postcode":"74135",
    "sg:province":"OK",
    "sg:tags":[
        "attorney"
    ],
    "wof:name":"Sandra L Tolliver",
    "wof:placetype":"venue"
},
  "geometry": {"coordinates":[-95.927883,36.118933],"type":"Point"}
}