{
  "type": "Feature",
  "properties": {
    "iso:country":"US",
    "sg:address":"121 W Charlotte St",
    "sg:city":"Broken Arrow",
    "sg:classifiers":[
        {
            "category":"Professional",
            "subcategory":"Business Services",
            "type":"Services"
        }
    ],
    "sg:phone":"+1 918 451 4236",
    "sg:postcode":"74011",
    "sg:province":"OK",
    "wof:name":"M & N Group Inc",
    "wof:placetype":"venue"
},
  "geometry": {"coordinates":[-95.791935,35.981465],"type":"Point"}
}