{
  "type": "Feature",
  "properties": {
    "addr:full":"2101 N Lincoln Blvd Oklahoma City OK 73105",
    "addr:housenumber":"2101",
    "addr:postcode":"73105",
    "addr:street":"N Lincoln Blvd",
    "iso:country":"US",
    "sg:address":"2101 N Lincoln Blvd",
    "sg:city":"Oklahoma City",
    "sg:classifiers":[
        {
            "category":"Government",
            "subcategory":"Office",
            "type":"Public Place"
        }
    ],
    "sg:phone":"+1 405 521 3082",
    "sg:postcode":"73105",
    "sg:province":"OK",
    "sg:tags":[
        "program",
        "administrative"
    ],
    "wof:name":"Latin American/Hispanic Affair",
    "wof:placetype":"venue"
},
  "geometry": {"coordinates":[-97.50407199999999,35.489477],"type":"Point"}
}