{
  "type": "Feature",
  "properties": {
    "addr:full":"1308 SE Frank Phillips Blvd Bartlesville OK 74003",
    "addr:housenumber":"1308",
    "addr:postcode":"74003",
    "addr:street":"Se Frank Phillips Blvd",
    "iso:country":"US",
    "sg:address":"1308 SE Frank Phillips Blvd",
    "sg:city":"Bartlesville",
    "sg:classifiers":[
        {
            "category":"Retail",
            "subcategory":"Auto Repair",
            "type":"Services"
        }
    ],
    "sg:phone":"+1 918 337 9339",
    "sg:postcode":"74003",
    "sg:province":"OK",
    "sg:tags":[
        "glass",
        "coating",
        "tinting"
    ],
    "wof:name":"Pro-Tint",
    "wof:placetype":"venue"
},
  "geometry": {"coordinates":[-95.962692,36.750791],"type":"Point"}
}