{
  "type": "Feature",
  "properties": {
    "addr:full":"1002 SW D Ave Lawton OK 73501",
    "addr:housenumber":"1002",
    "addr:postcode":"73501",
    "addr:street":"Sw D Ave",
    "iso:country":"US",
    "sg:address":"1002 SW D Ave",
    "sg:city":"Lawton",
    "sg:classifiers":[
        {
            "category":"Shopping",
            "subcategory":"Used Merchandise",
            "type":"Retail Goods"
        }
    ],
    "sg:phone":"+1 580 581 1540",
    "sg:postcode":"73501",
    "sg:province":"OK",
    "sg:tags":[
        "antique"
    ],
    "wof:name":"Telaines Antiques",
    "wof:placetype":"venue"
},
  "geometry": {"coordinates":[-98.404759,34.603973],"type":"Point"}
}