{
  "type": "Feature",
  "properties": {
    "iso:country":"US",
    "sg:address":"8937 S May Ave",
    "sg:city":"Oklahoma City",
    "sg:classifiers":[
        {
            "category":"Autos & Motor Vehicles",
            "subcategory":"Fuel & Gas Station",
            "type":"Retail Goods"
        }
    ],
    "sg:phone":"+1 405 685 5745",
    "sg:postcode":"73159",
    "sg:province":"OK",
    "sg:tags":[
        "station",
        "gasoline"
    ],
    "wof:name":"Q Mart Conoco",
    "wof:placetype":"venue"
},
  "geometry": {"coordinates":[-97.56556500000001,35.368068],"type":"Point"}
}