{
  "type": "Feature",
  "properties": {
    "addr:full":"917 Arlington St Ada OK 74820",
    "addr:housenumber":"917",
    "addr:postcode":"74820",
    "addr:street":"Arlington St",
    "iso:country":"US",
    "sg:address":"917 Arlington St",
    "sg:city":"Ada",
    "sg:classifiers":[
        {
            "category":"Health Services",
            "subcategory":"Clinic",
            "type":"Services"
        }
    ],
    "sg:phone":"+1 580 436 2266",
    "sg:postcode":"74820",
    "sg:province":"OK",
    "sg:tags":[
        "home",
        "care"
    ],
    "wof:name":"At Home In Oklahoma",
    "wof:placetype":"venue"
},
  "geometry": {"coordinates":[-96.664879,34.781581],"type":"Point"}
}