{
  "type": "Feature",
  "properties": {
    "addr:full":"611 W Highpoint Dr Stillwater OK 74075",
    "addr:housenumber":"611",
    "addr:postcode":"74075",
    "addr:street":"W Highpoint Dr",
    "iso:country":"US",
    "sg:address":"611 W Highpoint Dr",
    "sg:city":"Stillwater",
    "sg:classifiers":[
        {
            "category":"Real Estate",
            "subcategory":"Surveying",
            "type":"Services"
        }
    ],
    "sg:phone":"+1 405 377 2394",
    "sg:postcode":"74075",
    "sg:province":"OK",
    "sg:tags":[
        "surveyor"
    ],
    "wof:name":"Land Surveying Svc",
    "wof:placetype":"venue"
},
  "geometry": {"coordinates":[-97.065208,36.141527],"type":"Point"}
}