{
  "type": "Feature",
  "properties": {
    "iso:country":"US",
    "sg:address":"458 S Main St",
    "sg:city":"Mcalester",
    "sg:classifiers":[
        {
            "category":"Autos & Motor Vehicles",
            "subcategory":"Automobile Sales",
            "type":"Retail Goods"
        }
    ],
    "sg:phone":"+1 918 423 0850",
    "sg:postcode":"74501",
    "sg:province":"OK",
    "sg:tags":[
        "car",
        "dealer"
    ],
    "wof:name":"Kelly Motor Co",
    "wof:placetype":"venue"
},
  "geometry": {"coordinates":[-95.769588,34.931633],"type":"Point"}
}