{
  "type": "Feature",
  "properties": {
    "iso:country":"US",
    "sg:address":"20 W 2nd St",
    "sg:city":"Sand Springs",
    "sg:classifiers":[
        {
            "category":"Professional",
            "subcategory":"Engineering",
            "type":"Services"
        }
    ],
    "sg:phone":"+1 918 241 2803",
    "sg:postcode":"74063",
    "sg:province":"OK",
    "sg:tags":[
        "engineer"
    ],
    "sg:website":"www.meshekengr.com",
    "wof:name":"Meshek & Assoc Inc",
    "wof:placetype":"venue"
},
  "geometry": {"coordinates":[-96.110406,36.13835],"type":"Point"}
}