{
  "type": "Feature",
  "properties": {
    "iso:country":"US",
    "sg:address":"403 E Roh St",
    "sg:city":"Thomas",
    "sg:classifiers":[
        {
            "category":"Farming",
            "subcategory":"Farm & Veterinary Services",
            "type":"Manufacturing & Wholesale Goods"
        }
    ],
    "sg:phone":"+1 580 661 2338",
    "sg:postcode":"73669",
    "sg:province":"OK",
    "sg:tags":[
        "crop",
        "harvesting"
    ],
    "wof:name":"Randy Dobbins Harvesting",
    "wof:placetype":"venue"
},
  "geometry": {"coordinates":[-98.742947,35.751057],"type":"Point"}
}