{
  "type": "Feature",
  "properties": {
    "iso:country":"US",
    "sg:address":"140 E Main St",
    "sg:city":"Tishomingo",
    "sg:classifiers":[
        {
            "category":"Shopping",
            "subcategory":"Pharmacy",
            "type":"Retail Goods"
        }
    ],
    "sg:phone":"+1 580 371 2355",
    "sg:postcode":"73460",
    "sg:province":"OK",
    "sg:tags":[
        "drug",
        "store"
    ],
    "wof:name":"Gene Lafitte Pharmacy Inc",
    "wof:placetype":"venue"
},
  "geometry": {"coordinates":[-96.676913,34.23438],"type":"Point"}
}