{
  "type": "Feature",
  "properties": {
    "iso:country":"US",
    "sg:address":"730 W Wilshire Blvd",
    "sg:city":"Oklahoma City",
    "sg:classifiers":[
        {
            "category":"Wholesale",
            "subcategory":"Non-durable Goods",
            "type":"Manufacturing & Wholesale Goods"
        }
    ],
    "sg:phone":"+1 405 848 3193",
    "sg:postcode":"73116",
    "sg:province":"OK",
    "sg:tags":[
        "printing",
        "commercial"
    ],
    "wof:name":"McDowell Incentives Inc",
    "wof:placetype":"venue"
},
  "geometry": {"coordinates":[-97.523647,35.551045],"type":"Point"}
}