{
  "type": "Feature",
  "properties": {
    "iso:country":"US",
    "sg:address":"217 W 5th Ave",
    "sg:city":"Stillwater",
    "sg:classifiers":[
        {
            "category":"Government",
            "subcategory":"Office",
            "type":"Public Place"
        }
    ],
    "sg:phone":"+1 405 372 7387",
    "sg:postcode":"74074",
    "sg:province":"OK",
    "sg:tags":[
        "state",
        "program"
    ],
    "wof:name":"Environmental Quality Dept",
    "wof:placetype":"venue"
},
  "geometry": {"coordinates":[-97.060141,36.116659],"type":"Point"}
}