{
  "type": "Feature",
  "properties": {
    "iso:country":"US",
    "sg:address":"4118 S 25th West Ave",
    "sg:city":"Tulsa",
    "sg:classifiers":[
        {
            "category":"Manufacturing",
            "subcategory":"Printing",
            "type":"Manufacturing & Wholesale Goods"
        }
    ],
    "sg:phone":"+1 918 446 7069",
    "sg:postcode":"74107",
    "sg:province":"OK",
    "sg:tags":[
        "printer"
    ],
    "wof:name":"Big Red Printing",
    "wof:placetype":"venue"
},
  "geometry": {"coordinates":[-96.02057,36.104066],"type":"Point"}
}