{
  "type": "Feature",
  "properties": {
    "addr:full":"4518 SE 29th St Oklahoma City OK 73115",
    "addr:housenumber":"4518",
    "addr:postcode":"73115",
    "addr:street":"Se 29Th St",
    "iso:country":"US",
    "sg:address":"4518 SE 29th St",
    "sg:city":"Oklahoma City",
    "sg:classifiers":[
        {
            "category":"Restaurant",
            "type":"Food & Drink"
        }
    ],
    "sg:menulink":"http://www.allmenus.com/ok/oklahoma-city/164429-wendys/menu/",
    "sg:phone":"+1 405 672 7394",
    "sg:postcode":"73115",
    "sg:province":"OK",
    "sg:tags":[
        "burger",
        "american",
        "soup"
    ],
    "wof:name":"Wendy's",
    "wof:placetype":"venue"
},
  "geometry": {"coordinates":[-97.435917,35.434706],"type":"Point"}
}