{
  "type": "Feature",
  "properties": {
    "addr:full":"13800 Benson Rd Edmond OK 73013",
    "addr:housenumber":"13800",
    "addr:postcode":"73013",
    "addr:street":"Benson Rd",
    "iso:country":"US",
    "sg:address":"13800 Benson Rd",
    "sg:city":"Edmond",
    "sg:classifiers":[
        {
            "category":"Professional",
            "subcategory":"Computer Services",
            "type":"Services"
        }
    ],
    "sg:phone":"+1 405 936 2500",
    "sg:postcode":"73013",
    "sg:province":"OK",
    "sg:tags":[
        "consulting"
    ],
    "wof:name":"Vialink Company",
    "wof:placetype":"venue"
},
  "geometry": {"coordinates":[-97.464872,35.613317],"type":"Point"}
}