{
  "type": "Feature",
  "properties": {
    "iso:country":"US",
    "sg:address":"8222 E 103rd St Ste 130",
    "sg:city":"Tulsa",
    "sg:classifiers":[
        {
            "category":"Professional",
            "type":"Services"
        },
        {
            "category":"Restaurant",
            "type":"Food & Drink"
        }
    ],
    "sg:phone":"+1 918 366 4777",
    "sg:postcode":"74133",
    "sg:province":"OK",
    "sg:tags":[
        "caterer",
        "pizza"
    ],
    "wof:name":"Hideaway Pizza",
    "wof:placetype":"venue"
},
  "geometry": {"coordinates":[-95.885084,36.013722],"type":"Point"}
}