{
  "type": "Feature",
  "properties": {
    "iso:country":"US",
    "sg:address":"6431 Avondale Dr",
    "sg:city":"Oklahoma City",
    "sg:classifiers":[
        {
            "category":"Travel",
            "subcategory":"Travel Agent",
            "type":"Entertainment"
        }
    ],
    "sg:phone":"+1 405 843 9447",
    "sg:postcode":"73116",
    "sg:province":"OK",
    "sg:tags":[
        "agency"
    ],
    "wof:name":"Journey House Travel Amercn Ex",
    "wof:placetype":"venue"
},
  "geometry": {"coordinates":[-97.530017,35.537442],"type":"Point"}
}