{
  "type": "Feature",
  "properties": {
    "addr:full":"1930 Church Ave Harrah OK 73045",
    "addr:housenumber":"1930",
    "addr:postcode":"73045",
    "addr:street":"Church Ave",
    "iso:country":"US",
    "sg:address":"1930 Church Ave",
    "sg:city":"Harrah",
    "sg:classifiers":[
        {
            "category":"Education",
            "subcategory":"Library",
            "type":"Public Place"
        }
    ],
    "sg:phone":"+1 405 454 2001",
    "sg:postcode":"73045",
    "sg:province":"OK",
    "wof:name":"Harrah Library",
    "wof:placetype":"venue"
},
  "geometry": {"coordinates":[-97.164873,35.490588],"type":"Point"}
}