{
  "type": "Feature",
  "properties": {
    "iso:country":"US",
    "sg:address":"920 E Broadway St",
    "sg:city":"Altus",
    "sg:classifiers":[
        {
            "category":"Retail",
            "subcategory":"Auto Repair",
            "type":"Services"
        }
    ],
    "sg:phone":"+1 580 482 8606",
    "sg:postcode":"73521",
    "sg:province":"OK",
    "sg:tags":[
        "muffler",
        "exhaust",
        "system"
    ],
    "wof:name":"Johnson Auto Care",
    "wof:placetype":"venue"
},
  "geometry": {"coordinates":[-99.322881,34.637719],"type":"Point"}
}