{
  "type": "Feature",
  "properties": {
    "iso:country":"US",
    "sg:address":"2426 N 32nd St",
    "sg:city":"Muskogee",
    "sg:classifiers":[
        {
            "category":"Manufacturing",
            "subcategory":"Retail Goods",
            "type":"Manufacturing & Wholesale Goods"
        }
    ],
    "sg:phone":"+1 918 686 8788",
    "sg:postcode":"74401",
    "sg:province":"OK",
    "sg:tags":[
        "product",
        "merchandise",
        "mfg"
    ],
    "wof:name":"Sentury Candle Company",
    "wof:placetype":"venue"
},
  "geometry": {"coordinates":[-95.402397,35.774365],"type":"Point"}
}