{
  "type": "Feature",
  "properties": {
    "addr:full":"11021 E 71st St Tulsa OK 74133",
    "addr:housenumber":"11021",
    "addr:postcode":"74133",
    "addr:street":"E 71St St",
    "iso:country":"US",
    "sg:address":"11021 E 71st St",
    "sg:city":"Tulsa",
    "sg:classifiers":[
        {
            "category":"Restaurant",
            "type":"Food & Drink"
        }
    ],
    "sg:menulink":"http://www.allmenus.com/ok/tulsa/98463-carrabbas/menu/",
    "sg:phone":"+1 918 254 8888",
    "sg:postcode":"74133",
    "sg:province":"OK",
    "sg:tags":[
        "italian"
    ],
    "wof:name":"Carrabba's",
    "wof:placetype":"venue"
},
  "geometry": {"coordinates":[-95.853798,36.061393],"type":"Point"}
}