{
  "type": "Feature",
  "properties": {
    "addr:full":"105 NE 12th St Oklahoma City OK 73160",
    "addr:housenumber":"105",
    "addr:postcode":"73160",
    "addr:street":"Ne 12Th St",
    "iso:country":"US",
    "sg:address":"105 NE 12th St",
    "sg:city":"Oklahoma City",
    "sg:classifiers":[
        {
            "category":"Restaurant",
            "type":"Food & Drink"
        }
    ],
    "sg:menulink":"http://www.allmenus.com/ok/north-cleveland/199332-sonic/menu/",
    "sg:phone":"+1 405 794 3355",
    "sg:postcode":"73160",
    "sg:province":"OK",
    "sg:tags":[
        "burger",
        "american"
    ],
    "wof:name":"Sonic",
    "wof:placetype":"venue"
},
  "geometry": {"coordinates":[-97.489694,35.348827],"type":"Point"}
}