{
  "type": "Feature",
  "properties": {
    "iso:country":"US",
    "sg:address":"601 S Boulder Ave W",
    "sg:city":"Tulsa",
    "sg:classifiers":[
        {
            "category":"Social Services",
            "type":"Services"
        }
    ],
    "sg:phone":"+1 918 585 3232",
    "sg:postcode":"74119",
    "sg:province":"OK",
    "wof:name":"Harry Champ",
    "wof:placetype":"venue"
},
  "geometry": {"coordinates":[-95.990246,36.149136],"type":"Point"}
}