{
  "type": "Feature",
  "properties": {
    "iso:country":"US",
    "sg:address":"6827 NW 39th Expy",
    "sg:city":"Bethany",
    "sg:classifiers":[
        {
            "category":"Autos & Motor Vehicles",
            "subcategory":"Automobile Sales",
            "type":"Retail Goods"
        }
    ],
    "sg:phone":"+1 405 787 1088",
    "sg:postcode":"73008",
    "sg:province":"OK",
    "sg:tags":[
        "equipment",
        "aircraft",
        "parts",
        "supply"
    ],
    "wof:name":"Hardware Inc",
    "wof:placetype":"venue"
},
  "geometry": {"coordinates":[-97.63307,35.512345],"type":"Point"}
}