{
  "type": "Feature",
  "properties": {
    "iso:country":"US",
    "sg:address":"15 S Adair St",
    "sg:city":"Pryor",
    "sg:classifiers":[
        {
            "category":"Home & Garden",
            "subcategory":"Household Appliances",
            "type":"Retail Goods"
        }
    ],
    "sg:phone":"+1 918 825 5732",
    "sg:postcode":"74361",
    "sg:province":"OK",
    "sg:tags":[
        "equipment",
        "rental",
        "furniture"
    ],
    "wof:name":"Little Rental Centre",
    "wof:placetype":"venue"
},
  "geometry": {"coordinates":[-95.317025,36.30754],"type":"Point"}
}