{
  "type": "Feature",
  "properties": {
    "addr:full":"139 NE Washington Blvd Bartlesville OK 74006",
    "addr:housenumber":"139",
    "addr:postcode":"74006",
    "addr:street":"Ne Washington Blvd",
    "iso:country":"US",
    "sg:address":"139 NE Washington Blvd",
    "sg:city":"Bartlesville",
    "sg:classifiers":[
        {
            "category":"Shopping",
            "subcategory":"Bicycles & Sporting Goods",
            "type":"Retail Goods"
        }
    ],
    "sg:phone":"+1 918 335 9361",
    "sg:postcode":"74006",
    "sg:province":"OK",
    "sg:tags":[
        "tackle",
        "fishing"
    ],
    "wof:name":"Tom's Tackle Plus",
    "wof:placetype":"venue"
},
  "geometry": {"coordinates":[-95.93542600000001,36.758653],"type":"Point"}
}