{
  "type": "Feature",
  "properties": {
    "iso:country":"US",
    "sg:address":"1016 S 10th St",
    "sg:city":"Clinton",
    "sg:classifiers":[
        {
            "category":"Building & Trades",
            "subcategory":"Plumbing",
            "type":"Services"
        }
    ],
    "sg:phone":"+1 580 323 0830",
    "sg:postcode":"73601",
    "sg:province":"OK",
    "sg:tags":[
        "heating",
        "contractor"
    ],
    "wof:name":"Hinz REFRIGERATION-AC & Htg",
    "wof:placetype":"venue"
},
  "geometry": {"coordinates":[-98.972135,35.504028],"type":"Point"}
}