{
  "type": "Feature",
  "properties": {
    "iso:country":"US",
    "sg:address":"9921 S 71st East Ave",
    "sg:city":"Tulsa",
    "sg:classifiers":[
        {
            "category":"Professional",
            "type":"Services"
        }
    ],
    "sg:phone":"+1 918 298 2106",
    "sg:postcode":"74133",
    "sg:province":"OK",
    "sg:tags":[
        "establishment"
    ],
    "wof:name":"American Capital Recovery Inc",
    "wof:placetype":"venue"
},
  "geometry": {"coordinates":[-95.896896,36.020406],"type":"Point"}
}