{
  "type": "Feature",
  "properties": {
    "iso:country":"US",
    "sg:address":"200 Georgia Pl",
    "sg:city":"Poteau",
    "sg:classifiers":[
        {
            "category":"Real Estate",
            "subcategory":"Real Estate Operator",
            "type":"Services"
        }
    ],
    "sg:phone":"+1 918 647 2541",
    "sg:postcode":"74953",
    "sg:province":"OK",
    "sg:tags":[
        "apartment"
    ],
    "wof:name":"Georgia Place Apts.",
    "wof:placetype":"venue"
},
  "geometry": {"coordinates":[-94.631503,35.076861],"type":"Point"}
}