{
  "type": "Feature",
  "properties": {
    "iso:country":"US",
    "sg:address":"23715 E 105th St",
    "sg:city":"Broken Arrow",
    "sg:classifiers":[
        {
            "category":"Wholesale",
            "subcategory":"Electrical",
            "type":"Manufacturing & Wholesale Goods"
        }
    ],
    "sg:phone":"+1 918 455 3974",
    "sg:postcode":"74014",
    "sg:province":"OK",
    "sg:tags":[
        "re",
        "electronic",
        "merchandise"
    ],
    "wof:name":"R&J Electronics Inc",
    "wof:placetype":"venue"
},
  "geometry": {"coordinates":[-95.710936,36.010985],"type":"Point"}
}