{
  "type": "Feature",
  "properties": {
    "iso:country":"US",
    "sg:address":"130 S 9th St",
    "sg:city":"Roff",
    "sg:classifiers":[
        {
            "category":"Wholesale",
            "subcategory":"Scrap",
            "type":"Manufacturing & Wholesale Goods"
        }
    ],
    "sg:phone":"+1 580 456 7553",
    "sg:postcode":"74865",
    "sg:province":"OK",
    "sg:tags":[
        "recycling",
        "center"
    ],
    "wof:name":"J & A Recycle Ctr",
    "wof:placetype":"venue"
},
  "geometry": {"coordinates":[-96.84219400000001,34.627156],"type":"Point"}
}