{
  "type": "Feature",
  "properties": {
    "iso:country":"US",
    "sg:address":"708 Quail Creek Rd",
    "sg:city":"Perry",
    "sg:classifiers":[
        {
            "category":"Professional",
            "subcategory":"Business Services",
            "type":"Services"
        }
    ],
    "sg:phone":"+1 580 336 5336",
    "sg:postcode":"73077",
    "sg:province":"OK",
    "wof:name":"Noble County Repeater Group",
    "wof:placetype":"venue"
},
  "geometry": {"coordinates":[-97.2884,36.306694],"type":"Point"}
}