{
  "type": "Feature",
  "properties": {
    "iso:country":"US",
    "sg:address":"23938 W 171st St S",
    "sg:city":"Kellyville",
    "sg:classifiers":[
        {
            "category":"Professional",
            "subcategory":"Management & Consulting",
            "type":"Services"
        }
    ],
    "sg:phone":"+1 918 855 5046",
    "sg:postcode":"74039",
    "sg:province":"OK",
    "sg:tags":[
        "business"
    ],
    "wof:name":"Ashby Consulting",
    "wof:placetype":"venue"
},
  "geometry": {"coordinates":[-96.261798,35.915424],"type":"Point"}
}