{
  "type": "Feature",
  "properties": {
    "iso:country":"US",
    "sg:address":"12028 N Pennsylvania Ave",
    "sg:city":"Oklahoma City",
    "sg:classifiers":[
        {
            "category":"Mining & Drilling",
            "type":"Manufacturing & Wholesale Goods"
        }
    ],
    "sg:phone":"+1 405 752 0318",
    "sg:postcode":"73120",
    "sg:province":"OK",
    "sg:tags":[
        "oil",
        "producer"
    ],
    "wof:name":"Agent Ken Okc Har",
    "wof:placetype":"venue"
},
  "geometry": {"coordinates":[-97.549285,35.591259],"type":"Point"}
}