{
  "type": "Feature",
  "properties": {
    "iso:country":"US",
    "sg:address":"1875 E Elm St",
    "sg:city":"El Reno",
    "sg:classifiers":[
        {
            "category":"Wholesale",
            "subcategory":"Motor Vehicles",
            "type":"Manufacturing & Wholesale Goods"
        }
    ],
    "sg:phone":"+1 405 422 3307",
    "sg:postcode":"73036",
    "sg:province":"OK",
    "sg:tags":[
        "bus"
    ],
    "wof:name":"Ross Transportation",
    "wof:placetype":"venue"
},
  "geometry": {"coordinates":[-97.92965,35.522565],"type":"Point"}
}