{
  "type": "Feature",
  "properties": {
    "addr:full":"13016 S Pennsylvania Ave Oklahoma City OK 73170",
    "addr:housenumber":"13016",
    "addr:postcode":"73170",
    "addr:street":"S Pennsylvania Ave",
    "iso:country":"US",
    "sg:address":"13016 S Pennsylvania Ave",
    "sg:city":"Oklahoma City",
    "sg:classifiers":[
        {
            "category":"Social Services",
            "subcategory":"Adult Care",
            "type":"Services"
        }
    ],
    "sg:phone":"+1 405 692 1001",
    "sg:postcode":"73170",
    "sg:province":"OK",
    "sg:tags":[
        "retardation",
        "home",
        "dev",
        "disabled"
    ],
    "wof:name":"Meadowbrook Acres Ctr",
    "wof:placetype":"venue"
},
  "geometry": {"coordinates":[-97.547567,35.338288],"type":"Point"}
}