{
  "type": "Feature",
  "properties": {
    "iso:country":"US",
    "sg:address":"5162 S 24th West Ave",
    "sg:city":"Tulsa",
    "sg:classifiers":[
        {
            "category":"Wholesale",
            "subcategory":"Machinery & Supplies",
            "type":"Manufacturing & Wholesale Goods"
        }
    ],
    "sg:phone":"+1 918 445 0005",
    "sg:postcode":"74107",
    "sg:province":"OK",
    "sg:tags":[
        "equipment",
        "mining",
        "construction",
        "valve"
    ],
    "sg:website":"www.unitedwaterworks.com",
    "wof:name":"United Water Works Co",
    "wof:placetype":"venue"
},
  "geometry": {"coordinates":[-96.018996,36.088034],"type":"Point"}
}