{
  "type": "Feature",
  "properties": {
    "iso:country":"US",
    "sg:address":"222 E Main St",
    "sg:city":"Ada",
    "sg:classifiers":[
        {
            "category":"Wholesale",
            "subcategory":"Non-durable Goods",
            "type":"Manufacturing & Wholesale Goods"
        }
    ],
    "sg:phone":"+1 580 436 1111",
    "sg:postcode":"74820",
    "sg:province":"OK",
    "sg:tags":[
        "fund",
        "raising",
        "merchandise"
    ],
    "sg:website":"www.regalfundraising.us",
    "wof:name":"Regal Fund Raisings",
    "wof:placetype":"venue"
},
  "geometry": {"coordinates":[-96.67664,34.774585],"type":"Point"}
}