{
  "type": "Feature",
  "properties": {
    "iso:country":"US",
    "sg:address":"3152 Elmwood Ave",
    "sg:city":"Oklahoma City",
    "sg:classifiers":[
        {
            "category":"Real Estate",
            "subcategory":"Real Estate Agent",
            "type":"Services"
        }
    ],
    "sg:phone":"+1 405 848 7006",
    "sg:postcode":"73116",
    "sg:province":"OK",
    "wof:name":"Drue Ridley & Associates",
    "wof:placetype":"venue"
},
  "geometry": {"coordinates":[-97.574671,35.549663],"type":"Point"}
}