{
  "type": "Feature",
  "properties": {
    "addr:full":"317 E Elm Ave Eufaula OK 74432",
    "addr:housenumber":"317",
    "addr:postcode":"74432",
    "addr:street":"E Elm Ave",
    "iso:country":"US",
    "sg:address":"317 E Elm Ave",
    "sg:city":"Eufaula",
    "sg:classifiers":[
        {
            "category":"Retail",
            "subcategory":"Repair Shop",
            "type":"Services"
        }
    ],
    "sg:phone":"+1 918 689 3903",
    "sg:postcode":"74432",
    "sg:province":"OK",
    "sg:tags":[
        "repairing",
        "saw"
    ],
    "wof:name":"Jay's Saw Svc",
    "wof:placetype":"venue"
},
  "geometry": {"coordinates":[-95.575988,35.290418],"type":"Point"}
}