{
  "type": "Feature",
  "properties": {
    "addr:full":"6433 N Olie Ave Oklahoma City OK 73116",
    "addr:housenumber":"6433",
    "addr:postcode":"73116",
    "addr:street":"N Olie Ave",
    "iso:country":"US",
    "sg:address":"6433 N Olie Ave",
    "sg:city":"Oklahoma City",
    "sg:classifiers":[
        {
            "category":"Personal",
            "type":"Services"
        }
    ],
    "sg:phone":"+1 405 848 8900",
    "sg:postcode":"73116",
    "sg:province":"OK",
    "sg:tags":[
        "program",
        "physical",
        "exercise",
        "fitness"
    ],
    "wof:name":"Pilates-A Ctr For Integration",
    "wof:placetype":"venue"
},
  "geometry": {"coordinates":[-97.528595,35.538634],"type":"Point"}
}