{
  "type": "Feature",
  "properties": {
    "iso:country":"US",
    "sg:address":"401 S Washington Ave",
    "sg:city":"Elk City",
    "sg:classifiers":[
        {
            "category":"Retail",
            "subcategory":"Animal Services",
            "type":"Services"
        }
    ],
    "sg:phone":"+1 580 225 0068",
    "sg:postcode":"73644",
    "sg:province":"OK",
    "sg:tags":[
        "pet",
        "grooming",
        "washing"
    ],
    "wof:name":"Perfect Groom",
    "wof:placetype":"venue"
},
  "geometry": {"coordinates":[-99.40852700000001,35.407404],"type":"Point"}
}