{
  "type": "Feature",
  "properties": {
    "iso:country":"US",
    "sg:address":"7100 Terminal Dr",
    "sg:city":"Oklahoma City",
    "sg:classifiers":[
        {
            "category":"Restaurant",
            "type":"Food & Drink"
        }
    ],
    "sg:menulink":"http://www.allmenus.com/ok/oklahoma-city/199330-sonic/menu/",
    "sg:phone":"+1 405 681 5567",
    "sg:postcode":"73159",
    "sg:province":"OK",
    "sg:tags":[
        "burger",
        "american"
    ],
    "wof:name":"Sonic",
    "wof:placetype":"venue"
},
  "geometry": {"coordinates":[-97.596407,35.395347],"type":"Point"}
}