{
  "type": "Feature",
  "properties": {
    "iso:country":"US",
    "sg:address":"804 W Delaware St",
    "sg:city":"Cleveland",
    "sg:classifiers":[
        {
            "category":"Professional",
            "type":"Services"
        }
    ],
    "sg:phone":"+1 918 358 2350",
    "sg:postcode":"74020",
    "sg:province":"OK",
    "wof:name":"Vernon Brown",
    "wof:placetype":"venue"
},
  "geometry": {"coordinates":[-96.473165,36.308861],"type":"Point"}
}