{
  "type": "Feature",
  "properties": {
    "iso:country":"US",
    "sg:address":"1025 Swan Dr",
    "sg:city":"Bartlesville",
    "sg:classifiers":[
        {
            "category":"Real Estate",
            "subcategory":"Real Estate Operator",
            "type":"Services"
        }
    ],
    "sg:phone":"+1 918 335 2086",
    "sg:postcode":"74006",
    "sg:province":"OK",
    "sg:tags":[
        "retirement",
        "village"
    ],
    "wof:name":"Green Cnty Vlg Rtrment Cmmunit",
    "wof:placetype":"venue"
},
  "geometry": {"coordinates":[-95.931218,36.738304],"type":"Point"}
}