{
  "type": "Feature",
  "properties": {
    "iso:country":"US",
    "sg:address":"3850 E Frank Phillips Blvd",
    "sg:city":"Bartlesville",
    "sg:classifiers":[
        {
            "category":"Shopping",
            "subcategory":"Optical Goods",
            "type":"Retail Goods"
        }
    ],
    "sg:phone":"+1 918 333 3387",
    "sg:postcode":"74006",
    "sg:province":"OK",
    "sg:tags":[
        "sun",
        "goggles",
        "sunglasses"
    ],
    "wof:name":"Sunbusters",
    "wof:placetype":"venue"
},
  "geometry": {"coordinates":[-95.93308,36.750645],"type":"Point"}
}