{
  "type": "Feature",
  "properties": {
    "addr:full":"804 McGee Dr Norman OK 73069",
    "addr:housenumber":"804",
    "addr:postcode":"73069",
    "addr:street":"Mcgee Dr",
    "iso:country":"US",
    "sg:address":"804 McGee Dr",
    "sg:city":"Norman",
    "sg:classifiers":[
        {
            "category":"Organizations",
            "subcategory":"Community Association",
            "type":"Services"
        }
    ],
    "sg:phone":"+1 405 329 0276",
    "sg:postcode":"73069",
    "sg:province":"OK",
    "sg:tags":[
        "membership"
    ],
    "wof:name":"D Company 179th Infantry 45th",
    "wof:placetype":"venue"
},
  "geometry": {"coordinates":[-97.46778399999999,35.209541],"type":"Point"}
}