{
  "type": "Feature",
  "properties": {
    "iso:country":"US",
    "sg:address":"5830 S Indianapolis Ave",
    "sg:city":"Tulsa",
    "sg:classifiers":[
        {
            "category":"Banks & Credit Unions",
            "subcategory":"Financial Services",
            "type":"Services"
        }
    ],
    "sg:phone":"+1 918 747 3167",
    "sg:postcode":"74135",
    "sg:province":"OK",
    "sg:tags":[
        "royalty",
        "oil"
    ],
    "wof:name":"Loma Inc",
    "wof:placetype":"venue"
},
  "geometry": {"coordinates":[-95.939468,36.077752],"type":"Point"}
}