{
  "type": "Feature",
  "properties": {
    "addr:full":"624 6th St Pawnee OK 74058",
    "addr:housenumber":"624",
    "addr:postcode":"74058",
    "addr:street":"6Th St",
    "iso:country":"US",
    "sg:address":"624 6th St",
    "sg:city":"Pawnee",
    "sg:classifiers":[
        {
            "category":"Utilities",
            "subcategory":"Telephone",
            "type":"Services"
        }
    ],
    "sg:phone":"+1 405 236 6611",
    "sg:postcode":"74058",
    "sg:province":"OK",
    "sg:tags":[
        "company"
    ],
    "wof:name":"Southwestern Bell Telephone LP",
    "wof:placetype":"venue"
},
  "geometry": {"coordinates":[-96.80393100000001,36.33762],"type":"Point"}
}