{
  "type": "Feature",
  "properties": {
    "iso:country":"US",
    "sg:address":"201 E Ave I",
    "sg:city":"Heavener",
    "sg:classifiers":[
        {
            "category":"Real Estate",
            "subcategory":"Real Estate Agent",
            "type":"Services"
        }
    ],
    "sg:phone":"+1 918 653 2500",
    "sg:postcode":"74937",
    "sg:province":"OK",
    "sg:tags":[
        "authorities",
        "housing"
    ],
    "wof:name":"Heavener Housing Authority",
    "wof:placetype":"venue"
},
  "geometry": {"coordinates":[-94.602002,34.884029],"type":"Point"}
}