{
  "type": "Feature",
  "properties": {
    "addr:full":"5445 S 101st East Ave Tulsa OK 74146",
    "addr:housenumber":"5445",
    "addr:postcode":"74146",
    "addr:street":"S 101St;Ave",
    "iso:country":"US",
    "sg:address":"5445 S 101st East Ave",
    "sg:city":"Tulsa",
    "sg:classifiers":[
        {
            "category":"Building & Trades",
            "subcategory":"Construction",
            "type":"Services"
        }
    ],
    "sg:phone":"+1 918 622 7955",
    "sg:postcode":"74146",
    "sg:province":"OK",
    "sg:tags":[
        "carpentry",
        "contractor"
    ],
    "wof:name":"Mike Dudding",
    "wof:placetype":"venue"
},
  "geometry": {"coordinates":[-95.863877,36.084834],"type":"Point"}
}