{
  "type": "Feature",
  "properties": {
    "iso:country":"US",
    "sg:address":"23 E 1st St",
    "sg:city":"Edmond",
    "sg:classifiers":[
        {
            "category":"Government",
            "subcategory":"Police Station",
            "type":"Public Place"
        }
    ],
    "sg:phone":"+1 405 359 4420",
    "sg:postcode":"73034",
    "sg:province":"OK",
    "sg:tags":[
        "department"
    ],
    "sg:website":"www.ci.edmond.ok.us",
    "wof:name":"Edmond Police Dept",
    "wof:placetype":"venue"
},
  "geometry": {"coordinates":[-97.480077,35.654173],"type":"Point"}
}