{
  "type": "Feature",
  "properties": {
    "iso:country":"US",
    "sg:address":"784 Asp Ave",
    "sg:city":"Norman",
    "sg:classifiers":[
        {
            "category":"Wholesale",
            "subcategory":"Apparel",
            "type":"Manufacturing & Wholesale Goods"
        }
    ],
    "sg:phone":"+1 405 447 2345",
    "sg:postcode":"73069",
    "sg:province":"OK",
    "sg:tags":[
        "clothing",
        "mi"
    ],
    "wof:name":"Apothem",
    "wof:placetype":"venue"
},
  "geometry": {"coordinates":[-97.443769,35.212589],"type":"Point"}
}