{
  "type": "Feature",
  "properties": {
    "iso:country":"US",
    "sg:address":"528 S Lincoln St",
    "sg:city":"Hobart",
    "sg:classifiers":[
        {
            "category":"Professional",
            "subcategory":"Business Services",
            "type":"Services"
        }
    ],
    "sg:phone":"+1 580 726 2316",
    "sg:postcode":"73651",
    "sg:province":"OK",
    "wof:name":"James Reimer",
    "wof:placetype":"venue"
},
  "geometry": {"coordinates":[-99.088836,35.022754],"type":"Point"}
}