{
  "type": "Feature",
  "properties": {
    "iso:country":"US",
    "sg:address":"3901 S 505 Rd",
    "sg:city":"Miami",
    "sg:classifiers":[
        {
            "category":"Farming",
            "subcategory":"Livestock Farm",
            "type":"Manufacturing & Wholesale Goods"
        }
    ],
    "sg:phone":"+1 918 673 2612",
    "sg:postcode":"74354",
    "sg:province":"OK",
    "sg:tags":[
        "animal",
        "general"
    ],
    "wof:name":"3k",
    "wof:placetype":"venue"
},
  "geometry": {"coordinates":[-94.966076,36.959288],"type":"Point"}
}