{
  "type": "Feature",
  "properties": {
    "iso:country":"US",
    "sg:address":"826 W Oregon Ave",
    "sg:city":"Chickasha",
    "sg:classifiers":[
        {
            "category":"Health Services",
            "subcategory":"Nursing And Care Facility",
            "type":"Services"
        }
    ],
    "sg:phone":"+1 405 222 1023",
    "sg:postcode":"73018",
    "sg:province":"OK",
    "wof:name":"Special Young Adults Group Hm",
    "wof:placetype":"venue"
},
  "geometry": {"coordinates":[-97.943812,35.043094],"type":"Point"}
}