{
  "type": "Feature",
  "properties": {
    "iso:country":"US",
    "sg:address":"500 1st St",
    "sg:city":"Kingston",
    "sg:classifiers":[
        {
            "category":"Real Estate",
            "subcategory":"Real Estate Operator",
            "type":"Services"
        }
    ],
    "sg:phone":"+1 580 564 2600",
    "sg:postcode":"73439",
    "sg:province":"OK",
    "sg:tags":[
        "apartment"
    ],
    "wof:name":"Carol-Lynn Apartments",
    "wof:placetype":"venue"
},
  "geometry": {"coordinates":[-96.72430300000001,34.000399],"type":"Point"}
}