{
  "type": "Feature",
  "properties": {
    "iso:country":"US",
    "sg:address":"2308 S Meridian Ave",
    "sg:city":"Oklahoma City",
    "sg:classifiers":[
        {
            "category":"Travel",
            "subcategory":"Hotels & Motels",
            "type":"Entertainment"
        }
    ],
    "sg:phone":"+1 405 682 5299",
    "sg:postcode":"73108",
    "sg:province":"OK",
    "sg:website":"www.governorssuites-okc.com",
    "wof:name":"Governor's Inn",
    "wof:placetype":"venue"
},
  "geometry": {"coordinates":[-97.600978,35.439872],"type":"Point"}
}