{
  "type": "Feature",
  "properties": {
    "iso:country":"US",
    "sg:address":"205 S 9th Ave",
    "sg:city":"Durant",
    "sg:classifiers":[
        {
            "category":"Autos & Motor Vehicles",
            "subcategory":"Automobile Sales",
            "type":"Retail Goods"
        }
    ],
    "sg:phone":"+1 580 924 3282",
    "sg:postcode":"74701",
    "sg:province":"OK",
    "sg:tags":[
        "car",
        "used",
        "dealer"
    ],
    "wof:name":"Triple E Auto Sales",
    "wof:placetype":"venue"
},
  "geometry": {"coordinates":[-96.386033,33.991498],"type":"Point"}
}