{
  "type": "Feature",
  "properties": {
    "iso:country":"US",
    "sg:address":"3823 N Monroe St",
    "sg:city":"Stillwater",
    "sg:classifiers":[
        {
            "category":"Building & Trades",
            "subcategory":"Construction",
            "type":"Services"
        }
    ],
    "sg:phone":"+1 405 372 2104",
    "sg:postcode":"74075",
    "sg:province":"OK",
    "sg:tags":[
        "home",
        "improvement"
    ],
    "wof:name":"Higgens Home Improvement",
    "wof:placetype":"venue"
},
  "geometry": {"coordinates":[-97.07244300000001,36.159468],"type":"Point"}
}