{
  "type": "Feature",
  "properties": {
    "iso:country":"US",
    "sg:address":"4505 Memorial Cir",
    "sg:city":"Oklahoma City",
    "sg:classifiers":[
        {
            "category":"Health Services",
            "subcategory":"Doctor",
            "type":"Services"
        }
    ],
    "sg:phone":"+1 405 755 1880",
    "sg:postcode":"73142",
    "sg:province":"OK",
    "sg:tags":[
        "medical"
    ],
    "wof:name":"Mueller Roger A",
    "wof:placetype":"venue"
},
  "geometry": {"coordinates":[-97.603404,35.607204],"type":"Point"}
}