{
  "type": "Feature",
  "properties": {
    "addr:full":"1134 Industrial Dr Yukon OK 73099",
    "addr:housenumber":"1134",
    "addr:postcode":"73099",
    "addr:street":"Industrial Dr",
    "iso:country":"US",
    "sg:address":"1134 Industrial Dr",
    "sg:city":"Yukon",
    "sg:phone":"+1 405 350 8099",
    "sg:postcode":"73099",
    "sg:province":"OK",
    "sg:tags":[
        "repair",
        "industrial",
        "commercial",
        "scale"
    ],
    "wof:name":"Scale Source",
    "wof:placetype":"venue"
},
  "geometry": {"coordinates":[-97.728582,35.504862],"type":"Point"}
}