{
  "type": "Feature",
  "properties": {
    "addr:full":"2535 E Hereford Ln Bache OK 74501",
    "addr:housenumber":"2535",
    "addr:postcode":"74501",
    "addr:street":"E Hereford Ln",
    "iso:country":"US",
    "sg:address":"2535 E Hereford Ln",
    "sg:city":"Bache",
    "sg:classifiers":[
        {
            "category":"Building & Trades",
            "subcategory":"Construction",
            "type":"Services"
        }
    ],
    "sg:phone":"+1 918 423 4303",
    "sg:postcode":"74501",
    "sg:province":"OK",
    "sg:tags":[
        "house"
    ],
    "wof:name":"Pingleton Construction",
    "wof:placetype":"venue"
},
  "geometry": {"coordinates":[-95.73626899999999,34.956602],"type":"Point"}
}