{
  "type": "Feature",
  "properties": {
    "iso:country":"US",
    "sg:address":"1110 W 115th Pl",
    "sg:city":"Jenks",
    "sg:classifiers":[
        {
            "category":"Professional",
            "subcategory":"Business Services",
            "type":"Services"
        }
    ],
    "sg:phone":"+1 918 296 9481",
    "sg:postcode":"74037",
    "sg:province":"OK",
    "wof:name":"Impressions On Hold",
    "wof:placetype":"venue"
},
  "geometry": {"coordinates":[-95.984363,35.996013],"type":"Point"}
}