{
  "type": "Feature",
  "properties": {
    "iso:country":"US",
    "sg:address":"12700 S Anderson Rd",
    "sg:city":"Oklahoma City",
    "sg:classifiers":[
        {
            "category":"Real Estate",
            "subcategory":"Real Estate Agent",
            "type":"Services"
        }
    ],
    "sg:phone":"+1 405 799 6406",
    "sg:postcode":"73165",
    "sg:province":"OK",
    "wof:name":"Aylor Appraisal Svc",
    "wof:placetype":"venue"
},
  "geometry": {"coordinates":[-97.318002,35.340077],"type":"Point"}
}