{
  "type": "Feature",
  "properties": {
    "iso:country":"US",
    "sg:address":"1930 S Bryant Ave",
    "sg:city":"Edmond",
    "sg:classifiers":[
        {
            "category":"Insurance",
            "subcategory":"Insurance Agent",
            "type":"Services"
        }
    ],
    "sg:phone":"+1 405 340 5607",
    "sg:postcode":"73013",
    "sg:province":"OK",
    "wof:name":"Advanced Benefit Solutions LLC",
    "wof:placetype":"venue"
},
  "geometry": {"coordinates":[-97.460346,35.634916],"type":"Point"}
}