{
  "type": "Feature",
  "properties": {
    "iso:country":"US",
    "sg:address":"2800 NW 63rd St",
    "sg:city":"Oklahoma City",
    "sg:classifiers":[
        {
            "category":"Utilities",
            "subcategory":"Mobile Phone",
            "type":"Services"
        }
    ],
    "sg:phone":"+1 405 848 2298",
    "sg:postcode":"73116",
    "sg:province":"OK",
    "sg:tags":[
        "telephone",
        "cellular"
    ],
    "wof:name":"Touchtell Wireless",
    "wof:placetype":"venue"
},
  "geometry": {"coordinates":[-97.563778,35.536556],"type":"Point"}
}