{
  "type": "Feature",
  "properties": {
    "addr:full":"5151 S 110th East Ave Tulsa OK 74146",
    "addr:housenumber":"5151",
    "addr:postcode":"74146",
    "addr:street":"S 110Th;Ave",
    "iso:country":"US",
    "sg:address":"5151 S 110th East Ave",
    "sg:city":"Tulsa",
    "sg:classifiers":[
        {
            "category":"Manufacturing",
            "subcategory":"Tools & Machinery",
            "type":"Manufacturing & Wholesale Goods"
        }
    ],
    "sg:phone":"+1 918 359 2000",
    "sg:postcode":"74146",
    "sg:province":"OK",
    "sg:tags":[
        "company",
        "holding"
    ],
    "wof:name":"Sinties Corporation",
    "wof:placetype":"venue"
},
  "geometry": {"coordinates":[-95.85163799999999,36.086676],"type":"Point"}
}