{
  "type": "Feature",
  "properties": {
    "iso:country":"US",
    "sg:address":"12300 Park Ave",
    "sg:city":"Yukon",
    "sg:classifiers":[
        {
            "category":"Professional",
            "subcategory":"Accounting & Tax Preparation",
            "type":"Services"
        }
    ],
    "sg:phone":"+1 405 350 9940",
    "sg:postcode":"73099",
    "sg:province":"OK",
    "sg:tags":[
        "accountant",
        "public",
        "certified"
    ],
    "wof:name":"Robin Wilkerson CPA",
    "wof:placetype":"venue"
},
  "geometry": {"coordinates":[-97.745343,35.467197],"type":"Point"}
}