{
  "type": "Feature",
  "properties": {
    "addr:full":"10301 E 51st St Tulsa OK 74146",
    "addr:housenumber":"10301",
    "addr:postcode":"74146",
    "addr:street":"E 51St St",
    "iso:country":"US",
    "sg:address":"10301 E 51st St",
    "sg:city":"Tulsa",
    "sg:classifiers":[
        {
            "category":"Health Services",
            "subcategory":"Clinic",
            "type":"Services"
        }
    ],
    "sg:phone":"+1 918 628 2831",
    "sg:postcode":"74146",
    "sg:province":"OK",
    "sg:tags":[
        "ultrasound",
        "imaging"
    ],
    "wof:name":"Advanced Ultrasound Electronic",
    "wof:placetype":"venue"
},
  "geometry": {"coordinates":[-95.861149,36.08994],"type":"Point"}
}