{
  "type": "Feature",
  "properties": {
    "iso:country":"US",
    "sg:address":"1200 NW 10th St",
    "sg:city":"Oklahoma City",
    "sg:classifiers":[
        {
            "category":"Real Estate",
            "subcategory":"Real Estate Operator",
            "type":"Services"
        }
    ],
    "sg:phone":"+1 405 794 0201",
    "sg:postcode":"73170",
    "sg:province":"OK",
    "wof:name":"Jamestown Square Apartments",
    "wof:placetype":"venue"
},
  "geometry": {"coordinates":[-97.514075,35.346794],"type":"Point"}
}