{
  "type": "Feature",
  "properties": {
    "addr:full":"902 E Main St Antlers OK 74523",
    "addr:housenumber":"902",
    "addr:postcode":"74523",
    "addr:street":"E Main St",
    "iso:country":"US",
    "sg:address":"902 E Main St",
    "sg:city":"Antlers",
    "sg:classifiers":[
        {
            "category":"Restaurant",
            "type":"Food & Drink"
        }
    ],
    "sg:phone":"+1 580 298 5400",
    "sg:postcode":"74523",
    "sg:province":"OK",
    "sg:tags":[
        "eating"
    ],
    "wof:name":"Hot Stuff Pizza",
    "wof:placetype":"venue"
},
  "geometry": {"coordinates":[-95.60887099999999,34.232179],"type":"Point"}
}