{
  "type": "Feature",
  "properties": {
    "iso:country":"US",
    "sg:address":"4505 SE 15th St",
    "sg:city":"Oklahoma City",
    "sg:classifiers":[
        {
            "category":"Social Services",
            "type":"Services"
        }
    ],
    "sg:phone":"+1 405 671 2868",
    "sg:postcode":"73115",
    "sg:province":"OK",
    "sg:tags":[
        "center",
        "community"
    ],
    "wof:name":"Community Center",
    "wof:placetype":"venue"
},
  "geometry": {"coordinates":[-97.43729,35.449781],"type":"Point"}
}