{
  "type": "Feature",
  "properties": {
    "iso:country":"US",
    "sg:address":"202 N Broadway",
    "sg:city":"Marlow",
    "sg:classifiers":[
        {
            "category":"Food & Beverages",
            "subcategory":"Groceries & Convenience Stores",
            "type":"Retail Goods"
        }
    ],
    "sg:phone":"+1 580 658 3033",
    "sg:postcode":"73055",
    "sg:province":"OK",
    "wof:name":"Hop & Sack Stores",
    "wof:placetype":"venue"
},
  "geometry": {"coordinates":[-97.957739,34.649993],"type":"Point"}
}