{
  "type": "Feature",
  "properties": {
    "addr:full":"6764 E 28th St Tulsa OK 74129",
    "addr:housenumber":"6764",
    "addr:postcode":"74129",
    "addr:street":"E 28Th St",
    "iso:country":"US",
    "sg:address":"6764 E 28th St",
    "sg:city":"Tulsa",
    "sg:classifiers":[
        {
            "category":"Building & Trades",
            "subcategory":"Construction",
            "type":"Services"
        }
    ],
    "sg:phone":"+1 918 835 2788",
    "sg:postcode":"74129",
    "sg:province":"OK",
    "sg:tags":[
        "sun",
        "solarium",
        "rooms"
    ],
    "wof:name":"Mack Construction Co",
    "wof:placetype":"venue"
},
  "geometry": {"coordinates":[-95.89545200000001,36.122694],"type":"Point"}
}