{
  "type": "Feature",
  "properties": {
    "iso:country":"US",
    "sg:address":"501 W Kings Rd",
    "sg:city":"Ada",
    "sg:classifiers":[
        {
            "category":"Building & Trades",
            "subcategory":"Construction",
            "type":"Services"
        }
    ],
    "sg:phone":"+1 580 421 6746",
    "sg:postcode":"74820",
    "sg:province":"OK",
    "sg:tags":[
        "excavating",
        "contractor"
    ],
    "wof:name":"Phil Reid Dozer Svc",
    "wof:placetype":"venue"
},
  "geometry": {"coordinates":[-96.686627,34.759983],"type":"Point"}
}