{
  "type": "Feature",
  "properties": {
    "addr:full":"3500 N Harrison Ave Shawnee OK 74804",
    "addr:housenumber":"3500",
    "addr:postcode":"74804",
    "addr:street":"N Harrison Ave",
    "iso:country":"US",
    "sg:address":"3500 N Harrison Ave",
    "sg:city":"Shawnee",
    "sg:classifiers":[
        {
            "category":"Manufacturing",
            "subcategory":"Rubber & Plastics",
            "type":"Manufacturing & Wholesale Goods"
        }
    ],
    "sg:phone":"+1 405 275 3171",
    "sg:postcode":"74804",
    "sg:province":"OK",
    "sg:tags":[
        "product",
        "metalwork",
        "sheet",
        "mfg"
    ],
    "sg:website":"www.general-plastics.com",
    "wof:name":"General Plastics Inc",
    "wof:placetype":"venue"
},
  "geometry": {"coordinates":[-96.912132,35.370962],"type":"Point"}
}