{
  "type": "Feature",
  "properties": {
    "iso:country":"US",
    "sg:address":"1501 New Sapulpa Rd",
    "sg:city":"Sapulpa",
    "sg:classifiers":[
        {
            "category":"Autos & Motor Vehicles",
            "subcategory":"Recreational Vehicle Sales",
            "type":"Retail Goods"
        }
    ],
    "sg:phone":"+1 918 224 9444",
    "sg:postcode":"74066",
    "sg:province":"OK",
    "wof:name":"R V Hunter Center Inc",
    "wof:placetype":"venue"
},
  "geometry": {"coordinates":[-96.09858800000001,36.012893],"type":"Point"}
}