{
  "type": "Feature",
  "properties": {
    "addr:full":"2250 NW 39th St Oklahoma City OK 73112",
    "addr:housenumber":"2250",
    "addr:postcode":"73112",
    "addr:street":"Nw 39Th St",
    "iso:country":"US",
    "sg:address":"2250 NW 39th St",
    "sg:city":"Oklahoma City",
    "sg:classifiers":[
        {
            "category":"Professional",
            "subcategory":"Computer Services",
            "type":"Services"
        }
    ],
    "sg:phone":"+1 405 524 1919",
    "sg:postcode":"73112",
    "sg:province":"OK",
    "sg:tags":[
        "prepackaged",
        "software"
    ],
    "wof:name":"Custom Software Systems Inc",
    "wof:placetype":"venue"
},
  "geometry": {"coordinates":[-97.551862,35.511276],"type":"Point"}
}