{
  "type": "Feature",
  "properties": {
    "addr:full":"910 SE Washington St Idabel OK 74745",
    "addr:housenumber":"910",
    "addr:postcode":"74745",
    "addr:street":"Se Washington St",
    "iso:country":"US",
    "sg:address":"910 SE Washington St",
    "sg:city":"Idabel",
    "sg:classifiers":[
        {
            "category":"Autos & Motor Vehicles",
            "subcategory":"Auto Supplies",
            "type":"Retail Goods"
        }
    ],
    "sg:phone":"+1 580 286 3464",
    "sg:postcode":"74745",
    "sg:province":"OK",
    "sg:tags":[
        "automobile",
        "parts"
    ],
    "wof:name":"O'Reilly Auto Parts",
    "wof:placetype":"venue"
},
  "geometry": {"coordinates":[-94.817696,33.895475],"type":"Point"}
}