{
  "type": "Feature",
  "properties": {
    "iso:country":"US",
    "sg:address":"122 N Main St",
    "sg:city":"Medford",
    "sg:classifiers":[
        {
            "category":"Insurance",
            "subcategory":"Insurance Agent",
            "type":"Services"
        }
    ],
    "sg:phone":"+1 580 395 2447",
    "sg:postcode":"73759",
    "sg:province":"OK",
    "wof:name":"High Plains Insurance",
    "wof:placetype":"venue"
},
  "geometry": {"coordinates":[-97.73501899999999,36.807448],"type":"Point"}
}