{
  "type": "Feature",
  "properties": {
    "iso:country":"US",
    "sg:address":"125 N 4th St",
    "sg:city":"Sayre",
    "sg:classifiers":[
        {
            "category":"Autos & Motor Vehicles",
            "subcategory":"Auto Supplies",
            "type":"Retail Goods"
        }
    ],
    "sg:phone":"+1 580 928 3669",
    "sg:postcode":"73662",
    "sg:province":"OK",
    "sg:tags":[
        "new",
        "parts"
    ],
    "wof:name":"Sayre Auto Supply",
    "wof:placetype":"venue"
},
  "geometry": {"coordinates":[-99.640036,35.291571],"type":"Point"}
}