{
  "type": "Feature",
  "properties": {
    "iso:country":"US",
    "sg:address":"5317 E 4th Pl",
    "sg:city":"Tulsa",
    "sg:classifiers":[
        {
            "category":"Food & Beverages",
            "subcategory":"Specialty",
            "type":"Retail Goods"
        }
    ],
    "sg:phone":"+1 918 832 0843",
    "sg:postcode":"74112",
    "sg:province":"OK",
    "wof:name":"Bailey's Mill Gourmet Foods",
    "wof:placetype":"venue"
},
  "geometry": {"coordinates":[-95.915936,36.155189],"type":"Point"}
}