{
  "type": "Feature",
  "properties": {
    "iso:country":"US",
    "sg:address":"3200 N May Ave",
    "sg:city":"Oklahoma City",
    "sg:classifiers":[
        {
            "category":"Shopping",
            "type":"Retail Goods"
        }
    ],
    "sg:phone":"+1 405 947 4615",
    "sg:postcode":"73112",
    "sg:province":"OK",
    "sg:tags":[
        "mexican"
    ],
    "wof:name":"LA Tienda Tropical",
    "wof:placetype":"venue"
},
  "geometry": {"coordinates":[-97.565666,35.503115],"type":"Point"}
}