{
  "type": "Feature",
  "properties": {
    "iso:country":"US",
    "sg:address":"340 N Council Rd",
    "sg:city":"Oklahoma City",
    "sg:classifiers":[
        {
            "category":"Education",
            "subcategory":"School",
            "type":"Public Place"
        }
    ],
    "sg:phone":"+1 405 350 3485",
    "sg:postcode":"73127",
    "sg:province":"OK",
    "wof:name":"Western Heights School System",
    "wof:placetype":"venue"
},
  "geometry": {"coordinates":[-97.654204,35.471338],"type":"Point"}
}