{
  "type": "Feature",
  "properties": {
    "iso:country":"US",
    "sg:address":"4116 N Portland Ave",
    "sg:city":"Oklahoma City",
    "sg:classifiers":[
        {
            "category":"Personal",
            "subcategory":"Barber",
            "type":"Services"
        }
    ],
    "sg:phone":"+1 405 942 5669",
    "sg:postcode":"73112",
    "sg:province":"OK",
    "sg:tags":[
        "shop"
    ],
    "wof:name":"Portland Plaza Sebring Styling",
    "wof:placetype":"venue"
},
  "geometry": {"coordinates":[-97.583338,35.511636],"type":"Point"}
}