{
  "type": "Feature",
  "properties": {
    "addr:full":"1400 NW 12th St Oklahoma City OK 73170",
    "addr:housenumber":"1400",
    "addr:postcode":"73170",
    "addr:street":"Nw 12Th St",
    "iso:country":"US",
    "sg:address":"1400 NW 12th St",
    "sg:city":"Oklahoma City",
    "sg:classifiers":[
        {
            "category":"Social Services",
            "subcategory":"Child Care",
            "type":"Services"
        }
    ],
    "sg:phone":"+1 405 794 0808",
    "sg:postcode":"73170",
    "sg:province":"OK",
    "wof:name":"MDO Preschool",
    "wof:placetype":"venue"
},
  "geometry": {"coordinates":[-97.518294,35.348754],"type":"Point"}
}