{
  "type": "Feature",
  "properties": {
    "iso:country":"US",
    "sg:address":"240 E Apache St",
    "sg:city":"Tulsa",
    "sg:classifiers":[
        {
            "category":"Professional",
            "subcategory":"Lawyer & Legal Services",
            "type":"Services"
        }
    ],
    "sg:phone":"+1 918 582 4224",
    "sg:postcode":"74106",
    "sg:province":"OK",
    "sg:tags":[
        "attorney"
    ],
    "wof:name":"Damario Solomon Simmons",
    "wof:placetype":"venue"
},
  "geometry": {"coordinates":[-95.989699,36.191366],"type":"Point"}
}