{
  "type": "Feature",
  "properties": {
    "iso:country":"US",
    "sg:address":"10944 N May Ave",
    "sg:city":"Oklahoma City",
    "sg:classifiers":[
        {
            "category":"Recreation",
            "type":"Entertainment"
        }
    ],
    "sg:phone":"+1 405 751 7545",
    "sg:postcode":"73120",
    "sg:province":"OK",
    "wof:name":"Laser Quest",
    "wof:placetype":"venue"
},
  "geometry": {"coordinates":[-97.56711300000001,35.580629],"type":"Point"}
}