{
  "type": "Feature",
  "properties": {
    "iso:country":"US",
    "sg:address":"5512 S Lewis Ave",
    "sg:city":"Tulsa",
    "sg:classifiers":[
        {
            "category":"Health Services",
            "subcategory":"Health Practitioner",
            "type":"Services"
        }
    ],
    "sg:phone":"+1 918 712 9004",
    "sg:postcode":"74105",
    "sg:province":"OK",
    "sg:tags":[
        "psychologist"
    ],
    "wof:name":"Clinical & Neuropsychological",
    "wof:placetype":"venue"
},
  "geometry": {"coordinates":[-95.95802,36.083607],"type":"Point"}
}