{
  "type": "Feature",
  "properties": {
    "iso:country":"US",
    "sg:address":"1650 S 81st W Ave",
    "sg:city":"Tulsa",
    "sg:classifiers":[
        {
            "category":"Railroad",
            "type":"Transportation"
        }
    ],
    "sg:phone":"+1 918 245 8625",
    "sg:postcode":"74127",
    "sg:province":"OK",
    "wof:name":"Sand Springs Railway",
    "wof:placetype":"venue"
},
  "geometry": {"coordinates":[-96.083509,36.13914],"type":"Point"}
}