{
  "type": "Feature",
  "properties": {
    "addr:full":"1240 N Eastern Ave Moore OK 73160",
    "addr:housenumber":"1240",
    "addr:postcode":"73160",
    "addr:street":"N Eastern Ave",
    "iso:country":"US",
    "sg:address":"1240 N Eastern Ave",
    "sg:city":"Moore",
    "sg:classifiers":[
        {
            "category":"Retail",
            "subcategory":"Laundry & Dry Cleaning",
            "type":"Services"
        },
        {
            "category":"Shopping",
            "subcategory":"Clothing, Apparel, & Fashions",
            "type":"Retail Goods"
        }
    ],
    "sg:phone":"+1 405 895 7397",
    "sg:postcode":"73160",
    "sg:province":"OK",
    "sg:tags":[
        "alteration"
    ],
    "wof:name":"Han's Alterations",
    "wof:placetype":"venue"
},
  "geometry": {"coordinates":[-97.476828,35.347823],"type":"Point"}
}