{
  "type": "Feature",
  "properties": {
    "iso:country":"US",
    "sg:address":"4606 N Mingo Rd",
    "sg:city":"Tulsa",
    "sg:classifiers":[
        {
            "category":"Manufacturing",
            "subcategory":"Tools & Machinery",
            "type":"Manufacturing & Wholesale Goods"
        }
    ],
    "sg:phone":"+1 918 836 4200",
    "sg:postcode":"74117",
    "sg:province":"OK",
    "sg:tags":[
        "machine",
        "shop"
    ],
    "wof:name":"JIT Machine",
    "wof:placetype":"venue"
},
  "geometry": {"coordinates":[-95.868858,36.226027],"type":"Point"}
}