{
  "type": "Feature",
  "properties": {
    "iso:country":"US",
    "sg:address":"209 Darlene Dr",
    "sg:city":"Broken Bow",
    "sg:classifiers":[
        {
            "category":"Health Services",
            "subcategory":"Clinic",
            "type":"Services"
        }
    ],
    "sg:phone":"+1 580 584 3054",
    "sg:postcode":"74728",
    "sg:province":"OK",
    "wof:name":"Evergreen Occupational Health",
    "wof:placetype":"venue"
},
  "geometry": {"coordinates":[-94.752043,34.047508],"type":"Point"}
}