{
  "type": "Feature",
  "properties": {
    "addr:full":"7408 E 74th St Tulsa OK 74133",
    "addr:housenumber":"7408",
    "addr:postcode":"74133",
    "addr:street":"E 74Th St",
    "iso:country":"US",
    "sg:address":"7408 E 74th St",
    "sg:city":"Tulsa",
    "sg:classifiers":[
        {
            "category":"Professional",
            "subcategory":"Business Services",
            "type":"Services"
        }
    ],
    "sg:phone":"+1 918 249 9104",
    "sg:postcode":"74133",
    "sg:province":"OK",
    "wof:name":"Message In Movement Foundation",
    "wof:placetype":"venue"
},
  "geometry": {"coordinates":[-95.89142200000001,36.055552],"type":"Point"}
}