{
  "type": "Feature",
  "properties": {
    "iso:country":"US",
    "sg:address":"200 E Main St",
    "sg:city":"Antlers",
    "sg:classifiers":[
        {
            "category":"Shopping",
            "subcategory":"Used Merchandise",
            "type":"Retail Goods"
        }
    ],
    "sg:phone":"+1 580 298 9822",
    "sg:postcode":"74523",
    "sg:province":"OK",
    "sg:tags":[
        "pawnbroker"
    ],
    "wof:name":"Smith's Pawn & Gun & Rental",
    "wof:placetype":"venue"
},
  "geometry": {"coordinates":[-95.618074,34.231507],"type":"Point"}
}