{
  "type": "Feature",
  "properties": {
    "iso:country":"US",
    "sg:address":"1003 NE 12th St",
    "sg:city":"Wagoner",
    "sg:classifiers":[
        {
            "category":"Building & Trades",
            "subcategory":"Construction",
            "type":"Services"
        }
    ],
    "sg:phone":"+1 918 485 1133",
    "sg:postcode":"74467",
    "sg:province":"OK",
    "sg:tags":[
        "general",
        "contractor"
    ],
    "wof:name":"Ringling Construction",
    "wof:placetype":"venue"
},
  "geometry": {"coordinates":[-95.364903,35.971867],"type":"Point"}
}