{
  "type": "Feature",
  "properties": {
    "addr:full":"5829 Melton Dr Oklahoma City OK 73132",
    "addr:housenumber":"5829",
    "addr:postcode":"73132",
    "addr:street":"Melton Dr",
    "iso:country":"US",
    "sg:address":"5829 Melton Dr",
    "sg:city":"Oklahoma City",
    "sg:classifiers":[
        {
            "category":"Restaurant",
            "type":"Food & Drink"
        }
    ],
    "sg:phone":"+1 405 728 8343",
    "sg:postcode":"73132",
    "sg:province":"OK",
    "sg:tags":[
        "eating"
    ],
    "wof:name":"Jimmy's Egg Restaurant",
    "wof:placetype":"venue"
},
  "geometry": {"coordinates":[-97.619061,35.552504],"type":"Point"}
}