{
  "type": "Feature",
  "properties": {
    "iso:country":"US",
    "sg:address":"3020 N Walker Ave",
    "sg:city":"Oklahoma City",
    "sg:classifiers":[
        {
            "category":"Food & Beverages",
            "subcategory":"Groceries & Convenience Stores",
            "type":"Retail Goods"
        }
    ],
    "sg:phone":"+1 405 521 8321",
    "sg:postcode":"73103",
    "sg:province":"OK",
    "wof:name":"A A Food Mart",
    "wof:placetype":"venue"
},
  "geometry": {"coordinates":[-97.52093,35.500294],"type":"Point"}
}