{
  "type": "Feature",
  "properties": {
    "addr:full":"32 W Main St Durant OK 74701",
    "addr:housenumber":"32",
    "addr:postcode":"74701",
    "addr:street":"W Main St",
    "iso:country":"US",
    "sg:address":"32 W Main St",
    "sg:city":"Durant",
    "sg:classifiers":[
        {
            "category":"Building & Trades",
            "subcategory":"Plumbing",
            "type":"Services"
        }
    ],
    "sg:phone":"+1 580 924 1967",
    "sg:postcode":"74701",
    "sg:province":"OK",
    "sg:tags":[
        "refrigeration",
        "contractor"
    ],
    "wof:name":"Parker-Mitchell Rfrgn Svc",
    "wof:placetype":"venue"
},
  "geometry": {"coordinates":[-96.37622,33.990759],"type":"Point"}
}