{
  "type": "Feature",
  "properties": {
    "iso:country":"US",
    "sg:address":"2304 W Waco St",
    "sg:city":"Broken Arrow",
    "sg:classifiers":[
        {
            "category":"Manufacturing",
            "subcategory":"Printing",
            "type":"Manufacturing & Wholesale Goods"
        }
    ],
    "sg:phone":"+1 918 455 5937",
    "sg:postcode":"74011",
    "sg:province":"OK",
    "sg:tags":[
        "gift",
        "mfg",
        "de",
        "novelty",
        "scrapbook",
        "home"
    ],
    "wof:name":"Among Friends",
    "wof:placetype":"venue"
},
  "geometry": {"coordinates":[-95.816936,36.009069],"type":"Point"}
}