{
  "type": "Feature",
  "properties": {
    "addr:full":"23801 E 101st St Broken Arrow OK 74014",
    "addr:housenumber":"23801",
    "addr:postcode":"74014",
    "addr:street":"E 101St St",
    "iso:country":"US",
    "sg:address":"23801 E 101st St",
    "sg:city":"Broken Arrow",
    "sg:classifiers":[
        {
            "category":"Home & Garden",
            "subcategory":"Building Materials",
            "type":"Retail Goods"
        }
    ],
    "sg:phone":"+1 918 451 4488",
    "sg:postcode":"74014",
    "sg:province":"OK",
    "wof:name":"Keystone Millwork",
    "wof:placetype":"venue"
},
  "geometry": {"coordinates":[-95.71113,36.017357],"type":"Point"}
}