{
  "type": "Feature",
  "properties": {
    "iso:country":"US",
    "sg:address":"1602 NW Lawton Ave",
    "sg:city":"Lawton",
    "sg:classifiers":[
        {
            "category":"Home & Garden",
            "subcategory":"Garden Supply",
            "type":"Retail Goods"
        }
    ],
    "sg:phone":"+1 580 355 1242",
    "sg:postcode":"73507",
    "sg:province":"OK",
    "sg:tags":[
        "lawn",
        "mower"
    ],
    "wof:name":"Ron Stephens Svc",
    "wof:placetype":"venue"
},
  "geometry": {"coordinates":[-98.415245,34.62419],"type":"Point"}
}