{
  "type": "Feature",
  "properties": {
    "addr:full":"1350 W Sheridan Ave Oklahoma City OK 73106",
    "addr:housenumber":"1350",
    "addr:postcode":"73106",
    "addr:street":"W Sheridan Ave",
    "iso:country":"US",
    "sg:address":"1350 W Sheridan Ave",
    "sg:city":"Oklahoma City",
    "sg:classifiers":[
        {
            "category":"Building & Trades",
            "subcategory":"Construction",
            "type":"Services"
        }
    ],
    "sg:phone":"+1 405 239 8888",
    "sg:postcode":"73106",
    "sg:province":"OK",
    "sg:tags":[
        "general",
        "contractor"
    ],
    "wof:name":"Grand Construction LLC",
    "wof:placetype":"venue"
},
  "geometry": {"coordinates":[-97.53739299999999,35.466477],"type":"Point"}
}