{
  "type": "Feature",
  "properties": {
    "addr:full":"5534 E Reno Ave Oklahoma City OK 73117",
    "addr:housenumber":"5534",
    "addr:postcode":"73117",
    "addr:street":"E Reno Ave",
    "iso:country":"US",
    "sg:address":"5534 E Reno Ave",
    "sg:city":"Oklahoma City",
    "sg:classifiers":[
        {
            "category":"Professional",
            "subcategory":"Accounting & Tax Preparation",
            "type":"Services"
        }
    ],
    "sg:phone":"+1 405 619 5777",
    "sg:postcode":"73117",
    "sg:province":"OK",
    "sg:tags":[
        "return",
        "filing"
    ],
    "wof:name":"Tax Office",
    "wof:placetype":"venue"
},
  "geometry": {"coordinates":[-97.42465300000001,35.463995],"type":"Point"}
}