{
  "type": "Feature",
  "properties": {
    "iso:country":"US",
    "sg:address":"1010 W Gore Blvd",
    "sg:city":"Lawton",
    "sg:classifiers":[
        {
            "category":"Shopping",
            "subcategory":"Bicycles & Sporting Goods",
            "type":"Retail Goods"
        }
    ],
    "sg:phone":"+1 580 357 2841",
    "sg:postcode":"73501",
    "sg:province":"OK",
    "wof:name":"Bills Scoreboard Inc",
    "wof:placetype":"venue"
},
  "geometry": {"coordinates":[-98.404649,34.608611],"type":"Point"}
}