{
  "type": "Feature",
  "properties": {
    "addr:full":"936 NW 63rd St Oklahoma City OK 73116",
    "addr:housenumber":"936",
    "addr:postcode":"73116",
    "addr:street":"Nw 63Rd St",
    "iso:country":"US",
    "sg:address":"936 NW 63rd St",
    "sg:city":"Oklahoma City",
    "sg:classifiers":[
        {
            "category":"Shopping",
            "type":"Retail Goods"
        },
        {
            "category":"Restaurant",
            "type":"Food & Drink"
        }
    ],
    "sg:phone":"+1 405 840 9772",
    "sg:postcode":"73116",
    "sg:province":"OK",
    "sg:tags":[
        "eating",
        "mexican"
    ],
    "wof:name":"Laredo's Mexican Restaurant",
    "wof:placetype":"venue"
},
  "geometry": {"coordinates":[-97.52628799999999,35.537153],"type":"Point"}
}