{
  "type": "Feature",
  "properties": {
    "iso:country":"US",
    "sg:address":"9146 S Memorial Dr",
    "sg:city":"Tulsa",
    "sg:classifiers":[
        {
            "category":"Autos & Motor Vehicles",
            "subcategory":"Automobile Sales",
            "type":"Retail Goods"
        }
    ],
    "sg:phone":"+1 918 481 8000",
    "sg:postcode":"74133",
    "sg:province":"OK",
    "sg:tags":[
        "repair",
        "dealer",
        "car",
        "general"
    ],
    "wof:name":"South Pointe Chevrolet",
    "wof:placetype":"venue"
},
  "geometry": {"coordinates":[-95.88655900000001,36.030852],"type":"Point"}
}