{
  "type": "Feature",
  "properties": {
    "addr:full":"2700 SW 59th St Oklahoma City OK 73119",
    "addr:housenumber":"2700",
    "addr:postcode":"73119",
    "addr:street":"Sw 59Th St",
    "iso:country":"US",
    "sg:address":"2700 SW 59th St",
    "sg:city":"Oklahoma City",
    "sg:classifiers":[
        {
            "category":"Organizations",
            "subcategory":"Religious Organization",
            "type":"Services"
        }
    ],
    "sg:phone":"+1 405 685 7761",
    "sg:postcode":"73119",
    "sg:province":"OK",
    "sg:tags":[
        "baptist",
        "church"
    ],
    "wof:name":"Knob Hill Baptist Church",
    "wof:placetype":"venue"
},
  "geometry": {"coordinates":[-97.565569,35.406158],"type":"Point"}
}