{
  "type": "Feature",
  "properties": {
    "iso:country":"US",
    "sg:address":"304 S Air Depot Blvd",
    "sg:city":"Midwest City",
    "sg:classifiers":[
        {
            "category":"Health Services",
            "subcategory":"Doctor",
            "type":"Services"
        }
    ],
    "sg:phone":"+1 405 733 0002",
    "sg:postcode":"73110",
    "sg:province":"OK",
    "sg:tags":[
        "dentist"
    ],
    "wof:name":"Gentle Dental",
    "wof:placetype":"venue"
},
  "geometry": {"coordinates":[-97.406142,35.460712],"type":"Point"}
}