{
  "type": "Feature",
  "properties": {
    "iso:country":"US",
    "sg:address":"15151 Co Rd 230",
    "sg:city":"Red Rock",
    "sg:classifiers":[
        {
            "category":"Food & Beverages",
            "subcategory":"Groceries & Convenience Stores",
            "type":"Retail Goods"
        },
        {
            "category":"Travel",
            "subcategory":"Campground",
            "type":"Entertainment"
        }
    ],
    "sg:phone":"+1 580 723 4277",
    "sg:postcode":"74651",
    "sg:province":"OK",
    "sg:tags":[
        "sporting",
        "trailer",
        "variety"
    ],
    "wof:name":"Pete's Place",
    "wof:placetype":"venue"
},
  "geometry": {"coordinates":[-97.067784,36.391764],"type":"Point"}
}