{
  "type": "Feature",
  "properties": {
    "addr:full":"506 E Broadway Ave Cheyenne OK 73644",
    "addr:housenumber":"506",
    "addr:postcode":"73644",
    "addr:street":"E Broadway Ave",
    "iso:country":"US",
    "sg:address":"506 E Broadway Ave",
    "sg:city":"Cheyenne",
    "sg:classifiers":[
        {
            "category":"Government",
            "subcategory":"Office",
            "type":"Public Place"
        }
    ],
    "sg:phone":"+1 580 497 3365",
    "sg:postcode":"73644",
    "sg:province":"OK",
    "sg:tags":[
        "executive"
    ],
    "wof:name":"Commisioner Office",
    "wof:placetype":"venue"
},
  "geometry": {"coordinates":[-99.398383,35.410679],"type":"Point"}
}