{
  "type": "Feature",
  "properties": {
    "addr:full":"9401 S Shartel Ave Oklahoma City OK 73139",
    "addr:housenumber":"9401",
    "addr:postcode":"73139",
    "addr:street":"S Shartel Ave",
    "iso:country":"US",
    "sg:address":"9401 S Shartel Ave",
    "sg:city":"Oklahoma City",
    "sg:classifiers":[
        {
            "category":"Real Estate",
            "subcategory":"Real Estate Operator",
            "type":"Services"
        }
    ],
    "sg:phone":"+1 405 691 2661",
    "sg:postcode":"73139",
    "sg:province":"OK",
    "sg:tags":[
        "building",
        "apartment"
    ],
    "wof:name":"Brookwood Village Apartments",
    "wof:placetype":"venue"
},
  "geometry": {"coordinates":[-97.52465599999999,35.372679],"type":"Point"}
}