{
  "type": "Feature",
  "properties": {
    "iso:country":"US",
    "sg:address":"124 E 35th St",
    "sg:city":"Tulsa",
    "sg:classifiers":[
        {
            "category":"Travel",
            "subcategory":"Travel Agent",
            "type":"Entertainment"
        }
    ],
    "sg:phone":"+1 918 582 3717",
    "sg:postcode":"74105",
    "sg:province":"OK",
    "sg:tags":[
        "agency",
        "bureau"
    ],
    "sg:website":"www.bostonavetravel.com",
    "wof:name":"Boston Avenue Travel Inc",
    "wof:placetype":"venue"
},
  "geometry": {"coordinates":[-95.98030199999999,36.112937],"type":"Point"}
}