{
  "type": "Feature",
  "properties": {
    "iso:country":"US",
    "sg:address":"508 Boren Blvd",
    "sg:city":"Seminole",
    "sg:classifiers":[
        {
            "category":"Mining & Drilling",
            "type":"Manufacturing & Wholesale Goods"
        }
    ],
    "sg:phone":"+1 405 382 3494",
    "sg:postcode":"74868",
    "sg:province":"OK",
    "sg:tags":[
        "field",
        "oil"
    ],
    "wof:name":"Wallace Inc",
    "wof:placetype":"venue"
},
  "geometry": {"coordinates":[-96.679838,35.225533],"type":"Point"}
}