{
  "type": "Feature",
  "properties": {
    "iso:country":"US",
    "sg:address":"504 S State St",
    "sg:city":"Wagoner",
    "sg:classifiers":[
        {
            "category":"Organizations",
            "subcategory":"Religious Organization",
            "type":"Services"
        }
    ],
    "sg:phone":"+1 918 485 2664",
    "sg:postcode":"74467",
    "sg:province":"OK",
    "sg:tags":[
        "church"
    ],
    "wof:name":"Abundant Life Pentecostal",
    "wof:placetype":"venue"
},
  "geometry": {"coordinates":[-95.372246,35.955379],"type":"Point"}
}