{
  "type": "Feature",
  "properties": {
    "iso:country":"US",
    "sg:address":"610 S Lynn Riggs Blvd",
    "sg:city":"Claremore",
    "sg:classifiers":[
        {
            "category":"Insurance",
            "subcategory":"Insurance Agent",
            "type":"Services"
        }
    ],
    "sg:phone":"+1 918 342 3266",
    "sg:postcode":"74017",
    "sg:province":"OK",
    "wof:name":"David Merriman Insurance Inc",
    "wof:placetype":"venue"
},
  "geometry": {"coordinates":[-95.620377,36.306843],"type":"Point"}
}