{
  "type": "Feature",
  "properties": {
    "addr:full":"137 S 5th St W Collinsville OK 74021",
    "addr:housenumber":"137",
    "addr:postcode":"74021",
    "addr:street":"S 5Th St W",
    "iso:country":"US",
    "sg:address":"137 S 5th St W",
    "sg:city":"Collinsville",
    "sg:classifiers":[
        {
            "category":"Food & Beverages",
            "subcategory":"Groceries & Convenience Stores",
            "type":"Retail Goods"
        }
    ],
    "sg:phone":"+1 918 371 2263",
    "sg:postcode":"74021",
    "sg:province":"OK",
    "wof:name":"Miller's Picnic Supply",
    "wof:placetype":"venue"
},
  "geometry": {"coordinates":[-95.830077,36.364082],"type":"Point"}
}