{
  "type": "Feature",
  "properties": {
    "iso:country":"US",
    "sg:address":"1218 W Spruce Ave",
    "sg:city":"Enid",
    "sg:classifiers":[
        {
            "category":"Building & Trades",
            "subcategory":"Construction",
            "type":"Services"
        }
    ],
    "sg:phone":"+1 580 234 7266",
    "sg:postcode":"73703",
    "sg:province":"OK",
    "sg:tags":[
        "water",
        "driller",
        "well"
    ],
    "wof:name":"Bules Water Well Inc",
    "wof:placetype":"venue"
},
  "geometry": {"coordinates":[-97.894371,36.411969],"type":"Point"}
}