{
  "type": "Feature",
  "properties": {
    "iso:country":"US",
    "sg:address":"5103 S Sheridan Rd",
    "sg:city":"Tulsa",
    "sg:classifiers":[
        {
            "category":"Professional",
            "subcategory":"Computer Services",
            "type":"Services"
        }
    ],
    "sg:phone":"+1 918 254 9340",
    "sg:postcode":"74145",
    "sg:province":"OK",
    "sg:tags":[
        "related"
    ],
    "wof:name":"Fishercreations",
    "wof:placetype":"venue"
},
  "geometry": {"coordinates":[-95.90433299999999,36.088988],"type":"Point"}
}