{
  "type": "Feature",
  "properties": {
    "iso:country":"US",
    "sg:address":"8400 S Hillcrest Dr",
    "sg:city":"Oklahoma City",
    "sg:classifiers":[
        {
            "category":"Real Estate",
            "subcategory":"Architect",
            "type":"Services"
        }
    ],
    "sg:phone":"+1 405 601 8514",
    "sg:postcode":"73159",
    "sg:province":"OK",
    "sg:tags":[
        "building",
        "designer"
    ],
    "wof:name":"G S Home Design",
    "wof:placetype":"venue"
},
  "geometry": {"coordinates":[-97.556173,35.382255],"type":"Point"}
}