{
  "type": "Feature",
  "properties": {
    "addr:full":"2011 N Madison Pl Tulsa OK 74106",
    "addr:housenumber":"2011",
    "addr:postcode":"74106",
    "addr:street":"N Madison Pl",
    "iso:country":"US",
    "sg:address":"2011 N Madison Pl",
    "sg:city":"Tulsa",
    "sg:classifiers":[
        {
            "category":"Recreation",
            "subcategory":"Picnic Area",
            "type":"Entertainment"
        }
    ],
    "sg:phone":"+1 918 282 1770",
    "sg:postcode":"74106",
    "sg:province":"OK",
    "sg:tags":[
        "place",
        "arcade",
        "amusement"
    ],
    "wof:name":"Silver Gate City",
    "wof:placetype":"venue"
},
  "geometry": {"coordinates":[-95.97894100000001,36.183517],"type":"Point"}
}