{
  "type": "Feature",
  "properties": {
    "iso:country":"US",
    "sg:address":"236 S 1st St",
    "sg:city":"Vinita",
    "sg:classifiers":[
        {
            "category":"Retail",
            "subcategory":"Auto Repair",
            "type":"Services"
        }
    ],
    "sg:phone":"+1 918 256 7240",
    "sg:postcode":"74301",
    "sg:province":"OK",
    "sg:tags":[
        "body"
    ],
    "wof:name":"Auto Stripe and Window Tinting",
    "wof:placetype":"venue"
},
  "geometry": {"coordinates":[-95.153461,36.63534],"type":"Point"}
}