{
  "type": "Feature",
  "properties": {
    "iso:country":"US",
    "sg:address":"1913 N Blue Sage Dr",
    "sg:city":"Guymon",
    "sg:classifiers":[
        {
            "category":"Freight",
            "type":"Transportation"
        }
    ],
    "sg:phone":"+1 580 468 1973",
    "sg:postcode":"73942",
    "sg:province":"OK",
    "sg:tags":[
        "trucking"
    ],
    "wof:name":"Transpetco Transport Co",
    "wof:placetype":"venue"
},
  "geometry": {"coordinates":[-101.471203,36.699098],"type":"Point"}
}