{
  "type": "Feature",
  "properties": {
    "iso:country":"US",
    "sg:address":"205 W Maple Ave",
    "sg:city":"Enid",
    "sg:classifiers":[
        {
            "category":"Mining & Drilling",
            "type":"Manufacturing & Wholesale Goods"
        }
    ],
    "sg:phone":"+1 580 242 6040",
    "sg:postcode":"73701",
    "sg:province":"OK",
    "sg:tags":[
        "gathering",
        "oil",
        "natural",
        "producer",
        "gas",
        "pipeline"
    ],
    "wof:name":"Hiland Partners LP",
    "wof:placetype":"venue"
},
  "geometry": {"coordinates":[-97.881496,36.398901],"type":"Point"}
}