{
  "type": "Feature",
  "properties": {
    "iso:country":"US",
    "sg:address":"1404 E Lincoln Ave",
    "sg:city":"Sapulpa",
    "sg:classifiers":[
        {
            "category":"Professional",
            "subcategory":"Engineering",
            "type":"Services"
        }
    ],
    "sg:phone":"+1 918 227 1450",
    "sg:postcode":"74066",
    "sg:province":"OK",
    "sg:tags":[
        "production",
        "hydrogen"
    ],
    "wof:name":"Coastal Hydrogen Energy Inc",
    "wof:placetype":"venue"
},
  "geometry": {"coordinates":[-96.090478,35.995609],"type":"Point"}
}