{
  "type": "Feature",
  "properties": {
    "addr:full":"112 W Main St Oilton OK 74052",
    "addr:housenumber":"112",
    "addr:postcode":"74052",
    "addr:street":"W Main St",
    "iso:country":"US",
    "sg:address":"112 W Main St",
    "sg:city":"Oilton",
    "sg:classifiers":[
        {
            "category":"Personal",
            "type":"Services"
        }
    ],
    "sg:phone":"+1 918 862 3705",
    "sg:postcode":"74052",
    "sg:province":"OK",
    "sg:tags":[
        "department",
        "motor",
        "vehicle"
    ],
    "wof:name":"Oilton Tag Agency",
    "wof:placetype":"venue"
},
  "geometry": {"coordinates":[-96.58713400000001,36.086474],"type":"Point"}
}