{
  "type": "Feature",
  "properties": {
    "iso:country":"US",
    "sg:address":"1043 Carlisle Cir",
    "sg:city":"Norman",
    "sg:classifiers":[
        {
            "category":"Professional",
            "subcategory":"Accounting & Tax Preparation",
            "type":"Services"
        }
    ],
    "sg:phone":"+1 405 321 8584",
    "sg:postcode":"73069",
    "sg:province":"OK",
    "wof:name":"Dyan Shetley Bookkeeping",
    "wof:placetype":"venue"
},
  "geometry": {"coordinates":[-97.462415,35.231361],"type":"Point"}
}