{
  "type": "Feature",
  "properties": {
    "addr:full":"125 E 1st St Edmond OK 73034",
    "addr:housenumber":"125",
    "addr:postcode":"73034",
    "addr:street":"E 1St St",
    "iso:country":"US",
    "sg:address":"125 E 1st St",
    "sg:city":"Edmond",
    "sg:classifiers":[
        {
            "category":"Banks & Credit Unions",
            "subcategory":"Bank",
            "type":"Services"
        }
    ],
    "sg:phone":"+1 405 782 4390",
    "sg:postcode":"73034",
    "sg:province":"OK",
    "sg:tags":[
        "institution",
        "business"
    ],
    "wof:name":"Union Bank",
    "wof:placetype":"venue"
},
  "geometry": {"coordinates":[-97.478632,35.654054],"type":"Point"}
}