{
  "type": "Feature",
  "properties": {
    "iso:country":"US",
    "sg:address":"5225 Rocky Ridge Rd",
    "sg:city":"Kaw City",
    "sg:classifiers":[
        {
            "category":"Professional",
            "subcategory":"Computer Services",
            "type":"Services"
        }
    ],
    "sg:phone":"+1 580 762 5664",
    "sg:postcode":"74641",
    "sg:province":"OK",
    "sg:tags":[
        "graphic",
        "electronic",
        "form"
    ],
    "wof:name":"Legend Graphics",
    "wof:placetype":"venue"
},
  "geometry": {"coordinates":[-96.923705,36.768499],"type":"Point"}
}