{
  "type": "Feature",
  "properties": {
    "addr:full":"11802 S Memorial Dr Bixby OK 74008",
    "addr:housenumber":"11802",
    "addr:postcode":"74008",
    "addr:street":"S Memorial Dr",
    "iso:country":"US",
    "sg:address":"11802 S Memorial Dr",
    "sg:city":"Bixby",
    "sg:classifiers":[
        {
            "category":"Professional",
            "type":"Services"
        }
    ],
    "sg:phone":"+1 918 369 8989",
    "sg:postcode":"74008",
    "sg:province":"OK",
    "sg:website":"www.toddsgarage.net",
    "wof:name":"Advanced Wholesale",
    "wof:placetype":"venue"
},
  "geometry": {"coordinates":[-95.88648999999999,35.990821],"type":"Point"}
}