{
  "type": "Feature",
  "properties": {
    "iso:country":"US",
    "sg:address":"4216 N Portland Ave",
    "sg:city":"Oklahoma City",
    "sg:classifiers":[
        {
            "category":"Professional",
            "subcategory":"Computer Services",
            "type":"Services"
        },
        {
            "category":"Shopping",
            "subcategory":"Computers & Home Electronics",
            "type":"Retail Goods"
        }
    ],
    "sg:phone":"+1 405 949 5531",
    "sg:postcode":"73112",
    "sg:province":"OK",
    "sg:tags":[
        "prepackaged",
        "software"
    ],
    "wof:name":"O A O Healthcare Solutions",
    "wof:placetype":"venue"
},
  "geometry": {"coordinates":[-97.58334000000001,35.513206],"type":"Point"}
}