{
  "type": "Feature",
  "properties": {
    "addr:full":"700 E Golden Ave Copan OK 74022",
    "addr:housenumber":"700",
    "addr:postcode":"74022",
    "addr:street":"E Golden Ave",
    "iso:country":"US",
    "sg:address":"700 E Golden Ave",
    "sg:city":"Copan",
    "sg:classifiers":[
        {
            "category":"Building & Trades",
            "subcategory":"Construction",
            "type":"Services"
        }
    ],
    "sg:phone":"+1 918 532 4558",
    "sg:postcode":"74022",
    "sg:province":"OK",
    "sg:tags":[
        "home",
        "improvement"
    ],
    "wof:name":"Copan Country Store",
    "wof:placetype":"venue"
},
  "geometry": {"coordinates":[-95.924734,36.90222],"type":"Point"}
}