{
  "type": "Feature",
  "properties": {
    "iso:country":"US",
    "sg:address":"5666 S 122nd East Ave",
    "sg:city":"Tulsa",
    "sg:classifiers":[
        {
            "category":"Wholesale",
            "subcategory":"Machinery & Supplies",
            "type":"Manufacturing & Wholesale Goods"
        }
    ],
    "sg:phone":"+1 918 249 9865",
    "sg:postcode":"74146",
    "sg:province":"OK",
    "sg:tags":[
        "dock",
        "loading",
        "equipment"
    ],
    "wof:name":"Johnson Equipment Co",
    "wof:placetype":"venue"
},
  "geometry": {"coordinates":[-95.840635,36.08156],"type":"Point"}
}