{
  "type": "Feature",
  "properties": {
    "iso:country":"US",
    "sg:address":"800 NW 67th St",
    "sg:city":"Oklahoma City",
    "sg:classifiers":[
        {
            "category":"Building & Trades",
            "subcategory":"Construction",
            "type":"Services"
        }
    ],
    "sg:phone":"+1 405 842 0721",
    "sg:postcode":"73116",
    "sg:province":"OK",
    "sg:tags":[
        "repairing",
        "family",
        "house",
        "general",
        "contractor",
        "remodeling"
    ],
    "wof:name":"Professional Remodeling Svc",
    "wof:placetype":"venue"
},
  "geometry": {"coordinates":[-97.526861,35.540483],"type":"Point"}
}