{
  "type": "Feature",
  "properties": {
    "addr:full":"601 SE 6th St Wagoner OK 74467",
    "addr:housenumber":"601",
    "addr:postcode":"74467",
    "addr:street":"Se 6Th St",
    "iso:country":"US",
    "sg:address":"601 SE 6th St",
    "sg:city":"Wagoner",
    "sg:classifiers":[
        {
            "category":"Education",
            "subcategory":"School",
            "type":"Public Place"
        }
    ],
    "sg:phone":"+1 918 485 2228",
    "sg:postcode":"74467",
    "sg:province":"OK",
    "wof:name":"Wagoner Public School",
    "wof:placetype":"venue"
},
  "geometry": {"coordinates":[-95.370699,35.953266],"type":"Point"}
}