{
  "type": "Feature",
  "properties": {
    "iso:country":"US",
    "sg:address":"2009 Shorewood Ln",
    "sg:city":"Edmond",
    "sg:classifiers":[
        {
            "category":"Real Estate",
            "subcategory":"Real Estate Agent",
            "type":"Services"
        }
    ],
    "sg:phone":"+1 405 340 1582",
    "sg:postcode":"73003",
    "sg:province":"OK",
    "wof:name":"Gary & Marian Crandall",
    "wof:placetype":"venue"
},
  "geometry": {"coordinates":[-97.510842,35.655926],"type":"Point"}
}