{
  "type": "Feature",
  "properties": {
    "iso:country":"US",
    "sg:address":"200 N Broadway St",
    "sg:city":"Holdenville",
    "sg:classifiers":[
        {
            "category":"Government",
            "subcategory":"Office",
            "type":"Public Place"
        }
    ],
    "sg:phone":"+1 405 379 2174",
    "sg:postcode":"74848",
    "sg:province":"OK",
    "wof:name":"Hughes County Election Board",
    "wof:placetype":"venue"
},
  "geometry": {"coordinates":[-96.399433,35.084021],"type":"Point"}
}