{
  "type": "Feature",
  "properties": {
    "iso:country":"US",
    "sg:address":"8320 NW 34th Ter",
    "sg:city":"Bethany",
    "sg:classifiers":[
        {
            "category":"Organizations",
            "subcategory":"Membership Organization",
            "type":"Services"
        }
    ],
    "sg:phone":"+1 405 787 1250",
    "sg:postcode":"73008",
    "sg:province":"OK",
    "wof:name":"RACE Inc",
    "wof:placetype":"venue"
},
  "geometry": {"coordinates":[-97.662125,35.506016],"type":"Point"}
}