{
  "type": "Feature",
  "properties": {
    "iso:country":"US",
    "sg:address":"1304 N Cypress Ave",
    "sg:city":"Broken Arrow",
    "sg:classifiers":[
        {
            "category":"Building & Trades",
            "subcategory":"Construction",
            "type":"Services"
        }
    ],
    "sg:phone":"+1 918 250 8330",
    "sg:postcode":"74012",
    "sg:province":"OK",
    "sg:tags":[
        "hanging",
        "contractor"
    ],
    "wof:name":"Charles E Story",
    "wof:placetype":"venue"
},
  "geometry": {"coordinates":[-95.846493,36.068638],"type":"Point"}
}