{
  "type": "Feature",
  "properties": {
    "addr:full":"12206 Skyline Dr Jenks OK 74037",
    "addr:housenumber":"12206",
    "addr:postcode":"74037",
    "addr:street":"Skyline Dr",
    "iso:country":"US",
    "sg:address":"12206 Skyline Dr",
    "sg:city":"Jenks",
    "sg:classifiers":[
        {
            "category":"Banks & Credit Unions",
            "subcategory":"Investment Brokerage",
            "type":"Services"
        }
    ],
    "sg:phone":"+1 918 296 9418",
    "sg:postcode":"74037",
    "sg:province":"OK",
    "wof:name":"Investment Professionals Inc",
    "wof:placetype":"venue"
},
  "geometry": {"coordinates":[-95.957272,35.98642],"type":"Point"}
}