{
  "type": "Feature",
  "properties": {
    "iso:country":"US",
    "sg:address":"1509 E Main St",
    "sg:city":"Cushing",
    "sg:classifiers":[
        {
            "category":"Retail",
            "subcategory":"Car Wash",
            "type":"Services"
        }
    ],
    "sg:phone":"+1 918 223 6566",
    "sg:postcode":"74023",
    "sg:province":"OK",
    "sg:tags":[
        "polishing",
        "washing"
    ],
    "wof:name":"Auto Brite Co",
    "wof:placetype":"venue"
},
  "geometry": {"coordinates":[-96.747443,35.984947],"type":"Point"}
}