{
  "type": "Feature",
  "properties": {
    "addr:full":"1528 Meyers Pl Oklahoma City OK 73111",
    "addr:housenumber":"1528",
    "addr:postcode":"73111",
    "addr:street":"Meyers Pl",
    "iso:country":"US",
    "sg:address":"1528 Meyers Pl",
    "sg:city":"Oklahoma City",
    "sg:classifiers":[
        {
            "category":"Shopping",
            "subcategory":"Books",
            "type":"Retail Goods"
        }
    ],
    "sg:phone":"+1 405 424 7889",
    "sg:postcode":"73111",
    "sg:province":"OK",
    "wof:name":"Spiritual Connection Book",
    "wof:placetype":"venue"
},
  "geometry": {"coordinates":[-97.483934,35.519583],"type":"Point"}
}