{
  "type": "Feature",
  "properties": {
    "addr:full":"400 S 2nd St Mcalester OK 74501",
    "addr:housenumber":"400",
    "addr:postcode":"74501",
    "addr:street":"S 2Nd St",
    "iso:country":"US",
    "sg:address":"400 S 2nd St",
    "sg:city":"Mcalester",
    "sg:classifiers":[
        {
            "category":"Organizations",
            "subcategory":"Community Association",
            "type":"Services"
        }
    ],
    "sg:phone":"+1 918 423 6308",
    "sg:postcode":"74501",
    "sg:province":"OK",
    "sg:tags":[
        "military"
    ],
    "wof:name":"American Legion",
    "wof:placetype":"venue"
},
  "geometry": {"coordinates":[-95.769082,34.927382],"type":"Point"}
}