{
  "type": "Feature",
  "properties": {
    "iso:country":"US",
    "sg:address":"124 W Harrison Ave",
    "sg:city":"Guthrie",
    "sg:classifiers":[
        {
            "category":"Restaurant",
            "type":"Food & Drink"
        }
    ],
    "sg:phone":"+1 405 260 2222",
    "sg:postcode":"73044",
    "sg:province":"OK",
    "wof:name":"Pollard Steakhouse",
    "wof:placetype":"venue"
},
  "geometry": {"coordinates":[-97.426302,35.877072],"type":"Point"}
}