{
  "type": "Feature",
  "properties": {
    "iso:country":"US",
    "sg:address":"2911 N Grand Ave",
    "sg:city":"Enid",
    "sg:classifiers":[
        {
            "category":"Building & Trades",
            "subcategory":"Pest Control",
            "type":"Services"
        }
    ],
    "sg:phone":"+1 580 242 3811",
    "sg:postcode":"73701",
    "sg:province":"OK",
    "wof:name":"Veterans Acres Inc",
    "wof:placetype":"venue"
},
  "geometry": {"coordinates":[-97.87827900000001,36.42723],"type":"Point"}
}