{
  "type": "Feature",
  "properties": {
    "iso:country":"US",
    "sg:address":"8925 E 61st St S",
    "sg:city":"Tulsa",
    "sg:classifiers":[
        {
            "category":"Real Estate",
            "subcategory":"Real Estate Agent",
            "type":"Services"
        }
    ],
    "sg:phone":"+1 918 254 5953",
    "sg:postcode":"74133",
    "sg:province":"OK",
    "wof:name":"Property One",
    "wof:placetype":"venue"
},
  "geometry": {"coordinates":[-95.876727,36.075536],"type":"Point"}
}