{
  "type": "Feature",
  "properties": {
    "iso:country":"US",
    "sg:address":"200 S Broadway St",
    "sg:city":"Sayre",
    "sg:classifiers":[
        {
            "category":"Real Estate",
            "subcategory":"Real Estate Operator",
            "type":"Services"
        }
    ],
    "sg:phone":"+1 580 928 2999",
    "sg:postcode":"73662",
    "sg:province":"OK",
    "sg:tags":[
        "building",
        "apartment"
    ],
    "wof:name":"Southgate Apartments",
    "wof:placetype":"venue"
},
  "geometry": {"coordinates":[-99.638529,35.289041],"type":"Point"}
}