{
  "type": "Feature",
  "properties": {
    "addr:full":"4004 Birdneck Edmond OK 73025",
    "addr:housenumber":"4004",
    "addr:postcode":"73025",
    "addr:street":"Birdneck Edmond",
    "iso:country":"US",
    "sg:address":"4004 Birdneck",
    "sg:city":"Edmond",
    "sg:classifiers":[
        {
            "category":"Professional",
            "subcategory":"Management & Consulting",
            "type":"Services"
        }
    ],
    "sg:phone":"+1 405 844 8903",
    "sg:postcode":"73025",
    "sg:province":"OK",
    "sg:tags":[
        "public",
        "relations"
    ],
    "wof:name":"Ace Aerial Artisty",
    "wof:placetype":"venue"
},
  "geometry": {"coordinates":[-97.517304,35.697489],"type":"Point"}
}