{
  "type": "Feature",
  "properties": {
    "iso:country":"US",
    "sg:address":"922 Roberts St",
    "sg:city":"Bokchito",
    "sg:classifiers":[
        {
            "category":"Government",
            "subcategory":"Office",
            "type":"Public Place"
        }
    ],
    "sg:phone":"+1 580 295 3737",
    "sg:postcode":"74726",
    "sg:province":"OK",
    "sg:tags":[
        "legislative",
        "body"
    ],
    "wof:name":"County Commissioner Office",
    "wof:placetype":"venue"
},
  "geometry": {"coordinates":[-96.132959,34.015213],"type":"Point"}
}