{
  "type": "Feature",
  "properties": {
    "addr:full":"2330 US Hwy 64 Guymon OK 73942",
    "addr:housenumber":"2330",
    "addr:postcode":"73942",
    "addr:street":"Us Hwy 64",
    "iso:country":"US",
    "sg:address":"2330 US Hwy 64",
    "sg:city":"Guymon",
    "sg:classifiers":[
        {
            "category":"Retail",
            "subcategory":"Auto Repair",
            "type":"Services"
        }
    ],
    "sg:phone":"+1 580 338 5267",
    "sg:postcode":"73942",
    "sg:province":"OK",
    "sg:tags":[
        "automobile",
        "lubrication"
    ],
    "wof:name":"KWIK Kar Lube & Tune",
    "wof:placetype":"venue"
},
  "geometry": {"coordinates":[-101.484937,36.704035],"type":"Point"}
}