{
  "type": "Feature",
  "properties": {
    "addr:full":"1550 S Harvard Ave Tulsa OK 74112",
    "addr:housenumber":"1550",
    "addr:postcode":"74112",
    "addr:street":"S Harvard Ave",
    "iso:country":"US",
    "sg:address":"1550 S Harvard Ave",
    "sg:city":"Tulsa",
    "sg:classifiers":[
        {
            "category":"Insurance",
            "subcategory":"Insurance Agent",
            "type":"Services"
        }
    ],
    "sg:phone":"+1 918 743 5996",
    "sg:postcode":"74112",
    "sg:province":"OK",
    "wof:name":"Bruening Agency",
    "wof:placetype":"venue"
},
  "geometry": {"coordinates":[-95.940442,36.139658],"type":"Point"}
}