{
  "type": "Feature",
  "properties": {
    "iso:country":"US",
    "sg:address":"440 S Houston Ave",
    "sg:city":"Tulsa",
    "sg:classifiers":[
        {
            "category":"Government",
            "subcategory":"Office",
            "type":"Public Place"
        }
    ],
    "sg:phone":"+1 918 581 2674",
    "sg:postcode":"74127",
    "sg:province":"OK",
    "sg:tags":[
        "state",
        "taxation"
    ],
    "wof:name":"State Auditor",
    "wof:placetype":"venue"
},
  "geometry": {"coordinates":[-95.99822,36.148109],"type":"Point"}
}