{
  "type": "Feature",
  "properties": {
    "iso:country":"US",
    "sg:address":"4300 N Western Ave",
    "sg:city":"Oklahoma City",
    "sg:classifiers":[
        {
            "category":"Food & Beverages",
            "subcategory":"Groceries & Convenience Stores",
            "type":"Retail Goods"
        }
    ],
    "sg:phone":"+1 405 528 2064",
    "sg:postcode":"73118",
    "sg:province":"OK",
    "wof:name":"Total Petroleum Inc",
    "wof:placetype":"venue"
},
  "geometry": {"coordinates":[-97.529831,35.515094],"type":"Point"}
}