{
  "type": "Feature",
  "properties": {
    "iso:country":"US",
    "sg:address":"11109 N 185th East Ave",
    "sg:city":"Owasso",
    "sg:classifiers":[
        {
            "category":"Professional",
            "subcategory":"Business Services",
            "type":"Services"
        }
    ],
    "sg:phone":"+1 918 694 4329",
    "sg:postcode":"74055",
    "sg:province":"OK",
    "wof:name":"Enterprise Data Solutions Inc",
    "wof:placetype":"venue"
},
  "geometry": {"coordinates":[-95.767259,36.314853],"type":"Point"}
}