{
  "type": "Feature",
  "properties": {
    "iso:country":"US",
    "sg:address":"18215 Quail Creek Rd",
    "sg:city":"Claremore",
    "sg:classifiers":[
        {
            "category":"Manufacturing",
            "subcategory":"Wood Products",
            "type":"Manufacturing & Wholesale Goods"
        }
    ],
    "sg:phone":"+1 918 342 9663",
    "sg:postcode":"74017",
    "sg:province":"OK",
    "sg:tags":[
        "mfg"
    ],
    "wof:name":"Sooner Pallet Services Inc",
    "wof:placetype":"venue"
},
  "geometry": {"coordinates":[-95.58441500000001,36.347743],"type":"Point"}
}