{
  "type": "Feature",
  "properties": {
    "addr:full":"6420 NW Expy Oklahoma City OK 73132",
    "addr:housenumber":"6420",
    "addr:postcode":"73132",
    "addr:street":"Nw Expy",
    "iso:country":"US",
    "sg:address":"6420 NW Expy",
    "sg:city":"Oklahoma City",
    "sg:classifiers":[
        {
            "category":"Restaurant",
            "type":"Food & Drink"
        }
    ],
    "sg:phone":"+1 405 720 0808",
    "sg:postcode":"73132",
    "sg:province":"OK",
    "wof:name":"Gaucho's Grill",
    "wof:placetype":"venue"
},
  "geometry": {"coordinates":[-97.62717499999999,35.552888],"type":"Point"}
}