{
  "type": "Feature",
  "properties": {
    "iso:country":"US",
    "sg:address":"924 Cedar Ave",
    "sg:city":"Yukon",
    "sg:classifiers":[
        {
            "category":"Retail",
            "subcategory":"Auto Repair",
            "type":"Services"
        }
    ],
    "sg:phone":"+1 405 354 6721",
    "sg:postcode":"73099",
    "sg:province":"OK",
    "sg:tags":[
        "general"
    ],
    "wof:name":"Jt Service",
    "wof:placetype":"venue"
},
  "geometry": {"coordinates":[-97.758285,35.508894],"type":"Point"}
}