{
  "type": "Feature",
  "properties": {
    "iso:country":"US",
    "sg:address":"100 E Creek Ave",
    "sg:city":"Sallisaw",
    "sg:classifiers":[
        {
            "category":"Organizations",
            "subcategory":"Religious Organization",
            "type":"Services"
        }
    ],
    "sg:phone":"+1 918 775 5812",
    "sg:postcode":"74955",
    "sg:province":"OK",
    "sg:tags":[
        "church"
    ],
    "wof:name":"Bethel Baptist Church",
    "wof:placetype":"venue"
},
  "geometry": {"coordinates":[-94.79005600000001,35.457511],"type":"Point"}
}