{
  "type": "Feature",
  "properties": {
    "iso:country":"US",
    "sg:address":"700 E Ballentine Rd",
    "sg:city":"Tahlequah",
    "sg:classifiers":[
        {
            "category":"Sports & Exercise",
            "subcategory":"Golf",
            "type":"Entertainment"
        }
    ],
    "sg:phone":"+1 918 456 5100",
    "sg:postcode":"74464",
    "sg:province":"OK",
    "sg:tags":[
        "course",
        "public"
    ],
    "wof:name":"Cherrys",
    "wof:placetype":"venue"
},
  "geometry": {"coordinates":[-94.97102099999999,35.88533],"type":"Point"}
}