{
  "type": "Feature",
  "properties": {
    "addr:full":"3100 E 26th St S Muskogee OK 74403",
    "addr:housenumber":"3100",
    "addr:postcode":"74403",
    "addr:street":"E 26Th St S",
    "iso:country":"US",
    "sg:address":"3100 E 26th St S",
    "sg:city":"Muskogee",
    "sg:classifiers":[
        {
            "category":"Building & Trades",
            "subcategory":"Construction",
            "type":"Services"
        }
    ],
    "sg:phone":"+1 918 683 3931",
    "sg:postcode":"74403",
    "sg:province":"OK",
    "sg:tags":[
        "concrete",
        "contractor"
    ],
    "wof:name":"Danny Hughes Con Specialist",
    "wof:placetype":"venue"
},
  "geometry": {"coordinates":[-95.33147099999999,35.72061],"type":"Point"}
}