{
  "type": "Feature",
  "properties": {
    "iso:country":"US",
    "sg:address":"1657 S Yale Ave",
    "sg:city":"Tulsa",
    "sg:classifiers":[
        {
            "category":"Personal",
            "subcategory":"Beauty Salon",
            "type":"Services"
        }
    ],
    "sg:phone":"+1 918 742 7895",
    "sg:postcode":"74112",
    "sg:province":"OK",
    "wof:name":"Instyle Hair Salon",
    "wof:placetype":"venue"
},
  "geometry": {"coordinates":[-95.92241199999999,36.133674],"type":"Point"}
}