{
  "type": "Feature",
  "properties": {
    "iso:country":"US",
    "sg:address":"4971 S Union Ave",
    "sg:city":"Tulsa",
    "sg:classifiers":[
        {
            "category":"Personal",
            "subcategory":"Beauty Salon",
            "type":"Services"
        }
    ],
    "sg:phone":"+1 918 446 5787",
    "sg:postcode":"74107",
    "sg:province":"OK",
    "sg:tags":[
        "manicuring"
    ],
    "wof:name":"Angel Nails",
    "wof:placetype":"venue"
},
  "geometry": {"coordinates":[-96.011562,36.09073],"type":"Point"}
}