{
  "type": "Feature",
  "properties": {
    "addr:full":"13962 N Lost City Rd Hulbert OK 74441",
    "addr:housenumber":"13962",
    "addr:postcode":"74441",
    "addr:street":"N Lost City Rd",
    "iso:country":"US",
    "sg:address":"13962 N Lost City Rd",
    "sg:city":"Hulbert",
    "sg:classifiers":[
        {
            "category":"Shopping",
            "subcategory":"Computers & Home Electronics",
            "type":"Retail Goods"
        }
    ],
    "sg:phone":"+1 918 207 1937",
    "sg:postcode":"74441",
    "sg:province":"OK",
    "sg:tags":[
        "equipment",
        "dealer"
    ],
    "wof:name":"Next Tek Computer Solutions",
    "wof:placetype":"venue"
},
  "geometry": {"coordinates":[-95.13403099999999,35.97362],"type":"Point"}
}