{
  "type": "Feature",
  "properties": {
    "addr:full":"200 7th St Barnsdall OK 74002",
    "addr:housenumber":"200",
    "addr:postcode":"74002",
    "addr:street":"7Th St",
    "iso:country":"US",
    "sg:address":"200 7th St",
    "sg:city":"Barnsdall",
    "sg:classifiers":[
        {
            "category":"Organizations",
            "subcategory":"Religious Organization",
            "type":"Services"
        }
    ],
    "sg:phone":"+1 918 847 2752",
    "sg:postcode":"74002",
    "sg:province":"OK",
    "sg:tags":[
        "church"
    ],
    "wof:name":"United Methodist Church",
    "wof:placetype":"venue"
},
  "geometry": {"coordinates":[-96.16430699999999,36.560756],"type":"Point"}
}