{
  "type": "Feature",
  "properties": {
    "iso:country":"US",
    "sg:address":"6200 NW 39th Expy",
    "sg:city":"Bethany",
    "sg:classifiers":[
        {
            "category":"Autos & Motor Vehicles",
            "subcategory":"Motorcycle Sales",
            "type":"Retail Goods"
        }
    ],
    "sg:phone":"+1 405 947 7278",
    "sg:postcode":"73008",
    "sg:province":"OK",
    "sg:tags":[
        "scooter"
    ],
    "wof:name":"Performance Cycle",
    "wof:placetype":"venue"
},
  "geometry": {"coordinates":[-97.62401199999999,35.511151],"type":"Point"}
}