{
  "type": "Feature",
  "properties": {
    "iso:country":"US",
    "sg:address":"517 N Husband St",
    "sg:city":"Stillwater",
    "sg:classifiers":[
        {
            "category":"Home & Garden",
            "subcategory":"Building Materials",
            "type":"Retail Goods"
        },
        {
            "category":"Building & Trades",
            "subcategory":"Construction",
            "type":"Services"
        }
    ],
    "sg:phone":"+1 405 377 6131",
    "sg:postcode":"74075",
    "sg:province":"OK",
    "sg:tags":[
        "glass",
        "glazing",
        "door",
        "contractor"
    ],
    "sg:website":"www.stillcommglass.com",
    "wof:name":"Stillwater Commercial Glass LP",
    "wof:placetype":"venue"
},
  "geometry": {"coordinates":[-97.060378,36.127937],"type":"Point"}
}