{
  "type": "Feature",
  "properties": {
    "iso:country":"US",
    "sg:address":"3332 S Santa Fe Ave",
    "sg:city":"Tulsa",
    "sg:classifiers":[
        {
            "category":"Retail",
            "subcategory":"Auto Repair",
            "type":"Services"
        }
    ],
    "sg:phone":"+1 918 587 1965",
    "sg:postcode":"74107",
    "sg:province":"OK",
    "sg:tags":[
        "body"
    ],
    "wof:name":"West Tulsa Paint & Body Shop",
    "wof:placetype":"venue"
},
  "geometry": {"coordinates":[-96.009542,36.115396],"type":"Point"}
}