{
  "type": "Feature",
  "properties": {
    "addr:full":"4144 E Admiral Pl Tulsa OK 74115",
    "addr:housenumber":"4144",
    "addr:postcode":"74115",
    "addr:street":"E Admiral Pl",
    "iso:country":"US",
    "sg:address":"4144 E Admiral Pl",
    "sg:city":"Tulsa",
    "sg:classifiers":[
        {
            "category":"Shopping",
            "subcategory":"Bicycles & Sporting Goods",
            "type":"Retail Goods"
        }
    ],
    "sg:phone":"+1 918 834 7989",
    "sg:postcode":"74115",
    "sg:province":"OK",
    "sg:tags":[
        "gun",
        "gunsmith"
    ],
    "sg:website":"www.dongsguns.com",
    "wof:name":"Dong's Gun-Archery-Reloading",
    "wof:placetype":"venue"
},
  "geometry": {"coordinates":[-95.92821600000001,36.160673],"type":"Point"}
}