{
  "type": "Feature",
  "properties": {
    "addr:full":"609 S Mississippi Ave Atoka OK 74525",
    "addr:housenumber":"609",
    "addr:postcode":"74525",
    "addr:street":"S Mississippi Ave",
    "iso:country":"US",
    "sg:address":"609 S Mississippi Ave",
    "sg:city":"Atoka",
    "sg:classifiers":[
        {
            "category":"Restaurant",
            "type":"Food & Drink"
        }
    ],
    "sg:menulink":"http://www.allmenus.com/ok/central-atoka/68490-mazzios-pizza/menu/",
    "sg:phone":"+1 580 889 8855",
    "sg:postcode":"74525",
    "sg:province":"OK",
    "sg:tags":[
        "american",
        "pizza"
    ],
    "wof:name":"Mazzio's Pizza",
    "wof:placetype":"venue"
},
  "geometry": {"coordinates":[-96.130427,34.380918],"type":"Point"}
}