{
  "type": "Feature",
  "properties": {
    "addr:full":"2909 N Ann Arbor Ave Oklahoma City OK 73127",
    "addr:housenumber":"2909",
    "addr:postcode":"73127",
    "addr:street":"N Ann Arbor Ave",
    "iso:country":"US",
    "sg:address":"2909 N Ann Arbor Ave",
    "sg:city":"Oklahoma City",
    "sg:classifiers":[
        {
            "category":"Education",
            "subcategory":"School",
            "type":"Public Place"
        }
    ],
    "sg:phone":"+1 405 942 8673",
    "sg:postcode":"73127",
    "sg:province":"OK",
    "sg:website":"www.putnamcityschools.com",
    "wof:name":"Windsor Hills Elementary Schl",
    "wof:placetype":"venue"
},
  "geometry": {"coordinates":[-97.610106,35.499878],"type":"Point"}
}