{
  "type": "Feature",
  "properties": {
    "addr:full":"9212 N Rockwell Ave Oklahoma City OK 73132",
    "addr:housenumber":"9212",
    "addr:postcode":"73132",
    "addr:street":"N Rockwell Ave",
    "iso:country":"US",
    "sg:address":"9212 N Rockwell Ave",
    "sg:city":"Oklahoma City",
    "sg:classifiers":[
        {
            "category":"Banks & Credit Unions",
            "subcategory":"Bank",
            "type":"Services"
        }
    ],
    "sg:phone":"+1 405 728 1260",
    "sg:postcode":"73132",
    "sg:province":"OK",
    "sg:tags":[
        "loan",
        "real estate"
    ],
    "wof:name":"Smith & Assoc",
    "wof:placetype":"venue"
},
  "geometry": {"coordinates":[-97.638321,35.564679],"type":"Point"}
}