{
  "type": "Feature",
  "properties": {
    "iso:country":"US",
    "sg:address":"7038 S Richmond Ave",
    "sg:city":"Tulsa",
    "sg:classifiers":[
        {
            "category":"Banks & Credit Unions",
            "subcategory":"Financial Services",
            "type":"Services"
        }
    ],
    "sg:phone":"+1 918 492 6036",
    "sg:postcode":"74136",
    "sg:province":"OK",
    "sg:tags":[
        "investment",
        "closed"
    ],
    "wof:name":"Geole Investments Inc",
    "wof:placetype":"venue"
},
  "geometry": {"coordinates":[-95.92787,36.060866],"type":"Point"}
}