{
  "type": "Feature",
  "properties": {
    "iso:country":"US",
    "sg:address":"3132 S Garnett Rd",
    "sg:city":"Tulsa",
    "sg:classifiers":[
        {
            "category":"Shopping",
            "type":"Retail Goods"
        }
    ],
    "sg:phone":"+1 918 664 0016",
    "sg:postcode":"74146",
    "sg:province":"OK",
    "sg:tags":[
        "cosmetic",
        "perfume"
    ],
    "wof:name":"Kim Beauty Supply",
    "wof:placetype":"venue"
},
  "geometry": {"coordinates":[-95.851203,36.117933],"type":"Point"}
}