{
  "type": "Feature",
  "properties": {
    "iso:country":"US",
    "sg:address":"409 E Don Tyler Ave",
    "sg:city":"Dewey",
    "sg:classifiers":[
        {
            "category":"Government",
            "subcategory":"Police Station",
            "type":"Public Place"
        }
    ],
    "sg:phone":"+1 918 534 2223",
    "sg:postcode":"74029",
    "sg:province":"OK",
    "sg:tags":[
        "protection"
    ],
    "wof:name":"Dewey Police Department",
    "wof:placetype":"venue"
},
  "geometry": {"coordinates":[-95.936785,36.799205],"type":"Point"}
}