{
  "type": "Feature",
  "properties": {
    "addr:full":"510 Linda Ln Yukon OK 73099",
    "addr:housenumber":"510",
    "addr:postcode":"73099",
    "addr:street":"Linda Ln",
    "iso:country":"US",
    "sg:address":"510 Linda Ln",
    "sg:city":"Yukon",
    "sg:classifiers":[
        {
            "category":"Real Estate",
            "subcategory":"Real Estate Operator",
            "type":"Services"
        }
    ],
    "sg:phone":"+1 405 354 7122",
    "sg:postcode":"73099",
    "sg:province":"OK",
    "sg:tags":[
        "machine",
        "dwelling",
        "vending"
    ],
    "wof:name":"Theodore & Doris Castleberry",
    "wof:placetype":"venue"
},
  "geometry": {"coordinates":[-97.734172,35.516418],"type":"Point"}
}