{
  "type": "Feature",
  "properties": {
    "iso:country":"US",
    "sg:address":"34 A St NE",
    "sg:city":"Miami",
    "sg:classifiers":[
        {
            "category":"Social Services",
            "type":"Services"
        }
    ],
    "sg:phone":"+1 918 540 1379",
    "sg:postcode":"74354",
    "sg:province":"OK",
    "sg:tags":[
        "probation"
    ],
    "wof:name":"Probation & Parole Ofc",
    "wof:placetype":"venue"
},
  "geometry": {"coordinates":[-94.876328,36.875704],"type":"Point"}
}