{
  "type": "Feature",
  "properties": {
    "iso:country":"US",
    "sg:address":"303 S 45th West Ave",
    "sg:city":"Tulsa",
    "sg:classifiers":[
        {
            "category":"Organizations",
            "subcategory":"Religious Organization",
            "type":"Services"
        }
    ],
    "sg:phone":"+1 918 583 8040",
    "sg:postcode":"74127",
    "sg:province":"OK",
    "wof:name":"Guiding Light Tabernacle",
    "wof:placetype":"venue"
},
  "geometry": {"coordinates":[-96.042642,36.151696],"type":"Point"}
}