{
  "type": "Feature",
  "properties": {
    "iso:country":"US",
    "sg:address":"2912 Enterprise Blvd",
    "sg:city":"Durant",
    "sg:classifiers":[
        {
            "category":"Building & Trades",
            "subcategory":"Construction",
            "type":"Services"
        }
    ],
    "sg:phone":"+1 580 931 9193",
    "sg:postcode":"74701",
    "sg:province":"OK",
    "sg:tags":[
        "woodworker"
    ],
    "wof:name":"Precision Woodworking LLC",
    "wof:placetype":"venue"
},
  "geometry": {"coordinates":[-96.412441,33.972178],"type":"Point"}
}