{
  "type": "Feature",
  "properties": {
    "iso:country":"US",
    "sg:address":"7507 S 68th E Ave",
    "sg:city":"Tulsa",
    "sg:classifiers":[
        {
            "category":"Personal",
            "type":"Services"
        }
    ],
    "sg:phone":"+1 918 492 8244",
    "sg:postcode":"74133",
    "sg:province":"OK",
    "sg:tags":[
        "wedding",
        "chapel"
    ],
    "wof:name":"Paul C Horn",
    "wof:placetype":"venue"
},
  "geometry": {"coordinates":[-95.901544,36.054082],"type":"Point"}
}