{
  "type": "Feature",
  "properties": {
    "iso:country":"US",
    "sg:address":"200 N 6th St",
    "sg:city":"Sayre",
    "sg:classifiers":[
        {
            "category":"Retail",
            "subcategory":"Animal Services",
            "type":"Services"
        }
    ],
    "sg:phone":"+1 580 928 1111",
    "sg:postcode":"73662",
    "sg:province":"OK",
    "wof:name":"J & D Stables",
    "wof:placetype":"venue"
},
  "geometry": {"coordinates":[-99.64268,35.292429],"type":"Point"}
}