{
  "type": "Feature",
  "properties": {
    "iso:country":"US",
    "sg:address":"100 N Crosstimber Trl",
    "sg:city":"Edmond",
    "sg:classifiers":[
        {
            "category":"Manufacturing",
            "subcategory":"Apparel",
            "type":"Manufacturing & Wholesale Goods"
        }
    ],
    "sg:phone":"+1 405 330 9060",
    "sg:postcode":"73034",
    "sg:province":"OK",
    "sg:tags":[
        "mfg",
        "sweatshirt",
        "made",
        "custom"
    ],
    "wof:name":"Accessories Ala-Cart",
    "wof:placetype":"venue"
},
  "geometry": {"coordinates":[-97.43759799999999,35.655575],"type":"Point"}
}