{
  "type": "Feature",
  "properties": {
    "iso:country":"US",
    "sg:address":"22333 E 66th St",
    "sg:city":"Broken Arrow",
    "sg:classifiers":[
        {
            "category":"Professional",
            "subcategory":"Computer Services",
            "type":"Services"
        }
    ],
    "sg:phone":"+1 918 740 2418",
    "sg:postcode":"74014",
    "sg:province":"OK",
    "sg:tags":[
        "related"
    ],
    "wof:name":"SMC Pro Systems",
    "wof:placetype":"venue"
},
  "geometry": {"coordinates":[-95.728065,36.066556],"type":"Point"}
}