{
  "type": "Feature",
  "properties": {
    "addr:full":"2723 NW 32nd St Oklahoma City OK 73112",
    "addr:housenumber":"2723",
    "addr:postcode":"73112",
    "addr:street":"Nw 32Nd St",
    "iso:country":"US",
    "sg:address":"2723 NW 32nd St",
    "sg:city":"Oklahoma City",
    "sg:classifiers":[
        {
            "category":"Arts & Performance",
            "subcategory":"Theater",
            "type":"Entertainment"
        }
    ],
    "sg:phone":"+1 405 942 8271",
    "sg:postcode":"73112",
    "sg:province":"OK",
    "sg:tags":[
        "bureau"
    ],
    "wof:name":"Chameleon Entertainment",
    "wof:placetype":"venue"
},
  "geometry": {"coordinates":[-97.565372,35.50318],"type":"Point"}
}