{
  "type": "Feature",
  "properties": {
    "iso:country":"US",
    "sg:address":"928 NW 14th St",
    "sg:city":"Oklahoma City",
    "sg:classifiers":[
        {
            "category":"Wholesale",
            "subcategory":"Non-durable Goods",
            "type":"Manufacturing & Wholesale Goods"
        }
    ],
    "sg:phone":"+1 405 239 6027",
    "sg:postcode":"73106",
    "sg:province":"OK",
    "sg:tags":[
        "small",
        "leather",
        "own",
        "design"
    ],
    "wof:name":"Mission Leather Gear LLC",
    "wof:placetype":"venue"
},
  "geometry": {"coordinates":[-97.5282,35.483351],"type":"Point"}
}