{
  "type": "Feature",
  "properties": {
    "iso:country":"US",
    "sg:address":"8704 E 41st St",
    "sg:city":"Tulsa",
    "sg:classifiers":[
        {
            "category":"Building & Trades",
            "subcategory":"Pest Control",
            "type":"Services"
        }
    ],
    "sg:phone":"+1 918 663 7744",
    "sg:postcode":"74145",
    "sg:province":"OK",
    "wof:name":"Silver Seal Home Svc Group",
    "wof:placetype":"venue"
},
  "geometry": {"coordinates":[-95.878327,36.104391],"type":"Point"}
}