{
  "type": "Feature",
  "properties": {
    "iso:country":"US",
    "sg:address":"609 W E Ave",
    "sg:city":"Elk City",
    "sg:classifiers":[
        {
            "category":"Government",
            "subcategory":"Office",
            "type":"Public Place"
        }
    ],
    "sg:phone":"+1 580 225 1345",
    "sg:postcode":"73644",
    "sg:province":"OK",
    "sg:tags":[
        "federal",
        "security"
    ],
    "wof:name":"National Guard Opportunities",
    "wof:placetype":"venue"
},
  "geometry": {"coordinates":[-99.41199,35.418452],"type":"Point"}
}