{
  "type": "Feature",
  "properties": {
    "iso:country":"US",
    "sg:address":"1207 W Bois D Arc Ave",
    "sg:city":"Duncan",
    "sg:classifiers":[
        {
            "category":"Retail",
            "subcategory":"Laundry & Dry Cleaning",
            "type":"Services"
        }
    ],
    "sg:phone":"+1 580 255 1870",
    "sg:postcode":"73533",
    "sg:province":"OK",
    "wof:name":"Southside Laundry",
    "wof:placetype":"venue"
},
  "geometry": {"coordinates":[-97.965149,34.492723],"type":"Point"}
}