{
  "type": "Feature",
  "properties": {
    "addr:full":"1956 N Broadway St Poteau OK 74953",
    "addr:housenumber":"1956",
    "addr:postcode":"74953",
    "addr:street":"N Broadway St",
    "iso:country":"US",
    "sg:address":"1956 N Broadway St",
    "sg:city":"Poteau",
    "sg:classifiers":[
        {
            "category":"Shopping",
            "type":"Retail Goods"
        }
    ],
    "sg:phone":"+1 918 647 5350",
    "sg:postcode":"74953",
    "sg:province":"OK",
    "sg:tags":[
        "miscellaneous",
        "store"
    ],
    "wof:name":"Authorized Retail Dealer",
    "wof:placetype":"venue"
},
  "geometry": {"coordinates":[-94.62019100000001,35.062186],"type":"Point"}
}