{
  "type": "Feature",
  "properties": {
    "iso:country":"US",
    "sg:address":"901 NE 5th St",
    "sg:city":"Oklahoma City",
    "sg:classifiers":[
        {
            "category":"Freight",
            "type":"Transportation"
        }
    ],
    "sg:phone":"+1 405 794 7984",
    "sg:postcode":"73160",
    "sg:province":"OK",
    "sg:tags":[
        "operator",
        "trucking"
    ],
    "wof:name":"Peeks Transportation",
    "wof:placetype":"venue"
},
  "geometry": {"coordinates":[-97.472357,35.343472],"type":"Point"}
}