{
  "type": "Feature",
  "properties": {
    "iso:country":"US",
    "sg:address":"13261 W 78th St S",
    "sg:city":"Sapulpa",
    "sg:classifiers":[
        {
            "category":"Building & Trades",
            "subcategory":"Construction",
            "type":"Services"
        }
    ],
    "sg:phone":"+1 918 224 1019",
    "sg:postcode":"74066",
    "sg:province":"OK",
    "sg:tags":[
        "mobile",
        "home"
    ],
    "wof:name":"Mike's Mobile Home Svc Inc",
    "wof:placetype":"venue"
},
  "geometry": {"coordinates":[-96.141935,36.050192],"type":"Point"}
}