{
  "type": "Feature",
  "properties": {
    "iso:country":"US",
    "sg:address":"11720 S Western Ave",
    "sg:city":"Oklahoma City",
    "sg:classifiers":[
        {
            "category":"Personal",
            "type":"Services"
        }
    ],
    "sg:phone":"+1 405 691 6919",
    "sg:postcode":"73170",
    "sg:province":"OK",
    "sg:website":"www.universalfitness.net",
    "wof:name":"Universal Fitness",
    "wof:placetype":"venue"
},
  "geometry": {"coordinates":[-97.529907,35.351924],"type":"Point"}
}