{
  "type": "Feature",
  "properties": {
    "iso:country":"US",
    "sg:address":"106 N Broadway St",
    "sg:city":"Broken Bow",
    "sg:classifiers":[
        {
            "category":"Retail",
            "subcategory":"Laundry & Dry Cleaning",
            "type":"Services"
        }
    ],
    "sg:phone":"+1 580 584 9860",
    "sg:postcode":"74728",
    "sg:province":"OK",
    "sg:tags":[
        "cleaners",
        "plant",
        "drycleaning"
    ],
    "wof:name":"Rowan's Cleaners",
    "wof:placetype":"venue"
},
  "geometry": {"coordinates":[-94.738253,34.028332],"type":"Point"}
}