{
  "type": "Feature",
  "properties": {
    "iso:country":"US",
    "sg:address":"5353 E 68th St",
    "sg:city":"Tulsa",
    "sg:classifiers":[
        {
            "category":"Sports & Exercise",
            "subcategory":"Gym",
            "type":"Entertainment"
        }
    ],
    "sg:phone":"+1 918 494 1671",
    "sg:postcode":"74136",
    "sg:province":"OK",
    "sg:tags":[
        "club",
        "health",
        "studio",
        "gymnasium"
    ],
    "sg:website":"www.saintfrancis.com",
    "wof:name":"St Francis Hospital Health",
    "wof:placetype":"venue"
},
  "geometry": {"coordinates":[-95.917126,36.064556],"type":"Point"}
}