{
  "type": "Feature",
  "properties": {
    "iso:country":"US",
    "sg:address":"5611 S Western Ave",
    "sg:city":"Oklahoma City",
    "sg:classifiers":[
        {
            "category":"Shopping",
            "subcategory":"Used Merchandise",
            "type":"Retail Goods"
        }
    ],
    "sg:phone":"+1 405 616 5702",
    "sg:postcode":"73109",
    "sg:province":"OK",
    "sg:tags":[
        "shop",
        "thrift"
    ],
    "wof:name":"Southwestern Thrift Store",
    "wof:placetype":"venue"
},
  "geometry": {"coordinates":[-97.530286,35.40926],"type":"Point"}
}