{
  "type": "Feature",
  "properties": {
    "iso:country":"US",
    "sg:address":"113 N 6th St",
    "sg:city":"Clinton",
    "sg:classifiers":[
        {
            "category":"Retail",
            "subcategory":"Auto Repair",
            "type":"Services"
        }
    ],
    "sg:phone":"+1 580 323 7373",
    "sg:postcode":"73601",
    "sg:province":"OK",
    "sg:tags":[
        "repairing",
        "automobile"
    ],
    "wof:name":"John's Auto Repair",
    "wof:placetype":"venue"
},
  "geometry": {"coordinates":[-98.967126,35.51474],"type":"Point"}
}