{
  "type": "Feature",
  "properties": {
    "addr:full":"6901 N Robinson Ave Oklahoma City OK 73116",
    "addr:housenumber":"6901",
    "addr:postcode":"73116",
    "addr:street":"N Robinson Ave",
    "iso:country":"US",
    "sg:address":"6901 N Robinson Ave",
    "sg:city":"Oklahoma City",
    "sg:classifiers":[
        {
            "category":"Real Estate",
            "subcategory":"Architect",
            "type":"Services"
        }
    ],
    "sg:phone":"+1 405 848 0070",
    "sg:postcode":"73116",
    "sg:province":"OK",
    "sg:tags":[
        "planning",
        "house",
        "construction",
        "design",
        "architectural",
        "home"
    ],
    "sg:website":"www.fillmoredesign.com",
    "wof:name":"Fillmore Design Group",
    "wof:placetype":"venue"
},
  "geometry": {"coordinates":[-97.516503,35.542188],"type":"Point"}
}