{
  "type": "Feature",
  "properties": {
    "iso:country":"US",
    "sg:address":"437 W Broadway St",
    "sg:city":"Muskogee",
    "sg:classifiers":[
        {
            "category":"Personal",
            "subcategory":"Barber",
            "type":"Services"
        }
    ],
    "sg:phone":"+1 918 681 2547",
    "sg:postcode":"74401",
    "sg:province":"OK",
    "sg:tags":[
        "shop"
    ],
    "wof:name":"Lone Star Barber Shop",
    "wof:placetype":"venue"
},
  "geometry": {"coordinates":[-95.37261700000001,35.749926],"type":"Point"}
}