{
  "type": "Feature",
  "properties": {
    "iso:country":"US",
    "sg:address":"6929 S Sheridan Rd",
    "sg:city":"Tulsa",
    "sg:classifiers":[
        {
            "category":"Personal",
            "subcategory":"Barber",
            "type":"Services"
        }
    ],
    "sg:phone":"+1 918 492 4168",
    "sg:postcode":"74133",
    "sg:province":"OK",
    "sg:tags":[
        "shop"
    ],
    "wof:name":"Roffler Approach",
    "wof:placetype":"venue"
},
  "geometry": {"coordinates":[-95.904151,36.061212],"type":"Point"}
}