{
  "type": "Feature",
  "properties": {
    "iso:country":"US",
    "sg:address":"12300 E Britton Rd",
    "sg:city":"Jones",
    "sg:classifiers":[
        {
            "category":"Retail",
            "subcategory":"Auto Repair",
            "type":"Services"
        }
    ],
    "sg:phone":"+1 405 399 5022",
    "sg:postcode":"73049",
    "sg:province":"OK",
    "sg:tags":[
        "repairing",
        "automobile"
    ],
    "wof:name":"D & R Auto",
    "wof:placetype":"venue"
},
  "geometry": {"coordinates":[-97.31279,35.5657],"type":"Point"}
}