{
  "type": "Feature",
  "properties": {
    "iso:country":"US",
    "sg:address":"10221 E 96th St N",
    "sg:city":"Owasso",
    "sg:classifiers":[
        {
            "category":"Education",
            "subcategory":"School",
            "type":"Public Place"
        }
    ],
    "sg:phone":"+1 918 272 5399",
    "sg:postcode":"74055",
    "sg:province":"OK",
    "wof:name":"Bailey Elementary School",
    "wof:placetype":"venue"
},
  "geometry": {"coordinates":[-95.861795,36.293088],"type":"Point"}
}