{
  "type": "Feature",
  "properties": {
    "iso:country":"US",
    "sg:address":"203 E Cherry St",
    "sg:city":"Cushing",
    "sg:classifiers":[
        {
            "category":"Social Services",
            "type":"Services"
        }
    ],
    "sg:phone":"+1 918 225 5333",
    "sg:postcode":"74023",
    "sg:province":"OK",
    "sg:tags":[
        "senior",
        "citizen"
    ],
    "wof:name":"Cushing Senior Citizen Ctr",
    "wof:placetype":"venue"
},
  "geometry": {"coordinates":[-96.771394,35.978857],"type":"Point"}
}