{
  "type": "Feature",
  "properties": {
    "iso:country":"US",
    "sg:address":"3615 Williams Ave",
    "sg:city":"Woodward",
    "sg:classifiers":[
        {
            "category":"Mining & Drilling",
            "type":"Manufacturing & Wholesale Goods"
        }
    ],
    "sg:phone":"+1 580 254 2920",
    "sg:postcode":"73801",
    "sg:province":"OK",
    "sg:tags":[
        "field",
        "oil"
    ],
    "wof:name":"N W Sales",
    "wof:placetype":"venue"
},
  "geometry": {"coordinates":[-99.377297,36.410602],"type":"Point"}
}