{
  "type": "Feature",
  "properties": {
    "iso:country":"US",
    "sg:address":"931 N Kickapoo St",
    "sg:city":"Shawnee",
    "sg:classifiers":[
        {
            "category":"Autos & Motor Vehicles",
            "subcategory":"Automobile Sales",
            "type":"Retail Goods"
        }
    ],
    "sg:phone":"+1 405 214 9960",
    "sg:postcode":"74801",
    "sg:province":"OK",
    "sg:tags":[
        "used"
    ],
    "wof:name":"Oklahoma Motorsports",
    "wof:placetype":"venue"
},
  "geometry": {"coordinates":[-96.929852,35.340251],"type":"Point"}
}