{
  "type": "Feature",
  "properties": {
    "iso:country":"US",
    "sg:address":"2804 S 96th East Pl",
    "sg:city":"Tulsa",
    "sg:classifiers":[
        {
            "category":"Professional",
            "subcategory":"Printing & Photocopies",
            "type":"Services"
        }
    ],
    "sg:phone":"+1 918 622 3703",
    "sg:postcode":"74129",
    "sg:province":"OK",
    "sg:tags":[
        "lithographer"
    ],
    "wof:name":"Southwest Printing",
    "wof:placetype":"venue"
},
  "geometry": {"coordinates":[-95.86836099999999,36.123418],"type":"Point"}
}