{
  "type": "Feature",
  "properties": {
    "addr:full":"6900 NW Expy Oklahoma City OK 73132",
    "addr:housenumber":"6900",
    "addr:postcode":"73132",
    "addr:street":"Nw Expy",
    "iso:country":"US",
    "sg:address":"6900 NW Expy",
    "sg:city":"Oklahoma City",
    "sg:classifiers":[
        {
            "category":"Manufacturing",
            "subcategory":"Printing",
            "type":"Manufacturing & Wholesale Goods"
        }
    ],
    "sg:phone":"+1 405 773 2000",
    "sg:postcode":"73132",
    "sg:province":"OK",
    "sg:tags":[
        "printer"
    ],
    "wof:name":"Fed Ex Kinko's Ofc & Print Ctr",
    "wof:placetype":"venue"
},
  "geometry": {"coordinates":[-97.638402,35.557894],"type":"Point"}
}