{
  "type": "Feature",
  "properties": {
    "addr:full":"6206 Waterford Blvd Oklahoma City OK 73118",
    "addr:housenumber":"6206",
    "addr:postcode":"73118",
    "addr:street":"Waterford Blvd",
    "iso:country":"US",
    "sg:address":"6206 Waterford Blvd",
    "sg:city":"Oklahoma City",
    "sg:classifiers":[
        {
            "category":"Professional",
            "subcategory":"Detective & Security Services",
            "type":"Services"
        }
    ],
    "sg:phone":"+1 405 840 3340",
    "sg:postcode":"73118",
    "sg:province":"OK",
    "sg:tags":[
        "guard",
        "patrol"
    ],
    "wof:name":"Waterford Security",
    "wof:placetype":"venue"
},
  "geometry": {"coordinates":[-97.545631,35.534728],"type":"Point"}
}