{
  "type": "Feature",
  "properties": {
    "iso:country":"US",
    "sg:address":"301 S Perkins Rd",
    "sg:city":"Stillwater",
    "sg:classifiers":[
        {
            "category":"Organizations",
            "subcategory":"Community Association",
            "type":"Services"
        }
    ],
    "sg:phone":"+1 405 372 7903",
    "sg:postcode":"74074",
    "sg:province":"OK",
    "sg:tags":[
        "fraternal"
    ],
    "wof:name":"Loyal Order Of Moose",
    "wof:placetype":"venue"
},
  "geometry": {"coordinates":[-97.05133600000001,36.120383],"type":"Point"}
}