{
  "type": "Feature",
  "properties": {
    "iso:country":"US",
    "sg:address":"327 SW 25th St",
    "sg:city":"Oklahoma City",
    "sg:classifiers":[
        {
            "category":"Organizations",
            "subcategory":"Non-profit Organization",
            "type":"Services"
        }
    ],
    "sg:phone":"+1 405 634 2006",
    "sg:postcode":"73109",
    "sg:province":"OK",
    "wof:name":"Christmas Connection",
    "wof:placetype":"venue"
},
  "geometry": {"coordinates":[-97.519396,35.439492],"type":"Point"}
}