{
  "type": "Feature",
  "properties": {
    "iso:country":"US",
    "sg:address":"100 W Wanda Jackson Blvd",
    "sg:city":"Maud",
    "sg:classifiers":[
        {
            "category":"Autos & Motor Vehicles",
            "subcategory":"Automobile Sales",
            "type":"Retail Goods"
        }
    ],
    "sg:phone":"+1 405 374 1970",
    "sg:postcode":"74854",
    "sg:province":"OK",
    "sg:tags":[
        "car",
        "dealer"
    ],
    "wof:name":"O'Daniel Auto Sales",
    "wof:placetype":"venue"
},
  "geometry": {"coordinates":[-96.776911,35.130212],"type":"Point"}
}