{
  "type": "Feature",
  "properties": {
    "iso:country":"US",
    "sg:address":"5731 S 49th W Ave",
    "sg:city":"Tulsa",
    "sg:phone":"+1 918 445 0725",
    "sg:postcode":"74107",
    "sg:province":"OK",
    "sg:tags":[
        "distributor",
        "oil",
        "marketer"
    ],
    "sg:website":"www.bmoiltulsa.com",
    "wof:name":"B & M Oil Co",
    "wof:placetype":"venue"
},
  "geometry": {"coordinates":[-96.047174,36.079896],"type":"Point"}
}