{
  "type": "Feature",
  "properties": {
    "iso:country":"US",
    "sg:address":"1701 S Western Ave",
    "sg:city":"Oklahoma City",
    "sg:classifiers":[
        {
            "category":"Restaurant",
            "type":"Food & Drink"
        }
    ],
    "sg:phone":"+1 405 632 5288",
    "sg:postcode":"73109",
    "sg:province":"OK",
    "wof:name":"Downtown Air Park Cafe",
    "wof:placetype":"venue"
},
  "geometry": {"coordinates":[-97.530216,35.449091],"type":"Point"}
}