{
  "type": "Feature",
  "properties": {
    "addr:full":"1904 S Division St Guthrie OK 73044",
    "addr:housenumber":"1904",
    "addr:postcode":"73044",
    "addr:street":"S Division St",
    "iso:country":"US",
    "sg:address":"1904 S Division St",
    "sg:city":"Guthrie",
    "sg:classifiers":[
        {
            "category":"Health Services",
            "subcategory":"Health Practitioner",
            "type":"Services"
        }
    ],
    "sg:phone":"+1 405 282 4745",
    "sg:postcode":"73044",
    "sg:province":"OK",
    "sg:tags":[
        "therapist",
        "physical"
    ],
    "wof:name":"Veridian Corp",
    "wof:placetype":"venue"
},
  "geometry": {"coordinates":[-97.425341,35.860035],"type":"Point"}
}