{
  "type": "Feature",
  "properties": {
    "addr:full":"5918 NW 38th St Oklahoma City OK 73122",
    "addr:housenumber":"5918",
    "addr:postcode":"73122",
    "addr:street":"Nw 38Th St",
    "iso:country":"US",
    "sg:address":"5918 NW 38th St",
    "sg:city":"Oklahoma City",
    "sg:classifiers":[
        {
            "category":"Personal",
            "subcategory":"Beauty Salon",
            "type":"Services"
        }
    ],
    "sg:phone":"+1 405 787 8926",
    "sg:postcode":"73122",
    "sg:province":"OK",
    "sg:tags":[
        "shop"
    ],
    "wof:name":"Fantastic Sam's",
    "wof:placetype":"venue"
},
  "geometry": {"coordinates":[-97.62137300000001,35.509691],"type":"Point"}
}