{
  "type": "Feature",
  "properties": {
    "addr:full":"405 E Main St Tuttle OK 73089",
    "addr:housenumber":"405",
    "addr:postcode":"73089",
    "addr:street":"E Main St",
    "iso:country":"US",
    "sg:address":"405 E Main St",
    "sg:city":"Tuttle",
    "sg:classifiers":[
        {
            "category":"Restaurant",
            "type":"Food & Drink"
        }
    ],
    "sg:menulink":"http://www.allmenus.com/ok/tuttle/199280-sonic/menu/",
    "sg:phone":"+1 405 381 3381",
    "sg:postcode":"73089",
    "sg:province":"OK",
    "sg:tags":[
        "burger",
        "american"
    ],
    "wof:name":"Sonic",
    "wof:placetype":"venue"
},
  "geometry": {"coordinates":[-97.80784199999999,35.290817],"type":"Point"}
}