{
  "type": "Feature",
  "properties": {
    "addr:full":"919 NW 23rd St Oklahoma City OK 73106",
    "addr:housenumber":"919",
    "addr:postcode":"73106",
    "addr:street":"Nw 23Rd St",
    "iso:country":"US",
    "sg:address":"919 NW 23rd St",
    "sg:city":"Oklahoma City",
    "sg:classifiers":[
        {
            "category":"Education",
            "subcategory":"Special Training",
            "type":"Public Place"
        }
    ],
    "sg:phone":"+1 405 524 9762",
    "sg:postcode":"73106",
    "sg:province":"OK",
    "sg:website":"www.dsaokc.org",
    "wof:name":"Dove Science Academy",
    "wof:placetype":"venue"
},
  "geometry": {"coordinates":[-97.528486,35.493341],"type":"Point"}
}