{
  "type": "Feature",
  "properties": {
    "iso:country":"US",
    "sg:address":"211 E Gray St",
    "sg:city":"Norman",
    "sg:classifiers":[
        {
            "category":"Professional",
            "subcategory":"Detective & Security Services",
            "type":"Services"
        }
    ],
    "sg:phone":"+1 405 360 4224",
    "sg:postcode":"73069",
    "sg:province":"OK",
    "sg:tags":[
        "system",
        "business"
    ],
    "wof:name":"Frontier Security",
    "wof:placetype":"venue"
},
  "geometry": {"coordinates":[-97.441281,35.223081],"type":"Point"}
}