{
  "type": "Feature",
  "properties": {
    "iso:country":"US",
    "sg:address":"603 N Main St",
    "sg:city":"Blackwell",
    "sg:classifiers":[
        {
            "category":"Restaurant",
            "type":"Food & Drink"
        }
    ],
    "sg:phone":"+1 580 363 2972",
    "sg:postcode":"74631",
    "sg:province":"OK",
    "sg:tags":[
        "eating"
    ],
    "wof:name":"Lake Country",
    "wof:placetype":"venue"
},
  "geometry": {"coordinates":[-97.28302499999999,36.81023],"type":"Point"}
}