{
  "type": "Feature",
  "properties": {
    "addr:full":"1314 E Oklahoma Ave Guthrie OK 73044",
    "addr:housenumber":"1314",
    "addr:postcode":"73044",
    "addr:street":"E Oklahoma Ave",
    "iso:country":"US",
    "sg:address":"1314 E Oklahoma Ave",
    "sg:city":"Guthrie",
    "sg:classifiers":[
        {
            "category":"Health Services",
            "subcategory":"Nursing And Care Facility",
            "type":"Services"
        }
    ],
    "sg:phone":"+1 405 282 3980",
    "sg:postcode":"73044",
    "sg:province":"OK",
    "sg:tags":[
        "hospice"
    ],
    "wof:name":"Companion Hospice",
    "wof:placetype":"venue"
},
  "geometry": {"coordinates":[-97.40966400000001,35.878156],"type":"Point"}
}