{
  "type": "Feature",
  "properties": {
    "iso:country":"US",
    "sg:address":"315 N 7th St",
    "sg:city":"Perry",
    "sg:classifiers":[
        {
            "category":"Professional",
            "subcategory":"Management & Consulting",
            "type":"Services"
        }
    ],
    "sg:phone":"+1 580 336 1212",
    "sg:postcode":"73077",
    "sg:province":"OK",
    "sg:tags":[
        "development",
        "economic",
        "agency"
    ],
    "wof:name":"Main Street Of Perry",
    "wof:placetype":"venue"
},
  "geometry": {"coordinates":[-97.288256,36.287069],"type":"Point"}
}