{
  "type": "Feature",
  "properties": {
    "iso:country":"US",
    "sg:address":"3228 Wilshire Ter",
    "sg:city":"Oklahoma City",
    "sg:classifiers":[
        {
            "category":"Shopping",
            "subcategory":"Catalog Store",
            "type":"Retail Goods"
        }
    ],
    "sg:phone":"+1 405 843 7308",
    "sg:postcode":"73116",
    "sg:province":"OK",
    "sg:tags":[
        "mail",
        "house"
    ],
    "wof:name":"Infinite Discovery Inc",
    "wof:placetype":"venue"
},
  "geometry": {"coordinates":[-97.57341700000001,35.550037],"type":"Point"}
}