{
  "type": "Feature",
  "properties": {
    "addr:full":"127 N Division St Guthrie OK 73044",
    "addr:housenumber":"127",
    "addr:postcode":"73044",
    "addr:street":"N Division St",
    "iso:country":"US",
    "sg:address":"127 N Division St",
    "sg:city":"Guthrie",
    "sg:classifiers":[
        {
            "category":"Insurance",
            "subcategory":"Insurance Agent",
            "type":"Services"
        }
    ],
    "sg:phone":"+1 405 282 1788",
    "sg:postcode":"73044",
    "sg:province":"OK",
    "wof:name":"Farmers Insurance Group",
    "wof:placetype":"venue"
},
  "geometry": {"coordinates":[-97.425433,35.878273],"type":"Point"}
}