{
  "type": "Feature",
  "properties": {
    "iso:country":"US",
    "sg:address":"6505 E 40th St",
    "sg:city":"Tulsa",
    "sg:classifiers":[
        {
            "category":"Shopping",
            "type":"Retail Goods"
        }
    ],
    "sg:phone":"+1 918 663 4646",
    "sg:postcode":"74145",
    "sg:province":"OK",
    "sg:tags":[
        "merchandise",
        "business"
    ],
    "wof:name":"Discount Pool Supply",
    "wof:placetype":"venue"
},
  "geometry": {"coordinates":[-95.89719599999999,36.105332],"type":"Point"}
}