{
  "type": "Feature",
  "properties": {
    "iso:country":"US",
    "sg:address":"10655 E 450 Rd",
    "sg:city":"Claremore",
    "sg:classifiers":[
        {
            "category":"Professional",
            "subcategory":"Management & Consulting",
            "type":"Services"
        }
    ],
    "sg:phone":"+1 918 343 5017",
    "sg:postcode":"74017",
    "sg:province":"OK",
    "sg:tags":[
        "consultant",
        "business"
    ],
    "wof:name":"McFarlin Associates",
    "wof:placetype":"venue"
},
  "geometry": {"coordinates":[-95.636721,36.365398],"type":"Point"}
}