{
  "type": "Feature",
  "properties": {
    "iso:country":"US",
    "sg:address":"11920 E Admiral Pl",
    "sg:city":"Tulsa",
    "sg:classifiers":[
        {
            "category":"Home & Garden",
            "subcategory":"Mobile Homes",
            "type":"Retail Goods"
        }
    ],
    "sg:phone":"+1 918 438 8855",
    "sg:postcode":"74116",
    "sg:province":"OK",
    "sg:tags":[
        "house",
        "construction"
    ],
    "wof:name":"Select Homes",
    "wof:placetype":"venue"
},
  "geometry": {"coordinates":[-95.841397,36.160585],"type":"Point"}
}