{
  "type": "Feature",
  "properties": {
    "iso:country":"US",
    "sg:address":"424 E B Ave",
    "sg:city":"Waurika",
    "sg:classifiers":[
        {
            "category":"Organizations",
            "subcategory":"Religious Organization",
            "type":"Services"
        }
    ],
    "sg:phone":"+1 580 228 3559",
    "sg:postcode":"73573",
    "sg:province":"OK",
    "wof:name":"Waurika Church of Nazarene",
    "wof:placetype":"venue"
},
  "geometry": {"coordinates":[-97.996906,34.167089],"type":"Point"}
}