{
  "type": "Feature",
  "properties": {
    "iso:country":"US",
    "sg:address":"622 W Highland Ave",
    "sg:city":"Ponca City",
    "sg:classifiers":[
        {
            "category":"Bars & Pubs",
            "type":"Food & Drink"
        }
    ],
    "sg:phone":"+1 580 765 8061",
    "sg:postcode":"74601",
    "sg:province":"OK",
    "sg:tags":[
        "drinking"
    ],
    "wof:name":"Waynes' Tavern",
    "wof:placetype":"venue"
},
  "geometry": {"coordinates":[-97.090607,36.709687],"type":"Point"}
}