{
  "type": "Feature",
  "properties": {
    "iso:country":"US",
    "sg:address":"508 Vine St",
    "sg:city":"Chelsea",
    "sg:classifiers":[
        {
            "category":"Government",
            "subcategory":"Police Station",
            "type":"Public Place"
        }
    ],
    "sg:phone":"+1 918 789 3533",
    "sg:postcode":"74016",
    "sg:province":"OK",
    "sg:tags":[
        "protection"
    ],
    "wof:name":"Chelsea Police Department",
    "wof:placetype":"venue"
},
  "geometry": {"coordinates":[-95.432654,36.537136],"type":"Point"}
}