{
  "type": "Feature",
  "properties": {
    "iso:country":"US",
    "sg:address":"1433 N Indianapolis Ave",
    "sg:city":"Tulsa",
    "sg:classifiers":[
        {
            "category":"Building & Trades",
            "subcategory":"Construction",
            "type":"Services"
        }
    ],
    "sg:phone":"+1 918 834 3697",
    "sg:postcode":"74115",
    "sg:province":"OK",
    "sg:tags":[
        "painter"
    ],
    "wof:name":"All Around Painting & Remodel",
    "wof:placetype":"venue"
},
  "geometry": {"coordinates":[-95.939525,36.176454],"type":"Point"}
}