{
  "type": "Feature",
  "properties": {
    "addr:full":"3515 S Kentucky Ave Oklahoma City OK 73119",
    "addr:housenumber":"3515",
    "addr:postcode":"73119",
    "addr:street":"S Kentucky Ave",
    "iso:country":"US",
    "sg:address":"3515 S Kentucky Ave",
    "sg:city":"Oklahoma City",
    "sg:classifiers":[
        {
            "category":"Building & Trades",
            "subcategory":"Construction",
            "type":"Services"
        }
    ],
    "sg:phone":"+1 405 634 6660",
    "sg:postcode":"73119",
    "sg:province":"OK",
    "sg:tags":[
        "concrete",
        "pumping"
    ],
    "wof:name":"Morgan's Concrete Pumping",
    "wof:placetype":"venue"
},
  "geometry": {"coordinates":[-97.543598,35.429185],"type":"Point"}
}