{
  "type": "Feature",
  "properties": {
    "addr:full":"6302 S Peoria Ave Tulsa OK 74136",
    "addr:housenumber":"6302",
    "addr:postcode":"74136",
    "addr:street":"S Peoria Ave",
    "iso:country":"US",
    "sg:address":"6302 S Peoria Ave",
    "sg:city":"Tulsa",
    "sg:classifiers":[
        {
            "category":"Retail",
            "subcategory":"Laundry & Dry Cleaning",
            "type":"Services"
        }
    ],
    "sg:phone":"+1 918 745 2298",
    "sg:postcode":"74136",
    "sg:province":"OK",
    "sg:tags":[
        "cleaner",
        "operated",
        "dryer",
        "laundries-self",
        "washer",
        "coin"
    ],
    "wof:name":"J T Laundry",
    "wof:placetype":"venue"
},
  "geometry": {"coordinates":[-95.97577699999999,36.072271],"type":"Point"}
}