{
  "type": "Feature",
  "properties": {
    "iso:country":"US",
    "sg:address":"120 W Padon Ave",
    "sg:city":"Blackwell",
    "sg:classifiers":[
        {
            "category":"Retail",
            "subcategory":"Funeral Services",
            "type":"Services"
        }
    ],
    "sg:phone":"+1 580 363 3737",
    "sg:postcode":"74631",
    "sg:province":"OK",
    "sg:tags":[
        "director"
    ],
    "wof:name":"Roberts & Son Funeral Home",
    "wof:placetype":"venue"
},
  "geometry": {"coordinates":[-97.28341899999999,36.802347],"type":"Point"}
}