{
  "type": "Feature",
  "properties": {
    "addr:full":"14904 Salem Creek Rd Edmond OK 73013",
    "addr:housenumber":"14904",
    "addr:postcode":"73013",
    "addr:street":"Salem Creek Rd",
    "iso:country":"US",
    "sg:address":"14904 Salem Creek Rd",
    "sg:city":"Edmond",
    "sg:classifiers":[
        {
            "category":"Banks & Credit Unions",
            "subcategory":"Bank",
            "type":"Services"
        }
    ],
    "sg:phone":"+1 405 751 6607",
    "sg:postcode":"73013",
    "sg:province":"OK",
    "sg:tags":[
        "national",
        "commercial",
        "merchandise"
    ],
    "wof:name":"Cameron Communications",
    "wof:placetype":"venue"
},
  "geometry": {"coordinates":[-97.517707,35.621967],"type":"Point"}
}