{
  "type": "Feature",
  "properties": {
    "addr:full":"515 NE 3rd St Checotah OK 74426",
    "addr:housenumber":"515",
    "addr:postcode":"74426",
    "addr:street":"Ne 3Rd St",
    "iso:country":"US",
    "sg:address":"515 NE 3rd St",
    "sg:city":"Checotah",
    "sg:classifiers":[
        {
            "category":"Education",
            "subcategory":"School",
            "type":"Public Place"
        }
    ],
    "sg:phone":"+1 918 473 5302",
    "sg:postcode":"74426",
    "sg:province":"OK",
    "wof:name":"Checotah Alternative School",
    "wof:placetype":"venue"
},
  "geometry": {"coordinates":[-95.516165,35.473267],"type":"Point"}
}