{
  "type": "Feature",
  "properties": {
    "addr:full":"5033 N Macarthur Blvd Warr Acres OK 73122",
    "addr:housenumber":"5033",
    "addr:postcode":"73122",
    "addr:street":"N Macarthur Blvd",
    "iso:country":"US",
    "sg:address":"5033 N Macarthur Blvd",
    "sg:city":"Warr Acres",
    "sg:classifiers":[
        {
            "category":"Wholesale",
            "subcategory":"Painting Supplies",
            "type":"Manufacturing & Wholesale Goods"
        }
    ],
    "sg:phone":"+1 405 787 2330",
    "sg:postcode":"73122",
    "sg:province":"OK",
    "sg:tags":[
        "equipment",
        "painter"
    ],
    "wof:name":"David Mabry Supply",
    "wof:placetype":"venue"
},
  "geometry": {"coordinates":[-97.619044,35.521867],"type":"Point"}
}