{
  "type": "Feature",
  "properties": {
    "iso:country":"US",
    "sg:address":"5634 S 122nd East Ave",
    "sg:city":"Tulsa",
    "sg:classifiers":[
        {
            "category":"Building & Trades",
            "subcategory":"Construction",
            "type":"Services"
        }
    ],
    "sg:phone":"+1 918 307 8865",
    "sg:postcode":"74146",
    "sg:province":"OK",
    "sg:tags":[
        "general",
        "contractor"
    ],
    "wof:name":"Air Hygiene Inc",
    "wof:placetype":"venue"
},
  "geometry": {"coordinates":[-95.840635,36.081302],"type":"Point"}
}