{
  "type": "Feature",
  "properties": {
    "addr:full":"1025 E Seminole Ave Bache OK 74501",
    "addr:housenumber":"1025",
    "addr:postcode":"74501",
    "addr:street":"E Seminole Ave",
    "iso:country":"US",
    "sg:address":"1025 E Seminole Ave",
    "sg:city":"Bache",
    "sg:classifiers":[
        {
            "category":"Building & Trades",
            "subcategory":"Construction",
            "type":"Services"
        }
    ],
    "sg:phone":"+1 918 302 3295",
    "sg:postcode":"74501",
    "sg:province":"OK",
    "sg:tags":[
        "contractor"
    ],
    "wof:name":"Southeastern Insulation Svc",
    "wof:placetype":"venue"
},
  "geometry": {"coordinates":[-95.75890200000001,34.921882],"type":"Point"}
}