{
  "type": "Feature",
  "properties": {
    "iso:country":"US",
    "sg:address":"300 E 4th St",
    "sg:city":"Bartlesville",
    "sg:classifiers":[
        {
            "category":"Professional",
            "subcategory":"Management & Consulting",
            "type":"Services"
        }
    ],
    "sg:phone":"+1 918 336 2267",
    "sg:postcode":"74003",
    "sg:province":"OK",
    "sg:tags":[
        "communications",
        "consultant"
    ],
    "sg:website":"www.jwcom.com",
    "wof:name":"Joe Williams Communications",
    "wof:placetype":"venue"
},
  "geometry": {"coordinates":[-95.974925,36.749528],"type":"Point"}
}