{
  "type": "Feature",
  "properties": {
    "iso:country":"US",
    "sg:address":"8155 E 46th St",
    "sg:city":"Tulsa",
    "sg:classifiers":[
        {
            "category":"Wholesale",
            "subcategory":"Machinery & Supplies",
            "type":"Manufacturing & Wholesale Goods"
        }
    ],
    "sg:phone":"+1 918 627 7670",
    "sg:postcode":"74145",
    "sg:province":"OK",
    "sg:tags":[
        "tubing",
        "hose",
        "plastic"
    ],
    "wof:name":"Tulsa Hose & Fitting Co",
    "wof:placetype":"venue"
},
  "geometry": {"coordinates":[-95.884403,36.097871],"type":"Point"}
}