{
  "type": "Feature",
  "properties": {
    "addr:full":"209 Czech Hall Pl Yukon OK 73099",
    "addr:housenumber":"209",
    "addr:postcode":"73099",
    "addr:street":"Czech Hall Pl",
    "iso:country":"US",
    "sg:address":"209 Czech Hall Pl",
    "sg:city":"Yukon",
    "sg:classifiers":[
        {
            "category":"Wholesale",
            "subcategory":"Machinery & Supplies",
            "type":"Manufacturing & Wholesale Goods"
        }
    ],
    "sg:phone":"+1 405 324 0622",
    "sg:postcode":"73099",
    "sg:province":"OK",
    "sg:tags":[
        "equipment",
        "ride",
        "park",
        "amusement"
    ],
    "wof:name":"Inflatable Adventures Moonwalk",
    "wof:placetype":"venue"
},
  "geometry": {"coordinates":[-97.741967,35.468762],"type":"Point"}
}