{
  "type": "Feature",
  "properties": {
    "iso:country":"US",
    "sg:address":"2 State Hwy 74",
    "sg:city":"Maysville",
    "sg:classifiers":[
        {
            "category":"Personal",
            "subcategory":"Beauty Salon",
            "type":"Services"
        }
    ],
    "sg:phone":"+1 405 867 4792",
    "sg:postcode":"73057",
    "sg:province":"OK",
    "wof:name":"Yvonne's Cut & Curl",
    "wof:placetype":"venue"
},
  "geometry": {"coordinates":[-97.405506,34.822635],"type":"Point"}
}