{
  "type": "Feature",
  "properties": {
    "iso:country":"US",
    "sg:address":"1720 N Juniper Ave",
    "sg:city":"Broken Arrow",
    "sg:classifiers":[
        {
            "category":"Wholesale",
            "subcategory":"Machinery & Supplies",
            "type":"Manufacturing & Wholesale Goods"
        }
    ],
    "sg:phone":"+1 918 836 4094",
    "sg:postcode":"74012",
    "sg:province":"OK",
    "sg:tags":[
        "industrial"
    ],
    "wof:name":"Machinery Consultants Inc",
    "wof:placetype":"venue"
},
  "geometry": {"coordinates":[-95.809062,36.070603],"type":"Point"}
}