{
  "type": "Feature",
  "properties": {
    "iso:country":"US",
    "sg:address":"810 S Cincinnati Ave",
    "sg:city":"Tulsa",
    "sg:classifiers":[
        {
            "category":"Mining & Drilling",
            "type":"Manufacturing & Wholesale Goods"
        }
    ],
    "sg:phone":"+1 918 583 0933",
    "sg:postcode":"74119",
    "sg:province":"OK",
    "sg:tags":[
        "gas",
        "oil",
        "exploration"
    ],
    "wof:name":"M B R Resources Inc",
    "wof:placetype":"venue"
},
  "geometry": {"coordinates":[-95.985758,36.148539],"type":"Point"}
}