{
  "type": "Feature",
  "properties": {
    "addr:full":"220 S Park Ln Altus OK 73521",
    "addr:housenumber":"220",
    "addr:postcode":"73521",
    "addr:street":"S Park Ln",
    "iso:country":"US",
    "sg:address":"220 S Park Ln",
    "sg:city":"Altus",
    "sg:classifiers":[
        {
            "category":"Education",
            "subcategory":"School",
            "type":"Public Place"
        }
    ],
    "sg:phone":"+1 580 481 2134",
    "sg:postcode":"73521",
    "sg:province":"OK",
    "wof:name":"Life Long Learning",
    "wof:placetype":"venue"
},
  "geometry": {"coordinates":[-99.316395,34.636871],"type":"Point"}
}