{
  "type": "Feature",
  "properties": {
    "iso:country":"US",
    "sg:address":"9802 E 37th Pl",
    "sg:city":"Tulsa",
    "sg:classifiers":[
        {
            "category":"Wholesale",
            "subcategory":"Electrical",
            "type":"Manufacturing & Wholesale Goods"
        },
        {
            "category":"Manufacturing",
            "subcategory":"Tools & Machinery",
            "type":"Manufacturing & Wholesale Goods"
        }
    ],
    "sg:phone":"+1 918 665 8899",
    "sg:postcode":"74146",
    "sg:province":"OK",
    "sg:tags":[
        "representative"
    ],
    "wof:name":"Ron Fisher & Associates Inc",
    "wof:placetype":"venue"
},
  "geometry": {"coordinates":[-95.866379,36.110064],"type":"Point"}
}