{
  "type": "Feature",
  "properties": {
    "iso:country":"US",
    "sg:address":"1912 S Garnett Rd",
    "sg:city":"Tulsa",
    "sg:classifiers":[
        {
            "category":"Personal",
            "subcategory":"Beauty Salon",
            "type":"Services"
        }
    ],
    "sg:phone":"+1 918 437 2031",
    "sg:postcode":"74128",
    "sg:province":"OK",
    "wof:name":"Just Cuts & Tanning",
    "wof:placetype":"venue"
},
  "geometry": {"coordinates":[-95.851186,36.137094],"type":"Point"}
}