{
  "type": "Feature",
  "properties": {
    "iso:country":"US",
    "sg:address":"3215 Williams Ave",
    "sg:city":"Woodward",
    "sg:classifiers":[
        {
            "category":"Shopping",
            "subcategory":"Department Store",
            "type":"Retail Goods"
        }
    ],
    "sg:phone":"+1 580 254 3331",
    "sg:postcode":"73801",
    "sg:province":"OK",
    "sg:tags":[
        "grocery"
    ],
    "wof:name":"Wal-Mart",
    "wof:placetype":"venue"
},
  "geometry": {"coordinates":[-99.381744,36.414508],"type":"Point"}
}