{
  "type": "Feature",
  "properties": {
    "iso:country":"US",
    "sg:address":"4240 W I- 40 Svc Rd",
    "sg:city":"Oklahoma City",
    "sg:classifiers":[
        {
            "category":"Travel",
            "subcategory":"Hotels & Motels",
            "type":"Entertainment"
        }
    ],
    "sg:phone":"+1 405 943 4400",
    "sg:postcode":"73108",
    "sg:province":"OK",
    "wof:name":"Comfort Inn",
    "wof:placetype":"venue"
},
  "geometry": {"coordinates":[-97.59486,35.45986],"type":"Point"}
}