{
  "type": "Feature",
  "properties": {
    "addr:full":"9251 N W St Newkirk OK 74647",
    "addr:housenumber":"9251",
    "addr:postcode":"74647",
    "addr:street":"N W St",
    "iso:country":"US",
    "sg:address":"9251 N W St",
    "sg:city":"Newkirk",
    "sg:classifiers":[
        {
            "category":"Shopping",
            "subcategory":"Bicycles & Sporting Goods",
            "type":"Retail Goods"
        }
    ],
    "sg:phone":"+1 580 362 2177",
    "sg:postcode":"74647",
    "sg:province":"OK",
    "wof:name":"B & R Tack & Supply",
    "wof:placetype":"venue"
},
  "geometry": {"coordinates":[-97.12092,36.926963],"type":"Point"}
}