{
  "type": "Feature",
  "properties": {
    "iso:country":"US",
    "sg:address":"6550 SE 74th St",
    "sg:city":"Oklahoma City",
    "sg:classifiers":[
        {
            "category":"Local Transit",
            "type":"Transportation"
        }
    ],
    "sg:phone":"+1 405 869 9400",
    "sg:postcode":"73135",
    "sg:province":"OK",
    "sg:tags":[
        "limousine"
    ],
    "wof:name":"Suv Limos R Us",
    "wof:placetype":"venue"
},
  "geometry": {"coordinates":[-97.410854,35.391761],"type":"Point"}
}