{
  "type": "Feature",
  "properties": {
    "addr:full":"408 S F St Hugo OK 74743",
    "addr:housenumber":"408",
    "addr:postcode":"74743",
    "addr:street":"S F St",
    "iso:country":"US",
    "sg:address":"408 S F St",
    "sg:city":"Hugo",
    "sg:classifiers":[
        {
            "category":"Home & Garden",
            "subcategory":"Home Furnishings",
            "type":"Retail Goods"
        },
        {
            "category":"Manufacturing",
            "subcategory":"Glass & Minerals",
            "type":"Manufacturing & Wholesale Goods"
        }
    ],
    "sg:phone":"+1 580 326 2290",
    "sg:postcode":"74743",
    "sg:province":"OK",
    "sg:tags":[
        "plate",
        "shape",
        "glass-wholesale",
        "window",
        "special",
        "mirror",
        "circle",
        "glass-auto",
        "manufacturer"
    ],
    "wof:name":"Hugo Plate Glass & Mirror",
    "wof:placetype":"venue"
},
  "geometry": {"coordinates":[-95.518857,34.008063],"type":"Point"}
}