{
  "type": "Feature",
  "properties": {
    "iso:country":"US",
    "sg:address":"621 N Mississippi Ave",
    "sg:city":"Ada",
    "sg:classifiers":[
        {
            "category":"Personal",
            "subcategory":"Tanning Parlor",
            "type":"Services"
        }
    ],
    "sg:phone":"+1 580 332 1813",
    "sg:postcode":"74820",
    "sg:province":"OK",
    "sg:tags":[
        "salon"
    ],
    "wof:name":"Tan In Seconds",
    "wof:placetype":"venue"
},
  "geometry": {"coordinates":[-96.66991299999999,34.780468],"type":"Point"}
}