{
  "type": "Feature",
  "properties": {
    "addr:full":"1113 E Louisville St Broken Arrow OK 74012",
    "addr:housenumber":"1113",
    "addr:postcode":"74012",
    "addr:street":"E Louisville St",
    "iso:country":"US",
    "sg:address":"1113 E Louisville St",
    "sg:city":"Broken Arrow",
    "sg:classifiers":[
        {
            "category":"Wholesale",
            "subcategory":"Electrical",
            "type":"Manufacturing & Wholesale Goods"
        }
    ],
    "sg:phone":"+1 918 251 0644",
    "sg:postcode":"74012",
    "sg:province":"OK",
    "sg:tags":[
        "alarm",
        "burglar",
        "system"
    ],
    "sg:website":"www.advancealarm.com",
    "wof:name":"Advance Alarms Inc",
    "wof:placetype":"venue"
},
  "geometry": {"coordinates":[-95.776107,36.043683],"type":"Point"}
}