{
  "type": "Feature",
  "properties": {
    "iso:country":"US",
    "sg:address":"2701 E 15th St",
    "sg:city":"Tulsa",
    "sg:classifiers":[
        {
            "category":"Banks & Credit Unions",
            "subcategory":"Bank",
            "type":"Services"
        }
    ],
    "sg:phone":"+1 918 749 4447",
    "sg:postcode":"74104",
    "sg:province":"OK",
    "sg:tags":[
        "cashing",
        "check"
    ],
    "wof:name":"Cashland Inc",
    "wof:placetype":"venue"
},
  "geometry": {"coordinates":[-95.95043200000001,36.140558],"type":"Point"}
}