{
  "type": "Feature",
  "properties": {
    "iso:country":"US",
    "sg:address":"1230 N Interstate Dr",
    "sg:city":"Norman",
    "sg:classifiers":[
        {
            "category":"Personal",
            "subcategory":"Beauty Salon",
            "type":"Services"
        }
    ],
    "sg:phone":"+1 405 329 9999",
    "sg:postcode":"73072",
    "sg:province":"OK",
    "wof:name":"Moda Salon",
    "wof:placetype":"venue"
},
  "geometry": {"coordinates":[-97.488151,35.233329],"type":"Point"}
}