{
  "type": "Feature",
  "properties": {
    "addr:full":"11111 E 116th St N Collinsville OK 74021",
    "addr:housenumber":"11111",
    "addr:postcode":"74021",
    "addr:street":"E 116Th St N",
    "iso:country":"US",
    "sg:address":"11111 E 116th St N",
    "sg:city":"Collinsville",
    "sg:classifiers":[
        {
            "category":"Home & Garden",
            "subcategory":"Building Materials",
            "type":"Retail Goods"
        }
    ],
    "sg:phone":"+1 918 371 2511",
    "sg:postcode":"74021",
    "sg:province":"OK",
    "wof:name":"Hughes Lumber Co",
    "wof:placetype":"venue"
},
  "geometry": {"coordinates":[-95.85006799999999,36.322161],"type":"Point"}
}