{
  "type": "Feature",
  "properties": {
    "addr:full":"517 S Main St Hennessey OK 73742",
    "addr:housenumber":"517",
    "addr:postcode":"73742",
    "addr:street":"S Main St",
    "iso:country":"US",
    "sg:address":"517 S Main St",
    "sg:city":"Hennessey",
    "sg:classifiers":[
        {
            "category":"Government",
            "subcategory":"Office",
            "type":"Public Place"
        }
    ],
    "sg:phone":"+1 405 853 2730",
    "sg:postcode":"73742",
    "sg:province":"OK",
    "sg:tags":[
        "city",
        "taxation"
    ],
    "wof:name":"Hennessey Town Treasurer",
    "wof:placetype":"venue"
},
  "geometry": {"coordinates":[-97.898893,36.105145],"type":"Point"}
}