{
  "type": "Feature",
  "properties": {
    "addr:full":"2200 S 32nd St Muskogee OK 74401",
    "addr:housenumber":"2200",
    "addr:postcode":"74401",
    "addr:street":"S 32Nd St",
    "iso:country":"US",
    "sg:address":"2200 S 32nd St",
    "sg:city":"Muskogee",
    "sg:classifiers":[
        {
            "category":"Organizations",
            "subcategory":"Religious Organization",
            "type":"Services"
        }
    ],
    "sg:phone":"+1 918 686 9600",
    "sg:postcode":"74401",
    "sg:province":"OK",
    "sg:tags":[
        "church"
    ],
    "wof:name":"Evangel Assembly Of God",
    "wof:placetype":"venue"
},
  "geometry": {"coordinates":[-95.402452,35.728954],"type":"Point"}
}