{
  "type": "Feature",
  "properties": {
    "iso:country":"US",
    "sg:address":"1150 S Lynn Riggs Blvd",
    "sg:city":"Claremore",
    "sg:classifiers":[
        {
            "category":"Professional",
            "subcategory":"Accounting & Tax Preparation",
            "type":"Services"
        }
    ],
    "sg:phone":"+1 918 283 1040",
    "sg:postcode":"74017",
    "sg:province":"OK",
    "sg:tags":[
        "return",
        "filing"
    ],
    "wof:name":"Jackson Hewitt Tax Svc",
    "wof:placetype":"venue"
},
  "geometry": {"coordinates":[-95.626876,36.298499],"type":"Point"}
}