{
  "type": "Feature",
  "properties": {
    "addr:full":"6110 N Pennsylvania Ave Oklahoma City OK 73112",
    "addr:housenumber":"6110",
    "addr:postcode":"73112",
    "addr:street":"N Pennsylvania Ave",
    "iso:country":"US",
    "sg:address":"6110 N Pennsylvania Ave",
    "sg:city":"Oklahoma City",
    "sg:classifiers":[
        {
            "category":"Health Services",
            "subcategory":"Nursing And Care Facility",
            "type":"Services"
        },
        {
            "category":"Social Services",
            "subcategory":"Adult Care",
            "type":"Services"
        }
    ],
    "sg:phone":"+1 405 848 1817",
    "sg:postcode":"73112",
    "sg:province":"OK",
    "sg:tags":[
        "home",
        "intermediate",
        "residential"
    ],
    "sg:website":"www.themansionatwaterford.com",
    "wof:name":"Mansions At Waterford",
    "wof:placetype":"venue"
},
  "geometry": {"coordinates":[-97.54762100000001,35.534401],"type":"Point"}
}