{
  "type": "Feature",
  "properties": {
    "addr:full":"7311 Kelly Ln Harrah OK 73045",
    "addr:housenumber":"7311",
    "addr:postcode":"73045",
    "addr:street":"Kelly Ln",
    "iso:country":"US",
    "sg:address":"7311 Kelly Ln",
    "sg:city":"Harrah",
    "sg:classifiers":[
        {
            "category":"Building & Trades",
            "subcategory":"Electrical",
            "type":"Services"
        }
    ],
    "sg:phone":"+1 405 454 1487",
    "sg:postcode":"73045",
    "sg:province":"OK",
    "sg:tags":[
        "telecommunication",
        "contractor"
    ],
    "wof:name":"B-C Walker Inc",
    "wof:placetype":"venue"
},
  "geometry": {"coordinates":[-97.155885,35.544264],"type":"Point"}
}