{
  "type": "Feature",
  "properties": {
    "iso:country":"US",
    "sg:address":"4815 S Harvard Ave",
    "sg:city":"Tulsa",
    "sg:classifiers":[
        {
            "category":"Organizations",
            "subcategory":"Community Association",
            "type":"Services"
        }
    ],
    "sg:phone":"+1 918 742 0007",
    "sg:postcode":"74135",
    "sg:province":"OK",
    "sg:tags":[
        "military"
    ],
    "wof:name":"AVA-American Veterans Assn",
    "wof:placetype":"venue"
},
  "geometry": {"coordinates":[-95.940068,36.091645],"type":"Point"}
}