{
  "type": "Feature",
  "properties": {
    "iso:country":"US",
    "sg:address":"2104 N Robin St",
    "sg:city":"Altus",
    "sg:classifiers":[
        {
            "category":"Manufacturing",
            "subcategory":"Tools & Machinery",
            "type":"Manufacturing & Wholesale Goods"
        }
    ],
    "sg:phone":"+1 580 480 1953",
    "sg:postcode":"73521",
    "sg:province":"OK",
    "sg:tags":[
        "maintenance",
        "grounds"
    ],
    "wof:name":"R & R Lawncare & Cleaning",
    "wof:placetype":"venue"
},
  "geometry": {"coordinates":[-99.335911,34.662189],"type":"Point"}
}