{
  "type": "Feature",
  "properties": {
    "iso:country":"US",
    "sg:address":"456 N Brown St",
    "sg:city":"Vinita",
    "sg:classifiers":[
        {
            "category":"Building & Trades",
            "subcategory":"Construction",
            "type":"Services"
        }
    ],
    "sg:phone":"+1 918 256 2544",
    "sg:postcode":"74301",
    "sg:province":"OK",
    "sg:tags":[
        "house"
    ],
    "wof:name":"Dean Construction Company",
    "wof:placetype":"venue"
},
  "geometry": {"coordinates":[-95.16166200000001,36.648834],"type":"Point"}
}