{
  "type": "Feature",
  "properties": {
    "iso:country":"US",
    "sg:address":"3121 SW 29th St",
    "sg:city":"Oklahoma City",
    "sg:classifiers":[
        {
            "category":"Shopping",
            "subcategory":"Gifts & Souvenirs",
            "type":"Retail Goods"
        }
    ],
    "sg:phone":"+1 405 686 1110",
    "sg:postcode":"73119",
    "sg:province":"OK",
    "sg:tags":[
        "novelty"
    ],
    "wof:name":"Naughty N Nice",
    "wof:placetype":"venue"
},
  "geometry": {"coordinates":[-97.572239,35.435226],"type":"Point"}
}