{
  "type": "Feature",
  "properties": {
    "iso:country":"US",
    "sg:address":"850 Yukon Ave",
    "sg:city":"Yukon",
    "sg:classifiers":[
        {
            "category":"Education",
            "subcategory":"School",
            "type":"Public Place"
        }
    ],
    "sg:phone":"+1 405 354 8356",
    "sg:postcode":"73099",
    "sg:province":"OK",
    "wof:name":"Yukon Fine Art Center",
    "wof:placetype":"venue"
},
  "geometry": {"coordinates":[-97.756936,35.500587],"type":"Point"}
}