{
  "type": "Feature",
  "properties": {
    "iso:country":"US",
    "sg:address":"2425 Morning Glory Dr",
    "sg:city":"Oklahoma City",
    "sg:classifiers":[
        {
            "category":"Home & Garden",
            "subcategory":"Carpets & Floor Coverings",
            "type":"Retail Goods"
        }
    ],
    "sg:phone":"+1 405 236 3811",
    "sg:postcode":"73159",
    "sg:province":"OK",
    "sg:tags":[
        "dealer",
        "rug"
    ],
    "wof:name":"Carpets & Floors",
    "wof:placetype":"venue"
},
  "geometry": {"coordinates":[-97.555421,35.366706],"type":"Point"}
}