{
  "type": "Feature",
  "properties": {
    "addr:full":"223 S Main St Wagoner OK 74477",
    "addr:housenumber":"223",
    "addr:postcode":"74477",
    "addr:street":"S Main St",
    "iso:country":"US",
    "sg:address":"223 S Main St",
    "sg:city":"Wagoner",
    "sg:classifiers":[
        {
            "category":"Building & Trades",
            "subcategory":"Construction",
            "type":"Services"
        }
    ],
    "sg:phone":"+1 918 485 9353",
    "sg:postcode":"74477",
    "sg:province":"OK",
    "sg:tags":[
        "contractor"
    ],
    "wof:name":"SC Piping and Mechanical Inc",
    "wof:placetype":"venue"
},
  "geometry": {"coordinates":[-95.376941,35.95847],"type":"Point"}
}