{
  "type": "Feature",
  "properties": {
    "iso:country":"US",
    "sg:address":"8802 S Urbana Ave",
    "sg:city":"Tulsa",
    "sg:classifiers":[
        {
            "category":"Professional",
            "subcategory":"Computer Services",
            "type":"Services"
        }
    ],
    "sg:phone":"+1 918 488 9660",
    "sg:postcode":"74137",
    "sg:province":"OK",
    "sg:tags":[
        "programming"
    ],
    "sg:website":"www.technicalsolutionsgrp.com",
    "wof:name":"Technical Solutions Group Inc",
    "wof:placetype":"venue"
},
  "geometry": {"coordinates":[-95.926194,36.03492],"type":"Point"}
}