{
  "type": "Feature",
  "properties": {
    "iso:country":"US",
    "sg:address":"1202 S Monroe St",
    "sg:city":"Enid",
    "sg:classifiers":[
        {
            "category":"Shopping",
            "subcategory":"Used Merchandise",
            "type":"Retail Goods"
        }
    ],
    "sg:phone":"+1 580 237 3622",
    "sg:postcode":"73701",
    "sg:province":"OK",
    "wof:name":"Lowder Used Books",
    "wof:placetype":"venue"
},
  "geometry": {"coordinates":[-97.886565,36.383312],"type":"Point"}
}