{
  "type": "Feature",
  "properties": {
    "iso:country":"US",
    "sg:address":"2207 E 6th Ave",
    "sg:city":"Stillwater",
    "sg:classifiers":[
        {
            "category":"Retail",
            "subcategory":"Auto Repair",
            "type":"Services"
        }
    ],
    "sg:phone":"+1 405 377 0430",
    "sg:postcode":"74074",
    "sg:province":"OK",
    "sg:tags":[
        "body",
        "shop",
        "automobile",
        "paint",
        "automotive",
        "painting"
    ],
    "wof:name":"G & M Body Shop Inc",
    "wof:placetype":"venue"
},
  "geometry": {"coordinates":[-97.031085,36.115913],"type":"Point"}
}