{
  "type": "Feature",
  "properties": {
    "addr:full":"5615 S Western Ave Oklahoma City OK 73109",
    "addr:housenumber":"5615",
    "addr:postcode":"73109",
    "addr:street":"S Western Ave",
    "iso:country":"US",
    "sg:address":"5615 S Western Ave",
    "sg:city":"Oklahoma City",
    "sg:classifiers":[
        {
            "category":"Shopping",
            "subcategory":"Tobacco",
            "type":"Retail Goods"
        }
    ],
    "sg:phone":"+1 405 631 5234",
    "sg:postcode":"73109",
    "sg:province":"OK",
    "sg:tags":[
        "product"
    ],
    "wof:name":"Td K Discount Cigarettes",
    "wof:placetype":"venue"
},
  "geometry": {"coordinates":[-97.53028500000001,35.409298],"type":"Point"}
}