{
  "type": "Feature",
  "properties": {
    "iso:country":"US",
    "sg:address":"1400 NW Sheridan Rd",
    "sg:city":"Lawton",
    "sg:classifiers":[
        {
            "category":"Insurance",
            "subcategory":"Insurance Agent",
            "type":"Services"
        }
    ],
    "sg:phone":"+1 580 355 4285",
    "sg:postcode":"73505",
    "sg:province":"OK",
    "wof:name":"Anthony Libro",
    "wof:placetype":"venue"
},
  "geometry": {"coordinates":[-98.422389,34.623357],"type":"Point"}
}