{
  "type": "Feature",
  "properties": {
    "iso:country":"US",
    "sg:address":"1628 S Kelham Ave",
    "sg:city":"Oklahoma City",
    "sg:classifiers":[
        {
            "category":"Freight",
            "type":"Transportation"
        }
    ],
    "sg:phone":"+1 405 672 3017",
    "sg:postcode":"73129",
    "sg:province":"OK",
    "sg:tags":[
        "packing",
        "crating"
    ],
    "wof:name":"Navis Pack & Ship Ctr",
    "wof:placetype":"venue"
},
  "geometry": {"coordinates":[-97.482443,35.448551],"type":"Point"}
}