{
  "type": "Feature",
  "properties": {
    "iso:country":"US",
    "sg:address":"3535 NE Military Cir",
    "sg:city":"Oklahoma City",
    "sg:classifiers":[
        {
            "category":"Organizations",
            "subcategory":"Non-profit Organization",
            "type":"Services"
        },
        {
            "category":"Insurance",
            "subcategory":"Insurance Agent",
            "type":"Services"
        }
    ],
    "sg:phone":"+1 405 424 1231",
    "sg:postcode":"73111",
    "sg:province":"OK",
    "wof:name":"National Guard Assn Of Okla",
    "wof:placetype":"venue"
},
  "geometry": {"coordinates":[-97.47034,35.504085],"type":"Point"}
}