{
  "type": "Feature",
  "properties": {
    "iso:country":"US",
    "sg:address":"310 W Choctaw St",
    "sg:city":"Lindsay",
    "sg:classifiers":[
        {
            "category":"Social Services",
            "type":"Services"
        }
    ],
    "sg:phone":"+1 405 756 4780",
    "sg:postcode":"73052",
    "sg:province":"OK",
    "sg:tags":[
        "senior",
        "citizen"
    ],
    "wof:name":"Senior Citizens Community Ctr",
    "wof:placetype":"venue"
},
  "geometry": {"coordinates":[-97.6069,34.835888],"type":"Point"}
}