{
  "type": "Feature",
  "properties": {
    "addr:full":"4017 NW 56th Ter Oklahoma City OK 73112",
    "addr:housenumber":"4017",
    "addr:postcode":"73112",
    "addr:street":"Nw 56Th Ter",
    "iso:country":"US",
    "sg:address":"4017 NW 56th Ter",
    "sg:city":"Oklahoma City",
    "sg:classifiers":[
        {
            "category":"Shopping",
            "subcategory":"Optical Goods",
            "type":"Retail Goods"
        }
    ],
    "sg:phone":"+1 405 943 9569",
    "sg:postcode":"73112",
    "sg:province":"OK",
    "wof:name":"Beverley S Optical Inc",
    "wof:placetype":"venue"
},
  "geometry": {"coordinates":[-97.59211000000001,35.528555],"type":"Point"}
}