{
  "type": "Feature",
  "properties": {
    "addr:full":"5320 NW Cache Rd Lawton OK 73505",
    "addr:housenumber":"5320",
    "addr:postcode":"73505",
    "addr:street":"Nw Cache Rd",
    "iso:country":"US",
    "sg:address":"5320 NW Cache Rd",
    "sg:city":"Lawton",
    "sg:classifiers":[
        {
            "category":"Shopping",
            "subcategory":"Discount & Variety Stores",
            "type":"Retail Goods"
        }
    ],
    "sg:phone":"+1 580 353 4802",
    "sg:postcode":"73505",
    "sg:province":"OK",
    "wof:name":"Dollar General",
    "wof:placetype":"venue"
},
  "geometry": {"coordinates":[-98.459215,34.623364],"type":"Point"}
}