{
  "type": "Feature",
  "properties": {
    "iso:country":"US",
    "sg:address":"4930 W Kenosha St",
    "sg:city":"Broken Arrow",
    "sg:classifiers":[
        {
            "category":"Food & Beverages",
            "subcategory":"Bakery",
            "type":"Retail Goods"
        }
    ],
    "sg:phone":"+1 918 250 1607",
    "sg:postcode":"74012",
    "sg:province":"OK",
    "sg:tags":[
        "baker"
    ],
    "wof:name":"Merritts Bakery",
    "wof:placetype":"venue"
},
  "geometry": {"coordinates":[-95.847973,36.060963],"type":"Point"}
}