{
  "type": "Feature",
  "properties": {
    "addr:full":"111 N Cabaniss Ave Bixby OK 74008",
    "addr:housenumber":"111",
    "addr:postcode":"74008",
    "addr:street":"N Cabaniss Ave",
    "iso:country":"US",
    "sg:address":"111 N Cabaniss Ave",
    "sg:city":"Bixby",
    "sg:classifiers":[
        {
            "category":"Shopping",
            "subcategory":"Discount & Variety Stores",
            "type":"Retail Goods"
        }
    ],
    "sg:phone":"+1 918 366 9000",
    "sg:postcode":"74008",
    "sg:province":"OK",
    "wof:name":"Dollar General",
    "wof:placetype":"venue"
},
  "geometry": {"coordinates":[-95.884514,35.94165],"type":"Point"}
}