{
  "type": "Feature",
  "properties": {
    "iso:country":"US",
    "sg:address":"1221 W 1st St",
    "sg:city":"Sulphur",
    "sg:classifiers":[
        {
            "category":"Autos & Motor Vehicles",
            "subcategory":"Fuel & Gas Station",
            "type":"Retail Goods"
        }
    ],
    "sg:phone":"+1 580 622 3000",
    "sg:postcode":"73086",
    "sg:province":"OK",
    "sg:tags":[
        "oil"
    ],
    "wof:name":"Courtney Texaco",
    "wof:placetype":"venue"
},
  "geometry": {"coordinates":[-96.968343,34.510096],"type":"Point"}
}