{
  "type": "Feature",
  "properties": {
    "iso:country":"US",
    "sg:address":"5425 S 101st East Ave",
    "sg:city":"Tulsa",
    "sg:classifiers":[
        {
            "category":"Building & Trades",
            "subcategory":"Plumbing",
            "type":"Services"
        }
    ],
    "sg:phone":"+1 918 622 0629",
    "sg:postcode":"74146",
    "sg:province":"OK",
    "sg:tags":[
        "conditioning",
        "air",
        "system",
        "contractor"
    ],
    "wof:name":"Tulsa Custom Air",
    "wof:placetype":"venue"
},
  "geometry": {"coordinates":[-95.86386299999999,36.084279],"type":"Point"}
}