{
  "type": "Feature",
  "properties": {
    "iso:country":"US",
    "sg:address":"5244 S Pennsylvania Ave",
    "sg:city":"Oklahoma City",
    "sg:classifiers":[
        {
            "category":"Banks & Credit Unions",
            "subcategory":"Investment Brokerage",
            "type":"Services"
        }
    ],
    "sg:phone":"+1 405 682 2620",
    "sg:postcode":"73119",
    "sg:province":"OK",
    "sg:tags":[
        "consultant",
        "planning",
        "financial"
    ],
    "wof:name":"Tom H Ledbetter",
    "wof:placetype":"venue"
},
  "geometry": {"coordinates":[-97.547861,35.413415],"type":"Point"}
}