{
  "type": "Feature",
  "properties": {
    "iso:country":"US",
    "sg:address":"3201 Riverwalk Dr",
    "sg:city":"Norman",
    "sg:classifiers":[
        {
            "category":"Shopping",
            "subcategory":"Used Merchandise",
            "type":"Retail Goods"
        }
    ],
    "sg:phone":"+1 405 321 3534",
    "sg:postcode":"73072",
    "sg:province":"OK",
    "wof:name":"Gingersnap Resale Shoppe",
    "wof:placetype":"venue"
},
  "geometry": {"coordinates":[-97.48913899999999,35.210446],"type":"Point"}
}