{
  "type": "Feature",
  "properties": {
    "addr:full":"6709 N Willow Ridge Dr Oklahoma City OK 73122",
    "addr:housenumber":"6709",
    "addr:postcode":"73122",
    "addr:street":"N Willow Ridge Dr",
    "iso:country":"US",
    "sg:address":"6709 N Willow Ridge Dr",
    "sg:city":"Oklahoma City",
    "sg:classifiers":[
        {
            "category":"Organizations",
            "subcategory":"Membership Organization",
            "type":"Services"
        }
    ],
    "sg:phone":"+1 405 721 8132",
    "sg:postcode":"73122",
    "sg:province":"OK",
    "wof:name":"Putnam City Athletic Assoc",
    "wof:placetype":"venue"
},
  "geometry": {"coordinates":[-97.632071,35.533799],"type":"Point"}
}