{
  "type": "Feature",
  "properties": {
    "addr:full":"1021 17th St Woodward OK 73801",
    "addr:housenumber":"1021",
    "addr:postcode":"73801",
    "addr:street":"17Th St",
    "iso:country":"US",
    "sg:address":"1021 17th St",
    "sg:city":"Woodward",
    "sg:classifiers":[
        {
            "category":"Coffee & Tea",
            "type":"Food & Drink"
        },
        {
            "category":"Restaurant",
            "type":"Food & Drink"
        },
        {
            "category":"Bakery",
            "type":"Food & Drink"
        },
        {
            "category":"Donuts",
            "type":"Food & Drink"
        }
    ],
    "sg:menulink":"http://www.allmenus.com/ok/woodward/230884-daylight-donuts/menu/",
    "sg:phone":"+1 580 256 4852",
    "sg:postcode":"73801",
    "sg:province":"OK",
    "sg:tags":[
        "tea",
        "coffee",
        "bakery",
        "american",
        "pastry"
    ],
    "wof:name":"Daylight Donuts",
    "wof:placetype":"venue"
},
  "geometry": {"coordinates":[-99.40096800000001,36.436923],"type":"Point"}
}