{
  "type": "Feature",
  "properties": {
    "iso:country":"US",
    "sg:address":"4118 N Mingo Rd",
    "sg:city":"Tulsa",
    "sg:classifiers":[
        {
            "category":"Manufacturing",
            "subcategory":"Metals",
            "type":"Manufacturing & Wholesale Goods"
        }
    ],
    "sg:phone":"+1 918 835 4683",
    "sg:postcode":"74116",
    "sg:province":"OK",
    "sg:tags":[
        "aircraft",
        "mfg"
    ],
    "wof:name":"United Plating Works Inc",
    "wof:placetype":"venue"
},
  "geometry": {"coordinates":[-95.86890099999999,36.215389],"type":"Point"}
}