{
  "type": "Feature",
  "properties": {
    "iso:country":"US",
    "sg:address":"118 Cottonwood Dr",
    "sg:city":"Tuttle",
    "sg:classifiers":[
        {
            "category":"Building & Trades",
            "subcategory":"Construction",
            "type":"Services"
        }
    ],
    "sg:phone":"+1 405 381 3214",
    "sg:postcode":"73089",
    "sg:province":"OK",
    "sg:tags":[
        "concrete",
        "contractor"
    ],
    "wof:name":"House Dctor Foundation Hm Repr",
    "wof:placetype":"venue"
},
  "geometry": {"coordinates":[-97.698295,35.289814],"type":"Point"}
}