{
  "type": "Feature",
  "properties": {
    "iso:country":"US",
    "sg:address":"2505 NW 34th St",
    "sg:city":"Oklahoma City",
    "sg:classifiers":[
        {
            "category":"Building & Trades",
            "subcategory":"Construction",
            "type":"Services"
        }
    ],
    "sg:phone":"+1 405 601 1511",
    "sg:postcode":"73112",
    "sg:province":"OK",
    "sg:tags":[
        "repairing",
        "remodeling",
        "contractor"
    ],
    "wof:name":"Hart Construction",
    "wof:placetype":"venue"
},
  "geometry": {"coordinates":[-97.558743,35.505049],"type":"Point"}
}