{
  "type": "Feature",
  "properties": {
    "iso:country":"US",
    "sg:address":"105 S Main St",
    "sg:city":"Elk City",
    "sg:classifiers":[
        {
            "category":"Personal",
            "subcategory":"Beauty Salon",
            "type":"Services"
        }
    ],
    "sg:phone":"+1 580 225 2031",
    "sg:postcode":"73644",
    "sg:province":"OK",
    "sg:tags":[
        "manicuring"
    ],
    "wof:name":"R & R Wedding Salon",
    "wof:placetype":"venue"
},
  "geometry": {"coordinates":[-99.404995,35.410628],"type":"Point"}
}