{
  "type": "Feature",
  "properties": {
    "iso:country":"US",
    "sg:address":"1711 State Hwy 152",
    "sg:city":"Mustang",
    "sg:classifiers":[
        {
            "category":"Personal",
            "subcategory":"Tanning Parlor",
            "type":"Services"
        }
    ],
    "sg:phone":"+1 405 745 3777",
    "sg:postcode":"73064",
    "sg:province":"OK",
    "sg:tags":[
        "salon"
    ],
    "wof:name":"His & Hers Toning & Tanning",
    "wof:placetype":"venue"
},
  "geometry": {"coordinates":[-97.762272,35.391754],"type":"Point"}
}