{
  "type": "Feature",
  "properties": {
    "iso:country":"US",
    "sg:address":"201 S 4th St",
    "sg:city":"Sayre",
    "sg:classifiers":[
        {
            "category":"Retail",
            "subcategory":"Auto Repair",
            "type":"Services"
        }
    ],
    "sg:phone":"+1 580 928 2665",
    "sg:postcode":"73662",
    "sg:province":"OK",
    "sg:tags":[
        "muffler",
        "exhaust",
        "system",
        "general"
    ],
    "wof:name":"Johnston's Muffler & Welding",
    "wof:placetype":"venue"
},
  "geometry": {"coordinates":[-99.639944,35.290146],"type":"Point"}
}