{
  "type": "Feature",
  "properties": {
    "iso:country":"US",
    "sg:address":"2409 Hummingbird Ln",
    "sg:city":"Ponca City",
    "sg:classifiers":[
        {
            "category":"Professional",
            "subcategory":"Computer Services",
            "type":"Services"
        }
    ],
    "sg:phone":"+1 580 762 4470",
    "sg:postcode":"74604",
    "sg:province":"OK",
    "wof:name":"Th Repair",
    "wof:placetype":"venue"
},
  "geometry": {"coordinates":[-97.05186,36.729421],"type":"Point"}
}