{
  "type": "Feature",
  "properties": {
    "iso:country":"US",
    "sg:address":"303 S Main St",
    "sg:city":"Blackwell",
    "sg:classifiers":[
        {
            "category":"Museum",
            "type":"Entertainment"
        }
    ],
    "sg:phone":"+1 580 363 0209",
    "sg:postcode":"74631",
    "sg:province":"OK",
    "wof:name":"Top Of Oklahoma Historical",
    "wof:placetype":"venue"
},
  "geometry": {"coordinates":[-97.283055,36.80225],"type":"Point"}
}