{
  "type": "Feature",
  "properties": {
    "addr:city":"Blackwell",
    "addr:full":"303 S Main St Blackwell, Ok 74631",
    "addr:house_number":"303",
    "addr:housenumber":"303",
    "addr:phone":"+1 580-363-0209",
    "addr:postcode":"74631",
    "addr:road":"S Main St",
    "addr:state":"OK",
    "addr:street":"S Main St",
    "iso:country":"US",
    "sg:address":"303 S Main St",
    "sg:city":"Blackwell",
    "sg:classifiers":[
        {
            "category":"Museum",
            "type":"Entertainment"
        }
    ],
    "sg:phone":"+1 580 363 0209",
    "sg:postcode":"74631",
    "sg:province":"OK",
    "wof:name":"Top Of Oklahoma Historical Society Museum",
    "wof:placetype":"venue"
},
  "geometry": {"coordinates":[-97.28307,36.8013],"type":"Point"}
}