{
  "type": "Feature",
  "properties": {
    "iso:country":"US",
    "sg:address":"8364 S Urbana Ave",
    "sg:city":"Tulsa",
    "sg:classifiers":[
        {
            "category":"Manufacturing",
            "subcategory":"Tools & Machinery",
            "type":"Manufacturing & Wholesale Goods"
        },
        {
            "category":"Manufacturing",
            "subcategory":"Electronics",
            "type":"Manufacturing & Wholesale Goods"
        },
        {
            "category":"Shopping",
            "subcategory":"Computers & Home Electronics",
            "type":"Retail Goods"
        }
    ],
    "sg:phone":"+1 918 499 1920",
    "sg:postcode":"74137",
    "sg:province":"OK",
    "sg:tags":[
        "electric",
        "consumer",
        "equipment-testing",
        "equipment",
        "supplies-wholesale",
        "manufacturer"
    ],
    "wof:name":"Red River Marine Depot",
    "wof:placetype":"venue"
},
  "geometry": {"coordinates":[-95.92531,36.041483],"type":"Point"}
}