{
  "type": "Feature",
  "properties": {
    "iso:country":"US",
    "sg:address":"2900 N Bryant Ave",
    "sg:city":"Edmond",
    "sg:classifiers":[
        {
            "category":"Professional",
            "subcategory":"Management & Consulting",
            "type":"Services"
        }
    ],
    "sg:phone":"+1 405 715 9990",
    "sg:postcode":"73034",
    "sg:province":"OK",
    "sg:tags":[
        "public",
        "relations"
    ],
    "wof:name":"Auto Pilot Inc",
    "wof:placetype":"venue"
},
  "geometry": {"coordinates":[-97.460443,35.684861],"type":"Point"}
}