{
  "type": "Feature",
  "properties": {
    "iso:country":"US",
    "sg:address":"8101 W 33rd St S",
    "sg:city":"Muskogee",
    "sg:classifiers":[
        {
            "category":"Building & Trades",
            "subcategory":"Construction",
            "type":"Services"
        }
    ],
    "sg:phone":"+1 918 682 6762",
    "sg:postcode":"74401",
    "sg:province":"OK",
    "sg:tags":[
        "utility",
        "contractor"
    ],
    "wof:name":"Tonto Construction Inc",
    "wof:placetype":"venue"
},
  "geometry": {"coordinates":[-95.593117,35.711309],"type":"Point"}
}