{
  "type": "Feature",
  "properties": {
    "iso:country":"US",
    "sg:address":"231 S Adams Rd",
    "sg:city":"Sand Springs",
    "sg:classifiers":[
        {
            "category":"Retail",
            "subcategory":"Auto Repair",
            "type":"Services"
        }
    ],
    "sg:phone":"+1 918 245 4666",
    "sg:postcode":"74063",
    "sg:province":"OK",
    "sg:tags":[
        "repairing",
        "automobile"
    ],
    "wof:name":"Tech Center Inc",
    "wof:placetype":"venue"
},
  "geometry": {"coordinates":[-96.101103,36.134973],"type":"Point"}
}