{
  "type": "Feature",
  "properties": {
    "addr:full":"231 S Adams Rd Sand Springs OK 74063",
    "addr:housenumber":"231",
    "addr:postcode":"74063",
    "addr:street":"S Adams Rd",
    "iso:country":"US",
    "sg:address":"231 S Adams Rd",
    "sg:city":"Sand Springs",
    "sg:classifiers":[
        {
            "category":"Retail",
            "subcategory":"Auto Repair",
            "type":"Services"
        }
    ],
    "sg:phone":"+1 918 245 4666",
    "sg:postcode":"74063",
    "sg:province":"OK",
    "sg:tags":[
        "repairing",
        "automobile"
    ],
    "wof:name":"Tech Center Inc",
    "wof:placetype":"venue"
},
  "geometry": {"coordinates":[-96.10110299999999,36.134973],"type":"Point"}
}