{
  "type": "Feature",
  "properties": {
    "iso:country":"US",
    "sg:address":"11320 E 20th St",
    "sg:city":"Tulsa",
    "sg:classifiers":[
        {
            "category":"Shopping",
            "type":"Retail Goods"
        }
    ],
    "sg:phone":"+1 918 438 7727",
    "sg:postcode":"74128",
    "sg:province":"OK",
    "sg:tags":[
        "merchandise"
    ],
    "wof:name":"Custom Audio Installation",
    "wof:placetype":"venue"
},
  "geometry": {"coordinates":[-95.849614,36.134636],"type":"Point"}
}