{
  "type": "Feature",
  "properties": {
    "iso:country":"US",
    "sg:address":"2945 W Hefner Rd",
    "sg:city":"Oklahoma City",
    "sg:classifiers":[
        {
            "category":"Real Estate",
            "subcategory":"Real Estate Agent",
            "type":"Services"
        }
    ],
    "sg:phone":"+1 405 748 3383",
    "sg:postcode":"73120",
    "sg:province":"OK",
    "wof:name":"Snoddy Properties Inc",
    "wof:placetype":"venue"
},
  "geometry": {"coordinates":[-97.569775,35.580296],"type":"Point"}
}