{
  "type": "Feature",
  "properties": {
    "iso:country":"US",
    "sg:address":"222 W Carl Albert Pkwy",
    "sg:city":"Mcalester",
    "sg:classifiers":[
        {
            "category":"Retail",
            "subcategory":"Portrait Studio",
            "type":"Services"
        }
    ],
    "sg:phone":"+1 918 423 4366",
    "sg:postcode":"74501",
    "sg:province":"OK",
    "sg:tags":[
        "photographer"
    ],
    "wof:name":"Photography Of Distinction",
    "wof:placetype":"venue"
},
  "geometry": {"coordinates":[-95.77139,34.933747],"type":"Point"}
}