{
  "type": "Feature",
  "properties": {
    "iso:country":"US",
    "sg:address":"109 E Main St",
    "sg:city":"Duncan",
    "sg:classifiers":[
        {
            "category":"Building & Trades",
            "subcategory":"Cleaning & Sanitation",
            "type":"Services"
        }
    ],
    "sg:phone":"+1 580 252 2916",
    "sg:postcode":"73533",
    "sg:province":"OK",
    "sg:tags":[
        "janitor"
    ],
    "wof:name":"L A Janitorial & Maintenance",
    "wof:placetype":"venue"
},
  "geometry": {"coordinates":[-97.945252,34.500892],"type":"Point"}
}