{
  "type": "Feature",
  "properties": {
    "iso:country":"US",
    "sg:address":"5030 N May Ave",
    "sg:city":"Oklahoma City",
    "sg:classifiers":[
        {
            "category":"Shopping",
            "subcategory":"Clothing, Apparel, & Fashions",
            "type":"Retail Goods"
        }
    ],
    "sg:phone":"+1 405 570 1194",
    "sg:postcode":"73112",
    "sg:province":"OK",
    "wof:name":"Crescendo LLC",
    "wof:placetype":"venue"
},
  "geometry": {"coordinates":[-97.565603,35.5208],"type":"Point"}
}