{
  "type": "Feature",
  "properties": {
    "iso:country":"US",
    "sg:address":"6540 E 21st St S",
    "sg:city":"Tulsa",
    "sg:classifiers":[
        {
            "category":"Professional",
            "subcategory":"Business Services",
            "type":"Services"
        }
    ],
    "sg:phone":"+1 918 836 8273",
    "sg:postcode":"74129",
    "sg:province":"OK",
    "sg:tags":[
        "prerecorded",
        "mfg"
    ],
    "wof:name":"Audio/Video Duplication",
    "wof:placetype":"venue"
},
  "geometry": {"coordinates":[-95.902919,36.133366],"type":"Point"}
}