{
  "type": "Feature",
  "properties": {
    "iso:country":"US",
    "sg:address":"1624 Greenbriar Pl",
    "sg:city":"Oklahoma City",
    "sg:classifiers":[
        {
            "category":"Insurance",
            "subcategory":"Insurance Agent",
            "type":"Services"
        }
    ],
    "sg:phone":"+1 405 691 7472",
    "sg:postcode":"73159",
    "sg:province":"OK",
    "wof:name":"Ron Wallace / Farmers Ins",
    "wof:placetype":"venue"
},
  "geometry": {"coordinates":[-97.547536,35.365327],"type":"Point"}
}