{
  "type": "Feature",
  "properties": {
    "addr:full":"12802 E 31st St Tulsa OK 74146",
    "addr:housenumber":"12802",
    "addr:postcode":"74146",
    "addr:street":"E 31St St",
    "iso:country":"US",
    "sg:address":"12802 E 31st St",
    "sg:city":"Tulsa",
    "sg:classifiers":[
        {
            "category":"Banks & Credit Unions",
            "subcategory":"Bank",
            "type":"Services"
        }
    ],
    "sg:phone":"+1 918 663 4434",
    "sg:postcode":"74146",
    "sg:province":"OK",
    "sg:tags":[
        "loan",
        "broker",
        "mortgage"
    ],
    "wof:name":"Allied Home Mrtg Capitl Corp",
    "wof:placetype":"venue"
},
  "geometry": {"coordinates":[-95.835397,36.118863],"type":"Point"}
}