{
  "type": "Feature",
  "properties": {
    "iso:country":"US",
    "sg:address":"1102 Classen Dr",
    "sg:city":"Oklahoma City",
    "sg:classifiers":[
        {
            "category":"Restaurant",
            "type":"Food & Drink"
        }
    ],
    "sg:menulink":"http://www.allmenus.com/ok/oklahoma-city/144338-subway/menu/",
    "sg:phone":"+1 405 290 7643",
    "sg:postcode":"73103",
    "sg:province":"OK",
    "sg:tags":[
        "american",
        "sandwich"
    ],
    "wof:name":"Subway",
    "wof:placetype":"venue"
},
  "geometry": {"coordinates":[-97.521985,35.479457],"type":"Point"}
}