{
  "type": "Feature",
  "properties": {
    "iso:country":"US",
    "sg:address":"837 NW 10th St",
    "sg:city":"Oklahoma City",
    "sg:classifiers":[
        {
            "category":"Shopping",
            "type":"Retail Goods"
        }
    ],
    "sg:phone":"+1 405 232 7848",
    "sg:postcode":"73106",
    "sg:province":"OK",
    "sg:tags":[
        "hearing",
        "equipment",
        "supply",
        "impaired"
    ],
    "wof:name":"Huggie Aids",
    "wof:placetype":"venue"
},
  "geometry": {"coordinates":[-97.526696,35.478828],"type":"Point"}
}