{
  "type": "Feature",
  "properties": {
    "iso:country":"US",
    "sg:address":"1439 E 34th St",
    "sg:city":"Tulsa",
    "sg:classifiers":[
        {
            "category":"Professional",
            "subcategory":"Management & Consulting",
            "type":"Services"
        }
    ],
    "sg:phone":"+1 918 712 2772",
    "sg:postcode":"74105",
    "sg:province":"OK",
    "sg:tags":[
        "consultant",
        "gas",
        "business"
    ],
    "wof:name":"Fairway Producer Services LLC",
    "wof:placetype":"venue"
},
  "geometry": {"coordinates":[-95.972133,36.114315],"type":"Point"}
}