{
  "type": "Feature",
  "properties": {
    "addr:full":"117 W Paul Ave Pauls Valley OK 73075",
    "addr:housenumber":"117",
    "addr:postcode":"73075",
    "addr:street":"W Paul Ave",
    "iso:country":"US",
    "sg:address":"117 W Paul Ave",
    "sg:city":"Pauls Valley",
    "sg:classifiers":[
        {
            "category":"Restaurant",
            "type":"Food & Drink"
        }
    ],
    "sg:phone":"+1 405 238 2503",
    "sg:postcode":"73075",
    "sg:province":"OK",
    "sg:tags":[
        "eating"
    ],
    "wof:name":"Neta's Restaurant",
    "wof:placetype":"venue"
},
  "geometry": {"coordinates":[-97.219953,34.740634],"type":"Point"}
}