{
  "type": "Feature",
  "properties": {
    "iso:country":"US",
    "sg:address":"9400 Broadway Exn",
    "sg:city":"Oklahoma City",
    "sg:classifiers":[
        {
            "category":"Professional",
            "subcategory":"Accounting & Tax Preparation",
            "type":"Services"
        }
    ],
    "sg:phone":"+1 405 478 9595",
    "sg:postcode":"73114",
    "sg:province":"OK",
    "wof:name":"Jay Flinton CPA",
    "wof:placetype":"venue"
},
  "geometry": {"coordinates":[-97.51373,35.566305],"type":"Point"}
}