{
  "type": "Feature",
  "properties": {
    "addr:full":"417 N Ellison St Guymon OK 73942",
    "addr:housenumber":"417",
    "addr:postcode":"73942",
    "addr:street":"N Ellison St",
    "iso:country":"US",
    "sg:address":"417 N Ellison St",
    "sg:city":"Guymon",
    "sg:classifiers":[
        {
            "category":"Travel",
            "subcategory":"Hotels & Motels",
            "type":"Entertainment"
        }
    ],
    "sg:phone":"+1 580 338 6644",
    "sg:postcode":"73942",
    "sg:province":"OK",
    "wof:name":"Gross Hotel & Lock Shop",
    "wof:placetype":"venue"
},
  "geometry": {"coordinates":[-101.48018,36.681995],"type":"Point"}
}