{
  "type": "Feature",
  "properties": {
    "iso:country":"US",
    "sg:address":"13795 E 136th St N",
    "sg:city":"Collinsville",
    "sg:classifiers":[
        {
            "category":"Manufacturing",
            "subcategory":"Building Materials",
            "type":"Manufacturing & Wholesale Goods"
        },
        {
            "category":"Home & Garden",
            "subcategory":"Furniture",
            "type":"Retail Goods"
        }
    ],
    "sg:phone":"+1 918 371 7320",
    "sg:postcode":"74021",
    "sg:province":"OK",
    "sg:tags":[
        "no",
        "household",
        "mfg",
        "cabinet",
        "wood",
        "furn",
        "kitchen"
    ],
    "wof:name":"Colt Fixtures & Millwork LLC",
    "wof:placetype":"venue"
},
  "geometry": {"coordinates":[-95.82053,36.351105],"type":"Point"}
}