{
  "type": "Feature",
  "properties": {
    "iso:country":"US",
    "sg:address":"2625 E 55th Pl",
    "sg:city":"Tulsa",
    "sg:classifiers":[
        {
            "category":"Building & Trades",
            "subcategory":"Electrical",
            "type":"Services"
        }
    ],
    "sg:phone":"+1 918 743 5510",
    "sg:postcode":"74105",
    "sg:province":"OK",
    "sg:tags":[
        "installation"
    ],
    "wof:name":"B & B Installation Svc Inc",
    "wof:placetype":"venue"
},
  "geometry": {"coordinates":[-95.95191199999999,36.083481],"type":"Point"}
}