{
  "type": "Feature",
  "properties": {
    "iso:country":"US",
    "sg:address":"101 Shelby Ln",
    "sg:city":"Oklahoma City",
    "sg:classifiers":[
        {
            "category":"Wholesale",
            "subcategory":"Electrical",
            "type":"Manufacturing & Wholesale Goods"
        }
    ],
    "sg:phone":"+1 405 659 7889",
    "sg:postcode":"73130",
    "sg:province":"OK",
    "sg:tags":[
        "small",
        "electronics"
    ],
    "wof:name":"Shelby Industrial Supply",
    "wof:placetype":"venue"
},
  "geometry": {"coordinates":[-97.346323,35.462979],"type":"Point"}
}