{
  "type": "Feature",
  "properties": {
    "iso:country":"US",
    "sg:address":"811 S Littler Ave",
    "sg:city":"Edmond",
    "sg:classifiers":[
        {
            "category":"Personal",
            "type":"Services"
        }
    ],
    "sg:phone":"+1 405 341 8559",
    "sg:postcode":"73034",
    "sg:province":"OK",
    "sg:tags":[
        "consulting",
        "management"
    ],
    "wof:name":"Edmond Massage & Therapy Ctr",
    "wof:placetype":"venue"
},
  "geometry": {"coordinates":[-97.479641,35.645659],"type":"Point"}
}