{
  "type": "Feature",
  "properties": {
    "addr:full":"9300 W Reno Ave Oklahoma City OK 73099",
    "addr:housenumber":"9300",
    "addr:postcode":"73099",
    "addr:street":"W Reno Ave",
    "iso:country":"US",
    "sg:address":"9300 W Reno Ave",
    "sg:city":"Oklahoma City",
    "sg:classifiers":[
        {
            "category":"Retail",
            "subcategory":"Auto Repair",
            "type":"Services"
        }
    ],
    "sg:phone":"+1 405 495 6100",
    "sg:postcode":"73099",
    "sg:province":"OK",
    "sg:tags":[
        "truck"
    ],
    "sg:website":"www.fleetpride.com",
    "wof:name":"Fleet Pride Inc",
    "wof:placetype":"venue"
},
  "geometry": {"coordinates":[-97.682543,35.464283],"type":"Point"}
}