{
  "type": "Feature",
  "properties": {
    "iso:country":"US",
    "sg:address":"430 W Lincoln St",
    "sg:city":"Purcell",
    "sg:classifiers":[
        {
            "category":"Banks & Credit Unions",
            "subcategory":"Bank",
            "type":"Services"
        }
    ],
    "sg:phone":"+1 405 527 5634",
    "sg:postcode":"73080",
    "sg:province":"OK",
    "wof:name":"IBC Bank",
    "wof:placetype":"venue"
},
  "geometry": {"coordinates":[-97.364072,35.027788],"type":"Point"}
}