{
  "type": "Feature",
  "properties": {
    "iso:country":"US",
    "sg:address":"1646 W Robinson St",
    "sg:city":"Norman",
    "sg:classifiers":[
        {
            "category":"Professional",
            "subcategory":"Computer Services",
            "type":"Services"
        }
    ],
    "sg:phone":"+1 405 406 3044",
    "sg:postcode":"73069",
    "sg:province":"OK",
    "wof:name":"Christopher Michael Bentkowski",
    "wof:placetype":"venue"
},
  "geometry": {"coordinates":[-97.467812,35.232894],"type":"Point"}
}