{
  "type": "Feature",
  "properties": {
    "addr:full":"2211 US Hwy 81 Duncan OK 73533",
    "addr:housenumber":"2211",
    "addr:postcode":"73533",
    "addr:street":"Us Hwy 81",
    "iso:country":"US",
    "sg:address":"2211 US Hwy 81",
    "sg:city":"Duncan",
    "sg:classifiers":[
        {
            "category":"Insurance",
            "subcategory":"Insurance Agent",
            "type":"Services"
        }
    ],
    "sg:phone":"+1 580 255 8530",
    "sg:postcode":"73533",
    "sg:province":"OK",
    "wof:name":"Universal Fidelity Life",
    "wof:placetype":"venue"
},
  "geometry": {"coordinates":[-97.966874,34.532164],"type":"Point"}
}