{
  "type": "Feature",
  "properties": {
    "iso:country":"US",
    "sg:address":"907 N York St",
    "sg:city":"Muskogee",
    "sg:classifiers":[
        {
            "category":"Banks & Credit Unions",
            "subcategory":"Bank",
            "type":"Services"
        }
    ],
    "sg:phone":"+1 918 686 8130",
    "sg:postcode":"74403",
    "sg:province":"OK",
    "sg:tags":[
        "financing"
    ],
    "wof:name":"Commerce Finance Corp",
    "wof:placetype":"venue"
},
  "geometry": {"coordinates":[-95.340444,35.751412],"type":"Point"}
}